Workbook
Name MODEPAID: MODEPAID!$A$1:$A$3
Name MODEPAID: #REF!
Name MODEPAID: #REF!
Name MODEPAID: #REF!
Name MODEPAID: #REF!
Name MODEPAID: #REF!
Name MODEPAID: #REF!
Name MODEPAID: #REF!
Name MODEPAID: #REF!
Name MODEPAID: #REF!
Name MODEPAID: #REF!
Name MODEPAID: #REF!
Name MODEPAID: #REF!
Name MODEPAID: #REF!
Name MODEPAID: #REF!
Name MODEPAID: #REF!
Name MODEPAID: #REF!
Name VALMODEPAID: MODEPAID!$A$1:$A$3

Sheet Feuil1
B1: INTERET VENTE | C1: MISE A PRIX | D1: INTERET MISE EN VENTE | E1: INTERET PETIT LOT | F1: INT CUMUL MISE EN VENTE | G1: INTERET NON REMB | H1: PETIT LOT + INTERET
A2: 42979 | B2: =#REF! -> #REF! | C2: 200000 | D2: =B2-C2 -> #REF! | E2: =#REF! -> #REF! | H2: =#REF! -> #REF! | I2: OK
A3: 43009 | B3: =+#REF! -> #REF! | C3: 200000 | D3: =B3-C3 -> #REF! | E3: =+#REF! -> #REF! | F3: =D2+E2+D3 -> #REF! | H3: =#REF! -> #REF! | I3: OK
A4: 43040 | B4: =+#REF! -> #REF! | C4: 200000 | D4: =B4-C4 -> #REF! | E4: =+#REF! -> #REF! | F4: =F3+D4+E3 -> #REF! | H4: =#REF! -> #REF! | I4: OK
A5: 43070 | B5: =#REF! -> #REF! | C5: 200000 | D5: =B5-C5 -> #REF! | E5: =+#REF! -> #REF! | F5: =F4+D5+E4 -> #REF! | G5: 200000 | H5: =#REF! -> #REF! | I5: NOK
A6: 43101 | B6: =+#REF! -> #REF! | C6: 200000 | D6: =B6-C6 -> #REF! | E6: =+#REF! -> #REF! | F6: =F5+D6+E5 -> #REF! | H6: =#REF! -> #REF!
A7: 43132 | B7: =+#REF! -> #REF! | C7: 200000 | D7: =B7-C7 -> #REF! | E7: =+#REF! -> #REF! | F7: =F6+D7+E6 -> #REF! | G7: 200000 | H7: =#REF! -> #REF!
A8: 43160 | B8: =+#REF! -> #REF! | C8: 200000 | D8: =B8-C8 -> #REF! | E8: =+#REF! -> #REF! | F8: =F7+D8+E7 -> #REF! | H8: =#REF! -> #REF!
A9: 43191 | B9: =+#REF! -> #REF! | C9: 200000 | D9: =B9-C9 -> #REF! | E9: =+#REF! -> #REF! | F9: =F8+D9+E8 -> #REF! | H9: =#REF! -> #REF!
A10: 43221 | B10: =+#REF! -> #REF! | C10: 200000 | D10: =B10-C10 -> #REF! | E10: =+#REF! -> #REF! | F10: =F9+D10+E9 -> #REF! | H10: =#REF! -> #REF!
A11: 43252 | B11: =+#REF! -> #REF! | C11: 200000 | D11: =B11-C11 -> #REF! | E11: =+#REF! -> #REF! | F11: =F10+D11+E10 -> #REF! | H11: =#REF! -> #REF!
A12: 43282 | B12: =+#REF! -> #REF! | C12: 100000 | D12: =B12-C12 -> #REF! | E12: =+#REF! -> #REF! | F12: =F11+D12+E11 -> #REF! | H12: =#REF! -> #REF!
A13: 43313 | B13: 200000 | C13: 200000 | D13: 0 | E13: 0 | F13: =F12+D13+E12 -> #REF! | H13: =#REF! -> #REF!
B14: =SUM(B2:B13) -> #REF! | C14: =SUM(C2:C13) -> 2300000
C15: =+B14-C14 -> #REF! | D15: =SUM(D2:D14) -> #REF! | E15: =SUM(E2:E14) -> #REF! | H15: 1145500 | I15: 2300000
H16: 12000
B17: NGONDIEP | D17: 101000 | H17: =+H15+H16 -> 1157500
B18: NANGUEN | D18: 96000 | H18: 200000
B19: FOTSO THOMAS | D19: 206000 | H19: 269000
H20: =+H17+H18+H19 -> 1626500
H21: =D15+E15-H20 -> #REF!
D22: =SUM(D17:D21) -> 403000

Sheet MODEPAID
A1: BANQUE
A2: ESPECES
A3: ECHEC

Sheet TONTNOV
A1: ASSOCIATION | B1: ASELBY
A2: ANNEE | B2: 2019/2020
A3: TONTINE | B3: 100000
C4: 43793
A5: MATRICULE | B5: NOM ET PRENOM | C5: MONTANT TONTINE | D5: PENALITE | E5: MODE VERSEMENT TONTINE | F5: VENTE PETIT LOT | G5: INTERET PETIT LOT | H5: MODE VERSEMENT VENTE PETIT LOT | I5: NUMERO CHEQUE | J5: REMBOURSEMENT | K5: MODE VERSEMENT REMBOURSEMENT | L5: MODE VERSEMENT TONTINE PRINCIPAL | M5: NUMERO CHEQUE | N5: MONTANT TONTINE LOT PRINCIPAL | O5: INTERET LOT PRINCIPAL | P5: DATE VENTE
A6: AS201608 | B6: =VLOOKUP(A6,[1]LISTADHERENT!A$5:H$60,3,0) -> DJUOMBESSY ANTOINE | C6: =IF(E6="ECHEC",0,IF(E6="",0,100000)) -> 100000 | D6: =IF(E6="ESPECES",0,0) -> 0 | E6: BANQUE | N6: =IF(O6=0,0,($C$38-O6)) -> 0
A7: AS201613 | B7: =VLOOKUP(A7,[1]LISTADHERENT!A$5:H$60,3,0) -> HOTCHO BENJAMIN | C7: =IF(E7="ECHEC",0,IF(E7="",0,100000)) -> 100000 | D7: =IF(E7="ESPECES",0,0) -> 0 | E7: BANQUE | N7: =IF(O7=0,0,($C$38-O7)) -> 0
A8: AS201619 | B8: =VLOOKUP(A8,[1]LISTADHERENT!A$5:H$60,3,0) -> KOUATCHO MESSACK | C8: =IF(E8="ECHEC",0,IF(E8="",0,100000)) -> 100000 | D8: =IF(E8="ESPECES",0,0) -> 0 | E8: BANQUE | F8: =100000+50000 -> 150000 | G8: =2500+1000 -> 3500 | H8: BANQUE | N8: =IF(O8=0,0,($C$38-O8)) -> 0
A9: AS201617 | B9: =VLOOKUP(A9,[1]LISTADHERENT!A$5:H$60,3,0) -> KOUAMOU MOISE | C9: =IF(E9="ECHEC",0,IF(E9="",0,100000)) -> 100000 | D9: =IF(E9="ESPECES",0,0) -> 0 | E9: BANQUE | N9: =IF(O9=0,0,($C$38-O9)) -> 0
A10: AS201649 | B10: =VLOOKUP(A10,[1]LISTADHERENT!A$5:H$60,3,0) -> MBOGNING TUGMA GUY | C10: =IF(E10="ECHEC",0,IF(E10="",0,100000)) -> 100000 | D10: =IF(E10="ESPECES",0,0) -> 0 | E10: BANQUE | F10: =100000+100000 -> 200000 | G10: =2500+5500 -> 8000 | H10: ESPECES | N10: =IF(O10=0,0,($C$38-O10)) -> 0
A11: AS201649 | B11: =VLOOKUP(A11,[1]LISTADHERENT!A$5:H$60,3,0) -> MBOGNING TUGMA GUY | C11: =IF(E11="ECHEC",0,IF(E11="",0,100000)) -> 100000 | D11: =IF(E11="ESPECES",0,0) -> 0 | E11: BANQUE | N11: =IF(O11=0,0,($C$38-O11)) -> 0
A12: AS201639 | B12: =VLOOKUP(A12,[1]LISTADHERENT!A$5:H$60,3,0) -> NANGUEN MARTIN | C12: =IF(E12="ECHEC",0,IF(E12="",0,100000)) -> 100000 | D12: =IF(E12="ESPECES",0,0) -> 0 | E12: BANQUE | N12: =IF(O12=0,0,($C$38-O12)) -> 0
A13: AS201622 | B13: =VLOOKUP(A13,[1]LISTADHERENT!A$5:H$60,3,0) -> NDJOMO ETIENNE | C13: =IF(E13="ECHEC",0,IF(E13="",0,100000)) -> 100000 | D13: =IF(E13="ESPECES",0,0) -> 0 | E13: BANQUE | N13: =IF(O13=0,0,($C$38-O13)) -> 0
A14: AS201624 | B14: =VLOOKUP(A14,[1]LISTADHERENT!A$5:H$60,3,0) -> NGONDIEP CLAUDE | C14: =IF(E14="ECHEC",0,IF(E14="",0,100000)) -> 100000 | D14: =IF(E14="ESPECES",0,0) -> 0 | E14: BANQUE | N14: =IF(O14=0,0,($C$38-O14)) -> 0
A15: AS201614 | B15: =VLOOKUP(A15,[1]LISTADHERENT!A$5:H$60,3,0) -> NKEHE DAVID | C15: =IF(E15="ECHEC",0,IF(E15="",0,100000)) -> 100000 | D15: =IF(E15="ESPECES",0,0) -> 0 | E15: ESPECES | N15: =IF(O15=0,0,($C$38-O15)) -> 1350000 | O15: 150000 | P15: 43793
A16: AS201629 | B16: =VLOOKUP(A16,[1]LISTADHERENT!A$5:H$60,3,0) -> NKEPSEU DIEUDONNE | C16: =IF(E16="ECHEC",0,IF(E16="",0,100000)) -> 100000 | D16: =IF(E16="ESPECES",0,0) -> 0 | E16: BANQUE | N16: =IF(O16=0,0,($C$38-O16)) -> 0
A17: AS201636 | B17: =VLOOKUP(A17,[1]LISTADHERENT!A$5:H$60,3,0) -> SIMO FONGANG ERIC | C17: =IF(E17="ECHEC",0,IF(E17="",0,100000)) -> 100000 | D17: =IF(E17="ESPECES",0,0) -> 0 | E17: BANQUE | N17: =IF(O17=0,0,($C$38-O17)) -> 0
A18: AS201636 | B18: =VLOOKUP(A18,[1]LISTADHERENT!A$5:H$60,3,0) -> SIMO FONGANG ERIC | C18: =IF(E18="ECHEC",0,IF(E18="",0,100000)) -> 100000 | D18: =IF(E18="ESPECES",0,0) -> 0 | E18: BANQUE | N18: =IF(O18=0,0,($C$38-O18)) -> 0
A19: AS201637 | B19: =VLOOKUP(A19,[1]LISTADHERENT!A$5:H$60,3,0) -> SIME MATHIEU | C19: =IF(E19="ECHEC",0,IF(E19="",0,100000)) -> 100000 | D19: =IF(E19="ESPECES",0,0) -> 0 | E19: BANQUE | N19: =IF(O19=0,0,($C$38-O19)) -> 0
A20: AS201637 | B20: =VLOOKUP(A20,[1]LISTADHERENT!A$5:H$60,3,0) -> SIME MATHIEU | C20: =IF(E20="ECHEC",0,IF(E20="",0,100000)) -> 100000 | D20: =IF(E20="ESPECES",0,0) -> 0 | E20: BANQUE | N20: =IF(O20=0,0,($C$38-O20)) -> 0
A21: AS201641 | B21: =VLOOKUP(A21,[1]LISTADHERENT!A$5:H$60,3,0) -> TCHOUAMOU MATHIEU | C21: =IF(E21="ECHEC",0,IF(E21="",0,100000)) -> 100000 | D21: =IF(E21="ESPECES",0,0) -> 0 | E21: BANQUE | N21: =IF(O21=0,0,($C$38-O21)) -> 0
A22: AS201644 | B22: =VLOOKUP(A22,[1]LISTADHERENT!A$5:H$60,3,0) -> TIEYAM ERNEST | C22: =IF(E22="ECHEC",0,IF(E22="",0,100000)) -> 100000 | D22: =IF(E22="ESPECES",0,0) -> 0 | E22: BANQUE | F22: =100000+100000 -> 200000 | G22: =4000+9000 -> 13000 | H22: BANQUE | N22: =IF(O22=0,0,($C$38-O22)) -> 0
A23: AS201647 | B23: =VLOOKUP(A23,[1]LISTADHERENT!A$5:H$60,3,0) -> YOUMBI EMMANUEL | C23: =IF(E23="ECHEC",0,IF(E23="",0,100000)) -> 100000 | D23: =IF(E23="ESPECES",0,0) -> 0 | E23: BANQUE | N23: =IF(O23=0,0,($C$38-O23)) -> 0
A25: TOTAL | C25: =SUM(C6:C24) -> 1800000 | D25: =SUM(D6:D24) -> 0 | F25: =SUM(F6:F24) -> 550000 | G25: =SUM(G6:G24) -> 24500 | J25: =SUM(J6:J24) -> 0 | N25: =SUM(N6:N24) -> 1350000 | O25: =SUM(O6:O24) -> 150000
C27: TONTINE | D27: REMBOURSEMENT PETIT LOT | E27: VENTE PETIT LOT | F27: VENTE LOT PRINCIPAL | G27: SOLDE EN CAISSE | K27: TONTINE + REMB + INTERET VENTE | L27: =C25+D32+O25 -> 1950000
K28: TONTINE | L28: =IF(L27>=3000000,1500000*2,1500000) -> 1500000
B29: ESPECES | C29: =SUMIFS(C6:C23,E6:E23,"ESPECES") -> 100000 | D29: =SUMIFS(J6:J23,K6:K23,"ESPECES") -> 0 | E29: =SUMIFS(F6:F23,H6:H23,"ESPECES") -> 200000 | F29: =SUMIFS(N6:N23,L6:L23,"ESPECES") -> 0 | G29: =C29+D29-E29-F29 -> -100000 | K29: PETIT LOT | L29: =L27-L28 -> 450000
B30: BANQUE | C30: =SUMIFS(C6:C23,E6:E23,"BANQUE") -> 1700000 | D30: =SUMIFS(J6:J23,K6:K23,"BANQUE") -> 0 | E30: =SUMIFS(F6:F23,H6:H23,"BANQUE") -> 350000 | F30: =SUMIFS(N6:N23,L6:L23,"BANQUE") -> 0 | G30: =C30+D30-E30-F30 -> 1350000 | K30: RESTE | L30: =L29-F25 -> -100000 | M30: SURPLUS
B32: TOTAL | C32: =C29+C30 -> 1800000 | D32: =D29+D30 -> 0 | E32: =E29+E30 -> 550000 | F32: =F29+F30 -> 0 | G32: =G29+G30 -> 1250000 | K32: ECHEC TONTINE | L32: 0
K33: ECHEC REMBOURSEMENT | L33: 0
B35: INTERET LOT PRINCIPAL | C35: =O25 -> 150000
B36: INTERET PETIT LOT | C36: =+G25 -> 24500
B38: MONTANT TONTINE | C38: 1500000
B39: MONTANT PETIT LOT A VENDRE | C39: =L29 -> 450000

Sheet TONTDEC
A1: ASSOCIATION | B1: ASELBY
A2: ANNEE | B2: 2019/2020
A3: TONTINE | B3: 100000
C4: 43814
A5: MATRICULE | B5: NOM ET PRENOM | C5: MONTANT TONTINE | D5: PENALITE | E5: MODE VERSEMENT TONTINE | F5: VENTE PETIT LOT | G5: INTERET PETIT LOT | H5: MODE VERSEMENT VENTE PETIT LOT | I5: NUMERO CHEQUE | J5: REMBOURSEMENT | K5: MODE VERSEMENT REMBOURSEMENT | L5: MODE VERSEMENT TONTINE PRINCIPAL | M5: NUMERO CHEQUE | N5: MONTANT TONTINE LOT PRINCIPAL | O5: INTERET LOT PRINCIPAL | P5: DATE VENTE
A6: AS201608 | B6: =VLOOKUP(A6,[1]LISTADHERENT!A$5:H$60,3,0) -> DJUOMBESSY ANTOINE | C6: =IF(E6="ECHEC",0,IF(E6="",0,100000)) -> 100000 | D6: =IF(E6="ESPECES",0,0) -> 0 | E6: BANQUE | J6: =TONTNOV!F6+TONTNOV!G6 -> 0 | N6: =IF(O6=0,0,($C$38-O6)) -> 0
A7: AS201613 | B7: =VLOOKUP(A7,[1]LISTADHERENT!A$5:H$60,3,0) -> HOTCHO BENJAMIN | C7: =IF(E7="ECHEC",0,IF(E7="",0,100000)) -> 100000 | D7: =IF(E7="ESPECES",0,0) -> 0 | E7: BANQUE | J7: =TONTNOV!F7+TONTNOV!G7 -> 0 | N7: =IF(O7=0,0,($C$38-O7)) -> 0
A8: AS201619 | B8: =VLOOKUP(A8,[1]LISTADHERENT!A$5:H$60,3,0) -> KOUATCHO MESSACK | C8: =IF(E8="ECHEC",0,IF(E8="",0,100000)) -> 100000 | D8: =IF(E8="ESPECES",0,0) -> 0 | E8: BANQUE | J8: =TONTNOV!F8+TONTNOV!G8 -> 153500 | K8: BANQUE | N8: =IF(O8=0,0,($C$38-O8)) -> 1250000 | O8: 250000 | P8: 43814
A9: AS201617 | B9: =VLOOKUP(A9,[1]LISTADHERENT!A$5:H$60,3,0) -> KOUAMOU MOISE | C9: =IF(E9="ECHEC",0,IF(E9="",0,100000)) -> 100000 | D9: =IF(E9="ESPECES",0,0) -> 0 | E9: BANQUE | J9: =TONTNOV!F9+TONTNOV!G9 -> 0 | N9: =IF(O9=0,0,($C$38-O9)) -> 0
A10: AS201649 | B10: =VLOOKUP(A10,[1]LISTADHERENT!A$5:H$60,3,0) -> MBOGNING TUGMA GUY | C10: =IF(E10="ECHEC",0,IF(E10="",0,100000)) -> 100000 | D10: =IF(E10="ESPECES",0,0) -> 0 | E10: BANQUE | J10: =TONTNOV!F10+TONTNOV!G10 -> 208000 | K10: BANQUE | N10: =IF(O10=0,0,($C$38-O10)) -> 0
A11: AS201649 | B11: =VLOOKUP(A11,[1]LISTADHERENT!A$5:H$60,3,0) -> MBOGNING TUGMA GUY | C11: =IF(E11="ECHEC",0,IF(E11="",0,100000)) -> 100000 | D11: =IF(E11="ESPECES",0,0) -> 0 | E11: BANQUE | J11: =TONTNOV!F11+TONTNOV!G11 -> 0 | N11: =IF(O11=0,0,($C$38-O11)) -> 0
A12: AS201639 | B12: =VLOOKUP(A12,[1]LISTADHERENT!A$5:H$60,3,0) -> NANGUEN MARTIN | C12: =IF(E12="ECHEC",0,IF(E12="",0,100000)) -> 100000 | D12: =IF(E12="ESPECES",0,0) -> 0 | E12: BANQUE | J12: =TONTNOV!F12+TONTNOV!G12 -> 0 | N12: =IF(O12=0,0,($C$38-O12)) -> 0
A13: AS201622 | B13: =VLOOKUP(A13,[1]LISTADHERENT!A$5:H$60,3,0) -> NDJOMO ETIENNE | C13: =IF(E13="ECHEC",0,IF(E13="",0,100000)) -> 100000 | D13: =IF(E13="ESPECES",0,0) -> 0 | E13: BANQUE | J13: =TONTNOV!F13+TONTNOV!G13 -> 0 | N13: =IF(O13=0,0,($C$38-O13)) -> 0
A14: AS201624 | B14: =VLOOKUP(A14,[1]LISTADHERENT!A$5:H$60,3,0) -> NGONDIEP CLAUDE | C14: =IF(E14="ECHEC",0,IF(E14="",0,100000)) -> 100000 | D14: =IF(E14="ESPECES",0,0) -> 0 | E14: BANQUE | J14: =TONTNOV!F14+TONTNOV!G14 -> 0 | N14: =IF(O14=0,0,($C$38-O14)) -> 0
A15: AS201614 | B15: =VLOOKUP(A15,[1]LISTADHERENT!A$5:H$60,3,0) -> NKEHE DAVID | C15: =IF(E15="ECHEC",0,IF(E15="",0,100000)) -> 100000 | D15: =IF(E15="ESPECES",0,0) -> 0 | E15: BANQUE | J15: =TONTNOV!F15+TONTNOV!G15 -> 0 | N15: =IF(O15=0,0,($C$38-O15)) -> 0
A16: AS201629 | B16: =VLOOKUP(A16,[1]LISTADHERENT!A$5:H$60,3,0) -> NKEPSEU DIEUDONNE | C16: =IF(E16="ECHEC",0,IF(E16="",0,100000)) -> 100000 | D16: =IF(E16="ESPECES",0,0) -> 0 | E16: ESPECES | J16: =TONTNOV!F16+TONTNOV!G16 -> 0 | N16: =IF(O16=0,0,($C$38-O16)) -> 0
A17: AS201636 | B17: =VLOOKUP(A17,[1]LISTADHERENT!A$5:H$60,3,0) -> SIMO FONGANG ERIC | C17: =IF(E17="ECHEC",0,IF(E17="",0,100000)) -> 100000 | D17: =IF(E17="ESPECES",0,0) -> 0 | E17: ESPECES | J17: =TONTNOV!F17+TONTNOV!G17 -> 0 | N17: =IF(O17=0,0,($C$38-O17)) -> 1255000 | O17: 245000 | P17: 43814
A18: AS201636 | B18: =VLOOKUP(A18,[1]LISTADHERENT!A$5:H$60,3,0) -> SIMO FONGANG ERIC | C18: =IF(E18="ECHEC",0,IF(E18="",0,100000)) -> 100000 | D18: =IF(E18="ESPECES",0,0) -> 0 | E18: ESPECES | J18: =TONTNOV!F18+TONTNOV!G18 -> 0 | N18: =IF(O18=0,0,($C$38-O18)) -> 0
A19: AS201637 | B19: =VLOOKUP(A19,[1]LISTADHERENT!A$5:H$60,3,0) -> SIME MATHIEU | C19: =IF(E19="ECHEC",0,IF(E19="",0,100000)) -> 100000 | D19: =IF(E19="ESPECES",0,0) -> 0 | E19: BANQUE | J19: =TONTNOV!F19+TONTNOV!G19 -> 0 | N19: =IF(O19=0,0,($C$38-O19)) -> 0
A20: AS201637 | B20: =VLOOKUP(A20,[1]LISTADHERENT!A$5:H$60,3,0) -> SIME MATHIEU | C20: =IF(E20="ECHEC",0,IF(E20="",0,100000)) -> 100000 | D20: =IF(E20="ESPECES",0,0) -> 0 | E20: BANQUE | J20: =TONTNOV!F20+TONTNOV!G20 -> 0 | N20: =IF(O20=0,0,($C$38-O20)) -> 0
A21: AS201641 | B21: =VLOOKUP(A21,[1]LISTADHERENT!A$5:H$60,3,0) -> TCHOUAMOU MATHIEU | C21: =IF(E21="ECHEC",0,IF(E21="",0,100000)) -> 100000 | D21: =IF(E21="ESPECES",0,0) -> 0 | E21: BANQUE | J21: =TONTNOV!F21+TONTNOV!G21 -> 0 | N21: =IF(O21=0,0,($C$38-O21)) -> 0
A22: AS201644 | B22: =VLOOKUP(A22,[1]LISTADHERENT!A$5:H$60,3,0) -> TIEYAM ERNEST | C22: =IF(E22="ECHEC",0,IF(E22="",0,100000)) -> 100000 | D22: =IF(E22="ESPECES",0,0) -> 0 | E22: BANQUE | J22: =TONTNOV!F22+TONTNOV!G22 -> 213000 | K22: ESPECES | N22: =IF(O22=0,0,($C$38-O22)) -> 0
A23: AS201647 | B23: =VLOOKUP(A23,[1]LISTADHERENT!A$5:H$60,3,0) -> YOUMBI EMMANUEL | C23: =IF(E23="ECHEC",0,IF(E23="",0,100000)) -> 100000 | D23: =IF(E23="ESPECES",0,0) -> 0 | E23: BANQUE | J23: =TONTNOV!F23+TONTNOV!G23 -> 0 | N23: =IF(O23=0,0,($C$38-O23)) -> 0
A25: TOTAL | C25: =SUM(C6:C24) -> 1800000 | D25: =SUM(D6:D24) -> 0 | F25: =SUM(F6:F24) -> 0 | G25: =SUM(G6:G24) -> 0 | J25: =SUM(J6:J24) -> 574500 | N25: =SUM(N6:N24) -> 2505000 | O25: =SUM(O6:O24) -> 495000
C27: TONTINE | D27: REMBOURSEMENT PETIT LOT | E27: VENTE PETIT LOT | F27: VENTE LOT PRINCIPAL | G27: SOLDE EN CAISSE | K27: TONTINE + REMB + INTERET VENTE | L27: =C25+D32+O25+30500+100000 -> 3000000
K28: TONTINE | L28: =IF(L27>=3000000,1500000*2,1500000) -> 3000000
B29: ESPECES | C29: =SUMIFS(C6:C23,E6:E23,"ESPECES") -> 300000 | D29: =SUMIFS(J6:J23,K6:K23,"ESPECES") -> 213000 | E29: =SUMIFS(F6:F23,H6:H23,"ESPECES") -> 0 | F29: =SUMIFS(N6:N23,L6:L23,"ESPECES") -> 0 | G29: =C29+D29-E29-F29 -> 513000 | K29: PETIT LOT | L29: =L27-L28 -> 0
B30: BANQUE | C30: =SUMIFS(C6:C23,E6:E23,"BANQUE") -> 1500000 | D30: =SUMIFS(J6:J23,K6:K23,"BANQUE") -> 361500 | E30: =SUMIFS(F6:F23,H6:H23,"BANQUE") -> 0 | F30: =SUMIFS(N6:N23,L6:L23,"BANQUE") -> 0 | G30: =C30+D30-E30-F30 -> 1861500 | K30: RESTE | L30: 0
B32: TOTAL | C32: =C29+C30 -> 1800000 | D32: =D29+D30 -> 574500 | E32: =E29+E30 -> 0 | F32: =F29+F30 -> 0 | G32: =G29+G30 -> 2374500 | K32: ECHEC TONTINE | L32: 0
K33: ECHEC REMBOURSEMENT | L33: 0
B35: INTERET LOT PRINCIPAL | C35: =O25 -> 495000
B36: INTERET PETIT LOT | C36: =+G25 -> 0
B38: MONTANT TONTINE | C38: 1500000
B39: MONTANT PETIT LOT A VENDRE | C39: =L29 -> 0

Sheet TONTJANV
A1: ASSOCIATION | B1: ASELBY
A2: ANNEE | B2: 2019/2020
A3: TONTINE | B3: 100000
C4: 43848
A5: MATRICULE | B5: NOM ET PRENOM | C5: MONTANT TONTINE | D5: PENALITE | E5: MODE VERSEMENT TONTINE | F5: VENTE PETIT LOT | G5: INTERET PETIT LOT | H5: MODE VERSEMENT VENTE PETIT LOT | I5: NUMERO CHEQUE | J5: REMBOURSEMENT | K5: MODE VERSEMENT REMBOURSEMENT | L5: MODE VERSEMENT TONTINE PRINCIPAL | M5: NUMERO CHEQUE | N5: MONTANT TONTINE LOT PRINCIPAL | O5: INTERET LOT PRINCIPAL | P5: DATE VENTE
A6: AS201608 | B6: =VLOOKUP(A6,[1]LISTADHERENT!A$5:H$60,3,0) -> DJUOMBESSY ANTOINE | C6: =IF(E6="ECHEC",0,IF(E6="",0,100000)) -> 100000 | D6: =IF(E6="ESPECES",0,0) -> 0 | E6: BANQUE | J6: =TONTDEC!F6+TONTDEC!G6 -> 0 | N6: =IF(O6=0,0,($C$38-O6)) -> 0
A7: AS201613 | B7: =VLOOKUP(A7,[1]LISTADHERENT!A$5:H$60,3,0) -> HOTCHO BENJAMIN | C7: =IF(E7="ECHEC",0,IF(E7="",0,100000)) -> 100000 | D7: =IF(E7="ESPECES",0,0) -> 0 | E7: BANQUE | J7: =TONTDEC!F7+TONTDEC!G7 -> 0 | N7: =IF(O7=0,0,($C$38-O7)) -> 0
A8: AS201619 | B8: =VLOOKUP(A8,[1]LISTADHERENT!A$5:H$60,3,0) -> KOUATCHO MESSACK | C8: =IF(E8="ECHEC",0,IF(E8="",0,100000)) -> 100000 | D8: =IF(E8="ESPECES",0,0) -> 0 | E8: BANQUE | F8: 100000 | G8: 4000 | H8: ESPECES | J8: =TONTDEC!F8+TONTDEC!G8 -> 0 | N8: =IF(O8=0,0,($C$38-O8)) -> 0
A9: AS201617 | B9: =VLOOKUP(A9,[1]LISTADHERENT!A$5:H$60,3,0) -> KOUAMOU MOISE | C9: =IF(E9="ECHEC",0,IF(E9="",0,100000)) -> 100000 | D9: =IF(E9="ESPECES",0,0) -> 0 | E9: BANQUE | J9: =TONTDEC!F9+TONTDEC!G9 -> 0 | N9: =IF(O9=0,0,($C$38-O9)) -> 0
A10: AS201649 | B10: =VLOOKUP(A10,[1]LISTADHERENT!A$5:H$60,3,0) -> MBOGNING TUGMA GUY | C10: =IF(E10="ECHEC",0,IF(E10="",0,100000)) -> 100000 | D10: =IF(E10="ESPECES",0,0) -> 0 | E10: BANQUE | J10: =TONTDEC!F10+TONTDEC!G10 -> 0 | N10: =IF(O10=0,0,($C$38-O10)) -> 1270000 | O10: 230000
A11: AS201649 | B11: =VLOOKUP(A11,[1]LISTADHERENT!A$5:H$60,3,0) -> MBOGNING TUGMA GUY | C11: =IF(E11="ECHEC",0,IF(E11="",0,100000)) -> 100000 | D11: =IF(E11="ESPECES",0,0) -> 0 | E11: BANQUE | J11: =TONTDEC!F11+TONTDEC!G11 -> 0 | N11: =IF(O11=0,0,($C$38-O11)) -> 0
A12: AS201639 | B12: =VLOOKUP(A12,[1]LISTADHERENT!A$5:H$60,3,0) -> NANGUEN MARTIN | C12: =IF(E12="ECHEC",0,IF(E12="",0,100000)) -> 100000 | D12: =IF(E12="ESPECES",0,0) -> 0 | E12: BANQUE | J12: =TONTDEC!F12+TONTDEC!G12 -> 0 | N12: =IF(O12=0,0,($C$38-O12)) -> 0
A13: AS201622 | B13: =VLOOKUP(A13,[1]LISTADHERENT!A$5:H$60,3,0) -> NDJOMO ETIENNE | C13: =IF(E13="ECHEC",0,IF(E13="",0,100000)) -> 100000 | D13: =IF(E13="ESPECES",0,0) -> 0 | E13: BANQUE | J13: =TONTDEC!F13+TONTDEC!G13 -> 0 | N13: =IF(O13=0,0,($C$38-O13)) -> 0
A14: AS201624 | B14: =VLOOKUP(A14,[1]LISTADHERENT!A$5:H$60,3,0) -> NGONDIEP CLAUDE | C14: =IF(E14="ECHEC",0,IF(E14="",0,100000)) -> 100000 | D14: =IF(E14="ESPECES",0,0) -> 0 | E14: BANQUE | F14: 99500 | G14: 4000 | H14: ESPECES | J14: =TONTDEC!F14+TONTDEC!G14 -> 0 | N14: =IF(O14=0,0,($C$38-O14)) -> 0
A15: AS201614 | B15: =VLOOKUP(A15,[1]LISTADHERENT!A$5:H$60,3,0) -> NKEHE DAVID | C15: =IF(E15="ECHEC",0,IF(E15="",0,100000)) -> 100000 | D15: =IF(E15="ESPECES",0,0) -> 0 | E15: BANQUE | F15: 100000 | G15: 6000 | H15: ESPECES | J15: =TONTDEC!F15+TONTDEC!G15 -> 0 | N15: =IF(O15=0,0,($C$38-O15)) -> 0
A16: AS201629 | B16: =VLOOKUP(A16,[1]LISTADHERENT!A$5:H$60,3,0) -> NKEPSEU DIEUDONNE | C16: =IF(E16="ECHEC",0,IF(E16="",0,100000)) -> 100000 | D16: =IF(E16="ESPECES",0,0) -> 0 | E16: BANQUE | J16: =TONTDEC!F16+TONTDEC!G16 -> 0 | N16: =IF(O16=0,0,($C$38-O16)) -> 0
A17: AS201636 | B17: =VLOOKUP(A17,[1]LISTADHERENT!A$5:H$60,3,0) -> SIMO FONGANG ERIC | C17: =IF(E17="ECHEC",0,IF(E17="",0,100000)) -> 100000 | D17: =IF(E17="ESPECES",0,0) -> 0 | E17: BANQUE | J17: =TONTDEC!F17+TONTDEC!G17 -> 0 | N17: =IF(O17=0,0,($C$38-O17)) -> 0
A18: AS201636 | B18: =VLOOKUP(A18,[1]LISTADHERENT!A$5:H$60,3,0) -> SIMO FONGANG ERIC | C18: =IF(E18="ECHEC",0,IF(E18="",0,100000)) -> 100000 | D18: =IF(E18="ESPECES",0,0) -> 0 | E18: BANQUE | J18: =TONTDEC!F18+TONTDEC!G18 -> 0 | N18: =IF(O18=0,0,($C$38-O18)) -> 0
A19: AS201637 | B19: =VLOOKUP(A19,[1]LISTADHERENT!A$5:H$60,3,0) -> SIME MATHIEU | C19: =IF(E19="ECHEC",0,IF(E19="",0,100000)) -> 100000 | D19: =IF(E19="ESPECES",0,0) -> 0 | E19: BANQUE | J19: =TONTDEC!F19+TONTDEC!G19 -> 0 | N19: =IF(O19=0,0,($C$38-O19)) -> 0
A20: AS201637 | B20: =VLOOKUP(A20,[1]LISTADHERENT!A$5:H$60,3,0) -> SIME MATHIEU | C20: =IF(E20="ECHEC",0,IF(E20="",0,100000)) -> 100000 | D20: =IF(E20="ESPECES",0,0) -> 0 | E20: BANQUE | J20: =TONTDEC!F20+TONTDEC!G20 -> 0 | N20: =IF(O20=0,0,($C$38-O20)) -> 0
A21: AS201641 | B21: =VLOOKUP(A21,[1]LISTADHERENT!A$5:H$60,3,0) -> TCHOUAMOU MATHIEU | C21: =IF(E21="ECHEC",0,IF(E21="",0,100000)) -> 100000 | D21: =IF(E21="ESPECES",0,0) -> 0 | E21: BANQUE | J21: =TONTDEC!F21+TONTDEC!G21 -> 0 | N21: =IF(O21=0,0,($C$38-O21)) -> 0
A22: AS201644 | B22: =VLOOKUP(A22,[1]LISTADHERENT!A$5:H$60,3,0) -> TIEYAM ERNEST | C22: =IF(E22="ECHEC",0,IF(E22="",0,100000)) -> 100000 | D22: =IF(E22="ESPECES",0,0) -> 0 | E22: BANQUE | F22: 200000 | G22: 10000 | H22: ESPECES | J22: =TONTDEC!F22+TONTDEC!G22 -> 0 | N22: =IF(O22=0,0,($C$38-O22)) -> 0
A23: AS201647 | B23: =VLOOKUP(A23,[1]LISTADHERENT!A$5:H$60,3,0) -> YOUMBI EMMANUEL | C23: =IF(E23="ECHEC",0,IF(E23="",0,100000)) -> 100000 | D23: =IF(E23="ESPECES",0,0) -> 0 | E23: BANQUE | J23: =TONTDEC!F23+TONTDEC!G23 -> 0 | N23: =IF(O23=0,0,($C$38-O23)) -> 0
A25: TOTAL | C25: =SUM(C6:C24) -> 1800000 | D25: =SUM(D6:D24) -> 0 | F25: =SUM(F6:F24) -> 499500 | G25: =SUM(G6:G24) -> 24000 | J25: =SUM(J6:J24) -> 0 | N25: =SUM(N6:N24) -> 1270000 | O25: =SUM(O6:O24) -> 230000
C27: TONTINE | D27: REMBOURSEMENT PETIT LOT | E27: VENTE PETIT LOT | F27: VENTE LOT PRINCIPAL | G27: SOLDE EN CAISSE | K27: TONTINE + REMB + INTERET VENTE | L27: =C25+D32+O25 -> 2030000
K28: TONTINE | L28: =IF(L27>=3000000,1500000*2,1500000) -> 1500000
B29: ESPECES | C29: =SUMIFS(C6:C23,E6:E23,"ESPECES") -> 0 | D29: =SUMIFS(J6:J23,K6:K23,"ESPECES") -> 0 | E29: =SUMIFS(F6:F23,H6:H23,"ESPECES") -> 499500 | F29: =SUMIFS(N6:N23,L6:L23,"ESPECES") -> 0 | G29: =C29+D29-E29-F29 -> -499500 | K29: PETIT LOT | L29: =L27-L28-30500 -> 499500
B30: BANQUE | C30: =SUMIFS(C6:C23,E6:E23,"BANQUE") -> 1800000 | D30: =SUMIFS(J6:J23,K6:K23,"BANQUE") -> 0 | E30: =SUMIFS(F6:F23,H6:H23,"BANQUE") -> 0 | F30: =SUMIFS(N6:N23,L6:L23,"BANQUE") -> 0 | G30: =C30+D30-E30-F30 -> 1800000 | K30: RESTE | L30: =L29-F25 -> 0
B32: TOTAL | C32: =C29+C30 -> 1800000 | D32: =D29+D30 -> 0 | E32: =E29+E30 -> 499500 | F32: =F29+F30 -> 0 | G32: =G29+G30 -> 1300500
K33: ECHEC TONTINE | L33: 0
K34: ECHEC REMBOURSEMENT | L34: 0
B35: INTERET LOT PRINCIPAL | C35: =O25 -> 230000
B36: INTERET PETIT LOT | C36: =+G25 -> 24000
B38: MONTANT TONTINE | C38: 1500000
B39: MONTANT PETIT LOT A VENDRE | C39: =L29 -> 499500

Sheet TONTFEV
A1: ASSOCIATION | B1: ASELBY
A2: ANNEE | B2: 2019/2020
A3: TONTINE | B3: 100000
C4: 43877
A5: MATRICULE | B5: NOM ET PRENOM | C5: MONTANT TONTINE | D5: PENALITE | E5: MODE VERSEMENT TONTINE | F5: VENTE PETIT LOT | G5: INTERET PETIT LOT | H5: MODE VERSEMENT VENTE PETIT LOT | I5: NUMERO CHEQUE | J5: REMBOURSEMENT | K5: MODE VERSEMENT REMBOURSEMENT | L5: MODE VERSEMENT TONTINE PRINCIPAL | M5: NUMERO CHEQUE | N5: MONTANT TONTINE LOT PRINCIPAL | O5: INTERET LOT PRINCIPAL | P5: DATE VENTE
A6: AS201608 | B6: =VLOOKUP(A6,[1]LISTADHERENT!A$5:H$60,3,0) -> DJUOMBESSY ANTOINE | C6: =IF(E6="ECHEC",0,IF(E6="",0,100000)) -> 100000 | D6: =IF(E6="ESPECES",0,0) -> 0 | E6: BANQUE | J6: =TONTJANV!F6+TONTJANV!G6 -> 0 | N6: =IF(O6=0,0,($C$38-O6)) -> 0
A7: AS201613 | B7: =VLOOKUP(A7,[1]LISTADHERENT!A$5:H$60,3,0) -> HOTCHO BENJAMIN | C7: =IF(E7="ECHEC",0,IF(E7="",0,100000)) -> 100000 | D7: =IF(E7="ESPECES",0,0) -> 0 | E7: BANQUE | J7: =TONTJANV!F7+TONTJANV!G7 -> 0 | N7: =IF(O7=0,0,($C$38-O7)) -> 0
A8: AS201619 | B8: =VLOOKUP(A8,[1]LISTADHERENT!A$5:H$60,3,0) -> KOUATCHO MESSACK | C8: =IF(E8="ECHEC",0,IF(E8="",0,100000)) -> 100000 | D8: =IF(E8="ESPECES",0,0) -> 0 | E8: BANQUE | F8: 100000 | G8: 3000 | J8: =TONTJANV!F8+TONTJANV!G8 -> 104000 | K8: ESPECES | N8: =IF(O8=0,0,($C$38-O8)) -> 0
A9: AS201617 | B9: =VLOOKUP(A9,[1]LISTADHERENT!A$5:H$60,3,0) -> KOUAMOU MOISE | C9: =IF(E9="ECHEC",0,IF(E9="",0,100000)) -> 100000 | D9: =IF(E9="ESPECES",0,0) -> 0 | E9: BANQUE | J9: =TONTJANV!F9+TONTJANV!G9 -> 0 | N9: =IF(O9=0,0,($C$38-O9)) -> 0
A10: AS201649 | B10: =VLOOKUP(A10,[1]LISTADHERENT!A$5:H$60,3,0) -> MBOGNING TUGMA GUY | C10: =IF(E10="ECHEC",0,IF(E10="",0,100000)) -> 100000 | D10: =IF(E10="ESPECES",0,0) -> 0 | E10: BANQUE | F10: 200000 | G10: 5000 | J10: =TONTJANV!F10+TONTJANV!G10 -> 0 | N10: =IF(O10=0,0,($C$38-O10)) -> 0
A11: AS201649 | B11: =VLOOKUP(A11,[1]LISTADHERENT!A$5:H$60,3,0) -> MBOGNING TUGMA GUY | C11: =IF(E11="ECHEC",0,IF(E11="",0,100000)) -> 100000 | D11: =IF(E11="ESPECES",0,0) -> 0 | E11: BANQUE | J11: =TONTJANV!F11+TONTJANV!G11 -> 0 | N11: =IF(O11=0,0,($C$38-O11)) -> 0
A12: AS201639 | B12: =VLOOKUP(A12,[1]LISTADHERENT!A$5:H$60,3,0) -> NANGUEN MARTIN | C12: =IF(E12="ECHEC",0,IF(E12="",0,100000)) -> 100000 | D12: =IF(E12="ESPECES",0,0) -> 0 | E12: BANQUE | J12: =TONTJANV!F12+TONTJANV!G12 -> 0 | N12: =IF(O12=0,0,($C$38-O12)) -> 0
A13: AS201622 | B13: =VLOOKUP(A13,[1]LISTADHERENT!A$5:H$60,3,0) -> NDJOMO ETIENNE | C13: =IF(E13="ECHEC",0,IF(E13="",0,100000)) -> 100000 | D13: =IF(E13="ESPECES",0,0) -> 0 | E13: BANQUE | F13: 100000 | G13: 3000 | J13: =TONTJANV!F13+TONTJANV!G13 -> 0 | N13: =IF(O13=0,0,($C$38-O13)) -> 0
A14: AS201624 | B14: =VLOOKUP(A14,[1]LISTADHERENT!A$5:H$60,3,0) -> NGONDIEP CLAUDE | C14: =IF(E14="ECHEC",0,IF(E14="",0,100000)) -> 100000 | D14: =IF(E14="ESPECES",0,0) -> 0 | E14: BANQUE | J14: =TONTJANV!F14+TONTJANV!G14 -> 103500 | K14: ESPECES | N14: =IF(O14=0,0,($C$38-O14)) -> 0
A15: AS201614 | B15: =VLOOKUP(A15,[1]LISTADHERENT!A$5:H$60,3,0) -> NKEHE DAVID | C15: =IF(E15="ECHEC",0,IF(E15="",0,100000)) -> 100000 | D15: =IF(E15="ESPECES",0,0) -> 0 | E15: ESPECES | F15: 213500 | G15: 4000 | J15: =TONTJANV!F15+TONTJANV!G15 -> 106000 | K15: ESPECES | N15: =IF(O15=0,0,($C$38-O15)) -> 0
A16: AS201629 | B16: =VLOOKUP(A16,[1]LISTADHERENT!A$5:H$60,3,0) -> NKEPSEU DIEUDONNE | C16: =IF(E16="ECHEC",0,IF(E16="",0,100000)) -> 100000 | D16: =IF(E16="ESPECES",0,0) -> 0 | E16: BANQUE | F16: 100000 | G16: 2000 | J16: =TONTJANV!F16+TONTJANV!G16 -> 0 | N16: =IF(O16=0,0,($C$38-O16)) -> 1400000 | O16: 100000
A17: AS201636 | B17: =VLOOKUP(A17,[1]LISTADHERENT!A$5:H$60,3,0) -> SIMO FONGANG ERIC | C17: =IF(E17="ECHEC",0,IF(E17="",0,100000)) -> 100000 | D17: =IF(E17="ESPECES",0,0) -> 0 | E17: BANQUE | J17: =TONTJANV!F17+TONTJANV!G17 -> 0 | N17: =IF(O17=0,0,($C$38-O17)) -> 0
A18: AS201636 | B18: =VLOOKUP(A18,[1]LISTADHERENT!A$5:H$60,3,0) -> SIMO FONGANG ERIC | C18: =IF(E18="ECHEC",0,IF(E18="",0,100000)) -> 100000 | D18: =IF(E18="ESPECES",0,0) -> 0 | E18: BANQUE | J18: =TONTJANV!F18+TONTJANV!G18 -> 0 | N18: =IF(O18=0,0,($C$38-O18)) -> 0
A19: AS201637 | B19: =VLOOKUP(A19,[1]LISTADHERENT!A$5:H$60,3,0) -> SIME MATHIEU | C19: =IF(E19="ECHEC",0,IF(E19="",0,100000)) -> 100000 | D19: =IF(E19="ESPECES",0,0) -> 0 | E19: BANQUE | J19: =TONTJANV!F19+TONTJANV!G19 -> 0 | N19: =IF(O19=0,0,($C$38-O19)) -> 0
A20: AS201637 | B20: =VLOOKUP(A20,[1]LISTADHERENT!A$5:H$60,3,0) -> SIME MATHIEU | C20: =IF(E20="ECHEC",0,IF(E20="",0,100000)) -> 100000 | D20: =IF(E20="ESPECES",0,0) -> 0 | E20: BANQUE | J20: =TONTJANV!F20+TONTJANV!G20 -> 0 | N20: =IF(O20=0,0,($C$38-O20)) -> 0
A21: AS201641 | B21: =VLOOKUP(A21,[1]LISTADHERENT!A$5:H$60,3,0) -> TCHOUAMOU MATHIEU | C21: =IF(E21="ECHEC",0,IF(E21="",0,100000)) -> 100000 | D21: =IF(E21="ESPECES",0,0) -> 0 | E21: BANQUE | J21: =TONTJANV!F21+TONTJANV!G21 -> 0 | N21: =IF(O21=0,0,($C$38-O21)) -> 0
A22: AS201644 | B22: =VLOOKUP(A22,[1]LISTADHERENT!A$5:H$60,3,0) -> TIEYAM ERNEST | C22: =IF(E22="ECHEC",0,IF(E22="",0,100000)) -> 100000 | D22: =IF(E22="ESPECES",0,0) -> 0 | E22: BANQUE | F22: 210000 | G22: 20000 | J22: =TONTJANV!F22+TONTJANV!G22 -> 210000 | K22: ECHEC | N22: =IF(O22=0,0,($C$38-O22)) -> 0
A23: AS201647 | B23: =VLOOKUP(A23,[1]LISTADHERENT!A$5:H$60,3,0) -> YOUMBI EMMANUEL | C23: =IF(E23="ECHEC",0,IF(E23="",0,100000)) -> 100000 | D23: =IF(E23="ESPECES",0,0) -> 0 | E23: BANQUE | J23: =TONTJANV!F23+TONTJANV!G23 -> 0 | N23: =IF(O23=0,0,($C$38-O23)) -> 0
A25: TOTAL | C25: =SUM(C6:C24) -> 1800000 | D25: =SUM(D6:D24) -> 0 | F25: =SUM(F6:F24) -> 923500 | G25: =SUM(G6:G24) -> 37000 | J25: =SUM(J6:J24) -> 523500 | N25: =SUM(N6:N24) -> 1400000 | O25: =SUM(O6:O24) -> 100000
C27: TONTINE | D27: REMBOURSEMENT PETIT LOT | E27: VENTE PETIT LOT | F27: VENTE LOT PRINCIPAL | G27: SOLDE EN CAISSE | K27: TONTINE + REMB + INTERET VENTE | L27: =C25+D32+O25 -> 2213500
K28: TONTINE | L28: =IF(L27>=3000000,1500000*2,1500000) -> 1500000
B29: ESPECES | C29: =SUMIFS(C6:C23,E6:E23,"ESPECES") -> 100000 | D29: =SUMIFS(J6:J23,K6:K23,"ESPECES") -> 313500 | E29: =SUMIFS(F6:F23,H6:H23,"ESPECES") -> 0 | F29: =SUMIFS(N6:N23,L6:L23,"ESPECES") -> 0 | G29: =C29+D29-E29-F29 -> 413500 | K29: PETIT LOT | L29: =L27-L28 -> 713500
B30: BANQUE | C30: =SUMIFS(C6:C23,E6:E23,"BANQUE") -> 1700000 | D30: =SUMIFS(J6:J23,K6:K23,"BANQUE") -> 0 | E30: =SUMIFS(F6:F23,H6:H23,"BANQUE") -> 0 | F30: =SUMIFS(N6:N23,L6:L23,"BANQUE") -> 0 | G30: =C30+D30-E30-F30 -> 1700000 | K30: RESTE | L30: =L29-F25 -> -210000
B32: TOTAL | C32: =C29+C30 -> 1800000 | D32: =D29+D30 -> 313500 | E32: =E29+E30 -> 0 | F32: =F29+F30 -> 0 | G32: =G29+G30 -> 2113500 | K32: ECHEC TONTINE | L32: 0
K33: ECHEC REMBOURSEMENT | L33: 210000 | M33: TYAM ERNEST
B35: INTERET LOT PRINCIPAL | C35: =O25 -> 100000
B36: INTERET PETIT LOT | C36: =+G25 -> 37000
B38: MONTANT TONTINE | C38: 1500000
B39: MONTANT PETIT LOT A VENDRE | C39: =L29 -> 713500

Sheet TONTMARS
A1: ASSOCIATION | B1: ASELBY
A2: ANNEE | B2: 2019/2020
A3: TONTINE | B3: 100000
C4: 43905
A5: MATRICULE | B5: NOM ET PRENOM | C5: MONTANT TONTINE | D5: PENALITE | E5: MODE VERSEMENT TONTINE | F5: VENTE PETIT LOT | G5: INTERET PETIT LOT | H5: MODE VERSEMENT VENTE PETIT LOT | I5: NUMERO CHEQUE | J5: REMBOURSEMENT | K5: MODE VERSEMENT REMBOURSEMENT | L5: MODE VERSEMENT TONTINE PRINCIPAL | M5: NUMERO CHEQUE | N5: MONTANT TONTINE LOT PRINCIPAL | O5: INTERET LOT PRINCIPAL | P5: DATE VENTE
A6: AS201608 | B6: =VLOOKUP(A6,[1]LISTADHERENT!A$5:H$60,3,0) -> DJUOMBESSY ANTOINE | C6: =IF(E6="ECHEC",0,IF(E6="",0,100000)) -> 100000 | D6: =IF(E6="ESPECES",0,0) -> 0 | E6: BANQUE | J6: =TONTFEV!F6+TONTFEV!G6 -> 0 | N6: =IF(O6=0,0,($C$38-O6)) -> 0
A7: AS201613 | B7: =VLOOKUP(A7,[1]LISTADHERENT!A$5:H$60,3,0) -> HOTCHO BENJAMIN | C7: =IF(E7="ECHEC",0,IF(E7="",0,100000)) -> 100000 | D7: =IF(E7="ESPECES",0,0) -> 0 | E7: BANQUE | J7: =TONTFEV!F7+TONTFEV!G7 -> 0 | N7: =IF(O7=0,0,($C$38-O7)) -> 0
A8: AS201619 | B8: =VLOOKUP(A8,[1]LISTADHERENT!A$5:H$60,3,0) -> KOUATCHO MESSACK | C8: =IF(E8="ECHEC",0,IF(E8="",0,100000)) -> 100000 | D8: =IF(E8="ESPECES",0,0) -> 0 | E8: BANQUE | F8: 200000 | G8: 2500 | H8: BANQUE | J8: =TONTFEV!F8+TONTFEV!G8 -> 103000 | K8: BANQUE | N8: =IF(O8=0,0,($C$38-O8)) -> 0
A9: AS201617 | B9: =VLOOKUP(A9,[1]LISTADHERENT!A$5:H$60,3,0) -> KOUAMOU MOISE | C9: =IF(E9="ECHEC",0,IF(E9="",0,100000)) -> 100000 | D9: =IF(E9="ESPECES",0,0) -> 0 | E9: BANQUE | J9: =TONTFEV!F9+TONTFEV!G9 -> 0 | N9: =IF(O9=0,0,($C$38-O9)) -> 1365000 | O9: 135000
A10: AS201649 | B10: =VLOOKUP(A10,[1]LISTADHERENT!A$5:H$60,3,0) -> MBOGNING TUGMA GUY | C10: =IF(E10="ECHEC",0,IF(E10="",0,100000)) -> 100000 | D10: =IF(E10="ESPECES",0,0) -> 0 | E10: BANQUE | F10: 100000 | G10: 1000 | H10: BANQUE | J10: =TONTFEV!F10+TONTFEV!G10 -> 205000 | K10: BANQUE | N10: =IF(O10=0,0,($C$38-O10)) -> 0
A11: AS201649 | B11: =VLOOKUP(A11,[1]LISTADHERENT!A$5:H$60,3,0) -> MBOGNING TUGMA GUY | C11: =IF(E11="ECHEC",0,IF(E11="",0,100000)) -> 100000 | D11: =IF(E11="ESPECES",0,0) -> 0 | E11: BANQUE | J11: =TONTFEV!F11+TONTFEV!G11 -> 0 | N11: =IF(O11=0,0,($C$38-O11)) -> 0
A12: AS201639 | B12: =VLOOKUP(A12,[1]LISTADHERENT!A$5:H$60,3,0) -> NANGUEN MARTIN | C12: =IF(E12="ECHEC",0,IF(E12="",0,100000)) -> 100000 | D12: =IF(E12="ESPECES",0,0) -> 0 | E12: BANQUE | J12: =TONTFEV!F12+TONTFEV!G12 -> 0 | N12: =IF(O12=0,0,($C$38-O12)) -> 0
A13: AS201622 | B13: =VLOOKUP(A13,[1]LISTADHERENT!A$5:H$60,3,0) -> NDJOMO ETIENNE | C13: =IF(E13="ECHEC",0,IF(E13="",0,100000)) -> 100000 | D13: =IF(E13="ESPECES",0,0) -> 0 | E13: BANQUE | F13: 100000 | G13: 1500 | H13: BANQUE | J13: =TONTFEV!F13+TONTFEV!G13 -> 103000 | K13: BANQUE | N13: =IF(O13=0,0,($C$38-O13)) -> 0
A14: AS201624 | B14: =VLOOKUP(A14,[1]LISTADHERENT!A$5:H$60,3,0) -> NGONDIEP CLAUDE | C14: =IF(E14="ECHEC",0,IF(E14="",0,100000)) -> 100000 | D14: =IF(E14="ESPECES",0,0) -> 0 | E14: BANQUE | J14: =TONTFEV!F14+TONTFEV!G14 -> 0 | N14: =IF(O14=0,0,($C$38-O14)) -> 0
A15: AS201614 | B15: =VLOOKUP(A15,[1]LISTADHERENT!A$5:H$60,3,0) -> NKEHE DAVID | C15: =IF(E15="ECHEC",0,IF(E15="",0,100000)) -> 100000 | D15: =IF(E15="ESPECES",0,0) -> 0 | E15: BANQUE | F15: 217500 | G15: 8000 | H15: ECHEC | J15: =TONTFEV!F15+TONTFEV!G15 -> 217500 | K15: ECHEC | N15: =IF(O15=0,0,($C$38-O15)) -> 0
A16: AS201629 | B16: =VLOOKUP(A16,[1]LISTADHERENT!A$5:H$60,3,0) -> NKEPSEU DIEUDONNE | C16: =IF(E16="ECHEC",0,IF(E16="",0,100000)) -> 100000 | D16: =IF(E16="ESPECES",0,0) -> 0 | E16: BANQUE | F16: 200000 | G16: 3000 | H16: BANQUE | J16: =TONTFEV!F16+TONTFEV!G16 -> 102000 | K16: BANQUE | N16: =IF(O16=0,0,($C$38-O16)) -> 0
A17: AS201636 | B17: =VLOOKUP(A17,[1]LISTADHERENT!A$5:H$60,3,0) -> SIMO FONGANG ERIC | C17: =IF(E17="ECHEC",0,IF(E17="",0,100000)) -> 100000 | D17: =IF(E17="ESPECES",0,0) -> 0 | E17: ESPECES | F17: 200000 | G17: 2500 | H17: BANQUE | J17: =TONTFEV!F17+TONTFEV!G17 -> 0 | N17: =IF(O17=0,0,($C$38-O17)) -> 0
A18: AS201636 | B18: =VLOOKUP(A18,[1]LISTADHERENT!A$5:H$60,3,0) -> SIMO FONGANG ERIC | C18: =IF(E18="ECHEC",0,IF(E18="",0,100000)) -> 100000 | D18: =IF(E18="ESPECES",0,0) -> 0 | E18: ESPECES | J18: =TONTFEV!F18+TONTFEV!G18 -> 0 | N18: =IF(O18=0,0,($C$38-O18)) -> 0
A19: AS201637 | B19: =VLOOKUP(A19,[1]LISTADHERENT!A$5:H$60,3,0) -> SIME MATHIEU | C19: =IF(E19="ECHEC",0,IF(E19="",0,100000)) -> 100000 | D19: =IF(E19="ESPECES",0,0) -> 0 | E19: BANQUE | J19: =TONTFEV!F19+TONTFEV!G19 -> 0 | N19: =IF(O19=0,0,($C$38-O19)) -> 0
A20: AS201637 | B20: =VLOOKUP(A20,[1]LISTADHERENT!A$5:H$60,3,0) -> SIME MATHIEU | C20: =IF(E20="ECHEC",0,IF(E20="",0,100000)) -> 100000 | D20: =IF(E20="ESPECES",0,0) -> 0 | E20: BANQUE | J20: =TONTFEV!F20+TONTFEV!G20 -> 0 | N20: =IF(O20=0,0,($C$38-O20)) -> 0
A21: AS201641 | B21: =VLOOKUP(A21,[1]LISTADHERENT!A$5:H$60,3,0) -> TCHOUAMOU MATHIEU | C21: =IF(E21="ECHEC",0,IF(E21="",0,100000)) -> 100000 | D21: =IF(E21="ESPECES",0,0) -> 0 | E21: BANQUE | F21: 200000 | G21: 2000 | H21: BANQUE | J21: =TONTFEV!F21+TONTFEV!G21 -> 0 | N21: =IF(O21=0,0,($C$38-O21)) -> 0
A22: AS201644 | B22: =VLOOKUP(A22,[1]LISTADHERENT!A$5:H$60,3,0) -> TIEYAM ERNEST | C22: =IF(E22="ECHEC",0,IF(E22="",0,100000)) -> 100000 | D22: =IF(E22="ESPECES",0,0) -> 0 | E22: BANQUE | F22: 200000 | G22: 2000 | H22: BANQUE | J22: =TONTFEV!F22+TONTFEV!G22 -> 230000 | K22: BANQUE | N22: =IF(O22=0,0,($C$38-O22)) -> 0
A23: AS201647 | B23: =VLOOKUP(A23,[1]LISTADHERENT!A$5:H$60,3,0) -> YOUMBI EMMANUEL | C23: =IF(E23="ECHEC",0,IF(E23="",0,100000)) -> 100000 | D23: =IF(E23="ESPECES",0,0) -> 0 | E23: BANQUE | J23: =TONTFEV!F23+TONTFEV!G23 -> 0 | N23: =IF(O23=0,0,($C$38-O23)) -> 0
A25: TOTAL | C25: =SUM(C6:C24) -> 1800000 | D25: =SUM(D6:D24) -> 0 | F25: =SUM(F6:F24) -> 1417500 | G25: =SUM(G6:G24) -> 22500 | J25: =SUM(J6:J24) -> 960500 | N25: =SUM(N6:N24) -> 1365000 | O25: =SUM(O6:O24) -> 135000
C27: TONTINE | D27: REMBOURSEMENT PETIT LOT | E27: VENTE PETIT LOT | F27: VENTE LOT PRINCIPAL | G27: SOLDE EN CAISSE | K27: TONTINE + REMB + INTERET VENTE | L27: =C25+D32+O25 -> 2678000
K28: TONTINE | L28: =IF(L27>=3000000,1500000*2,1500000) -> 1500000
B29: ESPECES | C29: =SUMIFS(C6:C23,E6:E23,"ESPECES") -> 200000 | D29: =SUMIFS(J6:J23,K6:K23,"ESPECES") -> 0 | E29: =SUMIFS(F6:F23,H6:H23,"ESPECES") -> 0 | F29: =SUMIFS(N6:N23,L6:L23,"ESPECES") -> 0 | G29: =C29+D29-E29-F29 -> 200000 | K29: PETIT LOT | L29: =L27-L28 -> 1178000
B30: BANQUE | C30: =SUMIFS(C6:C23,E6:E23,"BANQUE") -> 1600000 | D30: =SUMIFS(J6:J23,K6:K23,"BANQUE") -> 743000 | E30: =SUMIFS(F6:F23,H6:H23,"BANQUE") -> 1200000 | F30: =SUMIFS(N6:N23,L6:L23,"BANQUE") -> 0 | G30: =C30+D30-E30-F30 -> 1143000 | K30: RESTE | L30: =L29-F25 -> -239500
B32: TOTAL | C32: =C29+C30 -> 1800000 | D32: =D29+D30 -> 743000 | E32: =E29+E30 -> 1200000 | F32: =F29+F30 -> 0 | G32: =G29+G30 -> 1343000 | K32: ECHEC TONTINE | L32: 0
K33: ECHEC REMBOURSEMENT | L33: 217500 | M33: NKEHEP DAVID
B35: INTERET LOT PRINCIPAL | C35: =O25 -> 135000
B36: INTERET PETIT LOT | C36: =+G25 -> 22500
B38: MONTANT TONTINE | C38: 1500000
B39: MONTANT PETIT LOT A VENDRE | C39: =L29 -> 1178000

Sheet TONTAVRIL
A1: ASSOCIATION | B1: ASELBY
A2: ANNEE | B2: 2019/2020
A3: TONTINE | B3: 100000
C4: 43940
A5: MATRICULE | B5: NOM ET PRENOM | C5: MONTANT TONTINE | D5: PENALITE | E5: MODE VERSEMENT TONTINE | F5: VENTE PETIT LOT | G5: INTERET PETIT LOT | H5: MODE VERSEMENT VENTE PETIT LOT | I5: NUMERO CHEQUE | J5: REMBOURSEMENT | K5: MODE VERSEMENT REMBOURSEMENT | L5: MODE VERSEMENT TONTINE PRINCIPAL | M5: NUMERO CHEQUE | N5: MONTANT TONTINE LOT PRINCIPAL | O5: INTERET LOT PRINCIPAL | P5: DATE VENTE
A6: AS201608 | B6: =VLOOKUP(A6,[1]LISTADHERENT!A$5:H$60,3,0) -> DJUOMBESSY ANTOINE | C6: =IF(E6="ECHEC",0,IF(E6="",0,100000)) -> 100000 | D6: =IF(E6="ESPECES",0,0) -> 0 | E6: BANQUE | J6: =TONTMARS!F6+TONTMARS!G6 -> 0 | N6: =IF(O6=0,0,($C$38-O6)) -> 0
A7: AS201613 | B7: =VLOOKUP(A7,[1]LISTADHERENT!A$5:H$60,3,0) -> HOTCHO BENJAMIN | C7: =IF(E7="ECHEC",0,IF(E7="",0,100000)) -> 100000 | D7: =IF(E7="ESPECES",0,0) -> 0 | E7: BANQUE | J7: =TONTMARS!F7+TONTMARS!G7 -> 0 | N7: =IF(O7=0,0,($C$38-O7)) -> 1400000 | O7: 100000
A8: AS201619 | B8: =VLOOKUP(A8,[1]LISTADHERENT!A$5:H$60,3,0) -> KOUATCHO MESSACK | C8: =IF(E8="ECHEC",0,IF(E8="",0,100000)) -> 100000 | D8: =IF(E8="ESPECES",0,0) -> 0 | E8: BANQUE | J8: =TONTMARS!F8+TONTMARS!G8 -> 202500 | K8: BANQUE | N8: =IF(O8=0,0,($C$38-O8)) -> 0
A9: AS201617 | B9: =VLOOKUP(A9,[1]LISTADHERENT!A$5:H$60,3,0) -> KOUAMOU MOISE | C9: =IF(E9="ECHEC",0,IF(E9="",0,100000)) -> 100000 | D9: =IF(E9="ESPECES",0,0) -> 0 | E9: BANQUE | J9: =TONTMARS!F9+TONTMARS!G9 -> 0 | N9: =IF(O9=0,0,($C$38-O9)) -> 0
A10: AS201649 | B10: =VLOOKUP(A10,[1]LISTADHERENT!A$5:H$60,3,0) -> MBOGNING TUGMA GUY | C10: =IF(E10="ECHEC",0,IF(E10="",0,100000)) -> 100000 | D10: =IF(E10="ESPECES",0,0) -> 0 | E10: BANQUE | J10: =TONTMARS!F10+TONTMARS!G10 -> 101000 | K10: BANQUE | N10: =IF(O10=0,0,($C$38-O10)) -> 0
A11: AS201649 | B11: =VLOOKUP(A11,[1]LISTADHERENT!A$5:H$60,3,0) -> MBOGNING TUGMA GUY | C11: =IF(E11="ECHEC",0,IF(E11="",0,100000)) -> 100000 | D11: =IF(E11="ESPECES",0,0) -> 0 | E11: BANQUE | J11: =TONTMARS!F11+TONTMARS!G11 -> 0 | N11: =IF(O11=0,0,($C$38-O11)) -> 0
A12: AS201639 | B12: =VLOOKUP(A12,[1]LISTADHERENT!A$5:H$60,3,0) -> NANGUEN MARTIN | C12: =IF(E12="ECHEC",0,IF(E12="",0,100000)) -> 100000 | D12: =IF(E12="ESPECES",0,0) -> 0 | E12: BANQUE | J12: =TONTMARS!F12+TONTMARS!G12 -> 0 | N12: =IF(O12=0,0,($C$38-O12)) -> 0
A13: AS201622 | B13: =VLOOKUP(A13,[1]LISTADHERENT!A$5:H$60,3,0) -> NDJOMO ETIENNE | C13: =IF(E13="ECHEC",0,IF(E13="",0,100000)) -> 100000 | D13: =IF(E13="ESPECES",0,0) -> 0 | E13: BANQUE | J13: =TONTMARS!F13+TONTMARS!G13 -> 101500 | K13: BANQUE | N13: =IF(O13=0,0,($C$38-O13)) -> 1400000 | O13: 100000
A14: AS201624 | B14: =VLOOKUP(A14,[1]LISTADHERENT!A$5:H$60,3,0) -> NGONDIEP CLAUDE | C14: =IF(E14="ECHEC",0,IF(E14="",0,100000)) -> 100000 | D14: =IF(E14="ESPECES",0,0) -> 0 | E14: BANQUE | J14: =TONTMARS!F14+TONTMARS!G14 -> 0 | N14: =IF(O14=0,0,($C$38-O14)) -> 0
A15: AS201614 | B15: =VLOOKUP(A15,[1]LISTADHERENT!A$5:H$60,3,0) -> NKEHE DAVID | C15: =IF(E15="ECHEC",0,IF(E15="",0,100000)) -> 100000 | D15: =IF(E15="ESPECES",0,0) -> 0 | E15: BANQUE | F15: 225500 | G15: 4000 | J15: =TONTMARS!F15+TONTMARS!G15 -> 225500 | N15: =IF(O15=0,0,($C$38-O15)) -> 0
A16: AS201629 | B16: =VLOOKUP(A16,[1]LISTADHERENT!A$5:H$60,3,0) -> NKEPSEU DIEUDONNE | C16: =IF(E16="ECHEC",0,IF(E16="",0,100000)) -> 100000 | D16: =IF(E16="ESPECES",0,0) -> 0 | E16: BANQUE | J16: =TONTMARS!F16+TONTMARS!G16 -> 203000 | K16: BANQUE | N16: =IF(O16=0,0,($C$38-O16)) -> 0
A17: AS201636 | B17: =VLOOKUP(A17,[1]LISTADHERENT!A$5:H$60,3,0) -> SIMO FONGANG ERIC | C17: =IF(E17="ECHEC",0,IF(E17="",0,100000)) -> 100000 | D17: =IF(E17="ESPECES",0,0) -> 0 | E17: ESPECES | J17: =TONTMARS!F17+TONTMARS!G17-22000 -> 180500 | K17: ESPECES | N17: =IF(O17=0,0,($C$38-O17)) -> 0
A18: AS201636 | B18: =VLOOKUP(A18,[1]LISTADHERENT!A$5:H$60,3,0) -> SIMO FONGANG ERIC | C18: =IF(E18="ECHEC",0,IF(E18="",0,100000)) -> 100000 | D18: =IF(E18="ESPECES",0,0) -> 0 | E18: ESPECES | J18: =TONTMARS!F18+TONTMARS!G18 -> 0 | N18: =IF(O18=0,0,($C$38-O18)) -> 0
A19: AS201637 | B19: =VLOOKUP(A19,[1]LISTADHERENT!A$5:H$60,3,0) -> SIME MATHIEU | C19: =IF(E19="ECHEC",0,IF(E19="",0,100000)) -> 100000 | D19: =IF(E19="ESPECES",0,0) -> 0 | E19: BANQUE | J19: =TONTMARS!F19+TONTMARS!G19 -> 0 | N19: =IF(O19=0,0,($C$38-O19)) -> 0
A20: AS201637 | B20: =VLOOKUP(A20,[1]LISTADHERENT!A$5:H$60,3,0) -> SIME MATHIEU | C20: =IF(E20="ECHEC",0,IF(E20="",0,100000)) -> 100000 | D20: =IF(E20="ESPECES",0,0) -> 0 | E20: BANQUE | J20: =TONTMARS!F20+TONTMARS!G20 -> 0 | N20: =IF(O20=0,0,($C$38-O20)) -> 0
A21: AS201641 | B21: =VLOOKUP(A21,[1]LISTADHERENT!A$5:H$60,3,0) -> TCHOUAMOU MATHIEU | C21: =IF(E21="ECHEC",0,IF(E21="",0,100000)) -> 100000 | D21: =IF(E21="ESPECES",0,0) -> 0 | E21: BANQUE | J21: =TONTMARS!F21+TONTMARS!G21 -> 202000 | K21: BANQUE | N21: =IF(O21=0,0,($C$38-O21)) -> 0
A22: AS201644 | B22: =VLOOKUP(A22,[1]LISTADHERENT!A$5:H$60,3,0) -> TIEYAM ERNEST | C22: =IF(E22="ECHEC",0,IF(E22="",0,100000)) -> 100000 | D22: =IF(E22="ESPECES",0,0) -> 0 | E22: BANQUE | F22: 202000 | G22: 4000 | J22: =TONTMARS!F22+TONTMARS!G22 -> 202000 | N22: =IF(O22=0,0,($C$38-O22)) -> 0
A23: AS201647 | B23: =VLOOKUP(A23,[1]LISTADHERENT!A$5:H$60,3,0) -> YOUMBI EMMANUEL | C23: =IF(E23="ECHEC",0,IF(E23="",0,100000)) -> 100000 | D23: =IF(E23="ESPECES",0,0) -> 0 | E23: BANQUE | J23: =TONTFEV!F23+TONTFEV!G23 -> 0 | N23: =IF(O23=0,0,($C$38-O23)) -> 0
A25: TOTAL | C25: =SUM(C6:C24) -> 1800000 | D25: =SUM(D6:D24) -> 0 | F25: =SUM(F6:F24) -> 427500 | G25: =SUM(G6:G24) -> 8000 | J25: =SUM(J6:J24) -> 1418000 | N25: =SUM(N6:N24) -> 2800000 | O25: =SUM(O6:O24) -> 200000
C27: TONTINE | D27: REMBOURSEMENT PETIT LOT | E27: VENTE PETIT LOT | F27: VENTE LOT PRINCIPAL | G27: SOLDE EN CAISSE | K27: TONTINE + REMB + INTERET VENTE | L27: =C25+D32+O25+9500 -> 3000000
K28: TONTINE | L28: =IF(L27>=3000000,1500000*2,1500000) -> 3000000
B29: ESPECES | C29: =SUMIFS(C6:C23,E6:E23,"ESPECES") -> 200000 | D29: =SUMIFS(J6:J23,K6:K23,"ESPECES") -> 180500 | E29: =SUMIFS(F6:F23,H6:H23,"ESPECES") -> 0 | F29: =SUMIFS(N6:N23,L6:L23,"ESPECES") -> 0 | G29: =C29+D29-E29-F29 -> 380500 | K29: PETIT LOT | L29: =L27-L28 -> 0
B30: BANQUE | C30: =SUMIFS(C6:C23,E6:E23,"BANQUE") -> 1600000 | D30: =SUMIFS(J6:J23,K6:K23,"BANQUE") -> 810000 | E30: =SUMIFS(F6:F23,H6:H23,"BANQUE") -> 0 | F30: =SUMIFS(N6:N23,L6:L23,"BANQUE") -> 0 | G30: =C30+D30-E30-F30 -> 2410000 | K30: RESTE | L30: =L29-F25 -> -427500
B32: TOTAL | C32: =C29+C30 -> 1800000 | D32: =D29+D30 -> 990500 | E32: =E29+E30 -> 0 | F32: =F29+F30 -> 0 | G32: =G29+G30 -> 2790500 | J32: COMPLEMENT TONTINE 9500 | K32: ECHEC TONTINE | L32: 0
K33: ECHEC REMBOURSEMENT | L33: =225500+202000 -> 427500 | M33: KEHEP/TYAM
B35: INTERET LOT PRINCIPAL | C35: =O25 -> 200000
B36: INTERET PETIT LOT | C36: =+G25 -> 8000
B38: MONTANT TONTINE | C38: 1500000
B39: MONTANT PETIT LOT A VENDRE | C39: =L29 -> 0

Sheet TONTMAI
A1: ASSOCIATION | B1: ASELBY
A2: ANNEE | B2: 2019/2020
A3: TONTINE | B3: 100000
C4: 43968
A5: MATRICULE | B5: NOM ET PRENOM | C5: MONTANT TONTINE | D5: PENALITE | E5: MODE VERSEMENT TONTINE | F5: VENTE PETIT LOT | G5: INTERET PETIT LOT | H5: MODE VERSEMENT VENTE PETIT LOT | I5: NUMERO CHEQUE | J5: REMBOURSEMENT | K5: MODE VERSEMENT REMBOURSEMENT | L5: MODE VERSEMENT TONTINE PRINCIPAL | M5: NUMERO CHEQUE | N5: MONTANT TONTINE LOT PRINCIPAL | O5: INTERET LOT PRINCIPAL | P5: DATE VENTE
A6: AS201608 | B6: =VLOOKUP(A6,[1]LISTADHERENT!A$5:H$60,3,0) -> DJUOMBESSY ANTOINE | C6: =IF(E6="ECHEC",0,IF(E6="",0,100000)) -> 100000 | D6: =IF(E6="ESPECES",0,0) -> 0 | E6: BANQUE | J6: =TONTAVRIL!F6+TONTAVRIL!G6 -> 0 | N6: =IF(O6=0,0,($C$38-O6)) -> 0
A7: AS201613 | B7: =VLOOKUP(A7,[1]LISTADHERENT!A$5:H$60,3,0) -> HOTCHO BENJAMIN | C7: =IF(E7="ECHEC",0,IF(E7="",0,100000)) -> 100000 | D7: =IF(E7="ESPECES",0,0) -> 0 | E7: BANQUE | J7: =TONTAVRIL!F7+TONTAVRIL!G7 -> 0 | N7: =IF(O7=0,0,($C$38-O7)) -> 0
A8: AS201619 | B8: =VLOOKUP(A8,[1]LISTADHERENT!A$5:H$60,3,0) -> KOUATCHO MESSACK | C8: =IF(E8="ECHEC",0,IF(E8="",0,100000)) -> 100000 | D8: =IF(E8="ESPECES",0,0) -> 0 | E8: BANQUE | F8: 200000 | G8: 10000 | J8: =TONTAVRIL!F8+TONTAVRIL!G8 -> 0 | N8: =IF(O8=0,0,($C$38-O8)) -> 0
A9: AS201617 | B9: =VLOOKUP(A9,[1]LISTADHERENT!A$5:H$60,3,0) -> KOUAMOU MOISE | C9: =IF(E9="ECHEC",0,IF(E9="",0,100000)) -> 100000 | D9: =IF(E9="ESPECES",0,0) -> 0 | E9: BANQUE | J9: =TONTAVRIL!F9+TONTAVRIL!G9 -> 0 | N9: =IF(O9=0,0,($C$38-O9)) -> 0
A10: AS201649 | B10: =VLOOKUP(A10,[1]LISTADHERENT!A$5:H$60,3,0) -> MBOGNING TUGMA GUY | C10: =IF(E10="ECHEC",0,IF(E10="",0,100000)) -> 100000 | D10: =IF(E10="ESPECES",0,0) -> 0 | E10: BANQUE | J10: =TONTAVRIL!F10+TONTAVRIL!G10 -> 0 | N10: =IF(O10=0,0,($C$38-O10)) -> 0
A11: AS201649 | B11: =VLOOKUP(A11,[1]LISTADHERENT!A$5:H$60,3,0) -> MBOGNING TUGMA GUY | C11: =IF(E11="ECHEC",0,IF(E11="",0,100000)) -> 100000 | D11: =IF(E11="ESPECES",0,0) -> 0 | E11: BANQUE | J11: =TONTAVRIL!F11+TONTAVRIL!G11 -> 0 | N11: =IF(O11=0,0,($C$38-O11)) -> 0
A12: AS201639 | B12: =VLOOKUP(A12,[1]LISTADHERENT!A$5:H$60,3,0) -> NANGUEN MARTIN | C12: =IF(E12="ECHEC",0,IF(E12="",0,100000)) -> 100000 | D12: =IF(E12="ESPECES",0,0) -> 0 | E12: BANQUE | J12: =TONTAVRIL!F12+TONTAVRIL!G12 -> 0 | N12: =IF(O12=0,0,($C$38-O12)) -> 0
A13: AS201622 | B13: =VLOOKUP(A13,[1]LISTADHERENT!A$5:H$60,3,0) -> NDJOMO ETIENNE | C13: =IF(E13="ECHEC",0,IF(E13="",0,100000)) -> 100000 | D13: =IF(E13="ESPECES",0,0) -> 0 | E13: BANQUE | F13: 126000 | G13: 1000 | J13: =TONTAVRIL!F13+TONTAVRIL!G13 -> 0 | N13: =IF(O13=0,0,($C$38-O13)) -> 0
A14: AS201624 | B14: =VLOOKUP(A14,[1]LISTADHERENT!A$5:H$60,3,0) -> NGONDIEP CLAUDE | C14: =IF(E14="ECHEC",0,IF(E14="",0,100000)) -> 100000 | D14: =IF(E14="ESPECES",0,0) -> 0 | E14: BANQUE | J14: =TONTAVRIL!F14+TONTAVRIL!G14 -> 0 | N14: =IF(O14=0,0,($C$38-O14)) -> 1370000 | O14: 130000
A15: AS201614 | B15: =VLOOKUP(A15,[1]LISTADHERENT!A$5:H$60,3,0) -> NKEHE DAVID | C15: =IF(E15="ECHEC",0,IF(E15="",0,100000)) -> 100000 | D15: =IF(E15="ESPECES",0,0) -> 0 | E15: ESPECES | F15: 229500 | J15: =TONTAVRIL!F15+TONTAVRIL!G15 -> 229500 | K15: ECHEC | N15: =IF(O15=0,0,($C$38-O15)) -> 0
A16: AS201629 | B16: =VLOOKUP(A16,[1]LISTADHERENT!A$5:H$60,3,0) -> NKEPSEU DIEUDONNE | C16: =IF(E16="ECHEC",0,IF(E16="",0,100000)) -> 100000 | D16: =IF(E16="ESPECES",0,0) -> 0 | E16: BANQUE | J16: =TONTAVRIL!F16+TONTAVRIL!G16 -> 0 | N16: =IF(O16=0,0,($C$38-O16)) -> 0
A17: AS201636 | B17: =VLOOKUP(A17,[1]LISTADHERENT!A$5:H$60,3,0) -> SIMO FONGANG ERIC | C17: =IF(E17="ECHEC",0,IF(E17="",0,100000)) -> 100000 | D17: =IF(E17="ESPECES",0,0) -> 0 | E17: ESPECES | F17: 200000 | G17: 11000 | J17: =TONTAVRIL!F17+TONTAVRIL!G17 -> 0 | N17: =IF(O17=0,0,($C$38-O17)) -> 0
A18: AS201636 | B18: =VLOOKUP(A18,[1]LISTADHERENT!A$5:H$60,3,0) -> SIMO FONGANG ERIC | C18: =IF(E18="ECHEC",0,IF(E18="",0,100000)) -> 100000 | D18: =IF(E18="ESPECES",0,0) -> 0 | E18: ESPECES | J18: =TONTAVRIL!F18+TONTAVRIL!G18 -> 0 | N18: =IF(O18=0,0,($C$38-O18)) -> 0
A19: AS201637 | B19: =VLOOKUP(A19,[1]LISTADHERENT!A$5:H$60,3,0) -> SIME MATHIEU | C19: =IF(E19="ECHEC",0,IF(E19="",0,100000)) -> 100000 | D19: =IF(E19="ESPECES",0,0) -> 0 | E19: BANQUE | J19: =TONTAVRIL!F19+TONTAVRIL!G19 -> 0 | N19: =IF(O19=0,0,($C$38-O19)) -> 0
A20: AS201637 | B20: =VLOOKUP(A20,[1]LISTADHERENT!A$5:H$60,3,0) -> SIME MATHIEU | C20: =IF(E20="ECHEC",0,IF(E20="",0,100000)) -> 100000 | D20: =IF(E20="ESPECES",0,0) -> 0 | E20: BANQUE | J20: =TONTAVRIL!F20+TONTAVRIL!G20 -> 0 | N20: =IF(O20=0,0,($C$38-O20)) -> 0
A21: AS201641 | B21: =VLOOKUP(A21,[1]LISTADHERENT!A$5:H$60,3,0) -> TCHOUAMOU MATHIEU | C21: =IF(E21="ECHEC",0,IF(E21="",0,100000)) -> 100000 | D21: =IF(E21="ESPECES",0,0) -> 0 | E21: BANQUE | J21: =TONTAVRIL!F21+TONTAVRIL!G21 -> 0 | N21: =IF(O21=0,0,($C$38-O21)) -> 0
A22: AS201644 | B22: =VLOOKUP(A22,[1]LISTADHERENT!A$5:H$60,3,0) -> TIEYAM ERNEST | C22: =IF(E22="ECHEC",0,IF(E22="",0,100000)) -> 100000 | D22: =IF(E22="ESPECES",0,0) -> 0 | E22: BANQUE | F22: 100000 | G22: 6000 | J22: =TONTAVRIL!F22+TONTAVRIL!G22+206000 -> 412000 | K22: ESPECES | N22: =IF(O22=0,0,($C$38-O22)) -> 0
A23: AS201647 | B23: =VLOOKUP(A23,[1]LISTADHERENT!A$5:H$60,3,0) -> YOUMBI EMMANUEL | C23: =IF(E23="ECHEC",0,IF(E23="",0,100000)) -> 100000 | D23: =IF(E23="ESPECES",0,0) -> 0 | E23: BANQUE | J23: =TONTAVRIL!F23+TONTAVRIL!G23 -> 0 | N23: =IF(O23=0,0,($C$38-O23)) -> 0
A25: TOTAL | C25: =SUM(C6:C24) -> 1800000 | D25: =SUM(D6:D24) -> 0 | F25: =SUM(F6:F24) -> 855500 | G25: =SUM(G6:G24) -> 28000 | J25: =SUM(J6:J24) -> 641500 | N25: =SUM(N6:N24) -> 1370000 | O25: =SUM(O6:O24) -> 130000
C27: TONTINE | D27: REMBOURSEMENT PETIT LOT | E27: VENTE PETIT LOT | F27: VENTE LOT PRINCIPAL | G27: SOLDE EN CAISSE | K27: TONTINE + REMB + INTERET VENTE | L27: =C25+D32+O25 -> 2342000
K28: TONTINE | L28: =IF(L27>=3000000,1500000*2,1500000) -> 1500000
B29: ESPECES | C29: =SUMIFS(C6:C23,E6:E23,"ESPECES") -> 300000 | D29: =SUMIFS(J6:J23,K6:K23,"ESPECES") -> 412000 | E29: =SUMIFS(F6:F23,H6:H23,"ESPECES") -> 0 | F29: =SUMIFS(N6:N23,L6:L23,"ESPECES") -> 0 | G29: =C29+D29-E29-F29 -> 712000 | K29: PETIT LOT | L29: =L27-L28 -> 842000
B30: BANQUE | C30: =SUMIFS(C6:C23,E6:E23,"BANQUE") -> 1500000 | D30: =SUMIFS(J6:J23,K6:K23,"BANQUE") -> 0 | E30: =SUMIFS(F6:F23,H6:H23,"BANQUE") -> 0 | F30: =SUMIFS(N6:N23,L6:L23,"BANQUE") -> 0 | G30: =C30+D30-E30-F30 -> 1500000 | K30: RESTE | L30: =L29-F25 -> -13500
B32: TOTAL | C32: =C29+C30 -> 1800000 | D32: =D29+D30 -> 412000 | E32: =E29+E30 -> 0 | F32: =F29+F30 -> 0 | G32: =G29+G30 -> 2212000 | K32: ECHEC TONTINE | L32: 0
K33: ECHEC REMBOURSEMENT | L33: 229500
B35: INTERET LOT PRINCIPAL | C35: =O25 -> 130000
B36: INTERET PETIT LOT | C36: =+G25 -> 28000
B38: MONTANT TONTINE | C38: 1500000
B39: MONTANT PETIT LOT A VENDRE | C39: =L29 -> 842000

Sheet TONTJUIN
A1: ASSOCIATION | B1: ASELBY
A2: ANNEE | B2: 2019/2020
A3: TONTINE | B3: 100000
C4: 44003
A5: MATRICULE | B5: NOM ET PRENOM | C5: MONTANT TONTINE | D5: PENALITE | E5: MODE VERSEMENT TONTINE | F5: VENTE PETIT LOT | G5: INTERET PETIT LOT | H5: MODE VERSEMENT VENTE PETIT LOT | I5: NUMERO CHEQUE | J5: REMBOURSEMENT | K5: MODE VERSEMENT REMBOURSEMENT | L5: MODE VERSEMENT TONTINE PRINCIPAL | M5: NUMERO CHEQUE | N5: MONTANT TONTINE LOT PRINCIPAL | O5: INTERET LOT PRINCIPAL | P5: DATE VENTE
A6: AS201608 | B6: =VLOOKUP(A6,[1]LISTADHERENT!A$5:H$60,3,0) -> DJUOMBESSY ANTOINE | C6: =IF(E6="ECHEC",0,IF(E6="",0,100000)) -> 100000 | D6: =IF(E6="ESPECES",0,0) -> 0 | E6: BANQUE | J6: =TONTMAI!F6+TONTMAI!G6 -> 0 | N6: =IF(O6=0,0,($C$38-O6)) -> 0
A7: AS201613 | B7: =VLOOKUP(A7,[1]LISTADHERENT!A$5:H$60,3,0) -> HOTCHO BENJAMIN | C7: =IF(E7="ECHEC",0,IF(E7="",0,100000)) -> 100000 | D7: =IF(E7="ESPECES",0,0) -> 0 | E7: BANQUE | J7: =TONTMAI!F7+TONTMAI!G7 -> 0 | N7: =IF(O7=0,0,($C$38-O7)) -> 0
A8: AS201619 | B8: =VLOOKUP(A8,[1]LISTADHERENT!A$5:H$60,3,0) -> KOUATCHO MESSACK | C8: =IF(E8="ECHEC",0,IF(E8="",0,100000)) -> 100000 | D8: =IF(E8="ESPECES",0,0) -> 0 | E8: BANQUE | F8: 200000 | G8: 2000 | J8: =TONTMAI!F8+TONTMAI!G8 -> 210000 | K8: BANQUE | N8: =IF(O8=0,0,($C$38-O8)) -> 0
A9: AS201617 | B9: =VLOOKUP(A9,[1]LISTADHERENT!A$5:H$60,3,0) -> KOUAMOU MOISE | C9: =IF(E9="ECHEC",0,IF(E9="",0,100000)) -> 100000 | D9: =IF(E9="ESPECES",0,0) -> 0 | E9: BANQUE | J9: =TONTMAI!F9+TONTMAI!G9 -> 0 | N9: =IF(O9=0,0,($C$38-O9)) -> 0
A10: AS201649 | B10: =VLOOKUP(A10,[1]LISTADHERENT!A$5:H$60,3,0) -> MBOGNING TUGMA GUY | C10: =IF(E10="ECHEC",0,IF(E10="",0,100000)) -> 100000 | D10: =IF(E10="ESPECES",0,0) -> 0 | E10: BANQUE | F10: 100000 | G10: 1000 | J10: =TONTMAI!F10+TONTMAI!G10 -> 0 | N10: =IF(O10=0,0,($C$38-O10)) -> 0
A11: AS201649 | B11: =VLOOKUP(A11,[1]LISTADHERENT!A$5:H$60,3,0) -> MBOGNING TUGMA GUY | C11: =IF(E11="ECHEC",0,IF(E11="",0,100000)) -> 100000 | D11: =IF(E11="ESPECES",0,0) -> 0 | E11: BANQUE | J11: =TONTMAI!F11+TONTMAI!G11 -> 0 | N11: =IF(O11=0,0,($C$38-O11)) -> 0
A12: AS201639 | B12: =VLOOKUP(A12,[1]LISTADHERENT!A$5:H$60,3,0) -> NANGUEN MARTIN | C12: =IF(E12="ECHEC",0,IF(E12="",0,100000)) -> 100000 | D12: =IF(E12="ESPECES",0,0) -> 0 | E12: BANQUE | J12: =TONTMAI!F12+TONTMAI!G12 -> 0 | N12: =IF(O12=0,0,($C$38-O12)) -> 0
A13: AS201622 | B13: =VLOOKUP(A13,[1]LISTADHERENT!A$5:H$60,3,0) -> NDJOMO ETIENNE | C13: =IF(E13="ECHEC",0,IF(E13="",0,100000)) -> 100000 | D13: =IF(E13="ESPECES",0,0) -> 0 | E13: BANQUE | F13: 200000 | G13: 2000 | J13: =TONTMAI!F13+TONTMAI!G13 -> 127000 | K13: ESPECES | N13: =IF(O13=0,0,($C$38-O13)) -> 0
A14: AS201624 | B14: =VLOOKUP(A14,[1]LISTADHERENT!A$5:H$60,3,0) -> NGONDIEP CLAUDE | C14: =IF(E14="ECHEC",0,IF(E14="",0,100000)) -> 100000 | D14: =IF(E14="ESPECES",0,0) -> 0 | E14: BANQUE | J14: =TONTMAI!F14+TONTMAI!G14 -> 0 | N14: =IF(O14=0,0,($C$38-O14)) -> 0
A15: AS201614 | B15: =VLOOKUP(A15,[1]LISTADHERENT!A$5:H$60,3,0) -> NKEHE DAVID | C15: =IF(E15="ECHEC",0,IF(E15="",0,100000)) -> 0 | D15: =IF(E15="ESPECES",0,0) -> 0 | E15: ECHEC | F15: 229500 | J15: =TONTMAI!F15+TONTMAI!G15 -> 229500 | K15: ECHEC | N15: =IF(O15=0,0,($C$38-O15)) -> 0
A16: AS201629 | B16: =VLOOKUP(A16,[1]LISTADHERENT!A$5:H$60,3,0) -> NKEPSEU DIEUDONNE | C16: =IF(E16="ECHEC",0,IF(E16="",0,100000)) -> 100000 | D16: =IF(E16="ESPECES",0,0) -> 0 | E16: BANQUE | J16: =TONTMAI!F16+TONTMAI!G16 -> 0 | N16: =IF(O16=0,0,($C$38-O16)) -> 0
A17: AS201636 | B17: =VLOOKUP(A17,[1]LISTADHERENT!A$5:H$60,3,0) -> SIMO FONGANG ERIC | C17: =IF(E17="ECHEC",0,IF(E17="",0,100000)) -> 100000 | D17: =IF(E17="ESPECES",0,0) -> 0 | E17: ESPECES | F17: 233000 | G17: 22000 | J17: =TONTMAI!F17+TONTMAI!G17+22000 -> 233000 | K17: ECHEC | N17: =IF(O17=0,0,($C$38-O17)) -> 0
A18: AS201636 | B18: =VLOOKUP(A18,[1]LISTADHERENT!A$5:H$60,3,0) -> SIMO FONGANG ERIC | C18: =IF(E18="ECHEC",0,IF(E18="",0,100000)) -> 100000 | D18: =IF(E18="ESPECES",0,0) -> 0 | E18: ESPECES | J18: =TONTMAI!F18+TONTMAI!G18 -> 0 | N18: =IF(O18=0,0,($C$38-O18)) -> 0
A19: AS201637 | B19: =VLOOKUP(A19,[1]LISTADHERENT!A$5:H$60,3,0) -> SIME MATHIEU | C19: =IF(E19="ECHEC",0,IF(E19="",0,100000)) -> 100000 | D19: =IF(E19="ESPECES",0,0) -> 0 | E19: BANQUE | J19: =TONTMAI!F19+TONTMAI!G19 -> 0 | N19: =IF(O19=0,0,($C$38-O19)) -> 0
A20: AS201637 | B20: =VLOOKUP(A20,[1]LISTADHERENT!A$5:H$60,3,0) -> SIME MATHIEU | C20: =IF(E20="ECHEC",0,IF(E20="",0,100000)) -> 100000 | D20: =IF(E20="ESPECES",0,0) -> 0 | E20: BANQUE | J20: =TONTMAI!F20+TONTMAI!G20 -> 0 | N20: =IF(O20=0,0,($C$38-O20)) -> 0
A21: AS201641 | B21: =VLOOKUP(A21,[1]LISTADHERENT!A$5:H$60,3,0) -> TCHOUAMOU MATHIEU | C21: =IF(E21="ECHEC",0,IF(E21="",0,100000)) -> 100000 | D21: =IF(E21="ESPECES",0,0) -> 0 | E21: BANQUE | F21: 238000 | G21: 2000 | J21: =TONTMAI!F21+TONTMAI!G21 -> 0 | N21: =IF(O21=0,0,($C$38-O21)) -> 0
A22: AS201644 | B22: =VLOOKUP(A22,[1]LISTADHERENT!A$5:H$60,3,0) -> TIEYAM ERNEST | C22: =IF(E22="ECHEC",0,IF(E22="",0,100000)) -> 100000 | D22: =IF(E22="ESPECES",0,0) -> 0 | E22: ESPECES | F22: 100000 | G22: 1000 | J22: =TONTMAI!F22+TONTMAI!G22 -> 106000 | K22: BANQUE | N22: =IF(O22=0,0,($C$38-O22)) -> 1305000 | O22: 195000
A23: AS201647 | B23: =VLOOKUP(A23,[1]LISTADHERENT!A$5:H$60,3,0) -> YOUMBI EMMANUEL | C23: =IF(E23="ECHEC",0,IF(E23="",0,100000)) -> 100000 | D23: =IF(E23="ESPECES",0,0) -> 0 | E23: BANQUE | J23: =TONTMAI!F23+TONTMAI!G23 -> 0 | N23: =IF(O23=0,0,($C$38-O23)) -> 0
A25: TOTAL | C25: =SUM(C6:C24) -> 1700000 | D25: =SUM(D6:D24) -> 0 | F25: =SUM(F6:F24) -> 1300500 | G25: =SUM(G6:G24) -> 30000 | J25: =SUM(J6:J24) -> 905500 | N25: =SUM(N6:N24) -> 1305000 | O25: =SUM(O6:O24) -> 195000
C27: TONTINE | D27: REMBOURSEMENT PETIT LOT | E27: VENTE PETIT LOT | F27: VENTE LOT PRINCIPAL | G27: SOLDE EN CAISSE | K27: TONTINE + REMB + INTERET VENTE | L27: =C25+D32+O25 -> 2338000
K28: TONTINE | L28: =IF(L27>=3000000,1500000*2,1500000) -> 1500000
B29: ESPECES | C29: =SUMIFS(C6:C23,E6:E23,"ESPECES") -> 300000 | D29: =SUMIFS(J6:J23,K6:K23,"ESPECES") -> 127000 | E29: =SUMIFS(F6:F23,H6:H23,"ESPECES") -> 0 | F29: =SUMIFS(N6:N23,L6:L23,"ESPECES") -> 0 | G29: =C29+D29-E29-F29 -> 427000 | K29: PETIT LOT | L29: =L27-L28 -> 838000
B30: BANQUE | C30: =SUMIFS(C6:C23,E6:E23,"BANQUE") -> 1400000 | D30: =SUMIFS(J6:J23,K6:K23,"BANQUE") -> 316000 | E30: =SUMIFS(F6:F23,H6:H23,"BANQUE") -> 0 | F30: =SUMIFS(N6:N23,L6:L23,"BANQUE") -> 0 | G30: =C30+D30-E30-F30 -> 1716000 | K30: RESTE | L30: =L29-F25 -> -462500
B32: TOTAL | C32: =C29+C30 -> 1700000 | D32: =D29+D30 -> 443000 | E32: =E29+E30 -> 0 | F32: =F29+F30 -> 0 | G32: =G29+G30 -> 2143000 | K32: ECHEC TONTINE | L32: 100000 | M32: KEHEP DAVID
K33: ECHEC REMBOURSEMENT | L33: =229500+233000 -> 462500 | M33: KEHEP DAVID/SIMO ERIC
B35: INTERET LOT PRINCIPAL | C35: =O25 -> 195000
B36: INTERET PETIT LOT | C36: =+G25 -> 30000
B38: MONTANT TONTINE | C38: 1500000
B39: MONTANT PETIT LOT A VENDRE | C39: =L29 -> 838000

Sheet TONTJUIL
A1: ASSOCIATION | B1: ASELBY
A2: ANNEE | B2: 2019/2020
A3: TONTINE | B3: 100000
C4: 44031
A5: MATRICULE | B5: NOM ET PRENOM | C5: MONTANT TONTINE | D5: PENALITE | E5: MODE VERSEMENT TONTINE | F5: VENTE PETIT LOT | G5: INTERET PETIT LOT | H5: MODE VERSEMENT VENTE PETIT LOT | I5: NUMERO CHEQUE | J5: REMBOURSEMENT | K5: MODE VERSEMENT REMBOURSEMENT | L5: MODE VERSEMENT TONTINE PRINCIPAL | M5: NUMERO CHEQUE | N5: MONTANT TONTINE LOT PRINCIPAL | O5: INTERET LOT PRINCIPAL | P5: DATE VENTE
A6: AS201608 | B6: =VLOOKUP(A6,[1]LISTADHERENT!A$5:H$60,3,0) -> DJUOMBESSY ANTOINE | C6: =IF(E6="ECHEC",0,IF(E6="",0,100000)) -> 100000 | D6: =IF(E6="ESPECES",0,0) -> 0 | E6: BANQUE | J6: =TONTJUIN!F6+TONTJUIN!G6 -> 0 | N6: =IF(O6=0,0,($C$38-O6)) -> 0
A7: AS201613 | B7: =VLOOKUP(A7,[1]LISTADHERENT!A$5:H$60,3,0) -> HOTCHO BENJAMIN | C7: =IF(E7="ECHEC",0,IF(E7="",0,100000)) -> 100000 | D7: =IF(E7="ESPECES",0,0) -> 0 | E7: BANQUE | J7: =TONTJUIN!F7+TONTJUIN!G7 -> 0 | N7: =IF(O7=0,0,($C$38-O7)) -> 0
A8: AS201619 | B8: =VLOOKUP(A8,[1]LISTADHERENT!A$5:H$60,3,0) -> KOUATCHO MESSACK | C8: =IF(E8="ECHEC",0,IF(E8="",0,100000)) -> 100000 | D8: =IF(E8="ESPECES",0,0) -> 0 | E8: BANQUE | F8: 69000 | G8: 1500 | J8: =TONTJUIN!F8+TONTJUIN!G8 -> 202000 | K8: BANQUE | N8: =IF(O8=0,0,($C$38-O8)) -> 0
A9: AS201617 | B9: =VLOOKUP(A9,[1]LISTADHERENT!A$5:H$60,3,0) -> KOUAMOU MOISE | C9: =IF(E9="ECHEC",0,IF(E9="",0,100000)) -> 100000 | D9: =IF(E9="ESPECES",0,0) -> 0 | E9: BANQUE | J9: =TONTJUIN!F9+TONTJUIN!G9 -> 0 | N9: =IF(O9=0,0,($C$38-O9)) -> 0
A10: AS201649 | B10: =VLOOKUP(A10,[1]LISTADHERENT!A$5:H$60,3,0) -> MBOGNING TUGMA GUY | C10: =IF(E10="ECHEC",0,IF(E10="",0,100000)) -> 100000 | D10: =IF(E10="ESPECES",0,0) -> 0 | E10: BANQUE | J10: =TONTJUIN!F10+TONTJUIN!G10 -> 101000 | K10: ESPECES | N10: =IF(O10=0,0,($C$38-O10)) -> 0
A11: AS201649 | B11: =VLOOKUP(A11,[1]LISTADHERENT!A$5:H$60,3,0) -> MBOGNING TUGMA GUY | C11: =IF(E11="ECHEC",0,IF(E11="",0,100000)) -> 100000 | D11: =IF(E11="ESPECES",0,0) -> 0 | E11: BANQUE | J11: =TONTJUIN!F11+TONTJUIN!G11 -> 0 | N11: =IF(O11=0,0,($C$38-O11)) -> 1255000 | O11: 245000
A12: AS201639 | B12: =VLOOKUP(A12,[1]LISTADHERENT!A$5:H$60,3,0) -> NANGUEN MARTIN | C12: =IF(E12="ECHEC",0,IF(E12="",0,100000)) -> 100000 | D12: =IF(E12="ESPECES",0,0) -> 0 | E12: BANQUE | J12: =TONTJUIN!F12+TONTJUIN!G12 -> 0 | N12: =IF(O12=0,0,($C$38-O12)) -> 0
A13: AS201622 | B13: =VLOOKUP(A13,[1]LISTADHERENT!A$5:H$60,3,0) -> NDJOMO ETIENNE | C13: =IF(E13="ECHEC",0,IF(E13="",0,100000)) -> 100000 | D13: =IF(E13="ESPECES",0,0) -> 0 | E13: BANQUE | J13: =TONTJUIN!F13+TONTJUIN!G13 -> 202000 | K13: BANQUE | N13: =IF(O13=0,0,($C$38-O13)) -> 0
A14: AS201624 | B14: =VLOOKUP(A14,[1]LISTADHERENT!A$5:H$60,3,0) -> NGONDIEP CLAUDE | C14: =IF(E14="ECHEC",0,IF(E14="",0,100000)) -> 100000 | D14: =IF(E14="ESPECES",0,0) -> 0 | E14: BANQUE | J14: =TONTJUIN!F14+TONTJUIN!G14 -> 0 | N14: =IF(O14=0,0,($C$38-O14)) -> 0
A15: AS201614 | B15: =VLOOKUP(A15,[1]LISTADHERENT!A$5:H$60,3,0) -> NKEHE DAVID | C15: =IF(E15="ECHEC",0,IF(E15="",0,100000)) -> 0 | D15: =IF(E15="ESPECES",0,0) -> 0 | E15: ECHEC | F15: 229500 | J15: =TONTJUIN!F15+TONTJUIN!G15 -> 229500 | K15: ECHEC | N15: =IF(O15=0,0,($C$38-O15)) -> 0
A16: AS201629 | B16: =VLOOKUP(A16,[1]LISTADHERENT!A$5:H$60,3,0) -> NKEPSEU DIEUDONNE | C16: =IF(E16="ECHEC",0,IF(E16="",0,100000)) -> 100000 | D16: =IF(E16="ESPECES",0,0) -> 0 | E16: BANQUE | J16: =TONTJUIN!F16+TONTJUIN!G16 -> 0 | N16: =IF(O16=0,0,($C$38-O16)) -> 0
A17: AS201636 | B17: =VLOOKUP(A17,[1]LISTADHERENT!A$5:H$60,3,0) -> SIMO FONGANG ERIC | C17: =IF(E17="ECHEC",0,IF(E17="",0,100000)) -> 100000 | D17: =IF(E17="ESPECES",0,0) -> 0 | E17: ESPECES | J17: =TONTJUIN!F17+TONTJUIN!G17+233000 -> 488000 | K17: ESPECES | N17: =IF(O17=0,0,($C$38-O17)) -> 0
A18: AS201636 | B18: =VLOOKUP(A18,[1]LISTADHERENT!A$5:H$60,3,0) -> SIMO FONGANG ERIC | C18: =IF(E18="ECHEC",0,IF(E18="",0,100000)) -> 100000 | D18: =IF(E18="ESPECES",0,0) -> 0 | E18: ESPECES | J18: =TONTJUIN!F18+TONTJUIN!G18 -> 0 | N18: =IF(O18=0,0,($C$38-O18)) -> 1254000 | O18: 246000
A19: AS201637 | B19: =VLOOKUP(A19,[1]LISTADHERENT!A$5:H$60,3,0) -> SIME MATHIEU | C19: =IF(E19="ECHEC",0,IF(E19="",0,100000)) -> 100000 | D19: =IF(E19="ESPECES",0,0) -> 0 | E19: BANQUE | J19: =TONTJUIN!F19+TONTJUIN!G19 -> 0 | N19: =IF(O19=0,0,($C$38-O19)) -> 0
A20: AS201637 | B20: =VLOOKUP(A20,[1]LISTADHERENT!A$5:H$60,3,0) -> SIME MATHIEU | C20: =IF(E20="ECHEC",0,IF(E20="",0,100000)) -> 100000 | D20: =IF(E20="ESPECES",0,0) -> 0 | E20: BANQUE | J20: =TONTJUIN!F20+TONTJUIN!G20 -> 0 | N20: =IF(O20=0,0,($C$38-O20)) -> 0
A21: AS201641 | B21: =VLOOKUP(A21,[1]LISTADHERENT!A$5:H$60,3,0) -> TCHOUAMOU MATHIEU | C21: =IF(E21="ECHEC",0,IF(E21="",0,100000)) -> 100000 | D21: =IF(E21="ESPECES",0,0) -> 0 | E21: BANQUE | J21: =TONTJUIN!F21+TONTJUIN!G21 -> 240000 | K21: BANQUE | N21: =IF(O21=0,0,($C$38-O21)) -> 0
A22: AS201644 | B22: =VLOOKUP(A22,[1]LISTADHERENT!A$5:H$60,3,0) -> TIEYAM ERNEST | C22: =IF(E22="ECHEC",0,IF(E22="",0,100000)) -> 0 | D22: =IF(E22="ESPECES",0,0) -> 0 | E22: ECHEC | F22: 101000 | G22: 2000 | J22: =TONTJUIN!F22+TONTJUIN!G22 -> 101000 | K22: ECHEC | N22: =IF(O22=0,0,($C$38-O22)) -> 0
A23: AS201647 | B23: =VLOOKUP(A23,[1]LISTADHERENT!A$5:H$60,3,0) -> YOUMBI EMMANUEL | C23: =IF(E23="ECHEC",0,IF(E23="",0,100000)) -> 100000 | D23: =IF(E23="ESPECES",0,0) -> 0 | E23: BANQUE | J23: =TONTJUIN!F23+TONTJUIN!G23 -> 0 | N23: =IF(O23=0,0,($C$38-O23)) -> 0
A25: TOTAL | C25: =SUM(C6:C24) -> 1600000 | D25: =SUM(D6:D24) -> 0 | F25: =SUM(F6:F24) -> 399500 | G25: =SUM(G6:G24) -> 3500 | J25: =SUM(J6:J24) -> 1563500 | N25: =SUM(N6:N24) -> 2509000 | O25: =SUM(O6:O24) -> 491000
C27: TONTINE | D27: REMBOURSEMENT PETIT LOT | E27: VENTE PETIT LOT | F27: VENTE LOT PRINCIPAL | G27: SOLDE EN CAISSE | K27: TONTINE + REMB + INTERET VENTE | L27: =C25+D32+O25 -> 3324000
K28: TONTINE | L28: =IF(L27>=3000000,1500000*2,1500000) -> 3000000
B29: ESPECES | C29: =SUMIFS(C6:C23,E6:E23,"ESPECES") -> 200000 | D29: =SUMIFS(J6:J23,K6:K23,"ESPECES") -> 589000 | E29: =SUMIFS(F6:F23,H6:H23,"ESPECES") -> 0 | F29: =SUMIFS(N6:N23,L6:L23,"ESPECES") -> 0 | G29: =C29+D29-E29-F29 -> 789000 | K29: PETIT LOT | L29: =L27-L28 -> 324000
B30: BANQUE | C30: =SUMIFS(C6:C23,E6:E23,"BANQUE") -> 1400000 | D30: =SUMIFS(J6:J23,K6:K23,"BANQUE") -> 644000 | E30: =SUMIFS(F6:F23,H6:H23,"BANQUE") -> 0 | F30: =SUMIFS(N6:N23,L6:L23,"BANQUE") -> 0 | G30: =C30+D30-E30-F30 -> 2044000 | K30: RESTE | L30: =L29-F25 -> -75500
B32: TOTAL | C32: =C29+C30 -> 1600000 | D32: =D29+D30 -> 1233000 | E32: =E29+E30 -> 0 | F32: =F29+F30 -> 0 | G32: =G29+G30 -> 2833000
K33: ECHEC TONTINE | L33: 200000 | M33: NKEHEP/TYAM
K34: ECHEC REMBOURSEMENT | L34: =229500+101000 -> 330500
B35: INTERET LOT PRINCIPAL | C35: =O25 -> 491000
B36: INTERET PETIT LOT | C36: =+G25 -> 3500
B38: MONTANT TONTINE | C38: 1500000
B39: MONTANT PETIT LOT A VENDRE | C39: =L29 -> 324000

Sheet TONTAOUT
A1: ASSOCIATION | B1: ASELBY
A2: ANNEE | B2: 2019/2020
A3: TONTINE | B3: 100000
C4: 16/O8/2020
A5: MATRICULE | B5: NOM ET PRENOM | C5: MONTANT TONTINE | D5: PENALITE | E5: MODE VERSEMENT TONTINE | F5: VENTE PETIT LOT | G5: INTERET PETIT LOT | H5: MODE VERSEMENT VENTE PETIT LOT | I5: NUMERO CHEQUE | J5: REMBOURSEMENT | K5: MODE VERSEMENT REMBOURSEMENT | L5: MODE VERSEMENT TONTINE PRINCIPAL | M5: NUMERO CHEQUE | N5: MONTANT TONTINE LOT PRINCIPAL | O5: INTERET LOT PRINCIPAL | P5: DATE VENTE
A6: AS201608 | B6: =VLOOKUP(A6,[1]LISTADHERENT!A$5:H$60,3,0) -> DJUOMBESSY ANTOINE | C6: =IF(E6="ECHEC",0,IF(E6="",0,100000)) -> 100000 | D6: =IF(E6="ESPECES",0,0) -> 0 | E6: BANQUE | J6: =TONTJUIL!F6+TONTJUIL!G6 -> 0 | N6: =IF(O6=0,0,($C$38-O6)) -> 0
A7: AS201613 | B7: =VLOOKUP(A7,[1]LISTADHERENT!A$5:H$60,3,0) -> HOTCHO BENJAMIN | C7: =IF(E7="ECHEC",0,IF(E7="",0,100000)) -> 100000 | D7: =IF(E7="ESPECES",0,0) -> 0 | E7: BANQUE | J7: =TONTJUIL!F7+TONTJUIL!G7 -> 0 | N7: =IF(O7=0,0,($C$38-O7)) -> 0
A8: AS201619 | B8: =VLOOKUP(A8,[1]LISTADHERENT!A$5:H$60,3,0) -> KOUATCHO MESSACK | C8: =IF(E8="ECHEC",0,IF(E8="",0,100000)) -> 100000 | D8: =IF(E8="ESPECES",0,0) -> 0 | E8: BANQUE | F8: 229000 | G8: 7000 | J8: =TONTJUIL!F8+TONTJUIL!G8 -> 70500 | K8: BANQUE | N8: =IF(O8=0,0,($C$38-O8)) -> 0
A9: AS201617 | B9: =VLOOKUP(A9,[1]LISTADHERENT!A$5:H$60,3,0) -> KOUAMOU MOISE | C9: =IF(E9="ECHEC",0,IF(E9="",0,100000)) -> 100000 | D9: =IF(E9="ESPECES",0,0) -> 0 | E9: ESPECES | J9: =TONTJUIL!F9+TONTJUIL!G9 -> 0 | N9: =IF(O9=0,0,($C$38-O9)) -> 0
A10: AS201649 | B10: =VLOOKUP(A10,[1]LISTADHERENT!A$5:H$60,3,0) -> MBOGNING TUGMA GUY | C10: =IF(E10="ECHEC",0,IF(E10="",0,100000)) -> 100000 | D10: =IF(E10="ESPECES",0,0) -> 0 | E10: BANQUE | J10: =TONTJUIL!F10+TONTJUIL!G10 -> 0 | N10: =IF(O10=0,0,($C$38-O10)) -> 0
A11: AS201649 | B11: =VLOOKUP(A11,[1]LISTADHERENT!A$5:H$60,3,0) -> MBOGNING TUGMA GUY | C11: =IF(E11="ECHEC",0,IF(E11="",0,100000)) -> 100000 | D11: =IF(E11="ESPECES",0,0) -> 0 | E11: BANQUE | J11: =TONTJUIL!F11+TONTJUIL!G11 -> 0 | N11: =IF(O11=0,0,($C$38-O11)) -> 0
A12: AS201639 | B12: =VLOOKUP(A12,[1]LISTADHERENT!A$5:H$60,3,0) -> NANGUEN MARTIN | C12: =IF(E12="ECHEC",0,IF(E12="",0,100000)) -> 100000 | D12: =IF(E12="ESPECES",0,0) -> 0 | E12: BANQUE | J12: =TONTJUIL!F12+TONTJUIL!G12 -> 0 | N12: =IF(O12=0,0,($C$38-O12)) -> 0
A13: AS201622 | B13: =VLOOKUP(A13,[1]LISTADHERENT!A$5:H$60,3,0) -> NDJOMO ETIENNE | C13: =IF(E13="ECHEC",0,IF(E13="",0,100000)) -> 100000 | D13: =IF(E13="ESPECES",0,0) -> 0 | E13: BANQUE | J13: =TONTJUIL!F13+TONTJUIL!G13 -> 0 | N13: =IF(O13=0,0,($C$38-O13)) -> 0
A14: AS201624 | B14: =VLOOKUP(A14,[1]LISTADHERENT!A$5:H$60,3,0) -> NGONDIEP CLAUDE | C14: =IF(E14="ECHEC",0,IF(E14="",0,100000)) -> 100000 | D14: =IF(E14="ESPECES",0,0) -> 0 | E14: ESPECES | J14: =TONTJUIL!F14+TONTJUIL!G14 -> 0 | N14: =IF(O14=0,0,($C$38-O14)) -> 0
A15: AS201614 | B15: =VLOOKUP(A15,[1]LISTADHERENT!A$5:H$60,3,0) -> NKEHE DAVID | C15: =IF(E15="ECHEC",0,IF(E15="",0,100000)) -> 0 | D15: =IF(E15="ESPECES",0,0) -> 0 | E15: ECHEC | F15: 229500 | J15: =TONTJUIL!F15+TONTJUIL!G15 -> 229500 | K15: ECHEC | N15: =IF(O15=0,0,($C$38-O15)) -> 0
A16: AS201629 | B16: =VLOOKUP(A16,[1]LISTADHERENT!A$5:H$60,3,0) -> NKEPSEU DIEUDONNE | C16: =IF(E16="ECHEC",0,IF(E16="",0,100000)) -> 100000 | D16: =IF(E16="ESPECES",0,0) -> 0 | E16: BANQUE | J16: =TONTJUIL!F16+TONTJUIL!G16 -> 0 | N16: =IF(O16=0,0,($C$38-O16)) -> 0
A17: AS201636 | B17: =VLOOKUP(A17,[1]LISTADHERENT!A$5:H$60,3,0) -> SIMO FONGANG ERIC | C17: =IF(E17="ECHEC",0,IF(E17="",0,100000)) -> 100000 | D17: =IF(E17="ESPECES",0,0) -> 0 | E17: ESPECES | F17: 200000 | G17: 12000 | J17: =TONTJUIL!F17+TONTJUIL!G17 -> 0 | N17: =IF(O17=0,0,($C$38-O17)) -> 0
A18: AS201636 | B18: =VLOOKUP(A18,[1]LISTADHERENT!A$5:H$60,3,0) -> SIMO FONGANG ERIC | C18: =IF(E18="ECHEC",0,IF(E18="",0,100000)) -> 100000 | D18: =IF(E18="ESPECES",0,0) -> 0 | E18: ESPECES | J18: =TONTJUIL!F18+TONTJUIL!G18 -> 0 | N18: =IF(O18=0,0,($C$38-O18)) -> 0
A19: AS201637 | B19: =VLOOKUP(A19,[1]LISTADHERENT!A$5:H$60,3,0) -> SIME MATHIEU | C19: =IF(E19="ECHEC",0,IF(E19="",0,100000)) -> 100000 | D19: =IF(E19="ESPECES",0,0) -> 0 | E19: ESPECES | J19: =TONTJUIL!F19+TONTJUIL!G19 -> 0 | N19: =IF(O19=0,0,($C$38-O19)) -> 1340000 | O19: 160000
A20: AS201637 | B20: =VLOOKUP(A20,[1]LISTADHERENT!A$5:H$60,3,0) -> SIME MATHIEU | C20: =IF(E20="ECHEC",0,IF(E20="",0,100000)) -> 100000 | D20: =IF(E20="ESPECES",0,0) -> 0 | E20: ESPECES | J20: =TONTJUIL!F20+TONTJUIL!G20 -> 0 | N20: =IF(O20=0,0,($C$38-O20)) -> 0
A21: AS201641 | B21: =VLOOKUP(A21,[1]LISTADHERENT!A$5:H$60,3,0) -> TCHOUAMOU MATHIEU | C21: =IF(E21="ECHEC",0,IF(E21="",0,100000)) -> 100000 | D21: =IF(E21="ESPECES",0,0) -> 0 | E21: BANQUE | J21: =TONTJUIL!F21+TONTJUIL!G21 -> 0 | N21: =IF(O21=0,0,($C$38-O21)) -> 0
A22: AS201644 | B22: =VLOOKUP(A22,[1]LISTADHERENT!A$5:H$60,3,0) -> TIEYAM ERNEST | C22: =IF(E22="ECHEC",0,IF(E22="",0,100000)) -> 100000 | D22: =IF(E22="ESPECES",0,0) -> 0 | E22: ESPECES | F22: 103000 | G22: 4000 | J22: =TONTJUIL!F22+TONTJUIL!G22 -> 103000 | K22: ECHEC | N22: =IF(O22=0,0,($C$38-O22)) -> 0
A23: AS201647 | B23: =VLOOKUP(A23,[1]LISTADHERENT!A$5:H$60,3,0) -> YOUMBI EMMANUEL | C23: =IF(E23="ECHEC",0,IF(E23="",0,100000)) -> 100000 | D23: =IF(E23="ESPECES",0,0) -> 0 | E23: BANQUE | J23: =TONTJUIL!F23+TONTJUIL!G23 -> 0 | N23: =IF(O23=0,0,($C$38-O23)) -> 0
A25: TOTAL | C25: =SUM(C6:C24) -> 1700000 | D25: =SUM(D6:D24) -> 0 | F25: =SUM(F6:F24) -> 761500 | G25: =SUM(G6:G24) -> 23000 | J25: =SUM(J6:J24) -> 403000 | N25: =SUM(N6:N24) -> 1340000 | O25: =SUM(O6:O24) -> 160000
C27: TONTINE | D27: REMBOURSEMENT PETIT LOT | E27: VENTE PETIT LOT | F27: VENTE LOT PRINCIPAL | G27: SOLDE EN CAISSE | K27: TONTINE + REMB + INTERET VENTE | L27: =C25+D32+O25 -> 1930500
K28: TONTINE | L28: =IF(L27>=3000000,1500000*2,1500000) -> 1500000
B29: ESPECES | C29: =SUMIFS(C6:C23,E6:E23,"ESPECES") -> 700000 | D29: =SUMIFS(J6:J23,K6:K23,"ESPECES") -> 0 | E29: =SUMIFS(F6:F23,H6:H23,"ESPECES") -> 0 | F29: =SUMIFS(N6:N23,L6:L23,"ESPECES") -> 0 | G29: =C29+D29-E29-F29 -> 700000 | K29: PETIT LOT | L29: =L27-L28 -> 430500
B30: BANQUE | C30: =SUMIFS(C6:C23,E6:E23,"BANQUE") -> 1000000 | D30: =SUMIFS(J6:J23,K6:K23,"BANQUE") -> 70500 | E30: =SUMIFS(F6:F23,H6:H23,"BANQUE") -> 0 | F30: =SUMIFS(N6:N23,L6:L23,"BANQUE") -> 0 | G30: =C30+D30-E30-F30 -> 1070500 | K30: RESTE | L30: =L29-F25 -> -331000
B32: TOTAL | C32: =C29+C30 -> 1700000 | D32: =D29+D30 -> 70500 | E32: =E29+E30 -> 0 | F32: =F29+F30 -> 0 | G32: =G29+G30 -> 1770500 | K32: ECHEC TONTINE | L32: 100000 | M32: KEHEP DAVID
K33: ECHEC REMBOURSEMENT | L33: =229500+103000 -> 332500 | M33: KEHEP DAVID/TYAM
B35: INTERET LOT PRINCIPAL | C35: =O25 -> 160000
B36: INTERET PETIT LOT | C36: =+G25 -> 23000
B38: MONTANT TONTINE | C38: 1500000
B39: MONTANT PETIT LOT A VENDRE | C39: =L29 -> 430500

Sheet TONTSEPT
A1: ASSOCIATION | B1: ASELBY
A2: ANNEE | B2: 2019/2020
A3: TONTINE | B3: 100000
C4: 44094
A5: MATRICULE | B5: NOM ET PRENOM | C5: MONTANT TONTINE | D5: PENALITE | E5: MODE VERSEMENT TONTINE | F5: VENTE PETIT LOT | G5: INTERET PETIT LOT | H5: MODE VERSEMENT VENTE PETIT LOT | I5: NUMERO CHEQUE | J5: REMBOURSEMENT | K5: MODE VERSEMENT REMBOURSEMENT | L5: MODE VERSEMENT TONTINE PRINCIPAL | M5: NUMERO CHEQUE | N5: MONTANT TONTINE LOT PRINCIPAL | O5: INTERET LOT PRINCIPAL | P5: DATE VENTE
A6: AS201608 | B6: =VLOOKUP(A6,[1]LISTADHERENT!A$5:H$60,3,0) -> DJUOMBESSY ANTOINE | C6: =IF(E6="ECHEC",0,IF(E6="",0,100000)) -> 100000 | D6: =IF(E6="ESPECES",0,0) -> 0 | E6: BANQUE | J6: =TONTAOUT!F6+TONTAOUT!G6 -> 0 | N6: =IF(O6=0,0,($C$38-O6)) -> 0
A7: AS201613 | B7: =VLOOKUP(A7,[1]LISTADHERENT!A$5:H$60,3,0) -> HOTCHO BENJAMIN | C7: =IF(E7="ECHEC",0,IF(E7="",0,100000)) -> 100000 | D7: =IF(E7="ESPECES",0,0) -> 0 | E7: BANQUE | J7: =TONTAOUT!F7+TONTAOUT!G7 -> 0 | N7: =IF(O7=0,0,($C$38-O7)) -> 0
A8: AS201619 | B8: =VLOOKUP(A8,[1]LISTADHERENT!A$5:H$60,3,0) -> KOUATCHO MESSACK | C8: =IF(E8="ECHEC",0,IF(E8="",0,100000)) -> 100000 | D8: =IF(E8="ESPECES",0,0) -> 0 | E8: ESPECES | F8: 136000 | G8: 5000 | J8: =TONTAOUT!F8+TONTAOUT!G8 -> 236000 | K8: ESPECES | N8: =IF(O8=0,0,($C$38-O8)) -> 0
A9: AS201617 | B9: =VLOOKUP(A9,[1]LISTADHERENT!A$5:H$60,3,0) -> KOUAMOU MOISE | C9: =IF(E9="ECHEC",0,IF(E9="",0,100000)) -> 100000 | D9: =IF(E9="ESPECES",0,0) -> 0 | E9: BANQUE | J9: =TONTAOUT!F9+TONTAOUT!G9 -> 0 | N9: =IF(O9=0,0,($C$38-O9)) -> 0
A10: AS201649 | B10: =VLOOKUP(A10,[1]LISTADHERENT!A$5:H$60,3,0) -> MBOGNING TUGMA GUY | C10: =IF(E10="ECHEC",0,IF(E10="",0,100000)) -> 100000 | D10: =IF(E10="ESPECES",0,0) -> 0 | E10: BANQUE | J10: =TONTAOUT!F10+TONTAOUT!G10 -> 0 | N10: =IF(O10=0,0,($C$38-O10)) -> 0
A11: AS201649 | B11: =VLOOKUP(A11,[1]LISTADHERENT!A$5:H$60,3,0) -> MBOGNING TUGMA GUY | C11: =IF(E11="ECHEC",0,IF(E11="",0,100000)) -> 100000 | D11: =IF(E11="ESPECES",0,0) -> 0 | E11: BANQUE | J11: =TONTAOUT!F11+TONTAOUT!G11 -> 0 | N11: =IF(O11=0,0,($C$38-O11)) -> 0
A12: AS201639 | B12: =VLOOKUP(A12,[1]LISTADHERENT!A$5:H$60,3,0) -> NANGUEN MARTIN | C12: =IF(E12="ECHEC",0,IF(E12="",0,100000)) -> 0 | D12: =IF(E12="ESPECES",0,0) -> 0 | E12: ECHEC | J12: =TONTAOUT!F12+TONTAOUT!G12 -> 0 | N12: =IF(O12=0,0,($C$38-O12)) -> 0
A13: AS201622 | B13: =VLOOKUP(A13,[1]LISTADHERENT!A$5:H$60,3,0) -> NDJOMO ETIENNE | C13: =IF(E13="ECHEC",0,IF(E13="",0,100000)) -> 100000 | D13: =IF(E13="ESPECES",0,0) -> 0 | E13: BANQUE | J13: =TONTAOUT!F13+TONTAOUT!G13 -> 0 | N13: =IF(O13=0,0,($C$38-O13)) -> 0
A14: AS201624 | B14: =VLOOKUP(A14,[1]LISTADHERENT!A$5:H$60,3,0) -> NGONDIEP CLAUDE | C14: =IF(E14="ECHEC",0,IF(E14="",0,100000)) -> 0 | D14: =IF(E14="ESPECES",0,0) -> 0 | E14: ECHEC | J14: =TONTAOUT!F14+TONTAOUT!G14 -> 0 | N14: =IF(O14=0,0,($C$38-O14)) -> 0
A15: AS201614 | B15: =VLOOKUP(A15,[1]LISTADHERENT!A$5:H$60,3,0) -> NKEHE DAVID | C15: =IF(E15="ECHEC",0,IF(E15="",0,100000)) -> 0 | D15: =IF(E15="ESPECES",0,0) -> 0 | E15: ECHEC | F15: 229500 | J15: =TONTAOUT!F15+TONTAOUT!G15 -> 229500 | K15: ECHEC | N15: =IF(O15=0,0,($C$38-O15)) -> 0
A16: AS201629 | B16: =VLOOKUP(A16,[1]LISTADHERENT!A$5:H$60,3,0) -> NKEPSEU DIEUDONNE | C16: =IF(E16="ECHEC",0,IF(E16="",0,100000)) -> 100000 | D16: =IF(E16="ESPECES",0,0) -> 0 | E16: BANQUE | J16: =TONTAOUT!F16+TONTAOUT!G16 -> 0 | N16: =IF(O16=0,0,($C$38-O16)) -> 0
A17: AS201636 | B17: =VLOOKUP(A17,[1]LISTADHERENT!A$5:H$60,3,0) -> SIMO FONGANG ERIC | C17: =IF(E17="ECHEC",0,IF(E17="",0,100000)) -> 100000 | D17: =IF(E17="ESPECES",0,0) -> 0 | E17: BANQUE | F17: 212000 | G17: 24000 | J17: =TONTAOUT!F17+TONTAOUT!G17 -> 212000 | K17: ECHEC | N17: =IF(O17=0,0,($C$38-O17)) -> 0
A18: AS201636 | B18: =VLOOKUP(A18,[1]LISTADHERENT!A$5:H$60,3,0) -> SIMO FONGANG ERIC | C18: =IF(E18="ECHEC",0,IF(E18="",0,100000)) -> 100000 | D18: =IF(E18="ESPECES",0,0) -> 0 | E18: BANQUE | J18: =TONTAOUT!F18+TONTAOUT!G18 -> 0 | N18: =IF(O18=0,0,($C$38-O18)) -> 0
A19: AS201637 | B19: =VLOOKUP(A19,[1]LISTADHERENT!A$5:H$60,3,0) -> SIME MATHIEU | C19: =IF(E19="ECHEC",0,IF(E19="",0,100000)) -> 100000 | D19: =IF(E19="ESPECES",0,0) -> 0 | E19: BANQUE | F19: 200000 | G19: 8000 | J19: =TONTAOUT!F19+TONTAOUT!G19 -> 0 | N19: =IF(O19=0,0,($C$38-O19)) -> 0
A20: AS201637 | B20: =VLOOKUP(A20,[1]LISTADHERENT!A$5:H$60,3,0) -> SIME MATHIEU | C20: =IF(E20="ECHEC",0,IF(E20="",0,100000)) -> 100000 | D20: =IF(E20="ESPECES",0,0) -> 0 | E20: BANQUE | J20: =TONTAOUT!F20+TONTAOUT!G20 -> 0 | N20: =IF(O20=0,0,($C$38-O20)) -> 0
A21: AS201641 | B21: =VLOOKUP(A21,[1]LISTADHERENT!A$5:H$60,3,0) -> TCHOUAMOU MATHIEU | C21: =IF(E21="ECHEC",0,IF(E21="",0,100000)) -> 100000 | D21: =IF(E21="ESPECES",0,0) -> 0 | E21: BANQUE | J21: =TONTAOUT!F21+TONTAOUT!G21 -> 0 | N21: =IF(O21=0,0,($C$38-O21)) -> 1400000 | O21: 100000
A22: AS201644 | B22: =VLOOKUP(A22,[1]LISTADHERENT!A$5:H$60,3,0) -> TIEYAM ERNEST | C22: =IF(E22="ECHEC",0,IF(E22="",0,100000)) -> 100000 | D22: =IF(E22="ESPECES",0,0) -> 0 | E22: BANQUE | F22: 107000 | J22: =TONTAOUT!F22+TONTAOUT!G22 -> 107000 | K22: ECHEC | N22: =IF(O22=0,0,($C$38-O22)) -> 0
A23: AS201647 | B23: =VLOOKUP(A23,[1]LISTADHERENT!A$5:H$60,3,0) -> YOUMBI EMMANUEL | C23: =IF(E23="ECHEC",0,IF(E23="",0,100000)) -> 100000 | D23: =IF(E23="ESPECES",0,0) -> 0 | E23: BANQUE | J23: =TONTAOUT!F23+TONTAOUT!G23 -> 0 | N23: =IF(O23=0,0,($C$38-O23)) -> 0
A25: TOTAL | C25: =SUM(C6:C24) -> 1500000 | D25: =SUM(D6:D24) -> 0 | F25: =SUM(F6:F24) -> 884500 | G25: =SUM(G6:G24) -> 37000 | J25: =SUM(J6:J24) -> 784500 | N25: =SUM(N6:N24) -> 1400000 | O25: =SUM(O6:O24) -> 100000
C27: TONTINE | D27: REMBOURSEMENT PETIT LOT | E27: VENTE PETIT LOT | F27: VENTE LOT PRINCIPAL | G27: SOLDE EN CAISSE | K27: TONTINE + REMB + INTERET VENTE | L27: =C25+D32+O25 -> 1836000
K28: TONTINE | L28: =IF(L27>=3000000,1500000*2,1500000) -> 1500000
B29: ESPECES | C29: =SUMIFS(C6:C23,E6:E23,"ESPECES") -> 100000 | D29: =SUMIFS(J6:J23,K6:K23,"ESPECES") -> 236000 | E29: =SUMIFS(F6:F23,H6:H23,"ESPECES") -> 0 | F29: =SUMIFS(N6:N23,L6:L23,"ESPECES") -> 0 | G29: =C29+D29-E29-F29 -> 336000 | K29: PETIT LOT | L29: =L27-L28 -> 336000
B30: BANQUE | C30: =SUMIFS(C6:C23,E6:E23,"BANQUE") -> 1400000 | D30: =SUMIFS(J6:J23,K6:K23,"BANQUE") -> 0 | E30: =SUMIFS(F6:F23,H6:H23,"BANQUE") -> 0 | F30: =SUMIFS(N6:N23,L6:L23,"BANQUE") -> 0 | G30: =C30+D30-E30-F30 -> 1400000 | K30: RESTE | L30: =L29-F25 -> -548500
B32: TOTAL | C32: =C29+C30 -> 1500000 | D32: =D29+D30 -> 236000 | E32: =E29+E30 -> 0 | F32: =F29+F30 -> 0 | G32: =G29+G30 -> 1736000 | K32: ECHEC TONTINE | L32: 300000 | M32: NANGUEM/NGONDIEP/KEHEP
K33: ECHEC REMBOURSEMENT | L33: =+F15+F17+F22 -> 548500 | M33: KEHEP/SIME ERIC/TYAM
B35: INTERET LOT PRINCIPAL | C35: =O25 -> 100000
B36: INTERET PETIT LOT | C36: =+G25 -> 37000
B38: MONTANT TONTINE | C38: 1500000
B39: MONTANT PETIT LOT A VENDRE | C39: =L29 -> 336000

Sheet TONT0CT
A1: ASSOCIATION | B1: ASELBY
A2: ANNEE | B2: 2019/2020
A3: TONTINE | B3: 100000
C4: 44122
A5: MATRICULE | B5: NOM ET PRENOM | C5: MONTANT TONTINE | D5: PENALITE | E5: MODE VERSEMENT TONTINE | F5: VENTE PETIT LOT | G5: INTERET PETIT LOT | H5: MODE VERSEMENT VENTE PETIT LOT | I5: NUMERO CHEQUE | J5: REMBOURSEMENT | K5: MODE VERSEMENT REMBOURSEMENT | L5: MODE VERSEMENT TONTINE PRINCIPAL | M5: NUMERO CHEQUE | N5: MONTANT TONTINE LOT PRINCIPAL | O5: INTERET LOT PRINCIPAL | P5: DATE VENTE
A6: AS201608 | B6: =VLOOKUP(A6,[1]LISTADHERENT!A$5:H$60,3,0) -> DJUOMBESSY ANTOINE | C6: =IF(E6="ECHEC",0,IF(E6="",0,100000)) -> 100000 | D6: =IF(E6="ESPECES",0,0) -> 0 | E6: BANQUE | J6: =TONTSEPT!F6+TONTSEPT!G6 -> 0 | N6: =IF(O6=0,0,($C$38-O6)) -> 0
A7: AS201613 | B7: =VLOOKUP(A7,[1]LISTADHERENT!A$5:H$60,3,0) -> HOTCHO BENJAMIN | C7: =IF(E7="ECHEC",0,IF(E7="",0,100000)) -> 100000 | D7: =IF(E7="ESPECES",0,0) -> 0 | E7: BANQUE | J7: =TONTSEPT!F7+TONTSEPT!G7 -> 0 | N7: =IF(O7=0,0,($C$38-O7)) -> 0
A8: AS201619 | B8: =VLOOKUP(A8,[1]LISTADHERENT!A$5:H$60,3,0) -> KOUATCHO MESSACK | C8: =IF(E8="ECHEC",0,IF(E8="",0,100000)) -> 100000 | D8: =IF(E8="ESPECES",0,0) -> 0 | E8: BANQUE | F8: 200000 | G8: 6000 | J8: =TONTSEPT!F8+TONTSEPT!G8 -> 141000 | K8: ESPECES | N8: =IF(O8=0,0,($C$38-O8)) -> 0
A9: AS201617 | B9: =VLOOKUP(A9,[1]LISTADHERENT!A$5:H$60,3,0) -> KOUAMOU MOISE | C9: =IF(E9="ECHEC",0,IF(E9="",0,100000)) -> 100000 | D9: =IF(E9="ESPECES",0,0) -> 0 | E9: BANQUE | J9: =TONTSEPT!F9+TONTSEPT!G9 -> 0 | N9: =IF(O9=0,0,($C$38-O9)) -> 0
A10: AS201649 | B10: =VLOOKUP(A10,[1]LISTADHERENT!A$5:H$60,3,0) -> MBOGNING TUGMA GUY | C10: =IF(E10="ECHEC",0,IF(E10="",0,100000)) -> 100000 | D10: =IF(E10="ESPECES",0,0) -> 0 | E10: BANQUE | F10: 159000 | G10: 2500 | J10: =TONTSEPT!F10+TONTSEPT!G10 -> 0 | N10: =IF(O10=0,0,($C$38-O10)) -> 0
A11: AS201649 | B11: =VLOOKUP(A11,[1]LISTADHERENT!A$5:H$60,3,0) -> MBOGNING TUGMA GUY | C11: =IF(E11="ECHEC",0,IF(E11="",0,100000)) -> 100000 | D11: =IF(E11="ESPECES",0,0) -> 0 | E11: BANQUE | J11: =TONTSEPT!F11+TONTSEPT!G11 -> 0 | N11: =IF(O11=0,0,($C$38-O11)) -> 0
A12: AS201639 | B12: =VLOOKUP(A12,[1]LISTADHERENT!A$5:H$60,3,0) -> NANGUEN MARTIN | C12: =IF(E12="ECHEC",0,IF(E12="",0,100000))+100000 -> 200000 | D12: =IF(E12="ESPECES",0,0) -> 0 | E12: BANQUE | J12: =TONTSEPT!F12+TONTSEPT!G12 -> 0 | N12: =IF(O12=0,0,($C$38-O12)) -> 1390000 | O12: 110000
A13: AS201622 | B13: =VLOOKUP(A13,[1]LISTADHERENT!A$5:H$60,3,0) -> NDJOMO ETIENNE | C13: =IF(E13="ECHEC",0,IF(E13="",0,100000)) -> 100000 | D13: =IF(E13="ESPECES",0,0) -> 0 | E13: BANQUE | J13: =TONTSEPT!F13+TONTSEPT!G13 -> 0 | N13: =IF(O13=0,0,($C$38-O13)) -> 0
A14: AS201624 | B14: =VLOOKUP(A14,[1]LISTADHERENT!A$5:H$60,3,0) -> NGONDIEP CLAUDE | C14: =IF(E14="ECHEC",0,IF(E14="",0,100000))+100000 -> 200000 | D14: =IF(E14="ESPECES",0,0) -> 0 | E14: BANQUE | J14: =TONTSEPT!F14+TONTSEPT!G14 -> 0 | N14: =IF(O14=0,0,($C$38-O14)) -> 0
A15: AS201614 | B15: =VLOOKUP(A15,[1]LISTADHERENT!A$5:H$60,3,0) -> NKEHE DAVID | C15: =IF(E15="ECHEC",0,IF(E15="",0,100000)) -> 0 | D15: =IF(E15="ESPECES",0,0) -> 0 | E15: ECHEC | F15: 229500 | J15: =TONTSEPT!F15+TONTSEPT!G15 -> 229500 | N15: =IF(O15=0,0,($C$38-O15)) -> 0
A16: AS201629 | B16: =VLOOKUP(A16,[1]LISTADHERENT!A$5:H$60,3,0) -> NKEPSEU DIEUDONNE | C16: =IF(E16="ECHEC",0,IF(E16="",0,100000)) -> 100000 | D16: =IF(E16="ESPECES",0,0) -> 0 | E16: BANQUE | F16: 100000 | G16: 1000 | J16: =TONTSEPT!F16+TONTSEPT!G16 -> 0 | N16: =IF(O16=0,0,($C$38-O16)) -> 0
A17: AS201636 | B17: =VLOOKUP(A17,[1]LISTADHERENT!A$5:H$60,3,0) -> SIMO FONGANG ERIC | C17: =IF(E17="ECHEC",0,IF(E17="",0,100000)) -> 100000 | D17: =IF(E17="ESPECES",0,0) -> 0 | E17: ESPECES | F17: 236000 | J17: =TONTSEPT!F17+TONTSEPT!G17 -> 236000 | N17: =IF(O17=0,0,($C$38-O17)) -> 0
A18: AS201636 | B18: =VLOOKUP(A18,[1]LISTADHERENT!A$5:H$60,3,0) -> SIMO FONGANG ERIC | C18: =IF(E18="ECHEC",0,IF(E18="",0,100000)) -> 100000 | D18: =IF(E18="ESPECES",0,0) -> 0 | E18: ESPECES | J18: =TONTSEPT!F18+TONTSEPT!G18 -> 0 | N18: =IF(O18=0,0,($C$38-O18)) -> 0
A19: AS201637 | B19: =VLOOKUP(A19,[1]LISTADHERENT!A$5:H$60,3,0) -> SIME MATHIEU | C19: =IF(E19="ECHEC",0,IF(E19="",0,100000)) -> 100000 | D19: =IF(E19="ESPECES",0,0) -> 0 | E19: BANQUE | F19: 208000 | J19: =TONTSEPT!F19+TONTSEPT!G19 -> 208000 | N19: =IF(O19=0,0,($C$38-O19)) -> 0
A20: AS201637 | B20: =VLOOKUP(A20,[1]LISTADHERENT!A$5:H$60,3,0) -> SIME MATHIEU | C20: =IF(E20="ECHEC",0,IF(E20="",0,100000)) -> 100000 | D20: =IF(E20="ESPECES",0,0) -> 0 | E20: BANQUE | J20: =TONTSEPT!F20+TONTSEPT!G20 -> 0 | N20: =IF(O20=0,0,($C$38-O20)) -> 0
A21: AS201641 | B21: =VLOOKUP(A21,[1]LISTADHERENT!A$5:H$60,3,0) -> TCHOUAMOU MATHIEU | C21: =IF(E21="ECHEC",0,IF(E21="",0,100000)) -> 100000 | D21: =IF(E21="ESPECES",0,0) -> 0 | E21: BANQUE | F21: 200000 | G21: 4500 | J21: =TONTSEPT!F21+TONTSEPT!G21 -> 0 | N21: =IF(O21=0,0,($C$38-O21)) -> 0
A22: AS201644 | B22: =VLOOKUP(A22,[1]LISTADHERENT!A$5:H$60,3,0) -> TIEYAM ERNEST | C22: =IF(E22="ECHEC",0,IF(E22="",0,100000)) -> 100000 | D22: =IF(E22="ESPECES",0,0) -> 0 | E22: ESPECES | F22: 107000 | J22: =TONTSEPT!F22+TONTSEPT!G22 -> 107000 | N22: =IF(O22=0,0,($C$38-O22)) -> 0
A23: AS201647 | B23: =VLOOKUP(A23,[1]LISTADHERENT!A$5:H$60,3,0) -> YOUMBI EMMANUEL | C23: =IF(E23="ECHEC",0,IF(E23="",0,100000)) -> 100000 | D23: =IF(E23="ESPECES",0,0) -> 0 | E23: BANQUE | J23: =TONTSEPT!F23+TONTSEPT!G23 -> 0 | N23: =IF(O23=0,0,($C$38-O23)) -> 0
A25: TOTAL | C25: =SUM(C6:C24) -> 1900000 | D25: =SUM(D6:D24) -> 0 | F25: =SUM(F6:F24) -> 1439500 | G25: =SUM(G6:G24) -> 14000 | J25: =SUM(J6:J24) -> 921500 | N25: =SUM(N6:N24) -> 1390000 | O25: =SUM(O6:O24) -> 110000
C27: TONTINE | D27: REMBOURSEMENT PETIT LOT | E27: VENTE PETIT LOT | F27: VENTE LOT PRINCIPAL | G27: SOLDE EN CAISSE | K27: TONTINE + REMB + INTERET VENTE | L27: =C25+D32+O25 -> 2151000
K28: TONTINE | L28: =IF(L27>=3000000,1500000*2,1500000) -> 1500000
B29: ESPECES | C29: =SUMIFS(C6:C23,E6:E23,"ESPECES") -> 300000 | D29: =SUMIFS(J6:J23,K6:K23,"ESPECES") -> 141000 | E29: =SUMIFS(F6:F23,H6:H23,"ESPECES") -> 0 | F29: =SUMIFS(N6:N23,L6:L23,"ESPECES") -> 0 | G29: =C29+D29-E29-F29 -> 441000 | K29: PETIT LOT | L29: =L27-L28+8000 -> 659000
B30: BANQUE | C30: =SUMIFS(C6:C23,E6:E23,"BANQUE") -> 1600000 | D30: =SUMIFS(J6:J23,K6:K23,"BANQUE") -> 0 | E30: =SUMIFS(F6:F23,H6:H23,"BANQUE") -> 0 | F30: =SUMIFS(N6:N23,L6:L23,"BANQUE") -> 0 | G30: =C30+D30-E30-F30 -> 1600000 | K30: RESTE | L30: =L29-F25 -> -780500
B32: TOTAL | C32: =C29+C30 -> 1900000 | D32: =D29+D30 -> 141000 | E32: =E29+E30 -> 0 | F32: =F29+F30 -> 0 | G32: =G29+G30 -> 2041000 | K32: ECHEC TONTINE | L32: 100000 | M32: KEHEP
K33: ECHEC REMBOURSEMENT | L33: 0
B35: INTERET LOT PRINCIPAL | C35: =O25 -> 110000
B36: INTERET PETIT LOT | C36: =+G25 -> 14000
B38: MONTANT TONTINE | C38: 1500000
B39: MONTANT PETIT LOT A VENDRE | C39: =L29 -> 659000

Sheet TONTNOV20
A1: ASSOCIATION | B1: ASELBY
A2: ANNEE | B2: 2019/2020
A3: TONTINE | B3: 100000
C4: 44150
A5: MATRICULE | B5: NOM ET PRENOM | C5: MONTANT TONTINE | D5: PENALITE | E5: MODE VERSEMENT TONTINE | F5: VENTE PETIT LOT | G5: INTERET PETIT LOT | H5: MODE VERSEMENT VENTE PETIT LOT | I5: NUMERO CHEQUE | J5: REMBOURSEMENT | K5: MODE VERSEMENT REMBOURSEMENT | L5: MODE VERSEMENT TONTINE PRINCIPAL | M5: NUMERO CHEQUE | N5: MONTANT TONTINE LOT PRINCIPAL | O5: INTERET LOT PRINCIPAL | P5: DATE VENTE
A6: AS201608 | B6: =VLOOKUP(A6,[1]LISTADHERENT!A$5:H$60,3,0) -> DJUOMBESSY ANTOINE | C6: =IF(E6="ECHEC",0,IF(E6="",0,100000)) -> 0 | D6: =IF(E6="ESPECES",0,0) -> 0 | E6: ECHEC | J6: =TONT0CT!F6+TONT0CT!G6 -> 0 | N6: =IF(O6=0,0,($C$38-O6)) -> 0
A7: AS201613 | B7: =VLOOKUP(A7,[1]LISTADHERENT!A$5:H$60,3,0) -> HOTCHO BENJAMIN | C7: =IF(E7="ECHEC",0,IF(E7="",0,100000)) -> 0 | D7: =IF(E7="ESPECES",0,0) -> 0 | E7: ECHEC | J7: =TONT0CT!F7+TONT0CT!G7 -> 0 | N7: =IF(O7=0,0,($C$38-O7)) -> 0
A8: AS201619 | B8: =VLOOKUP(A8,[1]LISTADHERENT!A$5:H$60,3,0) -> KOUATCHO MESSACK | C8: =IF(E8="ECHEC",0,IF(E8="",0,100000)) -> 0 | D8: =IF(E8="ESPECES",0,0) -> 0 | E8: ECHEC | J8: =TONT0CT!F8+TONT0CT!G8 -> 206000 | N8: =IF(O8=0,0,($C$38-O8)) -> 0
A9: AS201617 | B9: =VLOOKUP(A9,[1]LISTADHERENT!A$5:H$60,3,0) -> KOUAMOU MOISE | C9: =IF(E9="ECHEC",0,IF(E9="",0,100000)) -> 0 | D9: =IF(E9="ESPECES",0,0) -> 0 | E9: ECHEC | J9: =TONT0CT!F9+TONT0CT!G9 -> 0 | N9: =IF(O9=0,0,($C$38-O9)) -> 0
A10: AS201649 | B10: =VLOOKUP(A10,[1]LISTADHERENT!A$5:H$60,3,0) -> MBOGNING TUGMA GUY | C10: =IF(E10="ECHEC",0,IF(E10="",0,100000)) -> 0 | D10: =IF(E10="ESPECES",0,0) -> 0 | E10: ECHEC | J10: =TONT0CT!F10+TONT0CT!G10 -> 161500 | N10: =IF(O10=0,0,($C$38-O10)) -> 0
A11: AS201649 | B11: =VLOOKUP(A11,[1]LISTADHERENT!A$5:H$60,3,0) -> MBOGNING TUGMA GUY | C11: =IF(E11="ECHEC",0,IF(E11="",0,100000)) -> 0 | D11: =IF(E11="ESPECES",0,0) -> 0 | E11: ECHEC | J11: =TONT0CT!F11+TONT0CT!G11 -> 0 | N11: =IF(O11=0,0,($C$38-O11)) -> 0
A12: AS201639 | B12: =VLOOKUP(A12,[1]LISTADHERENT!A$5:H$60,3,0) -> NANGUEN MARTIN | C12: =IF(E12="ECHEC",0,IF(E12="",0,100000)) -> 0 | D12: =IF(E12="ESPECES",0,0) -> 0 | E12: ECHEC | J12: =TONT0CT!F12+TONT0CT!G12 -> 0 | N12: =IF(O12=0,0,($C$38-O12)) -> 0
A13: AS201622 | B13: =VLOOKUP(A13,[1]LISTADHERENT!A$5:H$60,3,0) -> NDJOMO ETIENNE | C13: =IF(E13="ECHEC",0,IF(E13="",0,100000)) -> 0 | D13: =IF(E13="ESPECES",0,0) -> 0 | E13: ECHEC | J13: =TONT0CT!F13+TONT0CT!G13 -> 0 | N13: =IF(O13=0,0,($C$38-O13)) -> 0
A14: AS201624 | B14: =VLOOKUP(A14,[1]LISTADHERENT!A$5:H$60,3,0) -> NGONDIEP CLAUDE | C14: =IF(E14="ECHEC",0,IF(E14="",0,100000)) -> 0 | D14: =IF(E14="ESPECES",0,0) -> 0 | E14: ECHEC | J14: =TONT0CT!F14+TONT0CT!G14 -> 0 | N14: =IF(O14=0,0,($C$38-O14)) -> 0
A15: AS201614 | B15: =VLOOKUP(A15,[1]LISTADHERENT!A$5:H$60,3,0) -> NKEHE DAVID | C15: =IF(E15="ECHEC",0,IF(E15="",0,100000)) -> 0 | D15: =IF(E15="ESPECES",0,0) -> 0 | E15: ECHEC | J15: =TONT0CT!F15+TONT0CT!G15 -> 229500 | N15: =IF(O15=0,0,($C$38-O15)) -> 0
A16: AS201629 | B16: =VLOOKUP(A16,[1]LISTADHERENT!A$5:H$60,3,0) -> NKEPSEU DIEUDONNE | C16: =IF(E16="ECHEC",0,IF(E16="",0,100000)) -> 0 | D16: =IF(E16="ESPECES",0,0) -> 0 | E16: ECHEC | J16: =TONT0CT!F16+TONT0CT!G16 -> 101000 | N16: =IF(O16=0,0,($C$38-O16)) -> 0
A17: AS201636 | B17: =VLOOKUP(A17,[1]LISTADHERENT!A$5:H$60,3,0) -> SIMO FONGANG ERIC | C17: =IF(E17="ECHEC",0,IF(E17="",0,100000)) -> 0 | D17: =IF(E17="ESPECES",0,0) -> 0 | E17: ECHEC | J17: =TONT0CT!F17+TONT0CT!G17 -> 236000 | N17: =IF(O17=0,0,($C$38-O17)) -> 0
... A23: AS201647 | B23: =VLOOKUP(A23,[1]LISTADHERENT!A$5:H$60,3,0) -> YOUMBI EMMANUEL | C23: =IF(E23="ECHEC",0,IF(E23="",0,100000)) -> 0 | D23: =IF(E23="ESPECES",0,0) -> 0 | E23: ECHEC | J23: =TONT0CT!F23+TONT0CT!G23 -> 0 | N23: =IF(O23=0,0,($C$38-O23)) -> 0
A25: TOTAL | C25: =SUM(C6:C24) -> 0 | D25: =SUM(D6:D24) -> 0 | F25: =SUM(F6:F24) -> 0 | G25: =SUM(G6:G24) -> 0 | J25: =SUM(J6:J24) -> 1453500 | N25: =SUM(N6:N24) -> 0 | O25: =SUM(O6:O24) -> 0
C27: TONTINE | D27: REMBOURSEMENT PETIT LOT | E27: VENTE PETIT LOT | F27: VENTE LOT PRINCIPAL | G27: SOLDE EN CAISSE | K27: TONTINE + REMB + INTERET VENTE | L27: =C25+D32+O25 -> 0
K28: TONTINE | L28: =IF(L27>=3000000,1500000*2,1500000) -> 1500000
B29: ESPECES | C29: =SUMIFS(C6:C23,E6:E23,"ESPECES") -> 0 | D29: =SUMIFS(J6:J23,K6:K23,"ESPECES") -> 0 | E29: =SUMIFS(F6:F23,H6:H23,"ESPECES") -> 0 | F29: =SUMIFS(N6:N23,L6:L23,"ESPECES") -> 0 | G29: =C29+D29-E29-F29 -> 0 | K29: PETIT LOT | L29: =L27-L28 -> -1500000
B30: BANQUE | C30: =SUMIFS(C6:C23,E6:E23,"BANQUE") -> 0 | D30: =SUMIFS(J6:J23,K6:K23,"BANQUE") -> 0 | E30: =SUMIFS(F6:F23,H6:H23,"BANQUE") -> 0 | F30: =SUMIFS(N6:N23,L6:L23,"BANQUE") -> 0 | G30: =C30+D30-E30-F30 -> 0 | K30: RESTE | L30: =L29-F25 -> -1500000
B32: TOTAL | C32: =C29+C30 -> 0 | D32: =D29+D30 -> 0 | E32: =E29+E30 -> 0 | F32: =F29+F30 -> 0 | G32: =G29+G30 -> 0 | K32: ECHEC TONTINE | L32: 0
K33: ECHEC REMBOURSEMENT | L33: 0
B35: INTERET LOT PRINCIPAL | C35: =O25 -> 0
B36: INTERET PETIT LOT | C36: =+G25 -> 0
B38: MONTANT TONTINE | C38: 1500000
B39: MONTANT PETIT LOT A VENDRE | C39: =L29 -> -1500000

Sheet TONTDEC20
A1: ASSOCIATION | B1: ASELBY
A2: ANNEE | B2: 2019/2020
A3: TONTINE | B3: 100000
C4: 44185
A5: MATRICULE | B5: NOM ET PRENOM | C5: MONTANT TONTINE | D5: PENALITE | E5: MODE VERSEMENT TONTINE | F5: VENTE PETIT LOT | G5: INTERET PETIT LOT | H5: MODE VERSEMENT VENTE PETIT LOT | I5: NUMERO CHEQUE | J5: REMBOURSEMENT | K5: MODE VERSEMENT REMBOURSEMENT | L5: MODE VERSEMENT TONTINE PRINCIPAL | M5: NUMERO CHEQUE | N5: MONTANT TONTINE LOT PRINCIPAL | O5: INTERET LOT PRINCIPAL | P5: DATE VENTE
A6: AS201608 | B6: =VLOOKUP(A6,[1]LISTADHERENT!A$5:H$60,3,0) -> DJUOMBESSY ANTOINE | C6: =IF(E6="ECHEC",0,IF(E6="",0,100000)) -> 0 | D6: =IF(E6="ESPECES",0,0) -> 0 | E6: ECHEC | J6: =TONTNOV20!F6+TONTNOV20!G6 -> 0 | N6: =IF(O6=0,0,($C$38-O6)) -> 0
A7: AS201613 | B7: =VLOOKUP(A7,[1]LISTADHERENT!A$5:H$60,3,0) -> HOTCHO BENJAMIN | C7: =IF(E7="ECHEC",0,IF(E7="",0,100000)) -> 0 | D7: =IF(E7="ESPECES",0,0) -> 0 | E7: ECHEC | J7: =TONTNOV20!F7+TONTNOV20!G7 -> 0 | N7: =IF(O7=0,0,($C$38-O7)) -> 0
A8: AS201619 | B8: =VLOOKUP(A8,[1]LISTADHERENT!A$5:H$60,3,0) -> KOUATCHO MESSACK | C8: =IF(E8="ECHEC",0,IF(E8="",0,100000)) -> 0 | D8: =IF(E8="ESPECES",0,0) -> 0 | E8: ECHEC | J8: =TONTNOV20!F8+TONTNOV20!G8 -> 0 | N8: =IF(O8=0,0,($C$38-O8)) -> 0
A9: AS201617 | B9: =VLOOKUP(A9,[1]LISTADHERENT!A$5:H$60,3,0) -> KOUAMOU MOISE | C9: =IF(E9="ECHEC",0,IF(E9="",0,100000)) -> 0 | D9: =IF(E9="ESPECES",0,0) -> 0 | E9: ECHEC | J9: =TONTNOV20!F9+TONTNOV20!G9 -> 0 | N9: =IF(O9=0,0,($C$38-O9)) -> 0
A10: AS201649 | B10: =VLOOKUP(A10,[1]LISTADHERENT!A$5:H$60,3,0) -> MBOGNING TUGMA GUY | C10: =IF(E10="ECHEC",0,IF(E10="",0,100000)) -> 0 | D10: =IF(E10="ESPECES",0,0) -> 0 | E10: ECHEC | J10: =TONTNOV20!F10+TONTNOV20!G10 -> 0 | N10: =IF(O10=0,0,($C$38-O10)) -> 0
A11: AS201649 | B11: =VLOOKUP(A11,[1]LISTADHERENT!A$5:H$60,3,0) -> MBOGNING TUGMA GUY | C11: =IF(E11="ECHEC",0,IF(E11="",0,100000)) -> 0 | D11: =IF(E11="ESPECES",0,0) -> 0 | E11: ECHEC | J11: =TONTNOV20!F11+TONTNOV20!G11 -> 0 | N11: =IF(O11=0,0,($C$38-O11)) -> 0
A12: AS201639 | B12: =VLOOKUP(A12,[1]LISTADHERENT!A$5:H$60,3,0) -> NANGUEN MARTIN | C12: =IF(E12="ECHEC",0,IF(E12="",0,100000)) -> 0 | D12: =IF(E12="ESPECES",0,0) -> 0 | E12: ECHEC | J12: =TONTNOV20!F12+TONTNOV20!G12 -> 0 | N12: =IF(O12=0,0,($C$38-O12)) -> 0
A13: AS201622 | B13: =VLOOKUP(A13,[1]LISTADHERENT!A$5:H$60,3,0) -> NDJOMO ETIENNE | C13: =IF(E13="ECHEC",0,IF(E13="",0,100000)) -> 0 | D13: =IF(E13="ESPECES",0,0) -> 0 | E13: ECHEC | J13: =TONTNOV20!F13+TONTNOV20!G13 -> 0 | N13: =IF(O13=0,0,($C$38-O13)) -> 0
A14: AS201624 | B14: =VLOOKUP(A14,[1]LISTADHERENT!A$5:H$60,3,0) -> NGONDIEP CLAUDE | C14: =IF(E14="ECHEC",0,IF(E14="",0,100000)) -> 0 | D14: =IF(E14="ESPECES",0,0) -> 0 | E14: ECHEC | J14: =TONTNOV20!F14+TONTNOV20!G14 -> 0 | N14: =IF(O14=0,0,($C$38-O14)) -> 0
A15: AS201614 | B15: =VLOOKUP(A15,[1]LISTADHERENT!A$5:H$60,3,0) -> NKEHE DAVID | C15: =IF(E15="ECHEC",0,IF(E15="",0,100000)) -> 0 | D15: =IF(E15="ESPECES",0,0) -> 0 | E15: ECHEC | J15: =TONTNOV20!F15+TONTNOV20!G15 -> 0 | N15: =IF(O15=0,0,($C$38-O15)) -> 0
A16: AS201629 | B16: =VLOOKUP(A16,[1]LISTADHERENT!A$5:H$60,3,0) -> NKEPSEU DIEUDONNE | C16: =IF(E16="ECHEC",0,IF(E16="",0,100000)) -> 0 | D16: =IF(E16="ESPECES",0,0) -> 0 | E16: ECHEC | J16: =TONTNOV20!F16+TONTNOV20!G16 -> 0 | N16: =IF(O16=0,0,($C$38-O16)) -> 0
A17: AS201636 | B17: =VLOOKUP(A17,[1]LISTADHERENT!A$5:H$60,3,0) -> SIMO FONGANG ERIC | C17: =IF(E17="ECHEC",0,IF(E17="",0,100000)) -> 0 | D17: =IF(E17="ESPECES",0,0) -> 0 | E17: ECHEC | J17: =TONTNOV20!F17+TONTNOV20!G17 -> 0 | N17: =IF(O17=0,0,($C$38-O17)) -> 0
... A23: AS201647 | B23: =VLOOKUP(A23,[1]LISTADHERENT!A$5:H$60,3,0) -> YOUMBI EMMANUEL | C23: =IF(E23="ECHEC",0,IF(E23="",0,100000)) -> 0 | D23: =IF(E23="ESPECES",0,0) -> 0 | E23: ECHEC | J23: =TONTNOV20!F23+TONTNOV20!G23 -> 0 | N23: =IF(O23=0,0,($C$38-O23)) -> 0
A25: TOTAL | C25: =SUM(C6:C24) -> 0 | D25: =SUM(D6:D24) -> 0 | F25: =SUM(F6:F24) -> 0 | G25: =SUM(G6:G24) -> 0 | J25: =SUM(J6:J24) -> 0 | N25: =SUM(N6:N24) -> 0 | O25: =SUM(O6:O24) -> 0
C27: TONTINE | D27: REMBOURSEMENT PETIT LOT | E27: VENTE PETIT LOT | F27: VENTE LOT PRINCIPAL | G27: SOLDE EN CAISSE | K27: TONTINE + REMB + INTERET VENTE | L27: =C25+D32+O25 -> 0
K28: TONTINE | L28: =IF(L27>=3000000,1500000*2,1500000) -> 1500000
B29: ESPECES | C29: =SUMIFS(C6:C23,E6:E23,"ESPECES") -> 0 | D29: =SUMIFS(J6:J23,K6:K23,"ESPECES") -> 0 | E29: =SUMIFS(F6:F23,H6:H23,"ESPECES") -> 0 | F29: =SUMIFS(N6:N23,L6:L23,"ESPECES") -> 0 | G29: =C29+D29-E29-F29 -> 0 | K29: PETIT LOT | L29: =L27-L28 -> -1500000
B30: BANQUE | C30: =SUMIFS(C6:C23,E6:E23,"BANQUE") -> 0 | D30: =SUMIFS(J6:J23,K6:K23,"BANQUE") -> 0 | E30: =SUMIFS(F6:F23,H6:H23,"BANQUE") -> 0 | F30: =SUMIFS(N6:N23,L6:L23,"BANQUE") -> 0 | G30: =C30+D30-E30-F30 -> 0 | K30: RESTE | L30: =L29-F25 -> -1500000
B32: TOTAL | C32: =C29+C30 -> 0 | D32: =D29+D30 -> 0 | E32: =E29+E30 -> 0 | F32: =F29+F30 -> 0 | G32: =G29+G30 -> 0 | K32: ECHEC TONTINE | L32: 0
K33: ECHEC REMBOURSEMENT | L33: 0
B35: INTERET LOT PRINCIPAL | C35: =O25 -> 0
B36: INTERET PETIT LOT | C36: =+G25 -> 0
B38: MONTANT TONTINE | C38: 1500000
B39: MONTANT PETIT LOT A VENDRE | C39: =L29 -> -1500000

Sheet TONTRESUME
A1: ASSOCIATION | B1: ASELBY | D1: RECAPITULATIF
A2: ANNEE | B2: 2019/2020
A3: TONTINE | B3: 100000
C4: 44185
A5: MATRICULE | B5: NOM ET PRENOM | C5: MONTANT TONTINE | D5: VENTE PETIT LOT | E5: INTERET PETIT LOT | F5: REMBOURSEMENT | G5: MONTANT TONTINE LOT PRINCIPAL | H5: INTERET LOT PRINCIPAL | I5: DATE VENTE | J5: BONUS
A6: AS201608 | B6: =VLOOKUP(A6,[1]LISTADHERENT!A$5:H$60,3,0) -> DJUOMBESSY ANTOINE | C6: =TONTNOV!C6+TONTDEC!C6+TONTJANV!C6+TONTFEV!C6+TONTMARS!C6+TONTAVRIL!C6+TONTMAI!C6+TONTJUIN!C6+TONTJUIL!C6+TONTAOUT!C6+TONTSEPT!C6+TONT0CT!C6+TONTNOV20!C6+TONTDEC20!C6 -> 1200000 | D6: =TONTNOV!F6+TONTDEC!F6+TONTJANV!F6+TONTFEV!F6+TONTMARS!F6+TONTAVRIL!F6+TONTMAI!F6+TONTJUIN!F6+TONTJUIL!F6+TONTAOUT!F6+TONTSEPT!F6+TONT0CT!F6+TONTNOV20!F6+TONTDEC20!F6 -> 0 | E6: =TONTNOV!G6+TONTDEC!G6+TONTJANV!G6+TONTFEV!G6+TONTMARS!G6+TONTAVRIL!G6+TONTMAI!G6+TONTJUIN!G6+TONTJUIL!G6+TONTAOUT!G6+TONTSEPT!G6+TONT0CT!G6+TONTNOV20!G6+TONTDEC20!G6 -> 0 | F6: =TONTNOV!J6+TONTDEC!J6+TONTJANV!J6+TONTFEV!J6+TONTMARS!J6+TONTAVRIL!J6+TONTMAI!J6+TONTJUIN!J6+TONTJUIL!J6+TONTAOUT!J6+TONTSEPT!J6+TONT0CT!J6+TONTNOV20!J6+TONTDEC20!J6 -> 0 | G6: =TONTNOV!N6+TONTDEC!N6+TONTJANV!N6+TONTFEV!N6+TONTMARS!N6+TONTAVRIL!N6+TONTMAI!N6+TONTJUIN!N6+TONTJUIL!N6+TONTAOUT!N6+TONTSEPT!N6+TONT0CT!N6+TONTNOV20!N6+TONTDEC20!N6 -> 0 | H6: =TONTNOV!O6+TONTDEC!O6+TONTJANV!O6+TONTFEV!O6+TONTMARS!O6+TONTAVRIL!O6+TONTMAI!O6+TONTJUIN!O6+TONTJUIL!O6+TONTAOUT!O6+TONTSEPT!O6+TONT0CT!O6+TONTNOV20!O6+TONTDEC20!O6 -> 0 | J6: =IF(G6=0,0,(H6-100000)) -> 0
A7: AS201613 | B7: =VLOOKUP(A7,[1]LISTADHERENT!A$5:H$60,3,0) -> HOTCHO BENJAMIN | C7: =TONTNOV!C7+TONTDEC!C7+TONTJANV!C7+TONTFEV!C7+TONTMARS!C7+TONTAVRIL!C7+TONTMAI!C7+TONTJUIN!C7+TONTJUIL!C7+TONTAOUT!C7+TONTSEPT!C7+TONT0CT!C7+TONTNOV20!C7+TONTDEC20!C7 -> 1200000 | D7: =TONTNOV!F7+TONTDEC!F7+TONTJANV!F7+TONTFEV!F7+TONTMARS!F7+TONTAVRIL!F7+TONTMAI!F7+TONTJUIN!F7+TONTJUIL!F7+TONTAOUT!F7+TONTSEPT!F7+TONT0CT!F7+TONTNOV20!F7+TONTDEC20!F7 -> 0 | E7: =TONTNOV!G7+TONTDEC!G7+TONTJANV!G7+TONTFEV!G7+TONTMARS!G7+TONTAVRIL!G7+TONTMAI!G7+TONTJUIN!G7+TONTJUIL!G7+TONTAOUT!G7+TONTSEPT!G7+TONT0CT!G7+TONTNOV20!G7+TONTDEC20!G7 -> 0 | F7: =TONTNOV!J7+TONTDEC!J7+TONTJANV!J7+TONTFEV!J7+TONTMARS!J7+TONTAVRIL!J7+TONTMAI!J7+TONTJUIN!J7+TONTJUIL!J7+TONTAOUT!J7+TONTSEPT!J7+TONT0CT!J7+TONTNOV20!J7+TONTDEC20!J7 -> 0 | G7: =TONTNOV!N7+TONTDEC!N7+TONTJANV!N7+TONTFEV!N7+TONTMARS!N7+TONTAVRIL!N7+TONTMAI!N7+TONTJUIN!N7+TONTJUIL!N7+TONTAOUT!N7+TONTSEPT!N7+TONT0CT!N7+TONTNOV20!N7+TONTDEC20!N7 -> 1400000 | H7: =TONTNOV!O7+TONTDEC!O7+TONTJANV!O7+TONTFEV!O7+TONTMARS!O7+TONTAVRIL!O7+TONTMAI!O7+TONTJUIN!O7+TONTJUIL!O7+TONTAOUT!O7+TONTSEPT!O7+TONT0CT!O7+TONTNOV20!O7+TONTDEC20!O7 -> 100000 | I7: 43940 | J7: =IF(G7=0,0,(H7-100000)) -> 0
A8: AS201619 | B8: =VLOOKUP(A8,[1]LISTADHERENT!A$5:H$60,3,0) -> KOUATCHO MESSACK | C8: =TONTNOV!C8+TONTDEC!C8+TONTJANV!C8+TONTFEV!C8+TONTMARS!C8+TONTAVRIL!C8+TONTMAI!C8+TONTJUIN!C8+TONTJUIL!C8+TONTAOUT!C8+TONTSEPT!C8+TONT0CT!C8+TONTNOV20!C8+TONTDEC20!C8 -> 1200000 | D8: =TONTNOV!F8+TONTDEC!F8+TONTJANV!F8+TONTFEV!F8+TONTMARS!F8+TONTAVRIL!F8+TONTMAI!F8+TONTJUIN!F8+TONTJUIL!F8+TONTAOUT!F8+TONTSEPT!F8+TONT0CT!F8+TONTNOV20!F8+TONTDEC20!F8 -> 1584000 | E8: =TONTNOV!G8+TONTDEC!G8+TONTJANV!G8+TONTFEV!G8+TONTMARS!G8+TONTAVRIL!G8+TONTMAI!G8+TONTJUIN!G8+TONTJUIL!G8+TONTAOUT!G8+TONTSEPT!G8+TONT0CT!G8+TONTNOV20!G8+TONTDEC20!G8 -> 44500 | F8: =TONTNOV!J8+TONTDEC!J8+TONTJANV!J8+TONTFEV!J8+TONTMARS!J8+TONTAVRIL!J8+TONTMAI!J8+TONTJUIN!J8+TONTJUIL!J8+TONTAOUT!J8+TONTSEPT!J8+TONT0CT!J8+TONTNOV20!J8+TONTDEC20!J8 -> 1628500 | G8: =TONTNOV!N8+TONTDEC!N8+TONTJANV!N8+TONTFEV!N8+TONTMARS!N8+TONTAVRIL!N8+TONTMAI!N8+TONTJUIN!N8+TONTJUIL!N8+TONTAOUT!N8+TONTSEPT!N8+TONT0CT!N8+TONTNOV20!N8+TONTDEC20!N8 -> 1250000 | H8: =TONTNOV!O8+TONTDEC!O8+TONTJANV!O8+TONTFEV!O8+TONTMARS!O8+TONTAVRIL!O8+TONTMAI!O8+TONTJUIN!O8+TONTJUIL!O8+TONTAOUT!O8+TONTSEPT!O8+TONT0CT!O8+TONTNOV20!O8+TONTDEC20!O8 -> 250000 | I8: 43819 | J8: =IF(G8=0,0,(H8-100000)) -> 150000
A9: AS201617 | B9: =VLOOKUP(A9,[1]LISTADHERENT!A$5:H$60,3,0) -> KOUAMOU MOISE | C9: =TONTNOV!C9+TONTDEC!C9+TONTJANV!C9+TONTFEV!C9+TONTMARS!C9+TONTAVRIL!C9+TONTMAI!C9+TONTJUIN!C9+TONTJUIL!C9+TONTAOUT!C9+TONTSEPT!C9+TONT0CT!C9+TONTNOV20!C9+TONTDEC20!C9 -> 1200000 | D9: =TONTNOV!F9+TONTDEC!F9+TONTJANV!F9+TONTFEV!F9+TONTMARS!F9+TONTAVRIL!F9+TONTMAI!F9+TONTJUIN!F9+TONTJUIL!F9+TONTAOUT!F9+TONTSEPT!F9+TONT0CT!F9+TONTNOV20!F9+TONTDEC20!F9 -> 0 | E9: =TONTNOV!G9+TONTDEC!G9+TONTJANV!G9+TONTFEV!G9+TONTMARS!G9+TONTAVRIL!G9+TONTMAI!G9+TONTJUIN!G9+TONTJUIL!G9+TONTAOUT!G9+TONTSEPT!G9+TONT0CT!G9+TONTNOV20!G9+TONTDEC20!G9 -> 0 | F9: =TONTNOV!J9+TONTDEC!J9+TONTJANV!J9+TONTFEV!J9+TONTMARS!J9+TONTAVRIL!J9+TONTMAI!J9+TONTJUIN!J9+TONTJUIL!J9+TONTAOUT!J9+TONTSEPT!J9+TONT0CT!J9+TONTNOV20!J9+TONTDEC20!J9 -> 0 | G9: =TONTNOV!N9+TONTDEC!N9+TONTJANV!N9+TONTFEV!N9+TONTMARS!N9+TONTAVRIL!N9+TONTMAI!N9+TONTJUIN!N9+TONTJUIL!N9+TONTAOUT!N9+TONTSEPT!N9+TONT0CT!N9+TONTNOV20!N9+TONTDEC20!N9 -> 1365000 | H9: =TONTNOV!O9+TONTDEC!O9+TONTJANV!O9+TONTFEV!O9+TONTMARS!O9+TONTAVRIL!O9+TONTMAI!O9+TONTJUIN!O9+TONTJUIL!O9+TONTAOUT!O9+TONTSEPT!O9+TONT0CT!O9+TONTNOV20!O9+TONTDEC20!O9 -> 135000 | I9: 43912 | J9: =IF(G9=0,0,(H9-100000)) -> 35000
A10: AS201649 | B10: =VLOOKUP(A10,[1]LISTADHERENT!A$5:H$60,3,0) -> MBOGNING TUGMA GUY | C10: =TONTNOV!C10+TONTDEC!C10+TONTJANV!C10+TONTFEV!C10+TONTMARS!C10+TONTAVRIL!C10+TONTMAI!C10+TONTJUIN!C10+TONTJUIL!C10+TONTAOUT!C10+TONTSEPT!C10+TONT0CT!C10+TONTNOV20!C10+TONTDEC20!C10 -> 1200000 | D10: =TONTNOV!F10+TONTDEC!F10+TONTJANV!F10+TONTFEV!F10+TONTMARS!F10+TONTAVRIL!F10+TONTMAI!F10+TONTJUIN!F10+TONTJUIL!F10+TONTAOUT!F10+TONTSEPT!F10+TONT0CT!F10+TONTNOV20!F10+TONTDEC20!F10 -> 759000 | E10: =TONTNOV!G10+TONTDEC!G10+TONTJANV!G10+TONTFEV!G10+TONTMARS!G10+TONTAVRIL!G10+TONTMAI!G10+TONTJUIN!G10+TONTJUIL!G10+TONTAOUT!G10+TONTSEPT!G10+TONT0CT!G10+TONTNOV20!G10+TONTDEC20!G10 -> 17500 | F10: =TONTNOV!J10+TONTDEC!J10+TONTJANV!J10+TONTFEV!J10+TONTMARS!J10+TONTAVRIL!J10+TONTMAI!J10+TONTJUIN!J10+TONTJUIL!J10+TONTAOUT!J10+TONTSEPT!J10+TONT0CT!J10+TONTNOV20!J10+TONTDEC20!J10 -> 776500 | G10: =TONTNOV!N10+TONTDEC!N10+TONTJANV!N10+TONTFEV!N10+TONTMARS!N10+TONTAVRIL!N10+TONTMAI!N10+TONTJUIN!N10+TONTJUIL!N10+TONTAOUT!N10+TONTSEPT!N10+TONT0CT!N10+TONTNOV20!N10+TONTDEC20!N10 -> 1270000 | H10: =TONTNOV!O10+TONTDEC!O10+TONTJANV!O10+TONTFEV!O10+TONTMARS!O10+TONTAVRIL!O10+TONTMAI!O10+TONTJUIN!O10+TONTJUIL!O10+TONTAOUT!O10+TONTSEPT!O10+TONT0CT!O10+TONTNOV20!O10+TONTDEC20!O10 -> 230000 | I10: 43849 | J10: =IF(G10=0,0,(H10-100000)) -> 130000
A11: AS201649 | B11: =VLOOKUP(A11,[1]LISTADHERENT!A$5:H$60,3,0) -> MBOGNING TUGMA GUY | C11: =TONTNOV!C11+TONTDEC!C11+TONTJANV!C11+TONTFEV!C11+TONTMARS!C11+TONTAVRIL!C11+TONTMAI!C11+TONTJUIN!C11+TONTJUIL!C11+TONTAOUT!C11+TONTSEPT!C11+TONT0CT!C11+TONTNOV20!C11+TONTDEC20!C11 -> 1200000 | D11: =TONTNOV!F11+TONTDEC!F11+TONTJANV!F11+TONTFEV!F11+TONTMARS!F11+TONTAVRIL!F11+TONTMAI!F11+TONTJUIN!F11+TONTJUIL!F11+TONTAOUT!F11+TONTSEPT!F11+TONT0CT!F11+TONTNOV20!F11+TONTDEC20!F11 -> 0 | E11: =TONTNOV!G11+TONTDEC!G11+TONTJANV!G11+TONTFEV!G11+TONTMARS!G11+TONTAVRIL!G11+TONTMAI!G11+TONTJUIN!G11+TONTJUIL!G11+TONTAOUT!G11+TONTSEPT!G11+TONT0CT!G11+TONTNOV20!G11+TONTDEC20!G11 -> 0 | F11: =TONTNOV!J11+TONTDEC!J11+TONTJANV!J11+TONTFEV!J11+TONTMARS!J11+TONTAVRIL!J11+TONTMAI!J11+TONTJUIN!J11+TONTJUIL!J11+TONTAOUT!J11+TONTSEPT!J11+TONT0CT!J11+TONTNOV20!J11+TONTDEC20!J11 -> 0 | G11: =TONTNOV!N11+TONTDEC!N11+TONTJANV!N11+TONTFEV!N11+TONTMARS!N11+TONTAVRIL!N11+TONTMAI!N11+TONTJUIN!N11+TONTJUIL!N11+TONTAOUT!N11+TONTSEPT!N11+TONT0CT!N11+TONTNOV20!N11+TONTDEC20!N11 -> 1255000 | H11: =TONTNOV!O11+TONTDEC!O11+TONTJANV!O11+TONTFEV!O11+TONTMARS!O11+TONTAVRIL!O11+TONTMAI!O11+TONTJUIN!O11+TONTJUIL!O11+TONTAOUT!O11+TONTSEPT!O11+TONT0CT!O11+TONTNOV20!O11+TONTDEC20!O11 -> 245000 | I11: 44031 | J11: =IF(G11=0,0,(H11-100000)) -> 145000
A12: AS201639 | B12: =VLOOKUP(A12,[1]LISTADHERENT!A$5:H$60,3,0) -> NANGUEN MARTIN | C12: =TONTNOV!C12+TONTDEC!C12+TONTJANV!C12+TONTFEV!C12+TONTMARS!C12+TONTAVRIL!C12+TONTMAI!C12+TONTJUIN!C12+TONTJUIL!C12+TONTAOUT!C12+TONTSEPT!C12+TONT0CT!C12+TONTNOV20!C12+TONTDEC20!C12 -> 1200000 | D12: =TONTNOV!F12+TONTDEC!F12+TONTJANV!F12+TONTFEV!F12+TONTMARS!F12+TONTAVRIL!F12+TONTMAI!F12+TONTJUIN!F12+TONTJUIL!F12+TONTAOUT!F12+TONTSEPT!F12+TONT0CT!F12+TONTNOV20!F12+TONTDEC20!F12 -> 0 | E12: =TONTNOV!G12+TONTDEC!G12+TONTJANV!G12+TONTFEV!G12+TONTMARS!G12+TONTAVRIL!G12+TONTMAI!G12+TONTJUIN!G12+TONTJUIL!G12+TONTAOUT!G12+TONTSEPT!G12+TONT0CT!G12+TONTNOV20!G12+TONTDEC20!G12 -> 0 | F12: =TONTNOV!J12+TONTDEC!J12+TONTJANV!J12+TONTFEV!J12+TONTMARS!J12+TONTAVRIL!J12+TONTMAI!J12+TONTJUIN!J12+TONTJUIL!J12+TONTAOUT!J12+TONTSEPT!J12+TONT0CT!J12+TONTNOV20!J12+TONTDEC20!J12 -> 0 | G12: =TONTNOV!N12+TONTDEC!N12+TONTJANV!N12+TONTFEV!N12+TONTMARS!N12+TONTAVRIL!N12+TONTMAI!N12+TONTJUIN!N12+TONTJUIL!N12+TONTAOUT!N12+TONTSEPT!N12+TONT0CT!N12+TONTNOV20!N12+TONTDEC20!N12 -> 1390000 | H12: =TONTNOV!O12+TONTDEC!O12+TONTJANV!O12+TONTFEV!O12+TONTMARS!O12+TONTAVRIL!O12+TONTMAI!O12+TONTJUIN!O12+TONTJUIL!O12+TONTAOUT!O12+TONTSEPT!O12+TONT0CT!O12+TONTNOV20!O12+TONTDEC20!O12 -> 110000 | I12: 44122 | J12: =IF(G12=0,0,(H12-100000)) -> 10000
A13: AS201622 | B13: =VLOOKUP(A13,[1]LISTADHERENT!A$5:H$60,3,0) -> NDJOMO ETIENNE | C13: =TONTNOV!C13+TONTDEC!C13+TONTJANV!C13+TONTFEV!C13+TONTMARS!C13+TONTAVRIL!C13+TONTMAI!C13+TONTJUIN!C13+TONTJUIL!C13+TONTAOUT!C13+TONTSEPT!C13+TONT0CT!C13+TONTNOV20!C13+TONTDEC20!C13 -> 1200000 | D13: =TONTNOV!F13+TONTDEC!F13+TONTJANV!F13+TONTFEV!F13+TONTMARS!F13+TONTAVRIL!F13+TONTMAI!F13+TONTJUIN!F13+TONTJUIL!F13+TONTAOUT!F13+TONTSEPT!F13+TONT0CT!F13+TONTNOV20!F13+TONTDEC20!F13 -> 526000 | E13: =TONTNOV!G13+TONTDEC!G13+TONTJANV!G13+TONTFEV!G13+TONTMARS!G13+TONTAVRIL!G13+TONTMAI!G13+TONTJUIN!G13+TONTJUIL!G13+TONTAOUT!G13+TONTSEPT!G13+TONT0CT!G13+TONTNOV20!G13+TONTDEC20!G13 -> 7500 | F13: =TONTNOV!J13+TONTDEC!J13+TONTJANV!J13+TONTFEV!J13+TONTMARS!J13+TONTAVRIL!J13+TONTMAI!J13+TONTJUIN!J13+TONTJUIL!J13+TONTAOUT!J13+TONTSEPT!J13+TONT0CT!J13+TONTNOV20!J13+TONTDEC20!J13 -> 533500 | G13: =TONTNOV!N13+TONTDEC!N13+TONTJANV!N13+TONTFEV!N13+TONTMARS!N13+TONTAVRIL!N13+TONTMAI!N13+TONTJUIN!N13+TONTJUIL!N13+TONTAOUT!N13+TONTSEPT!N13+TONT0CT!N13+TONTNOV20!N13+TONTDEC20!N13 -> 1400000 | H13: =TONTNOV!O13+TONTDEC!O13+TONTJANV!O13+TONTFEV!O13+TONTMARS!O13+TONTAVRIL!O13+TONTMAI!O13+TONTJUIN!O13+TONTJUIL!O13+TONTAOUT!O13+TONTSEPT!O13+TONT0CT!O13+TONTNOV20!O13+TONTDEC20!O13 -> 100000 | I13: 43940 | J13: =IF(G13=0,0,(H13-100000)) -> 0
A14: AS201624 | B14: =VLOOKUP(A14,[1]LISTADHERENT!A$5:H$60,3,0) -> NGONDIEP CLAUDE | C14: =TONTNOV!C14+TONTDEC!C14+TONTJANV!C14+TONTFEV!C14+TONTMARS!C14+TONTAVRIL!C14+TONTMAI!C14+TONTJUIN!C14+TONTJUIL!C14+TONTAOUT!C14+TONTSEPT!C14+TONT0CT!C14+TONTNOV20!C14+TONTDEC20!C14 -> 1200000 | D14: =TONTNOV!F14+TONTDEC!F14+TONTJANV!F14+TONTFEV!F14+TONTMARS!F14+TONTAVRIL!F14+TONTMAI!F14+TONTJUIN!F14+TONTJUIL!F14+TONTAOUT!F14+TONTSEPT!F14+TONT0CT!F14+TONTNOV20!F14+TONTDEC20!F14 -> 99500 | E14: =TONTNOV!G14+TONTDEC!G14+TONTJANV!G14+TONTFEV!G14+TONTMARS!G14+TONTAVRIL!G14+TONTMAI!G14+TONTJUIN!G14+TONTJUIL!G14+TONTAOUT!G14+TONTSEPT!G14+TONT0CT!G14+TONTNOV20!G14+TONTDEC20!G14 -> 4000 | F14: =TONTNOV!J14+TONTDEC!J14+TONTJANV!J14+TONTFEV!J14+TONTMARS!J14+TONTAVRIL!J14+TONTMAI!J14+TONTJUIN!J14+TONTJUIL!J14+TONTAOUT!J14+TONTSEPT!J14+TONT0CT!J14+TONTNOV20!J14+TONTDEC20!J14 -> 103500 | G14: =TONTNOV!N14+TONTDEC!N14+TONTJANV!N14+TONTFEV!N14+TONTMARS!N14+TONTAVRIL!N14+TONTMAI!N14+TONTJUIN!N14+TONTJUIL!N14+TONTAOUT!N14+TONTSEPT!N14+TONT0CT!N14+TONTNOV20!N14+TONTDEC20!N14 -> 1370000 | H14: =TONTNOV!O14+TONTDEC!O14+TONTJANV!O14+TONTFEV!O14+TONTMARS!O14+TONTAVRIL!O14+TONTMAI!O14+TONTJUIN!O14+TONTJUIL!O14+TONTAOUT!O14+TONTSEPT!O14+TONT0CT!O14+TONTNOV20!O14+TONTDEC20!O14 -> 130000 | I14: 43968 | J14: =IF(G14=0,0,(H14-100000)) -> 30000
A15: AS201614 | B15: =VLOOKUP(A15,[1]LISTADHERENT!A$5:H$60,3,0) -> NKEHE DAVID | C15: =TONTNOV!C15+TONTDEC!C15+TONTJANV!C15+TONTFEV!C15+TONTMARS!C15+TONTAVRIL!C15+TONTMAI!C15+TONTJUIN!C15+TONTJUIL!C15+TONTAOUT!C15+TONTSEPT!C15+TONT0CT!C15+TONTNOV20!C15+TONTDEC20!C15 -> 700000 | D15: =TONTNOV!F15+TONTDEC!F15+TONTJANV!F15+TONTFEV!F15+TONTMARS!F15+TONTAVRIL!F15+TONTMAI!F15+TONTJUIN!F15+TONTJUIL!F15+TONTAOUT!F15+TONTSEPT!F15+TONT0CT!F15+TONTNOV20!F15+TONTDEC20!F15 -> 2133500 | E15: =TONTNOV!G15+TONTDEC!G15+TONTJANV!G15+TONTFEV!G15+TONTMARS!G15+TONTAVRIL!G15+TONTMAI!G15+TONTJUIN!G15+TONTJUIL!G15+TONTAOUT!G15+TONTSEPT!G15+TONT0CT!G15+TONTNOV20!G15+TONTDEC20!G15 -> 22000 | F15: =TONTNOV!J15+TONTDEC!J15+TONTJANV!J15+TONTFEV!J15+TONTMARS!J15+TONTAVRIL!J15+TONTMAI!J15+TONTJUIN!J15+TONTJUIL!J15+TONTAOUT!J15+TONTSEPT!J15+TONT0CT!J15+TONTNOV20!J15+TONTDEC20!J15 -> 2155500 | G15: =TONTNOV!N15+TONTDEC!N15+TONTJANV!N15+TONTFEV!N15+TONTMARS!N15+TONTAVRIL!N15+TONTMAI!N15+TONTJUIN!N15+TONTJUIL!N15+TONTAOUT!N15+TONTSEPT!N15+TONT0CT!N15+TONTNOV20!N15+TONTDEC20!N15 -> 1350000 | H15: =TONTNOV!O15+TONTDEC!O15+TONTJANV!O15+TONTFEV!O15+TONTMARS!O15+TONTAVRIL!O15+TONTMAI!O15+TONTJUIN!O15+TONTJUIL!O15+TONTAOUT!O15+TONTSEPT!O15+TONT0CT!O15+TONTNOV20!O15+TONTDEC20!O15 -> 150000 | I15: 43793 | J15: =IF(G15=0,0,(H15-100000)) -> 50000
A16: AS201629 | B16: =VLOOKUP(A16,[1]LISTADHERENT!A$5:H$60,3,0) -> NKEPSEU DIEUDONNE | C16: =TONTNOV!C16+TONTDEC!C16+TONTJANV!C16+TONTFEV!C16+TONTMARS!C16+TONTAVRIL!C16+TONTMAI!C16+TONTJUIN!C16+TONTJUIL!C16+TONTAOUT!C16+TONTSEPT!C16+TONT0CT!C16+TONTNOV20!C16+TONTDEC20!C16 -> 1200000 | D16: =TONTNOV!F16+TONTDEC!F16+TONTJANV!F16+TONTFEV!F16+TONTMARS!F16+TONTAVRIL!F16+TONTMAI!F16+TONTJUIN!F16+TONTJUIL!F16+TONTAOUT!F16+TONTSEPT!F16+TONT0CT!F16+TONTNOV20!F16+TONTDEC20!F16 -> 400000 | E16: =TONTNOV!G16+TONTDEC!G16+TONTJANV!G16+TONTFEV!G16+TONTMARS!G16+TONTAVRIL!G16+TONTMAI!G16+TONTJUIN!G16+TONTJUIL!G16+TONTAOUT!G16+TONTSEPT!G16+TONT0CT!G16+TONTNOV20!G16+TONTDEC20!G16 -> 6000 | F16: =TONTNOV!J16+TONTDEC!J16+TONTJANV!J16+TONTFEV!J16+TONTMARS!J16+TONTAVRIL!J16+TONTMAI!J16+TONTJUIN!J16+TONTJUIL!J16+TONTAOUT!J16+TONTSEPT!J16+TONT0CT!J16+TONTNOV20!J16+TONTDEC20!J16 -> 406000 | G16: =TONTNOV!N16+TONTDEC!N16+TONTJANV!N16+TONTFEV!N16+TONTMARS!N16+TONTAVRIL!N16+TONTMAI!N16+TONTJUIN!N16+TONTJUIL!N16+TONTAOUT!N16+TONTSEPT!N16+TONT0CT!N16+TONTNOV20!N16+TONTDEC20!N16 -> 1400000 | H16: =TONTNOV!O16+TONTDEC!O16+TONTJANV!O16+TONTFEV!O16+TONTMARS!O16+TONTAVRIL!O16+TONTMAI!O16+TONTJUIN!O16+TONTJUIL!O16+TONTAOUT!O16+TONTSEPT!O16+TONT0CT!O16+TONTNOV20!O16+TONTDEC20!O16 -> 100000 | I16: 43877 | J16: =IF(G16=0,0,(H16-100000)) -> 0
A17: AS201636 | B17: =VLOOKUP(A17,[1]LISTADHERENT!A$5:H$60,3,0) -> SIMO FONGANG ERIC | C17: =TONTNOV!C17+TONTDEC!C17+TONTJANV!C17+TONTFEV!C17+TONTMARS!C17+TONTAVRIL!C17+TONTMAI!C17+TONTJUIN!C17+TONTJUIL!C17+TONTAOUT!C17+TONTSEPT!C17+TONT0CT!C17+TONTNOV20!C17+TONTDEC20!C17 -> 1200000 | D17: =TONTNOV!F17+TONTDEC!F17+TONTJANV!F17+TONTFEV!F17+TONTMARS!F17+TONTAVRIL!F17+TONTMAI!F17+TONTJUIN!F17+TONTJUIL!F17+TONTAOUT!F17+TONTSEPT!F17+TONT0CT!F17+TONTNOV20!F17+TONTDEC20!F17 -> 1281000 | E17: =TONTNOV!G17+TONTDEC!G17+TONTJANV!G17+TONTFEV!G17+TONTMARS!G17+TONTAVRIL!G17+TONTMAI!G17+TONTJUIN!G17+TONTJUIL!G17+TONTAOUT!G17+TONTSEPT!G17+TONT0CT!G17+TONTNOV20!G17+TONTDEC20!G17 -> 71500 | F17: =TONTNOV!J17+TONTDEC!J17+TONTJANV!J17+TONTFEV!J17+TONTMARS!J17+TONTAVRIL!J17+TONTMAI!J17+TONTJUIN!J17+TONTJUIL!J17+TONTAOUT!J17+TONTSEPT!J17+TONT0CT!J17+TONTNOV20!J17+TONTDEC20!J17 -> 1585500 | G17: =TONTNOV!N17+TONTDEC!N17+TONTJANV!N17+TONTFEV!N17+TONTMARS!N17+TONTAVRIL!N17+TONTMAI!N17+TONTJUIN!N17+TONTJUIL!N17+TONTAOUT!N17+TONTSEPT!N17+TONT0CT!N17+TONTNOV20!N17+TONTDEC20!N17 -> 1255000 | H17: =TONTNOV!O17+TONTDEC!O17+TONTJANV!O17+TONTFEV!O17+TONTMARS!O17+TONTAVRIL!O17+TONTMAI!O17+TONTJUIN!O17+TONTJUIL!O17+TONTAOUT!O17+TONTSEPT!O17+TONT0CT!O17+TONTNOV20!O17+TONTDEC20!O17 -> 245000 | I17: 43819 | J17: =IF(G17=0,0,(H17-100000)) -> 145000
A18: AS201636 | B18: =VLOOKUP(A18,[1]LISTADHERENT!A$5:H$60,3,0) -> SIMO FONGANG ERIC | C18: =TONTNOV!C18+TONTDEC!C18+TONTJANV!C18+TONTFEV!C18+TONTMARS!C18+TONTAVRIL!C18+TONTMAI!C18+TONTJUIN!C18+TONTJUIL!C18+TONTAOUT!C18+TONTSEPT!C18+TONT0CT!C18+TONTNOV20!C18+TONTDEC20!C18 -> 1200000 | D18: =TONTNOV!F18+TONTDEC!F18+TONTJANV!F18+TONTFEV!F18+TONTMARS!F18+TONTAVRIL!F18+TONTMAI!F18+TONTJUIN!F18+TONTJUIL!F18+TONTAOUT!F18+TONTSEPT!F18+TONT0CT!F18+TONTNOV20!F18+TONTDEC20!F18 -> 0 | E18: =TONTNOV!G18+TONTDEC!G18+TONTJANV!G18+TONTFEV!G18+TONTMARS!G18+TONTAVRIL!G18+TONTMAI!G18+TONTJUIN!G18+TONTJUIL!G18+TONTAOUT!G18+TONTSEPT!G18+TONT0CT!G18+TONTNOV20!G18+TONTDEC20!G18 -> 0 | F18: =TONTNOV!J18+TONTDEC!J18+TONTJANV!J18+TONTFEV!J18+TONTMARS!J18+TONTAVRIL!J18+TONTMAI!J18+TONTJUIN!J18+TONTJUIL!J18+TONTAOUT!J18+TONTSEPT!J18+TONT0CT!J18+TONTNOV20!J18+TONTDEC20!J18 -> 0 | G18: =TONTNOV!N18+TONTDEC!N18+TONTJANV!N18+TONTFEV!N18+TONTMARS!N18+TONTAVRIL!N18+TONTMAI!N18+TONTJUIN!N18+TONTJUIL!N18+TONTAOUT!N18+TONTSEPT!N18+TONT0CT!N18+TONTNOV20!N18+TONTDEC20!N18 -> 1254000 | H18: =TONTNOV!O18+TONTDEC!O18+TONTJANV!O18+TONTFEV!O18+TONTMARS!O18+TONTAVRIL!O18+TONTMAI!O18+TONTJUIN!O18+TONTJUIL!O18+TONTAOUT!O18+TONTSEPT!O18+TONT0CT!O18+TONTNOV20!O18+TONTDEC20!O18 -> 246000 | I18: 44031 | J18: =IF(G18=0,0,(H18-100000)) -> 146000
A19: AS201637 | B19: =VLOOKUP(A19,[1]LISTADHERENT!A$5:H$60,3,0) -> SIME MATHIEU | C19: =TONTNOV!C19+TONTDEC!C19+TONTJANV!C19+TONTFEV!C19+TONTMARS!C19+TONTAVRIL!C19+TONTMAI!C19+TONTJUIN!C19+TONTJUIL!C19+TONTAOUT!C19+TONTSEPT!C19+TONT0CT!C19+TONTNOV20!C19+TONTDEC20!C19 -> 1200000 | D19: =TONTNOV!F19+TONTDEC!F19+TONTJANV!F19+TONTFEV!F19+TONTMARS!F19+TONTAVRIL!F19+TONTMAI!F19+TONTJUIN!F19+TONTJUIL!F19+TONTAOUT!F19+TONTSEPT!F19+TONT0CT!F19+TONTNOV20!F19+TONTDEC20!F19 -> 408000 | E19: =TONTNOV!G19+TONTDEC!G19+TONTJANV!G19+TONTFEV!G19+TONTMARS!G19+TONTAVRIL!G19+TONTMAI!G19+TONTJUIN!G19+TONTJUIL!G19+TONTAOUT!G19+TONTSEPT!G19+TONT0CT!G19+TONTNOV20!G19+TONTDEC20!G19 -> 8000 | F19: =TONTNOV!J19+TONTDEC!J19+TONTJANV!J19+TONTFEV!J19+TONTMARS!J19+TONTAVRIL!J19+TONTMAI!J19+TONTJUIN!J19+TONTJUIL!J19+TONTAOUT!J19+TONTSEPT!J19+TONT0CT!J19+TONTNOV20!J19+TONTDEC20!J19 -> 416000 | G19: =TONTNOV!N19+TONTDEC!N19+TONTJANV!N19+TONTFEV!N19+TONTMARS!N19+TONTAVRIL!N19+TONTMAI!N19+TONTJUIN!N19+TONTJUIL!N19+TONTAOUT!N19+TONTSEPT!N19+TONT0CT!N19+TONTNOV20!N19+TONTDEC20!N19 -> 1340000 | H19: =TONTNOV!O19+TONTDEC!O19+TONTJANV!O19+TONTFEV!O19+TONTMARS!O19+TONTAVRIL!O19+TONTMAI!O19+TONTJUIN!O19+TONTJUIL!O19+TONTAOUT!O19+TONTSEPT!O19+TONT0CT!O19+TONTNOV20!O19+TONTDEC20!O19 -> 160000 | I19: 44059 | J19: =IF(G19=0,0,(H19-100000)) -> 60000
A20: AS201637 | B20: =VLOOKUP(A20,[1]LISTADHERENT!A$5:H$60,3,0) -> SIME MATHIEU | C20: =TONTNOV!C20+TONTDEC!C20+TONTJANV!C20+TONTFEV!C20+TONTMARS!C20+TONTAVRIL!C20+TONTMAI!C20+TONTJUIN!C20+TONTJUIL!C20+TONTAOUT!C20+TONTSEPT!C20+TONT0CT!C20+TONTNOV20!C20+TONTDEC20!C20 -> 1200000 | D20: =TONTNOV!F20+TONTDEC!F20+TONTJANV!F20+TONTFEV!F20+TONTMARS!F20+TONTAVRIL!F20+TONTMAI!F20+TONTJUIN!F20+TONTJUIL!F20+TONTAOUT!F20+TONTSEPT!F20+TONT0CT!F20+TONTNOV20!F20+TONTDEC20!F20 -> 0 | E20: =TONTNOV!G20+TONTDEC!G20+TONTJANV!G20+TONTFEV!G20+TONTMARS!G20+TONTAVRIL!G20+TONTMAI!G20+TONTJUIN!G20+TONTJUIL!G20+TONTAOUT!G20+TONTSEPT!G20+TONT0CT!G20+TONTNOV20!G20+TONTDEC20!G20 -> 0 | F20: =TONTNOV!J20+TONTDEC!J20+TONTJANV!J20+TONTFEV!J20+TONTMARS!J20+TONTAVRIL!J20+TONTMAI!J20+TONTJUIN!J20+TONTJUIL!J20+TONTAOUT!J20+TONTSEPT!J20+TONT0CT!J20+TONTNOV20!J20+TONTDEC20!J20 -> 0 | G20: =TONTNOV!N20+TONTDEC!N20+TONTJANV!N20+TONTFEV!N20+TONTMARS!N20+TONTAVRIL!N20+TONTMAI!N20+TONTJUIN!N20+TONTJUIL!N20+TONTAOUT!N20+TONTSEPT!N20+TONT0CT!N20+TONTNOV20!N20+TONTDEC20!N20 -> 0 | H20: =TONTNOV!O20+TONTDEC!O20+TONTJANV!O20+TONTFEV!O20+TONTMARS!O20+TONTAVRIL!O20+TONTMAI!O20+TONTJUIN!O20+TONTJUIL!O20+TONTAOUT!O20+TONTSEPT!O20+TONT0CT!O20+TONTNOV20!O20+TONTDEC20!O20 -> 0 | J20: =IF(G20=0,0,(H20-100000)) -> 0
A21: AS201641 | B21: =VLOOKUP(A21,[1]LISTADHERENT!A$5:H$60,3,0) -> TCHOUAMOU MATHIEU | C21: =TONTNOV!C21+TONTDEC!C21+TONTJANV!C21+TONTFEV!C21+TONTMARS!C21+TONTAVRIL!C21+TONTMAI!C21+TONTJUIN!C21+TONTJUIL!C21+TONTAOUT!C21+TONTSEPT!C21+TONT0CT!C21+TONTNOV20!C21+TONTDEC20!C21 -> 1200000 | D21: =TONTNOV!F21+TONTDEC!F21+TONTJANV!F21+TONTFEV!F21+TONTMARS!F21+TONTAVRIL!F21+TONTMAI!F21+TONTJUIN!F21+TONTJUIL!F21+TONTAOUT!F21+TONTSEPT!F21+TONT0CT!F21+TONTNOV20!F21+TONTDEC20!F21 -> 638000 | E21: =TONTNOV!G21+TONTDEC!G21+TONTJANV!G21+TONTFEV!G21+TONTMARS!G21+TONTAVRIL!G21+TONTMAI!G21+TONTJUIN!G21+TONTJUIL!G21+TONTAOUT!G21+TONTSEPT!G21+TONT0CT!G21+TONTNOV20!G21+TONTDEC20!G21 -> 8500 | F21: =TONTNOV!J21+TONTDEC!J21+TONTJANV!J21+TONTFEV!J21+TONTMARS!J21+TONTAVRIL!J21+TONTMAI!J21+TONTJUIN!J21+TONTJUIL!J21+TONTAOUT!J21+TONTSEPT!J21+TONT0CT!J21+TONTNOV20!J21+TONTDEC20!J21 -> 646500 | G21: =TONTNOV!N21+TONTDEC!N21+TONTJANV!N21+TONTFEV!N21+TONTMARS!N21+TONTAVRIL!N21+TONTMAI!N21+TONTJUIN!N21+TONTJUIL!N21+TONTAOUT!N21+TONTSEPT!N21+TONT0CT!N21+TONTNOV20!N21+TONTDEC20!N21 -> 1400000 | H21: =TONTNOV!O21+TONTDEC!O21+TONTJANV!O21+TONTFEV!O21+TONTMARS!O21+TONTAVRIL!O21+TONTMAI!O21+TONTJUIN!O21+TONTJUIL!O21+TONTAOUT!O21+TONTSEPT!O21+TONT0CT!O21+TONTNOV20!O21+TONTDEC20!O21 -> 100000 | I21: 44094 | J21: =IF(G21=0,0,(H21-100000)) -> 0
A22: AS201644 | B22: =VLOOKUP(A22,[1]LISTADHERENT!A$5:H$60,3,0) -> TIEYAM ERNEST | C22: =TONTNOV!C22+TONTDEC!C22+TONTJANV!C22+TONTFEV!C22+TONTMARS!C22+TONTAVRIL!C22+TONTMAI!C22+TONTJUIN!C22+TONTJUIL!C22+TONTAOUT!C22+TONTSEPT!C22+TONT0CT!C22+TONTNOV20!C22+TONTDEC20!C22 -> 1100000 | D22: =TONTNOV!F22+TONTDEC!F22+TONTJANV!F22+TONTFEV!F22+TONTMARS!F22+TONTAVRIL!F22+TONTMAI!F22+TONTJUIN!F22+TONTJUIL!F22+TONTAOUT!F22+TONTSEPT!F22+TONT0CT!F22+TONTNOV20!F22+TONTDEC20!F22 -> 1630000 | E22: =TONTNOV!G22+TONTDEC!G22+TONTJANV!G22+TONTFEV!G22+TONTMARS!G22+TONTAVRIL!G22+TONTMAI!G22+TONTJUIN!G22+TONTJUIL!G22+TONTAOUT!G22+TONTSEPT!G22+TONT0CT!G22+TONTNOV20!G22+TONTDEC20!G22 -> 62000 | F22: =TONTNOV!J22+TONTDEC!J22+TONTJANV!J22+TONTFEV!J22+TONTMARS!J22+TONTAVRIL!J22+TONTMAI!J22+TONTJUIN!J22+TONTJUIL!J22+TONTAOUT!J22+TONTSEPT!J22+TONT0CT!J22+TONTNOV20!J22+TONTDEC20!J22 -> 1898000 | G22: =TONTNOV!N22+TONTDEC!N22+TONTJANV!N22+TONTFEV!N22+TONTMARS!N22+TONTAVRIL!N22+TONTMAI!N22+TONTJUIN!N22+TONTJUIL!N22+TONTAOUT!N22+TONTSEPT!N22+TONT0CT!N22+TONTNOV20!N22+TONTDEC20!N22 -> 1305000 | H22: =TONTNOV!O22+TONTDEC!O22+TONTJANV!O22+TONTFEV!O22+TONTMARS!O22+TONTAVRIL!O22+TONTMAI!O22+TONTJUIN!O22+TONTJUIL!O22+TONTAOUT!O22+TONTSEPT!O22+TONT0CT!O22+TONTNOV20!O22+TONTDEC20!O22 -> 195000 | I22: 44003 | J22: =IF(G22=0,0,(H22-100000)) -> 95000
A23: AS201647 | B23: =VLOOKUP(A23,[1]LISTADHERENT!A$5:H$60,3,0) -> YOUMBI EMMANUEL | C23: =TONTNOV!C23+TONTDEC!C23+TONTJANV!C23+TONTFEV!C23+TONTMARS!C23+TONTAVRIL!C23+TONTMAI!C23+TONTJUIN!C23+TONTJUIL!C23+TONTAOUT!C23+TONTSEPT!C23+TONT0CT!C23+TONTNOV20!C23+TONTDEC20!C23 -> 1200000 | D23: =TONTNOV!F23+TONTDEC!F23+TONTJANV!F23+TONTFEV!F23+TONTMARS!F23+TONTAVRIL!F23+TONTMAI!F23+TONTJUIN!F23+TONTJUIL!F23+TONTAOUT!F23+TONTSEPT!F23+TONT0CT!F23+TONTNOV20!F23+TONTDEC20!F23 -> 0 | E23: =TONTNOV!G23+TONTDEC!G23+TONTJANV!G23+TONTFEV!G23+TONTMARS!G23+TONTAVRIL!G23+TONTMAI!G23+TONTJUIN!G23+TONTJUIL!G23+TONTAOUT!G23+TONTSEPT!G23+TONT0CT!G23+TONTNOV20!G23+TONTDEC20!G23 -> 0 | F23: =TONTNOV!J23+TONTDEC!J23+TONTJANV!J23+TONTFEV!J23+TONTMARS!J23+TONTAVRIL!J23+TONTMAI!J23+TONTJUIN!J23+TONTJUIL!J23+TONTAOUT!J23+TONTSEPT!J23+TONT0CT!J23+TONTNOV20!J23+TONTDEC20!J23 -> 0 | G23: =TONTNOV!N23+TONTDEC!N23+TONTJANV!N23+TONTFEV!N23+TONTMARS!N23+TONTAVRIL!N23+TONTMAI!N23+TONTJUIN!N23+TONTJUIL!N23+TONTAOUT!N23+TONTSEPT!N23+TONT0CT!N23+TONTNOV20!N23+TONTDEC20!N23 -> 0 | H23: =TONTNOV!O23+TONTDEC!O23+TONTJANV!O23+TONTFEV!O23+TONTMARS!O23+TONTAVRIL!O23+TONTMAI!O23+TONTJUIN!O23+TONTJUIL!O23+TONTAOUT!O23+TONTSEPT!O23+TONT0CT!O23+TONTNOV20!O23+TONTDEC20!O23 -> 0 | J23: =IF(G23=0,0,(H23-100000)) -> 0
A25: TOTAL | C25: =SUM(C6:C24) -> 21000000 | D25: =SUM(D6:D24) -> 9459000 | E25: =SUM(E6:E24) -> 251500 | F25: =SUM(F6:F24) -> 10149500 | G25: =SUM(G6:G24) -> 20004000 | H25: =SUM(H6:H24) -> 2496000 | J25: =SUM(J6:J24) -> 996000
F28: EN COMPTE | G28: =(G25+H25)-C25 -> 1500000
F30: RESTE | G30: =TONTNOV!L30+TONTDEC!L30+TONTJANV!L30+TONTFEV!L30+TONTMARS!L30+TONTAVRIL!L30+TONTMAI!L30+TONTJUIN!L30+TONTJUIL!L30 -> -1528500
F32: ECHEC TONTINE | G32: =TONTJUIN!L32+TONTJUIL!L32 -> 100000 | H32: NKEHEP 200000/TYAM 100000
F33: ECHEC REMB | G33: =+TONTMARS!N32+TONTJUIL!L33 -> 200000 | H33: NKEHEP 217000/TYAM 101500
