Workbook

Sheet BROUILLARD DE CAISSE 2023
B1: BROUILLARD DE CAISSE 15 JANVIER 2023
C3: EPARGNE | D3: F R | E3: F EX | F3: COLL | G3: T PRESENCE | I3: T 75 | K3: T 100 | M3: REMB PRÊT | N3: DEPOT | O3: PENALITE | P3: INTERET PRÊT | Q3: FOYER | R3: MUTUELLE | S3: TOTAL VERSE
G4: COTISE | H4: REMB | I4: COTISE | J4: REMB | K4: COTISE | L4: REMB | S4: CUMUL | T4: ESPECE | U4: BANQUE
A5: 0 | B5: ASELBY | K5: 100000 | S5: =+R5+Q5+P5+O5+N5+M5+L5+K5+J5+I5+H5+G5+F5+E5+D5+C5 -> 100000 | U5: =+S5-T5 -> 100000
A6: =+A5+1 -> 1 | B6: BOUTCHOUANG WILLIAM | C6: 9000 | D6: 1000 | E6: 1000 | F6: 4000 | G6: 25000 | I6: 75000 | S6: =+R6+Q6+P6+O6+N6+M6+L6+K6+J6+I6+H6+G6+F6+E6+D6+C6 -> 115000 | T6: 10000 | U6: =+S6-T6 -> 105000
A7: =+A6+1 -> 2 | B7: DJOMO JEAN PAUL | C7: 29000 | D7: 1000 | E7: 1000 | F7: 4000 | G7: 25000 | K7: 100000 | Q7: 140000 | S7: =+R7+Q7+P7+O7+N7+M7+L7+K7+J7+I7+H7+G7+F7+E7+D7+C7 -> 300000 | U7: =+S7-T7 -> 300000
A8: =+A7+1 -> 3 | B8: DJOMOU TCHANDA | C8: 9000 | D8: 1000 | E8: 1000 | F8: 4000 | G8: 25000 | S8: =+R8+Q8+P8+O8+N8+M8+L8+K8+J8+I8+H8+G8+F8+E8+D8+C8 -> 40000 | U8: =+S8-T8 -> 40000
A9: =+A8+1 -> 4 | B9: DJOUKWE NANGUEN GUY BLAISE | C9: 9000 | D9: 1000 | E9: 1000 | F9: 4000 | G9: 25000 | I9: 75000 | S9: =+R9+Q9+P9+O9+N9+M9+L9+K9+J9+I9+H9+G9+F9+E9+D9+C9 -> 115000 | U9: =+S9-T9 -> 115000
A10: =+A9+1 -> 5 | B10: DJUOMBESSY ANTOINE | C10: 14000 | D10: 1000 | E10: 1000 | F10: 4000 | G10: 25000 | I10: 75000 | K10: 200000 | S10: =+R10+Q10+P10+O10+N10+M10+L10+K10+J10+I10+H10+G10+F10+E10+D10+C10 -> 320000 | U10: =+S10-T10 -> 320000
A11: =+A10+1 -> 6 | B11: DOMOU FABIEN | C11: 9000 | D11: 1000 | E11: 1000 | F11: 4000 | G11: 25000 | S11: =+R11+Q11+P11+O11+N11+M11+L11+K11+J11+I11+H11+G11+F11+E11+D11+C11 -> 40000 | U11: =+S11-T11 -> 40000
A12: =+A11+1 -> 7 | B12: DONHOU DAVID | C12: 9000 | D12: 1000 | E12: 1000 | F12: 4000 | G12: 25000 | S12: =+R12+Q12+P12+O12+N12+M12+L12+K12+J12+I12+H12+G12+F12+E12+D12+C12 -> 40000 | U12: =+S12-T12 -> 40000
A13: =+A12+1 -> 8 | B13: FOTSO THOMAS | S13: =+R13+Q13+P13+O13+N13+M13+L13+K13+J13+I13+H13+G13+F13+E13+D13+C13 -> 0 | U13: =+S13-T13 -> 0
A14: =+A13+1 -> 9 | B14: HENGUE PAUL OMER | C14: 9000 | D14: 1000 | E14: 1000 | F14: 4000 | G14: 25000 | I14: 75000 | S14: =+R14+Q14+P14+O14+N14+M14+L14+K14+J14+I14+H14+G14+F14+E14+D14+C14 -> 115000 | U14: =+S14-T14 -> 115000
A15: =+A14+1 -> 10 | B15: HOTCHO BENJAMIN | C15: 44000 | D15: 1000 | E15: 1000 | F15: 4000 | G15: 25000 | I15: 75000 | K15: 100000 | S15: =+R15+Q15+P15+O15+N15+M15+L15+K15+J15+I15+H15+G15+F15+E15+D15+C15 -> 250000 | U15: =+S15-T15 -> 250000
A16: =+A15+1 -> 11 | B16: KOUAMOU MOISE | C16: 9000 | D16: 1000 | E16: 1000 | F16: 4000 | G16: 25000 | K16: 100000 | S16: =+R16+Q16+P16+O16+N16+M16+L16+K16+J16+I16+H16+G16+F16+E16+D16+C16 -> 140000 | U16: =+S16-T16 -> 140000
A17: =+A16+1 -> 12 | B17: KOUATCHO MESSACK | C17: 9000 | D17: 1000 | E17: 1000 | F17: 4000 | G17: 25000 | I17: 75000 | K17: 100000 | Q17: 70000 | S17: =+R17+Q17+P17+O17+N17+M17+L17+K17+J17+I17+H17+G17+F17+E17+D17+C17 -> 285000 | T17: 35000 | U17: =+S17-T17 -> 250000
A18: =+A17+1 -> 13 | B18: LOWE JEAN | C18: 9000 | D18: 1000 | E18: 1000 | F18: 4000 | G18: 25000 | S18: =+R18+Q18+P18+O18+N18+M18+L18+K18+J18+I18+H18+G18+F18+E18+D18+C18 -> 40000 | U18: =+S18-T18 -> 40000
A19: =+A18+1 -> 14 | B19: MBOGNING TUGMA GUY | C19: 9000 | D19: 1000 | E19: 1000 | F19: 4000 | G19: 25000 | I19: 75000 | K19: 100000 | S19: =+R19+Q19+P19+O19+N19+M19+L19+K19+J19+I19+H19+G19+F19+E19+D19+C19 -> 215000 | U19: =+S19-T19 -> 215000
A20: =+A19+1 -> 15 | B20: NANGUEN MARTIN | C20: 9000 | D20: 1000 | E20: 1000 | F20: 4000 | G20: 25000 | S20: =+R20+Q20+P20+O20+N20+M20+L20+K20+J20+I20+H20+G20+F20+E20+D20+C20 -> 40000 | U20: =+S20-T20 -> 40000
A21: =+A20+1 -> 16 | B21: NANKAM APPOLINAIRE | C21: 9000 | D21: 1000 | E21: 1000 | F21: 4000 | G21: 25000 | I21: 75000 | S21: =+R21+Q21+P21+O21+N21+M21+L21+K21+J21+I21+H21+G21+F21+E21+D21+C21 -> 115000 | U21: =+S21-T21 -> 115000
A22: =+A21+1 -> 17 | B22: NDJOMO ETIENNE | C22: 19000 | D22: 1000 | E22: 1000 | F22: 4000 | G22: 25000 | K22: 200000 | S22: =+R22+Q22+P22+O22+N22+M22+L22+K22+J22+I22+H22+G22+F22+E22+D22+C22 -> 250000 | U22: =+S22-T22 -> 250000
A23: =+A22+1 -> 18 | B23: NGONDIEP CLAUDE | C23: 9000 | D23: 1000 | E23: 1000 | F23: 4000 | G23: 25000 | I23: 75000 | K23: 100000 | S23: =+R23+Q23+P23+O23+N23+M23+L23+K23+J23+I23+H23+G23+F23+E23+D23+C23 -> 215000 | T23: 5000 | U23: =+S23-T23 -> 210000
A24: =+A23+1 -> 19 | B24: NGUIEMEGNI MATHIEU BLAISE | C24: 9000 | D24: 1000 | E24: 1000 | F24: 4000 | G24: 25000 | I24: 150000 | K24: 100000 | S24: =+R24+Q24+P24+O24+N24+M24+L24+K24+J24+I24+H24+G24+F24+E24+D24+C24 -> 290000 | T24: 10000 | U24: =+S24-T24 -> 280000
A25: =+A24+1 -> 20 | B25: NKAMGANG JUSTIN DEJOLIE | C25: 9000 | D25: 1000 | E25: 1000 | F25: 4000 | G25: 25000 | S25: =+R25+Q25+P25+O25+N25+M25+L25+K25+J25+I25+H25+G25+F25+E25+D25+C25 -> 40000 | T25: 40000 | U25: =+S25-T25 -> 0
A26: =+A25+1 -> 21 | B26: NKEHE DAVID | S26: =+R26+Q26+P26+O26+N26+M26+L26+K26+J26+I26+H26+G26+F26+E26+D26+C26 -> 0 | U26: =+S26-T26 -> 0
A27: =+A26+1 -> 22 | B27: NOUBE ETIENNE | C27: 9000 | D27: 1000 | E27: 1000 | F27: 4000 | G27: 25000 | N27: 25000 | S27: =+R27+Q27+P27+O27+N27+M27+L27+K27+J27+I27+H27+G27+F27+E27+D27+C27 -> 65000 | T27: 65000 | U27: =+S27-T27 -> 0
A28: =+A27+1 -> 23 | B28: PATEGO NJOSSU GUSTAVE | C28: 9000 | D28: 1000 | E28: 1000 | F28: 4000 | G28: 25000 | I28: 75000 | S28: =+R28+Q28+P28+O28+N28+M28+L28+K28+J28+I28+H28+G28+F28+E28+D28+C28 -> 115000 | U28: =+S28-T28 -> 115000
A29: =+A28+1 -> 24 | B29: SEUMOU POLYCARPE | C29: 9000 | D29: 1000 | E29: 1000 | F29: 4000 | G29: 25000 | N29: 25000 | S29: =+R29+Q29+P29+O29+N29+M29+L29+K29+J29+I29+H29+G29+F29+E29+D29+C29 -> 65000 | T29: 65000 | U29: =+S29-T29 -> 0
A30: =+A29+1 -> 25 | B30: SIME BRICE | C30: 9000 | D30: 1000 | E30: 1000 | F30: 4000 | G30: 25000 | I30: 75000 | S30: =+R30+Q30+P30+O30+N30+M30+L30+K30+J30+I30+H30+G30+F30+E30+D30+C30 -> 115000 | T30: 115000 | U30: =+S30-T30 -> 0
A31: =+A30+1 -> 26 | B31: SIMO FONGANG ERIC | S31: =+R31+Q31+P31+O31+N31+M31+L31+K31+J31+I31+H31+G31+F31+E31+D31+C31 -> 0 | U31: =+S31-T31 -> 0
A32: =+A31+1 -> 27 | B32: SIMO PIERRE | C32: 119000 | D32: 1000 | E32: 1000 | F32: 4000 | G32: 25000 | K32: 100000 | S32: =+R32+Q32+P32+O32+N32+M32+L32+K32+J32+I32+H32+G32+F32+E32+D32+C32 -> 250000 | U32: =+S32-T32 -> 250000
A33: =+A32+1 -> 28 | B33: TCHOUAMOU MATHIEU | C33: 9000 | D33: 1000 | E33: 1000 | F33: 4000 | G33: 25000 | I33: 75000 | S33: =+R33+Q33+P33+O33+N33+M33+L33+K33+J33+I33+H33+G33+F33+E33+D33+C33 -> 115000 | U33: =+S33-T33 -> 115000
A34: =+A33+1 -> 29 | B34: TCHOUTOU NANA CLAUDE | C34: 9000 | D34: 1000 | E34: 1000 | F34: 4000 | G34: 25000 | S34: =+R34+Q34+P34+O34+N34+M34+L34+K34+J34+I34+H34+G34+F34+E34+D34+C34 -> 40000 | T34: 40000 | U34: =+S34-T34 -> 0
A35: =+A34+1 -> 30 | B35: TIEYAM ERNEST | S35: =+R35+Q35+P35+O35+N35+M35+L35+K35+J35+I35+H35+G35+F35+E35+D35+C35 -> 0 | U35: =+S35-T35 -> 0
A36: =+A35+1 -> 31 | B36: YEPMOU JEAN JACQUES | C36: 9000 | D36: 1000 | E36: 1000 | F36: 4000 | G36: 25000 | S36: =+R36+Q36+P36+O36+N36+M36+L36+K36+J36+I36+H36+G36+F36+E36+D36+C36 -> 40000 | T36: 40000 | U36: =+S36-T36 -> 0
A37: =+A36+1 -> 32 | B37: YOUMBI EMMANUEL | C37: 9000 | D37: 1000 | E37: 1000 | F37: 4000 | G37: 25000 | I37: 150000 | K37: 100000 | S37: =+R37+Q37+P37+O37+N37+M37+L37+K37+J37+I37+H37+G37+F37+E37+D37+C37 -> 290000 | U37: =+S37-T37 -> 290000
A38: =+A37+1 -> 33 | B38: BAKOP ACHILLE | C38: 73000 | D38: 1000 | E38: 1000 | F38: 4000 | G38: 25000 | S38: =+R38+Q38+P38+O38+N38+M38+L38+K38+J38+I38+H38+G38+F38+E38+D38+C38 -> 104000 | T38: 104000 | U38: =+S38-T38 -> 0
A39: =+A38+1 -> 34 | B39: YANTCHOU GERVAIS | C39: 9000 | D39: 1000 | E39: 1000 | F39: 4000 | G39: 25000 | N39: 25000 | R39: 35000 | S39: =+R39+Q39+P39+O39+N39+M39+L39+K39+J39+I39+H39+G39+F39+E39+D39+C39 -> 100000 | T39: 100000 | U39: =+S39-T39 -> 0
A40: =+A39+1 -> 35 | S40: =+R40+Q40+P40+O40+N40+M40+L40+K40+J40+I40+H40+G40+F40+E40+D40+C40 -> 0 | U40: =+S40-T40 -> 0
A41: =+A40+1 -> 36 | S41: =+R41+Q41+P41+O41+N41+M41+L41+K41+J41+I41+H41+G41+F41+E41+D41+C41 -> 0 | U41: =+S41-T41 -> 0
A42: =+A41+1 -> 37 | S42: =+R42+Q42+P42+O42+N42+M42+L42+K42+J42+I42+H42+G42+F42+E42+D42+C42 -> 0 | U42: =+S42-T42 -> 0
A43: =+A42+1 -> 38 | S43: =+R43+Q43+P43+O43+N43+M43+L43+K43+J43+I43+H43+G43+F43+E43+D43+C43 -> 0 | U43: =+S43-T43 -> 0
A44: =+A43+1 -> 39 | S44: =+R44+Q44+P44+O44+N44+M44+L44+K44+J44+I44+H44+G44+F44+E44+D44+C44 -> 0 | U44: =+S44-T44 -> 0
A45: =+A44+1 -> 40 | S45: =+R45+Q45+P45+O45+N45+M45+L45+K45+J45+I45+H45+G45+F45+E45+D45+C45 -> 0 | U45: =+S45-T45 -> 0
A46: =+A45+1 -> 41 | S46: =+R46+Q46+P46+O46+N46+M46+L46+K46+J46+I46+H46+G46+F46+E46+D46+C46 -> 0 | U46: =+S46-T46 -> 0
C47: =SUM(C5:C46) -> 514000 | D47: =SUM(D5:D46) -> 30000 | E47: =SUM(E5:E46) -> 30000 | F47: =SUM(F5:F46) -> 120000 | G47: =SUM(G5:G46) -> 750000 | H47: =SUM(H5:H46) -> 0 | I47: =SUM(I6:I46) -> 1200000 | J47: =SUM(J5:J46) -> 0 | K47: =SUM(K5:K46) -> 1400000 | L47: =SUM(L5:L46) -> 0 | M47: =SUM(M5:M46) -> 0 | N47: =SUM(N5:N46) -> 75000 | O47: =SUM(O5:O46) -> 0 | P47: =SUM(P5:P46) -> 0 | Q47: =SUM(Q5:Q46) -> 210000 | ... U47: =SUM(U5:U46) -> 3735000
B48: BROUILLARD DE CAISSE 12 FEVRIER 2023
C50: EPARGNE | D50: F R | E50: F EX | F50: COLL | G50: T PRESENCE | I50: T75 | K50: T100 | M50: REMB PRÊT | N50: DEPOT | O50: PENALITE | P50: INTERET PRÊT | Q50: FOYER | S50: TOTAL VERSE
G51: COTISE | H51: REMB | I51: COTISE | J51: REMB | K51: COTISE | L51: REMB | S51: CUMUL | T51: ESPECE | U51: BANQUE
A52: 0 | B52: ASELBY | K52: 100000 | S52: =+R52+Q52+P52+O52+N52+M52+L52+K52+J52+I52+H52+G52+F52+E52+D52+C52 -> 100000 | U52: =+S52-T52 -> 100000
A53: =+A52+1 -> 1 | B53: BOUTCHOUANG WILLIAM | C53: 9000 | D53: 1000 | E53: 1000 | F53: 4000 | G53: 25000 | I53: 75000 | M53: 500000 | S53: =+R53+Q53+P53+O53+N53+M53+L53+K53+J53+I53+H53+G53+F53+E53+D53+C53 -> 615000 | U53: =+S53-T53 -> 615000
A54: =+A53+1 -> 2 | B54: DJOMO JEAN PAUL | C54: 17000 | D54: 1000 | E54: 1000 | F54: 4000 | G54: 25000 | K54: 100000 | L54: 52000 | S54: =+R54+Q54+P54+O54+N54+M54+L54+K54+J54+I54+H54+G54+F54+E54+D54+C54 -> 200000 | T54: 80000 | U54: =+S54-T54 -> 120000
A55: =+A54+1 -> 3 | B55: DJOMOU TCHANDA | C55: 9000 | D55: 1000 | E55: 1000 | F55: 4000 | G55: 25000 | H55: 63000 | S55: =+R55+Q55+P55+O55+N55+M55+L55+K55+J55+I55+H55+G55+F55+E55+D55+C55 -> 103000 | U55: =+S55-T55 -> 103000
A56: =+A55+1 -> 4 | B56: DJOUKWE NANGUEN GUY BLAISE | C56: 9000 | D56: 1000 | E56: 1000 | F56: 4000 | G56: 25000 | H56: 62000 | I56: 75000 | S56: =+R56+Q56+P56+O56+N56+M56+L56+K56+J56+I56+H56+G56+F56+E56+D56+C56 -> 177000 | U56: =+S56-T56 -> 177000
A57: =+A56+1 -> 5 | B57: DJUOMBESSY ANTOINE | C57: 14000 | D57: 1000 | E57: 1000 | F57: 4000 | G57: 25000 | I57: 75000 | K57: 200000 | S57: =+R57+Q57+P57+O57+N57+M57+L57+K57+J57+I57+H57+G57+F57+E57+D57+C57 -> 320000 | U57: =+S57-T57 -> 320000
A58: =+A57+1 -> 6 | B58: DOMOU FABIEN | C58: 9000 | D58: 1000 | E58: 1000 | F58: 4000 | G58: 25000 | S58: =+R58+Q58+P58+O58+N58+M58+L58+K58+J58+I58+H58+G58+F58+E58+D58+C58 -> 40000 | T58: 40000 | U58: =+S58-T58 -> 0
A59: =+A58+1 -> 7 | B59: DONHOU DAVID | C59: 9000 | D59: 1000 | E59: 1000 | F59: 4000 | G59: 25000 | S59: =+R59+Q59+P59+O59+N59+M59+L59+K59+J59+I59+H59+G59+F59+E59+D59+C59 -> 40000 | U59: =+S59-T59 -> 40000
A60: =+A59+1 -> 8 | B60: FOTSO THOMAS | S60: =+R60+Q60+P60+O60+N60+M60+L60+K60+J60+I60+H60+G60+F60+E60+D60+C60 -> 0 | U60: =+S60-T60 -> 0
A61: =+A60+1 -> 9 | B61: HENGUE PAUL OMER | C61: 9000 | D61: 1000 | E61: 1000 | F61: 4000 | G61: 25000 | I61: 75000 | S61: =+R61+Q61+P61+O61+N61+M61+L61+K61+J61+I61+H61+G61+F61+E61+D61+C61 -> 115000 | U61: =+S61-T61 -> 115000
A62: =+A61+1 -> 10 | B62: HOTCHO BENJAMIN | C62: 44000 | D62: 1000 | E62: 1000 | F62: 4000 | G62: 25000 | I62: 75000 | K62: 100000 | M62: 1000000 | S62: =+R62+Q62+P62+O62+N62+M62+L62+K62+J62+I62+H62+G62+F62+E62+D62+C62 -> 1250000 | U62: =+S62-T62 -> 1250000
A63: =+A62+1 -> 11 | B63: KOUAMOU MOISE | C63: 9000 | D63: 1000 | E63: 1000 | F63: 4000 | G63: 25000 | K63: 100000 | Q63: 70000 | S63: =+R63+Q63+P63+O63+N63+M63+L63+K63+J63+I63+H63+G63+F63+E63+D63+C63 -> 210000 | U63: =+S63-T63 -> 210000
A64: =+A63+1 -> 12 | B64: KOUATCHO MESSACK | C64: 9000 | D64: 1000 | E64: 1000 | F64: 4000 | G64: 25000 | I64: 75000 | J64: 51000 | K64: 100000 | S64: =+R64+Q64+P64+O64+N64+M64+L64+K64+J64+I64+H64+G64+F64+E64+D64+C64 -> 266000 | T64: 266000 | U64: =+S64-T64 -> 0
A65: =+A64+1 -> 13 | B65: LOWE JEAN | C65: 9000 | D65: 1000 | E65: 1000 | F65: 4000 | G65: 25000 | S65: =+R65+Q65+P65+O65+N65+M65+L65+K65+J65+I65+H65+G65+F65+E65+D65+C65 -> 40000 | T65: 40000 | U65: =+S65-T65 -> 0
A66: =+A65+1 -> 14 | B66: MBOGNING TUGMA GUY | C66: 9000 | D66: 1000 | E66: 1000 | F66: 4000 | G66: 25000 | I66: 75000 | J66: 0 | K66: 100000 | S66: =+R66+Q66+P66+O66+N66+M66+L66+K66+J66+I66+H66+G66+F66+E66+D66+C66 -> 215000 | T66: 215000 | U66: =+S66-T66 -> 0
A67: =+A66+1 -> 15 | B67: NANGUEN MARTIN | C67: 9000 | D67: 1000 | E67: 1000 | F67: 4000 | G67: 25000 | S67: =+R67+Q67+P67+O67+N67+M67+L67+K67+J67+I67+H67+G67+F67+E67+D67+C67 -> 40000 | U67: =+S67-T67 -> 40000
A68: =+A67+1 -> 16 | B68: NANKAM APPOLINAIRE | C68: 9000 | D68: 1000 | E68: 1000 | F68: 4000 | G68: 25000 | I68: 75000 | S68: =+R68+Q68+P68+O68+N68+M68+L68+K68+J68+I68+H68+G68+F68+E68+D68+C68 -> 115000 | U68: =+S68-T68 -> 115000
A69: =+A68+1 -> 17 | B69: NDJOMO ETIENNE | C69: 19000 | D69: 1000 | E69: 1000 | F69: 4000 | G69: 25000 | K69: 200000 | S69: =+R69+Q69+P69+O69+N69+M69+L69+K69+J69+I69+H69+G69+F69+E69+D69+C69 -> 250000 | U69: =+S69-T69 -> 250000
A70: =+A69+1 -> 18 | B70: NGONDIEP CLAUDE | C70: 9000 | D70: 1000 | E70: 1000 | F70: 4000 | G70: 25000 | H70: 26000 | I70: 75000 | J70: 102000 | K70: 100000 | L70: =156000-134000 -> 22000 | S70: =+R70+Q70+P70+O70+N70+M70+L70+K70+J70+I70+H70+G70+F70+E70+D70+C70 -> 365000 | U70: =+S70-T70 -> 365000
A71: =+A70+1 -> 19 | B71: NGUIEMEGNI MATHIEU BLAISE | C71: 9000 | D71: 1000 | E71: 1000 | F71: 4000 | G71: 25000 | H71: 10000 | I71: 150000 | J71: 102000 | K71: 100000 | L71: 78000 | Q71: 70000 | S71: =+R71+Q71+P71+O71+N71+M71+L71+K71+J71+I71+H71+G71+F71+E71+D71+C71 -> 550000 | T71: 50000 | U71: =+S71-T71 -> 500000
A72: =+A71+1 -> 20 | B72: NKAMGANG JUSTIN DEJOLIE | C72: 9000 | D72: 1000 | E72: 1000 | F72: 4000 | G72: 25000 | H72: 62000 | M72: 1000000 | P72: 30000 | Q72: 70000 | S72: =+R72+Q72+P72+O72+N72+M72+L72+K72+J72+I72+H72+G72+F72+E72+D72+C72 -> 1202000 | T72: 102000 | U72: =+S72-T72 -> 1100000
A73: =+A72+1 -> 21 | B73: NKEHE DAVID | S73: =+R73+Q73+P73+O73+N73+M73+L73+K73+J73+I73+H73+G73+F73+E73+D73+C73 -> 0 | U73: =+S73-T73 -> 0
A74: =+A73+1 -> 22 | B74: NOUBE ETIENNE | C74: 9000 | D74: 1000 | E74: 1000 | F74: 4000 | G74: 25000 | S74: =+R74+Q74+P74+O74+N74+M74+L74+K74+J74+I74+H74+G74+F74+E74+D74+C74 -> 40000 | U74: =+S74-T74 -> 40000
A75: =+A74+1 -> 23 | B75: PATEGO NJOSSU GUSTAVE | C75: 9000 | D75: 1000 | E75: 1000 | F75: 4000 | G75: 25000 | I75: 75000 | S75: =+R75+Q75+P75+O75+N75+M75+L75+K75+J75+I75+H75+G75+F75+E75+D75+C75 -> 115000 | U75: =+S75-T75 -> 115000
A76: =+A75+1 -> 24 | B76: SEUMOU POLYCARPE | C76: 9000 | D76: 1000 | E76: 1000 | F76: 4000 | G76: 25000 | S76: =+R76+Q76+P76+O76+N76+M76+L76+K76+J76+I76+H76+G76+F76+E76+D76+C76 -> 40000 | U76: =+S76-T76 -> 40000
A77: =+A76+1 -> 25 | B77: SIME BRICE | C77: 9000 | D77: 1000 | E77: 1000 | F77: 4000 | G77: 25000 | I77: 75000 | S77: =+R77+Q77+P77+O77+N77+M77+L77+K77+J77+I77+H77+G77+F77+E77+D77+C77 -> 115000 | U77: =+S77-T77 -> 115000
A78: =+A77+1 -> 26 | B78: SIMO FONGANG ERIC | S78: =+R78+Q78+P78+O78+N78+M78+L78+K78+J78+I78+H78+G78+F78+E78+D78+C78 -> 0 | U78: =+S78-T78 -> 0
A79: =+A78+1 -> 27 | B79: SIMO PIERRE | C79: 9000 | D79: 1000 | E79: 1000 | F79: 4000 | G79: 25000 | K79: 100000 | S79: =+R79+Q79+P79+O79+N79+M79+L79+K79+J79+I79+H79+G79+F79+E79+D79+C79 -> 140000 | T79: 140000 | U79: =+S79-T79 -> 0
A80: =+A79+1 -> 28 | B80: TCHOUAMOU MATHIEU | C80: 9000 | D80: 1000 | E80: 1000 | F80: 4000 | G80: 25000 | I80: 75000 | S80: =+R80+Q80+P80+O80+N80+M80+L80+K80+J80+I80+H80+G80+F80+E80+D80+C80 -> 115000 | U80: =+S80-T80 -> 115000
A81: =+A80+1 -> 29 | B81: TCHOUTOU NANA CLAUDE | C81: 9000 | D81: 1000 | E81: 1000 | F81: 4000 | G81: 25000 | S81: =+R81+Q81+P81+O81+N81+M81+L81+K81+J81+I81+H81+G81+F81+E81+D81+C81 -> 40000 | T81: 40000 | U81: =+S81-T81 -> 0
A82: =+A81+1 -> 30 | B82: TIEYAM ERNEST | S82: =+R82+Q82+P82+O82+N82+M82+L82+K82+J82+I82+H82+G82+F82+E82+D82+C82 -> 0 | U82: =+S82-T82 -> 0
A83: =+A82+1 -> 31 | B83: YEPMOU JEAN JACQUES | C83: 9000 | D83: 1000 | E83: 1000 | F83: 4000 | G83: 25000 | S83: =+R83+Q83+P83+O83+N83+M83+L83+K83+J83+I83+H83+G83+F83+E83+D83+C83 -> 40000 | T83: 40000 | U83: =+S83-T83 -> 0
A84: =+A83+1 -> 32 | B84: YOUMBI EMMANUEL | C84: 9000 | D84: 1000 | E84: 1000 | F84: 4000 | G84: 25000 | I84: 150000 | K84: 100000 | S84: =+R84+Q84+P84+O84+N84+M84+L84+K84+J84+I84+H84+G84+F84+E84+D84+C84 -> 290000 | U84: =+S84-T84 -> 290000
A85: =+A84+1 -> 33 | B85: BAKOP ACHILLE | C85: 9000 | D85: 1000 | E85: 1000 | F85: 4000 | G85: 25000 | S85: =+R85+Q85+P85+O85+N85+M85+L85+K85+J85+I85+H85+G85+F85+E85+D85+C85 -> 40000 | T85: 40000 | U85: =+S85-T85 -> 0
A86: =+A85+1 -> 34 | B86: YANTCHOU GERVAIS | C86: 9000 | D86: 1000 | E86: 1000 | F86: 4000 | G86: 25000 | R86: 60000 | S86: =+R86+Q86+P86+O86+N86+M86+L86+K86+J86+I86+H86+G86+F86+E86+D86+C86 -> 100000 | U86: =+S86-T86 -> 100000
A87: =+A86+1 -> 35 | S87: =+R87+Q87+P87+O87+N87+M87+L87+K87+J87+I87+H87+G87+F87+E87+D87+C87 -> 0 | U87: =+S87-T87 -> 0
A88: =+A87+1 -> 36 | S88: =+R88+Q88+P88+O88+N88+M88+L88+K88+J88+I88+H88+G88+F88+E88+D88+C88 -> 0 | U88: =+S88-T88 -> 0
A89: =+A88+1 -> 37 | S89: =+R89+Q89+P89+O89+N89+M89+L89+K89+J89+I89+H89+G89+F89+E89+D89+C89 -> 0 | U89: =+S89-T89 -> 0
A90: =+A89+1 -> 38 | S90: =+R90+Q90+P90+O90+N90+M90+L90+K90+J90+I90+H90+G90+F90+E90+D90+C90 -> 0 | U90: =+S90-T90 -> 0
A91: =+A90+1 -> 39 | S91: =+R91+Q91+P91+O91+N91+M91+L91+K91+J91+I91+H91+G91+F91+E91+D91+C91 -> 0 | U91: =+S91-T91 -> 0
A92: =+A91+1 -> 40 | S92: =+R92+Q92+P92+O92+N92+M92+L92+K92+J92+I92+H92+G92+F92+E92+D92+C92 -> 0 | U92: =+S92-T92 -> 0
A93: =+A92+1 -> 41 | S93: =+R93+Q93+P93+O93+N93+M93+L93+K93+J93+I93+H93+G93+F93+E93+D93+C93 -> 0 | U93: =+S93-T93 -> 0
C94: =SUM(C52:C93) -> 328000 | D94: =SUM(D52:D93) -> 30000 | E94: =SUM(E52:E93) -> 30000 | F94: =SUM(F52:F93) -> 120000 | G94: =SUM(G52:G93) -> 750000 | H94: =SUM(H52:H93) -> 223000 | I94: =SUM(I53:I93) -> 1200000 | J94: =SUM(J52:J93) -> 255000 | K94: =SUM(K52:K93) -> 1400000 | L94: =SUM(L52:L93) -> 152000 | M94: =SUM(M52:M93) -> 2500000 | N94: =SUM(N52:N93) -> 0 | O94: =SUM(O52:O93) -> 0 | P94: =SUM(P52:P93) -> 30000 | Q94: =SUM(Q52:Q93) -> 210000 | ... S94: =SUM(S52:S93) -> 7288000 | T94: =SUM(T52:T93)-40000 -> 1013000 | U94: =SUM(U52:U93) -> 6235000
B95: BROUILLARD DE CAISSE DU 19 MARS 2023
C97: EPARGNE | D97: F R | E97: F EX | F97: COLL | G97: T PRESENCE | I97: T75 | K97: T100 | M97: REMB PRÊT | N97: DEPOT | O97: PENALITE | P97: INTERET PRÊT | Q97: FOYER | S97: TOTAL VERSE
G98: COTISE | H98: REMB | I98: COTISE | J98: REMB | K98: COTISE | L98: REMB | S98: CUMUL | T98: ESPECE | U98: BANQUE
A99: 0 | B99: ASELBY | K99: 100000 | Q99: -1750000 | S99: =+R99+Q99+P99+O99+N99+M99+L99+K99+J99+I99+H99+G99+F99+E99+D99+C99 -> -1650000 | U99: =+S99-T99 -> -1650000
A100: =+A99+1 -> 1 | B100: BOUTCHOUANG WILLIAM | C100: 9000 | D100: 1000 | E100: 1000 | F100: 4000 | G100: 25000 | I100: 75000 | S100: =+R100+Q100+P100+O100+N100+M100+L100+K100+J100+I100+H100+G100+F100+E100+D100+C100 -> 115000 | U100: =+S100-T100 -> 115000
A101: =+A100+1 -> 2 | B101: DJOMO JEAN PAUL | C101: 9000 | D101: 1000 | E101: 1000 | F101: 4000 | G101: 25000 | K101: 100000 | S101: =+R101+Q101+P101+O101+N101+M101+L101+K101+J101+I101+H101+G101+F101+E101+D101+C101 -> 140000 | U101: =+S101-T101 -> 140000
A102: =+A101+1 -> 3 | B102: DJOMOU TCHANDA | C102: 10000 | D102: 1000 | E102: 1000 | F102: 4000 | G102: 25000 | H102: 41000 | S102: =+R102+Q102+P102+O102+N102+M102+L102+K102+J102+I102+H102+G102+F102+E102+D102+C102 -> 82000 | U102: =+S102-T102 -> 82000
A103: =+A102+1 -> 4 | B103: DJOUKWE NANGUEN GUY BLAISE | C103: 14000 | D103: 1000 | E103: 1000 | F103: 4000 | G103: 25000 | I103: 75000 | S103: =+R103+Q103+P103+O103+N103+M103+L103+K103+J103+I103+H103+G103+F103+E103+D103+C103 -> 120000 | U103: =+S103-T103 -> 120000
...

Sheet TONTINE PRESENCE EXO 2023 
B1: ANNEE 2023
F2: TOTINE AVEC RETENUE
B3: Date | C3: 44941 | E3: 12 fevrier 2023 | G3: 45004 | I3: 45032 | K3: 45067 | M3: 45095 | O3: 45123 | Q3: 27 aout 2023 | S3: 45186 | U3: 45214 | W3: 45249 | Y3: 17 decembre 2023
B4: Nom et Prénom | C4: Cotisation | D4: Mtant achat | E4: Cotisation | F4: Mtant achat | G4: Cotisation | H4: Mtant achat | I4: Cotisation | J4: Mtant achat | K4: Cotisation | L4: Mtant achat | M4: Cotisation | N4: Mtant achat | O4: Cotisation | P4: Mtant achat | Q4: Cotisation | R4: Mtant achat | S4: Cotisation | T4: Mtant achat | U4: cotisation | V4: mtant achat | W4: cotisation | X4: mtant achat | Y4: cotisation | Z4: mtant achat
A5: 1 | B5: BOUTCHOUANG WILLIAM | C5: 25000 | E5: 25000 | G5: 25000 | I5: 25000 | K5: 25000 | M5: 25000 | O5: 25000 | Q5: 25000 | S5: 25000 | U5: 25000 | V5: 2500 | W5: 25000
A6: =1+A5 -> 2 | B6: DJOMO JEAN PAUL | C6: 25000 | D6: 22500 | E6: 25000 | G6: 25000 | I6: 25000 | K6: 25000 | M6: 25000 | O6: 25000 | Q6: 25000 | S6: 25000 | U6: 25000 | W6: 25000
A7: =1+A6 -> 3 | B7: DJOMO TCHAPDA | C7: 25000 | E7: 25000 | G7: 25000 | I7: 25000 | J7: 11000 | K7: 25000 | M7: 25000 | O7: 25000 | Q7: 25000 | S7: 25000 | U7: 25000 | W7: 25000
A8: =1+A7 -> 4 | B8: DJOUKWEU GUY B | C8: 25000 | E8: 25000 | G8: 25000 | I8: 25000 | J8: 10000 | K8: 25000 | M8: 25000 | O8: 25000 | Q8: 25000 | S8: 25000 | U8: 25000 | W8: 25000
A9: =1+A8 -> 5 | B9: DJUOMBISSY ANTOINE | C9: 25000 | E9: 25000 | G9: 25000 | I9: 25000 | K9: 25000 | M9: 25000 | N9: 5000 | O9: 25000 | Q9: 25000 | S9: 25000 | U9: 25000 | W9: 25000
A10: =1+A9 -> 6 | B10: DOMOU FABIEN | C10: 25000 | E10: 25000 | G10: 25000 | H10: 10000 | I10: 25000 | K10: 25000 | M10: 25000 | O10: 25000 | Q10: 25000 | S10: 25000 | U10: 25000 | W10: 25000
A11: =1+A10 -> 7 | B11: DONHOU DAVID | C11: 25000 | E11: 25000 | G11: 25000 | I11: 25000 | K11: 25000 | M11: 25000 | O11: 25000 | Q11: 25000 | S11: 25000 | U11: 25000 | W11: 25000 | X11: 2500
A12: =1+A11 -> 8 | B12: HENGUE PAUL OMER | C12: 25000 | E12: 25000 | G12: 25000 | I12: 25000 | K12: 25000 | M12: 25000 | O12: 25000 | P12: 2500 | Q12: 25000 | S12: 25000 | U12: 25000 | W12: 25000
A13: =1+A12 -> 9 | B13: HOTCHO BENJAMIN | C13: 25000 | E13: 25000 | G13: 25000 | I13: 25000 | K13: 25000 | L13: 2500 | M13: 25000 | O13: 25000 | Q13: 25000 | S13: 25000 | U13: 25000 | W13: 25000
A14: =1+A13 -> 10 | B14: KOUAMOU MOISE | C14: 25000 | E14: 25000 | F14: 6500 | G14: 25000 | I14: 25000 | K14: 25000 | M14: 25000 | O14: 25000 | Q14: 25000 | S14: 25000 | U14: 25000 | W14: 25000
A15: =1+A14 -> 11 | B15: KOUATCHO | C15: 25000 | D15: 17500 | E15: 25000 | G15: 25000 | I15: 25000 | K15: 25000 | M15: 25000 | O15: 25000 | Q15: 25000 | S15: 25000 | U15: 25000 | W15: 25000
A16: =1+A15 -> 12 | B16: LOWE JEAN | C16: 25000 | E16: 25000 | G16: 25000 | I16: 25000 | K16: 25000 | L16: 3000 | M16: 25000 | O16: 25000 | Q16: 25000 | S16: 25000 | U16: 25000 | W16: 25000
A17: =1+A16 -> 13 | B17: MBOGNING TUGMA GUY | C17: 25000 | E17: 25000 | G17: 25000 | H17: 11000 | I17: 25000 | K17: 25000 | M17: 25000 | O17: 25000 | Q17: 25000 | S17: 25000 | U17: 25000 | W17: 25000
A18: =1+A17 -> 14 | B18: NANGUEN MARTIN | C18: 25000 | E18: 25000 | G18: 25000 | I18: 25000 | K18: 25000 | M18: 25000 | O18: 25000 | Q18: 25000 | R18: 2500 | S18: 25000 | U18: 25000 | W18: 25000
A19: =1+A18 -> 15 | B19: NANKAM APPOLINAIRE | C19: 25000 | E19: 25000 | G19: 25000 | I19: 25000 | K19: 25000 | M19: 25000 | N19: 4500 | O19: 25000 | Q19: 25000 | S19: 25000 | U19: 25000 | W19: 25000
A20: =1+A19 -> 16 | B20: NDJOMO ETIENNE | C20: 25000 | E20: 25000 | G20: 25000 | I20: 25000 | K20: 25000 | M20: 25000 | O20: 25000 | Q20: 25000 | S20: 25000 | T20: 2500 | U20: 25000 | W20: 25000
A21: =1+A20 -> 17 | B21: NGONDIEP CLAUDE | C21: 25000 | E21: 25000 | G21: 25000 | I21: 25000 | K21: 25000 | L21: 3000 | M21: 25000 | O21: 25000 | Q21: 25000 | S21: 25000 | U21: 25000 | W21: 25000
A22: =1+A21 -> 18 | B22: NGUIEMENI MATHIEU B | C22: 25000 | E22: 25000 | F22: 7500 | G22: 25000 | I22: 25000 | K22: 25000 | M22: 25000 | O22: 25000 | Q22: 25000 | S22: 25000 | U22: 25000 | W22: 25000
A23: =1+A22 -> 19 | B23: NKAMGANG JUSTIN DEJOLIE | C23: 25000 | E23: 25000 | F23: 3500 | G23: 25000 | I23: 25000 | K23: 25000 | M23: 25000 | O23: 25000 | Q23: 25000 | S23: 25000 | U23: 25000 | W23: 25000
A24: =1+A23 -> 20 | B24: PATEGO NJOSSU GUSTAVE | C24: 25000 | E24: 25000 | G24: 25000 | I24: 25000 | K24: 25000 | M24: 25000 | O24: 25000 | Q24: 25000 | S24: 25000 | U24: 25000 | W24: 25000 | X24: 2500
A25: =1+A24 -> 21 | B25: SIME BRICE | C25: 25000 | E25: 25000 | G25: 25000 | I25: 25000 | K25: 25000 | M25: 25000 | O25: 25000 | Q25: 25000 | R25: 3000 | S25: 25000 | U25: 25000 | W25: 25000
A26: =1+A25 -> 22 | B26: MBAKOP ACHILLE | C26: 25000 | E26: 25000 | G26: 25000 | I26: 25000 | K26: 25000 | M26: 25000 | O26: 25000 | P26: 3000 | Q26: 25000 | S26: 25000 | U26: 25000 | W26: 25000
A27: =1+A26 -> 23 | B27: SIME PIERRE | C27: 25000 | E27: 25000 | G27: 25000 | H27: 11000 | I27: 25000 | K27: 25000 | M27: 25000 | O27: 25000 | Q27: 25000 | S27: 25000 | U27: 25000 | W27: 25000
A28: =1+A27 -> 24 | B28: TCHOUAMOU MATHIEU | C28: 25000 | E28: 25000 | G28: 25000 | I28: 25000 | K28: 25000 | M28: 25000 | O28: 25000 | P28: 2500 | Q28: 25000 | S28: 25000 | U28: 25000 | W28: 25000
A29: =1+A28 -> 25 | B29: YEPMO JEAN JACQUES | C29: 25000 | E29: 25000 | G29: 25000 | I29: 0 | K29: 50000 | M29: 25000 | O29: 25000 | Q29: 25000 | S29: 25000 | U29: 25000 | W29: 25000 | Z29: 2500
A30: =1+A29 -> 26 | B30: YOUMBI EMMANUEL | C30: 25000 | E30: 25000 | G30: 25000 | I30: 25000 | K30: 25000 | M30: 25000 | O30: 25000 | Q30: 25000 | S30: 25000 | U30: 25000 | W30: 25000 | X30: 2500
A31: =1+A30 -> 27 | B31: SEUMOU POLYCARPE | C31: 25000 | E31: 25000 | G31: 25000 | I31: 25000 | K31: 25000 | M31: 25000 | O31: 25000 | Q31: 25000 | S31: 25000 | T31: 2500 | U31: 25000 | W31: 25000
A32: =1+A31 -> 28 | B32: NOUBE ETIENNE | C32: 25000 | E32: 25000 | G32: 25000 | I32: 25000 | K32: 25000 | M32: 25000 | O32: 25000 | Q32: 25000 | S32: 25000 | T32: 2500 | U32: 25000 | W32: 25000
A33: =1+A32 -> 29 | B33: TCHOUTOU NANA | C33: 25000 | E33: 25000 | G33: 25000 | I33: 25000 | K33: 25000 | M33: 25000 | O33: 25000 | Q33: 0 | S33: 0 | U33: 0 | W33: 75000
A34: =1+A33 -> 30 | B34: YANTCHOU GERVAIS | C34: 25000 | E34: 25000 | G34: 25000 | I34: 25000 | K34: 25000 | M34: 25000 | O34: 25000 | Q34: 25000 | S34: 25000 | U34: 25000 | V34: 2500 | W34: 25000 | Z34: 2500
B35: TOTAL | C35: =SUM(C5:C34) -> 750000 | D35: =SUM(D5:D34) -> 40000 | E35: =SUM(E5:E34) -> 750000 | F35: =SUM(F5:F34) -> 17500 | G35: =SUM(G5:G34) -> 750000 | H35: =SUM(H5:H34) -> 32000 | I35: =SUM(I5:I34) -> 725000 | J35: =SUM(J5:J34) -> 21000 | ... AA35: =SUM(AA5:AA34) -> 0 | AB35: =+Z35+X35+V35+T35+R35+P35+N35+L35+J35+H35+F35+D35 -> 167000 | AC35: =SUM(AC5:AC34) -> 0 | AD35: =SUM(AD5:AD34) -> 0 | AE35: =SUM(AE5:AE34) -> 0 | AF35: =SUM(AF5:AF34) -> 0 | AI35: =SUM(AI5:AI26) -> 0 | AJ35: =SUM(AJ5:AJ26) -> 0
C36: reliquat Janvier | E36: reliquat Février | G36: RELIQUAT MARS | I36: reliquat AVRIL | K36: RELIQUAT MAI | L36: 85500 | M36: reliquat fev | N36: 93500 | O36: reliquat mar | P36: 240500 | Q36: reliquat avr | R36: -53500 | S36: reliquat avr | T36: 0 | U36: reliquat avr | AB36: =+F53+F69+F85+F100+F117+F131+F146+F161+F176+F191+F212+F228 -> 26000 | AI36: Reliquat Juil | AJ36: 0
AB37: =SUM(AB35:AB36) -> 193000
C38: REMBOURSEMENTS ET EMPRUNTS DES SOUS-PRODUITS | O38: BILAN DE LA TONTINE VENTE | AB38: =+AB37/30 -> 6433.3333
B39: Dates | C39: Somme remboursée | E39: Somme empruntée | F39: Intérêt produit | G39: Montant à rembourser | H39: Solde en caisse | I39: Total disponible | K39: 44941 | O39: NOM | P39: Nbre de part | Q39: Mtant d'une part | R39: Net à percevoir
C40: Nom & Prénom | D40: Montant | J40: NOM | K40: Mt du lot | L40: Mt achat | M40: Net à percev | N40: 1 | P40: 1 | Q40: =D258/P74 -> 25806.452 | R40: =P40*$Q$40 -> 25806.452
B41: 44941 | C41: Disponible | D41: =C35-M44 -> 235000 | J41: DJOMO JP | K41: 300000 | L41: 45000 | M41: =K41-L41 -> 255000 | N41: =1+N40 -> 2 | P41: 1 | Q41: 0 | R41: =P41*$Q$40 -> 25806.452
C42: NKAMGANG J D | D42: 0 | E42: 30000 | F42: 1000 | G42: =E42+F42 -> 31000 | H42: 31000 | J42: KOUATCHO | K42: 300000 | L42: 40000 | M42: =K42-L42 -> 260000 | N42: =1+N41 -> 3 | P42: 1 | Q42: 0 | R42: =P42*$Q$40 -> 25806.452
C43: NGUIEMENI | D43: 0 | E43: 30000 | F43: 1000 | G43: =E43+F43 -> 31000 | H43: 31000 | K43: 0 | L43: 0 | M43: =K43-L43 -> 0 | N43: =1+N42 -> 4 | P43: 1 | Q43: 0 | R43: =P43*$Q$40 -> 25806.452
C44: NKAMGANG J D | D44: 0 | E44: 30000 | F44: 1000 | G44: =E44+F44 -> 31000 | H44: 31000 | L44: =SUM(L41:L43) -> 85000 | M44: =SUM(M41:M43) -> 515000 | N44: =1+N43 -> 5 | P44: 1 | Q44: 0 | R44: =P44*$Q$40 -> 25806.452
C45: DJOUKWEU G | D45: 0 | E45: 30000 | F45: 1000 | G45: =E45+F45 -> 31000 | H45: 31000 | N45: =1+N44 -> 6 | P45: 1 | Q45: 0 | R45: =P45*$Q$40 -> 25806.452
C46: DJOUKWEU G | D46: 0 | E46: 30000 | F46: 1000 | G46: =E46+F46 -> 31000 | H46: 31000 | N46: =1+N45 -> 7 | P46: 1 | Q46: 0 | R46: =P46*$Q$40 -> 25806.452
C47: DJOMO FRANCOIS | D47: 0 | E47: 30000 | F47: 1000 | G47: =E47+F47 -> 31000 | H47: 31000 | N47: =1+N46 -> 8 | P47: 1 | Q47: 0 | R47: =P47*$Q$40 -> 25806.452
C48: DJOMO FRANCOIS | D48: 0 | E48: 30000 | F48: 2000 | G48: =E48+F48 -> 32000 | H48: 32000 | N48: =1+N47 -> 9 | P48: 1 | Q48: 0 | R48: =P48*$Q$40 -> 25806.452
C49: NGONDIEP | D49: 0 | E49: 25000 | F49: 1000 | G49: =E49+F49 -> 26000 | H49: 26000 | N49: =1+N48 -> 10 | P49: 1 | Q49: 0 | R49: =P49*$Q$40 -> 25806.452
D50: 0 | E50: 0 | F50: 0 | G50: =E50+F50 -> 0 | N50: =1+N49 -> 11 | P50: 1 | Q50: 0 | R50: =P50*$Q$40 -> 25806.452
D51: 0 | E51: 0 | F51: 0 | G51: =E51+F51 -> 0 | N51: =1+N50 -> 12 | P51: 1 | Q51: 0 | R51: =P51*$Q$40 -> 25806.452
C52: TROP PERCU | D52: 0 | E52: 0 | F52: 0 | G52: =E52+F52 -> 0 | N52: =1+N51 -> 13 | P52: 1 | Q52: 0 | R52: =P52*$Q$40 -> 25806.452
C53: Total | D53: =SUM(D42:D52) -> 0 | E53: =SUM(E42:E52) -> 235000 | F53: =SUM(F42:F52) -> 9000 | G53: =SUM(G42:G52) -> 244000 | H53: =SUM(H42:H52) -> 244000 | I53: =E35+D53+H53 -> 994000 | K53: 19 fevrier 2023 | N53: =1+N52 -> 14 | P53: 1 | Q53: 0 | R53: =P53*$Q$40 -> 25806.452
B54: 12 fevrier 2023 | C54: Disponible | D54: =I53-M59 -> 111500 | J54: NOM | K54: Mt du lot | L54: Mt achat | M54: Net à percev | N54: =1+N53 -> 15 | P54: 1 | Q54: 0 | R54: =P54*$Q$40 -> 25806.452
C55: NKAMGANG J D | D55: 0 | E55: 40000 | F55: 1000 | G55: =E55+F55 -> 41000 | H55: 41000 | J55: NKAMGANG | K55: 300000 | L55: 3500 | M55: =K55-L55 -> 296500 | N55: =1+N54 -> 16 | P55: 1 | Q55: 0 | R55: =P55*$Q$40 -> 25806.452
C56: DJOMO FRANCOIS | D56: 0 | E56: 40000 | F56: 1000 | G56: =E56+F56 -> 41000 | H56: 41000 | J56: KOUAMOU MOISE | K56: 300000 | L56: 6500 | M56: =K56-L56 -> 293500 | N56: =1+N55 -> 17 | P56: 1 | Q56: 0 | R56: =P56*$Q$40 -> 25806.452
C57: MBOGNING | D57: 0 | E57: 31500 | F57: 1000 | G57: =E57+F57 -> 32500 | H57: 32500 | J57: NGUIEMENI MATHIEU | K57: 300000 | L57: 7500 | M57: =K57-L57 -> 292500 | N57: =1+N56 -> 18 | P57: 1 | Q57: 0 | R57: =P57*$Q$40 -> 25806.452
D58: 0 | E58: 0 | F58: 0 | G58: =E58+F58 -> 0 | K58: 0 | L58: 0 | M58: 0 | N58: =1+N57 -> 19 | P58: 1 | Q58: 0 | R58: =P58*$Q$40 -> 25806.452
D59: 0 | E59: 0 | F59: 0 | G59: =E59+F59 -> 0 | L59: =SUM(L55:L58) -> 17500 | M59: =SUM(M55:M58) -> 882500 | N59: =1+N58 -> 20 | P59: 1 | Q59: 0 | R59: =P59*$Q$40 -> 25806.452
D60: 0 | E60: 0 | F60: 0 | G60: =E60+F60 -> 0 | N60: =1+N59 -> 21 | P60: 1 | Q60: 0 | R60: =P60*$Q$40 -> 25806.452
D61: 0 | E61: 0 | F61: 0 | G61: =E61+F61 -> 0 | N61: =1+N60 -> 22 | P61: 1 | Q61: 0 | R61: =P61*$Q$40 -> 25806.452
D62: 0 | E62: 0 | F62: 0 | G62: =E62+F62 -> 0 | N62: =1+N61 -> 23 | P62: 1 | Q62: 0 | R62: 0
D63: 0 | E63: 0 | F63: 0 | G63: =E63+F63 -> 0 | N63: =1+N62 -> 24 | P63: 1 | Q63: 0
D64: 0 | E64: 0 | F64: 0 | G64: =E64+F64 -> 0 | N64: =1+N63 -> 25 | P64: 1 | Q64: 0
D65: 0 | E65: 0 | F65: 0 | G65: =E65+F65 -> 0 | N65: =1+N64 -> 26 | P65: 1 | Q65: 0
D66: 0 | E66: 0 | F66: 0 | G66: =E66+F66 -> 0 | N66: =1+N65 -> 27 | P66: 1 | Q66: 0
D67: 0 | E67: 0 | F67: 0 | G67: =E67+F67 -> 0 | N67: =1+N66 -> 28 | P67: 1 | Q67: 0
D68: 0 | E68: 0 | F68: 0 | G68: =E68+F68 -> 0 | N68: =1+N67 -> 29 | P68: 1 | Q68: 0 | R68: =P68*$Q$40 -> 25806.452
C69: Total | D69: =SUM(D55:D68) -> 0 | E69: =SUM(E55:E68) -> 111500 | F69: =SUM(F55:F68) -> 3000 | G69: =SUM(G55:G68) -> 114500 | H69: =SUM(H55:H68) -> 114500 | I69: =G35+D69+H69 -> 864500 | K69: 45004 | N69: =1+N68 -> 30 | P69: 1 | Q69: 0 | R69: =P69*$Q$40 -> 25806.452
B70: 45004 | C70: Disponible | D70: =I69-M78 -> -3500 | J70: NOM | K70: Mt du lot | L70: Mt achat | M70: Net à percev | N70: =1+N69 -> 31 | P70: 1 | Q70: 0 | R70: =P70*$Q$40 -> 25806.452
D71: 0 | E71: 0 | F71: 0 | G71: =E71+F71 -> 0 | J71: SIME PIERRE | K71: 300000 | L71: 11000 | M71: =K71-L71 -> 289000 | O71: reliquat | Q71: 0 | R71: 0
D72: 0 | E72: 0 | F72: 0 | G72: =E72+F72 -> 0 | J72: MBOGNING | K72: 300000 | L72: 11000 | M72: =K72-L72 -> 289000 | Q72: 0 | R72: =P72*$Q$40 -> 0
D73: 0 | E73: 0 | F73: 0 | G73: =E73+F73 -> 0 | J73: DOMOU FABIEN | K73: 300000 | L73: 10000 | M73: =K73-L73 -> 290000
D74: 0 | E74: 0 | F74: 0 | G74: =E74+F74 -> 0 | K74: 0 | L74: 0 | M74: 0 | O74: TOTAL | P74: =SUM(P40:P72) -> 31 | Q74: ::::::::::::::::::: | R74: =SUM(R40:R72) -> 645161.29
D75: 0 | E75: 0 | F75: 0 | G75: =E75+F75 -> 0
D76: 0 | E76: 0 | F76: 0 | G76: =E76+F76 -> 0
D77: 0 | E77: 0 | F77: 0 | G77: =E77+F77 -> 0
D78: 0 | E78: 0 | F78: 0 | G78: =E78+F78 -> 0 | L78: =SUM(L71:L74) -> 32000 | M78: =SUM(M71:M74) -> 868000
D79: 0 | E79: 0 | F79: 0 | G79: =E79+F79 -> 0
D80: 0 | E80: 0 | F80: 0 | G80: =E80+F80 -> 0
D81: 0 | E81: 0 | F81: 0 | G81: 0
D82: 0 | E82: 0 | F82: 0 | G82: =E82+F82 -> 0
D83: 0 | E83: 0 | F83: 0 | G83: =E83+F83 -> 0
D84: 0 | E84: 0 | F84: 0 | G84: =E84+F84 -> 0
C85: Total | D85: =SUM(D71:D84) -> 0 | E85: =SUM(E71:E84) -> 0 | F85: =SUM(F71:F84) -> 0 | G85: =SUM(G71:G84) -> 0 | H85: =D70-E85 -> -3500 | I85: =I35+D85+H85 -> 721500 | K85: 45032
B86: 45032 | C86: Disponible | D86: =I85-M99 -> 142500 | J86: NOM | K86: Mt du lot | L86: Mt achat | M86: Net à percev
C87: NKAMGANG J D | D87: 0 | E87: 30000 | F87: 500 | G87: =E87+F87 -> 30500 | H87: 30500 | J87: Djoukweu guy | K87: 300000 | L87: 10000 | M87: =K87-L87 -> 290000
C88: NKAMGANG J D | D88: 0 | E88: 30000 | F88: 500 | G88: =E88+F88 -> 30500 | H88: 30500 | J88: Djomo francois | K88: 300000 | L88: 11000 | M88: =K88-L88 -> 289000
C89: DJOMO FRANCOIS | D89: 0 | E89: 30000 | F89: 1000 | G89: =E89+F89 -> 31000 | H89: 31000 | K89: 0 | L89: 0 | M89: 0
C90: DJOMO FRANCOIS | D90: 0 | E90: 30000 | F90: 1000 | G90: =E90+F90 -> 31000 | H90: 31000
C91: Djomo jean p | D91: 0 | E91: 22500 | F91: 500 | G91: =E91+F91 -> 23000 | H91: 23000
D92: 0 | E92: 0 | F92: 0 | G92: =E92+F92 -> 0
D93: 0 | E93: 0 | F93: 0 | G93: =E93+F93 -> 0
D94: 0 | E94: 0 | F94: 0 | G94: =E94+F94 -> 0
D95: 0 | E95: 0 | F95: 0 | G95: =E95+F95 -> 0
D96: 0 | E96: 0 | F96: 0 | G96: =E96+F96 -> 0
D97: 0 | E97: 0 | F97: 0 | G97: =E97+F97 -> 0
D98: 0 | E98: 0 | F98: 0 | G98: =E98+F98 -> 0
D99: 0 | E99: 0 | F99: 0 | G99: =E99+F99 -> 0 | L99: =SUM(L87:L89) -> 21000 | M99: =SUM(M87:M89) -> 579000
C100: Total | D100: =SUM(D87:D99) -> 0 | E100: =SUM(E87:E99) -> 142500 | F100: =SUM(F87:F99) -> 3500 | G100: =SUM(G87:G99) -> 146000 | H100: =SUM(H87:H99) -> 146000 | I100: =K35+D100+H100 -> 921000 | K100: 45067
...

Sheet TONTINE 75000 EXO 2023
B1: ANNEE 2023
F2: TOTINE AVEC RETENUE
B3: Date | C3: 44941 | E3: 12 fevrier 2023 | G3: 45004 | I3: 45032 | K3: 45067 | M3: 45095 | O3: 45123 | Q3: 21 aout 2023 | S3: 45186 | U3: 45214 | W3: 45249 | Y3: 17 decembre 2023
B4: Nom et Prénom | C4: Cotisation | D4: Mtant achat | E4: Cotisation | F4: Mtant achat | G4: Cotisation | H4: Mtant achat | I4: Cotisation | J4: Mtant achat | K4: Cotisation | L4: Mtant achat | M4: Cotisation | N4: Mtant achat | O4: Cotisation | P4: Mtant achat | Q4: Cotisation | R4: Mtant achat | S4: Cotisation | T4: Mtant achat | U4: cotisation | V4: mtant achat | W4: cotisation | X4: mtant achat | Y4: cotisation | Z4: mtant achat
A5: 1 | B5: BOUTCHOUANG WILLIAM | C5: 75000 | E5: 75000 | G5: 75000 | I5: 75000 | K5: 75000 | M5: 75000 | O5: 75000 | Q5: 75000 | S5: 75000 | T5: 7500 | U5: 75000 | W5: 75000 | Y5: 75000
A6: =1+A5 -> 2 | B6: DJOUKWE GUY | C6: 75000 | E6: 75000 | G6: 75000 | H6: 7500 | I6: 75000 | K6: 75000 | M6: 75000 | O6: 75000 | Q6: 75000 | S6: 75000 | U6: 75000 | W6: 75000 | Y6: 75000
A7: =1+A6 -> 3 | B7: DJUOMBISSY ANTOINE | C7: 75000 | E7: 75000 | G7: 75000 | I7: 75000 | K7: 75000 | L7: 10000 | M7: 75000 | O7: 75000 | Q7: 75000 | S7: 75000 | U7: 75000 | W7: 75000 | Y7: 75000
A8: =1+A7 -> 4 | B8: HENGUE PAUL OMER | C8: 75000 | E8: 75000 | G8: 75000 | I8: 75000 | K8: 75000 | M8: 75000 | O8: 75000 | P8: 7500 | Q8: 75000 | S8: 75000 | U8: 75000 | W8: 75000 | Y8: 75000
A9: =1+A8 -> 5 | B9: HOTCHO BENJAMIN | C9: 75000 | E9: 75000 | F9: 20000 | G9: 75000 | I9: 75000 | K9: 75000 | M9: 75000 | O9: 75000 | Q9: 75000 | S9: 75000 | U9: 75000 | W9: 75000 | Y9: 75000
A10: =1+A9 -> 6 | B10: KOUATCHO | C10: 75000 | E10: 75000 | G10: 75000 | I10: 75000 | J10: 13000 | K10: 75000 | M10: 75000 | O10: 75000 | Q10: 75000 | S10: 75000 | U10: 75000 | W10: 75000 | Y10: 75000
A11: =1+A10 -> 7 | B11: MBOGNING GUY | C11: 75000 | E11: 75000 | F11: 22000 | G11: 75000 | I11: 75000 | K11: 75000 | M11: 75000 | O11: 75000 | Q11: 75000 | S11: 75000 | U11: 75000 | W11: 75000 | Y11: 75000
A12: =1+A11 -> 8 | B12: NANKAM APPOLINAIRE | C12: 75000 | E12: 75000 | G12: 75000 | I12: 75000 | K12: 75000 | M12: 75000 | O12: 75000 | Q12: 75000 | S12: 75000 | T12: 7500 | U12: 75000 | W12: 75000 | Y12: 75000
A13: =1+A12 -> 9 | B13: NGONDIEP CLAUDE | C13: 75000 | D13: 37500 | E13: 75000 | G13: 75000 | I13: 75000 | K13: 75000 | M13: 75000 | O13: 75000 | Q13: 75000 | S13: 75000 | U13: 75000 | W13: 75000 | Y13: 75000
A14: =1+A13 -> 10 | B14: NGUIEMENI MATHIEU BLAISE 1 | C14: 75000 | E14: 75000 | G14: 75000 | I14: 75000 | K14: 75000 | L14: 15000 | M14: 75000 | O14: 75000 | Q14: 75000 | S14: 75000 | U14: 75000 | W14: 75000 | Y14: 75000
A15: =1+A14 -> 11 | B15: NGUIEMENI MATHIEU BLAISE 2 | C15: 75000 | E15: 75000 | G15: 75000 | I15: 75000 | K15: 75000 | M15: 75000 | O15: 75000 | Q15: 75000 | R15: 7500 | S15: 75000 | U15: 75000 | W15: 75000 | Y15: 75000
A16: =1+A15 -> 12 | B16: PATEGO GUSTAVE | C16: 75000 | E16: 75000 | G16: 75000 | I16: 75000 | K16: 75000 | M16: 75000 | O16: 75000 | Q16: 75000 | S16: 75000 | U16: 75000 | W16: 75000 | X16: 7500 | Y16: 75000
A17: =1+A16 -> 13 | B17: SIME BRICE | C17: 75000 | E17: 75000 | G17: 75000 | I17: 75000 | K17: 75000 | M17: 75000 | O17: 75000 | Q17: 75000 | R17: 7500 | S17: 75000 | U17: 75000 | W17: 75000 | Y17: 75000
A18: =1+A17 -> 14 | B18: TCHOUAMOU MATHIEU | C18: 75000 | E18: 75000 | G18: 75000 | H18: 7500 | I18: 75000 | K18: 75000 | M18: 75000 | O18: 75000 | Q18: 75000 | S18: 75000 | U18: 75000 | W18: 75000 | Y18: 75000
A19: =1+A18 -> 15 | B19: YOUMBI EMMANUEL 1 | C19: 75000 | E19: 75000 | G19: 75000 | I19: 75000 | K19: 75000 | M19: 75000 | O19: 75000 | Q19: 75000 | S19: 75000 | U19: 75000 | W19: 75000 | X19: 7500 | Y19: 75000
A20: =1+A19 -> 16 | B20: YOUMBI EMMANUEL 2 | C20: 75000 | E20: 75000 | G20: 75000 | I20: 75000 | K20: 75000 | M20: 75000 | N20: 7500 | O20: 75000 | Q20: 75000 | S20: 75000 | U20: 75000 | W20: 75000 | Y20: 75000
A21: =1+A20 -> 17 | B21: ASELBY | C21: 75000 | E21: 75000 | G21: 75000 | I21: 75000 | K21: 75000 | M21: 75000 | O21: 75000 | Q21: 75000 | S21: 75000 | U21: 75000 | W21: 75000 | Y21: 75000 | Z21: 7500
A22: =1+A21 -> 18
A23: =1+A22 -> 19
A24: =1+A23 -> 20
B25: TOTAL | C25: =SUM(C5:C24) -> 1275000 | D25: =SUM(D5:D24) -> 37500 | E25: =SUM(E5:E24) -> 1275000 | F25: =SUM(F5:F24) -> 42000 | G25: =SUM(G5:G24) -> 1275000 | H25: =SUM(H5:H24) -> 15000 | I25: =SUM(I5:I24) -> 1275000 | J25: =SUM(J5:J24) -> 13000 | ... S25: =SUM(S5:S24) -> 1275000 | T25: =SUM(T5:T16) -> 15000 | U25: =SUM(U5:U24) -> 1275000 | V25: =SUM(V5:V24) -> 0 | W25: =SUM(W5:W24) -> 1275000 | X25: =SUM(X5:X24) -> 15000 | Y25: =SUM(Y5:Y24) -> 1275000 | Z25: =SUM(Z5:Z24) -> 7500 | AA25: =SUM(AA5:AA24) -> 0 | AB25: =SUM(AB5:AB24) -> 0 | AC25: =+Z25+X25+V25+T25+R25+P25+N25+L25+J25+H25+F25+D25 -> 200000 | AD25: =SUM(AD5:AD24) -> 0 | AE25: =SUM(AE5:AE24) -> 0 | AF25: =SUM(AF5:AF24) -> 0 | AI25: =SUM(AI5:AI16) -> 0 | AJ25: =SUM(AJ5:AJ16) -> 0
C26: reliquat Janvier | D26: 75000 | E26: reliquat Février | G26: RELIQUAT MARS | I26: reliquat AVRIL | K26: RELIQUAT MAI | M26: reliquat fev | O26: reliquat mar | Q26: reliquat avr | S26: reliquat avr | T26: 0 | U26: reliquat avr | AC26: =+F43+F59+F75+F90+F107+F121+F136+F151+F166+F181+F202+F218 -> 49500 | AI26: Reliquat Juil | AJ26: 0
AC27: =SUM(AC25:AC26) -> 249500
C28: REMBOURSEMENTS ET EMPRUNTS DES SOUS-PRODUITS | O28: BILAN DE LA TONTINE VENTE | AC28: =+AC27/17 -> 14676.471
B29: Dates | C29: Somme remboursée | E29: Somme empruntée | F29: Intérêt produit | G29: Montant à rembourser | H29: Solde en caisse | I29: Total disponible | K29: 44941 | O29: NOM | P29: Nbre de part | Q29: Mtant d'une part | R29: Net à percevoir
C30: Nom & Prénom | D30: Montant | J30: NOM | K30: Mt du lot | L30: Mt achat | M30: Net à percev | P30: 1 | Q30: =D248/P64 -> 159375 | R30: =P30*$Q$30 -> 159375
B31: 44941 | C31: Disponible | D31: =C25-M34 -> 480000 | J31: NGONDIEP CL | K31: 900000 | L31: 105000 | M31: =K31-L31 -> 795000 | P31: 1 | Q31: 0 | R31: =P31*$Q$30 -> 159375
C32: KOUATCHO | D32: 0 | E32: 50000 | F32: 1000 | G32: =E32+F32 -> 51000 | H32: 51000 | K32: 0 | L32: 0 | M32: =K32-L32 -> 0 | P32: 1 | Q32: 0 | R32: =P32*$Q$30 -> 159375
C33: KOUATCHO | D33: 0 | E33: 50000 | F33: 1000 | G33: =E33+F33 -> 51000 | H33: 51000 | K33: 0 | L33: 0 | M33: =K33-L33 -> 0 | P33: 1 | Q33: 0 | R33: =P33*$Q$30 -> 159375
C34: NGUIEMENI | D34: 0 | E34: 50000 | F34: 1000 | G34: =E34+F34 -> 51000 | H34: 51000 | L34: =SUM(L31:L33) -> 105000 | M34: =SUM(M31:M33) -> 795000 | P34: 1 | Q34: 0 | R34: =P34*$Q$30 -> 159375
C35: NGONDIEP | D35: 0 | E35: 50000 | F35: 1000 | G35: =E35+F35 -> 51000 | H35: 51000 | P35: 1 | Q35: 0 | R35: =P35*$Q$30 -> 159375
C36: NGONDIEP | D36: 0 | E36: 50000 | F36: 1000 | G36: =E36+F36 -> 51000 | H36: 51000 | P36: 1 | Q36: 0 | R36: =P36*$Q$30 -> 159375
C37: NGUIEMENI | D37: 0 | E37: 50000 | F37: 1000 | G37: =E37+F37 -> 51000 | H37: 51000 | P37: 1 | Q37: 0 | R37: =P37*$Q$30 -> 159375
C38: MBOGNING | D38: 0 | E38: 50000 | F38: 1000 | G38: =E38+F38 -> 51000 | H38: 51000 | P38: 1 | Q38: 0 | R38: =P38*$Q$30 -> 159375
C39: MBOGNING | D39: 0 | E39: 55000 | F39: 1000 | G39: =E39+F39 -> 56000 | H39: 56000 | P39: 1 | Q39: 0 | R39: =P39*$Q$30 -> 159375
C40: ASELBY | D40: 0 | E40: 75000 | F40: 0 | G40: =E40+F40 -> 75000 | H40: 75000 | P40: 1 | Q40: 0 | R40: =P40*$Q$30 -> 159375
D41: 0 | E41: 0 | F41: 0 | G41: =E41+F41 -> 0 | P41: 1 | Q41: 0 | R41: =P41*$Q$30 -> 159375
C42: TROP PERCU | D42: 0 | E42: 0 | F42: 0 | G42: =E42+F42 -> 0 | P42: 1 | Q42: 0 | R42: =P42*$Q$30 -> 159375
C43: Total | D43: =SUM(D32:D42) -> 0 | E43: =SUM(E32:E42) -> 480000 | F43: =SUM(F32:F42) -> 8000 | G43: =SUM(G32:G42) -> 488000 | H43: =SUM(H32:H42) -> 488000 | I43: =E25+D43+H43 -> 1763000 | K43: 12 fevrier 2023 | P43: 1 | Q43: 0 | R43: =P43*$Q$30 -> 159375
B44: 12 fevrier 2023 | C44: Disponible | D44: =I43-M49 -> 5000 | J44: NOM | K44: Mt du lot | L44: Mt achat | M44: Net à percev | P44: 1 | Q44: 0 | R44: =P44*$Q$30 -> 159375
C45: KOUATCHO | D45: 0 | E45: 100000 | F45: 2000 | G45: =E45+F45 -> 102000 | I45: 51000 | J45: BOGNING | K45: 900000 | L45: 22000 | M45: =K45-L45 -> 878000 | P45: 1 | Q45: 0 | R45: =P45*$Q$30 -> 159375
C46: NGUIEMENI | D46: 0 | E46: 100000 | F46: 2000 | G46: =E46+F46 -> 102000 | I46: 81000 | J46: HOTCHO | K46: 900000 | L46: 20000 | M46: =K46-L46 -> 880000 | P46: 0 | Q46: 0 | R46: =P46*$Q$30 -> 0
C47: NGONDIEP | D47: 0 | E47: 100000 | F47: 2000 | G47: =E47+F47 -> 102000 | K47: 0 | L47: 0 | M47: =K47-L47 -> 0 | P47: 0 | Q47: 0 | R47: =P47*$Q$30 -> 0
C48: BOGNING | D48: 0 | E48: 105000 | F48: 2000 | G48: =E48+F48 -> 107000 | K48: 0 | L48: 0 | M48: 0 | P48: 0 | Q48: 0 | R48: =P48*$Q$30 -> 0
D49: 0 | E49: 0 | F49: 0 | G49: =E49+F49 -> 0 | L49: =SUM(L45:L48) -> 42000 | M49: =SUM(M45:M48) -> 1758000 | P49: 0 | Q49: 0 | R49: =P49*$Q$30 -> 0
D50: 0 | E50: 0 | F50: 0 | G50: =E50+F50 -> 0 | P50: 0 | Q50: 0 | R50: =P50*$Q$30 -> 0
D51: 0 | E51: 0 | F51: 0 | G51: =E51+F51 -> 0 | P51: 0 | Q51: 0 | R51: =P51*$Q$30 -> 0
D52: 0 | E52: 0 | F52: 0 | G52: =E52+F52 -> 0 | P52: 0 | Q52: 0 | R52: 0
D53: 0 | E53: 0 | F53: 0 | G53: =E53+F53 -> 0
D54: 0 | E54: 0 | F54: 0 | G54: =E54+F54 -> 0
D55: 0 | E55: 0 | F55: 0 | G55: =E55+F55 -> 0
D56: 0 | E56: 0 | F56: 0 | G56: =E56+F56 -> 0
D57: 0 | E57: 0 | F57: 0 | G57: =E57+F57 -> 0
D58: 0 | E58: 0 | F58: 0 | G58: =E58+F58 -> 0 | P58: 0 | Q58: 0 | R58: =P58*$Q$30 -> 0
C59: Total | D59: =SUM(D45:D58) -> 0 | E59: =SUM(E45:E58) -> 405000 | F59: =SUM(F45:F58) -> 8000 | G59: =SUM(G45:G58) -> 413000 | H59: =D44-E59 -> -400000 | I59: =G25+D59+H59 -> 875000 | K59: 45004 | P59: 0 | Q59: 0 | R59: =P59*$Q$30 -> 0
B60: 45004 | C60: Disponible | D60: =I59-M68 -> -910000 | J60: NOM | K60: Mt du lot | L60: Mt achat | M60: Net à percev | P60: 0 | Q60: 0 | R60: =P60*$Q$30 -> 0
D61: 0 | E61: 0 | F61: 0 | G61: =E61+F61 -> 0 | J61: DJOUKWEU GUY | K61: 900000 | L61: 7500 | M61: =K61-L61 -> 892500 | O61: reliquat | Q61: 0 | R61: 0
D62: 0 | E62: 0 | F62: 0 | G62: =E62+F62 -> 0 | J62: TCHOUAMOU | K62: 900000 | L62: 7500 | M62: =K62-L62 -> 892500 | Q62: 0 | R62: =P62*$Q$30 -> 0
D63: 0 | E63: 0 | F63: 0 | G63: =E63+F63 -> 0 | J63: 0 | K63: 0 | L63: 0 | M63: 0
D64: 0 | E64: 0 | F64: 0 | G64: =E64+F64 -> 0 | K64: 0 | L64: 0 | M64: 0 | O64: TOTAL | P64: =SUM(P30:P62) -> 16 | Q64: ::::::::::::::::::: | R64: =SUM(R30:R62) -> 2550000
D65: 0 | E65: 0 | F65: 0 | G65: =E65+F65 -> 0
D66: 0 | E66: 0 | F66: 0 | G66: =E66+F66 -> 0
D67: 0 | E67: 0 | F67: 0 | G67: =E67+F67 -> 0
D68: 0 | E68: 0 | F68: 0 | G68: =E68+F68 -> 0 | L68: =SUM(L61:L64) -> 15000 | M68: =SUM(M61:M64) -> 1785000
D69: 0 | E69: 0 | F69: 0 | G69: =E69+F69 -> 0
D70: 0 | E70: 0 | F70: 0 | G70: =E70+F70 -> 0
D71: 0 | E71: 0 | F71: 0 | G71: 0
D72: 0 | E72: 0 | F72: 0 | G72: =E72+F72 -> 0
D73: 0 | E73: 0 | F73: 0 | G73: =E73+F73 -> 0
D74: 0 | E74: 0 | F74: 0 | G74: =E74+F74 -> 0
C75: Total | D75: =SUM(D61:D74) -> 0 | E75: =SUM(E61:E74) -> 0 | F75: =SUM(F61:F74) -> 0 | G75: =SUM(G61:G74) -> 0 | H75: =D60-E75 -> -910000 | I75: =I25+D75+H75 -> 365000 | K75: 45032
B76: 45032 | C76: Disponible | D76: =I75-M89 -> -522000 | J76: NOM | K76: Mt du lot | L76: Mt achat | M76: Net à percev
C77: Djoukweu | D77: 0 | E77: 100000 | F77: 1000 | G77: =E77+F77 -> 101000 | I77: 101000 | J77: kouatcho | K77: 900000 | L77: 13000 | M77: =K77-L77 -> 887000
C78: Tchouamou mat | D78: 0 | E78: 50000 | F78: 1000 | G78: =E78+F78 -> 51000 | I78: 51000 | K78: 0 | L78: 0 | M78: =K78-L78 -> 0
C79: kouatcho | D79: 0 | E79: 100000 | F79: 1000 | G79: =E79+F79 -> 101000 | I79: 101000 | K79: 0 | L79: 0 | M79: 0
C80: Djoukweu | D80: 0 | E80: 50000 | F80: 1000 | G80: =E80+F80 -> 51000 | I80: 51000
C81: Tchouamou mat | D81: 0 | E81: 88000 | F81: 1000 | G81: =E81+F81 -> 89000 | I81: 89000
D82: 0 | E82: 0 | F82: 0 | G82: =E82+F82 -> 0
D83: 0 | E83: 0 | F83: 0 | G83: =E83+F83 -> 0
D84: 0 | E84: 0 | F84: 0 | G84: =E84+F84 -> 0
D85: 0 | E85: 0 | F85: 0 | G85: =E85+F85 -> 0
D86: 0 | E86: 0 | F86: 0 | G86: =E86+F86 -> 0
D87: 0 | E87: 0 | F87: 0 | G87: =E87+F87 -> 0
D88: 0 | E88: 0 | F88: 0 | G88: =E88+F88 -> 0
D89: 0 | E89: 0 | F89: 0 | G89: =E89+F89 -> 0 | L89: =SUM(L77:L79) -> 13000 | M89: =SUM(M77:M79) -> 887000
C90: Total | D90: =SUM(D77:D89) -> 0 | E90: =SUM(E77:E89) -> 388000 | F90: =SUM(F77:F89) -> 5000 | G90: =SUM(G77:G89) -> 393000 | H90: =D76-E90 -> -910000 | I90: =K25+D90+H90 -> 365000 | K90: 45067
B91: 45067 | C91: Disponible | D91: =+I90-M99 -> -1410000 | J91: NOM | K91: Mt du lot | L91: Mt achat | M91: Net à percev
C92: Djoukweu | D92: 0 | E92: 100000 | F92: 2000 | G92: =E92+F92 -> 102000 | H92: 102000 | J92: nguiemeni | K92: 900000 | L92: 15000 | M92: =K92-L92 -> 885000
C93: Tchouamou mat | D93: 0 | E93: 100000 | F93: 2000 | G93: =E93+F93 -> 102000 | H93: 102000 | J93: Djumbissy | K93: 900000 | L93: 10000 | M93: =K93-L93 -> 890000
C94: NGUIEMENI | D94: 0 | E94: 50000 | F94: 1000 | G94: =E94+F94 -> 51000 | H94: 51000 | K94: 0 | L94: 0 | M94: =K94-L94 -> 0
C95: Djumbissy | D95: 0 | E95: 38000 | F95: 500 | G95: =E95+F95 -> 38500 | H95: 38500 | K95: 0 | L95: 0 | M95: =K95-L95 -> 0
D96: 0 | E96: 0 | F96: 0 | G96: =E96+F96 -> 0
D97: 0 | E97: 0 | F97: 0 | G97: =E97+F97 -> 0
D98: 0 | E98: 0 | F98: 0 | G98: =E98+F98 -> 0
D99: 0 | E99: 0 | F99: 0 | G99: =E99+F99 -> 0 | L99: =SUM(L92:L95) -> 25000 | M99: =SUM(M92:M95) -> 1775000
D100: 0 | E100: 0 | F100: 0 | G100: =E100+F100 -> 0
...

Sheet TONTINE DE 100 000 EXO 2023
B1: ANNEE 2023
F2: TOTINE AVEC RETENUE
B3: Date | C3: 44941 | E3: 12fevrier 2023 | G3: 45004 | I3: 45032 | K3: 45067 | M3: 45095 | O3: 45123 | Q3: 27 aout 2023 | S3: 45186 | U3: 45214 | W3: 45249 | Y3: 17 decembre 2023
B4: Nom et Prénom | C4: Cotisation | D4: Mtant achat | E4: Cotisation | F4: Mtant achat | G4: Cotisation | H4: Mtant achat | I4: Cotisation | J4: Mtant achat | K4: Cotisation | L4: Mtant achat | M4: Cotisation | N4: Mtant achat | O4: Cotisation | P4: Mtant achat | Q4: Cotisation | R4: Mtant achat | S4: Cotisation | T4: Mtant achat | U4: cotisation | V4: mtant achat | W4: cotisation | X4: mtant achat | Y4: cotisation | Z4: mtant achat
A5: 1 | B5: DJOMO JEAN PAUL | C5: 100000 | E5: 100000 | G5: 100000 | H5: 10000 | I5: 100000 | K5: 100000 | M5: 100000 | O5: 100000 | Q5: 100000 | S5: 100000 | U5: 100000
A6: =1+A5 -> 2 | B6: DJUOMBISSY ANTOINE 1 | C6: 100000 | E6: 100000 | G6: 100000 | H6: 10000 | I6: 100000 | K6: 100000 | M6: 100000 | O6: 100000 | Q6: 100000 | S6: 100000 | U6: 100000
A7: =1+A6 -> 3 | B7: DJUOMBISSY ANTOINE 2 | C7: 100000 | E7: 100000 | G7: 100000 | I7: 100000 | K7: 100000 | M7: 100000 | O7: 100000 | Q7: 100000 | R7: 10000 | S7: 100000 | U7: 100000
A8: =1+A7 -> 4 | B8: HOTCHO BENJAMIN | C8: 100000 | E8: 100000 | F8: 28000 | G8: 100000 | I8: 100000 | K8: 100000 | M8: 100000 | O8: 100000 | Q8: 100000 | S8: 100000 | U8: 100000
A9: =1+A8 -> 5 | B9: KOUAMOU MOISE | C9: 100000 | E9: 100000 | F9: 28000 | G9: 100000 | I9: 100000 | K9: 100000 | M9: 100000 | O9: 100000 | Q9: 100000 | S9: 100000 | U9: 100000
A10: =1+A9 -> 6 | B10: KOUATCHO | C10: 100000 | D10: 35000 | E10: 100000 | G10: 100000 | I10: 100000 | K10: 100000 | M10: 100000 | O10: 100000 | Q10: 100000 | S10: 100000 | U10: 100000
A11: =1+A10 -> 7 | B11: MBOGNING GUY | C11: 100000 | D11: 35000 | E11: 100000 | G11: 100000 | I11: 100000 | K11: 100000 | M11: 100000 | O11: 100000 | Q11: 100000 | S11: 100000 | U11: 100000
A12: =1+A11 -> 8 | B12: NDJOMO ETIENNE 1 | C12: 100000 | E12: 100000 | G12: 100000 | I12: 100000 | K12: 100000 | M12: 100000 | N12: 10000 | O12: 100000 | Q12: 100000 | S12: 100000 | U12: 100000
A13: =1+A12 -> 9 | B13: NDJOMO ETIENNE 2 | C13: 100000 | E13: 100000 | G13: 100000 | I13: 100000 | K13: 100000 | M13: 100000 | O13: 100000 | Q13: 100000 | R13: 10000 | S13: 100000 | U13: 100000
A14: =1+A13 -> 10 | B14: NGONDIEP CLAUDE | C14: 100000 | D14: 35000 | E14: 100000 | G14: 100000 | I14: 100000 | K14: 100000 | M14: 100000 | O14: 100000 | Q14: 100000 | S14: 100000 | U14: 100000
A15: =1+A14 -> 11 | B15: NGUIEMENI MATHIEU BALISE | C15: 100000 | E15: 100000 | G15: 100000 | I15: 100000 | J15: 20000 | K15: 100000 | M15: 100000 | O15: 100000 | Q15: 100000 | S15: 100000 | U15: 100000
A16: =1+A15 -> 12 | B16: SIME PIERRE | C16: 100000 | E16: 100000 | G16: 100000 | I16: 100000 | K16: 100000 | L16: 10000 | M16: 100000 | O16: 100000 | Q16: 100000 | S16: 100000 | U16: 100000
A17: =1+A16 -> 13 | B17: YOUMBI EMMANUEL | C17: 100000 | E17: 100000 | G17: 100000 | I17: 100000 | K17: 100000 | M17: 100000 | N17: 10000 | O17: 100000 | Q17: 100000 | S17: 100000 | U17: 100000
A18: =1+A17 -> 14 | B18: ASELBY | C18: 100000 | E18: 100000 | G18: 100000 | I18: 100000 | K18: 100000 | M18: 100000 | O18: 100000 | Q18: 100000 | S18: 100000 | U18: 100000 | X18: 10000
A19: =1+A18 -> 15
A20: =1+A19 -> 16
A21: =1+A20 -> 17
A22: =1+A21 -> 18
A23: =1+A22 -> 19
A24: =1+A23 -> 20
B25: TOTAL | C25: =SUM(C5:C24) -> 1400000 | D25: =SUM(D5:D24) -> 105000 | E25: =SUM(E5:E24) -> 1400000 | F25: =SUM(F5:F24) -> 56000 | G25: =SUM(G5:G24) -> 1400000 | H25: =SUM(H5:H24) -> 20000 | I25: =SUM(I5:I24) -> 1400000 | J25: =SUM(J5:J24) -> 20000 | ... S25: =SUM(S5:S24) -> 1400000 | T25: =SUM(T5:T16) -> 0 | U25: =SUM(U5:U24) -> 1400000 | V25: =SUM(V5:V24) -> 0 | W25: =SUM(W5:W24) -> 0 | X25: =SUM(X5:X24) -> 10000 | Y25: =SUM(Y5:Y24) -> 0 | Z25: =SUM(Z5:Z24) -> 0 | AA25: =+X25+V25+Z25+T25+R25+P25+N25+L25+J25+H25+F25+D25 -> 261000 | AB25: =SUM(AB5:AB24) -> 0 | AC25: =SUM(AC5:AC24) -> 0 | AD25: =SUM(AD5:AD24) -> 0 | AE25: =SUM(AE5:AE24) -> 0 | AF25: =SUM(AF5:AF24) -> 0 | AI25: =SUM(AI5:AI16) -> 0 | AJ25: =SUM(AJ5:AJ16) -> 0
C26: reliquat Janvier | D26: 250000 | E26: reliquat Février | G26: RELIQUAT MARS | I26: reliquat AVRIL | K26: RELIQUAT MAI | L26: 85500 | M26: reliquat fev | N26: 93500 | O26: reliquat mar | P26: 240500 | Q26: reliquat avr | R26: -53500 | S26: reliquat avr | T26: 0 | U26: reliquat avr | AA26: =+F43+F59+F75+F90+F107+F121+F136+F151+F166+F181+F202+F218 -> 76500 | AI26: Reliquat Juil | AJ26: 0
AA27: =SUM(AA25:AA26) -> 337500
C28: REMBOURSEMENTS ET EMPRUNTS DES SOUS-PRODUITS | O28: BILAN DE LA TONTINE VENTE | AA28: =+AA27/14 -> 24107.143
B29: Dates | C29: Somme remboursée | E29: Somme empruntée | F29: Intérêt produit | G29: Montant à rembourser | H29: Solde en caisse | I29: Total disponible | K29: 44941 | O29: NOM | P29: Nbre de part | Q29: Mtant d'une part | R29: Net à percevoir
C30: Nom & Prénom | D30: Montant | J30: NOM | K30: Mt du lot | L30: Mt achat | M30: Net à percev | P30: 1 | Q30: =D248/P64 -> 32625 | R30: =P30*$Q$30 -> 32625
B31: 44941 | C31: Disponible | D31: =C25-M34 -> -1825000 | J31: MBOGNING GUY | K31: 1200000 | L31: 125000 | M31: =K31-L31 -> 1075000 | P31: 1 | Q31: 0 | R31: =P31*$Q$30 -> 32625
C32: NGUIEMENI M B | D32: 0 | E32: 25000 | F32: 1000 | G32: =E32+F32 -> 26000 | H32: 26000 | J32: NGONDIEP CLAUDE | K32: 1200000 | L32: 125000 | M32: =K32-L32 -> 1075000 | P32: 1 | Q32: 0 | R32: =P32*$Q$30 -> 32625
C33: NGONDIEP CL | D33: 0 | E33: 100000 | F33: 4000 | G33: =E33+F33 -> 104000 | H33: 104000 | J33: KOUATCHO | K33: 1200000 | L33: 125000 | M33: =K33-L33 -> 1075000 | P33: 1 | Q33: 0 | R33: =P33*$Q$30 -> 32625
C34: DJOMO JEAN P | D34: 0 | E34: 50000 | F34: 2000 | G34: =E34+F34 -> 52000 | H34: 52000 | L34: =SUM(L31:L33) -> 375000 | M34: =SUM(M31:M33) -> 3225000 | P34: 1 | Q34: 0 | R34: =P34*$Q$30 -> 32625
C35: NGONDIEP CL | D35: 0 | E35: 100000 | F35: 4000 | G35: =E35+F35 -> 104000 | H35: 104000 | P35: 1 | Q35: 0 | R35: =P35*$Q$30 -> 32625
C36: NGUIEMENI M B | D36: 0 | E36: 50000 | F36: 2000 | G36: =E36+F36 -> 52000 | H36: 52000 | P36: 1 | Q36: 0 | R36: =P36*$Q$30 -> 32625
C37: ASELBY | D37: 0 | E37: 250000 | F37: 0 | G37: =E37+F37 -> 250000 | H37: 250000 | P37: 1 | Q37: 0 | R37: =P37*$Q$30 -> 32625
D38: 0 | E38: 0 | F38: 0 | G38: =E38+F38 -> 0 | P38: 1 | Q38: 0 | R38: =P38*$Q$30 -> 32625
D39: 0 | E39: 0 | F39: 0 | G39: =E39+F39 -> 0 | P39: 1 | Q39: 0 | R39: =P39*$Q$30 -> 32625
D40: 0 | E40: 0 | F40: 0 | G40: =E40+F40 -> 0 | P40: 1 | Q40: 0 | R40: =P40*$Q$30 -> 32625
D41: 0 | E41: 0 | F41: 0 | G41: =E41+F41 -> 0 | P41: 1 | Q41: 0 | R41: =P41*$Q$30 -> 32625
C42: TROP PERCU | D42: 0 | E42: 0 | F42: 0 | G42: =E42+F42 -> 0 | P42: 1 | Q42: 0 | R42: =P42*$Q$30 -> 32625
C43: Total | D43: =SUM(D32:D42) -> 0 | E43: =SUM(E32:E42) -> 575000 | F43: =SUM(F32:F42) -> 13000 | G43: =SUM(G32:G42) -> 588000 | H43: =SUM(H32:H42) -> 588000 | I43: =E25+D43+H43 -> 1988000 | K43: 12 fevrier 2023 | P43: 1 | Q43: 0 | R43: =P43*$Q$30 -> 32625
B44: 19 fevrier 2023 | C44: Disponible | D44: =I43-M49 -> -356000 | J44: NOM | K44: Mt du lot | L44: Mt achat | M44: Net à percev | P44: 1 | Q44: 0 | R44: =P44*$Q$30 -> 32625
D45: 0 | E45: 0 | F45: 0 | G45: =E45+F45 -> 0 | J45: KOUAMOU MOISE | K45: 1200000 | L45: 28000 | M45: =K45-L45 -> 1172000 | P45: 0 | Q45: 0 | R45: =P45*$Q$30 -> 0
D46: 0 | E46: 0 | F46: 0 | G46: =E46+F46 -> 0 | J46: HOTCHO BENJAMIN | K46: 1200000 | L46: 28000 | M46: =K46-L46 -> 1172000 | P46: 0 | Q46: 0 | R46: =P46*$Q$30 -> 0
D47: 0 | E47: 0 | F47: 0 | G47: =E47+F47 -> 0 | K47: 0 | L47: 0 | M47: =K47-L47 -> 0 | P47: 0 | Q47: 0 | R47: =P47*$Q$30 -> 0
D48: 0 | E48: 0 | F48: 0 | G48: =E48+F48 -> 0 | K48: 0 | L48: 0 | M48: 0 | P48: 0 | Q48: 0 | R48: =P48*$Q$30 -> 0
D49: 0 | E49: 0 | F49: 0 | G49: =E49+F49 -> 0 | L49: =SUM(L45:L48) -> 56000 | M49: =SUM(M45:M48) -> 2344000 | P49: 0 | Q49: 0 | R49: =P49*$Q$30 -> 0
D50: 0 | E50: 0 | F50: 0 | G50: =E50+F50 -> 0 | P50: 0 | Q50: 0 | R50: =P50*$Q$30 -> 0
D51: 0 | E51: 0 | F51: 0 | G51: =E51+F51 -> 0 | P51: 0 | Q51: 0 | R51: =P51*$Q$30 -> 0
D52: 0 | E52: 0 | F52: 0 | G52: =E52+F52 -> 0 | P52: 1 | Q52: 0 | R52: 0
D53: 0 | E53: 0 | F53: 0 | G53: =E53+F53 -> 0
D54: 0 | E54: 0 | F54: 0 | G54: =E54+F54 -> 0
D55: 0 | E55: 0 | F55: 0 | G55: =E55+F55 -> 0
D56: 0 | E56: 0 | F56: 0 | G56: =E56+F56 -> 0
D57: 0 | E57: 0 | F57: 0 | G57: =E57+F57 -> 0
D58: 0 | E58: 0 | F58: 0 | G58: =E58+F58 -> 0 | P58: 0 | Q58: 0 | R58: =P58*$Q$30 -> 0
C59: Total | D59: =SUM(D45:D58) -> 0 | E59: =SUM(E45:E58) -> 0 | F59: =SUM(F45:F58) -> 0 | G59: =SUM(G45:G58) -> 0 | H59: =D44-E59 -> -356000 | I59: =G25+D59+H59 -> 1044000 | K59: 45004 | P59: 0 | Q59: 0 | R59: =P59*$Q$30 -> 0
B60: 45004 | C60: Disponible | D60: =I59-M68 -> -1336000 | I60: 1064000 | J60: NOM | K60: Mt du lot | L60: Mt achat | M60: Net à percev | P60: 0 | Q60: 0 | R60: =P60*$Q$30 -> 0
C61: MBOGNING | D61: 0 | E61: 100000 | F61: 1000 | G61: =E61+F61 -> 101000 | H61: 101000 | J61: DJOMO Jean Paul | K61: 1200000 | L61: 10000 | M61: =K61-L61 -> 1190000 | O61: reliquat | Q61: 0 | R61: 0
C62: HOTCHO | D62: 0 | E62: 100000 | F62: 1000 | G62: =E62+F62 -> 101000 | H62: 101000 | J62: djuombissy antoine | K62: 1200000 | L62: 10000 | M62: =K62-L62 -> 1190000 | Q62: 0 | R62: =P62*$Q$30 -> 0
C63: KOUAMOU MOISE | D63: 0 | E63: 100000 | F63: 1000 | G63: =E63+F63 -> 101000 | H63: 101000 | J63: 0 | K63: 0 | L63: 0 | M63: 0
C64: MBOGNING | D64: 0 | E64: 100000 | F64: 1000 | G64: =E64+F64 -> 101000 | H64: 101000 | K64: 0 | L64: 0 | M64: 0 | O64: TOTAL | P64: =SUM(P30:P62) -> 16 | Q64: ::::::::::::::::::: | R64: =SUM(R30:R62) -> 489375
C65: KOUATCHO | D65: 0 | E65: 100000 | F65: 1000 | G65: =E65+F65 -> 101000 | H65: 101000
C66: KOUATCHO | D66: 0 | E66: 100000 | F66: 1000 | G66: =E66+F66 -> 101000 | H66: 101000
C67: NDJOMO ETIENNE | D67: 0 | E67: 100000 | F67: 1000 | G67: =E67+F67 -> 101000 | H67: 101000
C68: NDJOMO ETIENNE | D68: 0 | E68: 100000 | F68: 1000 | G68: =E68+F68 -> 101000 | H68: 101000 | L68: =SUM(L61:L64) -> 20000 | M68: =SUM(M61:M64) -> 2380000
C69: HOTCHO | D69: 0 | E69: 164000 | F69: 1000 | G69: =E69+F69 -> 165000 | H69: 164000
D70: 0 | E70: 0 | F70: 0 | G70: =E70+F70 -> 0
D71: 0 | E71: 0 | F71: 0 | G71: 0
D72: 0 | E72: 0 | F72: 0 | G72: =E72+F72 -> 0
D73: 0 | E73: 0 | F73: 0 | G73: =E73+F73 -> 0
D74: 0 | E74: 0 | F74: 0 | G74: =E74+F74 -> 0
C75: Total | D75: =SUM(D61:D74) -> 0 | E75: =SUM(E61:E74) -> 964000 | F75: =SUM(F61:F74) -> 9000 | G75: =SUM(G61:G74) -> 973000 | H75: =D60-E75 -> -2300000 | I75: =I25+D75+H75 -> -900000 | K75: 45032
B76: 45032 | C76: Disponible | D76: =I75-M89 -> -2080000 | J76: NOM | K76: Mt du lot | L76: Mt achat | M76: Net à percev
C77: NGUIEMENI M B | D77: 0 | E77: 93000 | F77: 6000 | G77: =E77+F77 -> 99000 | H77: 99000 | J77: Nguiemeni Mb | K77: 1200000 | L77: 20000 | M77: =K77-L77 -> 1180000
D78: 0 | E78: 0 | F78: 0 | G78: =E78+F78 -> 0 | K78: 0 | L78: 0 | M78: =K78-L78 -> 0
D79: 0 | E79: 0 | F79: 0 | G79: =E79+F79 -> 0 | K79: 0 | L79: 0 | M79: 0
D80: 0 | E80: 0 | F80: 0 | G80: =E80+F80 -> 0
D81: 0 | E81: 0 | F81: 0 | G81: =E81+F81 -> 0
D82: 0 | E82: 0 | F82: 0 | G82: =E82+F82 -> 0
D83: 0 | E83: 0 | F83: 0 | G83: =E83+F83 -> 0
D84: 0 | E84: 0 | F84: 0 | G84: =E84+F84 -> 0
D85: 0 | E85: 0 | F85: 0 | G85: =E85+F85 -> 0
D86: 0 | E86: 0 | F86: 0 | G86: =E86+F86 -> 0
D87: 0 | E87: 0 | F87: 0 | G87: =E87+F87 -> 0
D88: 0 | E88: 0 | F88: 0 | G88: =E88+F88 -> 0
D89: 0 | E89: 0 | F89: 0 | G89: =E89+F89 -> 0 | L89: =SUM(L77:L79) -> 20000 | M89: =SUM(M77:M79) -> 1180000
C90: Total | D90: =SUM(D77:D89) -> 0 | E90: =SUM(E77:E89) -> 93000 | F90: =SUM(F77:F89) -> 6000 | G90: =SUM(G77:G89) -> 99000 | H90: =D76-E90 -> -2173000 | I90: =K25+D90+H90 -> -773000 | K90: 45067
B91: 45067 | C91: Disponible | D91: =+I90-M99 -> -1963000 | J91: NOM | K91: Mt du lot | L91: Mt achat | M91: Net à percev
C92: djomo etienne | D92: 0 | E92: 200000 | F92: 2000 | G92: =E92+F92 -> 202000 | H92: 202000 | J92: sime pierre | K92: 1200000 | L92: 10000 | M92: =K92-L92 -> 1190000
C93: Djuimbissy | D93: 0 | E93: 200000 | F93: 2000 | G93: =E93+F93 -> 202000 | H93: 202000 | K93: 0 | L93: 0 | M93: =K93-L93 -> 0
C94: DJOMO JEAN P | D94: 0 | E94: 50000 | F94: 1000 | G94: =E94+F94 -> 51000 | H94: 51000 | K94: 0 | L94: 0 | M94: =K94-L94 -> 0
D95: 0 | E95: 0 | F95: 0 | G95: =E95+F95 -> 0 | K95: 0 | L95: 0 | M95: =K95-L95 -> 0
D96: 0 | E96: 0 | F96: 0 | G96: =E96+F96 -> 0
D97: 0 | E97: 0 | F97: 0 | G97: =E97+F97 -> 0
D98: 0 | E98: 0 | F98: 0 | G98: =E98+F98 -> 0
D99: 0 | E99: 0 | F99: 0 | G99: =E99+F99 -> 0 | L99: =SUM(L92:L95) -> 10000 | M99: =SUM(M92:M95) -> 1190000
D100: 0 | E100: 0 | F100: 0 | G100: =E100+F100 -> 0
...

Sheet EPARGNE 2023
B1: SITUATION FONDS DES MEMBRES DEC 2022 | F1: SITUATION FONDS DES MEMBRES DEC 2022 | K1: SITUATION FONDS DES MEMBRES DEC 2022 | P1: SITUATION FONDS DES MEMBRES DE2022 | V1: SITUATION FONDS DES MEMBRES DEC 2022 | AB1: SITUATION FONDS DES MEMBRES DEC 2022 | AI1: SITUATION FONDS DES MEMBRES DEC 2022 | AP1: SITUATION FONDS DES MEMBRES | AV1: SITUATION FONDS DES MEMBRES | BB1: SITUATION FONDS DES MEMBRES
A2: N° | B2: NOMS ET PRENOMS | C2: FONDS | D2: RECONDUCTIONS | E2: TOTAL | F2: DECEMBRE 2022 | H2: JANVIER 2023 | K2: FEVRIER 2023 | N2: MARS 2023 | Q2: AVRIL 2023 | T2: MAI 2023 | W2: JUIN 2023 | Z2: JUILLET 2023 | AC2: AOUT 2023 | AF2: SEPTEMBRE 2023 | AI2: OCTOBRE 2023 | AL2: NOVEMBRE 2023 | AO2: DECEMBRE 2023 | AR2: SYNTHESE ANNUELLE | AW2: OPERATION DE CASSATION
F3: 1268000 | H3: 0 | K3: =30000+0 -> 30000 | N3: =0+6000 -> 6000 | Q3: =10000+80000+12000+42000+60000 -> 204000 | T3: 30000 | W3: 74200 | Z3: 50000 | AC3: 64000 | AF3: 0 | AI3: 20000 | AL3: 0 | AR3: =+F3+H3+K3+N3+Q3+T3+W3+Z3+AC3+AF3+AI3+AL3+AO3 -> 1746200 | BE3: MONTANT DECHARGE | BF3: REPORT A NOUVEAU
F4: INTERET | G4: CUMUL | H4: EPARGNE | I4: INTERET | J4: CUMUL | K4: EPARGNE | L4: INTERET | M4: CUMUL | N4: EPARGNE | O4: INTERET | P4: CUMUL | Q4: EPARGNE | R4: INTERET | S4: CUMUL | T4: EPARGNE | U4: INTERET | V4: CUMUL | W4: EPARGNE | X4: INTERET | Y4: CUMUL | Z4: EPARGNE | AA4: INTERET | AB4: CUMUL | AC4: EPARGNE | AD4: INTERET | AE4: CUMUL | AF4: EPARGNE | AG4: INTERET | AH4: CUMUL | AI4: EPARGNE | AJ4: INTERET | AK4: CUMUL | AL4: EPARGNE | AM4: INTERET | AN4: CUMUL | AO4: EPARGNE | AP4: INTERET | AQ4: CUMUL | AR4: FONDS | AS4: RECONDUCTION | AT4: EPARGNE ANNUELLE | AU4: INTERET | AV4: CUMUL | AW4: RETRAIT FOND | AX4: RETRAIT MUTUEL | AY4: RETRAIT FOYER | AZ4: RETRAIT PENALITE | BA4: SAISIE REMB | BB4: RESTE | BC4: NOUVEAU FONDS | BD4: NAP
A5: AS201648 | B5: ASELBY | D5: =736543.521348481+80000 -> 816543.52 | E5: =+C5+D5 -> 816543.52 | F5: =+(1268000/19961560)*E5 -> 51868.551 | G5: =+E5+F5 -> 868412.07 | H5: 0 | I5: =+(0/(21229560+1050000))*(G5+H5) -> 0 | J5: =+G5+H5+I5 -> 868412.07 | K5: 0 | L5: =+(30000/((21638859-36000)+(328000-36000))*(J5+K5)) -> 1189.8849 | M5: =+J5+K5+L5 -> 869601.96 | N5: 0 | O5: =+(6000/(21996859-72000+345000-18000-19000-44000))*(M5+N5) -> 235.14556 | P5: =+M5+N5+O5 -> 869837.1 | Q5: 0 | R5: =+(204000/(22347859-54000-37000-62000+386000-18000-19000-66000))*(P5+Q5) -> 7894.2914 | S5: =+P5+Q5+R5 -> 877731.39 | T5: 0 | U5: =+((30000/(22937859+882000-36000-36000-56000-128000-6000-9000-409000-69000))*(S5+T5)) -> 1141.3507 | V5: =+S5+T5+U5 -> 878872.74 | W5: 0 | X5: =+(74200/(23849859+426500-42000-45000-465000-197000-9000-9000-14000-69000))*(V5+W5) -> 2783.7172 | Y5: =+V5+W5+X5 -> 881656.46 | Z5: 0 | AA5: =+(50000/(24350559+561768-51000-54000-479000-266000-9000-9000-19000-69000-153468))*(Y5+Z5) -> 1851.997 | AB5: =+Y5+Z5+AA5 -> 883508.46 | AC5: 0 | AD5: =+(64000/(24962327+403000-60000-63000-498000-335000-153468-9000-9000-19000-69000))*(AB5+AC5) -> 2341.4025 | AE5: =+AB5+AC5+AD5 -> 885849.86 | AF5: 0 | AG5: =+(0/20256265)*(AE5+AF5) -> 0 | AH5: =+AE5+AF5+AG5 -> 885849.86 | AI5: 0 | AJ5: =+((20000/(26194827+596000-60000-258500-9000-153468))*(AH5+AI5)) -> 673.39765 | AK5: =+AH5+AI5+AJ5 -> 886523.26 | AL5: 0 | AM5: =+(0/(23068716+171000))*(AK5+AL5) -> 0 | AN5: =+AK5+AL5+AM5 -> 886523.26 | AO5: 0 | AP5: =+(0/20000)*(AN5+AO5) -> 0 | AQ5: =+AN5+AO5+AP5 -> 886523.26 | AR5: =+C5 -> 0 | AS5: =+D5 -> 816543.52 | AT5: =+H5+K5+N5+Q5+T5+W5+Z5+AC5+AF5+AI5+AL5+AO5 -> 0 | AU5: =+F5+I5+L5+O5+R5+U5+X5+AA5+AD5+AG5+AJ5+AM5+AP5 -> 69979.738 | AV5: =+AN5+AO5+AP5 -> 886523.26 | BB5: =+AV5-AW5-AX5-AY5-AZ5-BA5 -> 886523.26 | BD5: =+BB5-BC5 -> 886523.26 | BE5: 0 | BF5: =+BD5-BE5 -> 886523.26 | BG5: 80000 DE NGANHOU JEAN
A6: AS201602 | B6: BOUTCHOUANG WILLIAM | C6: 600000 | D6: 7023.6611 | E6: =+C6+D6 -> 607023.66 | F6: =+(1268000/19961560)*E6 -> 38559.411 | G6: =+E6+F6 -> 645583.07 | H6: 9000 | I6: =+(0/(21229560+1050000))*(G6+H6) -> 0 | J6: =+G6+H6+I6 -> 654583.07 | K6: 9000 | L6: =+(30000/((21638859-36000)+(328000-36000))*(J6+K6)) -> 909.23135 | M6: =+J6+K6+L6 -> 664492.3 | N6: 9000 | O6: =+(6000/(21996859-72000+345000-18000-19000-44000))*(M6+N6) -> 182.11634 | P6: =+M6+N6+O6 -> 673674.42 | Q6: 9000 | R6: =+(204000/(22347859-54000-37000-62000+386000-18000-19000-66000))*(P6+Q6) -> 6195.6782 | S6: =+P6+Q6+R6 -> 688870.1 | T6: 9000 | U6: =+((30000/(22937859+882000-36000-36000-56000-128000-6000-9000-409000-69000))*(S6+T6)) -> 907.46959 | V6: =+S6+T6+U6 -> 698777.57 | W6: 9000 | X6: =+(74200/(23849859+426500-42000-45000-465000-197000-9000-9000-14000-69000))*(V6+W6) -> 2241.795 | Y6: =+V6+W6+X6 -> 710019.36 | Z6: 9000 | AA6: =+(50000/(24350559+561768-51000-54000-479000-266000-9000-9000-19000-69000-153468))*(Y6+Z6) -> 1510.3634 | AB6: =+Y6+Z6+AA6 -> 720529.73 | AC6: 9000 | AD6: =+(64000/(24962327+403000-60000-63000-498000-335000-153468-9000-9000-19000-69000))*(AB6+AC6) -> 1933.3406 | AE6: =+AB6+AC6+AD6 -> 731463.07 | AF6: 9000 | AG6: =+(0/20256265)*(AE6+AF6) -> 0 | AH6: =+AE6+AF6+AG6 -> 740463.07 | AI6: 9000 | AJ6: =+((20000/(26194827+596000-60000-258500-9000-153468))*(AH6+AI6)) -> 569.72032 | AK6: =+AH6+AI6+AJ6 -> 750032.79 | AL6: 9000 | AM6: =+(0/(23068716+171000))*(AK6+AL6) -> 0 | AN6: =+AK6+AL6+AM6 -> 759032.79 | AO6: 9000 | AP6: =+(0/20000)*(AN6+AO6) -> 0 | AQ6: =+AN6+AO6+AP6 -> 768032.79 | AR6: =+C6 -> 600000 | AS6: =+D6 -> 7023.6611 | AT6: =+H6+K6+N6+Q6+T6+W6+Z6+AC6+AF6+AI6+AL6+AO6 -> 108000 | AU6: =+F6+I6+L6+O6+R6+U6+X6+AA6+AD6+AG6+AJ6+AM6+AP6 -> 53009.126 | AV6: =+AN6+AO6+AP6 -> 768032.79 | AW6: 630000 | BB6: =+AV6-AW6-AX6-AY6-AZ6-BA6 -> 138032.79 | BD6: =+BB6 -> 138032.79 | BE6: 0 | BF6: =+BD6-BE6 -> 138032.79
A7: AS201604 | B7: DJOMO JEAN PAUL | C7: 600000 | D7: 4809.807 | E7: =+C7+D7 -> 604809.81 | F7: =+(1268000/19961560)*E7 -> 38418.783 | G7: =+E7+F7 -> 643228.59 | H7: 29000 | I7: =+(0/(21229560+1050000))*(G7+H7) -> 0 | J7: =+G7+H7+I7 -> 672228.59 | K7: 17000 | L7: =+(30000/((21638859-36000)+(328000-36000))*(J7+K7)) -> 944.37044 | M7: =+J7+K7+L7 -> 690172.96 | N7: 9000 | O7: =+(6000/(21996859-72000+345000-18000-19000-44000))*(M7+N7) -> 189.06054 | P7: =+M7+N7+O7 -> 699362.02 | Q7: 14000 | R7: =+(204000/(22347859-54000-37000-62000+386000-18000-19000-66000))*(P7+Q7) -> 6474.1865 | S7: =+P7+Q7+R7 -> 719836.21 | T7: 14000 | U7: =+((30000/(22937859+882000-36000-36000-56000-128000-6000-9000-409000-69000))*(S7+T7)) -> 954.23782 | V7: =+S7+T7+U7 -> 734790.44 | W7: 9000 | X7: =+(74200/(23849859+426500-42000-45000-465000-197000-9000-9000-14000-69000))*(V7+W7) -> 2355.8612 | Y7: =+V7+W7+X7 -> 746146.31 | Z7: 9000 | AA7: =+(50000/(24350559+561768-51000-54000-479000-266000-9000-9000-19000-69000-153468))*(Y7+Z7) -> 1586.2513 | AB7: =+Y7+Z7+AA7 -> 756732.56 | AC7: 9000 | AD7: =+(64000/(24962327+403000-60000-63000-498000-335000-153468-9000-9000-19000-69000))*(AB7+AC7) -> 2029.2824 | AE7: =+AB7+AC7+AD7 -> 767761.84 | AF7: 7000 | AG7: =+(0/20256265)*(AE7+AF7) -> 0 | AH7: =+AE7+AF7+AG7 -> 774761.84 | AI7: 9000 | AJ7: =+((20000/(26194827+596000-60000-258500-9000-153468))*(AH7+AI7)) -> 595.79327 | AK7: =+AH7+AI7+AJ7 -> 784357.63 | AL7: 9000 | AM7: =+(0/(23068716+171000))*(AK7+AL7) -> 0 | AN7: =+AK7+AL7+AM7 -> 793357.63 | AO7: 9000 | AP7: =+(0/20000)*(AN7+AO7) -> 0 | AQ7: =+AN7+AO7+AP7 -> 802357.63 | AR7: =+C7 -> 600000 | AS7: =+D7 -> 4809.807 | AT7: =+H7+K7+N7+Q7+T7+W7+Z7+AC7+AF7+AI7+AL7+AO7 -> 144000 | AU7: =+F7+I7+L7+O7+R7+U7+X7+AA7+AD7+AG7+AJ7+AM7+AP7 -> 53547.826 | AV7: =+AN7+AO7+AP7 -> 802357.63 | AW7: 630000 | BB7: =+AV7-AW7-AX7-AY7-AZ7-BA7 -> 172357.63 | BD7: =+BB7 -> 172357.63 | BE7: 0 | BF7: =+BD7-BE7 -> 172357.63
A8: AS201654 | B8: DJOMOU TCHANDA | C8: 600000 | D8: 48710.412 | E8: =+C8+D8 -> 648710.41 | F8: =+(1268000/19961560)*E8 -> 41207.441 | G8: =+E8+F8 -> 689917.85 | H8: 9000 | I8: =+(0/(21229560+1050000))*(G8+H8) -> 0 | J8: =+G8+H8+I8 -> 698917.85 | K8: 9000 | L8: =+(30000/((21638859-36000)+(328000-36000))*(J8+K8)) -> 969.97819 | M8: =+J8+K8+L8 -> 708887.83 | N8: 10000 | O8: =+(6000/(21996859-72000+345000-18000-19000-44000))*(M8+N8) -> 194.39156 | P8: =+M8+N8+O8 -> 719082.22 | Q8: 9000 | R8: =+(204000/(22347859-54000-37000-62000+386000-18000-19000-66000))*(P8+Q8) -> 6607.7812 | S8: =+P8+Q8+R8 -> 734690 | T8: 9000 | U8: =+((30000/(22937859+882000-36000-36000-56000-128000-6000-9000-409000-69000))*(S8+T8)) -> 967.05112 | V8: =+S8+T8+U8 -> 744657.06 | W8: 9000 | X8: =+(74200/(23849859+426500-42000-45000-465000-197000-9000-9000-14000-69000))*(V8+W8) -> 2387.1125 | Y8: =+V8+W8+X8 -> 756044.17 | Z8: 6000 | AA8: =+(50000/(24350559+561768-51000-54000-479000-266000-9000-9000-19000-69000-153468))*(Y8+Z8) -> 1600.7408 | AB8: =+Y8+Z8+AA8 -> 763644.91 | AC8: 9000 | AD8: =+(64000/(24962327+403000-60000-63000-498000-335000-153468-9000-9000-19000-69000))*(AB8+AC8) -> 2047.6009 | AE8: =+AB8+AC8+AD8 -> 774692.51 | AF8: 9000 | AG8: =+(0/20256265)*(AE8+AF8) -> 0 | AH8: =+AE8+AF8+AG8 -> 783692.51 | AI8: 9000 | AJ8: =+((20000/(26194827+596000-60000-258500-9000-153468))*(AH8+AI8)) -> 602.5821 | AK8: =+AH8+AI8+AJ8 -> 793295.09 | AL8: 9000 | AM8: =+(0/(23068716+171000))*(AK8+AL8) -> 0 | AN8: =+AK8+AL8+AM8 -> 802295.09 | AO8: 9000 | AP8: =+(0/20000)*(AN8+AO8) -> 0 | AQ8: =+AN8+AO8+AP8 -> 811295.09 | AR8: =+C8 -> 600000 | AS8: =+D8 -> 48710.412 | AT8: =+H8+K8+N8+Q8+T8+W8+Z8+AC8+AF8+AI8+AL8+AO8 -> 106000 | AU8: =+F8+I8+L8+O8+R8+U8+X8+AA8+AD8+AG8+AJ8+AM8+AP8 -> 56584.679 | AV8: =+AN8+AO8+AP8 -> 811295.09 | AW8: 630000 | BB8: =+AV8-AW8-AX8-AY8-AZ8-BA8 -> 181295.09 | BD8: =+BB8 -> 181295.09 | BE8: 0 | BF8: =+BD8-BE8 -> 181295.09
A9: AS201605 | B9: DJOUKWE NANGUEN GUY BLAISE | C9: 600000 | D9: 4750.0783 | E9: =+C9+D9 -> 604750.08 | F9: =+(1268000/19961560)*E9 -> 38414.989 | G9: =+E9+F9 -> 643165.07 | H9: 9000 | I9: =+(0/(21229560+1050000))*(G9+H9) -> 0 | J9: =+G9+H9+I9 -> 652165.07 | K9: 9000 | L9: =+(30000/((21638859-36000)+(328000-36000))*(J9+K9)) -> 905.91823 | M9: =+J9+K9+L9 -> 662070.99 | N9: 14000 | O9: =+(6000/(21996859-72000+345000-18000-19000-44000))*(M9+N9) -> 182.81363 | P9: =+M9+N9+O9 -> 676253.8 | Q9: 9000 | R9: =+(204000/(22347859-54000-37000-62000+386000-18000-19000-66000))*(P9+Q9) -> 6219.0876 | S9: =+P9+Q9+R9 -> 691472.89 | T9: 9000 | U9: =+((30000/(22937859+882000-36000-36000-56000-128000-6000-9000-409000-69000))*(S9+T9)) -> 910.8541 | V9: =+S9+T9+U9 -> 701383.74 | W9: 13000 | X9: =+(74200/(23849859+426500-42000-45000-465000-197000-9000-9000-14000-69000))*(V9+W9) -> 2262.7193 | Y9: =+V9+W9+X9 -> 716646.46 | Z9: 9000 | AA9: =+(50000/(24350559+561768-51000-54000-479000-266000-9000-9000-19000-69000-153468))*(Y9+Z9) -> 1524.2842 | AB9: =+Y9+Z9+AA9 -> 727170.74 | AC9: 9000 | AD9: =+(64000/(24962327+403000-60000-63000-498000-335000-153468-9000-9000-19000-69000))*(AB9+AC9) -> 1950.9401 | AE9: =+AB9+AC9+AD9 -> 738121.68 | AF9: 9500 | AG9: =+(0/20256265)*(AE9+AF9) -> 0 | AH9: =+AE9+AF9+AG9 -> 747621.68 | AI9: 9000 | AJ9: =+((20000/(26194827+596000-60000-258500-9000-153468))*(AH9+AI9)) -> 575.1621 | AK9: =+AH9+AI9+AJ9 -> 757196.85 | AL9: 9000 | AM9: =+(0/(23068716+171000))*(AK9+AL9) -> 0 | AN9: =+AK9+AL9+AM9 -> 766196.85 | AO9: 9000 | AP9: =+(0/20000)*(AN9+AO9) -> 0 | AQ9: =+AN9+AO9+AP9 -> 775196.85 | AR9: =+C9 -> 600000 | AS9: =+D9 -> 4750.0783 | AT9: =+H9+K9+N9+Q9+T9+W9+Z9+AC9+AF9+AI9+AL9+AO9 -> 117500 | AU9: =+F9+I9+L9+O9+R9+U9+X9+AA9+AD9+AG9+AJ9+AM9+AP9 -> 52946.768 | AV9: =+AN9+AO9+AP9 -> 775196.85 | AW9: 630000 | BB9: =+AV9-AW9-AX9-AY9-AZ9-BA9 -> 145196.85 | BD9: =+BB9 -> 145196.85 | BE9: 0 | BF9: =+BD9-BE9 -> 145196.85
A10: AS201608 | B10: DJUOMBESSY ANTOINE | C10: 600000 | D10: 10718.85 | E10: =+C10+D10 -> 610718.85 | F10: =+(1268000/19961560)*E10 -> 38794.137 | G10: =+E10+F10 -> 649512.99 | H10: 14000 | I10: =+(0/(21229560+1050000))*(G10+H10) -> 0 | J10: =+G10+H10+I10 -> 663512.99 | K10: 14000 | L10: =+(30000/((21638859-36000)+(328000-36000))*(J10+K10)) -> 928.3179 | M10: =+J10+K10+L10 -> 678441.31 | N10: 14000 | O10: =+(6000/(21996859-72000+345000-18000-19000-44000))*(M10+N10) -> 187.24026 | P10: =+M10+N10+O10 -> 692628.55 | Q10: 14000 | R10: =+(204000/(22347859-54000-37000-62000+386000-18000-19000-66000))*(P10+Q10) -> 6413.0762 | S10: =+P10+Q10+R10 -> 713041.62 | T10: 114000 | U10: =+((30000/(22937859+882000-36000-36000-56000-128000-6000-9000-409000-69000))*(S10+T10)) -> 1075.4367 | V10: =+S10+T10+U10 -> 828117.06 | W10: 43500 | X10: =+(74200/(23849859+426500-42000-45000-465000-197000-9000-9000-14000-69000))*(V10+W10) -> 2760.7357 | Y10: =+V10+W10+X10 -> 874377.79 | Z10: 25300 | AA10: =+(50000/(24350559+561768-51000-54000-479000-266000-9000-9000-19000-69000-153468))*(Y10+Z10) -> 1889.8524 | AB10: =+Y10+Z10+AA10 -> 901567.65 | AC10: 14000 | AD10: =+(64000/(24962327+403000-60000-63000-498000-335000-153468-9000-9000-19000-69000))*(AB10+AC10) -> 2426.3632 | AE10: =+AB10+AC10+AD10 -> 917994.01 | AF10: 14000 | AG10: =+(0/20256265)*(AE10+AF10) -> 0 | AH10: =+AE10+AF10+AG10 -> 931994.01 | AI10: 14000 | AJ10: =+((20000/(26194827+596000-60000-258500-9000-153468))*(AH10+AI10)) -> 719.11751 | AK10: =+AH10+AI10+AJ10 -> 946713.13 | AL10: 14000 | AM10: =+(0/(23068716+171000))*(AK10+AL10) -> 0 | AN10: =+AK10+AL10+AM10 -> 960713.13 | AO10: 14000 | AP10: =+(0/20000)*(AN10+AO10) -> 0 | AQ10: =+AN10+AO10+AP10 -> 974713.13 | AR10: =+C10 -> 600000 | AS10: =+D10 -> 10718.85 | AT10: =+H10+K10+N10+Q10+T10+W10+Z10+AC10+AF10+AI10+AL10+AO10 -> 308800 | AU10: =+F10+I10+L10+O10+R10+U10+X10+AA10+AD10+AG10+AJ10+AM10+AP10 -> 55194.277 | AV10: =+AN10+AO10+AP10 -> 974713.13 | AW10: 630000 | BB10: =+AV10-AW10-AX10-AY10-AZ10-BA10 -> 344713.13 | BD10: =+BB10 -> 344713.13 | BE10: 0 | BF10: =+BD10-BE10 -> 344713.13
A11: AS201651 | B11: DOMOU FABIEN | C11: 600000 | D11: 584.046 | E11: =+C11+D11 -> 600584.05 | F11: =+(1268000/19961560)*E11 -> 38150.353 | G11: =+E11+F11 -> 638734.4 | H11: 9000 | I11: =+(0/(21229560+1050000))*(G11+H11) -> 0 | J11: =+G11+H11+I11 -> 647734.4 | K11: 9000 | L11: =+(30000/((21638859-36000)+(328000-36000))*(J11+K11)) -> 899.8474 | M11: =+J11+K11+L11 -> 657634.25 | N11: 9000 | O11: =+(6000/(21996859-72000+345000-18000-19000-44000))*(M11+N11) -> 180.26188 | P11: =+M11+N11+O11 -> 666814.51 | Q11: 9000 | R11: =+(204000/(22347859-54000-37000-62000+386000-18000-19000-66000))*(P11+Q11) -> 6133.4204 | S11: =+P11+Q11+R11 -> 681947.93 | T11: 9000 | U11: =+((30000/(22937859+882000-36000-36000-56000-128000-6000-9000-409000-69000))*(S11+T11)) -> 898.4684 | V11: =+S11+T11+U11 -> 691846.4 | W11: 9000 | X11: =+(74200/(23849859+426500-42000-45000-465000-197000-9000-9000-14000-69000))*(V11+W11) -> 2219.8414 | Y11: =+V11+W11+X11 -> 703066.24 | Z11: 9000 | AA11: =+(50000/(24350559+561768-51000-54000-479000-266000-9000-9000-19000-69000-153468))*(Y11+Z11) -> 1495.7578 | AB11: =+Y11+Z11+AA11 -> 713562 | AC11: 9000 | AD11: =+(64000/(24962327+403000-60000-63000-498000-335000-153468-9000-9000-19000-69000))*(AB11+AC11) -> 1914.8753 | AE11: =+AB11+AC11+AD11 -> 724476.87 | AF11: 9000 | AG11: =+(0/20256265)*(AE11+AF11) -> 0 | AH11: =+AE11+AF11+AG11 -> 733476.87 | AI11: 9000 | AJ11: =+((20000/(26194827+596000-60000-258500-9000-153468))*(AH11+AI11)) -> 564.40962 | AK11: =+AH11+AI11+AJ11 -> 743041.28 | AL11: 9000 | AM11: =+(0/(23068716+171000))*(AK11+AL11) -> 0 | AN11: =+AK11+AL11+AM11 -> 752041.28 | AO11: 9000 | AP11: =+(0/20000)*(AN11+AO11) -> 0 | AQ11: =+AN11+AO11+AP11 -> 761041.28 | AR11: =+C11 -> 600000 | AS11: =+D11 -> 584.046 | AT11: =+H11+K11+N11+Q11+T11+W11+Z11+AC11+AF11+AI11+AL11+AO11 -> 108000 | AU11: =+F11+I11+L11+O11+R11+U11+X11+AA11+AD11+AG11+AJ11+AM11+AP11 -> 52457.236 | AV11: =+AN11+AO11+AP11 -> 761041.28 | AW11: 630000 | BB11: =+AV11-AW11-AX11-AY11-AZ11-BA11 -> 131041.28 | BD11: =+BB11 -> 131041.28 | BE11: 0 | BF11: =+BD11-BE11 -> 131041.28
A12: AS201609 | B12: DONHOU DAVID | C12: 600000 | D12: 458343.18 | E12: =+C12+D12 -> 1058343.2 | F12: =+(1268000/19961560)*E12 -> 67228.17 | G12: =+E12+F12 -> 1125571.3 | H12: 9000 | I12: =+(0/(21229560+1050000))*(G12+H12) -> 0 | J12: =+G12+H12+I12 -> 1134571.3 | K12: 9000 | L12: =+(30000/((21638859-36000)+(328000-36000))*(J12+K12)) -> 1566.9039 | M12: =+J12+K12+L12 -> 1145138.3 | N12: 9000 | O12: =+(6000/(21996859-72000+345000-18000-19000-44000))*(M12+N12) -> 312.08588 | P12: =+M12+N12+O12 -> 1154450.3 | Q12: 9000 | R12: =+(204000/(22347859-54000-37000-62000+386000-18000-19000-66000))*(P12+Q12) -> 10559.007 | S12: =+P12+Q12+R12 -> 1174009.3 | T12: 9000 | U12: =+((30000/(22937859+882000-36000-36000-56000-128000-6000-9000-409000-69000))*(S12+T12)) -> 1538.3164 | V12: =+S12+T12+U12 -> 1184547.7 | W12: 9000 | X12: =+(74200/(23849859+426500-42000-45000-465000-197000-9000-9000-14000-69000))*(V12+W12) -> 3780.4098 | Y12: =+V12+W12+X12 -> 1197328.1 | Z12: 9000 | AA12: =+(50000/(24350559+561768-51000-54000-479000-266000-9000-9000-19000-69000-153468))*(Y12+Z12) -> 2533.9983 | AB12: =+Y12+Z12+AA12 -> 1208862.1 | AC12: 9000 | AD12: =+(64000/(24962327+403000-60000-63000-498000-335000-153468-9000-9000-19000-69000))*(AB12+AC12) -> 3227.4794 | AE12: =+AB12+AC12+AD12 -> 1221089.5 | AF12: 9000 | AG12: =+(0/20256265)*(AE12+AF12) -> 0 | AH12: =+AE12+AF12+AG12 -> 1230089.5 | AI12: 9000 | AJ12: =+((20000/(26194827+596000-60000-258500-9000-153468))*(AH12+AI12)) -> 941.92033 | AK12: =+AH12+AI12+AJ12 -> 1240031.5 | AL12: 9000 | AM12: =+(0/(23068716+171000))*(AK12+AL12) -> 0 | AN12: =+AK12+AL12+AM12 -> 1249031.5 | AO12: 9000 | AP12: =+(0/20000)*(AN12+AO12) -> 0 | AQ12: =+AN12+AO12+AP12 -> 1258031.5 | AR12: =+C12 -> 600000 | AS12: =+D12 -> 458343.18 | AT12: =+H12+K12+N12+Q12+T12+W12+Z12+AC12+AF12+AI12+AL12+AO12 -> 108000 | AU12: =+F12+I12+L12+O12+R12+U12+X12+AA12+AD12+AG12+AJ12+AM12+AP12 -> 91688.291 | AV12: =+AN12+AO12+AP12 -> 1258031.5 | AW12: 630000 | BB12: =+AV12-AW12-AX12-AY12-AZ12-BA12 -> 628031.47 | BD12: =+BB12 -> 628031.47 | BE12: 0 | BF12: =+BD12-BE12 -> 628031.47
A13: AS201611 | B13: HENGUE PAUL OMER | C13: 600000 | D13: 51112.01 | E13: =+C13+D13 -> 651112.01 | F13: =+(1268000/19961560)*E13 -> 41359.995 | G13: =+E13+F13 -> 692472.01 | H13: 9000 | I13: =+(0/(21229560+1050000))*(G13+H13) -> 0 | J13: =+G13+H13+I13 -> 701472.01 | K13: 9000 | L13: =+(30000/((21638859-36000)+(328000-36000))*(J13+K13)) -> 973.47785 | M13: =+J13+K13+L13 -> 711445.48 | N13: 9000 | O13: =+(6000/(21996859-72000+345000-18000-19000-44000))*(M13+N13) -> 194.81276 | P13: =+M13+N13+O13 -> 720640.3 | Q13: 9000 | R13: =+(204000/(22347859-54000-37000-62000+386000-18000-19000-66000))*(P13+Q13) -> 6621.9216 | S13: =+P13+Q13+R13 -> 736262.22 | T13: 9000 | U13: =+((30000/(22937859+882000-36000-36000-56000-128000-6000-9000-409000-69000))*(S13+T13)) -> 969.09554 | V13: =+S13+T13+U13 -> 746231.31 | W13: 9000 | X13: =+(74200/(23849859+426500-42000-45000-465000-197000-9000-9000-14000-69000))*(V13+W13) -> 2392.0987 | Y13: =+V13+W13+X13 -> 757623.41 | Z13: 9000 | AA13: =+(50000/(24350559+561768-51000-54000-479000-266000-9000-9000-19000-69000-153468))*(Y13+Z13) -> 1610.3599 | AB13: =+Y13+Z13+AA13 -> 768233.77 | AC13: 9000 | AD13: =+(64000/(24962327+403000-60000-63000-498000-335000-153468-9000-9000-19000-69000))*(AB13+AC13) -> 2059.762 | AE13: =+AB13+AC13+AD13 -> 779293.53 | AF13: 9000 | AG13: =+(0/20256265)*(AE13+AF13) -> 0 | AH13: =+AE13+AF13+AG13 -> 788293.53 | AI13: 9000 | AJ13: =+((20000/(26194827+596000-60000-258500-9000-153468))*(AH13+AI13)) -> 606.07967 | AK13: =+AH13+AI13+AJ13 -> 797899.61 | AL13: 9000 | AM13: =+(0/(23068716+171000))*(AK13+AL13) -> 0 | AN13: =+AK13+AL13+AM13 -> 806899.61 | AO13: 9000 | AP13: =+(0/20000)*(AN13+AO13) -> 0 | AQ13: =+AN13+AO13+AP13 -> 815899.61 | AR13: =+C13 -> 600000 | AS13: =+D13 -> 51112.01 | AT13: =+H13+K13+N13+Q13+T13+W13+Z13+AC13+AF13+AI13+AL13+AO13 -> 108000 | AU13: =+F13+I13+L13+O13+R13+U13+X13+AA13+AD13+AG13+AJ13+AM13+AP13 -> 56787.603 | AV13: =+AN13+AO13+AP13 -> 815899.61 | AW13: 630000 | BB13: =+AV13-AW13-AX13-AY13-AZ13-BA13 -> 185899.61 | BD13: =+BB13 -> 185899.61 | BE13: 0 | BF13: =+BD13-BE13 -> 185899.61
A14: AS201613 | B14: HOTCHO BENJAMIN | C14: 600000 | D14: 16229.566 | E14: =+C14+D14 -> 616229.57 | F14: =+(1268000/19961560)*E14 -> 39144.19 | G14: =+E14+F14 -> 655373.76 | H14: 44000 | I14: =+(0/(21229560+1050000))*(G14+H14) -> 0 | J14: =+G14+H14+I14 -> 699373.76 | K14: 44000 | L14: =+(30000/((21638859-36000)+(328000-36000))*(J14+K14)) -> 1018.5593 | M14: =+J14+K14+L14 -> 744392.32 | N14: 44000 | O14: =+(6000/(21996859-72000+345000-18000-19000-44000))*(M14+N14) -> 213.18599 | P14: =+M14+N14+O14 -> 788605.5 | Q14: 44000 | R14: =+(204000/(22347859-54000-37000-62000+386000-18000-19000-66000))*(P14+Q14) -> 7556.3924 | S14: =+P14+Q14+R14 -> 840161.89 | T14: 24000 | U14: =+((30000/(22937859+882000-36000-36000-56000-128000-6000-9000-409000-69000))*(S14+T14)) -> 1123.7057 | V14: =+S14+T14+U14 -> 865285.6 | W14: 44000 | X14: =+(74200/(23849859+426500-42000-45000-465000-197000-9000-9000-14000-69000))*(V14+W14) -> 2880.046 | Y14: =+V14+W14+X14 -> 912165.65 | Z14: 44000 | AA14: =+(50000/(24350559+561768-51000-54000-479000-266000-9000-9000-19000-69000-153468))*(Y14+Z14) -> 2008.5101 | AB14: =+Y14+Z14+AA14 -> 958174.16 | AC14: 44000 | AD14: =+(64000/(24962327+403000-60000-63000-498000-335000-153468-9000-9000-19000-69000))*(AB14+AC14) -> 2655.8808 | AE14: =+AB14+AC14+AD14 -> 1004830 | AF14: 44000 | AG14: =+(0/20256265)*(AE14+AF14) -> 0 | AH14: =+AE14+AF14+AG14 -> 1048830 | AI14: 44000 | AJ14: =+((20000/(26194827+596000-60000-258500-9000-153468))*(AH14+AI14)) -> 830.73804 | AK14: =+AH14+AI14+AJ14 -> 1093660.8 | AL14: 44000 | AM14: =+(0/(23068716+171000))*(AK14+AL14) -> 0 | AN14: =+AK14+AL14+AM14 -> 1137660.8 | AO14: 44000 | AP14: =+(0/20000)*(AN14+AO14) -> 0 | AQ14: =+AN14+AO14+AP14 -> 1181660.8 | AR14: =+C14 -> 600000 | AS14: =+D14 -> 16229.566 | AT14: =+H14+K14+N14+Q14+T14+W14+Z14+AC14+AF14+AI14+AL14+AO14 -> 508000 | AU14: =+F14+I14+L14+O14+R14+U14+X14+AA14+AD14+AG14+AJ14+AM14+AP14 -> 57431.208 | AV14: =+AN14+AO14+AP14 -> 1181660.8 | AW14: 630000 | BB14: =+AV14-AW14-AX14-AY14-AZ14-BA14 -> 551660.77 | BD14: =+BB14 -> 551660.77 | BE14: 0 | BF14: =+BD14-BE14 -> 551660.77
A15: AS201617 | B15: KOUAMOU MOISE | C15: 600000 | D15: 53292.832 | E15: =+C15+D15 -> 653292.83 | F15: =+(1268000/19961560)*E15 -> 41498.526 | G15: =+E15+F15 -> 694791.36 | H15: 9000 | I15: =+(0/(21229560+1050000))*(G15+H15) -> 0 | J15: =+G15+H15+I15 -> 703791.36 | K15: 9000 | L15: =+(30000/((21638859-36000)+(328000-36000))*(J15+K15)) -> 976.65579 | M15: =+J15+K15+L15 -> 713768.01 | N15: 9000 | O15: =+(6000/(21996859-72000+345000-18000-19000-44000))*(M15+N15) -> 195.44079 | P15: =+M15+N15+O15 -> 722963.45 | Q15: 9000 | R15: =+(204000/(22347859-54000-37000-62000+386000-18000-19000-66000))*(P15+Q15) -> 6643.0057 | S15: =+P15+Q15+R15 -> 738606.46 | T15: 9000 | U15: =+((30000/(22937859+882000-36000-36000-56000-128000-6000-9000-409000-69000))*(S15+T15)) -> 972.14385 | V15: =+S15+T15+U15 -> 748578.6 | W15: 9000 | X15: =+(74200/(23849859+426500-42000-45000-465000-197000-9000-9000-14000-69000))*(V15+W15) -> 2399.5335 | Y15: =+V15+W15+X15 -> 759978.14 | Z15: 9000 | AA15: =+(50000/(24350559+561768-51000-54000-479000-266000-9000-9000-19000-69000-153468))*(Y15+Z15) -> 1615.3062 | AB15: =+Y15+Z15+AA15 -> 770593.44 | AC15: 9000 | AD15: =+(64000/(24962327+403000-60000-63000-498000-335000-153468-9000-9000-19000-69000))*(AB15+AC15) -> 2066.0154 | AE15: =+AB15+AC15+AD15 -> 781659.46 | AF15: 9000 | AG15: =+(0/20256265)*(AE15+AF15) -> 0 | AH15: =+AE15+AF15+AG15 -> 790659.46 | AI15: 9000 | AJ15: =+((20000/(26194827+596000-60000-258500-9000-153468))*(AH15+AI15)) -> 607.87818 | AK15: =+AH15+AI15+AJ15 -> 800267.34 | AL15: 9000 | AM15: =+(0/(23068716+171000))*(AK15+AL15) -> 0 | AN15: =+AK15+AL15+AM15 -> 809267.34 | AO15: 9000 | AP15: =+(0/20000)*(AN15+AO15) -> 0 | AQ15: =+AN15+AO15+AP15 -> 818267.34 | AR15: =+C15 -> 600000 | AS15: =+D15 -> 53292.832 | AT15: =+H15+K15+N15+Q15+T15+W15+Z15+AC15+AF15+AI15+AL15+AO15 -> 108000 | AU15: =+F15+I15+L15+O15+R15+U15+X15+AA15+AD15+AG15+AJ15+AM15+AP15 -> 56974.505 | AV15: =+AN15+AO15+AP15 -> 818267.34 | AW15: 630000 | BB15: =+AV15-AW15-AX15-AY15-AZ15-BA15 -> 188267.34 | BD15: =+BB15 -> 188267.34 | BE15: 0 | BF15: =+BD15-BE15 -> 188267.34
A16: AS201619 | B16: KOUATCHO MESSACK | C16: 600000 | D16: 6459.0432 | E16: =+C16+D16 -> 606459.04 | F16: =+(1268000/19961560)*E16 -> 38523.546 | G16: =+E16+F16 -> 644982.59 | H16: 9000 | I16: =+(0/(21229560+1050000))*(G16+H16) -> 0 | J16: =+G16+H16+I16 -> 653982.59 | K16: 9000 | L16: =+(30000/((21638859-36000)+(328000-36000))*(J16+K16)) -> 908.40858 | M16: =+J16+K16+L16 -> 663891 | N16: 8000 | O16: =+(6000/(21996859-72000+345000-18000-19000-44000))*(M16+N16) -> 181.68334 | P16: =+M16+N16+O16 -> 672072.68 | Q16: 11000 | R16: =+(204000/(22347859-54000-37000-62000+386000-18000-19000-66000))*(P16+Q16) -> 6199.2927 | S16: =+P16+Q16+R16 -> 689271.97 | T16: 8000 | U16: =+((30000/(22937859+882000-36000-36000-56000-128000-6000-9000-409000-69000))*(S16+T16)) -> 906.69182 | V16: =+S16+T16+U16 -> 698178.67 | W16: 9000 | X16: =+(74200/(23849859+426500-42000-45000-465000-197000-9000-9000-14000-69000))*(V16+W16) -> 2239.8981 | Y16: =+V16+W16+X16 -> 709418.56 | Z16: 9000 | AA16: =+(50000/(24350559+561768-51000-54000-479000-266000-9000-9000-19000-69000-153468))*(Y16+Z16) -> 1509.1014 | AB16: =+Y16+Z16+AA16 -> 719927.66 | AC16: 9000 | AD16: =+(64000/(24962327+403000-60000-63000-498000-335000-153468-9000-9000-19000-69000))*(AB16+AC16) -> 1931.745 | AE16: =+AB16+AC16+AD16 -> 730859.41 | AF16: 9000 | AG16: =+(0/20256265)*(AE16+AF16) -> 0 | AH16: =+AE16+AF16+AG16 -> 739859.41 | AI16: 9000 | AJ16: =+((20000/(26194827+596000-60000-258500-9000-153468))*(AH16+AI16)) -> 569.26144 | AK16: =+AH16+AI16+AJ16 -> 749428.67 | AL16: 9000 | AM16: =+(0/(23068716+171000))*(AK16+AL16) -> 0 | AN16: =+AK16+AL16+AM16 -> 758428.67 | AO16: 9000 | AP16: =+(0/20000)*(AN16+AO16) -> 0 | AQ16: =+AN16+AO16+AP16 -> 767428.67 | AR16: =+C16 -> 600000 | AS16: =+D16 -> 6459.0432 | AT16: =+H16+K16+N16+Q16+T16+W16+Z16+AC16+AF16+AI16+AL16+AO16 -> 108000 | AU16: =+F16+I16+L16+O16+R16+U16+X16+AA16+AD16+AG16+AJ16+AM16+AP16 -> 52969.628 | AV16: =+AN16+AO16+AP16 -> 767428.67 | AW16: 630000 | BB16: =+AV16-AW16-AX16-AY16-AZ16-BA16 -> 137428.67 | BD16: =+BB16 -> 137428.67 | BE16: 0 | BF16: =+BD16-BE16 -> 137428.67
A17: AS201620 | B17: LOWE JEAN | C17: 600000 | D17: 746.1759 | E17: =+C17+D17 -> 600746.18 | F17: =+(1268000/19961560)*E17 -> 38160.652 | G17: =+E17+F17 -> 638906.83 | H17: 9000 | I17: =+(0/(21229560+1050000))*(G17+H17) -> 0 | J17: =+G17+H17+I17 -> 647906.83 | K17: 9000 | L17: =+(30000/((21638859-36000)+(328000-36000))*(J17+K17)) -> 900.08366 | M17: =+J17+K17+L17 -> 657806.91 | N17: 9000 | O17: =+(6000/(21996859-72000+345000-18000-19000-44000))*(M17+N17) -> 180.30857 | P17: =+M17+N17+O17 -> 666987.22 | Q17: 9000 | R17: =+(204000/(22347859-54000-37000-62000+386000-18000-19000-66000))*(P17+Q17) -> 6134.9879 | S17: =+P17+Q17+R17 -> 682122.21 | T17: 9000 | U17: =+((30000/(22937859+882000-36000-36000-56000-128000-6000-9000-409000-69000))*(S17+T17)) -> 898.69503 | V17: =+S17+T17+U17 -> 692020.9 | W17: 9000 | X17: =+(74200/(23849859+426500-42000-45000-465000-197000-9000-9000-14000-69000))*(V17+W17) -> 2220.3942 | Y17: =+V17+W17+X17 -> 703241.3 | Z17: 9000 | AA17: =+(50000/(24350559+561768-51000-54000-479000-266000-9000-9000-19000-69000-153468))*(Y17+Z17) -> 1496.1255 | AB17: =+Y17+Z17+AA17 -> 713737.42 | AC17: 9000 | AD17: =+(64000/(24962327+403000-60000-63000-498000-335000-153468-9000-9000-19000-69000))*(AB17+AC17) -> 1915.3402 | AE17: =+AB17+AC17+AD17 -> 724652.76 | AF17: 9000 | AG17: =+(0/20256265)*(AE17+AF17) -> 0 | AH17: =+AE17+AF17+AG17 -> 733652.76 | AI17: 9000 | AJ17: =+((20000/(26194827+596000-60000-258500-9000-153468))*(AH17+AI17)) -> 564.54332 | AK17: =+AH17+AI17+AJ17 -> 743217.31 | AL17: 9000 | AM17: =+(0/(23068716+171000))*(AK17+AL17) -> 0 | AN17: =+AK17+AL17+AM17 -> 752217.31 | AO17: 9000 | AP17: =+(0/20000)*(AN17+AO17) -> 0 | AQ17: =+AN17+AO17+AP17 -> 761217.31 | AR17: =+C17 -> 600000 | AS17: =+D17 -> 746.1759 | AT17: =+H17+K17+N17+Q17+T17+W17+Z17+AC17+AF17+AI17+AL17+AO17 -> 108000 | AU17: =+F17+I17+L17+O17+R17+U17+X17+AA17+AD17+AG17+AJ17+AM17+AP17 -> 52471.131 | AV17: =+AN17+AO17+AP17 -> 761217.31 | AW17: 630000 | BB17: =+AV17-AW17-AX17-AY17-AZ17-BA17 -> 131217.31 | BD17: =+BB17 -> 131217.31 | BE17: 0 | BF17: =+BD17-BE17 -> 131217.31
... A24: AS201628 | B24: NKAMGANG JUSTIN DEJOLIE | C24: 600000 | D24: 575.28053 | E24: =+C24+D24 -> 600575.28 | F24: =+(1268000/19961560)*E24 -> 38149.797 | G24: =+E24+F24 -> 638725.08 | H24: 9000 | I24: =+(0/(21229560+1050000))*(G24+H24) -> 0 | J24: =+G24+H24+I24 -> 647725.08 | K24: 9000 | L24: =+(30000/((21638859-36000)+(328000-36000))*(J24+K24)) -> 899.83463 | M24: =+J24+K24+L24 -> 657624.91 | N24: 9000 | O24: =+(6000/(21996859-72000+345000-18000-19000-44000))*(M24+N24) -> 180.25936 | P24: =+M24+N24+O24 -> 666805.17 | Q24: 9000 | R24: =+(204000/(22347859-54000-37000-62000+386000-18000-19000-66000))*(P24+Q24) -> 6133.3357 | S24: =+P24+Q24+R24 -> 681938.51 | T24: 9000 | U24: =+((30000/(22937859+882000-36000-36000-56000-128000-6000-9000-409000-69000))*(S24+T24)) -> 898.45615 | V24: =+S24+T24+U24 -> 691836.96 | W24: 9000 | X24: =+(74200/(23849859+426500-42000-45000-465000-197000-9000-9000-14000-69000))*(V24+W24) -> 2219.8116 | Y24: =+V24+W24+X24 -> 703056.77 | Z24: 9000 | AA24: =+(50000/(24350559+561768-51000-54000-479000-266000-9000-9000-19000-69000-153468))*(Y24+Z24) -> 1495.7379 | AB24: =+Y24+Z24+AA24 -> 713552.51 | AC24: 9000 | AD24: =+(64000/(24962327+403000-60000-63000-498000-335000-153468-9000-9000-19000-69000))*(AB24+AC24) -> 1914.8501 | AE24: =+AB24+AC24+AD24 -> 724467.36 | AF24: 9000 | AG24: =+(0/20256265)*(AE24+AF24) -> 0 | AH24: =+AE24+AF24+AG24 -> 733467.36 | AI24: 9000 | AJ24: =+((20000/(26194827+596000-60000-258500-9000-153468))*(AH24+AI24)) -> 564.40239 | AK24: =+AH24+AI24+AJ24 -> 743031.77 | AL24: 7000 | AM24: =+(0/(23068716+171000))*(AK24+AL24) -> 0 | AN24: =+AK24+AL24+AM24 -> 750031.77 | AO24: 9000 | AP24: =+(0/20000)*(AN24+AO24) -> 0 | AQ24: =+AN24+AO24+AP24 -> 759031.77 | AR24: =+C24 -> 600000 | AS24: =+D24 -> 575.28053 | AT24: =+H24+K24+N24+Q24+T24+W24+Z24+AC24+AF24+AI24+AL24+AO24 -> 106000 | AU24: =+F24+I24+L24+O24+R24+U24+X24+AA24+AD24+AG24+AJ24+AM24+AP24 -> 52456.485 | AV24: =+AN24+AO24+AP24 -> 759031.77 | AW24: 630000 | BB24: =+AV24-AW24-AX24-AY24-AZ24-BA24 -> 129031.77 | BD24: =+BB24 -> 129031.77 | BE24: 0 | BF24: =+BD24-BE24 -> 129031.77
B25: NKEPSEU DIEUDONNE | C25: 600000 | D25: 2433.371 | E25: =+C25+D25 -> 602433.37 | F25: =+(1268000/19961560)*E25 -> 38267.826 | G25: =+E25+F25 -> 640701.2 | H25: -640701 | I25: =+(0/(21229560+1050000))*(G25+H25) -> 0 | J25: =+G25+H25+I25 -> 0.19748429 | K25: 0 | L25: =+(30000/((21638859-36000)+(328000-36000))*(J25+K25)) -> 0.00027058994 | M25: =+J25+K25+L25 -> 0.19775488 | N25: 0 | O25: =+(6000/(21996859-72000+345000-18000-19000-44000))*(M25+N25) -> 5.34741e-05 | P25: =+M25+N25+O25 -> 0.19780835 | Q25: 0 | R25: =+(204000/(22347859-54000-37000-62000+386000-18000-19000-66000))*(P25+Q25) -> 0.001795229 | S25: =+P25+Q25+R25 -> 0.19960358 | T25: 0 | U25: =+((30000/(22937859+882000-36000-36000-56000-128000-6000-9000-409000-69000))*(S25+T25)) -> 0.00025955286 | V25: =+S25+T25+U25 -> 0.19986313 | W25: 0 | X25: =+(74200/(23849859+426500-42000-45000-465000-197000-9000-9000-14000-69000))*(V25+W25) -> 0.00063304095 | Y25: =+V25+W25+X25 -> 0.20049617 | Z25: 0 | AA25: =+(50000/(24350559+561768-51000-54000-479000-266000-9000-9000-19000-69000-153468))*(Y25+Z25) -> 0.00042115986 | AB25: =+Y25+Z25+AA25 -> 0.20091733 | AC25: 0 | AD25: =+(64000/(24962327+403000-60000-63000-498000-335000-153468-9000-9000-19000-69000))*(AB25+AC25) -> 0.00053245484 | AE25: =+AB25+AC25+AD25 -> 0.20144979 | AF25: 0 | AG25: =+(0/20256265)*(AE25+AF25) -> 0 | AH25: =+AE25+AF25+AG25 -> 0.20144979 | AI25: 0 | AJ25: =+((20000/(26194827+596000-60000-258500-9000-153468))*(AH25+AI25)) -> 0.00015313635 | AK25: =+AH25+AI25+AJ25 -> 0.20160292 | AL25: 0 | AM25: =+(0/(23068716+171000))*(AK25+AL25) -> 0 | AN25: =+AK25+AL25+AM25 -> 0.20160292 | AO25: 0 | AP25: =+(0/20000)*(AN25+AO25) -> 0 | AQ25: =+AN25+AO25+AP25 -> 0.20160292 | AR25: =+C25 -> 600000 | AS25: =+D25 -> 2433.371 | AT25: =+H25+K25+N25+Q25+T25+W25+Z25+AC25+AF25+AI25+AL25+AO25 -> -640701 | AU25: =+F25+I25+L25+O25+R25+U25+X25+AA25+AD25+AG25+AJ25+AM25+AP25 -> 38267.831 | AV25: =+AN25+AO25+AP25 -> 0.20160292 | AW25: 0 | BB25: =+AV25-AW25-AX25-AY25-AZ25-BA25 -> 0.20160292 | BD25: =+BB25 -> 0.20160292 | BE25: 0 | BF25: =+BD25-BE25 -> 0.20160292
A26: AS201633 | B26: PATEGO NJOSSU GUSTAVE | C26: 600000 | D26: 21451.963 | E26: =+C26+D26 -> 621451.96 | F26: =+(1268000/19961560)*E26 -> 39475.927 | G26: =+E26+F26 -> 660927.89 | H26: 9000 | I26: =+(0/(21229560+1050000))*(G26+H26) -> 0 | J26: =+G26+H26+I26 -> 669927.89 | K26: 9000 | L26: =+(30000/((21638859-36000)+(328000-36000))*(J26+K26)) -> 930.25658 | M26: =+J26+K26+L26 -> 679858.15 | N26: 9000 | O26: =+(6000/(21996859-72000+345000-18000-19000-44000))*(M26+N26) -> 186.27136 | P26: =+M26+N26+O26 -> 689044.42 | Q26: 9000 | R26: =+(204000/(22347859-54000-37000-62000+386000-18000-19000-66000))*(P26+Q26) -> 6335.1701 | S26: =+P26+Q26+R26 -> 704379.59 | T26: 9000 | U26: =+((30000/(22937859+882000-36000-36000-56000-128000-6000-9000-409000-69000))*(S26+T26)) -> 927.63723 | V26: =+S26+T26+U26 -> 714307.23 | W26: 9000 | X26: =+(74200/(23849859+426500-42000-45000-465000-197000-9000-9000-14000-69000))*(V26+W26) -> 2290.9833 | Y26: =+V26+W26+X26 -> 725598.21 | Z26: 9000 | AA26: =+(50000/(24350559+561768-51000-54000-479000-266000-9000-9000-19000-69000-153468))*(Y26+Z26) -> 1543.0882 | AB26: =+Y26+Z26+AA26 -> 736141.3 | AC26: 9000 | AD26: =+(64000/(24962327+403000-60000-63000-498000-335000-153468-9000-9000-19000-69000))*(AB26+AC26) -> 1974.7131 | AE26: =+AB26+AC26+AD26 -> 747116.01 | AF26: 9000 | AG26: =+(0/20256265)*(AE26+AF26) -> 0 | AH26: =+AE26+AF26+AG26 -> 756116.01 | AI26: 9000 | AJ26: =+((20000/(26194827+596000-60000-258500-9000-153468))*(AH26+AI26)) -> 581.61924 | AK26: =+AH26+AI26+AJ26 -> 765697.63 | AL26: 9000 | AM26: =+(0/(23068716+171000))*(AK26+AL26) -> 0 | AN26: =+AK26+AL26+AM26 -> 774697.63 | AO26: 9000 | AP26: =+(0/20000)*(AN26+AO26) -> 0 | AQ26: =+AN26+AO26+AP26 -> 783697.63 | AR26: =+C26 -> 600000 | AS26: =+D26 -> 21451.963 | AT26: =+H26+K26+N26+Q26+T26+W26+Z26+AC26+AF26+AI26+AL26+AO26 -> 108000 | AU26: =+F26+I26+L26+O26+R26+U26+X26+AA26+AD26+AG26+AJ26+AM26+AP26 -> 54245.666 | AV26: =+AN26+AO26+AP26 -> 783697.63 | AW26: 630000 | BB26: =+AV26-AW26-AX26-AY26-AZ26-BA26 -> 153697.63 | BD26: =+BB26 -> 153697.63 | BE26: 0 | BF26: =+BD26-BE26 -> 153697.63
A27: AS201653 | B27: SIME BRICE | C27: 600000 | D27: 200752.48 | E27: =+C27+D27 -> 800752.48 | F27: =+(1268000/19961560)*E27 -> 50865.471 | G27: =+E27+F27 -> 851617.95 | H27: 9000 | I27: =+(0/(21229560+1050000))*(G27+H27) -> 0 | J27: =+G27+H27+I27 -> 860617.95 | K27: 9000 | L27: =+(30000/((21638859-36000)+(328000-36000))*(J27+K27)) -> 1191.5372 | M27: =+J27+K27+L27 -> 870809.49 | N27: 9000 | O27: =+(6000/(21996859-72000+345000-18000-19000-44000))*(M27+N27) -> 237.90574 | P27: =+M27+N27+O27 -> 880047.39 | Q27: 9000 | R27: =+(204000/(22347859-54000-37000-62000+386000-18000-19000-66000))*(P27+Q27) -> 8068.6363 | S27: =+P27+Q27+R27 -> 897116.03 | T27: 9000 | U27: =+((30000/(22937859+882000-36000-36000-56000-128000-6000-9000-409000-69000))*(S27+T27)) -> 1178.2605 | V27: =+S27+T27+U27 -> 907294.29 | W27: 9000 | X27: =+(74200/(23849859+426500-42000-45000-465000-197000-9000-9000-14000-69000))*(V27+W27) -> 2902.2451 | Y27: =+V27+W27+X27 -> 919196.54 | Z27: 9000 | AA27: =+(50000/(24350559+561768-51000-54000-479000-266000-9000-9000-19000-69000-153468))*(Y27+Z27) -> 1949.7585 | AB27: =+Y27+Z27+AA27 -> 930146.29 | AC27: 9000 | AD27: =+(64000/(24962327+403000-60000-63000-498000-335000-153468-9000-9000-19000-69000))*(AB27+AC27) -> 2488.8494 | AE27: =+AB27+AC27+AD27 -> 941635.14 | AF27: 9000 | AG27: =+(0/20256265)*(AE27+AF27) -> 0 | AH27: =+AE27+AF27+AG27 -> 950635.14 | AI27: 9000 | AJ27: =+((20000/(26194827+596000-60000-258500-9000-153468))*(AH27+AI27)) -> 729.4871 | AK27: =+AH27+AI27+AJ27 -> 960364.63 | AL27: 9000 | AM27: =+(0/(23068716+171000))*(AK27+AL27) -> 0 | AN27: =+AK27+AL27+AM27 -> 969364.63 | AO27: 9000 | AP27: =+(0/20000)*(AN27+AO27) -> 0 | AQ27: =+AN27+AO27+AP27 -> 978364.63 | AR27: =+C27 -> 600000 | AS27: =+D27 -> 200752.48 | AT27: =+H27+K27+N27+Q27+T27+W27+Z27+AC27+AF27+AI27+AL27+AO27 -> 108000 | AU27: =+F27+I27+L27+O27+R27+U27+X27+AA27+AD27+AG27+AJ27+AM27+AP27 -> 69612.15 | AV27: =+AN27+AO27+AP27 -> 978364.63 | AW27: 630000 | BB27: =+AV27-AW27-AX27-AY27-AZ27-BA27 -> 348364.63 | BD27: =+BB27 -> 348364.63 | BE27: 0 | BF27: =+BD27-BE27 -> 348364.63
A28: AS201638 | B28: SIMO PIERRE | C28: 600000 | D28: 103606.47 | E28: =+C28+D28 -> 703606.47 | F28: =+(1268000/19961560)*E28 -> 44694.553 | G28: =+E28+F28 -> 748301.03 | H28: 119000 | I28: =+(0/(21229560+1050000))*(G28+H28) -> 0 | J28: =+G28+H28+I28 -> 867301.03 | K28: 9000 | L28: =+(30000/((21638859-36000)+(328000-36000))*(J28+K28)) -> 1200.6942 | M28: =+J28+K28+L28 -> 877501.72 | N28: 9000 | O28: =+(6000/(21996859-72000+345000-18000-19000-44000))*(M28+N28) -> 239.71536 | P28: =+M28+N28+O28 -> 886741.43 | Q28: 9000 | R28: =+(204000/(22347859-54000-37000-62000+386000-18000-19000-66000))*(P28+Q28) -> 8129.3887 | S28: =+P28+Q28+R28 -> 903870.82 | T28: 9000 | U28: =+((30000/(22937859+882000-36000-36000-56000-128000-6000-9000-409000-69000))*(S28+T28)) -> 1187.044 | V28: =+S28+T28+U28 -> 914057.87 | W28: 9000 | X28: =+(74200/(23849859+426500-42000-45000-465000-197000-9000-9000-14000-69000))*(V28+W28) -> 2923.6679 | Y28: =+V28+W28+X28 -> 925981.54 | Z28: 9000 | AA28: =+(50000/(24350559+561768-51000-54000-479000-266000-9000-9000-19000-69000-153468))*(Y28+Z28) -> 1964.011 | AB28: =+Y28+Z28+AA28 -> 936945.55 | AC28: 9000 | AD28: =+(64000/(24962327+403000-60000-63000-498000-335000-153468-9000-9000-19000-69000))*(AB28+AC28) -> 2506.8683 | AE28: =+AB28+AC28+AD28 -> 948452.41 | AF28: 9000 | AG28: =+(0/20256265)*(AE28+AF28) -> 0 | AH28: =+AE28+AF28+AG28 -> 957452.41 | AI28: 9000 | AJ28: =+((20000/(26194827+596000-60000-258500-9000-153468))*(AH28+AI28)) -> 734.6694 | AK28: =+AH28+AI28+AJ28 -> 967187.08 | AL28: 9500 | AM28: =+(0/(23068716+171000))*(AK28+AL28) -> 0 | AN28: =+AK28+AL28+AM28 -> 976687.08 | AO28: 9000 | AP28: =+(0/20000)*(AN28+AO28) -> 0 | AQ28: =+AN28+AO28+AP28 -> 985687.08 | AR28: =+C28 -> 600000 | AS28: =+D28 -> 103606.47 | AT28: =+H28+K28+N28+Q28+T28+W28+Z28+AC28+AF28+AI28+AL28+AO28 -> 218500 | AU28: =+F28+I28+L28+O28+R28+U28+X28+AA28+AD28+AG28+AJ28+AM28+AP28 -> 63580.612 | AV28: =+AN28+AO28+AP28 -> 985687.08 | AW28: 630000 | BB28: =+AV28-AW28-AX28-AY28-AZ28-BA28 -> 355687.08 | BD28: =+BB28 -> 355687.08 | BE28: 0 | BF28: =+BD28-BE28 -> 355687.08
A29: AS201641 | B29: TCHOUAMOU MATHIEU | C29: 600000 | D29: 4207.8699 | E29: =+C29+D29 -> 604207.87 | F29: =+(1268000/19961560)*E29 -> 38380.546 | G29: =+E29+F29 -> 642588.42 | H29: 9000 | I29: =+(0/(21229560+1050000))*(G29+H29) -> 0 | J29: =+G29+H29+I29 -> 651588.42 | K29: 9000 | L29: =+(30000/((21638859-36000)+(328000-36000))*(J29+K29)) -> 905.12812 | M29: =+J29+K29+L29 -> 661493.54 | N29: 9000 | O29: =+(6000/(21996859-72000+345000-18000-19000-44000))*(M29+N29) -> 181.30546 | P29: =+M29+N29+O29 -> 670674.85 | Q29: 9000 | R29: =+(204000/(22347859-54000-37000-62000+386000-18000-19000-66000))*(P29+Q29) -> 6168.4553 | S29: =+P29+Q29+R29 -> 685843.31 | T29: 9000 | U29: =+((30000/(22937859+882000-36000-36000-56000-128000-6000-9000-409000-69000))*(S29+T29)) -> 903.53372 | V29: =+S29+T29+U29 -> 695746.84 | W29: 9000 | X29: =+(74200/(23849859+426500-42000-45000-465000-197000-9000-9000-14000-69000))*(V29+W29) -> 2232.1956 | Y29: =+V29+W29+X29 -> 706979.03 | Z29: 9000 | AA29: =+(50000/(24350559+561768-51000-54000-479000-266000-9000-9000-19000-69000-153468))*(Y29+Z29) -> 1503.977 | AB29: =+Y29+Z29+AA29 -> 717483.01 | AC29: 9000 | AD29: =+(64000/(24962327+403000-60000-63000-498000-335000-153468-9000-9000-19000-69000))*(AB29+AC29) -> 1925.2664 | AE29: =+AB29+AC29+AD29 -> 728408.28 | AF29: 9000 | AG29: =+(0/20256265)*(AE29+AF29) -> 0 | AH29: =+AE29+AF29+AG29 -> 737408.28 | AI29: 9000 | AJ29: =+((20000/(26194827+596000-60000-258500-9000-153468))*(AH29+AI29)) -> 567.39816 | AK29: =+AH29+AI29+AJ29 -> 746975.68 | AL29: 9000 | AM29: =+(0/(23068716+171000))*(AK29+AL29) -> 0 | AN29: =+AK29+AL29+AM29 -> 755975.68 | AO29: 9000 | AP29: =+(0/20000)*(AN29+AO29) -> 0 | AQ29: =+AN29+AO29+AP29 -> 764975.68 | AR29: =+C29 -> 600000 | AS29: =+D29 -> 4207.8699 | AT29: =+H29+K29+N29+Q29+T29+W29+Z29+AC29+AF29+AI29+AL29+AO29 -> 108000 | AU29: =+F29+I29+L29+O29+R29+U29+X29+AA29+AD29+AG29+AJ29+AM29+AP29 -> 52767.806 | AV29: =+AN29+AO29+AP29 -> 764975.68 | AW29: 630000 | BB29: =+AV29-AW29-AX29-AY29-AZ29-BA29 -> 134975.68 | BD29: =+BB29 -> 134975.68 | BE29: 0 | BF29: =+BD29-BE29 -> 134975.68
A30: AS201646 | B30: YEPMOU JEAN JACQUES | C30: 600000 | D30: 914734.42 | E30: =+C30+D30 -> 1514734.4 | F30: =+(1268000/19961560)*E30 -> 96219.095 | G30: =+E30+F30 -> 1610953.5 | H30: 9000 | I30: =+(0/(21229560+1050000))*(G30+H30) -> 0 | J30: =+G30+H30+I30 -> 1619953.5 | K30: 9000 | L30: =+(30000/((21638859-36000)+(328000-36000))*(J30+K30)) -> 2231.9671 | M30: =+J30+K30+L30 -> 1631185.5 | N30: 3000 | O30: =+(6000/(21996859-72000+345000-18000-19000-44000))*(M30+N30) -> 441.89352 | P30: =+M30+N30+O30 -> 1634627.4 | Q30: 0 | R30: =+(204000/(22347859-54000-37000-62000+386000-18000-19000-66000))*(P30+Q30) -> 14835.22 | S30: =+P30+Q30+R30 -> 1649462.6 | T30: 17000 | U30: =+((30000/(22937859+882000-36000-36000-56000-128000-6000-9000-409000-69000))*(S30+T30)) -> 2166.9708 | V30: =+S30+T30+U30 -> 1668629.6 | W30: 9000 | X30: =+(74200/(23849859+426500-42000-45000-465000-197000-9000-9000-14000-69000))*(V30+W30) -> 5313.6774 | Y30: =+V30+W30+X30 -> 1682943.2 | Z30: 9000 | AA30: =+(50000/(24350559+561768-51000-54000-479000-266000-9000-9000-19000-69000-153468))*(Y30+Z30) -> 3554.0757 | AB30: =+Y30+Z30+AA30 -> 1695497.3 | AC30: 9000 | AD30: =+(64000/(24962327+403000-60000-63000-498000-335000-153468-9000-9000-19000-69000))*(AB30+AC30) -> 4517.1207 | AE30: =+AB30+AC30+AD30 -> 1709014.4 | AF30: 9000 | AG30: =+(0/20256265)*(AE30+AF30) -> 0 | AH30: =+AE30+AF30+AG30 -> 1718014.4 | AI30: 9000 | AJ30: =+((20000/(26194827+596000-60000-258500-9000-153468))*(AH30+AI30)) -> 1312.8268 | AK30: =+AH30+AI30+AJ30 -> 1728327.3 | AL30: 6000 | AM30: =+(0/(23068716+171000))*(AK30+AL30) -> 0 | AN30: =+AK30+AL30+AM30 -> 1734327.3 | AO30: 9000 | AP30: =+(0/20000)*(AN30+AO30) -> 0 | AQ30: =+AN30+AO30+AP30 -> 1743327.3 | AR30: =+C30 -> 600000 | AS30: =+D30 -> 914734.42 | AT30: =+H30+K30+N30+Q30+T30+W30+Z30+AC30+AF30+AI30+AL30+AO30 -> 98000 | AU30: =+F30+I30+L30+O30+R30+U30+X30+AA30+AD30+AG30+AJ30+AM30+AP30 -> 130592.85 | AV30: =+AN30+AO30+AP30 -> 1743327.3 | AW30: 630000 | BB30: =+AV30-AW30-AX30-AY30-AZ30-BA30 -> 1113327.3 | BD30: =+BB30 -> 1113327.3 | BE30: 0 | BF30: =+BD30-BE30 -> 1113327.3
A31: AS201647 | B31: YOUMBI EMMANUEL | C31: 600000 | D31: 1057774.2 | E31: =+C31+D31 -> 1657774.2 | F31: =+(1268000/19961560)*E31 -> 105305.28 | G31: =+E31+F31 -> 1763079.5 | H31: 9000 | I31: =+(0/(21229560+1050000))*(G31+H31) -> 0 | J31: =+G31+H31+I31 -> 1772079.5 | K31: 9000 | L31: =+(30000/((21638859-36000)+(328000-36000))*(J31+K31)) -> 2440.4078 | M31: =+J31+K31+L31 -> 1783519.9 | N31: 9000 | O31: =+(6000/(21996859-72000+345000-18000-19000-44000))*(M31+N31) -> 484.70809 | P31: =+M31+N31+O31 -> 1793004.6 | Q31: 9000 | R31: =+(204000/(22347859-54000-37000-62000+386000-18000-19000-66000))*(P31+Q31) -> 16354.269 | S31: =+P31+Q31+R31 -> 1818358.9 | T31: 9000 | U31: =+((30000/(22937859+882000-36000-36000-56000-128000-6000-9000-409000-69000))*(S31+T31)) -> 2376.191 | V31: =+S31+T31+U31 -> 1829735.1 | W31: 9000 | X31: =+(74200/(23849859+426500-42000-45000-465000-197000-9000-9000-14000-69000))*(V31+W31) -> 5823.9586 | Y31: =+V31+W31+X31 -> 1844559.1 | Z31: 9000 | AA31: =+(50000/(24350559+561768-51000-54000-479000-266000-9000-9000-19000-69000-153468))*(Y31+Z31) -> 3893.5639 | AB31: =+Y31+Z31+AA31 -> 1857452.6 | AC31: 9000 | AD31: =+(64000/(24962327+403000-60000-63000-498000-335000-153468-9000-9000-19000-69000))*(AB31+AC31) -> 4946.3215 | AE31: =+AB31+AC31+AD31 -> 1871398.9 | AF31: 9000 | AG31: =+(0/20256265)*(AE31+AF31) -> 0 | AH31: =+AE31+AF31+AG31 -> 1880398.9 | AI31: 9000 | AJ31: =+((20000/(26194827+596000-60000-258500-9000-153468))*(AH31+AI31)) -> 1436.2669 | AK31: =+AH31+AI31+AJ31 -> 1890835.2 | AL31: 9000 | AM31: =+(0/(23068716+171000))*(AK31+AL31) -> 0 | AN31: =+AK31+AL31+AM31 -> 1899835.2 | AO31: 9000 | AP31: =+(0/20000)*(AN31+AO31) -> 0 | AQ31: =+AN31+AO31+AP31 -> 1908835.2 | AR31: =+C31 -> 600000 | AS31: =+D31 -> 1057774.2 | AT31: =+H31+K31+N31+Q31+T31+W31+Z31+AC31+AF31+AI31+AL31+AO31 -> 108000 | AU31: =+F31+I31+L31+O31+R31+U31+X31+AA31+AD31+AG31+AJ31+AM31+AP31 -> 143060.97 | AV31: =+AN31+AO31+AP31 -> 1908835.2 | AW31: 630000 | BB31: =+AV31-AW31-AX31-AY31-AZ31-BA31 -> 1278835.2 | BD31: =+BB31 -> 1278835.2 | BE31: 0 | BF31: =+BD31-BE31 -> 1278835.2
A32: AS201601 | B32: BAKOP ACHILLE | C32: 0 | H32: 609000 | I32: =+(0/(21229560+1050000))*(G32+H32) -> 0 | J32: =+G32+H32+I32 -> 609000 | K32: 9000 | L32: =+(30000/((21638859-36000)+(328000-36000))*(J32+K32)) -> 846.77412 | M32: =+J32+K32+L32 -> 618846.77 | N32: 9000 | O32: =+(6000/(21996859-72000+345000-18000-19000-44000))*(M32+N32) -> 169.77352 | P32: =+M32+N32+O32 -> 628016.55 | Q32: 9000 | R32: =+(204000/(22347859-54000-37000-62000+386000-18000-19000-66000))*(P32+Q32) -> 5781.3058 | S32: =+P32+Q32+R32 -> 642797.85 | T32: 9000 | U32: =+((30000/(22937859+882000-36000-36000-56000-128000-6000-9000-409000-69000))*(S32+T32)) -> 847.55993 | V32: =+S32+T32+U32 -> 652645.41 | W32: 9000 | X32: =+(74200/(23849859+426500-42000-45000-465000-197000-9000-9000-14000-69000))*(V32+W32) -> 2095.6773 | Y32: =+V32+W32+X32 -> 663741.09 | Z32: 6000 | AA32: =+(50000/(24350559+561768-51000-54000-479000-266000-9000-9000-19000-69000-153468))*(Y32+Z32) -> 1406.8501 | AB32: =+Y32+Z32+AA32 -> 671147.94 | AC32: 9000 | AD32: =+(64000/(24962327+403000-60000-63000-498000-335000-153468-9000-9000-19000-69000))*(AB32+AC32) -> 1802.473 | AE32: =+AB32+AC32+AD32 -> 681950.41 | AF32: 9000 | AG32: =+(0/20256265)*(AE32+AF32) -> 0 | AH32: =+AE32+AF32+AG32 -> 690950.41 | AI32: 9000 | AJ32: =+((20000/(26194827+596000-60000-258500-9000-153468))*(AH32+AI32)) -> 532.08222 | AK32: =+AH32+AI32+AJ32 -> 700482.5 | AL32: 9000 | AM32: =+(0/(23068716+171000))*(AK32+AL32) -> 0 | AN32: =+AK32+AL32+AM32 -> 709482.5 | AO32: 9000 | AP32: =+(0/20000)*(AN32+AO32) -> 0 | AQ32: =+AN32+AO32+AP32 -> 718482.5 | AR32: =+C32 -> 0 | AS32: =+D32 -> 0 | AT32: =+H32+K32+N32+Q32+T32+W32+Z32+AC32+AF32+AI32+AL32+AO32 -> 705000 | AU32: =+F32+I32+L32+O32+R32+U32+X32+AA32+AD32+AG32+AJ32+AM32+AP32 -> 13482.496 | AV32: =+AN32+AO32+AP32 -> 718482.5 | AW32: 630000 | BB32: =+AV32-AW32-AX32-AY32-AZ32-BA32 -> 88482.496 | BD32: =+BB32 -> 88482.496 | BE32: 0 | BF32: =+BD32-BE32 -> 88482.496
A33: AS201643 | B33: TCHOUTOU NANA CLAUDE | C33: 0 | H33: 9000 | I33: =+(0/(21229560+1050000))*(G33+H33) -> 0 | J33: =+G33+H33+I33 -> 9000 | K33: 9000 | M33: =+J33+K33+L33 -> 18000 | N33: 9000 | O33: =+(0/(20587216+246000))*(M33+N33) -> 0 | P33: =+M33+N33+O33 -> 27000 | Q33: 9000 | R33: =+(0/20256265)*(P33+Q33) -> 0 | S33: =+P33+Q33+R33 -> 36000 | T33: 6000 | U33: =+(0/20256265)*(S33+T33) -> 0 | V33: =+S33+T33+U33 -> 42000 | W33: 9000 | X33: 0 | Y33: =+V33+W33+X33 -> 51000 | Z33: 9000 | AA33: =+(0/(22195216+233000))*(Y33+Z33) -> 0 | AB33: =+Y33+Z33+AA33 -> 60000 | AC33: 0 | AD33: =+(0/20256265)*(AB33+AC33) -> 0 | AE33: =+AB33+AC33+AD33 -> 60000 | AF33: 0 | AG33: =+(0/20256265)*(AE33+AF33) -> 0 | AH33: =+AE33+AF33+AG33 -> 60000 | AI33: 0 | AJ33: =+(0/20256265)*(AH33+AI33) -> 0 | AK33: =+AH33+AI33+AJ33 -> 60000 | AL33: 15000 | AM33: =+(0/(23068716+171000))*(AK33+AL33) -> 0 | AN33: =+AK33+AL33+AM33 -> 75000 | AO33: 9000 | AP33: =+(0/20000)*(AN33+AO33) -> 0 | AQ33: =+AN33+AO33+AP33 -> 84000 | AR33: =+C33 -> 0 | AS33: =+D33 -> 0 | AT33: =+H33+K33+N33+Q33+T33+W33+Z33+AC33+AF33+AI33+AL33+AO33 -> 84000 | AU33: =+F33+I33+L33+O33+R33+U33+X33+AA33+AD33+AG33+AJ33+AM33+AP33 -> 0 | AV33: =+AN33+AO33+AP33 -> 84000 | AW33: 630000 | BB33: =+AV33-AW33-AX33-AY33-AZ33-BA33 -> -546000 | BD33: =+BB33 -> -546000 | BE33: 0 | BF33: =+BD33-BE33 -> -546000
A34: AS201657 | B34: SEUMOU POLYCARPE | C34: 0 | H34: 9000 | I34: =+(0/(21229560+1050000))*(G34+H34) -> 0 | J34: =+G34+H34+I34 -> 9000 | K34: 9000 | M34: =+J34+K34+L34 -> 18000 | N34: 9000 | O34: =+(0/(20587216+246000))*(M34+N34) -> 0 | P34: =+M34+N34+O34 -> 27000 | Q34: 9000 | R34: =+(0/20256265)*(P34+Q34) -> 0 | S34: =+P34+Q34+R34 -> 36000 | T34: 9000 | U34: =+(0/20256265)*(S34+T34) -> 0 | V34: =+S34+T34+U34 -> 45000 | W34: 9000 | X34: 0 | Y34: =+V34+W34+X34 -> 54000 | Z34: 9000 | AA34: =+(0/(22195216+233000))*(Y34+Z34) -> 0 | AB34: =+Y34+Z34+AA34 -> 63000 | AC34: 9000 | AD34: =+(0/20256265)*(AB34+AC34) -> 0 | AE34: =+AB34+AC34+AD34 -> 72000 | AF34: =9000+177500 -> 186500 | AG34: =+(0/20256265)*(AE34+AF34) -> 0 | AH34: =+AE34+AF34+AG34 -> 258500 | AI34: 9000 | AJ34: =+(0/20256265)*(AH34+AI34) -> 0 | AK34: =+AH34+AI34+AJ34 -> 267500 | AL34: 9000 | AM34: =+(0/(23068716+171000))*(AK34+AL34) -> 0 | AN34: =+AK34+AL34+AM34 -> 276500 | AO34: 9000 | AP34: =+(0/20000)*(AN34+AO34) -> 0 | AQ34: =+AN34+AO34+AP34 -> 285500 | AR34: =+C34 -> 0 | AS34: =+D34 -> 0 | AT34: =+H34+K34+N34+Q34+T34+W34+Z34+AC34+AF34+AI34+AL34+AO34 -> 285500 | AU34: =+F34+I34+L34+O34+R34+U34+X34+AA34+AD34+AG34+AJ34+AM34+AP34 -> 0 | AV34: =+AN34+AO34+AP34 -> 285500 | AW34: 630000 | BB34: =+AV34-AW34-AX34-AY34-AZ34-BA34 -> -344500 | BD34: =+BB34 -> -344500 | BE34: 0 | BF34: =+BD34-BE34 -> -344500
A35: AS201656 | B35: NOUBE ETIENNE | C35: 0 | H35: 9000 | I35: =+(0/(21229560+1050000))*(G35+H35) -> 0 | J35: =+G35+H35+I35 -> 9000 | K35: 9000 | M35: =+J35+K35+L35 -> 18000 | N35: 19000 | O35: =+(0/(20587216+246000))*(M35+N35) -> 0 | P35: =+M35+N35+O35 -> 37000 | Q35: 19000 | R35: =+(0/20256265)*(P35+Q35) -> 0 | S35: =+P35+Q35+R35 -> 56000 | T35: 409000 | U35: =+(0/20256265)*(S35+T35) -> 0 | V35: =+S35+T35+U35 -> 465000 | W35: 14000 | X35: 0 | Y35: =+V35+W35+X35 -> 479000 | Z35: 19000 | AA35: =+(0/(22195216+233000))*(Y35+Z35) -> 0 | AB35: =+Y35+Z35+AA35 -> 498000 | AC35: 19000 | AD35: =+(0/20256265)*(AB35+AC35) -> 0 | AE35: =+AB35+AC35+AD35 -> 517000 | AF35: =19000+127500 -> 146500 | AG35: =+(0/20256265)*(AE35+AF35) -> 0 | AH35: =+AE35+AF35+AG35 -> 663500 | AI35: 19000 | AJ35: =+((20000/(26194827+596000-60000-258500-9000-153468))*(AH35+AI35)) -> 518.81692 | AK35: =+AH35+AI35+AJ35 -> 683018.82 | AL35: 19000 | AM35: =+(0/(23068716+171000))*(AK35+AL35) -> 0 | AN35: =+AK35+AL35+AM35 -> 702018.82 | AO35: 19000 | AP35: =+(0/20000)*(AN35+AO35) -> 0 | AQ35: =+AN35+AO35+AP35 -> 721018.82 | AR35: =+C35 -> 0 | AS35: =+D35 -> 0 | AT35: =+H35+K35+N35+Q35+T35+W35+Z35+AC35+AF35+AI35+AL35+AO35 -> 720500 | AU35: =+F35+I35+L35+O35+R35+U35+X35+AA35+AD35+AG35+AJ35+AM35+AP35 -> 518.81692 | AV35: =+AN35+AO35+AP35 -> 721018.82 | AW35: 630000 | BB35: =+AV35-AW35-AX35-AY35-AZ35-BA35 -> 91018.817 | BD35: =+BB35 -> 91018.817 | BE35: 0 | BF35: =+BD35-BE35 -> 91018.817
A36: AS201658 | B36: YANTCHOU GERVAIS | C36: 0 | H36: 9000 | I36: =+(0/(21229560+1050000))*(G36+H36) -> 0 | J36: =+G36+H36+I36 -> 9000 | K36: 9000 | M36: =+J36+K36+L36 -> 18000 | N36: 44000 | O36: =+(0/(20587216+246000))*(M36+N36) -> 0 | P36: =+M36+N36+O36 -> 62000 | Q36: 66000 | R36: =+(0/20256265)*(P36+Q36) -> 0 | S36: =+P36+Q36+R36 -> 128000 | T36: 69000 | U36: =+(0/20256265)*(S36+T36) -> 0 | V36: =+S36+T36+U36 -> 197000 | W36: 69000 | X36: 0 | Y36: =+V36+W36+X36 -> 266000 | Z36: 69000 | AA36: =+(0/(22195216+233000))*(Y36+Z36) -> 0 | AB36: =+Y36+Z36+AA36 -> 335000 | AC36: 69000 | AD36: =+(0/20256265)*(AB36+AC36) -> 0 | AE36: =+AB36+AC36+AD36 -> 404000 | AF36: 9000 | AG36: =+(0/20256265)*(AE36+AF36) -> 0 | AH36: =+AE36+AF36+AG36 -> 413000 | AI36: 276000 | AJ36: =+((20000/(26194827+596000-60000-258500-9000-153468))*(AH36+AI36)) -> 523.75803 | AK36: =+AH36+AI36+AJ36 -> 689523.76 | AL36: 39000 | AM36: =+(0/(23068716+171000))*(AK36+AL36) -> 0 | AN36: =+AK36+AL36+AM36 -> 728523.76 | AO36: 9000 | AP36: =+(0/20000)*(AN36+AO36) -> 0 | AQ36: =+AN36+AO36+AP36 -> 737523.76 | AR36: =+C36 -> 0 | AS36: =+D36 -> 0 | AT36: =+H36+K36+N36+Q36+T36+W36+Z36+AC36+AF36+AI36+AL36+AO36 -> 737000 | AU36: =+F36+I36+L36+O36+R36+U36+X36+AA36+AD36+AG36+AJ36+AM36+AP36 -> 523.75803 | AV36: =+AN36+AO36+AP36 -> 737523.76 | AW36: 630000 | BB36: =+AV36-AW36-AX36-AY36-AZ36-BA36 -> 107523.76 | BD36: =+BB36 -> 107523.76 | BE36: 0 | BF36: =+BD36-BE36 -> 107523.76
A37: AS201636 | B37: SIME FONGANG ERIC | I37: =+(0/(21229560+1050000))*(G37+H37) -> 0 | J37: =+G37+H37+I37 -> 0 | T37: 0 | U37: =+(0/20256265)*(S37+T37) -> 0 | V37: =+S37+T37+U37 -> 0 | W37: 0 | X37: =+(74200/(23849859+426500))*(V37+W37) -> 0 | Y37: =+V37+W37+X37 -> 0 | Z37: 153468 | AA37: =+(0/(22195216+233000))*(Y37+Z37) -> 0 | AB37: =+Y37+Z37+AA37 -> 153468 | AC37: 0 | AD37: =+(0/20256265)*(AB37+AC37) -> 0 | AE37: =+AB37+AC37+AD37 -> 153468 | AF37: 0 | AG37: =+(0/20256265)*(AE37+AF37) -> 0 | AH37: =+AE37+AF37+AG37 -> 153468 | AI37: 0 | AJ37: =+(0/20256265)*(AH37+AI37) -> 0 | AK37: =+AH37+AI37+AJ37 -> 153468 | AL37: 0 | AM37: =+(0/(23068716+171000))*(AK37+AL37) -> 0 | AN37: =+AK37+AL37+AM37 -> 153468 | AO37: 0 | AP37: =+(0/20000)*(AN37+AO37) -> 0 | AQ37: =+AN37+AO37+AP37 -> 153468 | AR37: =+C37 -> 0 | AS37: =+D37 -> 0 | AT37: =+H37+K37+N37+Q37+T37+W37+Z37+AC37+AF37+AI37+AL37+AO37 -> 153468 | AU37: =+F37+I37+L37+O37+R37+U37+X37+AA37+AD37+AG37+AJ37+AM37+AP37 -> 0 | AV37: =+AN37+AO37+AP37 -> 153468 | BB37: =+AV37-AW37-AX37-AY37-AZ37-BA37 -> 153468 | BD37: =+BB37 -> 153468 | BE37: 0 | BF37: =+BD37-BE37 -> 153468
I38: =+(0/(21229560+1050000))*(G38+H38) -> 0 | J38: =+G38+H38+I38 -> 0 | T38: 0 | U38: =+(0/20256265)*(S38+T38) -> 0 | V38: =+S38+T38+U38 -> 0 | W38: 0 | X38: =+(74200/(23849859+426500))*(V38+W38) -> 0 | Y38: =+V38+W38+X38 -> 0 | Z38: 0 | AA38: =+(0/(22195216+233000))*(Y38+Z38) -> 0 | AB38: =+Y38+Z38+AA38 -> 0 | AC38: 0 | AD38: =+(0/20256265)*(AB38+AC38) -> 0 | AE38: =+AB38+AC38+AD38 -> 0 | AF38: 0 | AG38: =+(0/20256265)*(AE38+AF38) -> 0 | AH38: =+AE38+AF38+AG38 -> 0 | AI38: 0 | AJ38: =+(0/20256265)*(AH38+AI38) -> 0 | AK38: =+AH38+AI38+AJ38 -> 0 | AL38: 0 | AM38: =+(0/(23068716+171000))*(AK38+AL38) -> 0 | AN38: =+AK38+AL38+AM38 -> 0 | AO38: 0 | AP38: =+(0/20000)*(AN38+AO38) -> 0 | AQ38: =+AN38+AO38+AP38 -> 0 | AR38: =+C38 -> 0 | AS38: =+D38 -> 0 | AT38: =+H38+K38+N38+Q38+T38+W38+Z38+AC38+AF38+AI38+AL38+AO38 -> 0 | AU38: =+F38+I38+L38+O38+R38+U38+X38+AA38+AD38+AG38+AJ38+AM38+AP38 -> 0 | AV38: =+AN38+AO38+AP38 -> 0 | BB38: =+AV38-AW38-AX38-AY38-AZ38-BA38 -> 0 | BD38: =+BB38 -> 0 | BE38: 0 | BF38: =+BD38-BE38 -> 0
A39: TOTAL 1 | C39: =SUM(C5:C36) -> 15600000 | D39: =SUM(D5:D31) -> 4361559.6 | E39: =SUM(E5:E31) -> 19961560 | F39: =SUM(F5:F31) -> 1268000 | G39: =SUM(G5:G31) -> 21229560 | H39: =SUM(H5:H36)+640701 -> 1050000 | I39: =SUM(I5:I31) -> 0 | J39: =SUM(J5:J38) -> 21638859 | K39: =SUM(K5:K38) -> 328000 | L39: =SUM(L5:L38) -> 29999.999 | M39: =SUM(M5:M38) -> 21996859 | N39: =SUM(N5:N38) -> 345000 | O39: =SUM(O5:O38) -> 5999.9999 | P39: =SUM(P5:P38) -> 22347859 | Q39: =SUM(Q5:Q38) -> 386000 | ... BA39: =SUM(BA5:BA38) -> 0 | BB39: =+AV39-AW39-AX39-AY39-AZ39-BA39 -> 8621326.5 | BD39: =+AX39-AY39-AZ39-BA39-BB39-BC39 -> -8621326.5 | BE39: =+AY39-AZ39-BA39-BB39-BC39-BD39 -> 0 | BF39: =SUM(BF5:BF38) -> 8621326.5
A40: 28 | B40: SIME FONGANG ERIC | C40: 0 | D40: 0 | E40: 0 | F40: 0 | G40: 0 | I40: 0 | J40: 0 | L40: 0 | M40: 0 | O40: 0 | P40: 0 | R40: 0 | S40: 0 | U40: 0 | V40: 0 | X40: 0 | Y40: 0 | Z40: 0 | AA40: 0 | AB40: 0 | AD40: 0 | AE40: 0 | AG40: 0 | AH40: 0 | AJ40: 0 | AK40: 0 | AM40: 0 | AN40: 0 | AP40: 0 | AQ40: 0 | AR40: 0 | AS40: 0 | AT40: 0 | AU40: 0 | AV40: 0 | BA40: 0 | BB40: 0 | BF40: =+BD40-BE40 -> 0
A41: 29 | B41: TIEYAM ERNEST | C41: 0 | E41: 0 | F41: 0 | G41: 0 | I41: 0 | J41: 0 | L41: 0 | M41: 0 | O41: 0 | P41: 0 | R41: 0 | S41: 0 | U41: 0 | V41: 0 | X41: 0 | Y41: 0 | AA41: 0 | AB41: 0 | AD41: 0 | AE41: 0 | AG41: 0 | AH41: 0 | AJ41: 0 | AK41: 0 | AM41: 0 | AN41: 0 | AP41: 0 | AQ41: 0 | AR41: 0 | AS41: 0 | AT41: 0 | AU41: 0 | AV41: 0 | BA41: 0 | BB41: 0 | BF41: =+BD41-BE41 -> 0
A42: AS201601 | B42: BAKOP ACHILLE | C42: 536000 | E42: 536000 | F42: 0 | G42: 536000 | H42: -536000 | I42: 0 | J42: 0 | M42: 0 | P42: 0 | S42: 0 | V42: 0 | Y42: 0 | AB42: 0 | AE42: 0 | AH42: 0 | AK42: 0 | AN42: 0 | AP42: 0 | AQ42: 0 | AR42: 0 | AS42: 0 | AT42: 0 | AU42: 0 | AV42: 0 | BB42: 0 | BD42: 536000 | BF42: =+BD42-BE42 -> 536000
A43: 31 | B43: NGONGANG JEAN THEODORE | C43: 257476 | E43: 257476 | F43: 0 | G43: 257476 | H43: -257476 | I43: 0 | J43: =+G43+H43+I43 -> 0 | M43: 0 | P43: 0 | S43: 0 | V43: 0 | Y43: 0 | AB43: 0 | AE43: 0 | AH43: 0 | AK43: 0 | AN43: 0 | AP43: 0 | AQ43: 0 | AR43: 0 | AS43: 0 | AT43: 0 | AU43: 0 | AV43: 0 | BB43: 257476 | BD43: 257476 | BF43: =+BD43-BE43 -> 257476
A44: 32 | B44: NGANHOU JEAN | C44: 0 | E44: 0 | F44: 0 | G44: 0 | I44: 0 | J44: 0 | M44: 0 | P44: 0 | S44: 0 | V44: 0 | Y44: 0 | AB44: 0 | AE44: 0 | AH44: 0 | AK44: 0 | AN44: 0 | AP44: 0 | AQ44: 0 | AR44: 0 | AS44: 0 | AT44: 0 | AU44: 0 | AV44: 0 | BB44: 0 | BD44: 80000 | BF44: =+BD44-BE44 -> 80000
A45: =+A44+1 -> 33 | B45: FOTSO THOMAS | C45: 0 | D45: 0 | E45: =+C45+D45 -> 0 | F45: =+(0/18229032)*E45 -> 0 | G45: =+E45+F45 -> 0 | I45: =+(0/19121232)*(G45+H45) -> 0 | J45: =+G45+H45+I45 -> 0 | L45: =+(0/20256265)*(J45+K45) -> 0 | M45: =+J45+K45+L45 -> 0 | O45: =+(0/20256265)*(M45+N45) -> 0 | P45: =+M45+N45+O45 -> 0 | R45: =+(0/20256265)*(P45+Q45) -> 0 | S45: =+P45+Q45+R45 -> 0 | U45: =+(0/20256265)*(S45+T45) -> 0 | V45: =+S45+T45+U45 -> 0 | X45: =+(0/20256265)*(V45+W45) -> 0 | Y45: =+V45+W45+X45 -> 0 | AA45: =+(0/20256265)*(Y45+Z45) -> 0 | AB45: =+Y45+Z45+AA45 -> 0 | AD45: =+(0/20256265)*(AB45+AC45) -> 0 | AE45: =+AB45+AC45+AD45 -> 0 | AG45: =+(0/20256265)*(AE45+AF45) -> 0 | AH45: =+AE45+AF45+AG45 -> 0 | AJ45: =+(0/20256265)*(AH45+AI45) -> 0 | AK45: =+AH45+AI45+AJ45 -> 0 | AM45: =+(0/20256265)*(AK45+AL45) -> 0 | AN45: =+AK45+AL45+AM45 -> 0 | AP45: =+(0/20000)*(AN45+AO45) -> 0 | AQ45: =+AN45+AO45+AP45 -> 0 | AR45: =+C45 -> 0 | AS45: =+D45 -> 0 | AT45: =+H45+K45+N45+Q45+T45+W45+Z45+AC45+AF45+AI45+AL45+AO45 -> 0 | AU45: =+F45+I45+L45+O45+R45+U45+X45+AA45+AD45+AG45+AJ45+AM45+AP45 -> 0 | AV45: =+AN45+AO45+AP45 -> 0 | BA45: 0 | BB45: =+AV45-AW45-AX45-AY45-AZ45-BA45 -> 0 | BF45: =+BD45-BE45 -> 0
B46: TOTAL 2 | C46: =SUM(C40:C45) -> 793476 | D46: =SUM(D40:D45) -> 0 | E46: =SUM(E40:E45) -> 793476 | F46: =SUM(F40:F45) -> 0 | G46: =SUM(G40:G45) -> 793476 | H46: =SUM(H40:H45) -> -793476 | I46: =SUM(I40:I45) -> 0 | J46: =SUM(J40:J45) -> 0 | ... BD46: =SUM(BD40:BD45) -> 873476 | BF46: =+BD46-BE46 -> 873476
B47: TOTAL 1+2 | C47: =+C39+C46 -> 16393476 | D47: =+D39+D46 -> 4361559.6 | E47: =+E39+E46 -> 20755036 | F47: =+F39+F46 -> 1268000 | G47: =+G39+G46 -> 22023036 | H47: =+H39+H46 -> 256524 | I47: =+I39+I46 -> 0 | J47: =+J39+J46 -> 21638859 | ... BF47: =+BF39+BF46 -> 9494802.5

Sheet MOUVEMENTS PRETS 2023
A1: PRETS ET REMBOURSEMENTS 2023
C2: DECEMBRE 2022 | F2: 44927 | I2: 44958 | L2: 44986 | O2: 45017 | R2: 45047 | U2: 45078 | X2: 45108 | AA2: 45139 | AD2: 45170 | AG2: 45200 | AJ2: 45231 | AM2: 45261 | AP2: CUMUL ANNUEL | AS2: PRÊTS EN CIRCULATION
C3: PRETS | D3: REMBOURSEMENT | E3: INTERET PAYE | F3: PRETS | G3: REMBOURSEMENT | H3: INTERET PAYE | I3: PRETS | J3: REMBOURSEMENT | K3: INTERET PAYE | L3: PRETS | M3: REMBOURSEMENT | N3: INTERET PAYE | O3: PRETS | P3: REMBOURSEMENT | Q3: INTERET PAYE | R3: PRETS | S3: REMBOURSEMENT | T3: INTERET PAYE | U3: PRETS | V3: REMBOURSEMENT | W3: INTERET PAYE | X3: PRETS | Y3: REMBOURSEMENT | Z3: INTERET PAYE | AA3: PRETS | AB3: REMBOURSEMENT | AC3: INTERET PAYE | AD3: PRETS | AE3: REMBOURSEMENT | AF3: INTERET PAYE | AG3: PRETS | AH3: REMBOURSEMENT | AI3: INTERET PAYE | AJ3: PRETS | AK3: REMBOURSEMENT | AL3: INTERET PAYE | AM3: PRETS | AN3: REMBOURSEMENT | AO3: INTERET PAYE | AP3: PRETS | AQ3: REMBOURSEMENT | AR3: INTERET PAYE
A4: N° | B4: NOMS ET PRENOMS | C4: MONTANT | D4: MONTANT | E4: MONTANT | F4: MONTANT | G4: MONTANT | H4: MONTANT | I4: MONTANT | J4: MONTANT | K4: MONTANT | L4: MONTANT | M4: MONTANT | N4: MONTANT | O4: MONTANT | P4: MONTANT | Q4: MONTANT | R4: MONTANT | S4: MONTANT | T4: MONTANT | U4: MONTANT | V4: MONTANT | W4: MONTANT | X4: MONTANT | Y4: MONTANT | Z4: MONTANT | AA4: MONTANT | AB4: MONTANT | AC4: MONTANT | AD4: MONTANT | AE4: MONTANT | AF4: MONTANT | AG4: MONTANT | AH4: MONTANT | AI4: MONTANT | AJ4: MONTANT | AK4: MONTANT | AL4: MONTANT | AM4: MONTANT | AN4: MONTANT | AO4: MONTANT | AP4: MONTANT | AQ4: MONTANT | AR4: MONTANT
A5: 1 | B5: BOUTCHOUANG WILLIAM | C5: 500000 | D5: 0 | E5: 10000 | F5: 0 | G5: 0 | H5: 0 | I5: 0 | J5: 0 | K5: 0 | L5: 0 | M5: 500000 | N5: 0 | O5: 500000 | P5: 0 | Q5: 10000 | R5: 0 | S5: 0 | T5: 0 | U5: 0 | V5: 0 | W5: 0 | X5: 0 | Y5: 0 | Z5: 0 | AA5: 0 | AB5: 0 | AC5: 0 | AD5: 0 | AE5: 0 | AF5: 0 | AG5: 0 | AH5: 0 | AI5: 0 | AJ5: 0 | AK5: 0 | AL5: 0 | AM5: 0 | AN5: 0 | AO5: 0 | AP5: =+C5+F5+I5+L5+X5+AD5+AJ5+AG5+AA5+O5+U5+R5 -> 1000000 | AQ5: =+D5+G5+J5+M5+Y5+AE5+AK5+AH5+AB5+P5+V5 -> 500000 | AR5: =+E5+H5+K5+N5+Z5+AF5+AL5+AI5+AC5+Q5+W5+T5 -> 20000 | AS5: =+AP5-AQ5 -> 500000
A6: 2 | B6: DJOMO JEAN PAUL | C6: 1000000 | D6: 0 | E6: 120000 | F6: 0 | G6: 0 | H6: 0 | I6: 0 | J6: 0 | K6: 0 | L6: 0 | M6: 690000 | N6: 0 | O6: 0 | P6: 0 | Q6: 0 | R6: 690000 | S6: 0 | T6: 0 | U6: 0 | V6: 0 | W6: 0 | X6: 0 | Y6: 0 | Z6: 0 | AA6: 0 | AB6: 0 | AC6: 0 | AD6: 0 | AE6: 0 | AF6: 0 | AG6: 0 | AH6: 0 | AI6: 0 | AJ6: 0 | AK6: 0 | AL6: 0 | AM6: 0 | AN6: 0 | AO6: 0 | AP6: =+C6+F6+I6+L6+X6+AD6+AJ6+AG6+AA6+O6+U6+R6 -> 1690000 | AQ6: =+D6+G6+J6+M6+Y6+AE6+AK6+AH6+AB6+P6+V6 -> 690000 | AR6: =+E6+H6+K6+N6+Z6+AF6+AL6+AI6+AC6+Q6+W6+T6 -> 120000 | AS6: =+AP6-AQ6 -> 1000000
A7: 3 | B7: DJOMOU TCHANDA | C7: 0 | D7: 0 | E7: 0 | F7: 0 | G7: 0 | H7: 0 | I7: 0 | J7: 0 | K7: 0 | L7: 0 | M7: 0 | N7: 0 | O7: 0 | P7: 0 | Q7: 0 | R7: 0 | S7: 0 | T7: 0 | U7: 0 | V7: 0 | W7: 0 | X7: 0 | Y7: 0 | Z7: 0 | AA7: 0 | AB7: 0 | AC7: 0 | AD7: 0 | AE7: 0 | AF7: 0 | AG7: 0 | AH7: 0 | AI7: 0 | AJ7: 0 | AK7: 0 | AL7: 0 | AM7: 0 | AN7: 0 | AO7: 0 | AP7: =+C7+F7+I7+L7+X7+AD7+AJ7+AG7+AA7+O7+U7+R7 -> 0 | AQ7: =+D7+G7+J7+M7+Y7+AE7+AK7+AH7+AB7+P7+V7 -> 0 | AR7: =+E7+H7+K7+N7+Z7+AF7+AL7+AI7+AC7+Q7+W7+T7 -> 0 | AS7: =+AP7-AQ7 -> 0
A8: 4 | B8: DJOUKWE NANGUEN GUY BL | C8: 1000000 | D8: 0 | E8: 40000 | F8: 0 | G8: 0 | H8: 0 | I8: 0 | J8: 0 | K8: 0 | L8: 0 | M8: 0 | N8: 0 | O8: 1000000 | P8: 1000000 | Q8: 80000 | R8: 0 | S8: 0 | T8: 0 | U8: 0 | V8: 0 | W8: 0 | X8: 0 | Y8: 0 | Z8: 0 | AA8: 0 | AB8: 0 | AC8: 0 | AD8: 0 | AE8: 0 | AF8: 0 | AG8: 0 | AH8: 0 | AI8: 0 | AJ8: 0 | AK8: 0 | AL8: 0 | AM8: 0 | AN8: 0 | AO8: 0 | AP8: =+C8+F8+I8+L8+X8+AD8+AJ8+AG8+AA8+O8+U8+R8 -> 2000000 | AQ8: =+D8+G8+J8+M8+Y8+AE8+AK8+AH8+AB8+P8+V8 -> 1000000 | AR8: =+E8+H8+K8+N8+Z8+AF8+AL8+AI8+AC8+Q8+W8+T8 -> 120000 | AS8: =+AP8-AQ8 -> 1000000
A9: 5 | B9: DJUOMBESSY ANTOINE | C9: 1000000 | D9: 0 | E9: 60000 | F9: 0 | G9: 0 | H9: 0 | I9: 0 | J9: 0 | K9: 0 | L9: 0 | M9: 0 | N9: 0 | O9: 0 | P9: 0 | Q9: 0 | R9: 0 | S9: 0 | T9: 0 | U9: 705000 | V9: 1000000 | W9: 28200 | X9: 0 | Y9: 0 | Z9: 0 | AA9: 0 | AB9: 0 | AC9: 0 | AD9: 0 | AE9: 0 | AF9: 0 | AG9: 0 | AH9: 0 | AI9: 0 | AJ9: 0 | AK9: 0 | AL9: 0 | AM9: 0 | AN9: 0 | AO9: 0 | AP9: =+C9+F9+I9+L9+X9+AD9+AJ9+AG9+AA9+O9+U9+R9 -> 1705000 | AQ9: =+D9+G9+J9+M9+Y9+AE9+AK9+AH9+AB9+P9+V9 -> 1000000 | AR9: =+E9+H9+K9+N9+Z9+AF9+AL9+AI9+AC9+Q9+W9+T9 -> 88200 | AS9: =+AP9-AQ9 -> 705000
A10: 6 | B10: DOMOU FABIEN | C10: 1000000 | D10: 0 | E10: 120000 | F10: 0 | G10: 0 | H10: 0 | I10: 0 | J10: 0 | K10: 0 | L10: 0 | M10: 0 | N10: 0 | O10: 0 | P10: 0 | Q10: 0 | R10: 0 | S10: 0 | T10: 0 | U10: 0 | V10: 0 | W10: 0 | X10: 0 | Y10: 0 | Z10: 0 | AA10: 0 | AB10: 0 | AC10: 0 | AD10: 0 | AE10: 0 | AF10: 0 | AG10: 0 | AH10: 0 | AI10: 0 | AJ10: 0 | AK10: 0 | AL10: 0 | AM10: 0 | AN10: 0 | AO10: 0 | AP10: =+C10+F10+I10+L10+X10+AD10+AJ10+AG10+AA10+O10+U10+R10 -> 1000000 | AQ10: =+D10+G10+J10+M10+Y10+AE10+AK10+AH10+AB10+P10+V10 -> 0 | AR10: =+E10+H10+K10+N10+Z10+AF10+AL10+AI10+AC10+Q10+W10+T10 -> 120000 | AS10: =+AP10-AQ10 -> 1000000
A11: 7 | B11: DONHOU DAVID | C11: 0 | D11: 0 | E11: 0 | F11: 0 | G11: 0 | H11: 0 | I11: 0 | J11: 0 | K11: 0 | L11: 0 | M11: 0 | N11: 0 | O11: 0 | P11: 0 | Q11: 0 | R11: 0 | S11: 0 | T11: 0 | U11: 0 | V11: 0 | W11: 0 | X11: 0 | Y11: 0 | Z11: 0 | AA11: 0 | AB11: 0 | AC11: 0 | AD11: 0 | AE11: 0 | AF11: 0 | AG11: 0 | AH11: 0 | AI11: 0 | AJ11: 0 | AK11: 0 | AL11: 0 | AM11: 0 | AN11: 0 | AO11: 0 | AP11: =+C11+F11+I11+L11+X11+AD11+AJ11+AG11+AA11+O11+U11+R11 -> 0 | AQ11: =+D11+G11+J11+M11+Y11+AE11+AK11+AH11+AB11+P11+V11 -> 0 | AR11: =+E11+H11+K11+N11+Z11+AF11+AL11+AI11+AC11+Q11+W11+T11 -> 0 | AS11: =+AP11-AQ11 -> 0
A12: 8 | B12: HENGUE PAUL OMER | C12: 0 | D12: 0 | E12: 0 | F12: 0 | G12: 0 | H12: 0 | I12: 0 | J12: 0 | K12: 0 | L12: 0 | M12: 0 | N12: 0 | O12: 0 | P12: 0 | Q12: 0 | R12: 0 | S12: 0 | T12: 0 | U12: 0 | V12: 0 | W12: 0 | X12: 0 | Y12: 0 | Z12: 0 | AA12: 0 | AB12: 0 | AC12: 0 | AD12: 0 | AE12: 0 | AF12: 0 | AG12: 0 | AH12: 0 | AI12: 0 | AJ12: 0 | AK12: 0 | AL12: 0 | AM12: 0 | AN12: 0 | AO12: 0 | AP12: =+C12+F12+I12+L12+X12+AD12+AJ12+AG12+AA12+O12+U12+R12 -> 0 | AQ12: =+D12+G12+J12+M12+Y12+AE12+AK12+AH12+AB12+P12+V12 -> 0 | AR12: =+E12+H12+K12+N12+Z12+AF12+AL12+AI12+AC12+Q12+W12+T12 -> 0 | AS12: =+AP12-AQ12 -> 0
A13: 9 | B13: HOTCHO BENJAMIN | C13: 1000000 | D13: 0 | E13: 120000 | F13: 0 | G13: 0 | H13: 0 | I13: 0 | J13: 1000000 | K13: 0 | L13: 0 | M13: 0 | N13: 0 | O13: 0 | P13: 0 | Q13: 0 | R13: 0 | S13: 0 | T13: 0 | U13: 0 | V13: 0 | W13: 0 | X13: 0 | Y13: 0 | Z13: 0 | AA13: 0 | AB13: 0 | AC13: 0 | AD13: 0 | AE13: 0 | AF13: 0 | AG13: 0 | AH13: 0 | AI13: 0 | AJ13: 0 | AK13: 0 | AL13: 0 | AM13: 0 | AN13: 0 | AO13: 0 | AP13: =+C13+F13+I13+L13+X13+AD13+AJ13+AG13+AA13+O13+U13+R13 -> 1000000 | AQ13: =+D13+G13+J13+M13+Y13+AE13+AK13+AH13+AB13+P13+V13 -> 1000000 | AR13: =+E13+H13+K13+N13+Z13+AF13+AL13+AI13+AC13+Q13+W13+T13 -> 120000 | AS13: =+AP13-AQ13 -> 0
A14: 10 | B14: KOUAMOU MOISE | C14: 0 | D14: 0 | E14: 0 | F14: 0 | G14: 0 | H14: 0 | I14: 0 | J14: 0 | K14: 0 | L14: 0 | M14: 0 | N14: 0 | O14: 0 | P14: 0 | Q14: 0 | R14: 0 | S14: 0 | T14: 0 | U14: 0 | V14: 0 | W14: 0 | X14: 1000000 | Y14: 0 | Z14: 50000 | AA14: 0 | AB14: 0 | AC14: 0 | AD14: 0 | AE14: 0 | AF14: 0 | AG14: 0 | AH14: 0 | AI14: 0 | AJ14: 0 | AK14: 0 | AL14: 0 | AM14: 0 | AN14: 0 | AO14: 0 | AP14: =+C14+F14+I14+L14+X14+AD14+AJ14+AG14+AA14+O14+U14+R14 -> 1000000 | AQ14: =+D14+G14+J14+M14+Y14+AE14+AK14+AH14+AB14+P14+V14 -> 0 | AR14: =+E14+H14+K14+N14+Z14+AF14+AL14+AI14+AC14+Q14+W14+T14 -> 50000 | AS14: =+AP14-AQ14 -> 1000000
A15: 11 | B15: KOUATCHO MESSACK | C15: 1000000 | D15: 0 | E15: 60000 | F15: 0 | G15: 0 | H15: 0 | I15: 0 | J15: 0 | K15: 0 | L15: 0 | M15: 0 | N15: 0 | O15: 0 | P15: 0 | Q15: 0 | R15: 0 | S15: 0 | T15: 0 | U15: 250000 | V15: 1000000 | W15: 10000 | X15: 0 | Y15: 0 | Z15: 0 | AA15: 0 | AB15: 0 | AC15: 0 | AD15: 0 | AE15: 100000 | AF15: 0 | AG15: 0 | AH15: 140000 | AI15: 0 | AJ15: 0 | AK15: 0 | AL15: 0 | AM15: 0 | AN15: 0 | AO15: 0 | AP15: =+C15+F15+I15+L15+X15+AD15+AJ15+AG15+AA15+O15+U15+R15 -> 1250000 | AQ15: =+D15+G15+J15+M15+Y15+AE15+AK15+AH15+AB15+P15+V15 -> 1240000 | AR15: =+E15+H15+K15+N15+Z15+AF15+AL15+AI15+AC15+Q15+W15+T15 -> 70000 | AS15: =+AP15-AQ15 -> 10000
A16: 12 | B16: LOWE JEAN | C16: 1000000 | D16: 0 | E16: 40000 | F16: 0 | G16: 0 | H16: 0 | I16: 0 | J16: 0 | K16: 0 | L16: 0 | M16: 0 | N16: 0 | O16: 300000 | P16: 1000000 | Q16: 12000 | R16: 0 | S16: 0 | T16: 0 | U16: 0 | V16: 0 | W16: 0 | X16: 0 | Y16: 0 | Z16: 0 | AA16: 0 | AB16: 300000 | AC16: 0 | AD16: 0 | AE16: 0 | AF16: 0 | AG16: 0 | AH16: 0 | AI16: 0 | AJ16: 0 | AK16: 0 | AL16: 0 | AM16: 0 | AN16: 0 | AO16: 0 | AP16: =+C16+F16+I16+L16+X16+AD16+AJ16+AG16+AA16+O16+U16+R16 -> 1300000 | AQ16: =+D16+G16+J16+M16+Y16+AE16+AK16+AH16+AB16+P16+V16 -> 1300000 | AR16: =+E16+H16+K16+N16+Z16+AF16+AL16+AI16+AC16+Q16+W16+T16 -> 52000 | AS16: =+AP16-AQ16 -> 0
... A30: 27 | B30: YOUMBI EMMANUEL | C30: 0 | D30: 0 | E30: 0 | F30: 0 | G30: 0 | H30: 0 | I30: 0 | J30: 0 | K30: 0 | L30: 0 | M30: 0 | N30: 0 | O30: 1000000 | P30: 0 | Q30: 60000 | R30: 0 | S30: 0 | T30: 0 | U30: 0 | V30: 0 | W30: 0 | X30: 0 | Y30: 0 | Z30: 0 | AA30: 0 | AB30: 0 | AC30: 0 | AD30: 0 | AE30: 110000 | AF30: 0 | AG30: 0 | AH30: 290000 | AI30: 0 | AJ30: 0 | AK30: 0 | AL30: 0 | AM30: 0 | AN30: 0 | AO30: 0 | AP30: =+C30+F30+I30+L30+X30+AD30+AJ30+AG30+AA30+O30+U30+R30 -> 1000000 | AQ30: =+D30+G30+J30+M30+Y30+AE30+AK30+AH30+AB30+P30+V30 -> 400000 | AR30: =+E30+H30+K30+N30+Z30+AF30+AL30+AI30+AC30+Q30+W30+T30 -> 60000 | AS30: =+AP30-AQ30 -> 600000
A31: 28 | B31: NKEHE DAVID | C31: =788500 -> 788500 | D31: 536842 | E31: 0 | F31: 0 | G31: 0 | H31: 0 | I31: 0 | J31: 0 | K31: 0 | L31: 0 | M31: 0 | N31: 0 | O31: 0 | P31: 0 | Q31: 0 | R31: 0 | S31: 0 | T31: 0 | U31: 0 | V31: 0 | W31: 0 | X31: 0 | Y31: 0 | Z31: 0 | AA31: 0 | AB31: 0 | AC31: 0 | AD31: 0 | AE31: 0 | AF31: 0 | AG31: 0 | AH31: 0 | AI31: 0 | AJ31: 0 | AK31: 0 | AL31: 0 | AM31: 0 | AN31: 0 | AO31: 0 | AP31: =+C31+F31+I31+L31+X31+AD31+AJ31+AG31+AA31+O31+U31+R31 -> 788500 | AQ31: =+D31+G31+J31+M31+Y31+AE31+AK31+AH31+AB31+P31+V31 -> 536842 | AR31: =+E31+H31+K31+N31+Z31+AF31+AL31+AI31+AC31+Q31+W31+T31 -> 0 | AS31: =+AP31-AQ31 -> 251658
A32: 29 | B32: TIEYAM ERNEST | C32: =1067000 -> 1067000 | D32: 537217 | E32: 0 | F32: 0 | G32: 0 | H32: 0 | I32: 0 | J32: 0 | K32: 0 | L32: 0 | M32: 0 | N32: 0 | O32: 0 | P32: 0 | Q32: 0 | R32: 0 | S32: 0 | T32: 0 | U32: 0 | V32: 0 | W32: 0 | X32: 0 | Y32: 0 | Z32: 0 | AA32: 0 | AB32: 0 | AC32: 0 | AD32: 0 | AE32: 0 | AF32: 0 | AG32: 0 | AH32: 0 | AI32: 0 | AJ32: 0 | AK32: 0 | AL32: 0 | AM32: 0 | AN32: 0 | AO32: 0 | AP32: =+C32+F32+I32+L32+X32+AD32+AJ32+AG32+AA32+O32+U32+R32 -> 1067000 | AQ32: =+D32+G32+J32+M32+Y32+AE32+AK32+AH32+AB32+P32+V32 -> 537217 | AR32: =+E32+H32+K32+N32+Z32+AF32+AL32+AI32+AC32+Q32+W32+T32 -> 0 | AS32: =+AP32-AQ32 -> 529783
A33: 30 | B33: SIMO FONGANG ERIC | C33: =1453000 -> 1453000 | D33: 606468 | E33: 0 | F33: 0 | G33: 0 | H33: 0 | I33: 0 | J33: 0 | K33: 0 | L33: 0 | M33: 0 | N33: 0 | O33: 0 | P33: 0 | Q33: 0 | R33: 0 | S33: 0 | T33: 0 | U33: 0 | V33: 0 | W33: 0 | X33: 0 | Y33: 846532 | Z33: 0 | AA33: 0 | AB33: 0 | AC33: 0 | AD33: 0 | AE33: 0 | AF33: 0 | AG33: 0 | AH33: 0 | AI33: 0 | AJ33: 0 | AK33: 0 | AL33: 0 | AM33: 0 | AN33: 0 | AO33: 0 | AP33: =+C33+F33+I33+L33+X33+AD33+AJ33+AG33+AA33+O33+U33+R33 -> 1453000 | AQ33: =+D33+G33+J33+M33+Y33+AE33+AK33+AH33+AB33+P33+V33 -> 1453000 | AR33: =+E33+H33+K33+N33+Z33+AF33+AL33+AI33+AC33+Q33+W33+T33 -> 0 | AS33: =+AP33-AQ33 -> 0
A34: 31 | B34: FOTSO THOMAS | C34: =1132500 -> 1132500 | D34: 540421 | E34: 0 | F34: 0 | G34: 0 | H34: 0 | I34: 0 | J34: 0 | K34: 0 | L34: 0 | M34: 0 | N34: 0 | O34: 0 | P34: 0 | Q34: 0 | R34: 0 | S34: 0 | T34: 0 | U34: 0 | V34: 0 | W34: 0 | X34: 0 | Y34: 0 | Z34: 0 | AA34: 0 | AB34: 0 | AC34: 0 | AD34: 0 | AE34: 0 | AF34: 0 | AG34: 0 | AH34: 0 | AI34: 0 | AJ34: 0 | AK34: 0 | AL34: 0 | AM34: 0 | AN34: 0 | AO34: 0 | AP34: =+C34+F34+I34+L34+X34+AD34+AJ34+AG34+AA34+O34+U34+R34 -> 1132500 | AQ34: =+D34+G34+J34+M34+Y34+AE34+AK34+AH34+AB34+P34+V34 -> 540421 | AR34: =+E34+H34+K34+N34+Z34+AF34+AL34+AI34+AC34+Q34+W34+T34 -> 0 | AS34: =+AP34-AQ34 -> 592079
A35: 31 | B35: TCHOUANTE FRANCOIS | C35: 243805 | D35: 0 | E35: 0 | F35: 0 | G35: 0 | H35: 0 | I35: 0 | J35: 0 | K35: 0 | L35: 0 | M35: 0 | N35: 0 | O35: 0 | P35: 0 | Q35: 0 | R35: 0 | S35: 0 | T35: 0 | U35: 0 | V35: 0 | W35: 0 | X35: 0 | Y35: 0 | Z35: 0 | AA35: 0 | AB35: 0 | AC35: 0 | AD35: 0 | AE35: 0 | AF35: 0 | AG35: 0 | AH35: 0 | AI35: 0 | AJ35: 0 | AK35: 0 | AL35: 0 | AM35: 0 | AN35: 0 | AO35: 0 | AP35: =+C35+F35+I35+L35+X35+AD35+AJ35+AG35+AA35+O35+U35+R35 -> 243805 | AQ35: =+D35+G35+J35+M35+Y35+AE35+AK35+AH35+AB35+P35+V35 -> 0 | AR35: =+E35+H35+K35+N35+Z35+AF35+AL35+AI35+AC35+Q35+W35+T35 -> 0 | AS35: =+AP35-AQ35 -> 243805
A36: 31 | B36: NJIEPDJIO DELUXE | C36: 305000 | AP36: =+C36+F36+I36+L36+X36+AD36+AJ36+AG36+AA36+O36+U36+R36 -> 305000 | AR36: =+E36+H36+K36+N36+Z36+AF36+AL36+AI36+AC36+Q36+W36+T36 -> 0 | AS36: =+AP36-AQ36 -> 305000
A37: 31 | B37: TCHINGUE FABRICE | C37: 428899 | D37: 0 | E37: 0 | F37: 0 | G37: 0 | H37: 0 | I37: 0 | J37: 0 | K37: 0 | L37: 0 | M37: 0 | N37: 0 | O37: 0 | P37: 0 | Q37: 0 | R37: 0 | S37: 0 | T37: 0 | U37: 0 | V37: 0 | W37: 0 | X37: 0 | Y37: 0 | Z37: 0 | AA37: 0 | AB37: 0 | AC37: 0 | AD37: 0 | AE37: 0 | AF37: 0 | AG37: 0 | AH37: 0 | AI37: 0 | AJ37: 0 | AK37: 0 | AL37: 0 | AM37: 0 | AN37: 0 | AO37: 0 | AP37: =+C37+F37+I37+L37+X37+AD37+AJ37+AG37+AA37+O37+U37+R37 -> 428899 | AQ37: =+D37+G37+J37+M37+Y37+AE37+AK37+AH37+AB37+P37+V37 -> 0 | AR37: =+E37+H37+K37+N37+Z37+AF37+AL37+AI37+AC37+Q37+W37+T37 -> 0 | AS37: =+AP37-AQ37 -> 428899
A38: 31 | B38: tchoutou nana | C38: 51454 | W38: 0 | AP38: =+C38+F38+I38+L38+X38+AD38+AJ38+AG38+AA38+O38+U38+R38 -> 51454 | AR38: =+E38+H38+K38+N38+Z38+AF38+AL38+AI38+AC38+Q38+W38+T38 -> 0 | AS38: =+AP38-AQ38 -> 51454
A39: 32 | B39: BAKOP Achille | U39: 600000 | V39: 0 | W39: 36000 | AP39: =+C39+F39+I39+L39+X39+AD39+AJ39+AG39+AA39+O39+U39+R39 -> 600000 | AR39: =+E39+H39+K39+N39+Z39+AF39+AL39+AI39+AC39+Q39+W39+T39 -> 36000 | AS39: =+AP39-AQ39 -> 600000
A40: 33 | C40: 0 | D40: 0 | E40: 0 | F40: 0 | G40: 0 | H40: 0 | I40: 0 | J40: 0 | K40: 0 | L40: 0 | M40: 0 | N40: 0 | O40: 0 | P40: 0 | Q40: 0 | R40: 0 | S40: 0 | T40: 0 | U40: 0 | V40: 0 | W40: 0 | X40: 0 | Y40: 0 | Z40: 0 | AA40: 0 | AB40: 0 | AC40: 0 | AD40: 0 | AE40: 0 | AF40: 0 | AG40: 0 | AH40: 0 | AI40: 0 | AJ40: 0 | AK40: 0 | AL40: 0 | AM40: 0 | AN40: 0 | AO40: 0 | AP40: =+C40+F40+I40+L40+X40+AD40+AJ40+AG40+AA40+O40+U40+R40 -> 0 | AQ40: =+D40+G40+J40+M40+Y40+AE40+AK40+AH40+AB40+P40+V40 -> 0 | AR40: =+E40+H40+K40+N40+Z40+AF40+AL40+AI40+AC40+Q40+W40+T40 -> 0 | AS40: =+AP40-AQ40 -> 0
B41: TOTAL | C41: =SUM(C5:C40) -> 23081408 | D41: =SUM(D5:D40) -> 2220948 | E41: =SUM(E5:E40) -> 1268000 | F41: =SUM(F5:F40) -> 0 | G41: =SUM(G5:G40) -> 0 | H41: =SUM(H5:H40) -> 0 | I41: =SUM(I5:I40) -> 1000000 | J41: =SUM(J5:J40) -> 2000000 | ... AS41: =SUM(AS5:AS40) -> 18236428

Sheet CAISSE 2023
B1: CAISSE JANVIER 2023
B2: NOMS ET PRENOMS | C2: LIBELLES | D2: MONTANT A PAYER | E2: PAYE EN ESPECE | F2: EN COMPTE | G2: PAYE PAR CHEQUE | H2: SOLDE CCA AU 30/12/22 | I2: Observations
H3: 5945971 | I3: solde CCA
C4: VERSEMENTS en banque | H4: 3425000
A5: 1 | B5: KOUATCHO | C5: TONTINE DE PRESENCE | D5: 300000 | E5: 40000 | F5: 70000 | G5: =+D5-E5-F5 -> 190000 | I5: FOYER 70000
A6: =1+A5 -> 2 | B6: DJOMO JEAN PAUL | C6: TONTINE DE PRESENCE | D6: 300000 | E6: 45000 | F6: 140000 | G6: =+D6-E6-F6 -> 115000
A7: =1+A6 -> 3 | B7: NKAMGANG JUSTIN D | C7: INTERET T PRESENCE | D7: 60000 | E7: 60000 | F7: 0 | G7: =+D7-E7-F7 -> 0
A8: =1+A7 -> 4 | B8: DJOUKWEU GUY | C8: INTERET T PRESENCE | D8: 60000 | E8: 60000 | F8: 0 | G8: =+D8-E8-F8 -> 0
A9: =1+A8 -> 5 | B9: DJOMO FRANCOIS | C9: INTERET T PRESENCE | D9: 60000 | E9: 60000 | F9: 0 | G9: =+D9-E9-F9 -> 0
A10: =1+A9 -> 6 | B10: NGUIEMENI MATHIEU B | C10: INTERET T PRESENCE | D10: 30000 | E10: 30000 | F10: 0 | G10: =+D10-E10-F10 -> 0 | H10: 0
A11: =1+A10 -> 7 | B11: NGONDIEP CLAUDE | C11: INTERET T PRESENCE | D11: 25000 | E11: 0 | F11: 0 | G11: =+D11-E11-F11 -> 25000 | H11: 0
A12: =1+A11 -> 8 | B12: KOUATCHO | C12: BENEF T 100 | D12: 1200000 | E12: 125000 | G12: =+D12-E12-F12 -> 1075000
A13: =1+A12 -> 9 | B13: NGONDIEP CLAUDE | C13: BENEF T 100 | D13: 1200000 | E13: 125000 | G13: =+D13-E13-F13 -> 1075000
A14: =1+A13 -> 10 | B14: NBOGNING GUY | C14: BENEF T 100 | D14: 1200000 | E14: =125000+89000 -> 214000 | F14: 0 | G14: =+D14-E14-F14 -> 986000
A15: =1+A14 -> 11 | B15: NGONDIEP CLAUDE | C15: INTERET T 100 | D15: 200000 | E15: 0 | F15: 0 | G15: =+D15-E15-F15 -> 200000
A16: =1+A15 -> 12 | B16: NGUIEMENI MATHIEU B | C16: INTERET T 100 | D16: 75000 | E16: 75000 | G16: =+D16-E16-F16 -> 0
A17: =1+A16 -> 13 | B17: DJOMO JEAN PAUL | C17: INTERET T 100 | D17: 50000 | E17: 50000 | G17: =+D17-E17-F17 -> 0
A18: =1+A17 -> 14 | B18: NGONDIEP CLAUDE | C18: BENEFICIAIRE T 75 | D18: 900000 | E18: 105000 | G18: =+D18-E18-F18 -> 795000
A19: =1+A18 -> 15 | B19: NGONDIEP CLAUDE | C19: INTERET T 75 | D19: 100000 | E19: 0 | G19: =+D19-E19-F19 -> 100000
A20: =1+A19 -> 16 | B20: KOUATCHO | C20: INTERET T75 | D20: 100000 | G20: =+D20-E20-F20 -> 100000
A21: =1+A20 -> 17 | B21: NGUIEMENI MATHIEU B | C21: INTERET T75 | D21: 100000 | E21: 100000 | G21: =+D21-E21-F21 -> 0
A22: =1+A21 -> 18 | B22: NBOGNING GUY | C22: INTERET T75 | D22: 105000 | E22: 105000 | G22: =+D22-E22-F22 -> 0
A23: =1+A22 -> 19 | B23: NDJOMO ETIENNE | C23: TAXI BANQUE | D23: 6000 | G23: =+D23-E23-F23 -> 6000
A24: =1+A23 -> 20 | B24: KOUATCHO | C24: COLLATION FEVRIER | D24: 100000 | G24: =+D24-E24-F24 -> 100000
A25: =1+A24 -> 21 | B25: NGONGANG JEAN THIEDOR | C25: RETRAIT FOND | D25: 257000 | G25: =+D25-E25-F25 -> 257000
A26: =1+A25 -> 22 | G26: =+D26-E26-F26 -> 0
A27: =1+A26 -> 23 | G27: =+D27-E27-F27 -> 0
A28: =1+A27 -> 24 | G28: =+D28-E28-F28 -> 0
A29: =1+A28 -> 25
A30: =1+A29 -> 26
A31: =1+A30 -> 27
A32: =1+A31 -> 28 | D32: =SUM(D3:D31) -> 6428000 | E32: =SUM(E3:E31) -> 1194000 | F32: =SUM(F3:F31) -> 210000 | G32: =SUM(G3:G31) -> 5024000 | H32: =+H3+H4-G32 -> 4346971 | I32: solde après retrait 4337431 | J32: =4346971-4337431 -> 9540 | K32: difference entre mon solde et le solde en banque
B33: CAISSE FEVRIER 2023
B34: NOMS ET PRENOMS | C34: LIBELLES | D34: MONTANT A PAYER | E34: PAYE EN ESPECE | F34: EN COMPTE | G34: PAYE PAR CHEQUE | H34: SOLDE CCA AU 30/12/23 | I34: Observations
H35: 5735972
C36: VERSEMENTS
A37: 2 | B37: MBOGNING GUY | C37: saisie et impression rapports | D37: 35000 | E37: 35000 | G37: =+D37-E37-F37 -> 0
A38: =1+A37 -> 3 | B38: MBOGNING GUY | C38: commision du 22-1-23 | D38: 15000 | E38: 15000 | G38: =+D38-E38-F38 -> 0
A39: =1+A38 -> 4 | B39: MBOGNING GUY | C39: commission du 06--02-2023 | D39: 12500 | E39: 12500 | G39: =+D39-E39-F39 -> 0
A40: =1+A39 -> 5 | B40: NKAMGANG JUSTIN D | C40: benef tontine presence | D40: 300000 | E40: 196500 | F40: =3500+70000+30000 -> 103500 | G40: =+D40-E40-F40 -> 0 | I40: 70000 FOYER 30000 INTERET PRÊT
A41: =1+A40 -> 6 | B41: kouamou moise | C41: benef tontine presence | D41: 300000 | E41: 64500 | F41: =6500+70000 -> 76500 | G41: =+D41-E41-F41 -> 159000 | I41: 70000 FOYER
A42: =1+A41 -> 7 | B42: NGUIEMENI MATHIEU B | C42: benef tontine presence | D42: 300000 | E42: 0 | F42: =7500+70000 -> 77500 | G42: =+D42-E42-F42 -> 222500 | I42: 70000 FOYER
A43: =1+A42 -> 8 | B43: MBOGNING GUY | C43: BENEF T75 | D43: 900000 | E43: 378000 | F43: =22000+500000 -> 522000 | G43: =+D43-E43-F43 -> 0 | I43: 500000 PRÊT MBOUTCHOUANG
A44: =1+A43 -> 9 | B44: HOTCHO Benjamin | C44: BENEF T75 | D44: 900000 | F44: 20000 | G44: =+D44-E44-F44 -> 880000
A45: =1+A44 -> 10 | B45: MBOGNING GUY | C45: gratiffication du bureau | D45: 200000 | E45: 200000 | G45: =+D45-E45-F45 -> 0
A46: =1+A45 -> 11 | B46: kouamou moise | C46: BENEFICIAIRE T 100 | D46: 1200000 | F46: 28000 | G46: =+D46-E46-F46 -> 1172000
A47: =1+A46 -> 12 | B47: HOTCHO Benjamin | C47: BENEFICIAIRE T 100 | D47: 1200000 | F47: =28000+1000000 -> 1028000 | G47: =+D47-E47-F47 -> 172000 | I47: REMBOURSEMENT PRÊT
A48: =1+A47 -> 13 | B48: NKAMGANG JUSTIN D | C48: int presence | D48: 40000 | E48: 40000 | G48: =+D48-E48-F48 -> 0
A49: =1+A48 -> 14 | B49: DJOMO FRANCOIS | C49: int presence | D49: 40000 | E49: 40000 | G49: =+D49-E49-F49 -> 0
A50: =1+A49 -> 15 | B50: MBOGNING GUY | C50: int presence | D50: 31500 | E50: 31500 | G50: =+D50-E50-F50 -> 0
A51: =1+A50 -> 16 | B51: NKEPSEU DIEUDONNE | C51: FONDS | D51: 640700 | G51: =+D51-E51-F51 -> 640700
A52: =1+A51 -> 17 | B52: NKEPSEU DIEUDONNE | C52: OBSEQUES | D52: 560000 | G52: =+D52-E52-F52 -> 560000
A53: =1+A52 -> 18 | B53: NDJOMO ETIENNE | C53: TAXI BANQUE | D53: 6000 | G53: =+D53-E53-F53 -> 6000
A54: =1+A53 -> 19 | B54: NKAMGANG JUSTIN D | C54: PRÊT | D54: 1000000 | E54: 0 | F54: =30000+970000 -> 1000000 | G54: =+D54-E54-F54 -> 0 | I54: EN COMPTE (RECONDUCTION)
A55: =1+A54 -> 20 | B55: DJOMO JEAN PAUL | C55: RETOUR FONDS MOIS PASSE | D55: 190000 | G55: =+D55-E55-F55 -> 190000
A56: =1+A55 -> 21 | G56: =+D56-E56-F56 -> 0
A57: =1+A56 -> 22 | G57: =+D57-E57-F57 -> 0
A58: =1+A57 -> 23 | G58: =+D58-E58-F58 -> 0
A59: =1+A58 -> 24 | G59: =+D59-E59-F59 -> 0
A60: =1+A59 -> 25 | G60: =+D60-E60-F60 -> 0
A61: =1+A60 -> 26 | G61: =+D61-E61-F61 -> 0
A62: =1+A61 -> 27 | G62: =+D62-E62-F62 -> 0
A63: =1+A62 -> 28 | G63: =+D63-E63-F63 -> 0
A64: =1+A63 -> 29 | D64: =SUM(D35:D63) -> 7870700 | E64: =SUM(E35:E63) -> 1013000 | F64: =SUM(F35:F63) -> 2855500 | G64: =SUM(G35:G63) -> 4002200 | H64: =+H35+#REF!-F64-G64 -> #REF!
B65: CAISSE MARS 2023
B66: NOMS ET PRENOMS | C66: LIBELLES | D66: MONTANT A PAYER | E66: PAYE EN ESPECE | F66: EN COMPTE | G66: PAYE PAR CHEQUE | H66: SOLDE CCA AU 30/12/23 | I66: Observations
H67: 5735972
C68: VERSEMENTS
A69: 2 | B69: TCHOUMOU MATHIEU | C69: TONTINE DE 75000 | D69: 900000 | F69: 900000 | G69: =+D69-E69-F69 -> 0 | H69: RETENUE 892500 POUR SON REMBOURSEMENT
A70: =1+A69 -> 3 | B70: TCHOUMOU MATHIEU | C70: PRÊT | D70: 200000 | F70: =6000+107500 -> 113500 | G70: =+D70-E70-F70 -> 86500 | I70: 107500 COMPLEMENT REMB
A71: =1+A70 -> 4 | B71: DJOUKWEU GUY | C71: TONTINE DE 75000 | D71: 900000 | E71: 50000 | F71: =7500+842500 -> 850000 | G71: =+D71-E71-F71 -> 0
A72: =1+A71 -> 5 | B72: DJOUOMBISSI ANTOINE | C72: TONTINE DE 100000 | D72: 1200000 | F72: 10000 | G72: =+D72-E72-F72 -> 1190000
A73: =1+A72 -> 6 | B73: DJOMO JEAN PAUL | C73: TONTINE JP | D73: 1200000 | F73: =10000+690000 -> 700000 | G73: =+D73-E73-F73 -> 500000
A74: =1+A73 -> 7 | B74: SIMO PIERRE | C74: PRESENCE | D74: 300000 | F74: =11000+70000 -> 81000 | G74: =+D74-E74-F74 -> 219000 | I74: FOYER 70000
A75: =1+A74 -> 8 | B75: DOMOU FABIEN | C75: PRESENCE | D75: 300000 | F75: =10000+70000 -> 80000 | G75: =+D75-E75-F75 -> 220000 | I75: FOYER 70000
A76: =1+A75 -> 9 | B76: MBOGNING GUY | C76: PRESENCE | D76: 300000 | F76: =11000+70000 -> 81000 | G76: =+D76-E76-F76 -> 219000 | I76: FOYER 70000
A77: =1+A76 -> 10 | B77: NDJOMO ETIENNE | C77: INT T 100000 | D77: 200000 | E77: 100000 | G77: =+D77-E77-F77 -> 100000 | I77: A KOUATCHO
A78: =1+A77 -> 11 | B78: MBOGNING GUY | C78: INT T 100000 | D78: 200000 | E78: 105000 | G78: =+D78-E78-F78 -> 95000
A79: =1+A78 -> 12 | B79: HOTCHO Benjamin | C79: INT T 100000 | D79: 264000 | E79: 44000 | G79: =+D79-E79-F79 -> 220000 | I79: 66000 A REMETTRE A HOTCHO
A80: =1+A79 -> 13 | B80: KOUATCHO | C80: INT T 100000 | D80: 200000 | E80: 0 | F80: 0 | G80: =+D80-E80-F80 -> 200000
A81: =1+A80 -> 14 | B81: kouamou moise | C81: INT T 100000 | D81: 100000 | G81: =+D81-E81-F81 -> 100000
A82: =1+A81 -> 15 | B82: DJOUKWEU GUY | C82: COLLATION FEVRIER | D82: 100000 | F82: 100000 | G82: =+D82-E82-F82 -> 0
A83: =1+A82 -> 16 | B83: DJOMO TCHAPDA | C83: COLLATION MARS | D83: 100000 | G83: =+D83-E83-F83 -> 100000
A84: =1+A83 -> 17 | B84: NDJOMO ETIENNE | C84: TAXI BANQUE | D84: 6000 | G84: =+D84-E84-F84 -> 6000
A85: =1+A84 -> 18 | B85: NDJOMO ETIENNE | C85: VERSEMENT FOYER | D85: 1750000 | G85: 1750000
A86: =1+A85 -> 19
A87: =1+A86 -> 20
A88: =1+A87 -> 21
A89: =1+A88 -> 22
A90: =1+A89 -> 23
A91: =1+A90 -> 24
A92: =1+A91 -> 25
A93: =1+A92 -> 26
A94: =1+A93 -> 27
A95: =1+A94 -> 28
A96: =1+A95 -> 29 | D96: =SUM(D67:D95) -> 8220000 | E96: =SUM(E67:E95) -> 299000 | F96: =SUM(F67:F95) -> 2915500 | G96: =SUM(G67:G95) -> 5005500 | H96: =+H67+#REF!-F96-G96 -> #REF!
B97: CAISSE AVRIL 2023
B98: NOMS ET PRENOMS | C98: LIBELLES | D98: MONTANT A PAYER | E98: PAYE EN ESPECE | F98: EN COMPTE | G98: PAYE PAR CHEQUE | H98: SOLDE CCA AU 30/12/24 | I98: Observations
H99: 5735973
C100: VERSEMENTS
...

Sheet FOYER 2023
A1: COTISATION FOYER
A2: N° | B2: NOMS ET PRENOMS | C2: DETTE | D2: NOUVEAU | E2: 44562 | F2: FEV 2022 | G2: 44621 | H2: 44652 | I2: 44682 | J2: 44713 | K2: 44743 | L2: AOUT 2022 | M2: 44805 | N2: 44835 | O2: 44866 | P2: DEC 2022 | Q2: TOTAL COTISE | R2: RESTE A COTISER
A3: 0 | B3: ASELBY | C3: 0 | D3: 0 | Q3: =+E3+F3+G3+H3+I3+J3+L3+O3+P3 -> 0 | R3: =+C3+D3-Q3 -> 0
A4: =+A3+1 -> 1 | B4: BOUTCHOUANG WILLIAM | C4: 0 | D4: 70000 | Q4: =+E4+F4+G4+H4+I4+J4+L4+O4+P4 -> 0 | R4: =+C4+D4-Q4 -> 70000
A5: =+A4+1 -> 2 | B5: DJOMO JEAN PAUL | C5: 70000 | D5: 70000 | E5: 140000 | Q5: =+E5+F5+G5+H5+I5+J5+L5+O5+P5 -> 140000 | R5: =+C5+D5-Q5 -> 0
A6: =+A5+1 -> 3 | B6: DJOMOU TCHANDA | C6: 0 | D6: 70000 | H6: 70000 | Q6: =+E6+F6+G6+H6+I6+J6+L6+O6+P6 -> 70000 | R6: =+C6+D6-Q6 -> 0
A7: =+A6+1 -> 4 | B7: DJOUKWE NANGUEN GUY BL | C7: 0 | D7: 70000 | H7: 70000 | Q7: =+E7+F7+G7+H7+I7+J7+L7+O7+P7 -> 70000 | R7: =+C7+D7-Q7 -> 0
A8: =+A7+1 -> 5 | B8: DJUOMBESSY ANTOINE | C8: 0 | D8: 70000 | I8: 70000 | Q8: =+E8+F8+G8+H8+I8+J8+L8+O8+P8 -> 70000 | R8: =+C8+D8-Q8 -> 0
A9: =+A8+1 -> 6 | B9: DOMOU FABIEN | C9: 0 | D9: 70000 | G9: 70000 | Q9: =+E9+F9+G9+H9+I9+J9+L9+O9+P9 -> 70000 | R9: =+C9+D9-Q9 -> 0
A10: =+A9+1 -> 7 | B10: DONHOU DAVID | C10: 0 | D10: 70000 | Q10: =+E10+F10+G10+H10+I10+J10+L10+O10+P10 -> 0 | R10: =+C10+D10-Q10 -> 70000
A11: =+A10+1 -> 8 | B11: FOTSO THOMAS | C11: 0 | D11: 0 | Q11: =+E11+F11+G11+H11+I11+J11+L11+O11+P11 -> 0 | R11: =+C11+D11-Q11 -> 0
A12: =+A11+1 -> 9 | B12: HENGUE PAUL OMER | C12: 0 | D12: 70000 | K12: 70000 | Q12: =+E12+F12+G12+H12+I12+J12+L12+O12+P12 -> 0 | R12: =+C12+D12-Q12 -> 70000
A13: =+A12+1 -> 10 | B13: HOTCHO BENJAMIN | C13: 0 | D13: 70000 | I13: 70000 | Q13: =+E13+F13+G13+H13+I13+J13+L13+O13+P13 -> 70000 | R13: =+C13+D13-Q13 -> 0
A14: =+A13+1 -> 11 | B14: KOUAMOU MOISE | C14: 0 | D14: 70000 | F14: 70000 | Q14: =+E14+F14+G14+H14+I14+J14+L14+O14+P14 -> 70000 | R14: =+C14+D14-Q14 -> 0
A15: =+A14+1 -> 12 | B15: KOUATCHO MESSACK | C15: 0 | D15: 70000 | E15: 70000 | Q15: =+E15+F15+G15+H15+I15+J15+L15+O15+P15 -> 70000 | R15: =+C15+D15-Q15 -> 0
A16: =+A15+1 -> 13 | B16: LOWE JEAN | C16: 70000 | D16: 70000 | I16: 70000 | Q16: =+E16+F16+G16+H16+I16+J16+L16+O16+P16 -> 70000 | R16: =+C16+D16-Q16 -> 70000
A17: =+A16+1 -> 14 | B17: MBOGNING TUGMA GUY | C17: 0 | D17: 70000 | G17: 70000 | Q17: =+E17+F17+G17+H17+I17+J17+L17+O17+P17 -> 70000 | R17: =+C17+D17-Q17 -> 0
A18: =+A17+1 -> 15 | B18: NANGUEN MARTIN | C18: 0 | D18: 70000 | L18: 70000 | Q18: =+E18+F18+G18+H18+I18+J18+L18+O18+P18 -> 70000 | R18: =+C18+D18-Q18 -> 0
A19: =+A18+1 -> 16 | B19: NANKAM APPOLINAIRE | C19: 0 | D19: 70000 | J19: 70000 | Q19: =+E19+F19+G19+H19+I19+J19+L19+O19+P19 -> 70000 | R19: =+C19+D19-Q19 -> 0
A20: =+A19+1 -> 17 | B20: NDJOMO ETIENNE | C20: 0 | D20: 70000 | M20: 70000 | Q20: =+E20+F20+G20+H20+I20+J20+L20+O20+P20 -> 0 | R20: =+C20+D20-Q20 -> 70000
A21: =+A20+1 -> 18 | B21: NGONDIEP CLAUDE | C21: 0 | D21: 70000 | I21: 70000 | Q21: =+E21+F21+G21+H21+I21+J21+L21+O21+P21 -> 70000 | R21: =+C21+D21-Q21 -> 0
A22: =+A21+1 -> 19 | B22: NGUIEMEGNI MATHIEU BL | C22: 0 | D22: 70000 | Q22: =+E22+F22+G22+H22+I22+J22+L22+O22+P22 -> 0 | R22: =+C22+D22-Q22 -> 70000
A23: =+A22+1 -> 20 | B23: NKAMGANG JUSTIN DEJOLIE | C23: 0 | D23: 70000 | F23: 70000 | Q23: =+E23+F23+G23+H23+I23+J23+L23+O23+P23 -> 70000 | R23: =+C23+D23-Q23 -> 0
A24: =+A23+1 -> 21 | B24: NKEHE DAVID | C24: 0 | D24: 0 | Q24: =+E24+F24+G24+H24+I24+J24+L24+O24+P24 -> 0 | R24: =+C24+D24-Q24 -> 0
A25: =+A24+1 -> 22 | B25: NKEPSEU DIEUDONNE | C25: 0 | D25: 0 | Q25: =+E25+F25+G25+H25+I25+J25+L25+O25+P25 -> 0 | R25: =+C25+D25-Q25 -> 0
A26: =+A25+1 -> 23 | B26: PATEGO NJOSSU GUSTAVE | C26: 0 | D26: 70000 | Q26: =+E26+F26+G26+H26+I26+J26+L26+O26+P26 -> 0 | R26: =+C26+D26-Q26 -> 70000
A27: =+A26+1 -> 24 | B27: SIME BRICE | C27: 0 | D27: 70000 | L27: 70000 | Q27: =+E27+F27+G27+H27+I27+J27+L27+O27+P27 -> 70000 | R27: =+C27+D27-Q27 -> 0
A28: =+A27+1 -> 25 | B28: SIMO FONGANG ERIC | C28: 0 | D28: 0 | Q28: =+E28+F28+G28+H28+I28+J28+L28+O28+P28 -> 0 | R28: =+C28+D28-Q28 -> 0
A29: =+A28+1 -> 26 | B29: SIMO PIERRE | C29: 0 | D29: 70000 | G29: 70000 | Q29: =+E29+F29+G29+H29+I29+J29+L29+O29+P29 -> 70000 | R29: =+C29+D29-Q29 -> 0
A30: =+A29+1 -> 27 | B30: TCHOUAMOU MATHIEU | C30: 0 | D30: 70000 | K30: 70000 | Q30: =+E30+F30+G30+H30+I30+J30+L30+O30+P30 -> 0 | R30: =+C30+D30-Q30 -> 70000
A31: =+A30+1 -> 28 | B31: TIEYAM ERNEST | C31: 0 | D31: 0 | Q31: =+E31+F31+G31+H31+I31+J31+L31+O31+P31 -> 0 | R31: =+C31+D31-Q31 -> 0
A32: =+A31+1 -> 29 | B32: YEPMOU JEAN JACQUES | C32: 0 | D32: 70000 | Q32: =+E32+F32+G32+H32+I32+J32+L32+O32+P32 -> 0 | R32: =+C32+D32-Q32 -> 70000
A33: =+A32+1 -> 30 | B33: YOUMBI EMMANUEL | C33: 0 | D33: 70000 | J33: 70000 | Q33: =+E33+F33+G33+H33+I33+J33+L33+O33+P33 -> 70000 | R33: =+C33+D33-Q33 -> 0
A34: =+A33+1 -> 31 | B34: BAKOP ACHILLE | C34: 70000 | D34: 70000 | K34: 140000 | Q34: =+E34+F34+G34+H34+I34+J34+L34+O34+P34 -> 0 | R34: =+C34+D34-Q34 -> 140000
A35: =+A34+1 -> 32 | B35: SEUMOU POLYCARPE | C35: 0 | D35: 70000 | M35: 70000 | Q35: =+E35+F35+G35+H35+I35+J35+L35+O35+P35 -> 0 | R35: =+C35+D35-Q35 -> 70000
A36: =+A35+1 -> 33 | B36: YANTCHOU GERVAIS | C36: 170000 | D36: 70000 | Q36: =+E36+F36+G36+H36+I36+J36+L36+O36+P36 -> 0 | R36: =+C36+D36-Q36 -> 240000
A37: =+A36+1 -> 34 | B37: NOUBE ETIENNE | C37: 0 | D37: 70000 | M37: 70000 | Q37: =+E37+F37+G37+H37+I37+J37+L37+O37+P37 -> 0 | R37: =+C37+D37-Q37 -> 70000
A38: =+A37+1 -> 35 | B38: TCHOUTOU NANA CLAUDE | C38: 0 | D38: 70000 | Q38: =+E38+F38+G38+H38+I38+J38+L38+O38+P38 -> 0
A39: =+A38+1 -> 36 | Q39: =+E39+F39+G39+H39+I39+J39+L39+O39+P39 -> 0
A40: =+A39+1 -> 37
A41: =+A40+1 -> 38
A42: =+A41+1 -> 39
A43: TOTAL | C43: =SUM(C3:C42) -> 380000 | D43: =SUM(D3:D42) -> 2100000 | E43: =SUM(E3:E42) -> 210000 | F43: =SUM(F3:F42) -> 140000 | G43: =SUM(G3:G42) -> 210000 | H43: =SUM(H3:H42) -> 140000 | I43: =SUM(I3:I42) -> 280000 | J43: =SUM(J3:J42) -> 140000 | ... P43: =SUM(P3:P42) -> 0 | Q43: =SUM(Q3:Q37) -> 1260000 | R43: =SUM(R3:R37) -> 1150000
A44: SOLDE | D44: =+(C43+D43)-Q43 -> 1220000

Sheet SYNTHESE DES FINANCES
A1: N° | B1: RUBRIQUES | C1: REPORT A NOUVEAU | D1: ENTREES | E1: SORTIES | F1: SOLDES
A2: 1 | B2: FONDS DE CAISSE ET RELIQUAT | C2: 21567166 | D2: =+'EPARGNE 2023'!AT39+640701+'EPARGNE 2023'!AU39 -> 8200468 | F2: =+C2+D2-E2 -> 29767634
A3: =1+A2 -> 2 | B3: FONDS DE ROULEMENT | C3: 1996228 | D3: =+'BROUILLARD DE CAISSE 2023'!D610 -> 332000 | E3: =+'CAISSE 2023'!D23+'CAISSE 2023'!D37+'CAISSE 2023'!D38+'CAISSE 2023'!D39+'CAISSE 2023'!D45+'CAISSE 2023'!D53+'CAISSE 2023'!D84+'CAISSE 2023'!D113+'CAISSE 2023'!D143 -> 295500 | F3: =+C3+D3-E3 -> 2032728
A4: =1+A3 -> 3 | B4: FRAIS EXCEPTIONNELS | C4: 1503460 | D4: =+'BROUILLARD DE CAISSE 2023'!E610 -> 329000 | F4: =+C4+D4-E4 -> 1832460
A5: =1+A4 -> 4 | B5: MUTUELLE | C5: 634762 | D5: =+'BROUILLARD DE CAISSE 2023'!R610 -> 360000 | E5: =+'CAISSE 2023'!D52+'CAISSE 2023'!D136+'CAISSE 2023'!D146 -> 760000 | F5: =+C5+D5-E5 -> 234762
A6: =1+A5 -> 5 | B6: INSCRIPTION | C6: 680000 | D6: =+'BROUILLARD DE CAISSE 2023'!N610 -> 75000 | F6: =+C6+D6-E6 -> 755000
A7: =1+A6 -> 6 | B7: PENALITES | C7: 768025 | D7: =+'BROUILLARD DE CAISSE 2023'!O610 -> 76000 | F7: =+C7+D7-E7 -> 844025
A8: =1+A7 -> 7 | B8: COLLATION | C8: 1320525 | D8: =+'BROUILLARD DE CAISSE 2023'!F610 -> 1320000 | E8: =+'CAISSE 2023'!D24+'CAISSE 2023'!D82+'CAISSE 2023'!D83+'CAISSE 2023'!D112+'CAISSE 2023'!D148 -> 500000 | F8: =+C8+D8-E8 -> 2140525
A9: =1+A8 -> 8 | B9: TONTINE DE PRESENCE | C9: 94000 | D9: =+'BROUILLARD DE CAISSE 2023'!G610+'BROUILLARD DE CAISSE 2023'!H610 -> 9075500 | E9: =+'CAISSE 2023'!D5+'CAISSE 2023'!D6+'CAISSE 2023'!D7+'CAISSE 2023'!D8+'CAISSE 2023'!D9+'CAISSE 2023'!D10+'CAISSE 2023'!D11+'CAISSE 2023'!D40+'CAISSE 2023'!D41+'CAISSE 2023'!D42+'CAISSE 2023'!D48+'CAISSE 2023'!D49+'CAISSE 2023'!D50+'CAISSE 2023'!D74+'CAISSE 2023'!D75+'CAISSE 2023'!D76+'CAISSE 2023'!D103+'CAISSE 2023'!D104+'CAISSE 2023'!D105+'CAISSE 2023'!D106+'CAISSE 2023'!D111+'CAISSE 2023'!D134+'CAISSE 2023'!D140+'CAISSE 2023'!D141+'CAISSE 2023'!D144 -> 4418500 | F9: =+C9+D9-E9 -> 4751000
A10: =1+A9 -> 9 | B10: RECOUVREMENT LAGWEU | C10: 0 | F10: =+C10+D10-E10 -> 0
A11: =1+A10 -> 10 | B11: FOYER | C11: 586000 | D11: =+'BROUILLARD DE CAISSE 2023'!Q610+1750000 -> 1260000 | E11: 1750000 | F11: =+C11+D11-E11 -> 96000
A12: =1+A11 -> 11 | B12: INTERETS PRETS ET AUTRES | C12: 3293134 | F12: =+C12+D12-E12 -> 3293134
A13: =1+A12 -> 12 | B13: TONTINE DE 75000 | C13: 0 | D13: =+'BROUILLARD DE CAISSE 2023'!I610+'BROUILLARD DE CAISSE 2023'!J610 -> #VALUE! | E13: =+'CAISSE 2023'!D151+'CAISSE 2023'!D150+'CAISSE 2023'!D145+'CAISSE 2023'!D137+'CAISSE 2023'!D135+'CAISSE 2023'!D109+'CAISSE 2023'!D108+'CAISSE 2023'!D107+'CAISSE 2023'!D101+'CAISSE 2023'!D71+'CAISSE 2023'!D69+'CAISSE 2023'!D44+'CAISSE 2023'!D43+'CAISSE 2023'!D22+'CAISSE 2023'!D21+'CAISSE 2023'!D20+'CAISSE 2023'!D19+'CAISSE 2023'!D18 -> 8243000 | F13: =+C13+D13-E13 -> #VALUE!
A14: =1+A13 -> 13 | B14: TONTINE DE 100 000 | C14: -1452000 | D14: =1452000+'BROUILLARD DE CAISSE 2023'!K610+'BROUILLARD DE CAISSE 2023'!L610 -> 22212500 | E14: =+'CAISSE 2023'!D12+'CAISSE 2023'!D13+'CAISSE 2023'!D14+'CAISSE 2023'!D15+'CAISSE 2023'!D16+'CAISSE 2023'!D17+'CAISSE 2023'!D46+'CAISSE 2023'!D47+'CAISSE 2023'!D72+'CAISSE 2023'!D73+'CAISSE 2023'!D77+'CAISSE 2023'!D78+'CAISSE 2023'!D79+'CAISSE 2023'!D80+'CAISSE 2023'!D81+'CAISSE 2023'!D102+'CAISSE 2023'!D110+'CAISSE 2023'!D139+'CAISSE 2023'!D142+'CAISSE 2023'!D149 -> 12582000 | F14: =+C14+D14-E14 -> 8178500
A15: =1+A14 -> 14 | B15: ANCIENNES TONTINES | C15: 0 | F15: =+C15+D15-E15 -> 0
A16: =1+A15 -> 15 | B16: SURPLUS DE CAISSE | C16: 82104 | F16: =+C16+D16-E16 -> 82104
A17: =1+A16 -> 16 | C17: 0 | F17: =+C17+D17-E17 -> 0
B18: TOTAL | C18: =SUM(C2:C17) -> 31073404 | D18: =SUM(D2:D17) -> #VALUE! | E18: =SUM(E2:E17) -> 28549000 | F18: =SUM(F2:F17) -> #VALUE!
