Workbook
Name MODEPAID: [1]Feuil2!$A$1:$A$3

Sheet FICHESUIVI
A1: LIEU RECEPTION | D1: TONTINE 20 000 | E1: TONTINE 60 000 | F1: TONTINE 100 000
A2: NOM ADHERENT
A3: DATE TONTINE
A4: NOM ACHETEUR
A5: MONTANT INTERET ACHAT
A6: NATURE OPERATION | B6: EPARGNE | D6: FONDS DE ROULEMENT | F6: FRAIS EXCEPTIONNEL | H6: COLLATION | J6: EMPRUNT/REMBOURSEMENT | L6: PENALITE EMPRUNT | M6: PENALITE FONDS | N6: INTERET ACHAT TONTINE | O6: COMPLEMENT TONTINE | Q6: SANCTION
B7: ENTREE | C7: SORTIE | D7: ENTREE | E7: SORTIE | F7: ENTREE | G7: SORTIE | H7: ENTREE | I7: SORTIE | J7: ENTREE | K7: SORTIE | L7: ENTREE | M7: ENTREE | N7: ENTREE | O7: ENTREE | P7: SORTIE | Q7: ENTREE | R7: SORTIE

Sheet TRAVAUXINVENTAIRE
A1: ASSOCIATION | B1: ASELBY
A2: ANNEE | B2: 2016/2017
A3: TONTINE | B3: 20 000
A4: MATRICULE | B4: NOM ET PRENOM | C4: FONDS DE CAISSE | D4: RELIQUAT 2015 | E4: CAPITAL DEPART | F4: REPARTITION INTERET | G4: CAPITAL COMPOSE FIN | H4: CAPITAL TOTAL A PERCEVOIR | I4: RETENUE | J4: CAPITAL A DISTRIBUER | K4: MONTANT EFFECTIVEMENT VERSE | L4: COMPLEMENT FONDS | M4: SANCTION | N4: RETOUR EN CAISSE MUTUELLE | O4: FRAIS FIXE A PRELEVER | P4: MONTANT VERSE | Q4: EPARGNE | R4: FONDS DE ROULEMENT | S4: FRAIS EXCEPTIONNEL | T4: COLLATION | U4: MUTUELLE | V4: TONTINE | W4: EMPRUNT | X4: INTERET EMPRUNT | Y4: REMBOURSEMENT | Z4: PENALITE EMPRUNT | AA4: PENALITE FONDS | AB4: INTERET ACHAT | AC4: DATE ACHAT
A5: AS201648 | B5: =VLOOKUP(A5,[2]LISTADHERENT!A$5:H$52,2,0) -> ASELBY | C5: =VLOOKUP(A5,[2]FONDSDECAISSE!A$5:C$52,3,0) -> 0 | D5: 318145 | E5: =C5+D5+Q5 -> 318145 | F5: =INT([2]TONT20000DEC2015!E5+[2]TONT20000JANV!C5+[2]TONT20000FEV!C5+[2]TONT20000MARS!C5+[2]TONT20000AVRIL!C5+[2]TONT20000MAI!C5+[2]TONT20000JUIN!C5+[2]TONT20000JUIL!C5+[2]TONT20000AOUT!C5+[2]TONT20000SEPT!C5+[2]TONT20000OCT!C5+[2]TONT20000NOV!C5) -> 36952 | G5: =[2]TONT20000NOV!E5 -> 355097.52 | H5: =D5+F5+Q5 -> 355097 | I5: =L5+M5+N5+O5 -> 0 | J5: =H5-I5 -> 355097 | K5: 353000 | L5: 0 | M5: 0 | N5: 0 | O5: 0 | P5: =[2]TONT20000DEC2015!H5+[2]TONT20000JANV!F5+[2]TONT20000FEV!F5+[2]TONT20000MARS!F5+[2]TONT20000AVRIL!F5+[2]TONT20000MAI!F5+[2]TONT20000JUIN!F5+[2]TONT20000JUIL!F5+[2]TONT20000AOUT!F5+[2]TONT20000SEPT!F5+[2]TONT20000OCT!F5+[2]TONT20000NOV!G5 -> 0 | Q5: =[2]TONT20000DEC2015!I5+[2]TONT20000JANV!G5+[2]TONT20000FEV!G5+[2]TONT20000MARS!G5+[2]TONT20000AVRIL!G5+[2]TONT20000MAI!G5+[2]TONT20000JUIN!G5+[2]TONT20000JUIL!G5+[2]TONT20000AOUT!G5+[2]TONT20000SEPT!G5+[2]TONT20000OCT!G5+[2]TONT20000NOV!H5 -> 0 | R5: =[2]TONT20000DEC2015!J5+[2]TONT20000JANV!H5+[2]TONT20000FEV!H5+[2]TONT20000MARS!H5+[2]TONT20000AVRIL!H5+[2]TONT20000MAI!H5+[2]TONT20000JUIN!H5+[2]TONT20000JUIL!H5+[2]TONT20000AOUT!H5+[2]TONT20000SEPT!H5+[2]TONT20000OCT!H5+[2]TONT20000NOV!I5 -> 0 | S5: =[2]TONT20000DEC2015!K5+[2]TONT20000JANV!I5+[2]TONT20000FEV!I5+[2]TONT20000MARS!I5+[2]TONT20000AVRIL!I5+[2]TONT20000MAI!I5+[2]TONT20000JUIN!I5+[2]TONT20000JUIL!I5+[2]TONT20000AOUT!I5+[2]TONT20000SEPT!I5+[2]TONT20000OCT!I5+[2]TONT20000NOV!J5 -> 0 | T5: =[2]TONT20000DEC2015!L5+[2]TONT20000JANV!J5+[2]TONT20000FEV!J5+[2]TONT20000MARS!J5+[2]TONT20000AVRIL!J5+[2]TONT20000MAI!J5+[2]TONT20000JUIN!J5+[2]TONT20000JUIL!J5+[2]TONT20000AOUT!J5+[2]TONT20000SEPT!J5+[2]TONT20000OCT!J5+[2]TONT20000NOV!K5 -> 0 | U5: =[2]TONT20000DEC2015!M5+[2]TONT20000JANV!K5+[2]TONT20000FEV!K5+[2]TONT20000MARS!K5+[2]TONT20000AVRIL!K5+[2]TONT20000MAI!K5+[2]TONT20000JUIN!K5+[2]TONT20000JUIL!K5+[2]TONT20000AOUT!K5+[2]TONT20000SEPT!K5+[2]TONT20000OCT!K5+[2]TONT20000NOV!L5 -> 0 | V5: =[2]TONT20000DEC2015!N5+[2]TONT20000JANV!L5+[2]TONT20000FEV!L5+[2]TONT20000MARS!L5+[2]TONT20000AVRIL!L5+[2]TONT20000MAI!L5+[2]TONT20000JUIN!L5+[2]TONT20000JUIL!L5+[2]TONT20000AOUT!L5+[2]TONT20000SEPT!L5+[2]TONT20000OCT!L5+[2]TONT20000NOV!M5 -> 0 | W5: =[2]TONT20000DEC2015!O5+[2]TONT20000JANV!M5+[2]TONT20000FEV!M5+[2]TONT20000MARS!M5+[2]TONT20000AVRIL!M5+[2]TONT20000MAI!M5+[2]TONT20000JUIN!M5+[2]TONT20000JUIL!M5+[2]TONT20000AOUT!M5+[2]TONT20000SEPT!M5+[2]TONT20000OCT!M5+[2]TONT20000NOV!N5 -> 0 | ... AB5: =[2]TONT20000DEC2015!T5+[2]TONT20000JANV!R5+[2]TONT20000FEV!R5+[2]TONT20000MARS!R5+[2]TONT20000AVRIL!R5+[2]TONT20000MAI!R5+[2]TONT20000JUIN!R5+[2]TONT20000JUIL!R5+[2]TONT20000AOUT!R5+[2]TONT20000SEPT!R5+[2]TONT20000OCT!R5+[2]TONT20000NOV!S5 -> 0
A6: AS201601 | B6: =VLOOKUP(A6,[2]LISTADHERENT!A$5:H$52,2,0) -> BAKOP ACHILLE | C6: =VLOOKUP(A6,[2]FONDSDECAISSE!A$5:C$52,3,0) -> 390000 | D6: 33536 | E6: =C6+D6+Q6 -> 453536 | F6: =INT([2]TONT20000DEC2015!E6+[2]TONT20000JANV!C6+[2]TONT20000FEV!C6+[2]TONT20000MARS!C6+[2]TONT20000AVRIL!C6+[2]TONT20000MAI!C6+[2]TONT20000JUIN!C6+[2]TONT20000JUIL!C6+[2]TONT20000AOUT!C6+[2]TONT20000SEPT!C6+[2]TONT20000OCT!C6+[2]TONT20000NOV!C6) -> 51457 | G6: =[2]TONT20000NOV!E6 -> 504993.98 | H6: =D6+F6+Q6 -> 114993 | I6: =L6+M6+N6+O6 -> 63000 | J6: =H6-I6 -> 51993 | K6: 0 | L6: 30000 | N6: 25000 | O6: =48000-(R6+S6+T6) -> 8000 | P6: =[2]TONT20000DEC2015!H6+[2]TONT20000JANV!F6+[2]TONT20000FEV!F6+[2]TONT20000MARS!F6+[2]TONT20000AVRIL!F6+[2]TONT20000MAI!F6+[2]TONT20000JUIN!F6+[2]TONT20000JUIL!F6+[2]TONT20000AOUT!F6+[2]TONT20000SEPT!F6+[2]TONT20000OCT!F6+[2]TONT20000NOV!G6 -> 225000 | Q6: =[2]TONT20000DEC2015!I6+[2]TONT20000JANV!G6+[2]TONT20000FEV!G6+[2]TONT20000MARS!G6+[2]TONT20000AVRIL!G6+[2]TONT20000MAI!G6+[2]TONT20000JUIN!G6+[2]TONT20000JUIL!G6+[2]TONT20000AOUT!G6+[2]TONT20000SEPT!G6+[2]TONT20000OCT!G6+[2]TONT20000NOV!H6 -> 30000 | R6: =[2]TONT20000DEC2015!J6+[2]TONT20000JANV!H6+[2]TONT20000FEV!H6+[2]TONT20000MARS!H6+[2]TONT20000AVRIL!H6+[2]TONT20000MAI!H6+[2]TONT20000JUIN!H6+[2]TONT20000JUIL!H6+[2]TONT20000AOUT!H6+[2]TONT20000SEPT!H6+[2]TONT20000OCT!H6+[2]TONT20000NOV!I6 -> 5000 | S6: =[2]TONT20000DEC2015!K6+[2]TONT20000JANV!I6+[2]TONT20000FEV!I6+[2]TONT20000MARS!I6+[2]TONT20000AVRIL!I6+[2]TONT20000MAI!I6+[2]TONT20000JUIN!I6+[2]TONT20000JUIL!I6+[2]TONT20000AOUT!I6+[2]TONT20000SEPT!I6+[2]TONT20000OCT!I6+[2]TONT20000NOV!J6 -> 10000 | T6: =[2]TONT20000DEC2015!L6+[2]TONT20000JANV!J6+[2]TONT20000FEV!J6+[2]TONT20000MARS!J6+[2]TONT20000AVRIL!J6+[2]TONT20000MAI!J6+[2]TONT20000JUIN!J6+[2]TONT20000JUIL!J6+[2]TONT20000AOUT!J6+[2]TONT20000SEPT!J6+[2]TONT20000OCT!J6+[2]TONT20000NOV!K6 -> 25000 | U6: =[2]TONT20000DEC2015!M6+[2]TONT20000JANV!K6+[2]TONT20000FEV!K6+[2]TONT20000MARS!K6+[2]TONT20000AVRIL!K6+[2]TONT20000MAI!K6+[2]TONT20000JUIN!K6+[2]TONT20000JUIL!K6+[2]TONT20000AOUT!K6+[2]TONT20000SEPT!K6+[2]TONT20000OCT!K6+[2]TONT20000NOV!L6 -> 25000 | V6: =[2]TONT20000DEC2015!N6+[2]TONT20000JANV!L6+[2]TONT20000FEV!L6+[2]TONT20000MARS!L6+[2]TONT20000AVRIL!L6+[2]TONT20000MAI!L6+[2]TONT20000JUIN!L6+[2]TONT20000JUIL!L6+[2]TONT20000AOUT!L6+[2]TONT20000SEPT!L6+[2]TONT20000OCT!L6+[2]TONT20000NOV!M6 -> 130000 | W6: =[2]TONT20000DEC2015!O6+[2]TONT20000JANV!M6+[2]TONT20000FEV!M6+[2]TONT20000MARS!M6+[2]TONT20000AVRIL!M6+[2]TONT20000MAI!M6+[2]TONT20000JUIN!M6+[2]TONT20000JUIL!M6+[2]TONT20000AOUT!M6+[2]TONT20000SEPT!M6+[2]TONT20000OCT!M6+[2]TONT20000NOV!N6 -> 500000 | ... AB6: =[2]TONT20000DEC2015!T6+[2]TONT20000JANV!R6+[2]TONT20000FEV!R6+[2]TONT20000MARS!R6+[2]TONT20000AVRIL!R6+[2]TONT20000MAI!R6+[2]TONT20000JUIN!R6+[2]TONT20000JUIL!R6+[2]TONT20000AOUT!R6+[2]TONT20000SEPT!R6+[2]TONT20000OCT!R6+[2]TONT20000NOV!S6 -> 0
A7: AS201602 | B7: =VLOOKUP(A7,[2]LISTADHERENT!A$5:H$52,2,0) -> BOUTCHOUANG WILLIAM | C7: =VLOOKUP(A7,[2]FONDSDECAISSE!A$5:C$52,3,0) -> 390000 | D7: 1704 | E7: =C7+D7+Q7 -> 427704 | F7: =INT([2]TONT20000DEC2015!E7+[2]TONT20000JANV!C7+[2]TONT20000FEV!C7+[2]TONT20000MARS!C7+[2]TONT20000AVRIL!C7+[2]TONT20000MAI!C7+[2]TONT20000JUIN!C7+[2]TONT20000JUIL!C7+[2]TONT20000AOUT!C7+[2]TONT20000SEPT!C7+[2]TONT20000OCT!C7+[2]TONT20000NOV!C7) -> 48016 | G7: =[2]TONT20000NOV!E7 -> 475720.56 | H7: =D7+F7+Q7 -> 85720 | I7: =L7+M7+N7+O7 -> 80000 | J7: =H7-I7 -> 5720 | K7: 3000 | L7: 30000 | N7: 50000 | O7: =48000-(R7+S7+T7) -> 0 | P7: =[2]TONT20000DEC2015!H7+[2]TONT20000JANV!F7+[2]TONT20000FEV!F7+[2]TONT20000MARS!F7+[2]TONT20000AVRIL!F7+[2]TONT20000MAI!F7+[2]TONT20000JUIN!F7+[2]TONT20000JUIL!F7+[2]TONT20000AOUT!F7+[2]TONT20000SEPT!F7+[2]TONT20000OCT!F7+[2]TONT20000NOV!G7 -> 240000 | Q7: =[2]TONT20000DEC2015!I7+[2]TONT20000JANV!G7+[2]TONT20000FEV!G7+[2]TONT20000MARS!G7+[2]TONT20000AVRIL!G7+[2]TONT20000MAI!G7+[2]TONT20000JUIN!G7+[2]TONT20000JUIL!G7+[2]TONT20000AOUT!G7+[2]TONT20000SEPT!G7+[2]TONT20000OCT!G7+[2]TONT20000NOV!H7 -> 36000 | R7: =[2]TONT20000DEC2015!J7+[2]TONT20000JANV!H7+[2]TONT20000FEV!H7+[2]TONT20000MARS!H7+[2]TONT20000AVRIL!H7+[2]TONT20000MAI!H7+[2]TONT20000JUIN!H7+[2]TONT20000JUIL!H7+[2]TONT20000AOUT!H7+[2]TONT20000SEPT!H7+[2]TONT20000OCT!H7+[2]TONT20000NOV!I7 -> 6000 | S7: =[2]TONT20000DEC2015!K7+[2]TONT20000JANV!I7+[2]TONT20000FEV!I7+[2]TONT20000MARS!I7+[2]TONT20000AVRIL!I7+[2]TONT20000MAI!I7+[2]TONT20000JUIN!I7+[2]TONT20000JUIL!I7+[2]TONT20000AOUT!I7+[2]TONT20000SEPT!I7+[2]TONT20000OCT!I7+[2]TONT20000NOV!J7 -> 12000 | T7: =[2]TONT20000DEC2015!L7+[2]TONT20000JANV!J7+[2]TONT20000FEV!J7+[2]TONT20000MARS!J7+[2]TONT20000AVRIL!J7+[2]TONT20000MAI!J7+[2]TONT20000JUIN!J7+[2]TONT20000JUIL!J7+[2]TONT20000AOUT!J7+[2]TONT20000SEPT!J7+[2]TONT20000OCT!J7+[2]TONT20000NOV!K7 -> 30000 | U7: =[2]TONT20000DEC2015!M7+[2]TONT20000JANV!K7+[2]TONT20000FEV!K7+[2]TONT20000MARS!K7+[2]TONT20000AVRIL!K7+[2]TONT20000MAI!K7+[2]TONT20000JUIN!K7+[2]TONT20000JUIL!K7+[2]TONT20000AOUT!K7+[2]TONT20000SEPT!K7+[2]TONT20000OCT!K7+[2]TONT20000NOV!L7 -> 0 | V7: =[2]TONT20000DEC2015!N7+[2]TONT20000JANV!L7+[2]TONT20000FEV!L7+[2]TONT20000MARS!L7+[2]TONT20000AVRIL!L7+[2]TONT20000MAI!L7+[2]TONT20000JUIN!L7+[2]TONT20000JUIL!L7+[2]TONT20000AOUT!L7+[2]TONT20000SEPT!L7+[2]TONT20000OCT!L7+[2]TONT20000NOV!M7 -> 156000 | W7: =[2]TONT20000DEC2015!O7+[2]TONT20000JANV!M7+[2]TONT20000FEV!M7+[2]TONT20000MARS!M7+[2]TONT20000AVRIL!M7+[2]TONT20000MAI!M7+[2]TONT20000JUIN!M7+[2]TONT20000JUIL!M7+[2]TONT20000AOUT!M7+[2]TONT20000SEPT!M7+[2]TONT20000OCT!M7+[2]TONT20000NOV!N7 -> 1700000 | ... AB7: =[2]TONT20000DEC2015!T7+[2]TONT20000JANV!R7+[2]TONT20000FEV!R7+[2]TONT20000MARS!R7+[2]TONT20000AVRIL!R7+[2]TONT20000MAI!R7+[2]TONT20000JUIN!R7+[2]TONT20000JUIL!R7+[2]TONT20000AOUT!R7+[2]TONT20000SEPT!R7+[2]TONT20000OCT!R7+[2]TONT20000NOV!S7 -> 0
A8: AS201603 | B8: =VLOOKUP(A8,[2]LISTADHERENT!A$5:H$52,2,0) -> CHINGUE FABRICE | C8: =VLOOKUP(A8,[2]FONDSDECAISSE!A$5:C$52,3,0) -> 390000 | D8: 1842 | E8: =C8+D8+Q8 -> 427842 | F8: =INT([2]TONT20000DEC2015!E8+[2]TONT20000JANV!C8+[2]TONT20000FEV!C8+[2]TONT20000MARS!C8+[2]TONT20000AVRIL!C8+[2]TONT20000MAI!C8+[2]TONT20000JUIN!C8+[2]TONT20000JUIL!C8+[2]TONT20000AOUT!C8+[2]TONT20000SEPT!C8+[2]TONT20000OCT!C8+[2]TONT20000NOV!C8) -> 48032 | G8: =[2]TONT20000NOV!E8 -> 475874.59 | H8: =D8+F8+Q8 -> 85874 | I8: =L8+M8+N8+O8 -> 80000 | J8: =H8-I8 -> 5874 | K8: 0 | L8: 30000 | N8: 50000 | O8: =48000-(R8+S8+T8) -> 0 | P8: =[2]TONT20000DEC2015!H8+[2]TONT20000JANV!F8+[2]TONT20000FEV!F8+[2]TONT20000MARS!F8+[2]TONT20000AVRIL!F8+[2]TONT20000MAI!F8+[2]TONT20000JUIN!F8+[2]TONT20000JUIL!F8+[2]TONT20000AOUT!F8+[2]TONT20000SEPT!F8+[2]TONT20000OCT!F8+[2]TONT20000NOV!G8 -> 240000 | Q8: =[2]TONT20000DEC2015!I8+[2]TONT20000JANV!G8+[2]TONT20000FEV!G8+[2]TONT20000MARS!G8+[2]TONT20000AVRIL!G8+[2]TONT20000MAI!G8+[2]TONT20000JUIN!G8+[2]TONT20000JUIL!G8+[2]TONT20000AOUT!G8+[2]TONT20000SEPT!G8+[2]TONT20000OCT!G8+[2]TONT20000NOV!H8 -> 36000 | R8: =[2]TONT20000DEC2015!J8+[2]TONT20000JANV!H8+[2]TONT20000FEV!H8+[2]TONT20000MARS!H8+[2]TONT20000AVRIL!H8+[2]TONT20000MAI!H8+[2]TONT20000JUIN!H8+[2]TONT20000JUIL!H8+[2]TONT20000AOUT!H8+[2]TONT20000SEPT!H8+[2]TONT20000OCT!H8+[2]TONT20000NOV!I8 -> 6000 | S8: =[2]TONT20000DEC2015!K8+[2]TONT20000JANV!I8+[2]TONT20000FEV!I8+[2]TONT20000MARS!I8+[2]TONT20000AVRIL!I8+[2]TONT20000MAI!I8+[2]TONT20000JUIN!I8+[2]TONT20000JUIL!I8+[2]TONT20000AOUT!I8+[2]TONT20000SEPT!I8+[2]TONT20000OCT!I8+[2]TONT20000NOV!J8 -> 12000 | T8: =[2]TONT20000DEC2015!L8+[2]TONT20000JANV!J8+[2]TONT20000FEV!J8+[2]TONT20000MARS!J8+[2]TONT20000AVRIL!J8+[2]TONT20000MAI!J8+[2]TONT20000JUIN!J8+[2]TONT20000JUIL!J8+[2]TONT20000AOUT!J8+[2]TONT20000SEPT!J8+[2]TONT20000OCT!J8+[2]TONT20000NOV!K8 -> 30000 | U8: =[2]TONT20000DEC2015!M8+[2]TONT20000JANV!K8+[2]TONT20000FEV!K8+[2]TONT20000MARS!K8+[2]TONT20000AVRIL!K8+[2]TONT20000MAI!K8+[2]TONT20000JUIN!K8+[2]TONT20000JUIL!K8+[2]TONT20000AOUT!K8+[2]TONT20000SEPT!K8+[2]TONT20000OCT!K8+[2]TONT20000NOV!L8 -> 0 | V8: =[2]TONT20000DEC2015!N8+[2]TONT20000JANV!L8+[2]TONT20000FEV!L8+[2]TONT20000MARS!L8+[2]TONT20000AVRIL!L8+[2]TONT20000MAI!L8+[2]TONT20000JUIN!L8+[2]TONT20000JUIL!L8+[2]TONT20000AOUT!L8+[2]TONT20000SEPT!L8+[2]TONT20000OCT!L8+[2]TONT20000NOV!M8 -> 156000 | W8: =[2]TONT20000DEC2015!O8+[2]TONT20000JANV!M8+[2]TONT20000FEV!M8+[2]TONT20000MARS!M8+[2]TONT20000AVRIL!M8+[2]TONT20000MAI!M8+[2]TONT20000JUIN!M8+[2]TONT20000JUIL!M8+[2]TONT20000AOUT!M8+[2]TONT20000SEPT!M8+[2]TONT20000OCT!M8+[2]TONT20000NOV!N8 -> 2000000 | ... AB8: =[2]TONT20000DEC2015!T8+[2]TONT20000JANV!R8+[2]TONT20000FEV!R8+[2]TONT20000MARS!R8+[2]TONT20000AVRIL!R8+[2]TONT20000MAI!R8+[2]TONT20000JUIN!R8+[2]TONT20000JUIL!R8+[2]TONT20000AOUT!R8+[2]TONT20000SEPT!R8+[2]TONT20000OCT!R8+[2]TONT20000NOV!S8 -> 0
A9: AS201604 | B9: =VLOOKUP(A9,[2]LISTADHERENT!A$5:H$52,2,0) -> DJOMO JEAN PAUL | C9: =VLOOKUP(A9,[2]FONDSDECAISSE!A$5:C$52,3,0) -> 390000 | D9: 8156 | E9: =C9+D9+Q9 -> 441156 | F9: =INT([2]TONT20000DEC2015!E9+[2]TONT20000JANV!C9+[2]TONT20000FEV!C9+[2]TONT20000MARS!C9+[2]TONT20000AVRIL!C9+[2]TONT20000MAI!C9+[2]TONT20000JUIN!C9+[2]TONT20000JUIL!C9+[2]TONT20000AOUT!C9+[2]TONT20000SEPT!C9+[2]TONT20000OCT!C9+[2]TONT20000NOV!C9) -> 48914 | G9: =[2]TONT20000NOV!E9 -> 490070.36 | H9: =D9+F9+Q9 -> 100070 | I9: =L9+M9+N9+O9 -> 80000 | J9: =H9-I9 -> 20070 | K9: 17500 | L9: 30000 | N9: 50000 | O9: =48000-(R9+S9+T9) -> 0 | P9: =[2]TONT20000DEC2015!H9+[2]TONT20000JANV!F9+[2]TONT20000FEV!F9+[2]TONT20000MARS!F9+[2]TONT20000AVRIL!F9+[2]TONT20000MAI!F9+[2]TONT20000JUIN!F9+[2]TONT20000JUIL!F9+[2]TONT20000AOUT!F9+[2]TONT20000SEPT!F9+[2]TONT20000OCT!F9+[2]TONT20000NOV!G9 -> 247000 | Q9: =[2]TONT20000DEC2015!I9+[2]TONT20000JANV!G9+[2]TONT20000FEV!G9+[2]TONT20000MARS!G9+[2]TONT20000AVRIL!G9+[2]TONT20000MAI!G9+[2]TONT20000JUIN!G9+[2]TONT20000JUIL!G9+[2]TONT20000AOUT!G9+[2]TONT20000SEPT!G9+[2]TONT20000OCT!G9+[2]TONT20000NOV!H9 -> 43000 | R9: =[2]TONT20000DEC2015!J9+[2]TONT20000JANV!H9+[2]TONT20000FEV!H9+[2]TONT20000MARS!H9+[2]TONT20000AVRIL!H9+[2]TONT20000MAI!H9+[2]TONT20000JUIN!H9+[2]TONT20000JUIL!H9+[2]TONT20000AOUT!H9+[2]TONT20000SEPT!H9+[2]TONT20000OCT!H9+[2]TONT20000NOV!I9 -> 6000 | S9: =[2]TONT20000DEC2015!K9+[2]TONT20000JANV!I9+[2]TONT20000FEV!I9+[2]TONT20000MARS!I9+[2]TONT20000AVRIL!I9+[2]TONT20000MAI!I9+[2]TONT20000JUIN!I9+[2]TONT20000JUIL!I9+[2]TONT20000AOUT!I9+[2]TONT20000SEPT!I9+[2]TONT20000OCT!I9+[2]TONT20000NOV!J9 -> 12000 | T9: =[2]TONT20000DEC2015!L9+[2]TONT20000JANV!J9+[2]TONT20000FEV!J9+[2]TONT20000MARS!J9+[2]TONT20000AVRIL!J9+[2]TONT20000MAI!J9+[2]TONT20000JUIN!J9+[2]TONT20000JUIL!J9+[2]TONT20000AOUT!J9+[2]TONT20000SEPT!J9+[2]TONT20000OCT!J9+[2]TONT20000NOV!K9 -> 30000 | U9: =[2]TONT20000DEC2015!M9+[2]TONT20000JANV!K9+[2]TONT20000FEV!K9+[2]TONT20000MARS!K9+[2]TONT20000AVRIL!K9+[2]TONT20000MAI!K9+[2]TONT20000JUIN!K9+[2]TONT20000JUIL!K9+[2]TONT20000AOUT!K9+[2]TONT20000SEPT!K9+[2]TONT20000OCT!K9+[2]TONT20000NOV!L9 -> 0 | V9: =[2]TONT20000DEC2015!N9+[2]TONT20000JANV!L9+[2]TONT20000FEV!L9+[2]TONT20000MARS!L9+[2]TONT20000AVRIL!L9+[2]TONT20000MAI!L9+[2]TONT20000JUIN!L9+[2]TONT20000JUIL!L9+[2]TONT20000AOUT!L9+[2]TONT20000SEPT!L9+[2]TONT20000OCT!L9+[2]TONT20000NOV!M9 -> 156000 | W9: =[2]TONT20000DEC2015!O9+[2]TONT20000JANV!M9+[2]TONT20000FEV!M9+[2]TONT20000MARS!M9+[2]TONT20000AVRIL!M9+[2]TONT20000MAI!M9+[2]TONT20000JUIN!M9+[2]TONT20000JUIL!M9+[2]TONT20000AOUT!M9+[2]TONT20000SEPT!M9+[2]TONT20000OCT!M9+[2]TONT20000NOV!N9 -> 200000 | ... AB9: =[2]TONT20000DEC2015!T9+[2]TONT20000JANV!R9+[2]TONT20000FEV!R9+[2]TONT20000MARS!R9+[2]TONT20000AVRIL!R9+[2]TONT20000MAI!R9+[2]TONT20000JUIN!R9+[2]TONT20000JUIL!R9+[2]TONT20000AOUT!R9+[2]TONT20000SEPT!R9+[2]TONT20000OCT!R9+[2]TONT20000NOV!S9 -> 0
A10: AS201605 | B10: =VLOOKUP(A10,[2]LISTADHERENT!A$5:H$52,2,0) -> DJOUKWE GUY | C10: =VLOOKUP(A10,[2]FONDSDECAISSE!A$5:C$52,3,0) -> 390000 | D10: 5905 | E10: =C10+D10+Q10 -> 471905 | F10: =INT([2]TONT20000DEC2015!E10+[2]TONT20000JANV!C10+[2]TONT20000FEV!C10+[2]TONT20000MARS!C10+[2]TONT20000AVRIL!C10+[2]TONT20000MAI!C10+[2]TONT20000JUIN!C10+[2]TONT20000JUIL!C10+[2]TONT20000AOUT!C10+[2]TONT20000SEPT!C10+[2]TONT20000OCT!C10+[2]TONT20000NOV!C10) -> 51792 | G10: =[2]TONT20000NOV!E10 -> 523697.05 | H10: =D10+F10+Q10 -> 133697 | I10: =L10+M10+N10+O10 -> 80000 | J10: =H10-I10 -> 53697 | K10: 51000 | L10: 30000 | N10: 50000 | O10: =48000-(R10+S10+T10) -> 0 | P10: =[2]TONT20000DEC2015!H10+[2]TONT20000JANV!F10+[2]TONT20000FEV!F10+[2]TONT20000MARS!F10+[2]TONT20000AVRIL!F10+[2]TONT20000MAI!F10+[2]TONT20000JUIN!F10+[2]TONT20000JUIL!F10+[2]TONT20000AOUT!F10+[2]TONT20000SEPT!F10+[2]TONT20000OCT!F10+[2]TONT20000NOV!G10 -> 280000 | Q10: =[2]TONT20000DEC2015!I10+[2]TONT20000JANV!G10+[2]TONT20000FEV!G10+[2]TONT20000MARS!G10+[2]TONT20000AVRIL!G10+[2]TONT20000MAI!G10+[2]TONT20000JUIN!G10+[2]TONT20000JUIL!G10+[2]TONT20000AOUT!G10+[2]TONT20000SEPT!G10+[2]TONT20000OCT!G10+[2]TONT20000NOV!H10 -> 76000 | R10: =[2]TONT20000DEC2015!J10+[2]TONT20000JANV!H10+[2]TONT20000FEV!H10+[2]TONT20000MARS!H10+[2]TONT20000AVRIL!H10+[2]TONT20000MAI!H10+[2]TONT20000JUIN!H10+[2]TONT20000JUIL!H10+[2]TONT20000AOUT!H10+[2]TONT20000SEPT!H10+[2]TONT20000OCT!H10+[2]TONT20000NOV!I10 -> 6000 | S10: =[2]TONT20000DEC2015!K10+[2]TONT20000JANV!I10+[2]TONT20000FEV!I10+[2]TONT20000MARS!I10+[2]TONT20000AVRIL!I10+[2]TONT20000MAI!I10+[2]TONT20000JUIN!I10+[2]TONT20000JUIL!I10+[2]TONT20000AOUT!I10+[2]TONT20000SEPT!I10+[2]TONT20000OCT!I10+[2]TONT20000NOV!J10 -> 12000 | T10: =[2]TONT20000DEC2015!L10+[2]TONT20000JANV!J10+[2]TONT20000FEV!J10+[2]TONT20000MARS!J10+[2]TONT20000AVRIL!J10+[2]TONT20000MAI!J10+[2]TONT20000JUIN!J10+[2]TONT20000JUIL!J10+[2]TONT20000AOUT!J10+[2]TONT20000SEPT!J10+[2]TONT20000OCT!J10+[2]TONT20000NOV!K10 -> 30000 | U10: =[2]TONT20000DEC2015!M10+[2]TONT20000JANV!K10+[2]TONT20000FEV!K10+[2]TONT20000MARS!K10+[2]TONT20000AVRIL!K10+[2]TONT20000MAI!K10+[2]TONT20000JUIN!K10+[2]TONT20000JUIL!K10+[2]TONT20000AOUT!K10+[2]TONT20000SEPT!K10+[2]TONT20000OCT!K10+[2]TONT20000NOV!L10 -> 0 | V10: =[2]TONT20000DEC2015!N10+[2]TONT20000JANV!L10+[2]TONT20000FEV!L10+[2]TONT20000MARS!L10+[2]TONT20000AVRIL!L10+[2]TONT20000MAI!L10+[2]TONT20000JUIN!L10+[2]TONT20000JUIL!L10+[2]TONT20000AOUT!L10+[2]TONT20000SEPT!L10+[2]TONT20000OCT!L10+[2]TONT20000NOV!M10 -> 156000 | W10: =[2]TONT20000DEC2015!O10+[2]TONT20000JANV!M10+[2]TONT20000FEV!M10+[2]TONT20000MARS!M10+[2]TONT20000AVRIL!M10+[2]TONT20000MAI!M10+[2]TONT20000JUIN!M10+[2]TONT20000JUIL!M10+[2]TONT20000AOUT!M10+[2]TONT20000SEPT!M10+[2]TONT20000OCT!M10+[2]TONT20000NOV!N10 -> 250000 | ... AB10: =[2]TONT20000DEC2015!T10+[2]TONT20000JANV!R10+[2]TONT20000FEV!R10+[2]TONT20000MARS!R10+[2]TONT20000AVRIL!R10+[2]TONT20000MAI!R10+[2]TONT20000JUIN!R10+[2]TONT20000JUIL!R10+[2]TONT20000AOUT!R10+[2]TONT20000SEPT!R10+[2]TONT20000OCT!R10+[2]TONT20000NOV!S10 -> 0
A11: AS201606 | B11: =VLOOKUP(A11,[2]LISTADHERENT!A$5:H$52,2,0) -> DJOSSEU JOSUE
A12: AS201607 | B12: =VLOOKUP(A12,[2]LISTADHERENT!A$5:H$52,2,0) -> DJOUNKEP SAMUEL | C12: =VLOOKUP(A12,[2]FONDSDECAISSE!A$5:C$52,3,0) -> 390000 | D12: 1055294 | E12: =C12+D12+Q12 -> 2001294 | F12: =INT([2]TONT20000DEC2015!E12+[2]TONT20000JANV!C12+[2]TONT20000FEV!C12+[2]TONT20000MARS!C12+[2]TONT20000AVRIL!C12+[2]TONT20000MAI!C12+[2]TONT20000JUIN!C12+[2]TONT20000JUIL!C12+[2]TONT20000AOUT!C12+[2]TONT20000SEPT!C12+[2]TONT20000OCT!C12+[2]TONT20000NOV!C12) -> 204246 | G12: =[2]TONT20000NOV!E12 -> 2135835.7 | H12: =D12+F12+Q12 -> 1815540 | I12: =L12+M12+N12+O12 -> 80000 | J12: =H12-I12 -> 1735540 | K12: 1100000 | L12: 30000 | N12: 50000 | O12: =48000-(R12+S12+T12) -> 0 | P12: =[2]TONT20000DEC2015!H12+[2]TONT20000JANV!F12+[2]TONT20000FEV!F12+[2]TONT20000MARS!F12+[2]TONT20000AVRIL!F12+[2]TONT20000MAI!F12+[2]TONT20000JUIN!F12+[2]TONT20000JUIL!F12+[2]TONT20000AOUT!F12+[2]TONT20000SEPT!F12+[2]TONT20000OCT!F12+[2]TONT20000NOV!G12 -> 760000 | Q12: =[2]TONT20000DEC2015!I12+[2]TONT20000JANV!G12+[2]TONT20000FEV!G12+[2]TONT20000MARS!G12+[2]TONT20000AVRIL!G12+[2]TONT20000MAI!G12+[2]TONT20000JUIN!G12+[2]TONT20000JUIL!G12+[2]TONT20000AOUT!G12+[2]TONT20000SEPT!G12+[2]TONT20000OCT!G12+[2]TONT20000NOV!H12 -> 556000 | R12: =[2]TONT20000DEC2015!J12+[2]TONT20000JANV!H12+[2]TONT20000FEV!H12+[2]TONT20000MARS!H12+[2]TONT20000AVRIL!H12+[2]TONT20000MAI!H12+[2]TONT20000JUIN!H12+[2]TONT20000JUIL!H12+[2]TONT20000AOUT!H12+[2]TONT20000SEPT!H12+[2]TONT20000OCT!H12+[2]TONT20000NOV!I12 -> 6000 | S12: =[2]TONT20000DEC2015!K12+[2]TONT20000JANV!I12+[2]TONT20000FEV!I12+[2]TONT20000MARS!I12+[2]TONT20000AVRIL!I12+[2]TONT20000MAI!I12+[2]TONT20000JUIN!I12+[2]TONT20000JUIL!I12+[2]TONT20000AOUT!I12+[2]TONT20000SEPT!I12+[2]TONT20000OCT!I12+[2]TONT20000NOV!J12 -> 12000 | T12: =[2]TONT20000DEC2015!L12+[2]TONT20000JANV!J12+[2]TONT20000FEV!J12+[2]TONT20000MARS!J12+[2]TONT20000AVRIL!J12+[2]TONT20000MAI!J12+[2]TONT20000JUIN!J12+[2]TONT20000JUIL!J12+[2]TONT20000AOUT!J12+[2]TONT20000SEPT!J12+[2]TONT20000OCT!J12+[2]TONT20000NOV!K12 -> 30000 | U12: =[2]TONT20000DEC2015!M12+[2]TONT20000JANV!K12+[2]TONT20000FEV!K12+[2]TONT20000MARS!K12+[2]TONT20000AVRIL!K12+[2]TONT20000MAI!K12+[2]TONT20000JUIN!K12+[2]TONT20000JUIL!K12+[2]TONT20000AOUT!K12+[2]TONT20000SEPT!K12+[2]TONT20000OCT!K12+[2]TONT20000NOV!L12 -> 0 | V12: =[2]TONT20000DEC2015!N12+[2]TONT20000JANV!L12+[2]TONT20000FEV!L12+[2]TONT20000MARS!L12+[2]TONT20000AVRIL!L12+[2]TONT20000MAI!L12+[2]TONT20000JUIN!L12+[2]TONT20000JUIL!L12+[2]TONT20000AOUT!L12+[2]TONT20000SEPT!L12+[2]TONT20000OCT!L12+[2]TONT20000NOV!M12 -> 156000 | W12: =[2]TONT20000DEC2015!O12+[2]TONT20000JANV!M12+[2]TONT20000FEV!M12+[2]TONT20000MARS!M12+[2]TONT20000AVRIL!M12+[2]TONT20000MAI!M12+[2]TONT20000JUIN!M12+[2]TONT20000JUIL!M12+[2]TONT20000AOUT!M12+[2]TONT20000SEPT!M12+[2]TONT20000OCT!M12+[2]TONT20000NOV!N12 -> 0 | ... AB12: =[2]TONT20000DEC2015!T12+[2]TONT20000JANV!R12+[2]TONT20000FEV!R12+[2]TONT20000MARS!R12+[2]TONT20000AVRIL!R12+[2]TONT20000MAI!R12+[2]TONT20000JUIN!R12+[2]TONT20000JUIL!R12+[2]TONT20000AOUT!R12+[2]TONT20000SEPT!R12+[2]TONT20000OCT!R12+[2]TONT20000NOV!S12 -> 0
A13: AS201608 | B13: =VLOOKUP(A13,[2]LISTADHERENT!A$5:H$52,2,0) -> DJUOMBESSY ANTOINE | C13: 390000 | D13: 0 | E13: =C13+D13+Q13 -> 457560 | F13: =INT([2]TONT20000DEC2015!E13+[2]TONT20000JANV!C13+[2]TONT20000FEV!C13+[2]TONT20000MARS!C13+[2]TONT20000AVRIL!C13+[2]TONT20000MAI!C13+[2]TONT20000JUIN!C13+[2]TONT20000JUIL!C13+[2]TONT20000AOUT!C13+[2]TONT20000SEPT!C13+[2]TONT20000OCT!C13+[2]TONT20000NOV!C13) -> 43186 | G13: =[2]TONT20000NOV!E13 -> 500746.25 | H13: =D13+F13+Q13 -> 110746 | I13: =L13+M13+N13+O13 -> 80000 | J13: =H13-I13 -> 30746 | K13: 28000 | L13: 30000 | N13: 50000 | O13: =48000-(R13+S13+T13) -> 0 | P13: =[2]TONT20000DEC2015!H13+[2]TONT20000JANV!F13+[2]TONT20000FEV!F13+[2]TONT20000MARS!F13+[2]TONT20000AVRIL!F13+[2]TONT20000MAI!F13+[2]TONT20000JUIN!F13+[2]TONT20000JUIL!F13+[2]TONT20000AOUT!F13+[2]TONT20000SEPT!F13+[2]TONT20000OCT!F13+[2]TONT20000NOV!G13 -> 271560 | Q13: =[2]TONT20000DEC2015!I13+[2]TONT20000JANV!G13+[2]TONT20000FEV!G13+[2]TONT20000MARS!G13+[2]TONT20000AVRIL!G13+[2]TONT20000MAI!G13+[2]TONT20000JUIN!G13+[2]TONT20000JUIL!G13+[2]TONT20000AOUT!G13+[2]TONT20000SEPT!G13+[2]TONT20000OCT!G13+[2]TONT20000NOV!H13 -> 67560 | R13: =[2]TONT20000DEC2015!J13+[2]TONT20000JANV!H13+[2]TONT20000FEV!H13+[2]TONT20000MARS!H13+[2]TONT20000AVRIL!H13+[2]TONT20000MAI!H13+[2]TONT20000JUIN!H13+[2]TONT20000JUIL!H13+[2]TONT20000AOUT!H13+[2]TONT20000SEPT!H13+[2]TONT20000OCT!H13+[2]TONT20000NOV!I13 -> 6000 | S13: =[2]TONT20000DEC2015!K13+[2]TONT20000JANV!I13+[2]TONT20000FEV!I13+[2]TONT20000MARS!I13+[2]TONT20000AVRIL!I13+[2]TONT20000MAI!I13+[2]TONT20000JUIN!I13+[2]TONT20000JUIL!I13+[2]TONT20000AOUT!I13+[2]TONT20000SEPT!I13+[2]TONT20000OCT!I13+[2]TONT20000NOV!J13 -> 12000 | T13: =[2]TONT20000DEC2015!L13+[2]TONT20000JANV!J13+[2]TONT20000FEV!J13+[2]TONT20000MARS!J13+[2]TONT20000AVRIL!J13+[2]TONT20000MAI!J13+[2]TONT20000JUIN!J13+[2]TONT20000JUIL!J13+[2]TONT20000AOUT!J13+[2]TONT20000SEPT!J13+[2]TONT20000OCT!J13+[2]TONT20000NOV!K13 -> 30000 | U13: =[2]TONT20000DEC2015!M13+[2]TONT20000JANV!K13+[2]TONT20000FEV!K13+[2]TONT20000MARS!K13+[2]TONT20000AVRIL!K13+[2]TONT20000MAI!K13+[2]TONT20000JUIN!K13+[2]TONT20000JUIL!K13+[2]TONT20000AOUT!K13+[2]TONT20000SEPT!K13+[2]TONT20000OCT!K13+[2]TONT20000NOV!L13 -> 0 | V13: =[2]TONT20000DEC2015!N13+[2]TONT20000JANV!L13+[2]TONT20000FEV!L13+[2]TONT20000MARS!L13+[2]TONT20000AVRIL!L13+[2]TONT20000MAI!L13+[2]TONT20000JUIN!L13+[2]TONT20000JUIL!L13+[2]TONT20000AOUT!L13+[2]TONT20000SEPT!L13+[2]TONT20000OCT!L13+[2]TONT20000NOV!M13 -> 156000 | W13: =[2]TONT20000DEC2015!O13+[2]TONT20000JANV!M13+[2]TONT20000FEV!M13+[2]TONT20000MARS!M13+[2]TONT20000AVRIL!M13+[2]TONT20000MAI!M13+[2]TONT20000JUIN!M13+[2]TONT20000JUIL!M13+[2]TONT20000AOUT!M13+[2]TONT20000SEPT!M13+[2]TONT20000OCT!M13+[2]TONT20000NOV!N13 -> 700000 | ... AB13: =[2]TONT20000DEC2015!T13+[2]TONT20000JANV!R13+[2]TONT20000FEV!R13+[2]TONT20000MARS!R13+[2]TONT20000AVRIL!R13+[2]TONT20000MAI!R13+[2]TONT20000JUIN!R13+[2]TONT20000JUIL!R13+[2]TONT20000AOUT!R13+[2]TONT20000SEPT!R13+[2]TONT20000OCT!R13+[2]TONT20000NOV!S13 -> 0
A14: AS201609 | B14: =VLOOKUP(A14,[2]LISTADHERENT!A$5:H$52,2,0) -> DONHOU DAVID | C14: =VLOOKUP(A14,[2]FONDSDECAISSE!A$5:C$52,3,0) -> 390000 | D14: 44734 | E14: =C14+D14+Q14 -> 470734 | F14: =INT([2]TONT20000DEC2015!E14+[2]TONT20000JANV!C14+[2]TONT20000FEV!C14+[2]TONT20000MARS!C14+[2]TONT20000AVRIL!C14+[2]TONT20000MAI!C14+[2]TONT20000JUIN!C14+[2]TONT20000JUIL!C14+[2]TONT20000AOUT!C14+[2]TONT20000SEPT!C14+[2]TONT20000OCT!C14+[2]TONT20000NOV!C14) -> 53014 | G14: =[2]TONT20000NOV!E14 -> 523748.49 | H14: =D14+F14+Q14 -> 133748 | I14: =L14+M14+N14+O14 -> 80000 | J14: =H14-I14 -> 53748 | K14: 0 | L14: 30000 | N14: 50000 | O14: =48000-(R14+S14+T14) -> 0 | P14: =[2]TONT20000DEC2015!H14+[2]TONT20000JANV!F14+[2]TONT20000FEV!F14+[2]TONT20000MARS!F14+[2]TONT20000AVRIL!F14+[2]TONT20000MAI!F14+[2]TONT20000JUIN!F14+[2]TONT20000JUIL!F14+[2]TONT20000AOUT!F14+[2]TONT20000SEPT!F14+[2]TONT20000OCT!F14+[2]TONT20000NOV!G14 -> 240000 | Q14: =[2]TONT20000DEC2015!I14+[2]TONT20000JANV!G14+[2]TONT20000FEV!G14+[2]TONT20000MARS!G14+[2]TONT20000AVRIL!G14+[2]TONT20000MAI!G14+[2]TONT20000JUIN!G14+[2]TONT20000JUIL!G14+[2]TONT20000AOUT!G14+[2]TONT20000SEPT!G14+[2]TONT20000OCT!G14+[2]TONT20000NOV!H14 -> 36000 | R14: =[2]TONT20000DEC2015!J14+[2]TONT20000JANV!H14+[2]TONT20000FEV!H14+[2]TONT20000MARS!H14+[2]TONT20000AVRIL!H14+[2]TONT20000MAI!H14+[2]TONT20000JUIN!H14+[2]TONT20000JUIL!H14+[2]TONT20000AOUT!H14+[2]TONT20000SEPT!H14+[2]TONT20000OCT!H14+[2]TONT20000NOV!I14 -> 6000 | S14: =[2]TONT20000DEC2015!K14+[2]TONT20000JANV!I14+[2]TONT20000FEV!I14+[2]TONT20000MARS!I14+[2]TONT20000AVRIL!I14+[2]TONT20000MAI!I14+[2]TONT20000JUIN!I14+[2]TONT20000JUIL!I14+[2]TONT20000AOUT!I14+[2]TONT20000SEPT!I14+[2]TONT20000OCT!I14+[2]TONT20000NOV!J14 -> 12000 | T14: =[2]TONT20000DEC2015!L14+[2]TONT20000JANV!J14+[2]TONT20000FEV!J14+[2]TONT20000MARS!J14+[2]TONT20000AVRIL!J14+[2]TONT20000MAI!J14+[2]TONT20000JUIN!J14+[2]TONT20000JUIL!J14+[2]TONT20000AOUT!J14+[2]TONT20000SEPT!J14+[2]TONT20000OCT!J14+[2]TONT20000NOV!K14 -> 30000 | U14: =[2]TONT20000DEC2015!M14+[2]TONT20000JANV!K14+[2]TONT20000FEV!K14+[2]TONT20000MARS!K14+[2]TONT20000AVRIL!K14+[2]TONT20000MAI!K14+[2]TONT20000JUIN!K14+[2]TONT20000JUIL!K14+[2]TONT20000AOUT!K14+[2]TONT20000SEPT!K14+[2]TONT20000OCT!K14+[2]TONT20000NOV!L14 -> 0 | V14: =[2]TONT20000DEC2015!N14+[2]TONT20000JANV!L14+[2]TONT20000FEV!L14+[2]TONT20000MARS!L14+[2]TONT20000AVRIL!L14+[2]TONT20000MAI!L14+[2]TONT20000JUIN!L14+[2]TONT20000JUIL!L14+[2]TONT20000AOUT!L14+[2]TONT20000SEPT!L14+[2]TONT20000OCT!L14+[2]TONT20000NOV!M14 -> 156000 | W14: =[2]TONT20000DEC2015!O14+[2]TONT20000JANV!M14+[2]TONT20000FEV!M14+[2]TONT20000MARS!M14+[2]TONT20000AVRIL!M14+[2]TONT20000MAI!M14+[2]TONT20000JUIN!M14+[2]TONT20000JUIL!M14+[2]TONT20000AOUT!M14+[2]TONT20000SEPT!M14+[2]TONT20000OCT!M14+[2]TONT20000NOV!N14 -> 0 | ... AB14: =[2]TONT20000DEC2015!T14+[2]TONT20000JANV!R14+[2]TONT20000FEV!R14+[2]TONT20000MARS!R14+[2]TONT20000AVRIL!R14+[2]TONT20000MAI!R14+[2]TONT20000JUIN!R14+[2]TONT20000JUIL!R14+[2]TONT20000AOUT!R14+[2]TONT20000SEPT!R14+[2]TONT20000OCT!R14+[2]TONT20000NOV!S14 -> 0
A15: AS201610 | B15: =VLOOKUP(A15,[2]LISTADHERENT!A$5:H$52,2,0) -> FOTSO THOMAS | C15: =VLOOKUP(A15,[2]FONDSDECAISSE!A$5:C$52,3,0) -> 390000 | D15: 3318 | E15: =C15+D15+Q15 -> 429318 | F15: =INT([2]TONT20000DEC2015!E15+[2]TONT20000JANV!C15+[2]TONT20000FEV!C15+[2]TONT20000MARS!C15+[2]TONT20000AVRIL!C15+[2]TONT20000MAI!C15+[2]TONT20000JUIN!C15+[2]TONT20000JUIL!C15+[2]TONT20000AOUT!C15+[2]TONT20000SEPT!C15+[2]TONT20000OCT!C15+[2]TONT20000NOV!C15) -> 48204 | G15: =[2]TONT20000NOV!E15 -> 477522.03 | H15: =D15+F15+Q15 -> 87522 | I15: =L15+M15+N15+O15 -> 80000 | J15: =H15-I15 -> 7522 | K15: 5000 | L15: 30000 | N15: 50000 | O15: =48000-(R15+S15+T15) -> 0 | P15: =[2]TONT20000DEC2015!H15+[2]TONT20000JANV!F15+[2]TONT20000FEV!F15+[2]TONT20000MARS!F15+[2]TONT20000AVRIL!F15+[2]TONT20000MAI!F15+[2]TONT20000JUIN!F15+[2]TONT20000JUIL!F15+[2]TONT20000AOUT!F15+[2]TONT20000SEPT!F15+[2]TONT20000OCT!F15+[2]TONT20000NOV!G15 -> 240000 | Q15: =[2]TONT20000DEC2015!I15+[2]TONT20000JANV!G15+[2]TONT20000FEV!G15+[2]TONT20000MARS!G15+[2]TONT20000AVRIL!G15+[2]TONT20000MAI!G15+[2]TONT20000JUIN!G15+[2]TONT20000JUIL!G15+[2]TONT20000AOUT!G15+[2]TONT20000SEPT!G15+[2]TONT20000OCT!G15+[2]TONT20000NOV!H15 -> 36000 | R15: =[2]TONT20000DEC2015!J15+[2]TONT20000JANV!H15+[2]TONT20000FEV!H15+[2]TONT20000MARS!H15+[2]TONT20000AVRIL!H15+[2]TONT20000MAI!H15+[2]TONT20000JUIN!H15+[2]TONT20000JUIL!H15+[2]TONT20000AOUT!H15+[2]TONT20000SEPT!H15+[2]TONT20000OCT!H15+[2]TONT20000NOV!I15 -> 6000 | S15: =[2]TONT20000DEC2015!K15+[2]TONT20000JANV!I15+[2]TONT20000FEV!I15+[2]TONT20000MARS!I15+[2]TONT20000AVRIL!I15+[2]TONT20000MAI!I15+[2]TONT20000JUIN!I15+[2]TONT20000JUIL!I15+[2]TONT20000AOUT!I15+[2]TONT20000SEPT!I15+[2]TONT20000OCT!I15+[2]TONT20000NOV!J15 -> 12000 | T15: =[2]TONT20000DEC2015!L15+[2]TONT20000JANV!J15+[2]TONT20000FEV!J15+[2]TONT20000MARS!J15+[2]TONT20000AVRIL!J15+[2]TONT20000MAI!J15+[2]TONT20000JUIN!J15+[2]TONT20000JUIL!J15+[2]TONT20000AOUT!J15+[2]TONT20000SEPT!J15+[2]TONT20000OCT!J15+[2]TONT20000NOV!K15 -> 30000 | U15: =[2]TONT20000DEC2015!M15+[2]TONT20000JANV!K15+[2]TONT20000FEV!K15+[2]TONT20000MARS!K15+[2]TONT20000AVRIL!K15+[2]TONT20000MAI!K15+[2]TONT20000JUIN!K15+[2]TONT20000JUIL!K15+[2]TONT20000AOUT!K15+[2]TONT20000SEPT!K15+[2]TONT20000OCT!K15+[2]TONT20000NOV!L15 -> 0 | V15: =[2]TONT20000DEC2015!N15+[2]TONT20000JANV!L15+[2]TONT20000FEV!L15+[2]TONT20000MARS!L15+[2]TONT20000AVRIL!L15+[2]TONT20000MAI!L15+[2]TONT20000JUIN!L15+[2]TONT20000JUIL!L15+[2]TONT20000AOUT!L15+[2]TONT20000SEPT!L15+[2]TONT20000OCT!L15+[2]TONT20000NOV!M15 -> 156000 | W15: =[2]TONT20000DEC2015!O15+[2]TONT20000JANV!M15+[2]TONT20000FEV!M15+[2]TONT20000MARS!M15+[2]TONT20000AVRIL!M15+[2]TONT20000MAI!M15+[2]TONT20000JUIN!M15+[2]TONT20000JUIL!M15+[2]TONT20000AOUT!M15+[2]TONT20000SEPT!M15+[2]TONT20000OCT!M15+[2]TONT20000NOV!N15 -> 1000000 | ... AB15: =[2]TONT20000DEC2015!T15+[2]TONT20000JANV!R15+[2]TONT20000FEV!R15+[2]TONT20000MARS!R15+[2]TONT20000AVRIL!R15+[2]TONT20000MAI!R15+[2]TONT20000JUIN!R15+[2]TONT20000JUIL!R15+[2]TONT20000AOUT!R15+[2]TONT20000SEPT!R15+[2]TONT20000OCT!R15+[2]TONT20000NOV!S15 -> 0
A16: AS201611 | B16: =VLOOKUP(A16,[2]LISTADHERENT!A$5:H$52,2,0) -> HENGUE PAUL OMER | C16: =VLOOKUP(A16,[2]FONDSDECAISSE!A$5:C$52,3,0) -> 390000 | E16: =C16+D16+Q16 -> 420000 | F16: =INT([2]TONT20000DEC2015!E16+[2]TONT20000JANV!C16+[2]TONT20000FEV!C16+[2]TONT20000MARS!C16+[2]TONT20000AVRIL!C16+[2]TONT20000MAI!C16+[2]TONT20000JUIN!C16+[2]TONT20000JUIL!C16+[2]TONT20000AOUT!C16+[2]TONT20000SEPT!C16+[2]TONT20000OCT!C16+[2]TONT20000NOV!C16) -> 47702 | G16: =[2]TONT20000NOV!E16 -> 467702.04 | H16: =D16+F16+Q16 -> 77702 | I16: =L16+M16+N16+O16 -> 88000 | J16: =H16-I16 -> -10298 | K16: 0 | L16: 30000 | N16: 50000 | O16: =48000-(R16+S16+T16) -> 8000 | P16: =[2]TONT20000DEC2015!H16+[2]TONT20000JANV!F16+[2]TONT20000FEV!F16+[2]TONT20000MARS!F16+[2]TONT20000AVRIL!F16+[2]TONT20000MAI!F16+[2]TONT20000JUIN!F16+[2]TONT20000JUIL!F16+[2]TONT20000AOUT!F16+[2]TONT20000SEPT!F16+[2]TONT20000OCT!F16+[2]TONT20000NOV!G16 -> 200000 | Q16: =[2]TONT20000DEC2015!I16+[2]TONT20000JANV!G16+[2]TONT20000FEV!G16+[2]TONT20000MARS!G16+[2]TONT20000AVRIL!G16+[2]TONT20000MAI!G16+[2]TONT20000JUIN!G16+[2]TONT20000JUIL!G16+[2]TONT20000AOUT!G16+[2]TONT20000SEPT!G16+[2]TONT20000OCT!G16+[2]TONT20000NOV!H16 -> 30000 | R16: =[2]TONT20000DEC2015!J16+[2]TONT20000JANV!H16+[2]TONT20000FEV!H16+[2]TONT20000MARS!H16+[2]TONT20000AVRIL!H16+[2]TONT20000MAI!H16+[2]TONT20000JUIN!H16+[2]TONT20000JUIL!H16+[2]TONT20000AOUT!H16+[2]TONT20000SEPT!H16+[2]TONT20000OCT!H16+[2]TONT20000NOV!I16 -> 5000 | S16: =[2]TONT20000DEC2015!K16+[2]TONT20000JANV!I16+[2]TONT20000FEV!I16+[2]TONT20000MARS!I16+[2]TONT20000AVRIL!I16+[2]TONT20000MAI!I16+[2]TONT20000JUIN!I16+[2]TONT20000JUIL!I16+[2]TONT20000AOUT!I16+[2]TONT20000SEPT!I16+[2]TONT20000OCT!I16+[2]TONT20000NOV!J16 -> 10000 | T16: =[2]TONT20000DEC2015!L16+[2]TONT20000JANV!J16+[2]TONT20000FEV!J16+[2]TONT20000MARS!J16+[2]TONT20000AVRIL!J16+[2]TONT20000MAI!J16+[2]TONT20000JUIN!J16+[2]TONT20000JUIL!J16+[2]TONT20000AOUT!J16+[2]TONT20000SEPT!J16+[2]TONT20000OCT!J16+[2]TONT20000NOV!K16 -> 25000 | U16: =[2]TONT20000DEC2015!M16+[2]TONT20000JANV!K16+[2]TONT20000FEV!K16+[2]TONT20000MARS!K16+[2]TONT20000AVRIL!K16+[2]TONT20000MAI!K16+[2]TONT20000JUIN!K16+[2]TONT20000JUIL!K16+[2]TONT20000AOUT!K16+[2]TONT20000SEPT!K16+[2]TONT20000OCT!K16+[2]TONT20000NOV!L16 -> 0 | V16: =[2]TONT20000DEC2015!N16+[2]TONT20000JANV!L16+[2]TONT20000FEV!L16+[2]TONT20000MARS!L16+[2]TONT20000AVRIL!L16+[2]TONT20000MAI!L16+[2]TONT20000JUIN!L16+[2]TONT20000JUIL!L16+[2]TONT20000AOUT!L16+[2]TONT20000SEPT!L16+[2]TONT20000OCT!L16+[2]TONT20000NOV!M16 -> 130000 | W16: =[2]TONT20000DEC2015!O16+[2]TONT20000JANV!M16+[2]TONT20000FEV!M16+[2]TONT20000MARS!M16+[2]TONT20000AVRIL!M16+[2]TONT20000MAI!M16+[2]TONT20000JUIN!M16+[2]TONT20000JUIL!M16+[2]TONT20000AOUT!M16+[2]TONT20000SEPT!M16+[2]TONT20000OCT!M16+[2]TONT20000NOV!N16 -> 0 | ... AB16: =[2]TONT20000DEC2015!T16+[2]TONT20000JANV!R16+[2]TONT20000FEV!R16+[2]TONT20000MARS!R16+[2]TONT20000AVRIL!R16+[2]TONT20000MAI!R16+[2]TONT20000JUIN!R16+[2]TONT20000JUIL!R16+[2]TONT20000AOUT!R16+[2]TONT20000SEPT!R16+[2]TONT20000OCT!R16+[2]TONT20000NOV!S16 -> 0
A17: AS201612 | B17: =VLOOKUP(A17,[2]LISTADHERENT!A$5:H$52,2,0) -> HODIEP JULES | C17: 50000 | D17: 0 | E17: =C17+D17+Q17 -> 58100 | F17: =INT([2]TONT20000DEC2015!E17+[2]TONT20000JANV!C17+[2]TONT20000FEV!C17+[2]TONT20000MARS!C17+[2]TONT20000AVRIL!C17+[2]TONT20000MAI!C17+[2]TONT20000JUIN!C17+[2]TONT20000JUIL!C17+[2]TONT20000AOUT!C17+[2]TONT20000SEPT!C17+[2]TONT20000OCT!C17+[2]TONT20000NOV!C17) -> 6252 | G17: =[2]TONT20000NOV!E17 -> 92252.382 | H17: =D17+F17+Q17 -> 14352 | I17: =L17+M17+N17+O17 -> 14092 | J17: =H17-I17 -> 260 | K17: 0 | N17: =50000-35908 -> 14092 | O17: =48000-(R17+S17+T17) -> 0 | P17: =[2]TONT20000DEC2015!H17+[2]TONT20000JANV!F17+[2]TONT20000FEV!F17+[2]TONT20000MARS!F17+[2]TONT20000AVRIL!F17+[2]TONT20000MAI!F17+[2]TONT20000JUIN!F17+[2]TONT20000JUIL!F17+[2]TONT20000AOUT!F17+[2]TONT20000SEPT!F17+[2]TONT20000OCT!F17+[2]TONT20000NOV!G17 -> 240000 | Q17: =[2]TONT20000DEC2015!I17+[2]TONT20000JANV!G17+[2]TONT20000FEV!G17+[2]TONT20000MARS!G17+[2]TONT20000AVRIL!G17+[2]TONT20000MAI!G17+[2]TONT20000JUIN!G17+[2]TONT20000JUIL!G17+[2]TONT20000AOUT!G17+[2]TONT20000SEPT!G17+[2]TONT20000OCT!G17+[2]TONT20000NOV!H17-18000-9900 -> 8100 | R17: =[2]TONT20000DEC2015!J17+[2]TONT20000JANV!H17+[2]TONT20000FEV!H17+[2]TONT20000MARS!H17+[2]TONT20000AVRIL!H17+[2]TONT20000MAI!H17+[2]TONT20000JUIN!H17+[2]TONT20000JUIL!H17+[2]TONT20000AOUT!H17+[2]TONT20000SEPT!H17+[2]TONT20000OCT!H17+[2]TONT20000NOV!I17 -> 6000 | S17: =[2]TONT20000DEC2015!K17+[2]TONT20000JANV!I17+[2]TONT20000FEV!I17+[2]TONT20000MARS!I17+[2]TONT20000AVRIL!I17+[2]TONT20000MAI!I17+[2]TONT20000JUIN!I17+[2]TONT20000JUIL!I17+[2]TONT20000AOUT!I17+[2]TONT20000SEPT!I17+[2]TONT20000OCT!I17+[2]TONT20000NOV!J17 -> 12000 | T17: =[2]TONT20000DEC2015!L17+[2]TONT20000JANV!J17+[2]TONT20000FEV!J17+[2]TONT20000MARS!J17+[2]TONT20000AVRIL!J17+[2]TONT20000MAI!J17+[2]TONT20000JUIN!J17+[2]TONT20000JUIL!J17+[2]TONT20000AOUT!J17+[2]TONT20000SEPT!J17+[2]TONT20000OCT!J17+[2]TONT20000NOV!K17 -> 30000 | U17: =[2]TONT20000DEC2015!M17+[2]TONT20000JANV!K17+[2]TONT20000FEV!K17+[2]TONT20000MARS!K17+[2]TONT20000AVRIL!K17+[2]TONT20000MAI!K17+[2]TONT20000JUIN!K17+[2]TONT20000JUIL!K17+[2]TONT20000AOUT!K17+[2]TONT20000SEPT!K17+[2]TONT20000OCT!K17+[2]TONT20000NOV!L17 -> 0 | V17: =[2]TONT20000DEC2015!N17+[2]TONT20000JANV!L17+[2]TONT20000FEV!L17+[2]TONT20000MARS!L17+[2]TONT20000AVRIL!L17+[2]TONT20000MAI!L17+[2]TONT20000JUIN!L17+[2]TONT20000JUIL!L17+[2]TONT20000AOUT!L17+[2]TONT20000SEPT!L17+[2]TONT20000OCT!L17+[2]TONT20000NOV!M17 -> 156000 | W17: =[2]TONT20000DEC2015!O17+[2]TONT20000JANV!M17+[2]TONT20000FEV!M17+[2]TONT20000MARS!M17+[2]TONT20000AVRIL!M17+[2]TONT20000MAI!M17+[2]TONT20000JUIN!M17+[2]TONT20000JUIL!M17+[2]TONT20000AOUT!M17+[2]TONT20000SEPT!M17+[2]TONT20000OCT!M17+[2]TONT20000NOV!N17 -> 0 | X17: =[2]TONT20000DEC2015!P17+[2]TONT20000JANV!N17+[2]TONT20000FEV!N17+[2]TONT20000MARS!N17+[2]TONT20000AVRIL!N17+[2]TONT20000MAI!N17+[2]TONT20000JUIN!N17+[2]TONT20000JUIL!N17+[2]TONT20000AOUT!N17+[2]TONT20000SEPT!N17+[2]TONT20000OCT!N17+[2]TONT20000NOV!O17 -> 0 | Y17: =[2]TONT20000DEC2015!Q17+[2]TONT20000JANV!O17+[2]TONT20000FEV!O17+[2]TONT20000MARS!O17+[2]TONT20000AVRIL!O17+[2]TONT20000MAI!O17+[2]TONT20000JUIN!O17+[2]TONT20000JUIL!O17+[2]TONT20000AOUT!O17+[2]TONT20000SEPT!O17+[2]TONT20000OCT!O17+[2]TONT20000NOV!P17 -> 0 | ... AB17: =[2]TONT20000DEC2015!T17+[2]TONT20000JANV!R17+[2]TONT20000FEV!R17+[2]TONT20000MARS!R17+[2]TONT20000AVRIL!R17+[2]TONT20000MAI!R17+[2]TONT20000JUIN!R17+[2]TONT20000JUIL!R17+[2]TONT20000AOUT!R17+[2]TONT20000SEPT!R17+[2]TONT20000OCT!R17+[2]TONT20000NOV!S17 -> 0
A18: AS201613 | B18: =VLOOKUP(A18,[2]LISTADHERENT!A$5:H$52,2,0) -> HOTCHO BENJAMIN | C18: =VLOOKUP(A18,[2]FONDSDECAISSE!A$5:C$52,3,0) -> 390000 | D18: 8723 | E18: =C18+D18+Q18 -> 482723 | F18: =INT([2]TONT20000DEC2015!E18+[2]TONT20000JANV!C18+[2]TONT20000FEV!C18+[2]TONT20000MARS!C18+[2]TONT20000AVRIL!C18+[2]TONT20000MAI!C18+[2]TONT20000JUIN!C18+[2]TONT20000JUIL!C18+[2]TONT20000AOUT!C18+[2]TONT20000SEPT!C18+[2]TONT20000OCT!C18+[2]TONT20000NOV!C18) -> 49962 | G18: =[2]TONT20000NOV!E18 -> 532685.38 | H18: =D18+F18+Q18 -> 142685 | I18: =L18+M18+N18+O18 -> 30000 | J18: =H18-I18 -> 112685 | K18: 0 | L18: 30000 | N18: 0 | O18: =48000-(R18+S18+T18) -> 0 | P18: =[2]TONT20000DEC2015!H18+[2]TONT20000JANV!F18+[2]TONT20000FEV!F18+[2]TONT20000MARS!F18+[2]TONT20000AVRIL!F18+[2]TONT20000MAI!F18+[2]TONT20000JUIN!F18+[2]TONT20000JUIL!F18+[2]TONT20000AOUT!F18+[2]TONT20000SEPT!F18+[2]TONT20000OCT!F18+[2]TONT20000NOV!G18 -> 338000 | Q18: =[2]TONT20000DEC2015!I18+[2]TONT20000JANV!G18+[2]TONT20000FEV!G18+[2]TONT20000MARS!G18+[2]TONT20000AVRIL!G18+[2]TONT20000MAI!G18+[2]TONT20000JUIN!G18+[2]TONT20000JUIL!G18+[2]TONT20000AOUT!G18+[2]TONT20000SEPT!G18+[2]TONT20000OCT!G18+[2]TONT20000NOV!H18 -> 84000 | R18: =[2]TONT20000DEC2015!J18+[2]TONT20000JANV!H18+[2]TONT20000FEV!H18+[2]TONT20000MARS!H18+[2]TONT20000AVRIL!H18+[2]TONT20000MAI!H18+[2]TONT20000JUIN!H18+[2]TONT20000JUIL!H18+[2]TONT20000AOUT!H18+[2]TONT20000SEPT!H18+[2]TONT20000OCT!H18+[2]TONT20000NOV!I18 -> 6000 | S18: =[2]TONT20000DEC2015!K18+[2]TONT20000JANV!I18+[2]TONT20000FEV!I18+[2]TONT20000MARS!I18+[2]TONT20000AVRIL!I18+[2]TONT20000MAI!I18+[2]TONT20000JUIN!I18+[2]TONT20000JUIL!I18+[2]TONT20000AOUT!I18+[2]TONT20000SEPT!I18+[2]TONT20000OCT!I18+[2]TONT20000NOV!J18 -> 12000 | T18: =[2]TONT20000DEC2015!L18+[2]TONT20000JANV!J18+[2]TONT20000FEV!J18+[2]TONT20000MARS!J18+[2]TONT20000AVRIL!J18+[2]TONT20000MAI!J18+[2]TONT20000JUIN!J18+[2]TONT20000JUIL!J18+[2]TONT20000AOUT!J18+[2]TONT20000SEPT!J18+[2]TONT20000OCT!J18+[2]TONT20000NOV!K18 -> 30000 | U18: =[2]TONT20000DEC2015!M18+[2]TONT20000JANV!K18+[2]TONT20000FEV!K18+[2]TONT20000MARS!K18+[2]TONT20000AVRIL!K18+[2]TONT20000MAI!K18+[2]TONT20000JUIN!K18+[2]TONT20000JUIL!K18+[2]TONT20000AOUT!K18+[2]TONT20000SEPT!K18+[2]TONT20000OCT!K18+[2]TONT20000NOV!L18 -> 50000 | V18: =[2]TONT20000DEC2015!N18+[2]TONT20000JANV!L18+[2]TONT20000FEV!L18+[2]TONT20000MARS!L18+[2]TONT20000AVRIL!L18+[2]TONT20000MAI!L18+[2]TONT20000JUIN!L18+[2]TONT20000JUIL!L18+[2]TONT20000AOUT!L18+[2]TONT20000SEPT!L18+[2]TONT20000OCT!L18+[2]TONT20000NOV!M18 -> 156000 | W18: =[2]TONT20000DEC2015!O18+[2]TONT20000JANV!M18+[2]TONT20000FEV!M18+[2]TONT20000MARS!M18+[2]TONT20000AVRIL!M18+[2]TONT20000MAI!M18+[2]TONT20000JUIN!M18+[2]TONT20000JUIL!M18+[2]TONT20000AOUT!M18+[2]TONT20000SEPT!M18+[2]TONT20000OCT!M18+[2]TONT20000NOV!N18 -> 0 | ... AB18: =[2]TONT20000DEC2015!T18+[2]TONT20000JANV!R18+[2]TONT20000FEV!R18+[2]TONT20000MARS!R18+[2]TONT20000AVRIL!R18+[2]TONT20000MAI!R18+[2]TONT20000JUIN!R18+[2]TONT20000JUIL!R18+[2]TONT20000AOUT!R18+[2]TONT20000SEPT!R18+[2]TONT20000OCT!R18+[2]TONT20000NOV!S18 -> 0
A19: AS201614 | B19: =VLOOKUP(A19,[2]LISTADHERENT!A$5:H$52,2,0) -> KEPHE DAVID | C19: =VLOOKUP(A19,[2]FONDSDECAISSE!A$5:C$52,3,0) -> 0 | D19: 12795 | E19: =C19+D19+Q19 -> 18000 | F19: =INT([2]TONT20000DEC2015!E19+[2]TONT20000JANV!C19+[2]TONT20000FEV!C19+[2]TONT20000MARS!C19+[2]TONT20000AVRIL!C19+[2]TONT20000MAI!C19+[2]TONT20000JUIN!C19+[2]TONT20000JUIL!C19+[2]TONT20000AOUT!C19+[2]TONT20000SEPT!C19+[2]TONT20000OCT!C19+[2]TONT20000NOV!C19) -> 4006 | G19: =[2]TONT20000NOV!E19 -> 52801.313 | H19: =D19+F19+Q19 -> 22006 | I19: =L19+M19+N19+O19 -> 21829 | J19: =H19-I19 -> 177 | K19: 0 | N19: =50000-24839-3332 -> 21829 | O19: =48000-(R19+S19+T19) -> 0 | P19: =[2]TONT20000DEC2015!H19+[2]TONT20000JANV!F19+[2]TONT20000FEV!F19+[2]TONT20000MARS!F19+[2]TONT20000AVRIL!F19+[2]TONT20000MAI!F19+[2]TONT20000JUIN!F19+[2]TONT20000JUIL!F19+[2]TONT20000AOUT!F19+[2]TONT20000SEPT!F19+[2]TONT20000OCT!F19+[2]TONT20000NOV!G19 -> 240000 | Q19: =[2]TONT20000DEC2015!I19+[2]TONT20000JANV!G19+[2]TONT20000FEV!G19+[2]TONT20000MARS!G19+[2]TONT20000AVRIL!G19+[2]TONT20000MAI!G19+[2]TONT20000JUIN!G19+[2]TONT20000JUIL!G19+[2]TONT20000AOUT!G19+[2]TONT20000SEPT!G19+[2]TONT20000OCT!G19+[2]TONT20000NOV!H19-30795 -> 5205 | R19: =[2]TONT20000DEC2015!J19+[2]TONT20000JANV!H19+[2]TONT20000FEV!H19+[2]TONT20000MARS!H19+[2]TONT20000AVRIL!H19+[2]TONT20000MAI!H19+[2]TONT20000JUIN!H19+[2]TONT20000JUIL!H19+[2]TONT20000AOUT!H19+[2]TONT20000SEPT!H19+[2]TONT20000OCT!H19+[2]TONT20000NOV!I19 -> 6000 | S19: =[2]TONT20000DEC2015!K19+[2]TONT20000JANV!I19+[2]TONT20000FEV!I19+[2]TONT20000MARS!I19+[2]TONT20000AVRIL!I19+[2]TONT20000MAI!I19+[2]TONT20000JUIN!I19+[2]TONT20000JUIL!I19+[2]TONT20000AOUT!I19+[2]TONT20000SEPT!I19+[2]TONT20000OCT!I19+[2]TONT20000NOV!J19 -> 12000 | T19: =[2]TONT20000DEC2015!L19+[2]TONT20000JANV!J19+[2]TONT20000FEV!J19+[2]TONT20000MARS!J19+[2]TONT20000AVRIL!J19+[2]TONT20000MAI!J19+[2]TONT20000JUIN!J19+[2]TONT20000JUIL!J19+[2]TONT20000AOUT!J19+[2]TONT20000SEPT!J19+[2]TONT20000OCT!J19+[2]TONT20000NOV!K19 -> 30000 | U19: =[2]TONT20000DEC2015!M19+[2]TONT20000JANV!K19+[2]TONT20000FEV!K19+[2]TONT20000MARS!K19+[2]TONT20000AVRIL!K19+[2]TONT20000MAI!K19+[2]TONT20000JUIN!K19+[2]TONT20000JUIL!K19+[2]TONT20000AOUT!K19+[2]TONT20000SEPT!K19+[2]TONT20000OCT!K19+[2]TONT20000NOV!L19 -> 0 | V19: =[2]TONT20000DEC2015!N19+[2]TONT20000JANV!L19+[2]TONT20000FEV!L19+[2]TONT20000MARS!L19+[2]TONT20000AVRIL!L19+[2]TONT20000MAI!L19+[2]TONT20000JUIN!L19+[2]TONT20000JUIL!L19+[2]TONT20000AOUT!L19+[2]TONT20000SEPT!L19+[2]TONT20000OCT!L19+[2]TONT20000NOV!M19 -> 156000 | W19: =[2]TONT20000DEC2015!O19+[2]TONT20000JANV!M19+[2]TONT20000FEV!M19+[2]TONT20000MARS!M19+[2]TONT20000AVRIL!M19+[2]TONT20000MAI!M19+[2]TONT20000JUIN!M19+[2]TONT20000JUIL!M19+[2]TONT20000AOUT!M19+[2]TONT20000SEPT!M19+[2]TONT20000OCT!M19+[2]TONT20000NOV!N19 -> 0 | X19: =[2]TONT20000DEC2015!P19+[2]TONT20000JANV!N19+[2]TONT20000FEV!N19+[2]TONT20000MARS!N19+[2]TONT20000AVRIL!N19+[2]TONT20000MAI!N19+[2]TONT20000JUIN!N19+[2]TONT20000JUIL!N19+[2]TONT20000AOUT!N19+[2]TONT20000SEPT!N19+[2]TONT20000OCT!N19+[2]TONT20000NOV!O19 -> 0 | Y19: =[2]TONT20000DEC2015!Q19+[2]TONT20000JANV!O19+[2]TONT20000FEV!O19+[2]TONT20000MARS!O19+[2]TONT20000AVRIL!O19+[2]TONT20000MAI!O19+[2]TONT20000JUIN!O19+[2]TONT20000JUIL!O19+[2]TONT20000AOUT!O19+[2]TONT20000SEPT!O19+[2]TONT20000OCT!O19+[2]TONT20000NOV!P19 -> 0 | ... AB19: =[2]TONT20000DEC2015!T19+[2]TONT20000JANV!R19+[2]TONT20000FEV!R19+[2]TONT20000MARS!R19+[2]TONT20000AVRIL!R19+[2]TONT20000MAI!R19+[2]TONT20000JUIN!R19+[2]TONT20000JUIL!R19+[2]TONT20000AOUT!R19+[2]TONT20000SEPT!R19+[2]TONT20000OCT!R19+[2]TONT20000NOV!S19 -> 0
A20: AS201615 | B20: =VLOOKUP(A20,[2]LISTADHERENT!A$5:H$52,2,0) -> KEPSEU FRANCIS | C20: =VLOOKUP(A20,[2]FONDSDECAISSE!A$5:C$52,3,0) -> 390000 | D20: 186997 | E20: =C20+D20+Q20 -> 1128997 | F20: =INT([2]TONT20000DEC2015!E20+[2]TONT20000JANV!C20+[2]TONT20000FEV!C20+[2]TONT20000MARS!C20+[2]TONT20000AVRIL!C20+[2]TONT20000MAI!C20+[2]TONT20000JUIN!C20+[2]TONT20000JUIL!C20+[2]TONT20000AOUT!C20+[2]TONT20000SEPT!C20+[2]TONT20000OCT!C20+[2]TONT20000NOV!C20) -> 117428 | G20: =[2]TONT20000NOV!E20 -> 1246425.8 | H20: =D20+F20+Q20 -> 856425 | I20: =L20+M20+N20+O20 -> 80000 | J20: =H20-I20 -> 776425 | K20: 71000 | L20: 30000 | N20: 50000 | O20: =48000-(R20+S20+T20) -> 0 | P20: =[2]TONT20000DEC2015!H20+[2]TONT20000JANV!F20+[2]TONT20000FEV!F20+[2]TONT20000MARS!F20+[2]TONT20000AVRIL!F20+[2]TONT20000MAI!F20+[2]TONT20000JUIN!F20+[2]TONT20000JUIL!F20+[2]TONT20000AOUT!F20+[2]TONT20000SEPT!F20+[2]TONT20000OCT!F20+[2]TONT20000NOV!G20 -> 756000 | Q20: =[2]TONT20000DEC2015!I20+[2]TONT20000JANV!G20+[2]TONT20000FEV!G20+[2]TONT20000MARS!G20+[2]TONT20000AVRIL!G20+[2]TONT20000MAI!G20+[2]TONT20000JUIN!G20+[2]TONT20000JUIL!G20+[2]TONT20000AOUT!G20+[2]TONT20000SEPT!G20+[2]TONT20000OCT!G20+[2]TONT20000NOV!H20 -> 552000 | R20: =[2]TONT20000DEC2015!J20+[2]TONT20000JANV!H20+[2]TONT20000FEV!H20+[2]TONT20000MARS!H20+[2]TONT20000AVRIL!H20+[2]TONT20000MAI!H20+[2]TONT20000JUIN!H20+[2]TONT20000JUIL!H20+[2]TONT20000AOUT!H20+[2]TONT20000SEPT!H20+[2]TONT20000OCT!H20+[2]TONT20000NOV!I20 -> 6000 | S20: =[2]TONT20000DEC2015!K20+[2]TONT20000JANV!I20+[2]TONT20000FEV!I20+[2]TONT20000MARS!I20+[2]TONT20000AVRIL!I20+[2]TONT20000MAI!I20+[2]TONT20000JUIN!I20+[2]TONT20000JUIL!I20+[2]TONT20000AOUT!I20+[2]TONT20000SEPT!I20+[2]TONT20000OCT!I20+[2]TONT20000NOV!J20 -> 12000 | T20: =[2]TONT20000DEC2015!L20+[2]TONT20000JANV!J20+[2]TONT20000FEV!J20+[2]TONT20000MARS!J20+[2]TONT20000AVRIL!J20+[2]TONT20000MAI!J20+[2]TONT20000JUIN!J20+[2]TONT20000JUIL!J20+[2]TONT20000AOUT!J20+[2]TONT20000SEPT!J20+[2]TONT20000OCT!J20+[2]TONT20000NOV!K20 -> 30000 | U20: =[2]TONT20000DEC2015!M20+[2]TONT20000JANV!K20+[2]TONT20000FEV!K20+[2]TONT20000MARS!K20+[2]TONT20000AVRIL!K20+[2]TONT20000MAI!K20+[2]TONT20000JUIN!K20+[2]TONT20000JUIL!K20+[2]TONT20000AOUT!K20+[2]TONT20000SEPT!K20+[2]TONT20000OCT!K20+[2]TONT20000NOV!L20 -> 0 | V20: =[2]TONT20000DEC2015!N20+[2]TONT20000JANV!L20+[2]TONT20000FEV!L20+[2]TONT20000MARS!L20+[2]TONT20000AVRIL!L20+[2]TONT20000MAI!L20+[2]TONT20000JUIN!L20+[2]TONT20000JUIL!L20+[2]TONT20000AOUT!L20+[2]TONT20000SEPT!L20+[2]TONT20000OCT!L20+[2]TONT20000NOV!M20 -> 156000 | W20: =[2]TONT20000DEC2015!O20+[2]TONT20000JANV!M20+[2]TONT20000FEV!M20+[2]TONT20000MARS!M20+[2]TONT20000AVRIL!M20+[2]TONT20000MAI!M20+[2]TONT20000JUIN!M20+[2]TONT20000JUIL!M20+[2]TONT20000AOUT!M20+[2]TONT20000SEPT!M20+[2]TONT20000OCT!M20+[2]TONT20000NOV!N20 -> 0 | ... AB20: =[2]TONT20000DEC2015!T20+[2]TONT20000JANV!R20+[2]TONT20000FEV!R20+[2]TONT20000MARS!R20+[2]TONT20000AVRIL!R20+[2]TONT20000MAI!R20+[2]TONT20000JUIN!R20+[2]TONT20000JUIL!R20+[2]TONT20000AOUT!R20+[2]TONT20000SEPT!R20+[2]TONT20000OCT!R20+[2]TONT20000NOV!S20 -> 0
A21: AS201616 | B21: =VLOOKUP(A21,[2]LISTADHERENT!A$5:H$52,2,0) -> KOUAMOU EMMANUEL | C21: =VLOOKUP(A21,[2]FONDSDECAISSE!A$5:C$52,3,0) -> 390000 | D21: 2723 | E21: =C21+D21+Q21 -> 428723 | F21: =INT([2]TONT20000DEC2015!E21+[2]TONT20000JANV!C21+[2]TONT20000FEV!C21+[2]TONT20000MARS!C21+[2]TONT20000AVRIL!C21+[2]TONT20000MAI!C21+[2]TONT20000JUIN!C21+[2]TONT20000JUIL!C21+[2]TONT20000AOUT!C21+[2]TONT20000SEPT!C21+[2]TONT20000OCT!C21+[2]TONT20000NOV!C21) -> 48134 | G21: =[2]TONT20000NOV!E21 -> 476857.92 | H21: =D21+F21+Q21 -> 86857 | I21: =L21+M21+N21+O21 -> 80000 | J21: =H21-I21 -> 6857 | K21: 4500 | L21: 30000 | N21: 50000 | O21: =48000-(R21+S21+T21) -> 0 | P21: =[2]TONT20000DEC2015!H21+[2]TONT20000JANV!F21+[2]TONT20000FEV!F21+[2]TONT20000MARS!F21+[2]TONT20000AVRIL!F21+[2]TONT20000MAI!F21+[2]TONT20000JUIN!F21+[2]TONT20000JUIL!F21+[2]TONT20000AOUT!F21+[2]TONT20000SEPT!F21+[2]TONT20000OCT!F21+[2]TONT20000NOV!G21 -> 240000 | Q21: =[2]TONT20000DEC2015!I21+[2]TONT20000JANV!G21+[2]TONT20000FEV!G21+[2]TONT20000MARS!G21+[2]TONT20000AVRIL!G21+[2]TONT20000MAI!G21+[2]TONT20000JUIN!G21+[2]TONT20000JUIL!G21+[2]TONT20000AOUT!G21+[2]TONT20000SEPT!G21+[2]TONT20000OCT!G21+[2]TONT20000NOV!H21 -> 36000 | R21: =[2]TONT20000DEC2015!J21+[2]TONT20000JANV!H21+[2]TONT20000FEV!H21+[2]TONT20000MARS!H21+[2]TONT20000AVRIL!H21+[2]TONT20000MAI!H21+[2]TONT20000JUIN!H21+[2]TONT20000JUIL!H21+[2]TONT20000AOUT!H21+[2]TONT20000SEPT!H21+[2]TONT20000OCT!H21+[2]TONT20000NOV!I21 -> 6000 | S21: =[2]TONT20000DEC2015!K21+[2]TONT20000JANV!I21+[2]TONT20000FEV!I21+[2]TONT20000MARS!I21+[2]TONT20000AVRIL!I21+[2]TONT20000MAI!I21+[2]TONT20000JUIN!I21+[2]TONT20000JUIL!I21+[2]TONT20000AOUT!I21+[2]TONT20000SEPT!I21+[2]TONT20000OCT!I21+[2]TONT20000NOV!J21 -> 12000 | T21: =[2]TONT20000DEC2015!L21+[2]TONT20000JANV!J21+[2]TONT20000FEV!J21+[2]TONT20000MARS!J21+[2]TONT20000AVRIL!J21+[2]TONT20000MAI!J21+[2]TONT20000JUIN!J21+[2]TONT20000JUIL!J21+[2]TONT20000AOUT!J21+[2]TONT20000SEPT!J21+[2]TONT20000OCT!J21+[2]TONT20000NOV!K21 -> 30000 | U21: =[2]TONT20000DEC2015!M21+[2]TONT20000JANV!K21+[2]TONT20000FEV!K21+[2]TONT20000MARS!K21+[2]TONT20000AVRIL!K21+[2]TONT20000MAI!K21+[2]TONT20000JUIN!K21+[2]TONT20000JUIL!K21+[2]TONT20000AOUT!K21+[2]TONT20000SEPT!K21+[2]TONT20000OCT!K21+[2]TONT20000NOV!L21 -> 0 | V21: =[2]TONT20000DEC2015!N21+[2]TONT20000JANV!L21+[2]TONT20000FEV!L21+[2]TONT20000MARS!L21+[2]TONT20000AVRIL!L21+[2]TONT20000MAI!L21+[2]TONT20000JUIN!L21+[2]TONT20000JUIL!L21+[2]TONT20000AOUT!L21+[2]TONT20000SEPT!L21+[2]TONT20000OCT!L21+[2]TONT20000NOV!M21 -> 156000 | W21: =[2]TONT20000DEC2015!O21+[2]TONT20000JANV!M21+[2]TONT20000FEV!M21+[2]TONT20000MARS!M21+[2]TONT20000AVRIL!M21+[2]TONT20000MAI!M21+[2]TONT20000JUIN!M21+[2]TONT20000JUIL!M21+[2]TONT20000AOUT!M21+[2]TONT20000SEPT!M21+[2]TONT20000OCT!M21+[2]TONT20000NOV!N21 -> 1000000 | ... AB21: =[2]TONT20000DEC2015!T21+[2]TONT20000JANV!R21+[2]TONT20000FEV!R21+[2]TONT20000MARS!R21+[2]TONT20000AVRIL!R21+[2]TONT20000MAI!R21+[2]TONT20000JUIN!R21+[2]TONT20000JUIL!R21+[2]TONT20000AOUT!R21+[2]TONT20000SEPT!R21+[2]TONT20000OCT!R21+[2]TONT20000NOV!S21 -> 0
A22: AS201617 | B22: =VLOOKUP(A22,[2]LISTADHERENT!A$5:H$52,2,0) -> KOUAMOU MOISE | C22: 390000 | D22: 2099 | E22: =C22+D22+Q22 -> 428099 | F22: =INT([2]TONT20000DEC2015!E22+[2]TONT20000JANV!C22+[2]TONT20000FEV!C22+[2]TONT20000MARS!C22+[2]TONT20000AVRIL!C22+[2]TONT20000MAI!C22+[2]TONT20000JUIN!C22+[2]TONT20000JUIL!C22+[2]TONT20000AOUT!C22+[2]TONT20000SEPT!C22+[2]TONT20000OCT!C22+[2]TONT20000NOV!C22) -> 44949 | G22: =[2]TONT20000NOV!E22 -> 473048.51 | H22: =D22+F22+Q22 -> 83048 | I22: =L22+M22+N22+O22 -> 80000 | J22: =H22-I22 -> 3048 | K22: 0 | L22: 30000 | N22: 50000 | O22: =48000-(R22+S22+T22) -> 0 | P22: =[2]TONT20000DEC2015!H22+[2]TONT20000JANV!F22+[2]TONT20000FEV!F22+[2]TONT20000MARS!F22+[2]TONT20000AVRIL!F22+[2]TONT20000MAI!F22+[2]TONT20000JUIN!F22+[2]TONT20000JUIL!F22+[2]TONT20000AOUT!F22+[2]TONT20000SEPT!F22+[2]TONT20000OCT!F22+[2]TONT20000NOV!G22 -> 240000 | Q22: =[2]TONT20000DEC2015!I22+[2]TONT20000JANV!G22+[2]TONT20000FEV!G22+[2]TONT20000MARS!G22+[2]TONT20000AVRIL!G22+[2]TONT20000MAI!G22+[2]TONT20000JUIN!G22+[2]TONT20000JUIL!G22+[2]TONT20000AOUT!G22+[2]TONT20000SEPT!G22+[2]TONT20000OCT!G22+[2]TONT20000NOV!H22 -> 36000 | R22: =[2]TONT20000DEC2015!J22+[2]TONT20000JANV!H22+[2]TONT20000FEV!H22+[2]TONT20000MARS!H22+[2]TONT20000AVRIL!H22+[2]TONT20000MAI!H22+[2]TONT20000JUIN!H22+[2]TONT20000JUIL!H22+[2]TONT20000AOUT!H22+[2]TONT20000SEPT!H22+[2]TONT20000OCT!H22+[2]TONT20000NOV!I22 -> 6000 | S22: =[2]TONT20000DEC2015!K22+[2]TONT20000JANV!I22+[2]TONT20000FEV!I22+[2]TONT20000MARS!I22+[2]TONT20000AVRIL!I22+[2]TONT20000MAI!I22+[2]TONT20000JUIN!I22+[2]TONT20000JUIL!I22+[2]TONT20000AOUT!I22+[2]TONT20000SEPT!I22+[2]TONT20000OCT!I22+[2]TONT20000NOV!J22 -> 12000 | T22: =[2]TONT20000DEC2015!L22+[2]TONT20000JANV!J22+[2]TONT20000FEV!J22+[2]TONT20000MARS!J22+[2]TONT20000AVRIL!J22+[2]TONT20000MAI!J22+[2]TONT20000JUIN!J22+[2]TONT20000JUIL!J22+[2]TONT20000AOUT!J22+[2]TONT20000SEPT!J22+[2]TONT20000OCT!J22+[2]TONT20000NOV!K22 -> 30000 | U22: =[2]TONT20000DEC2015!M22+[2]TONT20000JANV!K22+[2]TONT20000FEV!K22+[2]TONT20000MARS!K22+[2]TONT20000AVRIL!K22+[2]TONT20000MAI!K22+[2]TONT20000JUIN!K22+[2]TONT20000JUIL!K22+[2]TONT20000AOUT!K22+[2]TONT20000SEPT!K22+[2]TONT20000OCT!K22+[2]TONT20000NOV!L22 -> 0 | V22: =[2]TONT20000DEC2015!N22+[2]TONT20000JANV!L22+[2]TONT20000FEV!L22+[2]TONT20000MARS!L22+[2]TONT20000AVRIL!L22+[2]TONT20000MAI!L22+[2]TONT20000JUIN!L22+[2]TONT20000JUIL!L22+[2]TONT20000AOUT!L22+[2]TONT20000SEPT!L22+[2]TONT20000OCT!L22+[2]TONT20000NOV!M22 -> 156000 | W22: =[2]TONT20000DEC2015!O22+[2]TONT20000JANV!M22+[2]TONT20000FEV!M22+[2]TONT20000MARS!M22+[2]TONT20000AVRIL!M22+[2]TONT20000MAI!M22+[2]TONT20000JUIN!M22+[2]TONT20000JUIL!M22+[2]TONT20000AOUT!M22+[2]TONT20000SEPT!M22+[2]TONT20000OCT!M22+[2]TONT20000NOV!N22 -> 860000 | ... AB22: =[2]TONT20000DEC2015!T22+[2]TONT20000JANV!R22+[2]TONT20000FEV!R22+[2]TONT20000MARS!R22+[2]TONT20000AVRIL!R22+[2]TONT20000MAI!R22+[2]TONT20000JUIN!R22+[2]TONT20000JUIL!R22+[2]TONT20000AOUT!R22+[2]TONT20000SEPT!R22+[2]TONT20000OCT!R22+[2]TONT20000NOV!S22 -> 0
A23: AS201618 | B23: =VLOOKUP(A23,[2]LISTADHERENT!A$5:H$52,2,0) -> KOUAMOU VICTOR PEGUY | C23: =VLOOKUP(A23,[2]FONDSDECAISSE!A$5:C$52,3,0) -> 390000 | D23: 36629 | E23: =C23+D23+Q23 -> 461629 | F23: =INT([2]TONT20000DEC2015!E23+[2]TONT20000JANV!C23+[2]TONT20000FEV!C23+[2]TONT20000MARS!C23+[2]TONT20000AVRIL!C23+[2]TONT20000MAI!C23+[2]TONT20000JUIN!C23+[2]TONT20000JUIL!C23+[2]TONT20000AOUT!C23+[2]TONT20000SEPT!C23+[2]TONT20000OCT!C23+[2]TONT20000NOV!C23) -> 52057 | G23: =[2]TONT20000NOV!E23 -> 513686.78 | H23: =D23+F23+Q23 -> 123686 | I23: =L23+M23+N23+O23 -> 80000 | J23: =H23-I23 -> 43686 | K23: 41000 | L23: 30000 | N23: 50000 | O23: =48000-(R23+S23+T23) -> 0 | P23: =[2]TONT20000DEC2015!H23+[2]TONT20000JANV!F23+[2]TONT20000FEV!F23+[2]TONT20000MARS!F23+[2]TONT20000AVRIL!F23+[2]TONT20000MAI!F23+[2]TONT20000JUIN!F23+[2]TONT20000JUIL!F23+[2]TONT20000AOUT!F23+[2]TONT20000SEPT!F23+[2]TONT20000OCT!F23+[2]TONT20000NOV!G23 -> 239000 | Q23: =[2]TONT20000DEC2015!I23+[2]TONT20000JANV!G23+[2]TONT20000FEV!G23+[2]TONT20000MARS!G23+[2]TONT20000AVRIL!G23+[2]TONT20000MAI!G23+[2]TONT20000JUIN!G23+[2]TONT20000JUIL!G23+[2]TONT20000AOUT!G23+[2]TONT20000SEPT!G23+[2]TONT20000OCT!G23+[2]TONT20000NOV!H23 -> 35000 | R23: =[2]TONT20000DEC2015!J23+[2]TONT20000JANV!H23+[2]TONT20000FEV!H23+[2]TONT20000MARS!H23+[2]TONT20000AVRIL!H23+[2]TONT20000MAI!H23+[2]TONT20000JUIN!H23+[2]TONT20000JUIL!H23+[2]TONT20000AOUT!H23+[2]TONT20000SEPT!H23+[2]TONT20000OCT!H23+[2]TONT20000NOV!I23 -> 6000 | S23: =[2]TONT20000DEC2015!K23+[2]TONT20000JANV!I23+[2]TONT20000FEV!I23+[2]TONT20000MARS!I23+[2]TONT20000AVRIL!I23+[2]TONT20000MAI!I23+[2]TONT20000JUIN!I23+[2]TONT20000JUIL!I23+[2]TONT20000AOUT!I23+[2]TONT20000SEPT!I23+[2]TONT20000OCT!I23+[2]TONT20000NOV!J23 -> 12000 | T23: =[2]TONT20000DEC2015!L23+[2]TONT20000JANV!J23+[2]TONT20000FEV!J23+[2]TONT20000MARS!J23+[2]TONT20000AVRIL!J23+[2]TONT20000MAI!J23+[2]TONT20000JUIN!J23+[2]TONT20000JUIL!J23+[2]TONT20000AOUT!J23+[2]TONT20000SEPT!J23+[2]TONT20000OCT!J23+[2]TONT20000NOV!K23 -> 30000 | U23: =[2]TONT20000DEC2015!M23+[2]TONT20000JANV!K23+[2]TONT20000FEV!K23+[2]TONT20000MARS!K23+[2]TONT20000AVRIL!K23+[2]TONT20000MAI!K23+[2]TONT20000JUIN!K23+[2]TONT20000JUIL!K23+[2]TONT20000AOUT!K23+[2]TONT20000SEPT!K23+[2]TONT20000OCT!K23+[2]TONT20000NOV!L23 -> 0 | V23: =[2]TONT20000DEC2015!N23+[2]TONT20000JANV!L23+[2]TONT20000FEV!L23+[2]TONT20000MARS!L23+[2]TONT20000AVRIL!L23+[2]TONT20000MAI!L23+[2]TONT20000JUIN!L23+[2]TONT20000JUIL!L23+[2]TONT20000AOUT!L23+[2]TONT20000SEPT!L23+[2]TONT20000OCT!L23+[2]TONT20000NOV!M23 -> 156000 | W23: =[2]TONT20000DEC2015!O23+[2]TONT20000JANV!M23+[2]TONT20000FEV!M23+[2]TONT20000MARS!M23+[2]TONT20000AVRIL!M23+[2]TONT20000MAI!M23+[2]TONT20000JUIN!M23+[2]TONT20000JUIL!M23+[2]TONT20000AOUT!M23+[2]TONT20000SEPT!M23+[2]TONT20000OCT!M23+[2]TONT20000NOV!N23 -> 1800000 | ... AB23: =[2]TONT20000DEC2015!T23+[2]TONT20000JANV!R23+[2]TONT20000FEV!R23+[2]TONT20000MARS!R23+[2]TONT20000AVRIL!R23+[2]TONT20000MAI!R23+[2]TONT20000JUIN!R23+[2]TONT20000JUIL!R23+[2]TONT20000AOUT!R23+[2]TONT20000SEPT!R23+[2]TONT20000OCT!R23+[2]TONT20000NOV!S23 -> 0
A24: AS201619 | B24: =VLOOKUP(A24,[2]LISTADHERENT!A$5:H$52,2,0) -> KOUATCHO MESSACK | C24: =VLOOKUP(A24,[2]FONDSDECAISSE!A$5:C$52,3,0) -> 390000 | D24: 0 | E24: =C24+D24+Q24 -> 426000 | F24: =INT([2]TONT20000DEC2015!E24+[2]TONT20000JANV!C24+[2]TONT20000FEV!C24+[2]TONT20000MARS!C24+[2]TONT20000AVRIL!C24+[2]TONT20000MAI!C24+[2]TONT20000JUIN!C24+[2]TONT20000JUIL!C24+[2]TONT20000AOUT!C24+[2]TONT20000SEPT!C24+[2]TONT20000OCT!C24+[2]TONT20000NOV!C24) -> 47818 | G24: =[2]TONT20000NOV!E24 -> 473818.64 | H24: =D24+F24+Q24 -> 83818 | I24: =L24+M24+N24+O24 -> 80000 | J24: =H24-I24 -> 3818 | K24: 0 | L24: 30000 | N24: 50000 | O24: =48000-(R24+S24+T24) -> 0 | P24: =[2]TONT20000DEC2015!H24+[2]TONT20000JANV!F24+[2]TONT20000FEV!F24+[2]TONT20000MARS!F24+[2]TONT20000AVRIL!F24+[2]TONT20000MAI!F24+[2]TONT20000JUIN!F24+[2]TONT20000JUIL!F24+[2]TONT20000AOUT!F24+[2]TONT20000SEPT!F24+[2]TONT20000OCT!F24+[2]TONT20000NOV!G24 -> 240000 | Q24: =[2]TONT20000DEC2015!I24+[2]TONT20000JANV!G24+[2]TONT20000FEV!G24+[2]TONT20000MARS!G24+[2]TONT20000AVRIL!G24+[2]TONT20000MAI!G24+[2]TONT20000JUIN!G24+[2]TONT20000JUIL!G24+[2]TONT20000AOUT!G24+[2]TONT20000SEPT!G24+[2]TONT20000OCT!G24+[2]TONT20000NOV!H24 -> 36000 | R24: =[2]TONT20000DEC2015!J24+[2]TONT20000JANV!H24+[2]TONT20000FEV!H24+[2]TONT20000MARS!H24+[2]TONT20000AVRIL!H24+[2]TONT20000MAI!H24+[2]TONT20000JUIN!H24+[2]TONT20000JUIL!H24+[2]TONT20000AOUT!H24+[2]TONT20000SEPT!H24+[2]TONT20000OCT!H24+[2]TONT20000NOV!I24 -> 6000 | S24: =[2]TONT20000DEC2015!K24+[2]TONT20000JANV!I24+[2]TONT20000FEV!I24+[2]TONT20000MARS!I24+[2]TONT20000AVRIL!I24+[2]TONT20000MAI!I24+[2]TONT20000JUIN!I24+[2]TONT20000JUIL!I24+[2]TONT20000AOUT!I24+[2]TONT20000SEPT!I24+[2]TONT20000OCT!I24+[2]TONT20000NOV!J24 -> 12000 | T24: =[2]TONT20000DEC2015!L24+[2]TONT20000JANV!J24+[2]TONT20000FEV!J24+[2]TONT20000MARS!J24+[2]TONT20000AVRIL!J24+[2]TONT20000MAI!J24+[2]TONT20000JUIN!J24+[2]TONT20000JUIL!J24+[2]TONT20000AOUT!J24+[2]TONT20000SEPT!J24+[2]TONT20000OCT!J24+[2]TONT20000NOV!K24 -> 30000 | U24: =[2]TONT20000DEC2015!M24+[2]TONT20000JANV!K24+[2]TONT20000FEV!K24+[2]TONT20000MARS!K24+[2]TONT20000AVRIL!K24+[2]TONT20000MAI!K24+[2]TONT20000JUIN!K24+[2]TONT20000JUIL!K24+[2]TONT20000AOUT!K24+[2]TONT20000SEPT!K24+[2]TONT20000OCT!K24+[2]TONT20000NOV!L24 -> 0 | V24: =[2]TONT20000DEC2015!N24+[2]TONT20000JANV!L24+[2]TONT20000FEV!L24+[2]TONT20000MARS!L24+[2]TONT20000AVRIL!L24+[2]TONT20000MAI!L24+[2]TONT20000JUIN!L24+[2]TONT20000JUIL!L24+[2]TONT20000AOUT!L24+[2]TONT20000SEPT!L24+[2]TONT20000OCT!L24+[2]TONT20000NOV!M24 -> 156000 | W24: =[2]TONT20000DEC2015!O24+[2]TONT20000JANV!M24+[2]TONT20000FEV!M24+[2]TONT20000MARS!M24+[2]TONT20000AVRIL!M24+[2]TONT20000MAI!M24+[2]TONT20000JUIN!M24+[2]TONT20000JUIL!M24+[2]TONT20000AOUT!M24+[2]TONT20000SEPT!M24+[2]TONT20000OCT!M24+[2]TONT20000NOV!N24 -> 1600000 | ... AB24: =[2]TONT20000DEC2015!T24+[2]TONT20000JANV!R24+[2]TONT20000FEV!R24+[2]TONT20000MARS!R24+[2]TONT20000AVRIL!R24+[2]TONT20000MAI!R24+[2]TONT20000JUIN!R24+[2]TONT20000JUIL!R24+[2]TONT20000AOUT!R24+[2]TONT20000SEPT!R24+[2]TONT20000OCT!R24+[2]TONT20000NOV!S24 -> 0
A25: AS201620 | B25: =VLOOKUP(A25,[2]LISTADHERENT!A$5:H$52,2,0) -> LOWE JEAN | C25: =VLOOKUP(A25,[2]FONDSDECAISSE!A$5:C$52,3,0) -> 390000 | D25: 4331 | E25: =C25+D25+Q25 -> 430331 | F25: =INT([2]TONT20000DEC2015!E25+[2]TONT20000JANV!C25+[2]TONT20000FEV!C25+[2]TONT20000MARS!C25+[2]TONT20000AVRIL!C25+[2]TONT20000MAI!C25+[2]TONT20000JUIN!C25+[2]TONT20000JUIL!C25+[2]TONT20000AOUT!C25+[2]TONT20000SEPT!C25+[2]TONT20000OCT!C25+[2]TONT20000NOV!C25) -> 48321 | G25: =[2]TONT20000NOV!E25 -> 478652.69 | H25: =D25+F25+Q25 -> 88652 | I25: =L25+M25+N25+O25 -> 80000 | J25: =H25-I25 -> 8652 | K25: 6000 | L25: 30000 | N25: 50000 | O25: =48000-(R25+S25+T25) -> 0 | P25: =[2]TONT20000DEC2015!H25+[2]TONT20000JANV!F25+[2]TONT20000FEV!F25+[2]TONT20000MARS!F25+[2]TONT20000AVRIL!F25+[2]TONT20000MAI!F25+[2]TONT20000JUIN!F25+[2]TONT20000JUIL!F25+[2]TONT20000AOUT!F25+[2]TONT20000SEPT!F25+[2]TONT20000OCT!F25+[2]TONT20000NOV!G25 -> 240000 | Q25: =[2]TONT20000DEC2015!I25+[2]TONT20000JANV!G25+[2]TONT20000FEV!G25+[2]TONT20000MARS!G25+[2]TONT20000AVRIL!G25+[2]TONT20000MAI!G25+[2]TONT20000JUIN!G25+[2]TONT20000JUIL!G25+[2]TONT20000AOUT!G25+[2]TONT20000SEPT!G25+[2]TONT20000OCT!G25+[2]TONT20000NOV!H25 -> 36000 | R25: =[2]TONT20000DEC2015!J25+[2]TONT20000JANV!H25+[2]TONT20000FEV!H25+[2]TONT20000MARS!H25+[2]TONT20000AVRIL!H25+[2]TONT20000MAI!H25+[2]TONT20000JUIN!H25+[2]TONT20000JUIL!H25+[2]TONT20000AOUT!H25+[2]TONT20000SEPT!H25+[2]TONT20000OCT!H25+[2]TONT20000NOV!I25 -> 6000 | S25: =[2]TONT20000DEC2015!K25+[2]TONT20000JANV!I25+[2]TONT20000FEV!I25+[2]TONT20000MARS!I25+[2]TONT20000AVRIL!I25+[2]TONT20000MAI!I25+[2]TONT20000JUIN!I25+[2]TONT20000JUIL!I25+[2]TONT20000AOUT!I25+[2]TONT20000SEPT!I25+[2]TONT20000OCT!I25+[2]TONT20000NOV!J25 -> 12000 | T25: =[2]TONT20000DEC2015!L25+[2]TONT20000JANV!J25+[2]TONT20000FEV!J25+[2]TONT20000MARS!J25+[2]TONT20000AVRIL!J25+[2]TONT20000MAI!J25+[2]TONT20000JUIN!J25+[2]TONT20000JUIL!J25+[2]TONT20000AOUT!J25+[2]TONT20000SEPT!J25+[2]TONT20000OCT!J25+[2]TONT20000NOV!K25 -> 30000 | U25: =[2]TONT20000DEC2015!M25+[2]TONT20000JANV!K25+[2]TONT20000FEV!K25+[2]TONT20000MARS!K25+[2]TONT20000AVRIL!K25+[2]TONT20000MAI!K25+[2]TONT20000JUIN!K25+[2]TONT20000JUIL!K25+[2]TONT20000AOUT!K25+[2]TONT20000SEPT!K25+[2]TONT20000OCT!K25+[2]TONT20000NOV!L25 -> 0 | V25: =[2]TONT20000DEC2015!N25+[2]TONT20000JANV!L25+[2]TONT20000FEV!L25+[2]TONT20000MARS!L25+[2]TONT20000AVRIL!L25+[2]TONT20000MAI!L25+[2]TONT20000JUIN!L25+[2]TONT20000JUIL!L25+[2]TONT20000AOUT!L25+[2]TONT20000SEPT!L25+[2]TONT20000OCT!L25+[2]TONT20000NOV!M25 -> 156000 | W25: =[2]TONT20000DEC2015!O25+[2]TONT20000JANV!M25+[2]TONT20000FEV!M25+[2]TONT20000MARS!M25+[2]TONT20000AVRIL!M25+[2]TONT20000MAI!M25+[2]TONT20000JUIN!M25+[2]TONT20000JUIL!M25+[2]TONT20000AOUT!M25+[2]TONT20000SEPT!M25+[2]TONT20000OCT!M25+[2]TONT20000NOV!N25 -> 240000 | ... AB25: =[2]TONT20000DEC2015!T25+[2]TONT20000JANV!R25+[2]TONT20000FEV!R25+[2]TONT20000MARS!R25+[2]TONT20000AVRIL!R25+[2]TONT20000MAI!R25+[2]TONT20000JUIN!R25+[2]TONT20000JUIL!R25+[2]TONT20000AOUT!R25+[2]TONT20000SEPT!R25+[2]TONT20000OCT!R25+[2]TONT20000NOV!S25 -> 0
A26: AS201621 | B26: =VLOOKUP(A26,[2]LISTADHERENT!A$5:H$52,2,0) -> NANKAM APPOLINAIRE | C26: =VLOOKUP(A26,[2]FONDSDECAISSE!A$5:C$52,3,0) -> 390000 | D26: 4411 | E26: =C26+D26+Q26 -> 430411 | F26: =INT([2]TONT20000DEC2015!E26+[2]TONT20000JANV!C26+[2]TONT20000FEV!C26+[2]TONT20000MARS!C26+[2]TONT20000AVRIL!C26+[2]TONT20000MAI!C26+[2]TONT20000JUIN!C26+[2]TONT20000JUIL!C26+[2]TONT20000AOUT!C26+[2]TONT20000SEPT!C26+[2]TONT20000OCT!C26+[2]TONT20000NOV!C26) -> 48330 | G26: =[2]TONT20000NOV!E26 -> 478741.98 | H26: =D26+F26+Q26 -> 88741 | I26: =L26+M26+N26+O26 -> 80000 | J26: =H26-I26 -> 8741 | K26: 6000 | L26: 30000 | N26: 50000 | O26: =48000-(R26+S26+T26) -> 0 | P26: =[2]TONT20000DEC2015!H26+[2]TONT20000JANV!F26+[2]TONT20000FEV!F26+[2]TONT20000MARS!F26+[2]TONT20000AVRIL!F26+[2]TONT20000MAI!F26+[2]TONT20000JUIN!F26+[2]TONT20000JUIL!F26+[2]TONT20000AOUT!F26+[2]TONT20000SEPT!F26+[2]TONT20000OCT!F26+[2]TONT20000NOV!G26 -> 240000 | Q26: =[2]TONT20000DEC2015!I26+[2]TONT20000JANV!G26+[2]TONT20000FEV!G26+[2]TONT20000MARS!G26+[2]TONT20000AVRIL!G26+[2]TONT20000MAI!G26+[2]TONT20000JUIN!G26+[2]TONT20000JUIL!G26+[2]TONT20000AOUT!G26+[2]TONT20000SEPT!G26+[2]TONT20000OCT!G26+[2]TONT20000NOV!H26 -> 36000 | R26: =[2]TONT20000DEC2015!J26+[2]TONT20000JANV!H26+[2]TONT20000FEV!H26+[2]TONT20000MARS!H26+[2]TONT20000AVRIL!H26+[2]TONT20000MAI!H26+[2]TONT20000JUIN!H26+[2]TONT20000JUIL!H26+[2]TONT20000AOUT!H26+[2]TONT20000SEPT!H26+[2]TONT20000OCT!H26+[2]TONT20000NOV!I26 -> 6000 | S26: =[2]TONT20000DEC2015!K26+[2]TONT20000JANV!I26+[2]TONT20000FEV!I26+[2]TONT20000MARS!I26+[2]TONT20000AVRIL!I26+[2]TONT20000MAI!I26+[2]TONT20000JUIN!I26+[2]TONT20000JUIL!I26+[2]TONT20000AOUT!I26+[2]TONT20000SEPT!I26+[2]TONT20000OCT!I26+[2]TONT20000NOV!J26 -> 12000 | T26: =[2]TONT20000DEC2015!L26+[2]TONT20000JANV!J26+[2]TONT20000FEV!J26+[2]TONT20000MARS!J26+[2]TONT20000AVRIL!J26+[2]TONT20000MAI!J26+[2]TONT20000JUIN!J26+[2]TONT20000JUIL!J26+[2]TONT20000AOUT!J26+[2]TONT20000SEPT!J26+[2]TONT20000OCT!J26+[2]TONT20000NOV!K26 -> 30000 | U26: =[2]TONT20000DEC2015!M26+[2]TONT20000JANV!K26+[2]TONT20000FEV!K26+[2]TONT20000MARS!K26+[2]TONT20000AVRIL!K26+[2]TONT20000MAI!K26+[2]TONT20000JUIN!K26+[2]TONT20000JUIL!K26+[2]TONT20000AOUT!K26+[2]TONT20000SEPT!K26+[2]TONT20000OCT!K26+[2]TONT20000NOV!L26 -> 0 | V26: =[2]TONT20000DEC2015!N26+[2]TONT20000JANV!L26+[2]TONT20000FEV!L26+[2]TONT20000MARS!L26+[2]TONT20000AVRIL!L26+[2]TONT20000MAI!L26+[2]TONT20000JUIN!L26+[2]TONT20000JUIL!L26+[2]TONT20000AOUT!L26+[2]TONT20000SEPT!L26+[2]TONT20000OCT!L26+[2]TONT20000NOV!M26 -> 156000 | W26: =[2]TONT20000DEC2015!O26+[2]TONT20000JANV!M26+[2]TONT20000FEV!M26+[2]TONT20000MARS!M26+[2]TONT20000AVRIL!M26+[2]TONT20000MAI!M26+[2]TONT20000JUIN!M26+[2]TONT20000JUIL!M26+[2]TONT20000AOUT!M26+[2]TONT20000SEPT!M26+[2]TONT20000OCT!M26+[2]TONT20000NOV!N26 -> 1000000 | ... AB26: =[2]TONT20000DEC2015!T26+[2]TONT20000JANV!R26+[2]TONT20000FEV!R26+[2]TONT20000MARS!R26+[2]TONT20000AVRIL!R26+[2]TONT20000MAI!R26+[2]TONT20000JUIN!R26+[2]TONT20000JUIL!R26+[2]TONT20000AOUT!R26+[2]TONT20000SEPT!R26+[2]TONT20000OCT!R26+[2]TONT20000NOV!S26 -> 0
A27: AS201622 | B27: =VLOOKUP(A27,[2]LISTADHERENT!A$5:H$52,2,0) -> NDJOMO ETIENNE | C27: =VLOOKUP(A27,[2]FONDSDECAISSE!A$5:C$52,3,0) -> 390000 | D27: 2060 | E27: =C27+D27+Q27 -> 488060 | F27: =INT([2]TONT20000DEC2015!E27+[2]TONT20000JANV!C27+[2]TONT20000FEV!C27+[2]TONT20000MARS!C27+[2]TONT20000AVRIL!C27+[2]TONT20000MAI!C27+[2]TONT20000JUIN!C27+[2]TONT20000JUIL!C27+[2]TONT20000AOUT!C27+[2]TONT20000SEPT!C27+[2]TONT20000OCT!C27+[2]TONT20000NOV!C27) -> 52258 | G27: =[2]TONT20000NOV!E27 -> 540318.2 | H27: =D27+F27+Q27 -> 150318 | I27: =L27+M27+N27+O27 -> 80000 | J27: =H27-I27 -> 70318 | K27: 67500 | L27: 30000 | N27: 50000 | O27: =48000-(R27+S27+T27) -> 0 | P27: =[2]TONT20000DEC2015!H27+[2]TONT20000JANV!F27+[2]TONT20000FEV!F27+[2]TONT20000MARS!F27+[2]TONT20000AVRIL!F27+[2]TONT20000MAI!F27+[2]TONT20000JUIN!F27+[2]TONT20000JUIL!F27+[2]TONT20000AOUT!F27+[2]TONT20000SEPT!F27+[2]TONT20000OCT!F27+[2]TONT20000NOV!G27 -> 300000 | Q27: =[2]TONT20000DEC2015!I27+[2]TONT20000JANV!G27+[2]TONT20000FEV!G27+[2]TONT20000MARS!G27+[2]TONT20000AVRIL!G27+[2]TONT20000MAI!G27+[2]TONT20000JUIN!G27+[2]TONT20000JUIL!G27+[2]TONT20000AOUT!G27+[2]TONT20000SEPT!G27+[2]TONT20000OCT!G27+[2]TONT20000NOV!H27 -> 96000 | R27: =[2]TONT20000DEC2015!J27+[2]TONT20000JANV!H27+[2]TONT20000FEV!H27+[2]TONT20000MARS!H27+[2]TONT20000AVRIL!H27+[2]TONT20000MAI!H27+[2]TONT20000JUIN!H27+[2]TONT20000JUIL!H27+[2]TONT20000AOUT!H27+[2]TONT20000SEPT!H27+[2]TONT20000OCT!H27+[2]TONT20000NOV!I27 -> 6000 | S27: =[2]TONT20000DEC2015!K27+[2]TONT20000JANV!I27+[2]TONT20000FEV!I27+[2]TONT20000MARS!I27+[2]TONT20000AVRIL!I27+[2]TONT20000MAI!I27+[2]TONT20000JUIN!I27+[2]TONT20000JUIL!I27+[2]TONT20000AOUT!I27+[2]TONT20000SEPT!I27+[2]TONT20000OCT!I27+[2]TONT20000NOV!J27 -> 12000 | T27: =[2]TONT20000DEC2015!L27+[2]TONT20000JANV!J27+[2]TONT20000FEV!J27+[2]TONT20000MARS!J27+[2]TONT20000AVRIL!J27+[2]TONT20000MAI!J27+[2]TONT20000JUIN!J27+[2]TONT20000JUIL!J27+[2]TONT20000AOUT!J27+[2]TONT20000SEPT!J27+[2]TONT20000OCT!J27+[2]TONT20000NOV!K27 -> 30000 | U27: =[2]TONT20000DEC2015!M27+[2]TONT20000JANV!K27+[2]TONT20000FEV!K27+[2]TONT20000MARS!K27+[2]TONT20000AVRIL!K27+[2]TONT20000MAI!K27+[2]TONT20000JUIN!K27+[2]TONT20000JUIL!K27+[2]TONT20000AOUT!K27+[2]TONT20000SEPT!K27+[2]TONT20000OCT!K27+[2]TONT20000NOV!L27 -> 0 | V27: =[2]TONT20000DEC2015!N27+[2]TONT20000JANV!L27+[2]TONT20000FEV!L27+[2]TONT20000MARS!L27+[2]TONT20000AVRIL!L27+[2]TONT20000MAI!L27+[2]TONT20000JUIN!L27+[2]TONT20000JUIL!L27+[2]TONT20000AOUT!L27+[2]TONT20000SEPT!L27+[2]TONT20000OCT!L27+[2]TONT20000NOV!M27 -> 156000 | W27: =[2]TONT20000DEC2015!O27+[2]TONT20000JANV!M27+[2]TONT20000FEV!M27+[2]TONT20000MARS!M27+[2]TONT20000AVRIL!M27+[2]TONT20000MAI!M27+[2]TONT20000JUIN!M27+[2]TONT20000JUIL!M27+[2]TONT20000AOUT!M27+[2]TONT20000SEPT!M27+[2]TONT20000OCT!M27+[2]TONT20000NOV!N27 -> 1600000 | ... AB27: =[2]TONT20000DEC2015!T27+[2]TONT20000JANV!R27+[2]TONT20000FEV!R27+[2]TONT20000MARS!R27+[2]TONT20000AVRIL!R27+[2]TONT20000MAI!R27+[2]TONT20000JUIN!R27+[2]TONT20000JUIL!R27+[2]TONT20000AOUT!R27+[2]TONT20000SEPT!R27+[2]TONT20000OCT!R27+[2]TONT20000NOV!S27 -> 0
A28: AS201623 | B28: =VLOOKUP(A28,[2]LISTADHERENT!A$5:H$52,2,0) -> NDOMBOU JEAN CLAUDE | C28: =VLOOKUP(A28,[2]FONDSDECAISSE!A$5:C$52,3,0) -> 0 | D28: 0 | E28: =C28+D28+Q28 -> 0 | F28: =INT([2]TONT20000DEC2015!E28+[2]TONT20000JANV!C28+[2]TONT20000FEV!C28+[2]TONT20000MARS!C28+[2]TONT20000AVRIL!C28+[2]TONT20000MAI!C28+[2]TONT20000JUIN!C28+[2]TONT20000JUIL!C28+[2]TONT20000AOUT!C28+[2]TONT20000SEPT!C28+[2]TONT20000OCT!C28+[2]TONT20000NOV!C28) -> 0 | G28: =[2]TONT20000NOV!E28 -> 0 | H28: =D28+F28+Q28 -> 0 | I28: =L28+M28+N28+O28 -> 0 | J28: =H28-I28 -> 0 | P28: =[2]TONT20000DEC2015!H28+[2]TONT20000JANV!F28+[2]TONT20000FEV!F28+[2]TONT20000MARS!F28+[2]TONT20000AVRIL!F28+[2]TONT20000MAI!F28+[2]TONT20000JUIN!F28+[2]TONT20000JUIL!F28+[2]TONT20000AOUT!F28+[2]TONT20000SEPT!F28+[2]TONT20000OCT!F28+[2]TONT20000NOV!G28 -> 0 | Q28: =[2]TONT20000DEC2015!I28+[2]TONT20000JANV!G28+[2]TONT20000FEV!G28+[2]TONT20000MARS!G28+[2]TONT20000AVRIL!G28+[2]TONT20000MAI!G28+[2]TONT20000JUIN!G28+[2]TONT20000JUIL!G28+[2]TONT20000AOUT!G28+[2]TONT20000SEPT!G28+[2]TONT20000OCT!G28+[2]TONT20000NOV!H28 -> 0 | R28: =[2]TONT20000DEC2015!J28+[2]TONT20000JANV!H28+[2]TONT20000FEV!H28+[2]TONT20000MARS!H28+[2]TONT20000AVRIL!H28+[2]TONT20000MAI!H28+[2]TONT20000JUIN!H28+[2]TONT20000JUIL!H28+[2]TONT20000AOUT!H28+[2]TONT20000SEPT!H28+[2]TONT20000OCT!H28+[2]TONT20000NOV!I28 -> 0 | S28: =[2]TONT20000DEC2015!K28+[2]TONT20000JANV!I28+[2]TONT20000FEV!I28+[2]TONT20000MARS!I28+[2]TONT20000AVRIL!I28+[2]TONT20000MAI!I28+[2]TONT20000JUIN!I28+[2]TONT20000JUIL!I28+[2]TONT20000AOUT!I28+[2]TONT20000SEPT!I28+[2]TONT20000OCT!I28+[2]TONT20000NOV!J28 -> 0 | T28: =[2]TONT20000DEC2015!L28+[2]TONT20000JANV!J28+[2]TONT20000FEV!J28+[2]TONT20000MARS!J28+[2]TONT20000AVRIL!J28+[2]TONT20000MAI!J28+[2]TONT20000JUIN!J28+[2]TONT20000JUIL!J28+[2]TONT20000AOUT!J28+[2]TONT20000SEPT!J28+[2]TONT20000OCT!J28+[2]TONT20000NOV!K28 -> 0 | U28: =[2]TONT20000DEC2015!M28+[2]TONT20000JANV!K28+[2]TONT20000FEV!K28+[2]TONT20000MARS!K28+[2]TONT20000AVRIL!K28+[2]TONT20000MAI!K28+[2]TONT20000JUIN!K28+[2]TONT20000JUIL!K28+[2]TONT20000AOUT!K28+[2]TONT20000SEPT!K28+[2]TONT20000OCT!K28+[2]TONT20000NOV!L28 -> 0 | V28: =[2]TONT20000DEC2015!N28+[2]TONT20000JANV!L28+[2]TONT20000FEV!L28+[2]TONT20000MARS!L28+[2]TONT20000AVRIL!L28+[2]TONT20000MAI!L28+[2]TONT20000JUIN!L28+[2]TONT20000JUIL!L28+[2]TONT20000AOUT!L28+[2]TONT20000SEPT!L28+[2]TONT20000OCT!L28+[2]TONT20000NOV!M28 -> 0 | W28: =[2]TONT20000DEC2015!O28+[2]TONT20000JANV!M28+[2]TONT20000FEV!M28+[2]TONT20000MARS!M28+[2]TONT20000AVRIL!M28+[2]TONT20000MAI!M28+[2]TONT20000JUIN!M28+[2]TONT20000JUIL!M28+[2]TONT20000AOUT!M28+[2]TONT20000SEPT!M28+[2]TONT20000OCT!M28+[2]TONT20000NOV!N28 -> 0 | ... AB28: =[2]TONT20000DEC2015!T28+[2]TONT20000JANV!R28+[2]TONT20000FEV!R28+[2]TONT20000MARS!R28+[2]TONT20000AVRIL!R28+[2]TONT20000MAI!R28+[2]TONT20000JUIN!R28+[2]TONT20000JUIL!R28+[2]TONT20000AOUT!R28+[2]TONT20000SEPT!R28+[2]TONT20000OCT!R28+[2]TONT20000NOV!S28 -> 0
A29: AS201624 | B29: =VLOOKUP(A29,[2]LISTADHERENT!A$5:H$52,2,0) -> NGONDIEP CLAUDE | C29: =VLOOKUP(A29,[2]FONDSDECAISSE!A$5:C$52,3,0) -> 390000 | D29: 179574 | E29: =C29+D29+Q29 -> 605574 | F29: =INT([2]TONT20000DEC2015!E29+[2]TONT20000JANV!C29+[2]TONT20000FEV!C29+[2]TONT20000MARS!C29+[2]TONT20000AVRIL!C29+[2]TONT20000MAI!C29+[2]TONT20000JUIN!C29+[2]TONT20000JUIL!C29+[2]TONT20000AOUT!C29+[2]TONT20000SEPT!C29+[2]TONT20000OCT!C29+[2]TONT20000NOV!C29) -> 68676 | G29: =[2]TONT20000NOV!E29 -> 674250.15 | H29: =D29+F29+Q29 -> 284250 | I29: =L29+M29+N29+O29 -> 80000 | J29: =H29-I29 -> 204250 | K29: 201000 | L29: 30000 | N29: 50000 | O29: =48000-(R29+S29+T29) -> 0 | P29: =[2]TONT20000DEC2015!H29+[2]TONT20000JANV!F29+[2]TONT20000FEV!F29+[2]TONT20000MARS!F29+[2]TONT20000AVRIL!F29+[2]TONT20000MAI!F29+[2]TONT20000JUIN!F29+[2]TONT20000JUIL!F29+[2]TONT20000AOUT!F29+[2]TONT20000SEPT!F29+[2]TONT20000OCT!F29+[2]TONT20000NOV!G29 -> 240000 | Q29: =[2]TONT20000DEC2015!I29+[2]TONT20000JANV!G29+[2]TONT20000FEV!G29+[2]TONT20000MARS!G29+[2]TONT20000AVRIL!G29+[2]TONT20000MAI!G29+[2]TONT20000JUIN!G29+[2]TONT20000JUIL!G29+[2]TONT20000AOUT!G29+[2]TONT20000SEPT!G29+[2]TONT20000OCT!G29+[2]TONT20000NOV!H29 -> 36000 | R29: =[2]TONT20000DEC2015!J29+[2]TONT20000JANV!H29+[2]TONT20000FEV!H29+[2]TONT20000MARS!H29+[2]TONT20000AVRIL!H29+[2]TONT20000MAI!H29+[2]TONT20000JUIN!H29+[2]TONT20000JUIL!H29+[2]TONT20000AOUT!H29+[2]TONT20000SEPT!H29+[2]TONT20000OCT!H29+[2]TONT20000NOV!I29 -> 6000 | S29: =[2]TONT20000DEC2015!K29+[2]TONT20000JANV!I29+[2]TONT20000FEV!I29+[2]TONT20000MARS!I29+[2]TONT20000AVRIL!I29+[2]TONT20000MAI!I29+[2]TONT20000JUIN!I29+[2]TONT20000JUIL!I29+[2]TONT20000AOUT!I29+[2]TONT20000SEPT!I29+[2]TONT20000OCT!I29+[2]TONT20000NOV!J29 -> 12000 | T29: =[2]TONT20000DEC2015!L29+[2]TONT20000JANV!J29+[2]TONT20000FEV!J29+[2]TONT20000MARS!J29+[2]TONT20000AVRIL!J29+[2]TONT20000MAI!J29+[2]TONT20000JUIN!J29+[2]TONT20000JUIL!J29+[2]TONT20000AOUT!J29+[2]TONT20000SEPT!J29+[2]TONT20000OCT!J29+[2]TONT20000NOV!K29 -> 30000 | U29: =[2]TONT20000DEC2015!M29+[2]TONT20000JANV!K29+[2]TONT20000FEV!K29+[2]TONT20000MARS!K29+[2]TONT20000AVRIL!K29+[2]TONT20000MAI!K29+[2]TONT20000JUIN!K29+[2]TONT20000JUIL!K29+[2]TONT20000AOUT!K29+[2]TONT20000SEPT!K29+[2]TONT20000OCT!K29+[2]TONT20000NOV!L29 -> 0 | V29: =[2]TONT20000DEC2015!N29+[2]TONT20000JANV!L29+[2]TONT20000FEV!L29+[2]TONT20000MARS!L29+[2]TONT20000AVRIL!L29+[2]TONT20000MAI!L29+[2]TONT20000JUIN!L29+[2]TONT20000JUIL!L29+[2]TONT20000AOUT!L29+[2]TONT20000SEPT!L29+[2]TONT20000OCT!L29+[2]TONT20000NOV!M29 -> 156000 | W29: =[2]TONT20000DEC2015!O29+[2]TONT20000JANV!M29+[2]TONT20000FEV!M29+[2]TONT20000MARS!M29+[2]TONT20000AVRIL!M29+[2]TONT20000MAI!M29+[2]TONT20000JUIN!M29+[2]TONT20000JUIL!M29+[2]TONT20000AOUT!M29+[2]TONT20000SEPT!M29+[2]TONT20000OCT!M29+[2]TONT20000NOV!N29 -> 0 | ... AB29: =[2]TONT20000DEC2015!T29+[2]TONT20000JANV!R29+[2]TONT20000FEV!R29+[2]TONT20000MARS!R29+[2]TONT20000AVRIL!R29+[2]TONT20000MAI!R29+[2]TONT20000JUIN!R29+[2]TONT20000JUIL!R29+[2]TONT20000AOUT!R29+[2]TONT20000SEPT!R29+[2]TONT20000OCT!R29+[2]TONT20000NOV!S29 -> 0
A30: AS201625 | B30: =VLOOKUP(A30,[2]LISTADHERENT!A$5:H$52,2,0) -> NGONGANG JEAN THEODORE | C30: =VLOOKUP(A30,[2]FONDSDECAISSE!A$5:C$52,3,0) -> 0 | D30: 0 | E30: =C30+D30+Q30 -> 17782 | F30: =INT([2]TONT20000DEC2015!E30+[2]TONT20000JANV!C30+[2]TONT20000FEV!C30+[2]TONT20000MARS!C30+[2]TONT20000AVRIL!C30+[2]TONT20000MAI!C30+[2]TONT20000JUIN!C30+[2]TONT20000JUIL!C30+[2]TONT20000AOUT!C30+[2]TONT20000SEPT!C30+[2]TONT20000OCT!C30+[2]TONT20000NOV!C30) -> 2520 | G30: =[2]TONT20000NOV!E30 -> 38520.175 | H30: =D30+F30+Q30 -> 20302 | I30: =L30+M30+N30+O30 -> 20196 | J30: =H30-I30 -> 106 | K30: 0 | N30: =50000-29804 -> 20196 | O30: =48000-(R30+S30+T30) -> 0 | P30: =[2]TONT20000DEC2015!H30+[2]TONT20000JANV!F30+[2]TONT20000FEV!F30+[2]TONT20000MARS!F30+[2]TONT20000AVRIL!F30+[2]TONT20000MAI!F30+[2]TONT20000JUIN!F30+[2]TONT20000JUIL!F30+[2]TONT20000AOUT!F30+[2]TONT20000SEPT!F30+[2]TONT20000OCT!F30+[2]TONT20000NOV!G30 -> 240000 | Q30: =[2]TONT20000DEC2015!I30+[2]TONT20000JANV!G30+[2]TONT20000FEV!G30+[2]TONT20000MARS!G30+[2]TONT20000AVRIL!G30+[2]TONT20000MAI!G30+[2]TONT20000JUIN!G30+[2]TONT20000JUIL!G30+[2]TONT20000AOUT!G30+[2]TONT20000SEPT!G30+[2]TONT20000OCT!G30+[2]TONT20000NOV!H30-18218 -> 17782 | R30: =[2]TONT20000DEC2015!J30+[2]TONT20000JANV!H30+[2]TONT20000FEV!H30+[2]TONT20000MARS!H30+[2]TONT20000AVRIL!H30+[2]TONT20000MAI!H30+[2]TONT20000JUIN!H30+[2]TONT20000JUIL!H30+[2]TONT20000AOUT!H30+[2]TONT20000SEPT!H30+[2]TONT20000OCT!H30+[2]TONT20000NOV!I30 -> 6000 | S30: =[2]TONT20000DEC2015!K30+[2]TONT20000JANV!I30+[2]TONT20000FEV!I30+[2]TONT20000MARS!I30+[2]TONT20000AVRIL!I30+[2]TONT20000MAI!I30+[2]TONT20000JUIN!I30+[2]TONT20000JUIL!I30+[2]TONT20000AOUT!I30+[2]TONT20000SEPT!I30+[2]TONT20000OCT!I30+[2]TONT20000NOV!J30 -> 12000 | T30: =[2]TONT20000DEC2015!L30+[2]TONT20000JANV!J30+[2]TONT20000FEV!J30+[2]TONT20000MARS!J30+[2]TONT20000AVRIL!J30+[2]TONT20000MAI!J30+[2]TONT20000JUIN!J30+[2]TONT20000JUIL!J30+[2]TONT20000AOUT!J30+[2]TONT20000SEPT!J30+[2]TONT20000OCT!J30+[2]TONT20000NOV!K30 -> 30000 | U30: =[2]TONT20000DEC2015!M30+[2]TONT20000JANV!K30+[2]TONT20000FEV!K30+[2]TONT20000MARS!K30+[2]TONT20000AVRIL!K30+[2]TONT20000MAI!K30+[2]TONT20000JUIN!K30+[2]TONT20000JUIL!K30+[2]TONT20000AOUT!K30+[2]TONT20000SEPT!K30+[2]TONT20000OCT!K30+[2]TONT20000NOV!L30 -> 0 | V30: =[2]TONT20000DEC2015!N30+[2]TONT20000JANV!L30+[2]TONT20000FEV!L30+[2]TONT20000MARS!L30+[2]TONT20000AVRIL!L30+[2]TONT20000MAI!L30+[2]TONT20000JUIN!L30+[2]TONT20000JUIL!L30+[2]TONT20000AOUT!L30+[2]TONT20000SEPT!L30+[2]TONT20000OCT!L30+[2]TONT20000NOV!M30 -> 156000 | W30: =[2]TONT20000DEC2015!O30+[2]TONT20000JANV!M30+[2]TONT20000FEV!M30+[2]TONT20000MARS!M30+[2]TONT20000AVRIL!M30+[2]TONT20000MAI!M30+[2]TONT20000JUIN!M30+[2]TONT20000JUIL!M30+[2]TONT20000AOUT!M30+[2]TONT20000SEPT!M30+[2]TONT20000OCT!M30+[2]TONT20000NOV!N30 -> 0 | X30: =[2]TONT20000DEC2015!P30+[2]TONT20000JANV!N30+[2]TONT20000FEV!N30+[2]TONT20000MARS!N30+[2]TONT20000AVRIL!N30+[2]TONT20000MAI!N30+[2]TONT20000JUIN!N30+[2]TONT20000JUIL!N30+[2]TONT20000AOUT!N30+[2]TONT20000SEPT!N30+[2]TONT20000OCT!N30+[2]TONT20000NOV!O30 -> 0 | Y30: =[2]TONT20000DEC2015!Q30+[2]TONT20000JANV!O30+[2]TONT20000FEV!O30+[2]TONT20000MARS!O30+[2]TONT20000AVRIL!O30+[2]TONT20000MAI!O30+[2]TONT20000JUIN!O30+[2]TONT20000JUIL!O30+[2]TONT20000AOUT!O30+[2]TONT20000SEPT!O30+[2]TONT20000OCT!O30+[2]TONT20000NOV!P30 -> 0 | ... AB30: =[2]TONT20000DEC2015!T30+[2]TONT20000JANV!R30+[2]TONT20000FEV!R30+[2]TONT20000MARS!R30+[2]TONT20000AVRIL!R30+[2]TONT20000MAI!R30+[2]TONT20000JUIN!R30+[2]TONT20000JUIL!R30+[2]TONT20000AOUT!R30+[2]TONT20000SEPT!R30+[2]TONT20000OCT!R30+[2]TONT20000NOV!S30 -> 0
A31: AS201626 | B31: =VLOOKUP(A31,[2]LISTADHERENT!A$5:H$52,2,0) -> NGUIEMEGNI MATHIEU BLAISE | C31: 390000 | D31: 0 | E31: =C31+D31+Q31 -> 945945 | F31: =INT([2]TONT20000DEC2015!E31+[2]TONT20000JANV!C31+[2]TONT20000FEV!C31+[2]TONT20000MARS!C31+[2]TONT20000AVRIL!C31+[2]TONT20000MAI!C31+[2]TONT20000JUIN!C31+[2]TONT20000JUIL!C31+[2]TONT20000AOUT!C31+[2]TONT20000SEPT!C31+[2]TONT20000OCT!C31+[2]TONT20000NOV!C31) -> 39243 | G31: =[2]TONT20000NOV!E31 -> 985188.09 | H31: =D31+F31+Q31 -> 595188 | I31: =L31+M31+N31+O31 -> 30000 | J31: =H31-I31 -> 565188 | K31: 0 | L31: 30000 | N31: 0 | O31: =48000-(R31+S31+T31) -> 0 | P31: =[2]TONT20000DEC2015!H31+[2]TONT20000JANV!F31+[2]TONT20000FEV!F31+[2]TONT20000MARS!F31+[2]TONT20000AVRIL!F31+[2]TONT20000MAI!F31+[2]TONT20000JUIN!F31+[2]TONT20000JUIL!F31+[2]TONT20000AOUT!F31+[2]TONT20000SEPT!F31+[2]TONT20000OCT!F31+[2]TONT20000NOV!G31 -> 860000 | Q31: =[2]TONT20000DEC2015!I31+[2]TONT20000JANV!G31+[2]TONT20000FEV!G31+[2]TONT20000MARS!G31+[2]TONT20000AVRIL!G31+[2]TONT20000MAI!G31+[2]TONT20000JUIN!G31+[2]TONT20000JUIL!G31+[2]TONT20000AOUT!G31+[2]TONT20000SEPT!G31+[2]TONT20000OCT!G31+[2]TONT20000NOV!H31 -> 555945 | R31: =[2]TONT20000DEC2015!J31+[2]TONT20000JANV!H31+[2]TONT20000FEV!H31+[2]TONT20000MARS!H31+[2]TONT20000AVRIL!H31+[2]TONT20000MAI!H31+[2]TONT20000JUIN!H31+[2]TONT20000JUIL!H31+[2]TONT20000AOUT!H31+[2]TONT20000SEPT!H31+[2]TONT20000OCT!H31+[2]TONT20000NOV!I31 -> 6000 | S31: =[2]TONT20000DEC2015!K31+[2]TONT20000JANV!I31+[2]TONT20000FEV!I31+[2]TONT20000MARS!I31+[2]TONT20000AVRIL!I31+[2]TONT20000MAI!I31+[2]TONT20000JUIN!I31+[2]TONT20000JUIL!I31+[2]TONT20000AOUT!I31+[2]TONT20000SEPT!I31+[2]TONT20000OCT!I31+[2]TONT20000NOV!J31 -> 12000 | T31: =[2]TONT20000DEC2015!L31+[2]TONT20000JANV!J31+[2]TONT20000FEV!J31+[2]TONT20000MARS!J31+[2]TONT20000AVRIL!J31+[2]TONT20000MAI!J31+[2]TONT20000JUIN!J31+[2]TONT20000JUIL!J31+[2]TONT20000AOUT!J31+[2]TONT20000SEPT!J31+[2]TONT20000OCT!J31+[2]TONT20000NOV!K31 -> 30000 | U31: =[2]TONT20000DEC2015!M31+[2]TONT20000JANV!K31+[2]TONT20000FEV!K31+[2]TONT20000MARS!K31+[2]TONT20000AVRIL!K31+[2]TONT20000MAI!K31+[2]TONT20000JUIN!K31+[2]TONT20000JUIL!K31+[2]TONT20000AOUT!K31+[2]TONT20000SEPT!K31+[2]TONT20000OCT!K31+[2]TONT20000NOV!L31 -> 50000 | V31: =[2]TONT20000DEC2015!N31+[2]TONT20000JANV!L31+[2]TONT20000FEV!L31+[2]TONT20000MARS!L31+[2]TONT20000AVRIL!L31+[2]TONT20000MAI!L31+[2]TONT20000JUIN!L31+[2]TONT20000JUIL!L31+[2]TONT20000AOUT!L31+[2]TONT20000SEPT!L31+[2]TONT20000OCT!L31+[2]TONT20000NOV!M31 -> 156000 | W31: =[2]TONT20000DEC2015!O31+[2]TONT20000JANV!M31+[2]TONT20000FEV!M31+[2]TONT20000MARS!M31+[2]TONT20000AVRIL!M31+[2]TONT20000MAI!M31+[2]TONT20000JUIN!M31+[2]TONT20000JUIL!M31+[2]TONT20000AOUT!M31+[2]TONT20000SEPT!M31+[2]TONT20000OCT!M31+[2]TONT20000NOV!N31 -> 0 | ... AB31: =[2]TONT20000DEC2015!T31+[2]TONT20000JANV!R31+[2]TONT20000FEV!R31+[2]TONT20000MARS!R31+[2]TONT20000AVRIL!R31+[2]TONT20000MAI!R31+[2]TONT20000JUIN!R31+[2]TONT20000JUIL!R31+[2]TONT20000AOUT!R31+[2]TONT20000SEPT!R31+[2]TONT20000OCT!R31+[2]TONT20000NOV!S31 -> 0
A32: AS201627 | B32: =VLOOKUP(A32,[2]LISTADHERENT!A$5:H$52,2,0) -> NJEPDJIO MBOUKAM DELUXE | C32: =VLOOKUP(A32,[2]FONDSDECAISSE!A$5:C$52,3,0) -> 390000 | D32: 1734 | E32: =C32+D32+Q32 -> 443734 | F32: =INT([2]TONT20000DEC2015!E32+[2]TONT20000JANV!C32+[2]TONT20000FEV!C32+[2]TONT20000MARS!C32+[2]TONT20000AVRIL!C32+[2]TONT20000MAI!C32+[2]TONT20000JUIN!C32+[2]TONT20000JUIL!C32+[2]TONT20000AOUT!C32+[2]TONT20000SEPT!C32+[2]TONT20000OCT!C32+[2]TONT20000NOV!C32) -> 49539 | G32: =[2]TONT20000NOV!E32 -> 493273.71 | H32: =D32+F32+Q32 -> 103273 | I32: =L32+M32+N32+O32 -> 80000 | J32: =H32-I32 -> 23273 | K32: 20500 | L32: 30000 | N32: 50000 | O32: =48000-(R32+S32+T32) -> 0 | P32: =[2]TONT20000DEC2015!H32+[2]TONT20000JANV!F32+[2]TONT20000FEV!F32+[2]TONT20000MARS!F32+[2]TONT20000AVRIL!F32+[2]TONT20000MAI!F32+[2]TONT20000JUIN!F32+[2]TONT20000JUIL!F32+[2]TONT20000AOUT!F32+[2]TONT20000SEPT!F32+[2]TONT20000OCT!F32+[2]TONT20000NOV!G32 -> 256000 | Q32: =[2]TONT20000DEC2015!I32+[2]TONT20000JANV!G32+[2]TONT20000FEV!G32+[2]TONT20000MARS!G32+[2]TONT20000AVRIL!G32+[2]TONT20000MAI!G32+[2]TONT20000JUIN!G32+[2]TONT20000JUIL!G32+[2]TONT20000AOUT!G32+[2]TONT20000SEPT!G32+[2]TONT20000OCT!G32+[2]TONT20000NOV!H32 -> 52000 | R32: =[2]TONT20000DEC2015!J32+[2]TONT20000JANV!H32+[2]TONT20000FEV!H32+[2]TONT20000MARS!H32+[2]TONT20000AVRIL!H32+[2]TONT20000MAI!H32+[2]TONT20000JUIN!H32+[2]TONT20000JUIL!H32+[2]TONT20000AOUT!H32+[2]TONT20000SEPT!H32+[2]TONT20000OCT!H32+[2]TONT20000NOV!I32 -> 6000 | S32: =[2]TONT20000DEC2015!K32+[2]TONT20000JANV!I32+[2]TONT20000FEV!I32+[2]TONT20000MARS!I32+[2]TONT20000AVRIL!I32+[2]TONT20000MAI!I32+[2]TONT20000JUIN!I32+[2]TONT20000JUIL!I32+[2]TONT20000AOUT!I32+[2]TONT20000SEPT!I32+[2]TONT20000OCT!I32+[2]TONT20000NOV!J32 -> 12000 | T32: =[2]TONT20000DEC2015!L32+[2]TONT20000JANV!J32+[2]TONT20000FEV!J32+[2]TONT20000MARS!J32+[2]TONT20000AVRIL!J32+[2]TONT20000MAI!J32+[2]TONT20000JUIN!J32+[2]TONT20000JUIL!J32+[2]TONT20000AOUT!J32+[2]TONT20000SEPT!J32+[2]TONT20000OCT!J32+[2]TONT20000NOV!K32 -> 30000 | U32: =[2]TONT20000DEC2015!M32+[2]TONT20000JANV!K32+[2]TONT20000FEV!K32+[2]TONT20000MARS!K32+[2]TONT20000AVRIL!K32+[2]TONT20000MAI!K32+[2]TONT20000JUIN!K32+[2]TONT20000JUIL!K32+[2]TONT20000AOUT!K32+[2]TONT20000SEPT!K32+[2]TONT20000OCT!K32+[2]TONT20000NOV!L32 -> 0 | V32: =[2]TONT20000DEC2015!N32+[2]TONT20000JANV!L32+[2]TONT20000FEV!L32+[2]TONT20000MARS!L32+[2]TONT20000AVRIL!L32+[2]TONT20000MAI!L32+[2]TONT20000JUIN!L32+[2]TONT20000JUIL!L32+[2]TONT20000AOUT!L32+[2]TONT20000SEPT!L32+[2]TONT20000OCT!L32+[2]TONT20000NOV!M32 -> 156000 | W32: =[2]TONT20000DEC2015!O32+[2]TONT20000JANV!M32+[2]TONT20000FEV!M32+[2]TONT20000MARS!M32+[2]TONT20000AVRIL!M32+[2]TONT20000MAI!M32+[2]TONT20000JUIN!M32+[2]TONT20000JUIL!M32+[2]TONT20000AOUT!M32+[2]TONT20000SEPT!M32+[2]TONT20000OCT!M32+[2]TONT20000NOV!N32 -> 2000000 | ... AB32: =[2]TONT20000DEC2015!T32+[2]TONT20000JANV!R32+[2]TONT20000FEV!R32+[2]TONT20000MARS!R32+[2]TONT20000AVRIL!R32+[2]TONT20000MAI!R32+[2]TONT20000JUIN!R32+[2]TONT20000JUIL!R32+[2]TONT20000AOUT!R32+[2]TONT20000SEPT!R32+[2]TONT20000OCT!R32+[2]TONT20000NOV!S32 -> 0
A33: AS201628 | B33: =VLOOKUP(A33,[2]LISTADHERENT!A$5:H$52,2,0) -> NKAMGANG JUSTIN DEJOLIE | C33: 372800 | D33: 0 | E33: =C33+D33+Q33 -> 444800 | F33: =INT([2]TONT20000DEC2015!E33+[2]TONT20000JANV!C33+[2]TONT20000FEV!C33+[2]TONT20000MARS!C33+[2]TONT20000AVRIL!C33+[2]TONT20000MAI!C33+[2]TONT20000JUIN!C33+[2]TONT20000JUIL!C33+[2]TONT20000AOUT!C33+[2]TONT20000SEPT!C33+[2]TONT20000OCT!C33+[2]TONT20000NOV!C33) -> 22208 | G33: =[2]TONT20000NOV!E33 -> 539008.02 | H33: =D33+F33+Q33 -> 94208 | I33: =L33+M33+N33+O33 -> 80000 | J33: =H33-I33 -> 14208 | K33: 0 | L33: 30000 | N33: 50000 | O33: =48000-(R33+S33+T33) -> 0 | P33: =[2]TONT20000DEC2015!H33+[2]TONT20000JANV!F33+[2]TONT20000FEV!F33+[2]TONT20000MARS!F33+[2]TONT20000AVRIL!F33+[2]TONT20000MAI!F33+[2]TONT20000JUIN!F33+[2]TONT20000JUIL!F33+[2]TONT20000AOUT!F33+[2]TONT20000SEPT!F33+[2]TONT20000OCT!F33+[2]TONT20000NOV!G33 -> 648800 | Q33: =[2]TONT20000DEC2015!I33+[2]TONT20000JANV!G33+[2]TONT20000FEV!G33+[2]TONT20000MARS!G33+[2]TONT20000AVRIL!G33+[2]TONT20000MAI!G33+[2]TONT20000JUIN!G33+[2]TONT20000JUIL!G33+[2]TONT20000AOUT!G33+[2]TONT20000SEPT!G33+[2]TONT20000OCT!G33+[2]TONT20000NOV!H33-372800 -> 72000 | R33: =[2]TONT20000DEC2015!J33+[2]TONT20000JANV!H33+[2]TONT20000FEV!H33+[2]TONT20000MARS!H33+[2]TONT20000AVRIL!H33+[2]TONT20000MAI!H33+[2]TONT20000JUIN!H33+[2]TONT20000JUIL!H33+[2]TONT20000AOUT!H33+[2]TONT20000SEPT!H33+[2]TONT20000OCT!H33+[2]TONT20000NOV!I33 -> 6000 | S33: =[2]TONT20000DEC2015!K33+[2]TONT20000JANV!I33+[2]TONT20000FEV!I33+[2]TONT20000MARS!I33+[2]TONT20000AVRIL!I33+[2]TONT20000MAI!I33+[2]TONT20000JUIN!I33+[2]TONT20000JUIL!I33+[2]TONT20000AOUT!I33+[2]TONT20000SEPT!I33+[2]TONT20000OCT!I33+[2]TONT20000NOV!J33 -> 12000 | T33: =[2]TONT20000DEC2015!L33+[2]TONT20000JANV!J33+[2]TONT20000FEV!J33+[2]TONT20000MARS!J33+[2]TONT20000AVRIL!J33+[2]TONT20000MAI!J33+[2]TONT20000JUIN!J33+[2]TONT20000JUIL!J33+[2]TONT20000AOUT!J33+[2]TONT20000SEPT!J33+[2]TONT20000OCT!J33+[2]TONT20000NOV!K33 -> 30000 | U33: =[2]TONT20000DEC2015!M33+[2]TONT20000JANV!K33+[2]TONT20000FEV!K33+[2]TONT20000MARS!K33+[2]TONT20000AVRIL!K33+[2]TONT20000MAI!K33+[2]TONT20000JUIN!K33+[2]TONT20000JUIL!K33+[2]TONT20000AOUT!K33+[2]TONT20000SEPT!K33+[2]TONT20000OCT!K33+[2]TONT20000NOV!L33 -> 0 | V33: =[2]TONT20000DEC2015!N33+[2]TONT20000JANV!L33+[2]TONT20000FEV!L33+[2]TONT20000MARS!L33+[2]TONT20000AVRIL!L33+[2]TONT20000MAI!L33+[2]TONT20000JUIN!L33+[2]TONT20000JUIL!L33+[2]TONT20000AOUT!L33+[2]TONT20000SEPT!L33+[2]TONT20000OCT!L33+[2]TONT20000NOV!M33 -> 156000 | W33: =[2]TONT20000DEC2015!O33+[2]TONT20000JANV!M33+[2]TONT20000FEV!M33+[2]TONT20000MARS!M33+[2]TONT20000AVRIL!M33+[2]TONT20000MAI!M33+[2]TONT20000JUIN!M33+[2]TONT20000JUIL!M33+[2]TONT20000AOUT!M33+[2]TONT20000SEPT!M33+[2]TONT20000OCT!M33+[2]TONT20000NOV!N33 -> 1000000 | X33: =[2]TONT20000DEC2015!P33+[2]TONT20000JANV!N33+[2]TONT20000FEV!N33+[2]TONT20000MARS!N33+[2]TONT20000AVRIL!N33+[2]TONT20000MAI!N33+[2]TONT20000JUIN!N33+[2]TONT20000JUIL!N33+[2]TONT20000AOUT!N33+[2]TONT20000SEPT!N33+[2]TONT20000OCT!N33+[2]TONT20000NOV!O33 -> 120000 | Y33: =[2]TONT20000DEC2015!Q33+[2]TONT20000JANV!O33+[2]TONT20000FEV!O33+[2]TONT20000MARS!O33+[2]TONT20000AVRIL!O33+[2]TONT20000MAI!O33+[2]TONT20000JUIN!O33+[2]TONT20000JUIL!O33+[2]TONT20000AOUT!O33+[2]TONT20000SEPT!O33+[2]TONT20000OCT!O33+[2]TONT20000NOV!P33 -> 0 | ... AB33: =[2]TONT20000DEC2015!T33+[2]TONT20000JANV!R33+[2]TONT20000FEV!R33+[2]TONT20000MARS!R33+[2]TONT20000AVRIL!R33+[2]TONT20000MAI!R33+[2]TONT20000JUIN!R33+[2]TONT20000JUIL!R33+[2]TONT20000AOUT!R33+[2]TONT20000SEPT!R33+[2]TONT20000OCT!R33+[2]TONT20000NOV!S33 -> 0
A34: AS201629 | B34: =VLOOKUP(A34,[2]LISTADHERENT!A$5:H$52,2,0) -> NKEPSEU DIEUDONNE | C34: =VLOOKUP(A34,[2]FONDSDECAISSE!A$5:C$52,3,0) -> 390000 | D34: 8739 | E34: =C34+D34+Q34 -> 494739 | F34: =INT([2]TONT20000DEC2015!E34+[2]TONT20000JANV!C34+[2]TONT20000FEV!C34+[2]TONT20000MARS!C34+[2]TONT20000AVRIL!C34+[2]TONT20000MAI!C34+[2]TONT20000JUIN!C34+[2]TONT20000JUIL!C34+[2]TONT20000AOUT!C34+[2]TONT20000SEPT!C34+[2]TONT20000OCT!C34+[2]TONT20000NOV!C34) -> 53033 | G34: =[2]TONT20000NOV!E34 -> 547772.97 | H34: =D34+F34+Q34 -> 157772 | I34: =L34+M34+N34+O34 -> 30000 | J34: =H34-I34 -> 127772 | K34: 125000 | L34: 30000 | N34: 0 | O34: =48000-(R34+S34+T34) -> 0 | P34: =[2]TONT20000DEC2015!H34+[2]TONT20000JANV!F34+[2]TONT20000FEV!F34+[2]TONT20000MARS!F34+[2]TONT20000AVRIL!F34+[2]TONT20000MAI!F34+[2]TONT20000JUIN!F34+[2]TONT20000JUIL!F34+[2]TONT20000AOUT!F34+[2]TONT20000SEPT!F34+[2]TONT20000OCT!F34+[2]TONT20000NOV!G34 -> 350000 | Q34: =[2]TONT20000DEC2015!I34+[2]TONT20000JANV!G34+[2]TONT20000FEV!G34+[2]TONT20000MARS!G34+[2]TONT20000AVRIL!G34+[2]TONT20000MAI!G34+[2]TONT20000JUIN!G34+[2]TONT20000JUIL!G34+[2]TONT20000AOUT!G34+[2]TONT20000SEPT!G34+[2]TONT20000OCT!G34+[2]TONT20000NOV!H34 -> 96000 | R34: =[2]TONT20000DEC2015!J34+[2]TONT20000JANV!H34+[2]TONT20000FEV!H34+[2]TONT20000MARS!H34+[2]TONT20000AVRIL!H34+[2]TONT20000MAI!H34+[2]TONT20000JUIN!H34+[2]TONT20000JUIL!H34+[2]TONT20000AOUT!H34+[2]TONT20000SEPT!H34+[2]TONT20000OCT!H34+[2]TONT20000NOV!I34 -> 6000 | S34: =[2]TONT20000DEC2015!K34+[2]TONT20000JANV!I34+[2]TONT20000FEV!I34+[2]TONT20000MARS!I34+[2]TONT20000AVRIL!I34+[2]TONT20000MAI!I34+[2]TONT20000JUIN!I34+[2]TONT20000JUIL!I34+[2]TONT20000AOUT!I34+[2]TONT20000SEPT!I34+[2]TONT20000OCT!I34+[2]TONT20000NOV!J34 -> 12000 | T34: =[2]TONT20000DEC2015!L34+[2]TONT20000JANV!J34+[2]TONT20000FEV!J34+[2]TONT20000MARS!J34+[2]TONT20000AVRIL!J34+[2]TONT20000MAI!J34+[2]TONT20000JUIN!J34+[2]TONT20000JUIL!J34+[2]TONT20000AOUT!J34+[2]TONT20000SEPT!J34+[2]TONT20000OCT!J34+[2]TONT20000NOV!K34 -> 30000 | U34: =[2]TONT20000DEC2015!M34+[2]TONT20000JANV!K34+[2]TONT20000FEV!K34+[2]TONT20000MARS!K34+[2]TONT20000AVRIL!K34+[2]TONT20000MAI!K34+[2]TONT20000JUIN!K34+[2]TONT20000JUIL!K34+[2]TONT20000AOUT!K34+[2]TONT20000SEPT!K34+[2]TONT20000OCT!K34+[2]TONT20000NOV!L34 -> 50000 | V34: =[2]TONT20000DEC2015!N34+[2]TONT20000JANV!L34+[2]TONT20000FEV!L34+[2]TONT20000MARS!L34+[2]TONT20000AVRIL!L34+[2]TONT20000MAI!L34+[2]TONT20000JUIN!L34+[2]TONT20000JUIL!L34+[2]TONT20000AOUT!L34+[2]TONT20000SEPT!L34+[2]TONT20000OCT!L34+[2]TONT20000NOV!M34 -> 156000 | W34: =[2]TONT20000DEC2015!O34+[2]TONT20000JANV!M34+[2]TONT20000FEV!M34+[2]TONT20000MARS!M34+[2]TONT20000AVRIL!M34+[2]TONT20000MAI!M34+[2]TONT20000JUIN!M34+[2]TONT20000JUIL!M34+[2]TONT20000AOUT!M34+[2]TONT20000SEPT!M34+[2]TONT20000OCT!M34+[2]TONT20000NOV!N34 -> 600000 | ... AB34: =[2]TONT20000DEC2015!T34+[2]TONT20000JANV!R34+[2]TONT20000FEV!R34+[2]TONT20000MARS!R34+[2]TONT20000AVRIL!R34+[2]TONT20000MAI!R34+[2]TONT20000JUIN!R34+[2]TONT20000JUIL!R34+[2]TONT20000AOUT!R34+[2]TONT20000SEPT!R34+[2]TONT20000OCT!R34+[2]TONT20000NOV!S34 -> 0
A35: AS201630 | B35: =VLOOKUP(A35,[2]LISTADHERENT!A$5:H$52,2,0) -> NKEPSEU HENANG RENE
A36: AS201631 | B36: =VLOOKUP(A36,[2]LISTADHERENT!A$5:H$52,2,0) -> NTEPDIE TUEMAC MZ | C36: =VLOOKUP(A36,[2]FONDSDECAISSE!A$5:C$52,3,0) -> 0 | D36: 0 | E36: =C36+D36+Q36 -> 15000 | F36: =INT([2]TONT20000DEC2015!E36+[2]TONT20000JANV!C36+[2]TONT20000FEV!C36+[2]TONT20000MARS!C36+[2]TONT20000AVRIL!C36+[2]TONT20000MAI!C36+[2]TONT20000JUIN!C36+[2]TONT20000JUIL!C36+[2]TONT20000AOUT!C36+[2]TONT20000SEPT!C36+[2]TONT20000OCT!C36+[2]TONT20000NOV!C36) -> 895 | G36: =[2]TONT20000NOV!E36 -> 15895.449 | H36: =D36+F36+Q36 -> 15895 | I36: =L36+M36+N36+O36 -> 28000 | J36: =H36-I36 -> -12105 | K36: 0 | O36: =48000-(R36+S36+T36) -> 28000 | P36: =[2]TONT20000DEC2015!H36+[2]TONT20000JANV!F36+[2]TONT20000FEV!F36+[2]TONT20000MARS!F36+[2]TONT20000AVRIL!F36+[2]TONT20000MAI!F36+[2]TONT20000JUIN!F36+[2]TONT20000JUIL!F36+[2]TONT20000AOUT!F36+[2]TONT20000SEPT!F36+[2]TONT20000OCT!F36+[2]TONT20000NOV!G36 -> 100000 | Q36: =[2]TONT20000DEC2015!I36+[2]TONT20000JANV!G36+[2]TONT20000FEV!G36+[2]TONT20000MARS!G36+[2]TONT20000AVRIL!G36+[2]TONT20000MAI!G36+[2]TONT20000JUIN!G36+[2]TONT20000JUIL!G36+[2]TONT20000AOUT!G36+[2]TONT20000SEPT!G36+[2]TONT20000OCT!G36+[2]TONT20000NOV!H36 -> 15000 | R36: =[2]TONT20000DEC2015!J36+[2]TONT20000JANV!H36+[2]TONT20000FEV!H36+[2]TONT20000MARS!H36+[2]TONT20000AVRIL!H36+[2]TONT20000MAI!H36+[2]TONT20000JUIN!H36+[2]TONT20000JUIL!H36+[2]TONT20000AOUT!H36+[2]TONT20000SEPT!H36+[2]TONT20000OCT!H36+[2]TONT20000NOV!I36 -> 2500 | S36: =[2]TONT20000DEC2015!K36+[2]TONT20000JANV!I36+[2]TONT20000FEV!I36+[2]TONT20000MARS!I36+[2]TONT20000AVRIL!I36+[2]TONT20000MAI!I36+[2]TONT20000JUIN!I36+[2]TONT20000JUIL!I36+[2]TONT20000AOUT!I36+[2]TONT20000SEPT!I36+[2]TONT20000OCT!I36+[2]TONT20000NOV!J36 -> 5000 | T36: =[2]TONT20000DEC2015!L36+[2]TONT20000JANV!J36+[2]TONT20000FEV!J36+[2]TONT20000MARS!J36+[2]TONT20000AVRIL!J36+[2]TONT20000MAI!J36+[2]TONT20000JUIN!J36+[2]TONT20000JUIL!J36+[2]TONT20000AOUT!J36+[2]TONT20000SEPT!J36+[2]TONT20000OCT!J36+[2]TONT20000NOV!K36 -> 12500 | U36: =[2]TONT20000DEC2015!M36+[2]TONT20000JANV!K36+[2]TONT20000FEV!K36+[2]TONT20000MARS!K36+[2]TONT20000AVRIL!K36+[2]TONT20000MAI!K36+[2]TONT20000JUIN!K36+[2]TONT20000JUIL!K36+[2]TONT20000AOUT!K36+[2]TONT20000SEPT!K36+[2]TONT20000OCT!K36+[2]TONT20000NOV!L36 -> 0 | V36: =[2]TONT20000DEC2015!N36+[2]TONT20000JANV!L36+[2]TONT20000FEV!L36+[2]TONT20000MARS!L36+[2]TONT20000AVRIL!L36+[2]TONT20000MAI!L36+[2]TONT20000JUIN!L36+[2]TONT20000JUIL!L36+[2]TONT20000AOUT!L36+[2]TONT20000SEPT!L36+[2]TONT20000OCT!L36+[2]TONT20000NOV!M36 -> 65000 | W36: =[2]TONT20000DEC2015!O36+[2]TONT20000JANV!M36+[2]TONT20000FEV!M36+[2]TONT20000MARS!M36+[2]TONT20000AVRIL!M36+[2]TONT20000MAI!M36+[2]TONT20000JUIN!M36+[2]TONT20000JUIL!M36+[2]TONT20000AOUT!M36+[2]TONT20000SEPT!M36+[2]TONT20000OCT!M36+[2]TONT20000NOV!N36 -> 0 | ... AB36: =[2]TONT20000DEC2015!T36+[2]TONT20000JANV!R36+[2]TONT20000FEV!R36+[2]TONT20000MARS!R36+[2]TONT20000AVRIL!R36+[2]TONT20000MAI!R36+[2]TONT20000JUIN!R36+[2]TONT20000JUIL!R36+[2]TONT20000AOUT!R36+[2]TONT20000SEPT!R36+[2]TONT20000OCT!R36+[2]TONT20000NOV!S36 -> 0
A37: AS201632 | B37: =VLOOKUP(A37,[2]LISTADHERENT!A$5:H$52,2,0) -> NTOMBOU ADOLPHE
A38: AS201633 | B38: =VLOOKUP(A38,[2]LISTADHERENT!A$5:H$52,2,0) -> PATEGO NJOSSU GUSTAVE | C38: =VLOOKUP(A38,[2]FONDSDECAISSE!A$5:C$52,3,0) -> 390000 | D38: 140 | E38: =C38+D38+Q38 -> 426140 | F38: =INT([2]TONT20000DEC2015!E38+[2]TONT20000JANV!C38+[2]TONT20000FEV!C38+[2]TONT20000MARS!C38+[2]TONT20000AVRIL!C38+[2]TONT20000MAI!C38+[2]TONT20000JUIN!C38+[2]TONT20000JUIL!C38+[2]TONT20000AOUT!C38+[2]TONT20000SEPT!C38+[2]TONT20000OCT!C38+[2]TONT20000NOV!C38) -> 47834 | G38: =[2]TONT20000NOV!E38 -> 473974.9 | H38: =D38+F38+Q38 -> 83974 | I38: =L38+M38+N38+O38 -> 80000 | J38: =H38-I38 -> 3974 | K38: 1500 | L38: 30000 | N38: 50000 | O38: =48000-(R38+S38+T38) -> 0 | P38: =[2]TONT20000DEC2015!H38+[2]TONT20000JANV!F38+[2]TONT20000FEV!F38+[2]TONT20000MARS!F38+[2]TONT20000AVRIL!F38+[2]TONT20000MAI!F38+[2]TONT20000JUIN!F38+[2]TONT20000JUIL!F38+[2]TONT20000AOUT!F38+[2]TONT20000SEPT!F38+[2]TONT20000OCT!F38+[2]TONT20000NOV!G38 -> 240000 | Q38: =[2]TONT20000DEC2015!I38+[2]TONT20000JANV!G38+[2]TONT20000FEV!G38+[2]TONT20000MARS!G38+[2]TONT20000AVRIL!G38+[2]TONT20000MAI!G38+[2]TONT20000JUIN!G38+[2]TONT20000JUIL!G38+[2]TONT20000AOUT!G38+[2]TONT20000SEPT!G38+[2]TONT20000OCT!G38+[2]TONT20000NOV!H38 -> 36000 | R38: =[2]TONT20000DEC2015!J38+[2]TONT20000JANV!H38+[2]TONT20000FEV!H38+[2]TONT20000MARS!H38+[2]TONT20000AVRIL!H38+[2]TONT20000MAI!H38+[2]TONT20000JUIN!H38+[2]TONT20000JUIL!H38+[2]TONT20000AOUT!H38+[2]TONT20000SEPT!H38+[2]TONT20000OCT!H38+[2]TONT20000NOV!I38 -> 6000 | S38: =[2]TONT20000DEC2015!K38+[2]TONT20000JANV!I38+[2]TONT20000FEV!I38+[2]TONT20000MARS!I38+[2]TONT20000AVRIL!I38+[2]TONT20000MAI!I38+[2]TONT20000JUIN!I38+[2]TONT20000JUIL!I38+[2]TONT20000AOUT!I38+[2]TONT20000SEPT!I38+[2]TONT20000OCT!I38+[2]TONT20000NOV!J38 -> 12000 | T38: =[2]TONT20000DEC2015!L38+[2]TONT20000JANV!J38+[2]TONT20000FEV!J38+[2]TONT20000MARS!J38+[2]TONT20000AVRIL!J38+[2]TONT20000MAI!J38+[2]TONT20000JUIN!J38+[2]TONT20000JUIL!J38+[2]TONT20000AOUT!J38+[2]TONT20000SEPT!J38+[2]TONT20000OCT!J38+[2]TONT20000NOV!K38 -> 30000 | U38: =[2]TONT20000DEC2015!M38+[2]TONT20000JANV!K38+[2]TONT20000FEV!K38+[2]TONT20000MARS!K38+[2]TONT20000AVRIL!K38+[2]TONT20000MAI!K38+[2]TONT20000JUIN!K38+[2]TONT20000JUIL!K38+[2]TONT20000AOUT!K38+[2]TONT20000SEPT!K38+[2]TONT20000OCT!K38+[2]TONT20000NOV!L38 -> 0 | V38: =[2]TONT20000DEC2015!N38+[2]TONT20000JANV!L38+[2]TONT20000FEV!L38+[2]TONT20000MARS!L38+[2]TONT20000AVRIL!L38+[2]TONT20000MAI!L38+[2]TONT20000JUIN!L38+[2]TONT20000JUIL!L38+[2]TONT20000AOUT!L38+[2]TONT20000SEPT!L38+[2]TONT20000OCT!L38+[2]TONT20000NOV!M38 -> 156000 | W38: =[2]TONT20000DEC2015!O38+[2]TONT20000JANV!M38+[2]TONT20000FEV!M38+[2]TONT20000MARS!M38+[2]TONT20000AVRIL!M38+[2]TONT20000MAI!M38+[2]TONT20000JUIN!M38+[2]TONT20000JUIL!M38+[2]TONT20000AOUT!M38+[2]TONT20000SEPT!M38+[2]TONT20000OCT!M38+[2]TONT20000NOV!N38 -> 0 | ... AB38: =[2]TONT20000DEC2015!T38+[2]TONT20000JANV!R38+[2]TONT20000FEV!R38+[2]TONT20000MARS!R38+[2]TONT20000AVRIL!R38+[2]TONT20000MAI!R38+[2]TONT20000JUIN!R38+[2]TONT20000JUIL!R38+[2]TONT20000AOUT!R38+[2]TONT20000SEPT!R38+[2]TONT20000OCT!R38+[2]TONT20000NOV!S38 -> 0
A39: AS201634 | B39: =VLOOKUP(A39,[2]LISTADHERENT!A$5:H$52,2,0) -> SEUNOU RICHELOT | C39: =VLOOKUP(A39,[2]FONDSDECAISSE!A$5:C$52,3,0) -> 390000 | D39: 2632 | E39: =C39+D39+Q39 -> 428632 | F39: =INT([2]TONT20000DEC2015!E39+[2]TONT20000JANV!C39+[2]TONT20000FEV!C39+[2]TONT20000MARS!C39+[2]TONT20000AVRIL!C39+[2]TONT20000MAI!C39+[2]TONT20000JUIN!C39+[2]TONT20000JUIL!C39+[2]TONT20000AOUT!C39+[2]TONT20000SEPT!C39+[2]TONT20000OCT!C39+[2]TONT20000NOV!C39) -> 48124 | G39: =[2]TONT20000NOV!E39 -> 476756.35 | H39: =D39+F39+Q39 -> 86756 | I39: =L39+M39+N39+O39 -> 80000 | J39: =H39-I39 -> 6756 | K39: 0 | L39: 30000 | N39: 50000 | O39: =48000-(R39+S39+T39) -> 0 | P39: =[2]TONT20000DEC2015!H39+[2]TONT20000JANV!F39+[2]TONT20000FEV!F39+[2]TONT20000MARS!F39+[2]TONT20000AVRIL!F39+[2]TONT20000MAI!F39+[2]TONT20000JUIN!F39+[2]TONT20000JUIL!F39+[2]TONT20000AOUT!F39+[2]TONT20000SEPT!F39+[2]TONT20000OCT!F39+[2]TONT20000NOV!G39 -> 240000 | Q39: =[2]TONT20000DEC2015!I39+[2]TONT20000JANV!G39+[2]TONT20000FEV!G39+[2]TONT20000MARS!G39+[2]TONT20000AVRIL!G39+[2]TONT20000MAI!G39+[2]TONT20000JUIN!G39+[2]TONT20000JUIL!G39+[2]TONT20000AOUT!G39+[2]TONT20000SEPT!G39+[2]TONT20000OCT!G39+[2]TONT20000NOV!H39 -> 36000 | R39: =[2]TONT20000DEC2015!J39+[2]TONT20000JANV!H39+[2]TONT20000FEV!H39+[2]TONT20000MARS!H39+[2]TONT20000AVRIL!H39+[2]TONT20000MAI!H39+[2]TONT20000JUIN!H39+[2]TONT20000JUIL!H39+[2]TONT20000AOUT!H39+[2]TONT20000SEPT!H39+[2]TONT20000OCT!H39+[2]TONT20000NOV!I39 -> 6000 | S39: =[2]TONT20000DEC2015!K39+[2]TONT20000JANV!I39+[2]TONT20000FEV!I39+[2]TONT20000MARS!I39+[2]TONT20000AVRIL!I39+[2]TONT20000MAI!I39+[2]TONT20000JUIN!I39+[2]TONT20000JUIL!I39+[2]TONT20000AOUT!I39+[2]TONT20000SEPT!I39+[2]TONT20000OCT!I39+[2]TONT20000NOV!J39 -> 12000 | T39: =[2]TONT20000DEC2015!L39+[2]TONT20000JANV!J39+[2]TONT20000FEV!J39+[2]TONT20000MARS!J39+[2]TONT20000AVRIL!J39+[2]TONT20000MAI!J39+[2]TONT20000JUIN!J39+[2]TONT20000JUIL!J39+[2]TONT20000AOUT!J39+[2]TONT20000SEPT!J39+[2]TONT20000OCT!J39+[2]TONT20000NOV!K39 -> 30000 | U39: =[2]TONT20000DEC2015!M39+[2]TONT20000JANV!K39+[2]TONT20000FEV!K39+[2]TONT20000MARS!K39+[2]TONT20000AVRIL!K39+[2]TONT20000MAI!K39+[2]TONT20000JUIN!K39+[2]TONT20000JUIL!K39+[2]TONT20000AOUT!K39+[2]TONT20000SEPT!K39+[2]TONT20000OCT!K39+[2]TONT20000NOV!L39 -> 0 | V39: =[2]TONT20000DEC2015!N39+[2]TONT20000JANV!L39+[2]TONT20000FEV!L39+[2]TONT20000MARS!L39+[2]TONT20000AVRIL!L39+[2]TONT20000MAI!L39+[2]TONT20000JUIN!L39+[2]TONT20000JUIL!L39+[2]TONT20000AOUT!L39+[2]TONT20000SEPT!L39+[2]TONT20000OCT!L39+[2]TONT20000NOV!M39 -> 156000 | W39: =[2]TONT20000DEC2015!O39+[2]TONT20000JANV!M39+[2]TONT20000FEV!M39+[2]TONT20000MARS!M39+[2]TONT20000AVRIL!M39+[2]TONT20000MAI!M39+[2]TONT20000JUIN!M39+[2]TONT20000JUIL!M39+[2]TONT20000AOUT!M39+[2]TONT20000SEPT!M39+[2]TONT20000OCT!M39+[2]TONT20000NOV!N39 -> 1000000 | ... AB39: =[2]TONT20000DEC2015!T39+[2]TONT20000JANV!R39+[2]TONT20000FEV!R39+[2]TONT20000MARS!R39+[2]TONT20000AVRIL!R39+[2]TONT20000MAI!R39+[2]TONT20000JUIN!R39+[2]TONT20000JUIL!R39+[2]TONT20000AOUT!R39+[2]TONT20000SEPT!R39+[2]TONT20000OCT!R39+[2]TONT20000NOV!S39 -> 0
A40: AS201635 | B40: =VLOOKUP(A40,[2]LISTADHERENT!A$5:H$52,2,0) -> SIME ABEL | C40: 390000 | D40: 0 | E40: =C40+D40+Q40 -> 398873 | F40: =INT([2]TONT20000DEC2015!E40+[2]TONT20000JANV!C40+[2]TONT20000FEV!C40+[2]TONT20000MARS!C40+[2]TONT20000AVRIL!C40+[2]TONT20000MAI!C40+[2]TONT20000JUIN!C40+[2]TONT20000JUIL!C40+[2]TONT20000AOUT!C40+[2]TONT20000SEPT!C40+[2]TONT20000OCT!C40+[2]TONT20000NOV!C40) -> 15621 | G40: =[2]TONT20000NOV!E40 -> 441621.35 | H40: =D40+F40+Q40 -> 24494 | I40: =L40+M40+N40+O40 -> 24006 | J40: =H40-I40 -> 488 | K40: 0 | N40: =50000-25994 -> 24006 | O40: =48000-(R40+S40+T40) -> 0 | P40: =[2]TONT20000DEC2015!H40+[2]TONT20000JANV!F40+[2]TONT20000FEV!F40+[2]TONT20000MARS!F40+[2]TONT20000AVRIL!F40+[2]TONT20000MAI!F40+[2]TONT20000JUIN!F40+[2]TONT20000JUIL!F40+[2]TONT20000AOUT!F40+[2]TONT20000SEPT!F40+[2]TONT20000OCT!F40+[2]TONT20000NOV!G40 -> 240000 | Q40: =[2]TONT20000DEC2015!I40+[2]TONT20000JANV!G40+[2]TONT20000FEV!G40+[2]TONT20000MARS!G40+[2]TONT20000AVRIL!G40+[2]TONT20000MAI!G40+[2]TONT20000JUIN!G40+[2]TONT20000JUIL!G40+[2]TONT20000AOUT!G40+[2]TONT20000SEPT!G40+[2]TONT20000OCT!G40+[2]TONT20000NOV!H40-27127 -> 8873 | R40: =[2]TONT20000DEC2015!J40+[2]TONT20000JANV!H40+[2]TONT20000FEV!H40+[2]TONT20000MARS!H40+[2]TONT20000AVRIL!H40+[2]TONT20000MAI!H40+[2]TONT20000JUIN!H40+[2]TONT20000JUIL!H40+[2]TONT20000AOUT!H40+[2]TONT20000SEPT!H40+[2]TONT20000OCT!H40+[2]TONT20000NOV!I40 -> 6000 | S40: =[2]TONT20000DEC2015!K40+[2]TONT20000JANV!I40+[2]TONT20000FEV!I40+[2]TONT20000MARS!I40+[2]TONT20000AVRIL!I40+[2]TONT20000MAI!I40+[2]TONT20000JUIN!I40+[2]TONT20000JUIL!I40+[2]TONT20000AOUT!I40+[2]TONT20000SEPT!I40+[2]TONT20000OCT!I40+[2]TONT20000NOV!J40 -> 12000 | T40: =[2]TONT20000DEC2015!L40+[2]TONT20000JANV!J40+[2]TONT20000FEV!J40+[2]TONT20000MARS!J40+[2]TONT20000AVRIL!J40+[2]TONT20000MAI!J40+[2]TONT20000JUIN!J40+[2]TONT20000JUIL!J40+[2]TONT20000AOUT!J40+[2]TONT20000SEPT!J40+[2]TONT20000OCT!J40+[2]TONT20000NOV!K40 -> 30000 | U40: =[2]TONT20000DEC2015!M40+[2]TONT20000JANV!K40+[2]TONT20000FEV!K40+[2]TONT20000MARS!K40+[2]TONT20000AVRIL!K40+[2]TONT20000MAI!K40+[2]TONT20000JUIN!K40+[2]TONT20000JUIL!K40+[2]TONT20000AOUT!K40+[2]TONT20000SEPT!K40+[2]TONT20000OCT!K40+[2]TONT20000NOV!L40 -> 0 | V40: =[2]TONT20000DEC2015!N40+[2]TONT20000JANV!L40+[2]TONT20000FEV!L40+[2]TONT20000MARS!L40+[2]TONT20000AVRIL!L40+[2]TONT20000MAI!L40+[2]TONT20000JUIN!L40+[2]TONT20000JUIL!L40+[2]TONT20000AOUT!L40+[2]TONT20000SEPT!L40+[2]TONT20000OCT!L40+[2]TONT20000NOV!M40 -> 156000 | W40: =[2]TONT20000DEC2015!O40+[2]TONT20000JANV!M40+[2]TONT20000FEV!M40+[2]TONT20000MARS!M40+[2]TONT20000AVRIL!M40+[2]TONT20000MAI!M40+[2]TONT20000JUIN!M40+[2]TONT20000JUIL!M40+[2]TONT20000AOUT!M40+[2]TONT20000SEPT!M40+[2]TONT20000OCT!M40+[2]TONT20000NOV!N40 -> 0 | X40: =[2]TONT20000DEC2015!P40+[2]TONT20000JANV!N40+[2]TONT20000FEV!N40+[2]TONT20000MARS!N40+[2]TONT20000AVRIL!N40+[2]TONT20000MAI!N40+[2]TONT20000JUIN!N40+[2]TONT20000JUIL!N40+[2]TONT20000AOUT!N40+[2]TONT20000SEPT!N40+[2]TONT20000OCT!N40+[2]TONT20000NOV!O40 -> 0 | Y40: =[2]TONT20000DEC2015!Q40+[2]TONT20000JANV!O40+[2]TONT20000FEV!O40+[2]TONT20000MARS!O40+[2]TONT20000AVRIL!O40+[2]TONT20000MAI!O40+[2]TONT20000JUIN!O40+[2]TONT20000JUIL!O40+[2]TONT20000AOUT!O40+[2]TONT20000SEPT!O40+[2]TONT20000OCT!O40+[2]TONT20000NOV!P40 -> 0 | ... AB40: =[2]TONT20000DEC2015!T40+[2]TONT20000JANV!R40+[2]TONT20000FEV!R40+[2]TONT20000MARS!R40+[2]TONT20000AVRIL!R40+[2]TONT20000MAI!R40+[2]TONT20000JUIN!R40+[2]TONT20000JUIL!R40+[2]TONT20000AOUT!R40+[2]TONT20000SEPT!R40+[2]TONT20000OCT!R40+[2]TONT20000NOV!S40 -> 0
A41: AS201636 | B41: =VLOOKUP(A41,[2]LISTADHERENT!A$5:H$52,2,0) -> SIME FONGANG ERIC | C41: =VLOOKUP(A41,[2]FONDSDECAISSE!A$5:C$52,3,0) -> 390000 | D41: 982 | E41: =C41+D41+Q41 -> 426982 | F41: =INT([2]TONT20000DEC2015!E41+[2]TONT20000JANV!C41+[2]TONT20000FEV!C41+[2]TONT20000MARS!C41+[2]TONT20000AVRIL!C41+[2]TONT20000MAI!C41+[2]TONT20000JUIN!C41+[2]TONT20000JUIL!C41+[2]TONT20000AOUT!C41+[2]TONT20000SEPT!C41+[2]TONT20000OCT!C41+[2]TONT20000NOV!C41) -> 47932 | G41: =[2]TONT20000NOV!E41 -> 474914.7 | H41: =D41+F41+Q41 -> 84914 | I41: =L41+M41+N41+O41 -> 80000 | J41: =H41-I41 -> 4914 | K41: 0 | L41: 30000 | N41: 50000 | O41: =48000-(R41+S41+T41) -> 0 | P41: =[2]TONT20000DEC2015!H41+[2]TONT20000JANV!F41+[2]TONT20000FEV!F41+[2]TONT20000MARS!F41+[2]TONT20000AVRIL!F41+[2]TONT20000MAI!F41+[2]TONT20000JUIN!F41+[2]TONT20000JUIL!F41+[2]TONT20000AOUT!F41+[2]TONT20000SEPT!F41+[2]TONT20000OCT!F41+[2]TONT20000NOV!G41 -> 240000 | Q41: =[2]TONT20000DEC2015!I41+[2]TONT20000JANV!G41+[2]TONT20000FEV!G41+[2]TONT20000MARS!G41+[2]TONT20000AVRIL!G41+[2]TONT20000MAI!G41+[2]TONT20000JUIN!G41+[2]TONT20000JUIL!G41+[2]TONT20000AOUT!G41+[2]TONT20000SEPT!G41+[2]TONT20000OCT!G41+[2]TONT20000NOV!H41 -> 36000 | R41: =[2]TONT20000DEC2015!J41+[2]TONT20000JANV!H41+[2]TONT20000FEV!H41+[2]TONT20000MARS!H41+[2]TONT20000AVRIL!H41+[2]TONT20000MAI!H41+[2]TONT20000JUIN!H41+[2]TONT20000JUIL!H41+[2]TONT20000AOUT!H41+[2]TONT20000SEPT!H41+[2]TONT20000OCT!H41+[2]TONT20000NOV!I41 -> 6000 | S41: =[2]TONT20000DEC2015!K41+[2]TONT20000JANV!I41+[2]TONT20000FEV!I41+[2]TONT20000MARS!I41+[2]TONT20000AVRIL!I41+[2]TONT20000MAI!I41+[2]TONT20000JUIN!I41+[2]TONT20000JUIL!I41+[2]TONT20000AOUT!I41+[2]TONT20000SEPT!I41+[2]TONT20000OCT!I41+[2]TONT20000NOV!J41 -> 12000 | T41: =[2]TONT20000DEC2015!L41+[2]TONT20000JANV!J41+[2]TONT20000FEV!J41+[2]TONT20000MARS!J41+[2]TONT20000AVRIL!J41+[2]TONT20000MAI!J41+[2]TONT20000JUIN!J41+[2]TONT20000JUIL!J41+[2]TONT20000AOUT!J41+[2]TONT20000SEPT!J41+[2]TONT20000OCT!J41+[2]TONT20000NOV!K41 -> 30000 | U41: =[2]TONT20000DEC2015!M41+[2]TONT20000JANV!K41+[2]TONT20000FEV!K41+[2]TONT20000MARS!K41+[2]TONT20000AVRIL!K41+[2]TONT20000MAI!K41+[2]TONT20000JUIN!K41+[2]TONT20000JUIL!K41+[2]TONT20000AOUT!K41+[2]TONT20000SEPT!K41+[2]TONT20000OCT!K41+[2]TONT20000NOV!L41 -> 0 | V41: =[2]TONT20000DEC2015!N41+[2]TONT20000JANV!L41+[2]TONT20000FEV!L41+[2]TONT20000MARS!L41+[2]TONT20000AVRIL!L41+[2]TONT20000MAI!L41+[2]TONT20000JUIN!L41+[2]TONT20000JUIL!L41+[2]TONT20000AOUT!L41+[2]TONT20000SEPT!L41+[2]TONT20000OCT!L41+[2]TONT20000NOV!M41 -> 156000 | W41: =[2]TONT20000DEC2015!O41+[2]TONT20000JANV!M41+[2]TONT20000FEV!M41+[2]TONT20000MARS!M41+[2]TONT20000AVRIL!M41+[2]TONT20000MAI!M41+[2]TONT20000JUIN!M41+[2]TONT20000JUIL!M41+[2]TONT20000AOUT!M41+[2]TONT20000SEPT!M41+[2]TONT20000OCT!M41+[2]TONT20000NOV!N41 -> 1000000 | ... AB41: =[2]TONT20000DEC2015!T41+[2]TONT20000JANV!R41+[2]TONT20000FEV!R41+[2]TONT20000MARS!R41+[2]TONT20000AVRIL!R41+[2]TONT20000MAI!R41+[2]TONT20000JUIN!R41+[2]TONT20000JUIL!R41+[2]TONT20000AOUT!R41+[2]TONT20000SEPT!R41+[2]TONT20000OCT!R41+[2]TONT20000NOV!S41 -> 0
A42: AS201637 | B42: =VLOOKUP(A42,[2]LISTADHERENT!A$5:H$52,2,0) -> SIME MATHIEU | C42: =VLOOKUP(A42,[2]FONDSDECAISSE!A$5:C$52,3,0) -> 390000 | D42: 636 | E42: =C42+D42+Q42 -> 426636 | F42: =INT([2]TONT20000DEC2015!E42+[2]TONT20000JANV!C42+[2]TONT20000FEV!C42+[2]TONT20000MARS!C42+[2]TONT20000AVRIL!C42+[2]TONT20000MAI!C42+[2]TONT20000JUIN!C42+[2]TONT20000JUIL!C42+[2]TONT20000AOUT!C42+[2]TONT20000SEPT!C42+[2]TONT20000OCT!C42+[2]TONT20000NOV!C42) -> 47892 | G42: =[2]TONT20000NOV!E42 -> 474528.51 | H42: =D42+F42+Q42 -> 84528 | I42: =L42+M42+N42+O42 -> 80000 | J42: =H42-I42 -> 4528 | K42: 0 | L42: 30000 | N42: 50000 | O42: =48000-(R42+S42+T42) -> 0 | P42: =[2]TONT20000DEC2015!H42+[2]TONT20000JANV!F42+[2]TONT20000FEV!F42+[2]TONT20000MARS!F42+[2]TONT20000AVRIL!F42+[2]TONT20000MAI!F42+[2]TONT20000JUIN!F42+[2]TONT20000JUIL!F42+[2]TONT20000AOUT!F42+[2]TONT20000SEPT!F42+[2]TONT20000OCT!F42+[2]TONT20000NOV!G42 -> 240000 | Q42: =[2]TONT20000DEC2015!I42+[2]TONT20000JANV!G42+[2]TONT20000FEV!G42+[2]TONT20000MARS!G42+[2]TONT20000AVRIL!G42+[2]TONT20000MAI!G42+[2]TONT20000JUIN!G42+[2]TONT20000JUIL!G42+[2]TONT20000AOUT!G42+[2]TONT20000SEPT!G42+[2]TONT20000OCT!G42+[2]TONT20000NOV!H42 -> 36000 | R42: =[2]TONT20000DEC2015!J42+[2]TONT20000JANV!H42+[2]TONT20000FEV!H42+[2]TONT20000MARS!H42+[2]TONT20000AVRIL!H42+[2]TONT20000MAI!H42+[2]TONT20000JUIN!H42+[2]TONT20000JUIL!H42+[2]TONT20000AOUT!H42+[2]TONT20000SEPT!H42+[2]TONT20000OCT!H42+[2]TONT20000NOV!I42 -> 6000 | S42: =[2]TONT20000DEC2015!K42+[2]TONT20000JANV!I42+[2]TONT20000FEV!I42+[2]TONT20000MARS!I42+[2]TONT20000AVRIL!I42+[2]TONT20000MAI!I42+[2]TONT20000JUIN!I42+[2]TONT20000JUIL!I42+[2]TONT20000AOUT!I42+[2]TONT20000SEPT!I42+[2]TONT20000OCT!I42+[2]TONT20000NOV!J42 -> 12000 | T42: =[2]TONT20000DEC2015!L42+[2]TONT20000JANV!J42+[2]TONT20000FEV!J42+[2]TONT20000MARS!J42+[2]TONT20000AVRIL!J42+[2]TONT20000MAI!J42+[2]TONT20000JUIN!J42+[2]TONT20000JUIL!J42+[2]TONT20000AOUT!J42+[2]TONT20000SEPT!J42+[2]TONT20000OCT!J42+[2]TONT20000NOV!K42 -> 30000 | U42: =[2]TONT20000DEC2015!M42+[2]TONT20000JANV!K42+[2]TONT20000FEV!K42+[2]TONT20000MARS!K42+[2]TONT20000AVRIL!K42+[2]TONT20000MAI!K42+[2]TONT20000JUIN!K42+[2]TONT20000JUIL!K42+[2]TONT20000AOUT!K42+[2]TONT20000SEPT!K42+[2]TONT20000OCT!K42+[2]TONT20000NOV!L42 -> 0 | V42: =[2]TONT20000DEC2015!N42+[2]TONT20000JANV!L42+[2]TONT20000FEV!L42+[2]TONT20000MARS!L42+[2]TONT20000AVRIL!L42+[2]TONT20000MAI!L42+[2]TONT20000JUIN!L42+[2]TONT20000JUIL!L42+[2]TONT20000AOUT!L42+[2]TONT20000SEPT!L42+[2]TONT20000OCT!L42+[2]TONT20000NOV!M42 -> 156000 | W42: =[2]TONT20000DEC2015!O42+[2]TONT20000JANV!M42+[2]TONT20000FEV!M42+[2]TONT20000MARS!M42+[2]TONT20000AVRIL!M42+[2]TONT20000MAI!M42+[2]TONT20000JUIN!M42+[2]TONT20000JUIL!M42+[2]TONT20000AOUT!M42+[2]TONT20000SEPT!M42+[2]TONT20000OCT!M42+[2]TONT20000NOV!N42 -> 800000 | ... AB42: =[2]TONT20000DEC2015!T42+[2]TONT20000JANV!R42+[2]TONT20000FEV!R42+[2]TONT20000MARS!R42+[2]TONT20000AVRIL!R42+[2]TONT20000MAI!R42+[2]TONT20000JUIN!R42+[2]TONT20000JUIL!R42+[2]TONT20000AOUT!R42+[2]TONT20000SEPT!R42+[2]TONT20000OCT!R42+[2]TONT20000NOV!S42 -> 0
A43: AS201638 | B43: =VLOOKUP(A43,[2]LISTADHERENT!A$5:H$52,2,0) -> SIME PIERRE | C43: =VLOOKUP(A43,[2]FONDSDECAISSE!A$5:C$52,3,0) -> 390000 | D43: 146079 | E43: =C43+D43+Q43 -> 1147306 | F43: =INT([2]TONT20000DEC2015!E43+[2]TONT20000JANV!C43+[2]TONT20000FEV!C43+[2]TONT20000MARS!C43+[2]TONT20000AVRIL!C43+[2]TONT20000MAI!C43+[2]TONT20000JUIN!C43+[2]TONT20000JUIL!C43+[2]TONT20000AOUT!C43+[2]TONT20000SEPT!C43+[2]TONT20000OCT!C43+[2]TONT20000NOV!C43) -> 121669 | G43: =[2]TONT20000NOV!E43 -> 1268975.9 | H43: =D43+F43+Q43 -> 878975 | I43: =L43+M43+N43+O43 -> 80000 | J43: =H43-I43 -> 798975 | K43: 693000 | L43: 30000 | N43: 50000 | O43: =48000-(R43+S43+T43) -> 0 | P43: =[2]TONT20000DEC2015!H43+[2]TONT20000JANV!F43+[2]TONT20000FEV!F43+[2]TONT20000MARS!F43+[2]TONT20000AVRIL!F43+[2]TONT20000MAI!F43+[2]TONT20000JUIN!F43+[2]TONT20000JUIL!F43+[2]TONT20000AOUT!F43+[2]TONT20000SEPT!F43+[2]TONT20000OCT!F43+[2]TONT20000NOV!G43 -> 1130000 | Q43: =[2]TONT20000DEC2015!I43+[2]TONT20000JANV!G43+[2]TONT20000FEV!G43+[2]TONT20000MARS!G43+[2]TONT20000AVRIL!G43+[2]TONT20000MAI!G43+[2]TONT20000JUIN!G43+[2]TONT20000JUIL!G43+[2]TONT20000AOUT!G43+[2]TONT20000SEPT!G43+[2]TONT20000OCT!G43+[2]TONT20000NOV!H43-854773+550000 -> 611227 | R43: =[2]TONT20000DEC2015!J43+[2]TONT20000JANV!H43+[2]TONT20000FEV!H43+[2]TONT20000MARS!H43+[2]TONT20000AVRIL!H43+[2]TONT20000MAI!H43+[2]TONT20000JUIN!H43+[2]TONT20000JUIL!H43+[2]TONT20000AOUT!H43+[2]TONT20000SEPT!H43+[2]TONT20000OCT!H43+[2]TONT20000NOV!I43 -> 6000 | S43: =[2]TONT20000DEC2015!K43+[2]TONT20000JANV!I43+[2]TONT20000FEV!I43+[2]TONT20000MARS!I43+[2]TONT20000AVRIL!I43+[2]TONT20000MAI!I43+[2]TONT20000JUIN!I43+[2]TONT20000JUIL!I43+[2]TONT20000AOUT!I43+[2]TONT20000SEPT!I43+[2]TONT20000OCT!I43+[2]TONT20000NOV!J43 -> 12000 | T43: =[2]TONT20000DEC2015!L43+[2]TONT20000JANV!J43+[2]TONT20000FEV!J43+[2]TONT20000MARS!J43+[2]TONT20000AVRIL!J43+[2]TONT20000MAI!J43+[2]TONT20000JUIN!J43+[2]TONT20000JUIL!J43+[2]TONT20000AOUT!J43+[2]TONT20000SEPT!J43+[2]TONT20000OCT!J43+[2]TONT20000NOV!K43 -> 30000 | U43: =[2]TONT20000DEC2015!M43+[2]TONT20000JANV!K43+[2]TONT20000FEV!K43+[2]TONT20000MARS!K43+[2]TONT20000AVRIL!K43+[2]TONT20000MAI!K43+[2]TONT20000JUIN!K43+[2]TONT20000JUIL!K43+[2]TONT20000AOUT!K43+[2]TONT20000SEPT!K43+[2]TONT20000OCT!K43+[2]TONT20000NOV!L43 -> 10000 | V43: =[2]TONT20000DEC2015!N43+[2]TONT20000JANV!L43+[2]TONT20000FEV!L43+[2]TONT20000MARS!L43+[2]TONT20000AVRIL!L43+[2]TONT20000MAI!L43+[2]TONT20000JUIN!L43+[2]TONT20000JUIL!L43+[2]TONT20000AOUT!L43+[2]TONT20000SEPT!L43+[2]TONT20000OCT!L43+[2]TONT20000NOV!M43 -> 156000 | W43: =[2]TONT20000DEC2015!O43+[2]TONT20000JANV!M43+[2]TONT20000FEV!M43+[2]TONT20000MARS!M43+[2]TONT20000AVRIL!M43+[2]TONT20000MAI!M43+[2]TONT20000JUIN!M43+[2]TONT20000JUIL!M43+[2]TONT20000AOUT!M43+[2]TONT20000SEPT!M43+[2]TONT20000OCT!M43+[2]TONT20000NOV!N43 -> 1110000 | X43: =[2]TONT20000DEC2015!P43+[2]TONT20000JANV!N43+[2]TONT20000FEV!N43+[2]TONT20000MARS!N43+[2]TONT20000AVRIL!N43+[2]TONT20000MAI!N43+[2]TONT20000JUIN!N43+[2]TONT20000JUIL!N43+[2]TONT20000AOUT!N43+[2]TONT20000SEPT!N43+[2]TONT20000OCT!N43+[2]TONT20000NOV!O43 -> 84600 | Y43: =[2]TONT20000DEC2015!Q43+[2]TONT20000JANV!O43+[2]TONT20000FEV!O43+[2]TONT20000MARS!O43+[2]TONT20000AVRIL!O43+[2]TONT20000MAI!O43+[2]TONT20000JUIN!O43+[2]TONT20000JUIL!O43+[2]TONT20000AOUT!O43+[2]TONT20000SEPT!O43+[2]TONT20000OCT!O43+[2]TONT20000NOV!P43 -> 540000 | ... AB43: =[2]TONT20000DEC2015!T43+[2]TONT20000JANV!R43+[2]TONT20000FEV!R43+[2]TONT20000MARS!R43+[2]TONT20000AVRIL!R43+[2]TONT20000MAI!R43+[2]TONT20000JUIN!R43+[2]TONT20000JUIL!R43+[2]TONT20000AOUT!R43+[2]TONT20000SEPT!R43+[2]TONT20000OCT!R43+[2]TONT20000NOV!S43 -> 0
A44: AS201639 | B44: =VLOOKUP(A44,[2]LISTADHERENT!A$5:H$52,2,0) -> TAGNE NANGUEN MARTIN | C44: 390000 | D44: 0 | E44: =C44+D44+Q44 -> 426000 | F44: =INT([2]TONT20000DEC2015!E44+[2]TONT20000JANV!C44+[2]TONT20000FEV!C44+[2]TONT20000MARS!C44+[2]TONT20000AVRIL!C44+[2]TONT20000MAI!C44+[2]TONT20000JUIN!C44+[2]TONT20000JUIL!C44+[2]TONT20000AOUT!C44+[2]TONT20000SEPT!C44+[2]TONT20000OCT!C44+[2]TONT20000NOV!C44) -> 15621 | G44: =[2]TONT20000NOV!E44 -> 441621.35 | H44: =D44+F44+Q44 -> 51621 | I44: =L44+M44+N44+O44 -> 50000 | J44: =H44-I44 -> 1621 | K44: 0 | N44: 50000 | O44: =48000-(R44+S44+T44) -> 0 | P44: =[2]TONT20000DEC2015!H44+[2]TONT20000JANV!F44+[2]TONT20000FEV!F44+[2]TONT20000MARS!F44+[2]TONT20000AVRIL!F44+[2]TONT20000MAI!F44+[2]TONT20000JUIN!F44+[2]TONT20000JUIL!F44+[2]TONT20000AOUT!F44+[2]TONT20000SEPT!F44+[2]TONT20000OCT!F44+[2]TONT20000NOV!G44 -> 240000 | Q44: =[2]TONT20000DEC2015!I44+[2]TONT20000JANV!G44+[2]TONT20000FEV!G44+[2]TONT20000MARS!G44+[2]TONT20000AVRIL!G44+[2]TONT20000MAI!G44+[2]TONT20000JUIN!G44+[2]TONT20000JUIL!G44+[2]TONT20000AOUT!G44+[2]TONT20000SEPT!G44+[2]TONT20000OCT!G44+[2]TONT20000NOV!H44 -> 36000 | R44: =[2]TONT20000DEC2015!J44+[2]TONT20000JANV!H44+[2]TONT20000FEV!H44+[2]TONT20000MARS!H44+[2]TONT20000AVRIL!H44+[2]TONT20000MAI!H44+[2]TONT20000JUIN!H44+[2]TONT20000JUIL!H44+[2]TONT20000AOUT!H44+[2]TONT20000SEPT!H44+[2]TONT20000OCT!H44+[2]TONT20000NOV!I44 -> 6000 | S44: =[2]TONT20000DEC2015!K44+[2]TONT20000JANV!I44+[2]TONT20000FEV!I44+[2]TONT20000MARS!I44+[2]TONT20000AVRIL!I44+[2]TONT20000MAI!I44+[2]TONT20000JUIN!I44+[2]TONT20000JUIL!I44+[2]TONT20000AOUT!I44+[2]TONT20000SEPT!I44+[2]TONT20000OCT!I44+[2]TONT20000NOV!J44 -> 12000 | T44: =[2]TONT20000DEC2015!L44+[2]TONT20000JANV!J44+[2]TONT20000FEV!J44+[2]TONT20000MARS!J44+[2]TONT20000AVRIL!J44+[2]TONT20000MAI!J44+[2]TONT20000JUIN!J44+[2]TONT20000JUIL!J44+[2]TONT20000AOUT!J44+[2]TONT20000SEPT!J44+[2]TONT20000OCT!J44+[2]TONT20000NOV!K44 -> 30000 | U44: =[2]TONT20000DEC2015!M44+[2]TONT20000JANV!K44+[2]TONT20000FEV!K44+[2]TONT20000MARS!K44+[2]TONT20000AVRIL!K44+[2]TONT20000MAI!K44+[2]TONT20000JUIN!K44+[2]TONT20000JUIL!K44+[2]TONT20000AOUT!K44+[2]TONT20000SEPT!K44+[2]TONT20000OCT!K44+[2]TONT20000NOV!L44 -> 0 | V44: =[2]TONT20000DEC2015!N44+[2]TONT20000JANV!L44+[2]TONT20000FEV!L44+[2]TONT20000MARS!L44+[2]TONT20000AVRIL!L44+[2]TONT20000MAI!L44+[2]TONT20000JUIN!L44+[2]TONT20000JUIL!L44+[2]TONT20000AOUT!L44+[2]TONT20000SEPT!L44+[2]TONT20000OCT!L44+[2]TONT20000NOV!M44 -> 156000 | W44: =[2]TONT20000DEC2015!O44+[2]TONT20000JANV!M44+[2]TONT20000FEV!M44+[2]TONT20000MARS!M44+[2]TONT20000AVRIL!M44+[2]TONT20000MAI!M44+[2]TONT20000JUIN!M44+[2]TONT20000JUIL!M44+[2]TONT20000AOUT!M44+[2]TONT20000SEPT!M44+[2]TONT20000OCT!M44+[2]TONT20000NOV!N44 -> 0 | ... AB44: =[2]TONT20000DEC2015!T44+[2]TONT20000JANV!R44+[2]TONT20000FEV!R44+[2]TONT20000MARS!R44+[2]TONT20000AVRIL!R44+[2]TONT20000MAI!R44+[2]TONT20000JUIN!R44+[2]TONT20000JUIL!R44+[2]TONT20000AOUT!R44+[2]TONT20000SEPT!R44+[2]TONT20000OCT!R44+[2]TONT20000NOV!S44 -> 0
A45: AS201640 | B45: =VLOOKUP(A45,[2]LISTADHERENT!A$5:H$52,2,0) -> TCHOUAMOU JEAN PAUL | C45: =VLOOKUP(A45,[2]FONDSDECAISSE!A$5:C$52,3,0) -> 0 | D45: 0 | E45: =C45+D45+Q45 -> 12323 | F45: =INT([2]TONT20000DEC2015!E45+[2]TONT20000JANV!C45+[2]TONT20000FEV!C45+[2]TONT20000MARS!C45+[2]TONT20000AVRIL!C45+[2]TONT20000MAI!C45+[2]TONT20000JUIN!C45+[2]TONT20000JUIL!C45+[2]TONT20000AOUT!C45+[2]TONT20000SEPT!C45+[2]TONT20000OCT!C45+[2]TONT20000NOV!C45) -> 2520 | G45: =[2]TONT20000NOV!E45 -> 38520.175 | H45: =D45+F45+Q45 -> 14843 | I45: =L45+M45+N45+O45 -> 14737 | J45: =H45-I45 -> 106 | K45: 0 | N45: =50000-35263 -> 14737 | O45: =48000-(R45+S45+T45) -> 0 | P45: =[2]TONT20000DEC2015!H45+[2]TONT20000JANV!F45+[2]TONT20000FEV!F45+[2]TONT20000MARS!F45+[2]TONT20000AVRIL!F45+[2]TONT20000MAI!F45+[2]TONT20000JUIN!F45+[2]TONT20000JUIL!F45+[2]TONT20000AOUT!F45+[2]TONT20000SEPT!F45+[2]TONT20000OCT!F45+[2]TONT20000NOV!G45 -> 290000 | Q45: =[2]TONT20000DEC2015!I45+[2]TONT20000JANV!G45+[2]TONT20000FEV!G45+[2]TONT20000MARS!G45+[2]TONT20000AVRIL!G45+[2]TONT20000MAI!G45+[2]TONT20000JUIN!G45+[2]TONT20000JUIL!G45+[2]TONT20000AOUT!G45+[2]TONT20000SEPT!G45+[2]TONT20000OCT!G45+[2]TONT20000NOV!H45-23677 -> 12323 | R45: =[2]TONT20000DEC2015!J45+[2]TONT20000JANV!H45+[2]TONT20000FEV!H45+[2]TONT20000MARS!H45+[2]TONT20000AVRIL!H45+[2]TONT20000MAI!H45+[2]TONT20000JUIN!H45+[2]TONT20000JUIL!H45+[2]TONT20000AOUT!H45+[2]TONT20000SEPT!H45+[2]TONT20000OCT!H45+[2]TONT20000NOV!I45 -> 6000 | S45: =[2]TONT20000DEC2015!K45+[2]TONT20000JANV!I45+[2]TONT20000FEV!I45+[2]TONT20000MARS!I45+[2]TONT20000AVRIL!I45+[2]TONT20000MAI!I45+[2]TONT20000JUIN!I45+[2]TONT20000JUIL!I45+[2]TONT20000AOUT!I45+[2]TONT20000SEPT!I45+[2]TONT20000OCT!I45+[2]TONT20000NOV!J45 -> 12000 | T45: =[2]TONT20000DEC2015!L45+[2]TONT20000JANV!J45+[2]TONT20000FEV!J45+[2]TONT20000MARS!J45+[2]TONT20000AVRIL!J45+[2]TONT20000MAI!J45+[2]TONT20000JUIN!J45+[2]TONT20000JUIL!J45+[2]TONT20000AOUT!J45+[2]TONT20000SEPT!J45+[2]TONT20000OCT!J45+[2]TONT20000NOV!K45 -> 30000 | U45: =[2]TONT20000DEC2015!M45+[2]TONT20000JANV!K45+[2]TONT20000FEV!K45+[2]TONT20000MARS!K45+[2]TONT20000AVRIL!K45+[2]TONT20000MAI!K45+[2]TONT20000JUIN!K45+[2]TONT20000JUIL!K45+[2]TONT20000AOUT!K45+[2]TONT20000SEPT!K45+[2]TONT20000OCT!K45+[2]TONT20000NOV!L45 -> 50000 | V45: =[2]TONT20000DEC2015!N45+[2]TONT20000JANV!L45+[2]TONT20000FEV!L45+[2]TONT20000MARS!L45+[2]TONT20000AVRIL!L45+[2]TONT20000MAI!L45+[2]TONT20000JUIN!L45+[2]TONT20000JUIL!L45+[2]TONT20000AOUT!L45+[2]TONT20000SEPT!L45+[2]TONT20000OCT!L45+[2]TONT20000NOV!M45 -> 156000 | W45: =[2]TONT20000DEC2015!O45+[2]TONT20000JANV!M45+[2]TONT20000FEV!M45+[2]TONT20000MARS!M45+[2]TONT20000AVRIL!M45+[2]TONT20000MAI!M45+[2]TONT20000JUIN!M45+[2]TONT20000JUIL!M45+[2]TONT20000AOUT!M45+[2]TONT20000SEPT!M45+[2]TONT20000OCT!M45+[2]TONT20000NOV!N45 -> 0 | X45: =[2]TONT20000DEC2015!P45+[2]TONT20000JANV!N45+[2]TONT20000FEV!N45+[2]TONT20000MARS!N45+[2]TONT20000AVRIL!N45+[2]TONT20000MAI!N45+[2]TONT20000JUIN!N45+[2]TONT20000JUIL!N45+[2]TONT20000AOUT!N45+[2]TONT20000SEPT!N45+[2]TONT20000OCT!N45+[2]TONT20000NOV!O45 -> 0 | Y45: =[2]TONT20000DEC2015!Q45+[2]TONT20000JANV!O45+[2]TONT20000FEV!O45+[2]TONT20000MARS!O45+[2]TONT20000AVRIL!O45+[2]TONT20000MAI!O45+[2]TONT20000JUIN!O45+[2]TONT20000JUIL!O45+[2]TONT20000AOUT!O45+[2]TONT20000SEPT!O45+[2]TONT20000OCT!O45+[2]TONT20000NOV!P45 -> 0 | ... AB45: =[2]TONT20000DEC2015!T45+[2]TONT20000JANV!R45+[2]TONT20000FEV!R45+[2]TONT20000MARS!R45+[2]TONT20000AVRIL!R45+[2]TONT20000MAI!R45+[2]TONT20000JUIN!R45+[2]TONT20000JUIL!R45+[2]TONT20000AOUT!R45+[2]TONT20000SEPT!R45+[2]TONT20000OCT!R45+[2]TONT20000NOV!S45 -> 0
A46: AS201641 | B46: =VLOOKUP(A46,[2]LISTADHERENT!A$5:H$52,2,0) -> TCHOUAMOU MATHIEU | C46: =VLOOKUP(A46,[2]FONDSDECAISSE!A$5:C$52,3,0) -> 390000 | D46: 3437 | E46: =C46+D46+Q46 -> 429437 | F46: =INT([2]TONT20000DEC2015!E46+[2]TONT20000JANV!C46+[2]TONT20000FEV!C46+[2]TONT20000MARS!C46+[2]TONT20000AVRIL!C46+[2]TONT20000MAI!C46+[2]TONT20000JUIN!C46+[2]TONT20000JUIL!C46+[2]TONT20000AOUT!C46+[2]TONT20000SEPT!C46+[2]TONT20000OCT!C46+[2]TONT20000NOV!C46) -> 48217 | G46: =[2]TONT20000NOV!E46 -> 477654.85 | H46: =D46+F46+Q46 -> 87654 | I46: =L46+M46+N46+O46 -> 80000 | J46: =H46-I46 -> 7654 | K46: 5000 | L46: 30000 | N46: 50000 | O46: =48000-(R46+S46+T46) -> 0 | P46: =[2]TONT20000DEC2015!H46+[2]TONT20000JANV!F46+[2]TONT20000FEV!F46+[2]TONT20000MARS!F46+[2]TONT20000AVRIL!F46+[2]TONT20000MAI!F46+[2]TONT20000JUIN!F46+[2]TONT20000JUIL!F46+[2]TONT20000AOUT!F46+[2]TONT20000SEPT!F46+[2]TONT20000OCT!F46+[2]TONT20000NOV!G46 -> 240000 | Q46: =[2]TONT20000DEC2015!I46+[2]TONT20000JANV!G46+[2]TONT20000FEV!G46+[2]TONT20000MARS!G46+[2]TONT20000AVRIL!G46+[2]TONT20000MAI!G46+[2]TONT20000JUIN!G46+[2]TONT20000JUIL!G46+[2]TONT20000AOUT!G46+[2]TONT20000SEPT!G46+[2]TONT20000OCT!G46+[2]TONT20000NOV!H46 -> 36000 | R46: =[2]TONT20000DEC2015!J46+[2]TONT20000JANV!H46+[2]TONT20000FEV!H46+[2]TONT20000MARS!H46+[2]TONT20000AVRIL!H46+[2]TONT20000MAI!H46+[2]TONT20000JUIN!H46+[2]TONT20000JUIL!H46+[2]TONT20000AOUT!H46+[2]TONT20000SEPT!H46+[2]TONT20000OCT!H46+[2]TONT20000NOV!I46 -> 6000 | S46: =[2]TONT20000DEC2015!K46+[2]TONT20000JANV!I46+[2]TONT20000FEV!I46+[2]TONT20000MARS!I46+[2]TONT20000AVRIL!I46+[2]TONT20000MAI!I46+[2]TONT20000JUIN!I46+[2]TONT20000JUIL!I46+[2]TONT20000AOUT!I46+[2]TONT20000SEPT!I46+[2]TONT20000OCT!I46+[2]TONT20000NOV!J46 -> 12000 | T46: =[2]TONT20000DEC2015!L46+[2]TONT20000JANV!J46+[2]TONT20000FEV!J46+[2]TONT20000MARS!J46+[2]TONT20000AVRIL!J46+[2]TONT20000MAI!J46+[2]TONT20000JUIN!J46+[2]TONT20000JUIL!J46+[2]TONT20000AOUT!J46+[2]TONT20000SEPT!J46+[2]TONT20000OCT!J46+[2]TONT20000NOV!K46 -> 30000 | U46: =[2]TONT20000DEC2015!M46+[2]TONT20000JANV!K46+[2]TONT20000FEV!K46+[2]TONT20000MARS!K46+[2]TONT20000AVRIL!K46+[2]TONT20000MAI!K46+[2]TONT20000JUIN!K46+[2]TONT20000JUIL!K46+[2]TONT20000AOUT!K46+[2]TONT20000SEPT!K46+[2]TONT20000OCT!K46+[2]TONT20000NOV!L46 -> 0 | V46: =[2]TONT20000DEC2015!N46+[2]TONT20000JANV!L46+[2]TONT20000FEV!L46+[2]TONT20000MARS!L46+[2]TONT20000AVRIL!L46+[2]TONT20000MAI!L46+[2]TONT20000JUIN!L46+[2]TONT20000JUIL!L46+[2]TONT20000AOUT!L46+[2]TONT20000SEPT!L46+[2]TONT20000OCT!L46+[2]TONT20000NOV!M46 -> 156000 | W46: =[2]TONT20000DEC2015!O46+[2]TONT20000JANV!M46+[2]TONT20000FEV!M46+[2]TONT20000MARS!M46+[2]TONT20000AVRIL!M46+[2]TONT20000MAI!M46+[2]TONT20000JUIN!M46+[2]TONT20000JUIL!M46+[2]TONT20000AOUT!M46+[2]TONT20000SEPT!M46+[2]TONT20000OCT!M46+[2]TONT20000NOV!N46 -> 1500000 | ... AB46: =[2]TONT20000DEC2015!T46+[2]TONT20000JANV!R46+[2]TONT20000FEV!R46+[2]TONT20000MARS!R46+[2]TONT20000AVRIL!R46+[2]TONT20000MAI!R46+[2]TONT20000JUIN!R46+[2]TONT20000JUIL!R46+[2]TONT20000AOUT!R46+[2]TONT20000SEPT!R46+[2]TONT20000OCT!R46+[2]TONT20000NOV!S46 -> 0
A47: AS201642 | B47: =VLOOKUP(A47,[2]LISTADHERENT!A$5:H$52,2,0) -> TCHOUANTE FRANCOIS | C47: 325719 | D47: 4925 | E47: =C47+D47+Q47 -> 393644 | F47: =INT([2]TONT20000DEC2015!E47+[2]TONT20000JANV!C47+[2]TONT20000FEV!C47+[2]TONT20000MARS!C47+[2]TONT20000AVRIL!C47+[2]TONT20000MAI!C47+[2]TONT20000JUIN!C47+[2]TONT20000JUIL!C47+[2]TONT20000AOUT!C47+[2]TONT20000SEPT!C47+[2]TONT20000OCT!C47+[2]TONT20000NOV!C47) -> 37907 | G47: =[2]TONT20000NOV!E47 -> 431551.07 | H47: =D47+F47+Q47 -> 105832 | I47: =L47+M47+N47+O47 -> 80000 | J47: =H47-I47 -> 25832 | K47: 0 | L47: 30000 | N47: 50000 | O47: =48000-(R47+S47+T47) -> 0 | P47: =[2]TONT20000DEC2015!H47+[2]TONT20000JANV!F47+[2]TONT20000FEV!F47+[2]TONT20000MARS!F47+[2]TONT20000AVRIL!F47+[2]TONT20000MAI!F47+[2]TONT20000JUIN!F47+[2]TONT20000JUIL!F47+[2]TONT20000AOUT!F47+[2]TONT20000SEPT!F47+[2]TONT20000OCT!F47+[2]TONT20000NOV!G47 -> 267000 | Q47: =[2]TONT20000DEC2015!I47+[2]TONT20000JANV!G47+[2]TONT20000FEV!G47+[2]TONT20000MARS!G47+[2]TONT20000AVRIL!G47+[2]TONT20000MAI!G47+[2]TONT20000JUIN!G47+[2]TONT20000JUIL!G47+[2]TONT20000AOUT!G47+[2]TONT20000SEPT!G47+[2]TONT20000OCT!G47+[2]TONT20000NOV!H47 -> 63000 | R47: =[2]TONT20000DEC2015!J47+[2]TONT20000JANV!H47+[2]TONT20000FEV!H47+[2]TONT20000MARS!H47+[2]TONT20000AVRIL!H47+[2]TONT20000MAI!H47+[2]TONT20000JUIN!H47+[2]TONT20000JUIL!H47+[2]TONT20000AOUT!H47+[2]TONT20000SEPT!H47+[2]TONT20000OCT!H47+[2]TONT20000NOV!I47 -> 6000 | S47: =[2]TONT20000DEC2015!K47+[2]TONT20000JANV!I47+[2]TONT20000FEV!I47+[2]TONT20000MARS!I47+[2]TONT20000AVRIL!I47+[2]TONT20000MAI!I47+[2]TONT20000JUIN!I47+[2]TONT20000JUIL!I47+[2]TONT20000AOUT!I47+[2]TONT20000SEPT!I47+[2]TONT20000OCT!I47+[2]TONT20000NOV!J47 -> 12000 | T47: =[2]TONT20000DEC2015!L47+[2]TONT20000JANV!J47+[2]TONT20000FEV!J47+[2]TONT20000MARS!J47+[2]TONT20000AVRIL!J47+[2]TONT20000MAI!J47+[2]TONT20000JUIN!J47+[2]TONT20000JUIL!J47+[2]TONT20000AOUT!J47+[2]TONT20000SEPT!J47+[2]TONT20000OCT!J47+[2]TONT20000NOV!K47 -> 30000 | U47: =[2]TONT20000DEC2015!M47+[2]TONT20000JANV!K47+[2]TONT20000FEV!K47+[2]TONT20000MARS!K47+[2]TONT20000AVRIL!K47+[2]TONT20000MAI!K47+[2]TONT20000JUIN!K47+[2]TONT20000JUIL!K47+[2]TONT20000AOUT!K47+[2]TONT20000SEPT!K47+[2]TONT20000OCT!K47+[2]TONT20000NOV!L47 -> 0 | V47: =[2]TONT20000DEC2015!N47+[2]TONT20000JANV!L47+[2]TONT20000FEV!L47+[2]TONT20000MARS!L47+[2]TONT20000AVRIL!L47+[2]TONT20000MAI!L47+[2]TONT20000JUIN!L47+[2]TONT20000JUIL!L47+[2]TONT20000AOUT!L47+[2]TONT20000SEPT!L47+[2]TONT20000OCT!L47+[2]TONT20000NOV!M47 -> 156000 | W47: =[2]TONT20000DEC2015!O47+[2]TONT20000JANV!M47+[2]TONT20000FEV!M47+[2]TONT20000MARS!M47+[2]TONT20000AVRIL!M47+[2]TONT20000MAI!M47+[2]TONT20000JUIN!M47+[2]TONT20000JUIL!M47+[2]TONT20000AOUT!M47+[2]TONT20000SEPT!M47+[2]TONT20000OCT!M47+[2]TONT20000NOV!N47 -> 1250000 | ... AB47: =[2]TONT20000DEC2015!T47+[2]TONT20000JANV!R47+[2]TONT20000FEV!R47+[2]TONT20000MARS!R47+[2]TONT20000AVRIL!R47+[2]TONT20000MAI!R47+[2]TONT20000JUIN!R47+[2]TONT20000JUIL!R47+[2]TONT20000AOUT!R47+[2]TONT20000SEPT!R47+[2]TONT20000OCT!R47+[2]TONT20000NOV!S47 -> 0
A48: AS201643 | B48: =VLOOKUP(A48,[2]LISTADHERENT!A$5:H$52,2,0) -> TCHOUTOU NANA CLAUDE | C48: =VLOOKUP(A48,[2]FONDSDECAISSE!A$5:C$52,3,0) -> 0 | D48: 0 | E48: =C48+D48+Q48 -> 14126 | F48: =INT([2]TONT20000DEC2015!E48+[2]TONT20000JANV!C48+[2]TONT20000FEV!C48+[2]TONT20000MARS!C48+[2]TONT20000AVRIL!C48+[2]TONT20000MAI!C48+[2]TONT20000JUIN!C48+[2]TONT20000JUIL!C48+[2]TONT20000AOUT!C48+[2]TONT20000SEPT!C48+[2]TONT20000OCT!C48+[2]TONT20000NOV!C48) -> 1437 | G48: =[2]TONT20000NOV!E48 -> 25437.043 | H48: =D48+F48+Q48 -> 15563 | I48: =L48+M48+N48+O48 -> 16000 | J48: =H48-I48 -> -437 | K48: 0 | O48: =48000-(R48+S48+T48) -> 16000 | P48: =[2]TONT20000DEC2015!H48+[2]TONT20000JANV!F48+[2]TONT20000FEV!F48+[2]TONT20000MARS!F48+[2]TONT20000AVRIL!F48+[2]TONT20000MAI!F48+[2]TONT20000JUIN!F48+[2]TONT20000JUIL!F48+[2]TONT20000AOUT!F48+[2]TONT20000SEPT!F48+[2]TONT20000OCT!F48+[2]TONT20000NOV!G48 -> 160000 | Q48: =[2]TONT20000DEC2015!I48+[2]TONT20000JANV!G48+[2]TONT20000FEV!G48+[2]TONT20000MARS!G48+[2]TONT20000AVRIL!G48+[2]TONT20000MAI!G48+[2]TONT20000JUIN!G48+[2]TONT20000JUIL!G48+[2]TONT20000AOUT!G48+[2]TONT20000SEPT!G48+[2]TONT20000OCT!G48+[2]TONT20000NOV!H48-9874 -> 14126 | R48: =[2]TONT20000DEC2015!J48+[2]TONT20000JANV!H48+[2]TONT20000FEV!H48+[2]TONT20000MARS!H48+[2]TONT20000AVRIL!H48+[2]TONT20000MAI!H48+[2]TONT20000JUIN!H48+[2]TONT20000JUIL!H48+[2]TONT20000AOUT!H48+[2]TONT20000SEPT!H48+[2]TONT20000OCT!H48+[2]TONT20000NOV!I48 -> 4000 | S48: =[2]TONT20000DEC2015!K48+[2]TONT20000JANV!I48+[2]TONT20000FEV!I48+[2]TONT20000MARS!I48+[2]TONT20000AVRIL!I48+[2]TONT20000MAI!I48+[2]TONT20000JUIN!I48+[2]TONT20000JUIL!I48+[2]TONT20000AOUT!I48+[2]TONT20000SEPT!I48+[2]TONT20000OCT!I48+[2]TONT20000NOV!J48 -> 8000 | T48: =[2]TONT20000DEC2015!L48+[2]TONT20000JANV!J48+[2]TONT20000FEV!J48+[2]TONT20000MARS!J48+[2]TONT20000AVRIL!J48+[2]TONT20000MAI!J48+[2]TONT20000JUIN!J48+[2]TONT20000JUIL!J48+[2]TONT20000AOUT!J48+[2]TONT20000SEPT!J48+[2]TONT20000OCT!J48+[2]TONT20000NOV!K48 -> 20000 | U48: =[2]TONT20000DEC2015!M48+[2]TONT20000JANV!K48+[2]TONT20000FEV!K48+[2]TONT20000MARS!K48+[2]TONT20000AVRIL!K48+[2]TONT20000MAI!K48+[2]TONT20000JUIN!K48+[2]TONT20000JUIL!K48+[2]TONT20000AOUT!K48+[2]TONT20000SEPT!K48+[2]TONT20000OCT!K48+[2]TONT20000NOV!L48 -> 0 | V48: =[2]TONT20000DEC2015!N48+[2]TONT20000JANV!L48+[2]TONT20000FEV!L48+[2]TONT20000MARS!L48+[2]TONT20000AVRIL!L48+[2]TONT20000MAI!L48+[2]TONT20000JUIN!L48+[2]TONT20000JUIL!L48+[2]TONT20000AOUT!L48+[2]TONT20000SEPT!L48+[2]TONT20000OCT!L48+[2]TONT20000NOV!M48 -> 104000 | W48: =[2]TONT20000DEC2015!O48+[2]TONT20000JANV!M48+[2]TONT20000FEV!M48+[2]TONT20000MARS!M48+[2]TONT20000AVRIL!M48+[2]TONT20000MAI!M48+[2]TONT20000JUIN!M48+[2]TONT20000JUIL!M48+[2]TONT20000AOUT!M48+[2]TONT20000SEPT!M48+[2]TONT20000OCT!M48+[2]TONT20000NOV!N48 -> 0 | X48: =[2]TONT20000DEC2015!P48+[2]TONT20000JANV!N48+[2]TONT20000FEV!N48+[2]TONT20000MARS!N48+[2]TONT20000AVRIL!N48+[2]TONT20000MAI!N48+[2]TONT20000JUIN!N48+[2]TONT20000JUIL!N48+[2]TONT20000AOUT!N48+[2]TONT20000SEPT!N48+[2]TONT20000OCT!N48+[2]TONT20000NOV!O48 -> 0 | Y48: =[2]TONT20000DEC2015!Q48+[2]TONT20000JANV!O48+[2]TONT20000FEV!O48+[2]TONT20000MARS!O48+[2]TONT20000AVRIL!O48+[2]TONT20000MAI!O48+[2]TONT20000JUIN!O48+[2]TONT20000JUIL!O48+[2]TONT20000AOUT!O48+[2]TONT20000SEPT!O48+[2]TONT20000OCT!O48+[2]TONT20000NOV!P48 -> 0 | ... AB48: =[2]TONT20000DEC2015!T48+[2]TONT20000JANV!R48+[2]TONT20000FEV!R48+[2]TONT20000MARS!R48+[2]TONT20000AVRIL!R48+[2]TONT20000MAI!R48+[2]TONT20000JUIN!R48+[2]TONT20000JUIL!R48+[2]TONT20000AOUT!R48+[2]TONT20000SEPT!R48+[2]TONT20000OCT!R48+[2]TONT20000NOV!S48 -> 0
A49: AS201644 | B49: =VLOOKUP(A49,[2]LISTADHERENT!A$5:H$52,2,0) -> TIEYAM ERNEST | C49: =VLOOKUP(A49,[2]FONDSDECAISSE!A$5:C$52,3,0) -> 390000 | D49: 804 | E49: =C49+D49+Q49 -> 426804 | F49: =INT([2]TONT20000DEC2015!E49+[2]TONT20000JANV!C49+[2]TONT20000FEV!C49+[2]TONT20000MARS!C49+[2]TONT20000AVRIL!C49+[2]TONT20000MAI!C49+[2]TONT20000JUIN!C49+[2]TONT20000JUIL!C49+[2]TONT20000AOUT!C49+[2]TONT20000SEPT!C49+[2]TONT20000OCT!C49+[2]TONT20000NOV!C49) -> 47789 | G49: =[2]TONT20000NOV!E49 -> 474593.29 | H49: =D49+F49+Q49 -> 84593 | I49: =L49+M49+N49+O49 -> 80000 | J49: =H49-I49 -> 4593 | K49: 2000 | L49: 30000 | N49: 50000 | O49: =48000-(R49+S49+T49) -> 0 | P49: =[2]TONT20000DEC2015!H49+[2]TONT20000JANV!F49+[2]TONT20000FEV!F49+[2]TONT20000MARS!F49+[2]TONT20000AVRIL!F49+[2]TONT20000MAI!F49+[2]TONT20000JUIN!F49+[2]TONT20000JUIL!F49+[2]TONT20000AOUT!F49+[2]TONT20000SEPT!F49+[2]TONT20000OCT!F49+[2]TONT20000NOV!G49 -> 240000 | Q49: =[2]TONT20000DEC2015!I49+[2]TONT20000JANV!G49+[2]TONT20000FEV!G49+[2]TONT20000MARS!G49+[2]TONT20000AVRIL!G49+[2]TONT20000MAI!G49+[2]TONT20000JUIN!G49+[2]TONT20000JUIL!G49+[2]TONT20000AOUT!G49+[2]TONT20000SEPT!G49+[2]TONT20000OCT!G49+[2]TONT20000NOV!H49 -> 36000 | R49: =[2]TONT20000DEC2015!J49+[2]TONT20000JANV!H49+[2]TONT20000FEV!H49+[2]TONT20000MARS!H49+[2]TONT20000AVRIL!H49+[2]TONT20000MAI!H49+[2]TONT20000JUIN!H49+[2]TONT20000JUIL!H49+[2]TONT20000AOUT!H49+[2]TONT20000SEPT!H49+[2]TONT20000OCT!H49+[2]TONT20000NOV!I49 -> 6000 | S49: =[2]TONT20000DEC2015!K49+[2]TONT20000JANV!I49+[2]TONT20000FEV!I49+[2]TONT20000MARS!I49+[2]TONT20000AVRIL!I49+[2]TONT20000MAI!I49+[2]TONT20000JUIN!I49+[2]TONT20000JUIL!I49+[2]TONT20000AOUT!I49+[2]TONT20000SEPT!I49+[2]TONT20000OCT!I49+[2]TONT20000NOV!J49 -> 12000 | T49: =[2]TONT20000DEC2015!L49+[2]TONT20000JANV!J49+[2]TONT20000FEV!J49+[2]TONT20000MARS!J49+[2]TONT20000AVRIL!J49+[2]TONT20000MAI!J49+[2]TONT20000JUIN!J49+[2]TONT20000JUIL!J49+[2]TONT20000AOUT!J49+[2]TONT20000SEPT!J49+[2]TONT20000OCT!J49+[2]TONT20000NOV!K49 -> 30000 | U49: =[2]TONT20000DEC2015!M49+[2]TONT20000JANV!K49+[2]TONT20000FEV!K49+[2]TONT20000MARS!K49+[2]TONT20000AVRIL!K49+[2]TONT20000MAI!K49+[2]TONT20000JUIN!K49+[2]TONT20000JUIL!K49+[2]TONT20000AOUT!K49+[2]TONT20000SEPT!K49+[2]TONT20000OCT!K49+[2]TONT20000NOV!L49 -> 0 | V49: =[2]TONT20000DEC2015!N49+[2]TONT20000JANV!L49+[2]TONT20000FEV!L49+[2]TONT20000MARS!L49+[2]TONT20000AVRIL!L49+[2]TONT20000MAI!L49+[2]TONT20000JUIN!L49+[2]TONT20000JUIL!L49+[2]TONT20000AOUT!L49+[2]TONT20000SEPT!L49+[2]TONT20000OCT!L49+[2]TONT20000NOV!M49 -> 156000 | W49: =[2]TONT20000DEC2015!O49+[2]TONT20000JANV!M49+[2]TONT20000FEV!M49+[2]TONT20000MARS!M49+[2]TONT20000AVRIL!M49+[2]TONT20000MAI!M49+[2]TONT20000JUIN!M49+[2]TONT20000JUIL!M49+[2]TONT20000AOUT!M49+[2]TONT20000SEPT!M49+[2]TONT20000OCT!M49+[2]TONT20000NOV!N49 -> 1000000 | ... AB49: =[2]TONT20000DEC2015!T49+[2]TONT20000JANV!R49+[2]TONT20000FEV!R49+[2]TONT20000MARS!R49+[2]TONT20000AVRIL!R49+[2]TONT20000MAI!R49+[2]TONT20000JUIN!R49+[2]TONT20000JUIL!R49+[2]TONT20000AOUT!R49+[2]TONT20000SEPT!R49+[2]TONT20000OCT!R49+[2]TONT20000NOV!S49 -> 0
A50: AS201645 | B50: =VLOOKUP(A50,[2]LISTADHERENT!A$5:H$52,2,0) -> TUGMA PIERRE LOTI | C50: =VLOOKUP(A50,[2]FONDSDECAISSE!A$5:C$52,3,0) -> 390000 | D50: 17636 | E50: =C50+D50+Q50 -> 443636 | F50: =INT([2]TONT20000DEC2015!E50+[2]TONT20000JANV!C50+[2]TONT20000FEV!C50+[2]TONT20000MARS!C50+[2]TONT20000AVRIL!C50+[2]TONT20000MAI!C50+[2]TONT20000JUIN!C50+[2]TONT20000JUIL!C50+[2]TONT20000AOUT!C50+[2]TONT20000SEPT!C50+[2]TONT20000OCT!C50+[2]TONT20000NOV!C50) -> 49867 | G50: =[2]TONT20000NOV!E50 -> 493503.06 | H50: =D50+F50+Q50 -> 103503 | I50: =L50+M50+N50+O50 -> 80000 | J50: =H50-I50 -> 23503 | K50: 21000 | L50: 30000 | N50: 50000 | O50: =48000-(R50+S50+T50) -> 0 | P50: =[2]TONT20000DEC2015!H50+[2]TONT20000JANV!F50+[2]TONT20000FEV!F50+[2]TONT20000MARS!F50+[2]TONT20000AVRIL!F50+[2]TONT20000MAI!F50+[2]TONT20000JUIN!F50+[2]TONT20000JUIL!F50+[2]TONT20000AOUT!F50+[2]TONT20000SEPT!F50+[2]TONT20000OCT!F50+[2]TONT20000NOV!G50 -> 240000 | Q50: =[2]TONT20000DEC2015!I50+[2]TONT20000JANV!G50+[2]TONT20000FEV!G50+[2]TONT20000MARS!G50+[2]TONT20000AVRIL!G50+[2]TONT20000MAI!G50+[2]TONT20000JUIN!G50+[2]TONT20000JUIL!G50+[2]TONT20000AOUT!G50+[2]TONT20000SEPT!G50+[2]TONT20000OCT!G50+[2]TONT20000NOV!H50 -> 36000 | R50: =[2]TONT20000DEC2015!J50+[2]TONT20000JANV!H50+[2]TONT20000FEV!H50+[2]TONT20000MARS!H50+[2]TONT20000AVRIL!H50+[2]TONT20000MAI!H50+[2]TONT20000JUIN!H50+[2]TONT20000JUIL!H50+[2]TONT20000AOUT!H50+[2]TONT20000SEPT!H50+[2]TONT20000OCT!H50+[2]TONT20000NOV!I50 -> 6000 | S50: =[2]TONT20000DEC2015!K50+[2]TONT20000JANV!I50+[2]TONT20000FEV!I50+[2]TONT20000MARS!I50+[2]TONT20000AVRIL!I50+[2]TONT20000MAI!I50+[2]TONT20000JUIN!I50+[2]TONT20000JUIL!I50+[2]TONT20000AOUT!I50+[2]TONT20000SEPT!I50+[2]TONT20000OCT!I50+[2]TONT20000NOV!J50 -> 12000 | T50: =[2]TONT20000DEC2015!L50+[2]TONT20000JANV!J50+[2]TONT20000FEV!J50+[2]TONT20000MARS!J50+[2]TONT20000AVRIL!J50+[2]TONT20000MAI!J50+[2]TONT20000JUIN!J50+[2]TONT20000JUIL!J50+[2]TONT20000AOUT!J50+[2]TONT20000SEPT!J50+[2]TONT20000OCT!J50+[2]TONT20000NOV!K50 -> 30000 | U50: =[2]TONT20000DEC2015!M50+[2]TONT20000JANV!K50+[2]TONT20000FEV!K50+[2]TONT20000MARS!K50+[2]TONT20000AVRIL!K50+[2]TONT20000MAI!K50+[2]TONT20000JUIN!K50+[2]TONT20000JUIL!K50+[2]TONT20000AOUT!K50+[2]TONT20000SEPT!K50+[2]TONT20000OCT!K50+[2]TONT20000NOV!L50 -> 0 | V50: =[2]TONT20000DEC2015!N50+[2]TONT20000JANV!L50+[2]TONT20000FEV!L50+[2]TONT20000MARS!L50+[2]TONT20000AVRIL!L50+[2]TONT20000MAI!L50+[2]TONT20000JUIN!L50+[2]TONT20000JUIL!L50+[2]TONT20000AOUT!L50+[2]TONT20000SEPT!L50+[2]TONT20000OCT!L50+[2]TONT20000NOV!M50 -> 156000 | W50: =[2]TONT20000DEC2015!O50+[2]TONT20000JANV!M50+[2]TONT20000FEV!M50+[2]TONT20000MARS!M50+[2]TONT20000AVRIL!M50+[2]TONT20000MAI!M50+[2]TONT20000JUIN!M50+[2]TONT20000JUIL!M50+[2]TONT20000AOUT!M50+[2]TONT20000SEPT!M50+[2]TONT20000OCT!M50+[2]TONT20000NOV!N50 -> 0 | ... AB50: =[2]TONT20000DEC2015!T50+[2]TONT20000JANV!R50+[2]TONT20000FEV!R50+[2]TONT20000MARS!R50+[2]TONT20000AVRIL!R50+[2]TONT20000MAI!R50+[2]TONT20000JUIN!R50+[2]TONT20000JUIL!R50+[2]TONT20000AOUT!R50+[2]TONT20000SEPT!R50+[2]TONT20000OCT!R50+[2]TONT20000NOV!S50 -> 0
A51: AS201646 | B51: =VLOOKUP(A51,[2]LISTADHERENT!A$5:H$52,2,0) -> YEPMOU JEAN JACQUES | C51: =VLOOKUP(A51,[2]FONDSDECAISSE!A$5:C$52,3,0) -> 390000 | D51: 421237 | E51: =C51+D51+Q51 -> 847237 | F51: =INT([2]TONT20000DEC2015!E51+[2]TONT20000JANV!C51+[2]TONT20000FEV!C51+[2]TONT20000MARS!C51+[2]TONT20000AVRIL!C51+[2]TONT20000MAI!C51+[2]TONT20000JUIN!C51+[2]TONT20000JUIL!C51+[2]TONT20000AOUT!C51+[2]TONT20000SEPT!C51+[2]TONT20000OCT!C51+[2]TONT20000NOV!C51) -> 96745 | G51: =[2]TONT20000NOV!E51 -> 943982.29 | H51: =D51+F51+Q51 -> 553982 | I51: =L51+M51+N51+O51 -> 80000 | J51: =H51-I51 -> 473982 | K51: 80000 | L51: 30000 | N51: 50000 | O51: =48000-(R51+S51+T51) -> 0 | P51: =[2]TONT20000DEC2015!H51+[2]TONT20000JANV!F51+[2]TONT20000FEV!F51+[2]TONT20000MARS!F51+[2]TONT20000AVRIL!F51+[2]TONT20000MAI!F51+[2]TONT20000JUIN!F51+[2]TONT20000JUIL!F51+[2]TONT20000AOUT!F51+[2]TONT20000SEPT!F51+[2]TONT20000OCT!F51+[2]TONT20000NOV!G51 -> 240000 | Q51: =[2]TONT20000DEC2015!I51+[2]TONT20000JANV!G51+[2]TONT20000FEV!G51+[2]TONT20000MARS!G51+[2]TONT20000AVRIL!G51+[2]TONT20000MAI!G51+[2]TONT20000JUIN!G51+[2]TONT20000JUIL!G51+[2]TONT20000AOUT!G51+[2]TONT20000SEPT!G51+[2]TONT20000OCT!G51+[2]TONT20000NOV!H51 -> 36000 | R51: =[2]TONT20000DEC2015!J51+[2]TONT20000JANV!H51+[2]TONT20000FEV!H51+[2]TONT20000MARS!H51+[2]TONT20000AVRIL!H51+[2]TONT20000MAI!H51+[2]TONT20000JUIN!H51+[2]TONT20000JUIL!H51+[2]TONT20000AOUT!H51+[2]TONT20000SEPT!H51+[2]TONT20000OCT!H51+[2]TONT20000NOV!I51 -> 6000 | S51: =[2]TONT20000DEC2015!K51+[2]TONT20000JANV!I51+[2]TONT20000FEV!I51+[2]TONT20000MARS!I51+[2]TONT20000AVRIL!I51+[2]TONT20000MAI!I51+[2]TONT20000JUIN!I51+[2]TONT20000JUIL!I51+[2]TONT20000AOUT!I51+[2]TONT20000SEPT!I51+[2]TONT20000OCT!I51+[2]TONT20000NOV!J51 -> 12000 | T51: =[2]TONT20000DEC2015!L51+[2]TONT20000JANV!J51+[2]TONT20000FEV!J51+[2]TONT20000MARS!J51+[2]TONT20000AVRIL!J51+[2]TONT20000MAI!J51+[2]TONT20000JUIN!J51+[2]TONT20000JUIL!J51+[2]TONT20000AOUT!J51+[2]TONT20000SEPT!J51+[2]TONT20000OCT!J51+[2]TONT20000NOV!K51 -> 30000 | U51: =[2]TONT20000DEC2015!M51+[2]TONT20000JANV!K51+[2]TONT20000FEV!K51+[2]TONT20000MARS!K51+[2]TONT20000AVRIL!K51+[2]TONT20000MAI!K51+[2]TONT20000JUIN!K51+[2]TONT20000JUIL!K51+[2]TONT20000AOUT!K51+[2]TONT20000SEPT!K51+[2]TONT20000OCT!K51+[2]TONT20000NOV!L51 -> 0 | V51: =[2]TONT20000DEC2015!N51+[2]TONT20000JANV!L51+[2]TONT20000FEV!L51+[2]TONT20000MARS!L51+[2]TONT20000AVRIL!L51+[2]TONT20000MAI!L51+[2]TONT20000JUIN!L51+[2]TONT20000JUIL!L51+[2]TONT20000AOUT!L51+[2]TONT20000SEPT!L51+[2]TONT20000OCT!L51+[2]TONT20000NOV!M51 -> 156000 | W51: =[2]TONT20000DEC2015!O51+[2]TONT20000JANV!M51+[2]TONT20000FEV!M51+[2]TONT20000MARS!M51+[2]TONT20000AVRIL!M51+[2]TONT20000MAI!M51+[2]TONT20000JUIN!M51+[2]TONT20000JUIL!M51+[2]TONT20000AOUT!M51+[2]TONT20000SEPT!M51+[2]TONT20000OCT!M51+[2]TONT20000NOV!N51 -> 0 | ... AB51: =[2]TONT20000DEC2015!T51+[2]TONT20000JANV!R51+[2]TONT20000FEV!R51+[2]TONT20000MARS!R51+[2]TONT20000AVRIL!R51+[2]TONT20000MAI!R51+[2]TONT20000JUIN!R51+[2]TONT20000JUIL!R51+[2]TONT20000AOUT!R51+[2]TONT20000SEPT!R51+[2]TONT20000OCT!R51+[2]TONT20000NOV!S51 -> 0
A52: AS201647 | B52: =VLOOKUP(A52,[2]LISTADHERENT!A$5:H$52,2,0) -> YOUMBI EMMANUEL | C52: =VLOOKUP(A52,[2]FONDSDECAISSE!A$5:C$52,3,0) -> 390000 | D52: 1003279 | E52: =C52+D52+Q52 -> 1429279 | F52: =INT([2]TONT20000DEC2015!E52+[2]TONT20000JANV!C52+[2]TONT20000FEV!C52+[2]TONT20000MARS!C52+[2]TONT20000AVRIL!C52+[2]TONT20000MAI!C52+[2]TONT20000JUIN!C52+[2]TONT20000JUIL!C52+[2]TONT20000AOUT!C52+[2]TONT20000SEPT!C52+[2]TONT20000OCT!C52+[2]TONT20000NOV!C52) -> 164349 | G52: =[2]TONT20000NOV!E52 -> 1593628.4 | H52: =D52+F52+Q52 -> 1203628 | I52: =L52+M52+N52+O52 -> 80000 | J52: =H52-I52 -> 1123628 | K52: 240000 | L52: 30000 | N52: 50000 | O52: =48000-(R52+S52+T52) -> 0 | P52: =[2]TONT20000DEC2015!H52+[2]TONT20000JANV!F52+[2]TONT20000FEV!F52+[2]TONT20000MARS!F52+[2]TONT20000AVRIL!F52+[2]TONT20000MAI!F52+[2]TONT20000JUIN!F52+[2]TONT20000JUIL!F52+[2]TONT20000AOUT!F52+[2]TONT20000SEPT!F52+[2]TONT20000OCT!F52+[2]TONT20000NOV!G52 -> 240000 | Q52: =[2]TONT20000DEC2015!I52+[2]TONT20000JANV!G52+[2]TONT20000FEV!G52+[2]TONT20000MARS!G52+[2]TONT20000AVRIL!G52+[2]TONT20000MAI!G52+[2]TONT20000JUIN!G52+[2]TONT20000JUIL!G52+[2]TONT20000AOUT!G52+[2]TONT20000SEPT!G52+[2]TONT20000OCT!G52+[2]TONT20000NOV!H52 -> 36000 | R52: =[2]TONT20000DEC2015!J52+[2]TONT20000JANV!H52+[2]TONT20000FEV!H52+[2]TONT20000MARS!H52+[2]TONT20000AVRIL!H52+[2]TONT20000MAI!H52+[2]TONT20000JUIN!H52+[2]TONT20000JUIL!H52+[2]TONT20000AOUT!H52+[2]TONT20000SEPT!H52+[2]TONT20000OCT!H52+[2]TONT20000NOV!I52 -> 6000 | S52: =[2]TONT20000DEC2015!K52+[2]TONT20000JANV!I52+[2]TONT20000FEV!I52+[2]TONT20000MARS!I52+[2]TONT20000AVRIL!I52+[2]TONT20000MAI!I52+[2]TONT20000JUIN!I52+[2]TONT20000JUIL!I52+[2]TONT20000AOUT!I52+[2]TONT20000SEPT!I52+[2]TONT20000OCT!I52+[2]TONT20000NOV!J52 -> 12000 | T52: =[2]TONT20000DEC2015!L52+[2]TONT20000JANV!J52+[2]TONT20000FEV!J52+[2]TONT20000MARS!J52+[2]TONT20000AVRIL!J52+[2]TONT20000MAI!J52+[2]TONT20000JUIN!J52+[2]TONT20000JUIL!J52+[2]TONT20000AOUT!J52+[2]TONT20000SEPT!J52+[2]TONT20000OCT!J52+[2]TONT20000NOV!K52 -> 30000 | U52: =[2]TONT20000DEC2015!M52+[2]TONT20000JANV!K52+[2]TONT20000FEV!K52+[2]TONT20000MARS!K52+[2]TONT20000AVRIL!K52+[2]TONT20000MAI!K52+[2]TONT20000JUIN!K52+[2]TONT20000JUIL!K52+[2]TONT20000AOUT!K52+[2]TONT20000SEPT!K52+[2]TONT20000OCT!K52+[2]TONT20000NOV!L52 -> 0 | V52: =[2]TONT20000DEC2015!N52+[2]TONT20000JANV!L52+[2]TONT20000FEV!L52+[2]TONT20000MARS!L52+[2]TONT20000AVRIL!L52+[2]TONT20000MAI!L52+[2]TONT20000JUIN!L52+[2]TONT20000JUIL!L52+[2]TONT20000AOUT!L52+[2]TONT20000SEPT!L52+[2]TONT20000OCT!L52+[2]TONT20000NOV!M52 -> 156000 | W52: =[2]TONT20000DEC2015!O52+[2]TONT20000JANV!M52+[2]TONT20000FEV!M52+[2]TONT20000MARS!M52+[2]TONT20000AVRIL!M52+[2]TONT20000MAI!M52+[2]TONT20000JUIN!M52+[2]TONT20000JUIL!M52+[2]TONT20000AOUT!M52+[2]TONT20000SEPT!M52+[2]TONT20000OCT!M52+[2]TONT20000NOV!N52 -> 0 | ... AB52: =[2]TONT20000DEC2015!T52+[2]TONT20000JANV!R52+[2]TONT20000FEV!R52+[2]TONT20000MARS!R52+[2]TONT20000AVRIL!R52+[2]TONT20000MAI!R52+[2]TONT20000JUIN!R52+[2]TONT20000JUIL!R52+[2]TONT20000AOUT!R52+[2]TONT20000SEPT!R52+[2]TONT20000OCT!R52+[2]TONT20000NOV!S52 -> 0
A54: TOTAL | C54: =SUM(C5:C53) -> 14398519 | D54: =SUM(D5:D53) -> 3525236 | E54: =SUM(E5:E53) -> 21744896 | F54: =SUM(F5:F53) -> 2230668 | G54: =SUM(G5:G53) -> 24115470 | H54: =SUM(H5:H53) -> 9577045 | I54: =SUM(I5:I53) -> 2829860 | J54: =SUM(J5:J53) -> 6747185 | ... AB54: =SUM(AB5:AB53) -> 0
A55: TOTAL A DISTRIBUER | J55: =J5+J6+J7+J8+J9+J10+J12+J13+J14+J15+J17+J18+J19+J20+J21+J22+J23+J24+J25+J26+J27+J29+J30+J31+J32+J33+J34+J38+J39+J40+J41+J42+J43+J44+J45+J46+J47+J49+J50+J51+J52 -> 6770025
J56: =J16+J36+J48 -> -22840
B57: CAPITAL A DISTRIBUER | G57: =E58+E59+E60 -> 9577045
D58: RELIQUAT 2015 | E58: =D54 -> 3525236
D59: INTERET 2016 | E59: =+F54 -> 2230668
D60: EPARGNE 2016 | E60: =Q54 -> 3821141
B62: CAPITAL A DISTRIBUER | F62: =J55 -> 6770025
B63: CAPITAL EFFECTIVEMENT DISTRIBUE | F63: =K54 -> 3142500
B64: RETOUR MUTUELLE | F64: =N54 -> 1719860
B65: COMPLEMENT FONDS | F65: =L54 -> 1050000
B66: FRAIS FIXE A COMPLETER | F66: =O54 -> 60000
B67: SANCTION | F67: =M54 -> 0
B69: TOTAL | G69: =F62+F64+F65+F66+F67 -> 9599885
B71: RELIQUAT | G71: =G57-G69 -> -22840

Sheet TRAVAUXINVENTAIREDEC
B3: TOTAUX | C3: DEC2015 | D3: 42370 | E3: 42401 | F3: 42430 | G3: 42461 | H3: 42491 | I3: 42522 | J3: 42552 | K3: 42583 | L3: 42614 | M3: 42644 | N3: 42675
A4: EPARGNE | B4: =SUM(C4:N4) -> 1869000 | C4: =EPARGNE!B17 -> 0 | D4: =EPARGNE!C17 -> 0 | E4: =EPARGNE!D17 -> 1869000 | F4: =EPARGNE!E17 -> 0 | G4: =EPARGNE!F17 -> 0 | H4: =EPARGNE!G17 -> 0 | I4: =EPARGNE!H17 -> 0 | J4: =EPARGNE!I17 -> 0 | ... N4: =EPARGNE!M17 -> 0
A5: FONDS DE ROULEMENT | B5: =SUM(C5:N5) -> 452400 | C5: ='FONDS DE ROULEMENT'!B18 -> 190400 | D5: ='FONDS DE ROULEMENT'!C18 -> 2000 | E5: ='FONDS DE ROULEMENT'!D18 -> 2000 | F5: ='FONDS DE ROULEMENT'!E18 -> 4000 | G5: ='FONDS DE ROULEMENT'!F18 -> 97000 | H5: ='FONDS DE ROULEMENT'!G18 -> 0 | I5: ='FONDS DE ROULEMENT'!H18 -> 77000 | J5: ='FONDS DE ROULEMENT'!I18 -> 0 | ... N5: ='FONDS DE ROULEMENT'!M18 -> 23000
A6: FRAIS EXCEPTIONNEL | B6: =SUM(C6:N6) -> 400000 | C6: ='FRAIS EXCEPTIONNEL'!B17 -> 0 | D6: ='FRAIS EXCEPTIONNEL'!C17 -> 0 | E6: ='FRAIS EXCEPTIONNEL'!D17 -> 0 | F6: ='FRAIS EXCEPTIONNEL'!E17 -> 0 | G6: ='FRAIS EXCEPTIONNEL'!F17 -> 0 | H6: ='FRAIS EXCEPTIONNEL'!G17 -> 0 | I6: ='FRAIS EXCEPTIONNEL'!H17 -> 0 | J6: ='FRAIS EXCEPTIONNEL'!I17 -> 0 | ... N6: ='FRAIS EXCEPTIONNEL'!M17 -> 0
A7: COLLATION | B7: =SUM(C7:N7) -> 1240000 | C7: =COLLATION!B17 -> 100000 | D7: =COLLATION!C17 -> 100000 | E7: =COLLATION!D17 -> 100000 | F7: =COLLATION!E17 -> 100000 | G7: =COLLATION!F17 -> 100000 | H7: =COLLATION!G17 -> 100000 | I7: =COLLATION!H17 -> 100000 | J7: =COLLATION!I17 -> 100000 | ... N7: =COLLATION!M17 -> 100000
A8: MUTUELLE | B8: =SUM(C8:N8) -> 2495000 | C8: =MUTUELLE!B19 -> 0 | D8: =MUTUELLE!C19 -> 650000 | E8: =MUTUELLE!D19 -> 0 | F8: =MUTUELLE!E19 -> 100000 | G8: =MUTUELLE!F19 -> 0 | H8: =MUTUELLE!G19 -> 0 | I8: =MUTUELLE!H19 -> 200000 | J8: =MUTUELLE!I19 -> 0 | ... N8: =MUTUELLE!M19 -> 200000
A9: SANCTION | B9: =SUM(C9:N9) -> 0
A10: INSCRIPTION | B10: =SUM(C10:N10) -> 0 | C10: =INSCRIPTION!B17 -> 0 | D10: =INSCRIPTION!C17 -> 0 | E10: =INSCRIPTION!D17 -> 0 | F10: =INSCRIPTION!E17 -> 0 | G10: =INSCRIPTION!F17 -> 0 | H10: =INSCRIPTION!G17 -> 0 | I10: =INSCRIPTION!H17 -> 0 | J10: =INSCRIPTION!I17 -> 0 | ... N10: =INSCRIPTION!M17 -> 0
A11: EMPRUNT | B11: =SUM(C11:N11) -> 25710000 | C11: =EMPRUNT!B32 -> 1500000 | D11: =EMPRUNT!C32 -> 2200000 | E11: =EMPRUNT!D32 -> 750000 | F11: =EMPRUNT!E32 -> 1980000 | G11: =EMPRUNT!F32 -> 2200000 | H11: =EMPRUNT!G32 -> 750000 | I11: =EMPRUNT!H32 -> 3040000 | J11: =EMPRUNT!I32 -> 4870000 | ... N11: =EMPRUNT!M32 -> 3170000
A12: COMPLEMENT TONTINE | B12: =SUM(C12:N12) -> 303800 | C12: ='COMPLEMENT TONTINE'!B17 -> 0 | D12: ='COMPLEMENT TONTINE'!C17 -> 0 | E12: ='COMPLEMENT TONTINE'!D17 -> 33300 | F12: ='COMPLEMENT TONTINE'!E17 -> 0 | G12: ='COMPLEMENT TONTINE'!F17 -> 0 | H12: ='COMPLEMENT TONTINE'!G17 -> 141000 | I12: ='COMPLEMENT TONTINE'!H17 -> 12500 | J12: ='COMPLEMENT TONTINE'!I17 -> 47000 | ... N12: ='COMPLEMENT TONTINE'!M17 -> 37500
A13: INTERET EMPRUNT
A14: REMBOURSEMENT
A15: PENALITE EMPRUNT
A16: PENALITE INSCRIPTION
A17: TROP PERCU
A19: TOTAL | B19: =SUM(B4:B17) -> 32470200
A52: =SUM(A5:A51) -> 0 | B52: =SUM(B5:B51) -> 63071400 | D52: =SUM(D5:D51) -> 2952000 | E52: =SUM(E5:E51) -> 885300 | G52: =SUM(G5:G51) -> 2397000 | H52: =SUM(H5:H51) -> 991000 | I52: =SUM(I5:I51) -> 3429500 | J52: =SUM(J5:J51) -> 5017000

Sheet EPARGNE
B2: DEC2015 | C2: 42370 | D2: 42401 | E2: 42430 | F2: 42461 | G2: 42491 | H2: 42522 | I2: 42552 | J2: 42583 | K2: 42614 | L2: 42644 | M2: 42675
A4: PAIEMENT EPARGNE 2015
A5: LOWE JEAN | D5: 160000
A6: KOUAMOU VICTOR PEGUY | D6: 50000
A7: KEPSEU FRANCIS | D7: 1609000
A8: BOUTCHOUANG WILLIAM | D8: 50000
A17: TOTAL | B17: =SUM(B4:B16) -> 0 | C17: =SUM(C4:C16) -> 0 | D17: =SUM(D4:D16) -> 1869000 | E17: =SUM(E4:E16) -> 0 | F17: =SUM(F4:F16) -> 0 | G17: =SUM(G4:G16) -> 0 | H17: =SUM(H4:H16) -> 0 | I17: =SUM(I4:I16) -> 0 | ... M17: =SUM(M4:M16) -> 0

Sheet FONDS DE ROULEMENT
B2: DEC2015 | C2: 42370 | D2: 42401 | E2: 42430 | F2: 42461 | G2: 42491 | H2: 42522 | I2: 42552 | J2: 42583 | K2: 42614 | L2: 42644 | M2: 42675
A4: TROP PERCU
A5: NKAMGANG JUSTIN DEJOLIE | B5: 60000
A6: TCHOUAMOU MATHIEU | B6: 18000
A7: NDJOMO ETIENNE | B7: 12400
A8: GRATIFICATION BUREAU | B8: 100000
A9: TAXI BANQUE | C9: 2000 | D9: 2000 | E9: 4000 | H9: 6000 | J9: 6000
A10: PHOTOCOPIE DES DOCUMENTS | F10: 55000
A11: OUVERTURE COMPTE | F11: 42000
A12: COMMISSION FINANCE | H12: 71000
A13: REUNION DE BUREAU | J13: 15000
A14: LAVAGE ECHAPPE | L14: 15000
A15: COOMMISSION BUREAU | L15: 21000 | M15: 18000
A16: COMMUNICATION | M16: 5000
A18: TOTAL | B18: =SUM(B5:B17) -> 190400 | C18: =SUM(C5:C17) -> 2000 | D18: =SUM(D5:D17) -> 2000 | E18: =SUM(E5:E17) -> 4000 | F18: =SUM(F5:F17) -> 97000 | G18: =SUM(G5:G17) -> 0 | H18: =SUM(H5:H17) -> 77000 | I18: =SUM(I5:I17) -> 0 | ... M18: =SUM(M5:M17) -> 23000

Sheet FRAIS EXCEPTIONNEL
B2: DEC2015 | C2: 42370 | D2: 42401 | E2: 42430 | F2: 42461 | G2: 42491 | H2: 42522 | I2: 42552 | J2: 42583 | K2: 42614 | L2: 42644 | M2: 42675
A4: ACHAT ORDINATEUR | J4: 400000
A17: TOTAL | B17: =SUM(B4:B16) -> 0 | C17: =SUM(C4:C16) -> 0 | D17: =SUM(D4:D16) -> 0 | E17: =SUM(E4:E16) -> 0 | F17: =SUM(F4:F16) -> 0 | G17: =SUM(G4:G16) -> 0 | H17: =SUM(H4:H16) -> 0 | I17: =SUM(I4:I16) -> 0 | ... M17: =SUM(M4:M16) -> 0

Sheet COLLATION
B2: DEC2015 | C2: 42370 | D2: 42401 | E2: 42430 | F2: 42461 | G2: 42491 | H2: 42522 | I2: 42552 | J2: 42583 | K2: 42614 | L2: 42644 | M2: 42675
A4: COLLATION | B4: 100000 | C4: 100000 | D4: 100000 | E4: 100000 | F4: 100000 | G4: 100000 | H4: 100000 | I4: 100000 | J4: 100000 | K4: 100000 | L4: 100000 | M4: 100000
A5: VEILLEE NKEPSEU HENANG | K5: 40000
A17: TOTAL | B17: =SUM(B4:B16) -> 100000 | C17: =SUM(C4:C16) -> 100000 | D17: =SUM(D4:D16) -> 100000 | E17: =SUM(E4:E16) -> 100000 | F17: =SUM(F4:F16) -> 100000 | G17: =SUM(G4:G16) -> 100000 | H17: =SUM(H4:H16) -> 100000 | I17: =SUM(I4:I16) -> 100000 | ... M17: =SUM(M4:M16) -> 100000

Sheet MUTUELLE
B2: DEC2015 | C2: 42370 | D2: 42401 | E2: 42430 | F2: 42461 | G2: 42491 | H2: 42522 | I2: 42552 | J2: 42583 | K2: 42614 | L2: 42644 | M2: 42675
A4: OBSEQUES DJOSSEU JOSUE | C4: 500000
A5: FUNERAILLES CHEF DE FAMILLE | C5: 150000
A6: OBSEQUES PÈRE HOTCHO | E6: 100000
A7: OBSEQUES BEAU PÈRE NTOMBO | H7: 100000
A8: OBSEQUES BELLE MERE KEPSEU FRANCIS | H8: 100000
A9: OBSEUES ENFANT KOUAMO EMMANUEL | J9: 45000
A10: OBSEQUES NTOMBO ADOLPHE | J10: 500000
A11: OBSEQUES PÈRE BAKOP | J11: 100000
A12: OBSEQUES PÈRE MBOUTCHOUANG | J12: 100000
A13: OBSEQUES MERE SIMO MATHIEU | K13: 100000
A14: OBSEQUES NKEPSEU HENANG | K14: 500000
A15: OBSEQUES BEAU PÈRE BOUTCHOUANG | M15: 100000
A16: OBSEQUES MERE DOWOU DAVID | M16: 100000
A19: TOTAL | B19: =SUM(B4:B16) -> 0 | C19: =SUM(C4:C16) -> 650000 | D19: =SUM(D4:D16) -> 0 | E19: =SUM(E4:E16) -> 100000 | F19: =SUM(F4:F16) -> 0 | G19: =SUM(G4:G16) -> 0 | H19: =SUM(H4:H16) -> 200000 | I19: =SUM(I4:I16) -> 0 | ... M19: =SUM(M4:M16) -> 200000

Sheet SANCTION
B2: DEC2015 | C2: 42370 | D2: 42401 | E2: 42430 | F2: 42461 | G2: 42491 | H2: 42522 | I2: 42552 | J2: 42583 | K2: 42614 | L2: 42644 | M2: 42675

Sheet INSCRIPTION
B2: DEC2015 | C2: 42370 | D2: 42401 | E2: 42430 | F2: 42461 | G2: 42491 | H2: 42522 | I2: 42552 | J2: 42583 | K2: 42614 | L2: 42644 | M2: 42675

Sheet EMPRUNT
B2: DEC2015 | C2: 42370 | D2: 42401 | E2: 42430 | F2: 42461 | G2: 42491 | H2: 42522 | I2: 42552 | J2: 42583 | K2: 42614 | L2: 42644 | M2: 42675
A4: TCHOUAMOU MATHIEU | B4: 500000
A5: KOUATCHO MESSACK | B5: 600000 | F5: 1000000
A6: CHINGUE FABRICE | C6: 1000000 | H6: 1000000
A7: SIMO PIERRE | C7: 200000 | F7: 200000 | I7: 70000 | L7: 70000 | M7: 570000
A8: TCHIAM ERNEST | C8: 1000000
A9: TCHOUANTE FRANCOIS | D9: 500000 | G9: 750000
A10: DJOUKWE GUY | D10: 250000
A11: LOWE JEAN | E11: 80000 | H11: 80000 | K11: 80000
A12: NJEPDJIO MBOUKAM DELUXE | E12: 1000000 | H12: 1000000
A13: TCHOUAMOU MATHIEU | E13: 500000 | H13: 500000
A14: NDJOMO ETIENNE | B14: 400000 | E14: 400000 | H14: 400000 | K14: 400000
A15: FOTSO THOMAS | F15: 1000000
A16: KOUAMOU MOISE | H16: 60000 | I16: 800000
A17: KOUAMOU EMMANUEL | I17: 1000000
A18: NANKAM APPOLINAIRE | I18: 1000000
A19: BOUTCHOUANG WILLIAM | I19: 1000000 | M19: 700000
A20: KOUAMOU VICTOR PEGUY | I20: 1000000 | M20: 800000
A21: DJOMO JEAN PAUL | J21: 100000 | M21: 100000
A22: DJUOMBESSY ANTOINE | J22: 700000
A23: BAKOP ACHILLE | J23: 500000
A24: SIME MATHIEU | K24: 800000
A25: SIME FONGANG ERIC | K25: 1000000
A26: SEUNOU RICHELOT | L26: 1000000
A27: NKEPSEU DIEUDONNE | L27: 600000
A28: NKAMGANG JUSTIN DEJOLIE | M28: 1000000
A32: TOTAL | B32: =SUM(B4:B31) -> 1500000 | C32: =SUM(C4:C31) -> 2200000 | D32: =SUM(D4:D31) -> 750000 | E32: =SUM(E4:E31) -> 1980000 | F32: =SUM(F4:F31) -> 2200000 | G32: =SUM(G4:G31) -> 750000 | H32: =SUM(H4:H31) -> 3040000 | I32: =SUM(I4:I31) -> 4870000 | ... M32: =SUM(M4:M31) -> 3170000

Sheet COMPLEMENT TONTINE
B2: DEC2015 | C2: 42370 | D2: 42401 | E2: 42430 | F2: 42461 | G2: 42491 | H2: 42522 | I2: 42552 | J2: 42583 | K2: 42614 | L2: 42644 | M2: 42675
A4: COMPLEMENT TONTINE
A5: 60000 | D5: 11300 | G5: 1000 | H5: 12500
A6: 100000 | D6: 22000 | I6: 47000 | L6: 32500 | M6: 37500
A7: 20000 | G7: 140000
A17: TOTAL | B17: =SUM(B4:B16) -> 0 | C17: =SUM(C4:C16) -> 0 | D17: =SUM(D4:D16) -> 33300 | E17: =SUM(E4:E16) -> 0 | F17: =SUM(F4:F16) -> 0 | G17: =SUM(G4:G16) -> 141000 | H17: =SUM(H4:H16) -> 12500 | I17: =SUM(I4:I16) -> 47000 | ... M17: =SUM(M4:M16) -> 37500

Sheet FONDS DE CAISSE
B2: DEC2015 | C2: 42370 | D2: 42401 | E2: 42430 | F2: 42461 | G2: 42491 | H2: 42522 | I2: 42552 | J2: 42583 | K2: 42614 | L2: 42644 | M2: 42675
A4: SOLDE COMPTE DJOSSEU JOSUE | H4: 400500
A5: SOLDE COMPTE NTOMBOU ADOLPHE | L5: 441105
A17: TOTAL | B17: =SUM(B4:B16) -> 0 | C17: =SUM(C4:C16) -> 0 | D17: =SUM(D4:D16) -> 0 | E17: =SUM(E4:E16) -> 0 | F17: =SUM(F4:F16) -> 0 | G17: =SUM(G4:G16) -> 0 | H17: =SUM(H4:H16) -> 400500 | I17: =SUM(I4:I16) -> 0 | ... M17: =SUM(M4:M16) -> 0
