Workbook
Name BANQUE: #REF!
Name BANQUE: #REF!
Name BANQUE: #REF!
Name BANQUE: #REF!
Name BANQUE: #REF!
Name BANQUE: #REF!
Name BANQUE: #REF!
Name BANQUE: #REF!
Name BANQUE: #REF!
Name BANQUE: #REF!
Name BANQUE: #REF!
Name BANQUE: #REF!
Name BANQUE: #REF!
Name BANQUE: #REF!
Name BANQUE: #REF!
Name BANQUE: #REF!
Name BANQUE: #REF!
Name BANQUE: #REF!
Name BANQUE: #REF!
Name BANQUE: #REF!
Name BANQUE: #REF!
Name BANQUE: #REF!
Name BANQUE: #REF!
Name BANQUE: #REF!
Name BANQUE: #REF!
Name BANQUE: #REF!
Name BANQUE: #REF!
Name BANQUE: #REF!
Name BANQUE: #REF!
Name BANQUE: #REF!
Name BANQUE: #REF!
Name BANQUE: #REF!
Name BANQUE: #REF!
Name BANQUE: #REF!
Name BANQUE: #REF!
Name BANQUE: #REF!
Name BANQUE: #REF!
Name BANQUE: #REF!
Name BANQUE: #REF!
Name ECHEC: #REF!
Name MODEET30000: [1]MODEVERSEMENT!$A$1:$A$3
Name MODEET30000: [2]MODEVERSEMENT!$A$1:$A$3
Name MODEET30000: [2]MODEVERSEMENT!$A$1:$A$3
Name MODEET30000: [2]MODEVERSEMENT!$A$1:$A$3
Name MODEET30000: [2]MODEVERSEMENT!$A$1:$A$3
Name MODEET30000: [2]MODEVERSEMENT!$A$1:$A$3
Name MODEET30000: [2]MODEVERSEMENT!$A$1:$A$3
Name MODEET30000: [2]MODEVERSEMENT!$A$1:$A$3
Name MODEET30000: [2]MODEVERSEMENT!$A$1:$A$3
Name MODEET30000: [2]MODEVERSEMENT!$A$1:$A$3
Name MODEET30000: [2]MODEVERSEMENT!$A$1:$A$3
Name MODEET30000: [2]MODEVERSEMENT!$A$1:$A$3
Name MODEET30000: [2]MODEVERSEMENT!$A$1:$A$3
Name MODEET30000: [2]MODEVERSEMENT!$A$1:$A$3
Name MODEET30000: [2]MODEVERSEMENT!$A$1:$A$3
Name MODEET30000: [2]MODEVERSEMENT!$A$1:$A$3
Name MODEET30000: [3]MODEVERSEMENT!$A$1:$A$3
Name MODEPAID: [4]Feuil2!$A$1:$A$3
Name MODEPAID: [5]Feuil2!$A$1:$A$3
Name MODEPAID: #REF!

Sheet TAF
A1: AIDE
A2: PRÊT
A3: REMBOURSEMENT
A4: AGIOS BANCAIRE
A5: DETAIL CHEQUE
A6: RAPPORT FINANCIER

Sheet MODEVERSEMENT
A1: BANQUE
A2: ESPECES
A3: ECHEC

Sheet MODET25000
A1: BANQUE
A2: ESPECES
A3: ECHEC

Sheet MVTDEC21
A1: ASSOCIATION | B1: ASELBY | G1: K
A2: ANNEE | B2: 2022
A3: TONTINE
J4: 44578
A5: MATRICULE | B5: NOM ET PRENOM | C5: FONDES DE DEPART | D5: RELIQUAT | E5: RETRAIT PARTIEL | F5: FONDS DEFINITIF | G5: REPARTITION INTERET | H5: CAPITAL COMPOSE | I5: SANCTION | J5: RESTE | K5: EPARGNE | L5: FONDS DE ROULEMENT | M5: FRAIS EXCEPTIONNEL | N5: COLLATION | O5: PENALITE VST ESPECES | P5: INSCRISPTION | Q5: MUTUELLE | R5: PRÊT FONDS | S5: INTERETPRET FONDS | T5: NUMERO CHEQUE | U5: REMBOURSEMENTPRET FONDS | V5: MODE VERSEMENT REMBOURSEMENT | W5: MODE VERSEMENT PRÊT | X5: NUMERO CHEQUE | Y5: PENALITE PRET FONDS | Z5: PENALITE FONDS | AA5: PENALITE ECHEC TONTINE | AB5: PENALITE RETARD TONTINE | AC5: REMBOURSEMENT TRANSPORT | AD5: CONTRIBUTION FOYER | AE5: DEPENSE FONCTIONNEMENT
A6: AS201648 | B6: =VLOOKUP(A6,[15]LISTADHERENT!$A$5:$J$50,3,0) -> ASELBY | C6: =MVTJANV23!C6 -> 0 | D6: =MVTJANV23!D6 -> 816543.52 | F6: =C6+D6-E6+K6 -> 816543.52 | G6: =$S$40/$H$40*H6 -> #REF! | H6: =F6+D6+K6 -> 1633087 | AE6: =[16]HISTOMVTDEPENSE!$T$39 -> 0
A7: AS201601 | B7: =VLOOKUP(A7,[15]LISTADHERENT!$A$5:$J$50,3,0) -> BAKOP ACHILLE | C7: =MVTJANV23!C7 -> 0 | D7: =MVTJANV23!D7 -> 0 | F7: =C7+D7-E7+K7 -> 0 | G7: =$S$40/$H$40*H7 -> #REF! | H7: =F7+D7+K7 -> 0 | Y7: 4000
A8: AS201602 | B8: =VLOOKUP(A8,[15]LISTADHERENT!$A$5:$J$50,3,0) -> BOUTCHOUANG WILLIAM | C8: =MVTJANV23!C8 -> 600000 | D8: =MVTJANV23!D8 -> 7024 | F8: =C8+D8-E8+K8 -> 610024 | G8: =$S$40/$H$40*H8 -> #REF! | H8: =F8+D8+K8 -> 620048 | I8: =VLOOKUP($A8,[16]HISTOJANV22!$A$6:$AQ$37,22,0) -> 0 | J8: =VLOOKUP($A8,[16]HISTOJANV22!$A$6:$AU$39,45,0) -> 7000 | K8: =IF(J8=0,0,J8-(L8+M8+N8)) -> 3000 | L8: =IF(J8=0,0,500) -> 500 | M8: =IF(J8=0,0,1000) -> 1000 | N8: =IF(J8=0,0,2500) -> 2500 | O8: =VLOOKUP($A8,[16]HISTOJANV22!$A$6:$AU$39,7,0) -> 0 | P8: =VLOOKUP($A8,[16]HISTOJANV22!$A$6:$AU$39,23,0) -> 0 | Q8: =VLOOKUP($A8,[16]HISTOJANV22!$A$6:$AU$39,46,0) -> 0 | R8: =VLOOKUP($A8,[16]HISTODEC21!$A$6:$AU$39,26,0) -> 525000 | S8: =R8*12/1200*12 -> 63000 | T8: =VLOOKUP($A8,[16]HISTOJANV22!$A$6:$AU$39,28,0) -> 0 | U8: =VLOOKUP($A8,[16]HISTOJANV22!$A$6:$AU$39,19,0) -> 0 | V8: =VLOOKUP($A8,[16]HISTOJANV22!$A$6:$AU$39,20,0) -> 0 | W8: =VLOOKUP($A8,[16]HISTOJANV22!$A$6:$AU$39,27,0) -> 0 | X8: =VLOOKUP($A8,[16]HISTOJANV22!$A$6:$AU$39,33,0) -> 0 | AA8: =VLOOKUP($A8,[16]HISTOJANV22!$A$6:$AU$39,43,0) -> 0 | AB8: =VLOOKUP($A8,[16]HISTOJANV22!$A$6:$AU$39,44,0) -> 0 | AC8: =VLOOKUP($A8,[16]HISTOJANV22!$A$6:$AU$39,47,0) -> 0 | AD8: =VLOOKUP(A8,[16]HISTOJANV22!$A$6:$BB$36,54,0) -> 0
A9: AS201604 | B9: =VLOOKUP(A9,[15]LISTADHERENT!$A$5:$J$50,3,0) -> DJOMO JEAN PAUL | C9: =MVTJANV23!C9 -> 600000 | D9: =MVTJANV23!D9 -> 4810 | F9: =C9+D9-E9+K9 -> 652810 | G9: =$S$40/$H$40*H9 -> #REF! | H9: =F9+D9+K9 -> 705620 | I9: =VLOOKUP($A9,[16]HISTOJANV22!$A$6:$AQ$37,22,0) -> 0 | J9: =VLOOKUP($A9,[16]HISTOJANV22!$A$6:$AU$39,45,0) -> 52000 | K9: =IF(J9=0,0,J9-(L9+M9+N9)) -> 48000 | L9: =IF(J9=0,0,500) -> 500 | M9: =IF(J9=0,0,1000) -> 1000 | N9: =IF(J9=0,0,2500) -> 2500 | O9: =VLOOKUP($A9,[16]HISTOJANV22!$A$6:$AU$39,7,0) -> 0 | P9: =VLOOKUP($A9,[16]HISTOJANV22!$A$6:$AU$39,23,0) -> 0 | Q9: =VLOOKUP($A9,[16]HISTOJANV22!$A$6:$AU$39,46,0) -> 0 | R9: =VLOOKUP($A9,[16]HISTODEC21!$A$6:$AU$39,26,0) -> 1000000 | S9: =R9*12/1200*12 -> 120000 | T9: =VLOOKUP($A9,[16]HISTOJANV22!$A$6:$AU$39,28,0) -> OKK | U9: =VLOOKUP($A9,[16]HISTOJANV22!$A$6:$AU$39,19,0) -> 0 | V9: =VLOOKUP($A9,[16]HISTOJANV22!$A$6:$AU$39,20,0) -> 0 | W9: =VLOOKUP($A9,[16]HISTOJANV22!$A$6:$AU$39,27,0) -> BANQUE | X9: =VLOOKUP($A9,[16]HISTOJANV22!$A$6:$AU$39,33,0) -> 0 | AA9: =VLOOKUP($A9,[16]HISTOJANV22!$A$6:$AU$39,43,0) -> 0 | AB9: =VLOOKUP($A9,[16]HISTOJANV22!$A$6:$AU$39,44,0) -> 0 | AC9: =VLOOKUP($A9,[16]HISTOJANV22!$A$6:$AU$39,47,0) -> 0 | AD9: =VLOOKUP(A9,[16]HISTOJANV22!$A$6:$BB$36,54,0) -> 0
A10: AS201654 | B10: =VLOOKUP(A10,[15]LISTADHERENT!$A$5:$J$50,3,0) -> DJOMOU TCHAPDA | C10: =MVTJANV23!C10 -> 600000 | D10: =MVTJANV23!D10 -> 48710 | F10: =C10+D10-E10+K10 -> 651710 | G10: =$S$40/$H$40*H10 -> #REF! | H10: =F10+D10+K10 -> 703420 | I10: =VLOOKUP($A10,[16]HISTOJANV22!$A$6:$AQ$37,22,0) -> 0 | J10: =VLOOKUP($A10,[16]HISTOJANV22!$A$6:$AU$39,45,0) -> 7000 | K10: =IF(J10=0,0,J10-(L10+M10+N10)) -> 3000 | L10: =IF(J10=0,0,500) -> 500 | M10: =IF(J10=0,0,1000) -> 1000 | N10: =IF(J10=0,0,2500) -> 2500 | O10: =VLOOKUP($A10,[16]HISTOJANV22!$A$6:$AU$39,7,0) -> 0 | P10: =VLOOKUP($A10,[16]HISTOJANV22!$A$6:$AU$39,23,0) -> 0 | Q10: =VLOOKUP($A10,[16]HISTOJANV22!$A$6:$AU$39,46,0) -> 0 | R10: =VLOOKUP($A10,[16]HISTODEC21!$A$6:$AU$39,26,0) -> #REF! | S10: =R10*1/1200*12 -> #REF! | T10: =VLOOKUP($A10,[16]HISTOJANV22!$A$6:$AU$39,28,0) -> 0 | U10: =VLOOKUP($A10,[16]HISTOJANV22!$A$6:$AU$39,19,0) -> 0 | V10: =VLOOKUP($A10,[16]HISTOJANV22!$A$6:$AU$39,20,0) -> 0 | W10: =VLOOKUP($A10,[16]HISTOJANV22!$A$6:$AU$39,27,0) -> 0 | X10: =VLOOKUP($A10,[16]HISTOJANV22!$A$6:$AU$39,33,0) -> 0 | AA10: =VLOOKUP($A10,[16]HISTOJANV22!$A$6:$AU$39,43,0) -> 0 | AB10: =VLOOKUP($A10,[16]HISTOJANV22!$A$6:$AU$39,44,0) -> 0 | AC10: =VLOOKUP($A10,[16]HISTOJANV22!$A$6:$AU$39,47,0) -> 0 | AD10: =VLOOKUP(A10,[16]HISTOJANV22!$A$6:$BB$36,54,0) -> 0
A11: AS201605 | B11: =VLOOKUP(A11,[15]LISTADHERENT!$A$5:$J$50,3,0) -> DJOUKWE NANGUEN GUY BLAISE | C11: =MVTJANV23!C11 -> 600000 | D11: =MVTJANV23!D11 -> 4750 | F11: =C11+D11-E11+K11 -> 612750 | G11: =$S$40/$H$40*H11 -> #REF! | H11: =F11+D11+K11 -> 625500 | I11: =VLOOKUP($A11,[16]HISTOJANV22!$A$6:$AQ$37,22,0) -> 0 | J11: =VLOOKUP($A11,[16]HISTOJANV22!$A$6:$AU$39,45,0) -> 12000 | K11: =IF(J11=0,0,J11-(L11+M11+N11)) -> 8000 | L11: =IF(J11=0,0,500) -> 500 | M11: =IF(J11=0,0,1000) -> 1000 | N11: =IF(J11=0,0,2500) -> 2500 | O11: =VLOOKUP($A11,[16]HISTOJANV22!$A$6:$AU$39,7,0) -> 0 | P11: =VLOOKUP($A11,[16]HISTOJANV22!$A$6:$AU$39,23,0) -> 0 | Q11: =VLOOKUP($A11,[16]HISTOJANV22!$A$6:$AU$39,46,0) -> 0 | R11: =VLOOKUP($A11,[16]HISTODEC21!$A$6:$AU$39,26,0) -> 1000000 | S11: =R11*1/1200*12 -> 10000 | T11: =VLOOKUP($A11,[16]HISTOJANV22!$A$6:$AU$39,28,0) -> OKK | U11: =VLOOKUP($A11,[16]HISTOJANV22!$A$6:$AU$39,19,0) -> 0 | V11: =VLOOKUP($A11,[16]HISTOJANV22!$A$6:$AU$39,20,0) -> 0 | W11: =VLOOKUP($A11,[16]HISTOJANV22!$A$6:$AU$39,27,0) -> BANQUE | X11: =VLOOKUP($A11,[16]HISTOJANV22!$A$6:$AU$39,33,0) -> 0 | Y11: 29000 | AA11: =VLOOKUP($A11,[16]HISTOJANV22!$A$6:$AU$39,43,0) -> 0 | AB11: =VLOOKUP($A11,[16]HISTOJANV22!$A$6:$AU$39,44,0) -> 0 | AC11: =VLOOKUP($A11,[16]HISTOJANV22!$A$6:$AU$39,47,0) -> 0 | AD11: =VLOOKUP(A11,[16]HISTOJANV22!$A$6:$BB$36,54,0) -> 0
A12: AS201608 | B12: =VLOOKUP(A12,[15]LISTADHERENT!$A$5:$J$50,3,0) -> DJUOMBESSY ANTOINE | C12: =MVTJANV23!C12 -> 600000 | D12: =MVTJANV23!D12 -> 10719 | F12: =C12+D12-E12+K12 -> 613719 | G12: =$S$40/$H$40*H12 -> #REF! | H12: =F12+D12+K12 -> 627438 | I12: =VLOOKUP($A12,[16]HISTOJANV22!$A$6:$AQ$37,22,0) -> 0 | J12: =VLOOKUP($A12,[16]HISTOJANV22!$A$6:$AU$39,45,0) -> 7000 | K12: =IF(J12=0,0,J12-(L12+M12+N12)) -> 3000 | L12: =IF(J12=0,0,500) -> 500 | M12: =IF(J12=0,0,1000) -> 1000 | N12: =IF(J12=0,0,2500) -> 2500 | O12: =VLOOKUP($A12,[16]HISTOJANV22!$A$6:$AU$39,7,0) -> 0 | P12: =VLOOKUP($A12,[16]HISTOJANV22!$A$6:$AU$39,23,0) -> 0 | Q12: =VLOOKUP($A12,[16]HISTOJANV22!$A$6:$AU$39,46,0) -> 0 | R12: =VLOOKUP($A12,[16]HISTODEC21!$A$6:$AU$39,26,0) -> 1029000 | S12: =R12*12/1200*12 -> 123480 | T12: =VLOOKUP($A12,[16]HISTOJANV22!$A$6:$AU$39,28,0) -> 0 | U12: =VLOOKUP($A12,[16]HISTOJANV22!$A$6:$AU$39,19,0) -> 1000000 | V12: =VLOOKUP($A12,[16]HISTOJANV22!$A$6:$AU$39,20,0) -> BANQUE | W12: =VLOOKUP($A12,[16]HISTOJANV22!$A$6:$AU$39,27,0) -> 0 | X12: =VLOOKUP($A12,[16]HISTOJANV22!$A$6:$AU$39,33,0) -> 0 | AA12: =VLOOKUP($A12,[16]HISTOJANV22!$A$6:$AU$39,43,0) -> 0 | AB12: =VLOOKUP($A12,[16]HISTOJANV22!$A$6:$AU$39,44,0) -> 0 | AC12: =VLOOKUP($A12,[16]HISTOJANV22!$A$6:$AU$39,47,0) -> 0 | AD12: =VLOOKUP(A12,[16]HISTOJANV22!$A$6:$BB$36,54,0) -> 61000
A13: AS201651 | B13: =VLOOKUP(A13,[15]LISTADHERENT!$A$5:$J$50,3,0) -> DOMOU FABIEN | C13: =MVTJANV23!C13 -> 600000 | D13: =MVTJANV23!D13 -> 584 | F13: =C13+D13-E13+K13 -> 608584 | G13: =$S$40/$H$40*H13 -> #REF! | H13: =F13+D13+K13 -> 617168 | I13: =VLOOKUP($A13,[16]HISTOJANV22!$A$6:$AQ$37,22,0) -> 0 | J13: =VLOOKUP($A13,[16]HISTOJANV22!$A$6:$AU$39,45,0) -> 12000 | K13: =IF(J13=0,0,J13-(L13+M13+N13)) -> 8000 | L13: =IF(J13=0,0,500) -> 500 | M13: =IF(J13=0,0,1000) -> 1000 | N13: =IF(J13=0,0,2500) -> 2500 | O13: =VLOOKUP($A13,[16]HISTOJANV22!$A$6:$AU$39,7,0) -> 0 | P13: =VLOOKUP($A13,[16]HISTOJANV22!$A$6:$AU$39,23,0) -> 0 | Q13: =VLOOKUP($A13,[16]HISTOJANV22!$A$6:$AU$39,46,0) -> 0 | R13: =VLOOKUP($A13,[16]HISTODEC21!$A$6:$AU$39,26,0) -> 1000000 | S13: =R13*12/1200*12 -> 120000 | T13: =VLOOKUP($A13,[16]HISTOJANV22!$A$6:$AU$39,28,0) -> OKK | U13: =VLOOKUP($A13,[16]HISTOJANV22!$A$6:$AU$39,19,0) -> 0 | V13: =VLOOKUP($A13,[16]HISTOJANV22!$A$6:$AU$39,20,0) -> 0 | W13: =VLOOKUP($A13,[16]HISTOJANV22!$A$6:$AU$39,27,0) -> BANQUE | X13: =VLOOKUP($A13,[16]HISTOJANV22!$A$6:$AU$39,33,0) -> 0 | AA13: =VLOOKUP($A13,[16]HISTOJANV22!$A$6:$AU$39,43,0) -> 0 | AB13: =VLOOKUP($A13,[16]HISTOJANV22!$A$6:$AU$39,44,0) -> 0 | AC13: =VLOOKUP($A13,[16]HISTOJANV22!$A$6:$AU$39,47,0) -> 0 | AD13: =VLOOKUP(A13,[16]HISTOJANV22!$A$6:$BB$36,54,0) -> 57000
A14: AS201609 | B14: =VLOOKUP(A14,[15]LISTADHERENT!$A$5:$J$50,3,0) -> DONHOU DAVID | C14: =MVTJANV23!C14 -> 600000 | D14: =MVTJANV23!D14 -> 458343 | F14: =C14+D14-E14+K14 -> 1061343 | G14: =$S$40/$H$40*H14 -> #REF! | H14: =F14+D14+K14 -> 1522686 | I14: =VLOOKUP($A14,[16]HISTOJANV22!$A$6:$AQ$37,22,0) -> 0 | J14: =VLOOKUP($A14,[16]HISTOJANV22!$A$6:$AU$39,45,0) -> 7000 | K14: =IF(J14=0,0,J14-(L14+M14+N14)) -> 3000 | L14: =IF(J14=0,0,500) -> 500 | M14: =IF(J14=0,0,1000) -> 1000 | N14: =IF(J14=0,0,2500) -> 2500 | O14: =VLOOKUP($A14,[16]HISTOJANV22!$A$6:$AU$39,7,0) -> 0 | P14: =VLOOKUP($A14,[16]HISTOJANV22!$A$6:$AU$39,23,0) -> 0 | Q14: =VLOOKUP($A14,[16]HISTOJANV22!$A$6:$AU$39,46,0) -> 0 | R14: =VLOOKUP($A14,[16]HISTODEC21!$A$6:$AU$39,26,0) -> #REF! | S14: =R14*0/1200*12 -> #REF! | T14: =VLOOKUP($A14,[16]HISTOJANV22!$A$6:$AU$39,28,0) -> 0 | U14: =VLOOKUP($A14,[16]HISTOJANV22!$A$6:$AU$39,19,0) -> 0 | V14: =VLOOKUP($A14,[16]HISTOJANV22!$A$6:$AU$39,20,0) -> 0 | W14: =VLOOKUP($A14,[16]HISTOJANV22!$A$6:$AU$39,27,0) -> 0 | X14: =VLOOKUP($A14,[16]HISTOJANV22!$A$6:$AU$39,33,0) -> 0 | Y14: 155000 | AA14: =VLOOKUP($A14,[16]HISTOJANV22!$A$6:$AU$39,43,0) -> 0 | AB14: =VLOOKUP($A14,[16]HISTOJANV22!$A$6:$AU$39,44,0) -> 0 | AC14: =VLOOKUP($A14,[16]HISTOJANV22!$A$6:$AU$39,47,0) -> 0 | AD14: =VLOOKUP(A14,[16]HISTOJANV22!$A$6:$BB$36,54,0) -> 70000
A15: AS201611 | B15: =VLOOKUP(A15,[15]LISTADHERENT!$A$5:$J$50,3,0) -> HENGUE PAUL OMER | C15: =MVTJANV23!C15 -> 600000 | D15: =MVTJANV23!D15 -> 51112 | F15: =C15+D15-E15+K15 -> 654112 | G15: =$S$40/$H$40*H15 -> #REF! | H15: =F15+D15+K15 -> 708224 | I15: =VLOOKUP($A15,[16]HISTOJANV22!$A$6:$AQ$37,22,0) -> 0 | J15: =VLOOKUP($A15,[16]HISTOJANV22!$A$6:$AU$39,45,0) -> 7000 | K15: =IF(J15=0,0,J15-(L15+M15+N15)) -> 3000 | L15: =IF(J15=0,0,500) -> 500 | M15: =IF(J15=0,0,1000) -> 1000 | N15: =IF(J15=0,0,2500) -> 2500 | O15: =VLOOKUP($A15,[16]HISTOJANV22!$A$6:$AU$39,7,0) -> 0 | P15: =VLOOKUP($A15,[16]HISTOJANV22!$A$6:$AU$39,23,0) -> 0 | Q15: =VLOOKUP($A15,[16]HISTOJANV22!$A$6:$AU$39,46,0) -> 0 | R15: =VLOOKUP($A15,[16]HISTODEC21!$A$6:$AU$39,26,0) -> #REF! | S15: =R15*12/1200*12 -> #REF! | T15: =VLOOKUP($A15,[16]HISTOJANV22!$A$6:$AU$39,28,0) -> 0 | U15: =VLOOKUP($A15,[16]HISTOJANV22!$A$6:$AU$39,19,0) -> 0 | V15: =VLOOKUP($A15,[16]HISTOJANV22!$A$6:$AU$39,20,0) -> 0 | W15: =VLOOKUP($A15,[16]HISTOJANV22!$A$6:$AU$39,27,0) -> 0 | X15: =VLOOKUP($A15,[16]HISTOJANV22!$A$6:$AU$39,33,0) -> 0 | AA15: =VLOOKUP($A15,[16]HISTOJANV22!$A$6:$AU$39,43,0) -> 0 | AB15: =VLOOKUP($A15,[16]HISTOJANV22!$A$6:$AU$39,44,0) -> 0 | AC15: =VLOOKUP($A15,[16]HISTOJANV22!$A$6:$AU$39,47,0) -> 0 | AD15: =VLOOKUP(A15,[16]HISTOJANV22!$A$6:$BB$36,54,0) -> 0
A16: AS201613 | B16: =VLOOKUP(A16,[15]LISTADHERENT!$A$5:$J$50,3,0) -> HOTCHO BENJAMIN | C16: =MVTJANV23!C16 -> 600000 | D16: =MVTJANV23!D16 -> 16230 | F16: =C16+D16-E16+K16 -> 664230 | G16: =$S$40/$H$40*H16 -> #REF! | H16: =F16+D16+K16 -> 728460 | I16: =VLOOKUP($A16,[16]HISTOJANV22!$A$6:$AQ$37,22,0) -> 0 | J16: =VLOOKUP($A16,[16]HISTOJANV22!$A$6:$AU$39,45,0) -> 52000 | K16: =IF(J16=0,0,J16-(L16+M16+N16)) -> 48000 | L16: =IF(J16=0,0,500) -> 500 | M16: =IF(J16=0,0,1000) -> 1000 | N16: =IF(J16=0,0,2500) -> 2500 | O16: =VLOOKUP($A16,[16]HISTOJANV22!$A$6:$AU$39,7,0) -> 0 | P16: =VLOOKUP($A16,[16]HISTOJANV22!$A$6:$AU$39,23,0) -> 0 | Q16: =VLOOKUP($A16,[16]HISTOJANV22!$A$6:$AU$39,46,0) -> 0 | R16: =VLOOKUP($A16,[16]HISTODEC21!$A$6:$AU$39,26,0) -> #REF! | S16: =R16*12/1200*12 -> #REF! | T16: =VLOOKUP($A16,[16]HISTOJANV22!$A$6:$AU$39,28,0) -> 0 | U16: =VLOOKUP($A16,[16]HISTOJANV22!$A$6:$AU$39,19,0) -> 0 | V16: =VLOOKUP($A16,[16]HISTOJANV22!$A$6:$AU$39,20,0) -> 0 | W16: =VLOOKUP($A16,[16]HISTOJANV22!$A$6:$AU$39,27,0) -> 0 | X16: =VLOOKUP($A16,[16]HISTOJANV22!$A$6:$AU$39,33,0) -> 0 | AA16: =VLOOKUP($A16,[16]HISTOJANV22!$A$6:$AU$39,43,0) -> 0 | AB16: =VLOOKUP($A16,[16]HISTOJANV22!$A$6:$AU$39,44,0) -> 0 | AC16: =VLOOKUP($A16,[16]HISTOJANV22!$A$6:$AU$39,47,0) -> 0 | AD16: =VLOOKUP(A16,[16]HISTOJANV22!$A$6:$BB$36,54,0) -> 70000
A17: AS201617 | B17: =VLOOKUP(A17,[15]LISTADHERENT!$A$5:$J$50,3,0) -> KOUAMOU MOISE | C17: =MVTJANV23!C17 -> 600000 | D17: =MVTJANV23!D17 -> 53293 | F17: =C17+D17-E17+K17 -> 656293 | G17: =$S$40/$H$40*H17 -> #REF! | H17: =F17+D17+K17 -> 712586 | I17: =VLOOKUP($A17,[16]HISTOJANV22!$A$6:$AQ$37,22,0) -> 0 | J17: =VLOOKUP($A17,[16]HISTOJANV22!$A$6:$AU$39,45,0) -> 7000 | K17: =IF(J17=0,0,J17-(L17+M17+N17)) -> 3000 | L17: =IF(J17=0,0,500) -> 500 | M17: =IF(J17=0,0,1000) -> 1000 | N17: =IF(J17=0,0,2500) -> 2500 | O17: =VLOOKUP($A17,[16]HISTOJANV22!$A$6:$AU$39,7,0) -> 0 | P17: =VLOOKUP($A17,[16]HISTOJANV22!$A$6:$AU$39,23,0) -> 0 | Q17: =VLOOKUP($A17,[16]HISTOJANV22!$A$6:$AU$39,46,0) -> 0 | R17: =VLOOKUP($A17,[16]HISTODEC21!$A$6:$AU$39,26,0) -> #REF! | S17: =R17*12/1200*12 -> #REF! | T17: =VLOOKUP($A17,[16]HISTOJANV22!$A$6:$AU$39,28,0) -> 0 | U17: =VLOOKUP($A17,[16]HISTOJANV22!$A$6:$AU$39,19,0) -> 0 | V17: =VLOOKUP($A17,[16]HISTOJANV22!$A$6:$AU$39,20,0) -> 0 | W17: =VLOOKUP($A17,[16]HISTOJANV22!$A$6:$AU$39,27,0) -> 0 | X17: =VLOOKUP($A17,[16]HISTOJANV22!$A$6:$AU$39,33,0) -> 0 | AA17: =VLOOKUP($A17,[16]HISTOJANV22!$A$6:$AU$39,43,0) -> 0 | AB17: =VLOOKUP($A17,[16]HISTOJANV22!$A$6:$AU$39,44,0) -> 0 | AC17: =VLOOKUP($A17,[16]HISTOJANV22!$A$6:$AU$39,47,0) -> 0 | AD17: =VLOOKUP(A17,[16]HISTOJANV22!$A$6:$BB$36,54,0) -> 0
A18: AS201619 | B18: =VLOOKUP(A18,[15]LISTADHERENT!$A$5:$J$50,3,0) -> KOUATCHO MESSACK | C18: =MVTJANV23!C18 -> 600000 | D18: =MVTJANV23!D18 -> 6459 | F18: =C18+D18-E18+K18 -> 609459 | G18: =$S$40/$H$40*H18 -> #REF! | H18: =F18+D18+K18 -> 618918 | I18: =VLOOKUP($A18,[16]HISTOJANV22!$A$6:$AQ$37,22,0) -> 0 | J18: =VLOOKUP($A18,[16]HISTOJANV22!$A$6:$AU$39,45,0) -> 7000 | K18: =IF(J18=0,0,J18-(L18+M18+N18)) -> 3000 | L18: =IF(J18=0,0,500) -> 500 | M18: =IF(J18=0,0,1000) -> 1000 | N18: =IF(J18=0,0,2500) -> 2500 | O18: =VLOOKUP($A18,[16]HISTOJANV22!$A$6:$AU$39,7,0) -> 0 | P18: =VLOOKUP($A18,[16]HISTOJANV22!$A$6:$AU$39,23,0) -> 0 | Q18: =VLOOKUP($A18,[16]HISTOJANV22!$A$6:$AU$39,46,0) -> 0 | R18: =VLOOKUP($A18,[16]HISTODEC21!$A$6:$AU$39,26,0) -> 1000000 | S18: =R18*12/1200*12 -> 120000 | T18: =VLOOKUP($A18,[16]HISTOJANV22!$A$6:$AU$39,28,0) -> OKK | U18: =VLOOKUP($A18,[16]HISTOJANV22!$A$6:$AU$39,19,0) -> 0 | V18: =VLOOKUP($A18,[16]HISTOJANV22!$A$6:$AU$39,20,0) -> 0 | W18: =VLOOKUP($A18,[16]HISTOJANV22!$A$6:$AU$39,27,0) -> BANQUE | X18: =VLOOKUP($A18,[16]HISTOJANV22!$A$6:$AU$39,33,0) -> 0 | AA18: =VLOOKUP($A18,[16]HISTOJANV22!$A$6:$AU$39,43,0) -> 0 | AB18: =VLOOKUP($A18,[16]HISTOJANV22!$A$6:$AU$39,44,0) -> 0 | AC18: =VLOOKUP($A18,[16]HISTOJANV22!$A$6:$AU$39,47,0) -> 0 | AD18: =VLOOKUP(A18,[16]HISTOJANV22!$A$6:$BB$36,54,0) -> 0
A19: AS201620 | B19: =VLOOKUP(A19,[15]LISTADHERENT!$A$5:$J$50,3,0) -> LOWE JEAN | C19: =MVTJANV23!C19 -> 600000 | D19: =MVTJANV23!D19 -> 746 | F19: =C19+D19-E19+K19 -> 603746 | G19: =$S$40/$H$40*H19 -> #REF! | H19: =F19+D19+K19 -> 607492 | I19: =VLOOKUP($A19,[16]HISTOJANV22!$A$6:$AQ$37,22,0) -> 0 | J19: =VLOOKUP($A19,[16]HISTOJANV22!$A$6:$AU$39,45,0) -> 7000 | K19: =IF(J19=0,0,J19-(L19+M19+N19)) -> 3000 | L19: =IF(J19=0,0,500) -> 500 | M19: =IF(J19=0,0,1000) -> 1000 | N19: =IF(J19=0,0,2500) -> 2500 | O19: =VLOOKUP($A19,[16]HISTOJANV22!$A$6:$AU$39,7,0) -> 0 | P19: =VLOOKUP($A19,[16]HISTOJANV22!$A$6:$AU$39,23,0) -> 0 | Q19: =VLOOKUP($A19,[16]HISTOJANV22!$A$6:$AU$39,46,0) -> 0 | R19: =VLOOKUP($A19,[16]HISTODEC21!$A$6:$AU$39,26,0) -> 500000 | S19: =R19*12/1200*12 -> 60000 | T19: =VLOOKUP($A19,[16]HISTOJANV22!$A$6:$AU$39,28,0) -> OKK | U19: =VLOOKUP($A19,[16]HISTOJANV22!$A$6:$AU$39,19,0) -> 0 | V19: =VLOOKUP($A19,[16]HISTOJANV22!$A$6:$AU$39,20,0) -> 0 | W19: =VLOOKUP($A19,[16]HISTOJANV22!$A$6:$AU$39,27,0) -> BANQUE | X19: =VLOOKUP($A19,[16]HISTOJANV22!$A$6:$AU$39,33,0) -> 0 | AA19: =VLOOKUP($A19,[16]HISTOJANV22!$A$6:$AU$39,43,0) -> 0 | AB19: =VLOOKUP($A19,[16]HISTOJANV22!$A$6:$AU$39,44,0) -> 0 | AC19: =VLOOKUP($A19,[16]HISTOJANV22!$A$6:$AU$39,47,0) -> 0 | AD19: =VLOOKUP(A19,[16]HISTOJANV22!$A$6:$BB$36,54,0) -> 0
A20: AS201649 | B20: =VLOOKUP(A20,[15]LISTADHERENT!$A$5:$J$50,3,0) -> MBOGNING TUGMA GUY | C20: =MVTJANV23!C20 -> 600000 | D20: =MVTJANV23!D20 -> 47746 | F20: =C20+D20-E20+K20 -> 650746 | G20: =$S$40/$H$40*H20 -> #REF! | H20: =F20+D20+K20 -> 701492 | I20: =VLOOKUP($A20,[16]HISTOJANV22!$A$6:$AQ$37,22,0) -> 0 | J20: =VLOOKUP($A20,[16]HISTOJANV22!$A$6:$AU$39,45,0) -> 7000 | K20: =IF(J20=0,0,J20-(L20+M20+N20)) -> 3000 | L20: =IF(J20=0,0,500) -> 500 | M20: =IF(J20=0,0,1000) -> 1000 | N20: =IF(J20=0,0,2500) -> 2500 | O20: =VLOOKUP($A20,[16]HISTOJANV22!$A$6:$AU$39,7,0) -> 0 | P20: =VLOOKUP($A20,[16]HISTOJANV22!$A$6:$AU$39,23,0) -> 0 | Q20: =VLOOKUP($A20,[16]HISTOJANV22!$A$6:$AU$39,46,0) -> 0 | R20: =VLOOKUP($A20,[16]HISTODEC21!$A$6:$AU$39,26,0) -> 1050000 | S20: =R20*12/1200*12 -> 126000 | T20: =VLOOKUP($A20,[16]HISTOJANV22!$A$6:$AU$39,28,0) -> 0 | U20: =VLOOKUP($A20,[16]HISTOJANV22!$A$6:$AU$39,19,0) -> 1050000 | V20: =VLOOKUP($A20,[16]HISTOJANV22!$A$6:$AU$39,20,0) -> BANQUE | W20: =VLOOKUP($A20,[16]HISTOJANV22!$A$6:$AU$39,27,0) -> BANQUE | X20: =VLOOKUP($A20,[16]HISTOJANV22!$A$6:$AU$39,33,0) -> 0 | AA20: =VLOOKUP($A20,[16]HISTOJANV22!$A$6:$AU$39,43,0) -> 0 | AB20: =VLOOKUP($A20,[16]HISTOJANV22!$A$6:$AU$39,44,0) -> 0 | AC20: =VLOOKUP($A20,[16]HISTOJANV22!$A$6:$AU$39,47,0) -> 0 | AD20: =VLOOKUP(A20,[16]HISTOJANV22!$A$6:$BB$36,54,0) -> 0
A21: AS201639 | B21: =VLOOKUP(A21,[15]LISTADHERENT!$A$5:$J$50,3,0) -> NANGUEN MARTIN | C21: =MVTJANV23!C21 -> 600000 | D21: =MVTJANV23!D21 -> 51343 | F21: =C21+D21-E21+K21 -> 654343 | G21: =$S$40/$H$40*H21 -> #REF! | H21: =F21+D21+K21 -> 708686 | I21: =VLOOKUP($A21,[16]HISTOJANV22!$A$6:$AQ$37,22,0) -> 0 | J21: =VLOOKUP($A21,[16]HISTOJANV22!$A$6:$AU$39,45,0) -> 7000 | K21: =IF(J21=0,0,J21-(L21+M21+N21)) -> 3000 | L21: =IF(J21=0,0,500) -> 500 | M21: =IF(J21=0,0,1000) -> 1000 | N21: =IF(J21=0,0,2500) -> 2500 | O21: =VLOOKUP($A21,[16]HISTOJANV22!$A$6:$AU$39,7,0) -> 0 | P21: =VLOOKUP($A21,[16]HISTOJANV22!$A$6:$AU$39,23,0) -> 0 | Q21: =VLOOKUP($A21,[16]HISTOJANV22!$A$6:$AU$39,46,0) -> 0 | R21: =VLOOKUP($A21,[16]HISTODEC21!$A$6:$AU$39,26,0) -> #REF! | S21: =R21*12/1200*12 -> #REF! | T21: =VLOOKUP($A21,[16]HISTOJANV22!$A$6:$AU$39,28,0) -> 0 | U21: =VLOOKUP($A21,[16]HISTOJANV22!$A$6:$AU$39,19,0) -> 0 | V21: =VLOOKUP($A21,[16]HISTOJANV22!$A$6:$AU$39,20,0) -> 0 | W21: =VLOOKUP($A21,[16]HISTOJANV22!$A$6:$AU$39,27,0) -> 0 | X21: =VLOOKUP($A21,[16]HISTOJANV22!$A$6:$AU$39,33,0) -> 0 | AA21: =VLOOKUP($A21,[16]HISTOJANV22!$A$6:$AU$39,43,0) -> 0 | AB21: =VLOOKUP($A21,[16]HISTOJANV22!$A$6:$AU$39,44,0) -> 0 | AC21: =VLOOKUP($A21,[16]HISTOJANV22!$A$6:$AU$39,47,0) -> 0 | AD21: =VLOOKUP(A21,[16]HISTOJANV22!$A$6:$BB$36,54,0) -> 0
A22: AS201621 | B22: =VLOOKUP(A22,[15]LISTADHERENT!$A$5:$J$50,3,0) -> NANKAM APPOLINAIRE | C22: =MVTJANV23!C22 -> 600000 | D22: =MVTJANV23!D22 -> 140918 | F22: =C22+D22-E22+K22 -> 743918 | G22: =$S$40/$H$40*H22 -> #REF! | H22: =F22+D22+K22 -> 887836 | I22: =VLOOKUP($A22,[16]HISTOJANV22!$A$6:$AQ$37,22,0) -> 0 | J22: =VLOOKUP($A22,[16]HISTOJANV22!$A$6:$AU$39,45,0) -> 7000 | K22: =IF(J22=0,0,J22-(L22+M22+N22)) -> 3000 | L22: =IF(J22=0,0,500) -> 500 | M22: =IF(J22=0,0,1000) -> 1000 | N22: =IF(J22=0,0,2500) -> 2500 | O22: =VLOOKUP($A22,[16]HISTOJANV22!$A$6:$AU$39,7,0) -> 0 | P22: =VLOOKUP($A22,[16]HISTOJANV22!$A$6:$AU$39,23,0) -> 0 | Q22: =VLOOKUP($A22,[16]HISTOJANV22!$A$6:$AU$39,46,0) -> 0 | R22: =VLOOKUP($A22,[16]HISTODEC21!$A$6:$AU$39,26,0) -> 924000 | S22: =R22*12/1200*12 -> 110880 | T22: =VLOOKUP($A22,[16]HISTOJANV22!$A$6:$AU$39,28,0) -> 0 | U22: =VLOOKUP($A22,[16]HISTOJANV22!$A$6:$AU$39,19,0) -> 924000 | V22: =VLOOKUP($A22,[16]HISTOJANV22!$A$6:$AU$39,20,0) -> BANQUE | W22: =VLOOKUP($A22,[16]HISTOJANV22!$A$6:$AU$39,27,0) -> 0 | X22: =VLOOKUP($A22,[16]HISTOJANV22!$A$6:$AU$39,33,0) -> 0 | Y22: 50000 | AA22: =VLOOKUP($A22,[16]HISTOJANV22!$A$6:$AU$39,43,0) -> 0 | AB22: =VLOOKUP($A22,[16]HISTOJANV22!$A$6:$AU$39,44,0) -> 0 | AC22: =VLOOKUP($A22,[16]HISTOJANV22!$A$6:$AU$39,47,0) -> 0 | AD22: =VLOOKUP(A22,[16]HISTOJANV22!$A$6:$BB$36,54,0) -> 0
A23: AS201622 | B23: =VLOOKUP(A23,[15]LISTADHERENT!$A$5:$J$50,3,0) -> NDJOMO ETIENNE | C23: =MVTJANV23!C23 -> 600000 | D23: =MVTJANV23!D23 -> 283210 | F23: =C23+D23-E23+K23 -> 896210 | G23: =$S$40/$H$40*H23 -> #REF! | H23: =F23+D23+K23 -> 1192420 | I23: =VLOOKUP($A23,[16]HISTOJANV22!$A$6:$AQ$37,22,0) -> 0 | J23: =VLOOKUP($A23,[16]HISTOJANV22!$A$6:$AU$39,45,0) -> 17000 | K23: =IF(J23=0,0,J23-(L23+M23+N23)) -> 13000 | L23: =IF(J23=0,0,500) -> 500 | M23: =IF(J23=0,0,1000) -> 1000 | N23: =IF(J23=0,0,2500) -> 2500 | O23: =VLOOKUP($A23,[16]HISTOJANV22!$A$6:$AU$39,7,0) -> 0 | P23: =VLOOKUP($A23,[16]HISTOJANV22!$A$6:$AU$39,23,0) -> 0 | Q23: =VLOOKUP($A23,[16]HISTOJANV22!$A$6:$AU$39,46,0) -> 0 | R23: =VLOOKUP($A23,[16]HISTODEC21!$A$6:$AU$39,26,0) -> 500000 | S23: =R23*12/1200*12 -> 60000 | T23: =VLOOKUP($A23,[16]HISTOJANV22!$A$6:$AU$39,28,0) -> OKK | U23: =VLOOKUP($A23,[16]HISTOJANV22!$A$6:$AU$39,19,0) -> 0 | V23: =VLOOKUP($A23,[16]HISTOJANV22!$A$6:$AU$39,20,0) -> 0 | W23: =VLOOKUP($A23,[16]HISTOJANV22!$A$6:$AU$39,27,0) -> BANQUE | X23: =VLOOKUP($A23,[16]HISTOJANV22!$A$6:$AU$39,33,0) -> 0 | AA23: =VLOOKUP($A23,[16]HISTOJANV22!$A$6:$AU$39,43,0) -> 0 | AB23: =VLOOKUP($A23,[16]HISTOJANV22!$A$6:$AU$39,44,0) -> 0 | AC23: =VLOOKUP($A23,[16]HISTOJANV22!$A$6:$AU$39,47,0) -> 0 | AD23: =VLOOKUP(A23,[16]HISTOJANV22!$A$6:$BB$36,54,0) -> 0
A24: AS201624 | B24: =VLOOKUP(A24,[15]LISTADHERENT!$A$5:$J$50,3,0) -> NGONDIEP CLAUDE | C24: =MVTJANV23!C24 -> 600000 | D24: =MVTJANV23!D24 -> 39787 | F24: =C24+D24-E24+K24 -> 647787 | G24: =$S$40/$H$40*H24 -> #REF! | H24: =F24+D24+K24 -> 695574 | I24: =VLOOKUP($A24,[16]HISTOJANV22!$A$6:$AQ$37,22,0) -> 0 | J24: =VLOOKUP($A24,[16]HISTOJANV22!$A$6:$AU$39,45,0) -> 12000 | K24: =IF(J24=0,0,J24-(L24+M24+N24)) -> 8000 | L24: =IF(J24=0,0,500) -> 500 | M24: =IF(J24=0,0,1000) -> 1000 | N24: =IF(J24=0,0,2500) -> 2500 | O24: =VLOOKUP($A24,[16]HISTOJANV22!$A$6:$AU$39,7,0) -> 0 | P24: =VLOOKUP($A24,[16]HISTOJANV22!$A$6:$AU$39,23,0) -> 0 | Q24: =VLOOKUP($A24,[16]HISTOJANV22!$A$6:$AU$39,46,0) -> 0 | R24: =VLOOKUP($A24,[16]HISTODEC21!$A$6:$AU$39,26,0) -> 1000000 | S24: =R24*12/1200*12 -> 120000 | T24: =VLOOKUP($A24,[16]HISTOJANV22!$A$6:$AU$39,28,0) -> OKK | U24: =VLOOKUP($A24,[16]HISTOJANV22!$A$6:$AU$39,19,0) -> 0 | V24: =VLOOKUP($A24,[16]HISTOJANV22!$A$6:$AU$39,20,0) -> 0 | W24: =VLOOKUP($A24,[16]HISTOJANV22!$A$6:$AU$39,27,0) -> BANQUE | X24: =VLOOKUP($A24,[16]HISTOJANV22!$A$6:$AU$39,33,0) -> 0 | AA24: =VLOOKUP($A24,[16]HISTOJANV22!$A$6:$AU$39,43,0) -> 0 | AB24: =VLOOKUP($A24,[16]HISTOJANV22!$A$6:$AU$39,44,0) -> 0 | AC24: =VLOOKUP($A24,[16]HISTOJANV22!$A$6:$AU$39,47,0) -> 0 | AD24: =VLOOKUP(A24,[16]HISTOJANV22!$A$6:$BB$36,54,0) -> 70000
A25: AS201626 | B25: =VLOOKUP(A25,[15]LISTADHERENT!$A$5:$J$50,3,0) -> NGUIEMEGNI MATHIEU BLAISE | C25: =MVTJANV23!C25 -> 600000 | D25: =MVTJANV23!D25 -> 13696 | F25: =C25+D25-E25+K25 -> 616696 | G25: =$S$40/$H$40*H25 -> #REF! | H25: =F25+D25+K25 -> 633392 | I25: =VLOOKUP($A25,[16]HISTOJANV22!$A$6:$AQ$37,22,0) -> 0 | J25: =VLOOKUP($A25,[16]HISTOJANV22!$A$6:$AU$39,45,0) -> 7000 | K25: =IF(J25=0,0,J25-(L25+M25+N25)) -> 3000 | L25: =IF(J25=0,0,500) -> 500 | M25: =IF(J25=0,0,1000) -> 1000 | N25: =IF(J25=0,0,2500) -> 2500 | O25: =VLOOKUP($A25,[16]HISTOJANV22!$A$6:$AU$39,7,0) -> 0 | P25: =VLOOKUP($A25,[16]HISTOJANV22!$A$6:$AU$39,23,0) -> 0 | Q25: =VLOOKUP($A25,[16]HISTOJANV22!$A$6:$AU$39,46,0) -> 0 | R25: =VLOOKUP($A25,[16]HISTODEC21!$A$6:$AU$39,26,0) -> 1000000 | S25: =R25*12/1200*12 -> 120000 | T25: =VLOOKUP($A25,[16]HISTOJANV22!$A$6:$AU$39,28,0) -> OKK | U25: =VLOOKUP($A25,[16]HISTOJANV22!$A$6:$AU$39,19,0) -> 0 | V25: =VLOOKUP($A25,[16]HISTOJANV22!$A$6:$AU$39,20,0) -> 0 | W25: =VLOOKUP($A25,[16]HISTOJANV22!$A$6:$AU$39,27,0) -> BANQUE | X25: =VLOOKUP($A25,[16]HISTOJANV22!$A$6:$AU$39,33,0) -> 0 | AA25: =VLOOKUP($A25,[16]HISTOJANV22!$A$6:$AU$39,43,0) -> 0 | AB25: =VLOOKUP($A25,[16]HISTOJANV22!$A$6:$AU$39,44,0) -> 0 | AC25: =VLOOKUP($A25,[16]HISTOJANV22!$A$6:$AU$39,47,0) -> 0 | AD25: =VLOOKUP(A25,[16]HISTOJANV22!$A$6:$BB$36,54,0) -> 70000
A26: AS201628 | B26: =VLOOKUP(A26,[15]LISTADHERENT!$A$5:$J$50,3,0) -> NKAMGANG JUSTIN DEJOLIE | C26: =MVTJANV23!C26 -> 600000 | D26: =MVTJANV23!D26 -> 575 | F26: =C26+D26-E26+K26 -> 603575 | G26: =$S$40/$H$40*H26 -> #REF! | H26: =F26+D26+K26 -> 607150 | I26: =VLOOKUP($A26,[16]HISTOJANV22!$A$6:$AQ$37,22,0) -> 0 | J26: =VLOOKUP($A26,[16]HISTOJANV22!$A$6:$AU$39,45,0) -> 7000 | K26: =IF(J26=0,0,J26-(L26+M26+N26)) -> 3000 | L26: =IF(J26=0,0,500) -> 500 | M26: =IF(J26=0,0,1000) -> 1000 | N26: =IF(J26=0,0,2500) -> 2500 | O26: =VLOOKUP($A26,[16]HISTOJANV22!$A$6:$AU$39,7,0) -> 0 | P26: =VLOOKUP($A26,[16]HISTOJANV22!$A$6:$AU$39,23,0) -> 0 | Q26: =VLOOKUP($A26,[16]HISTOJANV22!$A$6:$AU$39,46,0) -> 0 | R26: =VLOOKUP($A26,[16]HISTODEC21!$A$6:$AU$39,26,0) -> 1155000 | S26: =R26*0/1200*12 -> 0 | T26: =VLOOKUP($A26,[16]HISTOJANV22!$A$6:$AU$39,28,0) -> 0 | U26: =VLOOKUP($A26,[16]HISTOJANV22!$A$6:$AU$39,19,0) -> 0 | V26: =VLOOKUP($A26,[16]HISTOJANV22!$A$6:$AU$39,20,0) -> 0 | W26: =VLOOKUP($A26,[16]HISTOJANV22!$A$6:$AU$39,27,0) -> BANQUE | X26: =VLOOKUP($A26,[16]HISTOJANV22!$A$6:$AU$39,33,0) -> 0 | Y26: 155000 | AA26: =VLOOKUP($A26,[16]HISTOJANV22!$A$6:$AU$39,43,0) -> 0 | AB26: =VLOOKUP($A26,[16]HISTOJANV22!$A$6:$AU$39,44,0) -> 0 | AC26: =VLOOKUP($A26,[16]HISTOJANV22!$A$6:$AU$39,47,0) -> 0 | AD26: =VLOOKUP(A26,[16]HISTOJANV22!$A$6:$BB$36,54,0) -> 0
A27: AS201656 | B27: =VLOOKUP(A27,[15]LISTADHERENT!$A$5:$J$50,3,0) -> NOUBE ETIENNE | C27: =MVTJANV23!C27 -> 0 | D27: =MVTJANV23!D27 -> 0 | F27: =C27+D27-E27+K27 -> #N/A | G27: =$S$40/$H$40*H27 -> #REF! | H27: =F27+D27+K27 -> #N/A | I27: =VLOOKUP($A27,[16]HISTOJANV22!$A$6:$AQ$37,22,0) -> #N/A | J27: =VLOOKUP($A27,[16]HISTOJANV22!$A$6:$AU$39,45,0) -> #N/A | K27: =IF(J27=0,0,J27-(L27+M27+N27)) -> #N/A | L27: =IF(J27=0,0,500) -> #N/A | M27: =IF(J27=0,0,1000) -> #N/A | N27: =IF(J27=0,0,2500) -> #N/A | O27: =VLOOKUP($A27,[16]HISTOJANV22!$A$6:$AU$39,7,0) -> #N/A | P27: =VLOOKUP($A27,[16]HISTOJANV22!$A$6:$AU$39,23,0) -> #N/A | Q27: =VLOOKUP($A27,[16]HISTOJANV22!$A$6:$AU$39,46,0) -> #N/A | R27: =VLOOKUP($A27,[16]HISTODEC21!$A$6:$AU$39,26,0) -> #N/A | S27: =R27*12/1200*12 -> #N/A | T27: =VLOOKUP($A27,[16]HISTOJANV22!$A$6:$AU$39,28,0) -> #N/A | U27: =VLOOKUP($A27,[16]HISTOJANV22!$A$6:$AU$39,19,0) -> #N/A | V27: =VLOOKUP($A27,[16]HISTOJANV22!$A$6:$AU$39,20,0) -> #N/A | W27: =VLOOKUP($A27,[16]HISTOJANV22!$A$6:$AU$39,27,0) -> #N/A | X27: =VLOOKUP($A27,[16]HISTOJANV22!$A$6:$AU$39,33,0) -> #N/A | AA27: =VLOOKUP($A27,[16]HISTOJANV22!$A$6:$AU$39,43,0) -> #N/A | AB27: =VLOOKUP($A27,[16]HISTOJANV22!$A$6:$AU$39,44,0) -> #N/A | AC27: =VLOOKUP($A27,[16]HISTOJANV22!$A$6:$AU$39,47,0) -> #N/A | AD27: =VLOOKUP(A27,[16]HISTOJANV22!$A$6:$BB$36,54,0) -> #N/A
A28: AS201633 | B28: =VLOOKUP(A28,[15]LISTADHERENT!$A$5:$J$50,3,0) -> PATEGO NJOSSU GUSTAVE | C28: =MVTJANV23!C28 -> 600000 | D28: =MVTJANV23!D28 -> 21452 | F28: =C28+D28-E28+K28 -> 624452 | G28: =$S$40/$H$40*H28 -> #REF! | H28: =F28+D28+K28 -> 648904 | I28: =VLOOKUP($A28,[16]HISTOJANV22!$A$6:$AQ$37,22,0) -> 0 | J28: =VLOOKUP($A28,[16]HISTOJANV22!$A$6:$AU$39,45,0) -> 7000 | K28: =IF(J28=0,0,J28-(L28+M28+N28)) -> 3000 | L28: =IF(J28=0,0,500) -> 500 | M28: =IF(J28=0,0,1000) -> 1000 | N28: =IF(J28=0,0,2500) -> 2500 | O28: =VLOOKUP($A28,[16]HISTOJANV22!$A$6:$AU$39,7,0) -> 0 | P28: =VLOOKUP($A28,[16]HISTOJANV22!$A$6:$AU$39,23,0) -> 0 | Q28: =VLOOKUP($A28,[16]HISTOJANV22!$A$6:$AU$39,46,0) -> 0 | R28: =VLOOKUP($A28,[16]HISTODEC21!$A$6:$AU$39,26,0) -> #REF! | S28: =R28*12/1200*12 -> #REF! | T28: =VLOOKUP($A28,[16]HISTOJANV22!$A$6:$AU$39,28,0) -> 0 | U28: =VLOOKUP($A28,[16]HISTOJANV22!$A$6:$AU$39,19,0) -> 0 | V28: =VLOOKUP($A28,[16]HISTOJANV22!$A$6:$AU$39,20,0) -> 0 | W28: =VLOOKUP($A28,[16]HISTOJANV22!$A$6:$AU$39,27,0) -> 0 | X28: =VLOOKUP($A28,[16]HISTOJANV22!$A$6:$AU$39,33,0) -> 0 | AA28: =VLOOKUP($A28,[16]HISTOJANV22!$A$6:$AU$39,43,0) -> 0 | AB28: =VLOOKUP($A28,[16]HISTOJANV22!$A$6:$AU$39,44,0) -> 0 | AC28: =VLOOKUP($A28,[16]HISTOJANV22!$A$6:$AU$39,47,0) -> 0 | AD28: =VLOOKUP(A28,[16]HISTOJANV22!$A$6:$BB$36,54,0) -> 0
A29: AS201657 | B29: =VLOOKUP(A29,[15]LISTADHERENT!$A$5:$J$50,3,0) -> SEUMO POLYCARPE | C29: =MVTJANV23!C29 -> 0 | D29: =MVTJANV23!D29 -> 0 | F29: =C29+D29-E29+K29 -> #N/A | G29: =$S$40/$H$40*H29 -> #REF! | H29: =F29+D29+K29 -> #N/A | I29: =VLOOKUP($A29,[16]HISTOJANV22!$A$6:$AQ$37,22,0) -> #N/A | J29: =VLOOKUP($A29,[16]HISTOJANV22!$A$6:$AU$39,45,0) -> #N/A | K29: =IF(J29=0,0,J29-(L29+M29+N29)) -> #N/A | L29: =IF(J29=0,0,500) -> #N/A | M29: =IF(J29=0,0,1000) -> #N/A | N29: =IF(J29=0,0,2500) -> #N/A | O29: =VLOOKUP($A29,[16]HISTOJANV22!$A$6:$AU$39,7,0) -> #N/A | P29: =VLOOKUP($A29,[16]HISTOJANV22!$A$6:$AU$39,23,0) -> #N/A | Q29: =VLOOKUP($A29,[16]HISTOJANV22!$A$6:$AU$39,46,0) -> #N/A | R29: =VLOOKUP($A29,[16]HISTODEC21!$A$6:$AU$39,26,0) -> #N/A | S29: =R29*12/1200*12 -> #N/A | T29: =VLOOKUP($A29,[16]HISTOJANV22!$A$6:$AU$39,28,0) -> #N/A | U29: =VLOOKUP($A29,[16]HISTOJANV22!$A$6:$AU$39,19,0) -> #N/A | V29: =VLOOKUP($A29,[16]HISTOJANV22!$A$6:$AU$39,20,0) -> #N/A | W29: =VLOOKUP($A29,[16]HISTOJANV22!$A$6:$AU$39,27,0) -> #N/A | X29: =VLOOKUP($A29,[16]HISTOJANV22!$A$6:$AU$39,33,0) -> #N/A | AA29: =VLOOKUP($A29,[16]HISTOJANV22!$A$6:$AU$39,43,0) -> #N/A | AB29: =VLOOKUP($A29,[16]HISTOJANV22!$A$6:$AU$39,44,0) -> #N/A | AC29: =VLOOKUP($A29,[16]HISTOJANV22!$A$6:$AU$39,47,0) -> #N/A | AD29: =VLOOKUP(A29,[16]HISTOJANV22!$A$6:$BB$36,54,0) -> #N/A
A30: AS201653 | B30: =VLOOKUP(A30,[15]LISTADHERENT!$A$5:$J$50,3,0) -> SIME BRICE | C30: =MVTJANV23!C30 -> 600000 | D30: =MVTJANV23!D30 -> 200752 | F30: =C30+D30-E30+K30 -> 803752 | G30: =$S$40/$H$40*H30 -> #REF! | H30: =F30+D30+K30 -> 1007504 | I30: =VLOOKUP($A30,[16]HISTOJANV22!$A$6:$AQ$37,22,0) -> 0 | J30: =VLOOKUP($A30,[16]HISTOJANV22!$A$6:$AU$39,45,0) -> 7000 | K30: =IF(J30=0,0,J30-(L30+M30+N30)) -> 3000 | L30: =IF(J30=0,0,500) -> 500 | M30: =IF(J30=0,0,1000) -> 1000 | N30: =IF(J30=0,0,2500) -> 2500 | O30: =VLOOKUP($A30,[16]HISTOJANV22!$A$6:$AU$39,7,0) -> 0 | P30: =VLOOKUP($A30,[16]HISTOJANV22!$A$6:$AU$39,23,0) -> 0 | Q30: =VLOOKUP($A30,[16]HISTOJANV22!$A$6:$AU$39,46,0) -> 0 | R30: =VLOOKUP($A30,[16]HISTODEC21!$A$6:$AU$39,26,0) -> #REF! | S30: =R30*12/1200*12 -> #REF! | T30: =VLOOKUP($A30,[16]HISTOJANV22!$A$6:$AU$39,28,0) -> 0 | U30: =VLOOKUP($A30,[16]HISTOJANV22!$A$6:$AU$39,19,0) -> 0 | V30: =VLOOKUP($A30,[16]HISTOJANV22!$A$6:$AU$39,20,0) -> 0 | W30: =VLOOKUP($A30,[16]HISTOJANV22!$A$6:$AU$39,27,0) -> 0 | X30: =VLOOKUP($A30,[16]HISTOJANV22!$A$6:$AU$39,33,0) -> 0 | AA30: =VLOOKUP($A30,[16]HISTOJANV22!$A$6:$AU$39,43,0) -> 0 | AB30: =VLOOKUP($A30,[16]HISTOJANV22!$A$6:$AU$39,44,0) -> 0 | AC30: =VLOOKUP($A30,[16]HISTOJANV22!$A$6:$AU$39,47,0) -> 0 | AD30: =VLOOKUP(A30,[16]HISTOJANV22!$A$6:$BB$36,54,0) -> 0
A31: AS201638 | B31: =VLOOKUP(A31,[15]LISTADHERENT!$A$5:$J$50,3,0) -> SIMO PIERRE | C31: =MVTJANV23!C31 -> 600000 | D31: =MVTJANV23!D31 -> 103606 | F31: =C31+D31-E31+K31 -> 721606 | G31: =$S$40/$H$40*H31 -> #REF! | H31: =F31+D31+K31 -> 843212 | I31: =VLOOKUP($A31,[16]HISTOJANV22!$A$6:$AQ$37,22,0) -> 0 | J31: =VLOOKUP($A31,[16]HISTOJANV22!$A$6:$AU$39,45,0) -> 22000 | K31: =IF(J31=0,0,J31-(L31+M31+N31)) -> 18000 | L31: =IF(J31=0,0,500) -> 500 | M31: =IF(J31=0,0,1000) -> 1000 | N31: =IF(J31=0,0,2500) -> 2500 | O31: =VLOOKUP($A31,[16]HISTOJANV22!$A$6:$AU$39,7,0) -> 0 | P31: =VLOOKUP($A31,[16]HISTOJANV22!$A$6:$AU$39,23,0) -> 0 | Q31: =VLOOKUP($A31,[16]HISTOJANV22!$A$6:$AU$39,46,0) -> 0 | R31: =VLOOKUP($A31,[16]HISTODEC21!$A$6:$AU$39,26,0) -> #REF! | S31: =R31*12/1200*12 -> #REF! | T31: =VLOOKUP($A31,[16]HISTOJANV22!$A$6:$AU$39,28,0) -> 0 | U31: =VLOOKUP($A31,[16]HISTOJANV22!$A$6:$AU$39,19,0) -> 0 | V31: =VLOOKUP($A31,[16]HISTOJANV22!$A$6:$AU$39,20,0) -> 0 | W31: =VLOOKUP($A31,[16]HISTOJANV22!$A$6:$AU$39,27,0) -> BANQUE | X31: =VLOOKUP($A31,[16]HISTOJANV22!$A$6:$AU$39,33,0) -> 0 | AA31: =VLOOKUP($A31,[16]HISTOJANV22!$A$6:$AU$39,43,0) -> 0 | AB31: =VLOOKUP($A31,[16]HISTOJANV22!$A$6:$AU$39,44,0) -> 0 | AC31: =VLOOKUP($A31,[16]HISTOJANV22!$A$6:$AU$39,47,0) -> 0 | AD31: =VLOOKUP(A31,[16]HISTOJANV22!$A$6:$BB$36,54,0) -> 70000
A32: AS201641 | B32: =VLOOKUP(A32,[15]LISTADHERENT!$A$5:$J$50,3,0) -> TCHOUAMOU MATHIEU | C32: =MVTJANV23!C32 -> 600000 | D32: =MVTJANV23!D32 -> 4208 | F32: =C32+D32-E32+K32 -> 607208 | G32: =$S$40/$H$40*H32 -> #REF! | H32: =F32+D32+K32 -> 614416 | I32: =VLOOKUP($A32,[16]HISTOJANV22!$A$6:$AQ$37,22,0) -> 0 | J32: =VLOOKUP($A32,[16]HISTOJANV22!$A$6:$AU$39,45,0) -> 7000 | K32: =IF(J32=0,0,J32-(L32+M32+N32)) -> 3000 | L32: =IF(J32=0,0,500) -> 500 | M32: =IF(J32=0,0,1000) -> 1000 | N32: =IF(J32=0,0,2500) -> 2500 | O32: =VLOOKUP($A32,[16]HISTOJANV22!$A$6:$AU$39,7,0) -> 0 | P32: =VLOOKUP($A32,[16]HISTOJANV22!$A$6:$AU$39,23,0) -> 0 | Q32: =VLOOKUP($A32,[16]HISTOJANV22!$A$6:$AU$39,46,0) -> 0 | R32: =VLOOKUP($A32,[16]HISTODEC21!$A$6:$AU$39,26,0) -> 560000 | S32: =R32*12/1200*12 -> 67200 | T32: =VLOOKUP($A32,[16]HISTOJANV22!$A$6:$AU$39,28,0) -> OKK | U32: =VLOOKUP($A32,[16]HISTOJANV22!$A$6:$AU$39,19,0) -> 0 | V32: =VLOOKUP($A32,[16]HISTOJANV22!$A$6:$AU$39,20,0) -> 0 | W32: =VLOOKUP($A32,[16]HISTOJANV22!$A$6:$AU$39,27,0) -> BANQUE | X32: =VLOOKUP($A32,[16]HISTOJANV22!$A$6:$AU$39,33,0) -> 0 | AA32: =VLOOKUP($A32,[16]HISTOJANV22!$A$6:$AU$39,43,0) -> 0 | AB32: =VLOOKUP($A32,[16]HISTOJANV22!$A$6:$AU$39,44,0) -> 0 | AC32: =VLOOKUP($A32,[16]HISTOJANV22!$A$6:$AU$39,47,0) -> 0 | AD32: =VLOOKUP(A32,[16]HISTOJANV22!$A$6:$BB$36,54,0) -> 0
A33: AS201643 | B33: =VLOOKUP(A33,[15]LISTADHERENT!$A$5:$J$50,3,0) -> TCHOUTOU NANA CLAUDE | C33: =MVTJANV23!C33 -> 0 | D33: =MVTJANV23!D33 -> 0 | F33: =C33+D33-E33+K33 -> #N/A | G33: =$S$40/$H$40*H33 -> #REF! | H33: =F33+D33+K33 -> #N/A | I33: =VLOOKUP($A33,[16]HISTOJANV22!$A$6:$AQ$37,22,0) -> #N/A | J33: =VLOOKUP($A33,[16]HISTOJANV22!$A$6:$AU$39,45,0) -> #N/A | K33: =IF(J33=0,0,J33-(L33+M33+N33)) -> #N/A | L33: =IF(J33=0,0,500) -> #N/A | M33: =IF(J33=0,0,1000) -> #N/A | N33: =IF(J33=0,0,2500) -> #N/A | O33: =VLOOKUP($A33,[16]HISTOJANV22!$A$6:$AU$39,7,0) -> #N/A | P33: =VLOOKUP($A33,[16]HISTOJANV22!$A$6:$AU$39,23,0) -> #N/A | Q33: =VLOOKUP($A33,[16]HISTOJANV22!$A$6:$AU$39,46,0) -> #N/A | R33: =VLOOKUP($A33,[16]HISTODEC21!$A$6:$AU$39,26,0) -> #N/A | S33: =R33*12/1200*12 -> #N/A | T33: =VLOOKUP($A33,[16]HISTOJANV22!$A$6:$AU$39,28,0) -> #N/A | U33: =VLOOKUP($A33,[16]HISTOJANV22!$A$6:$AU$39,19,0) -> #N/A | V33: =VLOOKUP($A33,[16]HISTOJANV22!$A$6:$AU$39,20,0) -> #N/A | W33: =VLOOKUP($A33,[16]HISTOJANV22!$A$6:$AU$39,27,0) -> #N/A | X33: =VLOOKUP($A33,[16]HISTOJANV22!$A$6:$AU$39,33,0) -> #N/A | AA33: =VLOOKUP($A33,[16]HISTOJANV22!$A$6:$AU$39,43,0) -> #N/A | AB33: =VLOOKUP($A33,[16]HISTOJANV22!$A$6:$AU$39,44,0) -> #N/A | AC33: =VLOOKUP($A33,[16]HISTOJANV22!$A$6:$AU$39,47,0) -> #N/A | AD33: =VLOOKUP(A33,[16]HISTOJANV22!$A$6:$BB$36,54,0) -> #N/A
A34: AS201658 | B34: =VLOOKUP(A34,[15]LISTADHERENT!$A$5:$J$50,3,0) -> YANTCHOU GERVAIS | C34: =MVTJANV23!C34 -> 0 | D34: =MVTJANV23!D34 -> 0 | F34: =C34+D34-E34+K34 -> #N/A | G34: =$S$40/$H$40*H34 -> #REF! | H34: =F34+D34+K34 -> #N/A | I34: =VLOOKUP($A34,[16]HISTOJANV22!$A$6:$AQ$37,22,0) -> #N/A | J34: =VLOOKUP($A34,[16]HISTOJANV22!$A$6:$AU$39,45,0) -> #N/A | K34: =IF(J34=0,0,J34-(L34+M34+N34)) -> #N/A | L34: =IF(J34=0,0,500) -> #N/A | M34: =IF(J34=0,0,1000) -> #N/A | N34: =IF(J34=0,0,2500) -> #N/A | O34: =VLOOKUP($A34,[16]HISTOJANV22!$A$6:$AU$39,7,0) -> #N/A | P34: =VLOOKUP($A34,[16]HISTOJANV22!$A$6:$AU$39,23,0) -> #N/A | Q34: =VLOOKUP($A34,[16]HISTOJANV22!$A$6:$AU$39,46,0) -> #N/A | R34: =VLOOKUP($A34,[16]HISTODEC21!$A$6:$AU$39,26,0) -> #N/A | S34: =R34*12/1200*12 -> #N/A | T34: =VLOOKUP($A34,[16]HISTOJANV22!$A$6:$AU$39,28,0) -> #N/A | U34: =VLOOKUP($A34,[16]HISTOJANV22!$A$6:$AU$39,19,0) -> #N/A | V34: =VLOOKUP($A34,[16]HISTOJANV22!$A$6:$AU$39,20,0) -> #N/A | W34: =VLOOKUP($A34,[16]HISTOJANV22!$A$6:$AU$39,27,0) -> #N/A | X34: =VLOOKUP($A34,[16]HISTOJANV22!$A$6:$AU$39,33,0) -> #N/A | AA34: =VLOOKUP($A34,[16]HISTOJANV22!$A$6:$AU$39,43,0) -> #N/A | AB34: =VLOOKUP($A34,[16]HISTOJANV22!$A$6:$AU$39,44,0) -> #N/A | AC34: =VLOOKUP($A34,[16]HISTOJANV22!$A$6:$AU$39,47,0) -> #N/A | AD34: =VLOOKUP(A34,[16]HISTOJANV22!$A$6:$BB$36,54,0) -> #N/A
A35: AS201646 | B35: =VLOOKUP(A35,[15]LISTADHERENT!$A$5:$J$50,3,0) -> YEPMOU JEAN JACQUES | C35: =MVTJANV23!C35 -> 600000 | D35: =MVTJANV23!D35 -> 914734 | F35: =C35+D35-E35+K35 -> 1517734 | G35: =$S$40/$H$40*H35 -> #REF! | H35: =F35+D35+K35 -> 2435468 | I35: =VLOOKUP($A35,[16]HISTOJANV22!$A$6:$AQ$37,22,0) -> 0 | J35: =VLOOKUP($A35,[16]HISTOJANV22!$A$6:$AU$39,45,0) -> 7000 | K35: =IF(J35=0,0,J35-(L35+M35+N35)) -> 3000 | L35: =IF(J35=0,0,500) -> 500 | M35: =IF(J35=0,0,1000) -> 1000 | N35: =IF(J35=0,0,2500) -> 2500 | O35: =VLOOKUP($A35,[16]HISTOJANV22!$A$6:$AU$39,7,0) -> 3000 | P35: =VLOOKUP($A35,[16]HISTOJANV22!$A$6:$AU$39,23,0) -> 0 | Q35: =VLOOKUP($A35,[16]HISTOJANV22!$A$6:$AU$39,46,0) -> 0 | R35: =VLOOKUP($A35,[16]HISTODEC21!$A$6:$AU$39,26,0) -> 1155000 | S35: =R35*0/1200*12 -> 0 | T35: =VLOOKUP($A35,[16]HISTOJANV22!$A$6:$AU$39,28,0) -> 0 | U35: =VLOOKUP($A35,[16]HISTOJANV22!$A$6:$AU$39,19,0) -> 0 | V35: =VLOOKUP($A35,[16]HISTOJANV22!$A$6:$AU$39,20,0) -> 0 | W35: =VLOOKUP($A35,[16]HISTOJANV22!$A$6:$AU$39,27,0) -> BANQUE | X35: =VLOOKUP($A35,[16]HISTOJANV22!$A$6:$AU$39,33,0) -> 0 | Y35: 155000 | AA35: =VLOOKUP($A35,[16]HISTOJANV22!$A$6:$AU$39,43,0) -> 0 | AB35: =VLOOKUP($A35,[16]HISTOJANV22!$A$6:$AU$39,44,0) -> 0 | AC35: =VLOOKUP($A35,[16]HISTOJANV22!$A$6:$AU$39,47,0) -> 0 | AD35: =VLOOKUP(A35,[16]HISTOJANV22!$A$6:$BB$36,54,0) -> 0
A36: AS201647 | B36: =VLOOKUP(A36,[15]LISTADHERENT!$A$5:$J$50,3,0) -> YOUMBI EMMANUEL | C36: =MVTJANV23!C36 -> 600000 | D36: =MVTJANV23!D36 -> 1057774 | F36: =C36+D36-E36+K36 -> 1660774 | G36: =$S$40/$H$40*H36 -> #REF! | H36: =F36+D36+K36 -> 2721548 | I36: =VLOOKUP($A36,[16]HISTOJANV22!$A$6:$AQ$37,22,0) -> 0 | J36: =VLOOKUP($A36,[16]HISTOJANV22!$A$6:$AU$39,45,0) -> 7000 | K36: =IF(J36=0,0,J36-(L36+M36+N36)) -> 3000 | L36: =IF(J36=0,0,500) -> 500 | M36: =IF(J36=0,0,1000) -> 1000 | N36: =IF(J36=0,0,2500) -> 2500 | O36: =VLOOKUP($A36,[16]HISTOJANV22!$A$6:$AU$39,7,0) -> 0 | P36: =VLOOKUP($A36,[16]HISTOJANV22!$A$6:$AU$39,23,0) -> 0 | Q36: =VLOOKUP($A36,[16]HISTOJANV22!$A$6:$AU$39,46,0) -> 0 | R36: =VLOOKUP($A36,[16]HISTODEC21!$A$6:$AU$39,26,0) -> #REF! | S36: =R36*12/1200*12 -> #REF! | T36: =VLOOKUP($A36,[16]HISTOJANV22!$A$6:$AU$39,28,0) -> 0 | U36: =VLOOKUP($A36,[16]HISTOJANV22!$A$6:$AU$39,19,0) -> 0 | V36: =VLOOKUP($A36,[16]HISTOJANV22!$A$6:$AU$39,20,0) -> 0 | W36: =VLOOKUP($A36,[16]HISTOJANV22!$A$6:$AU$39,27,0) -> 0 | X36: =VLOOKUP($A36,[16]HISTOJANV22!$A$6:$AU$39,33,0) -> 0 | AA36: =VLOOKUP($A36,[16]HISTOJANV22!$A$6:$AU$39,43,0) -> 0 | AB36: =VLOOKUP($A36,[16]HISTOJANV22!$A$6:$AU$39,44,0) -> 0 | AC36: =VLOOKUP($A36,[16]HISTOJANV22!$A$6:$AU$39,47,0) -> 0 | AD36: =VLOOKUP(A36,[16]HISTOJANV22!$A$6:$BB$36,54,0) -> 70000
A40: TOTAL | C40: =SUM(C6:C39) -> 15000000 | D40: =SUM(D6:D39) -> 4359124.5 | E40: =SUM(E6:E39) -> 0 | F40: =SUM(F6:F39) -> #N/A | G40: =SUM(G6:G39) -> #REF! | H40: =SUM(H6:H39) -> #N/A | I40: =SUM(I6:I39) -> #N/A | J40: =SUM(J6:J39) -> #N/A | ... AE40: =SUM(AE6:AE39) -> 0

Sheet MVTDEC22
A1: ASSOCIATION | B1: ASELBY | G1: K
A2: ANNEE | B2: 2022
A3: TONTINE
J4: 44912
A5: MATRICULE | B5: NOM ET PRENOM | C5: FONDES DE DEPART | D5: RELIQUAT | E5: RETRAIT PARTIEL | F5: FONDS DEFINITIF | G5: REPARTITION INTERET | H5: CAPITAL COMPOSE | I5: SANCTION | J5: RESTE | K5: EPARGNE | L5: FONDS DE ROULEMENT | M5: FRAIS EXCEPTIONNEL | N5: COLLATION | O5: PENALITE VST ESPECES | P5: INSCRISPTION | Q5: MUTUELLE | R5: PRÊT FONDS | S5: INTERETPRET FONDS | T5: NUMERO CHEQUE | U5: REMBOURSEMENTPRET FONDS | V5: MODE VERSEMENT REMBOURSEMENT | W5: MODE VERSEMENT PRÊT | X5: NUMERO CHEQUE | Y5: PENALITE PRET FONDS | Z5: PENALITE FONDS | AA5: PENALITE ECHEC TONTINE | AB5: PENALITE RETARD TONTINE | AC5: REMBOURSEMENT TRANSPORT | AD5: CONTRIBUTION FOYER | AE5: FONDS DE ROULEMENT | AF5: FRAIS EXCEPTIONNEL | AG5: FONDS MUTUELLE | AH5: COLLATION RECEPTION | AI5: PENALITE PRET FONDS | AJ5: DEPENSE PENALITE VERSEMENT BANQUE
A6: AS201648 | B6: =VLOOKUP(A6,[15]LISTADHERENT!$A$5:$J$45,3,0) -> ASELBY | C6: 0 | D6: =VLOOKUP(A6,'[17]EPARGNE 2023'!$A$5:$BF$47,4,0) -> 816543.52 | F6: =C6+D6-E6 -> 816543.52 | G6: 51868.55 | H6: =+F6+G6 -> 868412.07 | AE6: =VLOOKUP($A6,[16]HISTODEC22!$A$6:$CA$36,60,0) -> 6000 | AF6: =VLOOKUP($A6,[16]HISTODEC22!$A$6:$CA$36,61,0) -> 0 | AG6: =VLOOKUP($A6,[16]HISTODEC22!$A$6:$CA$36,62,0) -> 0 | AH6: =VLOOKUP($A6,[16]HISTODEC22!$A$6:$CA$36,63,0) -> 0 | AI6: =VLOOKUP($A6,[16]HISTODEC22!$A$6:$CA$36,64,0) -> 0 | AJ6: =VLOOKUP($A6,[16]HISTODEC22!$A$6:$CA$36,65,0) -> 0
A7: AS201601 | B7: =VLOOKUP(A7,[15]LISTADHERENT!$A$5:$J$45,3,0) -> BAKOP ACHILLE | C7: 0 | D7: =VLOOKUP(A7,'[17]EPARGNE 2023'!$A$5:$BF$47,4,0) -> 0 | F7: =C7+D7-E7 -> 0 | G7: 0 | H7: =+F7+G7 -> 0
A8: AS201602 | B8: =VLOOKUP(A8,[15]LISTADHERENT!$A$5:$J$45,3,0) -> BOUTCHOUANG WILLIAM | C8: 600000 | D8: =VLOOKUP(A8,'[17]EPARGNE 2023'!$A$5:$BF$47,4,0) -> 7023.6611 | F8: =C8+D8-E8 -> 607023.66 | G8: 38559.411 | H8: =+F8+G8 -> 645583.07 | I8: =VLOOKUP($A8,[16]HISTODEC22!$A$6:$AQ$37,22,0) -> 0 | J8: =VLOOKUP($A8,[16]HISTODEC22!$A$6:$AU$39,45,0) -> 7000 | L8: =IF(J8=0,0,500) -> 500 | M8: =IF(J8=0,0,1000) -> 1000 | N8: =IF(J8=0,0,2500) -> 2500 | O8: =VLOOKUP($A8,[16]HISTODEC22!$A$6:$AU$39,7,0) -> 0 | P8: =VLOOKUP($A8,[16]HISTODEC22!$A$6:$AU$39,23,0) -> 0 | Q8: =VLOOKUP($A8,[16]HISTODEC22!$A$6:$AU$39,46,0) -> 0 | R8: =VLOOKUP($A8,[18]HISTODEC22!$A$6:$AU$39,26,0) -> 500000 | S8: =VLOOKUP($A8,[18]HISTODEC22!$A$6:$BG$39,58,0) -> 10000 | T8: =VLOOKUP($A8,[16]HISTODEC22!$A$6:$AU$39,28,0) -> 0 | U8: =VLOOKUP($A8,[16]HISTODEC22!$A$6:$AU$39,19,0) -> 0 | V8: =VLOOKUP($A8,[16]HISTODEC22!$A$6:$AU$39,20,0) -> 0 | W8: =VLOOKUP($A8,[16]HISTODEC22!$A$6:$AU$39,27,0) -> BANQUE | X8: =VLOOKUP($A8,[16]HISTODEC22!$A$6:$AU$39,33,0) -> 0 | Y8: =VLOOKUP($A8,[16]HISTODEC22!$A$6:$BP$39,65,0) -> 0 | AA8: =VLOOKUP($A8,[16]HISTODEC22!$A$6:$AU$39,43,0) -> 0 | AB8: =VLOOKUP($A8,[16]HISTODEC22!$A$6:$AU$39,44,0) -> 0 | AC8: =VLOOKUP($A8,[16]HISTODEC22!$A$6:$AU$39,47,0) -> 0 | AD8: =VLOOKUP(A8,[16]HISTODEC22!$A$6:$BB$36,54,0) -> 0 | AE8: =VLOOKUP($A8,[16]HISTODEC22!$A$6:$CA$36,60,0) -> 0 | AF8: =VLOOKUP($A8,[16]HISTODEC22!$A$6:$CA$36,61,0) -> 0 | AG8: =VLOOKUP($A8,[16]HISTODEC22!$A$6:$CA$36,62,0) -> 0 | AH8: =VLOOKUP($A8,[16]HISTODEC22!$A$6:$CA$36,63,0) -> 0 | AI8: =VLOOKUP($A8,[16]HISTODEC22!$A$6:$CA$36,64,0) -> 0 | AJ8: =VLOOKUP($A8,[16]HISTODEC22!$A$6:$CA$36,65,0) -> 0
A9: AS201604 | B9: =VLOOKUP(A9,[15]LISTADHERENT!$A$5:$J$45,3,0) -> DJOMO JEAN PAUL | C9: 600000 | D9: =VLOOKUP(A9,'[17]EPARGNE 2023'!$A$5:$BF$47,4,0) -> 4809.807 | F9: =C9+D9-E9 -> 604809.81 | G9: 38418.782 | H9: =+F9+G9 -> 643228.59 | I9: =VLOOKUP($A9,[16]HISTODEC22!$A$6:$AQ$37,22,0) -> 0 | J9: =VLOOKUP($A9,[16]HISTODEC22!$A$6:$AU$39,45,0) -> 7000 | L9: =IF(J9=0,0,500) -> 500 | M9: =IF(J9=0,0,1000) -> 1000 | N9: =IF(J9=0,0,2500) -> 2500 | O9: =VLOOKUP($A9,[16]HISTODEC22!$A$6:$AU$39,7,0) -> 0 | P9: =VLOOKUP($A9,[16]HISTODEC22!$A$6:$AU$39,23,0) -> 0 | Q9: =VLOOKUP($A9,[16]HISTODEC22!$A$6:$AU$39,46,0) -> 0 | R9: =VLOOKUP($A9,[18]HISTODEC22!$A$6:$AU$39,26,0) -> 1000000 | S9: =VLOOKUP($A9,[18]HISTODEC22!$A$6:$BG$39,58,0) -> 120000 | T9: =VLOOKUP($A9,[16]HISTODEC22!$A$6:$AU$39,28,0) -> 0 | U9: =VLOOKUP($A9,[16]HISTODEC22!$A$6:$AU$39,19,0) -> 1000000 | V9: =VLOOKUP($A9,[16]HISTODEC22!$A$6:$AU$39,20,0) -> BANQUE | W9: =VLOOKUP($A9,[16]HISTODEC22!$A$6:$AU$39,27,0) -> BANQUE | X9: =VLOOKUP($A9,[16]HISTODEC22!$A$6:$AU$39,33,0) -> 0 | Y9: =VLOOKUP($A9,[16]HISTODEC22!$A$6:$BP$39,65,0) -> 0 | AA9: =VLOOKUP($A9,[16]HISTODEC22!$A$6:$AU$39,43,0) -> 0 | AB9: =VLOOKUP($A9,[16]HISTODEC22!$A$6:$AU$39,44,0) -> 0 | AC9: =VLOOKUP($A9,[16]HISTODEC22!$A$6:$AU$39,47,0) -> 0 | AD9: =VLOOKUP(A9,[16]HISTODEC22!$A$6:$BB$36,54,0) -> 0 | AE9: =VLOOKUP($A9,[16]HISTODEC22!$A$6:$CA$36,60,0) -> 0 | AF9: =VLOOKUP($A9,[16]HISTODEC22!$A$6:$CA$36,61,0) -> 0 | AG9: =VLOOKUP($A9,[16]HISTODEC22!$A$6:$CA$36,62,0) -> 0 | AH9: =VLOOKUP($A9,[16]HISTODEC22!$A$6:$CA$36,63,0) -> 0 | AI9: =VLOOKUP($A9,[16]HISTODEC22!$A$6:$CA$36,64,0) -> 0 | AJ9: =VLOOKUP($A9,[16]HISTODEC22!$A$6:$CA$36,65,0) -> 0
A10: AS201654 | B10: =VLOOKUP(A10,[15]LISTADHERENT!$A$5:$J$45,3,0) -> DJOMOU TCHAPDA | C10: 600000 | D10: =VLOOKUP(A10,'[17]EPARGNE 2023'!$A$5:$BF$47,4,0) -> 48710.412 | F10: =C10+D10-E10 -> 648710.41 | G10: 41207.44 | H10: =+F10+G10 -> 689917.85 | I10: =VLOOKUP($A10,[16]HISTODEC22!$A$6:$AQ$37,22,0) -> 0 | J10: =VLOOKUP($A10,[16]HISTODEC22!$A$6:$AU$39,45,0) -> 7000 | L10: =IF(J10=0,0,500) -> 500 | M10: =IF(J10=0,0,1000) -> 1000 | N10: =IF(J10=0,0,2500) -> 2500 | O10: =VLOOKUP($A10,[16]HISTODEC22!$A$6:$AU$39,7,0) -> 0 | P10: =VLOOKUP($A10,[16]HISTODEC22!$A$6:$AU$39,23,0) -> 0 | Q10: =VLOOKUP($A10,[16]HISTODEC22!$A$6:$AU$39,46,0) -> 0 | R10: =VLOOKUP($A10,[18]HISTODEC22!$A$6:$AU$39,26,0) -> 0 | S10: =VLOOKUP($A10,[18]HISTODEC22!$A$6:$BG$39,58,0) -> 0 | T10: =VLOOKUP($A10,[16]HISTODEC22!$A$6:$AU$39,28,0) -> 0 | U10: =VLOOKUP($A10,[16]HISTODEC22!$A$6:$AU$39,19,0) -> 0 | V10: =VLOOKUP($A10,[16]HISTODEC22!$A$6:$AU$39,20,0) -> 0 | W10: =VLOOKUP($A10,[16]HISTODEC22!$A$6:$AU$39,27,0) -> 0 | X10: =VLOOKUP($A10,[16]HISTODEC22!$A$6:$AU$39,33,0) -> 0 | Y10: =VLOOKUP($A10,[16]HISTODEC22!$A$6:$BP$39,65,0) -> 0 | AA10: =VLOOKUP($A10,[16]HISTODEC22!$A$6:$AU$39,43,0) -> 0 | AB10: =VLOOKUP($A10,[16]HISTODEC22!$A$6:$AU$39,44,0) -> 0 | AC10: =VLOOKUP($A10,[16]HISTODEC22!$A$6:$AU$39,47,0) -> 0 | AD10: =VLOOKUP(A10,[16]HISTODEC22!$A$6:$BB$36,54,0) -> 0 | AE10: =VLOOKUP($A10,[16]HISTODEC22!$A$6:$CA$36,60,0) -> 0 | AF10: =VLOOKUP($A10,[16]HISTODEC22!$A$6:$CA$36,61,0) -> 0 | AG10: =VLOOKUP($A10,[16]HISTODEC22!$A$6:$CA$36,62,0) -> 0 | AH10: =VLOOKUP($A10,[16]HISTODEC22!$A$6:$CA$36,63,0) -> 0 | AI10: =VLOOKUP($A10,[16]HISTODEC22!$A$6:$CA$36,64,0) -> 0 | AJ10: =VLOOKUP($A10,[16]HISTODEC22!$A$6:$CA$36,65,0) -> 0
A11: AS201605 | B11: =VLOOKUP(A11,[15]LISTADHERENT!$A$5:$J$45,3,0) -> DJOUKWE NANGUEN GUY BLAISE | C11: 600000 | D11: =VLOOKUP(A11,'[17]EPARGNE 2023'!$A$5:$BF$47,4,0) -> 4750.0783 | F11: =C11+D11-E11 -> 604750.08 | G11: 38414.988 | H11: =+F11+G11 -> 643165.07 | I11: =VLOOKUP($A11,[16]HISTODEC22!$A$6:$AQ$37,22,0) -> 0 | J11: =VLOOKUP($A11,[16]HISTODEC22!$A$6:$AU$39,45,0) -> 7000 | L11: =IF(J11=0,0,500) -> 500 | M11: =IF(J11=0,0,1000) -> 1000 | N11: =IF(J11=0,0,2500) -> 2500 | O11: =VLOOKUP($A11,[16]HISTODEC22!$A$6:$AU$39,7,0) -> 0 | P11: =VLOOKUP($A11,[16]HISTODEC22!$A$6:$AU$39,23,0) -> 0 | Q11: =VLOOKUP($A11,[16]HISTODEC22!$A$6:$AU$39,46,0) -> 0 | R11: =VLOOKUP($A11,[18]HISTODEC22!$A$6:$AU$39,26,0) -> 1000000 | S11: =VLOOKUP($A11,[18]HISTODEC22!$A$6:$BG$39,58,0) -> 40000 | T11: =VLOOKUP($A11,[16]HISTODEC22!$A$6:$AU$39,28,0) -> 0 | U11: =VLOOKUP($A11,[16]HISTODEC22!$A$6:$AU$39,19,0) -> 1000000 | V11: =VLOOKUP($A11,[16]HISTODEC22!$A$6:$AU$39,20,0) -> BANQUE | W11: =VLOOKUP($A11,[16]HISTODEC22!$A$6:$AU$39,27,0) -> BANQUE | X11: =VLOOKUP($A11,[16]HISTODEC22!$A$6:$AU$39,33,0) -> 0 | Y11: =VLOOKUP($A11,[16]HISTODEC22!$A$6:$BP$39,65,0) -> 0 | AA11: =VLOOKUP($A11,[16]HISTODEC22!$A$6:$AU$39,43,0) -> 0 | AB11: =VLOOKUP($A11,[16]HISTODEC22!$A$6:$AU$39,44,0) -> 0 | AC11: =VLOOKUP($A11,[16]HISTODEC22!$A$6:$AU$39,47,0) -> 0 | AD11: =VLOOKUP(A11,[16]HISTODEC22!$A$6:$BB$36,54,0) -> 0 | AE11: =VLOOKUP($A11,[16]HISTODEC22!$A$6:$CA$36,60,0) -> 0 | AF11: =VLOOKUP($A11,[16]HISTODEC22!$A$6:$CA$36,61,0) -> 0 | AG11: =VLOOKUP($A11,[16]HISTODEC22!$A$6:$CA$36,62,0) -> 0 | AH11: =VLOOKUP($A11,[16]HISTODEC22!$A$6:$CA$36,63,0) -> 0 | AI11: =VLOOKUP($A11,[16]HISTODEC22!$A$6:$CA$36,64,0) -> 0 | AJ11: =VLOOKUP($A11,[16]HISTODEC22!$A$6:$CA$36,65,0) -> 0
A12: AS201608 | B12: =VLOOKUP(A12,[15]LISTADHERENT!$A$5:$J$45,3,0) -> DJUOMBESSY ANTOINE | C12: 600000 | D12: =VLOOKUP(A12,'[17]EPARGNE 2023'!$A$5:$BF$47,4,0) -> 10718.85 | F12: =C12+D12-E12 -> 610718.85 | G12: 38794.137 | H12: =+F12+G12 -> 649512.99 | I12: =VLOOKUP($A12,[16]HISTODEC22!$A$6:$AQ$37,22,0) -> 0 | J12: =VLOOKUP($A12,[16]HISTODEC22!$A$6:$AU$39,45,0) -> 8000 | L12: =IF(J12=0,0,500) -> 500 | M12: =IF(J12=0,0,1000) -> 1000 | N12: =IF(J12=0,0,2500) -> 2500 | O12: =VLOOKUP($A12,[16]HISTODEC22!$A$6:$AU$39,7,0) -> 0 | P12: =VLOOKUP($A12,[16]HISTODEC22!$A$6:$AU$39,23,0) -> 0 | Q12: =VLOOKUP($A12,[16]HISTODEC22!$A$6:$AU$39,46,0) -> 0 | R12: =VLOOKUP($A12,[18]HISTODEC22!$A$6:$AU$39,26,0) -> 1000000 | S12: =VLOOKUP($A12,[18]HISTODEC22!$A$6:$BG$39,58,0) -> 60000 | T12: =VLOOKUP($A12,[16]HISTODEC22!$A$6:$AU$39,28,0) -> 0 | U12: =VLOOKUP($A12,[16]HISTODEC22!$A$6:$AU$39,19,0) -> 0 | V12: =VLOOKUP($A12,[16]HISTODEC22!$A$6:$AU$39,20,0) -> 0 | W12: =VLOOKUP($A12,[16]HISTODEC22!$A$6:$AU$39,27,0) -> BANQUE | X12: =VLOOKUP($A12,[16]HISTODEC22!$A$6:$AU$39,33,0) -> 0 | Y12: =VLOOKUP($A12,[16]HISTODEC22!$A$6:$BP$39,65,0) -> 0 | AA12: =VLOOKUP($A12,[16]HISTODEC22!$A$6:$AU$39,43,0) -> 0 | AB12: =VLOOKUP($A12,[16]HISTODEC22!$A$6:$AU$39,44,0) -> 0 | AC12: =VLOOKUP($A12,[16]HISTODEC22!$A$6:$AU$39,47,0) -> 0 | AD12: =VLOOKUP(A12,[16]HISTODEC22!$A$6:$BB$36,54,0) -> 9000 | AE12: =VLOOKUP($A12,[16]HISTODEC22!$A$6:$CA$36,60,0) -> 0 | AF12: =VLOOKUP($A12,[16]HISTODEC22!$A$6:$CA$36,61,0) -> 0 | AG12: =VLOOKUP($A12,[16]HISTODEC22!$A$6:$CA$36,62,0) -> 0 | AH12: =VLOOKUP($A12,[16]HISTODEC22!$A$6:$CA$36,63,0) -> 0 | AI12: =VLOOKUP($A12,[16]HISTODEC22!$A$6:$CA$36,64,0) -> 0 | AJ12: =VLOOKUP($A12,[16]HISTODEC22!$A$6:$CA$36,65,0) -> 0
A13: AS201651 | B13: =VLOOKUP(A13,[15]LISTADHERENT!$A$5:$J$45,3,0) -> DOMOU FABIEN | C13: 600000 | D13: =VLOOKUP(A13,'[17]EPARGNE 2023'!$A$5:$BF$47,4,0) -> 584.046 | F13: =C13+D13-E13 -> 600584.05 | G13: 38150.353 | H13: =+F13+G13 -> 638734.4 | I13: =VLOOKUP($A13,[16]HISTODEC22!$A$6:$AQ$37,22,0) -> 0 | J13: =VLOOKUP($A13,[16]HISTODEC22!$A$6:$AU$39,45,0) -> 12000 | L13: =IF(J13=0,0,500) -> 500 | M13: =IF(J13=0,0,1000) -> 1000 | N13: =IF(J13=0,0,2500) -> 2500 | O13: =VLOOKUP($A13,[16]HISTODEC22!$A$6:$AU$39,7,0) -> 0 | P13: =VLOOKUP($A13,[16]HISTODEC22!$A$6:$AU$39,23,0) -> 0 | Q13: =VLOOKUP($A13,[16]HISTODEC22!$A$6:$AU$39,46,0) -> 0 | R13: =VLOOKUP($A13,[18]HISTODEC22!$A$6:$AU$39,26,0) -> 1000000 | S13: =VLOOKUP($A13,[18]HISTODEC22!$A$6:$BG$39,58,0) -> 120000 | T13: =VLOOKUP($A13,[16]HISTODEC22!$A$6:$AU$39,28,0) -> 0 | U13: =VLOOKUP($A13,[16]HISTODEC22!$A$6:$AU$39,19,0) -> 1000000 | V13: =VLOOKUP($A13,[16]HISTODEC22!$A$6:$AU$39,20,0) -> BANQUE | W13: =VLOOKUP($A13,[16]HISTODEC22!$A$6:$AU$39,27,0) -> BANQUE | X13: =VLOOKUP($A13,[16]HISTODEC22!$A$6:$AU$39,33,0) -> 0 | Y13: =VLOOKUP($A13,[16]HISTODEC22!$A$6:$BP$39,65,0) -> 0 | AA13: =VLOOKUP($A13,[16]HISTODEC22!$A$6:$AU$39,43,0) -> 0 | AB13: =VLOOKUP($A13,[16]HISTODEC22!$A$6:$AU$39,44,0) -> 0 | AC13: =VLOOKUP($A13,[16]HISTODEC22!$A$6:$AU$39,47,0) -> 0 | AD13: =VLOOKUP(A13,[16]HISTODEC22!$A$6:$BB$36,54,0) -> 0 | AE13: =VLOOKUP($A13,[16]HISTODEC22!$A$6:$CA$36,60,0) -> 0 | AF13: =VLOOKUP($A13,[16]HISTODEC22!$A$6:$CA$36,61,0) -> 0 | AG13: =VLOOKUP($A13,[16]HISTODEC22!$A$6:$CA$36,62,0) -> 0 | AH13: =VLOOKUP($A13,[16]HISTODEC22!$A$6:$CA$36,63,0) -> 0 | AI13: =VLOOKUP($A13,[16]HISTODEC22!$A$6:$CA$36,64,0) -> 0 | AJ13: =VLOOKUP($A13,[16]HISTODEC22!$A$6:$CA$36,65,0) -> 0
A14: AS201609 | B14: =VLOOKUP(A14,[15]LISTADHERENT!$A$5:$J$45,3,0) -> DONHOU DAVID | C14: 600000 | D14: =VLOOKUP(A14,'[17]EPARGNE 2023'!$A$5:$BF$47,4,0) -> 458343.18 | F14: =C14+D14-E14 -> 1058343.2 | G14: 67228.169 | H14: =+F14+G14 -> 1125571.3 | I14: =VLOOKUP($A14,[16]HISTODEC22!$A$6:$AQ$37,22,0) -> 0 | J14: =VLOOKUP($A14,[16]HISTODEC22!$A$6:$AU$39,45,0) -> 12000 | L14: =IF(J14=0,0,500) -> 500 | M14: =IF(J14=0,0,1000) -> 1000 | N14: =IF(J14=0,0,2500) -> 2500 | O14: =VLOOKUP($A14,[16]HISTODEC22!$A$6:$AU$39,7,0) -> 0 | P14: =VLOOKUP($A14,[16]HISTODEC22!$A$6:$AU$39,23,0) -> 0 | Q14: =VLOOKUP($A14,[16]HISTODEC22!$A$6:$AU$39,46,0) -> 0 | R14: =VLOOKUP($A14,[18]HISTODEC22!$A$6:$AU$39,26,0) -> 0 | S14: =VLOOKUP($A14,[18]HISTODEC22!$A$6:$BG$39,58,0) -> 0 | T14: =VLOOKUP($A14,[16]HISTODEC22!$A$6:$AU$39,28,0) -> 0 | U14: =VLOOKUP($A14,[16]HISTODEC22!$A$6:$AU$39,19,0) -> 0 | V14: =VLOOKUP($A14,[16]HISTODEC22!$A$6:$AU$39,20,0) -> 0 | W14: =VLOOKUP($A14,[16]HISTODEC22!$A$6:$AU$39,27,0) -> 0 | X14: =VLOOKUP($A14,[16]HISTODEC22!$A$6:$AU$39,33,0) -> 0 | Y14: =VLOOKUP($A14,[16]HISTODEC22!$A$6:$BP$39,65,0) -> 0 | AA14: =VLOOKUP($A14,[16]HISTODEC22!$A$6:$AU$39,43,0) -> 0 | AB14: =VLOOKUP($A14,[16]HISTODEC22!$A$6:$AU$39,44,0) -> 0 | AC14: =VLOOKUP($A14,[16]HISTODEC22!$A$6:$AU$39,47,0) -> 0 | AD14: =VLOOKUP(A14,[16]HISTODEC22!$A$6:$BB$36,54,0) -> 0 | AE14: =VLOOKUP($A14,[16]HISTODEC22!$A$6:$CA$36,60,0) -> 0 | AF14: =VLOOKUP($A14,[16]HISTODEC22!$A$6:$CA$36,61,0) -> 0 | AG14: =VLOOKUP($A14,[16]HISTODEC22!$A$6:$CA$36,62,0) -> 0 | AH14: =VLOOKUP($A14,[16]HISTODEC22!$A$6:$CA$36,63,0) -> 0 | AI14: =VLOOKUP($A14,[16]HISTODEC22!$A$6:$CA$36,64,0) -> 0 | AJ14: =VLOOKUP($A14,[16]HISTODEC22!$A$6:$CA$36,65,0) -> 0
A15: AS201611 | B15: =VLOOKUP(A15,[15]LISTADHERENT!$A$5:$J$45,3,0) -> HENGUE PAUL OMER | C15: 600000 | D15: =VLOOKUP(A15,'[17]EPARGNE 2023'!$A$5:$BF$47,4,0) -> 51112.01 | F15: =C15+D15-E15 -> 651112.01 | G15: 41359.995 | H15: =+F15+G15 -> 692472.01 | I15: =VLOOKUP($A15,[16]HISTODEC22!$A$6:$AQ$37,22,0) -> 0 | J15: =VLOOKUP($A15,[16]HISTODEC22!$A$6:$AU$39,45,0) -> 7000 | L15: =IF(J15=0,0,500) -> 500 | M15: =IF(J15=0,0,1000) -> 1000 | N15: =IF(J15=0,0,2500) -> 2500 | O15: =VLOOKUP($A15,[16]HISTODEC22!$A$6:$AU$39,7,0) -> 0 | P15: =VLOOKUP($A15,[16]HISTODEC22!$A$6:$AU$39,23,0) -> 0 | Q15: =VLOOKUP($A15,[16]HISTODEC22!$A$6:$AU$39,46,0) -> 0 | R15: =VLOOKUP($A15,[18]HISTODEC22!$A$6:$AU$39,26,0) -> 0 | S15: =VLOOKUP($A15,[18]HISTODEC22!$A$6:$BG$39,58,0) -> 0 | T15: =VLOOKUP($A15,[16]HISTODEC22!$A$6:$AU$39,28,0) -> 0 | U15: =VLOOKUP($A15,[16]HISTODEC22!$A$6:$AU$39,19,0) -> 0 | V15: =VLOOKUP($A15,[16]HISTODEC22!$A$6:$AU$39,20,0) -> 0 | W15: =VLOOKUP($A15,[16]HISTODEC22!$A$6:$AU$39,27,0) -> 0 | X15: =VLOOKUP($A15,[16]HISTODEC22!$A$6:$AU$39,33,0) -> 0 | Y15: =VLOOKUP($A15,[16]HISTODEC22!$A$6:$BP$39,65,0) -> 0 | AA15: =VLOOKUP($A15,[16]HISTODEC22!$A$6:$AU$39,43,0) -> 0 | AB15: =VLOOKUP($A15,[16]HISTODEC22!$A$6:$AU$39,44,0) -> 0 | AC15: =VLOOKUP($A15,[16]HISTODEC22!$A$6:$AU$39,47,0) -> 0 | AD15: =VLOOKUP(A15,[16]HISTODEC22!$A$6:$BB$36,54,0) -> 0 | AE15: =VLOOKUP($A15,[16]HISTODEC22!$A$6:$CA$36,60,0) -> 0 | AF15: =VLOOKUP($A15,[16]HISTODEC22!$A$6:$CA$36,61,0) -> 0 | AG15: =VLOOKUP($A15,[16]HISTODEC22!$A$6:$CA$36,62,0) -> 0 | AH15: =VLOOKUP($A15,[16]HISTODEC22!$A$6:$CA$36,63,0) -> 0 | AI15: =VLOOKUP($A15,[16]HISTODEC22!$A$6:$CA$36,64,0) -> 0 | AJ15: =VLOOKUP($A15,[16]HISTODEC22!$A$6:$CA$36,65,0) -> 0
A16: AS201613 | B16: =VLOOKUP(A16,[15]LISTADHERENT!$A$5:$J$45,3,0) -> HOTCHO BENJAMIN | C16: 600000 | D16: =VLOOKUP(A16,'[17]EPARGNE 2023'!$A$5:$BF$47,4,0) -> 16229.566 | F16: =C16+D16-E16 -> 616229.57 | G16: 39144.189 | H16: =+F16+G16 -> 655373.76 | I16: =VLOOKUP($A16,[16]HISTODEC22!$A$6:$AQ$37,22,0) -> 0 | J16: =VLOOKUP($A16,[16]HISTODEC22!$A$6:$AU$39,45,0) -> 52000 | L16: =IF(J16=0,0,500) -> 500 | M16: =IF(J16=0,0,1000) -> 1000 | N16: =IF(J16=0,0,2500) -> 2500 | O16: =VLOOKUP($A16,[16]HISTODEC22!$A$6:$AU$39,7,0) -> 0 | P16: =VLOOKUP($A16,[16]HISTODEC22!$A$6:$AU$39,23,0) -> 0 | Q16: =VLOOKUP($A16,[16]HISTODEC22!$A$6:$AU$39,46,0) -> 0 | R16: =VLOOKUP($A16,[18]HISTODEC22!$A$6:$AU$39,26,0) -> 1000000 | S16: =VLOOKUP($A16,[18]HISTODEC22!$A$6:$BG$39,58,0) -> 120000 | T16: =VLOOKUP($A16,[16]HISTODEC22!$A$6:$AU$39,28,0) -> 0 | U16: =VLOOKUP($A16,[16]HISTODEC22!$A$6:$AU$39,19,0) -> 1000000 | V16: =VLOOKUP($A16,[16]HISTODEC22!$A$6:$AU$39,20,0) -> BANQUE | W16: =VLOOKUP($A16,[16]HISTODEC22!$A$6:$AU$39,27,0) -> BANQUE | X16: =VLOOKUP($A16,[16]HISTODEC22!$A$6:$AU$39,33,0) -> 0 | Y16: =VLOOKUP($A16,[16]HISTODEC22!$A$6:$BP$39,65,0) -> 0 | AA16: =VLOOKUP($A16,[16]HISTODEC22!$A$6:$AU$39,43,0) -> 0 | AB16: =VLOOKUP($A16,[16]HISTODEC22!$A$6:$AU$39,44,0) -> 0 | AC16: =VLOOKUP($A16,[16]HISTODEC22!$A$6:$AU$39,47,0) -> 0 | AD16: =VLOOKUP(A16,[16]HISTODEC22!$A$6:$BB$36,54,0) -> 0 | AE16: =VLOOKUP($A16,[16]HISTODEC22!$A$6:$CA$36,60,0) -> 0 | AF16: =VLOOKUP($A16,[16]HISTODEC22!$A$6:$CA$36,61,0) -> 0 | AG16: =VLOOKUP($A16,[16]HISTODEC22!$A$6:$CA$36,62,0) -> 0 | AH16: =VLOOKUP($A16,[16]HISTODEC22!$A$6:$CA$36,63,0) -> 0 | AI16: =VLOOKUP($A16,[16]HISTODEC22!$A$6:$CA$36,64,0) -> 0 | AJ16: =VLOOKUP($A16,[16]HISTODEC22!$A$6:$CA$36,65,0) -> 0
A17: AS201617 | B17: =VLOOKUP(A17,[15]LISTADHERENT!$A$5:$J$45,3,0) -> KOUAMOU MOISE | C17: 600000 | D17: =VLOOKUP(A17,'[17]EPARGNE 2023'!$A$5:$BF$47,4,0) -> 53292.832 | F17: =C17+D17-E17 -> 653292.83 | G17: 41498.525 | H17: =+F17+G17 -> 694791.36 | I17: =VLOOKUP($A17,[16]HISTODEC22!$A$6:$AQ$37,22,0) -> 0 | J17: =VLOOKUP($A17,[16]HISTODEC22!$A$6:$AU$39,45,0) -> 7000 | L17: =IF(J17=0,0,500) -> 500 | M17: =IF(J17=0,0,1000) -> 1000 | N17: =IF(J17=0,0,2500) -> 2500 | O17: =VLOOKUP($A17,[16]HISTODEC22!$A$6:$AU$39,7,0) -> 0 | P17: =VLOOKUP($A17,[16]HISTODEC22!$A$6:$AU$39,23,0) -> 0 | Q17: =VLOOKUP($A17,[16]HISTODEC22!$A$6:$AU$39,46,0) -> 0 | R17: =VLOOKUP($A17,[18]HISTODEC22!$A$6:$AU$39,26,0) -> 0 | S17: =VLOOKUP($A17,[18]HISTODEC22!$A$6:$BG$39,58,0) -> 0 | T17: =VLOOKUP($A17,[16]HISTODEC22!$A$6:$AU$39,28,0) -> 0 | U17: =VLOOKUP($A17,[16]HISTODEC22!$A$6:$AU$39,19,0) -> 700000 | V17: =VLOOKUP($A17,[16]HISTODEC22!$A$6:$AU$39,20,0) -> BANQUE | W17: =VLOOKUP($A17,[16]HISTODEC22!$A$6:$AU$39,27,0) -> 0 | X17: =VLOOKUP($A17,[16]HISTODEC22!$A$6:$AU$39,33,0) -> 0 | Y17: =VLOOKUP($A17,[16]HISTODEC22!$A$6:$BP$39,65,0) -> 0 | AA17: =VLOOKUP($A17,[16]HISTODEC22!$A$6:$AU$39,43,0) -> 0 | AB17: =VLOOKUP($A17,[16]HISTODEC22!$A$6:$AU$39,44,0) -> 0 | AC17: =VLOOKUP($A17,[16]HISTODEC22!$A$6:$AU$39,47,0) -> 0 | AD17: =VLOOKUP(A17,[16]HISTODEC22!$A$6:$BB$36,54,0) -> 0 | AE17: =VLOOKUP($A17,[16]HISTODEC22!$A$6:$CA$36,60,0) -> 0 | AF17: =VLOOKUP($A17,[16]HISTODEC22!$A$6:$CA$36,61,0) -> 0 | AG17: =VLOOKUP($A17,[16]HISTODEC22!$A$6:$CA$36,62,0) -> 0 | AH17: =VLOOKUP($A17,[16]HISTODEC22!$A$6:$CA$36,63,0) -> 0 | AI17: =VLOOKUP($A17,[16]HISTODEC22!$A$6:$CA$36,64,0) -> 0 | AJ17: =VLOOKUP($A17,[16]HISTODEC22!$A$6:$CA$36,65,0) -> 0
A18: AS201619 | B18: =VLOOKUP(A18,[15]LISTADHERENT!$A$5:$J$45,3,0) -> KOUATCHO MESSACK | C18: 600000 | D18: =VLOOKUP(A18,'[17]EPARGNE 2023'!$A$5:$BF$47,4,0) -> 6459.0432 | F18: =C18+D18-E18 -> 606459.04 | G18: 38523.545 | H18: =+F18+G18 -> 644982.59 | I18: =VLOOKUP($A18,[16]HISTODEC22!$A$6:$AQ$37,22,0) -> 0 | J18: =VLOOKUP($A18,[16]HISTODEC22!$A$6:$AU$39,45,0) -> 7000 | L18: =IF(J18=0,0,500) -> 500 | M18: =IF(J18=0,0,1000) -> 1000 | N18: =IF(J18=0,0,2500) -> 2500 | O18: =VLOOKUP($A18,[16]HISTODEC22!$A$6:$AU$39,7,0) -> 0 | P18: =VLOOKUP($A18,[16]HISTODEC22!$A$6:$AU$39,23,0) -> 0 | Q18: =VLOOKUP($A18,[16]HISTODEC22!$A$6:$AU$39,46,0) -> 0 | R18: =VLOOKUP($A18,[18]HISTODEC22!$A$6:$AU$39,26,0) -> 1000000 | S18: =VLOOKUP($A18,[18]HISTODEC22!$A$6:$BG$39,58,0) -> 60000 | T18: =VLOOKUP($A18,[16]HISTODEC22!$A$6:$AU$39,28,0) -> 0 | U18: =VLOOKUP($A18,[16]HISTODEC22!$A$6:$AU$39,19,0) -> 1000000 | V18: =VLOOKUP($A18,[16]HISTODEC22!$A$6:$AU$39,20,0) -> BANQUE | W18: =VLOOKUP($A18,[16]HISTODEC22!$A$6:$AU$39,27,0) -> BANQUE | X18: =VLOOKUP($A18,[16]HISTODEC22!$A$6:$AU$39,33,0) -> 0 | Y18: =VLOOKUP($A18,[16]HISTODEC22!$A$6:$BP$39,65,0) -> 0 | AA18: =VLOOKUP($A18,[16]HISTODEC22!$A$6:$AU$39,43,0) -> 0 | AB18: =VLOOKUP($A18,[16]HISTODEC22!$A$6:$AU$39,44,0) -> 0 | AC18: =VLOOKUP($A18,[16]HISTODEC22!$A$6:$AU$39,47,0) -> 0 | AD18: =VLOOKUP(A18,[16]HISTODEC22!$A$6:$BB$36,54,0) -> 0 | AE18: =VLOOKUP($A18,[16]HISTODEC22!$A$6:$CA$36,60,0) -> 0 | AF18: =VLOOKUP($A18,[16]HISTODEC22!$A$6:$CA$36,61,0) -> 0 | AG18: =VLOOKUP($A18,[16]HISTODEC22!$A$6:$CA$36,62,0) -> 0 | AH18: =VLOOKUP($A18,[16]HISTODEC22!$A$6:$CA$36,63,0) -> 0 | AI18: =VLOOKUP($A18,[16]HISTODEC22!$A$6:$CA$36,64,0) -> 0 | AJ18: =VLOOKUP($A18,[16]HISTODEC22!$A$6:$CA$36,65,0) -> 0
A19: AS201620 | B19: =VLOOKUP(A19,[15]LISTADHERENT!$A$5:$J$45,3,0) -> LOWE JEAN | C19: 600000 | D19: =VLOOKUP(A19,'[17]EPARGNE 2023'!$A$5:$BF$47,4,0) -> 746.1759 | F19: =C19+D19-E19 -> 600746.18 | G19: 38160.652 | H19: =+F19+G19 -> 638906.83 | I19: =VLOOKUP($A19,[16]HISTODEC22!$A$6:$AQ$37,22,0) -> 0 | J19: =VLOOKUP($A19,[16]HISTODEC22!$A$6:$AU$39,45,0) -> 7000 | L19: =IF(J19=0,0,500) -> 500 | M19: =IF(J19=0,0,1000) -> 1000 | N19: =IF(J19=0,0,2500) -> 2500 | O19: =VLOOKUP($A19,[16]HISTODEC22!$A$6:$AU$39,7,0) -> 0 | P19: =VLOOKUP($A19,[16]HISTODEC22!$A$6:$AU$39,23,0) -> 0 | Q19: =VLOOKUP($A19,[16]HISTODEC22!$A$6:$AU$39,46,0) -> 0 | R19: =VLOOKUP($A19,[18]HISTODEC22!$A$6:$AU$39,26,0) -> 1000000 | S19: =VLOOKUP($A19,[18]HISTODEC22!$A$6:$BG$39,58,0) -> 40000 | T19: =VLOOKUP($A19,[16]HISTODEC22!$A$6:$AU$39,28,0) -> 0 | U19: =VLOOKUP($A19,[16]HISTODEC22!$A$6:$AU$39,19,0) -> 1000000 | V19: =VLOOKUP($A19,[16]HISTODEC22!$A$6:$AU$39,20,0) -> BANQUE | W19: =VLOOKUP($A19,[16]HISTODEC22!$A$6:$AU$39,27,0) -> BANQUE | X19: =VLOOKUP($A19,[16]HISTODEC22!$A$6:$AU$39,33,0) -> 0 | Y19: =VLOOKUP($A19,[16]HISTODEC22!$A$6:$BP$39,65,0) -> 0 | AA19: =VLOOKUP($A19,[16]HISTODEC22!$A$6:$AU$39,43,0) -> 0 | AB19: =VLOOKUP($A19,[16]HISTODEC22!$A$6:$AU$39,44,0) -> 0 | AC19: =VLOOKUP($A19,[16]HISTODEC22!$A$6:$AU$39,47,0) -> 0 | AD19: =VLOOKUP(A19,[16]HISTODEC22!$A$6:$BB$36,54,0) -> 0 | AE19: =VLOOKUP($A19,[16]HISTODEC22!$A$6:$CA$36,60,0) -> 0 | AF19: =VLOOKUP($A19,[16]HISTODEC22!$A$6:$CA$36,61,0) -> 0 | AG19: =VLOOKUP($A19,[16]HISTODEC22!$A$6:$CA$36,62,0) -> 0 | AH19: =VLOOKUP($A19,[16]HISTODEC22!$A$6:$CA$36,63,0) -> 0 | AI19: =VLOOKUP($A19,[16]HISTODEC22!$A$6:$CA$36,64,0) -> 0 | AJ19: =VLOOKUP($A19,[16]HISTODEC22!$A$6:$CA$36,65,0) -> 0
... A26: AS201628 | B26: =VLOOKUP(A26,[15]LISTADHERENT!$A$5:$J$45,3,0) -> NKAMGANG JUSTIN DEJOLIE | C26: 600000 | D26: =VLOOKUP(A26,'[17]EPARGNE 2023'!$A$5:$BF$47,4,0) -> 575.28053 | F26: =C26+D26-E26 -> 600575.28 | G26: 38149.796 | H26: =+F26+G26 -> 638725.08 | I26: =VLOOKUP($A26,[16]HISTODEC22!$A$6:$AQ$37,22,0) -> 0 | J26: =VLOOKUP($A26,[16]HISTODEC22!$A$6:$AU$39,45,0) -> 7000 | L26: =IF(J26=0,0,500) -> 500 | M26: =IF(J26=0,0,1000) -> 1000 | N26: =IF(J26=0,0,2500) -> 2500 | O26: =VLOOKUP($A26,[16]HISTODEC22!$A$6:$AU$39,7,0) -> 0 | P26: =VLOOKUP($A26,[16]HISTODEC22!$A$6:$AU$39,23,0) -> 0 | Q26: =VLOOKUP($A26,[16]HISTODEC22!$A$6:$AU$39,46,0) -> 0 | R26: =VLOOKUP($A26,[18]HISTODEC22!$A$6:$AU$39,26,0) -> 1000000 | S26: =VLOOKUP($A26,[18]HISTODEC22!$A$6:$BG$39,58,0) -> 20000 | T26: =VLOOKUP($A26,[16]HISTODEC22!$A$6:$AU$39,28,0) -> 0 | U26: =VLOOKUP($A26,[16]HISTODEC22!$A$6:$AU$39,19,0) -> 1000000 | V26: =VLOOKUP($A26,[16]HISTODEC22!$A$6:$AU$39,20,0) -> BANQUE | W26: =VLOOKUP($A26,[16]HISTODEC22!$A$6:$AU$39,27,0) -> BANQUE | X26: =VLOOKUP($A26,[16]HISTODEC22!$A$6:$AU$39,33,0) -> 0 | Y26: =VLOOKUP($A26,[16]HISTODEC22!$A$6:$BP$39,65,0) -> 0 | AA26: =VLOOKUP($A26,[16]HISTODEC22!$A$6:$AU$39,43,0) -> 0 | AB26: =VLOOKUP($A26,[16]HISTODEC22!$A$6:$AU$39,44,0) -> 0 | AC26: =VLOOKUP($A26,[16]HISTODEC22!$A$6:$AU$39,47,0) -> 0 | AD26: =VLOOKUP(A26,[16]HISTODEC22!$A$6:$BB$36,54,0) -> 0 | AE26: =VLOOKUP($A26,[16]HISTODEC22!$A$6:$CA$36,60,0) -> 0 | AF26: =VLOOKUP($A26,[16]HISTODEC22!$A$6:$CA$36,61,0) -> 0 | AG26: =VLOOKUP($A26,[16]HISTODEC22!$A$6:$CA$36,62,0) -> 0 | AH26: =VLOOKUP($A26,[16]HISTODEC22!$A$6:$CA$36,63,0) -> 0 | AI26: =VLOOKUP($A26,[16]HISTODEC22!$A$6:$CA$36,64,0) -> 0 | AJ26: =VLOOKUP($A26,[16]HISTODEC22!$A$6:$CA$36,65,0) -> 0
A27: AS201656 | B27: =VLOOKUP(A27,[15]LISTADHERENT!$A$5:$J$45,3,0) -> NOUBE ETIENNE | C27: 0 | D27: =VLOOKUP(A27,'[17]EPARGNE 2023'!$A$5:$BF$47,4,0) -> 0 | F27: =C27+D27-E27 -> 0 | G27: 0 | H27: =+F27+G27 -> 0
A28: AS201633 | B28: =VLOOKUP(A28,[15]LISTADHERENT!$A$5:$J$45,3,0) -> PATEGO NJOSSU GUSTAVE | C28: 600000 | D28: =VLOOKUP(A28,'[17]EPARGNE 2023'!$A$5:$BF$47,4,0) -> 21451.963 | F28: =C28+D28-E28 -> 621451.96 | G28: 39475.927 | H28: =+F28+G28 -> 660927.89 | I28: =VLOOKUP($A28,[16]HISTODEC22!$A$6:$AQ$37,22,0) -> 0 | J28: =VLOOKUP($A28,[16]HISTODEC22!$A$6:$AU$39,45,0) -> 7000 | L28: =IF(J28=0,0,500) -> 500 | M28: =IF(J28=0,0,1000) -> 1000 | N28: =IF(J28=0,0,2500) -> 2500 | O28: =VLOOKUP($A28,[16]HISTODEC22!$A$6:$AU$39,7,0) -> 0 | P28: =VLOOKUP($A28,[16]HISTODEC22!$A$6:$AU$39,23,0) -> 0 | Q28: =VLOOKUP($A28,[16]HISTODEC22!$A$6:$AU$39,46,0) -> 0 | R28: =VLOOKUP($A28,[18]HISTODEC22!$A$6:$AU$39,26,0) -> 0 | S28: =VLOOKUP($A28,[18]HISTODEC22!$A$6:$BG$39,58,0) -> 0 | T28: =VLOOKUP($A28,[16]HISTODEC22!$A$6:$AU$39,28,0) -> 0 | U28: =VLOOKUP($A28,[16]HISTODEC22!$A$6:$AU$39,19,0) -> 0 | V28: =VLOOKUP($A28,[16]HISTODEC22!$A$6:$AU$39,20,0) -> 0 | W28: =VLOOKUP($A28,[16]HISTODEC22!$A$6:$AU$39,27,0) -> 0 | X28: =VLOOKUP($A28,[16]HISTODEC22!$A$6:$AU$39,33,0) -> 0 | Y28: =VLOOKUP($A28,[16]HISTODEC22!$A$6:$BP$39,65,0) -> 0 | AA28: =VLOOKUP($A28,[16]HISTODEC22!$A$6:$AU$39,43,0) -> 0 | AB28: =VLOOKUP($A28,[16]HISTODEC22!$A$6:$AU$39,44,0) -> 0 | AC28: =VLOOKUP($A28,[16]HISTODEC22!$A$6:$AU$39,47,0) -> 0 | AD28: =VLOOKUP(A28,[16]HISTODEC22!$A$6:$BB$36,54,0) -> 0 | AE28: =VLOOKUP($A28,[16]HISTODEC22!$A$6:$CA$36,60,0) -> 0 | AF28: =VLOOKUP($A28,[16]HISTODEC22!$A$6:$CA$36,61,0) -> 0 | AG28: =VLOOKUP($A28,[16]HISTODEC22!$A$6:$CA$36,62,0) -> 0 | AH28: =VLOOKUP($A28,[16]HISTODEC22!$A$6:$CA$36,63,0) -> 0 | AI28: =VLOOKUP($A28,[16]HISTODEC22!$A$6:$CA$36,64,0) -> 0 | AJ28: =VLOOKUP($A28,[16]HISTODEC22!$A$6:$CA$36,65,0) -> 0
A29: AS201657 | B29: =VLOOKUP(A29,[15]LISTADHERENT!$A$5:$J$45,3,0) -> SEUMO POLYCARPE | C29: 0 | D29: =VLOOKUP(A29,'[17]EPARGNE 2023'!$A$5:$BF$47,4,0) -> 0 | F29: =C29+D29-E29 -> 0 | G29: 0 | H29: =+F29+G29 -> 0
A30: AS201653 | B30: =VLOOKUP(A30,[15]LISTADHERENT!$A$5:$J$45,3,0) -> SIME BRICE | C30: 600000 | D30: =VLOOKUP(A30,'[17]EPARGNE 2023'!$A$5:$BF$47,4,0) -> 200752.48 | F30: =C30+D30-E30 -> 800752.48 | G30: 50865.47 | H30: =+F30+G30 -> 851617.95 | I30: =VLOOKUP($A30,[16]HISTODEC22!$A$6:$AQ$37,22,0) -> 0 | J30: =VLOOKUP($A30,[16]HISTODEC22!$A$6:$AU$39,45,0) -> 7000 | L30: =IF(J30=0,0,500) -> 500 | M30: =IF(J30=0,0,1000) -> 1000 | N30: =IF(J30=0,0,2500) -> 2500 | O30: =VLOOKUP($A30,[16]HISTODEC22!$A$6:$AU$39,7,0) -> 0 | P30: =VLOOKUP($A30,[16]HISTODEC22!$A$6:$AU$39,23,0) -> 0 | Q30: =VLOOKUP($A30,[16]HISTODEC22!$A$6:$AU$39,46,0) -> 0 | R30: =VLOOKUP($A30,[18]HISTODEC22!$A$6:$AU$39,26,0) -> 0 | S30: =VLOOKUP($A30,[18]HISTODEC22!$A$6:$BG$39,58,0) -> 0 | T30: =VLOOKUP($A30,[16]HISTODEC22!$A$6:$AU$39,28,0) -> 0 | U30: =VLOOKUP($A30,[16]HISTODEC22!$A$6:$AU$39,19,0) -> 0 | V30: =VLOOKUP($A30,[16]HISTODEC22!$A$6:$AU$39,20,0) -> 0 | W30: =VLOOKUP($A30,[16]HISTODEC22!$A$6:$AU$39,27,0) -> 0 | X30: =VLOOKUP($A30,[16]HISTODEC22!$A$6:$AU$39,33,0) -> 0 | Y30: =VLOOKUP($A30,[16]HISTODEC22!$A$6:$BP$39,65,0) -> 0 | AA30: =VLOOKUP($A30,[16]HISTODEC22!$A$6:$AU$39,43,0) -> 0 | AB30: =VLOOKUP($A30,[16]HISTODEC22!$A$6:$AU$39,44,0) -> 0 | AC30: =VLOOKUP($A30,[16]HISTODEC22!$A$6:$AU$39,47,0) -> 0 | AD30: =VLOOKUP(A30,[16]HISTODEC22!$A$6:$BB$36,54,0) -> 0 | AE30: =VLOOKUP($A30,[16]HISTODEC22!$A$6:$CA$36,60,0) -> 0 | AF30: =VLOOKUP($A30,[16]HISTODEC22!$A$6:$CA$36,61,0) -> 0 | AG30: =VLOOKUP($A30,[16]HISTODEC22!$A$6:$CA$36,62,0) -> 0 | AH30: =VLOOKUP($A30,[16]HISTODEC22!$A$6:$CA$36,63,0) -> 0 | AI30: =VLOOKUP($A30,[16]HISTODEC22!$A$6:$CA$36,64,0) -> 0 | AJ30: =VLOOKUP($A30,[16]HISTODEC22!$A$6:$CA$36,65,0) -> 0
A31: AS201638 | B31: =VLOOKUP(A31,[15]LISTADHERENT!$A$5:$J$45,3,0) -> SIMO PIERRE | C31: 600000 | D31: =VLOOKUP(A31,'[17]EPARGNE 2023'!$A$5:$BF$47,4,0) -> 103606.47 | F31: =C31+D31-E31 -> 703606.47 | G31: 44694.553 | H31: =+F31+G31 -> 748301.02 | I31: =VLOOKUP($A31,[16]HISTODEC22!$A$6:$AQ$37,22,0) -> 0 | J31: =VLOOKUP($A31,[16]HISTODEC22!$A$6:$AU$39,45,0) -> 7000 | L31: =IF(J31=0,0,500) -> 500 | M31: =IF(J31=0,0,1000) -> 1000 | N31: =IF(J31=0,0,2500) -> 2500 | O31: =VLOOKUP($A31,[16]HISTODEC22!$A$6:$AU$39,7,0) -> 0 | P31: =VLOOKUP($A31,[16]HISTODEC22!$A$6:$AU$39,23,0) -> 0 | Q31: =VLOOKUP($A31,[16]HISTODEC22!$A$6:$AU$39,46,0) -> 0 | R31: =VLOOKUP($A31,[18]HISTODEC22!$A$6:$AU$39,26,0) -> 1000000 | S31: =VLOOKUP($A31,[18]HISTODEC22!$A$6:$BG$39,58,0) -> 120000 | T31: =VLOOKUP($A31,[16]HISTODEC22!$A$6:$AU$39,28,0) -> 0 | U31: =VLOOKUP($A31,[16]HISTODEC22!$A$6:$AU$39,19,0) -> 800000 | V31: =VLOOKUP($A31,[16]HISTODEC22!$A$6:$AU$39,20,0) -> BANQUE | W31: =VLOOKUP($A31,[16]HISTODEC22!$A$6:$AU$39,27,0) -> BANQUE | X31: =VLOOKUP($A31,[16]HISTODEC22!$A$6:$AU$39,33,0) -> 0 | Y31: =VLOOKUP($A31,[16]HISTODEC22!$A$6:$BP$39,65,0) -> 0 | AA31: =VLOOKUP($A31,[16]HISTODEC22!$A$6:$AU$39,43,0) -> 0 | AB31: =VLOOKUP($A31,[16]HISTODEC22!$A$6:$AU$39,44,0) -> 0 | AC31: =VLOOKUP($A31,[16]HISTODEC22!$A$6:$AU$39,47,0) -> 0 | AD31: =VLOOKUP(A31,[16]HISTODEC22!$A$6:$BB$36,54,0) -> 0 | AE31: =VLOOKUP($A31,[16]HISTODEC22!$A$6:$CA$36,60,0) -> 0 | AF31: =VLOOKUP($A31,[16]HISTODEC22!$A$6:$CA$36,61,0) -> 0 | AG31: =VLOOKUP($A31,[16]HISTODEC22!$A$6:$CA$36,62,0) -> 0 | AH31: =VLOOKUP($A31,[16]HISTODEC22!$A$6:$CA$36,63,0) -> 0 | AI31: =VLOOKUP($A31,[16]HISTODEC22!$A$6:$CA$36,64,0) -> 0 | AJ31: =VLOOKUP($A31,[16]HISTODEC22!$A$6:$CA$36,65,0) -> 0
A32: AS201641 | B32: =VLOOKUP(A32,[15]LISTADHERENT!$A$5:$J$45,3,0) -> TCHOUAMOU MATHIEU | C32: 600000 | D32: =VLOOKUP(A32,'[17]EPARGNE 2023'!$A$5:$BF$47,4,0) -> 4207.8699 | F32: =C32+D32-E32 -> 604207.87 | G32: 38380.546 | H32: =+F32+G32 -> 642588.42 | I32: =VLOOKUP($A32,[16]HISTODEC22!$A$6:$AQ$37,22,0) -> 0 | J32: =VLOOKUP($A32,[16]HISTODEC22!$A$6:$AU$39,45,0) -> 7000 | L32: =IF(J32=0,0,500) -> 500 | M32: =IF(J32=0,0,1000) -> 1000 | N32: =IF(J32=0,0,2500) -> 2500 | O32: =VLOOKUP($A32,[16]HISTODEC22!$A$6:$AU$39,7,0) -> 0 | P32: =VLOOKUP($A32,[16]HISTODEC22!$A$6:$AU$39,23,0) -> 0 | Q32: =VLOOKUP($A32,[16]HISTODEC22!$A$6:$AU$39,46,0) -> 0 | R32: =VLOOKUP($A32,[18]HISTODEC22!$A$6:$AU$39,26,0) -> 1000000 | S32: =VLOOKUP($A32,[18]HISTODEC22!$A$6:$BG$39,58,0) -> 30000 | T32: =VLOOKUP($A32,[16]HISTODEC22!$A$6:$AU$39,28,0) -> 0 | U32: =VLOOKUP($A32,[16]HISTODEC22!$A$6:$AU$39,19,0) -> 1000000 | V32: =VLOOKUP($A32,[16]HISTODEC22!$A$6:$AU$39,20,0) -> BANQUE | W32: =VLOOKUP($A32,[16]HISTODEC22!$A$6:$AU$39,27,0) -> 0 | X32: =VLOOKUP($A32,[16]HISTODEC22!$A$6:$AU$39,33,0) -> 0 | Y32: =VLOOKUP($A32,[16]HISTODEC22!$A$6:$BP$39,65,0) -> 0 | AA32: =VLOOKUP($A32,[16]HISTODEC22!$A$6:$AU$39,43,0) -> 0 | AB32: =VLOOKUP($A32,[16]HISTODEC22!$A$6:$AU$39,44,0) -> 0 | AC32: =VLOOKUP($A32,[16]HISTODEC22!$A$6:$AU$39,47,0) -> 0 | AD32: =VLOOKUP(A32,[16]HISTODEC22!$A$6:$BB$36,54,0) -> 0 | AE32: =VLOOKUP($A32,[16]HISTODEC22!$A$6:$CA$36,60,0) -> 0 | AF32: =VLOOKUP($A32,[16]HISTODEC22!$A$6:$CA$36,61,0) -> 0 | AG32: =VLOOKUP($A32,[16]HISTODEC22!$A$6:$CA$36,62,0) -> 0 | AH32: =VLOOKUP($A32,[16]HISTODEC22!$A$6:$CA$36,63,0) -> 0 | AI32: =VLOOKUP($A32,[16]HISTODEC22!$A$6:$CA$36,64,0) -> 0 | AJ32: =VLOOKUP($A32,[16]HISTODEC22!$A$6:$CA$36,65,0) -> 0
A33: AS201643 | B33: =VLOOKUP(A33,[15]LISTADHERENT!$A$5:$J$45,3,0) -> TCHOUTOU NANA CLAUDE | C33: 0 | D33: =VLOOKUP(A33,'[17]EPARGNE 2023'!$A$5:$BF$47,4,0) -> 0 | F33: =C33+D33-E33 -> 0 | G33: 0 | H33: =+F33+G33 -> 0
A34: AS201658 | B34: =VLOOKUP(A34,[15]LISTADHERENT!$A$5:$J$45,3,0) -> YANTCHOU GERVAIS | C34: 0 | D34: =VLOOKUP(A34,'[17]EPARGNE 2023'!$A$5:$BF$47,4,0) -> 0 | F34: =C34+D34-E34 -> 0 | G34: 0 | H34: =+F34+G34 -> 0
A35: AS201646 | B35: =VLOOKUP(A35,[15]LISTADHERENT!$A$5:$J$45,3,0) -> YEPMOU JEAN JACQUES | C35: 600000 | D35: =VLOOKUP(A35,'[17]EPARGNE 2023'!$A$5:$BF$47,4,0) -> 914734.42 | F35: =C35+D35-E35 -> 1514734.4 | G35: 96219.095 | H35: =+F35+G35 -> 1610953.5 | I35: =VLOOKUP($A35,[16]HISTODEC22!$A$6:$AQ$37,22,0) -> 0 | J35: =VLOOKUP($A35,[16]HISTODEC22!$A$6:$AU$39,45,0) -> 7000 | L35: =IF(J35=0,0,500) -> 500 | M35: =IF(J35=0,0,1000) -> 1000 | N35: =IF(J35=0,0,2500) -> 2500 | O35: =VLOOKUP($A35,[16]HISTODEC22!$A$6:$AU$39,7,0) -> 0 | P35: =VLOOKUP($A35,[16]HISTODEC22!$A$6:$AU$39,23,0) -> 0 | Q35: =VLOOKUP($A35,[16]HISTODEC22!$A$6:$AU$39,46,0) -> 0 | R35: =VLOOKUP($A35,[18]HISTODEC22!$A$6:$AU$39,26,0) -> 0 | S35: =VLOOKUP($A35,[18]HISTODEC22!$A$6:$BG$39,58,0) -> 0 | T35: =VLOOKUP($A35,[16]HISTODEC22!$A$6:$AU$39,28,0) -> 0 | U35: =VLOOKUP($A35,[16]HISTODEC22!$A$6:$AU$39,19,0) -> 1011250 | V35: =VLOOKUP($A35,[16]HISTODEC22!$A$6:$AU$39,20,0) -> BANQUE | W35: =VLOOKUP($A35,[16]HISTODEC22!$A$6:$AU$39,27,0) -> 0 | X35: =VLOOKUP($A35,[16]HISTODEC22!$A$6:$AU$39,33,0) -> 0 | Y35: =VLOOKUP($A35,[16]HISTODEC22!$A$6:$BP$39,65,0) -> 0 | AA35: =VLOOKUP($A35,[16]HISTODEC22!$A$6:$AU$39,43,0) -> 0 | AB35: =VLOOKUP($A35,[16]HISTODEC22!$A$6:$AU$39,44,0) -> 0 | AC35: =VLOOKUP($A35,[16]HISTODEC22!$A$6:$AU$39,47,0) -> 0 | AD35: =VLOOKUP(A35,[16]HISTODEC22!$A$6:$BB$36,54,0) -> 0 | AE35: =VLOOKUP($A35,[16]HISTODEC22!$A$6:$CA$36,60,0) -> 0 | AF35: =VLOOKUP($A35,[16]HISTODEC22!$A$6:$CA$36,61,0) -> 0 | AG35: =VLOOKUP($A35,[16]HISTODEC22!$A$6:$CA$36,62,0) -> 0 | AH35: =VLOOKUP($A35,[16]HISTODEC22!$A$6:$CA$36,63,0) -> 0 | AI35: =VLOOKUP($A35,[16]HISTODEC22!$A$6:$CA$36,64,0) -> 0 | AJ35: =VLOOKUP($A35,[16]HISTODEC22!$A$6:$CA$36,65,0) -> 0
A36: AS201647 | B36: =VLOOKUP(A36,[15]LISTADHERENT!$A$5:$J$45,3,0) -> YOUMBI EMMANUEL | C36: 600000 | D36: =VLOOKUP(A36,'[17]EPARGNE 2023'!$A$5:$BF$47,4,0) -> 1057774.2 | F36: =C36+D36-E36 -> 1657774.2 | G36: 105305.28 | H36: =+F36+G36 -> 1763079.5 | I36: =VLOOKUP($A36,[16]HISTODEC22!$A$6:$AQ$37,22,0) -> 0 | J36: =VLOOKUP($A36,[16]HISTODEC22!$A$6:$AU$39,45,0) -> 7000 | L36: =IF(J36=0,0,500) -> 500 | M36: =IF(J36=0,0,1000) -> 1000 | N36: =IF(J36=0,0,2500) -> 2500 | O36: =VLOOKUP($A36,[16]HISTODEC22!$A$6:$AU$39,7,0) -> 0 | P36: =VLOOKUP($A36,[16]HISTODEC22!$A$6:$AU$39,23,0) -> 0 | Q36: =VLOOKUP($A36,[16]HISTODEC22!$A$6:$AU$39,46,0) -> 0 | R36: =VLOOKUP($A36,[18]HISTODEC22!$A$6:$AU$39,26,0) -> 0 | S36: =VLOOKUP($A36,[18]HISTODEC22!$A$6:$BG$39,58,0) -> 0 | T36: =VLOOKUP($A36,[16]HISTODEC22!$A$6:$AU$39,28,0) -> 0 | U36: =VLOOKUP($A36,[16]HISTODEC22!$A$6:$AU$39,19,0) -> 0 | V36: =VLOOKUP($A36,[16]HISTODEC22!$A$6:$AU$39,20,0) -> 0 | W36: =VLOOKUP($A36,[16]HISTODEC22!$A$6:$AU$39,27,0) -> 0 | X36: =VLOOKUP($A36,[16]HISTODEC22!$A$6:$AU$39,33,0) -> 0 | Y36: =VLOOKUP($A36,[16]HISTODEC22!$A$6:$BP$39,65,0) -> 0 | AA36: =VLOOKUP($A36,[16]HISTODEC22!$A$6:$AU$39,43,0) -> 0 | AB36: =VLOOKUP($A36,[16]HISTODEC22!$A$6:$AU$39,44,0) -> 0 | AC36: =VLOOKUP($A36,[16]HISTODEC22!$A$6:$AU$39,47,0) -> 0 | AD36: =VLOOKUP(A36,[16]HISTODEC22!$A$6:$BB$36,54,0) -> 0 | AE36: =VLOOKUP($A36,[16]HISTODEC22!$A$6:$CA$36,60,0) -> 0 | AF36: =VLOOKUP($A36,[16]HISTODEC22!$A$6:$CA$36,61,0) -> 0 | AG36: =VLOOKUP($A36,[16]HISTODEC22!$A$6:$CA$36,62,0) -> 0 | AH36: =VLOOKUP($A36,[16]HISTODEC22!$A$6:$CA$36,63,0) -> 0 | AI36: =VLOOKUP($A36,[16]HISTODEC22!$A$6:$CA$36,64,0) -> 0 | AJ36: =VLOOKUP($A36,[16]HISTODEC22!$A$6:$CA$36,65,0) -> 0
A37: AS201629 | B37: =VLOOKUP(A37,[15]LISTADHERENT!$A$5:$J$45,3,0) -> NKEPSEU DIEUDONNE | C37: 600000 | D37: 2434 | F37: =C37+D37-E37 -> 602434 | G37: 38267.866 | H37: =+F37+G37 -> 640701.87
A39: TOTAL | C39: =SUM(C6:C37) -> 15600000 | D39: =SUM(D6:D37) -> 4361560.2 | E39: =SUM(E6:E37) -> 0 | F39: =SUM(F6:F37) -> 19961560 | G39: =SUM(G6:G37) -> 1268000 | H39: =SUM(H6:H37) -> 21229560 | I39: =SUM(I6:I37) -> 0 | J39: =SUM(J6:J37) -> 286000 | ... AJ39: =SUM(AJ6:AJ37) -> 0
C41: 536000 | D41: 4361500
C42: =C39-C41 -> 15064000 | D42: =D39-D41 -> 60.190811 | F42: 19359126
H43: =H39-H41 -> 21229560

Sheet MVTJANV23
A1: ASSOCIATION | B1: ASELBY | G1: K
A2: ANNEE | B2: 2023
A3: TONTINE
J4: 44943
A5: MATRICULE | B5: NOM ET PRENOM | C5: FONDES DE DEPART | D5: RECONDUCTION | E5: RETRAIT PARTIEL | F5: FONDS DEFINITIF | G5: REPARTITION INTERET | H5: CAPITAL COMPOSE | I5: SANCTION | J5: RESTE | K5: EPARGNE | L5: FONDS DE ROULEMENT | M5: FRAIS EXCEPTIONNEL | N5: COLLATION | O5: PENALITE VST ESPECES | P5: INSCRISPTION | Q5: MUTUELLE | R5: PRÊT FONDS | S5: INTERETPRET FONDS | T5: NUMERO CHEQUE | U5: REMBOURSEMENTPRET FONDS | V5: MODE VERSEMENT REMBOURSEMENT | W5: MODE VERSEMENT PRÊT | X5: NUMERO CHEQUE | Y5: PENALITE PRET FONDS | Z5: PENALITE FONDS | AA5: PENALITE ECHEC TONTINE | AB5: PENALITE RETARD TONTINE | AC5: REMBOURSEMENT TRANSPORT | AD5: CONTRIBUTION FOYER | AE5: FONDS DE ROULEMENT | AF5: FRAIS EXCEPTIONNEL | AG5: FONDS MUTUELLE | AH5: COLLATION RECEPTION | AI5: PENALITE PRET FONDS | AJ5: DEPENSE PENALITE VERSEMENT BANQUE
A6: AS201648 | B6: =VLOOKUP(A6,[15]LISTADHERENT!A$5:H$60,3,0) -> ASELBY | C6: =VLOOKUP(A6,MVTDEC22!A6:AJ36,3,0) -> 0 | D6: =MVTREPARTITION2022!U6 -> 816543.52 | F6: =MVTDEC22!F6+MVTDEC22!G6-MVTJANV23!E6+K6 -> 868412.07 | G6: =$S$40/$F$40*F6 -> 0 | H6: =F6+G6 -> 868412.07 | AE6: =VLOOKUP($A6,[18]HISTOJANV23!$A$6:$CA$36,60,0) -> 6000 | AF6: =VLOOKUP($A6,[18]HISTOJANV23!$A$6:$CA$36,61,0) -> 0 | AG6: =VLOOKUP($A6,[18]HISTOJANV23!$A$6:$CA$36,62,0) -> 0 | AH6: =VLOOKUP($A6,[18]HISTOJANV23!$A$6:$CA$36,63,0) -> 100000 | AI6: =VLOOKUP($A6,[18]HISTOJANV23!$A$6:$CA$36,64,0) -> 0 | AJ6: =VLOOKUP($A6,[18]HISTOJANV23!$A$6:$CA$36,65,0) -> 0
A7: AS201601 | B7: =VLOOKUP(A7,[15]LISTADHERENT!A$5:H$60,3,0) -> BAKOP ACHILLE | E7: =VLOOKUP($A7,[18]HISTOJANV23!$A$6:$BA$36,48,0) -> 0 | F7: =MVTDEC22!F7+MVTDEC22!G7-MVTJANV23!E7+K7 -> 609000 | G7: =$S$40/$F$40*F7 -> 0 | H7: =F7+G7 -> 609000 | I7: =VLOOKUP($A7,[18]HISTOJANV23!$A$6:$AQ$40,22,0) -> 0 | J7: =VLOOKUP($A7,[18]HISTOJANV23!$A$6:$AU$36,45,0) -> 79000 | K7: =IF(J7=0,0,J7-(L7+M7+N7))+536000 -> 609000 | L7: =IF(J7=0,0,1000) -> 1000 | M7: =IF(J7=0,0,1000) -> 1000 | N7: =IF(J7=0,0,4000) -> 4000 | O7: =VLOOKUP($A7,[18]HISTOJANV23!$A$6:$AU$36,7,0) -> 0 | P7: =VLOOKUP($A7,[18]HISTOJANV23!$A$6:$AU$36,23,0) -> 0 | Q7: =VLOOKUP($A7,[18]HISTOJANV23!$A$6:$AU$36,46,0) -> 0 | R7: =VLOOKUP($A7,[18]HISTOJANV23!$A$6:$AU$36,26,0) -> 0 | S7: =VLOOKUP($A7,[18]HISTOJANV23!$A$6:$BG$36,58,0) -> 0 | T7: =VLOOKUP($A7,[18]HISTOJANV23!$A$6:$AU$36,28,0) -> 0 | U7: =VLOOKUP($A7,[18]HISTOJANV23!$A$6:$AU$36,19,0) -> 0 | V7: =VLOOKUP($A7,[18]HISTOJANV23!$A$6:$AU$36,20,0) -> 0 | W7: =VLOOKUP($A7,[18]HISTOJANV23!$A$6:$AU$36,27,0) -> 0 | X7: =VLOOKUP($A7,[18]HISTOJANV23!$A$6:$BM$36,33,0) -> 0 | Y7: =VLOOKUP($A7,[18]HISTOJANV23!$A$6:$BM$36,65,0) -> 0 | AA7: =VLOOKUP($A7,[18]HISTOJANV23!$A$6:$AU$36,43,0) -> 0 | AB7: =VLOOKUP($A7,[18]HISTOJANV23!$A$6:$AU$36,44,0) -> 0 | AC7: =VLOOKUP($A7,[18]HISTOJANV23!$A$6:$AU$36,47,0) -> 0 | AD7: =VLOOKUP(A7,[18]HISTOJANV23!$A$6:$BB$36,54,0) -> 0 | AE7: =VLOOKUP($A7,[18]HISTOJANV23!$A$6:$CA$36,60,0) -> 0 | AF7: =VLOOKUP($A7,[18]HISTOJANV23!$A$6:$CA$36,61,0) -> 0 | AG7: =VLOOKUP($A7,[18]HISTOJANV23!$A$6:$CA$36,62,0) -> 0 | AH7: =VLOOKUP($A7,[18]HISTOJANV23!$A$6:$CA$36,63,0) -> 0 | AI7: =VLOOKUP($A7,[18]HISTOJANV23!$A$6:$CA$36,64,0) -> 0 | AJ7: =VLOOKUP($A7,[18]HISTOJANV23!$A$6:$CA$36,65,0) -> 0
A8: AS201602 | B8: =VLOOKUP(A8,[15]LISTADHERENT!A$5:H$60,3,0) -> BOUTCHOUANG WILLIAM | C8: =VLOOKUP(A8,MVTDEC22!A8:AJ39,3,0) -> 600000 | D8: =VLOOKUP($A8,[19]MVTREPARTITION2022!$A$6:$V$39,21,0) -> 7024 | E8: =VLOOKUP($A8,[18]HISTOJANV23!$A$6:$BA$36,48,0) -> 0 | F8: =MVTDEC22!F8+MVTDEC22!G8-MVTJANV23!E8+K8 -> 654583.07 | G8: =$S$40/$F$40*F8 -> 0 | H8: =F8+G8 -> 654583.07 | I8: =VLOOKUP($A8,[18]HISTOJANV23!$A$6:$AQ$40,22,0) -> 0 | J8: =VLOOKUP($A8,[18]HISTOJANV23!$A$6:$AU$36,45,0) -> 15000 | K8: =IF(J8=0,0,J8-(L8+M8+N8)) -> 9000 | L8: =IF(J8=0,0,1000) -> 1000 | M8: =IF(J8=0,0,1000) -> 1000 | N8: =IF(J8=0,0,4000) -> 4000 | O8: =VLOOKUP($A8,[18]HISTOJANV23!$A$6:$AU$36,7,0) -> 0 | P8: =VLOOKUP($A8,[18]HISTOJANV23!$A$6:$AU$36,23,0) -> 0 | Q8: =VLOOKUP($A8,[18]HISTOJANV23!$A$6:$AU$36,46,0) -> 0 | R8: =VLOOKUP($A8,[18]HISTOJANV23!$A$6:$AU$36,26,0) -> 0 | S8: =VLOOKUP($A8,[18]HISTOJANV23!$A$6:$BG$36,58,0) -> 0 | T8: =VLOOKUP($A8,[18]HISTOJANV23!$A$6:$AU$36,28,0) -> 0 | U8: =VLOOKUP($A8,[18]HISTOJANV23!$A$6:$AU$36,19,0) -> 0 | V8: =VLOOKUP($A8,[18]HISTOJANV23!$A$6:$AU$36,20,0) -> 0 | W8: =VLOOKUP($A8,[18]HISTOJANV23!$A$6:$AU$36,27,0) -> 0 | X8: =VLOOKUP($A8,[18]HISTOJANV23!$A$6:$BM$36,33,0) -> 0 | Y8: =VLOOKUP($A8,[18]HISTOJANV23!$A$6:$BM$36,65,0) -> 0 | AA8: =VLOOKUP($A8,[18]HISTOJANV23!$A$6:$AU$36,43,0) -> 0 | AB8: =VLOOKUP($A8,[18]HISTOJANV23!$A$6:$AU$36,44,0) -> 0 | AC8: =VLOOKUP($A8,[18]HISTOJANV23!$A$6:$AU$36,47,0) -> 0 | AD8: =VLOOKUP(A8,[18]HISTOJANV23!$A$6:$BB$36,54,0) -> 0 | AE8: =VLOOKUP($A8,[18]HISTOJANV23!$A$6:$CA$36,60,0) -> 0 | AF8: =VLOOKUP($A8,[18]HISTOJANV23!$A$6:$CA$36,61,0) -> 0 | AG8: =VLOOKUP($A8,[18]HISTOJANV23!$A$6:$CA$36,62,0) -> 0 | AH8: =VLOOKUP($A8,[18]HISTOJANV23!$A$6:$CA$36,63,0) -> 0 | AI8: =VLOOKUP($A8,[18]HISTOJANV23!$A$6:$CA$36,64,0) -> 0 | AJ8: =VLOOKUP($A8,[18]HISTOJANV23!$A$6:$CA$36,65,0) -> 0
A9: AS201604 | B9: =VLOOKUP(A9,[15]LISTADHERENT!A$5:H$60,3,0) -> DJOMO JEAN PAUL | C9: =VLOOKUP(A9,MVTDEC22!A9:AJ40,3,0) -> 600000 | D9: =VLOOKUP($A9,[19]MVTREPARTITION2022!$A$6:$V$39,21,0) -> 4810 | E9: =VLOOKUP($A9,[18]HISTOJANV23!$A$6:$BA$36,48,0) -> 0 | F9: =MVTDEC22!F9+MVTDEC22!G9-MVTJANV23!E9+K9 -> 672228.59 | G9: =$S$40/$F$40*F9 -> 0 | H9: =F9+G9 -> 672228.59 | I9: =VLOOKUP($A9,[18]HISTOJANV23!$A$6:$AQ$40,22,0) -> 0 | J9: =VLOOKUP($A9,[18]HISTOJANV23!$A$6:$AU$36,45,0) -> 35000 | K9: =IF(J9=0,0,J9-(L9+M9+N9)) -> 29000 | L9: =IF(J9=0,0,1000) -> 1000 | M9: =IF(J9=0,0,1000) -> 1000 | N9: =IF(J9=0,0,4000) -> 4000 | O9: =VLOOKUP($A9,[18]HISTOJANV23!$A$6:$AU$36,7,0) -> 0 | P9: =VLOOKUP($A9,[18]HISTOJANV23!$A$6:$AU$36,23,0) -> 0 | Q9: =VLOOKUP($A9,[18]HISTOJANV23!$A$6:$AU$36,46,0) -> 0 | R9: =VLOOKUP($A9,[18]HISTOJANV23!$A$6:$AU$36,26,0) -> 0 | S9: =VLOOKUP($A9,[18]HISTOJANV23!$A$6:$BG$36,58,0) -> 0 | T9: =VLOOKUP($A9,[18]HISTOJANV23!$A$6:$AU$36,28,0) -> 0 | U9: =VLOOKUP($A9,[18]HISTOJANV23!$A$6:$AU$36,19,0) -> 0 | V9: =VLOOKUP($A9,[18]HISTOJANV23!$A$6:$AU$36,20,0) -> 0 | W9: =VLOOKUP($A9,[18]HISTOJANV23!$A$6:$AU$36,27,0) -> 0 | X9: =VLOOKUP($A9,[18]HISTOJANV23!$A$6:$BM$36,33,0) -> 0 | Y9: =VLOOKUP($A9,[18]HISTOJANV23!$A$6:$BM$36,65,0) -> 0 | AA9: =VLOOKUP($A9,[18]HISTOJANV23!$A$6:$AU$36,43,0) -> 0 | AB9: =VLOOKUP($A9,[18]HISTOJANV23!$A$6:$AU$36,44,0) -> 0 | AC9: =VLOOKUP($A9,[18]HISTOJANV23!$A$6:$AU$36,47,0) -> 0 | AD9: =VLOOKUP(A9,[18]HISTOJANV23!$A$6:$BB$36,54,0) -> 140000 | AE9: =VLOOKUP($A9,[18]HISTOJANV23!$A$6:$CA$36,60,0) -> 0 | AF9: =VLOOKUP($A9,[18]HISTOJANV23!$A$6:$CA$36,61,0) -> 0 | AG9: =VLOOKUP($A9,[18]HISTOJANV23!$A$6:$CA$36,62,0) -> 0 | AH9: =VLOOKUP($A9,[18]HISTOJANV23!$A$6:$CA$36,63,0) -> 0 | AI9: =VLOOKUP($A9,[18]HISTOJANV23!$A$6:$CA$36,64,0) -> 0 | AJ9: =VLOOKUP($A9,[18]HISTOJANV23!$A$6:$CA$36,65,0) -> 0
A10: AS201654 | B10: =VLOOKUP(A10,[15]LISTADHERENT!A$5:H$60,3,0) -> DJOMOU TCHAPDA | C10: =VLOOKUP(A10,MVTDEC22!A10:AJ41,3,0) -> 600000 | D10: =VLOOKUP($A10,[19]MVTREPARTITION2022!$A$6:$V$39,21,0) -> 48710 | E10: =VLOOKUP($A10,[18]HISTOJANV23!$A$6:$BA$36,48,0) -> 0 | F10: =MVTDEC22!F10+MVTDEC22!G10-MVTJANV23!E10+K10 -> 698917.85 | G10: =$S$40/$F$40*F10 -> 0 | H10: =F10+G10 -> 698917.85 | I10: =VLOOKUP($A10,[18]HISTOJANV23!$A$6:$AQ$40,22,0) -> 0 | J10: =VLOOKUP($A10,[18]HISTOJANV23!$A$6:$AU$36,45,0) -> 15000 | K10: =IF(J10=0,0,J10-(L10+M10+N10)) -> 9000 | L10: =IF(J10=0,0,1000) -> 1000 | M10: =IF(J10=0,0,1000) -> 1000 | N10: =IF(J10=0,0,4000) -> 4000 | O10: =VLOOKUP($A10,[18]HISTOJANV23!$A$6:$AU$36,7,0) -> 0 | P10: =VLOOKUP($A10,[18]HISTOJANV23!$A$6:$AU$36,23,0) -> 0 | Q10: =VLOOKUP($A10,[18]HISTOJANV23!$A$6:$AU$36,46,0) -> 0 | R10: =VLOOKUP($A10,[18]HISTOJANV23!$A$6:$AU$36,26,0) -> 0 | S10: =VLOOKUP($A10,[18]HISTOJANV23!$A$6:$BG$36,58,0) -> 0 | T10: =VLOOKUP($A10,[18]HISTOJANV23!$A$6:$AU$36,28,0) -> 0 | U10: =VLOOKUP($A10,[18]HISTOJANV23!$A$6:$AU$36,19,0) -> 0 | V10: =VLOOKUP($A10,[18]HISTOJANV23!$A$6:$AU$36,20,0) -> 0 | W10: =VLOOKUP($A10,[18]HISTOJANV23!$A$6:$AU$36,27,0) -> 0 | X10: =VLOOKUP($A10,[18]HISTOJANV23!$A$6:$BM$36,33,0) -> 0 | Y10: =VLOOKUP($A10,[18]HISTOJANV23!$A$6:$BM$36,65,0) -> 0 | AA10: =VLOOKUP($A10,[18]HISTOJANV23!$A$6:$AU$36,43,0) -> 0 | AB10: =VLOOKUP($A10,[18]HISTOJANV23!$A$6:$AU$36,44,0) -> 0 | AC10: =VLOOKUP($A10,[18]HISTOJANV23!$A$6:$AU$36,47,0) -> 0 | AD10: =VLOOKUP(A10,[18]HISTOJANV23!$A$6:$BB$36,54,0) -> 0 | AE10: =VLOOKUP($A10,[18]HISTOJANV23!$A$6:$CA$36,60,0) -> 0 | AF10: =VLOOKUP($A10,[18]HISTOJANV23!$A$6:$CA$36,61,0) -> 0 | AG10: =VLOOKUP($A10,[18]HISTOJANV23!$A$6:$CA$36,62,0) -> 0 | AH10: =VLOOKUP($A10,[18]HISTOJANV23!$A$6:$CA$36,63,0) -> 0 | AI10: =VLOOKUP($A10,[18]HISTOJANV23!$A$6:$CA$36,64,0) -> 0 | AJ10: =VLOOKUP($A10,[18]HISTOJANV23!$A$6:$CA$36,65,0) -> 0
A11: AS201605 | B11: =VLOOKUP(A11,[15]LISTADHERENT!A$5:H$60,3,0) -> DJOUKWE NANGUEN GUY BLAISE | C11: =VLOOKUP(A11,MVTDEC22!A11:AJ42,3,0) -> 600000 | D11: =VLOOKUP($A11,[19]MVTREPARTITION2022!$A$6:$V$39,21,0) -> 4750 | E11: =VLOOKUP($A11,[18]HISTOJANV23!$A$6:$BA$36,48,0) -> 0 | F11: =MVTDEC22!F11+MVTDEC22!G11-MVTJANV23!E11+K11 -> 652165.07 | G11: =$S$40/$F$40*F11 -> 0 | H11: =F11+G11 -> 652165.07 | I11: =VLOOKUP($A11,[18]HISTOJANV23!$A$6:$AQ$40,22,0) -> 0 | J11: =VLOOKUP($A11,[18]HISTOJANV23!$A$6:$AU$36,45,0) -> 15000 | K11: =IF(J11=0,0,J11-(L11+M11+N11)) -> 9000 | L11: =IF(J11=0,0,1000) -> 1000 | M11: =IF(J11=0,0,1000) -> 1000 | N11: =IF(J11=0,0,4000) -> 4000 | O11: =VLOOKUP($A11,[18]HISTOJANV23!$A$6:$AU$36,7,0) -> 0 | P11: =VLOOKUP($A11,[18]HISTOJANV23!$A$6:$AU$36,23,0) -> 0 | Q11: =VLOOKUP($A11,[18]HISTOJANV23!$A$6:$AU$36,46,0) -> 0 | R11: =VLOOKUP($A11,[18]HISTOJANV23!$A$6:$AU$36,26,0) -> 0 | S11: =VLOOKUP($A11,[18]HISTOJANV23!$A$6:$BG$36,58,0) -> 0 | T11: =VLOOKUP($A11,[18]HISTOJANV23!$A$6:$AU$36,28,0) -> 0 | U11: =VLOOKUP($A11,[18]HISTOJANV23!$A$6:$AU$36,19,0) -> 0 | V11: =VLOOKUP($A11,[18]HISTOJANV23!$A$6:$AU$36,20,0) -> 0 | W11: =VLOOKUP($A11,[18]HISTOJANV23!$A$6:$AU$36,27,0) -> 0 | X11: =VLOOKUP($A11,[18]HISTOJANV23!$A$6:$BM$36,33,0) -> 0 | Y11: =VLOOKUP($A11,[18]HISTOJANV23!$A$6:$BM$36,65,0) -> 0 | AA11: =VLOOKUP($A11,[18]HISTOJANV23!$A$6:$AU$36,43,0) -> 0 | AB11: =VLOOKUP($A11,[18]HISTOJANV23!$A$6:$AU$36,44,0) -> 0 | AC11: =VLOOKUP($A11,[18]HISTOJANV23!$A$6:$AU$36,47,0) -> 0 | AD11: =VLOOKUP(A11,[18]HISTOJANV23!$A$6:$BB$36,54,0) -> 0 | AE11: =VLOOKUP($A11,[18]HISTOJANV23!$A$6:$CA$36,60,0) -> 0 | AF11: =VLOOKUP($A11,[18]HISTOJANV23!$A$6:$CA$36,61,0) -> 0 | AG11: =VLOOKUP($A11,[18]HISTOJANV23!$A$6:$CA$36,62,0) -> 0 | AH11: =VLOOKUP($A11,[18]HISTOJANV23!$A$6:$CA$36,63,0) -> 0 | AI11: =VLOOKUP($A11,[18]HISTOJANV23!$A$6:$CA$36,64,0) -> 0 | AJ11: =VLOOKUP($A11,[18]HISTOJANV23!$A$6:$CA$36,65,0) -> 0
A12: AS201608 | B12: =VLOOKUP(A12,[15]LISTADHERENT!A$5:H$60,3,0) -> DJUOMBESSY ANTOINE | C12: =VLOOKUP(A12,MVTDEC22!A12:AJ43,3,0) -> 600000 | D12: =VLOOKUP($A12,[19]MVTREPARTITION2022!$A$6:$V$39,21,0) -> 10719 | E12: =VLOOKUP($A12,[18]HISTOJANV23!$A$6:$BA$36,48,0) -> 0 | F12: =MVTDEC22!F12+MVTDEC22!G12-MVTJANV23!E12+K12 -> 663512.99 | G12: =$S$40/$F$40*F12 -> 0 | H12: =F12+G12 -> 663512.99 | I12: =VLOOKUP($A12,[18]HISTOJANV23!$A$6:$AQ$40,22,0) -> 0 | J12: =VLOOKUP($A12,[18]HISTOJANV23!$A$6:$AU$36,45,0) -> 20000 | K12: =IF(J12=0,0,J12-(L12+M12+N12)) -> 14000 | L12: =IF(J12=0,0,1000) -> 1000 | M12: =IF(J12=0,0,1000) -> 1000 | N12: =IF(J12=0,0,4000) -> 4000 | O12: =VLOOKUP($A12,[18]HISTOJANV23!$A$6:$AU$36,7,0) -> 0 | P12: =VLOOKUP($A12,[18]HISTOJANV23!$A$6:$AU$36,23,0) -> 0 | Q12: =VLOOKUP($A12,[18]HISTOJANV23!$A$6:$AU$36,46,0) -> 0 | R12: =VLOOKUP($A12,[18]HISTOJANV23!$A$6:$AU$36,26,0) -> 0 | S12: =VLOOKUP($A12,[18]HISTOJANV23!$A$6:$BG$36,58,0) -> 0 | T12: =VLOOKUP($A12,[18]HISTOJANV23!$A$6:$AU$36,28,0) -> 0 | U12: =VLOOKUP($A12,[18]HISTOJANV23!$A$6:$AU$36,19,0) -> 0 | V12: =VLOOKUP($A12,[18]HISTOJANV23!$A$6:$AU$36,20,0) -> 0 | W12: =VLOOKUP($A12,[18]HISTOJANV23!$A$6:$AU$36,27,0) -> 0 | X12: =VLOOKUP($A12,[18]HISTOJANV23!$A$6:$BM$36,33,0) -> 0 | Y12: =VLOOKUP($A12,[18]HISTOJANV23!$A$6:$BM$36,65,0) -> 0 | AA12: =VLOOKUP($A12,[18]HISTOJANV23!$A$6:$AU$36,43,0) -> 0 | AB12: =VLOOKUP($A12,[18]HISTOJANV23!$A$6:$AU$36,44,0) -> 0 | AC12: =VLOOKUP($A12,[18]HISTOJANV23!$A$6:$AU$36,47,0) -> 0 | AD12: =VLOOKUP(A12,[18]HISTOJANV23!$A$6:$BB$36,54,0) -> 0 | AE12: =VLOOKUP($A12,[18]HISTOJANV23!$A$6:$CA$36,60,0) -> 0 | AF12: =VLOOKUP($A12,[18]HISTOJANV23!$A$6:$CA$36,61,0) -> 0 | AG12: =VLOOKUP($A12,[18]HISTOJANV23!$A$6:$CA$36,62,0) -> 0 | AH12: =VLOOKUP($A12,[18]HISTOJANV23!$A$6:$CA$36,63,0) -> 0 | AI12: =VLOOKUP($A12,[18]HISTOJANV23!$A$6:$CA$36,64,0) -> 0 | AJ12: =VLOOKUP($A12,[18]HISTOJANV23!$A$6:$CA$36,65,0) -> 0
A13: AS201651 | B13: =VLOOKUP(A13,[15]LISTADHERENT!A$5:H$60,3,0) -> DOMOU FABIEN | C13: =VLOOKUP(A13,MVTDEC22!A13:AJ44,3,0) -> 600000 | D13: =VLOOKUP($A13,[19]MVTREPARTITION2022!$A$6:$V$39,21,0) -> 584 | E13: =VLOOKUP($A13,[18]HISTOJANV23!$A$6:$BA$36,48,0) -> 0 | F13: =MVTDEC22!F13+MVTDEC22!G13-MVTJANV23!E13+K13 -> 647734.4 | G13: =$S$40/$F$40*F13 -> 0 | H13: =F13+G13 -> 647734.4 | I13: =VLOOKUP($A13,[18]HISTOJANV23!$A$6:$AQ$40,22,0) -> 0 | J13: =VLOOKUP($A13,[18]HISTOJANV23!$A$6:$AU$36,45,0) -> 15000 | K13: =IF(J13=0,0,J13-(L13+M13+N13)) -> 9000 | L13: =IF(J13=0,0,1000) -> 1000 | M13: =IF(J13=0,0,1000) -> 1000 | N13: =IF(J13=0,0,4000) -> 4000 | O13: =VLOOKUP($A13,[18]HISTOJANV23!$A$6:$AU$36,7,0) -> 0 | P13: =VLOOKUP($A13,[18]HISTOJANV23!$A$6:$AU$36,23,0) -> 0 | Q13: =VLOOKUP($A13,[18]HISTOJANV23!$A$6:$AU$36,46,0) -> 0 | R13: =VLOOKUP($A13,[18]HISTOJANV23!$A$6:$AU$36,26,0) -> 0 | S13: =VLOOKUP($A13,[18]HISTOJANV23!$A$6:$BG$36,58,0) -> 0 | T13: =VLOOKUP($A13,[18]HISTOJANV23!$A$6:$AU$36,28,0) -> 0 | U13: =VLOOKUP($A13,[18]HISTOJANV23!$A$6:$AU$36,19,0) -> 0 | V13: =VLOOKUP($A13,[18]HISTOJANV23!$A$6:$AU$36,20,0) -> 0 | W13: =VLOOKUP($A13,[18]HISTOJANV23!$A$6:$AU$36,27,0) -> 0 | X13: =VLOOKUP($A13,[18]HISTOJANV23!$A$6:$BM$36,33,0) -> 0 | Y13: =VLOOKUP($A13,[18]HISTOJANV23!$A$6:$BM$36,65,0) -> 0 | AA13: =VLOOKUP($A13,[18]HISTOJANV23!$A$6:$AU$36,43,0) -> 0 | AB13: =VLOOKUP($A13,[18]HISTOJANV23!$A$6:$AU$36,44,0) -> 0 | AC13: =VLOOKUP($A13,[18]HISTOJANV23!$A$6:$AU$36,47,0) -> 0 | AD13: =VLOOKUP(A13,[18]HISTOJANV23!$A$6:$BB$36,54,0) -> 0 | AE13: =VLOOKUP($A13,[18]HISTOJANV23!$A$6:$CA$36,60,0) -> 0 | AF13: =VLOOKUP($A13,[18]HISTOJANV23!$A$6:$CA$36,61,0) -> 0 | AG13: =VLOOKUP($A13,[18]HISTOJANV23!$A$6:$CA$36,62,0) -> 0 | AH13: =VLOOKUP($A13,[18]HISTOJANV23!$A$6:$CA$36,63,0) -> 0 | AI13: =VLOOKUP($A13,[18]HISTOJANV23!$A$6:$CA$36,64,0) -> 0 | AJ13: =VLOOKUP($A13,[18]HISTOJANV23!$A$6:$CA$36,65,0) -> 0
A14: AS201609 | B14: =VLOOKUP(A14,[15]LISTADHERENT!A$5:H$60,3,0) -> DONHOU DAVID | C14: =VLOOKUP(A14,MVTDEC22!A14:AJ45,3,0) -> 600000 | D14: =VLOOKUP($A14,[19]MVTREPARTITION2022!$A$6:$V$39,21,0) -> 458343 | E14: =VLOOKUP($A14,[18]HISTOJANV23!$A$6:$BA$36,48,0) -> 0 | F14: =MVTDEC22!F14+MVTDEC22!G14-MVTJANV23!E14+K14 -> 1134571.3 | G14: =$S$40/$F$40*F14 -> 0 | H14: =F14+G14 -> 1134571.3 | I14: =VLOOKUP($A14,[18]HISTOJANV23!$A$6:$AQ$40,22,0) -> 0 | J14: =VLOOKUP($A14,[18]HISTOJANV23!$A$6:$AU$36,45,0) -> 15000 | K14: =IF(J14=0,0,J14-(L14+M14+N14)) -> 9000 | L14: =IF(J14=0,0,1000) -> 1000 | M14: =IF(J14=0,0,1000) -> 1000 | N14: =IF(J14=0,0,4000) -> 4000 | O14: =VLOOKUP($A14,[18]HISTOJANV23!$A$6:$AU$36,7,0) -> 0 | P14: =VLOOKUP($A14,[18]HISTOJANV23!$A$6:$AU$36,23,0) -> 0 | Q14: =VLOOKUP($A14,[18]HISTOJANV23!$A$6:$AU$36,46,0) -> 0 | R14: =VLOOKUP($A14,[18]HISTOJANV23!$A$6:$AU$36,26,0) -> 0 | S14: =VLOOKUP($A14,[18]HISTOJANV23!$A$6:$BG$36,58,0) -> 0 | T14: =VLOOKUP($A14,[18]HISTOJANV23!$A$6:$AU$36,28,0) -> 0 | U14: =VLOOKUP($A14,[18]HISTOJANV23!$A$6:$AU$36,19,0) -> 0 | V14: =VLOOKUP($A14,[18]HISTOJANV23!$A$6:$AU$36,20,0) -> 0 | W14: =VLOOKUP($A14,[18]HISTOJANV23!$A$6:$AU$36,27,0) -> 0 | X14: =VLOOKUP($A14,[18]HISTOJANV23!$A$6:$BM$36,33,0) -> 0 | Y14: =VLOOKUP($A14,[18]HISTOJANV23!$A$6:$BM$36,65,0) -> 0 | AA14: =VLOOKUP($A14,[18]HISTOJANV23!$A$6:$AU$36,43,0) -> 0 | AB14: =VLOOKUP($A14,[18]HISTOJANV23!$A$6:$AU$36,44,0) -> 0 | AC14: =VLOOKUP($A14,[18]HISTOJANV23!$A$6:$AU$36,47,0) -> 0 | AD14: =VLOOKUP(A14,[18]HISTOJANV23!$A$6:$BB$36,54,0) -> 0 | AE14: =VLOOKUP($A14,[18]HISTOJANV23!$A$6:$CA$36,60,0) -> 0 | AF14: =VLOOKUP($A14,[18]HISTOJANV23!$A$6:$CA$36,61,0) -> 0 | AG14: =VLOOKUP($A14,[18]HISTOJANV23!$A$6:$CA$36,62,0) -> 0 | AH14: =VLOOKUP($A14,[18]HISTOJANV23!$A$6:$CA$36,63,0) -> 0 | AI14: =VLOOKUP($A14,[18]HISTOJANV23!$A$6:$CA$36,64,0) -> 0 | AJ14: =VLOOKUP($A14,[18]HISTOJANV23!$A$6:$CA$36,65,0) -> 0
A15: AS201611 | B15: =VLOOKUP(A15,[15]LISTADHERENT!A$5:H$60,3,0) -> HENGUE PAUL OMER | C15: =VLOOKUP(A15,MVTDEC22!A15:AJ46,3,0) -> 600000 | D15: =VLOOKUP($A15,[19]MVTREPARTITION2022!$A$6:$V$39,21,0) -> 51112 | E15: =VLOOKUP($A15,[18]HISTOJANV23!$A$6:$BA$36,48,0) -> 0 | F15: =MVTDEC22!F15+MVTDEC22!G15-MVTJANV23!E15+K15 -> 701472.01 | G15: =$S$40/$F$40*F15 -> 0 | H15: =F15+G15 -> 701472.01 | I15: =VLOOKUP($A15,[18]HISTOJANV23!$A$6:$AQ$40,22,0) -> 0 | J15: =VLOOKUP($A15,[18]HISTOJANV23!$A$6:$AU$36,45,0) -> 15000 | K15: =IF(J15=0,0,J15-(L15+M15+N15)) -> 9000 | L15: =IF(J15=0,0,1000) -> 1000 | M15: =IF(J15=0,0,1000) -> 1000 | N15: =IF(J15=0,0,4000) -> 4000 | O15: =VLOOKUP($A15,[18]HISTOJANV23!$A$6:$AU$36,7,0) -> 0 | P15: =VLOOKUP($A15,[18]HISTOJANV23!$A$6:$AU$36,23,0) -> 0 | Q15: =VLOOKUP($A15,[18]HISTOJANV23!$A$6:$AU$36,46,0) -> 0 | R15: =VLOOKUP($A15,[18]HISTOJANV23!$A$6:$AU$36,26,0) -> 0 | S15: =VLOOKUP($A15,[18]HISTOJANV23!$A$6:$BG$36,58,0) -> 0 | T15: =VLOOKUP($A15,[18]HISTOJANV23!$A$6:$AU$36,28,0) -> 0 | U15: =VLOOKUP($A15,[18]HISTOJANV23!$A$6:$AU$36,19,0) -> 0 | V15: =VLOOKUP($A15,[18]HISTOJANV23!$A$6:$AU$36,20,0) -> 0 | W15: =VLOOKUP($A15,[18]HISTOJANV23!$A$6:$AU$36,27,0) -> 0 | X15: =VLOOKUP($A15,[18]HISTOJANV23!$A$6:$BM$36,33,0) -> 0 | Y15: =VLOOKUP($A15,[18]HISTOJANV23!$A$6:$BM$36,65,0) -> 0 | AA15: =VLOOKUP($A15,[18]HISTOJANV23!$A$6:$AU$36,43,0) -> 0 | AB15: =VLOOKUP($A15,[18]HISTOJANV23!$A$6:$AU$36,44,0) -> 0 | AC15: =VLOOKUP($A15,[18]HISTOJANV23!$A$6:$AU$36,47,0) -> 0 | AD15: =VLOOKUP(A15,[18]HISTOJANV23!$A$6:$BB$36,54,0) -> 0 | AE15: =VLOOKUP($A15,[18]HISTOJANV23!$A$6:$CA$36,60,0) -> 0 | AF15: =VLOOKUP($A15,[18]HISTOJANV23!$A$6:$CA$36,61,0) -> 0 | AG15: =VLOOKUP($A15,[18]HISTOJANV23!$A$6:$CA$36,62,0) -> 0 | AH15: =VLOOKUP($A15,[18]HISTOJANV23!$A$6:$CA$36,63,0) -> 0 | AI15: =VLOOKUP($A15,[18]HISTOJANV23!$A$6:$CA$36,64,0) -> 0 | AJ15: =VLOOKUP($A15,[18]HISTOJANV23!$A$6:$CA$36,65,0) -> 0
A16: AS201613 | B16: =VLOOKUP(A16,[15]LISTADHERENT!A$5:H$60,3,0) -> HOTCHO BENJAMIN | C16: =VLOOKUP(A16,MVTDEC22!A16:AJ47,3,0) -> 600000 | D16: =VLOOKUP($A16,[19]MVTREPARTITION2022!$A$6:$V$39,21,0) -> 16230 | E16: =VLOOKUP($A16,[18]HISTOJANV23!$A$6:$BA$36,48,0) -> 0 | F16: =MVTDEC22!F16+MVTDEC22!G16-MVTJANV23!E16+K16 -> 699373.76 | G16: =$S$40/$F$40*F16 -> 0 | H16: =F16+G16 -> 699373.76 | I16: =VLOOKUP($A16,[18]HISTOJANV23!$A$6:$AQ$40,22,0) -> 0 | J16: =VLOOKUP($A16,[18]HISTOJANV23!$A$6:$AU$36,45,0) -> 50000 | K16: =IF(J16=0,0,J16-(L16+M16+N16)) -> 44000 | L16: =IF(J16=0,0,1000) -> 1000 | M16: =IF(J16=0,0,1000) -> 1000 | N16: =IF(J16=0,0,4000) -> 4000 | O16: =VLOOKUP($A16,[18]HISTOJANV23!$A$6:$AU$36,7,0) -> 0 | P16: =VLOOKUP($A16,[18]HISTOJANV23!$A$6:$AU$36,23,0) -> 0 | Q16: =VLOOKUP($A16,[18]HISTOJANV23!$A$6:$AU$36,46,0) -> 0 | R16: =VLOOKUP($A16,[18]HISTOJANV23!$A$6:$AU$36,26,0) -> 0 | S16: =VLOOKUP($A16,[18]HISTOJANV23!$A$6:$BG$36,58,0) -> 0 | T16: =VLOOKUP($A16,[18]HISTOJANV23!$A$6:$AU$36,28,0) -> 0 | U16: =VLOOKUP($A16,[18]HISTOJANV23!$A$6:$AU$36,19,0) -> 0 | V16: =VLOOKUP($A16,[18]HISTOJANV23!$A$6:$AU$36,20,0) -> 0 | W16: =VLOOKUP($A16,[18]HISTOJANV23!$A$6:$AU$36,27,0) -> 0 | X16: =VLOOKUP($A16,[18]HISTOJANV23!$A$6:$BM$36,33,0) -> 0 | Y16: =VLOOKUP($A16,[18]HISTOJANV23!$A$6:$BM$36,65,0) -> 0 | AA16: =VLOOKUP($A16,[18]HISTOJANV23!$A$6:$AU$36,43,0) -> 0 | AB16: =VLOOKUP($A16,[18]HISTOJANV23!$A$6:$AU$36,44,0) -> 0 | AC16: =VLOOKUP($A16,[18]HISTOJANV23!$A$6:$AU$36,47,0) -> 0 | AD16: =VLOOKUP(A16,[18]HISTOJANV23!$A$6:$BB$36,54,0) -> 0 | AE16: =VLOOKUP($A16,[18]HISTOJANV23!$A$6:$CA$36,60,0) -> 0 | AF16: =VLOOKUP($A16,[18]HISTOJANV23!$A$6:$CA$36,61,0) -> 0 | AG16: =VLOOKUP($A16,[18]HISTOJANV23!$A$6:$CA$36,62,0) -> 0 | AH16: =VLOOKUP($A16,[18]HISTOJANV23!$A$6:$CA$36,63,0) -> 0 | AI16: =VLOOKUP($A16,[18]HISTOJANV23!$A$6:$CA$36,64,0) -> 0 | AJ16: =VLOOKUP($A16,[18]HISTOJANV23!$A$6:$CA$36,65,0) -> 0
A17: AS201617 | B17: =VLOOKUP(A17,[15]LISTADHERENT!A$5:H$60,3,0) -> KOUAMOU MOISE | C17: =VLOOKUP(A17,MVTDEC22!A17:AJ48,3,0) -> 600000 | D17: =VLOOKUP($A17,[19]MVTREPARTITION2022!$A$6:$V$39,21,0) -> 53293 | E17: =VLOOKUP($A17,[18]HISTOJANV23!$A$6:$BA$36,48,0) -> 0 | F17: =MVTDEC22!F17+MVTDEC22!G17-MVTJANV23!E17+K17 -> 703791.36 | G17: =$S$40/$F$40*F17 -> 0 | H17: =F17+G17 -> 703791.36 | I17: =VLOOKUP($A17,[18]HISTOJANV23!$A$6:$AQ$40,22,0) -> 0 | J17: =VLOOKUP($A17,[18]HISTOJANV23!$A$6:$AU$36,45,0) -> 15000 | K17: =IF(J17=0,0,J17-(L17+M17+N17)) -> 9000 | L17: =IF(J17=0,0,1000) -> 1000 | M17: =IF(J17=0,0,1000) -> 1000 | N17: =IF(J17=0,0,4000) -> 4000 | O17: =VLOOKUP($A17,[18]HISTOJANV23!$A$6:$AU$36,7,0) -> 0 | P17: =VLOOKUP($A17,[18]HISTOJANV23!$A$6:$AU$36,23,0) -> 0 | Q17: =VLOOKUP($A17,[18]HISTOJANV23!$A$6:$AU$36,46,0) -> 0 | R17: =VLOOKUP($A17,[18]HISTOJANV23!$A$6:$AU$36,26,0) -> 0 | S17: =VLOOKUP($A17,[18]HISTOJANV23!$A$6:$BG$36,58,0) -> 0 | T17: =VLOOKUP($A17,[18]HISTOJANV23!$A$6:$AU$36,28,0) -> 0 | U17: =VLOOKUP($A17,[18]HISTOJANV23!$A$6:$AU$36,19,0) -> 0 | V17: =VLOOKUP($A17,[18]HISTOJANV23!$A$6:$AU$36,20,0) -> 0 | W17: =VLOOKUP($A17,[18]HISTOJANV23!$A$6:$AU$36,27,0) -> 0 | X17: =VLOOKUP($A17,[18]HISTOJANV23!$A$6:$BM$36,33,0) -> 0 | Y17: =VLOOKUP($A17,[18]HISTOJANV23!$A$6:$BM$36,65,0) -> 0 | AA17: =VLOOKUP($A17,[18]HISTOJANV23!$A$6:$AU$36,43,0) -> 0 | AB17: =VLOOKUP($A17,[18]HISTOJANV23!$A$6:$AU$36,44,0) -> 0 | AC17: =VLOOKUP($A17,[18]HISTOJANV23!$A$6:$AU$36,47,0) -> 0 | AD17: =VLOOKUP(A17,[18]HISTOJANV23!$A$6:$BB$36,54,0) -> 0 | AE17: =VLOOKUP($A17,[18]HISTOJANV23!$A$6:$CA$36,60,0) -> 0 | AF17: =VLOOKUP($A17,[18]HISTOJANV23!$A$6:$CA$36,61,0) -> 0 | AG17: =VLOOKUP($A17,[18]HISTOJANV23!$A$6:$CA$36,62,0) -> 0 | AH17: =VLOOKUP($A17,[18]HISTOJANV23!$A$6:$CA$36,63,0) -> 0 | AI17: =VLOOKUP($A17,[18]HISTOJANV23!$A$6:$CA$36,64,0) -> 0 | AJ17: =VLOOKUP($A17,[18]HISTOJANV23!$A$6:$CA$36,65,0) -> 0
A18: AS201619 | B18: =VLOOKUP(A18,[15]LISTADHERENT!A$5:H$60,3,0) -> KOUATCHO MESSACK | C18: =VLOOKUP(A18,MVTDEC22!A18:AJ49,3,0) -> 600000 | D18: =VLOOKUP($A18,[19]MVTREPARTITION2022!$A$6:$V$39,21,0) -> 6459 | E18: =VLOOKUP($A18,[18]HISTOJANV23!$A$6:$BA$36,48,0) -> 0 | F18: =MVTDEC22!F18+MVTDEC22!G18-MVTJANV23!E18+K18 -> 653982.59 | G18: =$S$40/$F$40*F18 -> 0 | H18: =F18+G18 -> 653982.59 | I18: =VLOOKUP($A18,[18]HISTOJANV23!$A$6:$AQ$40,22,0) -> 0 | J18: =VLOOKUP($A18,[18]HISTOJANV23!$A$6:$AU$36,45,0) -> 15000 | K18: =IF(J18=0,0,J18-(L18+M18+N18)) -> 9000 | L18: =IF(J18=0,0,1000) -> 1000 | M18: =IF(J18=0,0,1000) -> 1000 | N18: =IF(J18=0,0,4000) -> 4000 | O18: =VLOOKUP($A18,[18]HISTOJANV23!$A$6:$AU$36,7,0) -> 0 | P18: =VLOOKUP($A18,[18]HISTOJANV23!$A$6:$AU$36,23,0) -> 0 | Q18: =VLOOKUP($A18,[18]HISTOJANV23!$A$6:$AU$36,46,0) -> 0 | R18: =VLOOKUP($A18,[18]HISTOJANV23!$A$6:$AU$36,26,0) -> 0 | S18: =VLOOKUP($A18,[18]HISTOJANV23!$A$6:$BG$36,58,0) -> 0 | T18: =VLOOKUP($A18,[18]HISTOJANV23!$A$6:$AU$36,28,0) -> 0 | U18: =VLOOKUP($A18,[18]HISTOJANV23!$A$6:$AU$36,19,0) -> 0 | V18: =VLOOKUP($A18,[18]HISTOJANV23!$A$6:$AU$36,20,0) -> 0 | W18: =VLOOKUP($A18,[18]HISTOJANV23!$A$6:$AU$36,27,0) -> 0 | X18: =VLOOKUP($A18,[18]HISTOJANV23!$A$6:$BM$36,33,0) -> 0 | Y18: =VLOOKUP($A18,[18]HISTOJANV23!$A$6:$BM$36,65,0) -> 0 | AA18: =VLOOKUP($A18,[18]HISTOJANV23!$A$6:$AU$36,43,0) -> 0 | AB18: =VLOOKUP($A18,[18]HISTOJANV23!$A$6:$AU$36,44,0) -> 0 | AC18: =VLOOKUP($A18,[18]HISTOJANV23!$A$6:$AU$36,47,0) -> 0 | AD18: =VLOOKUP(A18,[18]HISTOJANV23!$A$6:$BB$36,54,0) -> 70000 | AE18: =VLOOKUP($A18,[18]HISTOJANV23!$A$6:$CA$36,60,0) -> 0 | AF18: =VLOOKUP($A18,[18]HISTOJANV23!$A$6:$CA$36,61,0) -> 0 | AG18: =VLOOKUP($A18,[18]HISTOJANV23!$A$6:$CA$36,62,0) -> 0 | AH18: =VLOOKUP($A18,[18]HISTOJANV23!$A$6:$CA$36,63,0) -> 0 | AI18: =VLOOKUP($A18,[18]HISTOJANV23!$A$6:$CA$36,64,0) -> 0 | AJ18: =VLOOKUP($A18,[18]HISTOJANV23!$A$6:$CA$36,65,0) -> 0
A19: AS201620 | B19: =VLOOKUP(A19,[15]LISTADHERENT!A$5:H$60,3,0) -> LOWE JEAN | C19: =VLOOKUP(A19,MVTDEC22!A19:AJ50,3,0) -> 600000 | D19: =VLOOKUP($A19,[19]MVTREPARTITION2022!$A$6:$V$39,21,0) -> 746 | E19: =VLOOKUP($A19,[18]HISTOJANV23!$A$6:$BA$36,48,0) -> 0 | F19: =MVTDEC22!F19+MVTDEC22!G19-MVTJANV23!E19+K19 -> 647906.83 | G19: =$S$40/$F$40*F19 -> 0 | H19: =F19+G19 -> 647906.83 | I19: =VLOOKUP($A19,[18]HISTOJANV23!$A$6:$AQ$40,22,0) -> 0 | J19: =VLOOKUP($A19,[18]HISTOJANV23!$A$6:$AU$36,45,0) -> 15000 | K19: =IF(J19=0,0,J19-(L19+M19+N19)) -> 9000 | L19: =IF(J19=0,0,1000) -> 1000 | M19: =IF(J19=0,0,1000) -> 1000 | N19: =IF(J19=0,0,4000) -> 4000 | O19: =VLOOKUP($A19,[18]HISTOJANV23!$A$6:$AU$36,7,0) -> 0 | P19: =VLOOKUP($A19,[18]HISTOJANV23!$A$6:$AU$36,23,0) -> 0 | Q19: =VLOOKUP($A19,[18]HISTOJANV23!$A$6:$AU$36,46,0) -> 0 | R19: =VLOOKUP($A19,[18]HISTOJANV23!$A$6:$AU$36,26,0) -> 0 | S19: =VLOOKUP($A19,[18]HISTOJANV23!$A$6:$BG$36,58,0) -> 0 | T19: =VLOOKUP($A19,[18]HISTOJANV23!$A$6:$AU$36,28,0) -> 0 | U19: =VLOOKUP($A19,[18]HISTOJANV23!$A$6:$AU$36,19,0) -> 0 | V19: =VLOOKUP($A19,[18]HISTOJANV23!$A$6:$AU$36,20,0) -> 0 | W19: =VLOOKUP($A19,[18]HISTOJANV23!$A$6:$AU$36,27,0) -> 0 | X19: =VLOOKUP($A19,[18]HISTOJANV23!$A$6:$BM$36,33,0) -> 0 | Y19: =VLOOKUP($A19,[18]HISTOJANV23!$A$6:$BM$36,65,0) -> 0 | AA19: =VLOOKUP($A19,[18]HISTOJANV23!$A$6:$AU$36,43,0) -> 0 | AB19: =VLOOKUP($A19,[18]HISTOJANV23!$A$6:$AU$36,44,0) -> 0 | AC19: =VLOOKUP($A19,[18]HISTOJANV23!$A$6:$AU$36,47,0) -> 0 | AD19: =VLOOKUP(A19,[18]HISTOJANV23!$A$6:$BB$36,54,0) -> 0 | AE19: =VLOOKUP($A19,[18]HISTOJANV23!$A$6:$CA$36,60,0) -> 0 | AF19: =VLOOKUP($A19,[18]HISTOJANV23!$A$6:$CA$36,61,0) -> 0 | AG19: =VLOOKUP($A19,[18]HISTOJANV23!$A$6:$CA$36,62,0) -> 0 | AH19: =VLOOKUP($A19,[18]HISTOJANV23!$A$6:$CA$36,63,0) -> 0 | AI19: =VLOOKUP($A19,[18]HISTOJANV23!$A$6:$CA$36,64,0) -> 0 | AJ19: =VLOOKUP($A19,[18]HISTOJANV23!$A$6:$CA$36,65,0) -> 0
... A26: AS201628 | B26: =VLOOKUP(A26,[15]LISTADHERENT!A$5:H$60,3,0) -> NKAMGANG JUSTIN DEJOLIE | C26: =VLOOKUP(A26,MVTDEC22!A26:AJ57,3,0) -> 600000 | D26: =VLOOKUP($A26,[19]MVTREPARTITION2022!$A$6:$V$39,21,0) -> 575 | E26: =VLOOKUP($A26,[18]HISTOJANV23!$A$6:$BA$36,48,0) -> 0 | F26: =MVTDEC22!F26+MVTDEC22!G26-MVTJANV23!E26+K26 -> 647725.08 | G26: =$S$40/$F$40*F26 -> 0 | H26: =F26+G26 -> 647725.08 | I26: =VLOOKUP($A26,[18]HISTOJANV23!$A$6:$AQ$40,22,0) -> 0 | J26: =VLOOKUP($A26,[18]HISTOJANV23!$A$6:$AU$36,45,0) -> 15000 | K26: =IF(J26=0,0,J26-(L26+M26+N26)) -> 9000 | L26: =IF(J26=0,0,1000) -> 1000 | M26: =IF(J26=0,0,1000) -> 1000 | N26: =IF(J26=0,0,4000) -> 4000 | O26: =VLOOKUP($A26,[18]HISTOJANV23!$A$6:$AU$36,7,0) -> 0 | P26: =VLOOKUP($A26,[18]HISTOJANV23!$A$6:$AU$36,23,0) -> 0 | Q26: =VLOOKUP($A26,[18]HISTOJANV23!$A$6:$AU$36,46,0) -> 0 | R26: =VLOOKUP($A26,[18]HISTOJANV23!$A$6:$AU$36,26,0) -> 0 | S26: =VLOOKUP($A26,[18]HISTOJANV23!$A$6:$BG$36,58,0) -> 0 | T26: =VLOOKUP($A26,[18]HISTOJANV23!$A$6:$AU$36,28,0) -> 0 | U26: =VLOOKUP($A26,[18]HISTOJANV23!$A$6:$AU$36,19,0) -> 0 | V26: =VLOOKUP($A26,[18]HISTOJANV23!$A$6:$AU$36,20,0) -> 0 | W26: =VLOOKUP($A26,[18]HISTOJANV23!$A$6:$AU$36,27,0) -> 0 | X26: =VLOOKUP($A26,[18]HISTOJANV23!$A$6:$BM$36,33,0) -> 0 | Y26: =VLOOKUP($A26,[18]HISTOJANV23!$A$6:$BM$36,65,0) -> 0 | AA26: =VLOOKUP($A26,[18]HISTOJANV23!$A$6:$AU$36,43,0) -> 0 | AB26: =VLOOKUP($A26,[18]HISTOJANV23!$A$6:$AU$36,44,0) -> 0 | AC26: =VLOOKUP($A26,[18]HISTOJANV23!$A$6:$AU$36,47,0) -> 0 | AD26: =VLOOKUP(A26,[18]HISTOJANV23!$A$6:$BB$36,54,0) -> 0 | AE26: =VLOOKUP($A26,[18]HISTOJANV23!$A$6:$CA$36,60,0) -> 0 | AF26: =VLOOKUP($A26,[18]HISTOJANV23!$A$6:$CA$36,61,0) -> 0 | AG26: =VLOOKUP($A26,[18]HISTOJANV23!$A$6:$CA$36,62,0) -> 0 | AH26: =VLOOKUP($A26,[18]HISTOJANV23!$A$6:$CA$36,63,0) -> 0 | AI26: =VLOOKUP($A26,[18]HISTOJANV23!$A$6:$CA$36,64,0) -> 0 | AJ26: =VLOOKUP($A26,[18]HISTOJANV23!$A$6:$CA$36,65,0) -> 0
A27: AS201656 | B27: =VLOOKUP(A27,[15]LISTADHERENT!A$5:H$60,3,0) -> NOUBE ETIENNE | C27: =VLOOKUP(A27,MVTDEC22!A27:AJ58,3,0) -> 0 | E27: =VLOOKUP($A27,[18]HISTOJANV23!$A$6:$BA$36,48,0) -> 0 | F27: =MVTDEC22!F27+MVTDEC22!G27-MVTJANV23!E27+K27 -> 9000 | G27: =$S$40/$F$40*F27 -> 0 | H27: =F27+G27 -> 9000 | I27: =VLOOKUP($A27,[18]HISTOJANV23!$A$6:$AQ$40,22,0) -> 0 | J27: =VLOOKUP($A27,[18]HISTOJANV23!$A$6:$AU$36,45,0) -> 15000 | K27: =IF(J27=0,0,J27-(L27+M27+N27)) -> 9000 | L27: =IF(J27=0,0,1000) -> 1000 | M27: =IF(J27=0,0,1000) -> 1000 | N27: =IF(J27=0,0,4000) -> 4000 | O27: =VLOOKUP($A27,[18]HISTOJANV23!$A$6:$AU$36,7,0) -> 0 | P27: =VLOOKUP($A27,[18]HISTOJANV23!$A$6:$AU$36,23,0) -> 25000 | Q27: =VLOOKUP($A27,[18]HISTOJANV23!$A$6:$AU$36,46,0) -> 0 | R27: =VLOOKUP($A27,[18]HISTOJANV23!$A$6:$AU$36,26,0) -> 0 | S27: =VLOOKUP($A27,[18]HISTOJANV23!$A$6:$BG$36,58,0) -> 0 | T27: =VLOOKUP($A27,[18]HISTOJANV23!$A$6:$AU$36,28,0) -> 0 | U27: =VLOOKUP($A27,[18]HISTOJANV23!$A$6:$AU$36,19,0) -> 0 | V27: =VLOOKUP($A27,[18]HISTOJANV23!$A$6:$AU$36,20,0) -> 0 | W27: =VLOOKUP($A27,[18]HISTOJANV23!$A$6:$AU$36,27,0) -> 0 | X27: =VLOOKUP($A27,[18]HISTOJANV23!$A$6:$BM$36,33,0) -> 0 | Y27: =VLOOKUP($A27,[18]HISTOJANV23!$A$6:$BM$36,65,0) -> 0 | AA27: =VLOOKUP($A27,[18]HISTOJANV23!$A$6:$AU$36,43,0) -> 0 | AB27: =VLOOKUP($A27,[18]HISTOJANV23!$A$6:$AU$36,44,0) -> 0 | AC27: =VLOOKUP($A27,[18]HISTOJANV23!$A$6:$AU$36,47,0) -> 0 | AD27: =VLOOKUP(A27,[18]HISTOJANV23!$A$6:$BB$36,54,0) -> 0 | AE27: =VLOOKUP($A27,[18]HISTOJANV23!$A$6:$CA$36,60,0) -> 0 | AF27: =VLOOKUP($A27,[18]HISTOJANV23!$A$6:$CA$36,61,0) -> 0 | AG27: =VLOOKUP($A27,[18]HISTOJANV23!$A$6:$CA$36,62,0) -> 0 | AH27: =VLOOKUP($A27,[18]HISTOJANV23!$A$6:$CA$36,63,0) -> 0 | AI27: =VLOOKUP($A27,[18]HISTOJANV23!$A$6:$CA$36,64,0) -> 0 | AJ27: =VLOOKUP($A27,[18]HISTOJANV23!$A$6:$CA$36,65,0) -> 0
A28: AS201633 | B28: =VLOOKUP(A28,[15]LISTADHERENT!A$5:H$60,3,0) -> PATEGO NJOSSU GUSTAVE | C28: =VLOOKUP(A28,MVTDEC22!A28:AJ59,3,0) -> 600000 | D28: =VLOOKUP($A28,[19]MVTREPARTITION2022!$A$6:$V$39,21,0) -> 21452 | E28: =VLOOKUP($A28,[18]HISTOJANV23!$A$6:$BA$36,48,0) -> 0 | F28: =MVTDEC22!F28+MVTDEC22!G28-MVTJANV23!E28+K28 -> 669927.89 | G28: =$S$40/$F$40*F28 -> 0 | H28: =F28+G28 -> 669927.89 | I28: =VLOOKUP($A28,[18]HISTOJANV23!$A$6:$AQ$40,22,0) -> 0 | J28: =VLOOKUP($A28,[18]HISTOJANV23!$A$6:$AU$36,45,0) -> 15000 | K28: =IF(J28=0,0,J28-(L28+M28+N28)) -> 9000 | L28: =IF(J28=0,0,1000) -> 1000 | M28: =IF(J28=0,0,1000) -> 1000 | N28: =IF(J28=0,0,4000) -> 4000 | O28: =VLOOKUP($A28,[18]HISTOJANV23!$A$6:$AU$36,7,0) -> 0 | P28: =VLOOKUP($A28,[18]HISTOJANV23!$A$6:$AU$36,23,0) -> 0 | Q28: =VLOOKUP($A28,[18]HISTOJANV23!$A$6:$AU$36,46,0) -> 0 | R28: =VLOOKUP($A28,[18]HISTOJANV23!$A$6:$AU$36,26,0) -> 0 | S28: =VLOOKUP($A28,[18]HISTOJANV23!$A$6:$BG$36,58,0) -> 0 | T28: =VLOOKUP($A28,[18]HISTOJANV23!$A$6:$AU$36,28,0) -> 0 | U28: =VLOOKUP($A28,[18]HISTOJANV23!$A$6:$AU$36,19,0) -> 0 | V28: =VLOOKUP($A28,[18]HISTOJANV23!$A$6:$AU$36,20,0) -> 0 | W28: =VLOOKUP($A28,[18]HISTOJANV23!$A$6:$AU$36,27,0) -> 0 | X28: =VLOOKUP($A28,[18]HISTOJANV23!$A$6:$BM$36,33,0) -> 0 | Y28: =VLOOKUP($A28,[18]HISTOJANV23!$A$6:$BM$36,65,0) -> 0 | AA28: =VLOOKUP($A28,[18]HISTOJANV23!$A$6:$AU$36,43,0) -> 0 | AB28: =VLOOKUP($A28,[18]HISTOJANV23!$A$6:$AU$36,44,0) -> 0 | AC28: =VLOOKUP($A28,[18]HISTOJANV23!$A$6:$AU$36,47,0) -> 0 | AD28: =VLOOKUP(A28,[18]HISTOJANV23!$A$6:$BB$36,54,0) -> 0 | AE28: =VLOOKUP($A28,[18]HISTOJANV23!$A$6:$CA$36,60,0) -> 0 | AF28: =VLOOKUP($A28,[18]HISTOJANV23!$A$6:$CA$36,61,0) -> 0 | AG28: =VLOOKUP($A28,[18]HISTOJANV23!$A$6:$CA$36,62,0) -> 0 | AH28: =VLOOKUP($A28,[18]HISTOJANV23!$A$6:$CA$36,63,0) -> 0 | AI28: =VLOOKUP($A28,[18]HISTOJANV23!$A$6:$CA$36,64,0) -> 0 | AJ28: =VLOOKUP($A28,[18]HISTOJANV23!$A$6:$CA$36,65,0) -> 0
A29: AS201657 | B29: =VLOOKUP(A29,[15]LISTADHERENT!A$5:H$60,3,0) -> SEUMO POLYCARPE | C29: =VLOOKUP(A29,MVTDEC22!A29:AJ60,3,0) -> 0 | E29: =VLOOKUP($A29,[18]HISTOJANV23!$A$6:$BA$36,48,0) -> 0 | F29: =MVTDEC22!F29+MVTDEC22!G29-MVTJANV23!E29+K29 -> 9000 | G29: =$S$40/$F$40*F29 -> 0 | H29: =F29+G29 -> 9000 | I29: =VLOOKUP($A29,[18]HISTOJANV23!$A$6:$AQ$40,22,0) -> 0 | J29: =VLOOKUP($A29,[18]HISTOJANV23!$A$6:$AU$36,45,0) -> 15000 | K29: =IF(J29=0,0,J29-(L29+M29+N29)) -> 9000 | L29: =IF(J29=0,0,1000) -> 1000 | M29: =IF(J29=0,0,1000) -> 1000 | N29: =IF(J29=0,0,4000) -> 4000 | O29: =VLOOKUP($A29,[18]HISTOJANV23!$A$6:$AU$36,7,0) -> 0 | P29: =VLOOKUP($A29,[18]HISTOJANV23!$A$6:$AU$36,23,0) -> 25000 | Q29: =VLOOKUP($A29,[18]HISTOJANV23!$A$6:$AU$36,46,0) -> 0 | R29: =VLOOKUP($A29,[18]HISTOJANV23!$A$6:$AU$36,26,0) -> 0 | S29: =VLOOKUP($A29,[18]HISTOJANV23!$A$6:$BG$36,58,0) -> 0 | T29: =VLOOKUP($A29,[18]HISTOJANV23!$A$6:$AU$36,28,0) -> 0 | U29: =VLOOKUP($A29,[18]HISTOJANV23!$A$6:$AU$36,19,0) -> 0 | V29: =VLOOKUP($A29,[18]HISTOJANV23!$A$6:$AU$36,20,0) -> 0 | W29: =VLOOKUP($A29,[18]HISTOJANV23!$A$6:$AU$36,27,0) -> 0 | X29: =VLOOKUP($A29,[18]HISTOJANV23!$A$6:$BM$36,33,0) -> 0 | Y29: =VLOOKUP($A29,[18]HISTOJANV23!$A$6:$BM$36,65,0) -> 0 | AA29: =VLOOKUP($A29,[18]HISTOJANV23!$A$6:$AU$36,43,0) -> 0 | AB29: =VLOOKUP($A29,[18]HISTOJANV23!$A$6:$AU$36,44,0) -> 0 | AC29: =VLOOKUP($A29,[18]HISTOJANV23!$A$6:$AU$36,47,0) -> 0 | AD29: =VLOOKUP(A29,[18]HISTOJANV23!$A$6:$BB$36,54,0) -> 0 | AE29: =VLOOKUP($A29,[18]HISTOJANV23!$A$6:$CA$36,60,0) -> 0 | AF29: =VLOOKUP($A29,[18]HISTOJANV23!$A$6:$CA$36,61,0) -> 0 | AG29: =VLOOKUP($A29,[18]HISTOJANV23!$A$6:$CA$36,62,0) -> 0 | AH29: =VLOOKUP($A29,[18]HISTOJANV23!$A$6:$CA$36,63,0) -> 0 | AI29: =VLOOKUP($A29,[18]HISTOJANV23!$A$6:$CA$36,64,0) -> 0 | AJ29: =VLOOKUP($A29,[18]HISTOJANV23!$A$6:$CA$36,65,0) -> 0
A30: AS201653 | B30: =VLOOKUP(A30,[15]LISTADHERENT!A$5:H$60,3,0) -> SIME BRICE | C30: =VLOOKUP(A30,MVTDEC22!A30:AJ61,3,0) -> 600000 | D30: =VLOOKUP($A30,[19]MVTREPARTITION2022!$A$6:$V$39,21,0) -> 200752 | E30: =VLOOKUP($A30,[18]HISTOJANV23!$A$6:$BA$36,48,0) -> 0 | F30: =MVTDEC22!F30+MVTDEC22!G30-MVTJANV23!E30+K30 -> 860617.95 | G30: =$S$40/$F$40*F30 -> 0 | H30: =F30+G30 -> 860617.95 | I30: =VLOOKUP($A30,[18]HISTOJANV23!$A$6:$AQ$40,22,0) -> 0 | J30: =VLOOKUP($A30,[18]HISTOJANV23!$A$6:$AU$36,45,0) -> 15000 | K30: =IF(J30=0,0,J30-(L30+M30+N30)) -> 9000 | L30: =IF(J30=0,0,1000) -> 1000 | M30: =IF(J30=0,0,1000) -> 1000 | N30: =IF(J30=0,0,4000) -> 4000 | O30: =VLOOKUP($A30,[18]HISTOJANV23!$A$6:$AU$36,7,0) -> 0 | P30: =VLOOKUP($A30,[18]HISTOJANV23!$A$6:$AU$36,23,0) -> 0 | Q30: =VLOOKUP($A30,[18]HISTOJANV23!$A$6:$AU$36,46,0) -> 0 | R30: =VLOOKUP($A30,[18]HISTOJANV23!$A$6:$AU$36,26,0) -> 0 | S30: =VLOOKUP($A30,[18]HISTOJANV23!$A$6:$BG$36,58,0) -> 0 | T30: =VLOOKUP($A30,[18]HISTOJANV23!$A$6:$AU$36,28,0) -> 0 | U30: =VLOOKUP($A30,[18]HISTOJANV23!$A$6:$AU$36,19,0) -> 0 | V30: =VLOOKUP($A30,[18]HISTOJANV23!$A$6:$AU$36,20,0) -> 0 | W30: =VLOOKUP($A30,[18]HISTOJANV23!$A$6:$AU$36,27,0) -> 0 | X30: =VLOOKUP($A30,[18]HISTOJANV23!$A$6:$BM$36,33,0) -> 0 | Y30: =VLOOKUP($A30,[18]HISTOJANV23!$A$6:$BM$36,65,0) -> 0 | AA30: =VLOOKUP($A30,[18]HISTOJANV23!$A$6:$AU$36,43,0) -> 0 | AB30: =VLOOKUP($A30,[18]HISTOJANV23!$A$6:$AU$36,44,0) -> 0 | AC30: =VLOOKUP($A30,[18]HISTOJANV23!$A$6:$AU$36,47,0) -> 0 | AD30: =VLOOKUP(A30,[18]HISTOJANV23!$A$6:$BB$36,54,0) -> 0 | AE30: =VLOOKUP($A30,[18]HISTOJANV23!$A$6:$CA$36,60,0) -> 0 | AF30: =VLOOKUP($A30,[18]HISTOJANV23!$A$6:$CA$36,61,0) -> 0 | AG30: =VLOOKUP($A30,[18]HISTOJANV23!$A$6:$CA$36,62,0) -> 0 | AH30: =VLOOKUP($A30,[18]HISTOJANV23!$A$6:$CA$36,63,0) -> 0 | AI30: =VLOOKUP($A30,[18]HISTOJANV23!$A$6:$CA$36,64,0) -> 0 | AJ30: =VLOOKUP($A30,[18]HISTOJANV23!$A$6:$CA$36,65,0) -> 0
A31: AS201638 | B31: =VLOOKUP(A31,[15]LISTADHERENT!A$5:H$60,3,0) -> SIMO PIERRE | C31: =VLOOKUP(A31,MVTDEC22!A31:AJ62,3,0) -> 600000 | D31: =VLOOKUP($A31,[19]MVTREPARTITION2022!$A$6:$V$39,21,0) -> 103606 | E31: =VLOOKUP($A31,[18]HISTOJANV23!$A$6:$BA$36,48,0) -> 0 | F31: =MVTDEC22!F31+MVTDEC22!G31-MVTJANV23!E31+K31 -> 867301.02 | G31: =$S$40/$F$40*F31 -> 0 | H31: =F31+G31 -> 867301.02 | I31: =VLOOKUP($A31,[18]HISTOJANV23!$A$6:$AQ$40,22,0) -> 0 | J31: =VLOOKUP($A31,[18]HISTOJANV23!$A$6:$AU$36,45,0) -> 125000 | K31: =IF(J31=0,0,J31-(L31+M31+N31)) -> 119000 | L31: =IF(J31=0,0,1000) -> 1000 | M31: =IF(J31=0,0,1000) -> 1000 | N31: =IF(J31=0,0,4000) -> 4000 | O31: =VLOOKUP($A31,[18]HISTOJANV23!$A$6:$AU$36,7,0) -> 0 | P31: =VLOOKUP($A31,[18]HISTOJANV23!$A$6:$AU$36,23,0) -> 0 | Q31: =VLOOKUP($A31,[18]HISTOJANV23!$A$6:$AU$36,46,0) -> 0 | R31: =VLOOKUP($A31,[18]HISTOJANV23!$A$6:$AU$36,26,0) -> 0 | S31: =VLOOKUP($A31,[18]HISTOJANV23!$A$6:$BG$36,58,0) -> 0 | T31: =VLOOKUP($A31,[18]HISTOJANV23!$A$6:$AU$36,28,0) -> 0 | U31: =VLOOKUP($A31,[18]HISTOJANV23!$A$6:$AU$36,19,0) -> 0 | V31: =VLOOKUP($A31,[18]HISTOJANV23!$A$6:$AU$36,20,0) -> 0 | W31: =VLOOKUP($A31,[18]HISTOJANV23!$A$6:$AU$36,27,0) -> 0 | X31: =VLOOKUP($A31,[18]HISTOJANV23!$A$6:$BM$36,33,0) -> 0 | Y31: =VLOOKUP($A31,[18]HISTOJANV23!$A$6:$BM$36,65,0) -> 0 | AA31: =VLOOKUP($A31,[18]HISTOJANV23!$A$6:$AU$36,43,0) -> 0 | AB31: =VLOOKUP($A31,[18]HISTOJANV23!$A$6:$AU$36,44,0) -> 0 | AC31: =VLOOKUP($A31,[18]HISTOJANV23!$A$6:$AU$36,47,0) -> 0 | AD31: =VLOOKUP(A31,[18]HISTOJANV23!$A$6:$BB$36,54,0) -> 0 | AE31: =VLOOKUP($A31,[18]HISTOJANV23!$A$6:$CA$36,60,0) -> 0 | AF31: =VLOOKUP($A31,[18]HISTOJANV23!$A$6:$CA$36,61,0) -> 0 | AG31: =VLOOKUP($A31,[18]HISTOJANV23!$A$6:$CA$36,62,0) -> 0 | AH31: =VLOOKUP($A31,[18]HISTOJANV23!$A$6:$CA$36,63,0) -> 0 | AI31: =VLOOKUP($A31,[18]HISTOJANV23!$A$6:$CA$36,64,0) -> 0 | AJ31: =VLOOKUP($A31,[18]HISTOJANV23!$A$6:$CA$36,65,0) -> 0
A32: AS201641 | B32: =VLOOKUP(A32,[15]LISTADHERENT!A$5:H$60,3,0) -> TCHOUAMOU MATHIEU | C32: =VLOOKUP(A32,MVTDEC22!A32:AJ63,3,0) -> 600000 | D32: =VLOOKUP($A32,[19]MVTREPARTITION2022!$A$6:$V$39,21,0) -> 4208 | E32: =VLOOKUP($A32,[18]HISTOJANV23!$A$6:$BA$36,48,0) -> 0 | F32: =MVTDEC22!F32+MVTDEC22!G32-MVTJANV23!E32+K32 -> 651588.42 | G32: =$S$40/$F$40*F32 -> 0 | H32: =F32+G32 -> 651588.42 | I32: =VLOOKUP($A32,[18]HISTOJANV23!$A$6:$AQ$40,22,0) -> 0 | J32: =VLOOKUP($A32,[18]HISTOJANV23!$A$6:$AU$36,45,0) -> 15000 | K32: =IF(J32=0,0,J32-(L32+M32+N32)) -> 9000 | L32: =IF(J32=0,0,1000) -> 1000 | M32: =IF(J32=0,0,1000) -> 1000 | N32: =IF(J32=0,0,4000) -> 4000 | O32: =VLOOKUP($A32,[18]HISTOJANV23!$A$6:$AU$36,7,0) -> 0 | P32: =VLOOKUP($A32,[18]HISTOJANV23!$A$6:$AU$36,23,0) -> 0 | Q32: =VLOOKUP($A32,[18]HISTOJANV23!$A$6:$AU$36,46,0) -> 0 | R32: =VLOOKUP($A32,[18]HISTOJANV23!$A$6:$AU$36,26,0) -> 0 | S32: =VLOOKUP($A32,[18]HISTOJANV23!$A$6:$BG$36,58,0) -> 0 | T32: =VLOOKUP($A32,[18]HISTOJANV23!$A$6:$AU$36,28,0) -> 0 | U32: =VLOOKUP($A32,[18]HISTOJANV23!$A$6:$AU$36,19,0) -> 0 | V32: =VLOOKUP($A32,[18]HISTOJANV23!$A$6:$AU$36,20,0) -> 0 | W32: =VLOOKUP($A32,[18]HISTOJANV23!$A$6:$AU$36,27,0) -> 0 | X32: =VLOOKUP($A32,[18]HISTOJANV23!$A$6:$BM$36,33,0) -> 0 | Y32: =VLOOKUP($A32,[18]HISTOJANV23!$A$6:$BM$36,65,0) -> 0 | AA32: =VLOOKUP($A32,[18]HISTOJANV23!$A$6:$AU$36,43,0) -> 0 | AB32: =VLOOKUP($A32,[18]HISTOJANV23!$A$6:$AU$36,44,0) -> 0 | AC32: =VLOOKUP($A32,[18]HISTOJANV23!$A$6:$AU$36,47,0) -> 0 | AD32: =VLOOKUP(A32,[18]HISTOJANV23!$A$6:$BB$36,54,0) -> 0 | AE32: =VLOOKUP($A32,[18]HISTOJANV23!$A$6:$CA$36,60,0) -> 0 | AF32: =VLOOKUP($A32,[18]HISTOJANV23!$A$6:$CA$36,61,0) -> 0 | AG32: =VLOOKUP($A32,[18]HISTOJANV23!$A$6:$CA$36,62,0) -> 0 | AH32: =VLOOKUP($A32,[18]HISTOJANV23!$A$6:$CA$36,63,0) -> 0 | AI32: =VLOOKUP($A32,[18]HISTOJANV23!$A$6:$CA$36,64,0) -> 0 | AJ32: =VLOOKUP($A32,[18]HISTOJANV23!$A$6:$CA$36,65,0) -> 0
A33: AS201643 | B33: =VLOOKUP(A33,[15]LISTADHERENT!A$5:H$60,3,0) -> TCHOUTOU NANA CLAUDE | C33: =VLOOKUP(A33,MVTDEC22!A33:AJ64,3,0) -> 0 | E33: =VLOOKUP($A33,[18]HISTOJANV23!$A$6:$BA$36,48,0) -> 0 | F33: =MVTDEC22!F33+MVTDEC22!G33-MVTJANV23!E33+K33 -> 9000 | G33: =$S$40/$F$40*F33 -> 0 | H33: =F33+G33 -> 9000 | I33: =VLOOKUP($A33,[18]HISTOJANV23!$A$6:$AQ$40,22,0) -> 0 | J33: =VLOOKUP($A33,[18]HISTOJANV23!$A$6:$AU$36,45,0) -> 15000 | K33: =IF(J33=0,0,J33-(L33+M33+N33)) -> 9000 | L33: =IF(J33=0,0,1000) -> 1000 | M33: =IF(J33=0,0,1000) -> 1000 | N33: =IF(J33=0,0,4000) -> 4000 | O33: =VLOOKUP($A33,[18]HISTOJANV23!$A$6:$AU$36,7,0) -> 0 | P33: =VLOOKUP($A33,[18]HISTOJANV23!$A$6:$AU$36,23,0) -> 0 | Q33: =VLOOKUP($A33,[18]HISTOJANV23!$A$6:$AU$36,46,0) -> 0 | R33: =VLOOKUP($A33,[18]HISTOJANV23!$A$6:$AU$36,26,0) -> 0 | S33: =VLOOKUP($A33,[18]HISTOJANV23!$A$6:$BG$36,58,0) -> 0 | T33: =VLOOKUP($A33,[18]HISTOJANV23!$A$6:$AU$36,28,0) -> 0 | U33: =VLOOKUP($A33,[18]HISTOJANV23!$A$6:$AU$36,19,0) -> 0 | V33: =VLOOKUP($A33,[18]HISTOJANV23!$A$6:$AU$36,20,0) -> 0 | W33: =VLOOKUP($A33,[18]HISTOJANV23!$A$6:$AU$36,27,0) -> 0 | X33: =VLOOKUP($A33,[18]HISTOJANV23!$A$6:$BM$36,33,0) -> 0 | Y33: =VLOOKUP($A33,[18]HISTOJANV23!$A$6:$BM$36,65,0) -> 0 | AA33: =VLOOKUP($A33,[18]HISTOJANV23!$A$6:$AU$36,43,0) -> 0 | AB33: =VLOOKUP($A33,[18]HISTOJANV23!$A$6:$AU$36,44,0) -> 0 | AC33: =VLOOKUP($A33,[18]HISTOJANV23!$A$6:$AU$36,47,0) -> 0 | AD33: =VLOOKUP(A33,[18]HISTOJANV23!$A$6:$BB$36,54,0) -> 0 | AE33: =VLOOKUP($A33,[18]HISTOJANV23!$A$6:$CA$36,60,0) -> 0 | AF33: =VLOOKUP($A33,[18]HISTOJANV23!$A$6:$CA$36,61,0) -> 0 | AG33: =VLOOKUP($A33,[18]HISTOJANV23!$A$6:$CA$36,62,0) -> 0 | AH33: =VLOOKUP($A33,[18]HISTOJANV23!$A$6:$CA$36,63,0) -> 0 | AI33: =VLOOKUP($A33,[18]HISTOJANV23!$A$6:$CA$36,64,0) -> 0 | AJ33: =VLOOKUP($A33,[18]HISTOJANV23!$A$6:$CA$36,65,0) -> 0
A34: AS201658 | B34: =VLOOKUP(A34,[15]LISTADHERENT!A$5:H$60,3,0) -> YANTCHOU GERVAIS | C34: =VLOOKUP(A34,MVTDEC22!A34:AJ65,3,0) -> 0 | E34: =VLOOKUP($A34,[18]HISTOJANV23!$A$6:$BA$36,48,0) -> 0 | F34: =MVTDEC22!F34+MVTDEC22!G34-MVTJANV23!E34+K34 -> 9000 | G34: =$S$40/$F$40*F34 -> 0 | H34: =F34+G34 -> 9000 | I34: =VLOOKUP($A34,[18]HISTOJANV23!$A$6:$AQ$40,22,0) -> 0 | J34: =VLOOKUP($A34,[18]HISTOJANV23!$A$6:$AU$36,45,0) -> 15000 | K34: =IF(J34=0,0,J34-(L34+M34+N34)) -> 9000 | L34: =IF(J34=0,0,1000) -> 1000 | M34: =IF(J34=0,0,1000) -> 1000 | N34: =IF(J34=0,0,4000) -> 4000 | O34: =VLOOKUP($A34,[18]HISTOJANV23!$A$6:$AU$36,7,0) -> 0 | P34: =VLOOKUP($A34,[18]HISTOJANV23!$A$6:$AU$36,23,0) -> 25000 | Q34: =VLOOKUP($A34,[18]HISTOJANV23!$A$6:$AU$36,46,0) -> 35000 | R34: =VLOOKUP($A34,[18]HISTOJANV23!$A$6:$AU$36,26,0) -> 0 | S34: =VLOOKUP($A34,[18]HISTOJANV23!$A$6:$BG$36,58,0) -> 0 | T34: =VLOOKUP($A34,[18]HISTOJANV23!$A$6:$AU$36,28,0) -> 0 | U34: =VLOOKUP($A34,[18]HISTOJANV23!$A$6:$AU$36,19,0) -> 0 | V34: =VLOOKUP($A34,[18]HISTOJANV23!$A$6:$AU$36,20,0) -> 0 | W34: =VLOOKUP($A34,[18]HISTOJANV23!$A$6:$AU$36,27,0) -> 0 | X34: =VLOOKUP($A34,[18]HISTOJANV23!$A$6:$BM$36,33,0) -> 0 | Y34: =VLOOKUP($A34,[18]HISTOJANV23!$A$6:$BM$36,65,0) -> 0 | AA34: =VLOOKUP($A34,[18]HISTOJANV23!$A$6:$AU$36,43,0) -> 0 | AB34: =VLOOKUP($A34,[18]HISTOJANV23!$A$6:$AU$36,44,0) -> 0 | AC34: =VLOOKUP($A34,[18]HISTOJANV23!$A$6:$AU$36,47,0) -> 0 | AD34: =VLOOKUP(A34,[18]HISTOJANV23!$A$6:$BB$36,54,0) -> 0 | AE34: =VLOOKUP($A34,[18]HISTOJANV23!$A$6:$CA$36,60,0) -> 0 | AF34: =VLOOKUP($A34,[18]HISTOJANV23!$A$6:$CA$36,61,0) -> 0 | AG34: =VLOOKUP($A34,[18]HISTOJANV23!$A$6:$CA$36,62,0) -> 0 | AH34: =VLOOKUP($A34,[18]HISTOJANV23!$A$6:$CA$36,63,0) -> 0 | AI34: =VLOOKUP($A34,[18]HISTOJANV23!$A$6:$CA$36,64,0) -> 0 | AJ34: =VLOOKUP($A34,[18]HISTOJANV23!$A$6:$CA$36,65,0) -> 0
A35: AS201646 | B35: =VLOOKUP(A35,[15]LISTADHERENT!A$5:H$60,3,0) -> YEPMOU JEAN JACQUES | C35: =VLOOKUP(A35,MVTDEC22!A35:AJ66,3,0) -> 600000 | D35: =VLOOKUP($A35,[19]MVTREPARTITION2022!$A$6:$V$39,21,0) -> 914734 | E35: =VLOOKUP($A35,[18]HISTOJANV23!$A$6:$BA$36,48,0) -> 0 | F35: =MVTDEC22!F35+MVTDEC22!G35-MVTJANV23!E35+K35 -> 1619953.5 | G35: =$S$40/$F$40*F35 -> 0 | H35: =F35+G35 -> 1619953.5 | I35: =VLOOKUP($A35,[18]HISTOJANV23!$A$6:$AQ$40,22,0) -> 0 | J35: =VLOOKUP($A35,[18]HISTOJANV23!$A$6:$AU$36,45,0) -> 15000 | K35: =IF(J35=0,0,J35-(L35+M35+N35)) -> 9000 | L35: =IF(J35=0,0,1000) -> 1000 | M35: =IF(J35=0,0,1000) -> 1000 | N35: =IF(J35=0,0,4000) -> 4000 | O35: =VLOOKUP($A35,[18]HISTOJANV23!$A$6:$AU$36,7,0) -> 0 | P35: =VLOOKUP($A35,[18]HISTOJANV23!$A$6:$AU$36,23,0) -> 0 | Q35: =VLOOKUP($A35,[18]HISTOJANV23!$A$6:$AU$36,46,0) -> 0 | R35: =VLOOKUP($A35,[18]HISTOJANV23!$A$6:$AU$36,26,0) -> 0 | S35: =VLOOKUP($A35,[18]HISTOJANV23!$A$6:$BG$36,58,0) -> 0 | T35: =VLOOKUP($A35,[18]HISTOJANV23!$A$6:$AU$36,28,0) -> 0 | U35: =VLOOKUP($A35,[18]HISTOJANV23!$A$6:$AU$36,19,0) -> 0 | V35: =VLOOKUP($A35,[18]HISTOJANV23!$A$6:$AU$36,20,0) -> 0 | W35: =VLOOKUP($A35,[18]HISTOJANV23!$A$6:$AU$36,27,0) -> 0 | X35: =VLOOKUP($A35,[18]HISTOJANV23!$A$6:$BM$36,33,0) -> 0 | Y35: =VLOOKUP($A35,[18]HISTOJANV23!$A$6:$BM$36,65,0) -> 0 | AA35: =VLOOKUP($A35,[18]HISTOJANV23!$A$6:$AU$36,43,0) -> 0 | AB35: =VLOOKUP($A35,[18]HISTOJANV23!$A$6:$AU$36,44,0) -> 0 | AC35: =VLOOKUP($A35,[18]HISTOJANV23!$A$6:$AU$36,47,0) -> 0 | AD35: =VLOOKUP(A35,[18]HISTOJANV23!$A$6:$BB$36,54,0) -> 0 | AE35: =VLOOKUP($A35,[18]HISTOJANV23!$A$6:$CA$36,60,0) -> 0 | AF35: =VLOOKUP($A35,[18]HISTOJANV23!$A$6:$CA$36,61,0) -> 0 | AG35: =VLOOKUP($A35,[18]HISTOJANV23!$A$6:$CA$36,62,0) -> 0 | AH35: =VLOOKUP($A35,[18]HISTOJANV23!$A$6:$CA$36,63,0) -> 0 | AI35: =VLOOKUP($A35,[18]HISTOJANV23!$A$6:$CA$36,64,0) -> 0 | AJ35: =VLOOKUP($A35,[18]HISTOJANV23!$A$6:$CA$36,65,0) -> 0
A36: AS201647 | B36: =VLOOKUP(A36,[15]LISTADHERENT!A$5:H$60,3,0) -> YOUMBI EMMANUEL | C36: =VLOOKUP(A36,MVTDEC22!A36:AJ67,3,0) -> 600000 | D36: =VLOOKUP($A36,[19]MVTREPARTITION2022!$A$6:$V$39,21,0) -> 1057774 | E36: =VLOOKUP($A36,[18]HISTOJANV23!$A$6:$BA$36,48,0) -> 0 | F36: =MVTDEC22!F36+MVTDEC22!G36-MVTJANV23!E36+K36 -> 1772079.5 | G36: =$S$40/$F$40*F36 -> 0 | H36: =F36+G36 -> 1772079.5 | I36: =VLOOKUP($A36,[18]HISTOJANV23!$A$6:$AQ$40,22,0) -> 0 | J36: =VLOOKUP($A36,[18]HISTOJANV23!$A$6:$AU$36,45,0) -> 15000 | K36: =IF(J36=0,0,J36-(L36+M36+N36)) -> 9000 | L36: =IF(J36=0,0,1000) -> 1000 | M36: =IF(J36=0,0,1000) -> 1000 | N36: =IF(J36=0,0,4000) -> 4000 | O36: =VLOOKUP($A36,[18]HISTOJANV23!$A$6:$AU$36,7,0) -> 0 | P36: =VLOOKUP($A36,[18]HISTOJANV23!$A$6:$AU$36,23,0) -> 0 | Q36: =VLOOKUP($A36,[18]HISTOJANV23!$A$6:$AU$36,46,0) -> 0 | R36: =VLOOKUP($A36,[18]HISTOJANV23!$A$6:$AU$36,26,0) -> 0 | S36: =VLOOKUP($A36,[18]HISTOJANV23!$A$6:$BG$36,58,0) -> 0 | T36: =VLOOKUP($A36,[18]HISTOJANV23!$A$6:$AU$36,28,0) -> 0 | U36: =VLOOKUP($A36,[18]HISTOJANV23!$A$6:$AU$36,19,0) -> 0 | V36: =VLOOKUP($A36,[18]HISTOJANV23!$A$6:$AU$36,20,0) -> 0 | W36: =VLOOKUP($A36,[18]HISTOJANV23!$A$6:$AU$36,27,0) -> 0 | X36: =VLOOKUP($A36,[18]HISTOJANV23!$A$6:$BM$36,33,0) -> 0 | Y36: =VLOOKUP($A36,[18]HISTOJANV23!$A$6:$BM$36,65,0) -> 0 | AA36: =VLOOKUP($A36,[18]HISTOJANV23!$A$6:$AU$36,43,0) -> 0 | AB36: =VLOOKUP($A36,[18]HISTOJANV23!$A$6:$AU$36,44,0) -> 0 | AC36: =VLOOKUP($A36,[18]HISTOJANV23!$A$6:$AU$36,47,0) -> 0 | AD36: =VLOOKUP(A36,[18]HISTOJANV23!$A$6:$BB$36,54,0) -> 0 | AE36: =VLOOKUP($A36,[18]HISTOJANV23!$A$6:$CA$36,60,0) -> 0 | AF36: =VLOOKUP($A36,[18]HISTOJANV23!$A$6:$CA$36,61,0) -> 0 | AG36: =VLOOKUP($A36,[18]HISTOJANV23!$A$6:$CA$36,62,0) -> 0 | AH36: =VLOOKUP($A36,[18]HISTOJANV23!$A$6:$CA$36,63,0) -> 0 | AI36: =VLOOKUP($A36,[18]HISTOJANV23!$A$6:$CA$36,64,0) -> 0 | AJ36: =VLOOKUP($A36,[18]HISTOJANV23!$A$6:$CA$36,65,0) -> 0
A37: AS201629 | B37: =VLOOKUP(A37,[15]LISTADHERENT!$A$5:$J$45,3,0) -> NKEPSEU DIEUDONNE | C37: 600000 | D37: 2434 | E37: 640702 | F37: =MVTDEC22!F37+MVTDEC22!G37-MVTJANV23!E37+K37 -> -0.1339265 | G37: =$S$40/$F$40*F37 -> 0 | H37: =F37+G37 -> -0.1339265
A40: TOTAL | C40: =SUM(C6:C39) -> 15600000 | D40: =SUM(D6:D39) -> 4361558.5 | E40: =SUM(E6:E39) -> 640702 | F40: =SUM(F6:F39) -> 21638858 | G40: =SUM(G6:G39) -> 0 | H40: =SUM(H6:H39) -> 21638858 | I40: =SUM(I6:I39) -> 0 | J40: =SUM(J6:J39) -> 694000 | ... AJ40: =SUM(AJ6:AJ39) -> 0

Sheet MVTFEV23
A1: ASSOCIATION | B1: ASELBY | G1: K
A2: ANNEE | B2: 2023
A3: TONTINE
J4: 44974
A5: MATRICULE | B5: NOM ET PRENOM | C5: FONDES DE DEPART | D5: RECONDUCTION | E5: RETRAIT PARTIEL | F5: FONDS DEFINITIF | G5: REPARTITION INTERET | H5: CAPITAL COMPOSE | I5: SANCTION | J5: RESTE | K5: EPARGNE | L5: FONDS DE ROULEMENT | M5: FRAIS EXCEPTIONNEL | N5: COLLATION | O5: PENALITE VST ESPECES | P5: INSCRISPTION | Q5: MUTUELLE | R5: PRÊT FONDS | S5: INTERETPRET FONDS | T5: NUMERO CHEQUE | U5: REMBOURSEMENTPRET FONDS | V5: MODE VERSEMENT REMBOURSEMENT | W5: MODE VERSEMENT PRÊT | X5: NUMERO CHEQUE | Y5: PENALITE PRET FONDS | Z5: PENALITE FONDS | AA5: PENALITE ECHEC TONTINE | AB5: PENALITE RETARD TONTINE | AC5: REMBOURSEMENT TRANSPORT | AD5: CONTRIBUTION FOYER | AE5: FONDS DE ROULEMENT | AF5: FRAIS EXCEPTIONNEL | AG5: FONDS MUTUELLE | AH5: COLLATION RECEPTION | AI5: PENALITE PRET FONDS | AJ5: MONTANT GRATIFICATION 2021
A6: AS201648 | B6: =VLOOKUP(A6,[15]LISTADHERENT!A$5:H$60,3,0) -> ASELBY | F6: =MVTJANV23!F6+MVTJANV23!G6-MVTFEV23!E6+K6 -> 868412.07 | G6: 1189.8849 | H6: =F6+G6 -> 869601.96 | AE6: =VLOOKUP($A6,[18]HISTOFEV23!$A$6:$CA$36,60,0) -> 68500 | AF6: =VLOOKUP($A6,[18]HISTOFEV23!$A$6:$CA$36,61,0) -> 0 | AG6: =VLOOKUP($A6,[18]HISTOFEV23!$A$6:$CA$36,62,0) -> 560000 | AH6: =VLOOKUP($A6,[18]HISTOFEV23!$A$6:$CA$36,63,0) -> 0 | AI6: =VLOOKUP($A6,[18]HISTOFEV23!$A$6:$CA$36,64,0) -> 0 | AJ6: =VLOOKUP($A6,[18]HISTOFEV23!$A$6:$CA$36,65,0) -> 200000
A7: AS201601 | B7: =VLOOKUP(A7,[15]LISTADHERENT!A$5:H$60,3,0) -> BAKOP ACHILLE | E7: =VLOOKUP($A7,[18]HISTOFEV23!$A$6:$BA$36,48,0) -> 0 | F7: =MVTJANV23!F7+MVTJANV23!G7-MVTFEV23!E7+K7 -> 618000 | G7: 846.77415 | H7: =F7+G7 -> 618846.77 | I7: =VLOOKUP($A7,[18]HISTOFEV23!$A$6:$AQ$40,22,0) -> 0 | J7: =VLOOKUP($A7,[18]HISTOFEV23!$A$6:$AU$36,45,0) -> 15000 | K7: =IF(J7=0,0,J7-(L7+M7+N7)) -> 9000 | L7: =IF(J7=0,0,1000) -> 1000 | M7: =IF(J7=0,0,1000) -> 1000 | N7: =IF(J7=0,0,4000) -> 4000 | O7: =VLOOKUP($A7,[18]HISTOFEV23!$A$6:$AU$36,7,0) -> 0 | P7: =VLOOKUP($A7,[18]HISTOFEV23!$A$6:$AU$36,23,0) -> 0 | Q7: =VLOOKUP($A7,[18]HISTOFEV23!$A$6:$AU$36,46,0) -> 0 | R7: =VLOOKUP($A7,[18]HISTOFEV23!$A$6:$AU$36,26,0) -> 0 | S7: =VLOOKUP($A7,[18]HISTOFEV23!$A$6:$BG$36,58,0) -> 0 | T7: =VLOOKUP($A7,[18]HISTOFEV23!$A$6:$AU$36,28,0) -> 0 | U7: =VLOOKUP($A7,[18]HISTOFEV23!$A$6:$AU$36,19,0) -> 0 | V7: =VLOOKUP($A7,[18]HISTOFEV23!$A$6:$AU$36,20,0) -> 0 | W7: =VLOOKUP($A7,[18]HISTOFEV23!$A$6:$AU$36,27,0) -> 0 | X7: =VLOOKUP($A7,[18]HISTOFEV23!$A$6:$BM$36,33,0) -> 0 | Y7: =VLOOKUP($A7,[18]HISTOFEV23!$A$6:$BM$36,65,0) -> 0 | AA7: =VLOOKUP($A7,[18]HISTOFEV23!$A$6:$AU$36,43,0) -> 0 | AB7: =VLOOKUP($A7,[18]HISTOFEV23!$A$6:$AU$36,44,0) -> 0 | AC7: =VLOOKUP($A7,[18]HISTOFEV23!$A$6:$AU$36,47,0) -> 0 | AD7: =VLOOKUP(A7,[18]HISTOFEV23!$A$6:$BB$36,54,0) -> 0 | AE7: =VLOOKUP($A7,[18]HISTOFEV23!$A$6:$CA$36,60,0) -> 0 | AF7: =VLOOKUP($A7,[18]HISTOFEV23!$A$6:$CA$36,61,0) -> 0 | AG7: =VLOOKUP($A7,[18]HISTOFEV23!$A$6:$CA$36,62,0) -> 0 | AH7: =VLOOKUP($A7,[18]HISTOFEV23!$A$6:$CA$36,63,0) -> 0 | AI7: =VLOOKUP($A7,[18]HISTOFEV23!$A$6:$CA$36,64,0) -> 0 | AJ7: =VLOOKUP($A7,[18]HISTOFEV23!$A$6:$CA$36,65,0) -> 0
A8: AS201602 | B8: =VLOOKUP(A8,[15]LISTADHERENT!A$5:H$60,3,0) -> BOUTCHOUANG WILLIAM | E8: =VLOOKUP($A8,[18]HISTOFEV23!$A$6:$BA$36,48,0) -> 0 | F8: =MVTJANV23!F8+MVTJANV23!G8-MVTFEV23!E8+K8 -> 663583.07 | G8: 909.23138 | H8: =F8+G8 -> 664492.3 | I8: =VLOOKUP($A8,[18]HISTOFEV23!$A$6:$AQ$40,22,0) -> 0 | J8: =VLOOKUP($A8,[18]HISTOFEV23!$A$6:$AU$36,45,0) -> 15000 | K8: =IF(J8=0,0,J8-(L8+M8+N8)) -> 9000 | L8: =IF(J8=0,0,1000) -> 1000 | M8: =IF(J8=0,0,1000) -> 1000 | N8: =IF(J8=0,0,4000) -> 4000 | O8: =VLOOKUP($A8,[18]HISTOFEV23!$A$6:$AU$36,7,0) -> 0 | P8: =VLOOKUP($A8,[18]HISTOFEV23!$A$6:$AU$36,23,0) -> 0 | Q8: =VLOOKUP($A8,[18]HISTOFEV23!$A$6:$AU$36,46,0) -> 0 | R8: =VLOOKUP($A8,[18]HISTOFEV23!$A$6:$AU$36,26,0) -> 0 | S8: =VLOOKUP($A8,[18]HISTOFEV23!$A$6:$BG$36,58,0) -> 0 | T8: =VLOOKUP($A8,[18]HISTOFEV23!$A$6:$AU$36,28,0) -> 0 | U8: =VLOOKUP($A8,[18]HISTOFEV23!$A$6:$AU$36,19,0) -> 500000 | V8: =VLOOKUP($A8,[18]HISTOFEV23!$A$6:$AU$36,20,0) -> BANQUE | W8: =VLOOKUP($A8,[18]HISTOFEV23!$A$6:$AU$36,27,0) -> 0 | X8: =VLOOKUP($A8,[18]HISTOFEV23!$A$6:$BM$36,33,0) -> 0 | Y8: =VLOOKUP($A8,[18]HISTOFEV23!$A$6:$BM$36,65,0) -> 0 | AA8: =VLOOKUP($A8,[18]HISTOFEV23!$A$6:$AU$36,43,0) -> 0 | AB8: =VLOOKUP($A8,[18]HISTOFEV23!$A$6:$AU$36,44,0) -> 0 | AC8: =VLOOKUP($A8,[18]HISTOFEV23!$A$6:$AU$36,47,0) -> 0 | AD8: =VLOOKUP(A8,[18]HISTOFEV23!$A$6:$BB$36,54,0) -> 0 | AE8: =VLOOKUP($A8,[18]HISTOFEV23!$A$6:$CA$36,60,0) -> 0 | AF8: =VLOOKUP($A8,[18]HISTOFEV23!$A$6:$CA$36,61,0) -> 0 | AG8: =VLOOKUP($A8,[18]HISTOFEV23!$A$6:$CA$36,62,0) -> 0 | AH8: =VLOOKUP($A8,[18]HISTOFEV23!$A$6:$CA$36,63,0) -> 0 | AI8: =VLOOKUP($A8,[18]HISTOFEV23!$A$6:$CA$36,64,0) -> 0 | AJ8: =VLOOKUP($A8,[18]HISTOFEV23!$A$6:$CA$36,65,0) -> 0
A9: AS201604 | B9: =VLOOKUP(A9,[15]LISTADHERENT!A$5:H$60,3,0) -> DJOMO JEAN PAUL | E9: =VLOOKUP($A9,[18]HISTOFEV23!$A$6:$BA$36,48,0) -> 0 | F9: =MVTJANV23!F9+MVTJANV23!G9-MVTFEV23!E9+K9 -> 689228.59 | G9: 944.37047 | H9: =F9+G9 -> 690172.96 | I9: =VLOOKUP($A9,[18]HISTOFEV23!$A$6:$AQ$40,22,0) -> 0 | J9: =VLOOKUP($A9,[18]HISTOFEV23!$A$6:$AU$36,45,0) -> 23000 | K9: =IF(J9=0,0,J9-(L9+M9+N9)) -> 17000 | L9: =IF(J9=0,0,1000) -> 1000 | M9: =IF(J9=0,0,1000) -> 1000 | N9: =IF(J9=0,0,4000) -> 4000 | O9: =VLOOKUP($A9,[18]HISTOFEV23!$A$6:$AU$36,7,0) -> 0 | P9: =VLOOKUP($A9,[18]HISTOFEV23!$A$6:$AU$36,23,0) -> 0 | Q9: =VLOOKUP($A9,[18]HISTOFEV23!$A$6:$AU$36,46,0) -> 0 | R9: =VLOOKUP($A9,[18]HISTOFEV23!$A$6:$AU$36,26,0) -> 0 | S9: =VLOOKUP($A9,[18]HISTOFEV23!$A$6:$BG$36,58,0) -> 0 | T9: =VLOOKUP($A9,[18]HISTOFEV23!$A$6:$AU$36,28,0) -> 0 | U9: =VLOOKUP($A9,[18]HISTOFEV23!$A$6:$AU$36,19,0) -> 0 | V9: =VLOOKUP($A9,[18]HISTOFEV23!$A$6:$AU$36,20,0) -> 0 | W9: =VLOOKUP($A9,[18]HISTOFEV23!$A$6:$AU$36,27,0) -> 0 | X9: =VLOOKUP($A9,[18]HISTOFEV23!$A$6:$BM$36,33,0) -> 0 | Y9: =VLOOKUP($A9,[18]HISTOFEV23!$A$6:$BM$36,65,0) -> 0 | AA9: =VLOOKUP($A9,[18]HISTOFEV23!$A$6:$AU$36,43,0) -> 0 | AB9: =VLOOKUP($A9,[18]HISTOFEV23!$A$6:$AU$36,44,0) -> 0 | AC9: =VLOOKUP($A9,[18]HISTOFEV23!$A$6:$AU$36,47,0) -> 0 | AD9: =VLOOKUP(A9,[18]HISTOFEV23!$A$6:$BB$36,54,0) -> 0 | AE9: =VLOOKUP($A9,[18]HISTOFEV23!$A$6:$CA$36,60,0) -> 0 | AF9: =VLOOKUP($A9,[18]HISTOFEV23!$A$6:$CA$36,61,0) -> 0 | AG9: =VLOOKUP($A9,[18]HISTOFEV23!$A$6:$CA$36,62,0) -> 0 | AH9: =VLOOKUP($A9,[18]HISTOFEV23!$A$6:$CA$36,63,0) -> 0 | AI9: =VLOOKUP($A9,[18]HISTOFEV23!$A$6:$CA$36,64,0) -> 0 | AJ9: =VLOOKUP($A9,[18]HISTOFEV23!$A$6:$CA$36,65,0) -> 0
A10: AS201654 | B10: =VLOOKUP(A10,[15]LISTADHERENT!A$5:H$60,3,0) -> DJOMOU TCHAPDA | E10: =VLOOKUP($A10,[18]HISTOFEV23!$A$6:$BA$36,48,0) -> 0 | F10: =MVTJANV23!F10+MVTJANV23!G10-MVTFEV23!E10+K10 -> 707917.85 | G10: 969.97821 | H10: =F10+G10 -> 708887.83 | I10: =VLOOKUP($A10,[18]HISTOFEV23!$A$6:$AQ$40,22,0) -> 0 | J10: =VLOOKUP($A10,[18]HISTOFEV23!$A$6:$AU$36,45,0) -> 15000 | K10: =IF(J10=0,0,J10-(L10+M10+N10)) -> 9000 | L10: =IF(J10=0,0,1000) -> 1000 | M10: =IF(J10=0,0,1000) -> 1000 | N10: =IF(J10=0,0,4000) -> 4000 | O10: =VLOOKUP($A10,[18]HISTOFEV23!$A$6:$AU$36,7,0) -> 0 | P10: =VLOOKUP($A10,[18]HISTOFEV23!$A$6:$AU$36,23,0) -> 0 | Q10: =VLOOKUP($A10,[18]HISTOFEV23!$A$6:$AU$36,46,0) -> 0 | R10: =VLOOKUP($A10,[18]HISTOFEV23!$A$6:$AU$36,26,0) -> 0 | S10: =VLOOKUP($A10,[18]HISTOFEV23!$A$6:$BG$36,58,0) -> 0 | T10: =VLOOKUP($A10,[18]HISTOFEV23!$A$6:$AU$36,28,0) -> 0 | U10: =VLOOKUP($A10,[18]HISTOFEV23!$A$6:$AU$36,19,0) -> 0 | V10: =VLOOKUP($A10,[18]HISTOFEV23!$A$6:$AU$36,20,0) -> 0 | W10: =VLOOKUP($A10,[18]HISTOFEV23!$A$6:$AU$36,27,0) -> 0 | X10: =VLOOKUP($A10,[18]HISTOFEV23!$A$6:$BM$36,33,0) -> 0 | Y10: =VLOOKUP($A10,[18]HISTOFEV23!$A$6:$BM$36,65,0) -> 0 | AA10: =VLOOKUP($A10,[18]HISTOFEV23!$A$6:$AU$36,43,0) -> 0 | AB10: =VLOOKUP($A10,[18]HISTOFEV23!$A$6:$AU$36,44,0) -> 0 | AC10: =VLOOKUP($A10,[18]HISTOFEV23!$A$6:$AU$36,47,0) -> 0 | AD10: =VLOOKUP(A10,[18]HISTOFEV23!$A$6:$BB$36,54,0) -> 0 | AE10: =VLOOKUP($A10,[18]HISTOFEV23!$A$6:$CA$36,60,0) -> 0 | AF10: =VLOOKUP($A10,[18]HISTOFEV23!$A$6:$CA$36,61,0) -> 0 | AG10: =VLOOKUP($A10,[18]HISTOFEV23!$A$6:$CA$36,62,0) -> 0 | AH10: =VLOOKUP($A10,[18]HISTOFEV23!$A$6:$CA$36,63,0) -> 0 | AI10: =VLOOKUP($A10,[18]HISTOFEV23!$A$6:$CA$36,64,0) -> 0 | AJ10: =VLOOKUP($A10,[18]HISTOFEV23!$A$6:$CA$36,65,0) -> 0
A11: AS201605 | B11: =VLOOKUP(A11,[15]LISTADHERENT!A$5:H$60,3,0) -> DJOUKWE NANGUEN GUY BLAISE | E11: =VLOOKUP($A11,[18]HISTOFEV23!$A$6:$BA$36,48,0) -> 0 | F11: =MVTJANV23!F11+MVTJANV23!G11-MVTFEV23!E11+K11 -> 661165.07 | G11: 905.91826 | H11: =F11+G11 -> 662070.98 | I11: =VLOOKUP($A11,[18]HISTOFEV23!$A$6:$AQ$40,22,0) -> 0 | J11: =VLOOKUP($A11,[18]HISTOFEV23!$A$6:$AU$36,45,0) -> 15000 | K11: =IF(J11=0,0,J11-(L11+M11+N11)) -> 9000 | L11: =IF(J11=0,0,1000) -> 1000 | M11: =IF(J11=0,0,1000) -> 1000 | N11: =IF(J11=0,0,4000) -> 4000 | O11: =VLOOKUP($A11,[18]HISTOFEV23!$A$6:$AU$36,7,0) -> 0 | P11: =VLOOKUP($A11,[18]HISTOFEV23!$A$6:$AU$36,23,0) -> 0 | Q11: =VLOOKUP($A11,[18]HISTOFEV23!$A$6:$AU$36,46,0) -> 0 | R11: =VLOOKUP($A11,[18]HISTOFEV23!$A$6:$AU$36,26,0) -> 0 | S11: =VLOOKUP($A11,[18]HISTOFEV23!$A$6:$BG$36,58,0) -> 0 | T11: =VLOOKUP($A11,[18]HISTOFEV23!$A$6:$AU$36,28,0) -> 0 | U11: =VLOOKUP($A11,[18]HISTOFEV23!$A$6:$AU$36,19,0) -> 0 | V11: =VLOOKUP($A11,[18]HISTOFEV23!$A$6:$AU$36,20,0) -> 0 | W11: =VLOOKUP($A11,[18]HISTOFEV23!$A$6:$AU$36,27,0) -> 0 | X11: =VLOOKUP($A11,[18]HISTOFEV23!$A$6:$BM$36,33,0) -> 0 | Y11: =VLOOKUP($A11,[18]HISTOFEV23!$A$6:$BM$36,65,0) -> 0 | AA11: =VLOOKUP($A11,[18]HISTOFEV23!$A$6:$AU$36,43,0) -> 0 | AB11: =VLOOKUP($A11,[18]HISTOFEV23!$A$6:$AU$36,44,0) -> 0 | AC11: =VLOOKUP($A11,[18]HISTOFEV23!$A$6:$AU$36,47,0) -> 0 | AD11: =VLOOKUP(A11,[18]HISTOFEV23!$A$6:$BB$36,54,0) -> 0 | AE11: =VLOOKUP($A11,[18]HISTOFEV23!$A$6:$CA$36,60,0) -> 0 | AF11: =VLOOKUP($A11,[18]HISTOFEV23!$A$6:$CA$36,61,0) -> 0 | AG11: =VLOOKUP($A11,[18]HISTOFEV23!$A$6:$CA$36,62,0) -> 0 | AH11: =VLOOKUP($A11,[18]HISTOFEV23!$A$6:$CA$36,63,0) -> 0 | AI11: =VLOOKUP($A11,[18]HISTOFEV23!$A$6:$CA$36,64,0) -> 0 | AJ11: =VLOOKUP($A11,[18]HISTOFEV23!$A$6:$CA$36,65,0) -> 0
A12: AS201608 | B12: =VLOOKUP(A12,[15]LISTADHERENT!A$5:H$60,3,0) -> DJUOMBESSY ANTOINE | E12: =VLOOKUP($A12,[18]HISTOFEV23!$A$6:$BA$36,48,0) -> 0 | F12: =MVTJANV23!F12+MVTJANV23!G12-MVTFEV23!E12+K12 -> 677512.99 | G12: 928.31793 | H12: =F12+G12 -> 678441.31 | I12: =VLOOKUP($A12,[18]HISTOFEV23!$A$6:$AQ$40,22,0) -> 0 | J12: =VLOOKUP($A12,[18]HISTOFEV23!$A$6:$AU$36,45,0) -> 20000 | K12: =IF(J12=0,0,J12-(L12+M12+N12)) -> 14000 | L12: =IF(J12=0,0,1000) -> 1000 | M12: =IF(J12=0,0,1000) -> 1000 | N12: =IF(J12=0,0,4000) -> 4000 | O12: =VLOOKUP($A12,[18]HISTOFEV23!$A$6:$AU$36,7,0) -> 0 | P12: =VLOOKUP($A12,[18]HISTOFEV23!$A$6:$AU$36,23,0) -> 0 | Q12: =VLOOKUP($A12,[18]HISTOFEV23!$A$6:$AU$36,46,0) -> 0 | R12: =VLOOKUP($A12,[18]HISTOFEV23!$A$6:$AU$36,26,0) -> 0 | S12: =VLOOKUP($A12,[18]HISTOFEV23!$A$6:$BG$36,58,0) -> 0 | T12: =VLOOKUP($A12,[18]HISTOFEV23!$A$6:$AU$36,28,0) -> 0 | U12: =VLOOKUP($A12,[18]HISTOFEV23!$A$6:$AU$36,19,0) -> 0 | V12: =VLOOKUP($A12,[18]HISTOFEV23!$A$6:$AU$36,20,0) -> 0 | W12: =VLOOKUP($A12,[18]HISTOFEV23!$A$6:$AU$36,27,0) -> 0 | X12: =VLOOKUP($A12,[18]HISTOFEV23!$A$6:$BM$36,33,0) -> 0 | Y12: =VLOOKUP($A12,[18]HISTOFEV23!$A$6:$BM$36,65,0) -> 0 | AA12: =VLOOKUP($A12,[18]HISTOFEV23!$A$6:$AU$36,43,0) -> 0 | AB12: =VLOOKUP($A12,[18]HISTOFEV23!$A$6:$AU$36,44,0) -> 0 | AC12: =VLOOKUP($A12,[18]HISTOFEV23!$A$6:$AU$36,47,0) -> 0 | AD12: =VLOOKUP(A12,[18]HISTOFEV23!$A$6:$BB$36,54,0) -> 0 | AE12: =VLOOKUP($A12,[18]HISTOFEV23!$A$6:$CA$36,60,0) -> 0 | AF12: =VLOOKUP($A12,[18]HISTOFEV23!$A$6:$CA$36,61,0) -> 0 | AG12: =VLOOKUP($A12,[18]HISTOFEV23!$A$6:$CA$36,62,0) -> 0 | AH12: =VLOOKUP($A12,[18]HISTOFEV23!$A$6:$CA$36,63,0) -> 0 | AI12: =VLOOKUP($A12,[18]HISTOFEV23!$A$6:$CA$36,64,0) -> 0 | AJ12: =VLOOKUP($A12,[18]HISTOFEV23!$A$6:$CA$36,65,0) -> 0
A13: AS201651 | B13: =VLOOKUP(A13,[15]LISTADHERENT!A$5:H$60,3,0) -> DOMOU FABIEN | E13: =VLOOKUP($A13,[18]HISTOFEV23!$A$6:$BA$36,48,0) -> 0 | F13: =MVTJANV23!F13+MVTJANV23!G13-MVTFEV23!E13+K13 -> 656734.4 | G13: 899.84743 | H13: =F13+G13 -> 657634.25 | I13: =VLOOKUP($A13,[18]HISTOFEV23!$A$6:$AQ$40,22,0) -> 0 | J13: =VLOOKUP($A13,[18]HISTOFEV23!$A$6:$AU$36,45,0) -> 15000 | K13: =IF(J13=0,0,J13-(L13+M13+N13)) -> 9000 | L13: =IF(J13=0,0,1000) -> 1000 | M13: =IF(J13=0,0,1000) -> 1000 | N13: =IF(J13=0,0,4000) -> 4000 | O13: =VLOOKUP($A13,[18]HISTOFEV23!$A$6:$AU$36,7,0) -> 0 | P13: =VLOOKUP($A13,[18]HISTOFEV23!$A$6:$AU$36,23,0) -> 0 | Q13: =VLOOKUP($A13,[18]HISTOFEV23!$A$6:$AU$36,46,0) -> 0 | R13: =VLOOKUP($A13,[18]HISTOFEV23!$A$6:$AU$36,26,0) -> 0 | S13: =VLOOKUP($A13,[18]HISTOFEV23!$A$6:$BG$36,58,0) -> 0 | T13: =VLOOKUP($A13,[18]HISTOFEV23!$A$6:$AU$36,28,0) -> 0 | U13: =VLOOKUP($A13,[18]HISTOFEV23!$A$6:$AU$36,19,0) -> 0 | V13: =VLOOKUP($A13,[18]HISTOFEV23!$A$6:$AU$36,20,0) -> 0 | W13: =VLOOKUP($A13,[18]HISTOFEV23!$A$6:$AU$36,27,0) -> 0 | X13: =VLOOKUP($A13,[18]HISTOFEV23!$A$6:$BM$36,33,0) -> 0 | Y13: =VLOOKUP($A13,[18]HISTOFEV23!$A$6:$BM$36,65,0) -> 0 | AA13: =VLOOKUP($A13,[18]HISTOFEV23!$A$6:$AU$36,43,0) -> 0 | AB13: =VLOOKUP($A13,[18]HISTOFEV23!$A$6:$AU$36,44,0) -> 0 | AC13: =VLOOKUP($A13,[18]HISTOFEV23!$A$6:$AU$36,47,0) -> 0 | AD13: =VLOOKUP(A13,[18]HISTOFEV23!$A$6:$BB$36,54,0) -> 0 | AE13: =VLOOKUP($A13,[18]HISTOFEV23!$A$6:$CA$36,60,0) -> 0 | AF13: =VLOOKUP($A13,[18]HISTOFEV23!$A$6:$CA$36,61,0) -> 0 | AG13: =VLOOKUP($A13,[18]HISTOFEV23!$A$6:$CA$36,62,0) -> 0 | AH13: =VLOOKUP($A13,[18]HISTOFEV23!$A$6:$CA$36,63,0) -> 0 | AI13: =VLOOKUP($A13,[18]HISTOFEV23!$A$6:$CA$36,64,0) -> 0 | AJ13: =VLOOKUP($A13,[18]HISTOFEV23!$A$6:$CA$36,65,0) -> 0
A14: AS201609 | B14: =VLOOKUP(A14,[15]LISTADHERENT!A$5:H$60,3,0) -> DONHOU DAVID | E14: =VLOOKUP($A14,[18]HISTOFEV23!$A$6:$BA$36,48,0) -> 0 | F14: =MVTJANV23!F14+MVTJANV23!G14-MVTFEV23!E14+K14 -> 1143571.3 | G14: 1566.904 | H14: =F14+G14 -> 1145138.3 | I14: =VLOOKUP($A14,[18]HISTOFEV23!$A$6:$AQ$40,22,0) -> 0 | J14: =VLOOKUP($A14,[18]HISTOFEV23!$A$6:$AU$36,45,0) -> 15000 | K14: =IF(J14=0,0,J14-(L14+M14+N14)) -> 9000 | L14: =IF(J14=0,0,1000) -> 1000 | M14: =IF(J14=0,0,1000) -> 1000 | N14: =IF(J14=0,0,4000) -> 4000 | O14: =VLOOKUP($A14,[18]HISTOFEV23!$A$6:$AU$36,7,0) -> 0 | P14: =VLOOKUP($A14,[18]HISTOFEV23!$A$6:$AU$36,23,0) -> 0 | Q14: =VLOOKUP($A14,[18]HISTOFEV23!$A$6:$AU$36,46,0) -> 0 | R14: =VLOOKUP($A14,[18]HISTOFEV23!$A$6:$AU$36,26,0) -> 0 | S14: =VLOOKUP($A14,[18]HISTOFEV23!$A$6:$BG$36,58,0) -> 0 | T14: =VLOOKUP($A14,[18]HISTOFEV23!$A$6:$AU$36,28,0) -> 0 | U14: =VLOOKUP($A14,[18]HISTOFEV23!$A$6:$AU$36,19,0) -> 0 | V14: =VLOOKUP($A14,[18]HISTOFEV23!$A$6:$AU$36,20,0) -> 0 | W14: =VLOOKUP($A14,[18]HISTOFEV23!$A$6:$AU$36,27,0) -> 0 | X14: =VLOOKUP($A14,[18]HISTOFEV23!$A$6:$BM$36,33,0) -> 0 | Y14: =VLOOKUP($A14,[18]HISTOFEV23!$A$6:$BM$36,65,0) -> 0 | AA14: =VLOOKUP($A14,[18]HISTOFEV23!$A$6:$AU$36,43,0) -> 0 | AB14: =VLOOKUP($A14,[18]HISTOFEV23!$A$6:$AU$36,44,0) -> 0 | AC14: =VLOOKUP($A14,[18]HISTOFEV23!$A$6:$AU$36,47,0) -> 0 | AD14: =VLOOKUP(A14,[18]HISTOFEV23!$A$6:$BB$36,54,0) -> 0 | AE14: =VLOOKUP($A14,[18]HISTOFEV23!$A$6:$CA$36,60,0) -> 0 | AF14: =VLOOKUP($A14,[18]HISTOFEV23!$A$6:$CA$36,61,0) -> 0 | AG14: =VLOOKUP($A14,[18]HISTOFEV23!$A$6:$CA$36,62,0) -> 0 | AH14: =VLOOKUP($A14,[18]HISTOFEV23!$A$6:$CA$36,63,0) -> 0 | AI14: =VLOOKUP($A14,[18]HISTOFEV23!$A$6:$CA$36,64,0) -> 0 | AJ14: =VLOOKUP($A14,[18]HISTOFEV23!$A$6:$CA$36,65,0) -> 0
A15: AS201611 | B15: =VLOOKUP(A15,[15]LISTADHERENT!A$5:H$60,3,0) -> HENGUE PAUL OMER | E15: =VLOOKUP($A15,[18]HISTOFEV23!$A$6:$BA$36,48,0) -> 0 | F15: =MVTJANV23!F15+MVTJANV23!G15-MVTFEV23!E15+K15 -> 710472.01 | G15: 973.47788 | H15: =F15+G15 -> 711445.48 | I15: =VLOOKUP($A15,[18]HISTOFEV23!$A$6:$AQ$40,22,0) -> 0 | J15: =VLOOKUP($A15,[18]HISTOFEV23!$A$6:$AU$36,45,0) -> 15000 | K15: =IF(J15=0,0,J15-(L15+M15+N15)) -> 9000 | L15: =IF(J15=0,0,1000) -> 1000 | M15: =IF(J15=0,0,1000) -> 1000 | N15: =IF(J15=0,0,4000) -> 4000 | O15: =VLOOKUP($A15,[18]HISTOFEV23!$A$6:$AU$36,7,0) -> 0 | P15: =VLOOKUP($A15,[18]HISTOFEV23!$A$6:$AU$36,23,0) -> 0 | Q15: =VLOOKUP($A15,[18]HISTOFEV23!$A$6:$AU$36,46,0) -> 0 | R15: =VLOOKUP($A15,[18]HISTOFEV23!$A$6:$AU$36,26,0) -> 0 | S15: =VLOOKUP($A15,[18]HISTOFEV23!$A$6:$BG$36,58,0) -> 0 | T15: =VLOOKUP($A15,[18]HISTOFEV23!$A$6:$AU$36,28,0) -> 0 | U15: =VLOOKUP($A15,[18]HISTOFEV23!$A$6:$AU$36,19,0) -> 0 | V15: =VLOOKUP($A15,[18]HISTOFEV23!$A$6:$AU$36,20,0) -> 0 | W15: =VLOOKUP($A15,[18]HISTOFEV23!$A$6:$AU$36,27,0) -> 0 | X15: =VLOOKUP($A15,[18]HISTOFEV23!$A$6:$BM$36,33,0) -> 0 | Y15: =VLOOKUP($A15,[18]HISTOFEV23!$A$6:$BM$36,65,0) -> 0 | AA15: =VLOOKUP($A15,[18]HISTOFEV23!$A$6:$AU$36,43,0) -> 0 | AB15: =VLOOKUP($A15,[18]HISTOFEV23!$A$6:$AU$36,44,0) -> 0 | AC15: =VLOOKUP($A15,[18]HISTOFEV23!$A$6:$AU$36,47,0) -> 0 | AD15: =VLOOKUP(A15,[18]HISTOFEV23!$A$6:$BB$36,54,0) -> 0 | AE15: =VLOOKUP($A15,[18]HISTOFEV23!$A$6:$CA$36,60,0) -> 0 | AF15: =VLOOKUP($A15,[18]HISTOFEV23!$A$6:$CA$36,61,0) -> 0 | AG15: =VLOOKUP($A15,[18]HISTOFEV23!$A$6:$CA$36,62,0) -> 0 | AH15: =VLOOKUP($A15,[18]HISTOFEV23!$A$6:$CA$36,63,0) -> 0 | AI15: =VLOOKUP($A15,[18]HISTOFEV23!$A$6:$CA$36,64,0) -> 0 | AJ15: =VLOOKUP($A15,[18]HISTOFEV23!$A$6:$CA$36,65,0) -> 0
A16: AS201613 | B16: =VLOOKUP(A16,[15]LISTADHERENT!A$5:H$60,3,0) -> HOTCHO BENJAMIN | E16: =VLOOKUP($A16,[18]HISTOFEV23!$A$6:$BA$36,48,0) -> 0 | F16: =MVTJANV23!F16+MVTJANV23!G16-MVTFEV23!E16+K16 -> 743373.76 | G16: 1018.5594 | H16: =F16+G16 -> 744392.31 | I16: =VLOOKUP($A16,[18]HISTOFEV23!$A$6:$AQ$40,22,0) -> 0 | J16: =VLOOKUP($A16,[18]HISTOFEV23!$A$6:$AU$36,45,0) -> 50000 | K16: =IF(J16=0,0,J16-(L16+M16+N16)) -> 44000 | L16: =IF(J16=0,0,1000) -> 1000 | M16: =IF(J16=0,0,1000) -> 1000 | N16: =IF(J16=0,0,4000) -> 4000 | O16: =VLOOKUP($A16,[18]HISTOFEV23!$A$6:$AU$36,7,0) -> 0 | P16: =VLOOKUP($A16,[18]HISTOFEV23!$A$6:$AU$36,23,0) -> 0 | Q16: =VLOOKUP($A16,[18]HISTOFEV23!$A$6:$AU$36,46,0) -> 0 | R16: =VLOOKUP($A16,[18]HISTOFEV23!$A$6:$AU$36,26,0) -> 0 | S16: =VLOOKUP($A16,[18]HISTOFEV23!$A$6:$BG$36,58,0) -> 0 | T16: =VLOOKUP($A16,[18]HISTOFEV23!$A$6:$AU$36,28,0) -> 0 | U16: =VLOOKUP($A16,[18]HISTOFEV23!$A$6:$AU$36,19,0) -> 1000000 | V16: =VLOOKUP($A16,[18]HISTOFEV23!$A$6:$AU$36,20,0) -> BANQUE | W16: =VLOOKUP($A16,[18]HISTOFEV23!$A$6:$AU$36,27,0) -> 0 | X16: =VLOOKUP($A16,[18]HISTOFEV23!$A$6:$BM$36,33,0) -> 0 | Y16: =VLOOKUP($A16,[18]HISTOFEV23!$A$6:$BM$36,65,0) -> 0 | AA16: =VLOOKUP($A16,[18]HISTOFEV23!$A$6:$AU$36,43,0) -> 0 | AB16: =VLOOKUP($A16,[18]HISTOFEV23!$A$6:$AU$36,44,0) -> 0 | AC16: =VLOOKUP($A16,[18]HISTOFEV23!$A$6:$AU$36,47,0) -> 0 | AD16: =VLOOKUP(A16,[18]HISTOFEV23!$A$6:$BB$36,54,0) -> 0 | AE16: =VLOOKUP($A16,[18]HISTOFEV23!$A$6:$CA$36,60,0) -> 0 | AF16: =VLOOKUP($A16,[18]HISTOFEV23!$A$6:$CA$36,61,0) -> 0 | AG16: =VLOOKUP($A16,[18]HISTOFEV23!$A$6:$CA$36,62,0) -> 0 | AH16: =VLOOKUP($A16,[18]HISTOFEV23!$A$6:$CA$36,63,0) -> 0 | AI16: =VLOOKUP($A16,[18]HISTOFEV23!$A$6:$CA$36,64,0) -> 0 | AJ16: =VLOOKUP($A16,[18]HISTOFEV23!$A$6:$CA$36,65,0) -> 0
A17: AS201617 | B17: =VLOOKUP(A17,[15]LISTADHERENT!A$5:H$60,3,0) -> KOUAMOU MOISE | E17: =VLOOKUP($A17,[18]HISTOFEV23!$A$6:$BA$36,48,0) -> 0 | F17: =MVTJANV23!F17+MVTJANV23!G17-MVTFEV23!E17+K17 -> 712791.36 | G17: 976.65582 | H17: =F17+G17 -> 713768.01 | I17: =VLOOKUP($A17,[18]HISTOFEV23!$A$6:$AQ$40,22,0) -> 0 | J17: =VLOOKUP($A17,[18]HISTOFEV23!$A$6:$AU$36,45,0) -> 15000 | K17: =IF(J17=0,0,J17-(L17+M17+N17)) -> 9000 | L17: =IF(J17=0,0,1000) -> 1000 | M17: =IF(J17=0,0,1000) -> 1000 | N17: =IF(J17=0,0,4000) -> 4000 | O17: =VLOOKUP($A17,[18]HISTOFEV23!$A$6:$AU$36,7,0) -> 0 | P17: =VLOOKUP($A17,[18]HISTOFEV23!$A$6:$AU$36,23,0) -> 0 | Q17: =VLOOKUP($A17,[18]HISTOFEV23!$A$6:$AU$36,46,0) -> 0 | R17: =VLOOKUP($A17,[18]HISTOFEV23!$A$6:$AU$36,26,0) -> 0 | S17: =VLOOKUP($A17,[18]HISTOFEV23!$A$6:$BG$36,58,0) -> 0 | T17: =VLOOKUP($A17,[18]HISTOFEV23!$A$6:$AU$36,28,0) -> 0 | U17: =VLOOKUP($A17,[18]HISTOFEV23!$A$6:$AU$36,19,0) -> 0 | V17: =VLOOKUP($A17,[18]HISTOFEV23!$A$6:$AU$36,20,0) -> 0 | W17: =VLOOKUP($A17,[18]HISTOFEV23!$A$6:$AU$36,27,0) -> 0 | X17: =VLOOKUP($A17,[18]HISTOFEV23!$A$6:$BM$36,33,0) -> 0 | Y17: =VLOOKUP($A17,[18]HISTOFEV23!$A$6:$BM$36,65,0) -> 0 | AA17: =VLOOKUP($A17,[18]HISTOFEV23!$A$6:$AU$36,43,0) -> 0 | AB17: =VLOOKUP($A17,[18]HISTOFEV23!$A$6:$AU$36,44,0) -> 0 | AC17: =VLOOKUP($A17,[18]HISTOFEV23!$A$6:$AU$36,47,0) -> 0 | AD17: =VLOOKUP(A17,[18]HISTOFEV23!$A$6:$BB$36,54,0) -> 70000 | AE17: =VLOOKUP($A17,[18]HISTOFEV23!$A$6:$CA$36,60,0) -> 0 | AF17: =VLOOKUP($A17,[18]HISTOFEV23!$A$6:$CA$36,61,0) -> 0 | AG17: =VLOOKUP($A17,[18]HISTOFEV23!$A$6:$CA$36,62,0) -> 0 | AH17: =VLOOKUP($A17,[18]HISTOFEV23!$A$6:$CA$36,63,0) -> 0 | AI17: =VLOOKUP($A17,[18]HISTOFEV23!$A$6:$CA$36,64,0) -> 0 | AJ17: =VLOOKUP($A17,[18]HISTOFEV23!$A$6:$CA$36,65,0) -> 0
A18: AS201619 | B18: =VLOOKUP(A18,[15]LISTADHERENT!A$5:H$60,3,0) -> KOUATCHO MESSACK | E18: =VLOOKUP($A18,[18]HISTOFEV23!$A$6:$BA$36,48,0) -> 0 | F18: =MVTJANV23!F18+MVTJANV23!G18-MVTFEV23!E18+K18 -> 662982.59 | G18: 908.4086 | H18: =F18+G18 -> 663891 | I18: =VLOOKUP($A18,[18]HISTOFEV23!$A$6:$AQ$40,22,0) -> 0 | J18: =VLOOKUP($A18,[18]HISTOFEV23!$A$6:$AU$36,45,0) -> 15000 | K18: =IF(J18=0,0,J18-(L18+M18+N18)) -> 9000 | L18: =IF(J18=0,0,1000) -> 1000 | M18: =IF(J18=0,0,1000) -> 1000 | N18: =IF(J18=0,0,4000) -> 4000 | O18: =VLOOKUP($A18,[18]HISTOFEV23!$A$6:$AU$36,7,0) -> 0 | P18: =VLOOKUP($A18,[18]HISTOFEV23!$A$6:$AU$36,23,0) -> 0 | Q18: =VLOOKUP($A18,[18]HISTOFEV23!$A$6:$AU$36,46,0) -> 0 | R18: =VLOOKUP($A18,[18]HISTOFEV23!$A$6:$AU$36,26,0) -> 0 | S18: =VLOOKUP($A18,[18]HISTOFEV23!$A$6:$BG$36,58,0) -> 0 | T18: =VLOOKUP($A18,[18]HISTOFEV23!$A$6:$AU$36,28,0) -> 0 | U18: =VLOOKUP($A18,[18]HISTOFEV23!$A$6:$AU$36,19,0) -> 0 | V18: =VLOOKUP($A18,[18]HISTOFEV23!$A$6:$AU$36,20,0) -> 0 | W18: =VLOOKUP($A18,[18]HISTOFEV23!$A$6:$AU$36,27,0) -> 0 | X18: =VLOOKUP($A18,[18]HISTOFEV23!$A$6:$BM$36,33,0) -> 0 | Y18: =VLOOKUP($A18,[18]HISTOFEV23!$A$6:$BM$36,65,0) -> 0 | AA18: =VLOOKUP($A18,[18]HISTOFEV23!$A$6:$AU$36,43,0) -> 0 | AB18: =VLOOKUP($A18,[18]HISTOFEV23!$A$6:$AU$36,44,0) -> 0 | AC18: =VLOOKUP($A18,[18]HISTOFEV23!$A$6:$AU$36,47,0) -> 0 | AD18: =VLOOKUP(A18,[18]HISTOFEV23!$A$6:$BB$36,54,0) -> 0 | AE18: =VLOOKUP($A18,[18]HISTOFEV23!$A$6:$CA$36,60,0) -> 0 | AF18: =VLOOKUP($A18,[18]HISTOFEV23!$A$6:$CA$36,61,0) -> 0 | AG18: =VLOOKUP($A18,[18]HISTOFEV23!$A$6:$CA$36,62,0) -> 0 | AH18: =VLOOKUP($A18,[18]HISTOFEV23!$A$6:$CA$36,63,0) -> 0 | AI18: =VLOOKUP($A18,[18]HISTOFEV23!$A$6:$CA$36,64,0) -> 0 | AJ18: =VLOOKUP($A18,[18]HISTOFEV23!$A$6:$CA$36,65,0) -> 0
... A36: AS201647 | B36: =VLOOKUP(A36,[15]LISTADHERENT!A$5:H$60,3,0) -> YOUMBI EMMANUEL | E36: =VLOOKUP($A36,[18]HISTOFEV23!$A$6:$BA$36,48,0) -> 0 | F36: =MVTJANV23!F36+MVTJANV23!G36-MVTFEV23!E36+K36 -> 1781079.5 | G36: 2440.4079 | H36: =F36+G36 -> 1783519.9 | I36: =VLOOKUP($A36,[18]HISTOFEV23!$A$6:$AQ$40,22,0) -> 0 | J36: =VLOOKUP($A36,[18]HISTOFEV23!$A$6:$AU$36,45,0) -> 15000 | K36: =IF(J36=0,0,J36-(L36+M36+N36)) -> 9000 | L36: =IF(J36=0,0,1000) -> 1000 | M36: =IF(J36=0,0,1000) -> 1000 | N36: =IF(J36=0,0,4000) -> 4000 | O36: =VLOOKUP($A36,[18]HISTOFEV23!$A$6:$AU$36,7,0) -> 0 | P36: =VLOOKUP($A36,[18]HISTOFEV23!$A$6:$AU$36,23,0) -> 0 | Q36: =VLOOKUP($A36,[18]HISTOFEV23!$A$6:$AU$36,46,0) -> 0 | R36: =VLOOKUP($A36,[18]HISTOFEV23!$A$6:$AU$36,26,0) -> 0 | S36: =VLOOKUP($A36,[18]HISTOFEV23!$A$6:$BG$36,58,0) -> 0 | T36: =VLOOKUP($A36,[18]HISTOFEV23!$A$6:$AU$36,28,0) -> 0 | U36: =VLOOKUP($A36,[18]HISTOFEV23!$A$6:$AU$36,19,0) -> 0 | V36: =VLOOKUP($A36,[18]HISTOFEV23!$A$6:$AU$36,20,0) -> 0 | W36: =VLOOKUP($A36,[18]HISTOFEV23!$A$6:$AU$36,27,0) -> 0 | X36: =VLOOKUP($A36,[18]HISTOFEV23!$A$6:$BM$36,33,0) -> 0 | Y36: =VLOOKUP($A36,[18]HISTOFEV23!$A$6:$BM$36,65,0) -> 0 | AA36: =VLOOKUP($A36,[18]HISTOFEV23!$A$6:$AU$36,43,0) -> 0 | AB36: =VLOOKUP($A36,[18]HISTOFEV23!$A$6:$AU$36,44,0) -> 0 | AC36: =VLOOKUP($A36,[18]HISTOFEV23!$A$6:$AU$36,47,0) -> 0 | AD36: =VLOOKUP(A36,[18]HISTOFEV23!$A$6:$BB$36,54,0) -> 0 | AE36: =VLOOKUP($A36,[18]HISTOFEV23!$A$6:$CA$36,60,0) -> 0 | AF36: =VLOOKUP($A36,[18]HISTOFEV23!$A$6:$CA$36,61,0) -> 0 | AG36: =VLOOKUP($A36,[18]HISTOFEV23!$A$6:$CA$36,62,0) -> 0 | AH36: =VLOOKUP($A36,[18]HISTOFEV23!$A$6:$CA$36,63,0) -> 0 | AI36: =VLOOKUP($A36,[18]HISTOFEV23!$A$6:$CA$36,64,0) -> 0 | AJ36: =VLOOKUP($A36,[18]HISTOFEV23!$A$6:$CA$36,65,0) -> 0
A40: TOTAL | C40: =SUM(C6:C39) -> 0 | D40: =SUM(D6:D39) -> 0 | E40: =SUM(E6:E39) -> 0 | F40: =SUM(F6:F39) -> 21966858 | G40: =SUM(G6:G39) -> 30000 | H40: =SUM(H6:H39) -> 21996858 | I40: =SUM(I6:I39) -> 0 | J40: =SUM(J6:J39) -> 508000 | ... AJ40: =SUM(AJ6:AJ39) -> 200000

Sheet MVTMARS23
A1: ASSOCIATION | B1: ASELBY | G1: K
A2: ANNEE | B2: 2023
A3: TONTINE
J4: 45002
A5: MATRICULE | B5: NOM ET PRENOM | C5: FONDES DE DEPART | D5: RECONDUCTION | E5: RETRAIT PARTIEL | F5: FONDS DEFINITIF | G5: REPARTITION INTERET | H5: CAPITAL COMPOSE | I5: SANCTION | J5: RESTE | K5: EPARGNE | L5: FONDS DE ROULEMENT | M5: FRAIS EXCEPTIONNEL | N5: COLLATION | O5: PENALITE VST ESPECES | P5: INSCRISPTION | Q5: MUTUELLE | R5: PRÊT FONDS | S5: INTERETPRET FONDS | T5: NUMERO CHEQUE | U5: REMBOURSEMENTPRET FONDS | V5: MODE VERSEMENT REMBOURSEMENT | W5: MODE VERSEMENT PRÊT | X5: NUMERO CHEQUE | Y5: PENALITE PRET FONDS | Z5: PENALITE FONDS | AA5: PENALITE ECHEC TONTINE | AB5: PENALITE RETARD TONTINE | AC5: REMBOURSEMENT TRANSPORT | AD5: CONTRIBUTION FOYER | AE5: FONDS DE ROULEMENT | AF5: FRAIS EXCEPTIONNEL | AG5: FONDS MUTUELLE | AH5: COLLATION RECEPTION | AI5: PENALITE PRET FONDS | AJ5: DEPENSE PENALITE VERSEMENT BANQUE
A6: AS201648 | B6: =VLOOKUP(A6,[15]LISTADHERENT!A$5:H$60,3,0) -> ASELBY | F6: =MVTFEV23!F6+MVTFEV23!G6-MVTMARS23!E6+K6 -> 869601.96 | G6: 235.14557 | H6: =F6+G6 -> 869837.1 | AE6: =VLOOKUP($A6,[18]HISTOMARS23!$A$6:$CA$36,60,0) -> 6000 | AF6: =VLOOKUP($A6,[18]HISTOMARS23!$A$6:$CA$36,61,0) -> 0 | AG6: =VLOOKUP($A6,[18]HISTOMARS23!$A$6:$CA$36,62,0) -> 0 | AH6: =VLOOKUP($A6,[18]HISTOMARS23!$A$6:$CA$36,63,0) -> 100000 | AI6: =VLOOKUP($A6,[18]HISTOMARS23!$A$6:$CA$36,64,0) -> 0 | AJ6: =VLOOKUP($A6,[18]HISTOMARS23!$A$6:$CA$36,65,0) -> 0
A7: AS201601 | B7: =VLOOKUP(A7,[15]LISTADHERENT!A$5:H$60,3,0) -> BAKOP ACHILLE | E7: =VLOOKUP($A7,[18]HISTOMARS23!$A$6:$BA$36,48,0) -> 0 | F7: =MVTFEV23!F7+MVTFEV23!G7-MVTMARS23!E7+K7 -> 627846.77 | G7: 169.77352 | H7: =F7+G7 -> 628016.55 | I7: =VLOOKUP($A7,[18]HISTOMARS23!$A$6:$AQ$40,22,0) -> 0 | J7: =VLOOKUP($A7,[18]HISTOMARS23!$A$6:$AU$36,45,0) -> 15000 | K7: =IF(J7=0,0,J7-(L7+M7+N7)) -> 9000 | L7: =IF(J7=0,0,1000) -> 1000 | M7: =IF(J7=0,0,1000) -> 1000 | N7: =IF(J7=0,0,4000) -> 4000 | O7: =VLOOKUP($A7,[18]HISTOMARS23!$A$6:$AU$36,7,0) -> 0 | P7: =VLOOKUP($A7,[18]HISTOMARS23!$A$6:$AU$36,23,0) -> 0 | Q7: =VLOOKUP($A7,[18]HISTOMARS23!$A$6:$AU$36,46,0) -> 0 | R7: =VLOOKUP($A7,[18]HISTOMARS23!$A$6:$AU$36,26,0) -> 0 | S7: =VLOOKUP($A7,[18]HISTOMARS23!$A$6:$BG$36,58,0) -> 0 | T7: =VLOOKUP($A7,[18]HISTOMARS23!$A$6:$AU$36,28,0) -> 0 | U7: =VLOOKUP($A7,[18]HISTOMARS23!$A$6:$AU$36,19,0) -> 0 | V7: =VLOOKUP($A7,[18]HISTOMARS23!$A$6:$AU$36,20,0) -> 0 | W7: =VLOOKUP($A7,[18]HISTOMARS23!$A$6:$AU$36,27,0) -> 0 | X7: =VLOOKUP($A7,[18]HISTOMARS23!$A$6:$BM$36,33,0) -> 0 | Y7: =VLOOKUP($A7,[18]HISTOMARS23!$A$6:$BM$36,65,0) -> 0 | AA7: =VLOOKUP($A7,[18]HISTOMARS23!$A$6:$AU$36,43,0) -> 0 | AB7: =VLOOKUP($A7,[18]HISTOMARS23!$A$6:$AU$36,44,0) -> 0 | AC7: =VLOOKUP($A7,[18]HISTOMARS23!$A$6:$AU$36,47,0) -> 0 | AD7: =VLOOKUP(A7,[18]HISTOMARS23!$A$6:$BB$36,54,0) -> 0 | AE7: =VLOOKUP($A7,[18]HISTOMARS23!$A$6:$CA$36,60,0) -> 0 | AF7: =VLOOKUP($A7,[18]HISTOMARS23!$A$6:$CA$36,61,0) -> 0 | AG7: =VLOOKUP($A7,[18]HISTOMARS23!$A$6:$CA$36,62,0) -> 0 | AH7: =VLOOKUP($A7,[18]HISTOMARS23!$A$6:$CA$36,63,0) -> 0 | AI7: =VLOOKUP($A7,[18]HISTOMARS23!$A$6:$CA$36,64,0) -> 0 | AJ7: =VLOOKUP($A7,[18]HISTOMARS23!$A$6:$CA$36,65,0) -> 0
A8: AS201602 | B8: =VLOOKUP(A8,[15]LISTADHERENT!A$5:H$60,3,0) -> BOUTCHOUANG WILLIAM | E8: =VLOOKUP($A8,[18]HISTOMARS23!$A$6:$BA$36,48,0) -> 0 | F8: =MVTFEV23!F8+MVTFEV23!G8-MVTMARS23!E8+K8 -> 673492.3 | G8: 182.11635 | H8: =F8+G8 -> 673674.42 | I8: =VLOOKUP($A8,[18]HISTOMARS23!$A$6:$AQ$40,22,0) -> 0 | J8: =VLOOKUP($A8,[18]HISTOMARS23!$A$6:$AU$36,45,0) -> 15000 | K8: =IF(J8=0,0,J8-(L8+M8+N8)) -> 9000 | L8: =IF(J8=0,0,1000) -> 1000 | M8: =IF(J8=0,0,1000) -> 1000 | N8: =IF(J8=0,0,4000) -> 4000 | O8: =VLOOKUP($A8,[18]HISTOMARS23!$A$6:$AU$36,7,0) -> 0 | P8: =VLOOKUP($A8,[18]HISTOMARS23!$A$6:$AU$36,23,0) -> 0 | Q8: =VLOOKUP($A8,[18]HISTOMARS23!$A$6:$AU$36,46,0) -> 0 | R8: =VLOOKUP($A8,[18]HISTOMARS23!$A$6:$AU$36,26,0) -> 0 | S8: =VLOOKUP($A8,[18]HISTOMARS23!$A$6:$BG$36,58,0) -> 0 | T8: =VLOOKUP($A8,[18]HISTOMARS23!$A$6:$AU$36,28,0) -> 0 | U8: =VLOOKUP($A8,[18]HISTOMARS23!$A$6:$AU$36,19,0) -> 0 | V8: =VLOOKUP($A8,[18]HISTOMARS23!$A$6:$AU$36,20,0) -> 0 | W8: =VLOOKUP($A8,[18]HISTOMARS23!$A$6:$AU$36,27,0) -> 0 | X8: =VLOOKUP($A8,[18]HISTOMARS23!$A$6:$BM$36,33,0) -> 0 | Y8: =VLOOKUP($A8,[18]HISTOMARS23!$A$6:$BM$36,65,0) -> 0 | AA8: =VLOOKUP($A8,[18]HISTOMARS23!$A$6:$AU$36,43,0) -> 0 | AB8: =VLOOKUP($A8,[18]HISTOMARS23!$A$6:$AU$36,44,0) -> 0 | AC8: =VLOOKUP($A8,[18]HISTOMARS23!$A$6:$AU$36,47,0) -> 0 | AD8: =VLOOKUP(A8,[18]HISTOMARS23!$A$6:$BB$36,54,0) -> 0 | AE8: =VLOOKUP($A8,[18]HISTOMARS23!$A$6:$CA$36,60,0) -> 0 | AF8: =VLOOKUP($A8,[18]HISTOMARS23!$A$6:$CA$36,61,0) -> 0 | AG8: =VLOOKUP($A8,[18]HISTOMARS23!$A$6:$CA$36,62,0) -> 0 | AH8: =VLOOKUP($A8,[18]HISTOMARS23!$A$6:$CA$36,63,0) -> 0 | AI8: =VLOOKUP($A8,[18]HISTOMARS23!$A$6:$CA$36,64,0) -> 0 | AJ8: =VLOOKUP($A8,[18]HISTOMARS23!$A$6:$CA$36,65,0) -> 0
A9: AS201604 | B9: =VLOOKUP(A9,[15]LISTADHERENT!A$5:H$60,3,0) -> DJOMO JEAN PAUL | E9: =VLOOKUP($A9,[18]HISTOMARS23!$A$6:$BA$36,48,0) -> 0 | F9: =MVTFEV23!F9+MVTFEV23!G9-MVTMARS23!E9+K9 -> 699172.96 | G9: 189.06055 | H9: =F9+G9 -> 699362.02 | I9: =VLOOKUP($A9,[18]HISTOMARS23!$A$6:$AQ$40,22,0) -> 0 | J9: =VLOOKUP($A9,[18]HISTOMARS23!$A$6:$AU$36,45,0) -> 15000 | K9: =IF(J9=0,0,J9-(L9+M9+N9)) -> 9000 | L9: =IF(J9=0,0,1000) -> 1000 | M9: =IF(J9=0,0,1000) -> 1000 | N9: =IF(J9=0,0,4000) -> 4000 | O9: =VLOOKUP($A9,[18]HISTOMARS23!$A$6:$AU$36,7,0) -> 0 | P9: =VLOOKUP($A9,[18]HISTOMARS23!$A$6:$AU$36,23,0) -> 0 | Q9: =VLOOKUP($A9,[18]HISTOMARS23!$A$6:$AU$36,46,0) -> 0 | R9: =VLOOKUP($A9,[18]HISTOMARS23!$A$6:$AU$36,26,0) -> 0 | S9: =VLOOKUP($A9,[18]HISTOMARS23!$A$6:$BG$36,58,0) -> 0 | T9: =VLOOKUP($A9,[18]HISTOMARS23!$A$6:$AU$36,28,0) -> 0 | U9: =VLOOKUP($A9,[18]HISTOMARS23!$A$6:$AU$36,19,0) -> 690000 | V9: =VLOOKUP($A9,[18]HISTOMARS23!$A$6:$AU$36,20,0) -> BANQUE | W9: =VLOOKUP($A9,[18]HISTOMARS23!$A$6:$AU$36,27,0) -> 0 | X9: =VLOOKUP($A9,[18]HISTOMARS23!$A$6:$BM$36,33,0) -> 0 | Y9: =VLOOKUP($A9,[18]HISTOMARS23!$A$6:$BM$36,65,0) -> 0 | AA9: =VLOOKUP($A9,[18]HISTOMARS23!$A$6:$AU$36,43,0) -> 0 | AB9: =VLOOKUP($A9,[18]HISTOMARS23!$A$6:$AU$36,44,0) -> 0 | AC9: =VLOOKUP($A9,[18]HISTOMARS23!$A$6:$AU$36,47,0) -> 0 | AD9: =VLOOKUP(A9,[18]HISTOMARS23!$A$6:$BB$36,54,0) -> 0 | AE9: =VLOOKUP($A9,[18]HISTOMARS23!$A$6:$CA$36,60,0) -> 0 | AF9: =VLOOKUP($A9,[18]HISTOMARS23!$A$6:$CA$36,61,0) -> 0 | AG9: =VLOOKUP($A9,[18]HISTOMARS23!$A$6:$CA$36,62,0) -> 0 | AH9: =VLOOKUP($A9,[18]HISTOMARS23!$A$6:$CA$36,63,0) -> 0 | AI9: =VLOOKUP($A9,[18]HISTOMARS23!$A$6:$CA$36,64,0) -> 0 | AJ9: =VLOOKUP($A9,[18]HISTOMARS23!$A$6:$CA$36,65,0) -> 0
A10: AS201654 | B10: =VLOOKUP(A10,[15]LISTADHERENT!A$5:H$60,3,0) -> DJOMOU TCHAPDA | E10: =VLOOKUP($A10,[18]HISTOMARS23!$A$6:$BA$36,48,0) -> 0 | F10: =MVTFEV23!F10+MVTFEV23!G10-MVTMARS23!E10+K10 -> 718887.83 | G10: 194.39157 | H10: =F10+G10 -> 719082.22 | I10: =VLOOKUP($A10,[18]HISTOMARS23!$A$6:$AQ$40,22,0) -> 0 | J10: =VLOOKUP($A10,[18]HISTOMARS23!$A$6:$AU$36,45,0) -> 16000 | K10: =IF(J10=0,0,J10-(L10+M10+N10)) -> 10000 | L10: =IF(J10=0,0,1000) -> 1000 | M10: =IF(J10=0,0,1000) -> 1000 | N10: =IF(J10=0,0,4000) -> 4000 | O10: =VLOOKUP($A10,[18]HISTOMARS23!$A$6:$AU$36,7,0) -> 0 | P10: =VLOOKUP($A10,[18]HISTOMARS23!$A$6:$AU$36,23,0) -> 0 | Q10: =VLOOKUP($A10,[18]HISTOMARS23!$A$6:$AU$36,46,0) -> 0 | R10: =VLOOKUP($A10,[18]HISTOMARS23!$A$6:$AU$36,26,0) -> 0 | S10: =VLOOKUP($A10,[18]HISTOMARS23!$A$6:$BG$36,58,0) -> 0 | T10: =VLOOKUP($A10,[18]HISTOMARS23!$A$6:$AU$36,28,0) -> 0 | U10: =VLOOKUP($A10,[18]HISTOMARS23!$A$6:$AU$36,19,0) -> 0 | V10: =VLOOKUP($A10,[18]HISTOMARS23!$A$6:$AU$36,20,0) -> 0 | W10: =VLOOKUP($A10,[18]HISTOMARS23!$A$6:$AU$36,27,0) -> 0 | X10: =VLOOKUP($A10,[18]HISTOMARS23!$A$6:$BM$36,33,0) -> 0 | Y10: =VLOOKUP($A10,[18]HISTOMARS23!$A$6:$BM$36,65,0) -> 0 | AA10: =VLOOKUP($A10,[18]HISTOMARS23!$A$6:$AU$36,43,0) -> 0 | AB10: =VLOOKUP($A10,[18]HISTOMARS23!$A$6:$AU$36,44,0) -> 0 | AC10: =VLOOKUP($A10,[18]HISTOMARS23!$A$6:$AU$36,47,0) -> 0 | AD10: =VLOOKUP(A10,[18]HISTOMARS23!$A$6:$BB$36,54,0) -> 0 | AE10: =VLOOKUP($A10,[18]HISTOMARS23!$A$6:$CA$36,60,0) -> 0 | AF10: =VLOOKUP($A10,[18]HISTOMARS23!$A$6:$CA$36,61,0) -> 0 | AG10: =VLOOKUP($A10,[18]HISTOMARS23!$A$6:$CA$36,62,0) -> 0 | AH10: =VLOOKUP($A10,[18]HISTOMARS23!$A$6:$CA$36,63,0) -> 0 | AI10: =VLOOKUP($A10,[18]HISTOMARS23!$A$6:$CA$36,64,0) -> 0 | AJ10: =VLOOKUP($A10,[18]HISTOMARS23!$A$6:$CA$36,65,0) -> 0
A11: AS201605 | B11: =VLOOKUP(A11,[15]LISTADHERENT!A$5:H$60,3,0) -> DJOUKWE NANGUEN GUY BLAISE | E11: =VLOOKUP($A11,[18]HISTOMARS23!$A$6:$BA$36,48,0) -> 0 | F11: =MVTFEV23!F11+MVTFEV23!G11-MVTMARS23!E11+K11 -> 676070.98 | G11: 182.81364 | H11: =F11+G11 -> 676253.8 | I11: =VLOOKUP($A11,[18]HISTOMARS23!$A$6:$AQ$40,22,0) -> 0 | J11: =VLOOKUP($A11,[18]HISTOMARS23!$A$6:$AU$36,45,0) -> 20000 | K11: =IF(J11=0,0,J11-(L11+M11+N11)) -> 14000 | L11: =IF(J11=0,0,1000) -> 1000 | M11: =IF(J11=0,0,1000) -> 1000 | N11: =IF(J11=0,0,4000) -> 4000 | O11: =VLOOKUP($A11,[18]HISTOMARS23!$A$6:$AU$36,7,0) -> 0 | P11: =VLOOKUP($A11,[18]HISTOMARS23!$A$6:$AU$36,23,0) -> 0 | Q11: =VLOOKUP($A11,[18]HISTOMARS23!$A$6:$AU$36,46,0) -> 0 | R11: =VLOOKUP($A11,[18]HISTOMARS23!$A$6:$AU$36,26,0) -> 0 | S11: =VLOOKUP($A11,[18]HISTOMARS23!$A$6:$BG$36,58,0) -> 0 | T11: =VLOOKUP($A11,[18]HISTOMARS23!$A$6:$AU$36,28,0) -> 0 | U11: =VLOOKUP($A11,[18]HISTOMARS23!$A$6:$AU$36,19,0) -> 892500 | V11: =VLOOKUP($A11,[18]HISTOMARS23!$A$6:$AU$36,20,0) -> BANQUE | W11: =VLOOKUP($A11,[18]HISTOMARS23!$A$6:$AU$36,27,0) -> 0 | X11: =VLOOKUP($A11,[18]HISTOMARS23!$A$6:$BM$36,33,0) -> 0 | Y11: =VLOOKUP($A11,[18]HISTOMARS23!$A$6:$BM$36,65,0) -> 0 | AA11: =VLOOKUP($A11,[18]HISTOMARS23!$A$6:$AU$36,43,0) -> 0 | AB11: =VLOOKUP($A11,[18]HISTOMARS23!$A$6:$AU$36,44,0) -> 0 | AC11: =VLOOKUP($A11,[18]HISTOMARS23!$A$6:$AU$36,47,0) -> 0 | AD11: =VLOOKUP(A11,[18]HISTOMARS23!$A$6:$BB$36,54,0) -> 0 | AE11: =VLOOKUP($A11,[18]HISTOMARS23!$A$6:$CA$36,60,0) -> 0 | AF11: =VLOOKUP($A11,[18]HISTOMARS23!$A$6:$CA$36,61,0) -> 0 | AG11: =VLOOKUP($A11,[18]HISTOMARS23!$A$6:$CA$36,62,0) -> 0 | AH11: =VLOOKUP($A11,[18]HISTOMARS23!$A$6:$CA$36,63,0) -> 0 | AI11: =VLOOKUP($A11,[18]HISTOMARS23!$A$6:$CA$36,64,0) -> 0 | AJ11: =VLOOKUP($A11,[18]HISTOMARS23!$A$6:$CA$36,65,0) -> 0
A12: AS201608 | B12: =VLOOKUP(A12,[15]LISTADHERENT!A$5:H$60,3,0) -> DJUOMBESSY ANTOINE | E12: =VLOOKUP($A12,[18]HISTOMARS23!$A$6:$BA$36,48,0) -> 0 | F12: =MVTFEV23!F12+MVTFEV23!G12-MVTMARS23!E12+K12 -> 692441.31 | G12: 187.24027 | H12: =F12+G12 -> 692628.55 | I12: =VLOOKUP($A12,[18]HISTOMARS23!$A$6:$AQ$40,22,0) -> 0 | J12: =VLOOKUP($A12,[18]HISTOMARS23!$A$6:$AU$36,45,0) -> 20000 | K12: =IF(J12=0,0,J12-(L12+M12+N12)) -> 14000 | L12: =IF(J12=0,0,1000) -> 1000 | M12: =IF(J12=0,0,1000) -> 1000 | N12: =IF(J12=0,0,4000) -> 4000 | O12: =VLOOKUP($A12,[18]HISTOMARS23!$A$6:$AU$36,7,0) -> 0 | P12: =VLOOKUP($A12,[18]HISTOMARS23!$A$6:$AU$36,23,0) -> 0 | Q12: =VLOOKUP($A12,[18]HISTOMARS23!$A$6:$AU$36,46,0) -> 0 | R12: =VLOOKUP($A12,[18]HISTOMARS23!$A$6:$AU$36,26,0) -> 0 | S12: =VLOOKUP($A12,[18]HISTOMARS23!$A$6:$BG$36,58,0) -> 0 | T12: =VLOOKUP($A12,[18]HISTOMARS23!$A$6:$AU$36,28,0) -> 0 | U12: =VLOOKUP($A12,[18]HISTOMARS23!$A$6:$AU$36,19,0) -> 0 | V12: =VLOOKUP($A12,[18]HISTOMARS23!$A$6:$AU$36,20,0) -> 0 | W12: =VLOOKUP($A12,[18]HISTOMARS23!$A$6:$AU$36,27,0) -> 0 | X12: =VLOOKUP($A12,[18]HISTOMARS23!$A$6:$BM$36,33,0) -> 0 | Y12: =VLOOKUP($A12,[18]HISTOMARS23!$A$6:$BM$36,65,0) -> 0 | AA12: =VLOOKUP($A12,[18]HISTOMARS23!$A$6:$AU$36,43,0) -> 0 | AB12: =VLOOKUP($A12,[18]HISTOMARS23!$A$6:$AU$36,44,0) -> 0 | AC12: =VLOOKUP($A12,[18]HISTOMARS23!$A$6:$AU$36,47,0) -> 0 | AD12: =VLOOKUP(A12,[18]HISTOMARS23!$A$6:$BB$36,54,0) -> 0 | AE12: =VLOOKUP($A12,[18]HISTOMARS23!$A$6:$CA$36,60,0) -> 0 | AF12: =VLOOKUP($A12,[18]HISTOMARS23!$A$6:$CA$36,61,0) -> 0 | AG12: =VLOOKUP($A12,[18]HISTOMARS23!$A$6:$CA$36,62,0) -> 0 | AH12: =VLOOKUP($A12,[18]HISTOMARS23!$A$6:$CA$36,63,0) -> 0 | AI12: =VLOOKUP($A12,[18]HISTOMARS23!$A$6:$CA$36,64,0) -> 0 | AJ12: =VLOOKUP($A12,[18]HISTOMARS23!$A$6:$CA$36,65,0) -> 0
A13: AS201651 | B13: =VLOOKUP(A13,[15]LISTADHERENT!A$5:H$60,3,0) -> DOMOU FABIEN | E13: =VLOOKUP($A13,[18]HISTOMARS23!$A$6:$BA$36,48,0) -> 0 | F13: =MVTFEV23!F13+MVTFEV23!G13-MVTMARS23!E13+K13 -> 666634.25 | G13: 180.26189 | H13: =F13+G13 -> 666814.51 | I13: =VLOOKUP($A13,[18]HISTOMARS23!$A$6:$AQ$40,22,0) -> 0 | J13: =VLOOKUP($A13,[18]HISTOMARS23!$A$6:$AU$36,45,0) -> 15000 | K13: =IF(J13=0,0,J13-(L13+M13+N13)) -> 9000 | L13: =IF(J13=0,0,1000) -> 1000 | M13: =IF(J13=0,0,1000) -> 1000 | N13: =IF(J13=0,0,4000) -> 4000 | O13: =VLOOKUP($A13,[18]HISTOMARS23!$A$6:$AU$36,7,0) -> 0 | P13: =VLOOKUP($A13,[18]HISTOMARS23!$A$6:$AU$36,23,0) -> 0 | Q13: =VLOOKUP($A13,[18]HISTOMARS23!$A$6:$AU$36,46,0) -> 0 | R13: =VLOOKUP($A13,[18]HISTOMARS23!$A$6:$AU$36,26,0) -> 0 | S13: =VLOOKUP($A13,[18]HISTOMARS23!$A$6:$BG$36,58,0) -> 0 | T13: =VLOOKUP($A13,[18]HISTOMARS23!$A$6:$AU$36,28,0) -> 0 | U13: =VLOOKUP($A13,[18]HISTOMARS23!$A$6:$AU$36,19,0) -> 0 | V13: =VLOOKUP($A13,[18]HISTOMARS23!$A$6:$AU$36,20,0) -> 0 | W13: =VLOOKUP($A13,[18]HISTOMARS23!$A$6:$AU$36,27,0) -> 0 | X13: =VLOOKUP($A13,[18]HISTOMARS23!$A$6:$BM$36,33,0) -> 0 | Y13: =VLOOKUP($A13,[18]HISTOMARS23!$A$6:$BM$36,65,0) -> 0 | AA13: =VLOOKUP($A13,[18]HISTOMARS23!$A$6:$AU$36,43,0) -> 0 | AB13: =VLOOKUP($A13,[18]HISTOMARS23!$A$6:$AU$36,44,0) -> 0 | AC13: =VLOOKUP($A13,[18]HISTOMARS23!$A$6:$AU$36,47,0) -> 0 | AD13: =VLOOKUP(A13,[18]HISTOMARS23!$A$6:$BB$36,54,0) -> 70000 | AE13: =VLOOKUP($A13,[18]HISTOMARS23!$A$6:$CA$36,60,0) -> 0 | AF13: =VLOOKUP($A13,[18]HISTOMARS23!$A$6:$CA$36,61,0) -> 0 | AG13: =VLOOKUP($A13,[18]HISTOMARS23!$A$6:$CA$36,62,0) -> 0 | AH13: =VLOOKUP($A13,[18]HISTOMARS23!$A$6:$CA$36,63,0) -> 0 | AI13: =VLOOKUP($A13,[18]HISTOMARS23!$A$6:$CA$36,64,0) -> 0 | AJ13: =VLOOKUP($A13,[18]HISTOMARS23!$A$6:$CA$36,65,0) -> 0
A14: AS201609 | B14: =VLOOKUP(A14,[15]LISTADHERENT!A$5:H$60,3,0) -> DONHOU DAVID | E14: =VLOOKUP($A14,[18]HISTOMARS23!$A$6:$BA$36,48,0) -> 0 | F14: =MVTFEV23!F14+MVTFEV23!G14-MVTMARS23!E14+K14 -> 1154138.3 | G14: 312.08589 | H14: =F14+G14 -> 1154450.3 | I14: =VLOOKUP($A14,[18]HISTOMARS23!$A$6:$AQ$40,22,0) -> 0 | J14: =VLOOKUP($A14,[18]HISTOMARS23!$A$6:$AU$36,45,0) -> 15000 | K14: =IF(J14=0,0,J14-(L14+M14+N14)) -> 9000 | L14: =IF(J14=0,0,1000) -> 1000 | M14: =IF(J14=0,0,1000) -> 1000 | N14: =IF(J14=0,0,4000) -> 4000 | O14: =VLOOKUP($A14,[18]HISTOMARS23!$A$6:$AU$36,7,0) -> 0 | P14: =VLOOKUP($A14,[18]HISTOMARS23!$A$6:$AU$36,23,0) -> 0 | Q14: =VLOOKUP($A14,[18]HISTOMARS23!$A$6:$AU$36,46,0) -> 0 | R14: =VLOOKUP($A14,[18]HISTOMARS23!$A$6:$AU$36,26,0) -> 0 | S14: =VLOOKUP($A14,[18]HISTOMARS23!$A$6:$BG$36,58,0) -> 0 | T14: =VLOOKUP($A14,[18]HISTOMARS23!$A$6:$AU$36,28,0) -> 0 | U14: =VLOOKUP($A14,[18]HISTOMARS23!$A$6:$AU$36,19,0) -> 0 | V14: =VLOOKUP($A14,[18]HISTOMARS23!$A$6:$AU$36,20,0) -> 0 | W14: =VLOOKUP($A14,[18]HISTOMARS23!$A$6:$AU$36,27,0) -> 0 | X14: =VLOOKUP($A14,[18]HISTOMARS23!$A$6:$BM$36,33,0) -> 0 | Y14: =VLOOKUP($A14,[18]HISTOMARS23!$A$6:$BM$36,65,0) -> 0 | AA14: =VLOOKUP($A14,[18]HISTOMARS23!$A$6:$AU$36,43,0) -> 0 | AB14: =VLOOKUP($A14,[18]HISTOMARS23!$A$6:$AU$36,44,0) -> 0 | AC14: =VLOOKUP($A14,[18]HISTOMARS23!$A$6:$AU$36,47,0) -> 0 | AD14: =VLOOKUP(A14,[18]HISTOMARS23!$A$6:$BB$36,54,0) -> 0 | AE14: =VLOOKUP($A14,[18]HISTOMARS23!$A$6:$CA$36,60,0) -> 0 | AF14: =VLOOKUP($A14,[18]HISTOMARS23!$A$6:$CA$36,61,0) -> 0 | AG14: =VLOOKUP($A14,[18]HISTOMARS23!$A$6:$CA$36,62,0) -> 0 | AH14: =VLOOKUP($A14,[18]HISTOMARS23!$A$6:$CA$36,63,0) -> 0 | AI14: =VLOOKUP($A14,[18]HISTOMARS23!$A$6:$CA$36,64,0) -> 0 | AJ14: =VLOOKUP($A14,[18]HISTOMARS23!$A$6:$CA$36,65,0) -> 0
A15: AS201611 | B15: =VLOOKUP(A15,[15]LISTADHERENT!A$5:H$60,3,0) -> HENGUE PAUL OMER | E15: =VLOOKUP($A15,[18]HISTOMARS23!$A$6:$BA$36,48,0) -> 0 | F15: =MVTFEV23!F15+MVTFEV23!G15-MVTMARS23!E15+K15 -> 720445.48 | G15: 194.81277 | H15: =F15+G15 -> 720640.3 | I15: =VLOOKUP($A15,[18]HISTOMARS23!$A$6:$AQ$40,22,0) -> 0 | J15: =VLOOKUP($A15,[18]HISTOMARS23!$A$6:$AU$36,45,0) -> 15000 | K15: =IF(J15=0,0,J15-(L15+M15+N15)) -> 9000 | L15: =IF(J15=0,0,1000) -> 1000 | M15: =IF(J15=0,0,1000) -> 1000 | N15: =IF(J15=0,0,4000) -> 4000 | O15: =VLOOKUP($A15,[18]HISTOMARS23!$A$6:$AU$36,7,0) -> 0 | P15: =VLOOKUP($A15,[18]HISTOMARS23!$A$6:$AU$36,23,0) -> 0 | Q15: =VLOOKUP($A15,[18]HISTOMARS23!$A$6:$AU$36,46,0) -> 0 | R15: =VLOOKUP($A15,[18]HISTOMARS23!$A$6:$AU$36,26,0) -> 0 | S15: =VLOOKUP($A15,[18]HISTOMARS23!$A$6:$BG$36,58,0) -> 0 | T15: =VLOOKUP($A15,[18]HISTOMARS23!$A$6:$AU$36,28,0) -> 0 | U15: =VLOOKUP($A15,[18]HISTOMARS23!$A$6:$AU$36,19,0) -> 0 | V15: =VLOOKUP($A15,[18]HISTOMARS23!$A$6:$AU$36,20,0) -> 0 | W15: =VLOOKUP($A15,[18]HISTOMARS23!$A$6:$AU$36,27,0) -> 0 | X15: =VLOOKUP($A15,[18]HISTOMARS23!$A$6:$BM$36,33,0) -> 0 | Y15: =VLOOKUP($A15,[18]HISTOMARS23!$A$6:$BM$36,65,0) -> 0 | AA15: =VLOOKUP($A15,[18]HISTOMARS23!$A$6:$AU$36,43,0) -> 0 | AB15: =VLOOKUP($A15,[18]HISTOMARS23!$A$6:$AU$36,44,0) -> 0 | AC15: =VLOOKUP($A15,[18]HISTOMARS23!$A$6:$AU$36,47,0) -> 0 | AD15: =VLOOKUP(A15,[18]HISTOMARS23!$A$6:$BB$36,54,0) -> 0 | AE15: =VLOOKUP($A15,[18]HISTOMARS23!$A$6:$CA$36,60,0) -> 0 | AF15: =VLOOKUP($A15,[18]HISTOMARS23!$A$6:$CA$36,61,0) -> 0 | AG15: =VLOOKUP($A15,[18]HISTOMARS23!$A$6:$CA$36,62,0) -> 0 | AH15: =VLOOKUP($A15,[18]HISTOMARS23!$A$6:$CA$36,63,0) -> 0 | AI15: =VLOOKUP($A15,[18]HISTOMARS23!$A$6:$CA$36,64,0) -> 0 | AJ15: =VLOOKUP($A15,[18]HISTOMARS23!$A$6:$CA$36,65,0) -> 0
A16: AS201613 | B16: =VLOOKUP(A16,[15]LISTADHERENT!A$5:H$60,3,0) -> HOTCHO BENJAMIN | E16: =VLOOKUP($A16,[18]HISTOMARS23!$A$6:$BA$36,48,0) -> 0 | F16: =MVTFEV23!F16+MVTFEV23!G16-MVTMARS23!E16+K16 -> 788392.31 | G16: 213.186 | H16: =F16+G16 -> 788605.5 | I16: =VLOOKUP($A16,[18]HISTOMARS23!$A$6:$AQ$40,22,0) -> 0 | J16: =VLOOKUP($A16,[18]HISTOMARS23!$A$6:$AU$36,45,0) -> 50000 | K16: =IF(J16=0,0,J16-(L16+M16+N16)) -> 44000 | L16: =IF(J16=0,0,1000) -> 1000 | M16: =IF(J16=0,0,1000) -> 1000 | N16: =IF(J16=0,0,4000) -> 4000 | O16: =VLOOKUP($A16,[18]HISTOMARS23!$A$6:$AU$36,7,0) -> 0 | P16: =VLOOKUP($A16,[18]HISTOMARS23!$A$6:$AU$36,23,0) -> 0 | Q16: =VLOOKUP($A16,[18]HISTOMARS23!$A$6:$AU$36,46,0) -> 0 | R16: =VLOOKUP($A16,[18]HISTOMARS23!$A$6:$AU$36,26,0) -> 0 | S16: =VLOOKUP($A16,[18]HISTOMARS23!$A$6:$BG$36,58,0) -> 0 | T16: =VLOOKUP($A16,[18]HISTOMARS23!$A$6:$AU$36,28,0) -> 0 | U16: =VLOOKUP($A16,[18]HISTOMARS23!$A$6:$AU$36,19,0) -> 0 | V16: =VLOOKUP($A16,[18]HISTOMARS23!$A$6:$AU$36,20,0) -> 0 | W16: =VLOOKUP($A16,[18]HISTOMARS23!$A$6:$AU$36,27,0) -> 0 | X16: =VLOOKUP($A16,[18]HISTOMARS23!$A$6:$BM$36,33,0) -> 0 | Y16: =VLOOKUP($A16,[18]HISTOMARS23!$A$6:$BM$36,65,0) -> 0 | AA16: =VLOOKUP($A16,[18]HISTOMARS23!$A$6:$AU$36,43,0) -> 0 | AB16: =VLOOKUP($A16,[18]HISTOMARS23!$A$6:$AU$36,44,0) -> 0 | AC16: =VLOOKUP($A16,[18]HISTOMARS23!$A$6:$AU$36,47,0) -> 0 | AD16: =VLOOKUP(A16,[18]HISTOMARS23!$A$6:$BB$36,54,0) -> 0 | AE16: =VLOOKUP($A16,[18]HISTOMARS23!$A$6:$CA$36,60,0) -> 0 | AF16: =VLOOKUP($A16,[18]HISTOMARS23!$A$6:$CA$36,61,0) -> 0 | AG16: =VLOOKUP($A16,[18]HISTOMARS23!$A$6:$CA$36,62,0) -> 0 | AH16: =VLOOKUP($A16,[18]HISTOMARS23!$A$6:$CA$36,63,0) -> 0 | AI16: =VLOOKUP($A16,[18]HISTOMARS23!$A$6:$CA$36,64,0) -> 0 | AJ16: =VLOOKUP($A16,[18]HISTOMARS23!$A$6:$CA$36,65,0) -> 0
A17: AS201617 | B17: =VLOOKUP(A17,[15]LISTADHERENT!A$5:H$60,3,0) -> KOUAMOU MOISE | E17: =VLOOKUP($A17,[18]HISTOMARS23!$A$6:$BA$36,48,0) -> 0 | F17: =MVTFEV23!F17+MVTFEV23!G17-MVTMARS23!E17+K17 -> 722768.01 | G17: 195.44079 | H17: =F17+G17 -> 722963.45 | I17: =VLOOKUP($A17,[18]HISTOMARS23!$A$6:$AQ$40,22,0) -> 0 | J17: =VLOOKUP($A17,[18]HISTOMARS23!$A$6:$AU$36,45,0) -> 15000 | K17: =IF(J17=0,0,J17-(L17+M17+N17)) -> 9000 | L17: =IF(J17=0,0,1000) -> 1000 | M17: =IF(J17=0,0,1000) -> 1000 | N17: =IF(J17=0,0,4000) -> 4000 | O17: =VLOOKUP($A17,[18]HISTOMARS23!$A$6:$AU$36,7,0) -> 0 | P17: =VLOOKUP($A17,[18]HISTOMARS23!$A$6:$AU$36,23,0) -> 0 | Q17: =VLOOKUP($A17,[18]HISTOMARS23!$A$6:$AU$36,46,0) -> 0 | R17: =VLOOKUP($A17,[18]HISTOMARS23!$A$6:$AU$36,26,0) -> 0 | S17: =VLOOKUP($A17,[18]HISTOMARS23!$A$6:$BG$36,58,0) -> 0 | T17: =VLOOKUP($A17,[18]HISTOMARS23!$A$6:$AU$36,28,0) -> 0 | U17: =VLOOKUP($A17,[18]HISTOMARS23!$A$6:$AU$36,19,0) -> 0 | V17: =VLOOKUP($A17,[18]HISTOMARS23!$A$6:$AU$36,20,0) -> 0 | W17: =VLOOKUP($A17,[18]HISTOMARS23!$A$6:$AU$36,27,0) -> 0 | X17: =VLOOKUP($A17,[18]HISTOMARS23!$A$6:$BM$36,33,0) -> 0 | Y17: =VLOOKUP($A17,[18]HISTOMARS23!$A$6:$BM$36,65,0) -> 0 | AA17: =VLOOKUP($A17,[18]HISTOMARS23!$A$6:$AU$36,43,0) -> 0 | AB17: =VLOOKUP($A17,[18]HISTOMARS23!$A$6:$AU$36,44,0) -> 0 | AC17: =VLOOKUP($A17,[18]HISTOMARS23!$A$6:$AU$36,47,0) -> 0 | AD17: =VLOOKUP(A17,[18]HISTOMARS23!$A$6:$BB$36,54,0) -> 0 | AE17: =VLOOKUP($A17,[18]HISTOMARS23!$A$6:$CA$36,60,0) -> 0 | AF17: =VLOOKUP($A17,[18]HISTOMARS23!$A$6:$CA$36,61,0) -> 0 | AG17: =VLOOKUP($A17,[18]HISTOMARS23!$A$6:$CA$36,62,0) -> 0 | AH17: =VLOOKUP($A17,[18]HISTOMARS23!$A$6:$CA$36,63,0) -> 0 | AI17: =VLOOKUP($A17,[18]HISTOMARS23!$A$6:$CA$36,64,0) -> 0 | AJ17: =VLOOKUP($A17,[18]HISTOMARS23!$A$6:$CA$36,65,0) -> 0
A18: AS201619 | B18: =VLOOKUP(A18,[15]LISTADHERENT!A$5:H$60,3,0) -> KOUATCHO MESSACK | E18: =VLOOKUP($A18,[18]HISTOMARS23!$A$6:$BA$36,48,0) -> 0 | F18: =MVTFEV23!F18+MVTFEV23!G18-MVTMARS23!E18+K18 -> 671891 | G18: 181.68334 | H18: =F18+G18 -> 672072.68 | I18: =VLOOKUP($A18,[18]HISTOMARS23!$A$6:$AQ$40,22,0) -> 0 | J18: =VLOOKUP($A18,[18]HISTOMARS23!$A$6:$AU$36,45,0) -> 14000 | K18: =IF(J18=0,0,J18-(L18+M18+N18)) -> 8000 | L18: =IF(J18=0,0,1000) -> 1000 | M18: =IF(J18=0,0,1000) -> 1000 | N18: =IF(J18=0,0,4000) -> 4000 | O18: =VLOOKUP($A18,[18]HISTOMARS23!$A$6:$AU$36,7,0) -> 0 | P18: =VLOOKUP($A18,[18]HISTOMARS23!$A$6:$AU$36,23,0) -> 0 | Q18: =VLOOKUP($A18,[18]HISTOMARS23!$A$6:$AU$36,46,0) -> 0 | R18: =VLOOKUP($A18,[18]HISTOMARS23!$A$6:$AU$36,26,0) -> 0 | S18: =VLOOKUP($A18,[18]HISTOMARS23!$A$6:$BG$36,58,0) -> 0 | T18: =VLOOKUP($A18,[18]HISTOMARS23!$A$6:$AU$36,28,0) -> 0 | U18: =VLOOKUP($A18,[18]HISTOMARS23!$A$6:$AU$36,19,0) -> 0 | V18: =VLOOKUP($A18,[18]HISTOMARS23!$A$6:$AU$36,20,0) -> 0 | W18: =VLOOKUP($A18,[18]HISTOMARS23!$A$6:$AU$36,27,0) -> 0 | X18: =VLOOKUP($A18,[18]HISTOMARS23!$A$6:$BM$36,33,0) -> 0 | Y18: =VLOOKUP($A18,[18]HISTOMARS23!$A$6:$BM$36,65,0) -> 0 | AA18: =VLOOKUP($A18,[18]HISTOMARS23!$A$6:$AU$36,43,0) -> 0 | AB18: =VLOOKUP($A18,[18]HISTOMARS23!$A$6:$AU$36,44,0) -> 0 | AC18: =VLOOKUP($A18,[18]HISTOMARS23!$A$6:$AU$36,47,0) -> 0 | AD18: =VLOOKUP(A18,[18]HISTOMARS23!$A$6:$BB$36,54,0) -> 0 | AE18: =VLOOKUP($A18,[18]HISTOMARS23!$A$6:$CA$36,60,0) -> 0 | AF18: =VLOOKUP($A18,[18]HISTOMARS23!$A$6:$CA$36,61,0) -> 0 | AG18: =VLOOKUP($A18,[18]HISTOMARS23!$A$6:$CA$36,62,0) -> 0 | AH18: =VLOOKUP($A18,[18]HISTOMARS23!$A$6:$CA$36,63,0) -> 0 | AI18: =VLOOKUP($A18,[18]HISTOMARS23!$A$6:$CA$36,64,0) -> 0 | AJ18: =VLOOKUP($A18,[18]HISTOMARS23!$A$6:$CA$36,65,0) -> 0
... A23: AS201622 | B23: =VLOOKUP(A23,[15]LISTADHERENT!A$5:H$60,3,0) -> NDJOMO ETIENNE | E23: =VLOOKUP($A23,[18]HISTOMARS23!$A$6:$BA$36,48,0) -> 0 | F23: =MVTFEV23!F23+MVTFEV23!G23-MVTMARS23!E23+K23 -> 997652.93 | G23: 269.77132 | H23: =F23+G23 -> 997922.7 | I23: =VLOOKUP($A23,[18]HISTOMARS23!$A$6:$AQ$40,22,0) -> 0 | J23: =VLOOKUP($A23,[18]HISTOMARS23!$A$6:$AU$36,45,0) -> 25000 | K23: =IF(J23=0,0,J23-(L23+M23+N23)) -> 19000 | L23: =IF(J23=0,0,1000) -> 1000 | M23: =IF(J23=0,0,1000) -> 1000 | N23: =IF(J23=0,0,4000) -> 4000 | O23: =VLOOKUP($A23,[18]HISTOMARS23!$A$6:$AU$36,7,0) -> 0 | P23: =VLOOKUP($A23,[18]HISTOMARS23!$A$6:$AU$36,23,0) -> 0 | Q23: =VLOOKUP($A23,[18]HISTOMARS23!$A$6:$AU$36,46,0) -> 0 | R23: =VLOOKUP($A23,[18]HISTOMARS23!$A$6:$AU$36,26,0) -> 0 | S23: =VLOOKUP($A23,[18]HISTOMARS23!$A$6:$BG$36,58,0) -> 0 | T23: =VLOOKUP($A23,[18]HISTOMARS23!$A$6:$AU$36,28,0) -> 0 | U23: =VLOOKUP($A23,[18]HISTOMARS23!$A$6:$AU$36,19,0) -> 0 | V23: =VLOOKUP($A23,[18]HISTOMARS23!$A$6:$AU$36,20,0) -> 0 | W23: =VLOOKUP($A23,[18]HISTOMARS23!$A$6:$AU$36,27,0) -> 0 | X23: =VLOOKUP($A23,[18]HISTOMARS23!$A$6:$BM$36,33,0) -> 0 | Y23: =VLOOKUP($A23,[18]HISTOMARS23!$A$6:$BM$36,65,0) -> 0 | AA23: =VLOOKUP($A23,[18]HISTOMARS23!$A$6:$AU$36,43,0) -> 0 | AB23: =VLOOKUP($A23,[18]HISTOMARS23!$A$6:$AU$36,44,0) -> 0 | AC23: =VLOOKUP($A23,[18]HISTOMARS23!$A$6:$AU$36,47,0) -> 0 | AD23: =VLOOKUP(A23,[18]HISTOMARS23!$A$6:$BB$36,54,0) -> 0 | AE23: =VLOOKUP($A23,[18]HISTOMARS23!$A$6:$CA$36,60,0) -> 0 | AF23: =VLOOKUP($A23,[18]HISTOMARS23!$A$6:$CA$36,61,0) -> 0 | AG23: =VLOOKUP($A23,[18]HISTOMARS23!$A$6:$CA$36,62,0) -> 0 | AH23: =VLOOKUP($A23,[18]HISTOMARS23!$A$6:$CA$36,63,0) -> 0 | AI23: =VLOOKUP($A23,[18]HISTOMARS23!$A$6:$CA$36,64,0) -> 0 | AJ23: =VLOOKUP($A23,[18]HISTOMARS23!$A$6:$CA$36,65,0) -> 0
A24: AS201624 | B24: =VLOOKUP(A24,[15]LISTADHERENT!A$5:H$60,3,0) -> NGONDIEP CLAUDE | E24: =VLOOKUP($A24,[18]HISTOMARS23!$A$6:$BA$36,48,0) -> 0 | F24: =MVTFEV23!F24+MVTFEV23!G24-MVTMARS23!E24+K24 -> 705384.62 | G24: 190.74022 | H24: =F24+G24 -> 705575.36 | I24: =VLOOKUP($A24,[18]HISTOMARS23!$A$6:$AQ$40,22,0) -> 0 | J24: =VLOOKUP($A24,[18]HISTOMARS23!$A$6:$AU$36,45,0) -> 15000 | K24: =IF(J24=0,0,J24-(L24+M24+N24))-3000 -> 6000 | L24: =IF(J24=0,0,1000) -> 1000 | M24: =IF(J24=0,0,1000) -> 1000 | N24: =IF(J24=0,0,4000) -> 4000 | O24: =VLOOKUP($A24,[18]HISTOMARS23!$A$6:$AU$36,7,0) -> 3000 | P24: =VLOOKUP($A24,[18]HISTOMARS23!$A$6:$AU$36,23,0) -> 0 | Q24: =VLOOKUP($A24,[18]HISTOMARS23!$A$6:$AU$36,46,0) -> 0 | R24: =VLOOKUP($A24,[18]HISTOMARS23!$A$6:$AU$36,26,0) -> 0 | S24: =VLOOKUP($A24,[18]HISTOMARS23!$A$6:$BG$36,58,0) -> 0 | T24: =VLOOKUP($A24,[18]HISTOMARS23!$A$6:$AU$36,28,0) -> 0 | U24: =VLOOKUP($A24,[18]HISTOMARS23!$A$6:$AU$36,19,0) -> 0 | V24: =VLOOKUP($A24,[18]HISTOMARS23!$A$6:$AU$36,20,0) -> 0 | W24: =VLOOKUP($A24,[18]HISTOMARS23!$A$6:$AU$36,27,0) -> 0 | X24: =VLOOKUP($A24,[18]HISTOMARS23!$A$6:$BM$36,33,0) -> 0 | Y24: =VLOOKUP($A24,[18]HISTOMARS23!$A$6:$BM$36,65,0) -> 0 | AA24: =VLOOKUP($A24,[18]HISTOMARS23!$A$6:$AU$36,43,0) -> 0 | AB24: =VLOOKUP($A24,[18]HISTOMARS23!$A$6:$AU$36,44,0) -> 0 | AC24: =VLOOKUP($A24,[18]HISTOMARS23!$A$6:$AU$36,47,0) -> 0 | AD24: =VLOOKUP(A24,[18]HISTOMARS23!$A$6:$BB$36,54,0) -> 0 | AE24: =VLOOKUP($A24,[18]HISTOMARS23!$A$6:$CA$36,60,0) -> 0 | AF24: =VLOOKUP($A24,[18]HISTOMARS23!$A$6:$CA$36,61,0) -> 0 | AG24: =VLOOKUP($A24,[18]HISTOMARS23!$A$6:$CA$36,62,0) -> 0 | AH24: =VLOOKUP($A24,[18]HISTOMARS23!$A$6:$CA$36,63,0) -> 0 | AI24: =VLOOKUP($A24,[18]HISTOMARS23!$A$6:$CA$36,64,0) -> 0 | AJ24: =VLOOKUP($A24,[18]HISTOMARS23!$A$6:$CA$36,65,0) -> 0
A25: AS201626 | B25: =VLOOKUP(A25,[15]LISTADHERENT!A$5:H$60,3,0) -> NGUIEMEGNI MATHIEU BLAISE | E25: =VLOOKUP($A25,[18]HISTOMARS23!$A$6:$BA$36,48,0) -> 0 | F25: =MVTFEV23!F25+MVTFEV23!G25-MVTMARS23!E25+K25 -> 671597.93 | G25: 181.6041 | H25: =F25+G25 -> 671779.53 | I25: =VLOOKUP($A25,[18]HISTOMARS23!$A$6:$AQ$40,22,0) -> 0 | J25: =VLOOKUP($A25,[18]HISTOMARS23!$A$6:$AU$36,45,0) -> 5000 | K25: =IF(J25=0,0,J25-(L25+M25+N25)) -> 0 | L25: =IF(J25=0,0,1000)-1000 -> 0 | M25: =IF(J25=0,0,1000) -> 1000 | N25: =IF(J25=0,0,4000) -> 4000 | O25: =VLOOKUP($A25,[18]HISTOMARS23!$A$6:$AU$36,7,0) -> 0 | P25: =VLOOKUP($A25,[18]HISTOMARS23!$A$6:$AU$36,23,0) -> 0 | Q25: =VLOOKUP($A25,[18]HISTOMARS23!$A$6:$AU$36,46,0) -> 0 | R25: =VLOOKUP($A25,[18]HISTOMARS23!$A$6:$AU$36,26,0) -> 0 | S25: =VLOOKUP($A25,[18]HISTOMARS23!$A$6:$BG$36,58,0) -> 0 | T25: =VLOOKUP($A25,[18]HISTOMARS23!$A$6:$AU$36,28,0) -> 0 | U25: =VLOOKUP($A25,[18]HISTOMARS23!$A$6:$AU$36,19,0) -> 0 | V25: =VLOOKUP($A25,[18]HISTOMARS23!$A$6:$AU$36,20,0) -> 0 | W25: =VLOOKUP($A25,[18]HISTOMARS23!$A$6:$AU$36,27,0) -> 0 | X25: =VLOOKUP($A25,[18]HISTOMARS23!$A$6:$BM$36,33,0) -> 0 | Y25: =VLOOKUP($A25,[18]HISTOMARS23!$A$6:$BM$36,65,0) -> 0 | AA25: =VLOOKUP($A25,[18]HISTOMARS23!$A$6:$AU$36,43,0) -> 0 | AB25: =VLOOKUP($A25,[18]HISTOMARS23!$A$6:$AU$36,44,0) -> 0 | AC25: =VLOOKUP($A25,[18]HISTOMARS23!$A$6:$AU$36,47,0) -> 0 | AD25: =VLOOKUP(A25,[18]HISTOMARS23!$A$6:$BB$36,54,0) -> 0 | AE25: =VLOOKUP($A25,[18]HISTOMARS23!$A$6:$CA$36,60,0) -> 0 | AF25: =VLOOKUP($A25,[18]HISTOMARS23!$A$6:$CA$36,61,0) -> 0 | AG25: =VLOOKUP($A25,[18]HISTOMARS23!$A$6:$CA$36,62,0) -> 0 | AH25: =VLOOKUP($A25,[18]HISTOMARS23!$A$6:$CA$36,63,0) -> 0 | AI25: =VLOOKUP($A25,[18]HISTOMARS23!$A$6:$CA$36,64,0) -> 0 | AJ25: =VLOOKUP($A25,[18]HISTOMARS23!$A$6:$CA$36,65,0) -> 0
A26: AS201628 | B26: =VLOOKUP(A26,[15]LISTADHERENT!A$5:H$60,3,0) -> NKAMGANG JUSTIN DEJOLIE | E26: =VLOOKUP($A26,[18]HISTOMARS23!$A$6:$BA$36,48,0) -> 0 | F26: =MVTFEV23!F26+MVTFEV23!G26-MVTMARS23!E26+K26 -> 666624.91 | G26: 180.25936 | H26: =F26+G26 -> 666805.17 | I26: =VLOOKUP($A26,[18]HISTOMARS23!$A$6:$AQ$40,22,0) -> 0 | J26: =VLOOKUP($A26,[18]HISTOMARS23!$A$6:$AU$36,45,0) -> 15000 | K26: =IF(J26=0,0,J26-(L26+M26+N26)) -> 9000 | L26: =IF(J26=0,0,1000) -> 1000 | M26: =IF(J26=0,0,1000) -> 1000 | N26: =IF(J26=0,0,4000) -> 4000 | O26: =VLOOKUP($A26,[18]HISTOMARS23!$A$6:$AU$36,7,0) -> 3000 | P26: =VLOOKUP($A26,[18]HISTOMARS23!$A$6:$AU$36,23,0) -> 0 | Q26: =VLOOKUP($A26,[18]HISTOMARS23!$A$6:$AU$36,46,0) -> 0 | R26: =VLOOKUP($A26,[18]HISTOMARS23!$A$6:$AU$36,26,0) -> 0 | S26: =VLOOKUP($A26,[18]HISTOMARS23!$A$6:$BG$36,58,0) -> 0 | T26: =VLOOKUP($A26,[18]HISTOMARS23!$A$6:$AU$36,28,0) -> 0 | U26: =VLOOKUP($A26,[18]HISTOMARS23!$A$6:$AU$36,19,0) -> 0 | V26: =VLOOKUP($A26,[18]HISTOMARS23!$A$6:$AU$36,20,0) -> 0 | W26: =VLOOKUP($A26,[18]HISTOMARS23!$A$6:$AU$36,27,0) -> 0 | X26: =VLOOKUP($A26,[18]HISTOMARS23!$A$6:$BM$36,33,0) -> 0 | Y26: =VLOOKUP($A26,[18]HISTOMARS23!$A$6:$BM$36,65,0) -> 0 | AA26: =VLOOKUP($A26,[18]HISTOMARS23!$A$6:$AU$36,43,0) -> 0 | AB26: =VLOOKUP($A26,[18]HISTOMARS23!$A$6:$AU$36,44,0) -> 0 | AC26: =VLOOKUP($A26,[18]HISTOMARS23!$A$6:$AU$36,47,0) -> 0 | AD26: =VLOOKUP(A26,[18]HISTOMARS23!$A$6:$BB$36,54,0) -> 0 | AE26: =VLOOKUP($A26,[18]HISTOMARS23!$A$6:$CA$36,60,0) -> 0 | AF26: =VLOOKUP($A26,[18]HISTOMARS23!$A$6:$CA$36,61,0) -> 0 | AG26: =VLOOKUP($A26,[18]HISTOMARS23!$A$6:$CA$36,62,0) -> 0 | AH26: =VLOOKUP($A26,[18]HISTOMARS23!$A$6:$CA$36,63,0) -> 0 | AI26: =VLOOKUP($A26,[18]HISTOMARS23!$A$6:$CA$36,64,0) -> 0 | AJ26: =VLOOKUP($A26,[18]HISTOMARS23!$A$6:$CA$36,65,0) -> 0
A27: AS201656 | B27: =VLOOKUP(A27,[15]LISTADHERENT!A$5:H$60,3,0) -> NOUBE ETIENNE | E27: =VLOOKUP($A27,[18]HISTOMARS23!$A$6:$BA$36,48,0) -> 0 | F27: =MVTFEV23!F27+MVTFEV23!G27-MVTMARS23!E27+K27 -> 37000 | G27: 0 | H27: =F27+G27 -> 37000 | I27: =VLOOKUP($A27,[18]HISTOMARS23!$A$6:$AQ$40,22,0) -> 0 | J27: =VLOOKUP($A27,[18]HISTOMARS23!$A$6:$AU$36,45,0) -> 25000 | K27: =IF(J27=0,0,J27-(L27+M27+N27)) -> 19000 | L27: =IF(J27=0,0,1000) -> 1000 | M27: =IF(J27=0,0,1000) -> 1000 | N27: =IF(J27=0,0,4000) -> 4000 | O27: =VLOOKUP($A27,[18]HISTOMARS23!$A$6:$AU$36,7,0) -> 0 | P27: =VLOOKUP($A27,[18]HISTOMARS23!$A$6:$AU$36,23,0) -> 0 | Q27: =VLOOKUP($A27,[18]HISTOMARS23!$A$6:$AU$36,46,0) -> 0 | R27: =VLOOKUP($A27,[18]HISTOMARS23!$A$6:$AU$36,26,0) -> 0 | S27: =VLOOKUP($A27,[18]HISTOMARS23!$A$6:$BG$36,58,0) -> 0 | T27: =VLOOKUP($A27,[18]HISTOMARS23!$A$6:$AU$36,28,0) -> 0 | U27: =VLOOKUP($A27,[18]HISTOMARS23!$A$6:$AU$36,19,0) -> 0 | V27: =VLOOKUP($A27,[18]HISTOMARS23!$A$6:$AU$36,20,0) -> 0 | W27: =VLOOKUP($A27,[18]HISTOMARS23!$A$6:$AU$36,27,0) -> 0 | X27: =VLOOKUP($A27,[18]HISTOMARS23!$A$6:$BM$36,33,0) -> 0 | Y27: =VLOOKUP($A27,[18]HISTOMARS23!$A$6:$BM$36,65,0) -> 0 | AA27: =VLOOKUP($A27,[18]HISTOMARS23!$A$6:$AU$36,43,0) -> 0 | AB27: =VLOOKUP($A27,[18]HISTOMARS23!$A$6:$AU$36,44,0) -> 0 | AC27: =VLOOKUP($A27,[18]HISTOMARS23!$A$6:$AU$36,47,0) -> 0 | AD27: =VLOOKUP(A27,[18]HISTOMARS23!$A$6:$BB$36,54,0) -> 0 | AE27: =VLOOKUP($A27,[18]HISTOMARS23!$A$6:$CA$36,60,0) -> 0 | AF27: =VLOOKUP($A27,[18]HISTOMARS23!$A$6:$CA$36,61,0) -> 0 | AG27: =VLOOKUP($A27,[18]HISTOMARS23!$A$6:$CA$36,62,0) -> 0 | AH27: =VLOOKUP($A27,[18]HISTOMARS23!$A$6:$CA$36,63,0) -> 0 | AI27: =VLOOKUP($A27,[18]HISTOMARS23!$A$6:$CA$36,64,0) -> 0 | AJ27: =VLOOKUP($A27,[18]HISTOMARS23!$A$6:$CA$36,65,0) -> 0
A28: AS201633 | B28: =VLOOKUP(A28,[15]LISTADHERENT!A$5:H$60,3,0) -> PATEGO NJOSSU GUSTAVE | E28: =VLOOKUP($A28,[18]HISTOMARS23!$A$6:$BA$36,48,0) -> 0 | F28: =MVTFEV23!F28+MVTFEV23!G28-MVTMARS23!E28+K28 -> 688858.15 | G28: 186.27136 | H28: =F28+G28 -> 689044.42 | I28: =VLOOKUP($A28,[18]HISTOMARS23!$A$6:$AQ$40,22,0) -> 0 | J28: =VLOOKUP($A28,[18]HISTOMARS23!$A$6:$AU$36,45,0) -> 15000 | K28: =IF(J28=0,0,J28-(L28+M28+N28)) -> 9000 | L28: =IF(J28=0,0,1000) -> 1000 | M28: =IF(J28=0,0,1000) -> 1000 | N28: =IF(J28=0,0,4000) -> 4000 | O28: =VLOOKUP($A28,[18]HISTOMARS23!$A$6:$AU$36,7,0) -> 0 | P28: =VLOOKUP($A28,[18]HISTOMARS23!$A$6:$AU$36,23,0) -> 0 | Q28: =VLOOKUP($A28,[18]HISTOMARS23!$A$6:$AU$36,46,0) -> 0 | R28: =VLOOKUP($A28,[18]HISTOMARS23!$A$6:$AU$36,26,0) -> 0 | S28: =VLOOKUP($A28,[18]HISTOMARS23!$A$6:$BG$36,58,0) -> 0 | T28: =VLOOKUP($A28,[18]HISTOMARS23!$A$6:$AU$36,28,0) -> 0 | U28: =VLOOKUP($A28,[18]HISTOMARS23!$A$6:$AU$36,19,0) -> 0 | V28: =VLOOKUP($A28,[18]HISTOMARS23!$A$6:$AU$36,20,0) -> 0 | W28: =VLOOKUP($A28,[18]HISTOMARS23!$A$6:$AU$36,27,0) -> 0 | X28: =VLOOKUP($A28,[18]HISTOMARS23!$A$6:$BM$36,33,0) -> 0 | Y28: =VLOOKUP($A28,[18]HISTOMARS23!$A$6:$BM$36,65,0) -> 0 | AA28: =VLOOKUP($A28,[18]HISTOMARS23!$A$6:$AU$36,43,0) -> 0 | AB28: =VLOOKUP($A28,[18]HISTOMARS23!$A$6:$AU$36,44,0) -> 0 | AC28: =VLOOKUP($A28,[18]HISTOMARS23!$A$6:$AU$36,47,0) -> 0 | AD28: =VLOOKUP(A28,[18]HISTOMARS23!$A$6:$BB$36,54,0) -> 0 | AE28: =VLOOKUP($A28,[18]HISTOMARS23!$A$6:$CA$36,60,0) -> 0 | AF28: =VLOOKUP($A28,[18]HISTOMARS23!$A$6:$CA$36,61,0) -> 0 | AG28: =VLOOKUP($A28,[18]HISTOMARS23!$A$6:$CA$36,62,0) -> 0 | AH28: =VLOOKUP($A28,[18]HISTOMARS23!$A$6:$CA$36,63,0) -> 0 | AI28: =VLOOKUP($A28,[18]HISTOMARS23!$A$6:$CA$36,64,0) -> 0 | AJ28: =VLOOKUP($A28,[18]HISTOMARS23!$A$6:$CA$36,65,0) -> 0
A29: AS201657 | B29: =VLOOKUP(A29,[15]LISTADHERENT!A$5:H$60,3,0) -> SEUMO POLYCARPE | E29: =VLOOKUP($A29,[18]HISTOMARS23!$A$6:$BA$36,48,0) -> 0 | F29: =MVTFEV23!F29+MVTFEV23!G29-MVTMARS23!E29+K29 -> 27000 | G29: 0 | H29: =F29+G29 -> 27000 | I29: =VLOOKUP($A29,[18]HISTOMARS23!$A$6:$AQ$40,22,0) -> 0 | J29: =VLOOKUP($A29,[18]HISTOMARS23!$A$6:$AU$36,45,0) -> 15000 | K29: =IF(J29=0,0,J29-(L29+M29+N29)) -> 9000 | L29: =IF(J29=0,0,1000) -> 1000 | M29: =IF(J29=0,0,1000) -> 1000 | N29: =IF(J29=0,0,4000) -> 4000 | O29: =VLOOKUP($A29,[18]HISTOMARS23!$A$6:$AU$36,7,0) -> 0 | P29: =VLOOKUP($A29,[18]HISTOMARS23!$A$6:$AU$36,23,0) -> 0 | Q29: =VLOOKUP($A29,[18]HISTOMARS23!$A$6:$AU$36,46,0) -> 0 | R29: =VLOOKUP($A29,[18]HISTOMARS23!$A$6:$AU$36,26,0) -> 0 | S29: =VLOOKUP($A29,[18]HISTOMARS23!$A$6:$BG$36,58,0) -> 0 | T29: =VLOOKUP($A29,[18]HISTOMARS23!$A$6:$AU$36,28,0) -> 0 | U29: =VLOOKUP($A29,[18]HISTOMARS23!$A$6:$AU$36,19,0) -> 0 | V29: =VLOOKUP($A29,[18]HISTOMARS23!$A$6:$AU$36,20,0) -> 0 | W29: =VLOOKUP($A29,[18]HISTOMARS23!$A$6:$AU$36,27,0) -> 0 | X29: =VLOOKUP($A29,[18]HISTOMARS23!$A$6:$BM$36,33,0) -> 0 | Y29: =VLOOKUP($A29,[18]HISTOMARS23!$A$6:$BM$36,65,0) -> 0 | AA29: =VLOOKUP($A29,[18]HISTOMARS23!$A$6:$AU$36,43,0) -> 0 | AB29: =VLOOKUP($A29,[18]HISTOMARS23!$A$6:$AU$36,44,0) -> 0 | AC29: =VLOOKUP($A29,[18]HISTOMARS23!$A$6:$AU$36,47,0) -> 0 | AD29: =VLOOKUP(A29,[18]HISTOMARS23!$A$6:$BB$36,54,0) -> 0 | AE29: =VLOOKUP($A29,[18]HISTOMARS23!$A$6:$CA$36,60,0) -> 0 | AF29: =VLOOKUP($A29,[18]HISTOMARS23!$A$6:$CA$36,61,0) -> 0 | AG29: =VLOOKUP($A29,[18]HISTOMARS23!$A$6:$CA$36,62,0) -> 0 | AH29: =VLOOKUP($A29,[18]HISTOMARS23!$A$6:$CA$36,63,0) -> 0 | AI29: =VLOOKUP($A29,[18]HISTOMARS23!$A$6:$CA$36,64,0) -> 0 | AJ29: =VLOOKUP($A29,[18]HISTOMARS23!$A$6:$CA$36,65,0) -> 0
A30: AS201653 | B30: =VLOOKUP(A30,[15]LISTADHERENT!A$5:H$60,3,0) -> SIME BRICE | E30: =VLOOKUP($A30,[18]HISTOMARS23!$A$6:$BA$36,48,0) -> 0 | F30: =MVTFEV23!F30+MVTFEV23!G30-MVTMARS23!E30+K30 -> 879809.49 | G30: 237.90575 | H30: =F30+G30 -> 880047.39 | I30: =VLOOKUP($A30,[18]HISTOMARS23!$A$6:$AQ$40,22,0) -> 0 | J30: =VLOOKUP($A30,[18]HISTOMARS23!$A$6:$AU$36,45,0) -> 15000 | K30: =IF(J30=0,0,J30-(L30+M30+N30)) -> 9000 | L30: =IF(J30=0,0,1000) -> 1000 | M30: =IF(J30=0,0,1000) -> 1000 | N30: =IF(J30=0,0,4000) -> 4000 | O30: =VLOOKUP($A30,[18]HISTOMARS23!$A$6:$AU$36,7,0) -> 0 | P30: =VLOOKUP($A30,[18]HISTOMARS23!$A$6:$AU$36,23,0) -> 0 | Q30: =VLOOKUP($A30,[18]HISTOMARS23!$A$6:$AU$36,46,0) -> 0 | R30: =VLOOKUP($A30,[18]HISTOMARS23!$A$6:$AU$36,26,0) -> 0 | S30: =VLOOKUP($A30,[18]HISTOMARS23!$A$6:$BG$36,58,0) -> 0 | T30: =VLOOKUP($A30,[18]HISTOMARS23!$A$6:$AU$36,28,0) -> 0 | U30: =VLOOKUP($A30,[18]HISTOMARS23!$A$6:$AU$36,19,0) -> 0 | V30: =VLOOKUP($A30,[18]HISTOMARS23!$A$6:$AU$36,20,0) -> 0 | W30: =VLOOKUP($A30,[18]HISTOMARS23!$A$6:$AU$36,27,0) -> 0 | X30: =VLOOKUP($A30,[18]HISTOMARS23!$A$6:$BM$36,33,0) -> 0 | Y30: =VLOOKUP($A30,[18]HISTOMARS23!$A$6:$BM$36,65,0) -> 0 | AA30: =VLOOKUP($A30,[18]HISTOMARS23!$A$6:$AU$36,43,0) -> 0 | AB30: =VLOOKUP($A30,[18]HISTOMARS23!$A$6:$AU$36,44,0) -> 0 | AC30: =VLOOKUP($A30,[18]HISTOMARS23!$A$6:$AU$36,47,0) -> 0 | AD30: =VLOOKUP(A30,[18]HISTOMARS23!$A$6:$BB$36,54,0) -> 0 | AE30: =VLOOKUP($A30,[18]HISTOMARS23!$A$6:$CA$36,60,0) -> 0 | AF30: =VLOOKUP($A30,[18]HISTOMARS23!$A$6:$CA$36,61,0) -> 0 | AG30: =VLOOKUP($A30,[18]HISTOMARS23!$A$6:$CA$36,62,0) -> 0 | AH30: =VLOOKUP($A30,[18]HISTOMARS23!$A$6:$CA$36,63,0) -> 0 | AI30: =VLOOKUP($A30,[18]HISTOMARS23!$A$6:$CA$36,64,0) -> 0 | AJ30: =VLOOKUP($A30,[18]HISTOMARS23!$A$6:$CA$36,65,0) -> 0
A31: AS201638 | B31: =VLOOKUP(A31,[15]LISTADHERENT!A$5:H$60,3,0) -> SIMO PIERRE | E31: =VLOOKUP($A31,[18]HISTOMARS23!$A$6:$BA$36,48,0) -> 0 | F31: =MVTFEV23!F31+MVTFEV23!G31-MVTMARS23!E31+K31 -> 886501.72 | G31: 239.71537 | H31: =F31+G31 -> 886741.43 | I31: =VLOOKUP($A31,[18]HISTOMARS23!$A$6:$AQ$40,22,0) -> 0 | J31: =VLOOKUP($A31,[18]HISTOMARS23!$A$6:$AU$36,45,0) -> 15000 | K31: =IF(J31=0,0,J31-(L31+M31+N31)) -> 9000 | L31: =IF(J31=0,0,1000) -> 1000 | M31: =IF(J31=0,0,1000) -> 1000 | N31: =IF(J31=0,0,4000) -> 4000 | O31: =VLOOKUP($A31,[18]HISTOMARS23!$A$6:$AU$36,7,0) -> 0 | P31: =VLOOKUP($A31,[18]HISTOMARS23!$A$6:$AU$36,23,0) -> 0 | Q31: =VLOOKUP($A31,[18]HISTOMARS23!$A$6:$AU$36,46,0) -> 0 | R31: =VLOOKUP($A31,[18]HISTOMARS23!$A$6:$AU$36,26,0) -> 0 | S31: =VLOOKUP($A31,[18]HISTOMARS23!$A$6:$BG$36,58,0) -> 0 | T31: =VLOOKUP($A31,[18]HISTOMARS23!$A$6:$AU$36,28,0) -> 0 | U31: =VLOOKUP($A31,[18]HISTOMARS23!$A$6:$AU$36,19,0) -> 0 | V31: =VLOOKUP($A31,[18]HISTOMARS23!$A$6:$AU$36,20,0) -> 0 | W31: =VLOOKUP($A31,[18]HISTOMARS23!$A$6:$AU$36,27,0) -> 0 | X31: =VLOOKUP($A31,[18]HISTOMARS23!$A$6:$BM$36,33,0) -> 0 | Y31: =VLOOKUP($A31,[18]HISTOMARS23!$A$6:$BM$36,65,0) -> 0 | AA31: =VLOOKUP($A31,[18]HISTOMARS23!$A$6:$AU$36,43,0) -> 0 | AB31: =VLOOKUP($A31,[18]HISTOMARS23!$A$6:$AU$36,44,0) -> 0 | AC31: =VLOOKUP($A31,[18]HISTOMARS23!$A$6:$AU$36,47,0) -> 0 | AD31: =VLOOKUP(A31,[18]HISTOMARS23!$A$6:$BB$36,54,0) -> 70000 | AE31: =VLOOKUP($A31,[18]HISTOMARS23!$A$6:$CA$36,60,0) -> 0 | AF31: =VLOOKUP($A31,[18]HISTOMARS23!$A$6:$CA$36,61,0) -> 0 | AG31: =VLOOKUP($A31,[18]HISTOMARS23!$A$6:$CA$36,62,0) -> 0 | AH31: =VLOOKUP($A31,[18]HISTOMARS23!$A$6:$CA$36,63,0) -> 0 | AI31: =VLOOKUP($A31,[18]HISTOMARS23!$A$6:$CA$36,64,0) -> 0 | AJ31: =VLOOKUP($A31,[18]HISTOMARS23!$A$6:$CA$36,65,0) -> 0
A32: AS201641 | B32: =VLOOKUP(A32,[15]LISTADHERENT!A$5:H$60,3,0) -> TCHOUAMOU MATHIEU | E32: =VLOOKUP($A32,[18]HISTOMARS23!$A$6:$BA$36,48,0) -> 0 | F32: =MVTFEV23!F32+MVTFEV23!G32-MVTMARS23!E32+K32 -> 670493.54 | G32: 181.30546 | H32: =F32+G32 -> 670674.85 | I32: =VLOOKUP($A32,[18]HISTOMARS23!$A$6:$AQ$40,22,0) -> 0 | J32: =VLOOKUP($A32,[18]HISTOMARS23!$A$6:$AU$36,45,0) -> 15000 | K32: =IF(J32=0,0,J32-(L32+M32+N32)) -> 9000 | L32: =IF(J32=0,0,1000) -> 1000 | M32: =IF(J32=0,0,1000) -> 1000 | N32: =IF(J32=0,0,4000) -> 4000 | O32: =VLOOKUP($A32,[18]HISTOMARS23!$A$6:$AU$36,7,0) -> 0 | P32: =VLOOKUP($A32,[18]HISTOMARS23!$A$6:$AU$36,23,0) -> 0 | Q32: =VLOOKUP($A32,[18]HISTOMARS23!$A$6:$AU$36,46,0) -> 0 | R32: =VLOOKUP($A32,[18]HISTOMARS23!$A$6:$AU$36,26,0) -> 200000 | S32: =VLOOKUP($A32,[18]HISTOMARS23!$A$6:$BG$36,58,0) -> 6000 | T32: =VLOOKUP($A32,[18]HISTOMARS23!$A$6:$AU$36,28,0) -> 0 | U32: =VLOOKUP($A32,[18]HISTOMARS23!$A$6:$AU$36,19,0) -> 0 | V32: =VLOOKUP($A32,[18]HISTOMARS23!$A$6:$AU$36,20,0) -> 0 | W32: =VLOOKUP($A32,[18]HISTOMARS23!$A$6:$AU$36,27,0) -> BANQUE | X32: =VLOOKUP($A32,[18]HISTOMARS23!$A$6:$BM$36,33,0) -> 0 | Y32: =VLOOKUP($A32,[18]HISTOMARS23!$A$6:$BM$36,65,0) -> 0 | AA32: =VLOOKUP($A32,[18]HISTOMARS23!$A$6:$AU$36,43,0) -> 0 | AB32: =VLOOKUP($A32,[18]HISTOMARS23!$A$6:$AU$36,44,0) -> 0 | AC32: =VLOOKUP($A32,[18]HISTOMARS23!$A$6:$AU$36,47,0) -> 0 | AD32: =VLOOKUP(A32,[18]HISTOMARS23!$A$6:$BB$36,54,0) -> 0 | AE32: =VLOOKUP($A32,[18]HISTOMARS23!$A$6:$CA$36,60,0) -> 0 | AF32: =VLOOKUP($A32,[18]HISTOMARS23!$A$6:$CA$36,61,0) -> 0 | AG32: =VLOOKUP($A32,[18]HISTOMARS23!$A$6:$CA$36,62,0) -> 0 | AH32: =VLOOKUP($A32,[18]HISTOMARS23!$A$6:$CA$36,63,0) -> 0 | AI32: =VLOOKUP($A32,[18]HISTOMARS23!$A$6:$CA$36,64,0) -> 0 | AJ32: =VLOOKUP($A32,[18]HISTOMARS23!$A$6:$CA$36,65,0) -> 0
A33: AS201643 | B33: =VLOOKUP(A33,[15]LISTADHERENT!A$5:H$60,3,0) -> TCHOUTOU NANA CLAUDE | E33: =VLOOKUP($A33,[18]HISTOMARS23!$A$6:$BA$36,48,0) -> 0 | F33: =MVTFEV23!F33+MVTFEV23!G33-MVTMARS23!E33+K33 -> 27000 | G33: 0 | H33: =F33+G33 -> 27000 | I33: =VLOOKUP($A33,[18]HISTOMARS23!$A$6:$AQ$40,22,0) -> 0 | J33: =VLOOKUP($A33,[18]HISTOMARS23!$A$6:$AU$36,45,0) -> 15000 | K33: =IF(J33=0,0,J33-(L33+M33+N33)) -> 9000 | L33: =IF(J33=0,0,1000) -> 1000 | M33: =IF(J33=0,0,1000) -> 1000 | N33: =IF(J33=0,0,4000) -> 4000 | O33: =VLOOKUP($A33,[18]HISTOMARS23!$A$6:$AU$36,7,0) -> 0 | P33: =VLOOKUP($A33,[18]HISTOMARS23!$A$6:$AU$36,23,0) -> 0 | Q33: =VLOOKUP($A33,[18]HISTOMARS23!$A$6:$AU$36,46,0) -> 0 | R33: =VLOOKUP($A33,[18]HISTOMARS23!$A$6:$AU$36,26,0) -> 0 | S33: =VLOOKUP($A33,[18]HISTOMARS23!$A$6:$BG$36,58,0) -> 0 | T33: =VLOOKUP($A33,[18]HISTOMARS23!$A$6:$AU$36,28,0) -> 0 | U33: =VLOOKUP($A33,[18]HISTOMARS23!$A$6:$AU$36,19,0) -> 0 | V33: =VLOOKUP($A33,[18]HISTOMARS23!$A$6:$AU$36,20,0) -> 0 | W33: =VLOOKUP($A33,[18]HISTOMARS23!$A$6:$AU$36,27,0) -> 0 | X33: =VLOOKUP($A33,[18]HISTOMARS23!$A$6:$BM$36,33,0) -> 0 | Y33: =VLOOKUP($A33,[18]HISTOMARS23!$A$6:$BM$36,65,0) -> 0 | AA33: =VLOOKUP($A33,[18]HISTOMARS23!$A$6:$AU$36,43,0) -> 0 | AB33: =VLOOKUP($A33,[18]HISTOMARS23!$A$6:$AU$36,44,0) -> 0 | AC33: =VLOOKUP($A33,[18]HISTOMARS23!$A$6:$AU$36,47,0) -> 0 | AD33: =VLOOKUP(A33,[18]HISTOMARS23!$A$6:$BB$36,54,0) -> 0 | AE33: =VLOOKUP($A33,[18]HISTOMARS23!$A$6:$CA$36,60,0) -> 0 | AF33: =VLOOKUP($A33,[18]HISTOMARS23!$A$6:$CA$36,61,0) -> 0 | AG33: =VLOOKUP($A33,[18]HISTOMARS23!$A$6:$CA$36,62,0) -> 0 | AH33: =VLOOKUP($A33,[18]HISTOMARS23!$A$6:$CA$36,63,0) -> 0 | AI33: =VLOOKUP($A33,[18]HISTOMARS23!$A$6:$CA$36,64,0) -> 0 | AJ33: =VLOOKUP($A33,[18]HISTOMARS23!$A$6:$CA$36,65,0) -> 0
A34: AS201658 | B34: =VLOOKUP(A34,[15]LISTADHERENT!A$5:H$60,3,0) -> YANTCHOU GERVAIS | E34: =VLOOKUP($A34,[18]HISTOMARS23!$A$6:$BA$36,48,0) -> 0 | F34: =MVTFEV23!F34+MVTFEV23!G34-MVTMARS23!E34+K34 -> 62000 | G34: 0 | H34: =F34+G34 -> 62000 | I34: =VLOOKUP($A34,[18]HISTOMARS23!$A$6:$AQ$40,22,0) -> 0 | J34: =VLOOKUP($A34,[18]HISTOMARS23!$A$6:$AU$36,45,0) -> 50000 | K34: =IF(J34=0,0,J34-(L34+M34+N34)) -> 44000 | L34: =IF(J34=0,0,1000) -> 1000 | M34: =IF(J34=0,0,1000) -> 1000 | N34: =IF(J34=0,0,4000) -> 4000 | O34: =VLOOKUP($A34,[18]HISTOMARS23!$A$6:$AU$36,7,0) -> 0 | P34: =VLOOKUP($A34,[18]HISTOMARS23!$A$6:$AU$36,23,0) -> 0 | Q34: =VLOOKUP($A34,[18]HISTOMARS23!$A$6:$AU$36,46,0) -> 25000 | R34: =VLOOKUP($A34,[18]HISTOMARS23!$A$6:$AU$36,26,0) -> 0 | S34: =VLOOKUP($A34,[18]HISTOMARS23!$A$6:$BG$36,58,0) -> 0 | T34: =VLOOKUP($A34,[18]HISTOMARS23!$A$6:$AU$36,28,0) -> 0 | U34: =VLOOKUP($A34,[18]HISTOMARS23!$A$6:$AU$36,19,0) -> 0 | V34: =VLOOKUP($A34,[18]HISTOMARS23!$A$6:$AU$36,20,0) -> 0 | W34: =VLOOKUP($A34,[18]HISTOMARS23!$A$6:$AU$36,27,0) -> 0 | X34: =VLOOKUP($A34,[18]HISTOMARS23!$A$6:$BM$36,33,0) -> 0 | Y34: =VLOOKUP($A34,[18]HISTOMARS23!$A$6:$BM$36,65,0) -> 0 | AA34: =VLOOKUP($A34,[18]HISTOMARS23!$A$6:$AU$36,43,0) -> 0 | AB34: =VLOOKUP($A34,[18]HISTOMARS23!$A$6:$AU$36,44,0) -> 0 | AC34: =VLOOKUP($A34,[18]HISTOMARS23!$A$6:$AU$36,47,0) -> 0 | AD34: =VLOOKUP(A34,[18]HISTOMARS23!$A$6:$BB$36,54,0) -> 0 | AE34: =VLOOKUP($A34,[18]HISTOMARS23!$A$6:$CA$36,60,0) -> 0 | AF34: =VLOOKUP($A34,[18]HISTOMARS23!$A$6:$CA$36,61,0) -> 0 | AG34: =VLOOKUP($A34,[18]HISTOMARS23!$A$6:$CA$36,62,0) -> 0 | AH34: =VLOOKUP($A34,[18]HISTOMARS23!$A$6:$CA$36,63,0) -> 0 | AI34: =VLOOKUP($A34,[18]HISTOMARS23!$A$6:$CA$36,64,0) -> 0 | AJ34: =VLOOKUP($A34,[18]HISTOMARS23!$A$6:$CA$36,65,0) -> 0
A35: AS201646 | B35: =VLOOKUP(A35,[15]LISTADHERENT!A$5:H$60,3,0) -> YEPMOU JEAN JACQUES | E35: =VLOOKUP($A35,[18]HISTOMARS23!$A$6:$BA$36,48,0) -> 0 | F35: =MVTFEV23!F35+MVTFEV23!G35-MVTMARS23!E35+K35 -> 1634185.5 | G35: 441.89353 | H35: =F35+G35 -> 1634627.4 | I35: =VLOOKUP($A35,[18]HISTOMARS23!$A$6:$AQ$40,22,0) -> 0 | J35: =VLOOKUP($A35,[18]HISTOMARS23!$A$6:$AU$36,45,0) -> 9000 | K35: =IF(J35=0,0,J35-(L35+M35+N35)) -> 3000 | L35: =IF(J35=0,0,1000) -> 1000 | M35: =IF(J35=0,0,1000) -> 1000 | N35: =IF(J35=0,0,4000) -> 4000 | O35: =VLOOKUP($A35,[18]HISTOMARS23!$A$6:$AU$36,7,0) -> 0 | P35: =VLOOKUP($A35,[18]HISTOMARS23!$A$6:$AU$36,23,0) -> 0 | Q35: =VLOOKUP($A35,[18]HISTOMARS23!$A$6:$AU$36,46,0) -> 0 | R35: =VLOOKUP($A35,[18]HISTOMARS23!$A$6:$AU$36,26,0) -> 0 | S35: =VLOOKUP($A35,[18]HISTOMARS23!$A$6:$BG$36,58,0) -> 0 | T35: =VLOOKUP($A35,[18]HISTOMARS23!$A$6:$AU$36,28,0) -> 0 | U35: =VLOOKUP($A35,[18]HISTOMARS23!$A$6:$AU$36,19,0) -> 0 | V35: =VLOOKUP($A35,[18]HISTOMARS23!$A$6:$AU$36,20,0) -> 0 | W35: =VLOOKUP($A35,[18]HISTOMARS23!$A$6:$AU$36,27,0) -> 0 | X35: =VLOOKUP($A35,[18]HISTOMARS23!$A$6:$BM$36,33,0) -> 0 | Y35: =VLOOKUP($A35,[18]HISTOMARS23!$A$6:$BM$36,65,0) -> 0 | AA35: =VLOOKUP($A35,[18]HISTOMARS23!$A$6:$AU$36,43,0) -> 0 | AB35: =VLOOKUP($A35,[18]HISTOMARS23!$A$6:$AU$36,44,0) -> 0 | AC35: =VLOOKUP($A35,[18]HISTOMARS23!$A$6:$AU$36,47,0) -> 0 | AD35: =VLOOKUP(A35,[18]HISTOMARS23!$A$6:$BB$36,54,0) -> 0 | AE35: =VLOOKUP($A35,[18]HISTOMARS23!$A$6:$CA$36,60,0) -> 0 | AF35: =VLOOKUP($A35,[18]HISTOMARS23!$A$6:$CA$36,61,0) -> 0 | AG35: =VLOOKUP($A35,[18]HISTOMARS23!$A$6:$CA$36,62,0) -> 0 | AH35: =VLOOKUP($A35,[18]HISTOMARS23!$A$6:$CA$36,63,0) -> 0 | AI35: =VLOOKUP($A35,[18]HISTOMARS23!$A$6:$CA$36,64,0) -> 0 | AJ35: =VLOOKUP($A35,[18]HISTOMARS23!$A$6:$CA$36,65,0) -> 0
A36: AS201647 | B36: =VLOOKUP(A36,[15]LISTADHERENT!A$5:H$60,3,0) -> YOUMBI EMMANUEL | E36: =VLOOKUP($A36,[18]HISTOMARS23!$A$6:$BA$36,48,0) -> 0 | F36: =MVTFEV23!F36+MVTFEV23!G36-MVTMARS23!E36+K36 -> 1792519.9 | G36: 484.70811 | H36: =F36+G36 -> 1793004.6 | I36: =VLOOKUP($A36,[18]HISTOMARS23!$A$6:$AQ$40,22,0) -> 0 | J36: =VLOOKUP($A36,[18]HISTOMARS23!$A$6:$AU$36,45,0) -> 15000 | K36: =IF(J36=0,0,J36-(L36+M36+N36)) -> 9000 | L36: =IF(J36=0,0,1000) -> 1000 | M36: =IF(J36=0,0,1000) -> 1000 | N36: =IF(J36=0,0,4000) -> 4000 | O36: =VLOOKUP($A36,[18]HISTOMARS23!$A$6:$AU$36,7,0) -> 0 | P36: =VLOOKUP($A36,[18]HISTOMARS23!$A$6:$AU$36,23,0) -> 0 | Q36: =VLOOKUP($A36,[18]HISTOMARS23!$A$6:$AU$36,46,0) -> 0 | R36: =VLOOKUP($A36,[18]HISTOMARS23!$A$6:$AU$36,26,0) -> 0 | S36: =VLOOKUP($A36,[18]HISTOMARS23!$A$6:$BG$36,58,0) -> 0 | T36: =VLOOKUP($A36,[18]HISTOMARS23!$A$6:$AU$36,28,0) -> 0 | U36: =VLOOKUP($A36,[18]HISTOMARS23!$A$6:$AU$36,19,0) -> 0 | V36: =VLOOKUP($A36,[18]HISTOMARS23!$A$6:$AU$36,20,0) -> 0 | W36: =VLOOKUP($A36,[18]HISTOMARS23!$A$6:$AU$36,27,0) -> 0 | X36: =VLOOKUP($A36,[18]HISTOMARS23!$A$6:$BM$36,33,0) -> 0 | Y36: =VLOOKUP($A36,[18]HISTOMARS23!$A$6:$BM$36,65,0) -> 0 | AA36: =VLOOKUP($A36,[18]HISTOMARS23!$A$6:$AU$36,43,0) -> 0 | AB36: =VLOOKUP($A36,[18]HISTOMARS23!$A$6:$AU$36,44,0) -> 0 | AC36: =VLOOKUP($A36,[18]HISTOMARS23!$A$6:$AU$36,47,0) -> 0 | AD36: =VLOOKUP(A36,[18]HISTOMARS23!$A$6:$BB$36,54,0) -> 0 | AE36: =VLOOKUP($A36,[18]HISTOMARS23!$A$6:$CA$36,60,0) -> 0 | AF36: =VLOOKUP($A36,[18]HISTOMARS23!$A$6:$CA$36,61,0) -> 0 | AG36: =VLOOKUP($A36,[18]HISTOMARS23!$A$6:$CA$36,62,0) -> 0 | AH36: =VLOOKUP($A36,[18]HISTOMARS23!$A$6:$CA$36,63,0) -> 0 | AI36: =VLOOKUP($A36,[18]HISTOMARS23!$A$6:$CA$36,64,0) -> 0 | AJ36: =VLOOKUP($A36,[18]HISTOMARS23!$A$6:$CA$36,65,0) -> 0
A40: TOTAL | C40: =SUM(C6:C39) -> 0 | D40: =SUM(D6:D39) -> 0 | E40: =SUM(E6:E39) -> 0 | F40: =SUM(F6:F39) -> 22341858 | G40: =SUM(G6:G39) -> 6000 | H40: =SUM(H6:H39) -> 22347858 | I40: =SUM(I6:I39) -> 0 | J40: =SUM(J6:J39) -> 527000 | ... AJ40: =SUM(AJ6:AJ39) -> 0

Sheet MVTAVRIL23
A1: ASSOCIATION | B1: ASELBY | G1: K
A2: ANNEE | B2: 2023
A3: TONTINE
J4: 45033
A5: MATRICULE | B5: NOM ET PRENOM | C5: FONDES DE DEPART | D5: RECONDUCTION | E5: RETRAIT PARTIEL | F5: FONDS DEFINITIF | G5: REPARTITION INTERET | H5: CAPITAL COMPOSE | I5: SANCTION | J5: RESTE | K5: EPARGNE | L5: FONDS DE ROULEMENT | M5: FRAIS EXCEPTIONNEL | N5: COLLATION | O5: PENALITE VST ESPECES | P5: INSCRISPTION | Q5: MUTUELLE | R5: PRÊT FONDS | S5: INTERETPRET FONDS | T5: NUMERO CHEQUE | U5: REMBOURSEMENTPRET FONDS | V5: MODE VERSEMENT REMBOURSEMENT | W5: MODE VERSEMENT PRÊT | X5: NUMERO CHEQUE | Y5: PENALITE PRET FONDS | Z5: PENALITE FONDS | AA5: PENALITE ECHEC TONTINE | AB5: PENALITE RETARD TONTINE | AC5: REMBOURSEMENT TRANSPORT | AD5: CONTRIBUTION FOYER | AE5: FONDS DE ROULEMENT | AF5: FRAIS EXCEPTIONNEL | AG5: FONDS MUTUELLE | AH5: COLLATION RECEPTION | AI5: PENALITE PRET FONDS | AJ5: DEPENSE PENALITE VERSEMENT BANQUE
A6: AS201648 | B6: =VLOOKUP(A6,[15]LISTADHERENT!A$5:H$60,3,0) -> ASELBY | F6: =MVTMARS23!F6+MVTMARS23!G6-MVTAVRIL23!E6+K6 -> 869837.1 | G6: 7894.2916 | H6: =F6+G6 -> 877731.39 | AE6: =VLOOKUP($A6,[18]HISTOMARS23!$A$6:$CA$36,60,0) -> 6000 | AF6: =VLOOKUP($A6,[18]HISTOMARS23!$A$6:$CA$36,61,0) -> 0 | AG6: =VLOOKUP($A6,[18]HISTOMARS23!$A$6:$CA$36,62,0) -> 0 | AH6: =VLOOKUP($A6,[18]HISTOMARS23!$A$6:$CA$36,63,0) -> 100000 | AI6: =VLOOKUP($A6,[18]HISTOMARS23!$A$6:$CA$36,64,0) -> 0 | AJ6: =VLOOKUP($A6,[18]HISTOMARS23!$A$6:$CA$36,65,0) -> 0
