Workbook
Name BANQUE: #REF!
Name BANQUE: #REF!
Name BANQUE: #REF!
Name BANQUE: #REF!
Name BANQUE: #REF!
Name BANQUE: #REF!
Name BANQUE: #REF!
Name BANQUE: #REF!
Name BANQUE: #REF!
Name BANQUE: #REF!
Name BANQUE: #REF!
Name BANQUE: #REF!
Name BANQUE: #REF!
Name BANQUE: #REF!
Name BANQUE: #REF!
Name BANQUE: #REF!
Name BANQUE: #REF!
Name BANQUE: #REF!
Name MODEPAID: [1]Feuil2!$A$1:$A$3
Name MODET25000: [2]MODEVERSEMENT!$A$1:$A$3
Name MODEVERSEMENT: #REF!
Name MODEVERSEMENT: #REF!
Name MODEVERSEMENT: #REF!
Name MODEVERSEMENT: #REF!
Name MODEVERSEMENT: #REF!
Name MODEVERSEMENT: #REF!
Name MODEVERSEMENT: #REF!
Name MODEVERSEMENT: #REF!
Name MODEVERSEMENT: #REF!
Name MODEVERSEMENT: #REF!
Name MODEVERSEMENT: #REF!
Name MODEVERSEMENT: #REF!
Name MODEVERSEMENT: #REF!
Name MODEVERSEMENT: #REF!
Name MODEVERSEMENT: #REF!
Name MODEVERSEMENT: #REF!
Name MODEVERSEMENT: #REF!
Name MODEVERSEMENT: #REF!
Name MODEVERSEMENTS: [3]MODEVERSEMENT!$A$1:$A$3
Name MODEVERSEMENTS: [3]MODEVERSEMENT!$A$1:$A$3
Name MODEVERSEMENTS: [3]MODEVERSEMENT!$A$1:$A$3
Name MODEVERSEMENTS: [3]MODEVERSEMENT!$A$1:$A$3
Name MODEVERSEMENTS: [3]MODEVERSEMENT!$A$1:$A$3
Name MODEVERSEMENTS: [3]MODEVERSEMENT!$A$1:$A$3
Name MODEVERSEMENTS: [3]MODEVERSEMENT!$A$1:$A$3
Name MODEVERSEMENTS: [3]MODEVERSEMENT!$A$1:$A$3
Name MODEVERSEMENTS: [3]MODEVERSEMENT!$A$1:$A$3
Name MODEVERSEMENTS: [3]MODEVERSEMENT!$A$1:$A$3
Name MODEVERSEMENTS: [3]MODEVERSEMENT!$A$1:$A$3
Name MODEVERSEMENTS: [3]MODEVERSEMENT!$A$1:$A$3
Name MODEVERSEMENTS: [3]MODEVERSEMENT!$A$1:$A$3
Name MODEVERSEMENTS: [3]MODEVERSEMENT!$A$1:$A$3
Name MODEVERSEMENTS: [3]MODEVERSEMENT!$A$1:$A$3
Name MODEVERSEMENTS: [3]MODEVERSEMENT!$A$1:$A$3
Name MODEVERSEMENTS: MODEVERSEMENT!$A$1:$A$3
Name VALMODEPAID: [4]MODEPAID!$A$1:$A$3

Sheet MODEVERSEMENT
A1: BANQUE
A2: ESPECES
A3: ECHEC

Sheet HISTOMVTDEPENSE
A1: ASSOCIATION | B1: ASELBY
A2: ANNEE | B2: 2022
A3: 1 | B3: 2 | D3: 3 | E3: 4 | F3: 5 | G3: 6 | H3: 7 | I3: 8 | J3: 9 | K3: 10 | L3: 11 | M3: 12 | N3: 13 | O3: 14 | P3: 15 | Q3: 16 | R3: 17 | S3: 18
B4: TABLEAU DE BORD SAISIE DES DEPENSES
A5: MATRICULE | B5: NOM ET PRENOM | D5: FONDS DE ROULEMENT | M5: FRAIS EXCEPTIONNEL | P5: COLLATION | R5: MUTUELLE | T5: TOTAUX
C6: FRAIS BANCAIRE | D6: ACHAT FOURNITURE | E6: COMMUNICATION | F6: COMMISSION | G6: AUTRES AIDES | H6: CREDIT TELEPHONE | I6: PRODUCTION RAPPORT | J6: ACHAT SOURIS ET PHOTOCOPIE | K6: FRAIS DE BANQUE | L6: CONFECTION CACHET | M6: GRATIFICATION BUREAU | N6: DEVELOPPEMENT LAGWEU | O6: DEUIL | P6: COLLATION | Q6: BOISSON | R6: DECES | S6: TRANSPORT DELEGUE
A7: AS201648 | B7: =VLOOKUP(A7,[5]LISTADHERENT!A$5:H$60,3,0) -> ASELBY | T7: =SUM(D7:S7) -> 0
A8: AS201602 | B8: =VLOOKUP(A8,[5]LISTADHERENT!A$5:H$60,3,0) -> BOUTCHOUANG WILLIAM | T8: =SUM(D8:S8) -> 0
A9: AS201604 | B9: =VLOOKUP(A9,[5]LISTADHERENT!A$5:H$60,3,0) -> DJOMO JEAN PAUL | T9: =SUM(D9:S9) -> 0
A10: AS201654 | B10: =VLOOKUP(A10,[5]LISTADHERENT!A$5:H$60,3,0) -> DJOMOU TCHANDA | T10: =SUM(D10:S10) -> 0
A11: AS201605 | B11: =VLOOKUP(A11,[5]LISTADHERENT!A$5:H$60,3,0) -> DJOUKWE NANGUEN GUY BLAISE | T11: =SUM(D11:S11) -> 0
A12: AS201608 | B12: =VLOOKUP(A12,[5]LISTADHERENT!A$5:H$60,3,0) -> DJUOMBESSY ANTOINE | T12: =SUM(D12:S12) -> 0
A13: AS201651 | B13: =VLOOKUP(A13,[5]LISTADHERENT!A$5:H$60,3,0) -> DOMOU FABIEN | T13: =SUM(D13:S13) -> 0
A14: AS201609 | B14: =VLOOKUP(A14,[5]LISTADHERENT!A$5:H$60,3,0) -> DONHOU DAVID | T14: =SUM(D14:S14) -> 0
A15: AS201610 | B15: =VLOOKUP(A15,[5]LISTADHERENT!A$5:H$60,3,0) -> FOTSO THOMAS | T15: =SUM(D15:S15) -> 0
A16: AS201611 | B16: =VLOOKUP(A16,[5]LISTADHERENT!A$5:H$60,3,0) -> HENGUE PAUL OMER | T16: =SUM(D16:S16) -> 0
A17: AS201613 | B17: =VLOOKUP(A17,[5]LISTADHERENT!A$5:H$60,3,0) -> HOTCHO BENJAMIN | T17: =SUM(D17:S17) -> 0
A18: AS201617 | B18: =VLOOKUP(A18,[5]LISTADHERENT!A$5:H$60,3,0) -> KOUAMOU MOISE | T18: =SUM(D18:S18) -> 0
... A37: AS201647 | B37: =VLOOKUP(A37,[5]LISTADHERENT!A$5:H$60,3,0) -> YOUMBI EMMANUEL | T37: =SUM(D37:S37) -> 0
B39: TOTAUX | C39: =SUM(C8:C38) -> 0 | D39: =SUM(D8:D38) -> 0 | E39: =SUM(E8:E38) -> 0 | F39: =SUM(F8:F38) -> 0 | G39: =SUM(G8:G38) -> 0 | H39: =SUM(H8:H38) -> 0 | J39: =SUM(J8:J38) -> 0 | K39: =SUM(K8:K38) -> 0 | L39: =SUM(L8:L38) -> 0 | M39: =SUM(M8:M38) -> 0 | N39: =SUM(N8:N38) -> 0 | O39: =SUM(O8:O38) -> 0 | P39: =SUM(P8:P38) -> 0 | Q39: =SUM(Q8:Q38) -> 0 | ... T39: =SUM(T8:T38) -> 0

Sheet COMPTE BANQUE
C1: COMPTE BANQUE | H1: COMPTE CAISSE
A2: ANNEE | C2: 2022 | H2: 2022
A4: MOIS | B4: NUMERO CHEQUE | C4: SORTIE | D4: ENTREE | E4: SOLDE | G4: NUMERO PIECE | H4: ENTREE | I4: SORTIE | J4: SOLDE
A5: REPORT A NOUVEAU | E5: =14283661-6017000 -> 8266661
A6: JANVIER | C6: =#REF!+HISTOMVTDEPENSE!T39 -> #REF! | D6: =#REF! -> #REF! | E6: =IF(D6=0,0,E5+D6-C6) -> #REF!
A7: FÉVRIER | C7: =#REF! -> #REF! | D7: =#REF! -> #REF! | E7: =IF(D7=0,0,E6+D7-C7) -> #REF!
A8: MARS | C8: =#REF! -> #REF! | D8: =#REF! -> #REF! | E8: =IF(D8=0,0,E7+D8-C8) -> #REF!
A9: AVRIL | C9: =#REF! -> #REF! | D9: =#REF! -> #REF! | E9: =IF(D9=0,0,E8+D9-C9) -> #REF!
A10: MAI | C10: =#REF! -> #REF! | D10: =#REF! -> #REF! | E10: =IF(D10=0,0,E9+D10-C10) -> #REF!
A11: JUIN | C11: =#REF! -> #REF! | D11: =#REF! -> #REF! | E11: =IF(D11=0,0,E10+D11-C11) -> #REF!
A12: JUILLET | C12: =#REF! -> #REF! | D12: =#REF! -> #REF! | E12: =IF(D12=0,0,E11+D12-C12) -> #REF!
A13: AOÛT | C13: =#REF! -> #REF! | D13: =#REF! -> #REF! | E13: =IF(D13=0,0,E12+D13-C13) -> #REF!
A14: SEPTEMBRE | C14: =#REF! -> #REF! | D14: =#REF! -> #REF! | E14: =IF(D14=0,0,E13+D14-C14) -> #REF!
A15: OCTOBRE | C15: =#REF! -> #REF! | D15: =#REF! -> #REF! | E15: =IF(D15=0,0,E14+D15-C15) -> #REF!
A16: NOVEMBRE | C16: =#REF! -> #REF! | D16: =#REF! -> #REF! | E16: =IF(D16=0,0,E15+D16-C16) -> #REF!
A17: DÉCEMBRE | C17: =#REF! -> #REF! | D17: =#REF! -> #REF! | E17: =IF(D17=0,0,E16+D17-C17) -> #REF!
A19: TOTAL

Sheet HISTODEC22
A1: ASSOCIATION | B1: ASELBY
A2: ANNEE | B2: 2022
A3: 1 | B3: 2 | C3: 3 | D3: 4 | E3: 5 | F3: 6 | G3: 7 | H3: 8 | I3: 9 | J3: 10 | K3: 11 | L3: 12 | M3: 13 | N3: 14 | O3: 15 | P3: 16 | Q3: 17 | R3: 18 | S3: 19 | T3: 20 | U3: 21 | V3: 22 | W3: 23 | X3: 24 | Y3: 25 | Z3: 26 | AA3: 27 | AB3: 28 | AC3: 29 | AD3: 30 | AE3: 31 | AF3: 32 | AG3: 33 | AH3: 34 | AI3: 35 | AJ3: 36 | AK3: 37 | AL3: 38 | AM3: 39 | AN3: 40 | AO3: 41 | AP3: 42 | AQ3: 43 | AR3: 44 | AS3: 45 | AT3: 46 | AU3: 47 | AV3: 48 | AW3: 49 | AX3: 50 | AY3: 51 | AZ3: 52 | BA3: 53 | BB3: 54 | BC3: 55 | BD3: 56 | BE3: 57 | BF3: 58 | BG3: 59 | BH3: 60 | BI3: 61 | BJ3: 62 | BK3: 63 | BL3: 64 | BM3: 65 | BN3: 66
B4: TABLEAU DE BORD SAISIE DES DONNEES
A5: MATRICULE | B5: NOM ET PRENOM | C5: BONUS MALUS | D5: HISTORIQUE BANQUE | E5: HITORIQUE ESPECES | F5: HITORIQUE TONTINE | G5: PENALITE VERSEMENT ESPECES | H5: MODE PAIEMENT TONTINE | I5: NBRE DE LOT | J5: TONTINE 35 000 | K5: COMPLEMENT EPARGNE | L5: NBRE DE LOT | M5: TONTINE 75 000 | N5: NBRE DE LOT | O5: TONTINE 100 000 | P5: REMBOURSEMENT PETIT LOT T35 | Q5: REMBOURSEMENT PETIT LOT T75 | R5: REMBOURSEMENT PETIT LOT T100 | S5: REMBOURSEMENT PRÊT FONDS | T5: MODE PAIEMENT REMBOURSEMENT PRÊT FONDS | U5: MONTANT ENGAGEMENT | V5: SANCTION | W5: INSCRIPTION | X5: EPARGNE ASSURANCE | Y5: RECONSTITUTION FONDS | Z5: PRÊT FONDS | AA5: MODE PAIEMENT PRÊT | AB5: NUM CHEQUE | AC5: ACHAT LOT PRINCIPAL T30 | AD5: ACHAT LOT PRINCIPAL T75 | AE5: ACHAT LOT PRINCIPAL T100 | AF5: MODE PAIEMENT LOT PRINCIPAL | AG5: NUM CHEQUE | AH5: PENALITE VERSEMENT ESPECES | AI5: VENTE PETIT LOT T30 | AJ5: VENTE PETIT LOT T75 | AK5: VENTE PETIT LOT T100 | AL5: INTERET PETIT LOT T30 | AM5: INTERET PETIT LOT T75 | AN5: INTERET PETIT LOT T100 | AO5: NUM CHEQUE | AP5: MODE PAIEMENT PETEIT LOT | AQ5: PENELAITE RETARD TONTINE | AR5: PENELAITE ECHEC TONTINE | AS5: RESTE | AT5: MUTUELLE | AU5: REMBOURSEMENT TRANSPORT | AV5: RETRAIT PARTIEL FONDS | AW5: MONTANT T30 | AX5: MONTANT T75 | AY5: MONTANT T100 | AZ5: MONTANT CHEQUE | BA5: MONTANT ESPECES | BB5: CONTRIBUTION FOYER | BC5: AUTRES SOTIES | BD5: MONTANT CHEQUE EFFECTIF | BE5: NUMERO CHEQUE | BF5: INTERET PRÊT | BG5: NBRE MOIS | BH5: DEPENSE FONDS DE ROULEMENT | BI5: DEPENSE FRAIS EXCEPTIONNEL | BJ5: DEPENSE FONDS MUTUEL | BK5: DEPENSE COLLATION RECEPTION | BL5: PENALITE PRET FONDS | BM5: DEPENSE PENALITE VERSEMENT BANQUE | BN5: LIBELLE | BO5: COMPTE | BP5: MONTANT
A6: AS201648 | B6: =VLOOKUP(A6,[6]LISTADHERENT!A$5:H$60,3,0) -> ASELBY | C6: =D6+E6+F6-U6-BB6 -> 0 | D6: =VLOOKUP(A6,[7]HISTOBQUEDEC22!$A$6:$G$36,3,0) -> 100000 | E6: =VLOOKUP(A6,[7]HISTOBQUEDEC22!$A$6:$G$36,4,0) -> 0 | F6: =VLOOKUP(A6,[7]HISTOBQUEDEC22!$A$6:$G$36,5,0) -> 0 | G6: =IF(H6="ESPECES",3000,0) -> 0 | H6: =IF($D6<>0,"BANQUE",IF($E6<>0,"ESPECES","ECHEC")) -> BANQUE | J6: =IF($D6<>0,I6*30000,IF($E6<>0,I6*30000,0)) -> 0 | M6: =IF($D6<>0,L6*75000,IF($E6<>0,L6*75000,0)) -> 0 | N6: 1 | O6: =IF($D6<>0,N6*100000,IF($E6<>0,N6*100000,0)) -> 100000 | R6: =VLOOKUP(A6,[8]TONTDEC22!$A$6:$P$21,10,0) -> 0 | U6: =G6+S6++R6+P6+O6+M6+K6+J6+Q6+V6+W6 -> 100000 | AE6: 100000 | AF6: BANQUE | AQ6: =IF(H6="ECHEC",((J6+M6+O6)*20/100),0) -> 0 | AR6: =IF(H6="ECHEC",((J6+M6+O6)*20/100),0) -> 0 | AW6: =IF(AC6=0,AI6,(1*23000*13)+(1000+AI6)-AC6) -> 0 | AX6: =IF(AD6=0,AJ6,(1*75000*16)+(AJ6)-AD6) -> 0 | AY6: =IF(AE6=0,AK6,(1*100000*13)+(AK6)-AE6) -> 1200000 | AZ6: =SUM(AV6:AY6)-BF6+Z6-F6+BH6+BI6+BJ6+BK6 -> 1206000 | BD6: =IF(AZ6=0,(AZ6-BA6-BC6),(AZ6-BA6-BB6-BC6)) -> 1206000 | BF6: =Z6*1/100*BG6 -> 0 | BG6: 0 | BH6: =BP16 -> 6000 | BI6: =BP28 -> 0 | BJ6: =BP33 -> 0 | BM6: =BP22 -> 0 | BN6: ACHAT FOURNITURE | BO6: FONDS DE ROULEMENT
A7: AS201602 | B7: =VLOOKUP(A7,[6]LISTADHERENT!A$5:H$60,3,0) -> BOUTCHOUANG WILLIAM | C7: =D7+E7+F7-U7-BB7 -> 0 | D7: =VLOOKUP(A7,[7]HISTOBQUEDEC22!$A$6:$G$36,3,0) -> 105000 | E7: =VLOOKUP(A7,[7]HISTOBQUEDEC22!$A$6:$G$36,4,0) -> 0 | F7: =VLOOKUP(A7,[7]HISTOBQUEDEC22!$A$6:$G$36,5,0) -> 0 | G7: =IF(H7="ESPECES",3000,0) -> 0 | H7: =IF($D7<>0,"BANQUE",IF($E7<>0,"ESPECES","ECHEC")) -> BANQUE | I7: 1 | J7: =IF($D7<>0,I7*30000,IF($E7<>0,I7*30000,0)) -> 30000 | L7: 1 | M7: =IF($D7<>0,L7*75000,IF($E7<>0,L7*75000,0)) -> 75000 | O7: =IF($D7<>0,N7*100000,IF($E7<>0,N7*100000,0)) -> 0 | P7: =VLOOKUP(A7,[9]TONTDEC22!$A$6:$R$31,12,0) -> 0 | U7: =G7+S7++R7+P7+O7+M7+K7+J7+Q7+V7+W7 -> 105000 | Z7: 500000 | AA7: BANQUE | AQ7: =IF(H7="ECHEC",((J7+M7+O7)*20/100),0) -> 0 | AR7: =IF(H7="ECHEC",((J7+M7+O7)*20/100),0) -> 0 | AS7: =IF(H7="ECHEC",0,(J7+K7-23000)) -> 7000 | AT7: 20000 | AW7: =IF(AC7=0,AI7,(1*23000*13)+(1000+AI7)-AC7) -> 0 | AX7: =IF(AD7=0,AJ7,(1*75000*16)+(AJ7)-AD7) -> 0 | AY7: =IF(AE7=0,AK7,(1*100000*13)+(AK7)-AE7) -> 0 | AZ7: =SUM(AV7:AY7)-BF7+Z7-F7+BH7+BI7+BJ7+BK7 -> 490000 | BD7: =IF(AZ7=0,(AZ7-BA7-BC7),(AZ7-BA7-BB7-BC7)) -> 490000 | BF7: =Z7*1/100*BG7 -> 10000 | BG7: 2 | BN7: COMMUNICATION | BO7: FONDS DE ROULEMENT
A8: AS201604 | B8: =VLOOKUP(A8,[6]LISTADHERENT!A$5:H$60,3,0) -> DJOMO JEAN PAUL | C8: =D8+E8+F8-U8-BB8 -> 0 | D8: =VLOOKUP(A8,[7]HISTOBQUEDEC22!$A$6:$G$36,3,0) -> 1105000 | E8: =VLOOKUP(A8,[7]HISTOBQUEDEC22!$A$6:$G$36,4,0) -> 0 | F8: =VLOOKUP(A8,[7]HISTOBQUEDEC22!$A$6:$G$36,5,0) -> 0 | G8: =IF(H8="ESPECES",3000,0) -> 0 | H8: =IF($D8<>0,"BANQUE",IF($E8<>0,"ESPECES","ECHEC")) -> BANQUE | I8: 1 | J8: =IF($D8<>0,I8*30000,IF($E8<>0,I8*30000,0)) -> 30000 | L8: 1 | M8: =IF($D8<>0,L8*75000,IF($E8<>0,L8*75000,0)) -> 75000 | O8: =IF($D8<>0,N8*100000,IF($E8<>0,N8*100000,0)) -> 0 | P8: =VLOOKUP(A8,[9]TONTDEC22!$A$6:$R$31,12,0) -> 0 | Q8: =VLOOKUP(A8,[10]TONTDEC22!$A$6:$P$21,10,0) -> 0 | S8: =775000+130000+95000 -> 1000000 | T8: BANQUE | U8: =G8+S8++R8+P8+O8+M8+K8+J8+Q8+V8+W8 -> 1105000 | Z8: 1000000 | AA8: BANQUE | AQ8: =IF(H8="ECHEC",((J8+M8+O8)*20/100),0) -> 0 | AR8: =IF(H8="ECHEC",((J8+M8+O8)*20/100),0) -> 0 | AS8: =IF(H8="ECHEC",0,(J8+K8-23000)) -> 7000 | AT8: 20000 | AW8: =IF(AC8=0,AI8,(1*23000*13)+(1000+AI8)-AC8) -> 0 | AX8: =IF(AD8=0,AJ8,(1*75000*16)+(AJ8)-AD8) -> 0 | AY8: =IF(AE8=0,AK8,(1*100000*13)+(AK8)-AE8) -> 0 | AZ8: =SUM(AV8:AY8)-BF8+Z8-F8+BH8+BI8+BJ8+BK8 -> 880000 | BD8: =IF(AZ8=0,(AZ8-BA8-BC8),(AZ8-BA8-BB8-BC8)) -> 880000 | BF8: =Z8*1/100*BG8 -> 120000 | BG8: 12 | BN8: COMMISSION | BO8: FONDS DE ROULEMENT
A9: AS201654 | B9: =VLOOKUP(A9,[6]LISTADHERENT!A$5:H$60,3,0) -> DJOMOU TCHANDA | C9: =D9+E9+F9-U9-BB9 -> 0 | D9: =VLOOKUP(A9,[7]HISTOBQUEDEC22!$A$6:$G$36,3,0) -> 30000 | E9: =VLOOKUP(A9,[7]HISTOBQUEDEC22!$A$6:$G$36,4,0) -> 0 | F9: =VLOOKUP(A9,[7]HISTOBQUEDEC22!$A$6:$G$36,5,0) -> 0 | G9: =IF(H9="ESPECES",3000,0) -> 0 | H9: =IF($D9<>0,"BANQUE",IF($E9<>0,"ESPECES","ECHEC")) -> BANQUE | I9: 1 | J9: =IF($D9<>0,I9*30000,IF($E9<>0,I9*30000,0)) -> 30000 | M9: =IF($D9<>0,L9*75000,IF($E9<>0,L9*75000,0)) -> 0 | O9: =IF($D9<>0,N9*100000,IF($E9<>0,N9*100000,0)) -> 0 | P9: =VLOOKUP(A9,[9]TONTDEC22!$A$6:$R$31,12,0) -> 0 | U9: =G9+S9++R9+P9+O9+M9+K9+J9+Q9+V9+W9 -> 30000 | AQ9: =IF(H9="ECHEC",((J9+M9+O9)*20/100),0) -> 0 | AR9: =IF(H9="ECHEC",((J9+M9+O9)*20/100),0) -> 0 | AS9: =IF(H9="ECHEC",0,(J9+K9-23000)) -> 7000 | AT9: 20000 | AW9: =IF(AC9=0,AI9,(1*23000*13)+(1000+AI9)-AC9) -> 0 | AX9: =IF(AD9=0,AJ9,(1*75000*16)+(AJ9)-AD9) -> 0 | AY9: =IF(AE9=0,AK9,(1*100000*13)+(AK9)-AE9) -> 0 | AZ9: =SUM(AV9:AY9)-BF9+Z9-F9+BH9+BI9+BJ9+BK9 -> 0 | BD9: =IF(AZ9=0,(AZ9-BA9-BC9),(AZ9-BA9-BB9-BC9)) -> 0 | BF9: =Z9*1/100*BG9 -> 0 | BG9: 0 | BN9: AIDE UEEB ET CONT FEMME | BO9: FONDS DE ROULEMENT
A10: AS201605 | B10: =VLOOKUP(A10,[6]LISTADHERENT!A$5:H$60,3,0) -> DJOUKWE NANGUEN GUY BLAISE | C10: =D10+E10+F10-U10-BB10 -> 0 | D10: =VLOOKUP(A10,[7]HISTOBQUEDEC22!$A$6:$G$36,3,0) -> 1105000 | E10: =VLOOKUP(A10,[7]HISTOBQUEDEC22!$A$6:$G$36,4,0) -> 0 | F10: =VLOOKUP(A10,[7]HISTOBQUEDEC22!$A$6:$G$36,5,0) -> 0 | G10: =IF(H10="ESPECES",3000,0) -> 0 | H10: =IF($D10<>0,"BANQUE",IF($E10<>0,"ESPECES","ECHEC")) -> BANQUE | I10: 1 | J10: =IF($D10<>0,I10*30000,IF($E10<>0,I10*30000,0)) -> 30000 | L10: 1 | M10: =IF($D10<>0,L10*75000,IF($E10<>0,L10*75000,0)) -> 75000 | O10: =IF($D10<>0,N10*100000,IF($E10<>0,N10*100000,0)) -> 0 | P10: =VLOOKUP(A10,[9]TONTDEC22!$A$6:$R$31,12,0) -> 0 | Q10: =VLOOKUP(A10,[10]TONTDEC22!$A$6:$P$21,10,0) -> 0 | S10: =900000+100000 -> 1000000 | T10: BANQUE | U10: =G10+S10++R10+P10+O10+M10+K10+J10+Q10+V10+W10 -> 1105000 | Z10: 1000000 | AA10: BANQUE | AQ10: =IF(H10="ECHEC",((J10+M10+O10)*20/100),0) -> 0 | AR10: =IF(H10="ECHEC",((J10+M10+O10)*20/100),0) -> 0 | AS10: =IF(H10="ECHEC",0,(J10+K10-23000)) -> 7000 | AT10: 20000 | AW10: =IF(AC10=0,AI10,(1*23000*13)+(1000+AI10)-AC10) -> 0 | AX10: =IF(AD10=0,AJ10,(1*75000*16)+(AJ10)-AD10) -> 0 | AY10: =IF(AE10=0,AK10,(1*100000*13)+(AK10)-AE10) -> 0 | AZ10: =SUM(AV10:AY10)-BF10+Z10-F10+BH10+BI10+BJ10+BK10 -> 960000 | BD10: =IF(AZ10=0,(AZ10-BA10-BC10),(AZ10-BA10-BB10-BC10)) -> 960000 | BF10: =Z10*1/100*BG10 -> 40000 | BG10: 4 | BN10: CREDIT TELEPHONE | BO10: FONDS DE ROULEMENT
A11: AS201608 | B11: =VLOOKUP(A11,[6]LISTADHERENT!A$5:H$60,3,0) -> DJUOMBESSY ANTOINE | C11: =D11+E11+F11-U11-BB11 -> 0 | D11: =VLOOKUP(A11,[7]HISTOBQUEDEC22!$A$6:$G$36,3,0) -> 215000 | E11: =VLOOKUP(A11,[7]HISTOBQUEDEC22!$A$6:$G$36,4,0) -> 0 | F11: =VLOOKUP(A11,[7]HISTOBQUEDEC22!$A$6:$G$36,5,0) -> 0 | G11: =IF(H11="ESPECES",3000,0) -> 0 | H11: =IF($D11<>0,"BANQUE",IF($E11<>0,"ESPECES","ECHEC")) -> BANQUE | I11: 1 | J11: =IF($D11<>0,I11*30000,IF($E11<>0,I11*30000,0)) -> 30000 | K11: 1000 | L11: 1 | M11: =IF($D11<>0,L11*75000,IF($E11<>0,L11*75000,0)) -> 75000 | N11: 1 | O11: =IF($D11<>0,N11*100000,IF($E11<>0,N11*100000,0)) -> 100000 | P11: =VLOOKUP(A11,[9]TONTDEC22!$A$6:$R$31,12,0) -> 0 | Q11: =VLOOKUP(A11,[10]TONTDEC22!$A$6:$P$21,10,0) -> 0 | R11: =VLOOKUP(A11,[8]TONTDEC22!$A$6:$P$21,10,0) -> 0 | U11: =G11+S11++R11+P11+O11+M11+K11+J11+Q11+V11+W11 -> 206000 | Z11: 1000000 | AA11: BANQUE | AQ11: =IF(H11="ECHEC",((J11+M11+O11)*20/100),0) -> 0 | AR11: =IF(H11="ECHEC",((J11+M11+O11)*20/100),0) -> 0 | AS11: =IF(H11="ECHEC",0,(J11+K11-23000)) -> 8000 | AT11: 20000 | AW11: =IF(AC11=0,AI11,(1*23000*13)+(1000+AI11)-AC11) -> 0 | AX11: =IF(AD11=0,AJ11,(1*75000*16)+(AJ11)-AD11) -> 0 | AY11: =IF(AE11=0,AK11,(1*100000*13)+(AK11)-AE11) -> 0 | AZ11: =SUM(AV11:AY11)-BF11+Z11-F11+BH11+BI11+BJ11+BK11 -> 940000 | BB11: 9000 | BD11: =IF(AZ11=0,(AZ11-BA11-BC11),(AZ11-BA11-BB11-BC11)) -> 931000 | BF11: =Z11*1/100*BG11 -> 60000 | BG11: 6 | BN11: PRODUCTION RAPPORT | BO11: FONDS DE ROULEMENT
A12: AS201651 | B12: =VLOOKUP(A12,[6]LISTADHERENT!A$5:H$60,3,0) -> DOMOU FABIEN | C12: =D12+E12+F12-U12-BB12 -> 0 | D12: =VLOOKUP(A12,[7]HISTOBQUEDEC22!$A$6:$G$36,3,0) -> 1035000 | E12: =VLOOKUP(A12,[7]HISTOBQUEDEC22!$A$6:$G$36,4,0) -> 0 | F12: =VLOOKUP(A12,[7]HISTOBQUEDEC22!$A$6:$G$36,5,0) -> 0 | G12: =IF(H12="ESPECES",3000,0) -> 0 | H12: =IF($D12<>0,"BANQUE",IF($E12<>0,"ESPECES","ECHEC")) -> BANQUE | I12: 1 | J12: =IF($D12<>0,I12*30000,IF($E12<>0,I12*30000,0)) -> 30000 | K12: 5000 | M12: =IF($D12<>0,L12*75000,IF($E12<>0,L12*75000,0)) -> 0 | O12: =IF($D12<>0,N12*100000,IF($E12<>0,N12*100000,0)) -> 0 | P12: =VLOOKUP(A12,[9]TONTDEC22!$A$6:$R$31,12,0) -> 0 | S12: 1000000 | T12: BANQUE | U12: =G12+S12++R12+P12+O12+M12+K12+J12+Q12+V12+W12 -> 1035000 | Z12: 1000000 | AA12: BANQUE | AQ12: =IF(H12="ECHEC",((J12+M12+O12)*20/100),0) -> 0 | AR12: =IF(H12="ECHEC",((J12+M12+O12)*20/100),0) -> 0 | AS12: =IF(H12="ECHEC",0,(J12+K12-23000)) -> 12000 | AT12: 20000 | AW12: =IF(AC12=0,AI12,(1*23000*13)+(1000+AI12)-AC12) -> 0 | AX12: =IF(AD12=0,AJ12,(1*75000*16)+(AJ12)-AD12) -> 0 | AY12: =IF(AE12=0,AK12,(1*100000*13)+(AK12)-AE12) -> 0 | AZ12: =SUM(AV12:AY12)-BF12+Z12-F12+BH12+BI12+BJ12+BK12 -> 880000 | BD12: =IF(AZ12=0,(AZ12-BA12-BC12),(AZ12-BA12-BB12-BC12)) -> 880000 | BF12: =Z12*1/100*BG12 -> 120000 | BG12: 12 | BN12: ACHAT SOURIS ET PHOTOCOPIE | BO12: FONDS DE ROULEMENT
A13: AS201609 | B13: =VLOOKUP(A13,[6]LISTADHERENT!A$5:H$60,3,0) -> DONHOU DAVID | C13: =D13+E13+F13-U13-BB13 -> 0 | D13: =VLOOKUP(A13,[7]HISTOBQUEDEC22!$A$6:$G$36,3,0) -> 35000 | E13: =VLOOKUP(A13,[7]HISTOBQUEDEC22!$A$6:$G$36,4,0) -> 0 | F13: =VLOOKUP(A13,[7]HISTOBQUEDEC22!$A$6:$G$36,5,0) -> 0 | G13: =IF(H13="ESPECES",3000,0) -> 0 | H13: =IF($D13<>0,"BANQUE",IF($E13<>0,"ESPECES","ECHEC")) -> BANQUE | I13: 1 | J13: =IF($D13<>0,I13*30000,IF($E13<>0,I13*30000,0)) -> 30000 | K13: 5000 | M13: =IF($D13<>0,L13*75000,IF($E13<>0,L13*75000,0)) -> 0 | O13: =IF($D13<>0,N13*100000,IF($E13<>0,N13*100000,0)) -> 0 | P13: =VLOOKUP(A13,[9]TONTDEC22!$A$6:$R$31,12,0) -> 0 | U13: =G13+S13++R13+P13+O13+M13+K13+J13+Q13+V13+W13 -> 35000 | AC13: 23000 | AF13: BANQUE | AQ13: =IF(H13="ECHEC",((J13+M13+O13)*20/100),0) -> 0 | AR13: =IF(H13="ECHEC",((J13+M13+O13)*20/100),0) -> 0 | AS13: =IF(H13="ECHEC",0,(J13+K13-23000)) -> 12000 | AT13: 20000 | AW13: =IF(AC13=0,AI13,(1*23000*13)+(1000+AI13)-AC13) -> 277000 | AX13: =IF(AD13=0,AJ13,(1*75000*16)+(AJ13)-AD13) -> 0 | AY13: =IF(AE13=0,AK13,(1*100000*13)+(AK13)-AE13) -> 0 | AZ13: =SUM(AV13:AY13)-BF13+Z13-F13+BH13+BI13+BJ13+BK13 -> 277000 | BD13: =IF(AZ13=0,(AZ13-BA13-BC13),(AZ13-BA13-BB13-BC13)) -> 277000 | BF13: =Z13*1/100*BG13 -> 0 | BG13: 0 | BN13: TAXI BANQUE | BO13: FONDS DE ROULEMENT | BP13: 6000
A14: AS201610 | B14: =VLOOKUP(A14,[6]LISTADHERENT!A$5:H$60,3,0) -> FOTSO THOMAS | C14: =D14+E14+F14-U14-BB14 -> 0 | D14: =VLOOKUP(A14,[7]HISTOBQUEDEC22!$A$6:$G$36,3,0) -> 0 | E14: =VLOOKUP(A14,[7]HISTOBQUEDEC22!$A$6:$G$36,4,0) -> 0 | F14: =VLOOKUP(A14,[7]HISTOBQUEDEC22!$A$6:$G$36,5,0) -> 0 | G14: =IF(H14="ESPECES",3000,0) -> 0 | H14: =IF($D14<>0,"BANQUE",IF($E14<>0,"ESPECES","ECHEC")) -> ECHEC | J14: =IF($D14<>0,I14*30000,IF($E14<>0,I14*30000,0)) -> 0 | M14: =IF($D14<>0,L14*75000,IF($E14<>0,L14*75000,0)) -> 0 | O14: =IF($D14<>0,N14*100000,IF($E14<>0,N14*100000,0)) -> 0 | U14: =G14+S14++R14+P14+O14+M14+K14+J14+Q14+V14+W14 -> 0 | AQ14: =IF(H14="ECHEC",((J14+M14+O14)*20/100),0) -> 0 | AR14: =IF(H14="ECHEC",((J14+M14+O14)*20/100),0) -> 0 | AS14: =IF(H14="ECHEC",0,(J14+K14-23000)) -> 0 | AW14: =IF(AC14=0,AI14,(1*23000*13)+(1000+AI14)-AC14) -> 0 | AX14: =IF(AD14=0,AJ14,(1*75000*16)+(AJ14)-AD14) -> 0 | AY14: =IF(AE14=0,AK14,(1*100000*13)+(AK14)-AE14) -> 0 | AZ14: =SUM(AV14:AY14)-BF14+Z14-F14+BH14+BI14+BJ14+BK14 -> 0 | BD14: =IF(AZ14=0,(AZ14-BA14-BC14),(AZ14-BA14-BB14-BC14)) -> 0 | BF14: =Z14*1/100*BG14 -> 0 | BG14: 0 | BN14: CONFECTION CACHET | BO14: FONDS DE ROULEMENT
A15: AS201611 | B15: =VLOOKUP(A15,[6]LISTADHERENT!A$5:H$60,3,0) -> HENGUE PAUL OMER | C15: =D15+E15+F15-U15-BB15 -> 0 | D15: =VLOOKUP(A15,[7]HISTOBQUEDEC22!$A$6:$G$36,3,0) -> 105000 | E15: =VLOOKUP(A15,[7]HISTOBQUEDEC22!$A$6:$G$36,4,0) -> 0 | F15: =VLOOKUP(A15,[7]HISTOBQUEDEC22!$A$6:$G$36,5,0) -> 0 | G15: =IF(H15="ESPECES",3000,0) -> 0 | H15: =IF($D15<>0,"BANQUE",IF($E15<>0,"ESPECES","ECHEC")) -> BANQUE | I15: 1 | J15: =IF($D15<>0,I15*30000,IF($E15<>0,I15*30000,0)) -> 30000 | L15: 1 | M15: =IF($D15<>0,L15*75000,IF($E15<>0,L15*75000,0)) -> 75000 | O15: =IF($D15<>0,N15*100000,IF($E15<>0,N15*100000,0)) -> 0 | P15: =VLOOKUP(A15,[9]TONTDEC22!$A$6:$R$31,12,0) -> 0 | Q15: =VLOOKUP(A15,[10]TONTDEC22!$A$6:$P$21,10,0) -> 0 | U15: =G15+S15++R15+P15+O15+M15+K15+J15+Q15+V15+W15 -> 105000 | AD15: 75000 | AF15: BANQUE | AQ15: =IF(H15="ECHEC",((J15+M15+O15)*20/100),0) -> 0 | AR15: =IF(H15="ECHEC",((J15+M15+O15)*20/100),0) -> 0 | AS15: =IF(H15="ECHEC",0,(J15+K15-23000)) -> 7000 | AT15: 20000 | AW15: =IF(AC15=0,AI15,(1*23000*13)+(1000+AI15)-AC15) -> 0 | AX15: =IF(AD15=0,AJ15,(1*75000*16)+(AJ15)-AD15) -> 1125000 | AY15: =IF(AE15=0,AK15,(1*100000*13)+(AK15)-AE15) -> 0 | AZ15: =SUM(AV15:AY15)-BF15+Z15-F15+BH15+BI15+BJ15+BK15 -> 1125000 | BD15: =IF(AZ15=0,(AZ15-BA15-BC15),(AZ15-BA15-BB15-BC15)) -> 1125000 | BF15: =Z15*1/100*BG15 -> 0 | BG15: 0
A16: AS201613 | B16: =VLOOKUP(A16,[6]LISTADHERENT!A$5:H$60,3,0) -> HOTCHO BENJAMIN | C16: =D16+E16+F16-U16-BB16 -> 0 | D16: =VLOOKUP(A16,[7]HISTOBQUEDEC22!$A$6:$G$36,3,0) -> 1150000 | E16: =VLOOKUP(A16,[7]HISTOBQUEDEC22!$A$6:$G$36,4,0) -> 0 | F16: =VLOOKUP(A16,[7]HISTOBQUEDEC22!$A$6:$G$36,5,0) -> 0 | G16: =IF(H16="ESPECES",3000,0) -> 0 | H16: =IF($D16<>0,"BANQUE",IF($E16<>0,"ESPECES","ECHEC")) -> BANQUE | I16: 1 | J16: =IF($D16<>0,I16*30000,IF($E16<>0,I16*30000,0)) -> 30000 | K16: 45000 | L16: 1 | M16: =IF($D16<>0,L16*75000,IF($E16<>0,L16*75000,0)) -> 75000 | O16: =IF($D16<>0,N16*100000,IF($E16<>0,N16*100000,0)) -> 0 | P16: =VLOOKUP(A16,[9]TONTDEC22!$A$6:$R$31,12,0) -> 0 | Q16: =VLOOKUP(A16,[10]TONTDEC22!$A$6:$P$21,10,0) -> 0 | S16: 1000000 | T16: BANQUE | U16: =G16+S16++R16+P16+O16+M16+K16+J16+Q16+V16+W16 -> 1150000 | Z16: 1000000 | AA16: BANQUE | AQ16: =IF(H16="ECHEC",((J16+M16+O16)*20/100),0) -> 0 | AR16: =IF(H16="ECHEC",((J16+M16+O16)*20/100),0) -> 0 | AS16: =IF(H16="ECHEC",0,(J16+K16-23000)) -> 52000 | AT16: 20000 | AW16: =IF(AC16=0,AI16,(1*23000*13)+(1000+AI16)-AC16) -> 0 | AX16: =IF(AD16=0,AJ16,(1*75000*16)+(AJ16)-AD16) -> 0 | AY16: =IF(AE16=0,AK16,(1*100000*13)+(AK16)-AE16) -> 0 | AZ16: =SUM(AV16:AY16)-BF16+Z16-F16+BH16+BI16+BJ16+BK16 -> 880000 | BD16: =IF(AZ16=0,(AZ16-BA16-BC16),(AZ16-BA16-BB16-BC16)) -> 880000 | BF16: =Z16*1/100*BG16 -> 120000 | BG16: 12 | BN16: S/TOTAL | BP16: =SUM(BP6:BP15) -> 6000
A17: AS201617 | B17: =VLOOKUP(A17,[6]LISTADHERENT!A$5:H$60,3,0) -> KOUAMOU MOISE | C17: =D17+E17+F17-U17-BB17 -> 0 | D17: =VLOOKUP(A17,[7]HISTOBQUEDEC22!$A$6:$G$36,3,0) -> 1030000 | E17: =VLOOKUP(A17,[7]HISTOBQUEDEC22!$A$6:$G$36,4,0) -> 0 | F17: =VLOOKUP(A17,[7]HISTOBQUEDEC22!$A$6:$G$36,5,0) -> 0 | G17: =IF(H17="ESPECES",3000,0) -> 0 | H17: =IF($D17<>0,"BANQUE",IF($E17<>0,"ESPECES","ECHEC")) -> BANQUE | I17: 1 | J17: =IF($D17<>0,I17*30000,IF($E17<>0,I17*30000,0)) -> 30000 | M17: =IF($D17<>0,L17*75000,IF($E17<>0,L17*75000,0)) -> 0 | N17: 3 | O17: =IF($D17<>0,N17*100000,IF($E17<>0,N17*100000,0)) -> 300000 | P17: =VLOOKUP(A17,[9]TONTDEC22!$A$6:$R$31,12,0) -> 0 | R17: =VLOOKUP(A17,[8]TONTDEC22!$A$6:$P$21,10,0) -> 0 | S17: 700000 | T17: BANQUE | U17: =G17+S17++R17+P17+O17+M17+K17+J17+Q17+V17+W17 -> 1030000 | AQ17: =IF(H17="ECHEC",((J17+M17+O17)*20/100),0) -> 0 | AR17: =IF(H17="ECHEC",((J17+M17+O17)*20/100),0) -> 0 | AS17: =IF(H17="ECHEC",0,(J17+K17-23000)) -> 7000 | AT17: 20000 | AW17: =IF(AC17=0,AI17,(1*23000*13)+(1000+AI17)-AC17) -> 0 | AX17: =IF(AD17=0,AJ17,(1*75000*16)+(AJ17)-AD17) -> 0 | AY17: =IF(AE17=0,AK17,(1*100000*13)+(AK17)-AE17) -> 0 | AZ17: =SUM(AV17:AY17)-BF17+Z17-F17+BH17+BI17+BJ17+BK17 -> 0 | BD17: =IF(AZ17=0,(AZ17-BA17-BC17),(AZ17-BA17-BB17-BC17)) -> 0 | BF17: =Z17*1/100*BG17 -> 0 | BG17: 0
A18: AS201619 | B18: =VLOOKUP(A18,[6]LISTADHERENT!A$5:H$60,3,0) -> KOUATCHO MESSACK | C18: =D18+E18+F18-U18-BB18 -> 0 | D18: =VLOOKUP(A18,[7]HISTOBQUEDEC22!$A$6:$G$36,3,0) -> 1205000 | E18: =VLOOKUP(A18,[7]HISTOBQUEDEC22!$A$6:$G$36,4,0) -> 0 | F18: =VLOOKUP(A18,[7]HISTOBQUEDEC22!$A$6:$G$36,5,0) -> 0 | G18: =IF(H18="ESPECES",3000,0) -> 0 | H18: =IF($D18<>0,"BANQUE",IF($E18<>0,"ESPECES","ECHEC")) -> BANQUE | I18: 1 | J18: =IF($D18<>0,I18*30000,IF($E18<>0,I18*30000,0)) -> 30000 | L18: 1 | M18: =IF($D18<>0,L18*75000,IF($E18<>0,L18*75000,0)) -> 75000 | N18: 1 | O18: =IF($D18<>0,N18*100000,IF($E18<>0,N18*100000,0)) -> 100000 | P18: =VLOOKUP(A18,[9]TONTDEC22!$A$6:$R$31,12,0) -> 0 | Q18: =VLOOKUP(A18,[10]TONTDEC22!$A$6:$P$21,10,0) -> 0 | R18: =VLOOKUP(A18,[8]TONTDEC22!$A$6:$P$21,10,0) -> 0 | S18: 1000000 | T18: BANQUE | U18: =G18+S18++R18+P18+O18+M18+K18+J18+Q18+V18+W18 -> 1205000 | Z18: 1000000 | AA18: BANQUE | AQ18: =IF(H18="ECHEC",((J18+M18+O18)*20/100),0) -> 0 | AR18: =IF(H18="ECHEC",((J18+M18+O18)*20/100),0) -> 0 | AS18: =IF(H18="ECHEC",0,(J18+K18-23000)) -> 7000 | AT18: 20000 | AW18: =IF(AC18=0,AI18,(1*23000*13)+(1000+AI18)-AC18) -> 0 | AX18: =IF(AD18=0,AJ18,(1*75000*16)+(AJ18)-AD18) -> 0 | AY18: =IF(AE18=0,AK18,(1*100000*13)+(AK18)-AE18) -> 0 | AZ18: =SUM(AV18:AY18)-BF18+Z18-F18+BH18+BI18+BJ18+BK18 -> 940000 | BD18: =IF(AZ18=0,(AZ18-BA18-BC18),(AZ18-BA18-BB18-BC18)) -> 940000 | BF18: =Z18*1/100*BG18 -> 60000 | BG18: 6 | BN18: GRATIFICATION BUREAU 2021 | BO18: PENALITE VERSEMENT ESPECES
A19: AS201620 | B19: =VLOOKUP(A19,[6]LISTADHERENT!A$5:H$60,3,0) -> LOWE JEAN | C19: =D19+E19+F19-U19-BB19 -> 0 | D19: =VLOOKUP(A19,[7]HISTOBQUEDEC22!$A$6:$G$36,3,0) -> 1030000 | E19: =VLOOKUP(A19,[7]HISTOBQUEDEC22!$A$6:$G$36,4,0) -> 0 | F19: =VLOOKUP(A19,[7]HISTOBQUEDEC22!$A$6:$G$36,5,0) -> 0 | G19: =IF(H19="ESPECES",3000,0) -> 0 | H19: =IF($D19<>0,"BANQUE",IF($E19<>0,"ESPECES","ECHEC")) -> BANQUE | I19: 1 | J19: =IF($D19<>0,I19*30000,IF($E19<>0,I19*30000,0)) -> 30000 | M19: =IF($D19<>0,L19*75000,IF($E19<>0,L19*75000,0)) -> 0 | O19: =IF($D19<>0,N19*100000,IF($E19<>0,N19*100000,0)) -> 0 | P19: =VLOOKUP(A19,[9]TONTDEC22!$A$6:$R$31,12,0) -> 0 | S19: 1000000 | T19: BANQUE | U19: =G19+S19++R19+P19+O19+M19+K19+J19+Q19+V19+W19 -> 1030000 | Z19: 1000000 | AA19: BANQUE | AQ19: =IF(H19="ECHEC",((J19+M19+O19)*20/100),0) -> 0 | AR19: =IF(H19="ECHEC",((J19+M19+O19)*20/100),0) -> 0 | AS19: =IF(H19="ECHEC",0,(J19+K19-23000)) -> 7000 | AT19: 20000 | AW19: =IF(AC19=0,AI19,(1*23000*13)+(1000+AI19)-AC19) -> 0 | AX19: =IF(AD19=0,AJ19,(1*75000*16)+(AJ19)-AD19) -> 0 | AY19: =IF(AE19=0,AK19,(1*100000*13)+(AK19)-AE19) -> 0 | AZ19: =SUM(AV19:AY19)-BF19+Z19-F19+BH19+BI19+BJ19+BK19 -> 960000 | BD19: =IF(AZ19=0,(AZ19-BA19-BC19),(AZ19-BA19-BB19-BC19)) -> 960000 | BF19: =Z19*1/100*BG19 -> 40000 | BG19: 4 | BN19: ACHAT LAPTOP | BO19: PENALITE VERSEMENT ESPECES
A20: AS201649 | B20: =VLOOKUP(A20,[6]LISTADHERENT!A$5:H$60,3,0) -> MBOGNING TUGMA GUY | C20: =D20+E20+F20-U20-BB20 -> 0 | D20: =VLOOKUP(A20,[7]HISTOBQUEDEC22!$A$6:$G$36,3,0) -> 1627500 | E20: =VLOOKUP(A20,[7]HISTOBQUEDEC22!$A$6:$G$36,4,0) -> 0 | F20: =VLOOKUP(A20,[7]HISTOBQUEDEC22!$A$6:$G$36,5,0) -> 0 | G20: =IF(H20="ESPECES",3000,0) -> 0 | H20: =IF($D20<>0,"BANQUE",IF($E20<>0,"ESPECES","ECHEC")) -> BANQUE | I20: 1 | J20: =IF($D20<>0,I20*30000,IF($E20<>0,I20*30000,0)) -> 30000 | L20: 3 | M20: =IF($D20<>0,L20*75000,IF($E20<>0,L20*75000,0)) -> 225000 | N20: 2 | O20: =IF($D20<>0,N20*100000,IF($E20<>0,N20*100000,0)) -> 200000 | P20: =VLOOKUP(A20,[9]TONTDEC22!$A$6:$R$31,12,0) -> 0 | Q20: =VLOOKUP(A20,[10]TONTDEC22!$A$6:$P$21,10,0) -> 0 | R20: =VLOOKUP(A20,[8]TONTDEC22!$A$6:$P$21,10,0) -> 172500 | S20: 1000000 | T20: BANQUE | U20: =G20+S20++R20+P20+O20+M20+K20+J20+Q20+V20+W20 -> 1627500 | Z20: 1000000 | AA20: BANQUE | AP20: BANQUE | AQ20: =IF(H20="ECHEC",((J20+M20+O20)*20/100),0) -> 0 | AR20: =IF(H20="ECHEC",((J20+M20+O20)*20/100),0) -> 0 | AS20: =IF(H20="ECHEC",0,(J20+K20-23000)) -> 7000 | AT20: 20000 | AW20: =IF(AC20=0,AI20,(1*23000*13)+(1000+AI20)-AC20) -> 0 | AX20: =IF(AD20=0,AJ20,(1*75000*16)+(AJ20)-AD20) -> 0 | AY20: =IF(AE20=0,AK20,(1*100000*13)+(AK20)-AE20) -> 0 | AZ20: =SUM(AV20:AY20)-BF20+Z20-F20+BH20+BI20+BJ20+BK20 -> 940000 | BD20: =IF(AZ20=0,(AZ20-BA20-BC20),(AZ20-BA20-BB20-BC20)) -> 940000 | BF20: =Z20*1/100*BG20 -> 60000 | BG20: 6
A21: AS201639 | B21: =VLOOKUP(A21,[6]LISTADHERENT!A$5:H$60,3,0) -> NANGUEN MARTIN | C21: =D21+E21+F21-U21-BB21 -> 0 | D21: =VLOOKUP(A21,[7]HISTOBQUEDEC22!$A$6:$G$36,3,0) -> 30000 | E21: =VLOOKUP(A21,[7]HISTOBQUEDEC22!$A$6:$G$36,4,0) -> 0 | F21: =VLOOKUP(A21,[7]HISTOBQUEDEC22!$A$6:$G$36,5,0) -> 0 | G21: =IF(H21="ESPECES",3000,0) -> 0 | H21: =IF($D21<>0,"BANQUE",IF($E21<>0,"ESPECES","ECHEC")) -> BANQUE | I21: 1 | J21: =IF($D21<>0,I21*30000,IF($E21<>0,I21*30000,0)) -> 30000 | M21: =IF($D21<>0,L21*75000,IF($E21<>0,L21*75000,0)) -> 0 | O21: =IF($D21<>0,N21*100000,IF($E21<>0,N21*100000,0)) -> 0 | P21: =VLOOKUP(A21,[9]TONTDEC22!$A$6:$R$31,12,0) -> 0 | U21: =G21+S21++R21+P21+O21+M21+K21+J21+Q21+V21+W21 -> 30000 | Z21: 500000 | AA21: BANQUE | AQ21: =IF(H21="ECHEC",((J21+M21+O21)*20/100),0) -> 0 | AR21: =IF(H21="ECHEC",((J21+M21+O21)*20/100),0) -> 0 | AS21: =IF(H21="ECHEC",0,(J21+K21-23000)) -> 7000 | AT21: 20000 | AW21: =IF(AC21=0,AI21,(1*23000*13)+(1000+AI21)-AC21) -> 0 | AX21: =IF(AD21=0,AJ21,(1*75000*16)+(AJ21)-AD21) -> 0 | AY21: =IF(AE21=0,AK21,(1*100000*13)+(AK21)-AE21) -> 0 | AZ21: =SUM(AV21:AY21)-BF21+Z21-F21+BH21+BI21+BJ21+BK21 -> 510000 | BD21: =IF(AZ21=0,(AZ21-BA21-BC21),(AZ21-BA21-BB21-BC21)) -> 510000 | BF21: =Z21*1/100*BG21 -> 60000 | BG21: 12 | BK21: 70000
A22: AS201621 | B22: =VLOOKUP(A22,[6]LISTADHERENT!A$5:H$60,3,0) -> NANKAM APPOLINAIRE | C22: =D22+E22+F22-U22-BB22 -> 0 | D22: =VLOOKUP(A22,[7]HISTOBQUEDEC22!$A$6:$G$36,3,0) -> 1105000 | E22: =VLOOKUP(A22,[7]HISTOBQUEDEC22!$A$6:$G$36,4,0) -> 0 | F22: =VLOOKUP(A22,[7]HISTOBQUEDEC22!$A$6:$G$36,5,0) -> 0 | G22: =IF(H22="ESPECES",3000,0) -> 0 | H22: =IF($D22<>0,"BANQUE",IF($E22<>0,"ESPECES","ECHEC")) -> BANQUE | I22: 1 | J22: =IF($D22<>0,I22*30000,IF($E22<>0,I22*30000,0)) -> 30000 | L22: 1 | M22: =IF($D22<>0,L22*75000,IF($E22<>0,L22*75000,0)) -> 75000 | O22: =IF($D22<>0,N22*100000,IF($E22<>0,N22*100000,0)) -> 0 | P22: =VLOOKUP(A22,[9]TONTDEC22!$A$6:$R$31,12,0) -> 0 | Q22: =VLOOKUP(A22,[10]TONTDEC22!$A$6:$P$21,10,0) -> 0 | S22: 1000000 | T22: BANQUE | U22: =G22+S22++R22+P22+O22+M22+K22+J22+Q22+V22+W22 -> 1105000 | Z22: 1000000 | AA22: BANQUE | AQ22: =IF(H22="ECHEC",((J22+M22+O22)*20/100),0) -> 0 | AR22: =IF(H22="ECHEC",((J22+M22+O22)*20/100),0) -> 0 | AS22: =IF(H22="ECHEC",0,(J22+K22-23000)) -> 7000 | AT22: 20000 | AW22: =IF(AC22=0,AI22,(1*23000*13)+(1000+AI22)-AC22) -> 0 | AX22: =IF(AD22=0,AJ22,(1*75000*16)+(AJ22)-AD22) -> 0 | AY22: =IF(AE22=0,AK22,(1*100000*13)+(AK22)-AE22) -> 0 | AZ22: =SUM(AV22:AY22)-BF22+Z22-F22+BH22+BI22+BJ22+BK22 -> 880000 | BD22: =IF(AZ22=0,(AZ22-BA22-BC22),(AZ22-BA22-BB22-BC22))+71000 -> 951000 | BF22: =Z22*1/100*BG22 -> 120000 | BG22: 12 | BN22: S/TOTAL | BP22: =SUM(BP18:BP21) -> 0
A23: AS201622 | B23: =VLOOKUP(A23,[6]LISTADHERENT!A$5:H$60,3,0) -> NDJOMO ETIENNE | C23: =D23+E23+F23-U23-BB23 -> 0 | D23: =VLOOKUP(A23,[7]HISTOBQUEDEC22!$A$6:$G$36,3,0) -> 680000 | E23: =VLOOKUP(A23,[7]HISTOBQUEDEC22!$A$6:$G$36,4,0) -> 101000 | F23: =VLOOKUP(A23,[7]HISTOBQUEDEC22!$A$6:$G$36,5,0) -> 0 | G23: =IF(H23="ESPECES",3000,0) -> 0 | H23: =IF($D23<>0,"BANQUE",IF($E23<>0,"ESPECES","ECHEC")) -> BANQUE | I23: 1 | J23: =IF($D23<>0,I23*30000,IF($E23<>0,I23*30000,0)) -> 30000 | K23: 20000 | M23: =IF($D23<>0,L23*75000,IF($E23<>0,L23*75000,0)) -> 0 | N23: 1 | O23: =IF($D23<>0,N23*100000,IF($E23<>0,N23*100000,0)) -> 100000 | P23: =VLOOKUP(A23,[9]TONTDEC22!$A$6:$R$31,12,0) -> 0 | R23: =VLOOKUP(A23,[8]TONTDEC22!$A$6:$P$21,10,0) -> 101000 | S23: =449000+81000 -> 530000 | T23: BANQUE | U23: =G23+S23++R23+P23+O23+M23+K23+J23+Q23+V23+W23 -> 781000 | Z23: 600000 | AA23: BANQUE | AP23: BANQUE | AQ23: =IF(H23="ECHEC",((J23+M23+O23)*20/100),0) -> 0 | AR23: =IF(H23="ECHEC",((J23+M23+O23)*20/100),0) -> 0 | AS23: =IF(H23="ECHEC",0,(J23+K23-23000)) -> 27000 | AT23: 20000 | AW23: =IF(AC23=0,AI23,(1*23000*13)+(1000+AI23)-AC23) -> 0 | AX23: =IF(AD23=0,AJ23,(1*75000*16)+(AJ23)-AD23) -> 0 | AY23: =IF(AE23=0,AK23,(1*100000*13)+(AK23)-AE23) -> 0 | AZ23: =SUM(AV23:AY23)-BF23+Z23-F23+BH23+BI23+BJ23+BK23 -> 552000 | BD23: =IF(AZ23=0,(AZ23-BA23-BC23),(AZ23-BA23-BB23-BC23)) -> 552000 | BF23: =Z23*1/100*BG23 -> 48000 | BG23: 8
A24: AS201624 | B24: =VLOOKUP(A24,[6]LISTADHERENT!A$5:H$60,3,0) -> NGONDIEP CLAUDE | C24: =D24+E24+F24-U24-BB24 -> 0 | D24: =VLOOKUP(A24,[7]HISTOBQUEDEC22!$A$6:$G$36,3,0) -> 1240000 | E24: =VLOOKUP(A24,[7]HISTOBQUEDEC22!$A$6:$G$36,4,0) -> 0 | F24: =VLOOKUP(A24,[7]HISTOBQUEDEC22!$A$6:$G$36,5,0) -> 0 | G24: =IF(H24="ESPECES",3000,0) -> 0 | H24: =IF($D24<>0,"BANQUE",IF($E24<>0,"ESPECES","ECHEC")) -> BANQUE | I24: 1 | J24: =IF($D24<>0,I24*30000,IF($E24<>0,I24*30000,0)) -> 30000 | K24: 35000 | L24: 1 | M24: =IF($D24<>0,L24*75000,IF($E24<>0,L24*75000,0)) -> 75000 | N24: 1 | O24: =IF($D24<>0,N24*100000,IF($E24<>0,N24*100000,0)) -> 100000 | P24: =VLOOKUP(A24,[9]TONTDEC22!$A$6:$R$31,12,0) -> 0 | Q24: =VLOOKUP(A24,[10]TONTDEC22!$A$6:$P$21,10,0) -> 0 | R24: =VLOOKUP(A24,[8]TONTDEC22!$A$6:$P$21,10,0) -> 0 | S24: 1000000 | T24: BANQUE | U24: =G24+S24++R24+P24+O24+M24+K24+J24+Q24+V24+W24 -> 1240000 | Z24: 1000000 | AA24: BANQUE | AQ24: =IF(H24="ECHEC",((J24+M24+O24)*20/100),0) -> 0 | AR24: =IF(H24="ECHEC",((J24+M24+O24)*20/100),0) -> 0 | AS24: =IF(H24="ECHEC",0,(J24+K24-23000)) -> 42000 | AT24: 20000 | AW24: =IF(AC24=0,AI24,(1*23000*13)+(1000+AI24)-AC24) -> 0 | AX24: =IF(AD24=0,AJ24,(1*75000*16)+(AJ24)-AD24) -> 0 | AY24: =IF(AE24=0,AK24,(1*100000*13)+(AK24)-AE24) -> 0 | AZ24: =SUM(AV24:AY24)-BF24+Z24-F24+BH24+BI24+BJ24+BK24 -> 880000 | BD24: =IF(AZ24=0,(AZ24-BA24-BC24),(AZ24-BA24-BB24-BC24)) -> 880000 | BF24: =Z24*1/100*BG24 -> 120000 | BG24: 12 | BN24: GRATIFICATION BUREAU 2021 | BO24: FRAIS EXEPTIONNEL
A25: AS201626 | B25: =VLOOKUP(A25,[6]LISTADHERENT!A$5:H$60,3,0) -> NGUIEMEGNI MATHIEU BLAISE | C25: =D25+E25+F25-U25-BB25 -> 0 | D25: =VLOOKUP(A25,[7]HISTOBQUEDEC22!$A$6:$G$36,3,0) -> 1280000 | E25: =VLOOKUP(A25,[7]HISTOBQUEDEC22!$A$6:$G$36,4,0) -> 0 | F25: =VLOOKUP(A25,[7]HISTOBQUEDEC22!$A$6:$G$36,5,0) -> 0 | G25: =IF(H25="ESPECES",3000,0) -> 0 | H25: =IF($D25<>0,"BANQUE",IF($E25<>0,"ESPECES","ECHEC")) -> BANQUE | I25: 1 | J25: =IF($D25<>0,I25*30000,IF($E25<>0,I25*30000,0)) -> 30000 | L25: 2 | M25: =IF($D25<>0,L25*75000,IF($E25<>0,L25*75000,0)) -> 150000 | N25: 1 | O25: =IF($D25<>0,N25*100000,IF($E25<>0,N25*100000,0)) -> 100000 | P25: =VLOOKUP(A25,[9]TONTDEC22!$A$6:$R$31,12,0) -> 0 | Q25: =VLOOKUP(A25,[10]TONTDEC22!$A$6:$P$21,10,0) -> 0 | R25: =VLOOKUP(A25,[8]TONTDEC22!$A$6:$P$21,10,0) -> 0 | S25: 1000000 | T25: BANQUE | U25: =G25+S25++R25+P25+O25+M25+K25+J25+Q25+V25+W25 -> 1280000 | Z25: 1000000 | AA25: BANQUE | AQ25: =IF(H25="ECHEC",((J25+M25+O25)*20/100),0) -> 0 | AR25: =IF(H25="ECHEC",((J25+M25+O25)*20/100),0) -> 0 | AS25: =IF(H25="ECHEC",0,(J25+K25-23000)) -> 7000 | AT25: 20000 | AW25: =IF(AC25=0,AI25,(1*23000*13)+(1000+AI25)-AC25) -> 0 | AX25: =IF(AD25=0,AJ25,(1*75000*16)+(AJ25)-AD25) -> 0 | AY25: =IF(AE25=0,AK25,(1*100000*13)+(AK25)-AE25) -> 0 | AZ25: =SUM(AV25:AY25)-BF25+Z25-F25+BH25+BI25+BJ25+BK25 -> 880000 | BD25: =IF(AZ25=0,(AZ25-BA25-BC25),(AZ25-BA25-BB25-BC25)) -> 880000 | BF25: =Z25*1/100*BG25 -> 120000 | BG25: 12 | BN25: DEVELOPPEMENT LAGWEU | BO25: FRAIS EXEPTIONNEL
A26: AS201628 | B26: =VLOOKUP(A26,[6]LISTADHERENT!A$5:H$60,3,0) -> NKAMGANG JUSTIN DEJOLIE | C26: =D26+E26+F26-U26-BB26 -> 0 | D26: =VLOOKUP(A26,[7]HISTOBQUEDEC22!$A$6:$G$36,3,0) -> 1105000 | E26: =VLOOKUP(A26,[7]HISTOBQUEDEC22!$A$6:$G$36,4,0) -> 79500 | F26: =VLOOKUP(A26,[7]HISTOBQUEDEC22!$A$6:$G$36,5,0) -> 0 | G26: =IF(H26="ESPECES",3000,0) -> 0 | H26: =IF($D26<>0,"BANQUE",IF($E26<>0,"ESPECES","ECHEC")) -> BANQUE | I26: 1 | J26: =IF($D26<>0,I26*30000,IF($E26<>0,I26*30000,0)) -> 30000 | L26: 1 | M26: =IF($D26<>0,L26*75000,IF($E26<>0,L26*75000,0)) -> 75000 | O26: =IF($D26<>0,N26*100000,IF($E26<>0,N26*100000,0)) -> 0 | P26: =VLOOKUP(A26,[9]TONTDEC22!$A$6:$R$31,12,0) -> 41000 | Q26: =VLOOKUP(A26,[10]TONTDEC22!$A$6:$P$21,10,0) -> 38500 | S26: 1000000 | T26: BANQUE | U26: =G26+S26++R26+P26+O26+M26+K26+J26+Q26+V26+W26 -> 1184500 | Z26: 1000000 | AA26: BANQUE | AP26: BANQUE | AQ26: =IF(H26="ECHEC",((J26+M26+O26)*20/100),0) -> 0 | AR26: =IF(H26="ECHEC",((J26+M26+O26)*20/100),0) -> 0 | AS26: =IF(H26="ECHEC",0,(J26+K26-23000)) -> 7000 | AT26: 20000 | AW26: =IF(AC26=0,AI26,(1*23000*13)+(1000+AI26)-AC26) -> 0 | AX26: =IF(AD26=0,AJ26,(1*75000*16)+(AJ26)-AD26) -> 0 | AY26: =IF(AE26=0,AK26,(1*100000*13)+(AK26)-AE26) -> 0 | AZ26: =SUM(AV26:AY26)-BF26+Z26-F26+BH26+BI26+BJ26+BK26 -> 980000 | BD26: =IF(AZ26=0,(AZ26-BA26-BC26),(AZ26-BA26-BB26-BC26)) -> 980000 | BF26: =Z26*1/100*BG26 -> 20000 | BG26: 2 | BN26: DEUIL TCHEMNOU EMMANUEL | BO26: FRAIS EXEPTIONNEL
A27: AS201614 | B27: =VLOOKUP(A27,[6]LISTADHERENT!A$5:H$60,3,0) -> NKEHE DAVID | C27: =D27+E27+F27-U27-BB27 -> 520000 | D27: =VLOOKUP(A27,[7]HISTOBQUEDEC22!$A$6:$G$36,3,0) -> 520000 | E27: =VLOOKUP(A27,[7]HISTOBQUEDEC22!$A$6:$G$36,4,0) -> 0 | F27: =VLOOKUP(A27,[7]HISTOBQUEDEC22!$A$6:$G$36,5,0) -> 0 | G27: =IF(H27="ESPECES",3000,0) -> 0 | H27: =IF($D27<>0,"BANQUE",IF($E27<>0,"ESPECES","ECHEC")) -> BANQUE | I27: 0 | J27: =IF($D27<>0,I27*30000,IF($E27<>0,I27*30000,0)) -> 0 | M27: =IF($D27<>0,L27*75000,IF($E27<>0,L27*75000,0)) -> 0 | N27: 0 | O27: =IF($D27<>0,N27*100000,IF($E27<>0,N27*100000,0)) -> 0 | U27: =G27+S27++R27+P27+O27+M27+K27+J27+Q27+V27+W27 -> 0 | AQ27: =IF(H27="ECHEC",((J27+M27+O27)*20/100),0) -> 0 | AR27: =IF(H27="ECHEC",((J27+M27+O27)*20/100),0) -> 0 | AS27: =IF(H27="ECHEC",0,(J27+K27)) -> 0 | AW27: =IF(AC27=0,AI27,(1*23000*13)+(1000+AI27)-AC27) -> 0 | AX27: =IF(AD27=0,AJ27,(1*75000*16)+(AJ27)-AD27) -> 0 | AY27: =IF(AE27=0,AK27,(1*100000*13)+(AK27)-AE27) -> 0 | AZ27: =SUM(AV27:AY27)-BF27+Z27-F27+BH27+BI27+BJ27+BK27 -> 0 | BD27: =IF(AZ27=0,(AZ27-BA27-BC27),(AZ27-BA27-BB27-BC27)) -> 0 | BF27: =Z27*1/100*BG27 -> 0 | BG27: 0
A28: AS201629 | B28: =VLOOKUP(A28,[6]LISTADHERENT!A$5:H$60,3,0) -> NKEPSEU DIEUDONNE | C28: =D28+E28+F28-U28-BB28 -> 0 | D28: =VLOOKUP(A28,[7]HISTOBQUEDEC22!$A$6:$G$36,3,0) -> 1130000 | E28: =VLOOKUP(A28,[7]HISTOBQUEDEC22!$A$6:$G$36,4,0) -> 0 | F28: =VLOOKUP(A28,[7]HISTOBQUEDEC22!$A$6:$G$36,5,0) -> 0 | G28: =IF(H28="ESPECES",3000,0) -> 0 | H28: =IF($D28<>0,"BANQUE",IF($E28<>0,"ESPECES","ECHEC")) -> BANQUE | I28: 1 | J28: =IF($D28<>0,I28*30000,IF($E28<>0,I28*30000,0)) -> 30000 | M28: =IF($D28<>0,L28*75000,IF($E28<>0,L28*75000,0)) -> 0 | N28: 1 | O28: =IF($D28<>0,N28*100000,IF($E28<>0,N28*100000,0)) -> 100000 | P28: =VLOOKUP(A28,[9]TONTDEC22!$A$6:$R$31,12,0) -> 0 | R28: =VLOOKUP(A28,[8]TONTDEC22!$A$6:$P$21,10,0) -> 0 | S28: =600000+400000 -> 1000000 | T28: BANQUE | U28: =G28+S28++R28+P28+O28+M28+K28+J28+Q28+V28+W28 -> 1130000 | AQ28: =IF(H28="ECHEC",((J28+M28+O28)*20/100),0) -> 0 | AR28: =IF(H28="ECHEC",((J28+M28+O28)*20/100),0) -> 0 | AS28: =IF(H28="ECHEC",0,(J28+K28-23000)) -> 7000 | AT28: 20000 | AW28: =IF(AC28=0,AI28,(1*23000*13)+(1000+AI28)-AC28) -> 0 | AX28: =IF(AD28=0,AJ28,(1*75000*16)+(AJ28)-AD28) -> 0 | AY28: =IF(AE28=0,AK28,(1*100000*13)+(AK28)-AE28) -> 0 | AZ28: =SUM(AV28:AY28)-BF28+Z28-F28+BH28+BI28+BJ28+BK28 -> 0 | BD28: =IF(AZ28=0,(AZ28-BA28-BC28),(AZ28-BA28-BB28-BC28)) -> 0 | BF28: =Z28*1/100*BG28 -> 0 | BG28: 0 | BN28: S/TOTAL | BP28: =SUM(BP24:BP26) -> 0
A29: AS201633 | B29: =VLOOKUP(A29,[6]LISTADHERENT!A$5:H$60,3,0) -> PATEGO NJOSSU GUSTAVE | C29: =D29+E29+F29-U29-BB29 -> 0 | D29: =VLOOKUP(A29,[7]HISTOBQUEDEC22!$A$6:$G$36,3,0) -> 105000 | E29: =VLOOKUP(A29,[7]HISTOBQUEDEC22!$A$6:$G$36,4,0) -> 0 | F29: =VLOOKUP(A29,[7]HISTOBQUEDEC22!$A$6:$G$36,5,0) -> 0 | G29: =IF(H29="ESPECES",3000,0) -> 0 | H29: =IF($D29<>0,"BANQUE",IF($E29<>0,"ESPECES","ECHEC")) -> BANQUE | I29: 1 | J29: =IF($D29<>0,I29*30000,IF($E29<>0,I29*30000,0)) -> 30000 | L29: 1 | M29: =IF($D29<>0,L29*75000,IF($E29<>0,L29*75000,0)) -> 75000 | O29: =IF($D29<>0,N29*100000,IF($E29<>0,N29*100000,0)) -> 0 | P29: =VLOOKUP(A29,[9]TONTDEC22!$A$6:$R$31,12,0) -> 0 | Q29: =VLOOKUP(A29,[10]TONTDEC22!$A$6:$P$21,10,0) -> 0 | U29: =G29+S29++R29+P29+O29+M29+K29+J29+Q29+V29+W29 -> 105000 | AQ29: =IF(H29="ECHEC",((J29+M29+O29)*20/100),0) -> 0 | AR29: =IF(H29="ECHEC",((J29+M29+O29)*20/100),0) -> 0 | AS29: =IF(H29="ECHEC",0,(J29+K29-23000)) -> 7000 | AT29: 20000 | AW29: =IF(AC29=0,AI29,(1*23000*13)+(1000+AI29)-AC29) -> 0 | AX29: =IF(AD29=0,AJ29,(1*75000*16)+(AJ29)-AD29) -> 0 | AY29: =IF(AE29=0,AK29,(1*100000*13)+(AK29)-AE29) -> 0 | AZ29: =SUM(AV29:AY29)-BF29+Z29-F29+BH29+BI29+BJ29+BK29 -> 0 | BD29: =IF(AZ29=0,(AZ29-BA29-BC29),(AZ29-BA29-BB29-BC29)) -> 0 | BF29: =Z29*1/100*BG29 -> 0 | BG29: 0
A30: AS201653 | B30: =VLOOKUP(A30,[6]LISTADHERENT!A$5:H$60,3,0) -> SIME BRICE | C30: =D30+E30+F30-U30-BB30 -> -100000 | D30: =VLOOKUP(A30,[7]HISTOBQUEDEC22!$A$6:$G$36,3,0) -> 105000 | E30: =VLOOKUP(A30,[7]HISTOBQUEDEC22!$A$6:$G$36,4,0) -> 0 | F30: =VLOOKUP(A30,[7]HISTOBQUEDEC22!$A$6:$G$36,5,0) -> 0 | G30: =IF(H30="ESPECES",3000,0) -> 0 | H30: =IF($D30<>0,"BANQUE",IF($E30<>0,"ESPECES","ECHEC")) -> BANQUE | I30: 1 | J30: =IF($D30<>0,I30*30000,IF($E30<>0,I30*30000,0)) -> 30000 | L30: 1 | M30: =IF($D30<>0,L30*75000,IF($E30<>0,L30*75000,0)) -> 75000 | O30: =IF($D30<>0,N30*100000,IF($E30<>0,N30*100000,0)) -> 0 | P30: =VLOOKUP(A30,[9]TONTDEC22!$A$6:$R$31,12,0) -> 0 | Q30: =VLOOKUP(A30,[10]TONTDEC22!$A$6:$P$21,10,0) -> 0 | U30: =G30+S30++R30+P30+O30+M30+K30+J30+Q30+V30+W30 -> 105000 | AC30: 23000 | AF30: BANQUE | AQ30: =IF(H30="ECHEC",((J30+M30+O30)*20/100),0) -> 0 | AR30: =IF(H30="ECHEC",((J30+M30+O30)*20/100),0) -> 0 | AS30: =IF(H30="ECHEC",0,(J30+K30-23000)) -> 7000 | AT30: 20000 | AW30: =IF(AC30=0,AI30,(1*23000*13)+(1000+AI30)-AC30) -> 277000 | AX30: =IF(AD30=0,AJ30,(1*75000*16)+(AJ30)-AD30) -> 0 | AY30: =IF(AE30=0,AK30,(1*100000*13)+(AK30)-AE30) -> 0 | AZ30: =SUM(AV30:AY30)-BF30+Z30-F30+BH30+BI30+BJ30+BK30 -> 277000 | BB30: 100000 | BD30: =IF(AZ30=0,(AZ30-BA30-BC30),(AZ30-BA30-BB30-BC30)) -> 177000 | BF30: =Z30*1/100*BG30 -> 0 | BG30: 0 | BN30: DECES | BO30: MUTUELLE
A31: AS201636 | B31: =VLOOKUP(A31,[6]LISTADHERENT!A$5:H$60,3,0) -> SIMO FONGANG ERIC | C31: =D31+E31+F31-U31-BB31 -> 0 | D31: =VLOOKUP(A31,[7]HISTOBQUEDEC22!$A$6:$G$36,3,0) -> 0 | E31: =VLOOKUP(A31,[7]HISTOBQUEDEC22!$A$6:$G$36,4,0) -> 0 | F31: =VLOOKUP(A31,[7]HISTOBQUEDEC22!$A$6:$G$36,5,0) -> 0 | G31: =IF(H31="ESPECES",3000,0) -> 0 | H31: =IF($D31<>0,"BANQUE",IF($E31<>0,"ESPECES","ECHEC")) -> ECHEC | J31: =IF($D31<>0,I31*30000,IF($E31<>0,I31*30000,0)) -> 0 | M31: =IF($D31<>0,L31*75000,IF($E31<>0,L31*75000,0)) -> 0 | O31: =IF($D31<>0,N31*100000,IF($E31<>0,N31*100000,0)) -> 0 | U31: =G31+S31++R31+P31+O31+M31+K31+J31+Q31+V31+W31 -> 0 | AQ31: =IF(H31="ECHEC",((J31+M31+O31)*20/100),0) -> 0 | AR31: =IF(H31="ECHEC",((J31+M31+O31)*20/100),0) -> 0 | AS31: =IF(H31="ECHEC",0,(J31+K31-23000)) -> 0 | AT31: 20000 | AW31: =IF(AC31=0,AI31,(1*23000*13)+(1000+AI31)-AC31) -> 0 | AX31: =IF(AD31=0,AJ31,(1*75000*16)+(AJ31)-AD31) -> 0 | AY31: =IF(AE31=0,AK31,(1*100000*13)+(AK31)-AE31) -> 0 | AZ31: =SUM(AV31:AY31)-BF31+Z31-F31+BH31+BI31+BJ31+BK31 -> 0 | BD31: =IF(AZ31=0,(AZ31-BA31-BC31),(AZ31-BA31-BB31-BC31)) -> 0 | BF31: =Z31*1/100*BG31 -> 0 | BG31: 0 | BN31: TRANSPORT DELEGUE | BO31: MUTUELLE
A32: AS201638 | B32: =VLOOKUP(A32,[6]LISTADHERENT!A$5:H$60,3,0) -> SIMO PIERRE | C32: =D32+E32+F32-U32-BB32 -> 0 | D32: =VLOOKUP(A32,[7]HISTOBQUEDEC22!$A$6:$G$36,3,0) -> 905000 | E32: =VLOOKUP(A32,[7]HISTOBQUEDEC22!$A$6:$G$36,4,0) -> 0 | F32: =VLOOKUP(A32,[7]HISTOBQUEDEC22!$A$6:$G$36,5,0) -> 0 | G32: =IF(H32="ESPECES",3000,0) -> 0 | H32: =IF($D32<>0,"BANQUE",IF($E32<>0,"ESPECES","ECHEC")) -> BANQUE | I32: 1 | J32: =IF($D32<>0,I32*30000,IF($E32<>0,I32*30000,0)) -> 30000 | L32: 1 | M32: =IF($D32<>0,L32*75000,IF($E32<>0,L32*75000,0)) -> 75000 | O32: =IF($D32<>0,N32*100000,IF($E32<>0,N32*100000,0)) -> 0 | P32: =VLOOKUP(A32,[9]TONTDEC22!$A$6:$R$31,12,0) -> 0 | Q32: =VLOOKUP(A32,[10]TONTDEC22!$A$6:$P$21,10,0) -> 0 | S32: =395000+378000+27000 -> 800000 | T32: BANQUE | U32: =G32+S32++R32+P32+O32+M32+K32+J32+Q32+V32+W32 -> 905000 | Z32: 1000000 | AA32: BANQUE | AQ32: =IF(H32="ECHEC",((J32+M32+O32)*20/100),0) -> 0 | AR32: =IF(H32="ECHEC",((J32+M32+O32)*20/100),0) -> 0 | AS32: =IF(H32="ECHEC",0,(J32+K32-23000)) -> 7000 | AT32: 20000 | AW32: =IF(AC32=0,AI32,(1*23000*13)+(1000+AI32)-AC32) -> 0 | AX32: =IF(AD32=0,AJ32,(1*75000*16)+(AJ32)-AD32) -> 0 | AY32: =IF(AE32=0,AK32,(1*100000*13)+(AK32)-AE32) -> 0 | AZ32: =SUM(AV32:AY32)-BF32+Z32-F32+BH32+BI32+BJ32+BK32 -> 880000 | BD32: =IF(AZ32=0,(AZ32-BA32-BC32),(AZ32-BA32-BB32-BC32)) -> 880000 | BF32: =Z32*1/100*BG32 -> 120000 | BG32: 12
A33: AS201641 | B33: =VLOOKUP(A33,[6]LISTADHERENT!A$5:H$60,3,0) -> TCHOUAMOU MATHIEU | C33: =D33+E33+F33-U33-BB33 -> 0 | D33: =VLOOKUP(A33,[7]HISTOBQUEDEC22!$A$6:$G$36,3,0) -> 1030000 | E33: =VLOOKUP(A33,[7]HISTOBQUEDEC22!$A$6:$G$36,4,0) -> 0 | F33: =VLOOKUP(A33,[7]HISTOBQUEDEC22!$A$6:$G$36,5,0) -> 0 | G33: =IF(H33="ESPECES",3000,0) -> 0 | H33: =IF($D33<>0,"BANQUE",IF($E33<>0,"ESPECES","ECHEC")) -> BANQUE | I33: 1 | J33: =IF($D33<>0,I33*30000,IF($E33<>0,I33*30000,0)) -> 30000 | M33: =IF($D33<>0,L33*75000,IF($E33<>0,L33*75000,0)) -> 0 | O33: =IF($D33<>0,N33*100000,IF($E33<>0,N33*100000,0)) -> 0 | P33: =VLOOKUP(A33,[9]TONTDEC22!$A$6:$R$31,12,0) -> 0 | S33: 1000000 | T33: BANQUE | U33: =G33+S33++R33+P33+O33+M33+K33+J33+Q33+V33+W33 -> 1030000 | Z33: 1000000 | AA33: BANQUE | AQ33: =IF(H33="ECHEC",((J33+M33+O33)*20/100),0) -> 0 | AR33: =IF(H33="ECHEC",((J33+M33+O33)*20/100),0) -> 0 | AS33: =IF(H33="ECHEC",0,(J33+K33-23000)) -> 7000 | AT33: 20000 | AW33: =IF(AC33=0,AI33,(1*23000*13)+(1000+AI33)-AC33) -> 0 | AX33: =IF(AD33=0,AJ33,(1*75000*16)+(AJ33)-AD33) -> 0 | AY33: =IF(AE33=0,AK33,(1*100000*13)+(AK33)-AE33) -> 0 | AZ33: =SUM(AV33:AY33)-BF33+Z33-F33+BH33+BI33+BJ33+BK33 -> 970000 | BD33: =IF(AZ33=0,(AZ33-BA33-BC33),(AZ33-BA33-BB33-BC33)) -> 970000 | BF33: =Z33*1/100*BG33 -> 30000 | BG33: 3 | BN33: S/TOTAL | BP33: =SUM(BP30:BP32) -> 0
A34: AS201644 | B34: =VLOOKUP(A34,[6]LISTADHERENT!A$5:H$60,3,0) -> TIEYAM ERNEST | C34: =D34+E34+F34-U34-BB34 -> 0 | D34: =VLOOKUP(A34,[7]HISTOBQUEDEC22!$A$6:$G$36,3,0) -> 0 | E34: =VLOOKUP(A34,[7]HISTOBQUEDEC22!$A$6:$G$36,4,0) -> 0 | F34: =VLOOKUP(A34,[7]HISTOBQUEDEC22!$A$6:$G$36,5,0) -> 0 | G34: =IF(H34="ESPECES",3000,0) -> 0 | H34: =IF($D34<>0,"BANQUE",IF($E34<>0,"ESPECES","ECHEC")) -> ECHEC | I34: 0 | J34: =IF($D34<>0,I34*30000,IF($E34<>0,I34*30000,0)) -> 0 | M34: =IF($D34<>0,L34*75000,IF($E34<>0,L34*75000,0)) -> 0 | N34: 0 | O34: =IF($D34<>0,N34*100000,IF($E34<>0,N34*100000,0)) -> 0 | U34: =G34+S34++R34+P34+O34+M34+K34+J34+Q34+V34+W34 -> 0 | AQ34: =IF(H34="ECHEC",((J34+M34+O34)*20/100),0) -> 0 | AR34: =IF(H34="ECHEC",((J34+M34+O34)*20/100),0) -> 0 | AS34: =IF(H34="ECHEC",0,(J34+K34)) -> 0 | AW34: =IF(AC34=0,AI34,(1*23000*13)+(1000+AI34)-AC34) -> 0 | AX34: =IF(AD34=0,AJ34,(1*75000*16)+(AJ34)-AD34) -> 0 | AY34: =IF(AE34=0,AK34,(1*100000*13)+(AK34)-AE34) -> 0 | AZ34: =SUM(AV34:AY34)-BF34+Z34-F34+BH34+BI34+BJ34+BK34 -> 0 | BD34: =IF(AZ34=0,(AZ34-BA34-BC34),(AZ34-BA34-BB34-BC34)) -> 0 | BF34: =Z34*1/100*BG34 -> 0 | BG34: 0
A35: AS201646 | B35: =VLOOKUP(A35,[6]LISTADHERENT!A$5:H$60,3,0) -> YEPMOU JEAN JACQUES | C35: =D35+E35+F35-U35-BB35 -> 0 | D35: =VLOOKUP(A35,[7]HISTOBQUEDEC22!$A$6:$G$36,3,0) -> 1041250 | E35: =VLOOKUP(A35,[7]HISTOBQUEDEC22!$A$6:$G$36,4,0) -> 0 | F35: =VLOOKUP(A35,[7]HISTOBQUEDEC22!$A$6:$G$36,5,0) -> 0 | G35: =IF(H35="ESPECES",3000,0) -> 0 | H35: =IF($D35<>0,"BANQUE",IF($E35<>0,"ESPECES","ECHEC")) -> BANQUE | I35: 1 | J35: =IF($D35<>0,I35*30000,IF($E35<>0,I35*30000,0)) -> 30000 | M35: =IF($D35<>0,L35*75000,IF($E35<>0,L35*75000,0)) -> 0 | O35: =IF($D35<>0,N35*100000,IF($E35<>0,N35*100000,0)) -> 0 | P35: =VLOOKUP(A35,[9]TONTDEC22!$A$6:$R$31,12,0) -> 0 | S35: 1011250 | T35: BANQUE | U35: =G35+S35++R35+P35+O35+M35+K35+J35+Q35+V35+W35 -> 1041250 | AQ35: =IF(H35="ECHEC",((J35+M35+O35)*20/100),0) -> 0 | AR35: =IF(H35="ECHEC",((J35+M35+O35)*20/100),0) -> 0 | AS35: =IF(H35="ECHEC",0,(J35+K35-23000)) -> 7000 | AT35: 20000 | AW35: =IF(AC35=0,AI35,(1*23000*13)+(1000+AI35)-AC35) -> 0 | AX35: =IF(AD35=0,AJ35,(1*75000*16)+(AJ35)-AD35) -> 0 | AY35: =IF(AE35=0,AK35,(1*100000*13)+(AK35)-AE35) -> 0 | AZ35: =SUM(AV35:AY35)-BF35+Z35-F35+BH35+BI35+BJ35+BK35 -> 0 | BD35: =IF(AZ35=0,(AZ35-BA35-BC35),(AZ35-BA35-BB35-BC35)) -> 0 | BF35: =Z35*1/100*BG35 -> 0 | BG35: 0 | BN35: COLLATION | BO35: COLLATION
A36: AS201647 | B36: =VLOOKUP(A36,[6]LISTADHERENT!A$5:H$60,3,0) -> YOUMBI EMMANUEL | C36: =D36+E36+F36-U36-BB36 -> 0 | D36: =VLOOKUP(A36,[7]HISTOBQUEDEC22!$A$6:$G$36,3,0) -> 280000 | E36: =VLOOKUP(A36,[7]HISTOBQUEDEC22!$A$6:$G$36,4,0) -> 0 | F36: =VLOOKUP(A36,[7]HISTOBQUEDEC22!$A$6:$G$36,5,0) -> 0 | G36: =IF(H36="ESPECES",3000,0) -> 0 | H36: =IF($D36<>0,"BANQUE",IF($E36<>0,"ESPECES","ECHEC")) -> BANQUE | I36: 1 | J36: =IF($D36<>0,I36*30000,IF($E36<>0,I36*30000,0)) -> 30000 | L36: 2 | M36: =IF($D36<>0,L36*75000,IF($E36<>0,L36*75000,0)) -> 150000 | N36: 1 | O36: =IF($D36<>0,N36*100000,IF($E36<>0,N36*100000,0)) -> 100000 | P36: =VLOOKUP(A36,[9]TONTDEC22!$A$6:$R$31,12,0) -> 0 | Q36: =VLOOKUP(A36,[10]TONTDEC22!$A$6:$P$21,10,0) -> 0 | R36: =VLOOKUP(A36,[8]TONTDEC22!$A$6:$P$21,10,0) -> 0 | U36: =G36+S36++R36+P36+O36+M36+K36+J36+Q36+V36+W36 -> 280000 | AQ36: =IF(H36="ECHEC",((J36+M36+O36)*20/100),0) -> 0 | AR36: =IF(H36="ECHEC",((J36+M36+O36)*20/100),0) -> 0 | AS36: =IF(H36="ECHEC",0,(J36+K36-23000)) -> 7000 | AT36: 20000 | AW36: =IF(AC36=0,AI36,(1*23000*13)+(1000+AI36)-AC36) -> 0 | AX36: =IF(AD36=0,AJ36,(1*75000*16)+(AJ36)-AD36) -> 0 | AY36: =IF(AE36=0,AK36,(1*100000*13)+(AK36)-AE36) -> 0 | AZ36: =SUM(AV36:AY36)-BF36+Z36-F36+BH36+BI36+BJ36+BK36 -> 0 | BD36: =IF(AZ36=0,(AZ36-BA36-BC36),(AZ36-BA36-BB36-BC36)) -> 0 | BF36: =Z36*1/100*BG36 -> 0 | BG36: 0 | BN36: BOISSON | BO36: COLLATION
B38: TOTAUX | C38: =SUM(C6:C37) -> 420000 | D38: =SUM(D6:D37) -> 20433750 | E38: =SUM(E6:E37) -> 180500 | F38: =SUM(F6:F37) -> 0 | G38: =SUM(G6:G37) -> 0 | H38: =SUM(H6:H37) -> 0 | I38: =SUM(I6:I37) -> 26 | J38: =SUM(J6:J37) -> 780000 | ... BD38: =SUM(BD6:BD37) -> 17249000 | BF38: =SUM(BF6:BF37) -> 1268000 | BH38: =SUM(BH6:BH37) -> 6000 | BI38: =SUM(BI6:BI37) -> 0 | BJ38: =SUM(BJ6:BJ37) -> 0 | BK38: =SUM(BK6:BK37) -> 70000 | BL38: =SUM(BL6:BL37) -> 0 | BM38: =SUM(BM6:BM37) -> 0 | BN38: S/TOTAL | BP38: =SUM(BP35:BP37) -> 0
C42: BANQUE | F42: ESPECES
B43: LIBELLE | C43: SORTIE | D43: ENTREE | E43: SOLDE | F43: ENTREE | G43: SORTIE | H43: SOLDE
B44: REPORT
B45: TONTINE | C45: =AZ38 -> 17287000 | D45: =SUMIFS(D7:D38,H7:H38,"BANQUE") -> 20333750 | F45: =E38 -> 180500
AZ83: =SUM(AZ7:AZ82) -> 33368000

Sheet HISTOJANV23
A1: ASSOCIATION | B1: ASELBY
A2: ANNEE | B2: 2023
A3: 1 | B3: 2 | C3: 3 | D3: 4 | E3: 5 | F3: 6 | G3: 7 | H3: 8 | I3: 9 | J3: 10 | K3: 11 | L3: 12 | M3: 13 | N3: 14 | O3: 15 | P3: 16 | Q3: 17 | R3: 18 | S3: 19 | T3: 20 | U3: 21 | V3: 22 | W3: 23 | X3: 24 | Y3: 25 | Z3: 26 | AA3: 27 | AB3: 28 | AC3: 29 | AD3: 30 | AE3: 31 | AF3: 32 | AG3: 33 | AH3: 34 | AI3: 35 | AJ3: 36 | AK3: 37 | AL3: 38 | AM3: 39 | AN3: 40 | AO3: 41 | AP3: 42 | AQ3: 43 | AR3: 44 | AS3: 45 | AT3: 46 | AU3: 47 | AV3: 48 | AW3: 49 | AX3: 50 | AY3: 51 | AZ3: 52 | BA3: 53 | BB3: 54 | BC3: 55 | BD3: 56 | BE3: 57 | BF3: 58 | BG3: 59 | BH3: 60 | BI3: 61 | BJ3: 62 | BK3: 63 | BL3: 64 | BM3: 65 | BN3: 66 | BO3: 67 | BP3: 68
B4: TABLEAU DE BORD SAISIE DES DONNEES
A5: MATRICULE | B5: NOM ET PRENOM | C5: BONUS MALUS | D5: HISTORIQUE BANQUE | E5: HITORIQUE ESPECES | F5: HITORIQUE TONTINE | G5: PENALITE VERSEMENT ESPECES | H5: MODE PAIEMENT TONTINE | I5: COMPLEMENT EPARGNE | J5: NBRE DE LOT | K5: TONTINE 40 000 | L5: NBRE DE LOT | M5: TONTINE 75 000 | N5: NBRE DE LOT | O5: TONTINE 100 000 | P5: REMBOURSEMENT PETIT LOT T40 | Q5: REMBOURSEMENT PETIT LOT T75 | R5: REMBOURSEMENT PETIT LOT T100 | S5: REMBOURSEMENT PRÊT FONDS | T5: MODE PAIEMENT REMBOURSEMENT PRÊT FONDS | U5: MONTANT ENGAGEMENT | V5: SANCTION | W5: INSCRIPTION | X5: EPARGNE ASSURANCE | Y5: RECONSTITUTION FONDS | Z5: PRÊT FONDS | AA5: MODE PAIEMENT PRÊT | AB5: NUM CHEQUE | AC5: ACHAT LOT PRINCIPAL T40 | AD5: ACHAT LOT PRINCIPAL T75 | AE5: ACHAT LOT PRINCIPAL T100 | AF5: MODE PAIEMENT LOT PRINCIPAL | AG5: NUM CHEQUE | AH5: PENALITE VERSEMENT ESPECES | AI5: VENTE PETIT LOT T40 | AJ5: VENTE PETIT LOT T75 | AK5: VENTE PETIT LOT T100 | AL5: INTERET PETIT LOT T40 | AM5: INTERET PETIT LOT T75 | AN5: INTERET PETIT LOT T100 | AO5: NUM CHEQUE | AP5: MODE PAIEMENT PETEIT LOT | AQ5: PENELAITE RETARD TONTINE | AR5: PENELAITE ECHEC TONTINE | AS5: RESTE | AT5: MUTUELLE | AU5: REMBOURSEMENT TRANSPORT | AV5: RETRAIT PARTIEL FONDS | AW5: MONTANT T40 | AX5: MONTANT T75 | AY5: MONTANT T100 | AZ5: MONTANT CHEQUE | BA5: MONTANT ESPECES | BB5: CONTRIBUTION FOYER | BC5: AUTRES SOTIES | BD5: MONTANT CHEQUE EFFECTIF | BE5: NUMERO CHEQUE | BF5: INTERET PRÊT | BG5: NBRE MOIS | BH5: DEPENSE FONDS DE ROULEMENT | BI5: DEPENSE FRAIS EXCEPTIONNEL | BJ5: DEPENSE FONDS MUTUEL | BK5: DEPENSE COLLATION RECEPTION | BL5: PENALITE PRET FONDS | BM5: DEPENSE PENALITE VERSEMENT BANQUE | BN5: LIBELLE | BO5: COMPTE | BP5: MONTANT
A6: AS201648 | B6: =VLOOKUP(A6,[11]LISTADHERENT!A$5:H$39,3,0) -> ASELBY | C6: =D6+E6+F6-U6-BB6 -> 0 | D6: =VLOOKUP(A6,[12]HISTOBQUEJANV23!$A$6:$G$44,3,0) -> 175000 | E6: =VLOOKUP(A6,[12]HISTOBQUEJANV23!$A$6:$G$39,4,0) -> 0 | F6: =VLOOKUP(A6,[12]HISTOBQUEJANV23!$A$6:$G$39,5,0) -> 0 | G6: =IF(H6="ESPECES",3000,0) -> 0 | H6: =IF($D6<>0,"BANQUE",IF($E6<>0,"ESPECES","ECHEC")) -> BANQUE | K6: =IF($D6<>0,J6*40000,IF($E6<>0,J6*40000,0)) -> 0 | L6: 1 | M6: =IF($D6<>0,L6*75000,IF($E6<>0,L6*75000,0)) -> 75000 | N6: 1 | O6: =IF($D6<>0,N6*100000,IF($E6<>0,N6*100000,0)) -> 100000 | U6: =G6+S6++R6+P6+O6+M6+I6+K6+Q6+V6+W6 -> 175000 | AQ6: =IF(H6="ECHEC",((K6+M6+O6)*20/100),0) -> 0 | AR6: =IF(H6="ECHEC",((K6+M6+O6)*20/100),0) -> 0 | AW6: =IF(AC6=0,AI6,(1*25000*12)+AI6-AC6) -> 0 | AX6: =IF(AD6=0,AJ6,(1*75000*12)+(AJ6)-AD6) -> 0 | AY6: =IF(AE6=0,AK6,(1*100000*12)+(AK6)-AE6) -> 0 | AZ6: =SUM(AV6:AY6)-BF6+Z6-F6+BH6+BI6+BJ6+BK6+BL6+BM6 -> 106000 | BD6: =IF(AZ6=0,(AZ6-BA6-BC6),(AZ6-BA6-BB6-BC6))+F6 -> 106000 | BE6: 106000 | BF6: =Z6*1/100*BG6 -> 0 | BG6: 11 | BH6: =BP16 -> 6000 | BI6: =BP28 -> 0 | BJ6: =BP33 -> 0 | BK6: =+BP38 -> 100000 | BM6: =BP22 -> 0 | BN6: ACHAT FOURNITURE | BO6: FONDS DE ROULEMENT
A7: AS201601 | B7: =VLOOKUP(A7,[11]LISTADHERENT!A$5:H$39,3,0) -> BAKOP ACHILLE | C7: =D7+E7+F7-U7-BB7 -> 0 | D7: =VLOOKUP(A7,[12]HISTOBQUEJANV23!$A$6:$G$44,3,0) -> 0 | E7: =VLOOKUP(A7,[12]HISTOBQUEJANV23!$A$6:$G$39,4,0) -> 104000 | F7: =VLOOKUP(A7,[12]HISTOBQUEJANV23!$A$6:$G$39,5,0) -> 0 | G7: =IF(H7="ESPECES",3000,0)-3000 -> 0 | H7: =IF($D7<>0,"BANQUE",IF($E7<>0,"ESPECES","ECHEC")) -> ESPECES | I7: 64000 | J7: 1 | K7: =IF($D7<>0,J7*40000,IF($E7<>0,J7*40000,0)) -> 40000 | M7: =IF($D7<>0,L7*75000,IF($E7<>0,L7*75000,0)) -> 0 | O7: =IF($D7<>0,N7*100000,IF($E7<>0,N7*100000,0)) -> 0 | U7: =G7+S7++R7+P7+O7+M7+I7+K7+Q7+V7+W7 -> 104000 | AQ7: =IF(H7="ECHEC",((K7+M7+O7)*20/100),0) -> 0 | AR7: =IF(H7="ECHEC",((K7+M7+O7)*20/100),0) -> 0 | AS7: =IF(H7="ECHEC",0,(K7+I7-25000)) -> 79000 | AW7: =IF(AC7=0,AI7,(1*25000*12)+AI7-AC7) -> 0 | AX7: =IF(AD7=0,AJ7,(1*75000*12)+(AJ7)-AD7) -> 0 | AY7: =IF(AE7=0,AK7,(1*100000*12)+(AK7)-AE7) -> 0 | AZ7: =SUM(AV7:AY7)-BF7+Z7-F7+BH7+BI7+BJ7+BK7+BL7+BM7 -> 0 | BD7: =IF(AZ7=0,(AZ7-BA7-BC7),(AZ7-BA7-BB7-BC7))+F7 -> 0 | BF7: =Z7*1/100*BG7 -> 0 | BG7: 11 | BH7: =BP17 -> 0 | BI7: =BP27 -> 0 | BJ7: =BP33 -> 0 | BM7: =BP23 -> 0 | BN7: COMMUNICATION | BO7: FONDS DE ROULEMENT
A8: AS201602 | B8: =VLOOKUP(A8,[11]LISTADHERENT!A$5:H$39,3,0) -> BOUTCHOUANG WILLIAM | C8: =D8+E8+F8-U8-BB8 -> 0 | D8: =VLOOKUP(A8,[12]HISTOBQUEJANV23!$A$6:$G$44,3,0) -> 105000 | E8: =VLOOKUP(A8,[12]HISTOBQUEJANV23!$A$6:$G$39,4,0) -> 10000 | F8: =VLOOKUP(A8,[12]HISTOBQUEJANV23!$A$6:$G$39,5,0) -> 0 | G8: =IF(H8="ESPECES",3000,0) -> 0 | H8: =IF($D8<>0,"BANQUE",IF($E8<>0,"ESPECES","ECHEC")) -> BANQUE | J8: 1 | K8: =IF($D8<>0,J8*40000,IF($E8<>0,J8*40000,0)) -> 40000 | L8: 1 | M8: =IF($D8<>0,L8*75000,IF($E8<>0,L8*75000,0)) -> 75000 | O8: =IF($D8<>0,N8*100000,IF($E8<>0,N8*100000,0)) -> 0 | Q8: =VLOOKUP(A8,[13]TONTJANV23!$A$7:$P$20,10,0) -> 0 | U8: =G8+S8++R8+P8+O8+M8+I8+K8+Q8+V8+W8 -> 115000 | AQ8: =IF(H8="ECHEC",((K8+M8+O8)*20/100),0) -> 0 | AR8: =IF(H8="ECHEC",((K8+M8+O8)*20/100),0) -> 0 | AS8: =IF(H8="ECHEC",0,(K8+I8-25000)) -> 15000 | AW8: =IF(AC8=0,AI8,(1*25000*12)+AI8-AC8) -> 0 | AX8: =IF(AD8=0,AJ8,(1*75000*12)+(AJ8)-AD8) -> 0 | AY8: =IF(AE8=0,AK8,(1*100000*12)+(AK8)-AE8) -> 0 | AZ8: =SUM(AV8:AY8)-BF8+Z8-F8+BH8+BI8+BJ8+BK8+BL8+BM8 -> 0 | BD8: =IF(AZ8=0,(AZ8-BA8-BC8),(AZ8-BA8-BB8-BC8))+F8 -> 0 | BF8: =Z8*1/100*BG8 -> 0 | BG8: 11 | BN8: COMMISSION | BO8: FONDS DE ROULEMENT
A9: AS201604 | B9: =VLOOKUP(A9,[11]LISTADHERENT!A$5:H$39,3,0) -> DJOMO JEAN PAUL | C9: =D9+E9+F9-U9-BB9 -> 0 | D9: =VLOOKUP(A9,[12]HISTOBQUEJANV23!$A$6:$G$44,3,0) -> 160000 | E9: =VLOOKUP(A9,[12]HISTOBQUEJANV23!$A$6:$G$39,4,0) -> 0 | F9: =VLOOKUP(A9,[12]HISTOBQUEJANV23!$A$6:$G$39,5,0)+140000 -> 140000 | G9: =IF(H9="ESPECES",3000,0) -> 0 | H9: =IF($D9<>0,"BANQUE",IF($E9<>0,"ESPECES","ECHEC")) -> BANQUE | I9: 20000 | J9: 1 | K9: =IF($D9<>0,J9*40000,IF($E9<>0,J9*40000,0)) -> 40000 | M9: =IF($D9<>0,L9*75000,IF($E9<>0,L9*75000,0)) -> 0 | N9: 1 | O9: =IF($D9<>0,N9*100000,IF($E9<>0,N9*100000,0)) -> 100000 | U9: =G9+S9++R9+P9+O9+M9+I9+K9+Q9+V9+W9 -> 160000 | AC9: 45000 | AF9: BANQUE | AK9: 50000 | AN9: 2000 | AP9: BANQUE | AQ9: =IF(H9="ECHEC",((K9+M9+O9)*20/100),0) -> 0 | AR9: =IF(H9="ECHEC",((K9+M9+O9)*20/100),0) -> 0 | AS9: =IF(H9="ECHEC",0,(K9+I9-25000)) -> 35000 | AW9: =IF(AC9=0,AI9,(1*25000*12)+AI9-AC9) -> 255000 | AX9: =IF(AD9=0,AJ9,(1*75000*12)+(AJ9)-AD9) -> 0 | AY9: =IF(AE9=0,AK9,(1*100000*12)+(AK9)-AE9) -> 50000 | AZ9: =SUM(AV9:AY9)-BF9+Z9-F9+BH9+BI9+BJ9+BK9+BL9+BM9 -> 165000 | BA9: 50000 | BB9: 140000 | BD9: =IF(AZ9=0,(AZ9-BA9-BC9),(AZ9-BA9-BB9-BC9))+F9 -> 115000 | BE9: 115000 | BF9: =Z9*1/100*BG9 -> 0 | BG9: 11 | BN9: AIDE UEEB ET CONT FEMME | BO9: FONDS DE ROULEMENT | BQ9: 115000
A10: AS201654 | B10: =VLOOKUP(A10,[11]LISTADHERENT!A$5:H$39,3,0) -> DJOMOU TCHAPDA | C10: =D10+E10+F10-U10-BB10 -> 0 | D10: =VLOOKUP(A10,[12]HISTOBQUEJANV23!$A$6:$G$44,3,0) -> 40000 | E10: =VLOOKUP(A10,[12]HISTOBQUEJANV23!$A$6:$G$39,4,0) -> 0 | F10: =VLOOKUP(A10,[12]HISTOBQUEJANV23!$A$6:$G$39,5,0) -> 0 | G10: =IF(H10="ESPECES",3000,0) -> 0 | H10: =IF($D10<>0,"BANQUE",IF($E10<>0,"ESPECES","ECHEC")) -> BANQUE | J10: 1 | K10: =IF($D10<>0,J10*40000,IF($E10<>0,J10*40000,0)) -> 40000 | M10: =IF($D10<>0,L10*75000,IF($E10<>0,L10*75000,0)) -> 0 | O10: =IF($D10<>0,N10*100000,IF($E10<>0,N10*100000,0)) -> 0 | U10: =G10+S10++R10+P10+O10+M10+I10+K10+Q10+V10+W10 -> 40000 | AI10: 60000 | AL10: 3000 | AP10: BANQUE | AQ10: =IF(H10="ECHEC",((K10+M10+O10)*20/100),0) -> 0 | AR10: =IF(H10="ECHEC",((K10+M10+O10)*20/100),0) -> 0 | AS10: =IF(H10="ECHEC",0,(K10+I10-25000)) -> 15000 | AW10: =IF(AC10=0,AI10,(1*25000*12)+AI10-AC10) -> 60000 | AX10: =IF(AD10=0,AJ10,(1*75000*12)+(AJ10)-AD10) -> 0 | AY10: =IF(AE10=0,AK10,(1*100000*12)+(AK10)-AE10) -> 0 | AZ10: =SUM(AV10:AY10)-BF10+Z10-F10+BH10+BI10+BJ10+BK10+BL10+BM10 -> 60000 | BA10: 60000 | BD10: =IF(AZ10=0,(AZ10-BA10-BC10),(AZ10-BA10-BB10-BC10))+F10 -> 0 | BF10: =Z10*1/100*BG10 -> 0 | BG10: 11 | BN10: CREDIT TELEPHONE | BO10: FONDS DE ROULEMENT
A11: AS201605 | B11: =VLOOKUP(A11,[11]LISTADHERENT!A$5:H$39,3,0) -> DJOUKWE NANGUEN GUY BLAISE | C11: =D11+E11+F11-U11-BB11 -> 0 | D11: =VLOOKUP(A11,[12]HISTOBQUEJANV23!$A$6:$G$44,3,0) -> 115000 | E11: =VLOOKUP(A11,[12]HISTOBQUEJANV23!$A$6:$G$39,4,0) -> 0 | F11: =VLOOKUP(A11,[12]HISTOBQUEJANV23!$A$6:$G$39,5,0) -> 0 | G11: =IF(H11="ESPECES",3000,0) -> 0 | H11: =IF($D11<>0,"BANQUE",IF($E11<>0,"ESPECES","ECHEC")) -> BANQUE | J11: 1 | K11: =IF($D11<>0,J11*40000,IF($E11<>0,J11*40000,0)) -> 40000 | L11: 1 | M11: =IF($D11<>0,L11*75000,IF($E11<>0,L11*75000,0)) -> 75000 | O11: =IF($D11<>0,N11*100000,IF($E11<>0,N11*100000,0)) -> 0 | Q11: =VLOOKUP(A11,[13]TONTJANV23!$A$7:$P$20,10,0) -> 0 | U11: =G11+S11++R11+P11+O11+M11+I11+K11+Q11+V11+W11 -> 115000 | AI11: 60000 | AL11: 2000 | AP11: BANQUE | AQ11: =IF(H11="ECHEC",((K11+M11+O11)*20/100),0) -> 0 | AR11: =IF(H11="ECHEC",((K11+M11+O11)*20/100),0) -> 0 | AS11: =IF(H11="ECHEC",0,(K11+I11-25000)) -> 15000 | AW11: =IF(AC11=0,AI11,(1*25000*12)+AI11-AC11) -> 60000 | AX11: =IF(AD11=0,AJ11,(1*75000*12)+(AJ11)-AD11) -> 0 | AY11: =IF(AE11=0,AK11,(1*100000*12)+(AK11)-AE11) -> 0 | AZ11: =SUM(AV11:AY11)-BF11+Z11-F11+BH11+BI11+BJ11+BK11+BL11+BM11 -> 60000 | BA11: 60000 | BD11: =IF(AZ11=0,(AZ11-BA11-BC11),(AZ11-BA11-BB11-BC11))+F11 -> 0 | BF11: =Z11*1/100*BG11 -> 0 | BG11: 11 | BN11: PRODUCTION RAPPORT | BO11: FONDS DE ROULEMENT
A12: AS201608 | B12: =VLOOKUP(A12,[11]LISTADHERENT!A$5:H$39,3,0) -> DJUOMBESSY ANTOINE | C12: =D12+E12+F12-U12-BB12 -> 0 | D12: =VLOOKUP(A12,[12]HISTOBQUEJANV23!$A$6:$G$44,3,0) -> 320000 | E12: =VLOOKUP(A12,[12]HISTOBQUEJANV23!$A$6:$G$39,4,0) -> 0 | F12: =VLOOKUP(A12,[12]HISTOBQUEJANV23!$A$6:$G$39,5,0) -> 0 | G12: =IF(H12="ESPECES",3000,0) -> 0 | H12: =IF($D12<>0,"BANQUE",IF($E12<>0,"ESPECES","ECHEC")) -> BANQUE | I12: 5000 | J12: 1 | K12: =IF($D12<>0,J12*40000,IF($E12<>0,J12*40000,0)) -> 40000 | L12: 1 | M12: =IF($D12<>0,L12*75000,IF($E12<>0,L12*75000,0)) -> 75000 | N12: 2 | O12: =IF($D12<>0,N12*100000,IF($E12<>0,N12*100000,0)) -> 200000 | Q12: =VLOOKUP(A12,[13]TONTJANV23!$A$7:$P$20,10,0) -> 0 | U12: =G12+S12++R12+P12+O12+M12+I12+K12+Q12+V12+W12 -> 320000 | AQ12: =IF(H12="ECHEC",((K12+M12+O12)*20/100),0) -> 0 | AR12: =IF(H12="ECHEC",((K12+M12+O12)*20/100),0) -> 0 | AS12: =IF(H12="ECHEC",0,(K12+I12-25000)) -> 20000 | AW12: =IF(AC12=0,AI12,(1*25000*12)+AI12-AC12) -> 0 | AX12: =IF(AD12=0,AJ12,(1*75000*12)+(AJ12)-AD12) -> 0 | AY12: =IF(AE12=0,AK12,(1*100000*12)+(AK12)-AE12) -> 0 | AZ12: =SUM(AV12:AY12)-BF12+Z12-F12+BH12+BI12+BJ12+BK12+BL12+BM12 -> 0 | BD12: =IF(AZ12=0,(AZ12-BA12-BC12),(AZ12-BA12-BB12-BC12))+F12 -> 0 | BF12: =Z12*1/100*BG12 -> 0 | BG12: 11 | BN12: ACHAT SOURIS ET PHOTOCOPIE | BO12: FONDS DE ROULEMENT
A13: AS201651 | B13: =VLOOKUP(A13,[11]LISTADHERENT!A$5:H$39,3,0) -> DOMOU FABIEN | C13: =D13+E13+F13-U13-BB13 -> 0 | D13: =VLOOKUP(A13,[12]HISTOBQUEJANV23!$A$6:$G$44,3,0) -> 40000 | E13: =VLOOKUP(A13,[12]HISTOBQUEJANV23!$A$6:$G$39,4,0) -> 0 | F13: =VLOOKUP(A13,[12]HISTOBQUEJANV23!$A$6:$G$39,5,0) -> 0 | G13: =IF(H13="ESPECES",3000,0) -> 0 | H13: =IF($D13<>0,"BANQUE",IF($E13<>0,"ESPECES","ECHEC")) -> BANQUE | J13: 1 | K13: =IF($D13<>0,J13*40000,IF($E13<>0,J13*40000,0)) -> 40000 | M13: =IF($D13<>0,L13*75000,IF($E13<>0,L13*75000,0)) -> 0 | O13: =IF($D13<>0,N13*100000,IF($E13<>0,N13*100000,0)) -> 0 | U13: =G13+S13++R13+P13+O13+M13+I13+K13+Q13+V13+W13 -> 40000 | AQ13: =IF(H13="ECHEC",((K13+M13+O13)*20/100),0) -> 0 | AR13: =IF(H13="ECHEC",((K13+M13+O13)*20/100),0) -> 0 | AS13: =IF(H13="ECHEC",0,(K13+I13-25000)) -> 15000 | AW13: =IF(AC13=0,AI13,(1*25000*12)+AI13-AC13) -> 0 | AX13: =IF(AD13=0,AJ13,(1*75000*12)+(AJ13)-AD13) -> 0 | AY13: =IF(AE13=0,AK13,(1*100000*12)+(AK13)-AE13) -> 0 | AZ13: =SUM(AV13:AY13)-BF13+Z13-F13+BH13+BI13+BJ13+BK13+BL13+BM13 -> 0 | BD13: =IF(AZ13=0,(AZ13-BA13-BC13),(AZ13-BA13-BB13-BC13))+F13 -> 0 | BF13: =Z13*1/100*BG13 -> 0 | BG13: 11 | BN13: TAXI BANQUE | BO13: FONDS DE ROULEMENT | BP13: 6000
A14: AS201609 | B14: =VLOOKUP(A14,[11]LISTADHERENT!A$5:H$39,3,0) -> DONHOU DAVID | C14: =D14+E14+F14-U14-BB14 -> 0 | D14: =VLOOKUP(A14,[12]HISTOBQUEJANV23!$A$6:$G$44,3,0) -> 40000 | E14: =VLOOKUP(A14,[12]HISTOBQUEJANV23!$A$6:$G$39,4,0) -> 0 | F14: =VLOOKUP(A14,[12]HISTOBQUEJANV23!$A$6:$G$39,5,0) -> 0 | G14: =IF(H14="ESPECES",3000,0) -> 0 | H14: =IF($D14<>0,"BANQUE",IF($E14<>0,"ESPECES","ECHEC")) -> BANQUE | J14: 1 | K14: =IF($D14<>0,J14*40000,IF($E14<>0,J14*40000,0)) -> 40000 | M14: =IF($D14<>0,L14*75000,IF($E14<>0,L14*75000,0)) -> 0 | O14: =IF($D14<>0,N14*100000,IF($E14<>0,N14*100000,0)) -> 0 | U14: =G14+S14++R14+P14+O14+M14+I14+K14+Q14+V14+W14 -> 40000 | AQ14: =IF(H14="ECHEC",((K14+M14+O14)*20/100),0) -> 0 | AR14: =IF(H14="ECHEC",((K14+M14+O14)*20/100),0) -> 0 | AS14: =IF(H14="ECHEC",0,(K14+I14-25000)) -> 15000 | AW14: =IF(AC14=0,AI14,(1*25000*12)+AI14-AC14) -> 0 | AX14: =IF(AD14=0,AJ14,(1*75000*12)+(AJ14)-AD14) -> 0 | AY14: =IF(AE14=0,AK14,(1*100000*12)+(AK14)-AE14) -> 0 | AZ14: =SUM(AV14:AY14)-BF14+Z14-F14+BH14+BI14+BJ14+BK14+BL14+BM14 -> 0 | BD14: =IF(AZ14=0,(AZ14-BA14-BC14),(AZ14-BA14-BB14-BC14))+F14 -> 0 | BF14: =Z14*1/100*BG14 -> 0 | BG14: 11 | BN14: CONFECTION CACHET | BO14: FONDS DE ROULEMENT
A15: AS201611 | B15: =VLOOKUP(A15,[11]LISTADHERENT!A$5:H$39,3,0) -> HENGUE PAUL OMER | C15: =D15+E15+F15-U15-BB15 -> 0 | D15: =VLOOKUP(A15,[12]HISTOBQUEJANV23!$A$6:$G$44,3,0) -> 115000 | E15: =VLOOKUP(A15,[12]HISTOBQUEJANV23!$A$6:$G$39,4,0) -> 0 | F15: =VLOOKUP(A15,[12]HISTOBQUEJANV23!$A$6:$G$39,5,0) -> 0 | G15: =IF(H15="ESPECES",3000,0) -> 0 | H15: =IF($D15<>0,"BANQUE",IF($E15<>0,"ESPECES","ECHEC")) -> BANQUE | J15: 1 | K15: =IF($D15<>0,J15*40000,IF($E15<>0,J15*40000,0)) -> 40000 | L15: 1 | M15: =IF($D15<>0,L15*75000,IF($E15<>0,L15*75000,0)) -> 75000 | O15: =IF($D15<>0,N15*100000,IF($E15<>0,N15*100000,0)) -> 0 | Q15: =VLOOKUP(A15,[13]TONTJANV23!$A$7:$P$20,10,0) -> 0 | U15: =G15+S15++R15+P15+O15+M15+I15+K15+Q15+V15+W15 -> 115000 | AQ15: =IF(H15="ECHEC",((K15+M15+O15)*20/100),0) -> 0 | AR15: =IF(H15="ECHEC",((K15+M15+O15)*20/100),0) -> 0 | AS15: =IF(H15="ECHEC",0,(K15+I15-25000)) -> 15000 | AW15: =IF(AC15=0,AI15,(1*25000*12)+AI15-AC15) -> 0 | AX15: =IF(AD15=0,AJ15,(1*75000*12)+(AJ15)-AD15) -> 0 | AY15: =IF(AE15=0,AK15,(1*100000*12)+(AK15)-AE15) -> 0 | AZ15: =SUM(AV15:AY15)-BF15+Z15-F15+BH15+BI15+BJ15+BK15+BL15+BM15 -> 0 | BD15: =IF(AZ15=0,(AZ15-BA15-BC15),(AZ15-BA15-BB15-BC15))+F15 -> 0 | BF15: =Z15*1/100*BG15 -> 0 | BG15: 11
A16: AS201613 | B16: =VLOOKUP(A16,[11]LISTADHERENT!A$5:H$39,3,0) -> HOTCHO BENJAMIN | C16: =D16+E16+F16-U16-BB16 -> 0 | D16: =VLOOKUP(A16,[12]HISTOBQUEJANV23!$A$6:$G$44,3,0) -> 250000 | E16: =VLOOKUP(A16,[12]HISTOBQUEJANV23!$A$6:$G$39,4,0) -> 0 | F16: =VLOOKUP(A16,[12]HISTOBQUEJANV23!$A$6:$G$39,5,0) -> 0 | G16: =IF(H16="ESPECES",3000,0) -> 0 | H16: =IF($D16<>0,"BANQUE",IF($E16<>0,"ESPECES","ECHEC")) -> BANQUE | I16: 35000 | J16: 1 | K16: =IF($D16<>0,J16*40000,IF($E16<>0,J16*40000,0)) -> 40000 | L16: 1 | M16: =IF($D16<>0,L16*75000,IF($E16<>0,L16*75000,0)) -> 75000 | N16: 1 | O16: =IF($D16<>0,N16*100000,IF($E16<>0,N16*100000,0)) -> 100000 | Q16: =VLOOKUP(A16,[13]TONTJANV23!$A$7:$P$20,10,0) -> 0 | U16: =G16+S16++R16+P16+O16+M16+I16+K16+Q16+V16+W16 -> 250000 | AQ16: =IF(H16="ECHEC",((K16+M16+O16)*20/100),0) -> 0 | AR16: =IF(H16="ECHEC",((K16+M16+O16)*20/100),0) -> 0 | AS16: =IF(H16="ECHEC",0,(K16+I16-25000)) -> 50000 | AW16: =IF(AC16=0,AI16,(1*25000*12)+AI16-AC16) -> 0 | AX16: =IF(AD16=0,AJ16,(1*75000*12)+(AJ16)-AD16) -> 0 | AY16: =IF(AE16=0,AK16,(1*100000*12)+(AK16)-AE16) -> 0 | AZ16: =SUM(AV16:AY16)-BF16+Z16-F16+BH16+BI16+BJ16+BK16+BL16+BM16 -> 0 | BD16: =IF(AZ16=0,(AZ16-BA16-BC16),(AZ16-BA16-BB16-BC16))+F16 -> 0 | BF16: =Z16*1/100*BG16 -> 0 | BG16: 11 | BN16: S/TOTAL | BP16: =SUM(BP6:BP15) -> 6000
A17: AS201617 | B17: =VLOOKUP(A17,[11]LISTADHERENT!A$5:H$39,3,0) -> KOUAMOU MOISE | C17: =D17+E17+F17-U17-BB17 -> 0 | D17: =VLOOKUP(A17,[12]HISTOBQUEJANV23!$A$6:$G$44,3,0) -> 140000 | E17: =VLOOKUP(A17,[12]HISTOBQUEJANV23!$A$6:$G$39,4,0) -> 0 | F17: =VLOOKUP(A17,[12]HISTOBQUEJANV23!$A$6:$G$39,5,0) -> 0 | G17: =IF(H17="ESPECES",3000,0) -> 0 | H17: =IF($D17<>0,"BANQUE",IF($E17<>0,"ESPECES","ECHEC")) -> BANQUE | J17: 1 | K17: =IF($D17<>0,J17*40000,IF($E17<>0,J17*40000,0)) -> 40000 | M17: =IF($D17<>0,L17*75000,IF($E17<>0,L17*75000,0)) -> 0 | N17: 1 | O17: =IF($D17<>0,N17*100000,IF($E17<>0,N17*100000,0)) -> 100000 | U17: =G17+S17++R17+P17+O17+M17+I17+K17+Q17+V17+W17 -> 140000 | AQ17: =IF(H17="ECHEC",((K17+M17+O17)*20/100),0) -> 0 | AR17: =IF(H17="ECHEC",((K17+M17+O17)*20/100),0) -> 0 | AS17: =IF(H17="ECHEC",0,(K17+I17-25000)) -> 15000 | AW17: =IF(AC17=0,AI17,(1*25000*12)+AI17-AC17) -> 0 | AX17: =IF(AD17=0,AJ17,(1*75000*12)+(AJ17)-AD17) -> 0 | AY17: =IF(AE17=0,AK17,(1*100000*12)+(AK17)-AE17) -> 0 | AZ17: =SUM(AV17:AY17)-BF17+Z17-F17+BH17+BI17+BJ17+BK17+BL17+BM17 -> 0 | BD17: =IF(AZ17=0,(AZ17-BA17-BC17),(AZ17-BA17-BB17-BC17))+F17 -> 0 | BF17: =Z17*1/100*BG17 -> 0 | BG17: 11
A18: AS201619 | B18: =VLOOKUP(A18,[11]LISTADHERENT!A$5:H$39,3,0) -> KOUATCHO MESSACK | C18: =D18+E18+F18-U18-BB18 -> 0 | D18: =VLOOKUP(A18,[12]HISTOBQUEJANV23!$A$6:$G$44,3,0) -> 180000 | E18: =VLOOKUP(A18,[12]HISTOBQUEJANV23!$A$6:$G$39,4,0) -> 35000 | F18: =VLOOKUP(A18,[12]HISTOBQUEJANV23!$A$6:$G$39,5,0)+70000 -> 70000 | G18: =IF(H18="ESPECES",3000,0) -> 0 | H18: =IF($D18<>0,"BANQUE",IF($E18<>0,"ESPECES","ECHEC")) -> BANQUE | J18: 1 | K18: =IF($D18<>0,J18*40000,IF($E18<>0,J18*40000,0)) -> 40000 | L18: 1 | M18: =IF($D18<>0,L18*75000,IF($E18<>0,L18*75000,0)) -> 75000 | N18: 1 | O18: =IF($D18<>0,N18*100000,IF($E18<>0,N18*100000,0)) -> 100000 | Q18: =VLOOKUP(A18,[13]TONTJANV23!$A$7:$P$20,10,0) -> 0 | U18: =G18+S18++R18+P18+O18+M18+I18+K18+Q18+V18+W18 -> 215000 | AC18: 40000 | AE18: 125000 | AF18: BANQUE | AJ18: =50000+50000 -> 100000 | AM18: =1000+1000 -> 2000 | AP18: BANQUE | AQ18: =IF(H18="ECHEC",((K18+M18+O18)*20/100),0) -> 0 | AR18: =IF(H18="ECHEC",((K18+M18+O18)*20/100),0) -> 0 | AS18: =IF(H18="ECHEC",0,(K18+I18-25000)) -> 15000 | AW18: =IF(AC18=0,AI18,(1*25000*12)+AI18-AC18) -> 260000 | AX18: =IF(AD18=0,AJ18,(1*75000*12)+(AJ18)-AD18) -> 100000 | AY18: =IF(AE18=0,AK18,(1*100000*12)+(AK18)-AE18) -> 1075000 | AZ18: =SUM(AV18:AY18)-BF18+Z18-F18+BH18+BI18+BJ18+BK18+BL18+BM18 -> 1365000 | BB18: 70000 | BD18: =IF(AZ18=0,(AZ18-BA18-BC18),(AZ18-BA18-BB18-BC18))+F18 -> 1365000 | BE18: =1075000+100000+190000 -> 1365000 | BF18: =Z18*1/100*BG18 -> 0 | BG18: 11 | BN18: GRATIFICATION BUREAU 2021 | BO18: PENALITE VERSEMENT ESPECES | BQ18: 1075000 | BS18: 100000 | BT18: COLLATION | BU18: 257000 | BV18: NGONGANG
A19: AS201620 | B19: =VLOOKUP(A19,[11]LISTADHERENT!A$5:H$39,3,0) -> LOWE JEAN | C19: =D19+E19+F19-U19-BB19 -> 0 | D19: =VLOOKUP(A19,[12]HISTOBQUEJANV23!$A$6:$G$44,3,0) -> 40000 | E19: =VLOOKUP(A19,[12]HISTOBQUEJANV23!$A$6:$G$39,4,0) -> 0 | F19: =VLOOKUP(A19,[12]HISTOBQUEJANV23!$A$6:$G$39,5,0) -> 0 | G19: =IF(H19="ESPECES",3000,0) -> 0 | H19: =IF($D19<>0,"BANQUE",IF($E19<>0,"ESPECES","ECHEC")) -> BANQUE | J19: 1 | K19: =IF($D19<>0,J19*40000,IF($E19<>0,J19*40000,0)) -> 40000 | M19: =IF($D19<>0,L19*75000,IF($E19<>0,L19*75000,0)) -> 0 | O19: =IF($D19<>0,N19*100000,IF($E19<>0,N19*100000,0)) -> 0 | U19: =G19+S19++R19+P19+O19+M19+I19+K19+Q19+V19+W19 -> 40000 | AQ19: =IF(H19="ECHEC",((K19+M19+O19)*20/100),0) -> 0 | AR19: =IF(H19="ECHEC",((K19+M19+O19)*20/100),0) -> 0 | AS19: =IF(H19="ECHEC",0,(K19+I19-25000)) -> 15000 | AW19: =IF(AC19=0,AI19,(1*25000*12)+AI19-AC19) -> 0 | AX19: =IF(AD19=0,AJ19,(1*75000*12)+(AJ19)-AD19) -> 0 | AY19: =IF(AE19=0,AK19,(1*100000*12)+(AK19)-AE19) -> 0 | AZ19: =SUM(AV19:AY19)-BF19+Z19-F19+BH19+BI19+BJ19+BK19+BL19+BM19 -> 0 | BD19: =IF(AZ19=0,(AZ19-BA19-BC19),(AZ19-BA19-BB19-BC19))+F19 -> 0 | BF19: =Z19*1/100*BG19 -> 0 | BG19: 11 | BN19: ACHAT LAPTOP | BO19: PENALITE VERSEMENT ESPECES | BQ19: 100000 | BR19: T75
A20: AS201649 | B20: =VLOOKUP(A20,[11]LISTADHERENT!A$5:H$39,3,0) -> MBOGNING TUGMA GUY | C20: =D20+E20+F20-U20-BB20 -> 0 | D20: =VLOOKUP(A20,[12]HISTOBQUEJANV23!$A$6:$G$44,3,0) -> 215000 | E20: =VLOOKUP(A20,[12]HISTOBQUEJANV23!$A$6:$G$39,4,0) -> 0 | F20: =VLOOKUP(A20,[12]HISTOBQUEJANV23!$A$6:$G$39,5,0) -> 0 | G20: =IF(H20="ESPECES",3000,0) -> 0 | H20: =IF($D20<>0,"BANQUE",IF($E20<>0,"ESPECES","ECHEC")) -> BANQUE | J20: 1 | K20: =IF($D20<>0,J20*40000,IF($E20<>0,J20*40000,0)) -> 40000 | L20: 1 | M20: =IF($D20<>0,L20*75000,IF($E20<>0,L20*75000,0)) -> 75000 | N20: 1 | O20: =IF($D20<>0,N20*100000,IF($E20<>0,N20*100000,0)) -> 100000 | Q20: =VLOOKUP(A20,[13]TONTJANV23!$A$7:$P$20,10,0) -> 0 | U20: =G20+S20++R20+P20+O20+M20+I20+K20+Q20+V20+W20 -> 215000 | AE20: 125000 | AF20: BANQUE | AJ20: =50000+55000 -> 105000 | AM20: =1000+1000 -> 2000 | AP20: BANQUE | AQ20: =IF(H20="ECHEC",((K20+M20+O20)*20/100),0) -> 0 | AR20: =IF(H20="ECHEC",((K20+M20+O20)*20/100),0) -> 0 | AS20: =IF(H20="ECHEC",0,(K20+I20-25000)) -> 15000 | AW20: =IF(AC20=0,AI20,(1*25000*12)+AI20-AC20) -> 0 | AX20: =IF(AD20=0,AJ20,(1*75000*12)+(AJ20)-AD20) -> 105000 | AY20: =IF(AE20=0,AK20,(1*100000*12)+(AK20)-AE20) -> 1075000 | AZ20: =SUM(AV20:AY20)-BF20+Z20-F20+BH20+BI20+BJ20+BK20+BL20+BM20 -> 1180000 | BA20: 55000 | BD20: =IF(AZ20=0,(AZ20-BA20-BC20),(AZ20-BA20-BB20-BC20))+F20 -> 1125000 | BE20: 986000 | BF20: =Z20*1/100*BG20 -> 0 | BG20: 11 | BQ20: 190000 | BR20: T25 | BS20: 986000 | BT20: T100
A21: AS201639 | B21: =VLOOKUP(A21,[11]LISTADHERENT!A$5:H$39,3,0) -> NANGUEN MARTIN | C21: =D21+E21+F21-U21-BB21 -> 0 | D21: =VLOOKUP(A21,[12]HISTOBQUEJANV23!$A$6:$G$44,3,0) -> 40000 | E21: =VLOOKUP(A21,[12]HISTOBQUEJANV23!$A$6:$G$39,4,0) -> 0 | F21: =VLOOKUP(A21,[12]HISTOBQUEJANV23!$A$6:$G$39,5,0) -> 0 | G21: =IF(H21="ESPECES",3000,0) -> 0 | H21: =IF($D21<>0,"BANQUE",IF($E21<>0,"ESPECES","ECHEC")) -> BANQUE | J21: 1 | K21: =IF($D21<>0,J21*40000,IF($E21<>0,J21*40000,0)) -> 40000 | M21: =IF($D21<>0,L21*75000,IF($E21<>0,L21*75000,0)) -> 0 | O21: =IF($D21<>0,N21*100000,IF($E21<>0,N21*100000,0)) -> 0 | U21: =G21+S21++R21+P21+O21+M21+I21+K21+Q21+V21+W21 -> 40000 | AQ21: =IF(H21="ECHEC",((K21+M21+O21)*20/100),0) -> 0 | AR21: =IF(H21="ECHEC",((K21+M21+O21)*20/100),0) -> 0 | AS21: =IF(H21="ECHEC",0,(K21+I21-25000)) -> 15000 | AW21: =IF(AC21=0,AI21,(1*25000*12)+AI21-AC21) -> 0 | AX21: =IF(AD21=0,AJ21,(1*75000*12)+(AJ21)-AD21) -> 0 | AY21: =IF(AE21=0,AK21,(1*100000*12)+(AK21)-AE21) -> 0 | AZ21: =SUM(AV21:AY21)-BF21+Z21-F21+BH21+BI21+BJ21+BK21+BL21+BM21 -> 0 | BD21: =IF(AZ21=0,(AZ21-BA21-BC21),(AZ21-BA21-BB21-BC21))+F21 -> 0 | BE21: =BD20-BE20 -> 139000 | BF21: =Z21*1/100*BG21 -> 0 | BG21: 11
A22: AS201621 | B22: =VLOOKUP(A22,[11]LISTADHERENT!A$5:H$39,3,0) -> NANKAM APPOLINAIRE | C22: =D22+E22+F22-U22-BB22 -> 0 | D22: =VLOOKUP(A22,[12]HISTOBQUEJANV23!$A$6:$G$44,3,0) -> 115000 | E22: =VLOOKUP(A22,[12]HISTOBQUEJANV23!$A$6:$G$39,4,0) -> 0 | F22: =VLOOKUP(A22,[12]HISTOBQUEJANV23!$A$6:$G$39,5,0) -> 0 | G22: =IF(H22="ESPECES",3000,0) -> 0 | H22: =IF($D22<>0,"BANQUE",IF($E22<>0,"ESPECES","ECHEC")) -> BANQUE | J22: 1 | K22: =IF($D22<>0,J22*40000,IF($E22<>0,J22*40000,0)) -> 40000 | L22: 1 | M22: =IF($D22<>0,L22*75000,IF($E22<>0,L22*75000,0)) -> 75000 | O22: =IF($D22<>0,N22*100000,IF($E22<>0,N22*100000,0)) -> 0 | Q22: =VLOOKUP(A22,[13]TONTJANV23!$A$7:$P$20,10,0) -> 0 | U22: =G22+S22++R22+P22+O22+M22+I22+K22+Q22+V22+W22 -> 115000 | AQ22: =IF(H22="ECHEC",((K22+M22+O22)*20/100),0) -> 0 | AR22: =IF(H22="ECHEC",((K22+M22+O22)*20/100),0) -> 0 | AS22: =IF(H22="ECHEC",0,(K22+I22-25000)) -> 15000 | AW22: =IF(AC22=0,AI22,(1*25000*12)+AI22-AC22) -> 0 | AX22: =IF(AD22=0,AJ22,(1*75000*12)+(AJ22)-AD22) -> 0 | AY22: =IF(AE22=0,AK22,(1*100000*12)+(AK22)-AE22) -> 0 | AZ22: =SUM(AV22:AY22)-BF22+Z22-F22+BH22+BI22+BJ22+BK22+BL22+BM22 -> 0 | BD22: =IF(AZ22=0,(AZ22-BA22-BC22),(AZ22-BA22-BB22-BC22))+F22 -> 0 | BF22: =Z22*1/100*BG22 -> 0 | BG22: 11 | BN22: S/TOTAL | BP22: =SUM(BP18:BP21) -> 0
A23: AS201622 | B23: =VLOOKUP(A23,[11]LISTADHERENT!A$5:H$39,3,0) -> NDJOMO ETIENNE | C23: =D23+E23+F23-U23-BB23 -> 0 | D23: =VLOOKUP(A23,[12]HISTOBQUEJANV23!$A$6:$G$44,3,0) -> 250000 | E23: =VLOOKUP(A23,[12]HISTOBQUEJANV23!$A$6:$G$39,4,0) -> 0 | F23: =VLOOKUP(A23,[12]HISTOBQUEJANV23!$A$6:$G$39,5,0) -> 0 | G23: =IF(H23="ESPECES",3000,0) -> 0 | H23: =IF($D23<>0,"BANQUE",IF($E23<>0,"ESPECES","ECHEC")) -> BANQUE | I23: 10000 | J23: 1 | K23: =IF($D23<>0,J23*40000,IF($E23<>0,J23*40000,0)) -> 40000 | M23: =IF($D23<>0,L23*75000,IF($E23<>0,L23*75000,0)) -> 0 | N23: 2 | O23: =IF($D23<>0,N23*100000,IF($E23<>0,N23*100000,0)) -> 200000 | U23: =G23+S23++R23+P23+O23+M23+I23+K23+Q23+V23+W23 -> 250000 | AQ23: =IF(H23="ECHEC",((K23+M23+O23)*20/100),0) -> 0 | AR23: =IF(H23="ECHEC",((K23+M23+O23)*20/100),0) -> 0 | AS23: =IF(H23="ECHEC",0,(K23+I23-25000)) -> 25000 | AW23: =IF(AC23=0,AI23,(1*25000*12)+AI23-AC23) -> 0 | AX23: =IF(AD23=0,AJ23,(1*75000*12)+(AJ23)-AD23) -> 0 | AY23: =IF(AE23=0,AK23,(1*100000*12)+(AK23)-AE23) -> 0 | AZ23: =SUM(AV23:AY23)-BF23+Z23-F23+BH23+BI23+BJ23+BK23+BL23+BM23 -> 0 | BD23: =IF(AZ23=0,(AZ23-BA23-BC23),(AZ23-BA23-BB23-BC23))+F23 -> 0 | BF23: =Z23*1/100*BG23 -> 0 | BG23: 11
A24: AS201624 | B24: =VLOOKUP(A24,[11]LISTADHERENT!A$5:H$39,3,0) -> NGONDIEP CLAUDE | C24: =D24+E24+F24-U24-BB24 -> 0 | D24: =VLOOKUP(A24,[12]HISTOBQUEJANV23!$A$6:$G$44,3,0) -> 210000 | E24: =VLOOKUP(A24,[12]HISTOBQUEJANV23!$A$6:$G$39,4,0) -> 5000 | F24: =VLOOKUP(A24,[12]HISTOBQUEJANV23!$A$6:$G$39,5,0) -> 0 | G24: =IF(H24="ESPECES",3000,0) -> 0 | H24: =IF($D24<>0,"BANQUE",IF($E24<>0,"ESPECES","ECHEC")) -> BANQUE | J24: 1 | K24: =IF($D24<>0,J24*40000,IF($E24<>0,J24*40000,0)) -> 40000 | L24: 1 | M24: =IF($D24<>0,L24*75000,IF($E24<>0,L24*75000,0)) -> 75000 | N24: 1 | O24: =IF($D24<>0,N24*100000,IF($E24<>0,N24*100000,0)) -> 100000 | Q24: =VLOOKUP(A24,[13]TONTJANV23!$A$7:$P$20,10,0) -> 0 | U24: =G24+S24++R24+P24+O24+M24+I24+K24+Q24+V24+W24 -> 215000 | AD24: 105000 | AE24: 125000 | AF24: BANQUE | AI24: 25000 | AJ24: =50000+50000 -> 100000 | AK24: 200000 | AL24: 1000 | AM24: 2000 | AN24: 8000 | AP24: BANQUE | AQ24: =IF(H24="ECHEC",((K24+M24+O24)*20/100),0) -> 0 | AR24: =IF(H24="ECHEC",((K24+M24+O24)*20/100),0) -> 0 | AS24: =IF(H24="ECHEC",0,(K24+I24-25000)) -> 15000 | AW24: =IF(AC24=0,AI24,(1*25000*12)+AI24-AC24) -> 25000 | AX24: =IF(AD24=0,AJ24,(1*75000*12)+(AJ24)-AD24) -> 895000 | AY24: =IF(AE24=0,AK24,(1*100000*12)+(AK24)-AE24) -> 1275000 | AZ24: =SUM(AV24:AY24)-BF24+Z24-F24+BH24+BI24+BJ24+BK24+BL24+BM24 -> 2195000 | BD24: =IF(AZ24=0,(AZ24-BA24-BC24),(AZ24-BA24-BB24-BC24))+F24 -> 2195000 | BE24: =1075000+200000+795000+100000+25000 -> 2195000 | BF24: =Z24*1/100*BG24 -> 0 | BG24: 11 | BN24: GRATIFICATION BUREAU 2021 | BO24: FRAIS EXEPTIONNEL | BQ24: 1075000
A25: AS201626 | B25: =VLOOKUP(A25,[11]LISTADHERENT!A$5:H$39,3,0) -> NGUIEMEGNI MATHIEU BLAISE | C25: =D25+E25+F25-U25-BB25 -> 0 | D25: =VLOOKUP(A25,[12]HISTOBQUEJANV23!$A$6:$G$44,3,0) -> 280000 | E25: =VLOOKUP(A25,[12]HISTOBQUEJANV23!$A$6:$G$39,4,0) -> 10000 | F25: =VLOOKUP(A25,[12]HISTOBQUEJANV23!$A$6:$G$39,5,0) -> 0 | G25: =IF(H25="ESPECES",3000,0) -> 0 | H25: =IF($D25<>0,"BANQUE",IF($E25<>0,"ESPECES","ECHEC")) -> BANQUE | J25: 1 | K25: =IF($D25<>0,J25*40000,IF($E25<>0,J25*40000,0)) -> 40000 | L25: 2 | M25: =IF($D25<>0,L25*75000,IF($E25<>0,L25*75000,0)) -> 150000 | N25: 1 | O25: =IF($D25<>0,N25*100000,IF($E25<>0,N25*100000,0)) -> 100000 | Q25: =VLOOKUP(A25,[13]TONTJANV23!$A$7:$P$20,10,0) -> 0 | U25: =G25+S25++R25+P25+O25+M25+I25+K25+Q25+V25+W25 -> 290000 | AI25: 30000 | AJ25: =50000+50000 -> 100000 | AK25: =25000+50000 -> 75000 | AL25: 1000 | AM25: =1000+1000 -> 2000 | AN25: 3000 | AP25: BANQUE | AQ25: =IF(H25="ECHEC",((K25+M25+O25)*20/100),0) -> 0 | AR25: =IF(H25="ECHEC",((K25+M25+O25)*20/100),0) -> 0 | AS25: =IF(H25="ECHEC",0,(K25+I25-25000)) -> 15000 | AW25: =IF(AC25=0,AI25,(1*25000*12)+AI25-AC25) -> 30000 | AX25: =IF(AD25=0,AJ25,(1*75000*12)+(AJ25)-AD25) -> 100000 | AY25: =IF(AE25=0,AK25,(1*100000*12)+(AK25)-AE25) -> 75000 | AZ25: =SUM(AV25:AY25)-BF25+Z25-F25+BH25+BI25+BJ25+BK25+BL25+BM25 -> 205000 | BA25: =25000+50000+50000+50000+30000 -> 205000 | BD25: =IF(AZ25=0,(AZ25-BA25-BC25),(AZ25-BA25-BB25-BC25))+F25 -> 0 | BF25: =Z25*1/100*BG25 -> 0 | BG25: 11 | BN25: DEVELOPPEMENT LAGWEU | BO25: FRAIS EXEPTIONNEL | BQ25: 200000 | BR25: T100
A26: AS201628 | B26: =VLOOKUP(A26,[11]LISTADHERENT!A$5:H$39,3,0) -> NKAMGANG JUSTIN DEJOLIE | C26: =D26+E26+F26-U26-BB26 -> 0 | D26: =VLOOKUP(A26,[12]HISTOBQUEJANV23!$A$6:$G$44,3,0) -> 0 | E26: =VLOOKUP(A26,[12]HISTOBQUEJANV23!$A$6:$G$39,4,0) -> 40000 | F26: =VLOOKUP(A26,[12]HISTOBQUEJANV23!$A$6:$G$39,5,0) -> 0 | G26: =IF(H26="ESPECES",3000,0)-3000 -> 0 | H26: =IF($D26<>0,"BANQUE",IF($E26<>0,"ESPECES","ECHEC")) -> ESPECES | J26: 1 | K26: =IF($D26<>0,J26*40000,IF($E26<>0,J26*40000,0)) -> 40000 | M26: =IF($D26<>0,L26*75000,IF($E26<>0,L26*75000,0)) -> 0 | O26: =IF($D26<>0,N26*100000,IF($E26<>0,N26*100000,0)) -> 0 | U26: =G26+S26++R26+P26+O26+M26+I26+K26+Q26+V26+W26 -> 40000 | AI26: 60000 | AL26: 2000 | AP26: BANQUE | AQ26: =IF(H26="ECHEC",((K26+M26+O26)*20/100),0) -> 0 | AR26: =IF(H26="ECHEC",((K26+M26+O26)*20/100),0) -> 0 | AS26: =IF(H26="ECHEC",0,(K26+I26-25000)) -> 15000 | AW26: =IF(AC26=0,AI26,(1*25000*12)+AI26-AC26) -> 60000 | AX26: =IF(AD26=0,AJ26,(1*75000*12)+(AJ26)-AD26) -> 0 | AY26: =IF(AE26=0,AK26,(1*100000*12)+(AK26)-AE26) -> 0 | AZ26: =SUM(AV26:AY26)-BF26+Z26-F26+BH26+BI26+BJ26+BK26+BL26+BM26 -> 60000 | BA26: 60000 | BD26: =IF(AZ26=0,(AZ26-BA26-BC26),(AZ26-BA26-BB26-BC26))+F26 -> 0 | BF26: =Z26*1/100*BG26 -> 0 | BG26: 11 | BN26: DEUIL TCHEMNOU EMMANUEL | BO26: FRAIS EXEPTIONNEL | BQ26: 795000 | BR26: T75
A27: AS201656 | B27: =VLOOKUP(A27,[11]LISTADHERENT!A$5:H$39,3,0) -> NOUBE ETIENNE | C27: =D27+E27+F27-U27-BB27 -> 0 | D27: =VLOOKUP(A27,[12]HISTOBQUEJANV23!$A$6:$G$44,3,0) -> 0 | E27: =VLOOKUP(A27,[12]HISTOBQUEJANV23!$A$6:$G$39,4,0) -> 65000 | F27: =VLOOKUP(A27,[12]HISTOBQUEJANV23!$A$6:$G$39,5,0) -> 0 | G27: =IF(H27="ESPECES",3000,0) -> 0 | H27: BANQUE | J27: 1 | K27: =IF($D27<>0,J27*40000,IF($E27<>0,J27*40000,0)) -> 40000 | M27: =IF($D27<>0,L27*75000,IF($E27<>0,L27*75000,0)) -> 0 | O27: =IF($D27<>0,N27*100000,IF($E27<>0,N27*100000,0)) -> 0 | U27: =G27+S27++R27+P27+O27+M27+I27+K27+Q27+V27+W27 -> 65000 | W27: 25000 | AQ27: =IF(H27="ECHEC",((K27+M27+O27)*20/100),0) -> 0 | AR27: =IF(H27="ECHEC",((K27+M27+O27)*20/100),0) -> 0 | AS27: =IF(H27="ECHEC",0,(K27+I27-25000)) -> 15000 | AW27: =IF(AC27=0,AI27,(1*25000*12)+AI27-AC27) -> 0 | AX27: =IF(AD27=0,AJ27,(1*75000*12)+(AJ27)-AD27) -> 0 | AY27: =IF(AE27=0,AK27,(1*100000*12)+(AK27)-AE27) -> 0 | AZ27: =SUM(AV27:AY27)-BF27+Z27-F27+BH27+BI27+BJ27+BK27+BL27+BM27 -> 0 | BD27: =IF(AZ27=0,(AZ27-BA27-BC27),(AZ27-BA27-BB27-BC27))+F27 -> 0 | BF27: =Z27*1/100*BG27 -> 0 | BG27: 11 | BQ27: 25000 | BR27: T30
A28: AS201633 | B28: =VLOOKUP(A28,[11]LISTADHERENT!A$5:H$39,3,0) -> PATEGO NJOSSU GUSTAVE | C28: =D28+E28+F28-U28-BB28 -> 0 | D28: =VLOOKUP(A28,[12]HISTOBQUEJANV23!$A$6:$G$44,3,0) -> 115000 | E28: =VLOOKUP(A28,[12]HISTOBQUEJANV23!$A$6:$G$39,4,0) -> 0 | F28: =VLOOKUP(A28,[12]HISTOBQUEJANV23!$A$6:$G$39,5,0) -> 0 | G28: =IF(H28="ESPECES",3000,0) -> 0 | H28: =IF($D28<>0,"BANQUE",IF($E28<>0,"ESPECES","ECHEC")) -> BANQUE | J28: 1 | K28: =IF($D28<>0,J28*40000,IF($E28<>0,J28*40000,0)) -> 40000 | L28: 1 | M28: =IF($D28<>0,L28*75000,IF($E28<>0,L28*75000,0)) -> 75000 | O28: =IF($D28<>0,N28*100000,IF($E28<>0,N28*100000,0)) -> 0 | Q28: =VLOOKUP(A28,[13]TONTJANV23!$A$7:$P$20,10,0) -> 0 | U28: =G28+S28++R28+P28+O28+M28+I28+K28+Q28+V28+W28 -> 115000 | AQ28: =IF(H28="ECHEC",((K28+M28+O28)*20/100),0) -> 0 | AR28: =IF(H28="ECHEC",((K28+M28+O28)*20/100),0) -> 0 | AS28: =IF(H28="ECHEC",0,(K28+I28-25000)) -> 15000 | AW28: =IF(AC28=0,AI28,(1*25000*12)+AI28-AC28) -> 0 | AX28: =IF(AD28=0,AJ28,(1*75000*12)+(AJ28)-AD28) -> 0 | AY28: =IF(AE28=0,AK28,(1*100000*12)+(AK28)-AE28) -> 0 | AZ28: =SUM(AV28:AY28)-BF28+Z28-F28+BH28+BI28+BJ28+BK28+BL28+BM28 -> 0 | BD28: =IF(AZ28=0,(AZ28-BA28-BC28),(AZ28-BA28-BB28-BC28))+F28 -> 0 | BF28: =Z28*1/100*BG28 -> 0 | BG28: 11 | BN28: S/TOTAL | BP28: =SUM(BP24:BP26) -> 0
A29: AS201657 | B29: =VLOOKUP(A29,[11]LISTADHERENT!A$5:H$39,3,0) -> SEUMO POLYCARPE | C29: =D29+E29+F29-U29-BB29 -> 0 | D29: =VLOOKUP(A29,[12]HISTOBQUEJANV23!$A$6:$G$44,3,0) -> 0 | E29: =VLOOKUP(A29,[12]HISTOBQUEJANV23!$A$6:$G$39,4,0) -> 65000 | F29: =VLOOKUP(A29,[12]HISTOBQUEJANV23!$A$6:$G$39,5,0) -> 0 | G29: =IF(H29="ESPECES",3000,0) -> 0 | H29: BANQUE | J29: 1 | K29: =IF($D29<>0,J29*40000,IF($E29<>0,J29*40000,0)) -> 40000 | M29: =IF($D29<>0,L29*75000,IF($E29<>0,L29*75000,0)) -> 0 | O29: =IF($D29<>0,N29*100000,IF($E29<>0,N29*100000,0)) -> 0 | U29: =G29+S29++R29+P29+O29+M29+I29+K29+Q29+V29+W29 -> 65000 | W29: 25000 | AQ29: =IF(H29="ECHEC",((K29+M29+O29)*20/100),0) -> 0 | AR29: =IF(H29="ECHEC",((K29+M29+O29)*20/100),0) -> 0 | AS29: =IF(H29="ECHEC",0,(K29+I29-25000)) -> 15000 | AW29: =IF(AC29=0,AI29,(1*25000*12)+AI29-AC29) -> 0 | AX29: =IF(AD29=0,AJ29,(1*75000*12)+(AJ29)-AD29) -> 0 | AY29: =IF(AE29=0,AK29,(1*100000*12)+(AK29)-AE29) -> 0 | AZ29: =SUM(AV29:AY29)-BF29+Z29-F29+BH29+BI29+BJ29+BK29+BL29+BM29 -> 0 | BD29: =IF(AZ29=0,(AZ29-BA29-BC29),(AZ29-BA29-BB29-BC29))+F29 -> 0 | BF29: =Z29*1/100*BG29 -> 0 | BG29: 11
A30: AS201653 | B30: =VLOOKUP(A30,[11]LISTADHERENT!A$5:H$39,3,0) -> SIME BRICE | C30: =D30+E30+F30-U30-BB30 -> 0 | D30: =VLOOKUP(A30,[12]HISTOBQUEJANV23!$A$6:$G$44,3,0) -> 0 | E30: =VLOOKUP(A30,[12]HISTOBQUEJANV23!$A$6:$G$39,4,0) -> 115000 | F30: =VLOOKUP(A30,[12]HISTOBQUEJANV23!$A$6:$G$39,5,0) -> 0 | G30: =IF(H30="ESPECES",3000,0)-3000 -> 0 | H30: =IF($D30<>0,"BANQUE",IF($E30<>0,"ESPECES","ECHEC")) -> ESPECES | J30: 1 | K30: =IF($D30<>0,J30*40000,IF($E30<>0,J30*40000,0)) -> 40000 | L30: 1 | M30: =IF($D30<>0,L30*75000,IF($E30<>0,L30*75000,0)) -> 75000 | O30: =IF($D30<>0,N30*100000,IF($E30<>0,N30*100000,0)) -> 0 | Q30: =VLOOKUP(A30,[13]TONTJANV23!$A$7:$P$20,10,0) -> 0 | U30: =G30+S30++R30+P30+O30+M30+I30+K30+Q30+V30+W30 -> 115000 | AQ30: =IF(H30="ECHEC",((K30+M30+O30)*20/100),0) -> 0 | AR30: =IF(H30="ECHEC",((K30+M30+O30)*20/100),0) -> 0 | AS30: =IF(H30="ECHEC",0,(K30+I30-25000)) -> 15000 | AW30: =IF(AC30=0,AI30,(1*25000*12)+AI30-AC30) -> 0 | AX30: =IF(AD30=0,AJ30,(1*75000*12)+(AJ30)-AD30) -> 0 | AY30: =IF(AE30=0,AK30,(1*100000*12)+(AK30)-AE30) -> 0 | AZ30: =SUM(AV30:AY30)-BF30+Z30-F30+BH30+BI30+BJ30+BK30+BL30+BM30 -> 0 | BD30: =IF(AZ30=0,(AZ30-BA30-BC30),(AZ30-BA30-BB30-BC30))+F30 -> 0 | BF30: =Z30*1/100*BG30 -> 0 | BG30: 11 | BN30: DECES | BO30: MUTUELLE
A31: AS201638 | B31: =VLOOKUP(A31,[11]LISTADHERENT!A$5:H$39,3,0) -> SIMO PIERRE | C31: =D31+E31+F31-U31-BB31 -> 0 | D31: =VLOOKUP(A31,[12]HISTOBQUEJANV23!$A$6:$G$44,3,0) -> 250000 | E31: =VLOOKUP(A31,[12]HISTOBQUEJANV23!$A$6:$G$39,4,0) -> 0 | F31: =VLOOKUP(A31,[12]HISTOBQUEJANV23!$A$6:$G$39,5,0) -> 0 | G31: =IF(H31="ESPECES",3000,0) -> 0 | H31: =IF($D31<>0,"BANQUE",IF($E31<>0,"ESPECES","ECHEC")) -> BANQUE | I31: 110000 | J31: 1 | K31: =IF($D31<>0,J31*40000,IF($E31<>0,J31*40000,0)) -> 40000 | M31: =IF($D31<>0,L31*75000,IF($E31<>0,L31*75000,0)) -> 0 | N31: 1 | O31: =IF($D31<>0,N31*100000,IF($E31<>0,N31*100000,0)) -> 100000 | U31: =G31+S31++R31+P31+O31+M31+I31+K31+Q31+V31+W31 -> 250000 | AQ31: =IF(H31="ECHEC",((K31+M31+O31)*20/100),0) -> 0 | AR31: =IF(H31="ECHEC",((K31+M31+O31)*20/100),0) -> 0 | AS31: =IF(H31="ECHEC",0,(K31+I31-25000)) -> 125000 | AW31: =IF(AC31=0,AI31,(1*25000*12)+AI31-AC31) -> 0 | AX31: =IF(AD31=0,AJ31,(1*75000*12)+(AJ31)-AD31) -> 0 | AY31: =IF(AE31=0,AK31,(1*100000*12)+(AK31)-AE31) -> 0 | AZ31: =SUM(AV31:AY31)-BF31+Z31-F31+BH31+BI31+BJ31+BK31+BL31+BM31 -> 0 | BD31: =IF(AZ31=0,(AZ31-BA31-BC31),(AZ31-BA31-BB31-BC31))+F31 -> 0 | BF31: =Z31*1/100*BG31 -> 0 | BG31: 11 | BN31: TRANSPORT DELEGUE | BO31: MUTUELLE
A32: AS201641 | B32: =VLOOKUP(A32,[11]LISTADHERENT!A$5:H$39,3,0) -> TCHOUAMOU MATHIEU | C32: =D32+E32+F32-U32-BB32 -> 0 | D32: =VLOOKUP(A32,[12]HISTOBQUEJANV23!$A$6:$G$44,3,0) -> 115000 | E32: =VLOOKUP(A32,[12]HISTOBQUEJANV23!$A$6:$G$39,4,0) -> 0 | F32: =VLOOKUP(A32,[12]HISTOBQUEJANV23!$A$6:$G$39,5,0) -> 0 | G32: =IF(H32="ESPECES",3000,0) -> 0 | H32: =IF($D32<>0,"BANQUE",IF($E32<>0,"ESPECES","ECHEC")) -> BANQUE | J32: 1 | K32: =IF($D32<>0,J32*40000,IF($E32<>0,J32*40000,0)) -> 40000 | L32: 1 | M32: =IF($D32<>0,L32*75000,IF($E32<>0,L32*75000,0)) -> 75000 | O32: =IF($D32<>0,N32*100000,IF($E32<>0,N32*100000,0)) -> 0 | U32: =G32+S32++R32+P32+O32+M32+I32+K32+Q32+V32+W32 -> 115000 | AQ32: =IF(H32="ECHEC",((K32+M32+O32)*20/100),0) -> 0 | AR32: =IF(H32="ECHEC",((K32+M32+O32)*20/100),0) -> 0 | AS32: =IF(H32="ECHEC",0,(K32+I32-25000)) -> 15000 | AW32: =IF(AC32=0,AI32,(1*25000*12)+AI32-AC32) -> 0 | AX32: =IF(AD32=0,AJ32,(1*75000*12)+(AJ32)-AD32) -> 0 | AY32: =IF(AE32=0,AK32,(1*100000*12)+(AK32)-AE32) -> 0 | AZ32: =SUM(AV32:AY32)-BF32+Z32-F32+BH32+BI32+BJ32+BK32+BL32+BM32 -> 0 | BD32: =IF(AZ32=0,(AZ32-BA32-BC32),(AZ32-BA32-BB32-BC32))+F32 -> 0 | BF32: =Z32*1/100*BG32 -> 0 | BG32: 11
A33: AS201643 | B33: =VLOOKUP(A33,[11]LISTADHERENT!A$5:H$39,3,0) -> TCHOUTOU NANA CLAUDE | C33: =D33+E33+F33-U33-BB33 -> 0 | D33: =VLOOKUP(A33,[12]HISTOBQUEJANV23!$A$6:$G$44,3,0) -> 0 | E33: =VLOOKUP(A33,[12]HISTOBQUEJANV23!$A$6:$G$39,4,0) -> 40000 | F33: =VLOOKUP(A33,[12]HISTOBQUEJANV23!$A$6:$G$39,5,0) -> 0 | G33: =IF(H33="ESPECES",3000,0)-3000 -> 0 | H33: =IF($D33<>0,"BANQUE",IF($E33<>0,"ESPECES","ECHEC")) -> ESPECES | J33: 1 | K33: =IF($D33<>0,J33*40000,IF($E33<>0,J33*40000,0)) -> 40000 | M33: =IF($D33<>0,L33*75000,IF($E33<>0,L33*75000,0)) -> 0 | O33: =IF($D33<>0,N33*100000,IF($E33<>0,N33*100000,0)) -> 0 | U33: =G33+S33++R33+P33+O33+M33+I33+K33+Q33+V33+W33 -> 40000 | AQ33: =IF(H33="ECHEC",((K33+M33+O33)*20/100),0) -> 0 | AR33: =IF(H33="ECHEC",((K33+M33+O33)*20/100),0) -> 0 | AS33: =IF(H33="ECHEC",0,(K33+I33-25000)) -> 15000 | AW33: =IF(AC33=0,AI33,(1*25000*12)+AI33-AC33) -> 0 | AX33: =IF(AD33=0,AJ33,(1*75000*12)+(AJ33)-AD33) -> 0 | AY33: =IF(AE33=0,AK33,(1*100000*12)+(AK33)-AE33) -> 0 | AZ33: =SUM(AV33:AY33)-BF33+Z33-F33+BH33+BI33+BJ33+BK33+BL33+BM33 -> 0 | BD33: =IF(AZ33=0,(AZ33-BA33-BC33),(AZ33-BA33-BB33-BC33))+F33 -> 0 | BF33: =Z33*1/100*BG33 -> 0 | BG33: 11 | BN33: S/TOTAL | BP33: =SUM(BP30:BP32) -> 0
A34: AS201658 | B34: =VLOOKUP(A34,[11]LISTADHERENT!A$5:H$39,3,0) -> YANTCHOU GERVAIS | C34: =D34+E34+F34-U34-BB34 -> 35000 | D34: =VLOOKUP(A34,[12]HISTOBQUEJANV23!$A$6:$G$44,3,0) -> 0 | E34: =VLOOKUP(A34,[12]HISTOBQUEJANV23!$A$6:$G$39,4,0) -> 100000 | F34: =VLOOKUP(A34,[12]HISTOBQUEJANV23!$A$6:$G$39,5,0) -> 0 | G34: =IF(H34="ESPECES",3000,0)-3000 -> 0 | H34: =IF($D34<>0,"BANQUE",IF($E34<>0,"ESPECES","ECHEC")) -> ESPECES | J34: 1 | K34: =IF($D34<>0,J34*40000,IF($E34<>0,J34*40000,0)) -> 40000 | M34: =IF($D34<>0,L34*75000,IF($E34<>0,L34*75000,0)) -> 0 | O34: =IF($D34<>0,N34*100000,IF($E34<>0,N34*100000,0)) -> 0 | U34: =G34+S34++R34+P34+O34+M34+I34+K34+Q34+V34+W34 -> 65000 | W34: 25000 | AQ34: =IF(H34="ECHEC",((K34+M34+O34)*20/100),0) -> 0 | AR34: =IF(H34="ECHEC",((K34+M34+O34)*20/100),0) -> 0 | AS34: =IF(H34="ECHEC",0,(K34+I34-25000)) -> 15000 | AT34: 35000 | AW34: =IF(AC34=0,AI34,(1*25000*12)+AI34-AC34) -> 0 | AX34: =IF(AD34=0,AJ34,(1*75000*12)+(AJ34)-AD34) -> 0 | AY34: =IF(AE34=0,AK34,(1*100000*12)+(AK34)-AE34) -> 0 | AZ34: =SUM(AV34:AY34)-BF34+Z34-F34+BH34+BI34+BJ34+BK34+BL34+BM34 -> 0 | BD34: =IF(AZ34=0,(AZ34-BA34-BC34),(AZ34-BA34-BB34-BC34))+F34 -> 0 | BF34: =Z34*1/100*BG34 -> 0 | BG34: 11
A35: AS201646 | B35: =VLOOKUP(A35,[11]LISTADHERENT!A$5:H$39,3,0) -> YEPMOU JEAN JACQUES | C35: =D35+E35+F35-U35-BB35 -> 0 | D35: =VLOOKUP(A35,[12]HISTOBQUEJANV23!$A$6:$G$44,3,0) -> 40000 | E35: =VLOOKUP(A35,[12]HISTOBQUEJANV23!$A$6:$G$39,4,0) -> 0 | F35: =VLOOKUP(A35,[12]HISTOBQUEJANV23!$A$6:$G$39,5,0) -> 0 | G35: =IF(H35="ESPECES",3000,0) -> 0 | H35: =IF($D35<>0,"BANQUE",IF($E35<>0,"ESPECES","ECHEC")) -> BANQUE | J35: 1 | K35: =IF($D35<>0,J35*40000,IF($E35<>0,J35*40000,0)) -> 40000 | M35: =IF($D35<>0,L35*75000,IF($E35<>0,L35*75000,0)) -> 0 | O35: =IF($D35<>0,N35*100000,IF($E35<>0,N35*100000,0)) -> 0 | U35: =G35+S35++R35+P35+O35+M35+I35+K35+Q35+V35+W35 -> 40000 | AQ35: =IF(H35="ECHEC",((K35+M35+O35)*20/100),0) -> 0 | AR35: =IF(H35="ECHEC",((K35+M35+O35)*20/100),0) -> 0 | AS35: =IF(H35="ECHEC",0,(K35+I35-25000)) -> 15000 | AW35: =IF(AC35=0,AI35,(1*25000*12)+AI35-AC35) -> 0 | AX35: =IF(AD35=0,AJ35,(1*75000*12)+(AJ35)-AD35) -> 0 | AY35: =IF(AE35=0,AK35,(1*100000*12)+(AK35)-AE35) -> 0 | AZ35: =SUM(AV35:AY35)-BF35+Z35-F35+BH35+BI35+BJ35+BK35+BL35+BM35 -> 0 | BD35: =IF(AZ35=0,(AZ35-BA35-BC35),(AZ35-BA35-BB35-BC35))+F35 -> 0 | BF35: =Z35*1/100*BG35 -> 0 | BG35: 11 | BN35: COLLATION | BO35: COLLATION | BP35: 100000
A36: AS201647 | B36: =VLOOKUP(A36,[11]LISTADHERENT!A$5:H$39,3,0) -> YOUMBI EMMANUEL | C36: =D36+E36+F36-U36-BB36 -> 0 | D36: =VLOOKUP(A36,[12]HISTOBQUEJANV23!$A$6:$G$44,3,0) -> 290000 | E36: =VLOOKUP(A36,[12]HISTOBQUEJANV23!$A$6:$G$39,4,0) -> 0 | F36: =VLOOKUP(A36,[12]HISTOBQUEJANV23!$A$6:$G$39,5,0) -> 0 | G36: =IF(H36="ESPECES",3000,0) -> 0 | H36: =IF($D36<>0,"BANQUE",IF($E36<>0,"ESPECES","ECHEC")) -> BANQUE | J36: 1 | K36: =IF($D36<>0,J36*40000,IF($E36<>0,J36*40000,0)) -> 40000 | L36: 2 | M36: =IF($D36<>0,L36*75000,IF($E36<>0,L36*75000,0)) -> 150000 | N36: 1 | O36: =IF($D36<>0,N36*100000,IF($E36<>0,N36*100000,0)) -> 100000 | Q36: =VLOOKUP(A36,[13]TONTJANV23!$A$7:$P$20,10,0) -> 0 | U36: =G36+S36++R36+P36+O36+M36+I36+K36+Q36+V36+W36 -> 290000 | AQ36: =IF(H36="ECHEC",((K36+M36+O36)*20/100),0) -> 0 | AR36: =IF(H36="ECHEC",((K36+M36+O36)*20/100),0) -> 0 | AS36: =IF(H36="ECHEC",0,(K36+I36-25000)) -> 15000 | AW36: =IF(AC36=0,AI36,(1*25000*12)+AI36-AC36) -> 0 | AX36: =IF(AD36=0,AJ36,(1*75000*12)+(AJ36)-AD36) -> 0 | AY36: =IF(AE36=0,AK36,(1*100000*12)+(AK36)-AE36) -> 0 | AZ36: =SUM(AV36:AY36)-BF36+Z36-F36+BH36+BI36+BJ36+BK36+BL36+BM36 -> 0 | BD36: =IF(AZ36=0,(AZ36-BA36-BC36),(AZ36-BA36-BB36-BC36))+F36 -> 0 | BF36: =Z36*1/100*BG36 -> 0 | BG36: 11 | BN36: BOISSON | BO36: COLLATION
B38: TOTAUX | C38: =SUM(C6:C37) -> 35000 | D38: =SUM(D6:D37) -> 3640000 | E38: =SUM(E6:E37) -> 589000 | F38: =SUM(F6:F37) -> 210000 | G38: =SUM(G6:G37) -> 0 | H38: =SUM(H6:H37) -> 0 | I38: =SUM(I6:I37) -> 244000 | J38: =SUM(J6:J37) -> 30 | ... S38: =SUM(S6:S37) -> 0 | U38: =SUM(U6:U37) -> 4194000 | V38: =SUM(V6:V37) -> 0 | W38: =SUM(W6:W37) -> 75000 | X38: =SUM(X6:X37) -> 0 | Y38: =SUM(Y6:Y37) -> 0 | Z38: =SUM(Z6:Z37) -> 0 | AA38: =SUM(AA6:AA37) -> 0 | AC38: =SUM(AC6:AC37) -> 85000 | AD38: =SUM(AD6:AD37) -> 105000 | AE38: =SUM(AE6:AE37) -> 375000 | AF38: =SUM(AF6:AF37) -> 0 | AG38: =SUM(AG6:AG37) -> 0 | AI38: =SUM(AI6:AI37) -> 235000 | AJ38: =SUM(AJ6:AJ37) -> 405000 | AK38: =SUM(AK6:AK37) -> 325000 | AL38: =SUM(AL6:AL37) -> 9000 | AM38: =SUM(AM6:AM37) -> 8000 | AN38: =SUM(AN6:AN37) -> 13000 | AO38: =SUM(AO6:AO37) -> 0 | AP38: =SUM(AP6:AP37) -> 0 | ... BF38: =SUM(BF6:BF37) -> 0 | BH38: =SUM(BH6:BH37) -> 6000 | BI38: =SUM(BI6:BI37) -> 0 | BJ38: =SUM(BJ6:BJ37) -> 0 | BK38: =SUM(BK6:BK37) -> 100000 | BL38: =SUM(BL6:BL37) -> 0 | BM38: =SUM(BM6:BM37) -> 0 | BN38: S/TOTAL | BP38: =SUM(BP35:BP36) -> 100000
Y40: CHINGUE | Z40: 428899 | BA40: 619000 | BD40: BORDEREAU | BE40: 5024000
B41: AS201643 | Y41: NJIEPDIO DELUX | Z41: 805000 | AZ41: 5024000 | BC41: RETRAIT NGONGANG | BD41: 257000 | BE41: =+BE40-BE38 -> 118000 | BN41: TRANSPORT DELEGUE | BO41: MUTUELLE
C42: BANQUE | F42: ESPECES | Y42: TCHOUANTE FRANCOIS | Z42: 243805 | BN42: REMBOURSEMENT FOND NGONGANG | BP42: 257000
B43: LIBELLE | C43: SORTIE | D43: ENTREE | E43: SOLDE | F43: ENTREE | G43: SORTIE | H43: SOLDE | Y43: TCHOUTCHOU | Z43: 51454 | BN43: S/TOTAL | BP43: =SUM(BP40:BP42) -> 257000
B44: REPORT
B45: TONTINE | C45: =AZ38 -> 5396000 | D45: =SUMIFS(D8:D38,H8:H38,"BANQUE") -> 3465000 | F45: =E38 -> 589000
AZ83: =SUM(AZ8:AZ82) -> 15710000

Sheet HISTOFEV23
A1: ASSOCIATION | B1: ASELBY
A2: ANNEE | B2: 2023
A3: 1 | B3: 2 | C3: 3 | D3: 4 | E3: 5 | F3: 6 | G3: 7 | H3: 8 | I3: 9 | J3: 10 | K3: 11 | L3: 12 | M3: 13 | N3: 14 | O3: 15 | P3: 16 | Q3: 17 | R3: 18 | S3: 19 | T3: 20 | U3: 21 | V3: 22 | W3: 23 | X3: 24 | Y3: 25 | Z3: 26 | AA3: 27 | AB3: 28 | AC3: 29 | AD3: 30 | AE3: 31 | AF3: 32 | AG3: 33 | AH3: 34 | AI3: 35 | AJ3: 36 | AK3: 37 | AL3: 38 | AM3: 39 | AN3: 40 | AO3: 41 | AP3: 42 | AQ3: 43 | AR3: 44 | AS3: 45 | AT3: 46 | AU3: 47 | AV3: 48 | AW3: 49 | AX3: 50 | AY3: 51 | AZ3: 52 | BA3: 53 | BB3: 54 | BC3: 55 | BD3: 56 | BE3: 57 | BF3: 58 | BG3: 59 | BH3: 60 | BI3: 61 | BJ3: 62 | BK3: 63 | BL3: 64 | BM3: 65 | BN3: 66 | BO3: 67 | BP3: 68
B4: TABLEAU DE BORD SAISIE DES DONNEES
A5: MATRICULE | B5: NOM ET PRENOM | C5: BONUS MALUS | D5: HISTORIQUE BANQUE | E5: HITORIQUE ESPECES | F5: HITORIQUE TONTINE | G5: PENALITE VERSEMENT ESPECES | H5: MODE PAIEMENT TONTINE | I5: COMPLEMENT EPARGNE | J5: NBRE DE LOT | K5: TONTINE 40 000 | L5: NBRE DE LOT | M5: TONTINE 75 000 | N5: NBRE DE LOT | O5: TONTINE 100 000 | P5: REMBOURSEMENT PETIT LOT T40 | Q5: REMBOURSEMENT PETIT LOT T75 | R5: REMBOURSEMENT PETIT LOT T100 | S5: REMBOURSEMENT PRÊT FONDS | T5: MODE PAIEMENT REMBOURSEMENT PRÊT FONDS | U5: MONTANT ENGAGEMENT | V5: SANCTION | W5: INSCRIPTION | X5: EPARGNE ASSURANCE | Y5: RECONSTITUTION FONDS | Z5: PRÊT FONDS | AA5: MODE PAIEMENT PRÊT | AB5: NUM CHEQUE | AC5: ACHAT LOT PRINCIPAL T40 | AD5: ACHAT LOT PRINCIPAL T75 | AE5: ACHAT LOT PRINCIPAL T100 | AF5: MODE PAIEMENT LOT PRINCIPAL | AG5: NUM CHEQUE | AH5: PENALITE VERSEMENT ESPECES | AI5: VENTE PETIT LOT T40 | AJ5: VENTE PETIT LOT T75 | AK5: VENTE PETIT LOT T100 | AL5: INTERET PETIT LOT T40 | AM5: INTERET PETIT LOT T75 | AN5: INTERET PETIT LOT T100 | AO5: NUM CHEQUE | AP5: MODE PAIEMENT PETEIT LOT | AQ5: PENELAITE RETARD TONTINE | AR5: PENELAITE ECHEC TONTINE | AS5: RESTE | AT5: MUTUELLE | AU5: REMBOURSEMENT TRANSPORT | AV5: RETRAIT PARTIEL FONDS | AW5: MONTANT T40 | AX5: MONTANT T75 | AY5: MONTANT T100 | AZ5: MONTANT CHEQUE | BA5: MONTANT ESPECES | BB5: CONTRIBUTION FOYER | BC5: AUTRES SOTIES | BD5: MONTANT CHEQUE EFFECTIF | BE5: NUMERO CHEQUE | BF5: INTERET PRÊT | BG5: NBRE MOIS | BH5: DEPENSE FONDS DE ROULEMENT | BI5: DEPENSE FRAIS EXCEPTIONNEL | BJ5: DEPENSE FONDS MUTUEL | BK5: DEPENSE COLLATION RECEPTION | BL5: PENALITE PRET FONDS | BM5: MONTANT GRATIFICATION 2022 | BN5: LIBELLE | BO5: COMPTE | BP5: MONTANT
A6: AS201648 | B6: =VLOOKUP(A6,[11]LISTADHERENT!A$5:H$39,3,0) -> ASELBY | C6: =D6+E6+F6-U6-BB6 -> 0 | D6: =VLOOKUP(A6,[12]HISTOBQUEFEV23!$A$6:$G$44,3,0) -> 175000 | E6: =VLOOKUP(A6,[12]HISTOBQUEFEV23!$A$6:$G$39,4,0) -> 0 | F6: =VLOOKUP(A6,[12]HISTOBQUEFEV23!$A$6:$G$39,5,0) -> 0 | G6: =IF(H6="ESPECES",3000,0) -> 0 | H6: =IF($D6<>0,"BANQUE",IF($E6<>0,"ESPECES","ECHEC")) -> BANQUE | K6: =IF($D6<>0,J6*40000,IF($E6<>0,J6*40000,0)) -> 0 | L6: 1 | M6: =IF($D6<>0,L6*75000,IF($E6<>0,L6*75000,0)) -> 75000 | N6: 1 | O6: =IF($D6<>0,N6*100000,IF($E6<>0,N6*100000,0)) -> 100000 | Q6: =VLOOKUP($A6,[13]TONTFEV23!$A$6:$P$20,10,0) -> 0 | R6: =VLOOKUP($A6,[14]TONTFEV23!$A$6:$P$21,10,0) -> 0 | U6: =G6+S6+R6+P6+O6+M6+I6+K6+Q6+V6+W6 -> 175000 | AQ6: =IF(H6="ECHEC",((K6+M6+O6)*20/100),0) -> 0 | AR6: =IF(H6="ECHEC",((K6+M6+O6)*20/100),0) -> 0 | AW6: =IF(AC6=0,AI6,(1*25000*12)+AI6-AC6) -> 0 | AX6: =IF(AD6=0,AJ6,(1*75000*12)+(AJ6)-AD6) -> 0 | AY6: =IF(AE6=0,AK6,(1*100000*12)+(AK6)-AE6) -> 0 | AZ6: =SUM(AV6:AY6)-BF6+Z6-F6+BH6+BI6+BJ6+BK6+BL6+BM6 -> 828500 | BA6: 262500 | BD6: =IF(AZ6=0,(AZ6-BA6-BC6),(AZ6-BA6-BB6-BC6))+F6 -> 566000 | BE6: 1206700 | BF6: =Z6*1/100*BG6 -> 0 | BG6: 10 | BH6: =BP16 -> 68500 | BI6: =BP28 -> 0 | BJ6: =BP33 -> 560000 | BM6: =BP22 -> 200000 | BN6: ACHAT FOURNITURE | BO6: FONDS DE ROULEMENT
A7: AS201601 | B7: =VLOOKUP(A7,[11]LISTADHERENT!A$5:H$39,3,0) -> BAKOP ACHILLE | C7: =D7+E7+F7-U7-BB7 -> 0 | D7: =VLOOKUP(A7,[12]HISTOBQUEFEV23!$A$6:$G$44,3,0) -> 0 | E7: =VLOOKUP(A7,[12]HISTOBQUEFEV23!$A$6:$G$39,4,0) -> 40000 | F7: =VLOOKUP(A7,[12]HISTOBQUEFEV23!$A$6:$G$39,5,0) -> 0 | G7: =IF(H7="ESPECES",3000,0)-3000 -> 0 | H7: =IF($D7<>0,"BANQUE",IF($E7<>0,"ESPECES","ECHEC")) -> ESPECES | J7: 1 | K7: =IF($D7<>0,J7*40000,IF($E7<>0,J7*40000,0)) -> 40000 | M7: =IF($D7<>0,L7*75000,IF($E7<>0,L7*75000,0)) -> 0 | O7: =IF($D7<>0,N7*100000,IF($E7<>0,N7*100000,0)) -> 0 | P7: =VLOOKUP($A7,[15]TONTFEV23!$A$6:$P$35,12,0) -> 0 | U7: =G7+S7+R7+P7+O7+M7+I7+K7+Q7+V7+W7 -> 40000 | AQ7: =IF(H7="ECHEC",((K7+M7+O7)*20/100),0) -> 0 | AR7: =IF(H7="ECHEC",((K7+M7+O7)*20/100),0) -> 0 | AS7: =IF(H7="ECHEC",0,(K7+I7-25000)) -> 15000 | AW7: =IF(AC7=0,AI7,(1*25000*12)+AI7-AC7) -> 0 | AX7: =IF(AD7=0,AJ7,(1*75000*12)+(AJ7)-AD7) -> 0 | AY7: =IF(AE7=0,AK7,(1*100000*12)+(AK7)-AE7) -> 0 | AZ7: =SUM(AV7:AY7)-BF7+Z7-F7+BH7+BI7+BJ7+BK7 -> 0 | BD7: =IF(AZ7=0,(AZ7-BA7-BC7),(AZ7-BA7-BB7-BC7))+F7 -> 0 | BF7: =Z7*1/100*BG7 -> 0 | BG7: 10 | BN7: COMMUNICATION | BO7: FONDS DE ROULEMENT
A8: AS201602 | B8: =VLOOKUP(A8,[11]LISTADHERENT!A$5:H$39,3,0) -> BOUTCHOUANG WILLIAM | C8: =D8+E8+F8-U8-BB8 -> 0 | D8: =VLOOKUP(A8,[12]HISTOBQUEFEV23!$A$6:$G$44,3,0) -> 615000 | E8: =VLOOKUP(A8,[12]HISTOBQUEFEV23!$A$6:$G$39,4,0) -> 0 | F8: =VLOOKUP(A8,[12]HISTOBQUEFEV23!$A$6:$G$39,5,0) -> 0 | G8: =IF(H8="ESPECES",3000,0) -> 0 | H8: =IF($D8<>0,"BANQUE",IF($E8<>0,"ESPECES","ECHEC")) -> BANQUE | J8: 1 | K8: =IF($D8<>0,J8*40000,IF($E8<>0,J8*40000,0)) -> 40000 | L8: 1 | M8: =IF($D8<>0,L8*75000,IF($E8<>0,L8*75000,0)) -> 75000 | O8: =IF($D8<>0,N8*100000,IF($E8<>0,N8*100000,0)) -> 0 | P8: =VLOOKUP($A8,[15]TONTFEV23!$A$6:$P$35,12,0) -> 0 | Q8: =VLOOKUP($A8,[13]TONTFEV23!$A$7:$P$20,10,0) -> 0 | S8: 500000 | T8: BANQUE | U8: =G8+S8+R8+P8+O8+M8+I8+K8+Q8+V8+W8 -> 615000 | AQ8: =IF(H8="ECHEC",((K8+M8+O8)*20/100),0) -> 0 | AR8: =IF(H8="ECHEC",((K8+M8+O8)*20/100),0) -> 0 | AS8: =IF(H8="ECHEC",0,(K8+I8-25000)) -> 15000 | AW8: =IF(AC8=0,AI8,(1*25000*12)+AI8-AC8) -> 0 | AX8: =IF(AD8=0,AJ8,(1*75000*12)+(AJ8)-AD8) -> 0 | AY8: =IF(AE8=0,AK8,(1*100000*12)+(AK8)-AE8) -> 0 | AZ8: =SUM(AV8:AY8)-BF8+Z8-F8+BH8+BI8+BJ8+BK8 -> 0 | BD8: =IF(AZ8=0,(AZ8-BA8-BC8),(AZ8-BA8-BB8-BC8))+F8 -> 0 | BF8: =Z8*1/100*BG8 -> 0 | BG8: 10 | BN8: COMMISSION | BO8: FONDS DE ROULEMENT | BP8: 27500
A9: AS201604 | B9: =VLOOKUP(A9,[11]LISTADHERENT!A$5:H$39,3,0) -> DJOMO JEAN PAUL | C9: =D9+E9+F9-U9-BB9 -> 0 | D9: =VLOOKUP(A9,[12]HISTOBQUEFEV23!$A$6:$G$44,3,0) -> 120000 | E9: =VLOOKUP(A9,[12]HISTOBQUEFEV23!$A$6:$G$39,4,0) -> 80000 | F9: =VLOOKUP(A9,[12]HISTOBQUEFEV23!$A$6:$G$39,5,0) -> 0 | G9: =IF(H9="ESPECES",3000,0) -> 0 | H9: =IF($D9<>0,"BANQUE",IF($E9<>0,"ESPECES","ECHEC")) -> BANQUE | I9: 8000 | J9: 1 | K9: =IF($D9<>0,J9*40000,IF($E9<>0,J9*40000,0)) -> 40000 | M9: =IF($D9<>0,L9*75000,IF($E9<>0,L9*75000,0)) -> 0 | N9: 1 | O9: =IF($D9<>0,N9*100000,IF($E9<>0,N9*100000,0)) -> 100000 | P9: =VLOOKUP($A9,[15]TONTFEV23!$A$6:$P$35,12,0) -> 0 | R9: =VLOOKUP($A9,[14]TONTFEV23!$A$6:$P$21,10,0) -> 52000 | U9: =G9+S9+R9+P9+O9+M9+I9+K9+Q9+V9+W9 -> 200000 | AP9: BANQUE | AQ9: =IF(H9="ECHEC",((K9+M9+O9)*20/100),0) -> 0 | AR9: =IF(H9="ECHEC",((K9+M9+O9)*20/100),0) -> 0 | AS9: =IF(H9="ECHEC",0,(K9+I9-25000)) -> 23000 | AW9: =IF(AC9=0,AI9,(1*25000*12)+AI9-AC9) -> 0 | AX9: =IF(AD9=0,AJ9,(1*75000*12)+(AJ9)-AD9) -> 0 | AY9: =IF(AE9=0,AK9,(1*100000*12)+(AK9)-AE9) -> 0 | AZ9: =SUM(AV9:AY9)-BF9+Z9-F9+BH9+BI9+BJ9+BK9 -> 0 | BD9: =IF(AZ9=0,(AZ9-BA9-BC9),(AZ9-BA9-BB9-BC9))+F9 -> 0 | BF9: =Z9*1/100*BG9 -> 0 | BG9: 10 | BN9: AIDE UEEB ET CONT FEMME | BO9: FONDS DE ROULEMENT
A10: AS201654 | B10: =VLOOKUP(A10,[11]LISTADHERENT!A$5:H$39,3,0) -> DJOMOU TCHAPDA | C10: =D10+E10+F10-U10-BB10 -> 0 | D10: =VLOOKUP(A10,[12]HISTOBQUEFEV23!$A$6:$G$44,3,0) -> 103000 | E10: =VLOOKUP(A10,[12]HISTOBQUEFEV23!$A$6:$G$39,4,0) -> 0 | F10: =VLOOKUP(A10,[12]HISTOBQUEFEV23!$A$6:$G$39,5,0) -> 0 | G10: =IF(H10="ESPECES",3000,0) -> 0 | H10: =IF($D10<>0,"BANQUE",IF($E10<>0,"ESPECES","ECHEC")) -> BANQUE | J10: 1 | K10: =IF($D10<>0,J10*40000,IF($E10<>0,J10*40000,0)) -> 40000 | M10: =IF($D10<>0,L10*75000,IF($E10<>0,L10*75000,0)) -> 0 | O10: =IF($D10<>0,N10*100000,IF($E10<>0,N10*100000,0)) -> 0 | P10: =VLOOKUP($A10,[15]TONTFEV23!$A$6:$P$35,12,0) -> 63000 | U10: =G10+S10+R10+P10+O10+M10+I10+K10+Q10+V10+W10 -> 103000 | AI10: 40000 | AL10: 1000 | AP10: BANQUE | AQ10: =IF(H10="ECHEC",((K10+M10+O10)*20/100),0) -> 0 | AR10: =IF(H10="ECHEC",((K10+M10+O10)*20/100),0) -> 0 | AS10: =IF(H10="ECHEC",0,(K10+I10-25000)) -> 15000 | AW10: =IF(AC10=0,AI10,(1*25000*12)+AI10-AC10) -> 40000 | AX10: =IF(AD10=0,AJ10,(1*75000*12)+(AJ10)-AD10) -> 0 | AY10: =IF(AE10=0,AK10,(1*100000*12)+(AK10)-AE10) -> 0 | AZ10: =SUM(AV10:AY10)-BF10+Z10-F10+BH10+BI10+BJ10+BK10 -> 40000 | BA10: 40000 | BD10: =IF(AZ10=0,(AZ10-BA10-BC10),(AZ10-BA10-BB10-BC10))+F10 -> 0 | BF10: =Z10*1/100*BG10 -> 0 | BG10: 10 | BN10: CREDIT TELEPHONE | BO10: FONDS DE ROULEMENT
A11: AS201605 | B11: =VLOOKUP(A11,[11]LISTADHERENT!A$5:H$39,3,0) -> DJOUKWE NANGUEN GUY BLAISE | C11: =D11+E11+F11-U11-BB11 -> 0 | D11: =VLOOKUP(A11,[12]HISTOBQUEFEV23!$A$6:$G$44,3,0) -> 177000 | E11: =VLOOKUP(A11,[12]HISTOBQUEFEV23!$A$6:$G$39,4,0) -> 0 | F11: =VLOOKUP(A11,[12]HISTOBQUEFEV23!$A$6:$G$39,5,0) -> 0 | G11: =IF(H11="ESPECES",3000,0) -> 0 | H11: =IF($D11<>0,"BANQUE",IF($E11<>0,"ESPECES","ECHEC")) -> BANQUE | J11: 1 | K11: =IF($D11<>0,J11*40000,IF($E11<>0,J11*40000,0)) -> 40000 | L11: 1 | M11: =IF($D11<>0,L11*75000,IF($E11<>0,L11*75000,0)) -> 75000 | O11: =IF($D11<>0,N11*100000,IF($E11<>0,N11*100000,0)) -> 0 | P11: =VLOOKUP($A11,[15]TONTFEV23!$A$6:$P$35,12,0) -> 62000 | Q11: =VLOOKUP($A11,[13]TONTFEV23!$A$7:$P$20,10,0) -> 0 | U11: =G11+S11+R11+P11+O11+M11+I11+K11+Q11+V11+W11 -> 177000 | AP11: BANQUE | AQ11: =IF(H11="ECHEC",((K11+M11+O11)*20/100),0) -> 0 | AR11: =IF(H11="ECHEC",((K11+M11+O11)*20/100),0) -> 0 | AS11: =IF(H11="ECHEC",0,(K11+I11-25000)) -> 15000 | AW11: =IF(AC11=0,AI11,(1*25000*12)+AI11-AC11) -> 0 | AX11: =IF(AD11=0,AJ11,(1*75000*12)+(AJ11)-AD11) -> 0 | AY11: =IF(AE11=0,AK11,(1*100000*12)+(AK11)-AE11) -> 0 | AZ11: =SUM(AV11:AY11)-BF11+Z11-F11+BH11+BI11+BJ11+BK11 -> 0 | BD11: =IF(AZ11=0,(AZ11-BA11-BC11),(AZ11-BA11-BB11-BC11))+F11 -> 0 | BF11: =Z11*1/100*BG11 -> 0 | BG11: 10 | BN11: PRODUCTION RAPPORT | BO11: FONDS DE ROULEMENT | BP11: 35000
A12: AS201608 | B12: =VLOOKUP(A12,[11]LISTADHERENT!A$5:H$39,3,0) -> DJUOMBESSY ANTOINE | C12: =D12+E12+F12-U12-BB12 -> 0 | D12: =VLOOKUP(A12,[12]HISTOBQUEFEV23!$A$6:$G$44,3,0) -> 320000 | E12: =VLOOKUP(A12,[12]HISTOBQUEFEV23!$A$6:$G$39,4,0) -> 0 | F12: =VLOOKUP(A12,[12]HISTOBQUEFEV23!$A$6:$G$39,5,0) -> 0 | G12: =IF(H12="ESPECES",3000,0) -> 0 | H12: =IF($D12<>0,"BANQUE",IF($E12<>0,"ESPECES","ECHEC")) -> BANQUE | I12: 5000 | J12: 1 | K12: =IF($D12<>0,J12*40000,IF($E12<>0,J12*40000,0)) -> 40000 | L12: 1 | M12: =IF($D12<>0,L12*75000,IF($E12<>0,L12*75000,0)) -> 75000 | N12: 2 | O12: =IF($D12<>0,N12*100000,IF($E12<>0,N12*100000,0)) -> 200000 | P12: =VLOOKUP($A12,[15]TONTFEV23!$A$6:$P$35,12,0) -> 0 | Q12: =VLOOKUP($A12,[13]TONTFEV23!$A$7:$P$20,10,0) -> 0 | R12: =VLOOKUP($A12,[14]TONTFEV23!$A$6:$P$21,10,0) -> 0 | U12: =G12+S12+R12+P12+O12+M12+I12+K12+Q12+V12+W12 -> 320000 | AQ12: =IF(H12="ECHEC",((K12+M12+O12)*20/100),0) -> 0 | AR12: =IF(H12="ECHEC",((K12+M12+O12)*20/100),0) -> 0 | AS12: =IF(H12="ECHEC",0,(K12+I12-25000)) -> 20000 | AW12: =IF(AC12=0,AI12,(1*25000*12)+AI12-AC12) -> 0 | AX12: =IF(AD12=0,AJ12,(1*75000*12)+(AJ12)-AD12) -> 0 | AY12: =IF(AE12=0,AK12,(1*100000*12)+(AK12)-AE12) -> 0 | AZ12: =SUM(AV12:AY12)-BF12+Z12-F12+BH12+BI12+BJ12+BK12 -> 0 | BD12: =IF(AZ12=0,(AZ12-BA12-BC12),(AZ12-BA12-BB12-BC12))+F12 -> 0 | BF12: =Z12*1/100*BG12 -> 0 | BG12: 10 | BN12: ACHAT SOURIS ET PHOTOCOPIE | BO12: FONDS DE ROULEMENT
A13: AS201651 | B13: =VLOOKUP(A13,[11]LISTADHERENT!A$5:H$39,3,0) -> DOMOU FABIEN | C13: =D13+E13+F13-U13-BB13 -> 0 | D13: =VLOOKUP(A13,[12]HISTOBQUEFEV23!$A$6:$G$44,3,0) -> 0 | E13: =VLOOKUP(A13,[12]HISTOBQUEFEV23!$A$6:$G$39,4,0) -> 40000 | F13: =VLOOKUP(A13,[12]HISTOBQUEFEV23!$A$6:$G$39,5,0) -> 0 | G13: =IF(H13="ESPECES",3000,0)-3000 -> 0 | H13: =IF($D13<>0,"BANQUE",IF($E13<>0,"ESPECES","ECHEC")) -> ESPECES | J13: 1 | K13: =IF($D13<>0,J13*40000,IF($E13<>0,J13*40000,0)) -> 40000 | M13: =IF($D13<>0,L13*75000,IF($E13<>0,L13*75000,0)) -> 0 | O13: =IF($D13<>0,N13*100000,IF($E13<>0,N13*100000,0)) -> 0 | P13: =VLOOKUP($A13,[15]TONTFEV23!$A$6:$P$35,12,0) -> 0 | U13: =G13+S13+R13+P13+O13+M13+I13+K13+Q13+V13+W13 -> 40000 | AQ13: =IF(H13="ECHEC",((K13+M13+O13)*20/100),0) -> 0 | AR13: =IF(H13="ECHEC",((K13+M13+O13)*20/100),0) -> 0 | AS13: =IF(H13="ECHEC",0,(K13+I13-25000)) -> 15000 | AW13: =IF(AC13=0,AI13,(1*25000*12)+AI13-AC13) -> 0 | AX13: =IF(AD13=0,AJ13,(1*75000*12)+(AJ13)-AD13) -> 0 | AY13: =IF(AE13=0,AK13,(1*100000*12)+(AK13)-AE13) -> 0 | AZ13: =SUM(AV13:AY13)-BF13+Z13-F13+BH13+BI13+BJ13+BK13 -> 0 | BD13: =IF(AZ13=0,(AZ13-BA13-BC13),(AZ13-BA13-BB13-BC13))+F13 -> 0 | BF13: =Z13*1/100*BG13 -> 0 | BG13: 10 | BN13: TAXI BANQUE | BO13: FONDS DE ROULEMENT | BP13: 6000
A14: AS201609 | B14: =VLOOKUP(A14,[11]LISTADHERENT!A$5:H$39,3,0) -> DONHOU DAVID | C14: =D14+E14+F14-U14-BB14 -> 0 | D14: =VLOOKUP(A14,[12]HISTOBQUEFEV23!$A$6:$G$44,3,0) -> 40000 | E14: =VLOOKUP(A14,[12]HISTOBQUEFEV23!$A$6:$G$39,4,0) -> 0 | F14: =VLOOKUP(A14,[12]HISTOBQUEFEV23!$A$6:$G$39,5,0) -> 0 | G14: =IF(H14="ESPECES",3000,0) -> 0 | H14: =IF($D14<>0,"BANQUE",IF($E14<>0,"ESPECES","ECHEC")) -> BANQUE | J14: 1 | K14: =IF($D14<>0,J14*40000,IF($E14<>0,J14*40000,0)) -> 40000 | M14: =IF($D14<>0,L14*75000,IF($E14<>0,L14*75000,0)) -> 0 | O14: =IF($D14<>0,N14*100000,IF($E14<>0,N14*100000,0)) -> 0 | P14: =VLOOKUP($A14,[15]TONTFEV23!$A$6:$P$35,12,0) -> 0 | U14: =G14+S14+R14+P14+O14+M14+I14+K14+Q14+V14+W14 -> 40000 | AQ14: =IF(H14="ECHEC",((K14+M14+O14)*20/100),0) -> 0 | AR14: =IF(H14="ECHEC",((K14+M14+O14)*20/100),0) -> 0 | AS14: =IF(H14="ECHEC",0,(K14+I14-25000)) -> 15000 | AW14: =IF(AC14=0,AI14,(1*25000*12)+AI14-AC14) -> 0 | AX14: =IF(AD14=0,AJ14,(1*75000*12)+(AJ14)-AD14) -> 0 | AY14: =IF(AE14=0,AK14,(1*100000*12)+(AK14)-AE14) -> 0 | AZ14: =SUM(AV14:AY14)-BF14+Z14-F14+BH14+BI14+BJ14+BK14 -> 0 | BD14: =IF(AZ14=0,(AZ14-BA14-BC14),(AZ14-BA14-BB14-BC14))+F14 -> 0 | BF14: =Z14*1/100*BG14 -> 0 | BG14: 10 | BN14: CONFECTION CACHET | BO14: FONDS DE ROULEMENT
A15: AS201611 | B15: =VLOOKUP(A15,[11]LISTADHERENT!A$5:H$39,3,0) -> HENGUE PAUL OMER | C15: =D15+E15+F15-U15-BB15 -> 0 | D15: =VLOOKUP(A15,[12]HISTOBQUEFEV23!$A$6:$G$44,3,0) -> 115000 | E15: =VLOOKUP(A15,[12]HISTOBQUEFEV23!$A$6:$G$39,4,0) -> 0 | F15: =VLOOKUP(A15,[12]HISTOBQUEFEV23!$A$6:$G$39,5,0) -> 0 | G15: =IF(H15="ESPECES",3000,0) -> 0 | H15: =IF($D15<>0,"BANQUE",IF($E15<>0,"ESPECES","ECHEC")) -> BANQUE | J15: 1 | K15: =IF($D15<>0,J15*40000,IF($E15<>0,J15*40000,0)) -> 40000 | L15: 1 | M15: =IF($D15<>0,L15*75000,IF($E15<>0,L15*75000,0)) -> 75000 | O15: =IF($D15<>0,N15*100000,IF($E15<>0,N15*100000,0)) -> 0 | P15: =VLOOKUP($A15,[15]TONTFEV23!$A$6:$P$35,12,0) -> 0 | Q15: =VLOOKUP($A15,[13]TONTFEV23!$A$7:$P$20,10,0) -> 0 | U15: =G15+S15+R15+P15+O15+M15+I15+K15+Q15+V15+W15 -> 115000 | AQ15: =IF(H15="ECHEC",((K15+M15+O15)*20/100),0) -> 0 | AR15: =IF(H15="ECHEC",((K15+M15+O15)*20/100),0) -> 0 | AS15: =IF(H15="ECHEC",0,(K15+I15-25000)) -> 15000 | AW15: =IF(AC15=0,AI15,(1*25000*12)+AI15-AC15) -> 0 | AX15: =IF(AD15=0,AJ15,(1*75000*12)+(AJ15)-AD15) -> 0 | AY15: =IF(AE15=0,AK15,(1*100000*12)+(AK15)-AE15) -> 0 | AZ15: =SUM(AV15:AY15)-BF15+Z15-F15+BH15+BI15+BJ15+BK15 -> 0 | BD15: =IF(AZ15=0,(AZ15-BA15-BC15),(AZ15-BA15-BB15-BC15))+F15 -> 0 | BF15: =Z15*1/100*BG15 -> 0 | BG15: 10
A16: AS201613 | B16: =VLOOKUP(A16,[11]LISTADHERENT!A$5:H$39,3,0) -> HOTCHO BENJAMIN | C16: =D16+E16+F16-U16-BB16 -> 0 | D16: =VLOOKUP(A16,[12]HISTOBQUEFEV23!$A$6:$G$44,3,0) -> 250000 | E16: =VLOOKUP(A16,[12]HISTOBQUEFEV23!$A$6:$G$39,4,0) -> 0 | F16: =VLOOKUP(A16,[12]HISTOBQUEFEV23!$A$6:$G$39,5,0) -> 1000000 | G16: =IF(H16="ESPECES",3000,0) -> 0 | H16: =IF($D16<>0,"BANQUE",IF($E16<>0,"ESPECES","ECHEC")) -> BANQUE | I16: 35000 | J16: 1 | K16: =IF($D16<>0,J16*40000,IF($E16<>0,J16*40000,0)) -> 40000 | L16: 1 | M16: =IF($D16<>0,L16*75000,IF($E16<>0,L16*75000,0)) -> 75000 | N16: 1 | O16: =IF($D16<>0,N16*100000,IF($E16<>0,N16*100000,0)) -> 100000 | P16: =VLOOKUP($A16,[15]TONTFEV23!$A$6:$P$35,12,0) -> 0 | Q16: =VLOOKUP($A16,[13]TONTFEV23!$A$7:$P$20,10,0) -> 0 | R16: =VLOOKUP($A16,[14]TONTFEV23!$A$6:$P$21,10,0) -> 0 | S16: 1000000 | T16: BANQUE | U16: =G16+S16+R16+P16+O16+M16+I16+K16+Q16+V16+W16 -> 1250000 | AD16: 20000 | AE16: 28000 | AF16: BANQUE | AP16: BANQUE | AQ16: =IF(H16="ECHEC",((K16+M16+O16)*20/100),0) -> 0 | AR16: =IF(H16="ECHEC",((K16+M16+O16)*20/100),0) -> 0 | AS16: =IF(H16="ECHEC",0,(K16+I16-25000)) -> 50000 | AW16: =IF(AC16=0,AI16,(1*25000*12)+AI16-AC16) -> 0 | AX16: =IF(AD16=0,AJ16,(1*75000*12)+(AJ16)-AD16) -> 880000 | AY16: =IF(AE16=0,AK16,(1*100000*12)+(AK16)-AE16) -> 1172000 | AZ16: =SUM(AV16:AY16)-BF16+Z16-F16+BH16+BI16+BJ16+BK16 -> 1052000 | BD16: =IF(AZ16=0,(AZ16-BA16-BC16),(AZ16-BA16-BB16-BC16)) -> 1052000 | BE16: =880000+172000 -> 1052000 | BF16: =Z16*1/100*BG16 -> 0 | BG16: 10 | BN16: S/TOTAL | BP16: =SUM(BP6:BP15) -> 68500
A17: AS201617 | B17: =VLOOKUP(A17,[11]LISTADHERENT!A$5:H$39,3,0) -> KOUAMOU MOISE | C17: =D17+E17+F17-U17-BB17 -> -70000 | D17: =VLOOKUP(A17,[12]HISTOBQUEFEV23!$A$6:$G$44,3,0) -> 140000 | E17: =VLOOKUP(A17,[12]HISTOBQUEFEV23!$A$6:$G$39,4,0) -> 0 | F17: =VLOOKUP(A17,[12]HISTOBQUEFEV23!$A$6:$G$39,5,0) -> 0 | G17: =IF(H17="ESPECES",3000,0) -> 0 | H17: =IF($D17<>0,"BANQUE",IF($E17<>0,"ESPECES","ECHEC")) -> BANQUE | J17: 1 | K17: =IF($D17<>0,J17*40000,IF($E17<>0,J17*40000,0)) -> 40000 | M17: =IF($D17<>0,L17*75000,IF($E17<>0,L17*75000,0)) -> 0 | N17: 1 | O17: =IF($D17<>0,N17*100000,IF($E17<>0,N17*100000,0)) -> 100000 | P17: =VLOOKUP($A17,[15]TONTFEV23!$A$6:$P$35,12,0) -> 0 | R17: =VLOOKUP($A17,[14]TONTFEV23!$A$6:$P$21,10,0) -> 0 | U17: =G17+S17+R17+P17+O17+M17+I17+K17+Q17+V17+W17 -> 140000 | AC17: 6500 | AE17: 28000 | AF17: BANQUE | AP17: BANQUE | AQ17: =IF(H17="ECHEC",((K17+M17+O17)*20/100),0) -> 0 | AR17: =IF(H17="ECHEC",((K17+M17+O17)*20/100),0) -> 0 | AS17: =IF(H17="ECHEC",0,(K17+I17-25000)) -> 15000 | AW17: =IF(AC17=0,AI17,(1*25000*12)+AI17-AC17) -> 293500 | AX17: =IF(AD17=0,AJ17,(1*75000*12)+(AJ17)-AD17) -> 0 | AY17: =IF(AE17=0,AK17,(1*100000*12)+(AK17)-AE17) -> 1172000 | AZ17: =SUM(AV17:AY17)-BF17+Z17-F17+BH17+BI17+BJ17+BK17 -> 1465500 | BA17: 64500 | BB17: 70000 | BD17: =IF(AZ17=0,(AZ17-BA17-BC17),(AZ17-BA17-BB17-BC17))+F17 -> 1331000 | BE17: =159000+1172000 -> 1331000 | BF17: =Z17*1/100*BG17 -> 0 | BG17: 10
A18: AS201619 | B18: =VLOOKUP(A18,[11]LISTADHERENT!A$5:H$39,3,0) -> KOUATCHO MESSACK | C18: =D18+E18+F18-U18-BB18 -> 0 | D18: =VLOOKUP(A18,[12]HISTOBQUEFEV23!$A$6:$G$44,3,0) -> 51000 | E18: =VLOOKUP(A18,[12]HISTOBQUEFEV23!$A$6:$G$39,4,0) -> 266000 | F18: =VLOOKUP(A18,[12]HISTOBQUEFEV23!$A$6:$G$39,5,0) -> 0 | G18: =IF(H18="ESPECES",3000,0) -> 0 | H18: =IF($D18<>0,"BANQUE",IF($E18<>0,"ESPECES","ECHEC")) -> BANQUE | J18: 1 | K18: =IF($D18<>0,J18*40000,IF($E18<>0,J18*40000,0)) -> 40000 | L18: 1 | M18: =IF($D18<>0,L18*75000,IF($E18<>0,L18*75000,0)) -> 75000 | N18: 1 | O18: =IF($D18<>0,N18*100000,IF($E18<>0,N18*100000,0)) -> 100000 | P18: =VLOOKUP($A18,[15]TONTFEV23!$A$6:$P$35,12,0) -> 0 | Q18: =VLOOKUP($A18,[13]TONTFEV23!$A$7:$P$20,10,0) -> 102000 | R18: =VLOOKUP($A18,[14]TONTFEV23!$A$6:$P$21,10,0) -> 0 | U18: =G18+S18+R18+P18+O18+M18+I18+K18+Q18+V18+W18 -> 317000 | AP18: BANQUE | AQ18: =IF(H18="ECHEC",((K18+M18+O18)*20/100),0) -> 0 | AR18: =IF(H18="ECHEC",((K18+M18+O18)*20/100),0) -> 0 | AS18: =IF(H18="ECHEC",0,(K18+I18-25000)) -> 15000 | AW18: =IF(AC18=0,AI18,(1*25000*12)+AI18-AC18) -> 0 | AX18: =IF(AD18=0,AJ18,(1*75000*12)+(AJ18)-AD18) -> 0 | AY18: =IF(AE18=0,AK18,(1*100000*12)+(AK18)-AE18) -> 0 | AZ18: =SUM(AV18:AY18)-BF18+Z18-F18+BH18+BI18+BJ18+BK18 -> 0 | BD18: =IF(AZ18=0,(AZ18-BA18-BC18),(AZ18-BA18-BB18-BC18))+F18 -> 0 | BF18: =Z18*1/100*BG18 -> 0 | BG18: 10 | BN18: GRATIFICATION BUREAU 2022 | BO18: PENALITE VERSEMENT ESPECES | BP18: 200000
A19: AS201620 | B19: =VLOOKUP(A19,[11]LISTADHERENT!A$5:H$39,3,0) -> LOWE JEAN | C19: =D19+E19+F19-U19-BB19 -> 0 | D19: =VLOOKUP(A19,[12]HISTOBQUEFEV23!$A$6:$G$44,3,0) -> 0 | E19: =VLOOKUP(A19,[12]HISTOBQUEFEV23!$A$6:$G$39,4,0) -> 40000 | F19: =VLOOKUP(A19,[12]HISTOBQUEFEV23!$A$6:$G$39,5,0) -> 0 | G19: =IF(H19="ESPECES",3000,0)-3000 -> 0 | H19: =IF($D19<>0,"BANQUE",IF($E19<>0,"ESPECES","ECHEC")) -> ESPECES | J19: 1 | K19: =IF($D19<>0,J19*40000,IF($E19<>0,J19*40000,0)) -> 40000 | M19: =IF($D19<>0,L19*75000,IF($E19<>0,L19*75000,0)) -> 0 | O19: =IF($D19<>0,N19*100000,IF($E19<>0,N19*100000,0)) -> 0 | P19: =VLOOKUP($A19,[15]TONTFEV23!$A$6:$P$35,12,0) -> 0 | U19: =G19+S19+R19+P19+O19+M19+I19+K19+Q19+V19+W19 -> 40000 | AQ19: =IF(H19="ECHEC",((K19+M19+O19)*20/100),0) -> 0 | AR19: =IF(H19="ECHEC",((K19+M19+O19)*20/100),0) -> 0 | AS19: =IF(H19="ECHEC",0,(K19+I19-25000)) -> 15000 | AW19: =IF(AC19=0,AI19,(1*25000*12)+AI19-AC19) -> 0 | AX19: =IF(AD19=0,AJ19,(1*75000*12)+(AJ19)-AD19) -> 0 | AY19: =IF(AE19=0,AK19,(1*100000*12)+(AK19)-AE19) -> 0 | AZ19: =SUM(AV19:AY19)-BF19+Z19-F19+BH19+BI19+BJ19+BK19 -> 0 | BD19: =IF(AZ19=0,(AZ19-BA19-BC19),(AZ19-BA19-BB19-BC19))+F19 -> 0 | BF19: =Z19*1/100*BG19 -> 0 | BG19: 10 | BN19: ACHAT LAPTOP | BO19: PENALITE VERSEMENT ESPECES
A20: AS201649 | B20: =VLOOKUP(A20,[11]LISTADHERENT!A$5:H$39,3,0) -> MBOGNING TUGMA GUY | C20: =D20+E20+F20-U20-BB20 -> 0 | D20: =VLOOKUP(A20,[12]HISTOBQUEFEV23!$A$6:$G$44,3,0) -> 107000 | E20: =VLOOKUP(A20,[12]HISTOBQUEFEV23!$A$6:$G$39,4,0) -> 215000 | F20: =VLOOKUP(A20,[12]HISTOBQUEFEV23!$A$6:$G$39,5,0) -> 0 | G20: =IF(H20="ESPECES",3000,0) -> 0 | H20: =IF($D20<>0,"BANQUE",IF($E20<>0,"ESPECES","ECHEC")) -> BANQUE | J20: 1 | K20: =IF($D20<>0,J20*40000,IF($E20<>0,J20*40000,0)) -> 40000 | L20: 1 | M20: =IF($D20<>0,L20*75000,IF($E20<>0,L20*75000,0)) -> 75000 | N20: 1 | O20: =IF($D20<>0,N20*100000,IF($E20<>0,N20*100000,0)) -> 100000 | P20: =VLOOKUP($A20,[15]TONTFEV23!$A$6:$P$35,12,0) -> 0 | Q20: =VLOOKUP($A20,[13]TONTFEV23!$A$7:$P$20,10,0) -> 107000 | R20: =VLOOKUP($A20,[14]TONTFEV23!$A$6:$P$21,10,0) -> 0 | U20: =G20+S20+R20+P20+O20+M20+I20+K20+Q20+V20+W20 -> 322000 | AD20: 22000 | AF20: BANQUE | AI20: 31500 | AL20: 1000 | AP20: BANQUE | AQ20: =IF(H20="ECHEC",((K20+M20+O20)*20/100),0) -> 0 | AR20: =IF(H20="ECHEC",((K20+M20+O20)*20/100),0) -> 0 | AS20: =IF(H20="ECHEC",0,(K20+I20-25000)) -> 15000 | AW20: =IF(AC20=0,AI20,(1*25000*12)+AI20-AC20) -> 31500 | AX20: =IF(AD20=0,AJ20,(1*75000*12)+(AJ20)-AD20) -> 878000 | AY20: =IF(AE20=0,AK20,(1*100000*12)+(AK20)-AE20) -> 0 | AZ20: =SUM(AV20:AY20)-BF20+Z20-F20+BH20+BI20+BJ20+BK20-500000 -> 409500 | BA20: =378000+31500 -> 409500 | BD20: =IF(AZ20=0,(AZ20-BA20-BC20),(AZ20-BA20-BB20-BC20))+F20 -> 0 | BF20: =Z20*1/100*BG20 -> 0 | BG20: 10
A21: AS201639 | B21: =VLOOKUP(A21,[11]LISTADHERENT!A$5:H$39,3,0) -> NANGUEN MARTIN | C21: =D21+E21+F21-U21-BB21 -> 0 | D21: =VLOOKUP(A21,[12]HISTOBQUEFEV23!$A$6:$G$44,3,0) -> 40000 | E21: =VLOOKUP(A21,[12]HISTOBQUEFEV23!$A$6:$G$39,4,0) -> 0 | F21: =VLOOKUP(A21,[12]HISTOBQUEFEV23!$A$6:$G$39,5,0) -> 0 | G21: =IF(H21="ESPECES",3000,0) -> 0 | H21: =IF($D21<>0,"BANQUE",IF($E21<>0,"ESPECES","ECHEC")) -> BANQUE | J21: 1 | K21: =IF($D21<>0,J21*40000,IF($E21<>0,J21*40000,0)) -> 40000 | M21: =IF($D21<>0,L21*75000,IF($E21<>0,L21*75000,0)) -> 0 | O21: =IF($D21<>0,N21*100000,IF($E21<>0,N21*100000,0)) -> 0 | P21: =VLOOKUP($A21,[15]TONTFEV23!$A$6:$P$35,12,0) -> 0 | U21: =G21+S21+R21+P21+O21+M21+I21+K21+Q21+V21+W21 -> 40000 | AQ21: =IF(H21="ECHEC",((K21+M21+O21)*20/100),0) -> 0 | AR21: =IF(H21="ECHEC",((K21+M21+O21)*20/100),0) -> 0 | AS21: =IF(H21="ECHEC",0,(K21+I21-25000)) -> 15000 | AW21: =IF(AC21=0,AI21,(1*25000*12)+AI21-AC21) -> 0 | AX21: =IF(AD21=0,AJ21,(1*75000*12)+(AJ21)-AD21) -> 0 | AY21: =IF(AE21=0,AK21,(1*100000*12)+(AK21)-AE21) -> 0 | AZ21: =SUM(AV21:AY21)-BF21+Z21-F21+BH21+BI21+BJ21+BK21 -> 0 | BD21: =IF(AZ21=0,(AZ21-BA21-BC21),(AZ21-BA21-BB21-BC21))+F21 -> 0 | BF21: =Z21*1/100*BG21 -> 0 | BG21: 10
A22: AS201621 | B22: =VLOOKUP(A22,[11]LISTADHERENT!A$5:H$39,3,0) -> NANKAM APPOLINAIRE | C22: =D22+E22+F22-U22-BB22 -> 0 | D22: =VLOOKUP(A22,[12]HISTOBQUEFEV23!$A$6:$G$44,3,0) -> 115000 | E22: =VLOOKUP(A22,[12]HISTOBQUEFEV23!$A$6:$G$39,4,0) -> 0 | F22: =VLOOKUP(A22,[12]HISTOBQUEFEV23!$A$6:$G$39,5,0) -> 0 | G22: =IF(H22="ESPECES",3000,0) -> 0 | H22: =IF($D22<>0,"BANQUE",IF($E22<>0,"ESPECES","ECHEC")) -> BANQUE | J22: 1 | K22: =IF($D22<>0,J22*40000,IF($E22<>0,J22*40000,0)) -> 40000 | L22: 1 | M22: =IF($D22<>0,L22*75000,IF($E22<>0,L22*75000,0)) -> 75000 | O22: =IF($D22<>0,N22*100000,IF($E22<>0,N22*100000,0)) -> 0 | P22: =VLOOKUP($A22,[15]TONTFEV23!$A$6:$P$35,12,0) -> 0 | Q22: =VLOOKUP($A22,[13]TONTFEV23!$A$7:$P$20,10,0) -> 0 | U22: =G22+S22+R22+P22+O22+M22+I22+K22+Q22+V22+W22 -> 115000 | AQ22: =IF(H22="ECHEC",((K22+M22+O22)*20/100),0) -> 0 | AR22: =IF(H22="ECHEC",((K22+M22+O22)*20/100),0) -> 0 | AS22: =IF(H22="ECHEC",0,(K22+I22-25000)) -> 15000 | AW22: =IF(AC22=0,AI22,(1*25000*12)+AI22-AC22) -> 0 | AX22: =IF(AD22=0,AJ22,(1*75000*12)+(AJ22)-AD22) -> 0 | AY22: =IF(AE22=0,AK22,(1*100000*12)+(AK22)-AE22) -> 0 | AZ22: =SUM(AV22:AY22)-BF22+Z22-F22+BH22+BI22+BJ22+BK22 -> 0 | BD22: =IF(AZ22=0,(AZ22-BA22-BC22),(AZ22-BA22-BB22-BC22))+F22 -> 0 | BF22: =Z22*1/100*BG22 -> 0 | BG22: 10 | BN22: S/TOTAL | BP22: =SUM(BP18:BP21) -> 200000
A23: AS201622 | B23: =VLOOKUP(A23,[11]LISTADHERENT!A$5:H$39,3,0) -> NDJOMO ETIENNE | C23: =D23+E23+F23-U23-BB23 -> 0 | D23: =VLOOKUP(A23,[12]HISTOBQUEFEV23!$A$6:$G$44,3,0) -> 250000 | E23: =VLOOKUP(A23,[12]HISTOBQUEFEV23!$A$6:$G$39,4,0) -> 0 | F23: =VLOOKUP(A23,[12]HISTOBQUEFEV23!$A$6:$G$39,5,0) -> 0 | G23: =IF(H23="ESPECES",3000,0) -> 0 | H23: =IF($D23<>0,"BANQUE",IF($E23<>0,"ESPECES","ECHEC")) -> BANQUE | I23: 10000 | J23: 1 | K23: =IF($D23<>0,J23*40000,IF($E23<>0,J23*40000,0)) -> 40000 | M23: =IF($D23<>0,L23*75000,IF($E23<>0,L23*75000,0)) -> 0 | N23: 2 | O23: =IF($D23<>0,N23*100000,IF($E23<>0,N23*100000,0)) -> 200000 | P23: =VLOOKUP($A23,[15]TONTFEV23!$A$6:$P$35,12,0) -> 0 | R23: =VLOOKUP($A23,[14]TONTFEV23!$A$6:$P$21,10,0) -> 0 | U23: =G23+S23+R23+P23+O23+M23+I23+K23+Q23+V23+W23 -> 250000 | AQ23: =IF(H23="ECHEC",((K23+M23+O23)*20/100),0) -> 0 | AR23: =IF(H23="ECHEC",((K23+M23+O23)*20/100),0) -> 0 | AS23: =IF(H23="ECHEC",0,(K23+I23-25000)) -> 25000 | AW23: =IF(AC23=0,AI23,(1*25000*12)+AI23-AC23) -> 0 | AX23: =IF(AD23=0,AJ23,(1*75000*12)+(AJ23)-AD23) -> 0 | AY23: =IF(AE23=0,AK23,(1*100000*12)+(AK23)-AE23) -> 0 | AZ23: =SUM(AV23:AY23)-BF23+Z23-F23+BH23+BI23+BJ23+BK23 -> 0 | BD23: =IF(AZ23=0,(AZ23-BA23-BC23),(AZ23-BA23-BB23-BC23))+F23 -> 0 | BF23: =Z23*1/100*BG23 -> 0 | BG23: 10
A24: AS201624 | B24: =VLOOKUP(A24,[11]LISTADHERENT!A$5:H$39,3,0) -> NGONDIEP CLAUDE | C24: =D24+E24+F24-U24-BB24 -> 0 | D24: =VLOOKUP(A24,[12]HISTOBQUEFEV23!$A$6:$G$44,3,0) -> 551000 | E24: =VLOOKUP(A24,[12]HISTOBQUEFEV23!$A$6:$G$39,4,0) -> 0 | F24: =VLOOKUP(A24,[12]HISTOBQUEFEV23!$A$6:$G$39,5,0) -> 0 | G24: =IF(H24="ESPECES",3000,0) -> 0 | H24: =IF($D24<>0,"BANQUE",IF($E24<>0,"ESPECES","ECHEC")) -> BANQUE | J24: 1 | K24: =IF($D24<>0,J24*40000,IF($E24<>0,J24*40000,0)) -> 40000 | L24: 1 | M24: =IF($D24<>0,L24*75000,IF($E24<>0,L24*75000,0)) -> 75000 | N24: 1 | O24: =IF($D24<>0,N24*100000,IF($E24<>0,N24*100000,0)) -> 100000 | P24: =VLOOKUP($A24,[15]TONTFEV23!$A$6:$P$35,12,0) -> 26000 | Q24: =VLOOKUP($A24,[13]TONTFEV23!$A$7:$P$20,10,0) -> 102000 | R24: =VLOOKUP($A24,[14]TONTFEV23!$A$6:$P$21,10,0) -> 208000 | U24: =G24+S24+R24+P24+O24+M24+I24+K24+Q24+V24+W24 -> 551000 | AP24: BANQUE | AQ24: =IF(H24="ECHEC",((K24+M24+O24)*20/100),0) -> 0 | AR24: =IF(H24="ECHEC",((K24+M24+O24)*20/100),0) -> 0 | AS24: =IF(H24="ECHEC",0,(K24+I24-25000)) -> 15000 | AW24: =IF(AC24=0,AI24,(1*25000*12)+AI24-AC24) -> 0 | AX24: =IF(AD24=0,AJ24,(1*75000*12)+(AJ24)-AD24) -> 0 | AY24: =IF(AE24=0,AK24,(1*100000*12)+(AK24)-AE24) -> 0 | AZ24: =SUM(AV24:AY24)-BF24+Z24-F24+BH24+BI24+BJ24+BK24 -> 0 | BD24: =IF(AZ24=0,(AZ24-BA24-BC24),(AZ24-BA24-BB24-BC24))+F24 -> 0 | BF24: =Z24*1/100*BG24 -> 0 | BG24: 10 | BN24: GRATIFICATION BUREAU 2021 | BO24: FRAIS EXEPTIONNEL
A25: AS201626 | B25: =VLOOKUP(A25,[11]LISTADHERENT!A$5:H$39,3,0) -> NGUIEMEGNI MATHIEU BLAISE | C25: =D25+E25+F25-U25-BB25 -> 0 | D25: =VLOOKUP(A25,[12]HISTOBQUEFEV23!$A$6:$G$44,3,0) -> 451000 | E25: =VLOOKUP(A25,[12]HISTOBQUEFEV23!$A$6:$G$39,4,0) -> 50000 | F25: =VLOOKUP(A25,[12]HISTOBQUEFEV23!$A$6:$G$39,5,0) -> 70000 | G25: =IF(H25="ESPECES",3000,0) -> 0 | H25: =IF($D25<>0,"BANQUE",IF($E25<>0,"ESPECES","ECHEC")) -> BANQUE | J25: 1 | K25: =IF($D25<>0,J25*40000,IF($E25<>0,J25*40000,0)) -> 40000 | L25: 2 | M25: =IF($D25<>0,L25*75000,IF($E25<>0,L25*75000,0)) -> 150000 | N25: 1 | O25: =IF($D25<>0,N25*100000,IF($E25<>0,N25*100000,0)) -> 100000 | P25: =VLOOKUP($A25,[15]TONTFEV23!$A$6:$P$35,12,0) -> 31000 | Q25: =VLOOKUP($A25,[13]TONTFEV23!$A$7:$P$20,10,0) -> 102000 | R25: =VLOOKUP($A25,[14]TONTFEV23!$A$6:$P$21,10,0) -> 78000 | U25: =G25+S25+R25+P25+O25+M25+I25+K25+Q25+V25+W25 -> 501000 | AC25: 7500 | AF25: BANQUE | AP25: BANQUE | AQ25: =IF(H25="ECHEC",((K25+M25+O25)*20/100),0) -> 0 | AR25: =IF(H25="ECHEC",((K25+M25+O25)*20/100),0) -> 0 | AS25: =IF(H25="ECHEC",0,(K25+I25-25000)) -> 15000 | AW25: =IF(AC25=0,AI25,(1*25000*12)+AI25-AC25) -> 292500 | AX25: =IF(AD25=0,AJ25,(1*75000*12)+(AJ25)-AD25) -> 0 | AY25: =IF(AE25=0,AK25,(1*100000*12)+(AK25)-AE25) -> 0 | AZ25: =SUM(AV25:AY25)-BF25+Z25-F25+BH25+BI25+BJ25+BK25 -> 222500 | BB25: 70000 | BD25: =IF(AZ25=0,(AZ25-BA25-BC25),(AZ25-BA25-BB25-BC25))+F25 -> 222500 | BE25: 222500 | BF25: =Z25*1/100*BG25 -> 0 | BG25: 10 | BN25: DEVELOPPEMENT LAGWEU | BO25: FRAIS EXEPTIONNEL
A26: AS201628 | B26: =VLOOKUP(A26,[11]LISTADHERENT!A$5:H$39,3,0) -> NKAMGANG JUSTIN DEJOLIE | C26: =D26+E26+F26-U26-BB26 -> 0 | D26: =VLOOKUP(A26,[12]HISTOBQUEFEV23!$A$6:$G$44,3,0) -> 0 | E26: =VLOOKUP(A26,[12]HISTOBQUEFEV23!$A$6:$G$39,4,0) -> 102000 | F26: =VLOOKUP(A26,[12]HISTOBQUEFEV23!$A$6:$G$39,5,0)+1000000 -> 1070000 | G26: =IF(H26="ESPECES",3000,0)-3000 -> 0 | H26: =IF($D26<>0,"BANQUE",IF($E26<>0,"ESPECES","ECHEC")) -> ESPECES | J26: 1 | K26: =IF($D26<>0,J26*40000,IF($E26<>0,J26*40000,0)) -> 40000 | M26: =IF($D26<>0,L26*75000,IF($E26<>0,L26*75000,0)) -> 0 | O26: =IF($D26<>0,N26*100000,IF($E26<>0,N26*100000,0)) -> 0 | P26: =VLOOKUP($A26,[15]TONTFEV23!$A$6:$P$35,12,0) -> 62000 | S26: 1000000 | T26: BANQUE | U26: =G26+S26+R26+P26+O26+M26+I26+K26+Q26+V26+W26 -> 1102000 | Z26: 1000000 | AA26: BANQUE | AC26: 3500 | AF26: BANQUE | AI26: 40000 | AL26: 1000 | AP26: BANQUE | AQ26: =IF(H26="ECHEC",((K26+M26+O26)*20/100),0) -> 0 | AR26: =IF(H26="ECHEC",((K26+M26+O26)*20/100),0) -> 0 | AS26: =IF(H26="ECHEC",0,(K26+I26-25000)) -> 15000 | AW26: =IF(AC26=0,AI26,(1*25000*12)+AI26-AC26) -> 336500 | AX26: =IF(AD26=0,AJ26,(1*75000*12)+(AJ26)-AD26) -> 0 | AY26: =IF(AE26=0,AK26,(1*100000*12)+(AK26)-AE26) -> 0 | AZ26: =SUM(AV26:AY26)-BF26+Z26-F26+BH26+BI26+BJ26+BK26 -> 236500 | BA26: =196500+40000 -> 236500 | BB26: 70000 | BD26: =IF(AZ26=0,(AZ26-BA26-BC26),(AZ26-BA26-BB26-BC26))+70000 -> 0 | BF26: =Z26*1/100*BG26 -> 30000 | BG26: 3 | BN26: DEUIL TCHEMNOU EMMANUEL | BO26: FRAIS EXEPTIONNEL
A27: AS201656 | B27: =VLOOKUP(A27,[11]LISTADHERENT!A$5:H$39,3,0) -> NOUBE ETIENNE | C27: =D27+E27+F27-U27-BB27 -> 0 | D27: =VLOOKUP(A27,[12]HISTOBQUEFEV23!$A$6:$G$44,3,0) -> 40000 | E27: =VLOOKUP(A27,[12]HISTOBQUEFEV23!$A$6:$G$39,4,0) -> 0 | F27: =VLOOKUP(A27,[12]HISTOBQUEFEV23!$A$6:$G$39,5,0) -> 0 | G27: =IF(H27="ESPECES",3000,0) -> 0 | H27: =IF($D27<>0,"BANQUE",IF($E27<>0,"ESPECES","ECHEC")) -> BANQUE | J27: 1 | K27: =IF($D27<>0,J27*40000,IF($E27<>0,J27*40000,0)) -> 40000 | M27: =IF($D27<>0,L27*75000,IF($E27<>0,L27*75000,0)) -> 0 | O27: =IF($D27<>0,N27*100000,IF($E27<>0,N27*100000,0)) -> 0 | P27: =VLOOKUP($A27,[15]TONTFEV23!$A$6:$P$35,12,0) -> 0 | U27: =G27+S27+R27+P27+O27+M27+I27+K27+Q27+V27+W27 -> 40000 | AQ27: =IF(H27="ECHEC",((K27+M27+O27)*20/100),0) -> 0 | AR27: =IF(H27="ECHEC",((K27+M27+O27)*20/100),0) -> 0 | AS27: =IF(H27="ECHEC",0,(K27+I27-25000)) -> 15000 | AW27: =IF(AC27=0,AI27,(1*25000*12)+AI27-AC27) -> 0 | AX27: =IF(AD27=0,AJ27,(1*75000*12)+(AJ27)-AD27) -> 0 | AY27: =IF(AE27=0,AK27,(1*100000*12)+(AK27)-AE27) -> 0 | AZ27: =SUM(AV27:AY27)-BF27+Z27-F27+BH27+BI27+BJ27+BK27 -> 0 | BD27: =IF(AZ27=0,(AZ27-BA27-BC27),(AZ27-BA27-BB27-BC27))+F27 -> 0 | BF27: =Z27*1/100*BG27 -> 0 | BG27: 10
A28: AS201633 | B28: =VLOOKUP(A28,[11]LISTADHERENT!A$5:H$39,3,0) -> PATEGO NJOSSU GUSTAVE | C28: =D28+E28+F28-U28-BB28 -> 0 | D28: =VLOOKUP(A28,[12]HISTOBQUEFEV23!$A$6:$G$44,3,0) -> 115000 | E28: =VLOOKUP(A28,[12]HISTOBQUEFEV23!$A$6:$G$39,4,0) -> 0 | F28: =VLOOKUP(A28,[12]HISTOBQUEFEV23!$A$6:$G$39,5,0) -> 0 | G28: =IF(H28="ESPECES",3000,0) -> 0 | H28: =IF($D28<>0,"BANQUE",IF($E28<>0,"ESPECES","ECHEC")) -> BANQUE | J28: 1 | K28: =IF($D28<>0,J28*40000,IF($E28<>0,J28*40000,0)) -> 40000 | L28: 1 | M28: =IF($D28<>0,L28*75000,IF($E28<>0,L28*75000,0)) -> 75000 | O28: =IF($D28<>0,N28*100000,IF($E28<>0,N28*100000,0)) -> 0 | P28: =VLOOKUP($A28,[15]TONTFEV23!$A$6:$P$35,12,0) -> 0 | Q28: =VLOOKUP($A28,[13]TONTFEV23!$A$7:$P$20,10,0) -> 0 | U28: =G28+S28+R28+P28+O28+M28+I28+K28+Q28+V28+W28 -> 115000 | AQ28: =IF(H28="ECHEC",((K28+M28+O28)*20/100),0) -> 0 | AR28: =IF(H28="ECHEC",((K28+M28+O28)*20/100),0) -> 0 | AS28: =IF(H28="ECHEC",0,(K28+I28-25000)) -> 15000 | AW28: =IF(AC28=0,AI28,(1*25000*12)+AI28-AC28) -> 0 | AX28: =IF(AD28=0,AJ28,(1*75000*12)+(AJ28)-AD28) -> 0 | AY28: =IF(AE28=0,AK28,(1*100000*12)+(AK28)-AE28) -> 0 | AZ28: =SUM(AV28:AY28)-BF28+Z28-F28+BH28+BI28+BJ28+BK28 -> 0 | BD28: =IF(AZ28=0,(AZ28-BA28-BC28),(AZ28-BA28-BB28-BC28))+F28 -> 0 | BF28: =Z28*1/100*BG28 -> 0 | BG28: 10 | BN28: S/TOTAL | BP28: =SUM(BP24:BP26) -> 0
A29: AS201657 | B29: =VLOOKUP(A29,[11]LISTADHERENT!A$5:H$39,3,0) -> SEUMO POLYCARPE | C29: =D29+E29+F29-U29-BB29 -> 0 | D29: =VLOOKUP(A29,[12]HISTOBQUEFEV23!$A$6:$G$44,3,0) -> 40000 | E29: =VLOOKUP(A29,[12]HISTOBQUEFEV23!$A$6:$G$39,4,0) -> 0 | F29: =VLOOKUP(A29,[12]HISTOBQUEFEV23!$A$6:$G$39,5,0) -> 0 | G29: =IF(H29="ESPECES",3000,0) -> 0 | H29: =IF($D29<>0,"BANQUE",IF($E29<>0,"ESPECES","ECHEC")) -> BANQUE | J29: 1 | K29: =IF($D29<>0,J29*40000,IF($E29<>0,J29*40000,0)) -> 40000 | M29: =IF($D29<>0,L29*75000,IF($E29<>0,L29*75000,0)) -> 0 | O29: =IF($D29<>0,N29*100000,IF($E29<>0,N29*100000,0)) -> 0 | P29: =VLOOKUP($A29,[15]TONTFEV23!$A$6:$P$35,12,0) -> 0 | U29: =G29+S29+R29+P29+O29+M29+I29+K29+Q29+V29+W29 -> 40000 | AQ29: =IF(H29="ECHEC",((K29+M29+O29)*20/100),0) -> 0 | AR29: =IF(H29="ECHEC",((K29+M29+O29)*20/100),0) -> 0 | AS29: =IF(H29="ECHEC",0,(K29+I29-25000)) -> 15000 | AW29: =IF(AC29=0,AI29,(1*25000*12)+AI29-AC29) -> 0 | AX29: =IF(AD29=0,AJ29,(1*75000*12)+(AJ29)-AD29) -> 0 | AY29: =IF(AE29=0,AK29,(1*100000*12)+(AK29)-AE29) -> 0 | AZ29: =SUM(AV29:AY29)-BF29+Z29-F29+BH29+BI29+BJ29+BK29 -> 0 | BD29: =IF(AZ29=0,(AZ29-BA29-BC29),(AZ29-BA29-BB29-BC29))+F29 -> 0 | BF29: =Z29*1/100*BG29 -> 0 | BG29: 10
A30: AS201653 | B30: =VLOOKUP(A30,[11]LISTADHERENT!A$5:H$39,3,0) -> SIME BRICE | C30: =D30+E30+F30-U30-BB30 -> 0 | D30: =VLOOKUP(A30,[12]HISTOBQUEFEV23!$A$6:$G$44,3,0) -> 115000 | E30: =VLOOKUP(A30,[12]HISTOBQUEFEV23!$A$6:$G$39,4,0) -> 0 | F30: =VLOOKUP(A30,[12]HISTOBQUEFEV23!$A$6:$G$39,5,0) -> 0 | G30: =IF(H30="ESPECES",3000,0) -> 0 | H30: =IF($D30<>0,"BANQUE",IF($E30<>0,"ESPECES","ECHEC")) -> BANQUE | J30: 1 | K30: =IF($D30<>0,J30*40000,IF($E30<>0,J30*40000,0)) -> 40000 | L30: 1 | M30: =IF($D30<>0,L30*75000,IF($E30<>0,L30*75000,0)) -> 75000 | O30: =IF($D30<>0,N30*100000,IF($E30<>0,N30*100000,0)) -> 0 | P30: =VLOOKUP($A30,[15]TONTFEV23!$A$6:$P$35,12,0) -> 0 | Q30: =VLOOKUP($A30,[13]TONTFEV23!$A$7:$P$20,10,0) -> 0 | U30: =G30+S30+R30+P30+O30+M30+I30+K30+Q30+V30+W30 -> 115000 | AQ30: =IF(H30="ECHEC",((K30+M30+O30)*20/100),0) -> 0 | AR30: =IF(H30="ECHEC",((K30+M30+O30)*20/100),0) -> 0 | AS30: =IF(H30="ECHEC",0,(K30+I30-25000)) -> 15000 | AW30: =IF(AC30=0,AI30,(1*25000*12)+AI30-AC30) -> 0 | AX30: =IF(AD30=0,AJ30,(1*75000*12)+(AJ30)-AD30) -> 0 | AY30: =IF(AE30=0,AK30,(1*100000*12)+(AK30)-AE30) -> 0 | AZ30: =SUM(AV30:AY30)-BF30+Z30-F30+BH30+BI30+BJ30+BK30 -> 0 | BD30: =IF(AZ30=0,(AZ30-BA30-BC30),(AZ30-BA30-BB30-BC30))+F30 -> 0 | BF30: =Z30*1/100*BG30 -> 0 | BG30: 10 | BN30: DECES | BO30: MUTUELLE | BP30: 560000
A31: AS201638 | B31: =VLOOKUP(A31,[11]LISTADHERENT!A$5:H$39,3,0) -> SIMO PIERRE | C31: =D31+E31+F31-U31-BB31 -> 0 | D31: =VLOOKUP(A31,[12]HISTOBQUEFEV23!$A$6:$G$44,3,0) -> 0 | E31: =VLOOKUP(A31,[12]HISTOBQUEFEV23!$A$6:$G$39,4,0) -> 140000 | F31: =VLOOKUP(A31,[12]HISTOBQUEFEV23!$A$6:$G$39,5,0) -> 0 | G31: =IF(H31="ESPECES",3000,0)-3000 -> 0 | H31: =IF($D31<>0,"BANQUE",IF($E31<>0,"ESPECES","ECHEC")) -> ESPECES | J31: 1 | K31: =IF($D31<>0,J31*40000,IF($E31<>0,J31*40000,0)) -> 40000 | M31: =IF($D31<>0,L31*75000,IF($E31<>0,L31*75000,0)) -> 0 | N31: 1 | O31: =IF($D31<>0,N31*100000,IF($E31<>0,N31*100000,0)) -> 100000 | P31: =VLOOKUP($A31,[15]TONTFEV23!$A$6:$P$35,12,0) -> 0 | R31: =VLOOKUP($A31,[14]TONTFEV23!$A$6:$P$21,10,0) -> 0 | U31: =G31+S31+R31+P31+O31+M31+I31+K31+Q31+V31+W31 -> 140000 | AQ31: =IF(H31="ECHEC",((K31+M31+O31)*20/100),0) -> 0 | AR31: =IF(H31="ECHEC",((K31+M31+O31)*20/100),0) -> 0 | AS31: =IF(H31="ECHEC",0,(K31+I31-25000)) -> 15000 | AW31: =IF(AC31=0,AI31,(1*25000*12)+AI31-AC31) -> 0 | AX31: =IF(AD31=0,AJ31,(1*75000*12)+(AJ31)-AD31) -> 0 | AY31: =IF(AE31=0,AK31,(1*100000*12)+(AK31)-AE31) -> 0 | AZ31: =SUM(AV31:AY31)-BF31+Z31-F31+BH31+BI31+BJ31+BK31 -> 0 | BD31: =IF(AZ31=0,(AZ31-BA31-BC31),(AZ31-BA31-BB31-BC31))+F31 -> 0 | BF31: =Z31*1/100*BG31 -> 0 | BG31: 10 | BN31: TRANSPORT DELEGUE | BO31: MUTUELLE
A32: AS201641 | B32: =VLOOKUP(A32,[11]LISTADHERENT!A$5:H$39,3,0) -> TCHOUAMOU MATHIEU | C32: =D32+E32+F32-U32-BB32 -> 0 | D32: =VLOOKUP(A32,[12]HISTOBQUEFEV23!$A$6:$G$44,3,0) -> 115000 | E32: =VLOOKUP(A32,[12]HISTOBQUEFEV23!$A$6:$G$39,4,0) -> 0 | F32: =VLOOKUP(A32,[12]HISTOBQUEFEV23!$A$6:$G$39,5,0) -> 0 | G32: =IF(H32="ESPECES",3000,0) -> 0 | H32: =IF($D32<>0,"BANQUE",IF($E32<>0,"ESPECES","ECHEC")) -> BANQUE | J32: 1 | K32: =IF($D32<>0,J32*40000,IF($E32<>0,J32*40000,0)) -> 40000 | L32: 1 | M32: =IF($D32<>0,L32*75000,IF($E32<>0,L32*75000,0)) -> 75000 | O32: =IF($D32<>0,N32*100000,IF($E32<>0,N32*100000,0)) -> 0 | P32: =VLOOKUP($A32,[15]TONTFEV23!$A$6:$P$35,12,0) -> 0 | Q32: =VLOOKUP($A32,[13]TONTFEV23!$A$7:$P$20,10,0) -> 0 | U32: =G32+S32+R32+P32+O32+M32+I32+K32+Q32+V32+W32 -> 115000 | AQ32: =IF(H32="ECHEC",((K32+M32+O32)*20/100),0) -> 0 | AR32: =IF(H32="ECHEC",((K32+M32+O32)*20/100),0) -> 0 | AS32: =IF(H32="ECHEC",0,(K32+I32-25000)) -> 15000 | AW32: =IF(AC32=0,AI32,(1*25000*12)+AI32-AC32) -> 0 | AX32: =IF(AD32=0,AJ32,(1*75000*12)+(AJ32)-AD32) -> 0 | AY32: =IF(AE32=0,AK32,(1*100000*12)+(AK32)-AE32) -> 0 | AZ32: =SUM(AV32:AY32)-BF32+Z32-F32+BH32+BI32+BJ32+BK32 -> 0 | BD32: =IF(AZ32=0,(AZ32-BA32-BC32),(AZ32-BA32-BB32-BC32))+F32 -> 0 | BF32: =Z32*1/100*BG32 -> 0 | BG32: 10 | BN32: REMBOURSEMENT FONDS | BO32: FONDS DE CAISSE | BQ32: 640700
A33: AS201643 | B33: =VLOOKUP(A33,[11]LISTADHERENT!A$5:H$39,3,0) -> TCHOUTOU NANA CLAUDE | C33: =D33+E33+F33-U33-BB33 -> 0 | D33: =VLOOKUP(A33,[12]HISTOBQUEFEV23!$A$6:$G$44,3,0) -> 0 | E33: =VLOOKUP(A33,[12]HISTOBQUEFEV23!$A$6:$G$39,4,0) -> 40000 | F33: =VLOOKUP(A33,[12]HISTOBQUEFEV23!$A$6:$G$39,5,0) -> 0 | G33: =IF(H33="ESPECES",3000,0)-3000 -> 0 | H33: =IF($D33<>0,"BANQUE",IF($E33<>0,"ESPECES","ECHEC")) -> ESPECES | J33: 1 | K33: =IF($D33<>0,J33*40000,IF($E33<>0,J33*40000,0)) -> 40000 | M33: =IF($D33<>0,L33*75000,IF($E33<>0,L33*75000,0)) -> 0 | O33: =IF($D33<>0,N33*100000,IF($E33<>0,N33*100000,0)) -> 0 | P33: =VLOOKUP($A33,[15]TONTFEV23!$A$6:$P$35,12,0) -> 0 | U33: =G33+S33+R33+P33+O33+M33+I33+K33+Q33+V33+W33 -> 40000 | AQ33: =IF(H33="ECHEC",((K33+M33+O33)*20/100),0) -> 0 | AR33: =IF(H33="ECHEC",((K33+M33+O33)*20/100),0) -> 0 | AS33: =IF(H33="ECHEC",0,(K33+I33-25000)) -> 15000 | AW33: =IF(AC33=0,AI33,(1*25000*12)+AI33-AC33) -> 0 | AX33: =IF(AD33=0,AJ33,(1*75000*12)+(AJ33)-AD33) -> 0 | AY33: =IF(AE33=0,AK33,(1*100000*12)+(AK33)-AE33) -> 0 | AZ33: =SUM(AV33:AY33)-BF33+Z33-F33+BH33+BI33+BJ33+BK33 -> 0 | BD33: =IF(AZ33=0,(AZ33-BA33-BC33),(AZ33-BA33-BB33-BC33))+F33 -> 0 | BF33: =Z33*1/100*BG33 -> 0 | BG33: 10 | BN33: S/TOTAL | BP33: =SUM(BP30:BP32) -> 560000
A34: AS201658 | B34: =VLOOKUP(A34,[11]LISTADHERENT!A$5:H$39,3,0) -> YANTCHOU GERVAIS | C34: =D34+E34+F34-U34-BB34 -> 60000 | D34: =VLOOKUP(A34,[12]HISTOBQUEFEV23!$A$6:$G$44,3,0) -> 100000 | E34: =VLOOKUP(A34,[12]HISTOBQUEFEV23!$A$6:$G$39,4,0) -> 0 | F34: =VLOOKUP(A34,[12]HISTOBQUEFEV23!$A$6:$G$39,5,0) -> 0 | G34: =IF(H34="ESPECES",3000,0) -> 0 | H34: =IF($D34<>0,"BANQUE",IF($E34<>0,"ESPECES","ECHEC")) -> BANQUE | J34: 1 | K34: =IF($D34<>0,J34*40000,IF($E34<>0,J34*40000,0)) -> 40000 | M34: =IF($D34<>0,L34*75000,IF($E34<>0,L34*75000,0)) -> 0 | O34: =IF($D34<>0,N34*100000,IF($E34<>0,N34*100000,0)) -> 0 | P34: =VLOOKUP($A34,[15]TONTFEV23!$A$6:$P$35,12,0) -> 0 | U34: =G34+S34+R34+P34+O34+M34+I34+K34+Q34+V34+W34 -> 40000 | AQ34: =IF(H34="ECHEC",((K34+M34+O34)*20/100),0) -> 0 | AR34: =IF(H34="ECHEC",((K34+M34+O34)*20/100),0) -> 0 | AS34: =IF(H34="ECHEC",0,(K34+I34-25000)) -> 15000 | AT34: 60000 | AW34: =IF(AC34=0,AI34,(1*25000*12)+AI34-AC34) -> 0 | AX34: =IF(AD34=0,AJ34,(1*75000*12)+(AJ34)-AD34) -> 0 | AY34: =IF(AE34=0,AK34,(1*100000*12)+(AK34)-AE34) -> 0 | AZ34: =SUM(AV34:AY34)-BF34+Z34-F34+BH34+BI34+BJ34+BK34 -> 0 | BD34: =IF(AZ34=0,(AZ34-BA34-BC34),(AZ34-BA34-BB34-BC34))+F34 -> 0 | BF34: =Z34*1/100*BG34 -> 0 | BG34: 10
A35: AS201646 | B35: =VLOOKUP(A35,[11]LISTADHERENT!A$5:H$39,3,0) -> YEPMOU JEAN JACQUES | C35: =D35+E35+F35-U35-BB35 -> 0 | D35: =VLOOKUP(A35,[12]HISTOBQUEFEV23!$A$6:$G$44,3,0) -> 40000 | E35: =VLOOKUP(A35,[12]HISTOBQUEFEV23!$A$6:$G$39,4,0) -> 0 | F35: =VLOOKUP(A35,[12]HISTOBQUEFEV23!$A$6:$G$39,5,0) -> 0 | G35: =IF(H35="ESPECES",3000,0) -> 0 | H35: =IF($D35<>0,"BANQUE",IF($E35<>0,"ESPECES","ECHEC")) -> BANQUE | J35: 1 | K35: =IF($D35<>0,J35*40000,IF($E35<>0,J35*40000,0)) -> 40000 | M35: =IF($D35<>0,L35*75000,IF($E35<>0,L35*75000,0)) -> 0 | O35: =IF($D35<>0,N35*100000,IF($E35<>0,N35*100000,0)) -> 0 | P35: =VLOOKUP($A35,[15]TONTFEV23!$A$6:$P$35,12,0) -> 0 | U35: =G35+S35+R35+P35+O35+M35+I35+K35+Q35+V35+W35 -> 40000 | AQ35: =IF(H35="ECHEC",((K35+M35+O35)*20/100),0) -> 0 | AR35: =IF(H35="ECHEC",((K35+M35+O35)*20/100),0) -> 0 | AS35: =IF(H35="ECHEC",0,(K35+I35-25000)) -> 15000 | AW35: =IF(AC35=0,AI35,(1*25000*12)+AI35-AC35) -> 0 | AX35: =IF(AD35=0,AJ35,(1*75000*12)+(AJ35)-AD35) -> 0 | AY35: =IF(AE35=0,AK35,(1*100000*12)+(AK35)-AE35) -> 0 | AZ35: =SUM(AV35:AY35)-BF35+Z35-F35+BH35+BI35+BJ35+BK35 -> 0 | BD35: =IF(AZ35=0,(AZ35-BA35-BC35),(AZ35-BA35-BB35-BC35))+F35 -> 0 | BF35: =Z35*1/100*BG35 -> 0 | BG35: 10 | BN35: COLLATION | BO35: COLLATION
A36: AS201647 | B36: =VLOOKUP(A36,[11]LISTADHERENT!A$5:H$39,3,0) -> YOUMBI EMMANUEL | C36: =D36+E36+F36-U36-BB36 -> 0 | D36: =VLOOKUP(A36,[12]HISTOBQUEFEV23!$A$6:$G$44,3,0) -> 290000 | E36: =VLOOKUP(A36,[12]HISTOBQUEFEV23!$A$6:$G$39,4,0) -> 0 | F36: =VLOOKUP(A36,[12]HISTOBQUEFEV23!$A$6:$G$39,5,0) -> 0 | G36: =IF(H36="ESPECES",3000,0) -> 0 | H36: =IF($D36<>0,"BANQUE",IF($E36<>0,"ESPECES","ECHEC")) -> BANQUE | J36: 1 | K36: =IF($D36<>0,J36*40000,IF($E36<>0,J36*40000,0)) -> 40000 | L36: 2 | M36: =IF($D36<>0,L36*75000,IF($E36<>0,L36*75000,0)) -> 150000 | N36: 1 | O36: =IF($D36<>0,N36*100000,IF($E36<>0,N36*100000,0)) -> 100000 | P36: =VLOOKUP($A36,[15]TONTFEV23!$A$6:$P$35,12,0) -> 0 | Q36: =VLOOKUP($A36,[13]TONTFEV23!$A$7:$P$20,10,0) -> 0 | R36: =VLOOKUP($A36,[14]TONTFEV23!$A$6:$P$21,10,0) -> 0 | U36: =G36+S36+R36+P36+O36+M36+I36+K36+Q36+V36+W36 -> 290000 | AQ36: =IF(H36="ECHEC",((K36+M36+O36)*20/100),0) -> 0 | AR36: =IF(H36="ECHEC",((K36+M36+O36)*20/100),0) -> 0 | AS36: =IF(H36="ECHEC",0,(K36+I36-25000)) -> 15000 | AW36: =IF(AC36=0,AI36,(1*25000*12)+AI36-AC36) -> 0 | AX36: =IF(AD36=0,AJ36,(1*75000*12)+(AJ36)-AD36) -> 0 | AY36: =IF(AE36=0,AK36,(1*100000*12)+(AK36)-AE36) -> 0 | AZ36: =SUM(AV36:AY36)-BF36+Z36-F36+BH36+BI36+BJ36+BK36 -> 0 | BD36: =IF(AZ36=0,(AZ36-BA36-BC36),(AZ36-BA36-BB36-BC36))+F36 -> 0 | BF36: =Z36*1/100*BG36 -> 0 | BG36: 10 | BN36: BOISSON | BO36: COLLATION
B38: TOTAUX | C38: =SUM(C6:C37) -> -10000 | D38: =SUM(D6:D37) -> 4475000 | E38: =SUM(E6:E37) -> 1013000 | F38: =SUM(F6:F37) -> 2140000 | G38: =SUM(G6:G37) -> 0 | H38: =SUM(H6:H37) -> 0 | I38: =SUM(I6:I37) -> 58000 | J38: =SUM(J6:J37) -> 30 | ... S38: =SUM(S6:S37) -> 2500000 | U38: =SUM(U6:U37) -> 7428000 | V38: =SUM(V6:V37) -> 0 | W38: =SUM(W6:W37) -> 0 | X38: =SUM(X6:X37) -> 0 | Y38: =SUM(Y6:Y37) -> 0 | Z38: =SUM(Z6:Z37) -> 1000000 | AA38: =SUM(AA6:AA37) -> 0 | AC38: =SUM(AC6:AC37) -> 17500 | AD38: =SUM(AD6:AD37) -> 42000 | AE38: =SUM(AE6:AE37) -> 56000 | AF38: =SUM(AF6:AF37) -> 0 | AG38: =SUM(AG6:AG37) -> 0 | AI38: =SUM(AI6:AI37) -> 111500 | AJ38: =SUM(AJ6:AJ37) -> 0 | AK38: =SUM(AK6:AK37) -> 0 | AL38: =SUM(AL6:AL37) -> 3000 | AM38: =SUM(AM6:AM37) -> 0 | AN38: =SUM(AN6:AN37) -> 0 | AO38: =SUM(AO6:AO37) -> 0 | AP38: =SUM(AP6:AP37) -> 0 | ... BF38: =SUM(BF6:BF37) -> 30000 | BH38: =SUM(BH6:BH37) -> 68500 | BI38: =SUM(BI6:BI37) -> 0 | BJ38: =SUM(BJ6:BJ37) -> 560000 | BK38: =SUM(BK6:BK37) -> 0 | BL38: =SUM(BL6:BL37) -> 0 | BM38: =SUM(BM6:BM37) -> 200000 | BN38: S/TOTAL | BP38: =SUM(BP35:BP36) -> 0
C40: BANQUE | F40: ESPECES | BA40: =1013000-BA38 -> 0
B41: LIBELLE | C41: SORTIE | D41: ENTREE | E41: SOLDE | F41: ENTREE | G41: SORTIE | H41: SOLDE | BN41: S/TOTAL | BP41: =BP16+BP22+BP28+BP33+BP38 -> 828500
B42: REPORT
B43: TONTINE | C43: =AZ38 -> 4254500 | D43: =SUMIFS(D8:D38,H8:H38,"BANQUE") -> 4300000 | F43: =E38 -> 1013000
BO45: 640700 | BP45: FONDS
BO46: 560000 | BP46: OBSEQUES
AZ81: =SUM(AZ8:AZ80) -> 7680500

Sheet HISTOMARS23
A1: ASSOCIATION | B1: ASELBY
A2: ANNEE | B2: 2023
A3: 1 | B3: 2 | C3: 3 | D3: 4 | E3: 5 | F3: 6 | G3: 7 | H3: 8 | I3: 9 | J3: 10 | K3: 11 | L3: 12 | M3: 13 | N3: 14 | O3: 15 | P3: 16 | Q3: 17 | R3: 18 | S3: 19 | T3: 20 | U3: 21 | V3: 22 | W3: 23 | X3: 24 | Y3: 25 | Z3: 26 | AA3: 27 | AB3: 28 | AC3: 29 | AD3: 30 | AE3: 31 | AF3: 32 | AG3: 33 | AH3: 34 | AI3: 35 | AJ3: 36 | AK3: 37 | AL3: 38 | AM3: 39 | AN3: 40 | AO3: 41 | AP3: 42 | AQ3: 43 | AR3: 44 | AS3: 45 | AT3: 46 | AU3: 47 | AV3: 48 | AW3: 49 | AX3: 50 | AY3: 51 | AZ3: 52 | BA3: 53 | BB3: 54 | BC3: 55 | BD3: 56 | BE3: 57 | BF3: 58 | BG3: 59 | BH3: 60 | BI3: 61 | BJ3: 62 | BK3: 63 | BL3: 64 | BM3: 65 | BN3: 66 | BO3: 67 | BP3: 68
B4: TABLEAU DE BORD SAISIE DES DONNEES
A5: MATRICULE | B5: NOM ET PRENOM | C5: BONUS MALUS | D5: HISTORIQUE BANQUE | E5: HITORIQUE ESPECES | F5: HITORIQUE TONTINE | G5: PENALITE VERSEMENT ESPECES | H5: MODE PAIEMENT TONTINE | I5: COMPLEMENT EPARGNE | J5: NBRE DE LOT | K5: TONTINE 40 000 | L5: NBRE DE LOT | M5: TONTINE 75 000 | N5: NBRE DE LOT | O5: TONTINE 100 000 | P5: REMBOURSEMENT PETIT LOT T40 | Q5: REMBOURSEMENT PETIT LOT T75 | R5: REMBOURSEMENT PETIT LOT T100 | S5: REMBOURSEMENT PRÊT FONDS | T5: MODE PAIEMENT REMBOURSEMENT PRÊT FONDS | U5: MONTANT ENGAGEMENT | V5: SANCTION | W5: INSCRIPTION | X5: EPARGNE ASSURANCE | Y5: RECONSTITUTION FONDS | Z5: PRÊT FONDS | AA5: MODE PAIEMENT PRÊT | AB5: NUM CHEQUE | AC5: ACHAT LOT PRINCIPAL T40 | AD5: ACHAT LOT PRINCIPAL T75 | AE5: ACHAT LOT PRINCIPAL T100 | AF5: MODE PAIEMENT LOT PRINCIPAL | AG5: NUM CHEQUE | AH5: PENALITE VERSEMENT ESPECES | AI5: VENTE PETIT LOT T40 | AJ5: VENTE PETIT LOT T75 | AK5: VENTE PETIT LOT T100 | AL5: INTERET PETIT LOT T40 | AM5: INTERET PETIT LOT T75 | AN5: INTERET PETIT LOT T100 | AO5: NUM CHEQUE | AP5: MODE PAIEMENT PETEIT LOT | AQ5: PENELAITE RETARD TONTINE | AR5: PENELAITE ECHEC TONTINE | AS5: RESTE | AT5: MUTUELLE | AU5: REMBOURSEMENT TRANSPORT | AV5: RETRAIT PARTIEL FONDS | AW5: MONTANT T40 | AX5: MONTANT T75 | AY5: MONTANT T100 | AZ5: MONTANT CHEQUE | BA5: MONTANT ESPECES | BB5: CONTRIBUTION FOYER | BC5: AUTRES SOTIES | BD5: MONTANT CHEQUE EFFECTIF | BE5: NUMERO CHEQUE | BF5: INTERET PRÊT | BG5: NBRE MOIS | BH5: DEPENSE FONDS DE ROULEMENT | BI5: DEPENSE FRAIS EXCEPTIONNEL | BJ5: DEPENSE FONDS MUTUEL | BK5: DEPENSE COLLATION RECEPTION | BL5: PENALITE PRET FONDS | BM5: DEPENSE PENALITE VERSEMENT BANQUE | BN5: LIBELLE | BO5: COMPTE | BP5: MONTANT
A6: AS201648 | B6: =VLOOKUP(A6,[11]LISTADHERENT!A$5:H$39,3,0) -> ASELBY | C6: =D6+E6+F6-U6-BB6 -> 0 | D6: =VLOOKUP(A6,[12]HISTOBQUEMARS23!$A$6:$G$44,3,0) -> 175000 | E6: =VLOOKUP(A6,[12]HISTOBQUEMARS23!$A$6:$G$39,4,0) -> 0 | F6: =VLOOKUP(A6,[12]HISTOBQUEMARS23!$A$6:$G$39,5,0) -> 0 | G6: =IF(H6="ESPECES",3000,0) -> 0 | H6: =IF($D6<>0,"BANQUE",IF($E6<>0,"ESPECES","ECHEC")) -> BANQUE | K6: =IF($D6<>0,J6*40000,IF($E6<>0,J6*40000,0)) -> 0 | L6: 1 | M6: =IF($D6<>0,L6*75000,IF($E6<>0,L6*75000,0)) -> 75000 | N6: 1 | O6: =IF($D6<>0,N6*100000,IF($E6<>0,N6*100000,0)) -> 100000 | Q6: =VLOOKUP($A6,[13]TONTMARS23!$A$6:$P$20,10,0) -> 0 | R6: =VLOOKUP($A6,[14]TONTMARS23!$A$6:$P$21,10,0) -> 0 | U6: =G6+S6++R6+P6+O6+M6+I6+K6+Q6+V6+W6 -> 175000 | AQ6: =IF(H6="ECHEC",((K6+M6+O6)*20/100),0) -> 0 | AR6: =IF(H6="ECHEC",((K6+M6+O6)*20/100),0) -> 0 | AW6: =IF(AC6=0,AI6,(1*25000*12)+AI6-AC6) -> 0 | AX6: =IF(AD6=0,AJ6,(1*75000*12)+(AJ6)-AD6) -> 0 | AY6: =IF(AE6=0,AK6,(1*100000*12)+(AK6)-AE6) -> 0 | AZ6: =SUM(AV6:AY6)-BF6+Z6-F6+BH6+BI6+BJ6+BK6+BL6+BM6 -> 106000 | BD6: =IF(AZ6=0,(AZ6-BA6-BC6),(AZ6-BA6-BB6-BC6))+F6-1750000 -> -1644000 | BE6: 1858000 | BF6: =Z6*1/100*BG6 -> 0 | BG6: 9 | BH6: =BP16 -> 6000 | BI6: =BP28 -> 0 | BJ6: =BP33 -> 0 | BK6: =BP38 -> 100000 | BM6: =BP22 -> 0 | BN6: ACHAT FOURNITURE | BO6: FONDS DE ROULEMENT
A7: AS201601 | B7: =VLOOKUP(A7,[11]LISTADHERENT!A$5:H$39,3,0) -> BAKOP ACHILLE | C7: =D7+E7+F7-U7-BB7 -> 0 | D7: =VLOOKUP(A7,[12]HISTOBQUEMARS23!$A$6:$G$44,3,0) -> 40000 | E7: =VLOOKUP(A7,[12]HISTOBQUEMARS23!$A$6:$G$39,4,0) -> 0 | F7: =VLOOKUP(A7,[12]HISTOBQUEMARS23!$A$6:$G$39,5,0) -> 0 | G7: =IF(H7="ESPECES",3000,0) -> 0 | H7: =IF($D7<>0,"BANQUE",IF($E7<>0,"ESPECES","ECHEC")) -> BANQUE | J7: 1 | K7: =IF($D7<>0,J7*40000,IF($E7<>0,J7*40000,0)) -> 40000 | M7: =IF($D7<>0,L7*75000,IF($E7<>0,L7*75000,0)) -> 0 | O7: =IF($D7<>0,N7*100000,IF($E7<>0,N7*100000,0)) -> 0 | P7: =VLOOKUP($A7,[15]TONTMARS23!$A$6:$P$35,12,0) -> 0 | U7: =G7+S7++R7+P7+O7+M7+I7+K7+Q7+V7+W7 -> 40000 | AQ7: =IF(H7="ECHEC",((K7+M7+O7)*20/100),0) -> 0 | AR7: =IF(H7="ECHEC",((K7+M7+O7)*20/100),0) -> 0 | AS7: =IF(H7="ECHEC",0,(K7+I7-25000)) -> 15000 | AW7: =IF(AC7=0,AI7,(1*25000*12)+AI7-AC7) -> 0 | AX7: =IF(AD7=0,AJ7,(1*75000*12)+(AJ7)-AD7) -> 0 | AY7: =IF(AE7=0,AK7,(1*100000*12)+(AK7)-AE7) -> 0 | AZ7: =SUM(AV7:AY7)-BF7+Z7-F7+BH7+BI7+BJ7+BK7+BL7+BM7 -> 0 | BD7: =IF(AZ7=0,(AZ7-BA7-BC7),(AZ7-BA7-BB7-BC7))+F7 -> 0 | BF7: =Z7*1/100*BG7 -> 0 | BG7: 9 | BH7: =BP17 -> 0 | BI7: =BP27 -> 0 | BJ7: =BP33 -> 0 | BM7: =BP23 -> 0 | BN7: COMMUNICATION | BO7: FONDS DE ROULEMENT
A8: AS201602 | B8: =VLOOKUP(A8,[11]LISTADHERENT!A$5:H$39,3,0) -> BOUTCHOUANG WILLIAM | C8: =D8+E8+F8-U8-BB8 -> 0 | D8: =VLOOKUP(A8,[12]HISTOBQUEMARS23!$A$6:$G$44,3,0) -> 115000 | E8: =VLOOKUP(A8,[12]HISTOBQUEMARS23!$A$6:$G$39,4,0) -> 0 | F8: =VLOOKUP(A8,[12]HISTOBQUEMARS23!$A$6:$G$39,5,0) -> 0 | G8: =IF(H8="ESPECES",3000,0) -> 0 | H8: =IF($D8<>0,"BANQUE",IF($E8<>0,"ESPECES","ECHEC")) -> BANQUE | J8: 1 | K8: =IF($D8<>0,J8*40000,IF($E8<>0,J8*40000,0)) -> 40000 | L8: 1 | M8: =IF($D8<>0,L8*75000,IF($E8<>0,L8*75000,0)) -> 75000 | O8: =IF($D8<>0,N8*100000,IF($E8<>0,N8*100000,0)) -> 0 | P8: =VLOOKUP($A8,[15]TONTMARS23!$A$6:$P$35,12,0) -> 0 | Q8: =VLOOKUP($A8,[13]TONTMARS23!$A$6:$P$20,10,0) -> 0 | U8: =G8+S8++R8+P8+O8+M8+I8+K8+Q8+V8+W8 -> 115000 | AQ8: =IF(H8="ECHEC",((K8+M8+O8)*20/100),0) -> 0 | AR8: =IF(H8="ECHEC",((K8+M8+O8)*20/100),0) -> 0 | AS8: =IF(H8="ECHEC",0,(K8+I8-25000)) -> 15000 | AW8: =IF(AC8=0,AI8,(1*25000*12)+AI8-AC8) -> 0 | AX8: =IF(AD8=0,AJ8,(1*75000*12)+(AJ8)-AD8) -> 0 | AY8: =IF(AE8=0,AK8,(1*100000*12)+(AK8)-AE8) -> 0 | AZ8: =SUM(AV8:AY8)-BF8+Z8-F8+BH8+BI8+BJ8+BK8+BL8+BM8 -> 0 | BD8: =IF(AZ8=0,(AZ8-BA8-BC8),(AZ8-BA8-BB8-BC8))+F8 -> 0 | BF8: =Z8*1/100*BG8 -> 0 | BG8: 9 | BN8: COMMISSION | BO8: FONDS DE ROULEMENT
A9: AS201604 | B9: =VLOOKUP(A9,[11]LISTADHERENT!A$5:H$39,3,0) -> DJOMO JEAN PAUL | C9: =D9+E9+F9-U9-BB9 -> 0 | D9: =VLOOKUP(A9,[12]HISTOBQUEMARS23!$A$6:$G$44,3,0) -> 140000 | E9: =VLOOKUP(A9,[12]HISTOBQUEMARS23!$A$6:$G$39,4,0) -> 0 | F9: =VLOOKUP(A9,[12]HISTOBQUEMARS23!$A$6:$G$39,5,0)+690000 -> 690000 | G9: =IF(H9="ESPECES",3000,0) -> 0 | H9: =IF($D9<>0,"BANQUE",IF($E9<>0,"ESPECES","ECHEC")) -> BANQUE | J9: 1 | K9: =IF($D9<>0,J9*40000,IF($E9<>0,J9*40000,0)) -> 40000 | M9: =IF($D9<>0,L9*75000,IF($E9<>0,L9*75000,0)) -> 0 | N9: 1 | O9: =IF($D9<>0,N9*100000,IF($E9<>0,N9*100000,0)) -> 100000 | P9: =VLOOKUP($A9,[15]TONTMARS23!$A$6:$P$35,12,0) -> 0 | R9: =VLOOKUP($A9,[14]TONTMARS23!$A$6:$P$21,10,0) -> 0 | S9: 690000 | T9: BANQUE | U9: =G9+S9++R9+P9+O9+M9+I9+K9+Q9+V9+W9 -> 830000 | AE9: 10000 | AQ9: =IF(H9="ECHEC",((K9+M9+O9)*20/100),0) -> 0 | AR9: =IF(H9="ECHEC",((K9+M9+O9)*20/100),0) -> 0 | AS9: =IF(H9="ECHEC",0,(K9+I9-25000)) -> 15000 | AW9: =IF(AC9=0,AI9,(1*25000*12)+AI9-AC9) -> 0 | AX9: =IF(AD9=0,AJ9,(1*75000*12)+(AJ9)-AD9) -> 0 | AY9: =IF(AE9=0,AK9,(1*100000*12)+(AK9)-AE9) -> 1190000 | AZ9: =SUM(AV9:AY9)-BF9+Z9-F9+BH9+BI9+BJ9+BK9+BL9+BM9 -> 500000 | BD9: =IF(AZ9=0,(AZ9-BA9-BC9),(AZ9-BA9-BB9-BC9)) -> 500000 | BE9: 500000 | BF9: =Z9*1/100*BG9 -> 0 | BG9: 9 | BN9: AIDE UEEB ET CONT FEMME | BO9: FONDS DE ROULEMENT
A10: AS201654 | B10: =VLOOKUP(A10,[11]LISTADHERENT!A$5:H$39,3,0) -> DJOMOU TCHAPDA | C10: =D10+E10+F10-U10-BB10 -> 0 | D10: =VLOOKUP(A10,[12]HISTOBQUEMARS23!$A$6:$G$44,3,0) -> 82000 | E10: =VLOOKUP(A10,[12]HISTOBQUEMARS23!$A$6:$G$39,4,0) -> 0 | F10: =VLOOKUP(A10,[12]HISTOBQUEMARS23!$A$6:$G$39,5,0) -> 0 | G10: =IF(H10="ESPECES",3000,0) -> 0 | H10: =IF($D10<>0,"BANQUE",IF($E10<>0,"ESPECES","ECHEC")) -> BANQUE | I10: 1000 | J10: 1 | K10: =IF($D10<>0,J10*40000,IF($E10<>0,J10*40000,0)) -> 40000 | M10: =IF($D10<>0,L10*75000,IF($E10<>0,L10*75000,0)) -> 0 | O10: =IF($D10<>0,N10*100000,IF($E10<>0,N10*100000,0)) -> 0 | P10: =VLOOKUP($A10,[15]TONTMARS23!$A$6:$P$35,12,0) -> 41000 | U10: =G10+S10++R10+P10+O10+M10+I10+K10+Q10+V10+W10 -> 82000 | AQ10: =IF(H10="ECHEC",((K10+M10+O10)*20/100),0) -> 0 | AR10: =IF(H10="ECHEC",((K10+M10+O10)*20/100),0) -> 0 | AS10: =IF(H10="ECHEC",0,(K10+I10-25000)) -> 16000 | AW10: =IF(AC10=0,AI10,(1*25000*12)+AI10-AC10) -> 0 | AX10: =IF(AD10=0,AJ10,(1*75000*12)+(AJ10)-AD10) -> 0 | AY10: =IF(AE10=0,AK10,(1*100000*12)+(AK10)-AE10) -> 0 | AZ10: =SUM(AV10:AY10)-BF10+Z10-F10+BH10+BI10+BJ10+BK10+BL10+BM10 -> 0 | BD10: =IF(AZ10=0,(AZ10-BA10-BC10),(AZ10-BA10-BB10-BC10))+F10 -> 0 | BF10: =Z10*1/100*BG10 -> 0 | BG10: 9 | BN10: CREDIT TELEPHONE | BO10: FONDS DE ROULEMENT
A11: AS201605 | B11: =VLOOKUP(A11,[11]LISTADHERENT!A$5:H$39,3,0) -> DJOUKWE NANGUEN GUY BLAISE | C11: =D11+E11+F11-U11-BB11 -> -100000 | D11: =VLOOKUP(A11,[12]HISTOBQUEMARS23!$A$6:$G$44,3,0)+892500 -> 912500 | E11: =VLOOKUP(A11,[12]HISTOBQUEMARS23!$A$6:$G$39,4,0) -> 0 | F11: =VLOOKUP(A11,[12]HISTOBQUEMARS23!$A$6:$G$39,5,0) -> 0 | G11: =IF(H11="ESPECES",3000,0) -> 0 | H11: =IF($D11<>0,"BANQUE",IF($E11<>0,"ESPECES","ECHEC")) -> BANQUE | I11: 5000 | J11: 1 | K11: =IF($D11<>0,J11*40000,IF($E11<>0,J11*40000,0)) -> 40000 | L11: 1 | M11: =IF($D11<>0,L11*75000,IF($E11<>0,L11*75000,0)) -> 75000 | O11: =IF($D11<>0,N11*100000,IF($E11<>0,N11*100000,0)) -> 0 | P11: =VLOOKUP($A11,[15]TONTMARS23!$A$6:$P$35,12,0) -> 0 | Q11: =VLOOKUP($A11,[13]TONTMARS23!$A$6:$P$20,10,0) -> 0 | S11: 892500 | T11: BANQUE | U11: =G11+S11++R11+P11+O11+M11+I11+K11+Q11+V11+W11 -> 1012500 | AD11: 7500 | AQ11: =IF(H11="ECHEC",((K11+M11+O11)*20/100),0) -> 0 | AR11: =IF(H11="ECHEC",((K11+M11+O11)*20/100),0) -> 0 | AS11: =IF(H11="ECHEC",0,(K11+I11-25000)) -> 20000 | AW11: =IF(AC11=0,AI11,(1*25000*12)+AI11-AC11) -> 0 | AX11: =IF(AD11=0,AJ11,(1*75000*12)+(AJ11)-AD11) -> 892500 | AY11: =IF(AE11=0,AK11,(1*100000*12)+(AK11)-AE11) -> 0 | AZ11: =SUM(AV11:AY11)-BF11+Z11-F11+BH11+BI11+BJ11+BK11+BL11+BM11 -> 892500 | BA11: 50000 | BD11: =IF(AZ11=0,(AZ11-BA11-BC11),(AZ11-BA11-BB11-BC11)) -> 842500 | BF11: =Z11*1/100*BG11 -> 0 | BG11: 9 | BN11: PRODUCTION RAPPORT | BO11: FONDS DE ROULEMENT
A12: AS201608 | B12: =VLOOKUP(A12,[11]LISTADHERENT!A$5:H$39,3,0) -> DJUOMBESSY ANTOINE | C12: =D12+E12+F12-U12-BB12 -> 0 | D12: =VLOOKUP(A12,[12]HISTOBQUEMARS23!$A$6:$G$44,3,0) -> 320000 | E12: =VLOOKUP(A12,[12]HISTOBQUEMARS23!$A$6:$G$39,4,0) -> 0 | F12: =VLOOKUP(A12,[12]HISTOBQUEMARS23!$A$6:$G$39,5,0) -> 0 | G12: =IF(H12="ESPECES",3000,0) -> 0 | H12: =IF($D12<>0,"BANQUE",IF($E12<>0,"ESPECES","ECHEC")) -> BANQUE | I12: 5000 | J12: 1 | K12: =IF($D12<>0,J12*40000,IF($E12<>0,J12*40000,0)) -> 40000 | L12: 1 | M12: =IF($D12<>0,L12*75000,IF($E12<>0,L12*75000,0)) -> 75000 | N12: 2 | O12: =IF($D12<>0,N12*100000,IF($E12<>0,N12*100000,0)) -> 200000 | P12: =VLOOKUP($A12,[15]TONTMARS23!$A$6:$P$35,12,0) -> 0 | Q12: =VLOOKUP($A12,[13]TONTMARS23!$A$6:$P$20,10,0) -> 0 | R12: =VLOOKUP($A12,[14]TONTMARS23!$A$6:$P$21,10,0) -> 0 | U12: =G12+S12++R12+P12+O12+M12+I12+K12+Q12+V12+W12 -> 320000 | AE12: 10000 | AQ12: =IF(H12="ECHEC",((K12+M12+O12)*20/100),0) -> 0 | AR12: =IF(H12="ECHEC",((K12+M12+O12)*20/100),0) -> 0 | AS12: =IF(H12="ECHEC",0,(K12+I12-25000)) -> 20000 | AW12: =IF(AC12=0,AI12,(1*25000*12)+AI12-AC12) -> 0 | AX12: =IF(AD12=0,AJ12,(1*75000*12)+(AJ12)-AD12) -> 0 | AY12: =IF(AE12=0,AK12,(1*100000*12)+(AK12)-AE12) -> 1190000 | AZ12: =SUM(AV12:AY12)-BF12+Z12-F12+BH12+BI12+BJ12+BK12+BL12+BM12 -> 1190000 | BD12: =IF(AZ12=0,(AZ12-BA12-BC12),(AZ12-BA12-BB12-BC12))+F12 -> 1190000 | BE12: 1190000 | BF12: =Z12*1/100*BG12 -> 0 | BG12: 9 | BN12: ACHAT SOURIS ET PHOTOCOPIE | BO12: FONDS DE ROULEMENT
A13: AS201651 | B13: =VLOOKUP(A13,[11]LISTADHERENT!A$5:H$39,3,0) -> DOMOU FABIEN | C13: =D13+E13+F13-U13-BB13 -> 0 | D13: =VLOOKUP(A13,[12]HISTOBQUEMARS23!$A$6:$G$44,3,0) -> 40000 | E13: =VLOOKUP(A13,[12]HISTOBQUEMARS23!$A$6:$G$39,4,0) -> 0 | F13: =VLOOKUP(A13,[12]HISTOBQUEMARS23!$A$6:$G$39,5,0)+70000 -> 70000 | G13: =IF(H13="ESPECES",3000,0) -> 0 | H13: =IF($D13<>0,"BANQUE",IF($E13<>0,"ESPECES","ECHEC")) -> BANQUE | J13: 1 | K13: =IF($D13<>0,J13*40000,IF($E13<>0,J13*40000,0)) -> 40000 | M13: =IF($D13<>0,L13*75000,IF($E13<>0,L13*75000,0)) -> 0 | O13: =IF($D13<>0,N13*100000,IF($E13<>0,N13*100000,0)) -> 0 | P13: =VLOOKUP($A13,[15]TONTMARS23!$A$6:$P$35,12,0) -> 0 | U13: =G13+S13++R13+P13+O13+M13+I13+K13+Q13+V13+W13 -> 40000 | AC13: 10000 | AQ13: =IF(H13="ECHEC",((K13+M13+O13)*20/100),0) -> 0 | AR13: =IF(H13="ECHEC",((K13+M13+O13)*20/100),0) -> 0 | AS13: =IF(H13="ECHEC",0,(K13+I13-25000)) -> 15000 | AW13: =IF(AC13=0,AI13,(1*25000*12)+AI13-AC13) -> 290000 | AX13: =IF(AD13=0,AJ13,(1*75000*12)+(AJ13)-AD13) -> 0 | AY13: =IF(AE13=0,AK13,(1*100000*12)+(AK13)-AE13) -> 0 | AZ13: =SUM(AV13:AY13)-BF13+Z13-F13+BH13+BI13+BJ13+BK13+BL13+BM13 -> 220000 | BB13: 70000 | BD13: =IF(AZ13=0,(AZ13-BA13-BC13),(AZ13-BA13-BB13-BC13))+F13 -> 220000 | BE13: 220000 | BF13: =Z13*1/100*BG13 -> 0 | BG13: 9 | BN13: TAXI BANQUE | BO13: FONDS DE ROULEMENT | BP13: 6000
A14: AS201609 | B14: =VLOOKUP(A14,[11]LISTADHERENT!A$5:H$39,3,0) -> DONHOU DAVID | C14: =D14+E14+F14-U14-BB14 -> 0 | D14: =VLOOKUP(A14,[12]HISTOBQUEMARS23!$A$6:$G$44,3,0) -> 40000 | E14: =VLOOKUP(A14,[12]HISTOBQUEMARS23!$A$6:$G$39,4,0) -> 0 | F14: =VLOOKUP(A14,[12]HISTOBQUEMARS23!$A$6:$G$39,5,0) -> 0 | G14: =IF(H14="ESPECES",3000,0) -> 0 | H14: =IF($D14<>0,"BANQUE",IF($E14<>0,"ESPECES","ECHEC")) -> BANQUE | J14: 1 | K14: =IF($D14<>0,J14*40000,IF($E14<>0,J14*40000,0)) -> 40000 | M14: =IF($D14<>0,L14*75000,IF($E14<>0,L14*75000,0)) -> 0 | O14: =IF($D14<>0,N14*100000,IF($E14<>0,N14*100000,0)) -> 0 | P14: =VLOOKUP($A14,[15]TONTMARS23!$A$6:$P$35,12,0) -> 0 | U14: =G14+S14++R14+P14+O14+M14+I14+K14+Q14+V14+W14 -> 40000 | AQ14: =IF(H14="ECHEC",((K14+M14+O14)*20/100),0) -> 0 | AR14: =IF(H14="ECHEC",((K14+M14+O14)*20/100),0) -> 0 | AS14: =IF(H14="ECHEC",0,(K14+I14-25000)) -> 15000 | AW14: =IF(AC14=0,AI14,(1*25000*12)+AI14-AC14) -> 0 | AX14: =IF(AD14=0,AJ14,(1*75000*12)+(AJ14)-AD14) -> 0 | AY14: =IF(AE14=0,AK14,(1*100000*12)+(AK14)-AE14) -> 0 | AZ14: =SUM(AV14:AY14)-BF14+Z14-F14+BH14+BI14+BJ14+BK14+BL14+BM14 -> 0 | BD14: =IF(AZ14=0,(AZ14-BA14-BC14),(AZ14-BA14-BB14-BC14))+F14 -> 0 | BF14: =Z14*1/100*BG14 -> 0 | BG14: 9 | BN14: CONFECTION CACHET | BO14: FONDS DE ROULEMENT
A15: AS201611 | B15: =VLOOKUP(A15,[11]LISTADHERENT!A$5:H$39,3,0) -> HENGUE PAUL OMER | C15: =D15+E15+F15-U15-BB15 -> 0 | D15: =VLOOKUP(A15,[12]HISTOBQUEMARS23!$A$6:$G$44,3,0) -> 115000 | E15: =VLOOKUP(A15,[12]HISTOBQUEMARS23!$A$6:$G$39,4,0) -> 0 | F15: =VLOOKUP(A15,[12]HISTOBQUEMARS23!$A$6:$G$39,5,0) -> 0 | G15: =IF(H15="ESPECES",3000,0) -> 0 | H15: =IF($D15<>0,"BANQUE",IF($E15<>0,"ESPECES","ECHEC")) -> BANQUE | J15: 1 | K15: =IF($D15<>0,J15*40000,IF($E15<>0,J15*40000,0)) -> 40000 | L15: 1 | M15: =IF($D15<>0,L15*75000,IF($E15<>0,L15*75000,0)) -> 75000 | O15: =IF($D15<>0,N15*100000,IF($E15<>0,N15*100000,0)) -> 0 | P15: =VLOOKUP($A15,[15]TONTMARS23!$A$6:$P$35,12,0) -> 0 | Q15: =VLOOKUP($A15,[13]TONTMARS23!$A$6:$P$20,10,0) -> 0 | U15: =G15+S15++R15+P15+O15+M15+I15+K15+Q15+V15+W15 -> 115000 | AQ15: =IF(H15="ECHEC",((K15+M15+O15)*20/100),0) -> 0 | AR15: =IF(H15="ECHEC",((K15+M15+O15)*20/100),0) -> 0 | AS15: =IF(H15="ECHEC",0,(K15+I15-25000)) -> 15000 | AW15: =IF(AC15=0,AI15,(1*25000*12)+AI15-AC15) -> 0 | AX15: =IF(AD15=0,AJ15,(1*75000*12)+(AJ15)-AD15) -> 0 | AY15: =IF(AE15=0,AK15,(1*100000*12)+(AK15)-AE15) -> 0 | AZ15: =SUM(AV15:AY15)-BF15+Z15-F15+BH15+BI15+BJ15+BK15+BL15+BM15 -> 0 | BD15: =IF(AZ15=0,(AZ15-BA15-BC15),(AZ15-BA15-BB15-BC15))+F15 -> 0 | BF15: =Z15*1/100*BG15 -> 0 | BG15: 9
A16: AS201613 | B16: =VLOOKUP(A16,[11]LISTADHERENT!A$5:H$39,3,0) -> HOTCHO BENJAMIN | C16: =D16+E16+F16-U16-BB16 -> 0 | D16: =VLOOKUP(A16,[12]HISTOBQUEMARS23!$A$6:$G$44,3,0) -> 250000 | E16: =VLOOKUP(A16,[12]HISTOBQUEMARS23!$A$6:$G$39,4,0) -> 0 | F16: =VLOOKUP(A16,[12]HISTOBQUEMARS23!$A$6:$G$39,5,0) -> 0 | G16: =IF(H16="ESPECES",3000,0) -> 0 | H16: =IF($D16<>0,"BANQUE",IF($E16<>0,"ESPECES","ECHEC")) -> BANQUE | I16: 35000 | J16: 1 | K16: =IF($D16<>0,J16*40000,IF($E16<>0,J16*40000,0)) -> 40000 | L16: 1 | M16: =IF($D16<>0,L16*75000,IF($E16<>0,L16*75000,0)) -> 75000 | N16: 1 | O16: =IF($D16<>0,N16*100000,IF($E16<>0,N16*100000,0)) -> 100000 | P16: =VLOOKUP($A16,[15]TONTMARS23!$A$6:$P$35,12,0) -> 0 | Q16: =VLOOKUP($A16,[13]TONTMARS23!$A$6:$P$20,10,0) -> 0 | R16: =VLOOKUP($A16,[14]TONTMARS23!$A$6:$P$21,10,0) -> 0 | U16: =G16+S16++R16+P16+O16+M16+I16+K16+Q16+V16+W16 -> 250000 | AK16: 164000 | AN16: 1000 | AQ16: =IF(H16="ECHEC",((K16+M16+O16)*20/100),0) -> 0 | AR16: =IF(H16="ECHEC",((K16+M16+O16)*20/100),0) -> 0 | AS16: =IF(H16="ECHEC",0,(K16+I16-25000)) -> 50000 | AW16: =IF(AC16=0,AI16,(1*25000*12)+AI16-AC16) -> 0 | AX16: =IF(AD16=0,AJ16,(1*75000*12)+(AJ16)-AD16) -> 0 | AY16: =IF(AE16=0,AK16,(1*100000*12)+(AK16)-AE16) -> 164000 | AZ16: =SUM(AV16:AY16)-BF16+Z16-F16+BH16+BI16+BJ16+BK16+BL16+BM16 -> 164000 | BA16: 44000 | BD16: =IF(AZ16=0,(AZ16-BA16-BC16),(AZ16-BA16-BB16-BC16))+F16 -> 120000 | BE16: 220000 | BF16: =Z16*1/100*BG16 -> 0 | BG16: 9 | BN16: S/TOTAL | BP16: =SUM(BP6:BP15) -> 6000
A17: AS201617 | B17: =VLOOKUP(A17,[11]LISTADHERENT!A$5:H$39,3,0) -> KOUAMOU MOISE | C17: =D17+E17+F17-U17-BB17 -> 0 | D17: =VLOOKUP(A17,[12]HISTOBQUEMARS23!$A$6:$G$44,3,0) -> 140000 | E17: =VLOOKUP(A17,[12]HISTOBQUEMARS23!$A$6:$G$39,4,0) -> 0 | F17: =VLOOKUP(A17,[12]HISTOBQUEMARS23!$A$6:$G$39,5,0) -> 0 | G17: =IF(H17="ESPECES",3000,0) -> 0 | H17: =IF($D17<>0,"BANQUE",IF($E17<>0,"ESPECES","ECHEC")) -> BANQUE | J17: 1 | K17: =IF($D17<>0,J17*40000,IF($E17<>0,J17*40000,0)) -> 40000 | M17: =IF($D17<>0,L17*75000,IF($E17<>0,L17*75000,0)) -> 0 | N17: 1 | O17: =IF($D17<>0,N17*100000,IF($E17<>0,N17*100000,0)) -> 100000 | P17: =VLOOKUP($A17,[15]TONTMARS23!$A$6:$P$35,12,0) -> 0 | R17: =VLOOKUP($A17,[14]TONTMARS23!$A$6:$P$21,10,0) -> 0 | U17: =G17+S17++R17+P17+O17+M17+I17+K17+Q17+V17+W17 -> 140000 | AK17: 200000 | AN17: 2000 | AQ17: =IF(H17="ECHEC",((K17+M17+O17)*20/100),0) -> 0 | AR17: =IF(H17="ECHEC",((K17+M17+O17)*20/100),0) -> 0 | AS17: =IF(H17="ECHEC",0,(K17+I17-25000)) -> 15000 | AW17: =IF(AC17=0,AI17,(1*25000*12)+AI17-AC17) -> 0 | AX17: =IF(AD17=0,AJ17,(1*75000*12)+(AJ17)-AD17) -> 0 | AY17: =IF(AE17=0,AK17,(1*100000*12)+(AK17)-AE17) -> 200000 | AZ17: =SUM(AV17:AY17)-BF17+Z17-F17+BH17+BI17+BJ17+BK17+BL17+BM17 -> 200000 | BA17: 100000 | BD17: =IF(AZ17=0,(AZ17-BA17-BC17),(AZ17-BA17-BB17-BC17))+F17 -> 100000 | BE17: 100000 | BF17: =Z17*1/100*BG17 -> 0 | BG17: 9
A18: AS201619 | B18: =VLOOKUP(A18,[11]LISTADHERENT!A$5:H$39,3,0) -> KOUATCHO MESSACK | C18: =D18+E18+F18-U18-BB18 -> 1000 | D18: =VLOOKUP(A18,[12]HISTOBQUEMARS23!$A$6:$G$44,3,0) -> 215000 | E18: =VLOOKUP(A18,[12]HISTOBQUEMARS23!$A$6:$G$39,4,0) -> 0 | F18: =VLOOKUP(A18,[12]HISTOBQUEMARS23!$A$6:$G$39,5,0) -> 0 | G18: =IF(H18="ESPECES",3000,0) -> 0 | H18: =IF($D18<>0,"BANQUE",IF($E18<>0,"ESPECES","ECHEC")) -> BANQUE | I18: -1000 | J18: 1 | K18: =IF($D18<>0,J18*40000,IF($E18<>0,J18*40000,0)) -> 40000 | L18: 1 | M18: =IF($D18<>0,L18*75000,IF($E18<>0,L18*75000,0)) -> 75000 | N18: 1 | O18: =IF($D18<>0,N18*100000,IF($E18<>0,N18*100000,0)) -> 100000 | P18: =VLOOKUP($A18,[15]TONTMARS23!$A$6:$P$35,12,0) -> 0 | Q18: =VLOOKUP($A18,[13]TONTMARS23!$A$6:$P$20,10,0) -> 0 | R18: =VLOOKUP($A18,[14]TONTMARS23!$A$6:$P$21,10,0) -> 0 | U18: =G18+S18++R18+P18+O18+M18+I18+K18+Q18+V18+W18 -> 214000 | AK18: 200000 | AN18: 2000 | AQ18: =IF(H18="ECHEC",((K18+M18+O18)*20/100),0) -> 0 | AR18: =IF(H18="ECHEC",((K18+M18+O18)*20/100),0) -> 0 | AS18: =IF(H18="ECHEC",0,(K18+I18-25000)) -> 14000 | AW18: =IF(AC18=0,AI18,(1*25000*12)+AI18-AC18) -> 0 | AX18: =IF(AD18=0,AJ18,(1*75000*12)+(AJ18)-AD18) -> 0 | AY18: =IF(AE18=0,AK18,(1*100000*12)+(AK18)-AE18) -> 200000 | AZ18: =SUM(AV18:AY18)-BF18+Z18-F18+BH18+BI18+BJ18+BK18+BL18+BM18 -> 200000 | BD18: =IF(AZ18=0,(AZ18-BA18-BC18),(AZ18-BA18-BB18-BC18))+F18+100000 -> 300000 | BE18: 200000 | BF18: =Z18*1/100*BG18 -> 0 | BG18: 9 | BN18: GRATIFICATION BUREAU 2021 | BO18: PENALITE VERSEMENT ESPECES
A19: AS201620 | B19: =VLOOKUP(A19,[11]LISTADHERENT!A$5:H$39,3,0) -> LOWE JEAN | C19: =D19+E19+F19-U19-BB19 -> 0 | D19: =VLOOKUP(A19,[12]HISTOBQUEMARS23!$A$6:$G$44,3,0) -> 40000 | E19: =VLOOKUP(A19,[12]HISTOBQUEMARS23!$A$6:$G$39,4,0) -> 0 | F19: =VLOOKUP(A19,[12]HISTOBQUEMARS23!$A$6:$G$39,5,0) -> 0 | G19: =IF(H19="ESPECES",3000,0) -> 0 | H19: =IF($D19<>0,"BANQUE",IF($E19<>0,"ESPECES","ECHEC")) -> BANQUE | J19: 1 | K19: =IF($D19<>0,J19*40000,IF($E19<>0,J19*40000,0)) -> 40000 | M19: =IF($D19<>0,L19*75000,IF($E19<>0,L19*75000,0)) -> 0 | O19: =IF($D19<>0,N19*100000,IF($E19<>0,N19*100000,0)) -> 0 | P19: =VLOOKUP($A19,[15]TONTMARS23!$A$6:$P$35,12,0) -> 0 | U19: =G19+S19++R19+P19+O19+M19+I19+K19+Q19+V19+W19 -> 40000 | AQ19: =IF(H19="ECHEC",((K19+M19+O19)*20/100),0) -> 0 | AR19: =IF(H19="ECHEC",((K19+M19+O19)*20/100),0) -> 0 | AS19: =IF(H19="ECHEC",0,(K19+I19-25000)) -> 15000 | AW19: =IF(AC19=0,AI19,(1*25000*12)+AI19-AC19) -> 0 | AX19: =IF(AD19=0,AJ19,(1*75000*12)+(AJ19)-AD19) -> 0 | AY19: =IF(AE19=0,AK19,(1*100000*12)+(AK19)-AE19) -> 0 | AZ19: =SUM(AV19:AY19)-BF19+Z19-F19+BH19+BI19+BJ19+BK19+BL19+BM19 -> 0 | BD19: =IF(AZ19=0,(AZ19-BA19-BC19),(AZ19-BA19-BB19-BC19))+F19 -> 0 | BF19: =Z19*1/100*BG19 -> 0 | BG19: 9 | BN19: ACHAT LAPTOP | BO19: PENALITE VERSEMENT ESPECES
A20: AS201649 | B20: =VLOOKUP(A20,[11]LISTADHERENT!A$5:H$39,3,0) -> MBOGNING TUGMA GUY | C20: =D20+E20+F20-U20-BB20 -> 93000 | D20: =VLOOKUP(A20,[12]HISTOBQUEMARS23!$A$6:$G$44,3,0) -> 403500 | E20: =VLOOKUP(A20,[12]HISTOBQUEMARS23!$A$6:$G$39,4,0) -> 0 | F20: =VLOOKUP(A20,[12]HISTOBQUEMARS23!$A$6:$G$39,5,0) -> 0 | G20: =IF(H20="ESPECES",3000,0) -> 0 | H20: =IF($D20<>0,"BANQUE",IF($E20<>0,"ESPECES","ECHEC")) -> BANQUE | I20: -7000 | J20: 1 | K20: =IF($D20<>0,J20*40000,IF($E20<>0,J20*40000,0)) -> 40000 | L20: 1 | M20: =IF($D20<>0,L20*75000,IF($E20<>0,L20*75000,0)) -> 75000 | N20: 1 | O20: =IF($D20<>0,N20*100000,IF($E20<>0,N20*100000,0)) -> 100000 | P20: =VLOOKUP($A20,[15]TONTMARS23!$A$6:$P$35,12,0) -> 32500 | Q20: =VLOOKUP($A20,[13]TONTMARS23!$A$6:$P$20,10,0) -> 0 | R20: =VLOOKUP($A20,[14]TONTMARS23!$A$6:$P$21,10,0) -> 0 | U20: =G20+S20++R20+P20+O20+M20+I20+K20+Q20+V20+W20 -> 240500 | AC20: 11000 | AK20: 200000 | AN20: 2000 | AQ20: =IF(H20="ECHEC",((K20+M20+O20)*20/100),0) -> 0 | AR20: =IF(H20="ECHEC",((K20+M20+O20)*20/100),0) -> 0 | AS20: =IF(H20="ECHEC",0,(K20+I20-25000)) -> 8000 | AW20: =IF(AC20=0,AI20,(1*25000*12)+AI20-AC20) -> 289000 | AX20: =IF(AD20=0,AJ20,(1*75000*12)+(AJ20)-AD20) -> 0 | AY20: =IF(AE20=0,AK20,(1*100000*12)+(AK20)-AE20) -> 200000 | AZ20: =SUM(AV20:AY20)-BF20+Z20-F20+BH20+BI20+BJ20+BK20+BL20+BM20 -> 489000 | BA20: 105000 | BB20: 70000 | BD20: =IF(AZ20=0,(AZ20-BA20-BC20),(AZ20-BA20-BB20-BC20))+F20 -> 314000 | BE20: =95000+219000 -> 314000 | BF20: =Z20*1/100*BG20 -> 0 | BG20: 9
A21: AS201639 | B21: =VLOOKUP(A21,[11]LISTADHERENT!A$5:H$39,3,0) -> NANGUEN MARTIN | C21: =D21+E21+F21-U21-BB21 -> 0 | D21: =VLOOKUP(A21,[12]HISTOBQUEMARS23!$A$6:$G$44,3,0) -> 40000 | E21: =VLOOKUP(A21,[12]HISTOBQUEMARS23!$A$6:$G$39,4,0) -> 0 | F21: =VLOOKUP(A21,[12]HISTOBQUEMARS23!$A$6:$G$39,5,0) -> 0 | G21: =IF(H21="ESPECES",3000,0) -> 0 | H21: =IF($D21<>0,"BANQUE",IF($E21<>0,"ESPECES","ECHEC")) -> BANQUE | J21: 1 | K21: =IF($D21<>0,J21*40000,IF($E21<>0,J21*40000,0)) -> 40000 | M21: =IF($D21<>0,L21*75000,IF($E21<>0,L21*75000,0)) -> 0 | O21: =IF($D21<>0,N21*100000,IF($E21<>0,N21*100000,0)) -> 0 | P21: =VLOOKUP($A21,[15]TONTMARS23!$A$6:$P$35,12,0) -> 0 | U21: =G21+S21++R21+P21+O21+M21+I21+K21+Q21+V21+W21 -> 40000 | AQ21: =IF(H21="ECHEC",((K21+M21+O21)*20/100),0) -> 0 | AR21: =IF(H21="ECHEC",((K21+M21+O21)*20/100),0) -> 0 | AS21: =IF(H21="ECHEC",0,(K21+I21-25000)) -> 15000 | AW21: =IF(AC21=0,AI21,(1*25000*12)+AI21-AC21) -> 0 | AX21: =IF(AD21=0,AJ21,(1*75000*12)+(AJ21)-AD21) -> 0 | AY21: =IF(AE21=0,AK21,(1*100000*12)+(AK21)-AE21) -> 0 | AZ21: =SUM(AV21:AY21)-BF21+Z21-F21+BH21+BI21+BJ21+BK21+BL21+BM21 -> 0 | BD21: =IF(AZ21=0,(AZ21-BA21-BC21),(AZ21-BA21-BB21-BC21))+F21 -> 0 | BF21: =Z21*1/100*BG21 -> 0 | BG21: 9
A22: AS201621 | B22: =VLOOKUP(A22,[11]LISTADHERENT!A$5:H$39,3,0) -> NANKAM APPOLINAIRE | C22: =D22+E22+F22-U22-BB22 -> 0 | D22: =VLOOKUP(A22,[12]HISTOBQUEMARS23!$A$6:$G$44,3,0) -> 115000 | E22: =VLOOKUP(A22,[12]HISTOBQUEMARS23!$A$6:$G$39,4,0) -> 0 | F22: =VLOOKUP(A22,[12]HISTOBQUEMARS23!$A$6:$G$39,5,0) -> 0 | G22: =IF(H22="ESPECES",3000,0) -> 0 | H22: =IF($D22<>0,"BANQUE",IF($E22<>0,"ESPECES","ECHEC")) -> BANQUE | J22: 1 | K22: =IF($D22<>0,J22*40000,IF($E22<>0,J22*40000,0)) -> 40000 | L22: 1 | M22: =IF($D22<>0,L22*75000,IF($E22<>0,L22*75000,0)) -> 75000 | O22: =IF($D22<>0,N22*100000,IF($E22<>0,N22*100000,0)) -> 0 | P22: =VLOOKUP($A22,[15]TONTMARS23!$A$6:$P$35,12,0) -> 0 | Q22: =VLOOKUP($A22,[13]TONTMARS23!$A$6:$P$20,10,0) -> 0 | U22: =G22+S22++R22+P22+O22+M22+I22+K22+Q22+V22+W22 -> 115000 | AQ22: =IF(H22="ECHEC",((K22+M22+O22)*20/100),0) -> 0 | AR22: =IF(H22="ECHEC",((K22+M22+O22)*20/100),0) -> 0 | AS22: =IF(H22="ECHEC",0,(K22+I22-25000)) -> 15000 | AW22: =IF(AC22=0,AI22,(1*25000*12)+AI22-AC22) -> 0 | AX22: =IF(AD22=0,AJ22,(1*75000*12)+(AJ22)-AD22) -> 0 | AY22: =IF(AE22=0,AK22,(1*100000*12)+(AK22)-AE22) -> 0 | AZ22: =SUM(AV22:AY22)-BF22+Z22-F22+BH22+BI22+BJ22+BK22+BL22+BM22 -> 0 | BD22: =IF(AZ22=0,(AZ22-BA22-BC22),(AZ22-BA22-BB22-BC22))+F22 -> 0 | BF22: =Z22*1/100*BG22 -> 0 | BG22: 9 | BN22: S/TOTAL | BP22: =SUM(BP18:BP21) -> 0
A23: AS201622 | B23: =VLOOKUP(A23,[11]LISTADHERENT!A$5:H$39,3,0) -> NDJOMO ETIENNE | C23: =D23+E23+F23-U23-BB23 -> 0 | D23: =VLOOKUP(A23,[12]HISTOBQUEMARS23!$A$6:$G$44,3,0) -> 250000 | E23: =VLOOKUP(A23,[12]HISTOBQUEMARS23!$A$6:$G$39,4,0) -> 0 | F23: =VLOOKUP(A23,[12]HISTOBQUEMARS23!$A$6:$G$39,5,0) -> 0 | G23: =IF(H23="ESPECES",3000,0) -> 0 | H23: =IF($D23<>0,"BANQUE",IF($E23<>0,"ESPECES","ECHEC")) -> BANQUE | I23: 10000 | J23: 1 | K23: =IF($D23<>0,J23*40000,IF($E23<>0,J23*40000,0)) -> 40000 | M23: =IF($D23<>0,L23*75000,IF($E23<>0,L23*75000,0)) -> 0 | N23: 2 | O23: =IF($D23<>0,N23*100000,IF($E23<>0,N23*100000,0)) -> 200000 | P23: =VLOOKUP($A23,[15]TONTMARS23!$A$6:$P$35,12,0) -> 0 | R23: =VLOOKUP($A23,[14]TONTMARS23!$A$6:$P$21,10,0) -> 0 | U23: =G23+S23++R23+P23+O23+M23+I23+K23+Q23+V23+W23 -> 250000 | AK23: 200000 | AN23: 2000 | AQ23: =IF(H23="ECHEC",((K23+M23+O23)*20/100),0) -> 0 | AR23: =IF(H23="ECHEC",((K23+M23+O23)*20/100),0) -> 0 | AS23: =IF(H23="ECHEC",0,(K23+I23-25000)) -> 25000 | AW23: =IF(AC23=0,AI23,(1*25000*12)+AI23-AC23) -> 0 | AX23: =IF(AD23=0,AJ23,(1*75000*12)+(AJ23)-AD23) -> 0 | AY23: =IF(AE23=0,AK23,(1*100000*12)+(AK23)-AE23) -> 200000 | AZ23: =SUM(AV23:AY23)-BF23+Z23-F23+BH23+BI23+BJ23+BK23+BL23+BM23 -> 200000 | BA23: 100000 | BD23: =IF(AZ23=0,(AZ23-BA23-BC23),(AZ23-BA23-BB23-BC23))+F23 -> 100000 | BE23: 100000 | BF23: =Z23*1/100*BG23 -> 0 | BG23: 9
A24: AS201624 | B24: =VLOOKUP(A24,[11]LISTADHERENT!A$5:H$39,3,0) -> NGONDIEP CLAUDE | C24: =D24+E24+F24-U24-BB24 -> -3000 | D24: =VLOOKUP(A24,[12]HISTOBQUEMARS23!$A$6:$G$44,3,0) -> 0 | E24: =VLOOKUP(A24,[12]HISTOBQUEMARS23!$A$6:$G$39,4,0) -> 215000 | F24: =VLOOKUP(A24,[12]HISTOBQUEMARS23!$A$6:$G$39,5,0) -> 0 | G24: =IF(H24="ESPECES",3000,0) -> 3000 | H24: =IF($D24<>0,"BANQUE",IF($E24<>0,"ESPECES","ECHEC")) -> ESPECES | J24: 1 | K24: =IF($D24<>0,J24*40000,IF($E24<>0,J24*40000,0)) -> 40000 | L24: 1 | M24: =IF($D24<>0,L24*75000,IF($E24<>0,L24*75000,0)) -> 75000 | N24: 1 | O24: =IF($D24<>0,N24*100000,IF($E24<>0,N24*100000,0)) -> 100000 | P24: =VLOOKUP($A24,[15]TONTMARS23!$A$6:$P$35,12,0) -> 0 | Q24: =VLOOKUP($A24,[13]TONTMARS23!$A$6:$P$20,10,0) -> 0 | R24: =VLOOKUP($A24,[14]TONTMARS23!$A$6:$P$21,10,0) -> 0 | U24: =G24+S24++R24+P24+O24+M24+I24+K24+Q24+V24+W24 -> 218000 | AQ24: =IF(H24="ECHEC",((K24+M24+O24)*20/100),0) -> 0 | AR24: =IF(H24="ECHEC",((K24+M24+O24)*20/100),0) -> 0 | AS24: =IF(H24="ECHEC",0,(K24+I24-25000)) -> 15000 | AW24: =IF(AC24=0,AI24,(1*25000*12)+AI24-AC24) -> 0 | AX24: =IF(AD24=0,AJ24,(1*75000*12)+(AJ24)-AD24) -> 0 | AY24: =IF(AE24=0,AK24,(1*100000*12)+(AK24)-AE24) -> 0 | AZ24: =SUM(AV24:AY24)-BF24+Z24-F24+BH24+BI24+BJ24+BK24+BL24+BM24 -> 0 | BD24: =IF(AZ24=0,(AZ24-BA24-BC24),(AZ24-BA24-BB24-BC24))+F24 -> 0 | BF24: =Z24*1/100*BG24 -> 0 | BG24: 9 | BN24: GRATIFICATION BUREAU 2021 | BO24: FRAIS EXEPTIONNEL
A25: AS201626 | B25: =VLOOKUP(A25,[11]LISTADHERENT!A$5:H$39,3,0) -> NGUIEMEGNI MATHIEU BLAISE | C25: =D25+E25+F25-U25-BB25 -> -10000 | D25: =VLOOKUP(A25,[12]HISTOBQUEMARS23!$A$6:$G$44,3,0) -> 280000 | E25: =VLOOKUP(A25,[12]HISTOBQUEMARS23!$A$6:$G$39,4,0) -> 0 | F25: =VLOOKUP(A25,[12]HISTOBQUEMARS23!$A$6:$G$39,5,0) -> 0 | G25: =IF(H25="ESPECES",3000,0) -> 0 | H25: =IF($D25<>0,"BANQUE",IF($E25<>0,"ESPECES","ECHEC")) -> BANQUE | J25: 1 | K25: =IF($D25<>0,J25*40000,IF($E25<>0,J25*40000,0)) -> 40000 | L25: 2 | M25: =IF($D25<>0,L25*75000,IF($E25<>0,L25*75000,0)) -> 150000 | N25: 1 | O25: =IF($D25<>0,N25*100000,IF($E25<>0,N25*100000,0)) -> 100000 | P25: =VLOOKUP($A25,[15]TONTMARS23!$A$6:$P$35,12,0) -> 0 | Q25: =VLOOKUP($A25,[13]TONTMARS23!$A$6:$P$20,10,0) -> 0 | R25: =VLOOKUP($A25,[14]TONTMARS23!$A$6:$P$21,10,0) -> 0 | U25: =G25+S25++R25+P25+O25+M25+I25+K25+Q25+V25+W25 -> 290000 | AQ25: =IF(H25="ECHEC",((K25+M25+O25)*20/100),0) -> 0 | AR25: =IF(H25="ECHEC",((K25+M25+O25)*20/100),0) -> 0 | AS25: =IF(H25="ECHEC",0,(K25+I25-25000))-10000 -> 5000 | AW25: =IF(AC25=0,AI25,(1*25000*12)+AI25-AC25) -> 0 | AX25: =IF(AD25=0,AJ25,(1*75000*12)+(AJ25)-AD25) -> 0 | AY25: =IF(AE25=0,AK25,(1*100000*12)+(AK25)-AE25) -> 0 | AZ25: =SUM(AV25:AY25)-BF25+Z25-F25+BH25+BI25+BJ25+BK25+BL25+BM25 -> 0 | BD25: =IF(AZ25=0,(AZ25-BA25-BC25),(AZ25-BA25-BB25-BC25))+F25 -> 0 | BF25: =Z25*1/100*BG25 -> 0 | BG25: 9 | BN25: DEVELOPPEMENT LAGWEU | BO25: FRAIS EXEPTIONNEL
A26: AS201628 | B26: =VLOOKUP(A26,[11]LISTADHERENT!A$5:H$39,3,0) -> NKAMGANG JUSTIN DEJOLIE | C26: =D26+E26+F26-U26-BB26 -> 0 | D26: =VLOOKUP(A26,[12]HISTOBQUEMARS23!$A$6:$G$44,3,0) -> 0 | E26: =VLOOKUP(A26,[12]HISTOBQUEMARS23!$A$6:$G$39,4,0) -> 84000 | F26: =VLOOKUP(A26,[12]HISTOBQUEMARS23!$A$6:$G$39,5,0) -> 0 | G26: =IF(H26="ESPECES",3000,0) -> 3000 | H26: =IF($D26<>0,"BANQUE",IF($E26<>0,"ESPECES","ECHEC")) -> ESPECES | J26: 1 | K26: =IF($D26<>0,J26*40000,IF($E26<>0,J26*40000,0)) -> 40000 | M26: =IF($D26<>0,L26*75000,IF($E26<>0,L26*75000,0)) -> 0 | O26: =IF($D26<>0,N26*100000,IF($E26<>0,N26*100000,0)) -> 0 | P26: =VLOOKUP($A26,[15]TONTMARS23!$A$6:$P$35,12,0) -> 41000 | U26: =G26+S26++R26+P26+O26+M26+I26+K26+Q26+V26+W26 -> 84000 | AQ26: =IF(H26="ECHEC",((K26+M26+O26)*20/100),0) -> 0 | AR26: =IF(H26="ECHEC",((K26+M26+O26)*20/100),0) -> 0 | AS26: =IF(H26="ECHEC",0,(K26+I26-25000)) -> 15000 | AW26: =IF(AC26=0,AI26,(1*25000*12)+AI26-AC26) -> 0 | AX26: =IF(AD26=0,AJ26,(1*75000*12)+(AJ26)-AD26) -> 0 | AY26: =IF(AE26=0,AK26,(1*100000*12)+(AK26)-AE26) -> 0 | AZ26: =SUM(AV26:AY26)-BF26+Z26-F26+BH26+BI26+BJ26+BK26+BL26+BM26 -> 0 | BD26: =IF(AZ26=0,(AZ26-BA26-BC26),(AZ26-BA26-BB26-BC26))+F26 -> 0 | BF26: =Z26*1/100*BG26 -> 0 | BG26: 9 | BN26: DEUIL TCHEMNOU EMMANUEL | BO26: FRAIS EXEPTIONNEL
A27: AS201656 | B27: =VLOOKUP(A27,[11]LISTADHERENT!A$5:H$39,3,0) -> NOUBE ETIENNE | C27: =D27+E27+F27-U27-BB27 -> 0 | D27: =VLOOKUP(A27,[12]HISTOBQUEMARS23!$A$6:$G$44,3,0) -> 50000 | E27: =VLOOKUP(A27,[12]HISTOBQUEMARS23!$A$6:$G$39,4,0) -> 0 | F27: =VLOOKUP(A27,[12]HISTOBQUEMARS23!$A$6:$G$39,5,0) -> 0 | G27: =IF(H27="ESPECES",3000,0) -> 0 | H27: =IF($D27<>0,"BANQUE",IF($E27<>0,"ESPECES","ECHEC")) -> BANQUE | I27: 10000 | J27: 1 | K27: =IF($D27<>0,J27*40000,IF($E27<>0,J27*40000,0)) -> 40000 | M27: =IF($D27<>0,L27*75000,IF($E27<>0,L27*75000,0)) -> 0 | O27: =IF($D27<>0,N27*100000,IF($E27<>0,N27*100000,0)) -> 0 | P27: =VLOOKUP($A27,[15]TONTMARS23!$A$6:$P$35,12,0) -> 0 | U27: =G27+S27++R27+P27+O27+M27+I27+K27+Q27+V27+W27 -> 50000 | AQ27: =IF(H27="ECHEC",((K27+M27+O27)*20/100),0) -> 0 | AR27: =IF(H27="ECHEC",((K27+M27+O27)*20/100),0) -> 0 | AS27: =IF(H27="ECHEC",0,(K27+I27-25000)) -> 25000 | AW27: =IF(AC27=0,AI27,(1*25000*12)+AI27-AC27) -> 0 | AX27: =IF(AD27=0,AJ27,(1*75000*12)+(AJ27)-AD27) -> 0 | AY27: =IF(AE27=0,AK27,(1*100000*12)+(AK27)-AE27) -> 0 | AZ27: =SUM(AV27:AY27)-BF27+Z27-F27+BH27+BI27+BJ27+BK27+BL27+BM27 -> 0 | BD27: =IF(AZ27=0,(AZ27-BA27-BC27),(AZ27-BA27-BB27-BC27))+F27 -> 0 | BF27: =Z27*1/100*BG27 -> 0 | BG27: 9 | BN27: RETRAIT COMPTE FOYER | BQ27: 1750000
A28: AS201633 | B28: =VLOOKUP(A28,[11]LISTADHERENT!A$5:H$39,3,0) -> PATEGO NJOSSU GUSTAVE | C28: =D28+E28+F28-U28-BB28 -> 0 | D28: =VLOOKUP(A28,[12]HISTOBQUEMARS23!$A$6:$G$44,3,0) -> 115000 | E28: =VLOOKUP(A28,[12]HISTOBQUEMARS23!$A$6:$G$39,4,0) -> 0 | F28: =VLOOKUP(A28,[12]HISTOBQUEMARS23!$A$6:$G$39,5,0) -> 0 | G28: =IF(H28="ESPECES",3000,0) -> 0 | H28: =IF($D28<>0,"BANQUE",IF($E28<>0,"ESPECES","ECHEC")) -> BANQUE | J28: 1 | K28: =IF($D28<>0,J28*40000,IF($E28<>0,J28*40000,0)) -> 40000 | L28: 1 | M28: =IF($D28<>0,L28*75000,IF($E28<>0,L28*75000,0)) -> 75000 | O28: =IF($D28<>0,N28*100000,IF($E28<>0,N28*100000,0)) -> 0 | P28: =VLOOKUP($A28,[15]TONTMARS23!$A$6:$P$35,12,0) -> 0 | Q28: =VLOOKUP($A28,[13]TONTMARS23!$A$6:$P$20,10,0) -> 0 | U28: =G28+S28++R28+P28+O28+M28+I28+K28+Q28+V28+W28 -> 115000 | AQ28: =IF(H28="ECHEC",((K28+M28+O28)*20/100),0) -> 0 | AR28: =IF(H28="ECHEC",((K28+M28+O28)*20/100),0) -> 0 | AS28: =IF(H28="ECHEC",0,(K28+I28-25000)) -> 15000 | AW28: =IF(AC28=0,AI28,(1*25000*12)+AI28-AC28) -> 0 | AX28: =IF(AD28=0,AJ28,(1*75000*12)+(AJ28)-AD28) -> 0 | AY28: =IF(AE28=0,AK28,(1*100000*12)+(AK28)-AE28) -> 0 | AZ28: =SUM(AV28:AY28)-BF28+Z28-F28+BH28+BI28+BJ28+BK28+BL28+BM28 -> 0 | BD28: =IF(AZ28=0,(AZ28-BA28-BC28),(AZ28-BA28-BB28-BC28))+F28 -> 0 | BF28: =Z28*1/100*BG28 -> 0 | BG28: 9 | BN28: S/TOTAL | BP28: =SUM(BP24:BP27) -> 0
A29: AS201657 | B29: =VLOOKUP(A29,[11]LISTADHERENT!A$5:H$39,3,0) -> SEUMO POLYCARPE | C29: =D29+E29+F29-U29-BB29 -> 0 | D29: =VLOOKUP(A29,[12]HISTOBQUEMARS23!$A$6:$G$44,3,0) -> 40000 | E29: =VLOOKUP(A29,[12]HISTOBQUEMARS23!$A$6:$G$39,4,0) -> 0 | F29: =VLOOKUP(A29,[12]HISTOBQUEMARS23!$A$6:$G$39,5,0) -> 0 | G29: =IF(H29="ESPECES",3000,0) -> 0 | H29: =IF($D29<>0,"BANQUE",IF($E29<>0,"ESPECES","ECHEC")) -> BANQUE | J29: 1 | K29: =IF($D29<>0,J29*40000,IF($E29<>0,J29*40000,0)) -> 40000 | M29: =IF($D29<>0,L29*75000,IF($E29<>0,L29*75000,0)) -> 0 | O29: =IF($D29<>0,N29*100000,IF($E29<>0,N29*100000,0)) -> 0 | P29: =VLOOKUP($A29,[15]TONTMARS23!$A$6:$P$35,12,0) -> 0 | U29: =G29+S29++R29+P29+O29+M29+I29+K29+Q29+V29+W29 -> 40000 | AQ29: =IF(H29="ECHEC",((K29+M29+O29)*20/100),0) -> 0 | AR29: =IF(H29="ECHEC",((K29+M29+O29)*20/100),0) -> 0 | AS29: =IF(H29="ECHEC",0,(K29+I29-25000)) -> 15000 | AW29: =IF(AC29=0,AI29,(1*25000*12)+AI29-AC29) -> 0 | AX29: =IF(AD29=0,AJ29,(1*75000*12)+(AJ29)-AD29) -> 0 | AY29: =IF(AE29=0,AK29,(1*100000*12)+(AK29)-AE29) -> 0 | AZ29: =SUM(AV29:AY29)-BF29+Z29-F29+BH29+BI29+BJ29+BK29+BL29+BM29 -> 0 | BD29: =IF(AZ29=0,(AZ29-BA29-BC29),(AZ29-BA29-BB29-BC29))+F29 -> 0 | BF29: =Z29*1/100*BG29 -> 0 | BG29: 9
A30: AS201653 | B30: =VLOOKUP(A30,[11]LISTADHERENT!A$5:H$39,3,0) -> SIME BRICE | C30: =D30+E30+F30-U30-BB30 -> 0 | D30: =VLOOKUP(A30,[12]HISTOBQUEMARS23!$A$6:$G$44,3,0) -> 115000 | E30: =VLOOKUP(A30,[12]HISTOBQUEMARS23!$A$6:$G$39,4,0) -> 0 | F30: =VLOOKUP(A30,[12]HISTOBQUEMARS23!$A$6:$G$39,5,0) -> 0 | G30: =IF(H30="ESPECES",3000,0) -> 0 | H30: =IF($D30<>0,"BANQUE",IF($E30<>0,"ESPECES","ECHEC")) -> BANQUE | J30: 1 | K30: =IF($D30<>0,J30*40000,IF($E30<>0,J30*40000,0)) -> 40000 | L30: 1 | M30: =IF($D30<>0,L30*75000,IF($E30<>0,L30*75000,0)) -> 75000 | O30: =IF($D30<>0,N30*100000,IF($E30<>0,N30*100000,0)) -> 0 | P30: =VLOOKUP($A30,[15]TONTMARS23!$A$6:$P$35,12,0) -> 0 | Q30: =VLOOKUP($A30,[13]TONTMARS23!$A$6:$P$20,10,0) -> 0 | U30: =G30+S30++R30+P30+O30+M30+I30+K30+Q30+V30+W30 -> 115000 | AQ30: =IF(H30="ECHEC",((K30+M30+O30)*20/100),0) -> 0 | AR30: =IF(H30="ECHEC",((K30+M30+O30)*20/100),0) -> 0 | AS30: =IF(H30="ECHEC",0,(K30+I30-25000)) -> 15000 | AW30: =IF(AC30=0,AI30,(1*25000*12)+AI30-AC30) -> 0 | AX30: =IF(AD30=0,AJ30,(1*75000*12)+(AJ30)-AD30) -> 0 | AY30: =IF(AE30=0,AK30,(1*100000*12)+(AK30)-AE30) -> 0 | AZ30: =SUM(AV30:AY30)-BF30+Z30-F30+BH30+BI30+BJ30+BK30+BL30+BM30 -> 0 | BD30: =IF(AZ30=0,(AZ30-BA30-BC30),(AZ30-BA30-BB30-BC30))+F30 -> 0 | BF30: =Z30*1/100*BG30 -> 0 | BG30: 9 | BN30: DECES | BO30: MUTUELLE
A31: AS201638 | B31: =VLOOKUP(A31,[11]LISTADHERENT!A$5:H$39,3,0) -> SIMO PIERRE | C31: =D31+E31+F31-U31-BB31 -> -70000 | D31: =VLOOKUP(A31,[12]HISTOBQUEMARS23!$A$6:$G$44,3,0) -> 140000 | E31: =VLOOKUP(A31,[12]HISTOBQUEMARS23!$A$6:$G$39,4,0) -> 0 | F31: =VLOOKUP(A31,[12]HISTOBQUEMARS23!$A$6:$G$39,5,0) -> 0 | G31: =IF(H31="ESPECES",3000,0) -> 0 | H31: =IF($D31<>0,"BANQUE",IF($E31<>0,"ESPECES","ECHEC")) -> BANQUE | J31: 1 | K31: =IF($D31<>0,J31*40000,IF($E31<>0,J31*40000,0)) -> 40000 | M31: =IF($D31<>0,L31*75000,IF($E31<>0,L31*75000,0)) -> 0 | N31: 1 | O31: =IF($D31<>0,N31*100000,IF($E31<>0,N31*100000,0)) -> 100000 | P31: =VLOOKUP($A31,[15]TONTMARS23!$A$6:$P$35,12,0) -> 0 | R31: =VLOOKUP($A31,[14]TONTMARS23!$A$6:$P$21,10,0) -> 0 | U31: =G31+S31++R31+P31+O31+M31+I31+K31+Q31+V31+W31 -> 140000 | AC31: 11000 | AQ31: =IF(H31="ECHEC",((K31+M31+O31)*20/100),0) -> 0 | AR31: =IF(H31="ECHEC",((K31+M31+O31)*20/100),0) -> 0 | AS31: =IF(H31="ECHEC",0,(K31+I31-25000)) -> 15000 | AW31: =IF(AC31=0,AI31,(1*25000*12)+AI31-AC31) -> 289000 | AX31: =IF(AD31=0,AJ31,(1*75000*12)+(AJ31)-AD31) -> 0 | AY31: =IF(AE31=0,AK31,(1*100000*12)+(AK31)-AE31) -> 0 | AZ31: =SUM(AV31:AY31)-BF31+Z31-F31+BH31+BI31+BJ31+BK31+BL31+BM31 -> 289000 | BB31: 70000 | BD31: =IF(AZ31=0,(AZ31-BA31-BC31),(AZ31-BA31-BB31-BC31))+F31 -> 219000 | BE31: 219000 | BF31: =Z31*1/100*BG31 -> 0 | BG31: 9 | BN31: TRANSPORT DELEGUE | BO31: MUTUELLE
A32: AS201641 | B32: =VLOOKUP(A32,[11]LISTADHERENT!A$5:H$39,3,0) -> TCHOUAMOU MATHIEU | C32: =D32+E32+F32-U32-BB32 -> 0 | D32: =VLOOKUP(A32,[12]HISTOBQUEMARS23!$A$6:$G$44,3,0) -> 115000 | E32: =VLOOKUP(A32,[12]HISTOBQUEMARS23!$A$6:$G$39,4,0) -> 0 | F32: =VLOOKUP(A32,[12]HISTOBQUEMARS23!$A$6:$G$39,5,0) -> 0 | G32: =IF(H32="ESPECES",3000,0) -> 0 | H32: =IF($D32<>0,"BANQUE",IF($E32<>0,"ESPECES","ECHEC")) -> BANQUE | J32: 1 | K32: =IF($D32<>0,J32*40000,IF($E32<>0,J32*40000,0)) -> 40000 | L32: 1 | M32: =IF($D32<>0,L32*75000,IF($E32<>0,L32*75000,0)) -> 75000 | O32: =IF($D32<>0,N32*100000,IF($E32<>0,N32*100000,0)) -> 0 | P32: =VLOOKUP($A32,[15]TONTMARS23!$A$6:$P$35,12,0) -> 0 | Q32: =VLOOKUP($A32,[13]TONTMARS23!$A$6:$P$20,10,0) -> 0 | U32: =G32+S32++R32+P32+O32+M32+I32+K32+Q32+V32+W32 -> 115000 | Z32: 200000 | AA32: BANQUE | AD32: 7500 | AQ32: =IF(H32="ECHEC",((K32+M32+O32)*20/100),0) -> 0 | AR32: =IF(H32="ECHEC",((K32+M32+O32)*20/100),0) -> 0 | AS32: =IF(H32="ECHEC",0,(K32+I32-25000)) -> 15000 | AW32: =IF(AC32=0,AI32,(1*25000*12)+AI32-AC32) -> 0 | AX32: =IF(AD32=0,AJ32,(1*75000*12)+(AJ32)-AD32)-892500 -> 0 | AY32: =IF(AE32=0,AK32,(1*100000*12)+(AK32)-AE32) -> 0 | AZ32: =SUM(AV32:AY32)-BF32+Z32-F32+BH32+BI32+BJ32+BK32+BL32+BM32 -> 194000 | BD32: =IF(AZ32=0,(AZ32-BA32-BC32),(AZ32-BA32-BB32-BC32))+F32 -> 194000 | BE32: 86500 | BF32: =Z32*1/100*BG32 -> 6000 | BG32: 3
A33: AS201643 | B33: =VLOOKUP(A33,[11]LISTADHERENT!A$5:H$39,3,0) -> TCHOUTOU NANA CLAUDE | C33: =D33+E33+F33-U33-BB33 -> 0 | D33: =VLOOKUP(A33,[12]HISTOBQUEMARS23!$A$6:$G$44,3,0) -> 40000 | E33: =VLOOKUP(A33,[12]HISTOBQUEMARS23!$A$6:$G$39,4,0) -> 0 | F33: =VLOOKUP(A33,[12]HISTOBQUEMARS23!$A$6:$G$39,5,0) -> 0 | G33: =IF(H33="ESPECES",3000,0) -> 0 | H33: =IF($D33<>0,"BANQUE",IF($E33<>0,"ESPECES","ECHEC")) -> BANQUE | J33: 1 | K33: =IF($D33<>0,J33*40000,IF($E33<>0,J33*40000,0)) -> 40000 | M33: =IF($D33<>0,L33*75000,IF($E33<>0,L33*75000,0)) -> 0 | O33: =IF($D33<>0,N33*100000,IF($E33<>0,N33*100000,0)) -> 0 | P33: =VLOOKUP($A33,[15]TONTMARS23!$A$6:$P$35,12,0) -> 0 | U33: =G33+S33++R33+P33+O33+M33+I33+K33+Q33+V33+W33 -> 40000 | AQ33: =IF(H33="ECHEC",((K33+M33+O33)*20/100),0) -> 0 | AR33: =IF(H33="ECHEC",((K33+M33+O33)*20/100),0) -> 0 | AS33: =IF(H33="ECHEC",0,(K33+I33-25000)) -> 15000 | AW33: =IF(AC33=0,AI33,(1*25000*12)+AI33-AC33) -> 0 | AX33: =IF(AD33=0,AJ33,(1*75000*12)+(AJ33)-AD33) -> 0 | AY33: =IF(AE33=0,AK33,(1*100000*12)+(AK33)-AE33) -> 0 | AZ33: =SUM(AV33:AY33)-BF33+Z33-F33+BH33+BI33+BJ33+BK33+BL33+BM33 -> 0 | BD33: =IF(AZ33=0,(AZ33-BA33-BC33),(AZ33-BA33-BB33-BC33))+F33 -> 0 | BF33: =Z33*1/100*BG33 -> 0 | BG33: 9 | BN33: S/TOTAL | BP33: =SUM(BP30:BP32) -> 0
A34: AS201658 | B34: =VLOOKUP(A34,[11]LISTADHERENT!A$5:H$39,3,0) -> YANTCHOU GERVAIS | C34: =D34+E34+F34-U34-BB34 -> 25000 | D34: =VLOOKUP(A34,[12]HISTOBQUEMARS23!$A$6:$G$44,3,0) -> 100000 | E34: =VLOOKUP(A34,[12]HISTOBQUEMARS23!$A$6:$G$39,4,0) -> 0 | F34: =VLOOKUP(A34,[12]HISTOBQUEMARS23!$A$6:$G$39,5,0) -> 0 | G34: =IF(H34="ESPECES",3000,0) -> 0 | H34: =IF($D34<>0,"BANQUE",IF($E34<>0,"ESPECES","ECHEC")) -> BANQUE | I34: 35000 | J34: 1 | K34: =IF($D34<>0,J34*40000,IF($E34<>0,J34*40000,0)) -> 40000 | M34: =IF($D34<>0,L34*75000,IF($E34<>0,L34*75000,0)) -> 0 | O34: =IF($D34<>0,N34*100000,IF($E34<>0,N34*100000,0)) -> 0 | P34: =VLOOKUP($A34,[15]TONTMARS23!$A$6:$P$35,12,0) -> 0 | U34: =G34+S34++R34+P34+O34+M34+I34+K34+Q34+V34+W34 -> 75000 | AQ34: =IF(H34="ECHEC",((K34+M34+O34)*20/100),0) -> 0 | AR34: =IF(H34="ECHEC",((K34+M34+O34)*20/100),0) -> 0 | AS34: =IF(H34="ECHEC",0,(K34+I34-25000)) -> 50000 | AT34: 25000 | AW34: =IF(AC34=0,AI34,(1*25000*12)+AI34-AC34) -> 0 | AX34: =IF(AD34=0,AJ34,(1*75000*12)+(AJ34)-AD34) -> 0 | AY34: =IF(AE34=0,AK34,(1*100000*12)+(AK34)-AE34) -> 0 | AZ34: =SUM(AV34:AY34)-BF34+Z34-F34+BH34+BI34+BJ34+BK34+BL34+BM34 -> 0 | BD34: =IF(AZ34=0,(AZ34-BA34-BC34),(AZ34-BA34-BB34-BC34))+F34 -> 0 | BF34: =Z34*1/100*BG34 -> 0 | BG34: 9
A35: AS201646 | B35: =VLOOKUP(A35,[11]LISTADHERENT!A$5:H$39,3,0) -> YEPMOU JEAN JACQUES | C35: =D35+E35+F35-U35-BB35 -> -6000 | D35: =VLOOKUP(A35,[12]HISTOBQUEMARS23!$A$6:$G$44,3,0) -> 34000 | E35: =VLOOKUP(A35,[12]HISTOBQUEMARS23!$A$6:$G$39,4,0) -> 0 | F35: =VLOOKUP(A35,[12]HISTOBQUEMARS23!$A$6:$G$39,5,0) -> 0 | G35: =IF(H35="ESPECES",3000,0) -> 0 | H35: =IF($D35<>0,"BANQUE",IF($E35<>0,"ESPECES","ECHEC")) -> BANQUE | J35: 1 | K35: =IF($D35<>0,J35*40000,IF($E35<>0,J35*40000,0)) -> 40000 | M35: =IF($D35<>0,L35*75000,IF($E35<>0,L35*75000,0)) -> 0 | O35: =IF($D35<>0,N35*100000,IF($E35<>0,N35*100000,0)) -> 0 | P35: =VLOOKUP($A35,[15]TONTMARS23!$A$6:$P$35,12,0) -> 0 | U35: =G35+S35++R35+P35+O35+M35+I35+K35+Q35+V35+W35 -> 40000 | AQ35: =IF(H35="ECHEC",((K35+M35+O35)*20/100),0) -> 0 | AR35: =IF(H35="ECHEC",((K35+M35+O35)*20/100),0) -> 0 | AS35: =IF(H35="ECHEC",0,(K35+I35-25000))-6000 -> 9000 | AW35: =IF(AC35=0,AI35,(1*25000*12)+AI35-AC35) -> 0 | AX35: =IF(AD35=0,AJ35,(1*75000*12)+(AJ35)-AD35) -> 0 | AY35: =IF(AE35=0,AK35,(1*100000*12)+(AK35)-AE35) -> 0 | AZ35: =SUM(AV35:AY35)-BF35+Z35-F35+BH35+BI35+BJ35+BK35+BL35+BM35 -> 0 | BD35: =IF(AZ35=0,(AZ35-BA35-BC35),(AZ35-BA35-BB35-BC35))+F35 -> 0 | BF35: =Z35*1/100*BG35 -> 0 | BG35: 9 | BN35: COLLATION | BO35: COLLATION | BP35: 100000
A36: AS201647 | B36: =VLOOKUP(A36,[11]LISTADHERENT!A$5:H$39,3,0) -> YOUMBI EMMANUEL | C36: =D36+E36+F36-U36-BB36 -> 0 | D36: =VLOOKUP(A36,[12]HISTOBQUEMARS23!$A$6:$G$44,3,0) -> 290000 | E36: =VLOOKUP(A36,[12]HISTOBQUEMARS23!$A$6:$G$39,4,0) -> 0 | F36: =VLOOKUP(A36,[12]HISTOBQUEMARS23!$A$6:$G$39,5,0) -> 0 | G36: =IF(H36="ESPECES",3000,0) -> 0 | H36: =IF($D36<>0,"BANQUE",IF($E36<>0,"ESPECES","ECHEC")) -> BANQUE | J36: 1 | K36: =IF($D36<>0,J36*40000,IF($E36<>0,J36*40000,0)) -> 40000 | L36: 2 | M36: =IF($D36<>0,L36*75000,IF($E36<>0,L36*75000,0)) -> 150000 | N36: 1 | O36: =IF($D36<>0,N36*100000,IF($E36<>0,N36*100000,0)) -> 100000 | P36: =VLOOKUP($A36,[15]TONTMARS23!$A$6:$P$35,12,0) -> 0 | Q36: =VLOOKUP($A36,[13]TONTMARS23!$A$6:$P$20,10,0) -> 0 | R36: =VLOOKUP($A36,[14]TONTMARS23!$A$6:$P$21,10,0) -> 0 | U36: =G36+S36++R36+P36+O36+M36+I36+K36+Q36+V36+W36 -> 290000 | AQ36: =IF(H36="ECHEC",((K36+M36+O36)*20/100),0) -> 0 | AR36: =IF(H36="ECHEC",((K36+M36+O36)*20/100),0) -> 0 | AS36: =IF(H36="ECHEC",0,(K36+I36-25000)) -> 15000 | AW36: =IF(AC36=0,AI36,(1*25000*12)+AI36-AC36) -> 0 | AX36: =IF(AD36=0,AJ36,(1*75000*12)+(AJ36)-AD36) -> 0 | AY36: =IF(AE36=0,AK36,(1*100000*12)+(AK36)-AE36) -> 0 | AZ36: =SUM(AV36:AY36)-BF36+Z36-F36+BH36+BI36+BJ36+BK36+BL36+BM36 -> 0 | BD36: =IF(AZ36=0,(AZ36-BA36-BC36),(AZ36-BA36-BB36-BC36))+F36 -> 0 | BF36: =Z36*1/100*BG36 -> 0 | BG36: 9 | BN36: BOISSON | BO36: COLLATION
B38: TOTAUX | C38: =SUM(C6:C37) -> -70000 | D38: =SUM(D6:D37) -> 4752000 | E38: =SUM(E6:E37) -> 299000 | F38: =SUM(F6:F37) -> 760000 | G38: =SUM(G6:G37) -> 6000 | H38: =SUM(H6:H37) -> 0 | I38: =SUM(I6:I37) -> 93000 | J38: =SUM(J6:J37) -> 30 | ... S38: =SUM(S6:S37) -> 1582500 | U38: =SUM(U6:U37) -> 5671000 | V38: =SUM(V6:V37) -> 0 | W38: =SUM(W6:W37) -> 0 | X38: =SUM(X6:X37) -> 0 | Y38: =SUM(Y6:Y37) -> 0 | Z38: =SUM(Z6:Z37) -> 200000 | AA38: =SUM(AA6:AA37) -> 0 | AC38: =SUM(AC6:AC37) -> 32000 | AD38: =SUM(AD6:AD37) -> 15000 | AE38: =SUM(AE6:AE37) -> 20000 | AF38: =SUM(AF6:AF37) -> 0 | AG38: =SUM(AG6:AG37) -> 0 | AI38: =SUM(AI6:AI37) -> 0 | AJ38: =SUM(AJ6:AJ37) -> 0 | AK38: =SUM(AK6:AK37) -> 964000 | AL38: =SUM(AL6:AL37) -> 0 | AM38: =SUM(AM6:AM37) -> 0 | AN38: =SUM(AN6:AN37) -> 9000 | AO38: =SUM(AO6:AO37) -> 0 | AP38: =SUM(AP6:AP37) -> 0 | ... BF38: =SUM(BF6:BF37) -> 6000 | BH38: =SUM(BH6:BH37) -> 6000 | BI38: =SUM(BI6:BI37) -> 0 | BJ38: =SUM(BJ6:BJ37) -> 0 | BK38: =SUM(BK6:BK37) -> 100000 | BL38: =SUM(BL6:BL37) -> 0 | BM38: =SUM(BM6:BM37) -> 0 | BN38: S/TOTAL | BP38: =SUM(BP35:BP36) -> 100000
BD39: RETRAIT CPTE FOYER | BE39: 1750000
C40: BANQUE | F40: ESPECES | AZ40: TOTAL CENTRALISATION | BA40: 299000 | BD40: TOTAL BORDEREAU | BE40: 5005000
B41: LIBELLE | C41: SORTIE | D41: ENTREE | E41: SOLDE | F41: ENTREE | G41: SORTIE | H41: SOLDE | BN41: S/TOTAL | BP41: =BP16+BP22+BP28+BP33+BP38 -> 106000
B42: REPORT
B43: TONTINE | C43: =AZ38 -> 4644500 | D43: =SUMIFS(D8:D38,H8:H38,"BANQUE") -> 4537000 | F43: =E38 -> 299000
AZ81: =SUM(AZ8:AZ80) -> 9183000

Sheet HISTOAVRIL23
A1: ASSOCIATION | B1: ASELBY
A2: ANNEE | B2: 2023
A3: 1 | B3: 2 | C3: 3 | D3: 4 | E3: 5 | F3: 6 | G3: 7 | H3: 8 | I3: 9 | J3: 10 | K3: 11 | L3: 12 | M3: 13 | N3: 14 | O3: 15 | P3: 16 | Q3: 17 | R3: 18 | S3: 19 | T3: 20 | U3: 21 | V3: 22 | W3: 23 | X3: 24 | Y3: 25 | Z3: 26 | AA3: 27 | AB3: 28 | AC3: 29 | AD3: 30 | AE3: 31 | AF3: 32 | AG3: 33 | AH3: 34 | AI3: 35 | AJ3: 36 | AK3: 37 | AL3: 38 | AM3: 39 | AN3: 40 | AO3: 41 | AP3: 42 | AQ3: 43 | AR3: 44 | AS3: 45 | AT3: 46 | AU3: 47 | AV3: 48 | AW3: 49 | AX3: 50 | AY3: 51 | AZ3: 52 | BA3: 53 | BB3: 54 | BC3: 55 | BD3: 56 | BE3: 57 | BF3: 58 | BG3: 59 | BH3: 60 | BI3: 61 | BJ3: 62 | BK3: 63 | BL3: 64 | BM3: 65 | BN3: 66 | BO3: 67 | BP3: 68
B4: TABLEAU DE BORD SAISIE DES DONNEES
A5: MATRICULE | B5: NOM ET PRENOM | C5: BONUS MALUS | D5: HISTORIQUE BANQUE | E5: HITORIQUE ESPECES | F5: HITORIQUE TONTINE | G5: PENALITE VERSEMENT ESPECES | H5: MODE PAIEMENT TONTINE | I5: COMPLEMENT EPARGNE | J5: NBRE DE LOT | K5: TONTINE 40 000 | L5: NBRE DE LOT | M5: TONTINE 75 000 | N5: NBRE DE LOT | O5: TONTINE 100 000 | P5: REMBOURSEMENT PETIT LOT T40 | Q5: REMBOURSEMENT PETIT LOT T75 | R5: REMBOURSEMENT PETIT LOT T100 | S5: REMBOURSEMENT PRÊT FONDS | T5: MODE PAIEMENT REMBOURSEMENT PRÊT FONDS | U5: MONTANT ENGAGEMENT | V5: SANCTION | W5: INSCRIPTION | X5: EPARGNE ASSURANCE | Y5: RECONSTITUTION FONDS | Z5: PRÊT FONDS | AA5: MODE PAIEMENT PRÊT | AB5: NUM CHEQUE | AC5: ACHAT LOT PRINCIPAL T40 | AD5: ACHAT LOT PRINCIPAL T75 | AE5: ACHAT LOT PRINCIPAL T100 | AF5: MODE PAIEMENT LOT PRINCIPAL | AG5: NUM CHEQUE | AH5: PENALITE VERSEMENT ESPECES | AI5: VENTE PETIT LOT T40 | AJ5: VENTE PETIT LOT T75 | AK5: VENTE PETIT LOT T100 | AL5: INTERET PETIT LOT T40 | AM5: INTERET PETIT LOT T75 | AN5: INTERET PETIT LOT T100 | AO5: NUM CHEQUE | AP5: MODE PAIEMENT PETEIT LOT | AQ5: PENELAITE RETARD TONTINE | AR5: PENELAITE ECHEC TONTINE | AS5: RESTE | AT5: MUTUELLE | AU5: REMBOURSEMENT TRANSPORT | AV5: RETRAIT PARTIEL FONDS | AW5: MONTANT T40 | AX5: MONTANT T75 | AY5: MONTANT T100 | AZ5: MONTANT CHEQUE | BA5: MONTANT ESPECES | BB5: CONTRIBUTION FOYER | BC5: AUTRES SOTIES | BD5: MONTANT CHEQUE EFFECTIF | BE5: NUMERO CHEQUE | BF5: INTERET PRÊT | BG5: NBRE MOIS | BH5: DEPENSE FONDS DE ROULEMENT | BI5: DEPENSE FRAIS EXCEPTIONNEL | BJ5: DEPENSE FONDS MUTUEL | BK5: DEPENSE COLLATION RECEPTION | BL5: PENALITE PRET FONDS | BM5: DEPENSE PENALITE VERSEMENT BANQUE | BN5: LIBELLE | BO5: COMPTE | BP5: MONTANT
A6: AS201648 | B6: =VLOOKUP(A6,[11]LISTADHERENT!A$5:H$39,3,0) -> ASELBY | C6: =D6+E6+F6-U6-BB6 -> 0 | D6: =VLOOKUP(A6,[12]HISTOBQUEAVRIL23!$A$6:$G$44,3,0) -> 175000 | E6: =VLOOKUP(A6,[12]HISTOBQUEAVRIL23!$A$6:$G$39,4,0) -> 0 | F6: =VLOOKUP(A6,[12]HISTOBQUEAVRIL23!$A$6:$G$39,5,0) -> 0 | G6: =IF(H6="ESPECES",3000,0) -> 0 | H6: =IF($D6<>0,"BANQUE",IF($E6<>0,"ESPECES","ECHEC")) -> BANQUE | K6: =IF($D6<>0,J6*40000,IF($E6<>0,J6*40000,0)) -> 0 | L6: 1 | M6: =IF($D6<>0,L6*75000,IF($E6<>0,L6*75000,0)) -> 75000 | N6: 1 | O6: =IF($D6<>0,N6*100000,IF($E6<>0,N6*100000,0)) -> 100000 | Q6: =VLOOKUP($A6,[13]TONTAVRIL23!$A$6:$P$20,10,0) -> 0 | R6: =VLOOKUP($A6,[14]TONTAVRIL23!$A$6:$P$21,10,0) -> 0 | U6: =G6+S6++R6+P6+O6+M6+I6+K6+Q6+V6+W6 -> 175000 | AQ6: =IF(H6="ECHEC",((K6+M6+O6)*20/100),0) -> 0 | AR6: =IF(H6="ECHEC",((K6+M6+O6)*20/100),0) -> 0 | AW6: =IF(AC6=0,AI6,(1*25000*12)+AI6-AC6) -> 0 | AX6: =IF(AD6=0,AJ6,(1*75000*12)+(AJ6)-AD6) -> 0 | AY6: =IF(AE6=0,AK6,(1*100000*12)+(AK6)-AE6) -> 0 | AZ6: =SUM(AV6:AY6)-BF6+Z6-F6+BH6+BI6+BJ6+BK6+BL6+BM6 -> 106000 | BD6: =IF(AZ6=0,(AZ6-BA6-BC6),(AZ6-BA6-BB6-BC6))+F6 -> 106000 | BE6: 106000 | BF6: =Z6*1/100*BG6 -> 0 | BG6: 8 | BH6: =BP16 -> 6000 | BI6: =BP28 -> 0 | BJ6: =BP33 -> 0 | BK6: =+BP38 -> 100000 | BM6: =BP22 -> 0 | BN6: ACHAT FOURNITURE | BO6: FONDS DE ROULEMENT
A7: AS201601 | B7: =VLOOKUP(A7,[11]LISTADHERENT!A$5:H$39,3,0) -> BAKOP ACHILLE | C7: =D7+E7+F7-U7-BB7 -> 0 | D7: =VLOOKUP(A7,[12]HISTOBQUEAVRIL23!$A$6:$G$44,3,0) -> 40000 | E7: =VLOOKUP(A7,[12]HISTOBQUEAVRIL23!$A$6:$G$39,4,0) -> 0 | F7: =VLOOKUP(A7,[12]HISTOBQUEAVRIL23!$A$6:$G$39,5,0) -> 0 | G7: =IF(H7="ESPECES",3000,0) -> 0 | H7: =IF($D7<>0,"BANQUE",IF($E7<>0,"ESPECES","ECHEC")) -> BANQUE | J7: 1 | K7: =IF($D7<>0,J7*40000,IF($E7<>0,J7*40000,0)) -> 40000 | M7: =IF($D7<>0,L7*75000,IF($E7<>0,L7*75000,0)) -> 0 | O7: =IF($D7<>0,N7*100000,IF($E7<>0,N7*100000,0)) -> 0 | P7: =VLOOKUP($A7,[15]TONTAVRIL23!$A$6:$P$35,12,0) -> 0 | U7: =G7+S7++R7+P7+O7+M7+I7+K7+Q7+V7+W7 -> 40000 | AQ7: =IF(H7="ECHEC",((K7+M7+O7)*20/100),0) -> 0 | AR7: =IF(H7="ECHEC",((K7+M7+O7)*20/100),0) -> 0 | AS7: =IF(H7="ECHEC",0,(K7+I7-25000)) -> 15000 | AW7: =IF(AC7=0,AI7,(1*25000*12)+AI7-AC7) -> 0 | AX7: =IF(AD7=0,AJ7,(1*75000*12)+(AJ7)-AD7) -> 0 | AY7: =IF(AE7=0,AK7,(1*100000*12)+(AK7)-AE7) -> 0 | AZ7: =SUM(AV7:AY7)-BF7+Z7-F7+BH7+BI7+BJ7+BK7+BL7+BM7 -> 0 | BD7: =IF(AZ7=0,(AZ7-BA7-BC7),(AZ7-BA7-BB7-BC7))+F7 -> 0 | BF7: =Z7*1/100*BG7 -> 0 | BG7: 8 | BH7: =BP17 -> 0 | BI7: =BP27 -> 0 | BJ7: =BP33 -> 0 | BM7: =BP23 -> 0 | BN7: COMMUNICATION | BO7: FONDS DE ROULEMENT
A8: AS201602 | B8: =VLOOKUP(A8,[11]LISTADHERENT!A$5:H$39,3,0) -> BOUTCHOUANG WILLIAM | C8: =D8+E8+F8-U8-BB8 -> 0 | D8: =VLOOKUP(A8,[12]HISTOBQUEAVRIL23!$A$6:$G$44,3,0) -> 115000 | E8: =VLOOKUP(A8,[12]HISTOBQUEAVRIL23!$A$6:$G$39,4,0) -> 0 | F8: =VLOOKUP(A8,[12]HISTOBQUEAVRIL23!$A$6:$G$39,5,0) -> 0 | G8: =IF(H8="ESPECES",3000,0) -> 0 | H8: =IF($D8<>0,"BANQUE",IF($E8<>0,"ESPECES","ECHEC")) -> BANQUE | J8: 1 | K8: =IF($D8<>0,J8*40000,IF($E8<>0,J8*40000,0)) -> 40000 | L8: 1 | M8: =IF($D8<>0,L8*75000,IF($E8<>0,L8*75000,0)) -> 75000 | O8: =IF($D8<>0,N8*100000,IF($E8<>0,N8*100000,0)) -> 0 | P8: =VLOOKUP($A8,[15]TONTAVRIL23!$A$6:$P$35,12,0) -> 0 | Q8: =VLOOKUP($A8,[13]TONTAVRIL23!$A$6:$P$20,10,0) -> 0 | U8: =G8+S8++R8+P8+O8+M8+I8+K8+Q8+V8+W8 -> 115000 | Z8: 500000 | AA8: BANQUE | AQ8: =IF(H8="ECHEC",((K8+M8+O8)*20/100),0) -> 0 | AR8: =IF(H8="ECHEC",((K8+M8+O8)*20/100),0) -> 0 | AS8: =IF(H8="ECHEC",0,(K8+I8-25000)) -> 15000 | AW8: =IF(AC8=0,AI8,(1*25000*12)+AI8-AC8) -> 0 | AX8: =IF(AD8=0,AJ8,(1*75000*12)+(AJ8)-AD8) -> 0 | AY8: =IF(AE8=0,AK8,(1*100000*12)+(AK8)-AE8) -> 0 | AZ8: =SUM(AV8:AY8)-BF8+Z8-F8+BH8+BI8+BJ8+BK8+BL8+BM8 -> 490000 | BD8: =IF(AZ8=0,(AZ8-BA8-BC8),(AZ8-BA8-BB8-BC8))+F8 -> 490000 | BE8: 490000 | BF8: =Z8*1/100*BG8 -> 10000 | BG8: 2 | BN8: COMMISSION | BO8: FONDS DE ROULEMENT
A9: AS201604 | B9: =VLOOKUP(A9,[11]LISTADHERENT!A$5:H$39,3,0) -> DJOMO JEAN PAUL | C9: =D9+E9+F9-U9-BB9 -> 0 | D9: =VLOOKUP(A9,[12]HISTOBQUEAVRIL23!$A$6:$G$44,3,0) -> 145000 | E9: =VLOOKUP(A9,[12]HISTOBQUEAVRIL23!$A$6:$G$39,4,0) -> 0 | F9: =VLOOKUP(A9,[12]HISTOBQUEAVRIL23!$A$6:$G$39,5,0) -> 0 | G9: =IF(H9="ESPECES",3000,0) -> 0 | H9: =IF($D9<>0,"BANQUE",IF($E9<>0,"ESPECES","ECHEC")) -> BANQUE | I9: 5000 | J9: 1 | K9: =IF($D9<>0,J9*40000,IF($E9<>0,J9*40000,0)) -> 40000 | M9: =IF($D9<>0,L9*75000,IF($E9<>0,L9*75000,0)) -> 0 | N9: 1 | O9: =IF($D9<>0,N9*100000,IF($E9<>0,N9*100000,0)) -> 100000 | P9: =VLOOKUP($A9,[15]TONTAVRIL23!$A$6:$P$35,12,0) -> 0 | R9: =VLOOKUP($A9,[14]TONTAVRIL23!$A$6:$P$21,10,0) -> 0 | U9: =G9+S9++R9+P9+O9+M9+I9+K9+Q9+V9+W9 -> 145000 | AI9: 22500 | AL9: 500 | AQ9: =IF(H9="ECHEC",((K9+M9+O9)*20/100),0) -> 0 | AR9: =IF(H9="ECHEC",((K9+M9+O9)*20/100),0) -> 0 | AS9: =IF(H9="ECHEC",0,(K9+I9-25000)) -> 20000 | AW9: =IF(AC9=0,AI9,(1*25000*12)+AI9-AC9) -> 22500 | AX9: =IF(AD9=0,AJ9,(1*75000*12)+(AJ9)-AD9) -> 0 | AY9: =IF(AE9=0,AK9,(1*100000*12)+(AK9)-AE9) -> 0 | AZ9: =SUM(AV9:AY9)-BF9+Z9-F9+BH9+BI9+BJ9+BK9+BL9+BM9 -> 22500 | BA9: 22500 | BD9: =IF(AZ9=0,(AZ9-BA9-BC9),(AZ9-BA9-BB9-BC9))+F9 -> 0 | BF9: =Z9*1/100*BG9 -> 0 | BG9: 8 | BN9: AIDE UEEB ET CONT FEMME | BO9: FONDS DE ROULEMENT
A10: AS201654 | B10: =VLOOKUP(A10,[11]LISTADHERENT!A$5:H$39,3,0) -> DJOMOU TCHAPDA | C10: =D10+E10+F10-U10-BB10 -> -70000 | D10: =VLOOKUP(A10,[12]HISTOBQUEAVRIL23!$A$6:$G$44,3,0) -> 0 | E10: =VLOOKUP(A10,[12]HISTOBQUEAVRIL23!$A$6:$G$39,4,0) -> 43000 | F10: =VLOOKUP(A10,[12]HISTOBQUEAVRIL23!$A$6:$G$39,5,0) -> 0 | G10: =IF(H10="ESPECES",3000,0) -> 3000 | H10: =IF($D10<>0,"BANQUE",IF($E10<>0,"ESPECES","ECHEC")) -> ESPECES | J10: 1 | K10: =IF($D10<>0,J10*40000,IF($E10<>0,J10*40000,0)) -> 40000 | M10: =IF($D10<>0,L10*75000,IF($E10<>0,L10*75000,0)) -> 0 | O10: =IF($D10<>0,N10*100000,IF($E10<>0,N10*100000,0)) -> 0 | P10: =VLOOKUP($A10,[15]TONTAVRIL23!$A$6:$P$35,12,0) -> 0 | U10: =G10+S10++R10+P10+O10+M10+I10+K10+Q10+V10+W10 -> 43000 | AC10: 11000 | AI10: 60000 | AL10: 2000 | AQ10: =IF(H10="ECHEC",((K10+M10+O10)*20/100),0) -> 0 | AR10: =IF(H10="ECHEC",((K10+M10+O10)*20/100),0) -> 0 | AS10: =IF(H10="ECHEC",0,(K10+I10-25000)) -> 15000 | AW10: =IF(AC10=0,AI10,(1*25000*12)+AI10-AC10) -> 349000 | AX10: =IF(AD10=0,AJ10,(1*75000*12)+(AJ10)-AD10) -> 0 | AY10: =IF(AE10=0,AK10,(1*100000*12)+(AK10)-AE10) -> 0 | AZ10: =SUM(AV10:AY10)-BF10+Z10-F10+BH10+BI10+BJ10+BK10+BL10+BM10 -> 349000 | BA10: 60000 | BB10: 70000 | BD10: =IF(AZ10=0,(AZ10-BA10-BC10),(AZ10-BA10-BB10-BC10))+F10 -> 219000 | BE10: 219000 | BF10: =Z10*1/100*BG10 -> 0 | BG10: 8 | BN10: CREDIT TELEPHONE | BO10: FONDS DE ROULEMENT
A11: AS201605 | B11: =VLOOKUP(A11,[11]LISTADHERENT!A$5:H$39,3,0) -> DJOUKWE NANGUEN GUY BLAISE | C11: =D11+E11+F11-U11-BB11 -> -157500 | D11: =VLOOKUP(A11,[12]HISTOBQUEAVRIL23!$A$6:$G$44,3,0) -> 115000 | E11: =VLOOKUP(A11,[12]HISTOBQUEAVRIL23!$A$6:$G$39,4,0) -> 0 | F11: =VLOOKUP(A11,[12]HISTOBQUEAVRIL23!$A$6:$G$39,5,0)+70000 -> 70000 | G11: =IF(H11="ESPECES",3000,0) -> 0 | H11: =IF($D11<>0,"BANQUE",IF($E11<>0,"ESPECES","ECHEC")) -> BANQUE | J11: 1 | K11: =IF($D11<>0,J11*40000,IF($E11<>0,J11*40000,0)) -> 40000 | L11: 1 | M11: =IF($D11<>0,L11*75000,IF($E11<>0,L11*75000,0)) -> 75000 | O11: =IF($D11<>0,N11*100000,IF($E11<>0,N11*100000,0)) -> 0 | P11: =VLOOKUP($A11,[15]TONTAVRIL23!$A$6:$P$35,12,0) -> 0 | Q11: =VLOOKUP($A11,[13]TONTAVRIL23!$A$6:$P$20,10,0) -> 0 | S11: 157500 | U11: =G11+S11++R11+P11+O11+M11+I11+K11+Q11+V11+W11 -> 272500 | Z11: 1000000 | AA11: BANQUE | AC11: 10000 | AJ11: =50000+100000 -> 150000 | AM11: 2000 | AQ11: =IF(H11="ECHEC",((K11+M11+O11)*20/100),0) -> 0 | AR11: =IF(H11="ECHEC",((K11+M11+O11)*20/100),0) -> 0 | AS11: =IF(H11="ECHEC",0,(K11+I11-25000)) -> 15000 | AW11: =IF(AC11=0,AI11,(1*25000*12)+AI11-AC11)-S11 -> 132500 | AX11: =IF(AD11=0,AJ11,(1*75000*12)+(AJ11)-AD11) -> 150000 | AY11: =IF(AE11=0,AK11,(1*100000*12)+(AK11)-AE11) -> 0 | AZ11: =SUM(AV11:AY11)-BF11+Z11-F11+BH11+BI11+BJ11+BK11+BL11+BM11 -> 1132500 | BB11: 70000 | BD11: =IF(AZ11=0,(AZ11-BA11-BC11),(AZ11-BA11-BB11-BC11))+F11 -> 1132500 | BE11: =62500+150000+920000 -> 1132500 | BF11: =Z11*1/100*BG11 -> 80000 | BG11: 8 | BN11: PRODUCTION RAPPORT | BO11: FONDS DE ROULEMENT
A12: AS201608 | B12: =VLOOKUP(A12,[11]LISTADHERENT!A$5:H$39,3,0) -> DJUOMBESSY ANTOINE | C12: =D12+E12+F12-U12-BB12 -> 0 | D12: =VLOOKUP(A12,[12]HISTOBQUEAVRIL23!$A$6:$G$44,3,0) -> 320000 | E12: =VLOOKUP(A12,[12]HISTOBQUEAVRIL23!$A$6:$G$39,4,0) -> 0 | F12: =VLOOKUP(A12,[12]HISTOBQUEAVRIL23!$A$6:$G$39,5,0) -> 0 | G12: =IF(H12="ESPECES",3000,0) -> 0 | H12: =IF($D12<>0,"BANQUE",IF($E12<>0,"ESPECES","ECHEC")) -> BANQUE | I12: 5000 | J12: 1 | K12: =IF($D12<>0,J12*40000,IF($E12<>0,J12*40000,0)) -> 40000 | L12: 1 | M12: =IF($D12<>0,L12*75000,IF($E12<>0,L12*75000,0)) -> 75000 | N12: 2 | O12: =IF($D12<>0,N12*100000,IF($E12<>0,N12*100000,0)) -> 200000 | P12: =VLOOKUP($A12,[15]TONTAVRIL23!$A$6:$P$35,12,0) -> 0 | Q12: =VLOOKUP($A12,[13]TONTAVRIL23!$A$6:$P$20,10,0) -> 0 | R12: =VLOOKUP($A12,[14]TONTAVRIL23!$A$6:$P$21,10,0) -> 0 | U12: =G12+S12++R12+P12+O12+M12+I12+K12+Q12+V12+W12 -> 320000 | AQ12: =IF(H12="ECHEC",((K12+M12+O12)*20/100),0) -> 0 | AR12: =IF(H12="ECHEC",((K12+M12+O12)*20/100),0) -> 0 | AS12: =IF(H12="ECHEC",0,(K12+I12-25000)) -> 20000 | AW12: =IF(AC12=0,AI12,(1*25000*12)+AI12-AC12) -> 0 | AX12: =IF(AD12=0,AJ12,(1*75000*12)+(AJ12)-AD12) -> 0 | AY12: =IF(AE12=0,AK12,(1*100000*12)+(AK12)-AE12) -> 0 | AZ12: =SUM(AV12:AY12)-BF12+Z12-F12+BH12+BI12+BJ12+BK12+BL12+BM12 -> 0 | BD12: =IF(AZ12=0,(AZ12-BA12-BC12),(AZ12-BA12-BB12-BC12))+F12 -> 0 | BE12: =BD11-BE11 -> 0 | BF12: =Z12*1/100*BG12 -> 0 | BG12: 8 | BN12: ACHAT SOURIS ET PHOTOCOPIE | BO12: FONDS DE ROULEMENT
A13: AS201651 | B13: =VLOOKUP(A13,[11]LISTADHERENT!A$5:H$39,3,0) -> DOMOU FABIEN | C13: =D13+E13+F13-U13-BB13 -> 0 | D13: =VLOOKUP(A13,[12]HISTOBQUEAVRIL23!$A$6:$G$44,3,0) -> 40000 | E13: =VLOOKUP(A13,[12]HISTOBQUEAVRIL23!$A$6:$G$39,4,0) -> 0 | F13: =VLOOKUP(A13,[12]HISTOBQUEAVRIL23!$A$6:$G$39,5,0) -> 0 | G13: =IF(H13="ESPECES",3000,0) -> 0 | H13: =IF($D13<>0,"BANQUE",IF($E13<>0,"ESPECES","ECHEC")) -> BANQUE | J13: 1 | K13: =IF($D13<>0,J13*40000,IF($E13<>0,J13*40000,0)) -> 40000 | M13: =IF($D13<>0,L13*75000,IF($E13<>0,L13*75000,0)) -> 0 | O13: =IF($D13<>0,N13*100000,IF($E13<>0,N13*100000,0)) -> 0 | P13: =VLOOKUP($A13,[15]TONTAVRIL23!$A$6:$P$35,12,0) -> 0 | U13: =G13+S13++R13+P13+O13+M13+I13+K13+Q13+V13+W13 -> 40000 | AQ13: =IF(H13="ECHEC",((K13+M13+O13)*20/100),0) -> 0 | AR13: =IF(H13="ECHEC",((K13+M13+O13)*20/100),0) -> 0 | AS13: =IF(H13="ECHEC",0,(K13+I13-25000)) -> 15000 | AW13: =IF(AC13=0,AI13,(1*25000*12)+AI13-AC13) -> 0 | AX13: =IF(AD13=0,AJ13,(1*75000*12)+(AJ13)-AD13) -> 0 | AY13: =IF(AE13=0,AK13,(1*100000*12)+(AK13)-AE13) -> 0 | AZ13: =SUM(AV13:AY13)-BF13+Z13-F13+BH13+BI13+BJ13+BK13+BL13+BM13 -> 0 | BD13: =IF(AZ13=0,(AZ13-BA13-BC13),(AZ13-BA13-BB13-BC13))+F13 -> 0 | BF13: =Z13*1/100*BG13 -> 0 | BG13: 8 | BN13: TAXI BANQUE | BO13: FONDS DE ROULEMENT | BP13: 6000
