Workbook
Name BANQUE: #REF!
Name BANQUE: #REF!
Name BANQUE: #REF!
Name BANQUE: #REF!
Name BANQUE: #REF!
Name BANQUE: #REF!
Name BANQUE: #REF!
Name BANQUE: #REF!
Name BANQUE: #REF!
Name BANQUE: #REF!
Name BANQUE: #REF!
Name BANQUE: #REF!
Name BANQUE: #REF!
Name BANQUE: #REF!
Name BANQUE: #REF!
Name BANQUE: #REF!
Name BANQUE: #REF!
Name BANQUE: #REF!
Name BANQUE: #REF!
Name MODEPAID: MODEPAID!$A$1:$A$3
Name MODEPAID: #REF!
Name MODEPAID: #REF!
Name MODEPAID: [1]Feuil2!$A$1:$A$3
Name MODEPAID: #REF!
Name MODEPAID: [1]Feuil2!$A$1:$A$3
Name MODEPAID: #REF!
Name MODEPAID: #REF!
Name MODEPAID: [1]Feuil2!$A$1:$A$3
Name MODEPAID: #REF!
Name MODEPAID: [1]Feuil2!$A$1:$A$3
Name MODEPAID: #REF!
Name MODEPAID: [1]Feuil2!$A$1:$A$3
Name MODEPAID: #REF!
Name MODEPAID: #REF!
Name MODEPAID: [1]Feuil2!$A$1:$A$3
Name MODEPAID: #REF!
Name MODEPAID: [1]Feuil2!$A$1:$A$3
Name MODEPAID: #REF!
Name MODEPAID: [1]Feuil2!$A$1:$A$3
Name MODEPAID: #REF!
Name MODEPAID: [1]Feuil2!$A$1:$A$3
Name MODEPAID: #REF!
Name MODEPAID: #REF!
Name MODEPAID: [1]Feuil2!$A$1:$A$3
Name MODEPAID: #REF!
Name MODEPAID: #REF!
Name MODEPAID: [1]Feuil2!$A$1:$A$3
Name MODEPAID: #REF!
Name MODEPAID: #REF!
Name MODEPAID: [1]Feuil2!$A$1:$A$3
Name MODEPAID: #REF!
Name MODEPAID: #REF!
Name MODEPAID: [1]Feuil2!$A$1:$A$3
Name MODEPAID: #REF!
Name MODET25000: [2]MODEVERSEMENT!$A$1:$A$3
Name MODEVERSEMENT: #REF!
Name MODEVERSEMENT: #REF!
Name MODEVERSEMENT: #REF!
Name MODEVERSEMENT: #REF!
Name MODEVERSEMENT: #REF!

Sheet MODEPAID
A1: BANQUE
A2: ESPECES
A3: ECHEC

Sheet TONTJUIL
A1: ASSOCIATION | B1: ASELBY
A2: ANNEE | B2: 2019/2020
A3: TONTINE | B3: 75000
C4: 44031
A5: MATRICULE | B5: NOM ET PRENOM | C5: MONTANT TONTINE | D5: PENALITE | E5: MODE VERSEMENT TONTINE | F5: REPORT ECHEC PETIT LOT | G5: MODE VERSEMENT VENTE PETIT LOT | H5: VENTE PETIT LOT | I5: INTERET PETIT LOT | J5: MODE VERSEMENT VENTE PETIT LOT | K5: NUMERO CHEQUE | L5: MONTANT A REMOURSER | M5: MONTANT REMBOURSE | N5: MODE VERSEMENT REMBOURSEMENT | O5: MODE VERSEMENT TONTINE PRINCIPAL | P5: NUMERO CHEQUE | Q5: MONTANT TONTINE LOT PRINCIPAL | R5: INTERET LOT PRINCIPAL | S5: INTERET DU
A6: AS201602 | B6: =VLOOKUP(A6,[6]LISTADHERENT!A$5:H$60,3,0) -> BOUTCHOUANG WILLIAM | C6: =IF(E6="ECHEC",0,IF(E6="",0,75000)) -> 75000 | D6: =IF(E6="ESPECES",0,0) -> 0 | E6: ESPECES | M6: =L6 -> 0 | Q6: =IF(R6=0,0,($C$39-R6)) -> 0 | S6: =IF(R6=0,0,(R6-75000)) -> 0
A7: AS201603 | B7: =VLOOKUP(A7,[6]LISTADHERENT!A$5:H$60,3,0) -> CHINGUE FABRICE | C7: =IF(E7="ECHEC",0,IF(E7="",0,75000)) -> 75000 | D7: =IF(E7="ESPECES",0,0) -> 0 | E7: BANQUE | M7: =L7 -> 0 | Q7: =IF(R7=0,0,($C$39-R7)) -> 0 | S7: =IF(R7=0,0,(R7-75000)) -> 0
A8: AS201604 | B8: =VLOOKUP(A8,[6]LISTADHERENT!A$5:H$60,3,0) -> DJOMO JEAN PAUL | C8: =IF(E8="ECHEC",0,IF(E8="",0,75000)) -> 75000 | D8: =IF(E8="ESPECES",0,0) -> 0 | E8: BANQUE | H8: 100000 | I8: 2000 | J8: BANQUE | M8: =L8 -> 0 | O8: BANQUE | Q8: =IF(R8=0,0,($C$39-R8)) -> 1000000 | R8: 200000 | S8: =IF(R8=0,0,(R8-75000)) -> 125000
A9: AS201605 | B9: =VLOOKUP(A9,[6]LISTADHERENT!A$5:H$60,3,0) -> DJOUKWE NANGUEN GUY BLAISE | C9: =IF(E9="ECHEC",0,IF(E9="",0,75000)) -> 75000 | D9: =IF(E9="ESPECES",0,0) -> 0 | E9: BANQUE | M9: =L9 -> 0 | Q9: =IF(R9=0,0,($C$39-R9)) -> 0 | S9: =IF(R9=0,0,(R9-75000)) -> 0
A10: AS201613 | B10: =VLOOKUP(A10,[6]LISTADHERENT!A$5:H$60,3,0) -> HOTCHO BENJAMIN | C10: =IF(E10="ECHEC",0,IF(E10="",0,75000)) -> 75000 | D10: =IF(E10="ESPECES",0,0) -> 0 | E10: BANQUE | M10: =L10 -> 0 | Q10: =IF(R10=0,0,($C$39-R10)) -> 0 | S10: =IF(R10=0,0,(R10-75000)) -> 0
A11: AS201611 | B11: =VLOOKUP(A11,[6]LISTADHERENT!A$5:H$60,3,0) -> HENGUE PAUL OMER | C11: =IF(E11="ECHEC",0,IF(E11="",0,75000)) -> 75000 | D11: =IF(E11="ESPECES",0,0) -> 0 | E11: BANQUE | M11: =L11 -> 0 | Q11: =IF(R11=0,0,($C$39-R11)) -> 0 | S11: =IF(R11=0,0,(R11-75000)) -> 0
A12: AS201619 | B12: =VLOOKUP(A12,[6]LISTADHERENT!A$5:H$60,3,0) -> KOUATCHO MESSACK | C12: =IF(E12="ECHEC",0,IF(E12="",0,75000)) -> 75000 | D12: =IF(E12="ESPECES",0,0) -> 0 | E12: BANQUE | H12: 100000 | I12: 2000 | J12: BANQUE | M12: =L12 -> 0 | Q12: =IF(R12=0,0,($C$39-R12)) -> 0 | S12: =IF(R12=0,0,(R12-75000)) -> 0
A13: AS201621 | B13: =VLOOKUP(A13,[6]LISTADHERENT!A$5:H$60,3,0) -> NANKAM APPOLINAIRE | C13: =IF(E13="ECHEC",0,IF(E13="",0,75000)) -> 75000 | D13: =IF(E13="ESPECES",0,0) -> 0 | E13: ESPECES | M13: =L13 -> 0 | Q13: =IF(R13=0,0,($C$39-R13)) -> 0 | S13: =IF(R13=0,0,(R13-75000)) -> 0
A14: AS201649 | B14: =VLOOKUP(A14,[6]LISTADHERENT!A$5:H$60,3,0) -> MBOGNING TUGMA GUY | C14: =IF(E14="ECHEC",0,IF(E14="",0,75000))+150000 -> 225000 | D14: =IF(E14="ESPECES",0,0) -> 0 | E14: BANQUE | H14: 100000 | I14: 2000 | J14: BANQUE | M14: =L14 -> 0 | Q14: =IF(R14=0,0,($C$39-R14)) -> 0 | S14: =IF(R14=0,0,(R14-75000)) -> 0
A15: AS201649 | B15: =VLOOKUP(A15,[6]LISTADHERENT!A$5:H$60,3,0) -> MBOGNING TUGMA GUY | D15: =IF(E15="ESPECES",0,0) -> 0 | M15: =L15 -> 0 | Q15: =IF(R15=0,0,($C$39-R15)) -> 0 | S15: =IF(R15=0,0,(R15-75000)) -> 0
A16: AS201649 | B16: =VLOOKUP(A16,[6]LISTADHERENT!A$5:H$60,3,0) -> MBOGNING TUGMA GUY | D16: =IF(E16="ESPECES",0,0) -> 0 | M16: =L16 -> 0 | Q16: =IF(R16=0,0,($C$39-R16)) -> 0 | S16: =IF(R16=0,0,(R16-75000)) -> 0
A17: AS201626 | B17: =VLOOKUP(A17,[6]LISTADHERENT!A$5:H$60,3,0) -> NGUIEMEGNI MATHIEU BLAISE | C17: =IF(E17="ECHEC",0,IF(E17="",0,75000))+75000 -> 150000 | D17: =IF(E17="ESPECES",0,0) -> 0 | E17: BANQUE | M17: =L17 -> 0 | Q17: =IF(R17=0,0,($C$39-R17)) -> 0 | S17: =IF(R17=0,0,(R17-75000)) -> 0
A18: AS201626 | B18: =VLOOKUP(A18,[6]LISTADHERENT!A$5:H$60,3,0) -> NGUIEMEGNI MATHIEU BLAISE | D18: =IF(E18="ESPECES",0,0) -> 0 | M18: =L18 -> 0 | Q18: =IF(R18=0,0,($C$39-R18)) -> 0 | S18: =IF(R18=0,0,(R18-75000)) -> 0
A19: AS201628 | B19: =VLOOKUP(A19,[6]LISTADHERENT!A$5:H$60,3,0) -> NKAMGANG JUSTIN DEJOLIE | C19: =IF(E19="ECHEC",0,IF(E19="",0,75000)) -> 75000 | D19: =IF(E19="ESPECES",0,0) -> 0 | E19: ESPECES | H19: 50000 | I19: 1000 | J19: BANQUE | M19: =L19 -> 0 | Q19: =IF(R19=0,0,($C$39-R19)) -> 0 | S19: =IF(R19=0,0,(R19-75000)) -> 0
A20: AS201633 | B20: =VLOOKUP(A20,[6]LISTADHERENT!A$5:H$60,3,0) -> PATEGO NJOSSU GUSTAVE | C20: =IF(E20="ECHEC",0,IF(E20="",0,75000)) -> 75000 | D20: =IF(E20="ESPECES",0,0) -> 0 | E20: BANQUE | M20: =L20 -> 0 | Q20: =IF(R20=0,0,($C$39-R20)) -> 0 | S20: =IF(R20=0,0,(R20-75000)) -> 0
A21: AS201638 | B21: =VLOOKUP(A21,[6]LISTADHERENT!A$5:H$60,3,0) -> SIMO PIERRE | C21: =IF(E21="ECHEC",0,IF(E21="",0,75000)) -> 75000 | D21: =IF(E21="ESPECES",0,0) -> 0 | E21: BANQUE | M21: =L21 -> 0 | Q21: =IF(R21=0,0,($C$39-R21)) -> 0 | S21: =IF(R21=0,0,(R21-75000)) -> 0
A22: AS201655 | B22: =VLOOKUP(A22,[6]LISTADHERENT!A$5:H$60,3,0) -> TCHEMHOU EMMANUEL | C22: =IF(E22="ECHEC",0,IF(E22="",0,75000)) -> 0 | D22: =IF(E22="ESPECES",0,0) -> 0 | E22: ECHEC | L22: =M22 -> 0 | M22: =+TONTJUIL!H21+TONTJUIL!I21 -> 0 | Q22: =IF(R22=0,0,($C$39-R22)) -> 0 | S22: =IF(R22=0,0,(R22-75000)) -> 0
A23: AS201647 | B23: =VLOOKUP(A23,[6]LISTADHERENT!A$5:H$60,3,0) -> YOUMBI EMMANUEL | C23: =IF(E23="ECHEC",0,IF(E23="",0,75000))+75000 -> 150000 | D23: =IF(E23="ESPECES",0,0) -> 0 | E23: BANQUE | M23: =L23 -> 0 | Q23: =IF(R23=0,0,($C$39-R23)) -> 0 | S23: =IF(R23=0,0,(R23-75000)) -> 0
A24: AS201647 | B24: =VLOOKUP(A24,[6]LISTADHERENT!A$5:H$60,3,0) -> YOUMBI EMMANUEL | D24: =IF(E24="ESPECES",0,0) -> 0 | M24: =L24 -> 0 | Q24: =IF(R24=0,0,($C$39-R24)) -> 0 | S24: =IF(R24=0,0,(R24-75000)) -> 0
A26: TOTAL | C26: =SUM(C6:C24) -> 1350000 | D26: =SUM(D6:D24) -> 0 | F26: =SUM(F6:F24) -> 0 | H26: =SUM(H6:H24) -> 350000 | I26: =SUM(I6:I24) -> 7000 | K26: =SUM(K6:K24) -> 0 | L26: =SUM(L6:L24) -> 0 | M26: =SUM(M6:M24) -> 0 | O26: =SUM(O6:O24) -> 0 | P26: =SUM(P6:P24) -> 0 | Q26: =SUM(Q6:Q24) -> 1000000 | R26: =SUM(R6:R24) -> 200000 | S26: =SUM(S6:S24) -> 125000
C31: TONTINE | D31: REMBOURSEMENT PETIT LOT | E31: VENTE PETIT LOT | F31: VENTE LOT PRINCIPAL | G31: SOLDE EN CAISSE | I31: TONTINE + REMB + INTERET VENTE | J31: =C36+D36+R26 -> 1550000
I32: VENDUE | J32: =IF(J31>=2400000,1200000*2,1200000) -> 1200000
B33: ESPECES | C33: =SUMIFS(C6:C24,E6:E24,"ESPECES") -> 225000 | D33: =SUMIFS(D6:D24,F6:F24,"ESPECES") -> 0 | E33: =SUMIFS(H6:H24,J6:J24,"ESPECES") -> 0 | F33: =SUMIFS(Q6:Q24,O6:O24,"ESPECES") -> 0 | G33: =C33+D33-E33-F33 -> 225000
B34: BANQUE | C34: =SUMIFS(C6:C24,E6:E24,"BANQUE") -> 1125000 | E34: =SUMIFS(H6:H24,J6:J24,"BANQUE") -> 350000 | F34: =SUMIFS(Q6:Q24,O6:O24,"BANQUE") -> 1000000 | G34: =C34+D34-E34-F34 -> -225000 | I34: PETIT LOT | J34: =J31-J32 -> 350000
B36: TOTAL | C36: =C33+C34 -> 1350000 | D36: =D33+D34 -> 0 | E36: =E33+E34 -> 350000 | F36: =F33+F34 -> 1000000 | G36: =G33+G34 -> 0 | I36: RELIQUAT | J36: =J34-H26 -> 0 | K36: =J36 -> 0 | L36: CUMUL
I38: ECHEC TONTINE | J38: =COUNTIFS(E6:E24,"ECHEC")*75000 -> 75000 | K38: =J38 -> 75000 | L38: CUMUL
B39: MONTANT TONTINE | C39: 1200000 | I39: ECHEC REMBOURSEMENT | J39: =SUMIFS(F6:F24,G6:G24,"ECHEC") -> 0 | L39: CUMUL

Sheet TONTAOUT
A1: ASSOCIATION | B1: ASELBY
A2: ANNEE | B2: 2019/2020
A3: TONTINE | B3: 75000
C4: 44059
A5: MATRICULE | B5: NOM ET PRENOM | C5: MONTANT TONTINE | D5: PENALITE | E5: MODE VERSEMENT TONTINE | F5: REPORT ECHEC PETIT LOT | G5: MODE VERSEMENT VENTE PETIT LOT | H5: VENTE PETIT LOT | I5: INTERET PETIT LOT | J5: MODE VERSEMENT VENTE PETIT LOT | K5: NUMERO CHEQUE | L5: MONTANT REMBOURSE | M5: MONTANT A REMBOURSER | N5: MODE VERSEMENT REMBOURSEMENT | O5: MODE VERSEMENT TONTINE PRINCIPAL | P5: NUMERO CHEQUE | Q5: MONTANT TONTINE LOT PRINCIPAL | R5: INTERET LOT PRINCIPAL | S5: INTERET DU
A6: AS201602 | B6: =VLOOKUP(A6,[6]LISTADHERENT!A$5:H$60,3,0) -> BOUTCHOUANG WILLIAM | C6: =IF(E6="ECHEC",0,IF(E6="",0,75000)) -> 75000 | D6: =IF(E6="ESPECES",0,0) -> 0 | E6: BANQUE | F6: =TONTJUIL!F6 -> 0 | L6: =M6 -> 0 | M6: =+TONTJUIL!H6+TONTJUIL!I6 -> 0 | Q6: =IF(R6=0,0,($C$36-R6)) -> 0 | S6: =IF(R6=0,0,(R6-75000)) -> 0
A7: AS201603 | B7: =VLOOKUP(A7,[6]LISTADHERENT!A$5:H$60,3,0) -> CHINGUE FABRICE | C7: =IF(E7="ECHEC",0,IF(E7="",0,75000)) -> 0 | D7: =IF(E7="ESPECES",0,0) -> 0 | F7: =TONTJUIL!F7 -> 0 | L7: =M7 -> 0 | M7: =+TONTJUIL!H7+TONTJUIL!I7 -> 0 | Q7: =IF(R7=0,0,($C$36-R7)) -> 0 | S7: =IF(R7=0,0,(R7-75000)) -> 0
A8: AS201604 | B8: =VLOOKUP(A8,[6]LISTADHERENT!A$5:H$60,3,0) -> DJOMO JEAN PAUL | C8: =IF(E8="ECHEC",0,IF(E8="",0,75000)) -> 75000 | D8: =IF(E8="ESPECES",0,0) -> 0 | E8: BANQUE | F8: =TONTJUIL!F8 -> 0 | H8: 100000 | I8: 2000 | J8: ESPECES | L8: =M8 -> 102000 | M8: =+TONTJUIL!H8+TONTJUIL!I8 -> 102000 | N8: ESPECES | Q8: =IF(R8=0,0,($C$36-R8)) -> 0 | S8: =IF(R8=0,0,(R8-75000)) -> 0
A9: AS201605 | B9: =VLOOKUP(A9,[6]LISTADHERENT!A$5:H$60,3,0) -> DJOUKWE NANGUEN GUY BLAISE | C9: =IF(E9="ECHEC",0,IF(E9="",0,75000)) -> 75000 | D9: =IF(E9="ESPECES",0,0) -> 0 | E9: BANQUE | F9: =TONTJUIL!F9 -> 0 | H9: 100000 | I9: 2000 | J9: ESPECES | L9: =M9 -> 0 | M9: =+TONTJUIL!H9+TONTJUIL!I9 -> 0 | Q9: =IF(R9=0,0,($C$36-R9)) -> 0 | S9: =IF(R9=0,0,(R9-75000)) -> 0
A10: AS201613 | B10: =VLOOKUP(A10,[6]LISTADHERENT!A$5:H$60,3,0) -> HOTCHO BENJAMIN | C10: =IF(E10="ECHEC",0,IF(E10="",0,75000)) -> 75000 | D10: =IF(E10="ESPECES",0,0) -> 0 | E10: BANQUE | F10: =TONTJUIL!F10 -> 0 | L10: =M10 -> 0 | M10: =+TONTJUIL!H10+TONTJUIL!I10 -> 0 | Q10: =IF(R10=0,0,($C$36-R10)) -> 0 | S10: =IF(R10=0,0,(R10-75000)) -> 0
A11: AS201611 | B11: =VLOOKUP(A11,[6]LISTADHERENT!A$5:H$60,3,0) -> HENGUE PAUL OMER | C11: =IF(E11="ECHEC",0,IF(E11="",0,75000)) -> 75000 | D11: =IF(E11="ESPECES",0,0) -> 0 | E11: BANQUE | F11: =TONTJUIL!F11 -> 0 | L11: =M11 -> 0 | M11: =+TONTJUIL!H11+TONTJUIL!I11 -> 0 | Q11: =IF(R11=0,0,($C$36-R11)) -> 0 | S11: =IF(R11=0,0,(R11-75000)) -> 0
A12: AS201619 | B12: =VLOOKUP(A12,[6]LISTADHERENT!A$5:H$60,3,0) -> KOUATCHO MESSACK | C12: =IF(E12="ECHEC",0,IF(E12="",0,75000)) -> 75000 | D12: =IF(E12="ESPECES",0,0) -> 0 | E12: BANQUE | F12: 106000 | G12: ECHEC | L12: =M12 -> 102000 | M12: =+TONTJUIL!H12+TONTJUIL!I12 -> 102000 | N12: ECHEC | Q12: =IF(R12=0,0,($C$36-R12)) -> 0 | S12: =IF(R12=0,0,(R12-75000)) -> 0
A13: AS201621 | B13: =VLOOKUP(A13,[6]LISTADHERENT!A$5:H$60,3,0) -> NANKAM APPOLINAIRE | C13: =IF(E13="ECHEC",0,IF(E13="",0,75000)) -> 75000 | D13: =IF(E13="ESPECES",0,0) -> 0 | E13: BANQUE | F13: =TONTJUIL!F13 -> 0 | L13: =M13 -> 0 | M13: =+TONTJUIL!H13+TONTJUIL!I13 -> 0 | Q13: =IF(R13=0,0,($C$36-R13)) -> 0 | S13: =IF(R13=0,0,(R13-75000)) -> 0
A14: AS201649 | B14: =VLOOKUP(A14,[6]LISTADHERENT!A$5:H$60,3,0) -> MBOGNING TUGMA GUY | C14: =IF(E14="ECHEC",0,IF(E14="",0,75000))+150000 -> 225000 | D14: =IF(E14="ESPECES",0,0) -> 0 | E14: BANQUE | F14: =TONTJUIL!F14 -> 0 | H14: 100000 | I14: 2000 | J14: ESPECES | L14: =M14 -> 102000 | M14: =+TONTJUIL!H14+TONTJUIL!I14 -> 102000 | N14: BANQUE | O14: BANQUE | Q14: =IF(R14=0,0,($C$36-R14)) -> 1040000 | R14: 160000 | S14: =IF(R14=0,0,(R14-75000)) -> 85000
A15: AS201649 | B15: =VLOOKUP(A15,[6]LISTADHERENT!A$5:H$60,3,0) -> MBOGNING TUGMA GUY | D15: =IF(E15="ESPECES",0,0) -> 0 | F15: =TONTJUIL!F15 -> 0 | L15: =M15 -> 0 | M15: =+TONTJUIL!H15+TONTJUIL!I15 -> 0 | Q15: =IF(R15=0,0,($C$36-R15)) -> 0 | S15: =IF(R15=0,0,(R15-75000)) -> 0
A16: AS201649 | B16: =VLOOKUP(A16,[6]LISTADHERENT!A$5:H$60,3,0) -> MBOGNING TUGMA GUY | D16: =IF(E16="ESPECES",0,0) -> 0 | F16: =TONTJUIL!F16 -> 0 | L16: =M16 -> 0 | M16: =+TONTJUIL!H16+TONTJUIL!I16 -> 0 | Q16: =IF(R16=0,0,($C$36-R16)) -> 0 | S16: =IF(R16=0,0,(R16-75000)) -> 0
A17: AS201626 | B17: =VLOOKUP(A17,[6]LISTADHERENT!A$5:H$60,3,0) -> NGUIEMEGNI MATHIEU BLAISE | C17: =IF(E17="ECHEC",0,IF(E17="",0,75000))+75000 -> 150000 | D17: =IF(E17="ESPECES",0,0) -> 0 | E17: BANQUE | F17: =TONTJUIL!F17 -> 0 | H17: 100000 | I17: 2000 | J17: BANQUE | L17: =M17 -> 0 | M17: =+TONTJUIL!H17+TONTJUIL!I17 -> 0 | Q17: =IF(R17=0,0,($C$36-R17)) -> 0 | S17: =IF(R17=0,0,(R17-75000)) -> 0
A18: AS201626 | B18: =VLOOKUP(A18,[6]LISTADHERENT!A$5:H$60,3,0) -> NGUIEMEGNI MATHIEU BLAISE | D18: =IF(E18="ESPECES",0,0) -> 0 | F18: =TONTJUIL!F18 -> 0 | L18: =M18 -> 0 | M18: =+TONTJUIL!H18+TONTJUIL!I18 -> 0 | Q18: =IF(R18=0,0,($C$36-R18)) -> 0 | S18: =IF(R18=0,0,(R18-75000)) -> 0
A19: AS201628 | B19: =VLOOKUP(A19,[6]LISTADHERENT!A$5:H$60,3,0) -> NKAMGANG JUSTIN DEJOLIE | C19: =IF(E19="ECHEC",0,IF(E19="",0,75000)) -> 75000 | D19: =IF(E19="ESPECES",0,0) -> 0 | E19: ESPECES | F19: =TONTJUIL!F19 -> 0 | H19: 100000 | I19: 2000 | J19: BANQUE | L19: =M19 -> 51000 | M19: =+TONTJUIL!H19+TONTJUIL!I19 -> 51000 | N19: ESPECES | Q19: =IF(R19=0,0,($C$36-R19)) -> 0 | S19: =IF(R19=0,0,(R19-75000)) -> 0
A20: AS201633 | B20: =VLOOKUP(A20,[6]LISTADHERENT!A$5:H$60,3,0) -> PATEGO NJOSSU GUSTAVE | C20: =IF(E20="ECHEC",0,IF(E20="",0,75000)) -> 75000 | D20: =IF(E20="ESPECES",0,0) -> 0 | E20: BANQUE | F20: =TONTJUIL!F20 -> 0 | L20: =M20 -> 0 | M20: =+TONTJUIL!H20+TONTJUIL!I20 -> 0 | Q20: =IF(R20=0,0,($C$36-R20)) -> 0 | S20: =IF(R20=0,0,(R20-75000)) -> 0
A21: AS201638 | B21: =VLOOKUP(A21,[6]LISTADHERENT!A$5:H$60,3,0) -> SIMO PIERRE | C21: =IF(E21="ECHEC",0,IF(E21="",0,75000)) -> 75000 | D21: =IF(E21="ESPECES",0,0) -> 0 | E21: BANQUE | F21: =TONTJUIL!F21 -> 0 | L21: =M21 -> 0 | M21: =+TONTJUIL!H21+TONTJUIL!I21 -> 0 | Q21: =IF(R21=0,0,($C$36-R21)) -> 0 | S21: =IF(R21=0,0,(R21-75000)) -> 0
A22: AS201655 | B22: =VLOOKUP(A22,[6]LISTADHERENT!A$5:H$60,3,0) -> TCHEMHOU EMMANUEL | C22: =161000 -> 161000 | D22: =IF(E22="ESPECES",0,0) -> 0 | E22: ESPECES | F22: =TONTJUIL!F22 -> 0 | L22: =M22 -> 0 | M22: =+TONTJUIL!H21+TONTJUIL!I21 -> 0 | Q22: =IF(R22=0,0,($C$36-R22)) -> 0 | S22: =IF(R22=0,0,(R22-75000)) -> 0
A23: AS201647 | B23: =VLOOKUP(A23,[6]LISTADHERENT!A$5:H$60,3,0) -> YOUMBI EMMANUEL | C23: =IF(E23="ECHEC",0,IF(E23="",0,75000))+75000 -> 150000 | D23: =IF(E23="ESPECES",0,0) -> 0 | E23: BANQUE | F23: =TONTJUIL!F23 -> 0 | L23: =M23 -> 0 | M23: =+TONTJUIL!H23+TONTJUIL!I23 -> 0 | Q23: =IF(R23=0,0,($C$36-R23)) -> 0 | S23: =IF(R23=0,0,(R23-75000)) -> 0
A24: AS201647 | B24: =VLOOKUP(A24,[6]LISTADHERENT!A$5:H$60,3,0) -> YOUMBI EMMANUEL | D24: =IF(E24="ESPECES",0,0) -> 0 | F24: =TONTJUIL!F24 -> 0 | L24: =M24 -> 0 | M24: =+TONTJUIL!H24+TONTJUIL!I24 -> 0 | Q24: =IF(R24=0,0,($C$36-R24)) -> 0 | S24: =IF(R24=0,0,(R24-75000)) -> 0
A26: TOTAL | C26: =SUM(C6:C24) -> 1436000 | D26: =SUM(D6:D24) -> 0 | F26: =SUM(F6:F24) -> 106000 | H26: =SUM(H6:H24) -> 500000 | I26: =SUM(I6:I24) -> 10000 | K26: =SUM(K6:K24) -> 0 | L26: =SUM(L6:L24) -> 357000 | M26: =SUM(M6:M24) -> 357000 | O26: =SUM(O6:O24) -> 0 | P26: =SUM(P6:P24) -> 0 | Q26: =SUM(Q6:Q24) -> 1040000 | R26: =SUM(R6:R24) -> 160000 | S26: =SUM(S6:S24) -> 85000
C28: TONTINE | D28: REMBOURSEMENT PETIT LOT | E28: VENTE PETIT LOT | F28: VENTE LOT PRINCIPAL | G28: SOLDE EN CAISSE | I28: TONTINE + REMB + INTERET VENTE | J28: =C33+D33+R26 -> 1851000
I29: VENDUE | J29: =IF(J28>=2400000,1200000*2,1200000) -> 1200000
B30: ESPECES | C30: =SUMIFS(C6:C24,E6:E24,"ESPECES") -> 236000 | D30: =SUMIFS(L3:L21,N3:N21,"ESPECES")+SUMIFS(F3:F21,G3:G21,"ESPECES") -> 153000 | E30: =SUMIFS(H6:H24,J6:J24,"ESPECES") -> 300000 | F30: =SUMIFS(Q6:Q24,O6:O24,"ESPECES") -> 0 | G30: =C30+D30-E30-F30 -> 89000 | H30: =+G30+TONTJUIL!G33 -> 314000
B31: BANQUE | C31: =SUMIFS(C6:C24,E6:E24,"BANQUE") -> 1200000 | D31: =SUMIFS(M3:M21,N3:N21,"BANQUE")+SUMIFS(F3:F21,G3:G21,"BANQUE") -> 102000 | E31: =SUMIFS(H6:H24,J6:J24,"BANQUE") -> 200000 | F31: =SUMIFS(Q6:Q24,O6:O24,"BANQUE") -> 1040000 | G31: =C31+D31-E31-F31 -> 62000 | H31: =+G31+TONTJUIL!G34 -> -163000 | I31: PETIT LOT | J31: =J28-J29 -> 651000
B33: TOTAL | C33: =C30+C31 -> 1436000 | D33: =D30+D31 -> 255000 | E33: =E30+E31 -> 500000 | F33: =F30+F31 -> 1040000 | G33: =G30+G31 -> 151000 | H33: =H30+H31 -> 151000 | I33: RELIQUAT | J33: =J31-H26 -> 151000 | K33: =J33+TONTJUIL!K36 -> 151000 | L33: CUMUL
I35: ECHEC TONTINE | J35: =COUNTIFS(E6:E24,"ECHEC")*75000 -> 0 | K35: =J35+TONTJUIL!K38-75000 -> 0 | L35: CUMUL
B36: MONTANT TONTINE | C36: 1200000 | I36: ECHEC REMBOURSEMENT | J36: =SUMIFS(F6:F24,G6:G24,"ECHEC") -> 106000 | L36: CUMUL

Sheet TONTSEPT
A1: ASSOCIATION | B1: ASELBY
A2: ANNEE | B2: 2019/2020
A3: TONTINE | B3: 75000
C4: 44094
A5: MATRICULE | B5: NOM ET PRENOM | C5: MONTANT TONTINE | D5: PENALITE | E5: MODE VERSEMENT TONTINE | F5: REPORT ECHEC PETIT LOT | G5: MODE VERSEMENT VENTE PETIT LOT | H5: VENTE PETIT LOT | I5: INTERET PETIT LOT | J5: MODE VERSEMENT VENTE PETIT LOT | K5: NUMERO CHEQUE | L5: MONTANT REMBOURSE | M5: MONTANT A REMBOURSER | N5: MODE VERSEMENT REMBOURSEMENT | O5: MODE VERSEMENT TONTINE PRINCIPAL | P5: NUMERO CHEQUE | Q5: MONTANT TONTINE LOT PRINCIPAL | R5: INTERET LOT PRINCIPAL | S5: INTERET DU
A6: AS201602 | B6: =VLOOKUP(A6,[6]LISTADHERENT!A$5:H$60,3,0) -> BOUTCHOUANG WILLIAM | C6: =IF(E6="ECHEC",0,IF(E6="",0,75000)) -> 75000 | D6: =IF(E6="ESPECES",0,0) -> 0 | E6: BANQUE | F6: =TONTAOUT!F6 -> 0 | L6: =M6 -> 0 | M6: =+TONTAOUT!H6+TONTAOUT!I6 -> 0 | Q6: =IF(R6=0,0,($C$36-R6)) -> 0 | S6: =IF(R6=0,0,(R6-75000)) -> 0
A7: AS201603 | B7: =VLOOKUP(A7,[6]LISTADHERENT!A$5:H$60,3,0) -> CHINGUE FABRICE | C7: =IF(E7="ECHEC",0,IF(E7="",0,75000)) -> 0 | D7: =IF(E7="ESPECES",0,0) -> 0 | F7: =TONTAOUT!F7 -> 0 | L7: =M7 -> 0 | M7: =+TONTAOUT!H7+TONTAOUT!I7 -> 0 | Q7: =IF(R7=0,0,($C$36-R7)) -> 0 | S7: =IF(R7=0,0,(R7-75000)) -> 0
A8: AS201604 | B8: =VLOOKUP(A8,[6]LISTADHERENT!A$5:H$60,3,0) -> DJOMO JEAN PAUL | C8: =IF(E8="ECHEC",0,IF(E8="",0,75000)) -> 75000 | D8: =IF(E8="ESPECES",0,0) -> 0 | E8: BANQUE | F8: =TONTAOUT!F8 -> 0 | H8: 50000 | I8: 1000 | J8: BANQUE | L8: =M8 -> 102000 | M8: =+TONTAOUT!H8+TONTAOUT!I8 -> 102000 | N8: BANQUE | Q8: =IF(R8=0,0,($C$36-R8)) -> 0 | S8: =IF(R8=0,0,(R8-75000)) -> 0
A9: AS201605 | B9: =VLOOKUP(A9,[6]LISTADHERENT!A$5:H$60,3,0) -> DJOUKWE NANGUEN GUY BLAISE | C9: =IF(E9="ECHEC",0,IF(E9="",0,75000)) -> 75000 | D9: =IF(E9="ESPECES",0,0) -> 0 | E9: BANQUE | F9: =TONTAOUT!F9 -> 0 | H9: 150000 | I9: 3000 | J9: ESPECES | L9: =M9 -> 102000 | M9: =+TONTAOUT!H9+TONTAOUT!I9 -> 102000 | N9: BANQUE | Q9: =IF(R9=0,0,($C$36-R9)) -> 0 | S9: =IF(R9=0,0,(R9-75000)) -> 0
A10: AS201613 | B10: =VLOOKUP(A10,[6]LISTADHERENT!A$5:H$60,3,0) -> HOTCHO BENJAMIN | C10: =IF(E10="ECHEC",0,IF(E10="",0,75000)) -> 75000 | D10: =IF(E10="ESPECES",0,0) -> 0 | E10: BANQUE | F10: =TONTAOUT!F10 -> 0 | L10: =M10 -> 0 | M10: =+TONTAOUT!H10+TONTAOUT!I10 -> 0 | Q10: =IF(R10=0,0,($C$36-R10)) -> 0 | S10: =IF(R10=0,0,(R10-75000)) -> 0
A11: AS201611 | B11: =VLOOKUP(A11,[6]LISTADHERENT!A$5:H$60,3,0) -> HENGUE PAUL OMER | C11: =IF(E11="ECHEC",0,IF(E11="",0,75000)) -> 75000 | D11: =IF(E11="ESPECES",0,0) -> 0 | E11: BANQUE | F11: =TONTAOUT!F11 -> 0 | L11: =M11 -> 0 | M11: =+TONTAOUT!H11+TONTAOUT!I11 -> 0 | Q11: =IF(R11=0,0,($C$36-R11)) -> 0 | S11: =IF(R11=0,0,(R11-75000)) -> 0
A12: AS201619 | B12: =VLOOKUP(A12,[6]LISTADHERENT!A$5:H$60,3,0) -> KOUATCHO MESSACK | C12: =IF(E12="ECHEC",0,IF(E12="",0,75000)) -> 75000 | D12: =IF(E12="ESPECES",0,0) -> 0 | E12: BANQUE | F12: =TONTAOUT!F12 -> 106000 | G12: BANQUE | H12: 100000 | I12: 2000 | J12: BANQUE | L12: =M12 -> 0 | M12: =+TONTAOUT!H12+TONTAOUT!I12 -> 0 | Q12: =IF(R12=0,0,($C$36-R12)) -> 0 | S12: =IF(R12=0,0,(R12-75000)) -> 0
A13: AS201621 | B13: =VLOOKUP(A13,[6]LISTADHERENT!A$5:H$60,3,0) -> NANKAM APPOLINAIRE | C13: =IF(E13="ECHEC",0,IF(E13="",0,75000)) -> 75000 | D13: =IF(E13="ESPECES",0,0) -> 0 | E13: BANQUE | F13: =TONTAOUT!F13 -> 0 | L13: =M13 -> 0 | M13: =+TONTAOUT!H13+TONTAOUT!I13 -> 0 | Q13: =IF(R13=0,0,($C$36-R13)) -> 0 | S13: =IF(R13=0,0,(R13-75000)) -> 0
A14: AS201649 | B14: =VLOOKUP(A14,[6]LISTADHERENT!A$5:H$60,3,0) -> MBOGNING TUGMA GUY | C14: =IF(E14="ECHEC",0,IF(E14="",0,75000))+150000 -> 225000 | D14: =IF(E14="ESPECES",0,0) -> 0 | E14: BANQUE | F14: =TONTAOUT!F14 -> 0 | H14: 100000 | I14: 2000 | J14: BANQUE | L14: =M14 -> 102000 | M14: =+TONTAOUT!H14+TONTAOUT!I14 -> 102000 | N14: BANQUE | Q14: =IF(R14=0,0,($C$36-R14)) -> 0 | S14: =IF(R14=0,0,(R14-75000)) -> 0
A15: AS201649 | B15: =VLOOKUP(A15,[6]LISTADHERENT!A$5:H$60,3,0) -> MBOGNING TUGMA GUY | D15: =IF(E15="ESPECES",0,0) -> 0 | F15: =TONTAOUT!F15 -> 0 | L15: =M15 -> 0 | M15: =+TONTAOUT!H15+TONTAOUT!I15 -> 0 | Q15: =IF(R15=0,0,($C$36-R15)) -> 0 | S15: =IF(R15=0,0,(R15-75000)) -> 0
A16: AS201649 | B16: =VLOOKUP(A16,[6]LISTADHERENT!A$5:H$60,3,0) -> MBOGNING TUGMA GUY | D16: =IF(E16="ESPECES",0,0) -> 0 | F16: =TONTAOUT!F16 -> 0 | L16: =M16 -> 0 | M16: =+TONTAOUT!H16+TONTAOUT!I16 -> 0 | Q16: =IF(R16=0,0,($C$36-R16)) -> 0 | S16: =IF(R16=0,0,(R16-75000)) -> 0
A17: AS201626 | B17: =VLOOKUP(A17,[6]LISTADHERENT!A$5:H$60,3,0) -> NGUIEMEGNI MATHIEU BLAISE | C17: =IF(E17="ECHEC",0,IF(E17="",0,75000))+75000 -> 150000 | D17: =IF(E17="ESPECES",0,0) -> 0 | E17: BANQUE | F17: 106000 | G17: ECHEC | L17: =M17 -> 102000 | M17: =+TONTAOUT!H17+TONTAOUT!I17 -> 102000 | N17: ECHEC | Q17: =IF(R17=0,0,($C$36-R17)) -> 0 | S17: =IF(R17=0,0,(R17-75000)) -> 0
A18: AS201626 | B18: =VLOOKUP(A18,[6]LISTADHERENT!A$5:H$60,3,0) -> NGUIEMEGNI MATHIEU BLAISE | D18: =IF(E18="ESPECES",0,0) -> 0 | F18: =TONTAOUT!F18 -> 0 | L18: =M18 -> 0 | M18: =+TONTAOUT!H18+TONTAOUT!I18 -> 0 | Q18: =IF(R18=0,0,($C$36-R18)) -> 0 | S18: =IF(R18=0,0,(R18-75000)) -> 0
A19: AS201628 | B19: =VLOOKUP(A19,[6]LISTADHERENT!A$5:H$60,3,0) -> NKAMGANG JUSTIN DEJOLIE | C19: =IF(E19="ECHEC",0,IF(E19="",0,75000)) -> 75000 | D19: =IF(E19="ESPECES",0,0) -> 0 | E19: ESPECES | F19: =TONTAOUT!F19 -> 0 | H19: 100000 | I19: 2000 | J19: BANQUE | L19: =M19 -> 102000 | M19: =+TONTAOUT!H19+TONTAOUT!I19 -> 102000 | N19: ESPECES | O19: BANQUE | Q19: =IF(R19=0,0,($C$36-R19)) -> 1115000 | R19: 85000 | S19: =IF(R19=0,0,(R19-75000)) -> 10000
A20: AS201633 | B20: =VLOOKUP(A20,[6]LISTADHERENT!A$5:H$60,3,0) -> PATEGO NJOSSU GUSTAVE | C20: =IF(E20="ECHEC",0,IF(E20="",0,75000)) -> 75000 | D20: =IF(E20="ESPECES",0,0) -> 0 | E20: BANQUE | F20: =TONTAOUT!F20 -> 0 | L20: =M20 -> 0 | M20: =+TONTAOUT!H20+TONTAOUT!I20 -> 0 | Q20: =IF(R20=0,0,($C$36-R20)) -> 0 | S20: =IF(R20=0,0,(R20-75000)) -> 0
A21: AS201638 | B21: =VLOOKUP(A21,[6]LISTADHERENT!A$5:H$60,3,0) -> SIMO PIERRE | C21: =IF(E21="ECHEC",0,IF(E21="",0,75000)) -> 75000 | D21: =IF(E21="ESPECES",0,0) -> 0 | E21: BANQUE | F21: =TONTAOUT!F21 -> 0 | L21: =M21 -> 0 | M21: =+TONTAOUT!H21+TONTAOUT!I21 -> 0 | Q21: =IF(R21=0,0,($C$36-R21)) -> 0 | S21: =IF(R21=0,0,(R21-75000)) -> 0
A22: AS201655 | B22: =VLOOKUP(A22,[6]LISTADHERENT!A$5:H$60,3,0) -> TCHEMHOU EMMANUEL | C22: =IF(E22="ECHEC",0,IF(E22="",0,75000)) -> 75000 | D22: =IF(E22="ESPECES",0,0) -> 0 | E22: BANQUE | F22: =TONTAOUT!F22 -> 0 | L22: =M22 -> 0 | M22: =+TONTAOUT!H22+TONTAOUT!I22 -> 0 | Q22: =IF(R22=0,0,($C$36-R22)) -> 0 | S22: =IF(R22=0,0,(R22-75000)) -> 0
A23: AS201647 | B23: =VLOOKUP(A23,[6]LISTADHERENT!A$5:H$60,3,0) -> YOUMBI EMMANUEL | C23: =IF(E23="ECHEC",0,IF(E23="",0,75000))+75000 -> 150000 | D23: =IF(E23="ESPECES",0,0) -> 0 | E23: BANQUE | F23: =TONTAOUT!F23 -> 0 | L23: =M23 -> 0 | M23: =+TONTAOUT!H23+TONTAOUT!I23 -> 0 | Q23: =IF(R23=0,0,($C$36-R23)) -> 0 | S23: =IF(R23=0,0,(R23-75000)) -> 0
A24: AS201647 | B24: =VLOOKUP(A24,[6]LISTADHERENT!A$5:H$60,3,0) -> YOUMBI EMMANUEL | D24: =IF(E24="ESPECES",0,0) -> 0 | F24: =TONTAOUT!F24 -> 0 | L24: =M24 -> 0 | M24: =+TONTAOUT!H24+TONTAOUT!I24 -> 0 | Q24: =IF(R24=0,0,($C$36-R24)) -> 0 | S24: =IF(R24=0,0,(R24-75000)) -> 0
A26: TOTAL | C26: =SUM(C6:C24) -> 1350000 | D26: =SUM(D6:D24) -> 0 | F26: =SUM(F6:F24) -> 212000 | H26: =SUM(H6:H24) -> 500000 | I26: =SUM(I6:I24) -> 10000 | K26: =SUM(K6:K24) -> 0 | L26: =SUM(L6:L24) -> 510000 | M26: =SUM(M6:M24) -> 510000 | O26: =SUM(O6:O24) -> 0 | P26: =SUM(P6:P24) -> 0 | Q26: =SUM(Q6:Q24) -> 1115000 | R26: =SUM(R6:R24) -> 85000 | S26: =SUM(S6:S24) -> 10000
C28: TONTINE | D28: REMBOURSEMENT PETIT LOT | E28: VENTE PETIT LOT | F28: VENTE LOT PRINCIPAL | G28: SOLDE EN CAISSE | I28: TONTINE + REMB + INTERET VENTE | J28: =C33+D33+R26 -> 1949000
I29: VENDUE | J29: =IF(J28>=2400000,1200000*2,1200000) -> 1200000
B30: ESPECES | C30: =SUMIFS(C6:C24,E6:E24,"ESPECES") -> 75000 | D30: =SUMIFS(L3:L21,N3:N21,"ESPECES")+SUMIFS(F3:F21,G3:G21,"ESPECES") -> 102000 | E30: =SUMIFS(H6:H24,J6:J24,"ESPECES") -> 150000 | F30: =SUMIFS(Q6:Q24,O6:O24,"ESPECES") -> 0 | G30: =C30+D30-E30-F30 -> 27000 | H30: =G30+TONTAOUT!H30 -> 341000
B31: BANQUE | C31: =SUMIFS(C6:C24,E6:E24,"BANQUE") -> 1275000 | D31: =SUMIFS(M3:M21,N3:N21,"BANQUE")+SUMIFS(F3:F21,G3:G21,"BANQUE") -> 412000 | E31: =SUMIFS(H6:H24,J6:J24,"BANQUE") -> 350000 | F31: =SUMIFS(Q6:Q24,O6:O24,"BANQUE") -> 1115000 | G31: =C31+D31-E31-F31 -> 222000 | H31: =G31+TONTAOUT!H31 -> 59000 | I31: PETIT LOT | J31: =J28-J29 -> 749000
B33: TOTAL | C33: =C30+C31 -> 1350000 | D33: =D30+D31 -> 514000 | E33: =E30+E31 -> 500000 | F33: =F30+F31 -> 1115000 | G33: =G30+G31 -> 249000 | H33: =H30+H31 -> 400000 | I33: RELIQUAT | J33: =J31-H26 -> 249000 | K33: =J33+TONTAOUT!K33 -> 400000 | L33: CUMUL
I35: ECHEC TONTINE | J35: =COUNTIFS(E3:E21,"ECHEC")*75000 -> 0 | K35: =J35+TONTAOUT!K35 -> 0 | L35: CUMUL
B36: MONTANT TONTINE | C36: 1200000 | I36: ECHEC REMBOURSEMENT | J36: =SUMIFS(F3:F21,G3:G21,"ECHEC") -> 106000 | L36: CUMUL

Sheet TONTOCT
A1: ASSOCIATION | B1: ASELBY
A2: ANNEE | B2: 2019/2020
A3: TONTINE | B3: 75000
C4: 44122
A5: MATRICULE | B5: NOM ET PRENOM | C5: MONTANT TONTINE | D5: PENALITE | E5: MODE VERSEMENT TONTINE | F5: REPORT ECHEC PETIT LOT | G5: MODE VERSEMENT VENTE PETIT LOT | H5: VENTE PETIT LOT | I5: INTERET PETIT LOT | J5: MODE VERSEMENT VENTE PETIT LOT | K5: NUMERO CHEQUE | L5: MONTANT REMBOURSE | M5: MONTANT A REMBOURSER | N5: MODE VERSEMENT REMBOURSEMENT | O5: MODE VERSEMENT TONTINE PRINCIPAL | P5: NUMERO CHEQUE | Q5: MONTANT TONTINE LOT PRINCIPAL | R5: INTERET LOT PRINCIPAL | S5: INTERET DU
A6: AS201602 | B6: =VLOOKUP(A6,[6]LISTADHERENT!A$5:H$60,3,0) -> BOUTCHOUANG WILLIAM | C6: =IF(E6="ECHEC",0,IF(E6="",0,75000)) -> 75000 | D6: =IF(E6="ESPECES",0,0) -> 0 | E6: BANQUE | F6: =TONTSEPT!F6 -> 0 | L6: =M6 -> 0 | M6: =TONTSEPT!H6+TONTSEPT!I6 -> 0 | Q6: =IF(R6=0,0,($C$36-R6)) -> 0 | S6: =IF(R6=0,0,(R6-75000)) -> 0
A7: AS201603 | B7: =VLOOKUP(A7,[6]LISTADHERENT!A$5:H$60,3,0) -> CHINGUE FABRICE | C7: =IF(E7="ECHEC",0,IF(E7="",0,75000)) -> 0 | D7: =IF(E7="ESPECES",0,0) -> 0 | F7: =TONTSEPT!F7 -> 0 | L7: =M7 -> 0 | M7: =TONTSEPT!H7+TONTSEPT!I7 -> 0 | Q7: =IF(R7=0,0,($C$36-R7)) -> 0 | S7: =IF(R7=0,0,(R7-75000)) -> 0
A8: AS201604 | B8: =VLOOKUP(A8,[6]LISTADHERENT!A$5:H$60,3,0) -> DJOMO JEAN PAUL | C8: =IF(E8="ECHEC",0,IF(E8="",0,75000)) -> 75000 | D8: =IF(E8="ESPECES",0,0) -> 0 | E8: BANQUE | F8: =TONTSEPT!F8 -> 0 | H8: 66500 | I8: 4500 | L8: =M8 -> 51000 | M8: =TONTSEPT!H8+TONTSEPT!I8 -> 51000 | N8: BANQUE | Q8: =IF(R8=0,0,($C$36-R8)) -> 0 | S8: =IF(R8=0,0,(R8-75000)) -> 0
A9: AS201605 | B9: =VLOOKUP(A9,[6]LISTADHERENT!A$5:H$60,3,0) -> DJOUKWE NANGUEN GUY BLAISE | C9: =IF(E9="ECHEC",0,IF(E9="",0,75000)) -> 75000 | D9: =IF(E9="ESPECES",0,0) -> 0 | E9: BANQUE | F9: =TONTSEPT!F9 -> 0 | L9: =M9 -> 153000 | M9: =TONTSEPT!H9+TONTSEPT!I9 -> 153000 | N9: BANQUE | Q9: =IF(R9=0,0,($C$36-R9)) -> 0 | S9: =IF(R9=0,0,(R9-75000)) -> 0
A10: AS201613 | B10: =VLOOKUP(A10,[6]LISTADHERENT!A$5:H$60,3,0) -> HOTCHO BENJAMIN | C10: =IF(E10="ECHEC",0,IF(E10="",0,75000)) -> 75000 | D10: =IF(E10="ESPECES",0,0) -> 0 | E10: BANQUE | F10: =TONTSEPT!F10 -> 0 | L10: =M10 -> 0 | M10: =TONTSEPT!H10+TONTSEPT!I10 -> 0 | O10: BANQUE | Q10: =IF(R10=0,0,($C$36-R10)) -> 1125000 | R10: 75000 | S10: =IF(R10=0,0,(R10-75000)) -> 0
A11: AS201611 | B11: =VLOOKUP(A11,[6]LISTADHERENT!A$5:H$60,3,0) -> HENGUE PAUL OMER | C11: =IF(E11="ECHEC",0,IF(E11="",0,75000)) -> 75000 | D11: =IF(E11="ESPECES",0,0) -> 0 | E11: BANQUE | F11: =TONTSEPT!F11 -> 0 | L11: =M11 -> 0 | M11: =TONTSEPT!H11+TONTSEPT!I11 -> 0 | Q11: =IF(R11=0,0,($C$36-R11)) -> 0 | S11: =IF(R11=0,0,(R11-75000)) -> 0
A12: AS201619 | B12: =VLOOKUP(A12,[6]LISTADHERENT!A$5:H$60,3,0) -> KOUATCHO MESSACK | C12: =IF(E12="ECHEC",0,IF(E12="",0,75000)) -> 75000 | D12: =IF(E12="ESPECES",0,0) -> 0 | E12: BANQUE | H12: 50000 | I12: 1500 | L12: =M12 -> 102000 | M12: =TONTSEPT!H12+TONTSEPT!I12 -> 102000 | N12: BANQUE | Q12: =IF(R12=0,0,($C$36-R12)) -> 0 | S12: =IF(R12=0,0,(R12-75000)) -> 0
A13: AS201621 | B13: =VLOOKUP(A13,[6]LISTADHERENT!A$5:H$60,3,0) -> NANKAM APPOLINAIRE | C13: =IF(E13="ECHEC",0,IF(E13="",0,75000)) -> 75000 | D13: =IF(E13="ESPECES",0,0) -> 0 | E13: BANQUE | F13: =TONTSEPT!F13 -> 0 | L13: =M13 -> 0 | M13: =TONTSEPT!H13+TONTSEPT!I13 -> 0 | Q13: =IF(R13=0,0,($C$36-R13)) -> 0 | S13: =IF(R13=0,0,(R13-75000)) -> 0
A14: AS201649 | B14: =VLOOKUP(A14,[6]LISTADHERENT!A$5:H$60,3,0) -> MBOGNING TUGMA GUY | C14: =IF(E14="ECHEC",0,IF(E14="",0,75000))+150000 -> 225000 | D14: =IF(E14="ESPECES",0,0) -> 0 | E14: BANQUE | F14: =TONTSEPT!F14 -> 0 | L14: =M14 -> 102000 | M14: =TONTSEPT!H14+TONTSEPT!I14 -> 102000 | N14: BANQUE | Q14: =IF(R14=0,0,($C$36-R14)) -> 0 | S14: =IF(R14=0,0,(R14-75000)) -> 0
A15: AS201649 | B15: =VLOOKUP(A15,[6]LISTADHERENT!A$5:H$60,3,0) -> MBOGNING TUGMA GUY | D15: =IF(E15="ESPECES",0,0) -> 0 | F15: =TONTSEPT!F15 -> 0 | L15: =M15 -> 0 | M15: =TONTSEPT!H15+TONTSEPT!I15 -> 0 | Q15: =IF(R15=0,0,($C$36-R15)) -> 0 | S15: =IF(R15=0,0,(R15-75000)) -> 0
A16: AS201649 | B16: =VLOOKUP(A16,[6]LISTADHERENT!A$5:H$60,3,0) -> MBOGNING TUGMA GUY | D16: =IF(E16="ESPECES",0,0) -> 0 | F16: =TONTSEPT!F16 -> 0 | L16: =M16 -> 0 | M16: =TONTSEPT!H16+TONTSEPT!I16 -> 0 | Q16: =IF(R16=0,0,($C$36-R16)) -> 0 | S16: =IF(R16=0,0,(R16-75000)) -> 0
A17: AS201626 | B17: =VLOOKUP(A17,[6]LISTADHERENT!A$5:H$60,3,0) -> NGUIEMEGNI MATHIEU BLAISE | C17: =IF(E17="ECHEC",0,IF(E17="",0,75000))+75000 -> 150000 | D17: =IF(E17="ESPECES",0,0) -> 0 | E17: BANQUE | F17: =TONTSEPT!F17 -> 106000 | G17: BANQUE | L17: =M17 -> 0 | M17: =TONTSEPT!H17+TONTSEPT!I17 -> 0 | N17: BANQUE | Q17: =IF(R17=0,0,($C$36-R17)) -> 0 | S17: =IF(R17=0,0,(R17-75000)) -> 0
A18: AS201626 | B18: =VLOOKUP(A18,[6]LISTADHERENT!A$5:H$60,3,0) -> NGUIEMEGNI MATHIEU BLAISE | D18: =IF(E18="ESPECES",0,0) -> 0 | F18: =TONTSEPT!F18 -> 0 | L18: =M18 -> 0 | M18: =TONTSEPT!H18+TONTSEPT!I18 -> 0 | Q18: =IF(R18=0,0,($C$36-R18)) -> 0 | S18: =IF(R18=0,0,(R18-75000)) -> 0
A19: AS201628 | B19: =VLOOKUP(A19,[6]LISTADHERENT!A$5:H$60,3,0) -> NKAMGANG JUSTIN DEJOLIE | C19: =IF(E19="ECHEC",0,IF(E19="",0,75000)) -> 75000 | D19: =IF(E19="ESPECES",0,0) -> 0 | E19: ESPECES | F19: =TONTSEPT!F19 -> 0 | L19: =M19 -> 102000 | M19: =TONTSEPT!H19+TONTSEPT!I19 -> 102000 | N19: ESPECES | Q19: =IF(R19=0,0,($C$36-R19)) -> 0 | S19: =IF(R19=0,0,(R19-75000)) -> 0
A20: AS201633 | B20: =VLOOKUP(A20,[6]LISTADHERENT!A$5:H$60,3,0) -> PATEGO NJOSSU GUSTAVE | C20: =IF(E20="ECHEC",0,IF(E20="",0,75000)) -> 75000 | D20: =IF(E20="ESPECES",0,0) -> 0 | E20: BANQUE | F20: =TONTSEPT!F20 -> 0 | L20: =M20 -> 0 | M20: =TONTSEPT!H20+TONTSEPT!I20 -> 0 | Q20: =IF(R20=0,0,($C$36-R20)) -> 0 | S20: =IF(R20=0,0,(R20-75000)) -> 0
A21: AS201638 | B21: =VLOOKUP(A21,[6]LISTADHERENT!A$5:H$60,3,0) -> SIMO PIERRE | C21: =IF(E21="ECHEC",0,IF(E21="",0,75000)) -> 75000 | D21: =IF(E21="ESPECES",0,0) -> 0 | E21: BANQUE | F21: =TONTSEPT!F21 -> 0 | L21: =M21 -> 0 | M21: =TONTSEPT!H21+TONTSEPT!I21 -> 0 | Q21: =IF(R21=0,0,($C$36-R21)) -> 0 | S21: =IF(R21=0,0,(R21-75000)) -> 0
A22: AS201655 | B22: =VLOOKUP(A22,[6]LISTADHERENT!A$5:H$60,3,0) -> TCHEMHOU EMMANUEL | C22: =IF(E22="ECHEC",0,IF(E22="",0,75000)) -> 75000 | D22: =IF(E22="ESPECES",0,0) -> 0 | E22: BANQUE | F22: =TONTSEPT!F22 -> 0 | L22: =M22 -> 0 | M22: =TONTSEPT!H22+TONTSEPT!I22 -> 0 | Q22: =IF(R22=0,0,($C$36-R22)) -> 0 | S22: =IF(R22=0,0,(R22-75000)) -> 0
A23: AS201647 | B23: =VLOOKUP(A23,[6]LISTADHERENT!A$5:H$60,3,0) -> YOUMBI EMMANUEL | C23: =IF(E23="ECHEC",0,IF(E23="",0,75000))+75000 -> 150000 | D23: =IF(E23="ESPECES",0,0) -> 0 | E23: BANQUE | F23: =TONTSEPT!F23 -> 0 | L23: =M23 -> 0 | M23: =TONTSEPT!H23+TONTSEPT!I23 -> 0 | O23: BANQUE | Q23: =IF(R23=0,0,($C$36-R23)) -> 1125000 | R23: 75000 | S23: =IF(R23=0,0,(R23-75000)) -> 0
A24: AS201647 | B24: =VLOOKUP(A24,[6]LISTADHERENT!A$5:H$60,3,0) -> YOUMBI EMMANUEL | D24: =IF(E24="ESPECES",0,0) -> 0 | F24: =TONTSEPT!F24 -> 0 | L24: =M24 -> 0 | M24: =TONTSEPT!H24+TONTSEPT!I24 -> 0 | Q24: =IF(R24=0,0,($C$36-R24)) -> 0 | S24: =IF(R24=0,0,(R24-75000)) -> 0
A26: TOTAL | C26: =SUM(C6:C24) -> 1350000 | D26: =SUM(D6:D24) -> 0 | F26: =SUM(F6:F24) -> 106000 | H26: =SUM(H6:H24) -> 116500 | I26: =SUM(I6:I24) -> 6000 | K26: =SUM(K6:K24) -> 0 | L26: =SUM(L6:L24) -> 510000 | M26: =SUM(M6:M24) -> 510000 | O26: =SUM(O6:O24) -> 0 | P26: =SUM(P6:P24) -> 0 | Q26: =SUM(Q6:Q24) -> 2250000 | R26: =SUM(R6:R24) -> 150000 | S26: =SUM(S6:S24) -> 0
C28: TONTINE | D28: REMBOURSEMENT PETIT LOT | E28: VENTE PETIT LOT | F28: VENTE LOT PRINCIPAL | G28: SOLDE EN CAISSE | I28: TONTINE + REMB + INTERET VENTE | J28: =C33+D33+R26 -> 2116000
I29: VENDUE | J29: =IF(J28>=2400000,1200000*2,1200000)+1200000 -> 2400000
B30: ESPECES | C30: =SUMIFS(C6:C24,E6:E24,"ESPECES") -> 75000 | D30: =SUMIFS(L3:L21,N3:N21,"ESPECES")+SUMIFS(F3:F21,G3:G21,"ESPECES") -> 102000 | E30: =SUMIFS(H6:H24,J6:J24,"ESPECES") -> 0 | F30: =SUMIFS(Q6:Q24,O6:O24,"ESPECES") -> 0 | G30: =C30+D30-E30-F30 -> 177000
B31: BANQUE | C31: =SUMIFS(C6:C24,E6:E24,"BANQUE") -> 1275000 | D31: =SUMIFS(M3:M21,N3:N21,"BANQUE")+SUMIFS(F3:F21,G3:G21,"BANQUE") -> 514000 | E31: =SUMIFS(H6:H24,J6:J24,"BANQUE") -> 0 | F31: =SUMIFS(Q6:Q24,O6:O24,"BANQUE") -> 2250000 | G31: =C31+D31-E31-F31 -> -461000 | I31: PETIT LOT | J31: =J28-J29 -> -284000
B33: TOTAL | C33: =C30+C31 -> 1350000 | D33: =D30+D31 -> 616000 | E33: =E30+E31 -> 0 | F33: =F30+F31 -> 2250000 | G33: =G30+G31 -> -284000 | I33: RELIQUAT | J33: =J31-H26 -> -400500 | K33: =J33+TONTSEPT!K33 -> -500 | L33: CUMUL
I35: ECHEC TONTINE | J35: =COUNTIFS(E3:E21,"ECHEC")*75000 -> 0 | K35: =J35+TONTSEPT!K35 -> 0 | L35: CUMUL
B36: MONTANT TONTINE | C36: 1200000 | I36: ECHEC REMBOURSEMENT | J36: =SUMIFS(F3:F21,G3:G21,"ECHEC") -> 0 | L36: CUMUL

Sheet TONTNOV
A1: ASSOCIATION | B1: ASELBY
A2: ANNEE | B2: 2019/2020
A3: TONTINE | B3: 75000
C4: 44150
A5: MATRICULE | B5: NOM ET PRENOM | C5: MONTANT TONTINE | D5: PENALITE | E5: MODE VERSEMENT TONTINE | F5: REPORT ECHEC PETIT LOT | G5: MODE VERSEMENT VENTE PETIT LOT | H5: VENTE PETIT LOT | I5: INTERET PETIT LOT | J5: MODE VERSEMENT VENTE PETIT LOT | K5: NUMERO CHEQUE | L5: MONTANT REMBOURSE | M5: MONTANT A REMBOURSER | N5: MODE VERSEMENT REMBOURSEMENT | O5: MODE VERSEMENT TONTINE PRINCIPAL | P5: NUMERO CHEQUE | Q5: MONTANT TONTINE LOT PRINCIPAL | R5: INTERET LOT PRINCIPAL | S5: INTERET DU
A6: AS201602 | B6: =VLOOKUP(A6,[6]LISTADHERENT!A$5:H$60,3,0) -> BOUTCHOUANG WILLIAM | C6: =IF(E6="ECHEC",0,IF(E6="",0,75000)) -> 75000 | D6: =IF(E6="ESPECES",0,0) -> 0 | E6: =VLOOKUP(A6,[7]HISTONOV20!A$6:V$38,21,0) -> BANQUE | F6: =TONTOCT!F6 -> 0 | L6: =M6 -> 0 | M6: =+TONTOCT!H6+TONTOCT!I6 -> 0 | Q6: =IF(R6=0,0,($C$36-R6)) -> 0 | R6: =VLOOKUP(A6,[7]HISTONOV20!A$6:AI$38,19,0) -> 0 | S6: =IF(R6=0,0,(R6-75000)) -> 0
A7: AS201603 | B7: =VLOOKUP(A7,[6]LISTADHERENT!A$5:H$60,3,0) -> CHINGUE FABRICE | C7: =IF(E7="ECHEC",0,IF(E7="",0,75000)) -> 0 | D7: =IF(E7="ESPECES",0,0) -> 0 | F7: =TONTOCT!F7 -> 0 | L7: =M7 -> 0 | M7: =+TONTOCT!H7+TONTOCT!I7 -> 0 | Q7: =IF(R7=0,0,($C$36-R7)) -> 0 | S7: =IF(R7=0,0,(R7-75000)) -> 0
A8: AS201604 | B8: =VLOOKUP(A8,[6]LISTADHERENT!A$5:H$60,3,0) -> DJOMO JEAN PAUL | C8: =IF(E8="ECHEC",0,IF(E8="",0,75000)) -> 75000 | D8: =IF(E8="ESPECES",0,0) -> 0 | E8: =VLOOKUP(A8,[7]HISTONOV20!A$6:V$38,21,0) -> ESPECES | F8: =TONTOCT!F8 -> 0 | H8: 71000 | I8: 1500 | J8: ESPECES | L8: =M8 -> 71000 | M8: =+TONTOCT!H8+TONTOCT!I8 -> 71000 | N8: ESPECES | Q8: =IF(R8=0,0,($C$36-R8)) -> 0 | R8: =VLOOKUP(A8,[7]HISTONOV20!A$6:AI$38,19,0) -> 0 | S8: =IF(R8=0,0,(R8-75000)) -> 0
A9: AS201605 | B9: =VLOOKUP(A9,[6]LISTADHERENT!A$5:H$60,3,0) -> DJOUKWE NANGUEN GUY BLAISE | C9: =IF(E9="ECHEC",0,IF(E9="",0,75000)) -> 75000 | D9: =IF(E9="ESPECES",0,0) -> 0 | E9: =VLOOKUP(A9,[7]HISTONOV20!A$6:V$38,21,0) -> BANQUE | F9: =TONTOCT!F9 -> 0 | H9: 81500 | I9: 1500 | J9: BANQUE | L9: =M9 -> 0 | M9: =+TONTOCT!H9+TONTOCT!I9 -> 0 | Q9: =IF(R9=0,0,($C$36-R9)) -> 0 | R9: =VLOOKUP(A9,[7]HISTONOV20!A$6:AI$38,19,0) -> 0 | S9: =IF(R9=0,0,(R9-75000)) -> 0
A10: AS201613 | B10: =VLOOKUP(A10,[6]LISTADHERENT!A$5:H$60,3,0) -> HOTCHO BENJAMIN | C10: =IF(E10="ECHEC",0,IF(E10="",0,75000)) -> 75000 | D10: =IF(E10="ESPECES",0,0) -> 0 | E10: =VLOOKUP(A10,[7]HISTONOV20!A$6:V$38,21,0) -> BANQUE | F10: =TONTOCT!F10 -> 0 | L10: =M10 -> 0 | M10: =+TONTOCT!H10+TONTOCT!I10 -> 0 | Q10: =IF(R10=0,0,($C$36-R10)) -> 0 | R10: =VLOOKUP(A10,[7]HISTONOV20!A$6:AI$38,19,0) -> 0 | S10: =IF(R10=0,0,(R10-75000)) -> 0
A11: AS201611 | B11: =VLOOKUP(A11,[6]LISTADHERENT!A$5:H$60,3,0) -> HENGUE PAUL OMER | C11: =IF(E11="ECHEC",0,IF(E11="",0,75000)) -> 75000 | D11: =IF(E11="ESPECES",0,0) -> 0 | E11: =VLOOKUP(A11,[7]HISTONOV20!A$6:V$38,21,0) -> BANQUE | F11: =TONTOCT!F11 -> 0 | L11: =M11 -> 0 | M11: =+TONTOCT!H11+TONTOCT!I11 -> 0 | Q11: =IF(R11=0,0,($C$36-R11)) -> 0 | R11: =VLOOKUP(A11,[7]HISTONOV20!A$6:AI$38,19,0) -> 0 | S11: =IF(R11=0,0,(R11-75000)) -> 0
A12: AS201619 | B12: =VLOOKUP(A12,[6]LISTADHERENT!A$5:H$60,3,0) -> KOUATCHO MESSACK | C12: =IF(E12="ECHEC",0,IF(E12="",0,75000)) -> 75000 | D12: =IF(E12="ESPECES",0,0) -> 0 | E12: =VLOOKUP(A12,[7]HISTONOV20!A$6:V$38,21,0) -> BANQUE | F12: =TONTOCT!F12 -> 0 | H12: 100000 | I12: 2000 | J12: BANQUE | L12: =M12 -> 51500 | M12: =+TONTOCT!H12+TONTOCT!I12 -> 51500 | N12: BANQUE | Q12: =IF(R12=0,0,($C$36-R12)) -> 0 | R12: =VLOOKUP(A12,[7]HISTONOV20!A$6:AI$38,19,0) -> 0 | S12: =IF(R12=0,0,(R12-75000)) -> 0
A13: AS201621 | B13: =VLOOKUP(A13,[6]LISTADHERENT!A$5:H$60,3,0) -> NANKAM APPOLINAIRE | C13: =IF(E13="ECHEC",0,IF(E13="",0,75000)) -> 75000 | D13: =IF(E13="ESPECES",0,0) -> 0 | E13: =VLOOKUP(A13,[7]HISTONOV20!A$6:V$38,21,0) -> BANQUE | F13: =TONTOCT!F13 -> 0 | L13: =M13 -> 0 | M13: =+TONTOCT!H13+TONTOCT!I13 -> 0 | Q13: =IF(R13=0,0,($C$36-R13)) -> 0 | R13: =VLOOKUP(A13,[7]HISTONOV20!A$6:AI$38,19,0) -> 0 | S13: =IF(R13=0,0,(R13-75000)) -> 0
A14: AS201649 | B14: =VLOOKUP(A14,[6]LISTADHERENT!A$5:H$60,3,0) -> MBOGNING TUGMA GUY | C14: =IF(E14="ECHEC",0,IF(E14="",0,75000))+150000 -> 225000 | D14: =IF(E14="ESPECES",0,0) -> 0 | E14: =VLOOKUP(A14,[7]HISTONOV20!A$6:V$38,21,0) -> BANQUE | F14: =TONTOCT!F14 -> 0 | H14: 100000 | I14: 2000 | J14: BANQUE | L14: =M14 -> 0 | M14: =+TONTOCT!H14+TONTOCT!I14 -> 0 | Q14: =IF(R14=0,0,($C$36-R14)) -> 0 | R14: =VLOOKUP(A14,[7]HISTONOV20!A$6:AI$38,19,0) -> 0 | S14: =IF(R14=0,0,(R14-75000)) -> 0
A15: AS201649 | B15: =VLOOKUP(A15,[6]LISTADHERENT!A$5:H$60,3,0) -> MBOGNING TUGMA GUY | D15: =IF(E15="ESPECES",0,0) -> 0 | F15: =TONTOCT!F15 -> 0 | L15: =M15 -> 0 | M15: =+TONTOCT!H15+TONTOCT!I15 -> 0 | Q15: =IF(R15=0,0,($C$36-R15)) -> 0 | R15: =VLOOKUP(A15,[7]HISTONOV20!A$6:AI$38,19,0) -> 0 | S15: =IF(R15=0,0,(R15-75000)) -> 0
A16: AS201649 | B16: =VLOOKUP(A16,[6]LISTADHERENT!A$5:H$60,3,0) -> MBOGNING TUGMA GUY | D16: =IF(E16="ESPECES",0,0) -> 0 | F16: =TONTOCT!F16 -> 0 | L16: =M16 -> 0 | M16: =+TONTOCT!H16+TONTOCT!I16 -> 0 | Q16: =IF(R16=0,0,($C$36-R16)) -> 0 | R16: =VLOOKUP(A16,[7]HISTONOV20!A$6:AI$38,19,0) -> 0 | S16: =IF(R16=0,0,(R16-75000)) -> 0
A17: AS201626 | B17: =VLOOKUP(A17,[6]LISTADHERENT!A$5:H$60,3,0) -> NGUIEMEGNI MATHIEU BLAISE | C17: =IF(E17="ECHEC",0,IF(E17="",0,75000))+75000 -> 150000 | D17: =IF(E17="ESPECES",0,0) -> 0 | E17: =VLOOKUP(A17,[7]HISTONOV20!A$6:V$38,21,0) -> BANQUE | L17: =M17 -> 0 | M17: =+TONTOCT!H17+TONTOCT!I17 -> 0 | O17: BANQUE | Q17: =IF(R17=0,0,($C$36-R17)) -> 1020000 | R17: =VLOOKUP(A17,[7]HISTONOV20!A$6:AI$38,19,0) -> 180000 | S17: =IF(R17=0,0,(R17-75000)) -> 105000
A18: AS201626 | B18: =VLOOKUP(A18,[6]LISTADHERENT!A$5:H$60,3,0) -> NGUIEMEGNI MATHIEU BLAISE | D18: =IF(E18="ESPECES",0,0) -> 0 | F18: =TONTOCT!F18 -> 0 | L18: =M18 -> 0 | M18: =+TONTOCT!H18+TONTOCT!I18 -> 0 | Q18: =IF(R18=0,0,($C$36-R18)) -> 0 | S18: =IF(R18=0,0,(R18-75000)) -> 0
A19: AS201628 | B19: =VLOOKUP(A19,[6]LISTADHERENT!A$5:H$60,3,0) -> NKAMGANG JUSTIN DEJOLIE | C19: =IF(E19="ECHEC",0,IF(E19="",0,75000)) -> 75000 | D19: =IF(E19="ESPECES",0,0) -> 0 | E19: =VLOOKUP(A19,[7]HISTONOV20!A$6:V$38,21,0) -> ESPECES | F19: =TONTOCT!F19 -> 0 | H19: 100000 | I19: 2000 | J19: ESPECES | L19: =M19 -> 0 | M19: =+TONTOCT!H19+TONTOCT!I19 -> 0 | Q19: =IF(R19=0,0,($C$36-R19)) -> 0 | R19: =VLOOKUP(A19,[7]HISTONOV20!A$6:AI$38,19,0) -> 0 | S19: =IF(R19=0,0,(R19-75000)) -> 0
A20: AS201633 | B20: =VLOOKUP(A20,[6]LISTADHERENT!A$5:H$60,3,0) -> PATEGO NJOSSU GUSTAVE | C20: =IF(E20="ECHEC",0,IF(E20="",0,75000)) -> 75000 | D20: =IF(E20="ESPECES",0,0) -> 0 | E20: =VLOOKUP(A20,[7]HISTONOV20!A$6:V$38,21,0) -> BANQUE | F20: =TONTOCT!F20 -> 0 | L20: =M20 -> 0 | M20: =+TONTOCT!H20+TONTOCT!I20 -> 0 | Q20: =IF(R20=0,0,($C$36-R20)) -> 0 | R20: =VLOOKUP(A20,[7]HISTONOV20!A$6:AI$38,19,0) -> 0 | S20: =IF(R20=0,0,(R20-75000)) -> 0
A21: AS201638 | B21: =VLOOKUP(A21,[6]LISTADHERENT!A$5:H$60,3,0) -> SIMO PIERRE | C21: =IF(E21="ECHEC",0,IF(E21="",0,75000)) -> 75000 | D21: =IF(E21="ESPECES",0,0) -> 0 | E21: =VLOOKUP(A21,[7]HISTONOV20!A$6:V$38,21,0) -> BANQUE | F21: =TONTOCT!F21 -> 0 | L21: =M21 -> 0 | M21: =+TONTOCT!H21+TONTOCT!I21 -> 0 | Q21: =IF(R21=0,0,($C$36-R21)) -> 0 | R21: =VLOOKUP(A21,[7]HISTONOV20!A$6:AI$38,19,0) -> 0 | S21: =IF(R21=0,0,(R21-75000)) -> 0
A22: AS201655 | B22: =VLOOKUP(A22,[6]LISTADHERENT!A$5:H$60,3,0) -> TCHEMHOU EMMANUEL | C22: =IF(E22="ECHEC",0,IF(E22="",0,75000)) -> 75000 | D22: =IF(E22="ESPECES",0,0) -> 0 | E22: =VLOOKUP(A22,[7]HISTONOV20!A$6:V$38,21,0) -> BANQUE | F22: =TONTOCT!F22 -> 0 | L22: =M22 -> 0 | M22: =+TONTOCT!H22+TONTOCT!I22 -> 0 | Q22: =IF(R22=0,0,($C$36-R22)) -> 0 | R22: =VLOOKUP(A22,[7]HISTONOV20!A$6:AI$38,19,0) -> 0 | S22: =IF(R22=0,0,(R22-75000)) -> 0
A23: AS201647 | B23: =VLOOKUP(A23,[6]LISTADHERENT!A$5:H$60,3,0) -> YOUMBI EMMANUEL | C23: =IF(E23="ECHEC",0,IF(E23="",0,75000))+75000 -> 150000 | D23: =IF(E23="ESPECES",0,0) -> 0 | E23: =VLOOKUP(A23,[7]HISTONOV20!A$6:V$38,21,0) -> BANQUE | F23: =TONTOCT!F23 -> 0 | L23: =M23 -> 0 | M23: =+TONTOCT!H23+TONTOCT!I23 -> 0 | Q23: =IF(R23=0,0,($C$36-R23)) -> 0 | R23: =VLOOKUP(A23,[7]HISTONOV20!A$6:AI$38,19,0) -> 0 | S23: =IF(R23=0,0,(R23-75000)) -> 0
A24: AS201647 | B24: =VLOOKUP(A24,[6]LISTADHERENT!A$5:H$60,3,0) -> YOUMBI EMMANUEL | D24: =IF(E24="ESPECES",0,0) -> 0 | F24: =TONTOCT!F24 -> 0 | L24: =M24 -> 0 | M24: =+TONTOCT!H24+TONTOCT!I24 -> 0 | Q24: =IF(R24=0,0,($C$36-R24)) -> 0 | R24: =VLOOKUP(A24,[7]HISTONOV20!A$6:AI$38,19,0) -> 0 | S24: =IF(R24=0,0,(R24-75000)) -> 0
A26: TOTAL | C26: =SUM(C6:C24) -> 1350000 | D26: =SUM(D6:D24) -> 0 | F26: =SUM(F6:F24) -> 0 | H26: =SUM(H6:H24) -> 452500 | I26: =SUM(I6:I24) -> 9000 | K26: =SUM(K6:K24) -> 0 | L26: =SUM(L6:L24) -> 122500 | M26: =SUM(M6:M24) -> 122500 | O26: =SUM(O6:O24) -> 0 | P26: =SUM(P6:P24) -> 0 | Q26: =SUM(Q6:Q24) -> 1020000 | R26: =SUM(R6:R24) -> 180000 | S26: =SUM(S6:S24) -> 105000
C28: TONTINE | D28: REMBOURSEMENT PETIT LOT | E28: VENTE PETIT LOT | F28: VENTE LOT PRINCIPAL | G28: SOLDE EN CAISSE | I28: TONTINE + REMB + INTERET VENTE | J28: =C33+D33+R26 -> 1652500
I29: VENDUE | J29: =IF(J28>=2400000,1200000*2,1200000) -> 1200000
B30: ESPECES | C30: =SUMIFS(C6:C24,E6:E24,"ESPECES") -> 150000 | D30: =SUMIFS(L3:L21,N3:N21,"ESPECES")+SUMIFS(F3:F21,G3:G21,"ESPECES") -> 71000 | E30: =SUMIFS(H6:H24,J6:J24,"ESPECES") -> 171000 | F30: =SUMIFS(Q6:Q24,O6:O24,"ESPECES") -> 0 | G30: =C30+D30-E30-F30 -> 50000
B31: BANQUE | C31: =SUMIFS(C6:C24,E6:E24,"BANQUE") -> 1200000 | D31: =SUMIFS(M3:M21,N3:N21,"BANQUE")+SUMIFS(F3:F21,G3:G21,"BANQUE") -> 51500 | E31: =SUMIFS(H6:H24,J6:J24,"BANQUE") -> 281500 | F31: =SUMIFS(Q6:Q24,O6:O24,"BANQUE") -> 1020000 | G31: =C31+D31-E31-F31 -> -50000 | I31: PETIT LOT | J31: =J28-J29 -> 452500
B33: TOTAL | C33: =C30+C31 -> 1350000 | D33: =D30+D31 -> 122500 | E33: =E30+E31 -> 452500 | F33: =F30+F31 -> 1020000 | G33: =G30+G31 -> 0 | I33: RELIQUAT | J33: =J31-H26 -> 0 | K33: =J33+TONTOCT!K33 -> -500 | L33: CUMUL
I35: ECHEC TONTINE | J35: =COUNTIFS(E3:E21,"ECHEC")*75000 -> 0 | K35: =J35+TONTOCT!K35 -> 0 | L35: CUMUL
B36: MONTANT TONTINE | C36: 1200000 | I36: ECHEC REMBOURSEMENT | J36: =SUMIFS(F3:F21,G3:G21,"ECHEC") -> 0 | L36: CUMUL

Sheet TONTDEC
A1: ASSOCIATION | B1: ASELBY
A2: ANNEE | B2: 2019/2020
A3: TONTINE | B3: 75000
C4: 44185
A5: MATRICULE | B5: NOM ET PRENOM | C5: MONTANT TONTINE | D5: PENALITE | E5: MODE VERSEMENT TONTINE | F5: REPORT ECHEC PETIT LOT | G5: MODE VERSEMENT VENTE PETIT LOT | H5: VENTE PETIT LOT | I5: INTERET PETIT LOT | J5: MODE VERSEMENT VENTE PETIT LOT | K5: NUMERO CHEQUE | L5: MONTANT REMBOURSE | M5: MONTANT A REMBOURSER | N5: MODE VERSEMENT REMBOURSEMENT | O5: MODE VERSEMENT TONTINE PRINCIPAL | P5: NUMERO CHEQUE | Q5: MONTANT TONTINE LOT PRINCIPAL | R5: INTERET LOT PRINCIPAL | S5: INTERET DU
A6: AS201602 | B6: =VLOOKUP(A6,[6]LISTADHERENT!A$5:H$60,3,0) -> BOUTCHOUANG WILLIAM | C6: =IF(E6="ECHEC",0,IF(E6="",0,75000)) -> 75000 | D6: =IF(E6="ESPECES",0,0) -> 0 | E6: =VLOOKUP(A6,[7]HISTODEC20!A$6:V$38,21,0) -> BANQUE | F6: =TONTOCT!F6 -> 0 | L6: =M6 -> 0 | M6: =+TONTNOV!H6+TONTNOV!I6 -> 0 | Q6: =IF(R6=0,0,($C$36-R6)) -> 0 | R6: =VLOOKUP(A6,[7]HISTODEC20!A$6:AI$38,19,0) -> 0 | S6: =IF(R6=0,0,(R6-75000)) -> 0
A7: AS201603 | B7: =VLOOKUP(A7,[6]LISTADHERENT!A$5:H$60,3,0) -> CHINGUE FABRICE | C7: =IF(E7="ECHEC",0,IF(E7="",0,75000)) -> 0 | D7: =IF(E7="ESPECES",0,0) -> 0 | F7: =TONTOCT!F7 -> 0 | L7: =M7 -> 0 | M7: =+TONTNOV!H7+TONTNOV!I7 -> 0 | Q7: =IF(R7=0,0,($C$36-R7)) -> 0 | S7: =IF(R7=0,0,(R7-75000)) -> 0
A8: AS201604 | B8: =VLOOKUP(A8,[6]LISTADHERENT!A$5:H$60,3,0) -> DJOMO JEAN PAUL | C8: =IF(E8="ECHEC",0,IF(E8="",0,75000)) -> 75000 | D8: =IF(E8="ESPECES",0,0) -> 0 | E8: =VLOOKUP(A8,[7]HISTODEC20!A$6:V$38,21,0) -> BANQUE | F8: =TONTOCT!F8 -> 0 | H8: 100000 | I8: 2000 | L8: =M8 -> 72500 | M8: =+TONTNOV!H8+TONTNOV!I8 -> 72500 | N8: BANQUE | Q8: =IF(R8=0,0,($C$36-R8)) -> 0 | R8: =VLOOKUP(A8,[7]HISTODEC20!A$6:AI$38,19,0) -> 0 | S8: =IF(R8=0,0,(R8-75000)) -> 0
A9: AS201605 | B9: =VLOOKUP(A9,[6]LISTADHERENT!A$5:H$60,3,0) -> DJOUKWE NANGUEN GUY BLAISE | C9: =IF(E9="ECHEC",0,IF(E9="",0,75000)) -> 75000 | D9: =IF(E9="ESPECES",0,0) -> 0 | E9: =VLOOKUP(A9,[7]HISTODEC20!A$6:V$38,21,0) -> BANQUE | F9: =TONTOCT!F9 -> 0 | H9: 200000 | I9: 4000 | L9: =M9 -> 83000 | M9: =+TONTNOV!H9+TONTNOV!I9 -> 83000 | N9: BANQUE | Q9: =IF(R9=0,0,($C$36-R9)) -> 0 | R9: =VLOOKUP(A9,[7]HISTODEC20!A$6:AI$38,19,0) -> 0 | S9: =IF(R9=0,0,(R9-75000)) -> 0
A10: AS201613 | B10: =VLOOKUP(A10,[6]LISTADHERENT!A$5:H$60,3,0) -> HOTCHO BENJAMIN | C10: =IF(E10="ECHEC",0,IF(E10="",0,75000)) -> 75000 | D10: =IF(E10="ESPECES",0,0) -> 0 | E10: =VLOOKUP(A10,[7]HISTODEC20!A$6:V$38,21,0) -> BANQUE | F10: =TONTOCT!F10 -> 0 | L10: =M10 -> 0 | M10: =+TONTNOV!H10+TONTNOV!I10 -> 0 | Q10: =IF(R10=0,0,($C$36-R10)) -> 0 | R10: =VLOOKUP(A10,[7]HISTODEC20!A$6:AI$38,19,0) -> 0 | S10: =IF(R10=0,0,(R10-75000)) -> 0
A11: AS201611 | B11: =VLOOKUP(A11,[6]LISTADHERENT!A$5:H$60,3,0) -> HENGUE PAUL OMER | C11: =IF(E11="ECHEC",0,IF(E11="",0,75000)) -> 75000 | D11: =IF(E11="ESPECES",0,0) -> 0 | E11: =VLOOKUP(A11,[7]HISTODEC20!A$6:V$38,21,0) -> BANQUE | F11: =TONTOCT!F11 -> 0 | L11: =M11 -> 0 | M11: =+TONTNOV!H11+TONTNOV!I11 -> 0 | Q11: =IF(R11=0,0,($C$36-R11)) -> 0 | R11: =VLOOKUP(A11,[7]HISTODEC20!A$6:AI$38,19,0) -> 0 | S11: =IF(R11=0,0,(R11-75000)) -> 0
A12: AS201619 | B12: =VLOOKUP(A12,[6]LISTADHERENT!A$5:H$60,3,0) -> KOUATCHO MESSACK | C12: =IF(E12="ECHEC",0,IF(E12="",0,75000)) -> 75000 | D12: =IF(E12="ESPECES",0,0) -> 0 | E12: =VLOOKUP(A12,[7]HISTODEC20!A$6:V$38,21,0) -> BANQUE | F12: =TONTOCT!F12 -> 0 | G12: ECHEC | H12: 200000 | I12: 2000 | L12: =M12 -> 102000 | M12: =+TONTNOV!H12+TONTNOV!I12 -> 102000 | N12: BANQUE | Q12: =IF(R12=0,0,($C$36-R12)) -> 0 | R12: =VLOOKUP(A12,[7]HISTODEC20!A$6:AI$38,19,0) -> 0 | S12: =IF(R12=0,0,(R12-75000)) -> 0
A13: AS201621 | B13: =VLOOKUP(A13,[6]LISTADHERENT!A$5:H$60,3,0) -> NANKAM APPOLINAIRE | C13: =IF(E13="ECHEC",0,IF(E13="",0,75000)) -> 75000 | D13: =IF(E13="ESPECES",0,0) -> 0 | E13: =VLOOKUP(A13,[7]HISTODEC20!A$6:V$38,21,0) -> BANQUE | F13: =TONTOCT!F13 -> 0 | L13: =M13 -> 0 | M13: =+TONTNOV!H13+TONTNOV!I13 -> 0 | Q13: =IF(R13=0,0,($C$36-R13)) -> 0 | R13: =VLOOKUP(A13,[7]HISTODEC20!A$6:AI$38,19,0) -> 0 | S13: =IF(R13=0,0,(R13-75000)) -> 0
A14: AS201649 | B14: =VLOOKUP(A14,[6]LISTADHERENT!A$5:H$60,3,0) -> MBOGNING TUGMA GUY | C14: =IF(E14="ECHEC",0,IF(E14="",0,75000))+150000 -> 225000 | D14: =IF(E14="ESPECES",0,0) -> 0 | E14: =VLOOKUP(A14,[7]HISTODEC20!A$6:V$38,21,0) -> BANQUE | F14: =TONTOCT!F14 -> 0 | H14: 111000 | I14: 2000 | L14: =M14 -> 102000 | M14: =+TONTNOV!H14+TONTNOV!I14 -> 102000 | N14: BANQUE | Q14: =IF(R14=0,0,($C$36-R14)) -> 1050000 | R14: =VLOOKUP(A14,[7]HISTODEC20!A$6:AI$38,19,0) -> 150000 | S14: =IF(R14=0,0,(R14-75000)) -> 75000
A15: AS201649 | B15: =VLOOKUP(A15,[6]LISTADHERENT!A$5:H$60,3,0) -> MBOGNING TUGMA GUY | D15: =IF(E15="ESPECES",0,0) -> 0 | F15: =TONTOCT!F15 -> 0 | L15: =M15 -> 0 | M15: =+TONTNOV!H15+TONTNOV!I15 -> 0 | S15: =IF(R15=0,0,(R15-75000)) -> 0
A16: AS201649 | B16: =VLOOKUP(A16,[6]LISTADHERENT!A$5:H$60,3,0) -> MBOGNING TUGMA GUY | D16: =IF(E16="ESPECES",0,0) -> 0 | F16: =TONTOCT!F16 -> 0 | L16: =M16 -> 0 | M16: =+TONTNOV!H16+TONTNOV!I16 -> 0 | S16: =IF(R16=0,0,(R16-75000)) -> 0
A17: AS201626 | B17: =VLOOKUP(A17,[6]LISTADHERENT!A$5:H$60,3,0) -> NGUIEMEGNI MATHIEU BLAISE | C17: =IF(E17="ECHEC",0,IF(E17="",0,75000))+75000 -> 150000 | D17: =IF(E17="ESPECES",0,0) -> 0 | E17: =VLOOKUP(A17,[7]HISTODEC20!A$6:V$38,21,0) -> BANQUE | F17: 0 | G17: BANQUE | L17: =M17 -> 0 | M17: =+TONTNOV!H17+TONTNOV!I17 -> 0 | Q17: =IF(R17=0,0,($C$36-R17)) -> 0 | R17: =VLOOKUP(A17,[7]HISTODEC20!A$6:AI$38,19,0) -> 0 | S17: =IF(R17=0,0,(R17-75000)) -> 0
A18: AS201626 | B18: =VLOOKUP(A18,[6]LISTADHERENT!A$5:H$60,3,0) -> NGUIEMEGNI MATHIEU BLAISE | D18: =IF(E18="ESPECES",0,0) -> 0 | F18: =TONTOCT!F18 -> 0 | L18: =M18 -> 0 | M18: =+TONTNOV!H18+TONTNOV!I18 -> 0 | Q18: =IF(R18=0,0,($C$36-R18)) -> 0 | R18: =VLOOKUP(A18,[7]HISTODEC20!A$6:AI$38,19,0) -> 0 | S18: =IF(R18=0,0,(R18-75000)) -> 0
A19: AS201628 | B19: =VLOOKUP(A19,[6]LISTADHERENT!A$5:H$60,3,0) -> NKAMGANG JUSTIN DEJOLIE | C19: =IF(E19="ECHEC",0,IF(E19="",0,75000)) -> 75000 | D19: =IF(E19="ESPECES",0,0) -> 0 | E19: =VLOOKUP(A19,[7]HISTODEC20!A$6:V$38,21,0) -> ESPECES | F19: =TONTOCT!F19 -> 0 | H19: 150000 | I19: 2000 | L19: =M19 -> 102000 | M19: =+TONTNOV!H19+TONTNOV!I19 -> 102000 | N19: ESPECES | Q19: =IF(R19=0,0,($C$36-R19)) -> 0 | R19: =VLOOKUP(A19,[7]HISTODEC20!A$6:AI$38,19,0) -> 0 | S19: =IF(R19=0,0,(R19-75000)) -> 0
A20: AS201633 | B20: =VLOOKUP(A20,[6]LISTADHERENT!A$5:H$60,3,0) -> PATEGO NJOSSU GUSTAVE | C20: =IF(E20="ECHEC",0,IF(E20="",0,75000)) -> 75000 | D20: =IF(E20="ESPECES",0,0) -> 0 | E20: =VLOOKUP(A20,[7]HISTODEC20!A$6:V$38,21,0) -> BANQUE | F20: =TONTOCT!F20 -> 0 | L20: =M20 -> 0 | M20: =+TONTNOV!H20+TONTNOV!I20 -> 0 | Q20: =IF(R20=0,0,($C$36-R20)) -> 0 | R20: =VLOOKUP(A20,[7]HISTODEC20!A$6:AI$38,19,0) -> 0 | S20: =IF(R20=0,0,(R20-75000)) -> 0
A21: AS201638 | B21: =VLOOKUP(A21,[6]LISTADHERENT!A$5:H$60,3,0) -> SIMO PIERRE | C21: =IF(E21="ECHEC",0,IF(E21="",0,75000)) -> 75000 | D21: =IF(E21="ESPECES",0,0) -> 0 | E21: =VLOOKUP(A21,[7]HISTODEC20!A$6:V$38,21,0) -> BANQUE | F21: =TONTOCT!F21 -> 0 | L21: =M21 -> 0 | M21: =+TONTNOV!H21+TONTNOV!I21 -> 0 | Q21: =IF(R21=0,0,($C$36-R21)) -> 0 | R21: =VLOOKUP(A21,[7]HISTODEC20!A$6:AI$38,19,0) -> 0 | S21: =IF(R21=0,0,(R21-75000)) -> 0
A22: AS201655 | B22: =VLOOKUP(A22,[6]LISTADHERENT!A$5:H$60,3,0) -> TCHEMHOU EMMANUEL | C22: =IF(E22="ECHEC",0,IF(E22="",0,75000)) -> 75000 | D22: =IF(E22="ESPECES",0,0) -> 0 | E22: =VLOOKUP(A22,[7]HISTODEC20!A$6:V$38,21,0) -> BANQUE | F22: =TONTOCT!F22 -> 0 | L22: =M22 -> 0 | M22: =+TONTNOV!H22+TONTNOV!I22 -> 0 | Q22: =IF(R22=0,0,($C$36-R22)) -> 0 | R22: =VLOOKUP(A22,[7]HISTODEC20!A$6:AI$38,19,0) -> 0 | S22: =IF(R22=0,0,(R22-75000)) -> 0
A23: AS201647 | B23: =VLOOKUP(A23,[6]LISTADHERENT!A$5:H$60,3,0) -> YOUMBI EMMANUEL | C23: =IF(E23="ECHEC",0,IF(E23="",0,75000))+75000 -> 150000 | D23: =IF(E23="ESPECES",0,0) -> 0 | E23: =VLOOKUP(A23,[7]HISTODEC20!A$6:V$38,21,0) -> BANQUE | F23: =TONTOCT!F23 -> 0 | L23: =M23 -> 0 | M23: =+TONTNOV!H23+TONTNOV!I23 -> 0 | Q23: =IF(R23=0,0,($C$36-R23)) -> 0 | R23: =VLOOKUP(A23,[7]HISTODEC20!A$6:AI$38,19,0) -> 0 | S23: =IF(R23=0,0,(R23-75000)) -> 0
A24: AS201647 | B24: =VLOOKUP(A24,[6]LISTADHERENT!A$5:H$60,3,0) -> YOUMBI EMMANUEL | D24: =IF(E24="ESPECES",0,0) -> 0 | F24: =TONTOCT!F24 -> 0 | L24: =M24 -> 0 | M24: =+TONTNOV!H24+TONTNOV!I24 -> 0 | Q24: =IF(R24=0,0,($C$36-R24)) -> 0 | R24: =VLOOKUP(A24,[7]HISTODEC20!A$6:AI$38,19,0) -> 0 | S24: =IF(R24=0,0,(R24-75000)) -> 0
A26: TOTAL | C26: =SUM(C6:C24) -> 1350000 | D26: =SUM(D6:D24) -> 0 | F26: =SUM(F6:F24) -> 0 | H26: =SUM(H6:H24) -> 761000 | I26: =SUM(I6:I24) -> 12000 | K26: =SUM(K6:K24) -> 0 | L26: =SUM(L6:L24) -> 461500 | M26: =SUM(M6:M24) -> 461500 | O26: =SUM(O6:O24) -> 0 | P26: =SUM(P6:P24) -> 0 | Q26: =SUM(Q6:Q24) -> 1050000 | R26: =SUM(R6:R24) -> 150000 | S26: =SUM(S6:S24) -> 75000
C28: TONTINE | D28: REMBOURSEMENT PETIT LOT | E28: VENTE PETIT LOT | F28: VENTE LOT PRINCIPAL | G28: SOLDE EN CAISSE | I28: TONTINE + REMB + INTERET VENTE | J28: =C33+D33+R26 -> 1961500
I29: VENDUE | J29: =IF(J28>=2400000,1200000*2,1200000) -> 1200000
B30: ESPECES | C30: =SUMIFS(C6:C24,E6:E24,"ESPECES") -> 75000 | D30: =SUMIFS(L6:L25,N6:N25,"ESPECES")+SUMIFS(F6:F25,G6:G25,"ESPECES") -> 102000 | E30: =SUMIFS(H6:H24,J6:J24,"ESPECES") -> 0 | F30: =SUMIFS(Q6:Q24,O6:O24,"ESPECES") -> 0 | G30: =C30+D30-E30-F30 -> 177000
B31: BANQUE | C31: =SUMIFS(C6:C24,E6:E24,"BANQUE") -> 1275000 | D31: =SUMIFS(M6:M25,N6:N25,"BANQUE")+SUMIFS(F3:F21,G3:G21,"BANQUE") -> 359500 | E31: =SUMIFS(H6:H24,J6:J24,"BANQUE") -> 0 | F31: =SUMIFS(Q6:Q24,O6:O24,"BANQUE") -> 0 | G31: =C31+D31-E31-F31 -> 1634500 | I31: PETIT LOT | J31: =J28-J29 -> 761500
B33: TOTAL | C33: =C30+C31 -> 1350000 | D33: =D30+D31 -> 461500 | E33: =E30+E31 -> 0 | F33: =F30+F31 -> 0 | G33: =G30+G31 -> 1811500 | I33: RELIQUAT | J33: =J31-H26 -> 500 | K33: =J33+TONTNOV!K33 -> 0 | L33: CUMUL
I35: ECHEC TONTINE | J35: =COUNTIFS(E3:E21,"ECHEC")*75000 -> 0 | K35: =J35+TONTNOV!K35 -> 0 | L35: CUMUL
B36: MONTANT TONTINE | C36: 1200000 | I36: ECHEC REMBOURSEMENT | J36: =SUMIFS(F3:F21,G3:G21,"ECHEC") -> 0 | L36: CUMUL

Sheet TONTJANV
A1: ASSOCIATION | B1: ASELBY
A2: ANNEE | B2: 2021 | C2: TONIINE | D2: NBRE PART
A3: TAUX TONTINE | B3: 75000 | C3: =B3*16 -> 1200000 | D3: =ROUNDDOWN(L29/C3,0) -> 1
C4: 44213
A5: MATRICULE | B5: NOM ET PRENOM | C5: MONTANT TONTINE | D5: PENALITE | E5: MODE VERSEMENT TONTINE | F5: REPORT ECHEC PETIT LOT | G5: MODE VERSEMENT VENTE PETIT LOT | H5: VENTE PETIT LOT | I5: INTERET PETIT LOT | J5: MODE VERSEMENT VENTE PETIT LOT | K5: NUMERO CHEQUE | L5: MONTANT REMBOURSE | M5: MONTANT A REMBOURSER | N5: MODE VERSEMENT REMBOURSEMENT | O5: MODE VERSEMENT TONTINE PRINCIPAL | P5: NUMERO CHEQUE | Q5: MONTANT TONTINE LOT PRINCIPAL | R5: INTERET LOT PRINCIPAL | S5: INTERET DU
A6: AS201602 | B6: =VLOOKUP(A6,[6]LISTADHERENT!A$5:H$60,3,0) -> BOUTCHOUANG WILLIAM | C6: =IF(E6="ECHEC",0,VLOOKUP($A6,[8]HISTOJANV21!$A$6:$AU$39,13,0)) -> 75000 | E6: =VLOOKUP($A6,[8]HISTOJANV21!$A$6:$AU$39,8,0) -> BANQUE | F6: =TONTDEC!F6 -> 0 | H6: =VLOOKUP($A6,[8]HISTOJANV21!$A$6:$AU$39,36,0) -> 0 | I6: =VLOOKUP($A6,[8]HISTOJANV21!$A$6:$AU$39,39,0) -> 0 | J6: =IF(H6<>0,VLOOKUP($A6,[8]HISTOJANV21!$A$6:$AU$39,8,0),"ECHEC") -> ECHEC | K6: =VLOOKUP($A6,[8]HISTOJANV21!$A$6:$AU$39,41,0) -> 0 | L6: =VLOOKUP($A6,[8]HISTOJANV21!$A$6:$AU$39,17,0) -> 0 | M6: =TONTDEC!H6+TONTDEC!I6 -> 0 | N6: =IF(M6<>0,VLOOKUP($A6,[8]HISTOJANV21!$A$6:$AU$39,8,0),"ECHEC") -> ECHEC | O6: =IF(R6<>0,VLOOKUP($A6,[8]HISTOJANV21!$A$6:$AU$39,8,0),"ECHEC") -> ECHEC | P6: =VLOOKUP($A6,[8]HISTOJANV21!$A$6:$AU$39,33,0) -> 0 | Q6: =IF(R6=0,0,($C$37-R6)) -> 0 | R6: =VLOOKUP($A6,[8]HISTOJANV21!$A$6:$AU$39,30,0) -> 0 | S6: =IF(R6=0,0,(R6-75000)) -> 0
A7: AS201603 | B7: =VLOOKUP(A7,[6]LISTADHERENT!A$5:H$60,3,0) -> CHINGUE FABRICE | S7: =IF(R7=0,0,(R7-75000)) -> 0
A8: AS201604 | B8: =VLOOKUP(A8,[6]LISTADHERENT!A$5:H$60,3,0) -> DJOMO JEAN PAUL | C8: =IF(E8="ECHEC",0,VLOOKUP($A8,[8]HISTOJANV21!$A$6:$AU$39,13,0)) -> 75000 | E8: =VLOOKUP($A8,[8]HISTOJANV21!$A$6:$AU$39,8,0) -> BANQUE | F8: =TONTDEC!F8 -> 0 | H8: =VLOOKUP($A8,[8]HISTOJANV21!$A$6:$AU$39,36,0) -> 200000 | I8: =VLOOKUP($A8,[8]HISTOJANV21!$A$6:$AU$39,39,0) -> 2000 | J8: =IF(H8<>0,VLOOKUP($A8,[8]HISTOJANV21!$A$6:$AU$39,8,0),"ECHEC") -> BANQUE | K8: =VLOOKUP($A8,[8]HISTOJANV21!$A$6:$AU$39,41,0) -> 0 | L8: =VLOOKUP($A8,[8]HISTOJANV21!$A$6:$AU$39,17,0) -> 102000 | M8: =TONTDEC!H8+TONTDEC!I8 -> 102000 | N8: =IF(M8<>0,VLOOKUP($A8,[8]HISTOJANV21!$A$6:$AU$39,8,0),"ECHEC") -> BANQUE | O8: =IF(R8<>0,VLOOKUP($A8,[8]HISTOJANV21!$A$6:$AU$39,8,0),"ECHEC") -> ECHEC | P8: =VLOOKUP($A8,[8]HISTOJANV21!$A$6:$AU$39,33,0) -> 0 | Q8: =IF(R8=0,0,($C$37-R8)) -> 0 | R8: =VLOOKUP($A8,[8]HISTOJANV21!$A$6:$AU$39,30,0) -> 0 | S8: =IF(R8=0,0,(R8-75000)) -> 0
A9: AS201605 | B9: =VLOOKUP(A9,[6]LISTADHERENT!A$5:H$60,3,0) -> DJOUKWE NANGUEN GUY BLAISE | C9: =IF(E9="ECHEC",0,VLOOKUP($A9,[8]HISTOJANV21!$A$6:$AU$39,13,0)) -> 75000 | E9: =VLOOKUP($A9,[8]HISTOJANV21!$A$6:$AU$39,8,0) -> BANQUE | F9: =TONTDEC!F9 -> 0 | H9: =VLOOKUP($A9,[8]HISTOJANV21!$A$6:$AU$39,36,0) -> 200000 | I9: =VLOOKUP($A9,[8]HISTOJANV21!$A$6:$AU$39,39,0) -> 2000 | J9: =IF(H9<>0,VLOOKUP($A9,[8]HISTOJANV21!$A$6:$AU$39,8,0),"ECHEC") -> BANQUE | K9: =VLOOKUP($A9,[8]HISTOJANV21!$A$6:$AU$39,41,0) -> 0 | L9: =VLOOKUP($A9,[8]HISTOJANV21!$A$6:$AU$39,17,0) -> 204000 | M9: =TONTDEC!H9+TONTDEC!I9 -> 204000 | N9: =IF(M9<>0,VLOOKUP($A9,[8]HISTOJANV21!$A$6:$AU$39,8,0),"ECHEC") -> BANQUE | O9: =IF(R9<>0,VLOOKUP($A9,[8]HISTOJANV21!$A$6:$AU$39,8,0),"ECHEC") -> ECHEC | P9: =VLOOKUP($A9,[8]HISTOJANV21!$A$6:$AU$39,33,0) -> 0 | Q9: =IF(R9=0,0,($C$37-R9)) -> 0 | R9: =VLOOKUP($A9,[8]HISTOJANV21!$A$6:$AU$39,30,0) -> 0 | S9: =IF(R9=0,0,(R9-75000)) -> 0
A10: AS201613 | B10: =VLOOKUP(A10,[6]LISTADHERENT!A$5:H$60,3,0) -> HOTCHO BENJAMIN | C10: =IF(E10="ECHEC",0,VLOOKUP($A10,[8]HISTOJANV21!$A$6:$AU$39,13,0)) -> 75000 | E10: =VLOOKUP($A10,[8]HISTOJANV21!$A$6:$AU$39,8,0) -> BANQUE | F10: =TONTDEC!F10 -> 0 | H10: =VLOOKUP($A10,[8]HISTOJANV21!$A$6:$AU$39,36,0) -> 0 | I10: =VLOOKUP($A10,[8]HISTOJANV21!$A$6:$AU$39,39,0) -> 0 | J10: =IF(H10<>0,VLOOKUP($A10,[8]HISTOJANV21!$A$6:$AU$39,8,0),"ECHEC") -> ECHEC | K10: =VLOOKUP($A10,[8]HISTOJANV21!$A$6:$AU$39,41,0) -> 0 | L10: =VLOOKUP($A10,[8]HISTOJANV21!$A$6:$AU$39,17,0) -> 0 | M10: =TONTDEC!H10+TONTDEC!I10 -> 0 | N10: =IF(M10<>0,VLOOKUP($A10,[8]HISTOJANV21!$A$6:$AU$39,8,0),"ECHEC") -> ECHEC | O10: =IF(R10<>0,VLOOKUP($A10,[8]HISTOJANV21!$A$6:$AU$39,8,0),"ECHEC") -> ECHEC | P10: =VLOOKUP($A10,[8]HISTOJANV21!$A$6:$AU$39,33,0) -> 0 | Q10: =IF(R10=0,0,($C$37-R10)) -> 0 | R10: =VLOOKUP($A10,[8]HISTOJANV21!$A$6:$AU$39,30,0) -> 0 | S10: =IF(R10=0,0,(R10-75000)) -> 0
A11: AS201611 | B11: =VLOOKUP(A11,[6]LISTADHERENT!A$5:H$60,3,0) -> HENGUE PAUL OMER | C11: =IF(E11="ECHEC",0,VLOOKUP($A11,[8]HISTOJANV21!$A$6:$AU$39,13,0)) -> 75000 | E11: =VLOOKUP($A11,[8]HISTOJANV21!$A$6:$AU$39,8,0) -> BANQUE | F11: =TONTDEC!F11 -> 0 | H11: =VLOOKUP($A11,[8]HISTOJANV21!$A$6:$AU$39,36,0) -> 0 | I11: =VLOOKUP($A11,[8]HISTOJANV21!$A$6:$AU$39,39,0) -> 0 | J11: =IF(H11<>0,VLOOKUP($A11,[8]HISTOJANV21!$A$6:$AU$39,8,0),"ECHEC") -> ECHEC | K11: =VLOOKUP($A11,[8]HISTOJANV21!$A$6:$AU$39,41,0) -> 0 | L11: =VLOOKUP($A11,[8]HISTOJANV21!$A$6:$AU$39,17,0) -> 0 | M11: =TONTDEC!H11+TONTDEC!I11 -> 0 | N11: =IF(M11<>0,VLOOKUP($A11,[8]HISTOJANV21!$A$6:$AU$39,8,0),"ECHEC") -> ECHEC | O11: =IF(R11<>0,VLOOKUP($A11,[8]HISTOJANV21!$A$6:$AU$39,8,0),"ECHEC") -> ECHEC | P11: =VLOOKUP($A11,[8]HISTOJANV21!$A$6:$AU$39,33,0) -> 0 | Q11: =IF(R11=0,0,($C$37-R11)) -> 0 | R11: =VLOOKUP($A11,[8]HISTOJANV21!$A$6:$AU$39,30,0) -> 0 | S11: =IF(R11=0,0,(R11-75000)) -> 0
A12: AS201619 | B12: =VLOOKUP(A12,[6]LISTADHERENT!A$5:H$60,3,0) -> KOUATCHO MESSACK | C12: =IF(E12="ECHEC",0,VLOOKUP($A12,[8]HISTOJANV21!$A$6:$AU$39,13,0)) -> 75000 | E12: =VLOOKUP($A12,[8]HISTOJANV21!$A$6:$AU$39,8,0) -> ESPECES | F12: =TONTDEC!F12 -> 0 | H12: =VLOOKUP($A12,[8]HISTOJANV21!$A$6:$AU$39,36,0) -> 200000 | I12: =VLOOKUP($A12,[8]HISTOJANV21!$A$6:$AU$39,39,0) -> 2000 | J12: =IF(H12<>0,VLOOKUP($A12,[8]HISTOJANV21!$A$6:$AU$39,8,0),"ECHEC") -> ESPECES | K12: =VLOOKUP($A12,[8]HISTOJANV21!$A$6:$AU$39,41,0) -> 0 | L12: =VLOOKUP($A12,[8]HISTOJANV21!$A$6:$AU$39,17,0) -> 202000 | M12: =TONTDEC!H12+TONTDEC!I12 -> 202000 | N12: =IF(M12<>0,VLOOKUP($A12,[8]HISTOJANV21!$A$6:$AU$39,8,0),"ECHEC") -> ESPECES | O12: =IF(R12<>0,VLOOKUP($A12,[8]HISTOJANV21!$A$6:$AU$39,8,0),"ECHEC") -> ESPECES | P12: =VLOOKUP($A12,[8]HISTOJANV21!$A$6:$AU$39,33,0) -> 0 | Q12: =IF(R12=0,0,($C$37-R12)) -> 1110000 | R12: =VLOOKUP($A12,[8]HISTOJANV21!$A$6:$AU$39,30,0) -> 90000 | S12: =IF(R12=0,0,(R12-75000)) -> 15000
A13: AS201621 | B13: =VLOOKUP(A13,[6]LISTADHERENT!A$5:H$60,3,0) -> NANKAM APPOLINAIRE | C13: =IF(E13="ECHEC",0,VLOOKUP($A13,[8]HISTOJANV21!$A$6:$AU$39,13,0)) -> 75000 | E13: =VLOOKUP($A13,[8]HISTOJANV21!$A$6:$AU$39,8,0) -> BANQUE | F13: =TONTDEC!F13 -> 0 | H13: =VLOOKUP($A13,[8]HISTOJANV21!$A$6:$AU$39,36,0) -> 0 | I13: =VLOOKUP($A13,[8]HISTOJANV21!$A$6:$AU$39,39,0) -> 0 | J13: =IF(H13<>0,VLOOKUP($A13,[8]HISTOJANV21!$A$6:$AU$39,8,0),"ECHEC") -> ECHEC | K13: =VLOOKUP($A13,[8]HISTOJANV21!$A$6:$AU$39,41,0) -> 0 | L13: =VLOOKUP($A13,[8]HISTOJANV21!$A$6:$AU$39,17,0) -> 0 | M13: =TONTDEC!H13+TONTDEC!I13 -> 0 | N13: =IF(M13<>0,VLOOKUP($A13,[8]HISTOJANV21!$A$6:$AU$39,8,0),"ECHEC") -> ECHEC | O13: =IF(R13<>0,VLOOKUP($A13,[8]HISTOJANV21!$A$6:$AU$39,8,0),"ECHEC") -> ECHEC | P13: =VLOOKUP($A13,[8]HISTOJANV21!$A$6:$AU$39,33,0) -> 0 | Q13: =IF(R13=0,0,($C$37-R13)) -> 0 | R13: =VLOOKUP($A13,[8]HISTOJANV21!$A$6:$AU$39,30,0) -> 0 | S13: =IF(R13=0,0,(R13-75000)) -> 0
A14: AS201649 | B14: =VLOOKUP(A14,[6]LISTADHERENT!A$5:H$60,3,0) -> MBOGNING TUGMA GUY | C14: =IF(E14="ECHEC",0,VLOOKUP($A14,[8]HISTOJANV21!$A$6:$AU$39,13,0)) -> 225000 | E14: =VLOOKUP($A14,[8]HISTOJANV21!$A$6:$AU$39,8,0) -> BANQUE | F14: =TONTDEC!F14 -> 0 | H14: =VLOOKUP($A14,[8]HISTOJANV21!$A$6:$AU$39,36,0) -> 213000 | I14: =VLOOKUP($A14,[8]HISTOJANV21!$A$6:$AU$39,39,0) -> 2000 | J14: =IF(H14<>0,VLOOKUP($A14,[8]HISTOJANV21!$A$6:$AU$39,8,0),"ECHEC") -> BANQUE | K14: =VLOOKUP($A14,[8]HISTOJANV21!$A$6:$AU$39,41,0) -> 0 | L14: =VLOOKUP($A14,[8]HISTOJANV21!$A$6:$AU$39,17,0) -> 113000 | M14: =TONTDEC!H14+TONTDEC!I14 -> 113000 | N14: =IF(M14<>0,VLOOKUP($A14,[8]HISTOJANV21!$A$6:$AU$39,8,0),"ECHEC") -> BANQUE | O14: =IF(R14<>0,VLOOKUP($A14,[8]HISTOJANV21!$A$6:$AU$39,8,0),"ECHEC") -> ECHEC | P14: =VLOOKUP($A14,[8]HISTOJANV21!$A$6:$AU$39,33,0) -> 0 | Q14: =IF(R14=0,0,($C$37-R14)) -> 0 | R14: =VLOOKUP($A14,[8]HISTOJANV21!$A$6:$AU$39,30,0) -> 0 | S14: =IF(R14=0,0,(R14-75000)) -> 0
A15: AS201649 | B15: =VLOOKUP(A15,[6]LISTADHERENT!A$5:H$60,3,0) -> MBOGNING TUGMA GUY | P15: =VLOOKUP($A15,[8]HISTOJANV21!$A$6:$AU$39,33,0) -> 0 | R15: =VLOOKUP($A15,[8]HISTOJANV21!$A$6:$AU$39,30,0) -> 0 | S15: =IF(R15=0,0,(R15-75000)) -> 0
A16: AS201649 | B16: =VLOOKUP(A16,[6]LISTADHERENT!A$5:H$60,3,0) -> MBOGNING TUGMA GUY | P16: =VLOOKUP($A16,[8]HISTOJANV21!$A$6:$AU$39,33,0) -> 0 | R16: =VLOOKUP($A16,[8]HISTOJANV21!$A$6:$AU$39,30,0) -> 0 | S16: =IF(R16=0,0,(R16-75000)) -> 0
A17: AS201626 | B17: =VLOOKUP(A17,[6]LISTADHERENT!A$5:H$60,3,0) -> NGUIEMEGNI MATHIEU BLAISE | C17: =IF(E17="ECHEC",0,VLOOKUP($A17,[8]HISTOJANV21!$A$6:$AU$39,13,0)) -> 150000 | E17: =VLOOKUP($A17,[8]HISTOJANV21!$A$6:$AU$39,8,0) -> ESPECES | F17: =TONTDEC!F17 -> 0 | H17: =VLOOKUP($A17,[8]HISTOJANV21!$A$6:$AU$39,36,0) -> 0 | I17: =VLOOKUP($A17,[8]HISTOJANV21!$A$6:$AU$39,39,0) -> 0 | J17: =IF(H17<>0,VLOOKUP($A17,[8]HISTOJANV21!$A$6:$AU$39,8,0),"ECHEC") -> ECHEC | K17: =VLOOKUP($A17,[8]HISTOJANV21!$A$6:$AU$39,41,0) -> 0 | L17: =VLOOKUP($A17,[8]HISTOJANV21!$A$6:$AU$39,17,0) -> 0 | M17: =TONTDEC!H17+TONTDEC!I17 -> 0 | N17: =IF(M17<>0,VLOOKUP($A17,[8]HISTOJANV21!$A$6:$AU$39,8,0),"ECHEC") -> ECHEC | O17: =IF(R17<>0,VLOOKUP($A17,[8]HISTOJANV21!$A$6:$AU$39,8,0),"ECHEC") -> ECHEC | P17: =VLOOKUP($A17,[8]HISTOJANV21!$A$6:$AU$39,33,0) -> 0 | Q17: =IF(R17=0,0,($C$37-R17)) -> 0 | R17: =VLOOKUP($A17,[8]HISTOJANV21!$A$6:$AU$39,30,0) -> 0 | S17: =IF(R17=0,0,(R17-75000)) -> 0
A18: AS201626 | B18: =VLOOKUP(A18,[6]LISTADHERENT!A$5:H$60,3,0) -> NGUIEMEGNI MATHIEU BLAISE | N18: =IF(M18<>0,VLOOKUP($A18,[8]HISTOJANV21!$A$6:$AU$39,8,0),"ECHEC") -> ECHEC | O18: =IF(R18<>0,VLOOKUP($A18,[8]HISTOJANV21!$A$6:$AU$39,8,0),"ECHEC") -> ECHEC | P18: =VLOOKUP($A18,[8]HISTOJANV21!$A$6:$AU$39,33,0) -> 0 | R18: =VLOOKUP($A18,[8]HISTOJANV21!$A$6:$AU$39,30,0) -> 0 | S18: =IF(R18=0,0,(R18-75000)) -> 0
A19: AS201628 | B19: =VLOOKUP(A19,[6]LISTADHERENT!A$5:H$60,3,0) -> NKAMGANG JUSTIN DEJOLIE | C19: =IF(E19="ECHEC",0,VLOOKUP($A19,[8]HISTOJANV21!$A$6:$AU$39,13,0)) -> 75000 | E19: =VLOOKUP($A19,[8]HISTOJANV21!$A$6:$AU$39,8,0) -> ESPECES | F19: =TONTDEC!F19 -> 0 | H19: =VLOOKUP($A19,[8]HISTOJANV21!$A$6:$AU$39,36,0) -> 200000 | I19: =VLOOKUP($A19,[8]HISTOJANV21!$A$6:$AU$39,39,0) -> 2000 | J19: =IF(H19<>0,VLOOKUP($A19,[8]HISTOJANV21!$A$6:$AU$39,8,0),"ECHEC") -> ESPECES | K19: =VLOOKUP($A19,[8]HISTOJANV21!$A$6:$AU$39,41,0) -> 0 | L19: =VLOOKUP($A19,[8]HISTOJANV21!$A$6:$AU$39,17,0) -> 152000 | M19: =TONTDEC!H19+TONTDEC!I19 -> 152000 | N19: =IF(M19<>0,VLOOKUP($A19,[8]HISTOJANV21!$A$6:$AU$39,8,0),"ECHEC") -> ESPECES | O19: =IF(R19<>0,VLOOKUP($A19,[8]HISTOJANV21!$A$6:$AU$39,8,0),"ECHEC") -> ECHEC | P19: =VLOOKUP($A19,[8]HISTOJANV21!$A$6:$AU$39,33,0) -> 0 | Q19: =IF(R19=0,0,($C$37-R19)) -> 0 | R19: =VLOOKUP($A19,[8]HISTOJANV21!$A$6:$AU$39,30,0) -> 0 | S19: =IF(R19=0,0,(R19-75000)) -> 0
A20: AS201633 | B20: =VLOOKUP(A20,[6]LISTADHERENT!A$5:H$60,3,0) -> PATEGO NJOSSU GUSTAVE | C20: =IF(E20="ECHEC",0,VLOOKUP($A20,[8]HISTOJANV21!$A$6:$AU$39,13,0)) -> 75000 | E20: =VLOOKUP($A20,[8]HISTOJANV21!$A$6:$AU$39,8,0) -> BANQUE | F20: =TONTDEC!F20 -> 0 | H20: =VLOOKUP($A20,[8]HISTOJANV21!$A$6:$AU$39,36,0) -> 0 | I20: =VLOOKUP($A20,[8]HISTOJANV21!$A$6:$AU$39,39,0) -> 0 | J20: =IF(H20<>0,VLOOKUP($A20,[8]HISTOJANV21!$A$6:$AU$39,8,0),"ECHEC") -> ECHEC | K20: =VLOOKUP($A20,[8]HISTOJANV21!$A$6:$AU$39,41,0) -> 0 | L20: =VLOOKUP($A20,[8]HISTOJANV21!$A$6:$AU$39,17,0) -> 0 | M20: =TONTDEC!H20+TONTDEC!I20 -> 0 | N20: =IF(M20<>0,VLOOKUP($A20,[8]HISTOJANV21!$A$6:$AU$39,8,0),"ECHEC") -> ECHEC | O20: =IF(R20<>0,VLOOKUP($A20,[8]HISTOJANV21!$A$6:$AU$39,8,0),"ECHEC") -> ECHEC | P20: =VLOOKUP($A20,[8]HISTOJANV21!$A$6:$AU$39,33,0) -> 0 | Q20: =IF(R20=0,0,($C$37-R20)) -> 0 | R20: =VLOOKUP($A20,[8]HISTOJANV21!$A$6:$AU$39,30,0) -> 0 | S20: =IF(R20=0,0,(R20-75000)) -> 0
A21: AS201638 | B21: =VLOOKUP(A21,[6]LISTADHERENT!A$5:H$60,3,0) -> SIMO PIERRE | C21: =IF(E21="ECHEC",0,VLOOKUP($A21,[8]HISTOJANV21!$A$6:$AU$39,13,0)) -> 75000 | E21: =VLOOKUP($A21,[8]HISTOJANV21!$A$6:$AU$39,8,0) -> BANQUE | F21: =TONTDEC!F21 -> 0 | H21: =VLOOKUP($A21,[8]HISTOJANV21!$A$6:$AU$39,36,0) -> 0 | I21: =VLOOKUP($A21,[8]HISTOJANV21!$A$6:$AU$39,39,0) -> 0 | J21: =IF(H21<>0,VLOOKUP($A21,[8]HISTOJANV21!$A$6:$AU$39,8,0),"ECHEC") -> ECHEC | K21: =VLOOKUP($A21,[8]HISTOJANV21!$A$6:$AU$39,41,0) -> 0 | L21: =VLOOKUP($A21,[8]HISTOJANV21!$A$6:$AU$39,17,0) -> 0 | M21: =TONTDEC!H21+TONTDEC!I21 -> 0 | N21: =IF(M21<>0,VLOOKUP($A21,[8]HISTOJANV21!$A$6:$AU$39,8,0),"ECHEC") -> ECHEC | O21: =IF(R21<>0,VLOOKUP($A21,[8]HISTOJANV21!$A$6:$AU$39,8,0),"ECHEC") -> ECHEC | P21: =VLOOKUP($A21,[8]HISTOJANV21!$A$6:$AU$39,33,0) -> 0 | Q21: =IF(R21=0,0,($C$37-R21)) -> 0 | R21: =VLOOKUP($A21,[8]HISTOJANV21!$A$6:$AU$39,30,0) -> 0 | S21: =IF(R21=0,0,(R21-75000)) -> 0
A22: AS201655 | B22: =VLOOKUP(A22,[6]LISTADHERENT!A$5:H$60,3,0) -> TCHEMHOU EMMANUEL | C22: =IF(E22="ECHEC",0,VLOOKUP($A22,[8]HISTOJANV21!$A$6:$AU$39,13,0)) -> 75000 | E22: =VLOOKUP($A22,[8]HISTOJANV21!$A$6:$AU$39,8,0) -> BANQUE | F22: =TONTDEC!F22 -> 0 | H22: =VLOOKUP($A22,[8]HISTOJANV21!$A$6:$AU$39,36,0) -> 0 | I22: =VLOOKUP($A22,[8]HISTOJANV21!$A$6:$AU$39,39,0) -> 0 | J22: =IF(H22<>0,VLOOKUP($A22,[8]HISTOJANV21!$A$6:$AU$39,8,0),"ECHEC") -> ECHEC | K22: =VLOOKUP($A22,[8]HISTOJANV21!$A$6:$AU$39,41,0) -> 0 | L22: =VLOOKUP($A22,[8]HISTOJANV21!$A$6:$AU$39,17,0) -> 0 | M22: =TONTDEC!H22+TONTDEC!I22 -> 0 | N22: =IF(M22<>0,VLOOKUP($A22,[8]HISTOJANV21!$A$6:$AU$39,8,0),"ECHEC") -> ECHEC | O22: =IF(R22<>0,VLOOKUP($A22,[8]HISTOJANV21!$A$6:$AU$39,8,0),"ECHEC") -> ECHEC | P22: =VLOOKUP($A22,[8]HISTOJANV21!$A$6:$AU$39,33,0) -> 0 | Q22: =IF(R22=0,0,($C$37-R22)) -> 0 | R22: =VLOOKUP($A22,[8]HISTOJANV21!$A$6:$AU$39,30,0) -> 0 | S22: =IF(R22=0,0,(R22-75000)) -> 0
A23: AS201647 | B23: =VLOOKUP(A23,[6]LISTADHERENT!A$5:H$60,3,0) -> YOUMBI EMMANUEL | C23: =IF(E23="ECHEC",0,VLOOKUP($A23,[8]HISTOJANV21!$A$6:$AU$39,13,0)) -> 150000 | E23: =VLOOKUP($A23,[8]HISTOJANV21!$A$6:$AU$39,8,0) -> BANQUE | F23: =TONTDEC!F23 -> 0 | H23: =VLOOKUP($A23,[8]HISTOJANV21!$A$6:$AU$39,36,0) -> 0 | I23: =VLOOKUP($A23,[8]HISTOJANV21!$A$6:$AU$39,39,0) -> 0 | J23: =IF(H23<>0,VLOOKUP($A23,[8]HISTOJANV21!$A$6:$AU$39,8,0),"ECHEC") -> ECHEC | K23: =VLOOKUP($A23,[8]HISTOJANV21!$A$6:$AU$39,41,0) -> 0 | L23: =VLOOKUP($A23,[8]HISTOJANV21!$A$6:$AU$39,17,0) -> 0 | M23: =TONTDEC!H23+TONTDEC!I23 -> 0 | N23: =IF(M23<>0,VLOOKUP($A23,[8]HISTOJANV21!$A$6:$AU$39,8,0),"ECHEC") -> ECHEC | O23: =IF(R23<>0,VLOOKUP($A23,[8]HISTOJANV21!$A$6:$AU$39,8,0),"ECHEC") -> ECHEC | P23: =VLOOKUP($A23,[8]HISTOJANV21!$A$6:$AU$39,33,0) -> 0 | Q23: =IF(R23=0,0,($C$37-R23)) -> 0 | R23: =VLOOKUP($A23,[8]HISTOJANV21!$A$6:$AU$39,30,0) -> 0 | S23: =IF(R23=0,0,(R23-75000)) -> 0
A24: AS201647 | B24: =VLOOKUP(A24,[6]LISTADHERENT!A$5:H$60,3,0) -> YOUMBI EMMANUEL | S24: =IF(R24=0,0,(R24-75000)) -> 0
S26: =SUM(S6:S24) -> 15000
B27: TOTAL | C27: =SUM(C6:C26) -> 1350000 | D27: =SUM(D6:D26) -> 0 | E27: =SUM(E6:E26) -> 0 | F27: =SUM(F6:F26) -> 0 | G27: =SUM(G6:G26) -> 0 | H27: =SUM(H6:H26) -> 1013000 | I27: =SUM(I6:I26) -> 10000 | J27: =SUM(J6:J26) -> 0 | ... R27: =SUM(R6:R26) -> 90000
C29: TONTINE | D29: REMBOURSEMENT PETIT LOT | E29: VENTE PETIT LOT | F29: VENTE LOT PRINCIPAL | G29: SOLDE EN CAISSE | K29: TONTINE + REMB + INTERET VENTE | L29: =C34+D34+R27 -> 2213000
K30: LOT PRINCIPAL | L30: =C3*COUNTIF(Q6:Q26,">0") -> 1200000 | M30: =D3 -> 1
B31: ESPECES | C31: =SUMIFS(C6:C25,E6:E25,"ESPECES") -> 300000 | D31: =SUMIFS(L3:L22,N3:N22,"ESPECES")+SUMIFS(F3:F22,G3:G22,"ESPECES") -> 354000 | E31: =SUMIFS(H6:H25,J6:J25,"ESPECES") -> 400000 | F31: =SUMIFS(Q6:Q25,O6:O25,"ESPECES") -> 1110000 | G31: =C31+D31-E31-F31 -> -856000
B32: BANQUE | C32: =SUMIFS(C6:C25,E6:E25,"BANQUE") -> 1050000 | D32: =SUMIFS(M3:M22,N3:N22,"BANQUE")+SUMIFS(F3:F22,G3:G22,"BANQUE") -> 419000 | E32: =SUMIFS(H6:H25,J6:J25,"BANQUE") -> 613000 | F32: =SUMIFS(Q6:Q25,O6:O25,"BANQUE") -> 0 | G32: =C32+D32-E32-F32 -> 856000 | K32: PETIT LOT | L32: =L29-L30 -> 1013000
B34: TOTAL | C34: =C31+C32 -> 1350000 | D34: =D31+D32 -> 773000 | E34: =E31+E32 -> 1013000 | F34: =F31+F32 -> 1110000 | G34: =G31+G32 -> 0 | K34: RELIQUAT | L34: =L32-H27 -> 0 | M34: =L34+TONTDEC!K33 -> 0 | N34: CUMUL
K36: ECHEC TONTINE | L36: =COUNTIFS(E3:E22,"ECHEC")*75000 -> 0 | M36: =L36+TONTDEC!K35 -> 0 | N36: CUMUL
B37: MONTANT TONTINE | C37: 1200000 | K37: ECHEC REMBOURSEMENT | L37: =SUMIFS(F3:F22,G3:G22,"ECHEC") -> 0 | N37: CUMUL

Sheet TONTFEV
A1: ASSOCIATION | B1: ASELBY
A2: ANNEE | B2: 2021 | C2: TONIINE | D2: NBRE PART
A3: TAUX TONTINE | B3: 75000 | C3: =B3*16 -> 1200000 | D3: =ROUNDDOWN(L29/C3,0) -> 1
C4: 44245
A5: MATRICULE | B5: NOM ET PRENOM | C5: MONTANT TONTINE | D5: PENALITE | E5: MODE VERSEMENT TONTINE | F5: REPORT ECHEC PETIT LOT | G5: MODE VERSEMENT VENTE PETIT LOT | H5: VENTE PETIT LOT | I5: INTERET PETIT LOT | J5: MODE VERSEMENT VENTE PETIT LOT | K5: NUMERO CHEQUE | L5: MONTANT A REMBOURSER | M5: MONTANT REMBOURSE | N5: MODE VERSEMENT REMBOURSEMENT | O5: MODE VERSEMENT TONTINE PRINCIPAL | P5: NUMERO CHEQUE | Q5: MONTANT TONTINE LOT PRINCIPAL | R5: INTERET LOT PRINCIPAL | S5: INTERET DU
A6: AS201602 | B6: =VLOOKUP(A6,[6]LISTADHERENT!A$5:H$60,3,0) -> BOUTCHOUANG WILLIAM | C6: =IF(E6="ECHEC",0,VLOOKUP($A6,[8]HISTOFEV21!$A$6:$AU$39,13,0)) -> 75000 | E6: =VLOOKUP($A6,[8]HISTOFEV21!$A$6:$AU$39,8,0) -> BANQUE | F6: =IF(N6="ECHEC",L6+(TONTJANV!I6*2),0) -> 0 | H6: =VLOOKUP($A6,[8]HISTOFEV21!$A$6:$AU$39,36,0) -> 0 | I6: =VLOOKUP($A6,[8]HISTOFEV21!$A$6:$AU$39,39,0) -> 0 | J6: =IF(H6<>0,VLOOKUP($A6,[8]HISTOFEV21!$A$6:$AU$39,8,0),"ECHEC") -> ECHEC | K6: =VLOOKUP($A6,[8]HISTOFEV21!$A$6:$AU$39,41,0) -> 0 | L6: =TONTJANV!H6+TONTJANV!I6 -> 0 | M6: =VLOOKUP(A6,[8]HISTOFEV21!$A$6:$AZ$37,17,0) -> 0 | N6: =IF(L6<>0,VLOOKUP($A6,[8]HISTOFEV21!$A$6:$AU$39,8,0),"ECHEC") -> ECHEC | O6: =IF(R6<>0,VLOOKUP($A6,[8]HISTOFEV21!$A$6:$AU$39,8,0),"ECHEC") -> ECHEC | P6: =VLOOKUP($A6,[8]HISTOFEV21!$A$6:$AU$39,33,0) -> 0 | Q6: =IF(R6=0,0,($C$37-R6)) -> 0 | R6: =VLOOKUP($A6,[8]HISTOFEV21!$A$6:$AU$39,30,0) -> 0 | S6: =IF(R6=0,0,(R6-75000)) -> 0
A7: AS201603 | B7: =VLOOKUP(A7,[6]LISTADHERENT!A$5:H$60,3,0) -> CHINGUE FABRICE | F7: =IF(N7="ECHEC",L7+(TONTJANV!I7*2),0) -> 0 | L7: =TONTJANV!H7+TONTJANV!I7 -> 0 | S7: =IF(R7=0,0,(R7-75000)) -> 0
A8: AS201604 | B8: =VLOOKUP(A8,[6]LISTADHERENT!A$5:H$60,3,0) -> DJOMO JEAN PAUL | C8: =IF(E8="ECHEC",0,VLOOKUP($A8,[8]HISTOFEV21!$A$6:$AU$39,13,0)) -> 75000 | E8: =VLOOKUP($A8,[8]HISTOFEV21!$A$6:$AU$39,8,0) -> BANQUE | F8: =IF(N8="ECHEC",L8+(TONTJANV!I8*2),0) -> 0 | H8: =VLOOKUP($A8,[8]HISTOFEV21!$A$6:$AU$39,36,0) -> 0 | I8: =VLOOKUP($A8,[8]HISTOFEV21!$A$6:$AU$39,39,0) -> 0 | J8: =IF(H8<>0,VLOOKUP($A8,[8]HISTOFEV21!$A$6:$AU$39,8,0),"ECHEC") -> ECHEC | K8: =VLOOKUP($A8,[8]HISTOFEV21!$A$6:$AU$39,41,0) -> 0 | L8: =TONTJANV!H8+TONTJANV!I8 -> 202000 | M8: =VLOOKUP(A8,[8]HISTOFEV21!$A$6:$AZ$37,17,0) -> 202000 | N8: =IF(M8<>0,VLOOKUP($A8,[8]HISTOFEV21!$A$6:$AU$39,8,0),"ECHEC") -> BANQUE | O8: =IF(R8<>0,VLOOKUP($A8,[8]HISTOFEV21!$A$6:$AU$39,8,0),"ECHEC") -> ECHEC | P8: =VLOOKUP($A8,[8]HISTOFEV21!$A$6:$AU$39,33,0) -> 0 | Q8: =IF(R8=0,0,($C$37-R8)) -> 0 | R8: =VLOOKUP($A8,[8]HISTOFEV21!$A$6:$AU$39,30,0) -> 0 | S8: =IF(R8=0,0,(R8-75000)) -> 0
A9: AS201605 | B9: =VLOOKUP(A9,[6]LISTADHERENT!A$5:H$60,3,0) -> DJOUKWE NANGUEN GUY BLAISE | C9: =IF(E9="ECHEC",0,VLOOKUP($A9,[8]HISTOFEV21!$A$6:$AU$39,13,0)) -> 75000 | E9: =VLOOKUP($A9,[8]HISTOFEV21!$A$6:$AU$39,8,0) -> BANQUE | F9: =IF(N9="ECHEC",L9+(TONTJANV!I9*2),0) -> 0 | H9: =VLOOKUP($A9,[8]HISTOFEV21!$A$6:$AU$39,36,0) -> 0 | I9: =VLOOKUP($A9,[8]HISTOFEV21!$A$6:$AU$39,39,0) -> 0 | J9: =IF(H9<>0,VLOOKUP($A9,[8]HISTOFEV21!$A$6:$AU$39,8,0),"ECHEC") -> ECHEC | K9: =VLOOKUP($A9,[8]HISTOFEV21!$A$6:$AU$39,41,0) -> 0 | L9: =TONTJANV!H9+TONTJANV!I9 -> 202000 | M9: =VLOOKUP(A9,[8]HISTOFEV21!$A$6:$AZ$37,17,0) -> 202000 | N9: =IF(M9<>0,VLOOKUP($A9,[8]HISTOFEV21!$A$6:$AU$39,8,0),"ECHEC") -> BANQUE | O9: =IF(R9<>0,VLOOKUP($A9,[8]HISTOFEV21!$A$6:$AU$39,8,0),"ECHEC") -> BANQUE | P9: =VLOOKUP($A9,[8]HISTOFEV21!$A$6:$AU$39,33,0) -> 0 | Q9: =IF(R9=0,0,($C$37-R9)) -> 1125000 | R9: =VLOOKUP($A9,[8]HISTOFEV21!$A$6:$AU$39,30,0) -> 75000 | S9: =IF(R9=0,0,(R9-75000)) -> 0
A10: AS201613 | B10: =VLOOKUP(A10,[6]LISTADHERENT!A$5:H$60,3,0) -> HOTCHO BENJAMIN | C10: =IF(E10="ECHEC",0,VLOOKUP($A10,[8]HISTOFEV21!$A$6:$AU$39,13,0)) -> 75000 | E10: =VLOOKUP($A10,[8]HISTOFEV21!$A$6:$AU$39,8,0) -> BANQUE | F10: =IF(N10="ECHEC",L10+(TONTJANV!I10*2),0) -> 0 | H10: =VLOOKUP($A10,[8]HISTOFEV21!$A$6:$AU$39,36,0) -> 0 | I10: =VLOOKUP($A10,[8]HISTOFEV21!$A$6:$AU$39,39,0) -> 0 | J10: =IF(H10<>0,VLOOKUP($A10,[8]HISTOFEV21!$A$6:$AU$39,8,0),"ECHEC") -> ECHEC | K10: =VLOOKUP($A10,[8]HISTOFEV21!$A$6:$AU$39,41,0) -> 0 | L10: =TONTJANV!H10+TONTJANV!I10 -> 0 | M10: =VLOOKUP(A10,[8]HISTOFEV21!$A$6:$AZ$37,17,0) -> 0 | N10: =IF(M10<>0,VLOOKUP($A10,[8]HISTOFEV21!$A$6:$AU$39,8,0),"ECHEC") -> ECHEC | O10: =IF(R10<>0,VLOOKUP($A10,[8]HISTOFEV21!$A$6:$AU$39,8,0),"ECHEC") -> ECHEC | P10: =VLOOKUP($A10,[8]HISTOFEV21!$A$6:$AU$39,33,0) -> 0 | Q10: =IF(R10=0,0,($C$37-R10)) -> 0 | R10: =VLOOKUP($A10,[8]HISTOFEV21!$A$6:$AU$39,30,0) -> 0 | S10: =IF(R10=0,0,(R10-75000)) -> 0
A11: AS201611 | B11: =VLOOKUP(A11,[6]LISTADHERENT!A$5:H$60,3,0) -> HENGUE PAUL OMER | C11: =IF(E11="ECHEC",0,VLOOKUP($A11,[8]HISTOFEV21!$A$6:$AU$39,13,0)) -> 75000 | E11: =VLOOKUP($A11,[8]HISTOFEV21!$A$6:$AU$39,8,0) -> BANQUE | F11: =IF(N11="ECHEC",L11+(TONTJANV!I11*2),0) -> 0 | H11: =VLOOKUP($A11,[8]HISTOFEV21!$A$6:$AU$39,36,0) -> 0 | I11: =VLOOKUP($A11,[8]HISTOFEV21!$A$6:$AU$39,39,0) -> 0 | J11: =IF(H11<>0,VLOOKUP($A11,[8]HISTOFEV21!$A$6:$AU$39,8,0),"ECHEC") -> ECHEC | K11: =VLOOKUP($A11,[8]HISTOFEV21!$A$6:$AU$39,41,0) -> 0 | L11: =TONTJANV!H11+TONTJANV!I11 -> 0 | M11: =VLOOKUP(A11,[8]HISTOFEV21!$A$6:$AZ$37,17,0) -> 0 | N11: =IF(M11<>0,VLOOKUP($A11,[8]HISTOFEV21!$A$6:$AU$39,8,0),"ECHEC") -> ECHEC | O11: =IF(R11<>0,VLOOKUP($A11,[8]HISTOFEV21!$A$6:$AU$39,8,0),"ECHEC") -> ECHEC | P11: =VLOOKUP($A11,[8]HISTOFEV21!$A$6:$AU$39,33,0) -> 0 | Q11: =IF(R11=0,0,($C$37-R11)) -> 0 | R11: =VLOOKUP($A11,[8]HISTOFEV21!$A$6:$AU$39,30,0) -> 0 | S11: =IF(R11=0,0,(R11-75000)) -> 0
A12: AS201619 | B12: =VLOOKUP(A12,[6]LISTADHERENT!A$5:H$60,3,0) -> KOUATCHO MESSACK | C12: =IF(E12="ECHEC",0,VLOOKUP($A12,[8]HISTOFEV21!$A$6:$AU$39,13,0)) -> 75000 | E12: =VLOOKUP($A12,[8]HISTOFEV21!$A$6:$AU$39,8,0) -> BANQUE | F12: =IF(N12="ECHEC",L12+(TONTJANV!I12*2),0) -> 206000 | G12: ECHEC | H12: =VLOOKUP($A12,[8]HISTOFEV21!$A$6:$AU$39,36,0) -> 0 | I12: =VLOOKUP($A12,[8]HISTOFEV21!$A$6:$AU$39,39,0) -> 0 | J12: =IF(H12<>0,VLOOKUP($A12,[8]HISTOFEV21!$A$6:$AU$39,8,0),"ECHEC") -> ECHEC | K12: =VLOOKUP($A12,[8]HISTOFEV21!$A$6:$AU$39,41,0) -> 0 | L12: =TONTJANV!H12+TONTJANV!I12 -> 202000 | M12: =VLOOKUP(A12,[8]HISTOFEV21!$A$6:$AZ$37,17,0) -> 0 | N12: =IF(M12<>0,VLOOKUP($A12,[8]HISTOFEV21!$A$6:$AU$39,8,0),"ECHEC") -> ECHEC | O12: =IF(R12<>0,VLOOKUP($A12,[8]HISTOFEV21!$A$6:$AU$39,8,0),"ECHEC") -> ECHEC | P12: =VLOOKUP($A12,[8]HISTOFEV21!$A$6:$AU$39,33,0) -> 0 | Q12: =IF(R12=0,0,($C$37-R12)) -> 0 | R12: =VLOOKUP($A12,[8]HISTOFEV21!$A$6:$AU$39,30,0) -> 0 | S12: =IF(R12=0,0,(R12-75000)) -> 0
A13: AS201621 | B13: =VLOOKUP(A13,[6]LISTADHERENT!A$5:H$60,3,0) -> NANKAM APPOLINAIRE | C13: =IF(E13="ECHEC",0,VLOOKUP($A13,[8]HISTOFEV21!$A$6:$AU$39,13,0)) -> 75000 | E13: =VLOOKUP($A13,[8]HISTOFEV21!$A$6:$AU$39,8,0) -> BANQUE | F13: =IF(N13="ECHEC",L13+(TONTJANV!I13*2),0) -> 0 | H13: =VLOOKUP($A13,[8]HISTOFEV21!$A$6:$AU$39,36,0) -> 0 | I13: =VLOOKUP($A13,[8]HISTOFEV21!$A$6:$AU$39,39,0) -> 0 | J13: =IF(H13<>0,VLOOKUP($A13,[8]HISTOFEV21!$A$6:$AU$39,8,0),"ECHEC") -> ECHEC | K13: =VLOOKUP($A13,[8]HISTOFEV21!$A$6:$AU$39,41,0) -> 0 | L13: =TONTJANV!H13+TONTJANV!I13 -> 0 | M13: =VLOOKUP(A13,[8]HISTOFEV21!$A$6:$AZ$37,17,0) -> 0 | N13: =IF(M13<>0,VLOOKUP($A13,[8]HISTOFEV21!$A$6:$AU$39,8,0),"ECHEC") -> ECHEC | O13: =IF(R13<>0,VLOOKUP($A13,[8]HISTOFEV21!$A$6:$AU$39,8,0),"ECHEC") -> ECHEC | P13: =VLOOKUP($A13,[8]HISTOFEV21!$A$6:$AU$39,33,0) -> 0 | Q13: =IF(R13=0,0,($C$37-R13)) -> 0 | R13: =VLOOKUP($A13,[8]HISTOFEV21!$A$6:$AU$39,30,0) -> 0 | S13: =IF(R13=0,0,(R13-75000)) -> 0
A14: AS201649 | B14: =VLOOKUP(A14,[6]LISTADHERENT!A$5:H$60,3,0) -> MBOGNING TUGMA GUY | C14: =IF(E14="ECHEC",0,VLOOKUP($A14,[8]HISTOFEV21!$A$6:$AU$39,13,0)) -> 225000 | E14: =VLOOKUP($A14,[8]HISTOFEV21!$A$6:$AU$39,8,0) -> BANQUE | F14: =IF(N14="ECHEC",L14+(TONTJANV!I14*2),0) -> 0 | H14: =VLOOKUP($A14,[8]HISTOFEV21!$A$6:$AU$39,36,0) -> 200000 | I14: =VLOOKUP($A14,[8]HISTOFEV21!$A$6:$AU$39,39,0) -> 2000 | J14: =IF(H14<>0,VLOOKUP($A14,[8]HISTOFEV21!$A$6:$AU$39,8,0),"ECHEC") -> BANQUE | K14: =VLOOKUP($A14,[8]HISTOFEV21!$A$6:$AU$39,41,0) -> 0 | L14: =TONTJANV!H14+TONTJANV!I14 -> 215000 | M14: =VLOOKUP(A14,[8]HISTOFEV21!$A$6:$AZ$37,17,0) -> 215000 | N14: =IF(M14<>0,VLOOKUP($A14,[8]HISTOFEV21!$A$6:$AU$39,8,0),"ECHEC") -> BANQUE | O14: =IF(R14<>0,VLOOKUP($A14,[8]HISTOFEV21!$A$6:$AU$39,8,0),"ECHEC") -> ECHEC | P14: =VLOOKUP($A14,[8]HISTOFEV21!$A$6:$AU$39,33,0) -> 0 | Q14: =IF(R14=0,0,($C$37-R14)) -> 0 | R14: =VLOOKUP($A14,[8]HISTOFEV21!$A$6:$AU$39,30,0) -> 0 | S14: =IF(R14=0,0,(R14-75000)) -> 0
A15: AS201649 | B15: =VLOOKUP(A15,[6]LISTADHERENT!A$5:H$60,3,0) -> MBOGNING TUGMA GUY | F15: =IF(N15="ECHEC",L15+(TONTJANV!I15*2),0) -> 0 | L15: =TONTJANV!H15+TONTJANV!I15 -> 0 | P15: =VLOOKUP($A15,[8]HISTOFEV21!$A$6:$AU$39,33,0) -> 0 | R15: =VLOOKUP($A15,[8]HISTOFEV21!$A$6:$AU$39,30,0) -> 0 | S15: =IF(R15=0,0,(R15-75000)) -> 0
A16: AS201649 | B16: =VLOOKUP(A16,[6]LISTADHERENT!A$5:H$60,3,0) -> MBOGNING TUGMA GUY | F16: =IF(N16="ECHEC",L16+(TONTJANV!I16*2),0) -> 0 | L16: =TONTJANV!H16+TONTJANV!I16 -> 0 | S16: =IF(R16=0,0,(R16-75000)) -> 0
A17: AS201626 | B17: =VLOOKUP(A17,[6]LISTADHERENT!A$5:H$60,3,0) -> NGUIEMEGNI MATHIEU BLAISE | C17: =IF(E17="ECHEC",0,VLOOKUP($A17,[8]HISTOFEV21!$A$6:$AU$39,13,0)) -> 150000 | E17: =VLOOKUP($A17,[8]HISTOFEV21!$A$6:$AU$39,8,0) -> BANQUE | F17: =IF(N17="ECHEC",L17+(TONTJANV!I17*2),0) -> 0 | H17: =VLOOKUP($A17,[8]HISTOFEV21!$A$6:$AU$39,36,0) -> 0 | I17: =VLOOKUP($A17,[8]HISTOFEV21!$A$6:$AU$39,39,0) -> 0 | J17: =IF(H17<>0,VLOOKUP($A17,[8]HISTOFEV21!$A$6:$AU$39,8,0),"ECHEC") -> ECHEC | K17: =VLOOKUP($A17,[8]HISTOFEV21!$A$6:$AU$39,41,0) -> 0 | L17: =TONTJANV!H17+TONTJANV!I17 -> 0 | M17: =VLOOKUP(A17,[8]HISTOFEV21!$A$6:$AZ$37,17,0) -> 0 | N17: =IF(M17<>0,VLOOKUP($A17,[8]HISTOFEV21!$A$6:$AU$39,8,0),"ECHEC") -> ECHEC | O17: =IF(R17<>0,VLOOKUP($A17,[8]HISTOFEV21!$A$6:$AU$39,8,0),"ECHEC") -> ECHEC | P17: =VLOOKUP($A17,[8]HISTOFEV21!$A$6:$AU$39,33,0) -> 0 | Q17: =IF(R17=0,0,($C$37-R17)) -> 0 | R17: =VLOOKUP($A17,[8]HISTOFEV21!$A$6:$AU$39,30,0) -> 0 | S17: =IF(R17=0,0,(R17-75000)) -> 0
A18: AS201626 | B18: =VLOOKUP(A18,[6]LISTADHERENT!A$5:H$60,3,0) -> NGUIEMEGNI MATHIEU BLAISE | F18: =IF(N18="ECHEC",L18+(TONTJANV!I18*2),0) -> 0 | L18: =TONTJANV!H18+TONTJANV!I18 -> 0 | N18: =IF(M18<>0,VLOOKUP($A18,[8]HISTOFEV21!$A$6:$AU$39,8,0),"ECHEC") -> ECHEC | O18: =IF(R18<>0,VLOOKUP($A18,[8]HISTOFEV21!$A$6:$AU$39,8,0),"ECHEC") -> ECHEC | S18: =IF(R18=0,0,(R18-75000)) -> 0
A19: AS201628 | B19: =VLOOKUP(A19,[6]LISTADHERENT!A$5:H$60,3,0) -> NKAMGANG JUSTIN DEJOLIE | C19: =IF(E19="ECHEC",0,VLOOKUP($A19,[8]HISTOFEV21!$A$6:$AU$39,13,0)) -> 75000 | E19: =VLOOKUP($A19,[8]HISTOFEV21!$A$6:$AU$39,8,0) -> ESPECES | F19: =IF(N19="ECHEC",L19+(TONTJANV!I19*2),0) -> 0 | H19: =VLOOKUP($A19,[8]HISTOFEV21!$A$6:$AU$39,36,0) -> 200000 | I19: =VLOOKUP($A19,[8]HISTOFEV21!$A$6:$AU$39,39,0) -> 2000 | J19: =IF(H19<>0,VLOOKUP($A19,[8]HISTOFEV21!$A$6:$AU$39,8,0),"ECHEC") -> ESPECES | K19: =VLOOKUP($A19,[8]HISTOFEV21!$A$6:$AU$39,41,0) -> 0 | L19: =TONTJANV!H19+TONTJANV!I19 -> 202000 | M19: =VLOOKUP(A19,[8]HISTOFEV21!$A$6:$AZ$37,17,0) -> 202000 | N19: =IF(M19<>0,VLOOKUP($A19,[8]HISTOFEV21!$A$6:$AU$39,8,0),"ECHEC") -> ESPECES | O19: =IF(R19<>0,VLOOKUP($A19,[8]HISTOFEV21!$A$6:$AU$39,8,0),"ECHEC") -> ECHEC | P19: =VLOOKUP($A19,[8]HISTOFEV21!$A$6:$AU$39,33,0) -> 0 | Q19: =IF(R19=0,0,($C$37-R19)) -> 0 | R19: =VLOOKUP($A19,[8]HISTOFEV21!$A$6:$AU$39,30,0) -> 0 | S19: =IF(R19=0,0,(R19-75000)) -> 0
A20: AS201633 | B20: =VLOOKUP(A20,[6]LISTADHERENT!A$5:H$60,3,0) -> PATEGO NJOSSU GUSTAVE | C20: =IF(E20="ECHEC",0,VLOOKUP($A20,[8]HISTOFEV21!$A$6:$AU$39,13,0)) -> 75000 | E20: =VLOOKUP($A20,[8]HISTOFEV21!$A$6:$AU$39,8,0) -> BANQUE | F20: =IF(N20="ECHEC",L20+(TONTJANV!I20*2),0) -> 0 | H20: =VLOOKUP($A20,[8]HISTOFEV21!$A$6:$AU$39,36,0) -> 0 | I20: =VLOOKUP($A20,[8]HISTOFEV21!$A$6:$AU$39,39,0) -> 0 | J20: =IF(H20<>0,VLOOKUP($A20,[8]HISTOFEV21!$A$6:$AU$39,8,0),"ECHEC") -> ECHEC | K20: =VLOOKUP($A20,[8]HISTOFEV21!$A$6:$AU$39,41,0) -> 0 | L20: =TONTJANV!H20+TONTJANV!I20 -> 0 | M20: =VLOOKUP(A20,[8]HISTOFEV21!$A$6:$AZ$37,17,0) -> 0 | N20: =IF(M20<>0,VLOOKUP($A20,[8]HISTOFEV21!$A$6:$AU$39,8,0),"ECHEC") -> ECHEC | O20: =IF(R20<>0,VLOOKUP($A20,[8]HISTOFEV21!$A$6:$AU$39,8,0),"ECHEC") -> ECHEC | P20: =VLOOKUP($A20,[8]HISTOFEV21!$A$6:$AU$39,33,0) -> 0 | Q20: =IF(R20=0,0,($C$37-R20)) -> 0 | R20: =VLOOKUP($A20,[8]HISTOFEV21!$A$6:$AU$39,30,0) -> 0 | S20: =IF(R20=0,0,(R20-75000)) -> 0
A21: AS201638 | B21: =VLOOKUP(A21,[6]LISTADHERENT!A$5:H$60,3,0) -> SIMO PIERRE | C21: =IF(E21="ECHEC",0,VLOOKUP($A21,[8]HISTOFEV21!$A$6:$AU$39,13,0)) -> 75000 | E21: =VLOOKUP($A21,[8]HISTOFEV21!$A$6:$AU$39,8,0) -> BANQUE | F21: =IF(N21="ECHEC",L21+(TONTJANV!I21*2),0) -> 0 | H21: =VLOOKUP($A21,[8]HISTOFEV21!$A$6:$AU$39,36,0) -> 0 | I21: =VLOOKUP($A21,[8]HISTOFEV21!$A$6:$AU$39,39,0) -> 0 | J21: =IF(H21<>0,VLOOKUP($A21,[8]HISTOFEV21!$A$6:$AU$39,8,0),"ECHEC") -> ECHEC | K21: =VLOOKUP($A21,[8]HISTOFEV21!$A$6:$AU$39,41,0) -> 0 | L21: =TONTJANV!H21+TONTJANV!I21 -> 0 | M21: =VLOOKUP(A21,[8]HISTOFEV21!$A$6:$AZ$37,17,0) -> 0 | N21: =IF(M21<>0,VLOOKUP($A21,[8]HISTOFEV21!$A$6:$AU$39,8,0),"ECHEC") -> ECHEC | O21: =IF(R21<>0,VLOOKUP($A21,[8]HISTOFEV21!$A$6:$AU$39,8,0),"ECHEC") -> ECHEC | P21: =VLOOKUP($A21,[8]HISTOFEV21!$A$6:$AU$39,33,0) -> 0 | Q21: =IF(R21=0,0,($C$37-R21)) -> 0 | R21: =VLOOKUP($A21,[8]HISTOFEV21!$A$6:$AU$39,30,0) -> 0 | S21: =IF(R21=0,0,(R21-75000)) -> 0
A22: AS201655 | B22: =VLOOKUP(A22,[6]LISTADHERENT!A$5:H$60,3,0) -> TCHEMHOU EMMANUEL | C22: =IF(E22="ECHEC",0,VLOOKUP($A22,[8]HISTOFEV21!$A$6:$AU$39,13,0)) -> 0 | F22: =IF(N22="ECHEC",L22+(TONTJANV!I22*2),0) -> 0 | H22: =VLOOKUP($A22,[8]HISTOFEV21!$A$6:$AU$39,36,0) -> 0 | I22: =VLOOKUP($A22,[8]HISTOFEV21!$A$6:$AU$39,39,0) -> 0 | J22: =IF(H22<>0,VLOOKUP($A22,[8]HISTOFEV21!$A$6:$AU$39,8,0),"ECHEC") -> ECHEC | K22: =VLOOKUP($A22,[8]HISTOFEV21!$A$6:$AU$39,41,0) -> 0 | L22: =TONTJANV!H22+TONTJANV!I22 -> 0 | M22: =VLOOKUP(A22,[8]HISTOFEV21!$A$6:$AZ$37,17,0) -> 0 | N22: =IF(M22<>0,VLOOKUP($A22,[8]HISTOFEV21!$A$6:$AU$39,8,0),"ECHEC") -> ECHEC | O22: =IF(R22<>0,VLOOKUP($A22,[8]HISTOFEV21!$A$6:$AU$39,8,0),"ECHEC") -> ECHEC | P22: =VLOOKUP($A22,[8]HISTOFEV21!$A$6:$AU$39,33,0) -> 0 | Q22: =IF(R22=0,0,($C$37-R22)) -> 0 | R22: =VLOOKUP($A22,[8]HISTOFEV21!$A$6:$AU$39,30,0) -> 0 | S22: =IF(R22=0,0,(R22-75000)) -> 0
A23: AS201647 | B23: =VLOOKUP(A23,[6]LISTADHERENT!A$5:H$60,3,0) -> YOUMBI EMMANUEL | C23: =IF(E23="ECHEC",0,VLOOKUP($A23,[8]HISTOFEV21!$A$6:$AU$39,13,0)) -> 150000 | E23: =VLOOKUP($A23,[8]HISTOFEV21!$A$6:$AU$39,8,0) -> BANQUE | F23: =IF(N23="ECHEC",L23+(TONTJANV!I23*2),0) -> 0 | H23: =VLOOKUP($A23,[8]HISTOFEV21!$A$6:$AU$39,36,0) -> 0 | I23: =VLOOKUP($A23,[8]HISTOFEV21!$A$6:$AU$39,39,0) -> 0 | J23: =IF(H23<>0,VLOOKUP($A23,[8]HISTOFEV21!$A$6:$AU$39,8,0),"ECHEC") -> ECHEC | K23: =VLOOKUP($A23,[8]HISTOFEV21!$A$6:$AU$39,41,0) -> 0 | L23: =TONTJANV!H23+TONTJANV!I23 -> 0 | N23: =IF(M23<>0,VLOOKUP($A23,[8]HISTOFEV21!$A$6:$AU$39,8,0),"ECHEC") -> ECHEC | O23: =IF(R23<>0,VLOOKUP($A23,[8]HISTOFEV21!$A$6:$AU$39,8,0),"ECHEC") -> ECHEC | P23: =VLOOKUP($A23,[8]HISTOFEV21!$A$6:$AU$39,33,0) -> 0 | Q23: =IF(R23=0,0,($C$37-R23)) -> 0 | R23: =VLOOKUP($A23,[8]HISTOFEV21!$A$6:$AU$39,30,0) -> 0 | S23: =IF(R23=0,0,(R23-75000)) -> 0
A24: AS201647 | B24: =VLOOKUP(A24,[6]LISTADHERENT!A$5:H$60,3,0) -> YOUMBI EMMANUEL | F24: =IF(N24="ECHEC",L24+(TONTJANV!I24*2),0) -> 0 | S24: =IF(R24=0,0,(R24-75000)) -> 0
S26: =SUM(S6:S24) -> 0
B27: TOTAL | C27: =SUM(C6:C26) -> 1275000 | D27: =SUM(D6:D26) -> 0 | E27: =SUM(E6:E26) -> 0 | F27: =SUM(F6:F26) -> 206000 | G27: =SUM(G6:G26) -> 0 | H27: =SUM(H6:H26) -> 400000 | I27: =SUM(I6:I26) -> 4000 | J27: =SUM(J6:J26) -> 0 | ... R27: =SUM(R6:R26) -> 75000
C29: TONTINE | D29: REMBOURSEMENT PETIT LOT | E29: VENTE PETIT LOT | F29: VENTE LOT PRINCIPAL | G29: SOLDE EN CAISSE | K29: TONTINE + REMB + INTERET VENTE | L29: =C34+D34+R27+TONTJANV!M34 -> 2171000
K30: LOT PRINCIPAL | L30: =C3*COUNTIF(Q6:Q26,">0") -> 1200000 | M30: =D3 -> 1
B31: ESPECES | C31: =SUMIFS(C6:C25,E6:E25,"ESPECES") -> 75000 | D31: =SUMIFS(L2:L21,N2:N21,"ESPECES")+SUMIFS(F2:F21,G2:G21,"ESPECES") -> 202000 | E31: =SUMIFS(H6:H25,J6:J25,"ESPECES") -> 200000 | F31: =SUMIFS(Q6:Q25,O6:O25,"ESPECES") -> 0 | G31: =C31+D31-E31-F31 -> 77000
B32: BANQUE | C32: =SUMIFS(C6:C25,E6:E25,"BANQUE") -> 1200000 | D32: =SUMIFS(M3:M22,N3:N22,"BANQUE")+SUMIFS(F3:F22,G3:G22,"BANQUE") -> 619000 | E32: =SUMIFS(H6:H25,J6:J25,"BANQUE") -> 200000 | F32: =SUMIFS(Q6:Q25,O6:O25,"BANQUE") -> 1125000 | G32: =C32+D32-E32-F32 -> 494000 | K32: PETIT LOT | L32: =L29-L30 -> 971000
B34: TOTAL | C34: =C31+C32 -> 1275000 | D34: =D31+D32 -> 821000 | E34: =E31+E32 -> 400000 | F34: =F31+F32 -> 1125000 | G34: =G31+G32 -> 571000 | K34: RELIQUAT | L34: =L32-H27 -> 571000 | M34: =L34+TONTJANV!M34 -> 571000 | N34: CUMUL
K36: ECHEC TONTINE | L36: =COUNTIFS(E3:E22,"ECHEC")*75000 -> 0 | M36: =L36+TONTJANV!M36 -> 0 | N36: CUMUL
B37: MONTANT TONTINE | C37: 1200000 | K37: ECHEC REMBOURSEMENT | L37: =SUMIFS(F3:F22,G3:G22,"ECHEC") -> 206000 | M37: =L37+TONTJANV!M37 -> 206000 | N37: CUMUL

Sheet TONTMARS
A1: ASSOCIATION | B1: ASELBY
A2: ANNEE | B2: 2021 | C2: TONIINE | D2: NBRE PART
A3: TAUX TONTINE | B3: 75000 | C3: =B3*16 -> 1200000 | D3: =ROUNDDOWN(L29/C3,0) -> 2
C4: 44276
A5: MATRICULE | B5: NOM ET PRENOM | C5: MONTANT TONTINE | D5: PENALITE | E5: MODE VERSEMENT TONTINE | F5: REPORT ECHEC PETIT LOT | G5: MODE VERSEMENT VENTE PETIT LOT | H5: VENTE PETIT LOT | I5: INTERET PETIT LOT | J5: MODE VERSEMENT VENTE PETIT LOT | K5: NUMERO CHEQUE | L5: MONTANT A REMBOURSER | M5: MONTANT REMBOURSE | N5: MODE VERSEMENT REMBOURSEMENT | O5: MODE VERSEMENT TONTINE PRINCIPAL | P5: NUMERO CHEQUE | Q5: MONTANT TONTINE LOT PRINCIPAL | R5: INTERET LOT PRINCIPAL | S5: INTERET DU
A6: AS201602 | B6: =VLOOKUP(A6,[6]LISTADHERENT!A$5:H$60,3,0) -> BOUTCHOUANG WILLIAM | C6: =IF(E6="ECHEC",0,VLOOKUP($A6,[8]HISTOMARS21!$A$6:$AU$39,13,0)) -> 75000 | E6: =VLOOKUP($A6,[8]HISTOMARS21!$A$6:$AU$39,8,0) -> BANQUE | F6: =IF(N6="ECHEC",L6+(TONTFEV!I6*2),0) -> 0 | H6: =VLOOKUP($A6,[8]HISTOMARS21!$A$6:$AU$39,36,0) -> 0 | I6: =VLOOKUP($A6,[8]HISTOMARS21!$A$6:$AU$39,39,0) -> 0 | J6: =IF(H6<>0,VLOOKUP($A6,[8]HISTOMARS21!$A$6:$AU$39,8,0),"ECHEC") -> ECHEC | K6: =VLOOKUP($A6,[8]HISTOMARS21!$A$6:$AU$39,41,0) -> 0 | L6: =TONTFEV!H6+TONTFEV!I6+TONTFEV!F6 -> 0 | M6: =VLOOKUP(A6,[8]HISTOMARS21!$A$6:$AZ$37,17,0) -> 0 | N6: =IF(L6<>0,VLOOKUP($A6,[8]HISTOMARS21!$A$6:$AU$39,8,0),"ECHEC") -> ECHEC | O6: =IF(R6<>0,VLOOKUP($A6,[8]HISTOMARS21!$A$6:$AU$39,8,0),"ECHEC") -> ECHEC | P6: =VLOOKUP($A6,[8]HISTOMARS21!$A$6:$AU$39,33,0) -> 0 | Q6: =IF(R6=0,0,($C$37-R6)) -> 0 | R6: =VLOOKUP($A6,[8]HISTOMARS21!$A$6:$AU$39,30,0) -> 0 | S6: =IF(R6=0,0,(R6-75000)) -> 0
A7: AS201603 | B7: =VLOOKUP(A7,[6]LISTADHERENT!A$5:H$60,3,0) -> CHINGUE FABRICE | F7: =IF(N7="ECHEC",L7+(TONTFEV!I7*2),0) -> 0 | L7: =TONTFEV!H7+TONTFEV!I7+TONTFEV!F7 -> 0 | S7: =IF(R7=0,0,(R7-75000)) -> 0
A8: AS201604 | B8: =VLOOKUP(A8,[6]LISTADHERENT!A$5:H$60,3,0) -> DJOMO JEAN PAUL | C8: =IF(E8="ECHEC",0,VLOOKUP($A8,[8]HISTOMARS21!$A$6:$AU$39,13,0)) -> 75000 | E8: =VLOOKUP($A8,[8]HISTOMARS21!$A$6:$AU$39,8,0) -> BANQUE | F8: =IF(N8="ECHEC",L8+(TONTFEV!I8*2),0) -> 0 | H8: =VLOOKUP($A8,[8]HISTOMARS21!$A$6:$AU$39,36,0) -> 50000 | I8: =VLOOKUP($A8,[8]HISTOMARS21!$A$6:$AU$39,39,0) -> 1000 | J8: =IF(H8<>0,VLOOKUP($A8,[8]HISTOMARS21!$A$6:$AU$39,8,0),"ECHEC") -> BANQUE | K8: =VLOOKUP($A8,[8]HISTOMARS21!$A$6:$AU$39,41,0) -> 0 | L8: =TONTFEV!H8+TONTFEV!I8+TONTFEV!F8 -> 0 | M8: =VLOOKUP(A8,[8]HISTOMARS21!$A$6:$AZ$37,17,0) -> 0 | N8: =IF(M8<>0,VLOOKUP($A8,[8]HISTOMARS21!$A$6:$AU$39,8,0),"ECHEC") -> ECHEC | O8: =IF(R8<>0,VLOOKUP($A8,[8]HISTOMARS21!$A$6:$AU$39,8,0),"ECHEC") -> ECHEC | P8: =VLOOKUP($A8,[8]HISTOMARS21!$A$6:$AU$39,33,0) -> 0 | Q8: =IF(R8=0,0,($C$37-R8)) -> 0 | R8: =VLOOKUP($A8,[8]HISTOMARS21!$A$6:$AU$39,30,0) -> 0 | S8: =IF(R8=0,0,(R8-75000)) -> 0
A9: AS201605 | B9: =VLOOKUP(A9,[6]LISTADHERENT!A$5:H$60,3,0) -> DJOUKWE NANGUEN GUY BLAISE | C9: =IF(E9="ECHEC",0,VLOOKUP($A9,[8]HISTOMARS21!$A$6:$AU$39,13,0)) -> 75000 | E9: =VLOOKUP($A9,[8]HISTOMARS21!$A$6:$AU$39,8,0) -> BANQUE | F9: =IF(N9="ECHEC",L9+(TONTFEV!I9*2),0) -> 0 | H9: =VLOOKUP($A9,[8]HISTOMARS21!$A$6:$AU$39,36,0) -> 56000 | I9: =VLOOKUP($A9,[8]HISTOMARS21!$A$6:$AU$39,39,0) -> 1000 | J9: =IF(H9<>0,VLOOKUP($A9,[8]HISTOMARS21!$A$6:$AU$39,8,0),"ECHEC") -> BANQUE | K9: =VLOOKUP($A9,[8]HISTOMARS21!$A$6:$AU$39,41,0) -> 0 | L9: =TONTFEV!H9+TONTFEV!I9+TONTFEV!F9 -> 0 | M9: =VLOOKUP(A9,[8]HISTOMARS21!$A$6:$AZ$37,17,0) -> 0 | N9: =IF(M9<>0,VLOOKUP($A9,[8]HISTOMARS21!$A$6:$AU$39,8,0),"ECHEC") -> ECHEC | O9: =IF(R9<>0,VLOOKUP($A9,[8]HISTOMARS21!$A$6:$AU$39,8,0),"ECHEC") -> ECHEC | P9: =VLOOKUP($A9,[8]HISTOMARS21!$A$6:$AU$39,33,0) -> 0 | Q9: =IF(R9=0,0,($C$37-R9)) -> 0 | R9: =VLOOKUP($A9,[8]HISTOMARS21!$A$6:$AU$39,30,0) -> 0 | S9: =IF(R9=0,0,(R9-75000)) -> 0
A10: AS201613 | B10: =VLOOKUP(A10,[6]LISTADHERENT!A$5:H$60,3,0) -> HOTCHO BENJAMIN | C10: =IF(E10="ECHEC",0,VLOOKUP($A10,[8]HISTOMARS21!$A$6:$AU$39,13,0)) -> 75000 | E10: =VLOOKUP($A10,[8]HISTOMARS21!$A$6:$AU$39,8,0) -> BANQUE | F10: =IF(N10="ECHEC",L10+(TONTFEV!I10*2),0) -> 0 | H10: =VLOOKUP($A10,[8]HISTOMARS21!$A$6:$AU$39,36,0) -> 0 | I10: =VLOOKUP($A10,[8]HISTOMARS21!$A$6:$AU$39,39,0) -> 0 | J10: =IF(H10<>0,VLOOKUP($A10,[8]HISTOMARS21!$A$6:$AU$39,8,0),"ECHEC") -> ECHEC | K10: =VLOOKUP($A10,[8]HISTOMARS21!$A$6:$AU$39,41,0) -> 0 | L10: =TONTFEV!H10+TONTFEV!I10+TONTFEV!F10 -> 0 | M10: =VLOOKUP(A10,[8]HISTOMARS21!$A$6:$AZ$37,17,0) -> 0 | N10: =IF(M10<>0,VLOOKUP($A10,[8]HISTOMARS21!$A$6:$AU$39,8,0),"ECHEC") -> ECHEC | O10: =IF(R10<>0,VLOOKUP($A10,[8]HISTOMARS21!$A$6:$AU$39,8,0),"ECHEC") -> ECHEC | P10: =VLOOKUP($A10,[8]HISTOMARS21!$A$6:$AU$39,33,0) -> 0 | Q10: =IF(R10=0,0,($C$37-R10)) -> 0 | R10: =VLOOKUP($A10,[8]HISTOMARS21!$A$6:$AU$39,30,0) -> 0 | S10: =IF(R10=0,0,(R10-75000)) -> 0
A11: AS201611 | B11: =VLOOKUP(A11,[6]LISTADHERENT!A$5:H$60,3,0) -> HENGUE PAUL OMER | C11: =IF(E11="ECHEC",0,VLOOKUP($A11,[8]HISTOMARS21!$A$6:$AU$39,13,0)) -> 75000 | E11: =VLOOKUP($A11,[8]HISTOMARS21!$A$6:$AU$39,8,0) -> BANQUE | F11: =IF(N11="ECHEC",L11+(TONTFEV!I11*2),0) -> 0 | H11: =VLOOKUP($A11,[8]HISTOMARS21!$A$6:$AU$39,36,0) -> 0 | I11: =VLOOKUP($A11,[8]HISTOMARS21!$A$6:$AU$39,39,0) -> 0 | J11: =IF(H11<>0,VLOOKUP($A11,[8]HISTOMARS21!$A$6:$AU$39,8,0),"ECHEC") -> ECHEC | K11: =VLOOKUP($A11,[8]HISTOMARS21!$A$6:$AU$39,41,0) -> 0 | L11: =TONTFEV!H11+TONTFEV!I11+TONTFEV!F11 -> 0 | M11: =VLOOKUP(A11,[8]HISTOMARS21!$A$6:$AZ$37,17,0) -> 0 | N11: =IF(M11<>0,VLOOKUP($A11,[8]HISTOMARS21!$A$6:$AU$39,8,0),"ECHEC") -> ECHEC | O11: =IF(R11<>0,VLOOKUP($A11,[8]HISTOMARS21!$A$6:$AU$39,8,0),"ECHEC") -> ECHEC | P11: =VLOOKUP($A11,[8]HISTOMARS21!$A$6:$AU$39,33,0) -> 0 | Q11: =IF(R11=0,0,($C$37-R11)) -> 0 | R11: =VLOOKUP($A11,[8]HISTOMARS21!$A$6:$AU$39,30,0) -> 0 | S11: =IF(R11=0,0,(R11-75000)) -> 0
A12: AS201619 | B12: =VLOOKUP(A12,[6]LISTADHERENT!A$5:H$60,3,0) -> KOUATCHO MESSACK | C12: =IF(E12="ECHEC",0,VLOOKUP($A12,[8]HISTOMARS21!$A$6:$AU$39,13,0)) -> 75000 | E12: =VLOOKUP($A12,[8]HISTOMARS21!$A$6:$AU$39,8,0) -> BANQUE | F12: =IF(N12="ECHEC",L12+(TONTFEV!I12*2),0) -> 0 | G12: BANQUE | H12: =VLOOKUP($A12,[8]HISTOMARS21!$A$6:$AU$39,36,0) -> 0 | I12: =VLOOKUP($A12,[8]HISTOMARS21!$A$6:$AU$39,39,0) -> 0 | J12: =IF(H12<>0,VLOOKUP($A12,[8]HISTOMARS21!$A$6:$AU$39,8,0),"ECHEC") -> ECHEC | K12: =VLOOKUP($A12,[8]HISTOMARS21!$A$6:$AU$39,41,0) -> 0 | L12: =TONTFEV!H12+TONTFEV!I12+TONTFEV!F12 -> 206000 | M12: =VLOOKUP(A12,[8]HISTOMARS21!$A$6:$AZ$37,17,0) -> 206000 | N12: =IF(M12<>0,VLOOKUP($A12,[8]HISTOMARS21!$A$6:$AU$39,8,0),"ECHEC") -> BANQUE | O12: =IF(R12<>0,VLOOKUP($A12,[8]HISTOMARS21!$A$6:$AU$39,8,0),"ECHEC") -> ECHEC | P12: =VLOOKUP($A12,[8]HISTOMARS21!$A$6:$AU$39,33,0) -> 0 | Q12: =IF(R12=0,0,($C$37-R12)) -> 0 | R12: =VLOOKUP($A12,[8]HISTOMARS21!$A$6:$AU$39,30,0) -> 0 | S12: =IF(R12=0,0,(R12-75000)) -> 0
A13: AS201621 | B13: =VLOOKUP(A13,[6]LISTADHERENT!A$5:H$60,3,0) -> NANKAM APPOLINAIRE | C13: =IF(E13="ECHEC",0,VLOOKUP($A13,[8]HISTOMARS21!$A$6:$AU$39,13,0)) -> 75000 | E13: =VLOOKUP($A13,[8]HISTOMARS21!$A$6:$AU$39,8,0) -> BANQUE | F13: =IF(N13="ECHEC",L13+(TONTFEV!I13*2),0) -> 0 | H13: =VLOOKUP($A13,[8]HISTOMARS21!$A$6:$AU$39,36,0) -> 0 | I13: =VLOOKUP($A13,[8]HISTOMARS21!$A$6:$AU$39,39,0) -> 0 | J13: =IF(H13<>0,VLOOKUP($A13,[8]HISTOMARS21!$A$6:$AU$39,8,0),"ECHEC") -> ECHEC | K13: =VLOOKUP($A13,[8]HISTOMARS21!$A$6:$AU$39,41,0) -> 0 | L13: =TONTFEV!H13+TONTFEV!I13+TONTFEV!F13 -> 0 | M13: =VLOOKUP(A13,[8]HISTOMARS21!$A$6:$AZ$37,17,0) -> 0 | N13: =IF(M13<>0,VLOOKUP($A13,[8]HISTOMARS21!$A$6:$AU$39,8,0),"ECHEC") -> ECHEC | O13: =IF(R13<>0,VLOOKUP($A13,[8]HISTOMARS21!$A$6:$AU$39,8,0),"ECHEC") -> ECHEC | P13: =VLOOKUP($A13,[8]HISTOMARS21!$A$6:$AU$39,33,0) -> 0 | Q13: =IF(R13=0,0,($C$37-R13)) -> 0 | R13: =VLOOKUP($A13,[8]HISTOMARS21!$A$6:$AU$39,30,0) -> 0 | S13: =IF(R13=0,0,(R13-75000)) -> 0
A14: AS201649 | B14: =VLOOKUP(A14,[6]LISTADHERENT!A$5:H$60,3,0) -> MBOGNING TUGMA GUY | C14: =IF(E14="ECHEC",0,VLOOKUP($A14,[8]HISTOMARS21!$A$6:$AU$39,13,0)) -> 225000 | E14: =VLOOKUP($A14,[8]HISTOMARS21!$A$6:$AU$39,8,0) -> BANQUE | F14: =IF(N14="ECHEC",L14+(TONTFEV!I14*2),0) -> 0 | H14: =VLOOKUP($A14,[8]HISTOMARS21!$A$6:$AU$39,36,0) -> 100000 | I14: =VLOOKUP($A14,[8]HISTOMARS21!$A$6:$AU$39,39,0) -> 2000 | J14: =IF(H14<>0,VLOOKUP($A14,[8]HISTOMARS21!$A$6:$AU$39,8,0),"ECHEC") -> BANQUE | K14: =VLOOKUP($A14,[8]HISTOMARS21!$A$6:$AU$39,41,0) -> 0 | L14: =TONTFEV!H14+TONTFEV!I14+TONTFEV!F14 -> 202000 | M14: =VLOOKUP(A14,[8]HISTOMARS21!$A$6:$AZ$37,17,0) -> 202000 | N14: =IF(M14<>0,VLOOKUP($A14,[8]HISTOMARS21!$A$6:$AU$39,8,0),"ECHEC") -> BANQUE | O14: =IF(R14<>0,VLOOKUP($A14,[8]HISTOMARS21!$A$6:$AU$39,8,0),"ECHEC") -> ECHEC | P14: =VLOOKUP($A14,[8]HISTOMARS21!$A$6:$AU$39,33,0) -> 0 | Q14: =IF(R14=0,0,($C$37-R14)) -> 0 | R14: =VLOOKUP($A14,[8]HISTOMARS21!$A$6:$AU$39,30,0) -> 0 | S14: =IF(R14=0,0,(R14-75000)) -> 0
A15: AS201649 | B15: =VLOOKUP(A15,[6]LISTADHERENT!A$5:H$60,3,0) -> MBOGNING TUGMA GUY | F15: =IF(N15="ECHEC",L15+(TONTFEV!I15*2),0) -> 0 | L15: =TONTFEV!H15+TONTFEV!I15+TONTFEV!F15 -> 0 | P15: =VLOOKUP($A15,[8]HISTOMARS21!$A$6:$AU$39,33,0) -> 0 | R15: =VLOOKUP($A15,[8]HISTOMARS21!$A$6:$AU$39,30,0) -> 0 | S15: =IF(R15=0,0,(R15-75000)) -> 0
A16: AS201649 | B16: =VLOOKUP(A16,[6]LISTADHERENT!A$5:H$60,3,0) -> MBOGNING TUGMA GUY | F16: =IF(N16="ECHEC",L16+(TONTFEV!I16*2),0) -> 0 | L16: =TONTFEV!H16+TONTFEV!I16+TONTFEV!F16 -> 0 | S16: =IF(R16=0,0,(R16-75000)) -> 0
A17: AS201626 | B17: =VLOOKUP(A17,[6]LISTADHERENT!A$5:H$60,3,0) -> NGUIEMEGNI MATHIEU BLAISE | C17: =IF(E17="ECHEC",0,VLOOKUP($A17,[8]HISTOMARS21!$A$6:$AU$39,13,0)) -> 150000 | E17: =VLOOKUP($A17,[8]HISTOMARS21!$A$6:$AU$39,8,0) -> BANQUE | F17: =IF(N17="ECHEC",L17+(TONTFEV!I17*2),0) -> 0 | H17: =VLOOKUP($A17,[8]HISTOMARS21!$A$6:$AU$39,36,0) -> 0 | I17: =VLOOKUP($A17,[8]HISTOMARS21!$A$6:$AU$39,39,0) -> 0 | J17: =IF(H17<>0,VLOOKUP($A17,[8]HISTOMARS21!$A$6:$AU$39,8,0),"ECHEC") -> ECHEC | K17: =VLOOKUP($A17,[8]HISTOMARS21!$A$6:$AU$39,41,0) -> 0 | L17: =TONTFEV!H17+TONTFEV!I17+TONTFEV!F17 -> 0 | M17: =VLOOKUP(A17,[8]HISTOMARS21!$A$6:$AZ$37,17,0) -> 0 | N17: =IF(M17<>0,VLOOKUP($A17,[8]HISTOMARS21!$A$6:$AU$39,8,0),"ECHEC") -> ECHEC | O17: =IF(R17<>0,VLOOKUP($A17,[8]HISTOMARS21!$A$6:$AU$39,8,0),"ECHEC") -> ECHEC | P17: =VLOOKUP($A17,[8]HISTOMARS21!$A$6:$AU$39,33,0) -> 0 | Q17: =IF(R17=0,0,($C$37-R17)) -> 0 | R17: =VLOOKUP($A17,[8]HISTOMARS21!$A$6:$AU$39,30,0) -> 0 | S17: =IF(R17=0,0,(R17-75000)) -> 0
A18: AS201626 | B18: =VLOOKUP(A18,[6]LISTADHERENT!A$5:H$60,3,0) -> NGUIEMEGNI MATHIEU BLAISE | F18: =IF(N18="ECHEC",L18+(TONTFEV!I18*2),0) -> 0 | L18: =TONTFEV!H18+TONTFEV!I18+TONTFEV!F18 -> 0 | N18: =IF(M18<>0,VLOOKUP($A18,[8]HISTOMARS21!$A$6:$AU$39,8,0),"ECHEC") -> ECHEC | O18: =IF(R18<>0,VLOOKUP($A18,[8]HISTOMARS21!$A$6:$AU$39,8,0),"ECHEC") -> ECHEC | S18: =IF(R18=0,0,(R18-75000)) -> 0
A19: AS201628 | B19: =VLOOKUP(A19,[6]LISTADHERENT!A$5:H$60,3,0) -> NKAMGANG JUSTIN DEJOLIE | C19: =IF(E19="ECHEC",0,VLOOKUP($A19,[8]HISTOMARS21!$A$6:$AU$39,13,0)) -> 75000 | E19: =VLOOKUP($A19,[8]HISTOMARS21!$A$6:$AU$39,8,0) -> ESPECES | F19: =IF(N19="ECHEC",L19+(TONTFEV!I19*2),0) -> 0 | H19: =VLOOKUP($A19,[8]HISTOMARS21!$A$6:$AU$39,36,0) -> 100000 | I19: =VLOOKUP($A19,[8]HISTOMARS21!$A$6:$AU$39,39,0) -> 2000 | J19: =IF(H19<>0,VLOOKUP($A19,[8]HISTOMARS21!$A$6:$AU$39,8,0),"ECHEC") -> ESPECES | K19: =VLOOKUP($A19,[8]HISTOMARS21!$A$6:$AU$39,41,0) -> 0 | L19: =TONTFEV!H19+TONTFEV!I19+TONTFEV!F19 -> 202000 | M19: =VLOOKUP(A19,[8]HISTOMARS21!$A$6:$AZ$37,17,0) -> 202000 | N19: =IF(M19<>0,VLOOKUP($A19,[8]HISTOMARS21!$A$6:$AU$39,8,0),"ECHEC") -> ESPECES | O19: =IF(R19<>0,VLOOKUP($A19,[8]HISTOMARS21!$A$6:$AU$39,8,0),"ECHEC") -> ECHEC | P19: =VLOOKUP($A19,[8]HISTOMARS21!$A$6:$AU$39,33,0) -> 0 | Q19: =IF(R19=0,0,($C$37-R19)) -> 0 | R19: =VLOOKUP($A19,[8]HISTOMARS21!$A$6:$AU$39,30,0) -> 0 | S19: =IF(R19=0,0,(R19-75000)) -> 0
A20: AS201633 | B20: =VLOOKUP(A20,[6]LISTADHERENT!A$5:H$60,3,0) -> PATEGO NJOSSU GUSTAVE | C20: =IF(E20="ECHEC",0,VLOOKUP($A20,[8]HISTOMARS21!$A$6:$AU$39,13,0)) -> 75000 | E20: =VLOOKUP($A20,[8]HISTOMARS21!$A$6:$AU$39,8,0) -> BANQUE | F20: =IF(N20="ECHEC",L20+(TONTFEV!I20*2),0) -> 0 | H20: =VLOOKUP($A20,[8]HISTOMARS21!$A$6:$AU$39,36,0) -> 0 | I20: =VLOOKUP($A20,[8]HISTOMARS21!$A$6:$AU$39,39,0) -> 0 | J20: =IF(H20<>0,VLOOKUP($A20,[8]HISTOMARS21!$A$6:$AU$39,8,0),"ECHEC") -> ECHEC | K20: =VLOOKUP($A20,[8]HISTOMARS21!$A$6:$AU$39,41,0) -> 0 | L20: =TONTFEV!H20+TONTFEV!I20+TONTFEV!F20 -> 0 | M20: =VLOOKUP(A20,[8]HISTOMARS21!$A$6:$AZ$37,17,0) -> 0 | N20: =IF(M20<>0,VLOOKUP($A20,[8]HISTOMARS21!$A$6:$AU$39,8,0),"ECHEC") -> ECHEC | O20: =IF(R20<>0,VLOOKUP($A20,[8]HISTOMARS21!$A$6:$AU$39,8,0),"ECHEC") -> ECHEC | P20: =VLOOKUP($A20,[8]HISTOMARS21!$A$6:$AU$39,33,0) -> 0 | Q20: =IF(R20=0,0,($C$37-R20)) -> 0 | R20: =VLOOKUP($A20,[8]HISTOMARS21!$A$6:$AU$39,30,0) -> 0 | S20: =IF(R20=0,0,(R20-75000)) -> 0
A21: AS201638 | B21: =VLOOKUP(A21,[6]LISTADHERENT!A$5:H$60,3,0) -> SIMO PIERRE | C21: =IF(E21="ECHEC",0,VLOOKUP($A21,[8]HISTOMARS21!$A$6:$AU$39,13,0)) -> 75000 | E21: =VLOOKUP($A21,[8]HISTOMARS21!$A$6:$AU$39,8,0) -> BANQUE | F21: =IF(N21="ECHEC",L21+(TONTFEV!I21*2),0) -> 0 | H21: =VLOOKUP($A21,[8]HISTOMARS21!$A$6:$AU$39,36,0) -> 0 | I21: =VLOOKUP($A21,[8]HISTOMARS21!$A$6:$AU$39,39,0) -> 0 | J21: =IF(H21<>0,VLOOKUP($A21,[8]HISTOMARS21!$A$6:$AU$39,8,0),"ECHEC") -> ECHEC | K21: =VLOOKUP($A21,[8]HISTOMARS21!$A$6:$AU$39,41,0) -> 0 | L21: =TONTFEV!H21+TONTFEV!I21+TONTFEV!F21 -> 0 | M21: =VLOOKUP(A21,[8]HISTOMARS21!$A$6:$AZ$37,17,0) -> 0 | N21: =IF(M21<>0,VLOOKUP($A21,[8]HISTOMARS21!$A$6:$AU$39,8,0),"ECHEC") -> ECHEC | O21: =IF(R21<>0,VLOOKUP($A21,[8]HISTOMARS21!$A$6:$AU$39,8,0),"ECHEC") -> BANQUE | P21: =VLOOKUP($A21,[8]HISTOMARS21!$A$6:$AU$39,33,0) -> 0 | Q21: =IF(R21=0,0,($C$37-R21)) -> 1125000 | R21: =VLOOKUP($A21,[8]HISTOMARS21!$A$6:$AU$39,30,0) -> 75000 | S21: =IF(R21=0,0,(R21-75000)) -> 0
A22: AS201655 | B22: =VLOOKUP(A22,[6]LISTADHERENT!A$5:H$60,3,0) -> TCHEMHOU EMMANUEL | C22: =IF(E22="ECHEC",0,VLOOKUP($A22,[8]HISTOMARS21!$A$6:$AU$39,13,0)) -> 0 | F22: =IF(N22="ECHEC",L22+(TONTFEV!I22*2),0) -> 0 | H22: =VLOOKUP($A22,[8]HISTOMARS21!$A$6:$AU$39,36,0) -> 0 | I22: =VLOOKUP($A22,[8]HISTOMARS21!$A$6:$AU$39,39,0) -> 0 | J22: =IF(H22<>0,VLOOKUP($A22,[8]HISTOMARS21!$A$6:$AU$39,8,0),"ECHEC") -> ECHEC | K22: =VLOOKUP($A22,[8]HISTOMARS21!$A$6:$AU$39,41,0) -> 0 | L22: =TONTFEV!H22+TONTFEV!I22+TONTFEV!F22 -> 0 | M22: =VLOOKUP(A22,[8]HISTOMARS21!$A$6:$AZ$37,17,0) -> 0 | N22: =IF(M22<>0,VLOOKUP($A22,[8]HISTOMARS21!$A$6:$AU$39,8,0),"ECHEC") -> ECHEC | O22: =IF(R22<>0,VLOOKUP($A22,[8]HISTOMARS21!$A$6:$AU$39,8,0),"ECHEC") -> ECHEC | P22: =VLOOKUP($A22,[8]HISTOMARS21!$A$6:$AU$39,33,0) -> 0 | Q22: =IF(R22=0,0,($C$37-R22)) -> 0 | R22: =VLOOKUP($A22,[8]HISTOMARS21!$A$6:$AU$39,30,0) -> 0 | S22: =IF(R22=0,0,(R22-75000)) -> 0
A23: AS201647 | B23: =VLOOKUP(A23,[6]LISTADHERENT!A$5:H$60,3,0) -> YOUMBI EMMANUEL | C23: =IF(E23="ECHEC",0,VLOOKUP($A23,[8]HISTOMARS21!$A$6:$AU$39,13,0)) -> 150000 | E23: =VLOOKUP($A23,[8]HISTOMARS21!$A$6:$AU$39,8,0) -> BANQUE | F23: =IF(N23="ECHEC",L23+(TONTFEV!I23*2),0) -> 0 | H23: =VLOOKUP($A23,[8]HISTOMARS21!$A$6:$AU$39,36,0) -> 0 | I23: =VLOOKUP($A23,[8]HISTOMARS21!$A$6:$AU$39,39,0) -> 0 | J23: =IF(H23<>0,VLOOKUP($A23,[8]HISTOMARS21!$A$6:$AU$39,8,0),"ECHEC") -> ECHEC | K23: =VLOOKUP($A23,[8]HISTOMARS21!$A$6:$AU$39,41,0) -> 0 | L23: =TONTFEV!H23+TONTFEV!I23+TONTFEV!F23 -> 0 | N23: =IF(M23<>0,VLOOKUP($A23,[8]HISTOMARS21!$A$6:$AU$39,8,0),"ECHEC") -> ECHEC | O23: =IF(R23<>0,VLOOKUP($A23,[8]HISTOMARS21!$A$6:$AU$39,8,0),"ECHEC") -> BANQUE | P23: =VLOOKUP($A23,[8]HISTOMARS21!$A$6:$AU$39,33,0) -> 0 | Q23: =IF(R23=0,0,($C$37-R23)) -> 1125000 | R23: =VLOOKUP($A23,[8]HISTOMARS21!$A$6:$AU$39,30,0) -> 75000 | S23: =IF(R23=0,0,(R23-75000)) -> 0
A24: AS201647 | B24: =VLOOKUP(A24,[6]LISTADHERENT!A$5:H$60,3,0) -> YOUMBI EMMANUEL | F24: =IF(N24="ECHEC",L24+(TONTFEV!I24*2),0) -> 0 | S24: =IF(R24=0,0,(R24-75000)) -> 0
S26: =SUM(S6:S24) -> 0
B27: TOTAL | C27: =SUM(C6:C26) -> 1275000 | D27: =SUM(D6:D26) -> 0 | E27: =SUM(E6:E26) -> 0 | F27: =SUM(F6:F26) -> 0 | G27: =SUM(G6:G26) -> 0 | H27: =SUM(H6:H26) -> 306000 | I27: =SUM(I6:I26) -> 6000 | J27: =SUM(J6:J26) -> 0 | ... R27: =SUM(R6:R26) -> 150000
C29: TONTINE | D29: REMBOURSEMENT PETIT LOT | E29: VENTE PETIT LOT | F29: VENTE LOT PRINCIPAL | G29: SOLDE EN CAISSE | K29: TONTINE + REMB + INTERET VENTE | L29: =C34+D34+R27+TONTFEV!M34 -> 2606000
K30: LOT PRINCIPAL | L30: =C3*COUNTIF(Q6:Q26,">0") -> 2400000 | M30: =D3 -> 2
B31: ESPECES | C31: =SUMIFS(C6:C25,E6:E25,"ESPECES") -> 75000 | D31: =SUMIFS(L2:L21,N2:N21,"ESPECES")+SUMIFS(F2:F21,G2:G21,"ESPECES") -> 202000 | E31: =SUMIFS(H6:H25,J6:J25,"ESPECES") -> 100000 | F31: =SUMIFS(Q6:Q25,O6:O25,"ESPECES") -> 0 | G31: =C31+D31-E31-F31 -> 177000
B32: BANQUE | C32: =SUMIFS(C6:C25,E6:E25,"BANQUE") -> 1200000 | D32: =SUMIFS(M3:M22,N3:N22,"BANQUE")+SUMIFS(F3:F22,G3:G22,"BANQUE") -> 408000 | E32: =SUMIFS(H6:H25,J6:J25,"BANQUE") -> 206000 | F32: =SUMIFS(Q6:Q25,O6:O25,"BANQUE") -> 2250000 | G32: =C32+D32-E32-F32 -> -848000 | K32: PETIT LOT | L32: =L29-L30 -> 206000
B34: TOTAL | C34: =C31+C32 -> 1275000 | D34: =D31+D32 -> 610000 | E34: =E31+E32 -> 306000 | F34: =F31+F32 -> 2250000 | G34: =G31+G32 -> -671000 | K34: RELIQUAT | L34: =L32-H27 -> -100000 | M34: =L34 -> -100000 | N34: CUMUL
K36: ECHEC TONTINE | L36: =COUNTIFS(E6:E25,"ECHEC")*75000 -> 0 | M36: =L36+TONTFEV!M36 -> 0 | N36: CUMUL
B37: MONTANT TONTINE | C37: 1200000 | K37: ECHEC REMBOURSEMENT | L37: =SUMIFS(F3:F22,G3:G22,"ECHEC") -> 0 | M37: =L37+TONTFEV!M37-206000 -> 0 | N37: CUMUL

Sheet TONTAVRIL
A1: ASSOCIATION | B1: ASELBY
A2: ANNEE | B2: 2021 | C2: TONIINE | D2: NBRE PART
A3: TAUX TONTINE | B3: 75000 | C3: =B3*16 -> 1200000 | D3: =ROUNDDOWN(L29/C3,0) -> 1
C4: 44307
A5: MATRICULE | B5: NOM ET PRENOM | C5: MONTANT TONTINE | D5: PENALITE | E5: MODE VERSEMENT TONTINE | F5: REPORT ECHEC PETIT LOT | G5: MODE VERSEMENT VENTE PETIT LOT | H5: VENTE PETIT LOT | I5: INTERET PETIT LOT | J5: MODE VERSEMENT VENTE PETIT LOT | K5: NUMERO CHEQUE | L5: MONTANT A REMBOURSER | M5: MONTANT REMBOURSE | N5: MODE VERSEMENT REMBOURSEMENT | O5: MODE VERSEMENT TONTINE PRINCIPAL | P5: NUMERO CHEQUE | Q5: MONTANT TONTINE LOT PRINCIPAL | R5: INTERET LOT PRINCIPAL | S5: INTERET DU
A6: AS201602 | B6: =VLOOKUP(A6,[6]LISTADHERENT!A$5:H$60,3,0) -> BOUTCHOUANG WILLIAM | C6: =IF(E6="ECHEC",0,VLOOKUP($A6,[8]HISTOAVRIL21!$A$6:$AU$39,13,0)) -> 75000 | E6: =VLOOKUP($A6,[8]HISTOAVRIL21!$A$6:$AU$39,8,0) -> BANQUE | F6: =IF(N6="ECHEC",L6+(TONTMARS!I6*2),0) -> 0 | H6: =VLOOKUP($A6,[8]HISTOAVRIL21!$A$6:$AU$39,36,0) -> 0 | I6: =VLOOKUP($A6,[8]HISTOAVRIL21!$A$6:$AU$39,39,0) -> 0 | J6: =IF(H6<>0,VLOOKUP($A6,[8]HISTOAVRIL21!$A$6:$AU$39,8,0),"ECHEC") -> ECHEC | K6: =VLOOKUP($A6,[8]HISTOAVRIL21!$A$6:$AU$39,41,0) -> 0 | L6: =TONTMARS!H6+TONTMARS!I6+TONTMARS!F6 -> 0 | M6: =VLOOKUP(A6,[8]HISTOAVRIL21!$A$6:$AZ$37,17,0) -> 0 | N6: =IF(L6<>0,VLOOKUP($A6,[8]HISTOAVRIL21!$A$6:$AU$39,8,0),"ECHEC") -> ECHEC | O6: =IF(R6<>0,VLOOKUP($A6,[8]HISTOAVRIL21!$A$6:$AU$39,8,0),"ECHEC") -> BANQUE | P6: =VLOOKUP($A6,[8]HISTOAVRIL21!$A$6:$AU$39,33,0) -> 0 | Q6: =IF(R6=0,0,($C$37-R6)) -> 1125000 | R6: =VLOOKUP($A6,[8]HISTOAVRIL21!$A$6:$AU$39,30,0) -> 75000 | S6: =IF(R6=0,0,(R6-75000)) -> 0
A7: AS201603 | B7: =VLOOKUP(A7,[6]LISTADHERENT!A$5:H$60,3,0) -> CHINGUE FABRICE | F7: =IF(N7="ECHEC",L7+(TONTMARS!I7*2),0) -> 0 | L7: =TONTMARS!H7+TONTMARS!I7+TONTMARS!F7 -> 0 | S7: =IF(R7=0,0,(R7-75000)) -> 0
A8: AS201604 | B8: =VLOOKUP(A8,[6]LISTADHERENT!A$5:H$60,3,0) -> DJOMO JEAN PAUL | C8: =IF(E8="ECHEC",0,VLOOKUP($A8,[8]HISTOAVRIL21!$A$6:$AU$39,13,0)) -> 75000 | E8: =VLOOKUP($A8,[8]HISTOAVRIL21!$A$6:$AU$39,8,0) -> BANQUE | F8: =IF(N8="ECHEC",L8+(TONTMARS!I8*2),0) -> 0 | H8: =VLOOKUP($A8,[8]HISTOAVRIL21!$A$6:$AU$39,36,0) -> 100000 | I8: =VLOOKUP($A8,[8]HISTOAVRIL21!$A$6:$AU$39,39,0) -> 2500 | J8: =IF(H8<>0,VLOOKUP($A8,[8]HISTOAVRIL21!$A$6:$AU$39,8,0),"ECHEC") -> BANQUE | K8: =VLOOKUP($A8,[8]HISTOAVRIL21!$A$6:$AU$39,41,0) -> 0 | L8: =TONTMARS!H8+TONTMARS!I8+TONTMARS!F8 -> 51000 | M8: =VLOOKUP(A8,[8]HISTOAVRIL21!$A$6:$AZ$37,17,0) -> 51000 | N8: =IF(M8<>0,VLOOKUP($A8,[8]HISTOAVRIL21!$A$6:$AU$39,8,0),"ECHEC") -> BANQUE | O8: =IF(R8<>0,VLOOKUP($A8,[8]HISTOAVRIL21!$A$6:$AU$39,8,0),"ECHEC") -> ECHEC | P8: =VLOOKUP($A8,[8]HISTOAVRIL21!$A$6:$AU$39,33,0) -> 0 | Q8: =IF(R8=0,0,($C$37-R8)) -> 0 | R8: =VLOOKUP($A8,[8]HISTOAVRIL21!$A$6:$AU$39,30,0) -> 0 | S8: =IF(R8=0,0,(R8-75000)) -> 0
A9: AS201605 | B9: =VLOOKUP(A9,[6]LISTADHERENT!A$5:H$60,3,0) -> DJOUKWE NANGUEN GUY BLAISE | C9: =IF(E9="ECHEC",0,VLOOKUP($A9,[8]HISTOAVRIL21!$A$6:$AU$39,13,0)) -> 75000 | E9: =VLOOKUP($A9,[8]HISTOAVRIL21!$A$6:$AU$39,8,0) -> BANQUE | F9: =IF(N9="ECHEC",L9+(TONTMARS!I9*2),0) -> 0 | H9: =VLOOKUP($A9,[8]HISTOAVRIL21!$A$6:$AU$39,36,0) -> 0 | I9: =VLOOKUP($A9,[8]HISTOAVRIL21!$A$6:$AU$39,39,0) -> 0 | J9: =IF(H9<>0,VLOOKUP($A9,[8]HISTOAVRIL21!$A$6:$AU$39,8,0),"ECHEC") -> ECHEC | K9: =VLOOKUP($A9,[8]HISTOAVRIL21!$A$6:$AU$39,41,0) -> 0 | L9: =TONTMARS!H9+TONTMARS!I9+TONTMARS!F9 -> 57000 | M9: =VLOOKUP(A9,[8]HISTOAVRIL21!$A$6:$AZ$37,17,0) -> 57000 | N9: =IF(M9<>0,VLOOKUP($A9,[8]HISTOAVRIL21!$A$6:$AU$39,8,0),"ECHEC") -> BANQUE | O9: =IF(R9<>0,VLOOKUP($A9,[8]HISTOAVRIL21!$A$6:$AU$39,8,0),"ECHEC") -> ECHEC | P9: =VLOOKUP($A9,[8]HISTOAVRIL21!$A$6:$AU$39,33,0) -> 0 | Q9: =IF(R9=0,0,($C$37-R9)) -> 0 | R9: =VLOOKUP($A9,[8]HISTOAVRIL21!$A$6:$AU$39,30,0) -> 0 | S9: =IF(R9=0,0,(R9-75000)) -> 0
A10: AS201613 | B10: =VLOOKUP(A10,[6]LISTADHERENT!A$5:H$60,3,0) -> HOTCHO BENJAMIN | C10: =IF(E10="ECHEC",0,VLOOKUP($A10,[8]HISTOAVRIL21!$A$6:$AU$39,13,0)) -> 75000 | E10: =VLOOKUP($A10,[8]HISTOAVRIL21!$A$6:$AU$39,8,0) -> BANQUE | F10: =IF(N10="ECHEC",L10+(TONTMARS!I10*2),0) -> 0 | H10: =VLOOKUP($A10,[8]HISTOAVRIL21!$A$6:$AU$39,36,0) -> 0 | I10: =VLOOKUP($A10,[8]HISTOAVRIL21!$A$6:$AU$39,39,0) -> 0 | J10: =IF(H10<>0,VLOOKUP($A10,[8]HISTOAVRIL21!$A$6:$AU$39,8,0),"ECHEC") -> ECHEC | K10: =VLOOKUP($A10,[8]HISTOAVRIL21!$A$6:$AU$39,41,0) -> 0 | L10: =TONTMARS!H10+TONTMARS!I10+TONTMARS!F10 -> 0 | M10: =VLOOKUP(A10,[8]HISTOAVRIL21!$A$6:$AZ$37,17,0) -> 0 | N10: =IF(M10<>0,VLOOKUP($A10,[8]HISTOAVRIL21!$A$6:$AU$39,8,0),"ECHEC") -> ECHEC | O10: =IF(R10<>0,VLOOKUP($A10,[8]HISTOAVRIL21!$A$6:$AU$39,8,0),"ECHEC") -> ECHEC | P10: =VLOOKUP($A10,[8]HISTOAVRIL21!$A$6:$AU$39,33,0) -> 0 | Q10: =IF(R10=0,0,($C$37-R10)) -> 0 | R10: =VLOOKUP($A10,[8]HISTOAVRIL21!$A$6:$AU$39,30,0) -> 0 | S10: =IF(R10=0,0,(R10-75000)) -> 0
A11: AS201611 | B11: =VLOOKUP(A11,[6]LISTADHERENT!A$5:H$60,3,0) -> HENGUE PAUL OMER | C11: =IF(E11="ECHEC",0,VLOOKUP($A11,[8]HISTOAVRIL21!$A$6:$AU$39,13,0)) -> 75000 | E11: =VLOOKUP($A11,[8]HISTOAVRIL21!$A$6:$AU$39,8,0) -> BANQUE | F11: =IF(N11="ECHEC",L11+(TONTMARS!I11*2),0) -> 0 | H11: =VLOOKUP($A11,[8]HISTOAVRIL21!$A$6:$AU$39,36,0) -> 0 | I11: =VLOOKUP($A11,[8]HISTOAVRIL21!$A$6:$AU$39,39,0) -> 0 | J11: =IF(H11<>0,VLOOKUP($A11,[8]HISTOAVRIL21!$A$6:$AU$39,8,0),"ECHEC") -> ECHEC | K11: =VLOOKUP($A11,[8]HISTOAVRIL21!$A$6:$AU$39,41,0) -> 0 | L11: =TONTMARS!H11+TONTMARS!I11+TONTMARS!F11 -> 0 | M11: =VLOOKUP(A11,[8]HISTOAVRIL21!$A$6:$AZ$37,17,0) -> 0 | N11: =IF(M11<>0,VLOOKUP($A11,[8]HISTOAVRIL21!$A$6:$AU$39,8,0),"ECHEC") -> ECHEC | O11: =IF(R11<>0,VLOOKUP($A11,[8]HISTOAVRIL21!$A$6:$AU$39,8,0),"ECHEC") -> ECHEC | P11: =VLOOKUP($A11,[8]HISTOAVRIL21!$A$6:$AU$39,33,0) -> 0 | Q11: =IF(R11=0,0,($C$37-R11)) -> 0 | R11: =VLOOKUP($A11,[8]HISTOAVRIL21!$A$6:$AU$39,30,0) -> 0 | S11: =IF(R11=0,0,(R11-75000)) -> 0
A12: AS201619 | B12: =VLOOKUP(A12,[6]LISTADHERENT!A$5:H$60,3,0) -> KOUATCHO MESSACK | C12: =IF(E12="ECHEC",0,VLOOKUP($A12,[8]HISTOAVRIL21!$A$6:$AU$39,13,0)) -> 75000 | E12: =VLOOKUP($A12,[8]HISTOAVRIL21!$A$6:$AU$39,8,0) -> BANQUE | F12: =IF(N12="ECHEC",L12+(TONTMARS!I12*2),0) -> 0 | H12: =VLOOKUP($A12,[8]HISTOAVRIL21!$A$6:$AU$39,36,0) -> 0 | I12: =VLOOKUP($A12,[8]HISTOAVRIL21!$A$6:$AU$39,39,0) -> 0 | J12: =IF(H12<>0,VLOOKUP($A12,[8]HISTOAVRIL21!$A$6:$AU$39,8,0),"ECHEC") -> ECHEC | K12: =VLOOKUP($A12,[8]HISTOAVRIL21!$A$6:$AU$39,41,0) -> 0 | L12: =TONTMARS!H12+TONTMARS!I12+TONTMARS!F12 -> 0 | M12: =VLOOKUP(A12,[8]HISTOAVRIL21!$A$6:$AZ$37,17,0) -> 0 | N12: =IF(M12<>0,VLOOKUP($A12,[8]HISTOAVRIL21!$A$6:$AU$39,8,0),"ECHEC") -> ECHEC | O12: =IF(R12<>0,VLOOKUP($A12,[8]HISTOAVRIL21!$A$6:$AU$39,8,0),"ECHEC") -> ECHEC | P12: =VLOOKUP($A12,[8]HISTOAVRIL21!$A$6:$AU$39,33,0) -> 0 | Q12: =IF(R12=0,0,($C$37-R12)) -> 0 | R12: =VLOOKUP($A12,[8]HISTOAVRIL21!$A$6:$AU$39,30,0) -> 0 | S12: =IF(R12=0,0,(R12-75000)) -> 0
A13: AS201621 | B13: =VLOOKUP(A13,[6]LISTADHERENT!A$5:H$60,3,0) -> NANKAM APPOLINAIRE | C13: =IF(E13="ECHEC",0,VLOOKUP($A13,[8]HISTOAVRIL21!$A$6:$AU$39,13,0)) -> 75000 | E13: =VLOOKUP($A13,[8]HISTOAVRIL21!$A$6:$AU$39,8,0) -> BANQUE | F13: =IF(N13="ECHEC",L13+(TONTMARS!I13*2),0) -> 0 | H13: =VLOOKUP($A13,[8]HISTOAVRIL21!$A$6:$AU$39,36,0) -> 0 | I13: =VLOOKUP($A13,[8]HISTOAVRIL21!$A$6:$AU$39,39,0) -> 0 | J13: =IF(H13<>0,VLOOKUP($A13,[8]HISTOAVRIL21!$A$6:$AU$39,8,0),"ECHEC") -> ECHEC | K13: =VLOOKUP($A13,[8]HISTOAVRIL21!$A$6:$AU$39,41,0) -> 0 | L13: =TONTMARS!H13+TONTMARS!I13+TONTMARS!F13 -> 0 | M13: =VLOOKUP(A13,[8]HISTOAVRIL21!$A$6:$AZ$37,17,0) -> 0 | N13: =IF(M13<>0,VLOOKUP($A13,[8]HISTOAVRIL21!$A$6:$AU$39,8,0),"ECHEC") -> ECHEC | O13: =IF(R13<>0,VLOOKUP($A13,[8]HISTOAVRIL21!$A$6:$AU$39,8,0),"ECHEC") -> ECHEC | P13: =VLOOKUP($A13,[8]HISTOAVRIL21!$A$6:$AU$39,33,0) -> 0 | Q13: =IF(R13=0,0,($C$37-R13)) -> 0 | R13: =VLOOKUP($A13,[8]HISTOAVRIL21!$A$6:$AU$39,30,0) -> 0 | S13: =IF(R13=0,0,(R13-75000)) -> 0
A14: AS201649 | B14: =VLOOKUP(A14,[6]LISTADHERENT!A$5:H$60,3,0) -> MBOGNING TUGMA GUY | C14: =IF(E14="ECHEC",0,VLOOKUP($A14,[8]HISTOAVRIL21!$A$6:$AU$39,13,0)) -> 225000 | E14: =VLOOKUP($A14,[8]HISTOAVRIL21!$A$6:$AU$39,8,0) -> BANQUE | F14: =IF(N14="ECHEC",L14+(TONTMARS!I14*2),0) -> 0 | H14: =VLOOKUP($A14,[8]HISTOAVRIL21!$A$6:$AU$39,36,0) -> 112000 | I14: =VLOOKUP($A14,[8]HISTOAVRIL21!$A$6:$AU$39,39,0) -> 3000 | J14: =IF(H14<>0,VLOOKUP($A14,[8]HISTOAVRIL21!$A$6:$AU$39,8,0),"ECHEC") -> BANQUE | K14: =VLOOKUP($A14,[8]HISTOAVRIL21!$A$6:$AU$39,41,0) -> 0 | L14: =TONTMARS!H14+TONTMARS!I14+TONTMARS!F14 -> 102000 | M14: =VLOOKUP(A14,[8]HISTOAVRIL21!$A$6:$AZ$37,17,0) -> 102000 | N14: =IF(M14<>0,VLOOKUP($A14,[8]HISTOAVRIL21!$A$6:$AU$39,8,0),"ECHEC") -> BANQUE | O14: =IF(R14<>0,VLOOKUP($A14,[8]HISTOAVRIL21!$A$6:$AU$39,8,0),"ECHEC") -> ECHEC | P14: =VLOOKUP($A14,[8]HISTOAVRIL21!$A$6:$AU$39,33,0) -> 0 | Q14: =IF(R14=0,0,($C$37-R14)) -> 0 | R14: =VLOOKUP($A14,[8]HISTOAVRIL21!$A$6:$AU$39,30,0) -> 0 | S14: =IF(R14=0,0,(R14-75000)) -> 0
A15: AS201649 | B15: =VLOOKUP(A15,[6]LISTADHERENT!A$5:H$60,3,0) -> MBOGNING TUGMA GUY | F15: =IF(N15="ECHEC",L15+(TONTMARS!I15*2),0) -> 0 | L15: =TONTMARS!H15+TONTMARS!I15+TONTMARS!F15 -> 0 | P15: =VLOOKUP($A15,[8]HISTOAVRIL21!$A$6:$AU$39,33,0) -> 0 | R15: =VLOOKUP($A15,[8]HISTOAVRIL21!$A$6:$AU$39,30,0) -> 0 | S15: =IF(R15=0,0,(R15-75000)) -> 0
A16: AS201649 | B16: =VLOOKUP(A16,[6]LISTADHERENT!A$5:H$60,3,0) -> MBOGNING TUGMA GUY | F16: =IF(N16="ECHEC",L16+(TONTMARS!I16*2),0) -> 0 | L16: =TONTMARS!H16+TONTMARS!I16+TONTMARS!F16 -> 0 | S16: =IF(R16=0,0,(R16-75000)) -> 0
A17: AS201626 | B17: =VLOOKUP(A17,[6]LISTADHERENT!A$5:H$60,3,0) -> NGUIEMEGNI MATHIEU BLAISE | C17: =IF(E17="ECHEC",0,VLOOKUP($A17,[8]HISTOAVRIL21!$A$6:$AU$39,13,0)) -> 150000 | E17: =VLOOKUP($A17,[8]HISTOAVRIL21!$A$6:$AU$39,8,0) -> BANQUE | F17: =IF(N17="ECHEC",L17+(TONTMARS!I17*2),0) -> 0 | H17: =VLOOKUP($A17,[8]HISTOAVRIL21!$A$6:$AU$39,36,0) -> 50000 | I17: =VLOOKUP($A17,[8]HISTOAVRIL21!$A$6:$AU$39,39,0) -> 1000 | J17: =IF(H17<>0,VLOOKUP($A17,[8]HISTOAVRIL21!$A$6:$AU$39,8,0),"ECHEC") -> BANQUE | K17: =VLOOKUP($A17,[8]HISTOAVRIL21!$A$6:$AU$39,41,0) -> 0 | L17: =TONTMARS!H17+TONTMARS!I17+TONTMARS!F17 -> 0 | M17: =VLOOKUP(A17,[8]HISTOAVRIL21!$A$6:$AZ$37,17,0) -> 0 | N17: =IF(M17<>0,VLOOKUP($A17,[8]HISTOAVRIL21!$A$6:$AU$39,8,0),"ECHEC") -> ECHEC | O17: =IF(R17<>0,VLOOKUP($A17,[8]HISTOAVRIL21!$A$6:$AU$39,8,0),"ECHEC") -> ECHEC | P17: =VLOOKUP($A17,[8]HISTOAVRIL21!$A$6:$AU$39,33,0) -> 0 | Q17: =IF(R17=0,0,($C$37-R17)) -> 0 | R17: =VLOOKUP($A17,[8]HISTOAVRIL21!$A$6:$AU$39,30,0) -> 0 | S17: =IF(R17=0,0,(R17-75000)) -> 0
A18: AS201626 | B18: =VLOOKUP(A18,[6]LISTADHERENT!A$5:H$60,3,0) -> NGUIEMEGNI MATHIEU BLAISE | F18: =IF(N18="ECHEC",L18+(TONTMARS!I18*2),0) -> 0 | L18: =TONTMARS!H18+TONTMARS!I18+TONTMARS!F18 -> 0 | N18: =IF(M18<>0,VLOOKUP($A18,[8]HISTOAVRIL21!$A$6:$AU$39,8,0),"ECHEC") -> ECHEC | O18: =IF(R18<>0,VLOOKUP($A18,[8]HISTOAVRIL21!$A$6:$AU$39,8,0),"ECHEC") -> ECHEC | S18: =IF(R18=0,0,(R18-75000)) -> 0
A19: AS201628 | B19: =VLOOKUP(A19,[6]LISTADHERENT!A$5:H$60,3,0) -> NKAMGANG JUSTIN DEJOLIE | C19: =IF(E19="ECHEC",0,VLOOKUP($A19,[8]HISTOAVRIL21!$A$6:$AU$39,13,0)) -> 75000 | E19: =VLOOKUP($A19,[8]HISTOAVRIL21!$A$6:$AU$39,8,0) -> ESPECES | F19: =IF(N19="ECHEC",L19+(TONTMARS!I19*2),0) -> 0 | H19: =VLOOKUP($A19,[8]HISTOAVRIL21!$A$6:$AU$39,36,0) -> 100000 | I19: =VLOOKUP($A19,[8]HISTOAVRIL21!$A$6:$AU$39,39,0) -> 2000 | J19: =IF(H19<>0,VLOOKUP($A19,[8]HISTOAVRIL21!$A$6:$AU$39,8,0),"ECHEC") -> ESPECES | K19: =VLOOKUP($A19,[8]HISTOAVRIL21!$A$6:$AU$39,41,0) -> 0 | L19: =TONTMARS!H19+TONTMARS!I19+TONTMARS!F19 -> 102000 | M19: =VLOOKUP(A19,[8]HISTOAVRIL21!$A$6:$AZ$37,17,0) -> 102000 | N19: =IF(M19<>0,VLOOKUP($A19,[8]HISTOAVRIL21!$A$6:$AU$39,8,0),"ECHEC") -> ESPECES | O19: =IF(R19<>0,VLOOKUP($A19,[8]HISTOAVRIL21!$A$6:$AU$39,8,0),"ECHEC") -> ECHEC | P19: =VLOOKUP($A19,[8]HISTOAVRIL21!$A$6:$AU$39,33,0) -> 0 | Q19: =IF(R19=0,0,($C$37-R19)) -> 0 | R19: =VLOOKUP($A19,[8]HISTOAVRIL21!$A$6:$AU$39,30,0) -> 0 | S19: =IF(R19=0,0,(R19-75000)) -> 0
A20: AS201633 | B20: =VLOOKUP(A20,[6]LISTADHERENT!A$5:H$60,3,0) -> PATEGO NJOSSU GUSTAVE | C20: =IF(E20="ECHEC",0,VLOOKUP($A20,[8]HISTOAVRIL21!$A$6:$AU$39,13,0)) -> 75000 | E20: =VLOOKUP($A20,[8]HISTOAVRIL21!$A$6:$AU$39,8,0) -> BANQUE | F20: =IF(N20="ECHEC",L20+(TONTMARS!I20*2),0) -> 0 | H20: =VLOOKUP($A20,[8]HISTOAVRIL21!$A$6:$AU$39,36,0) -> 0 | I20: =VLOOKUP($A20,[8]HISTOAVRIL21!$A$6:$AU$39,39,0) -> 0 | J20: =IF(H20<>0,VLOOKUP($A20,[8]HISTOAVRIL21!$A$6:$AU$39,8,0),"ECHEC") -> ECHEC | K20: =VLOOKUP($A20,[8]HISTOAVRIL21!$A$6:$AU$39,41,0) -> 0 | L20: =TONTMARS!H20+TONTMARS!I20+TONTMARS!F20 -> 0 | M20: =VLOOKUP(A20,[8]HISTOAVRIL21!$A$6:$AZ$37,17,0) -> 0 | N20: =IF(M20<>0,VLOOKUP($A20,[8]HISTOAVRIL21!$A$6:$AU$39,8,0),"ECHEC") -> ECHEC | O20: =IF(R20<>0,VLOOKUP($A20,[8]HISTOAVRIL21!$A$6:$AU$39,8,0),"ECHEC") -> ECHEC | P20: =VLOOKUP($A20,[8]HISTOAVRIL21!$A$6:$AU$39,33,0) -> 0 | Q20: =IF(R20=0,0,($C$37-R20)) -> 0 | R20: =VLOOKUP($A20,[8]HISTOAVRIL21!$A$6:$AU$39,30,0) -> 0 | S20: =IF(R20=0,0,(R20-75000)) -> 0
A21: AS201638 | B21: =VLOOKUP(A21,[6]LISTADHERENT!A$5:H$60,3,0) -> SIMO PIERRE | C21: =IF(E21="ECHEC",0,VLOOKUP($A21,[8]HISTOAVRIL21!$A$6:$AU$39,13,0)) -> 75000 | E21: =VLOOKUP($A21,[8]HISTOAVRIL21!$A$6:$AU$39,8,0) -> BANQUE | F21: =IF(N21="ECHEC",L21+(TONTMARS!I21*2),0) -> 0 | H21: =VLOOKUP($A21,[8]HISTOAVRIL21!$A$6:$AU$39,36,0) -> 0 | I21: =VLOOKUP($A21,[8]HISTOAVRIL21!$A$6:$AU$39,39,0) -> 0 | J21: =IF(H21<>0,VLOOKUP($A21,[8]HISTOAVRIL21!$A$6:$AU$39,8,0),"ECHEC") -> ECHEC | K21: =VLOOKUP($A21,[8]HISTOAVRIL21!$A$6:$AU$39,41,0) -> 0 | L21: =TONTMARS!H21+TONTMARS!I21+TONTMARS!F21 -> 0 | M21: =VLOOKUP(A21,[8]HISTOAVRIL21!$A$6:$AZ$37,17,0) -> 0 | N21: =IF(M21<>0,VLOOKUP($A21,[8]HISTOAVRIL21!$A$6:$AU$39,8,0),"ECHEC") -> ECHEC | O21: =IF(R21<>0,VLOOKUP($A21,[8]HISTOAVRIL21!$A$6:$AU$39,8,0),"ECHEC") -> ECHEC | P21: =VLOOKUP($A21,[8]HISTOAVRIL21!$A$6:$AU$39,33,0) -> 0 | Q21: =IF(R21=0,0,($C$37-R21)) -> 0 | R21: =VLOOKUP($A21,[8]HISTOAVRIL21!$A$6:$AU$39,30,0) -> 0 | S21: =IF(R21=0,0,(R21-75000)) -> 0
A22: AS201655 | B22: =VLOOKUP(A22,[6]LISTADHERENT!A$5:H$60,3,0) -> TCHEMHOU EMMANUEL | C22: =IF(E22="ECHEC",0,VLOOKUP($A22,[8]HISTOAVRIL21!$A$6:$AU$39,13,0)) -> 0 | F22: =IF(N22="ECHEC",L22+(TONTMARS!I22*2),0) -> 0 | H22: =VLOOKUP($A22,[8]HISTOAVRIL21!$A$6:$AU$39,36,0) -> 0 | I22: =VLOOKUP($A22,[8]HISTOAVRIL21!$A$6:$AU$39,39,0) -> 0 | J22: =IF(H22<>0,VLOOKUP($A22,[8]HISTOAVRIL21!$A$6:$AU$39,8,0),"ECHEC") -> ECHEC | K22: =VLOOKUP($A22,[8]HISTOAVRIL21!$A$6:$AU$39,41,0) -> 0 | L22: =TONTMARS!H22+TONTMARS!I22+TONTMARS!F22 -> 0 | M22: =VLOOKUP(A22,[8]HISTOAVRIL21!$A$6:$AZ$37,17,0) -> 0 | N22: =IF(M22<>0,VLOOKUP($A22,[8]HISTOAVRIL21!$A$6:$AU$39,8,0),"ECHEC") -> ECHEC | O22: =IF(R22<>0,VLOOKUP($A22,[8]HISTOAVRIL21!$A$6:$AU$39,8,0),"ECHEC") -> ECHEC | P22: =VLOOKUP($A22,[8]HISTOAVRIL21!$A$6:$AU$39,33,0) -> 0 | Q22: =IF(R22=0,0,($C$37-R22)) -> 0 | R22: =VLOOKUP($A22,[8]HISTOAVRIL21!$A$6:$AU$39,30,0) -> 0 | S22: =IF(R22=0,0,(R22-75000)) -> 0
A23: AS201647 | B23: =VLOOKUP(A23,[6]LISTADHERENT!A$5:H$60,3,0) -> YOUMBI EMMANUEL | C23: =IF(E23="ECHEC",0,VLOOKUP($A23,[8]HISTOAVRIL21!$A$6:$AU$39,13,0)) -> 150000 | E23: =VLOOKUP($A23,[8]HISTOAVRIL21!$A$6:$AU$39,8,0) -> BANQUE | F23: =IF(N23="ECHEC",L23+(TONTMARS!I23*2),0) -> 0 | H23: =VLOOKUP($A23,[8]HISTOAVRIL21!$A$6:$AU$39,36,0) -> 0 | I23: =VLOOKUP($A23,[8]HISTOAVRIL21!$A$6:$AU$39,39,0) -> 0 | J23: =IF(H23<>0,VLOOKUP($A23,[8]HISTOAVRIL21!$A$6:$AU$39,8,0),"ECHEC") -> ECHEC | K23: =VLOOKUP($A23,[8]HISTOAVRIL21!$A$6:$AU$39,41,0) -> 0 | L23: =TONTMARS!H23+TONTMARS!I23+TONTMARS!F23 -> 0 | N23: =IF(M23<>0,VLOOKUP($A23,[8]HISTOAVRIL21!$A$6:$AU$39,8,0),"ECHEC") -> ECHEC | O23: =IF(R23<>0,VLOOKUP($A23,[8]HISTOAVRIL21!$A$6:$AU$39,8,0),"ECHEC") -> ECHEC | P23: =VLOOKUP($A23,[8]HISTOAVRIL21!$A$6:$AU$39,33,0) -> 0 | Q23: =IF(R23=0,0,($C$37-R23)) -> 0 | R23: =VLOOKUP($A23,[8]HISTOAVRIL21!$A$6:$AU$39,30,0) -> 0 | S23: =IF(R23=0,0,(R23-75000)) -> 0
A24: AS201647 | B24: =VLOOKUP(A24,[6]LISTADHERENT!A$5:H$60,3,0) -> YOUMBI EMMANUEL | F24: =IF(N24="ECHEC",L24+(TONTMARS!I24*2),0) -> 0 | S24: =IF(R24=0,0,(R24-75000)) -> 0
S26: =SUM(S6:S24) -> 0
B27: TOTAL | C27: =SUM(C6:C26) -> 1275000 | D27: =SUM(D6:D26) -> 0 | E27: =SUM(E6:E26) -> 0 | F27: =SUM(F6:F26) -> 0 | G27: =SUM(G6:G26) -> 0 | H27: =SUM(H6:H26) -> 362000 | I27: =SUM(I6:I26) -> 8500 | J27: =SUM(J6:J26) -> 0 | ... R27: =SUM(R6:R26) -> 75000
C29: TONTINE | D29: REMBOURSEMENT PETIT LOT | E29: VENTE PETIT LOT | F29: VENTE LOT PRINCIPAL | G29: SOLDE EN CAISSE | K29: TONTINE + REMB + INTERET VENTE | L29: =C34+D34+R27+TONTMARS!M34 -> 1562000
K30: LOT PRINCIPAL | L30: =C3*COUNTIF(Q6:Q26,">0") -> 1200000 | M30: =D3 -> 1
B31: ESPECES | C31: =SUMIFS(C6:C25,E6:E25,"ESPECES") -> 75000 | D31: =SUMIFS(L2:L21,N2:N21,"ESPECES")+SUMIFS(F2:F21,G2:G21,"ESPECES") -> 102000 | E31: =SUMIFS(H6:H25,J6:J25,"ESPECES") -> 100000 | F31: =SUMIFS(Q6:Q25,O6:O25,"ESPECES") -> 0 | G31: =C31+D31-E31-F31 -> 77000
B32: BANQUE | C32: =SUMIFS(C6:C25,E6:E25,"BANQUE") -> 1200000 | D32: =SUMIFS(M3:M22,N3:N22,"BANQUE")+SUMIFS(F3:F22,G3:G22,"BANQUE") -> 210000 | E32: =SUMIFS(H6:H25,J6:J25,"BANQUE") -> 262000 | F32: =SUMIFS(Q6:Q25,O6:O25,"BANQUE") -> 1125000 | G32: =C32+D32-E32-F32 -> 23000 | K32: PETIT LOT | L32: =L29-L30 -> 362000
B34: TOTAL | C34: =C31+C32 -> 1275000 | D34: =D31+D32 -> 312000 | E34: =E31+E32 -> 362000 | F34: =F31+F32 -> 1125000 | G34: =G31+G32 -> 100000 | K34: RELIQUAT | L34: =L32-H27 -> 0 | M34: =L34 -> 0 | N34: CUMUL
K36: ECHEC TONTINE | L36: =COUNTIFS(E6:E25,"ECHEC")*75000 -> 0 | M36: =L36+TONTMARS!M36 -> 0 | N36: CUMUL
B37: MONTANT TONTINE | C37: 1200000 | K37: ECHEC REMBOURSEMENT | L37: =SUMIFS(F3:F22,G3:G22,"ECHEC") -> 0 | M37: =L37+TONTMARS!M37 -> 0 | N37: CUMUL

Sheet TONTMAI
A1: ASSOCIATION | B1: ASELBY
A2: ANNEE | B2: 2021 | C2: TONIINE | D2: NBRE PART
A3: TAUX TONTINE | B3: 75000 | C3: =B3*16 -> 1200000 | D3: =ROUNDDOWN(L29/C3,0) -> 1
C4: 44337
A5: MATRICULE | B5: NOM ET PRENOM | C5: MONTANT TONTINE | D5: PENALITE | E5: MODE VERSEMENT TONTINE | F5: REPORT ECHEC PETIT LOT | G5: MODE VERSEMENT VENTE PETIT LOT | H5: VENTE PETIT LOT | I5: INTERET PETIT LOT | J5: MODE VERSEMENT VENTE PETIT LOT | K5: NUMERO CHEQUE | L5: MONTANT A REMBOURSER | M5: MONTANT REMBOURSE | N5: MODE VERSEMENT REMBOURSEMENT | O5: MODE VERSEMENT TONTINE PRINCIPAL | P5: NUMERO CHEQUE | Q5: MONTANT TONTINE LOT PRINCIPAL | R5: INTERET LOT PRINCIPAL | S5: INTERET DU
A6: AS201602 | B6: =VLOOKUP(A6,[6]LISTADHERENT!A$5:H$60,3,0) -> BOUTCHOUANG WILLIAM | C6: =IF(E6="ECHEC",0,VLOOKUP($A6,[8]HISTOMAI21!$A$6:$AU$39,13,0)) -> 75000 | E6: =VLOOKUP($A6,[8]HISTOMAI21!$A$6:$AU$39,8,0) -> ESPECES | F6: =IF(N6="ECHEC",L6+(TONTAVRIL!I6*2),0) -> 0 | H6: =VLOOKUP($A6,[8]HISTOMAI21!$A$6:$AU$39,36,0) -> 0 | I6: =VLOOKUP($A6,[8]HISTOMAI21!$A$6:$AU$39,39,0) -> 0 | J6: =IF(H6<>0,VLOOKUP($A6,[8]HISTOMAI21!$A$6:$AU$39,8,0),"ECHEC") -> ECHEC | K6: =VLOOKUP($A6,[8]HISTOMAI21!$A$6:$AU$39,41,0) -> 0 | L6: =TONTAVRIL!H6+TONTAVRIL!I6+TONTAVRIL!F6 -> 0 | M6: =VLOOKUP(A6,[8]HISTOMAI21!$A$6:$AZ$37,17,0) -> 0 | N6: =IF(L6<>0,VLOOKUP($A6,[8]HISTOMAI21!$A$6:$AU$39,8,0),"ECHEC") -> ECHEC | O6: =IF(R6<>0,VLOOKUP($A6,[8]HISTOMAI21!$A$6:$AU$39,8,0),"ECHEC") -> ECHEC | P6: =VLOOKUP($A6,[8]HISTOMAI21!$A$6:$AU$39,33,0) -> 0 | Q6: =IF(R6=0,0,($C$37-R6)) -> 0 | R6: =VLOOKUP($A6,[8]HISTOMAI21!$A$6:$AU$39,30,0) -> 0 | S6: =IF(R6=0,0,(R6-75000)) -> 0
A7: AS201603 | B7: =VLOOKUP(A7,[6]LISTADHERENT!A$5:H$60,3,0) -> CHINGUE FABRICE | F7: =IF(N7="ECHEC",L7+(TONTAVRIL!I7*2),0) -> 0 | L7: =TONTAVRIL!H7+TONTAVRIL!I7+TONTAVRIL!F7 -> 0 | S7: =IF(R7=0,0,(R7-75000)) -> 0
A8: AS201604 | B8: =VLOOKUP(A8,[6]LISTADHERENT!A$5:H$60,3,0) -> DJOMO JEAN PAUL | C8: =IF(E8="ECHEC",0,VLOOKUP($A8,[8]HISTOMAI21!$A$6:$AU$39,13,0)) -> 75000 | E8: =VLOOKUP($A8,[8]HISTOMAI21!$A$6:$AU$39,8,0) -> BANQUE | F8: =IF(N8="ECHEC",L8+(TONTAVRIL!I8*2),0) -> 0 | H8: =VLOOKUP($A8,[8]HISTOMAI21!$A$6:$AU$39,36,0) -> 100000 | I8: =VLOOKUP($A8,[8]HISTOMAI21!$A$6:$AU$39,39,0) -> 2000 | J8: =IF(H8<>0,VLOOKUP($A8,[8]HISTOMAI21!$A$6:$AU$39,8,0),"ECHEC") -> BANQUE | K8: =VLOOKUP($A8,[8]HISTOMAI21!$A$6:$AU$39,41,0) -> 0 | L8: =TONTAVRIL!H8+TONTAVRIL!I8+TONTAVRIL!F8 -> 102500 | M8: =VLOOKUP(A8,[8]HISTOMAI21!$A$6:$AZ$37,17,0) -> 102500 | N8: =IF(M8<>0,VLOOKUP($A8,[8]HISTOMAI21!$A$6:$AU$39,8,0),"ECHEC") -> BANQUE | O8: =IF(R8<>0,VLOOKUP($A8,[8]HISTOMAI21!$A$6:$AU$39,8,0),"ECHEC") -> ECHEC | P8: =VLOOKUP($A8,[8]HISTOMAI21!$A$6:$AU$39,33,0) -> 0 | Q8: =IF(R8=0,0,($C$37-R8)) -> 0 | R8: =VLOOKUP($A8,[8]HISTOMAI21!$A$6:$AU$39,30,0) -> 0 | S8: =IF(R8=0,0,(R8-75000)) -> 0
A9: AS201605 | B9: =VLOOKUP(A9,[6]LISTADHERENT!A$5:H$60,3,0) -> DJOUKWE NANGUEN GUY BLAISE | C9: =IF(E9="ECHEC",0,VLOOKUP($A9,[8]HISTOMAI21!$A$6:$AU$39,13,0)) -> 75000 | E9: =VLOOKUP($A9,[8]HISTOMAI21!$A$6:$AU$39,8,0) -> BANQUE | F9: =IF(N9="ECHEC",L9+(TONTAVRIL!I9*2),0) -> 0 | H9: =VLOOKUP($A9,[8]HISTOMAI21!$A$6:$AU$39,36,0) -> 150000 | I9: =VLOOKUP($A9,[8]HISTOMAI21!$A$6:$AU$39,39,0) -> 3500 | J9: =IF(H9<>0,VLOOKUP($A9,[8]HISTOMAI21!$A$6:$AU$39,8,0),"ECHEC") -> BANQUE | K9: =VLOOKUP($A9,[8]HISTOMAI21!$A$6:$AU$39,41,0) -> 0 | L9: =TONTAVRIL!H9+TONTAVRIL!I9+TONTAVRIL!F9 -> 0 | M9: =VLOOKUP(A9,[8]HISTOMAI21!$A$6:$AZ$37,17,0) -> 0 | N9: =IF(M9<>0,VLOOKUP($A9,[8]HISTOMAI21!$A$6:$AU$39,8,0),"ECHEC") -> ECHEC | O9: =IF(R9<>0,VLOOKUP($A9,[8]HISTOMAI21!$A$6:$AU$39,8,0),"ECHEC") -> ECHEC | P9: =VLOOKUP($A9,[8]HISTOMAI21!$A$6:$AU$39,33,0) -> 0 | Q9: =IF(R9=0,0,($C$37-R9)) -> 0 | R9: =VLOOKUP($A9,[8]HISTOMAI21!$A$6:$AU$39,30,0) -> 0 | S9: =IF(R9=0,0,(R9-75000)) -> 0
A10: AS201613 | B10: =VLOOKUP(A10,[6]LISTADHERENT!A$5:H$60,3,0) -> HOTCHO BENJAMIN | C10: =IF(E10="ECHEC",0,VLOOKUP($A10,[8]HISTOMAI21!$A$6:$AU$39,13,0)) -> 75000 | E10: =VLOOKUP($A10,[8]HISTOMAI21!$A$6:$AU$39,8,0) -> BANQUE | F10: =IF(N10="ECHEC",L10+(TONTAVRIL!I10*2),0) -> 0 | H10: =VLOOKUP($A10,[8]HISTOMAI21!$A$6:$AU$39,36,0) -> 0 | I10: =VLOOKUP($A10,[8]HISTOMAI21!$A$6:$AU$39,39,0) -> 0 | J10: =IF(H10<>0,VLOOKUP($A10,[8]HISTOMAI21!$A$6:$AU$39,8,0),"ECHEC") -> ECHEC | K10: =VLOOKUP($A10,[8]HISTOMAI21!$A$6:$AU$39,41,0) -> 0 | L10: =TONTAVRIL!H10+TONTAVRIL!I10+TONTAVRIL!F10 -> 0 | M10: =VLOOKUP(A10,[8]HISTOMAI21!$A$6:$AZ$37,17,0) -> 0 | N10: =IF(M10<>0,VLOOKUP($A10,[8]HISTOMAI21!$A$6:$AU$39,8,0),"ECHEC") -> ECHEC | O10: =IF(R10<>0,VLOOKUP($A10,[8]HISTOMAI21!$A$6:$AU$39,8,0),"ECHEC") -> ECHEC | P10: =VLOOKUP($A10,[8]HISTOMAI21!$A$6:$AU$39,33,0) -> 0 | Q10: =IF(R10=0,0,($C$37-R10)) -> 0 | R10: =VLOOKUP($A10,[8]HISTOMAI21!$A$6:$AU$39,30,0) -> 0 | S10: =IF(R10=0,0,(R10-75000)) -> 0
A11: AS201611 | B11: =VLOOKUP(A11,[6]LISTADHERENT!A$5:H$60,3,0) -> HENGUE PAUL OMER | C11: =IF(E11="ECHEC",0,VLOOKUP($A11,[8]HISTOMAI21!$A$6:$AU$39,13,0)) -> 75000 | E11: =VLOOKUP($A11,[8]HISTOMAI21!$A$6:$AU$39,8,0) -> BANQUE | F11: =IF(N11="ECHEC",L11+(TONTAVRIL!I11*2),0) -> 0 | H11: =VLOOKUP($A11,[8]HISTOMAI21!$A$6:$AU$39,36,0) -> 0 | I11: =VLOOKUP($A11,[8]HISTOMAI21!$A$6:$AU$39,39,0) -> 0 | J11: =IF(H11<>0,VLOOKUP($A11,[8]HISTOMAI21!$A$6:$AU$39,8,0),"ECHEC") -> ECHEC | K11: =VLOOKUP($A11,[8]HISTOMAI21!$A$6:$AU$39,41,0) -> 0 | L11: =TONTAVRIL!H11+TONTAVRIL!I11+TONTAVRIL!F11 -> 0 | M11: =VLOOKUP(A11,[8]HISTOMAI21!$A$6:$AZ$37,17,0) -> 0 | N11: =IF(M11<>0,VLOOKUP($A11,[8]HISTOMAI21!$A$6:$AU$39,8,0),"ECHEC") -> ECHEC | O11: =IF(R11<>0,VLOOKUP($A11,[8]HISTOMAI21!$A$6:$AU$39,8,0),"ECHEC") -> ECHEC | P11: =VLOOKUP($A11,[8]HISTOMAI21!$A$6:$AU$39,33,0) -> 0 | Q11: =IF(R11=0,0,($C$37-R11)) -> 0 | R11: =VLOOKUP($A11,[8]HISTOMAI21!$A$6:$AU$39,30,0) -> 0 | S11: =IF(R11=0,0,(R11-75000)) -> 0
A12: AS201619 | B12: =VLOOKUP(A12,[6]LISTADHERENT!A$5:H$60,3,0) -> KOUATCHO MESSACK | C12: =IF(E12="ECHEC",0,VLOOKUP($A12,[8]HISTOMAI21!$A$6:$AU$39,13,0)) -> 75000 | E12: =VLOOKUP($A12,[8]HISTOMAI21!$A$6:$AU$39,8,0) -> BANQUE | F12: =IF(N12="ECHEC",L12+(TONTAVRIL!I12*2),0) -> 0 | H12: =VLOOKUP($A12,[8]HISTOMAI21!$A$6:$AU$39,36,0) -> 120500 | I12: =VLOOKUP($A12,[8]HISTOMAI21!$A$6:$AU$39,39,0) -> 3000 | J12: =IF(H12<>0,VLOOKUP($A12,[8]HISTOMAI21!$A$6:$AU$39,8,0),"ECHEC") -> BANQUE | K12: =VLOOKUP($A12,[8]HISTOMAI21!$A$6:$AU$39,41,0) -> 0 | L12: =TONTAVRIL!H12+TONTAVRIL!I12+TONTAVRIL!F12 -> 0 | M12: =VLOOKUP(A12,[8]HISTOMAI21!$A$6:$AZ$37,17,0) -> 0 | N12: =IF(M12<>0,VLOOKUP($A12,[8]HISTOMAI21!$A$6:$AU$39,8,0),"ECHEC") -> ECHEC | O12: =IF(R12<>0,VLOOKUP($A12,[8]HISTOMAI21!$A$6:$AU$39,8,0),"ECHEC") -> ECHEC | P12: =VLOOKUP($A12,[8]HISTOMAI21!$A$6:$AU$39,33,0) -> 0 | Q12: =IF(R12=0,0,($C$37-R12)) -> 0 | R12: =VLOOKUP($A12,[8]HISTOMAI21!$A$6:$AU$39,30,0) -> 0 | S12: =IF(R12=0,0,(R12-75000)) -> 0
A13: AS201621 | B13: =VLOOKUP(A13,[6]LISTADHERENT!A$5:H$60,3,0) -> NANKAM APPOLINAIRE | C13: =IF(E13="ECHEC",0,VLOOKUP($A13,[8]HISTOMAI21!$A$6:$AU$39,13,0)) -> 75000 | E13: =VLOOKUP($A13,[8]HISTOMAI21!$A$6:$AU$39,8,0) -> BANQUE | F13: =IF(N13="ECHEC",L13+(TONTAVRIL!I13*2),0) -> 0 | H13: =VLOOKUP($A13,[8]HISTOMAI21!$A$6:$AU$39,36,0) -> 0 | I13: =VLOOKUP($A13,[8]HISTOMAI21!$A$6:$AU$39,39,0) -> 0 | J13: =IF(H13<>0,VLOOKUP($A13,[8]HISTOMAI21!$A$6:$AU$39,8,0),"ECHEC") -> ECHEC | K13: =VLOOKUP($A13,[8]HISTOMAI21!$A$6:$AU$39,41,0) -> 0 | L13: =TONTAVRIL!H13+TONTAVRIL!I13+TONTAVRIL!F13 -> 0 | M13: =VLOOKUP(A13,[8]HISTOMAI21!$A$6:$AZ$37,17,0) -> 0 | N13: =IF(M13<>0,VLOOKUP($A13,[8]HISTOMAI21!$A$6:$AU$39,8,0),"ECHEC") -> ECHEC | O13: =IF(R13<>0,VLOOKUP($A13,[8]HISTOMAI21!$A$6:$AU$39,8,0),"ECHEC") -> ECHEC | P13: =VLOOKUP($A13,[8]HISTOMAI21!$A$6:$AU$39,33,0) -> 0 | Q13: =IF(R13=0,0,($C$37-R13)) -> 0 | R13: =VLOOKUP($A13,[8]HISTOMAI21!$A$6:$AU$39,30,0) -> 0 | S13: =IF(R13=0,0,(R13-75000)) -> 0
A14: AS201649 | B14: =VLOOKUP(A14,[6]LISTADHERENT!A$5:H$60,3,0) -> MBOGNING TUGMA GUY | C14: =IF(E14="ECHEC",0,VLOOKUP($A14,[8]HISTOMAI21!$A$6:$AU$39,13,0)) -> 225000 | E14: =VLOOKUP($A14,[8]HISTOMAI21!$A$6:$AU$39,8,0) -> BANQUE | F14: =IF(N14="ECHEC",L14+(TONTAVRIL!I14*2),0) -> 0 | H14: =VLOOKUP($A14,[8]HISTOMAI21!$A$6:$AU$39,36,0) -> 50000 | I14: =VLOOKUP($A14,[8]HISTOMAI21!$A$6:$AU$39,39,0) -> 1500 | J14: =IF(H14<>0,VLOOKUP($A14,[8]HISTOMAI21!$A$6:$AU$39,8,0),"ECHEC") -> BANQUE | K14: =VLOOKUP($A14,[8]HISTOMAI21!$A$6:$AU$39,41,0) -> 0 | L14: =TONTAVRIL!H14+TONTAVRIL!I14+TONTAVRIL!F14 -> 115000 | M14: =VLOOKUP(A14,[8]HISTOMAI21!$A$6:$AZ$37,17,0) -> 115000 | N14: ESPECES | O14: =IF(R14<>0,VLOOKUP($A14,[8]HISTOMAI21!$A$6:$AU$39,8,0),"ECHEC") -> BANQUE | P14: =VLOOKUP($A14,[8]HISTOMAI21!$A$6:$AU$39,33,0) -> 0 | Q14: =IF(R14=0,0,($C$37-R14)) -> 1125000 | R14: =VLOOKUP($A14,[8]HISTOMAI21!$A$6:$AU$39,30,0) -> 75000 | S14: =IF(R14=0,0,(R14-75000)) -> 0
A15: AS201649 | B15: =VLOOKUP(A15,[6]LISTADHERENT!A$5:H$60,3,0) -> MBOGNING TUGMA GUY | F15: =IF(N15="ECHEC",L15+(TONTAVRIL!I15*2),0) -> 0 | L15: =TONTAVRIL!H15+TONTAVRIL!I15+TONTAVRIL!F15 -> 0 | P15: =VLOOKUP($A15,[8]HISTOMAI21!$A$6:$AU$39,33,0) -> 0 | S15: =IF(R15=0,0,(R15-75000)) -> 0
A16: AS201649 | B16: =VLOOKUP(A16,[6]LISTADHERENT!A$5:H$60,3,0) -> MBOGNING TUGMA GUY | F16: =IF(N16="ECHEC",L16+(TONTAVRIL!I16*2),0) -> 0 | L16: =TONTAVRIL!H16+TONTAVRIL!I16+TONTAVRIL!F16 -> 0 | S16: =IF(R16=0,0,(R16-75000)) -> 0
A17: AS201626 | B17: =VLOOKUP(A17,[6]LISTADHERENT!A$5:H$60,3,0) -> NGUIEMEGNI MATHIEU BLAISE | C17: =IF(E17="ECHEC",0,VLOOKUP($A17,[8]HISTOMAI21!$A$6:$AU$39,13,0)) -> 150000 | E17: =VLOOKUP($A17,[8]HISTOMAI21!$A$6:$AU$39,8,0) -> BANQUE | F17: =IF(N17="ECHEC",L17+(TONTAVRIL!I17*2),0) -> 0 | H17: =VLOOKUP($A17,[8]HISTOMAI21!$A$6:$AU$39,36,0) -> 0 | I17: =VLOOKUP($A17,[8]HISTOMAI21!$A$6:$AU$39,39,0) -> 0 | J17: =IF(H17<>0,VLOOKUP($A17,[8]HISTOMAI21!$A$6:$AU$39,8,0),"ECHEC") -> ECHEC | K17: =VLOOKUP($A17,[8]HISTOMAI21!$A$6:$AU$39,41,0) -> 0 | L17: =TONTAVRIL!H17+TONTAVRIL!I17+TONTAVRIL!F17 -> 51000 | M17: =VLOOKUP(A17,[8]HISTOMAI21!$A$6:$AZ$37,17,0) -> 51000 | N17: =IF(M17<>0,VLOOKUP($A17,[8]HISTOMAI21!$A$6:$AU$39,8,0),"ECHEC") -> BANQUE | O17: =IF(R17<>0,VLOOKUP($A17,[8]HISTOMAI21!$A$6:$AU$39,8,0),"ECHEC") -> ECHEC | P17: =VLOOKUP($A17,[8]HISTOMAI21!$A$6:$AU$39,33,0) -> 0 | Q17: =IF(R17=0,0,($C$37-R17)) -> 0 | R17: =VLOOKUP($A17,[8]HISTOMAI21!$A$6:$AU$39,30,0) -> 0 | S17: =IF(R17=0,0,(R17-75000)) -> 0
A18: AS201626 | B18: =VLOOKUP(A18,[6]LISTADHERENT!A$5:H$60,3,0) -> NGUIEMEGNI MATHIEU BLAISE | F18: =IF(N18="ECHEC",L18+(TONTAVRIL!I18*2),0) -> 0 | L18: =TONTAVRIL!H18+TONTAVRIL!I18+TONTAVRIL!F18 -> 0 | N18: =IF(M18<>0,VLOOKUP($A18,[8]HISTOMAI21!$A$6:$AU$39,8,0),"ECHEC") -> ECHEC | O18: =IF(R18<>0,VLOOKUP($A18,[8]HISTOMAI21!$A$6:$AU$39,8,0),"ECHEC") -> ECHEC | S18: =IF(R18=0,0,(R18-75000)) -> 0
A19: AS201628 | B19: =VLOOKUP(A19,[6]LISTADHERENT!A$5:H$60,3,0) -> NKAMGANG JUSTIN DEJOLIE | C19: =IF(E19="ECHEC",0,VLOOKUP($A19,[8]HISTOMAI21!$A$6:$AU$39,13,0)) -> 75000 | E19: =VLOOKUP($A19,[8]HISTOMAI21!$A$6:$AU$39,8,0) -> ESPECES | F19: =IF(N19="ECHEC",L19+(TONTAVRIL!I19*2),0) -> 0 | H19: =VLOOKUP($A19,[8]HISTOMAI21!$A$6:$AU$39,36,0) -> 100000 | I19: =VLOOKUP($A19,[8]HISTOMAI21!$A$6:$AU$39,39,0) -> 3000 | J19: =IF(H19<>0,VLOOKUP($A19,[8]HISTOMAI21!$A$6:$AU$39,8,0),"ECHEC") -> ESPECES | K19: =VLOOKUP($A19,[8]HISTOMAI21!$A$6:$AU$39,41,0) -> 0 | L19: =TONTAVRIL!H19+TONTAVRIL!I19+TONTAVRIL!F19 -> 102000 | M19: =VLOOKUP(A19,[8]HISTOMAI21!$A$6:$AZ$37,17,0) -> 102000 | N19: =IF(M19<>0,VLOOKUP($A19,[8]HISTOMAI21!$A$6:$AU$39,8,0),"ECHEC") -> ESPECES | O19: =IF(R19<>0,VLOOKUP($A19,[8]HISTOMAI21!$A$6:$AU$39,8,0),"ECHEC") -> ECHEC | P19: =VLOOKUP($A19,[8]HISTOMAI21!$A$6:$AU$39,33,0) -> 0 | Q19: =IF(R19=0,0,($C$37-R19)) -> 0 | R19: =VLOOKUP($A19,[8]HISTOMAI21!$A$6:$AU$39,30,0) -> 0 | S19: =IF(R19=0,0,(R19-75000)) -> 0
A20: AS201633 | B20: =VLOOKUP(A20,[6]LISTADHERENT!A$5:H$60,3,0) -> PATEGO NJOSSU GUSTAVE | C20: =IF(E20="ECHEC",0,VLOOKUP($A20,[8]HISTOMAI21!$A$6:$AU$39,13,0)) -> 75000 | E20: =VLOOKUP($A20,[8]HISTOMAI21!$A$6:$AU$39,8,0) -> BANQUE | F20: =IF(N20="ECHEC",L20+(TONTAVRIL!I20*2),0) -> 0 | H20: =VLOOKUP($A20,[8]HISTOMAI21!$A$6:$AU$39,36,0) -> 0 | I20: =VLOOKUP($A20,[8]HISTOMAI21!$A$6:$AU$39,39,0) -> 0 | J20: =IF(H20<>0,VLOOKUP($A20,[8]HISTOMAI21!$A$6:$AU$39,8,0),"ECHEC") -> ECHEC | K20: =VLOOKUP($A20,[8]HISTOMAI21!$A$6:$AU$39,41,0) -> 0 | L20: =TONTAVRIL!H20+TONTAVRIL!I20+TONTAVRIL!F20 -> 0 | M20: =VLOOKUP(A20,[8]HISTOMAI21!$A$6:$AZ$37,17,0) -> 0 | N20: =IF(M20<>0,VLOOKUP($A20,[8]HISTOMAI21!$A$6:$AU$39,8,0),"ECHEC") -> ECHEC | O20: =IF(R20<>0,VLOOKUP($A20,[8]HISTOMAI21!$A$6:$AU$39,8,0),"ECHEC") -> ECHEC | P20: =VLOOKUP($A20,[8]HISTOMAI21!$A$6:$AU$39,33,0) -> 0 | Q20: =IF(R20=0,0,($C$37-R20)) -> 0 | R20: =VLOOKUP($A20,[8]HISTOMAI21!$A$6:$AU$39,30,0) -> 0 | S20: =IF(R20=0,0,(R20-75000)) -> 0
A21: AS201638 | B21: =VLOOKUP(A21,[6]LISTADHERENT!A$5:H$60,3,0) -> SIMO PIERRE | C21: =IF(E21="ECHEC",0,VLOOKUP($A21,[8]HISTOMAI21!$A$6:$AU$39,13,0)) -> 75000 | E21: =VLOOKUP($A21,[8]HISTOMAI21!$A$6:$AU$39,8,0) -> BANQUE | F21: =IF(N21="ECHEC",L21+(TONTAVRIL!I21*2),0) -> 0 | H21: =VLOOKUP($A21,[8]HISTOMAI21!$A$6:$AU$39,36,0) -> 0 | I21: =VLOOKUP($A21,[8]HISTOMAI21!$A$6:$AU$39,39,0) -> 0 | J21: =IF(H21<>0,VLOOKUP($A21,[8]HISTOMAI21!$A$6:$AU$39,8,0),"ECHEC") -> ECHEC | K21: =VLOOKUP($A21,[8]HISTOMAI21!$A$6:$AU$39,41,0) -> 0 | L21: =TONTAVRIL!H21+TONTAVRIL!I21+TONTAVRIL!F21 -> 0 | M21: =VLOOKUP(A21,[8]HISTOMAI21!$A$6:$AZ$37,17,0) -> 0 | N21: =IF(M21<>0,VLOOKUP($A21,[8]HISTOMAI21!$A$6:$AU$39,8,0),"ECHEC") -> ECHEC | O21: =IF(R21<>0,VLOOKUP($A21,[8]HISTOMAI21!$A$6:$AU$39,8,0),"ECHEC") -> ECHEC | P21: =VLOOKUP($A21,[8]HISTOMAI21!$A$6:$AU$39,33,0) -> 0 | Q21: =IF(R21=0,0,($C$37-R21)) -> 0 | R21: =VLOOKUP($A21,[8]HISTOMAI21!$A$6:$AU$39,30,0) -> 0 | S21: =IF(R21=0,0,(R21-75000)) -> 0
A22: AS201655 | B22: =VLOOKUP(A22,[6]LISTADHERENT!A$5:H$60,3,0) -> TCHEMHOU EMMANUEL | C22: =IF(E22="ECHEC",0,VLOOKUP($A22,[8]HISTOMAI21!$A$6:$AU$39,13,0)) -> 0 | F22: =IF(N22="ECHEC",L22+(TONTAVRIL!I22*2),0) -> 0 | H22: =VLOOKUP($A22,[8]HISTOMAI21!$A$6:$AU$39,36,0) -> 0 | I22: =VLOOKUP($A22,[8]HISTOMAI21!$A$6:$AU$39,39,0) -> 0 | J22: =IF(H22<>0,VLOOKUP($A22,[8]HISTOMAI21!$A$6:$AU$39,8,0),"ECHEC") -> ECHEC | K22: =VLOOKUP($A22,[8]HISTOMAI21!$A$6:$AU$39,41,0) -> 0 | L22: =TONTAVRIL!H22+TONTAVRIL!I22+TONTAVRIL!F22 -> 0 | M22: =VLOOKUP(A22,[8]HISTOMAI21!$A$6:$AZ$37,17,0) -> 0 | N22: =IF(M22<>0,VLOOKUP($A22,[8]HISTOMAI21!$A$6:$AU$39,8,0),"ECHEC") -> ECHEC | O22: =IF(R22<>0,VLOOKUP($A22,[8]HISTOMAI21!$A$6:$AU$39,8,0),"ECHEC") -> ECHEC | P22: =VLOOKUP($A22,[8]HISTOMAI21!$A$6:$AU$39,33,0) -> 0 | Q22: =IF(R22=0,0,($C$37-R22)) -> 0 | R22: =VLOOKUP($A22,[8]HISTOMAI21!$A$6:$AU$39,30,0) -> 0 | S22: =IF(R22=0,0,(R22-75000)) -> 0
A23: AS201647 | B23: =VLOOKUP(A23,[6]LISTADHERENT!A$5:H$60,3,0) -> YOUMBI EMMANUEL | C23: =IF(E23="ECHEC",0,VLOOKUP($A23,[8]HISTOMAI21!$A$6:$AU$39,13,0)) -> 150000 | E23: =VLOOKUP($A23,[8]HISTOMAI21!$A$6:$AU$39,8,0) -> BANQUE | F23: =IF(N23="ECHEC",L23+(TONTAVRIL!I23*2),0) -> 0 | H23: =VLOOKUP($A23,[8]HISTOMAI21!$A$6:$AU$39,36,0) -> 0 | I23: =VLOOKUP($A23,[8]HISTOMAI21!$A$6:$AU$39,39,0) -> 0 | J23: =IF(H23<>0,VLOOKUP($A23,[8]HISTOMAI21!$A$6:$AU$39,8,0),"ECHEC") -> ECHEC | K23: =VLOOKUP($A23,[8]HISTOMAI21!$A$6:$AU$39,41,0) -> 0 | L23: =TONTAVRIL!H23+TONTAVRIL!I23+TONTAVRIL!F23 -> 0 | N23: =IF(M23<>0,VLOOKUP($A23,[8]HISTOMAI21!$A$6:$AU$39,8,0),"ECHEC") -> ECHEC | O23: =IF(R23<>0,VLOOKUP($A23,[8]HISTOMAI21!$A$6:$AU$39,8,0),"ECHEC") -> ECHEC | P23: =VLOOKUP($A23,[8]HISTOMAI21!$A$6:$AU$39,33,0) -> 0 | Q23: =IF(R23=0,0,($C$37-R23)) -> 0 | R23: =VLOOKUP($A23,[8]HISTOMAI21!$A$6:$AU$39,30,0) -> 0 | S23: =IF(R23=0,0,(R23-75000)) -> 0
A24: AS201647 | B24: =VLOOKUP(A24,[6]LISTADHERENT!A$5:H$60,3,0) -> YOUMBI EMMANUEL | F24: =IF(N24="ECHEC",L24+(TONTAVRIL!I24*2),0) -> 0 | S24: =IF(R24=0,0,(R24-75000)) -> 0
S26: =SUM(S6:S24) -> 0
B27: TOTAL | C27: =SUM(C6:C26) -> 1275000 | D27: =SUM(D6:D26) -> 0 | E27: =SUM(E6:E26) -> 0 | F27: =SUM(F6:F26) -> 0 | G27: =SUM(G6:G26) -> 0 | H27: =SUM(H6:H26) -> 520500 | I27: =SUM(I6:I26) -> 13000 | J27: =SUM(J6:J26) -> 0 | ... R27: =SUM(R6:R26) -> 75000
C29: TONTINE | D29: REMBOURSEMENT PETIT LOT | E29: VENTE PETIT LOT | F29: VENTE LOT PRINCIPAL | G29: SOLDE EN CAISSE | K29: TONTINE + REMB + INTERET VENTE | L29: =C34+D34+R27+TONTAVRIL!M34 -> 1720500
K30: LOT PRINCIPAL | L30: =C3*COUNTIF(Q6:Q26,">0") -> 1200000 | M30: =D3 -> 1
B31: ESPECES | C31: =SUMIFS(C6:C25,E6:E25,"ESPECES") -> 150000 | D31: =SUMIFS(L2:L21,N2:N21,"ESPECES")+SUMIFS(F2:F21,G2:G21,"ESPECES") -> 217000 | E31: =SUMIFS(H6:H25,J6:J25,"ESPECES") -> 100000 | F31: =SUMIFS(Q6:Q25,O6:O25,"ESPECES") -> 0 | G31: =C31+D31-E31-F31 -> 267000
B32: BANQUE | C32: =SUMIFS(C6:C25,E6:E25,"BANQUE") -> 1125000 | D32: =SUMIFS(M3:M22,N3:N22,"BANQUE")+SUMIFS(F3:F22,G3:G22,"BANQUE") -> 153500 | E32: =SUMIFS(H6:H25,J6:J25,"BANQUE") -> 420500 | F32: =SUMIFS(Q6:Q25,O6:O25,"BANQUE") -> 1125000 | G32: =C32+D32-E32-F32 -> -267000 | K32: PETIT LOT | L32: =L29-L30 -> 520500
B34: TOTAL | C34: =C31+C32 -> 1275000 | D34: =D31+D32 -> 370500 | E34: =E31+E32 -> 520500 | F34: =F31+F32 -> 1125000 | G34: =G31+G32 -> 0 | K34: RELIQUAT | L34: =L32-H27 -> 0 | M34: =L34 -> 0 | N34: CUMUL
K36: ECHEC TONTINE | L36: =COUNTIFS(E6:E25,"ECHEC")*75000 -> 0 | M36: =L36+TONTAVRIL!M36 -> 0 | N36: CUMUL
B37: MONTANT TONTINE | C37: 1200000 | K37: ECHEC REMBOURSEMENT | L37: =SUMIFS(F3:F22,G3:G22,"ECHEC") -> 0 | M37: =L37+TONTAVRIL!M37 -> 0 | N37: CUMUL

Sheet TONTJUIN
A1: ASSOCIATION | B1: ASELBY
A2: ANNEE | B2: 2021 | C2: TONIINE | D2: NBRE PART | K2: =102000+51500+61000 -> 214500
A3: TAUX TONTINE | B3: 75000 | C3: =B3*16 -> 1200000 | D3: =ROUNDDOWN(L29/C3,0) -> 1
C4: 44368
A5: MATRICULE | B5: NOM ET PRENOM | C5: MONTANT TONTINE | D5: PENALITE | E5: MODE VERSEMENT TONTINE | F5: REPORT ECHEC PETIT LOT | G5: MODE VERSEMENT VENTE PETIT LOT | H5: VENTE PETIT LOT | I5: INTERET PETIT LOT | J5: MODE VERSEMENT VENTE PETIT LOT | K5: NUMERO CHEQUE | L5: MONTANT A REMBOURSER | M5: MONTANT REMBOURSE | N5: MODE VERSEMENT REMBOURSEMENT | O5: MODE VERSEMENT TONTINE PRINCIPAL | P5: NUMERO CHEQUE | Q5: MONTANT TONTINE LOT PRINCIPAL | R5: INTERET LOT PRINCIPAL | S5: INTERET DU
A6: AS201602 | B6: =VLOOKUP(A6,[6]LISTADHERENT!A$5:H$60,3,0) -> BOUTCHOUANG WILLIAM | C6: =IF(E6="ECHEC",0,VLOOKUP($A6,[8]HISTOJUIN21!$A$6:$AU$39,13,0)) -> 75000 | E6: =VLOOKUP($A6,[8]HISTOJUIN21!$A$6:$AU$39,8,0) -> BANQUE | F6: =IF(N6="ECHEC",L6+(TONTMAI!I6*2),0) -> 0 | H6: =VLOOKUP($A6,[8]HISTOJUIN21!$A$6:$AU$39,36,0) -> 0 | I6: =VLOOKUP($A6,[8]HISTOJUIN21!$A$6:$AU$39,39,0) -> 0 | J6: =IF(H6<>0,VLOOKUP($A6,[8]HISTOJUIN21!$A$6:$AU$39,8,0),"ECHEC") -> ECHEC | K6: =VLOOKUP($A6,[8]HISTOJUIN21!$A$6:$AU$39,41,0) -> 0 | L6: =TONTMAI!H6+TONTMAI!I6+TONTMAI!F6 -> 0 | M6: =VLOOKUP(A6,[8]HISTOJUIN21!$A$6:$AZ$37,17,0) -> 0 | N6: =IF(L6<>0,VLOOKUP($A6,[8]HISTOJUIN21!$A$6:$AU$39,8,0),"ECHEC") -> ECHEC | O6: =IF(R6<>0,VLOOKUP($A6,[8]HISTOJUIN21!$A$6:$AU$39,8,0),"ECHEC") -> ECHEC | P6: =VLOOKUP($A6,[8]HISTOJUIN21!$A$6:$AU$39,33,0) -> 0 | Q6: =IF(R6=0,0,($C$37-R6)) -> 0 | R6: =VLOOKUP($A6,[8]HISTOJUIN21!$A$6:$AU$39,30,0) -> 0 | S6: =IF(R6=0,0,(R6-75000)) -> 0
A7: AS201603 | B7: =VLOOKUP(A7,[6]LISTADHERENT!A$5:H$60,3,0) -> CHINGUE FABRICE | F7: =IF(N7="ECHEC",L7+(TONTMAI!I7*2),0) -> 0 | L7: =TONTMAI!H7+TONTMAI!I7+TONTMAI!F7 -> 0 | S7: =IF(R7=0,0,(R7-75000)) -> 0
A8: AS201604 | B8: =VLOOKUP(A8,[6]LISTADHERENT!A$5:H$60,3,0) -> DJOMO JEAN PAUL | C8: =IF(E8="ECHEC",0,VLOOKUP($A8,[8]HISTOJUIN21!$A$6:$AU$39,13,0)) -> 75000 | E8: =VLOOKUP($A8,[8]HISTOJUIN21!$A$6:$AU$39,8,0) -> BANQUE | F8: =IF(N8="ECHEC",L8+(TONTMAI!I8*2),0) -> 0 | H8: =VLOOKUP($A8,[8]HISTOJUIN21!$A$6:$AU$39,36,0) -> 138500 | I8: =VLOOKUP($A8,[8]HISTOJUIN21!$A$6:$AU$39,39,0) -> 2000 | J8: =IF(H8<>0,VLOOKUP($A8,[8]HISTOJUIN21!$A$6:$AU$39,8,0),"ECHEC") -> BANQUE | K8: =VLOOKUP($A8,[8]HISTOJUIN21!$A$6:$AU$39,41,0) -> 0 | L8: =TONTMAI!H8+TONTMAI!I8+TONTMAI!F8 -> 102000 | M8: =VLOOKUP(A8,[8]HISTOJUIN21!$A$6:$AZ$37,17,0) -> 102000 | N8: =IF(M8<>0,VLOOKUP($A8,[8]HISTOJUIN21!$A$6:$AU$39,8,0),"ECHEC") -> BANQUE | O8: =IF(R8<>0,VLOOKUP($A8,[8]HISTOJUIN21!$A$6:$AU$39,8,0),"ECHEC") -> ECHEC | P8: =VLOOKUP($A8,[8]HISTOJUIN21!$A$6:$AU$39,33,0) -> 0 | Q8: =IF(R8=0,0,($C$37-R8)) -> 0 | R8: =VLOOKUP($A8,[8]HISTOJUIN21!$A$6:$AU$39,30,0) -> 0 | S8: =IF(R8=0,0,(R8-75000)) -> 0
A9: AS201605 | B9: =VLOOKUP(A9,[6]LISTADHERENT!A$5:H$60,3,0) -> DJOUKWE NANGUEN GUY BLAISE | C9: =IF(E9="ECHEC",0,VLOOKUP($A9,[8]HISTOJUIN21!$A$6:$AU$39,13,0)) -> 75000 | E9: =VLOOKUP($A9,[8]HISTOJUIN21!$A$6:$AU$39,8,0) -> BANQUE | F9: =IF(N9="ECHEC",L9+(TONTMAI!I9*2),0) -> 0 | H9: =VLOOKUP($A9,[8]HISTOJUIN21!$A$6:$AU$39,36,0) -> 200000 | I9: =VLOOKUP($A9,[8]HISTOJUIN21!$A$6:$AU$39,39,0) -> 4000 | J9: =IF(H9<>0,VLOOKUP($A9,[8]HISTOJUIN21!$A$6:$AU$39,8,0),"ECHEC") -> BANQUE | K9: =VLOOKUP($A9,[8]HISTOJUIN21!$A$6:$AU$39,41,0) -> 0 | L9: =TONTMAI!H9+TONTMAI!I9+TONTMAI!F9 -> 153500 | M9: =VLOOKUP(A9,[8]HISTOJUIN21!$A$6:$AZ$37,17,0) -> 153500 | N9: =IF(M9<>0,VLOOKUP($A9,[8]HISTOJUIN21!$A$6:$AU$39,8,0),"ECHEC") -> BANQUE | O9: =IF(R9<>0,VLOOKUP($A9,[8]HISTOJUIN21!$A$6:$AU$39,8,0),"ECHEC") -> ECHEC | P9: =VLOOKUP($A9,[8]HISTOJUIN21!$A$6:$AU$39,33,0) -> 0 | Q9: =IF(R9=0,0,($C$37-R9)) -> 0 | R9: =VLOOKUP($A9,[8]HISTOJUIN21!$A$6:$AU$39,30,0) -> 0 | S9: =IF(R9=0,0,(R9-75000)) -> 0
A10: AS201613 | B10: =VLOOKUP(A10,[6]LISTADHERENT!A$5:H$60,3,0) -> HOTCHO BENJAMIN | C10: =IF(E10="ECHEC",0,VLOOKUP($A10,[8]HISTOJUIN21!$A$6:$AU$39,13,0)) -> 75000 | E10: =VLOOKUP($A10,[8]HISTOJUIN21!$A$6:$AU$39,8,0) -> BANQUE | F10: =IF(N10="ECHEC",L10+(TONTMAI!I10*2),0) -> 0 | H10: =VLOOKUP($A10,[8]HISTOJUIN21!$A$6:$AU$39,36,0) -> 0 | I10: =VLOOKUP($A10,[8]HISTOJUIN21!$A$6:$AU$39,39,0) -> 0 | J10: =IF(H10<>0,VLOOKUP($A10,[8]HISTOJUIN21!$A$6:$AU$39,8,0),"ECHEC") -> ECHEC | K10: =VLOOKUP($A10,[8]HISTOJUIN21!$A$6:$AU$39,41,0) -> 0 | L10: =TONTMAI!H10+TONTMAI!I10+TONTMAI!F10 -> 0 | M10: =VLOOKUP(A10,[8]HISTOJUIN21!$A$6:$AZ$37,17,0) -> 0 | N10: =IF(M10<>0,VLOOKUP($A10,[8]HISTOJUIN21!$A$6:$AU$39,8,0),"ECHEC") -> ECHEC | O10: =IF(R10<>0,VLOOKUP($A10,[8]HISTOJUIN21!$A$6:$AU$39,8,0),"ECHEC") -> ECHEC | P10: =VLOOKUP($A10,[8]HISTOJUIN21!$A$6:$AU$39,33,0) -> 0 | Q10: =IF(R10=0,0,($C$37-R10)) -> 0 | R10: =VLOOKUP($A10,[8]HISTOJUIN21!$A$6:$AU$39,30,0) -> 0 | S10: =IF(R10=0,0,(R10-75000)) -> 0
A11: AS201611 | B11: =VLOOKUP(A11,[6]LISTADHERENT!A$5:H$60,3,0) -> HENGUE PAUL OMER | C11: =IF(E11="ECHEC",0,VLOOKUP($A11,[8]HISTOJUIN21!$A$6:$AU$39,13,0)) -> 75000 | E11: =VLOOKUP($A11,[8]HISTOJUIN21!$A$6:$AU$39,8,0) -> BANQUE | F11: =IF(N11="ECHEC",L11+(TONTMAI!I11*2),0) -> 0 | H11: =VLOOKUP($A11,[8]HISTOJUIN21!$A$6:$AU$39,36,0) -> 0 | I11: =VLOOKUP($A11,[8]HISTOJUIN21!$A$6:$AU$39,39,0) -> 0 | J11: =IF(H11<>0,VLOOKUP($A11,[8]HISTOJUIN21!$A$6:$AU$39,8,0),"ECHEC") -> ECHEC | K11: =VLOOKUP($A11,[8]HISTOJUIN21!$A$6:$AU$39,41,0) -> 0 | L11: =TONTMAI!H11+TONTMAI!I11+TONTMAI!F11 -> 0 | M11: =VLOOKUP(A11,[8]HISTOJUIN21!$A$6:$AZ$37,17,0) -> 0 | N11: =IF(M11<>0,VLOOKUP($A11,[8]HISTOJUIN21!$A$6:$AU$39,8,0),"ECHEC") -> ECHEC | O11: =IF(R11<>0,VLOOKUP($A11,[8]HISTOJUIN21!$A$6:$AU$39,8,0),"ECHEC") -> ECHEC | P11: =VLOOKUP($A11,[8]HISTOJUIN21!$A$6:$AU$39,33,0) -> 0 | Q11: =IF(R11=0,0,($C$37-R11)) -> 0 | R11: =VLOOKUP($A11,[8]HISTOJUIN21!$A$6:$AU$39,30,0) -> 0 | S11: =IF(R11=0,0,(R11-75000)) -> 0
A12: AS201619 | B12: =VLOOKUP(A12,[6]LISTADHERENT!A$5:H$60,3,0) -> KOUATCHO MESSACK | C12: =IF(E12="ECHEC",0,VLOOKUP($A12,[8]HISTOJUIN21!$A$6:$AU$39,13,0)) -> 75000 | E12: =VLOOKUP($A12,[8]HISTOJUIN21!$A$6:$AU$39,8,0) -> BANQUE | F12: =IF(N12="ECHEC",L12+(TONTMAI!I12*2),0) -> 0 | H12: =VLOOKUP($A12,[8]HISTOJUIN21!$A$6:$AU$39,36,0) -> 100000 | I12: =VLOOKUP($A12,[8]HISTOJUIN21!$A$6:$AU$39,39,0) -> 2000 | J12: =IF(H12<>0,VLOOKUP($A12,[8]HISTOJUIN21!$A$6:$AU$39,8,0),"ECHEC") -> BANQUE | K12: =VLOOKUP($A12,[8]HISTOJUIN21!$A$6:$AU$39,41,0) -> 0 | L12: =TONTMAI!H12+TONTMAI!I12+TONTMAI!F12 -> 123500 | M12: =VLOOKUP(A12,[8]HISTOJUIN21!$A$6:$AZ$37,17,0) -> 123500 | N12: =IF(M12<>0,VLOOKUP($A12,[8]HISTOJUIN21!$A$6:$AU$39,8,0),"ECHEC") -> BANQUE | O12: =IF(R12<>0,VLOOKUP($A12,[8]HISTOJUIN21!$A$6:$AU$39,8,0),"ECHEC") -> ECHEC | P12: =VLOOKUP($A12,[8]HISTOJUIN21!$A$6:$AU$39,33,0) -> 0 | Q12: =IF(R12=0,0,($C$37-R12)) -> 0 | R12: =VLOOKUP($A12,[8]HISTOJUIN21!$A$6:$AU$39,30,0) -> 0 | S12: =IF(R12=0,0,(R12-75000)) -> 0
A13: AS201621 | B13: =VLOOKUP(A13,[6]LISTADHERENT!A$5:H$60,3,0) -> NANKAM APPOLINAIRE | C13: =IF(E13="ECHEC",0,VLOOKUP($A13,[8]HISTOJUIN21!$A$6:$AU$39,13,0)) -> 75000 | E13: =VLOOKUP($A13,[8]HISTOJUIN21!$A$6:$AU$39,8,0) -> BANQUE | F13: =IF(N13="ECHEC",L13+(TONTMAI!I13*2),0) -> 0 | H13: =VLOOKUP($A13,[8]HISTOJUIN21!$A$6:$AU$39,36,0) -> 0 | I13: =VLOOKUP($A13,[8]HISTOJUIN21!$A$6:$AU$39,39,0) -> 0 | J13: =IF(H13<>0,VLOOKUP($A13,[8]HISTOJUIN21!$A$6:$AU$39,8,0),"ECHEC") -> ECHEC | K13: =VLOOKUP($A13,[8]HISTOJUIN21!$A$6:$AU$39,41,0) -> 0 | L13: =TONTMAI!H13+TONTMAI!I13+TONTMAI!F13 -> 0 | M13: =VLOOKUP(A13,[8]HISTOJUIN21!$A$6:$AZ$37,17,0) -> 0 | N13: =IF(M13<>0,VLOOKUP($A13,[8]HISTOJUIN21!$A$6:$AU$39,8,0),"ECHEC") -> ECHEC | O13: =IF(R13<>0,VLOOKUP($A13,[8]HISTOJUIN21!$A$6:$AU$39,8,0),"ECHEC") -> ECHEC | P13: =VLOOKUP($A13,[8]HISTOJUIN21!$A$6:$AU$39,33,0) -> 0 | Q13: =IF(R13=0,0,($C$37-R13)) -> 0 | R13: =VLOOKUP($A13,[8]HISTOJUIN21!$A$6:$AU$39,30,0) -> 0 | S13: =IF(R13=0,0,(R13-75000)) -> 0
A14: AS201649 | B14: =VLOOKUP(A14,[6]LISTADHERENT!A$5:H$60,3,0) -> MBOGNING TUGMA GUY | C14: =IF(E14="ECHEC",0,VLOOKUP($A14,[8]HISTOJUIN21!$A$6:$AU$39,13,0)) -> 225000 | E14: =VLOOKUP($A14,[8]HISTOJUIN21!$A$6:$AU$39,8,0) -> BANQUE | F14: =IF(N14="ECHEC",L14+(TONTMAI!I14*2),0) -> 0 | H14: =VLOOKUP($A14,[8]HISTOJUIN21!$A$6:$AU$39,36,0) -> 100000 | I14: =VLOOKUP($A14,[8]HISTOJUIN21!$A$6:$AU$39,39,0) -> 1000 | J14: =IF(H14<>0,VLOOKUP($A14,[8]HISTOJUIN21!$A$6:$AU$39,8,0),"ECHEC") -> BANQUE | K14: =VLOOKUP($A14,[8]HISTOJUIN21!$A$6:$AU$39,41,0) -> 0 | L14: =TONTMAI!H14+TONTMAI!I14+TONTMAI!F14 -> 51500 | M14: =VLOOKUP(A14,[8]HISTOJUIN21!$A$6:$AZ$37,17,0) -> 51500 | N14: =IF(M14<>0,VLOOKUP($A14,[8]HISTOJUIN21!$A$6:$AU$39,8,0),"ECHEC") -> BANQUE | O14: =IF(R14<>0,VLOOKUP($A14,[8]HISTOJUIN21!$A$6:$AU$39,8,0),"ECHEC") -> ECHEC | P14: =VLOOKUP($A14,[8]HISTOJUIN21!$A$6:$AU$39,33,0) -> 0 | Q14: =IF(R14=0,0,($C$37-R14)) -> 0 | R14: =VLOOKUP($A14,[8]HISTOJUIN21!$A$6:$AU$39,30,0) -> 0 | S14: =IF(R14=0,0,(R14-75000)) -> 0
A15: AS201649 | B15: =VLOOKUP(A15,[6]LISTADHERENT!A$5:H$60,3,0) -> MBOGNING TUGMA GUY | F15: =IF(N15="ECHEC",L15+(TONTMAI!I15*2),0) -> 0 | L15: =TONTMAI!H15+TONTMAI!I15+TONTMAI!F15 -> 0 | P15: =VLOOKUP($A15,[8]HISTOJUIN21!$A$6:$AU$39,33,0) -> 0 | R15: =VLOOKUP($A15,[8]HISTOJUIN21!$A$6:$AU$39,30,0) -> 0 | S15: =IF(R15=0,0,(R15-75000)) -> 0
A16: AS201649 | B16: =VLOOKUP(A16,[6]LISTADHERENT!A$5:H$60,3,0) -> MBOGNING TUGMA GUY | F16: =IF(N16="ECHEC",L16+(TONTMAI!I16*2),0) -> 0 | L16: =TONTMAI!H16+TONTMAI!I16+TONTMAI!F16 -> 0 | S16: =IF(R16=0,0,(R16-75000)) -> 0
A17: AS201626 | B17: =VLOOKUP(A17,[6]LISTADHERENT!A$5:H$60,3,0) -> NGUIEMEGNI MATHIEU BLAISE | C17: =IF(E17="ECHEC",0,VLOOKUP($A17,[8]HISTOJUIN21!$A$6:$AU$39,13,0)) -> 150000 | E17: =VLOOKUP($A17,[8]HISTOJUIN21!$A$6:$AU$39,8,0) -> BANQUE | F17: =IF(N17="ECHEC",L17+(TONTMAI!I17*2),0) -> 0 | H17: =VLOOKUP($A17,[8]HISTOJUIN21!$A$6:$AU$39,36,0) -> 50000 | I17: =VLOOKUP($A17,[8]HISTOJUIN21!$A$6:$AU$39,39,0) -> 1000 | J17: =IF(H17<>0,VLOOKUP($A17,[8]HISTOJUIN21!$A$6:$AU$39,8,0),"ECHEC") -> BANQUE | K17: =VLOOKUP($A17,[8]HISTOJUIN21!$A$6:$AU$39,41,0) -> 0 | L17: =TONTMAI!H17+TONTMAI!I17+TONTMAI!F17 -> 0 | M17: =VLOOKUP(A17,[8]HISTOJUIN21!$A$6:$AZ$37,17,0) -> 0 | N17: =IF(M17<>0,VLOOKUP($A17,[8]HISTOJUIN21!$A$6:$AU$39,8,0),"ECHEC") -> ECHEC | O17: =IF(R17<>0,VLOOKUP($A17,[8]HISTOJUIN21!$A$6:$AU$39,8,0),"ECHEC") -> BANQUE | P17: =VLOOKUP($A17,[8]HISTOJUIN21!$A$6:$AU$39,33,0) -> 0 | Q17: =IF(R17=0,0,($C$37-R17)) -> 1120000 | R17: =VLOOKUP($A17,[8]HISTOJUIN21!$A$6:$AU$39,30,0) -> 80000 | S17: =IF(R17=0,0,(R17-75000)) -> 5000
A18: AS201626 | B18: =VLOOKUP(A18,[6]LISTADHERENT!A$5:H$60,3,0) -> NGUIEMEGNI MATHIEU BLAISE | F18: =IF(N18="ECHEC",L18+(TONTMAI!I18*2),0) -> 0 | L18: =TONTMAI!H18+TONTMAI!I18+TONTMAI!F18 -> 0 | N18: =IF(M18<>0,VLOOKUP($A18,[8]HISTOJUIN21!$A$6:$AU$39,8,0),"ECHEC") -> ECHEC | O18: =IF(R18<>0,VLOOKUP($A18,[8]HISTOJUIN21!$A$6:$AU$39,8,0),"ECHEC") -> ECHEC | S18: =IF(R18=0,0,(R18-75000)) -> 0
A19: AS201628 | B19: =VLOOKUP(A19,[6]LISTADHERENT!A$5:H$60,3,0) -> NKAMGANG JUSTIN DEJOLIE | C19: =IF(E19="ECHEC",0,VLOOKUP($A19,[8]HISTOJUIN21!$A$6:$AU$39,13,0)) -> 75000 | E19: =VLOOKUP($A19,[8]HISTOJUIN21!$A$6:$AU$39,8,0) -> BANQUE | F19: =IF(N19="ECHEC",L19+(TONTMAI!I19*2),0) -> 0 | H19: =VLOOKUP($A19,[8]HISTOJUIN21!$A$6:$AU$39,36,0) -> 100000 | I19: =VLOOKUP($A19,[8]HISTOJUIN21!$A$6:$AU$39,39,0) -> 2000 | J19: =IF(H19<>0,VLOOKUP($A19,[8]HISTOJUIN21!$A$6:$AU$39,8,0),"ECHEC") -> BANQUE | K19: =VLOOKUP($A19,[8]HISTOJUIN21!$A$6:$AU$39,41,0) -> 0 | L19: =TONTMAI!H19+TONTMAI!I19+TONTMAI!F19 -> 103000 | M19: =VLOOKUP(A19,[8]HISTOJUIN21!$A$6:$AZ$37,17,0) -> 103000 | N19: =IF(M19<>0,VLOOKUP($A19,[8]HISTOJUIN21!$A$6:$AU$39,8,0),"ECHEC") -> BANQUE | O19: =IF(R19<>0,VLOOKUP($A19,[8]HISTOJUIN21!$A$6:$AU$39,8,0),"ECHEC") -> ECHEC | P19: =VLOOKUP($A19,[8]HISTOJUIN21!$A$6:$AU$39,33,0) -> 0 | Q19: =IF(R19=0,0,($C$37-R19)) -> 0 | R19: =VLOOKUP($A19,[8]HISTOJUIN21!$A$6:$AU$39,30,0) -> 0 | S19: =IF(R19=0,0,(R19-75000)) -> 0
A20: AS201633 | B20: =VLOOKUP(A20,[6]LISTADHERENT!A$5:H$60,3,0) -> PATEGO NJOSSU GUSTAVE | C20: =IF(E20="ECHEC",0,VLOOKUP($A20,[8]HISTOJUIN21!$A$6:$AU$39,13,0)) -> 75000 | E20: =VLOOKUP($A20,[8]HISTOJUIN21!$A$6:$AU$39,8,0) -> BANQUE | F20: =IF(N20="ECHEC",L20+(TONTMAI!I20*2),0) -> 0 | H20: =VLOOKUP($A20,[8]HISTOJUIN21!$A$6:$AU$39,36,0) -> 0 | I20: =VLOOKUP($A20,[8]HISTOJUIN21!$A$6:$AU$39,39,0) -> 0 | J20: =IF(H20<>0,VLOOKUP($A20,[8]HISTOJUIN21!$A$6:$AU$39,8,0),"ECHEC") -> ECHEC | K20: =VLOOKUP($A20,[8]HISTOJUIN21!$A$6:$AU$39,41,0) -> 0 | L20: =TONTMAI!H20+TONTMAI!I20+TONTMAI!F20 -> 0 | M20: =VLOOKUP(A20,[8]HISTOJUIN21!$A$6:$AZ$37,17,0) -> 0 | N20: =IF(M20<>0,VLOOKUP($A20,[8]HISTOJUIN21!$A$6:$AU$39,8,0),"ECHEC") -> ECHEC | O20: =IF(R20<>0,VLOOKUP($A20,[8]HISTOJUIN21!$A$6:$AU$39,8,0),"ECHEC") -> ECHEC | P20: =VLOOKUP($A20,[8]HISTOJUIN21!$A$6:$AU$39,33,0) -> 0 | Q20: =IF(R20=0,0,($C$37-R20)) -> 0 | R20: =VLOOKUP($A20,[8]HISTOJUIN21!$A$6:$AU$39,30,0) -> 0 | S20: =IF(R20=0,0,(R20-75000)) -> 0
A21: AS201638 | B21: =VLOOKUP(A21,[6]LISTADHERENT!A$5:H$60,3,0) -> SIMO PIERRE | C21: =IF(E21="ECHEC",0,VLOOKUP($A21,[8]HISTOJUIN21!$A$6:$AU$39,13,0)) -> 75000 | E21: =VLOOKUP($A21,[8]HISTOJUIN21!$A$6:$AU$39,8,0) -> BANQUE | F21: =IF(N21="ECHEC",L21+(TONTMAI!I21*2),0) -> 0 | H21: =VLOOKUP($A21,[8]HISTOJUIN21!$A$6:$AU$39,36,0) -> 0 | I21: =VLOOKUP($A21,[8]HISTOJUIN21!$A$6:$AU$39,39,0) -> 0 | J21: =IF(H21<>0,VLOOKUP($A21,[8]HISTOJUIN21!$A$6:$AU$39,8,0),"ECHEC") -> ECHEC | K21: =VLOOKUP($A21,[8]HISTOJUIN21!$A$6:$AU$39,41,0) -> 0 | L21: =TONTMAI!H21+TONTMAI!I21+TONTMAI!F21 -> 0 | M21: =VLOOKUP(A21,[8]HISTOJUIN21!$A$6:$AZ$37,17,0) -> 0 | N21: =IF(M21<>0,VLOOKUP($A21,[8]HISTOJUIN21!$A$6:$AU$39,8,0),"ECHEC") -> ECHEC | O21: =IF(R21<>0,VLOOKUP($A21,[8]HISTOJUIN21!$A$6:$AU$39,8,0),"ECHEC") -> ECHEC | P21: =VLOOKUP($A21,[8]HISTOJUIN21!$A$6:$AU$39,33,0) -> 0 | Q21: =IF(R21=0,0,($C$37-R21)) -> 0 | R21: =VLOOKUP($A21,[8]HISTOJUIN21!$A$6:$AU$39,30,0) -> 0 | S21: =IF(R21=0,0,(R21-75000)) -> 0
A22: AS201655 | B22: =VLOOKUP(A22,[6]LISTADHERENT!A$5:H$60,3,0) -> TCHEMHOU EMMANUEL | C22: =IF(E22="ECHEC",0,VLOOKUP($A22,[8]HISTOJUIN21!$A$6:$AU$39,13,0)) -> 0 | F22: =IF(N22="ECHEC",L22+(TONTMAI!I22*2),0) -> 0 | H22: =VLOOKUP($A22,[8]HISTOJUIN21!$A$6:$AU$39,36,0) -> 0 | I22: =VLOOKUP($A22,[8]HISTOJUIN21!$A$6:$AU$39,39,0) -> 0 | J22: =IF(H22<>0,VLOOKUP($A22,[8]HISTOJUIN21!$A$6:$AU$39,8,0),"ECHEC") -> ECHEC | K22: =VLOOKUP($A22,[8]HISTOJUIN21!$A$6:$AU$39,41,0) -> 0 | L22: =TONTMAI!H22+TONTMAI!I22+TONTMAI!F22 -> 0 | M22: =VLOOKUP(A22,[8]HISTOJUIN21!$A$6:$AZ$37,17,0) -> 0 | N22: =IF(M22<>0,VLOOKUP($A22,[8]HISTOJUIN21!$A$6:$AU$39,8,0),"ECHEC") -> ECHEC | O22: =IF(R22<>0,VLOOKUP($A22,[8]HISTOJUIN21!$A$6:$AU$39,8,0),"ECHEC") -> ECHEC | P22: =VLOOKUP($A22,[8]HISTOJUIN21!$A$6:$AU$39,33,0) -> 0 | Q22: =IF(R22=0,0,($C$37-R22)) -> 0 | R22: =VLOOKUP($A22,[8]HISTOJUIN21!$A$6:$AU$39,30,0) -> 0 | S22: =IF(R22=0,0,(R22-75000)) -> 0
A23: AS201647 | B23: =VLOOKUP(A23,[6]LISTADHERENT!A$5:H$60,3,0) -> YOUMBI EMMANUEL | C23: =IF(E23="ECHEC",0,VLOOKUP($A23,[8]HISTOJUIN21!$A$6:$AU$39,13,0)) -> 150000 | E23: =VLOOKUP($A23,[8]HISTOJUIN21!$A$6:$AU$39,8,0) -> BANQUE | F23: =IF(N23="ECHEC",L23+(TONTMAI!I23*2),0) -> 0 | H23: =VLOOKUP($A23,[8]HISTOJUIN21!$A$6:$AU$39,36,0) -> 0 | I23: =VLOOKUP($A23,[8]HISTOJUIN21!$A$6:$AU$39,39,0) -> 0 | J23: =IF(H23<>0,VLOOKUP($A23,[8]HISTOJUIN21!$A$6:$AU$39,8,0),"ECHEC") -> ECHEC | K23: =VLOOKUP($A23,[8]HISTOJUIN21!$A$6:$AU$39,41,0) -> 0 | L23: =TONTMAI!H23+TONTMAI!I23+TONTMAI!F23 -> 0 | N23: =IF(M23<>0,VLOOKUP($A23,[8]HISTOJUIN21!$A$6:$AU$39,8,0),"ECHEC") -> ECHEC | O23: =IF(R23<>0,VLOOKUP($A23,[8]HISTOJUIN21!$A$6:$AU$39,8,0),"ECHEC") -> ECHEC | P23: =VLOOKUP($A23,[8]HISTOJUIN21!$A$6:$AU$39,33,0) -> 0 | Q23: =IF(R23=0,0,($C$37-R23)) -> 0 | R23: =VLOOKUP($A23,[8]HISTOJUIN21!$A$6:$AU$39,30,0) -> 0 | S23: =IF(R23=0,0,(R23-75000)) -> 0
A24: AS201647 | B24: =VLOOKUP(A24,[6]LISTADHERENT!A$5:H$60,3,0) -> YOUMBI EMMANUEL | F24: =IF(N24="ECHEC",L24+(TONTMAI!I24*2),0) -> 0 | S24: =IF(R24=0,0,(R24-75000)) -> 0
S26: =SUM(S6:S24) -> 5000
B27: TOTAL | C27: =SUM(C6:C26) -> 1275000 | D27: =SUM(D6:D26) -> 0 | E27: =SUM(E6:E26) -> 0 | F27: =SUM(F6:F26) -> 0 | G27: =SUM(G6:G26) -> 0 | H27: =SUM(H6:H26) -> 688500 | I27: =SUM(I6:I26) -> 12000 | J27: =SUM(J6:J26) -> 0 | ... R27: =SUM(R6:R26) -> 80000
C29: TONTINE | D29: REMBOURSEMENT PETIT LOT | E29: VENTE PETIT LOT | F29: VENTE LOT PRINCIPAL | G29: SOLDE EN CAISSE | K29: TONTINE + REMB + INTERET VENTE | L29: =C34+D34+R27+TONTMAI!M34 -> 1888500
K30: LOT PRINCIPAL | L30: =C3*COUNTIF(Q6:Q26,">0") -> 1200000 | M30: =D3 -> 1
B31: ESPECES | C31: =SUMIFS(C6:C25,E6:E25,"ESPECES") -> 0 | D31: =SUMIFS(L2:L21,N2:N21,"ESPECES")+SUMIFS(F2:F21,G2:G21,"ESPECES") -> 0 | E31: =SUMIFS(H6:H25,J6:J25,"ESPECES") -> 0 | F31: =SUMIFS(Q6:Q25,O6:O25,"ESPECES") -> 0 | G31: =C31+D31-E31-F31 -> 0
B32: BANQUE | C32: =SUMIFS(C6:C25,E6:E25,"BANQUE") -> 1275000 | D32: =SUMIFS(M3:M22,N3:N22,"BANQUE")+SUMIFS(F3:F22,G3:G22,"BANQUE") -> 533500 | E32: =SUMIFS(H6:H25,J6:J25,"BANQUE") -> 688500 | F32: =SUMIFS(Q6:Q25,O6:O25,"BANQUE") -> 1120000 | G32: =C32+D32-E32-F32 -> 0 | K32: PETIT LOT | L32: =L29-L30 -> 688500
B34: TOTAL | C34: =C31+C32 -> 1275000 | D34: =D31+D32 -> 533500 | E34: =E31+E32 -> 688500 | F34: =F31+F32 -> 1120000 | G34: =G31+G32 -> 0 | K34: RELIQUAT | L34: =L32-H27 -> 0 | M34: =L34 -> 0 | N34: CUMUL
K36: ECHEC TONTINE | L36: =COUNTIFS(E6:E25,"ECHEC")*75000 -> 0 | M36: =L36+TONTMAI!M36 -> 0 | N36: CUMUL
B37: MONTANT TONTINE | C37: 1200000 | K37: ECHEC REMBOURSEMENT | L37: =SUMIFS(F3:F22,G3:G22,"ECHEC") -> 0 | M37: =L37+TONTMAI!M37 -> 0 | N37: CUMUL

Sheet TONTJUIL21
A1: ASSOCIATION | B1: ASELBY
A2: ANNEE | B2: 2021 | C2: TONIINE | D2: NBRE PART
A3: TAUX TONTINE | B3: 75000 | C3: =B3*16 -> 1200000 | D3: =ROUNDDOWN(L29/C3,0) -> 1
C4: 44398
A5: MATRICULE | B5: NOM ET PRENOM | C5: MONTANT TONTINE | D5: PENALITE | E5: MODE VERSEMENT TONTINE | F5: REPORT ECHEC PETIT LOT | G5: MODE VERSEMENT VENTE PETIT LOT | H5: VENTE PETIT LOT | I5: INTERET PETIT LOT | J5: MODE VERSEMENT VENTE PETIT LOT | K5: NUMERO CHEQUE | L5: MONTANT A REMBOURSER | M5: MONTANT REMBOURSE | N5: MODE VERSEMENT REMBOURSEMENT | O5: MODE VERSEMENT TONTINE PRINCIPAL | P5: NUMERO CHEQUE | Q5: MONTANT TONTINE LOT PRINCIPAL | R5: INTERET LOT PRINCIPAL | S5: INTERET DU
A6: AS201602 | B6: =VLOOKUP(A6,[6]LISTADHERENT!A$5:H$60,3,0) -> BOUTCHOUANG WILLIAM | C6: =IF(E6="ECHEC",0,VLOOKUP($A6,[8]HISTOJUIL21!$A$6:$AU$39,13,0)) -> 75000 | E6: =VLOOKUP($A6,[8]HISTOJUIL21!$A$6:$AU$39,8,0) -> BANQUE | F6: =IF(N6="ECHEC",L6+(TONTJUIN!I6*2),0) -> 0 | H6: =VLOOKUP($A6,[8]HISTOJUIL21!$A$6:$AU$39,36,0) -> 0 | I6: =VLOOKUP($A6,[8]HISTOJUIL21!$A$6:$AU$39,39,0) -> 0 | J6: =IF(H6<>0,VLOOKUP($A6,[8]HISTOJUIL21!$A$6:$AU$39,8,0),"ECHEC") -> ECHEC | K6: =VLOOKUP($A6,[8]HISTOJUIL21!$A$6:$AU$39,41,0) -> 0 | L6: =TONTJUIN!H6+TONTJUIN!I6+TONTJUIN!F6 -> 0 | M6: =VLOOKUP(A6,[8]HISTOJUIL21!$A$6:$AZ$37,17,0) -> 0 | N6: =IF(L6<>0,VLOOKUP($A6,[8]HISTOJUIL21!$A$6:$AU$39,8,0),"ECHEC") -> ECHEC | O6: =IF(R6<>0,VLOOKUP($A6,[8]HISTOJUIL21!$A$6:$AU$39,8,0),"ECHEC") -> ECHEC | P6: =VLOOKUP($A6,[8]HISTOJUIL21!$A$6:$AU$39,33,0) -> 0 | Q6: =IF(R6=0,0,($C$37-R6)) -> 0 | R6: =VLOOKUP($A6,[8]HISTOJUIL21!$A$6:$AU$39,30,0) -> 0 | S6: =IF(R6=0,0,(R6-75000)) -> 0
A7: AS201603 | B7: =VLOOKUP(A7,[6]LISTADHERENT!A$5:H$60,3,0) -> CHINGUE FABRICE | F7: =IF(N7="ECHEC",L7+(TONTJUIN!I7*2),0) -> 0 | L7: =TONTJUIN!H7+TONTJUIN!I7+TONTJUIN!F7 -> 0 | S7: =IF(R7=0,0,(R7-75000)) -> 0
A8: AS201604 | B8: =VLOOKUP(A8,[6]LISTADHERENT!A$5:H$60,3,0) -> DJOMO JEAN PAUL | C8: =IF(E8="ECHEC",0,VLOOKUP($A8,[8]HISTOJUIL21!$A$6:$AU$39,13,0)) -> 75000 | E8: =VLOOKUP($A8,[8]HISTOJUIL21!$A$6:$AU$39,8,0) -> BANQUE | F8: =IF(N8="ECHEC",L8+(TONTJUIN!I8*2),0) -> 0 | H8: =VLOOKUP($A8,[8]HISTOJUIL21!$A$6:$AU$39,36,0) -> 200000 | I8: =VLOOKUP($A8,[8]HISTOJUIL21!$A$6:$AU$39,39,0) -> 2000 | J8: =IF(H8<>0,VLOOKUP($A8,[8]HISTOJUIL21!$A$6:$AU$39,8,0),"ECHEC") -> BANQUE | K8: =VLOOKUP($A8,[8]HISTOJUIL21!$A$6:$AU$39,41,0) -> 0 | L8: =TONTJUIN!H8+TONTJUIN!I8+TONTJUIN!F8 -> 140500 | M8: =VLOOKUP(A8,[8]HISTOJUIL21!$A$6:$AZ$37,17,0) -> 140500 | N8: =IF(M8<>0,VLOOKUP($A8,[8]HISTOJUIL21!$A$6:$AU$39,8,0),"ECHEC") -> BANQUE | O8: =IF(R8<>0,VLOOKUP($A8,[8]HISTOJUIL21!$A$6:$AU$39,8,0),"ECHEC") -> ECHEC | P8: =VLOOKUP($A8,[8]HISTOJUIL21!$A$6:$AU$39,33,0) -> 0 | Q8: =IF(R8=0,0,($C$37-R8)) -> 0 | R8: =VLOOKUP($A8,[8]HISTOJUIL21!$A$6:$AU$39,30,0) -> 0 | S8: =IF(R8=0,0,(R8-75000)) -> 0
A9: AS201605 | B9: =VLOOKUP(A9,[6]LISTADHERENT!A$5:H$60,3,0) -> DJOUKWE NANGUEN GUY BLAISE | C9: =IF(E9="ECHEC",0,VLOOKUP($A9,[8]HISTOJUIL21!$A$6:$AU$39,13,0)) -> 75000 | E9: =VLOOKUP($A9,[8]HISTOJUIL21!$A$6:$AU$39,8,0) -> BANQUE | F9: =IF(N9="ECHEC",L9+(TONTJUIN!I9*2),0) -> 0 | H9: =VLOOKUP($A9,[8]HISTOJUIL21!$A$6:$AU$39,36,0) -> 149500 | I9: =VLOOKUP($A9,[8]HISTOJUIL21!$A$6:$AU$39,39,0) -> 2000 | J9: =IF(H9<>0,VLOOKUP($A9,[8]HISTOJUIL21!$A$6:$AU$39,8,0),"ECHEC") -> BANQUE | K9: =VLOOKUP($A9,[8]HISTOJUIL21!$A$6:$AU$39,41,0) -> 0 | L9: =TONTJUIN!H9+TONTJUIN!I9+TONTJUIN!F9 -> 204000 | M9: =VLOOKUP(A9,[8]HISTOJUIL21!$A$6:$AZ$37,17,0) -> 204000 | N9: =IF(M9<>0,VLOOKUP($A9,[8]HISTOJUIL21!$A$6:$AU$39,8,0),"ECHEC") -> BANQUE | O9: =IF(R9<>0,VLOOKUP($A9,[8]HISTOJUIL21!$A$6:$AU$39,8,0),"ECHEC") -> ECHEC | P9: =VLOOKUP($A9,[8]HISTOJUIL21!$A$6:$AU$39,33,0) -> 0 | Q9: =IF(R9=0,0,($C$37-R9)) -> 0 | R9: =VLOOKUP($A9,[8]HISTOJUIL21!$A$6:$AU$39,30,0) -> 0 | S9: =IF(R9=0,0,(R9-75000)) -> 0
A10: AS201613 | B10: =VLOOKUP(A10,[6]LISTADHERENT!A$5:H$60,3,0) -> HOTCHO BENJAMIN | C10: =IF(E10="ECHEC",0,VLOOKUP($A10,[8]HISTOJUIL21!$A$6:$AU$39,13,0)) -> 75000 | E10: =VLOOKUP($A10,[8]HISTOJUIL21!$A$6:$AU$39,8,0) -> BANQUE | F10: =IF(N10="ECHEC",L10+(TONTJUIN!I10*2),0) -> 0 | H10: =VLOOKUP($A10,[8]HISTOJUIL21!$A$6:$AU$39,36,0) -> 0 | I10: =VLOOKUP($A10,[8]HISTOJUIL21!$A$6:$AU$39,39,0) -> 0 | J10: =IF(H10<>0,VLOOKUP($A10,[8]HISTOJUIL21!$A$6:$AU$39,8,0),"ECHEC") -> ECHEC | K10: =VLOOKUP($A10,[8]HISTOJUIL21!$A$6:$AU$39,41,0) -> 0 | L10: =TONTJUIN!H10+TONTJUIN!I10+TONTJUIN!F10 -> 0 | M10: =VLOOKUP(A10,[8]HISTOJUIL21!$A$6:$AZ$37,17,0) -> 0 | N10: =IF(M10<>0,VLOOKUP($A10,[8]HISTOJUIL21!$A$6:$AU$39,8,0),"ECHEC") -> ECHEC | O10: =IF(R10<>0,VLOOKUP($A10,[8]HISTOJUIL21!$A$6:$AU$39,8,0),"ECHEC") -> ECHEC | P10: =VLOOKUP($A10,[8]HISTOJUIL21!$A$6:$AU$39,33,0) -> 0 | Q10: =IF(R10=0,0,($C$37-R10)) -> 0 | R10: =VLOOKUP($A10,[8]HISTOJUIL21!$A$6:$AU$39,30,0) -> 0 | S10: =IF(R10=0,0,(R10-75000)) -> 0
A11: AS201611 | B11: =VLOOKUP(A11,[6]LISTADHERENT!A$5:H$60,3,0) -> HENGUE PAUL OMER | C11: =IF(E11="ECHEC",0,VLOOKUP($A11,[8]HISTOJUIL21!$A$6:$AU$39,13,0)) -> 75000 | E11: =VLOOKUP($A11,[8]HISTOJUIL21!$A$6:$AU$39,8,0) -> BANQUE | F11: =IF(N11="ECHEC",L11+(TONTJUIN!I11*2),0) -> 0 | H11: =VLOOKUP($A11,[8]HISTOJUIL21!$A$6:$AU$39,36,0) -> 0 | I11: =VLOOKUP($A11,[8]HISTOJUIL21!$A$6:$AU$39,39,0) -> 0 | J11: =IF(H11<>0,VLOOKUP($A11,[8]HISTOJUIL21!$A$6:$AU$39,8,0),"ECHEC") -> ECHEC | K11: =VLOOKUP($A11,[8]HISTOJUIL21!$A$6:$AU$39,41,0) -> 0 | L11: =TONTJUIN!H11+TONTJUIN!I11+TONTJUIN!F11 -> 0 | M11: =VLOOKUP(A11,[8]HISTOJUIL21!$A$6:$AZ$37,17,0) -> 0 | N11: =IF(M11<>0,VLOOKUP($A11,[8]HISTOJUIL21!$A$6:$AU$39,8,0),"ECHEC") -> ECHEC | O11: =IF(R11<>0,VLOOKUP($A11,[8]HISTOJUIL21!$A$6:$AU$39,8,0),"ECHEC") -> ECHEC | P11: =VLOOKUP($A11,[8]HISTOJUIL21!$A$6:$AU$39,33,0) -> 0 | Q11: =IF(R11=0,0,($C$37-R11)) -> 0 | R11: =VLOOKUP($A11,[8]HISTOJUIL21!$A$6:$AU$39,30,0) -> 0 | S11: =IF(R11=0,0,(R11-75000)) -> 0
A12: AS201619 | B12: =VLOOKUP(A12,[6]LISTADHERENT!A$5:H$60,3,0) -> KOUATCHO MESSACK | C12: =IF(E12="ECHEC",0,VLOOKUP($A12,[8]HISTOJUIL21!$A$6:$AU$39,13,0)) -> 75000 | E12: =VLOOKUP($A12,[8]HISTOJUIL21!$A$6:$AU$39,8,0) -> BANQUE | F12: =IF(N12="ECHEC",L12+(TONTJUIN!I12*2),0) -> 0 | H12: =VLOOKUP($A12,[8]HISTOJUIL21!$A$6:$AU$39,36,0) -> 200000 | I12: =VLOOKUP($A12,[8]HISTOJUIL21!$A$6:$AU$39,39,0) -> 2000 | J12: =IF(H12<>0,VLOOKUP($A12,[8]HISTOJUIL21!$A$6:$AU$39,8,0),"ECHEC") -> BANQUE | K12: =VLOOKUP($A12,[8]HISTOJUIL21!$A$6:$AU$39,41,0) -> 0 | L12: =TONTJUIN!H12+TONTJUIN!I12+TONTJUIN!F12 -> 102000 | M12: =VLOOKUP(A12,[8]HISTOJUIL21!$A$6:$AZ$37,17,0) -> 102000 | N12: =IF(M12<>0,VLOOKUP($A12,[8]HISTOJUIL21!$A$6:$AU$39,8,0),"ECHEC") -> BANQUE | O12: =IF(R12<>0,VLOOKUP($A12,[8]HISTOJUIL21!$A$6:$AU$39,8,0),"ECHEC") -> ECHEC | P12: =VLOOKUP($A12,[8]HISTOJUIL21!$A$6:$AU$39,33,0) -> 0 | Q12: =IF(R12=0,0,($C$37-R12)) -> 0 | R12: =VLOOKUP($A12,[8]HISTOJUIL21!$A$6:$AU$39,30,0) -> 0 | S12: =IF(R12=0,0,(R12-75000)) -> 0
A13: AS201621 | B13: =VLOOKUP(A13,[6]LISTADHERENT!A$5:H$60,3,0) -> NANKAM APPOLINAIRE | C13: =IF(E13="ECHEC",0,VLOOKUP($A13,[8]HISTOJUIL21!$A$6:$AU$39,13,0)) -> 75000 | E13: =VLOOKUP($A13,[8]HISTOJUIL21!$A$6:$AU$39,8,0) -> BANQUE | F13: =IF(N13="ECHEC",L13+(TONTJUIN!I13*2),0) -> 0 | H13: =VLOOKUP($A13,[8]HISTOJUIL21!$A$6:$AU$39,36,0) -> 0 | I13: =VLOOKUP($A13,[8]HISTOJUIL21!$A$6:$AU$39,39,0) -> 0 | J13: =IF(H13<>0,VLOOKUP($A13,[8]HISTOJUIL21!$A$6:$AU$39,8,0),"ECHEC") -> ECHEC | K13: =VLOOKUP($A13,[8]HISTOJUIL21!$A$6:$AU$39,41,0) -> 0 | L13: =TONTJUIN!H13+TONTJUIN!I13+TONTJUIN!F13 -> 0 | M13: =VLOOKUP(A13,[8]HISTOJUIL21!$A$6:$AZ$37,17,0) -> 0 | N13: =IF(M13<>0,VLOOKUP($A13,[8]HISTOJUIL21!$A$6:$AU$39,8,0),"ECHEC") -> ECHEC | O13: =IF(R13<>0,VLOOKUP($A13,[8]HISTOJUIL21!$A$6:$AU$39,8,0),"ECHEC") -> ECHEC | P13: =VLOOKUP($A13,[8]HISTOJUIL21!$A$6:$AU$39,33,0) -> 0 | Q13: =IF(R13=0,0,($C$37-R13)) -> 0 | R13: =VLOOKUP($A13,[8]HISTOJUIL21!$A$6:$AU$39,30,0) -> 0 | S13: =IF(R13=0,0,(R13-75000)) -> 0
A14: AS201649 | B14: =VLOOKUP(A14,[6]LISTADHERENT!A$5:H$60,3,0) -> MBOGNING TUGMA GUY | C14: =IF(E14="ECHEC",0,VLOOKUP($A14,[8]HISTOJUIL21!$A$6:$AU$39,13,0)) -> 225000 | E14: =VLOOKUP($A14,[8]HISTOJUIL21!$A$6:$AU$39,8,0) -> BANQUE | F14: =IF(N14="ECHEC",L14+(TONTJUIN!I14*2),0) -> 0 | H14: =VLOOKUP($A14,[8]HISTOJUIL21!$A$6:$AU$39,36,0) -> 0 | I14: =VLOOKUP($A14,[8]HISTOJUIL21!$A$6:$AU$39,39,0) -> 0 | J14: =IF(H14<>0,VLOOKUP($A14,[8]HISTOJUIL21!$A$6:$AU$39,8,0),"ECHEC") -> ECHEC | K14: =VLOOKUP($A14,[8]HISTOJUIL21!$A$6:$AU$39,41,0) -> 0 | L14: =TONTJUIN!H14+TONTJUIN!I14+TONTJUIN!F14 -> 101000 | M14: =VLOOKUP(A14,[8]HISTOJUIL21!$A$6:$AZ$37,17,0) -> 101000 | N14: =IF(M14<>0,VLOOKUP($A14,[8]HISTOJUIL21!$A$6:$AU$39,8,0),"ECHEC") -> BANQUE | O14: =IF(R14<>0,VLOOKUP($A14,[8]HISTOJUIL21!$A$6:$AU$39,8,0),"ECHEC") -> ECHEC | P14: =VLOOKUP($A14,[8]HISTOJUIL21!$A$6:$AU$39,33,0) -> 0 | Q14: =IF(R14=0,0,($C$37-R14)) -> 0 | R14: =VLOOKUP($A14,[8]HISTOJUIL21!$A$6:$AU$39,30,0) -> 0 | S14: =IF(R14=0,0,(R14-75000)) -> 0
A15: AS201649 | B15: =VLOOKUP(A15,[6]LISTADHERENT!A$5:H$60,3,0) -> MBOGNING TUGMA GUY | F15: =IF(N15="ECHEC",L15+(TONTJUIN!I15*2),0) -> 0 | L15: =TONTJUIN!H15+TONTJUIN!I15+TONTJUIN!F15 -> 0 | P15: =VLOOKUP($A15,[8]HISTOJUIL21!$A$6:$AU$39,33,0) -> 0 | R15: =VLOOKUP($A15,[8]HISTOJUIL21!$A$6:$AU$39,30,0) -> 0 | S15: =IF(R15=0,0,(R15-75000)) -> 0
A16: AS201649 | B16: =VLOOKUP(A16,[6]LISTADHERENT!A$5:H$60,3,0) -> MBOGNING TUGMA GUY | F16: =IF(N16="ECHEC",L16+(TONTJUIN!I16*2),0) -> 0 | L16: =TONTJUIN!H16+TONTJUIN!I16+TONTJUIN!F16 -> 0 | S16: =IF(R16=0,0,(R16-75000)) -> 0
A17: AS201626 | B17: =VLOOKUP(A17,[6]LISTADHERENT!A$5:H$60,3,0) -> NGUIEMEGNI MATHIEU BLAISE | C17: =IF(E17="ECHEC",0,VLOOKUP($A17,[8]HISTOJUIL21!$A$6:$AU$39,13,0)) -> 150000 | E17: =VLOOKUP($A17,[8]HISTOJUIL21!$A$6:$AU$39,8,0) -> BANQUE | F17: =IF(N17="ECHEC",L17+(TONTJUIN!I17*2),0) -> 0 | H17: =VLOOKUP($A17,[8]HISTOJUIL21!$A$6:$AU$39,36,0) -> 100000 | I17: =VLOOKUP($A17,[8]HISTOJUIL21!$A$6:$AU$39,39,0) -> 1000 | J17: =IF(H17<>0,VLOOKUP($A17,[8]HISTOJUIL21!$A$6:$AU$39,8,0),"ECHEC") -> BANQUE | K17: =VLOOKUP($A17,[8]HISTOJUIL21!$A$6:$AU$39,41,0) -> 0 | L17: =TONTJUIN!H17+TONTJUIN!I17+TONTJUIN!F17 -> 51000 | M17: =VLOOKUP(A17,[8]HISTOJUIL21!$A$6:$AZ$37,17,0) -> 51000 | N17: =IF(M17<>0,VLOOKUP($A17,[8]HISTOJUIL21!$A$6:$AU$39,8,0),"ECHEC") -> BANQUE | O17: =IF(R17<>0,VLOOKUP($A17,[8]HISTOJUIL21!$A$6:$AU$39,8,0),"ECHEC") -> ECHEC | P17: =VLOOKUP($A17,[8]HISTOJUIL21!$A$6:$AU$39,33,0) -> 0 | Q17: =IF(R17=0,0,($C$37-R17)) -> 0 | R17: =VLOOKUP($A17,[8]HISTOJUIL21!$A$6:$AU$39,30,0) -> 0 | S17: =IF(R17=0,0,(R17-75000)) -> 0
A18: AS201626 | B18: =VLOOKUP(A18,[6]LISTADHERENT!A$5:H$60,3,0) -> NGUIEMEGNI MATHIEU BLAISE | F18: =IF(N18="ECHEC",L18+(TONTJUIN!I18*2),0) -> 0 | L18: =TONTJUIN!H18+TONTJUIN!I18+TONTJUIN!F18 -> 0 | N18: =IF(M18<>0,VLOOKUP($A18,[8]HISTOJUIL21!$A$6:$AU$39,8,0),"ECHEC") -> ECHEC | O18: =IF(R18<>0,VLOOKUP($A18,[8]HISTOJUIL21!$A$6:$AU$39,8,0),"ECHEC") -> ECHEC | S18: =IF(R18=0,0,(R18-75000)) -> 0
A19: AS201628 | B19: =VLOOKUP(A19,[6]LISTADHERENT!A$5:H$60,3,0) -> NKAMGANG JUSTIN DEJOLIE | C19: =IF(E19="ECHEC",0,VLOOKUP($A19,[8]HISTOJUIL21!$A$6:$AU$39,13,0)) -> 75000 | E19: =VLOOKUP($A19,[8]HISTOJUIL21!$A$6:$AU$39,8,0) -> ESPECES | F19: =IF(N19="ECHEC",L19+(TONTJUIN!I19*2),0) -> 0 | H19: =VLOOKUP($A19,[8]HISTOJUIL21!$A$6:$AU$39,36,0) -> 200000 | I19: =VLOOKUP($A19,[8]HISTOJUIL21!$A$6:$AU$39,39,0) -> 2000 | J19: =IF(H19<>0,VLOOKUP($A19,[8]HISTOJUIL21!$A$6:$AU$39,8,0),"ECHEC") -> ESPECES | K19: =VLOOKUP($A19,[8]HISTOJUIL21!$A$6:$AU$39,41,0) -> 0 | L19: =TONTJUIN!H19+TONTJUIN!I19+TONTJUIN!F19 -> 102000 | M19: =VLOOKUP(A19,[8]HISTOJUIL21!$A$6:$AZ$37,17,0) -> 102000 | N19: =IF(M19<>0,VLOOKUP($A19,[8]HISTOJUIL21!$A$6:$AU$39,8,0),"ECHEC") -> ESPECES | O19: =IF(R19<>0,VLOOKUP($A19,[8]HISTOJUIL21!$A$6:$AU$39,8,0),"ECHEC") -> ECHEC | P19: =VLOOKUP($A19,[8]HISTOJUIL21!$A$6:$AU$39,33,0) -> 0 | Q19: =IF(R19=0,0,($C$37-R19)) -> 0 | R19: =VLOOKUP($A19,[8]HISTOJUIL21!$A$6:$AU$39,30,0) -> 0 | S19: =IF(R19=0,0,(R19-75000)) -> 0
A20: AS201633 | B20: =VLOOKUP(A20,[6]LISTADHERENT!A$5:H$60,3,0) -> PATEGO NJOSSU GUSTAVE | C20: =IF(E20="ECHEC",0,VLOOKUP($A20,[8]HISTOJUIL21!$A$6:$AU$39,13,0)) -> 75000 | E20: =VLOOKUP($A20,[8]HISTOJUIL21!$A$6:$AU$39,8,0) -> BANQUE | F20: =IF(N20="ECHEC",L20+(TONTJUIN!I20*2),0) -> 0 | H20: =VLOOKUP($A20,[8]HISTOJUIL21!$A$6:$AU$39,36,0) -> 0 | I20: =VLOOKUP($A20,[8]HISTOJUIL21!$A$6:$AU$39,39,0) -> 0 | J20: =IF(H20<>0,VLOOKUP($A20,[8]HISTOJUIL21!$A$6:$AU$39,8,0),"ECHEC") -> ECHEC | K20: =VLOOKUP($A20,[8]HISTOJUIL21!$A$6:$AU$39,41,0) -> 0 | L20: =TONTJUIN!H20+TONTJUIN!I20+TONTJUIN!F20 -> 0 | M20: =VLOOKUP(A20,[8]HISTOJUIL21!$A$6:$AZ$37,17,0) -> 0 | N20: =IF(M20<>0,VLOOKUP($A20,[8]HISTOJUIL21!$A$6:$AU$39,8,0),"ECHEC") -> ECHEC | O20: =IF(R20<>0,VLOOKUP($A20,[8]HISTOJUIL21!$A$6:$AU$39,8,0),"ECHEC") -> BANQUE | P20: =VLOOKUP($A20,[8]HISTOJUIL21!$A$6:$AU$39,33,0) -> 0 | Q20: =IF(R20=0,0,($C$37-R20)) -> 1125000 | R20: =VLOOKUP($A20,[8]HISTOJUIL21!$A$6:$AU$39,30,0) -> 75000 | S20: =IF(R20=0,0,(R20-75000)) -> 0
A21: AS201638 | B21: =VLOOKUP(A21,[6]LISTADHERENT!A$5:H$60,3,0) -> SIMO PIERRE | C21: =IF(E21="ECHEC",0,VLOOKUP($A21,[8]HISTOJUIL21!$A$6:$AU$39,13,0)) -> 75000 | E21: =VLOOKUP($A21,[8]HISTOJUIL21!$A$6:$AU$39,8,0) -> BANQUE | F21: =IF(N21="ECHEC",L21+(TONTJUIN!I21*2),0) -> 0 | H21: =VLOOKUP($A21,[8]HISTOJUIL21!$A$6:$AU$39,36,0) -> 0 | I21: =VLOOKUP($A21,[8]HISTOJUIL21!$A$6:$AU$39,39,0) -> 0 | J21: =IF(H21<>0,VLOOKUP($A21,[8]HISTOJUIL21!$A$6:$AU$39,8,0),"ECHEC") -> ECHEC | K21: =VLOOKUP($A21,[8]HISTOJUIL21!$A$6:$AU$39,41,0) -> 0 | L21: =TONTJUIN!H21+TONTJUIN!I21+TONTJUIN!F21 -> 0 | M21: =VLOOKUP(A21,[8]HISTOJUIL21!$A$6:$AZ$37,17,0) -> 0 | N21: =IF(M21<>0,VLOOKUP($A21,[8]HISTOJUIL21!$A$6:$AU$39,8,0),"ECHEC") -> ECHEC | O21: =IF(R21<>0,VLOOKUP($A21,[8]HISTOJUIL21!$A$6:$AU$39,8,0),"ECHEC") -> ECHEC | P21: =VLOOKUP($A21,[8]HISTOJUIL21!$A$6:$AU$39,33,0) -> 0 | Q21: =IF(R21=0,0,($C$37-R21)) -> 0 | R21: =VLOOKUP($A21,[8]HISTOJUIL21!$A$6:$AU$39,30,0) -> 0 | S21: =IF(R21=0,0,(R21-75000)) -> 0
A22: AS201655 | B22: =VLOOKUP(A22,[6]LISTADHERENT!A$5:H$60,3,0) -> TCHEMHOU EMMANUEL | C22: =IF(E22="ECHEC",0,VLOOKUP($A22,[8]HISTOJUIL21!$A$6:$AU$39,13,0)) -> 0 | F22: =IF(N22="ECHEC",L22+(TONTJUIN!I22*2),0) -> 0 | H22: =VLOOKUP($A22,[8]HISTOJUIL21!$A$6:$AU$39,36,0) -> 0 | I22: =VLOOKUP($A22,[8]HISTOJUIL21!$A$6:$AU$39,39,0) -> 0 | J22: =IF(H22<>0,VLOOKUP($A22,[8]HISTOJUIL21!$A$6:$AU$39,8,0),"ECHEC") -> ECHEC | K22: =VLOOKUP($A22,[8]HISTOJUIL21!$A$6:$AU$39,41,0) -> 0 | L22: =TONTJUIN!H22+TONTJUIN!I22+TONTJUIN!F22 -> 0 | M22: =VLOOKUP(A22,[8]HISTOJUIL21!$A$6:$AZ$37,17,0) -> 0 | N22: =IF(M22<>0,VLOOKUP($A22,[8]HISTOJUIL21!$A$6:$AU$39,8,0),"ECHEC") -> ECHEC | O22: =IF(R22<>0,VLOOKUP($A22,[8]HISTOJUIL21!$A$6:$AU$39,8,0),"ECHEC") -> ECHEC | P22: =VLOOKUP($A22,[8]HISTOJUIL21!$A$6:$AU$39,33,0) -> 0 | Q22: =IF(R22=0,0,($C$37-R22)) -> 0 | R22: =VLOOKUP($A22,[8]HISTOJUIL21!$A$6:$AU$39,30,0) -> 0 | S22: =IF(R22=0,0,(R22-75000)) -> 0
A23: AS201647 | B23: =VLOOKUP(A23,[6]LISTADHERENT!A$5:H$60,3,0) -> YOUMBI EMMANUEL | C23: =IF(E23="ECHEC",0,VLOOKUP($A23,[8]HISTOJUIL21!$A$6:$AU$39,13,0)) -> 150000 | E23: =VLOOKUP($A23,[8]HISTOJUIL21!$A$6:$AU$39,8,0) -> BANQUE | F23: =IF(N23="ECHEC",L23+(TONTJUIN!I23*2),0) -> 0 | H23: =VLOOKUP($A23,[8]HISTOJUIL21!$A$6:$AU$39,36,0) -> 0 | I23: =VLOOKUP($A23,[8]HISTOJUIL21!$A$6:$AU$39,39,0) -> 0 | J23: =IF(H23<>0,VLOOKUP($A23,[8]HISTOJUIL21!$A$6:$AU$39,8,0),"ECHEC") -> ECHEC | K23: =VLOOKUP($A23,[8]HISTOJUIL21!$A$6:$AU$39,41,0) -> 0 | L23: =TONTJUIN!H23+TONTJUIN!I23+TONTJUIN!F23 -> 0 | N23: =IF(M23<>0,VLOOKUP($A23,[8]HISTOJUIL21!$A$6:$AU$39,8,0),"ECHEC") -> ECHEC | O23: =IF(R23<>0,VLOOKUP($A23,[8]HISTOJUIL21!$A$6:$AU$39,8,0),"ECHEC") -> ECHEC | P23: =VLOOKUP($A23,[8]HISTOJUIL21!$A$6:$AU$39,33,0) -> 0 | Q23: =IF(R23=0,0,($C$37-R23)) -> 0 | R23: =VLOOKUP($A23,[8]HISTOJUIL21!$A$6:$AU$39,30,0) -> 0 | S23: =IF(R23=0,0,(R23-75000)) -> 0
A24: AS201647 | B24: =VLOOKUP(A24,[6]LISTADHERENT!A$5:H$60,3,0) -> YOUMBI EMMANUEL | F24: =IF(N24="ECHEC",L24+(TONTJUIN!I24*2),0) -> 0 | S24: =IF(R24=0,0,(R24-75000)) -> 0
S26: =SUM(S6:S24) -> 0
B27: TOTAL | C27: =SUM(C6:C26) -> 1275000 | D27: =SUM(D6:D26) -> 0 | E27: =SUM(E6:E26) -> 0 | F27: =SUM(F6:F26) -> 0 | G27: =SUM(G6:G26) -> 0 | H27: =SUM(H6:H26) -> 849500 | I27: =SUM(I6:I26) -> 9000 | J27: =SUM(J6:J26) -> 0 | ... R27: =SUM(R6:R26) -> 75000
C29: TONTINE | D29: REMBOURSEMENT PETIT LOT | E29: VENTE PETIT LOT | F29: VENTE LOT PRINCIPAL | G29: SOLDE EN CAISSE | K29: TONTINE + REMB + INTERET VENTE | L29: =C34+D34+R27+TONTJUIN!M34 -> 2050500
K30: LOT PRINCIPAL | L30: =C3*COUNTIF(Q6:Q26,">0") -> 1200000 | M30: =D3 -> 1
B31: ESPECES | C31: =SUMIFS(C6:C25,E6:E25,"ESPECES") -> 75000 | D31: =SUMIFS(L2:L21,N2:N21,"ESPECES")+SUMIFS(F2:F21,G2:G21,"ESPECES") -> 102000 | E31: =SUMIFS(H6:H25,J6:J25,"ESPECES") -> 200000 | F31: =SUMIFS(Q6:Q25,O6:O25,"ESPECES") -> 0 | G31: =C31+D31-E31-F31 -> -23000
B32: BANQUE | C32: =SUMIFS(C6:C25,E6:E25,"BANQUE") -> 1200000 | D32: =SUMIFS(M3:M22,N3:N22,"BANQUE")+SUMIFS(F3:F22,G3:G22,"BANQUE") -> 598500 | E32: =SUMIFS(H6:H25,J6:J25,"BANQUE") -> 649500 | F32: =SUMIFS(Q6:Q25,O6:O25,"BANQUE") -> 1125000 | G32: =C32+D32-E32-F32 -> 24000 | K32: PETIT LOT | L32: =L29-L30 -> 850500
B34: TOTAL | C34: =C31+C32 -> 1275000 | D34: =D31+D32 -> 700500 | E34: =E31+E32 -> 849500 | F34: =F31+F32 -> 1125000 | G34: =G31+G32 -> 1000 | K34: RELIQUAT | L34: =L32-H27 -> 1000 | M34: =L34 -> 1000 | N34: CUMUL
K36: ECHEC TONTINE | L36: =COUNTIFS(E6:E25,"ECHEC")*75000 -> 0 | M36: =L36+TONTJUIN!M36 -> 0 | N36: CUMUL
B37: MONTANT TONTINE | C37: 1200000 | K37: ECHEC REMBOURSEMENT | L37: =SUMIFS(F3:F22,G3:G22,"ECHEC") -> 0 | M37: =L37+TONTJUIN!M37 -> 0 | N37: CUMUL

Sheet TONTAOUT21
A1: ASSOCIATION | B1: ASELBY
A2: ANNEE | B2: 2021 | C2: TONIINE | D2: NBRE PART
A3: TAUX TONTINE | B3: 75000 | C3: =B3*16 -> 1200000 | D3: =ROUNDDOWN(L29/C3,0) -> 1
C4: 44429
A5: MATRICULE | B5: NOM ET PRENOM | C5: MONTANT TONTINE | D5: PENALITE | E5: MODE VERSEMENT TONTINE | F5: REPORT ECHEC PETIT LOT | G5: MODE VERSEMENT VENTE PETIT LOT | H5: VENTE PETIT LOT | I5: INTERET PETIT LOT | J5: MODE VERSEMENT VENTE PETIT LOT | K5: NUMERO CHEQUE | L5: MONTANT A REMBOURSER | M5: MONTANT REMBOURSE | N5: MODE VERSEMENT REMBOURSEMENT | O5: MODE VERSEMENT TONTINE PRINCIPAL | P5: NUMERO CHEQUE | Q5: MONTANT TONTINE LOT PRINCIPAL | R5: INTERET LOT PRINCIPAL | S5: INTERET DU
A6: AS201602 | B6: =VLOOKUP(A6,[6]LISTADHERENT!A$5:H$60,3,0) -> BOUTCHOUANG WILLIAM | C6: =IF(E6="ECHEC",0,VLOOKUP($A6,[8]HISTOAOUT21!$A$6:$AU$39,13,0)) -> 75000 | E6: =VLOOKUP($A6,[8]HISTOAOUT21!$A$6:$AU$39,8,0) -> BANQUE | F6: =IF(N6="ECHEC",L6+(TONTJUIL21!I6*2),0) -> 0 | H6: =VLOOKUP($A6,[8]HISTOAOUT21!$A$6:$AU$39,36,0) -> 0 | I6: =VLOOKUP($A6,[8]HISTOAOUT21!$A$6:$AU$39,39,0) -> 0 | J6: =IF(H6<>0,VLOOKUP($A6,[8]HISTOAOUT21!$A$6:$AU$39,8,0),"ECHEC") -> ECHEC | K6: =VLOOKUP($A6,[8]HISTOAOUT21!$A$6:$AU$39,41,0) -> 0 | L6: =TONTJUIL21!H6+TONTJUIL21!I6+TONTJUIL21!F6 -> 0 | M6: =VLOOKUP(A6,[8]HISTOAOUT21!$A$6:$AZ$37,17,0) -> 0 | N6: =IF(L6<>0,VLOOKUP($A6,[8]HISTOAOUT21!$A$6:$AU$39,8,0),"ECHEC") -> ECHEC | O6: =IF(R6<>0,VLOOKUP($A6,[8]HISTOAOUT21!$A$6:$AU$39,8,0),"ECHEC") -> ECHEC | P6: =VLOOKUP($A6,[8]HISTOAOUT21!$A$6:$AU$39,33,0) -> 0 | Q6: =IF(R6=0,0,($C$37-R6)) -> 0 | R6: =VLOOKUP($A6,[8]HISTOAOUT21!$A$6:$AU$39,30,0) -> 0 | S6: =IF(R6=0,0,(R6-75000)) -> 0
A7: AS201603 | B7: =VLOOKUP(A7,[6]LISTADHERENT!A$5:H$60,3,0) -> CHINGUE FABRICE | F7: =IF(N7="ECHEC",L7+(TONTJUIL21!I7*2),0) -> 0 | L7: =TONTJUIL21!H7+TONTJUIL21!I7+TONTJUIL21!F7 -> 0 | S7: =IF(R7=0,0,(R7-75000)) -> 0
A8: AS201604 | B8: =VLOOKUP(A8,[6]LISTADHERENT!A$5:H$60,3,0) -> DJOMO JEAN PAUL | C8: =IF(E8="ECHEC",0,VLOOKUP($A8,[8]HISTOAOUT21!$A$6:$AU$39,13,0)) -> 75000 | E8: =VLOOKUP($A8,[8]HISTOAOUT21!$A$6:$AU$39,8,0) -> BANQUE | F8: =IF(N8="ECHEC",L8+(TONTJUIL21!I8*2),0) -> 0 | H8: =VLOOKUP($A8,[8]HISTOAOUT21!$A$6:$AU$39,36,0) -> 0 | I8: =VLOOKUP($A8,[8]HISTOAOUT21!$A$6:$AU$39,39,0) -> 0 | J8: =IF(H8<>0,VLOOKUP($A8,[8]HISTOAOUT21!$A$6:$AU$39,8,0),"ECHEC") -> ECHEC | K8: =VLOOKUP($A8,[8]HISTOAOUT21!$A$6:$AU$39,41,0) -> 0 | L8: =TONTJUIL21!H8+TONTJUIL21!I8+TONTJUIL21!F8 -> 202000 | M8: =VLOOKUP(A8,[8]HISTOAOUT21!$A$6:$AZ$37,17,0) -> 202000 | N8: =IF(M8<>0,VLOOKUP($A8,[8]HISTOAOUT21!$A$6:$AU$39,8,0),"ECHEC") -> BANQUE | O8: =IF(R8<>0,VLOOKUP($A8,[8]HISTOAOUT21!$A$6:$AU$39,8,0),"ECHEC") -> ECHEC | P8: =VLOOKUP($A8,[8]HISTOAOUT21!$A$6:$AU$39,33,0) -> 0 | Q8: =IF(R8=0,0,($C$37-R8)) -> 0 | R8: =VLOOKUP($A8,[8]HISTOAOUT21!$A$6:$AU$39,30,0) -> 0 | S8: =IF(R8=0,0,(R8-75000)) -> 0
A9: AS201605 | B9: =VLOOKUP(A9,[6]LISTADHERENT!A$5:H$60,3,0) -> DJOUKWE NANGUEN GUY BLAISE | C9: =IF(E9="ECHEC",0,VLOOKUP($A9,[8]HISTOAOUT21!$A$6:$AU$39,13,0)) -> 75000 | E9: =VLOOKUP($A9,[8]HISTOAOUT21!$A$6:$AU$39,8,0) -> BANQUE | F9: =IF(N9="ECHEC",L9+(TONTJUIL21!I9*2),0) -> 0 | H9: =VLOOKUP($A9,[8]HISTOAOUT21!$A$6:$AU$39,36,0) -> 0 | I9: =VLOOKUP($A9,[8]HISTOAOUT21!$A$6:$AU$39,39,0) -> 0 | J9: =IF(H9<>0,VLOOKUP($A9,[8]HISTOAOUT21!$A$6:$AU$39,8,0),"ECHEC") -> ECHEC | K9: =VLOOKUP($A9,[8]HISTOAOUT21!$A$6:$AU$39,41,0) -> 0 | L9: =TONTJUIL21!H9+TONTJUIL21!I9+TONTJUIL21!F9 -> 151500 | M9: =VLOOKUP(A9,[8]HISTOAOUT21!$A$6:$AZ$37,17,0) -> 151500 | N9: =IF(M9<>0,VLOOKUP($A9,[8]HISTOAOUT21!$A$6:$AU$39,8,0),"ECHEC") -> BANQUE | O9: =IF(R9<>0,VLOOKUP($A9,[8]HISTOAOUT21!$A$6:$AU$39,8,0),"ECHEC") -> ECHEC | P9: =VLOOKUP($A9,[8]HISTOAOUT21!$A$6:$AU$39,33,0) -> 0 | Q9: =IF(R9=0,0,($C$37-R9)) -> 0 | R9: =VLOOKUP($A9,[8]HISTOAOUT21!$A$6:$AU$39,30,0) -> 0 | S9: =IF(R9=0,0,(R9-75000)) -> 0
A10: AS201613 | B10: =VLOOKUP(A10,[6]LISTADHERENT!A$5:H$60,3,0) -> HOTCHO BENJAMIN | C10: =IF(E10="ECHEC",0,VLOOKUP($A10,[8]HISTOAOUT21!$A$6:$AU$39,13,0)) -> 75000 | E10: =VLOOKUP($A10,[8]HISTOAOUT21!$A$6:$AU$39,8,0) -> BANQUE | F10: =IF(N10="ECHEC",L10+(TONTJUIL21!I10*2),0) -> 0 | H10: =VLOOKUP($A10,[8]HISTOAOUT21!$A$6:$AU$39,36,0) -> 0 | I10: =VLOOKUP($A10,[8]HISTOAOUT21!$A$6:$AU$39,39,0) -> 0 | J10: =IF(H10<>0,VLOOKUP($A10,[8]HISTOAOUT21!$A$6:$AU$39,8,0),"ECHEC") -> ECHEC | K10: =VLOOKUP($A10,[8]HISTOAOUT21!$A$6:$AU$39,41,0) -> 0 | L10: =TONTJUIL21!H10+TONTJUIL21!I10+TONTJUIL21!F10 -> 0 | M10: =VLOOKUP(A10,[8]HISTOAOUT21!$A$6:$AZ$37,17,0) -> 0 | N10: =IF(M10<>0,VLOOKUP($A10,[8]HISTOAOUT21!$A$6:$AU$39,8,0),"ECHEC") -> ECHEC | O10: =IF(R10<>0,VLOOKUP($A10,[8]HISTOAOUT21!$A$6:$AU$39,8,0),"ECHEC") -> ECHEC | P10: =VLOOKUP($A10,[8]HISTOAOUT21!$A$6:$AU$39,33,0) -> 0 | Q10: =IF(R10=0,0,($C$37-R10)) -> 0 | R10: =VLOOKUP($A10,[8]HISTOAOUT21!$A$6:$AU$39,30,0) -> 0 | S10: =IF(R10=0,0,(R10-75000)) -> 0
A11: AS201611 | B11: =VLOOKUP(A11,[6]LISTADHERENT!A$5:H$60,3,0) -> HENGUE PAUL OMER | C11: =IF(E11="ECHEC",0,VLOOKUP($A11,[8]HISTOAOUT21!$A$6:$AU$39,13,0)) -> 75000 | E11: =VLOOKUP($A11,[8]HISTOAOUT21!$A$6:$AU$39,8,0) -> BANQUE | F11: =IF(N11="ECHEC",L11+(TONTJUIL21!I11*2),0) -> 0 | H11: =VLOOKUP($A11,[8]HISTOAOUT21!$A$6:$AU$39,36,0) -> 0 | I11: =VLOOKUP($A11,[8]HISTOAOUT21!$A$6:$AU$39,39,0) -> 0 | J11: =IF(H11<>0,VLOOKUP($A11,[8]HISTOAOUT21!$A$6:$AU$39,8,0),"ECHEC") -> ECHEC | K11: =VLOOKUP($A11,[8]HISTOAOUT21!$A$6:$AU$39,41,0) -> 0 | L11: =TONTJUIL21!H11+TONTJUIL21!I11+TONTJUIL21!F11 -> 0 | M11: =VLOOKUP(A11,[8]HISTOAOUT21!$A$6:$AZ$37,17,0) -> 0 | N11: =IF(M11<>0,VLOOKUP($A11,[8]HISTOAOUT21!$A$6:$AU$39,8,0),"ECHEC") -> ECHEC | O11: =IF(R11<>0,VLOOKUP($A11,[8]HISTOAOUT21!$A$6:$AU$39,8,0),"ECHEC") -> BANQUE | P11: =VLOOKUP($A11,[8]HISTOAOUT21!$A$6:$AU$39,33,0) -> 0 | Q11: =IF(R11=0,0,($C$37-R11)) -> 1125000 | R11: =VLOOKUP($A11,[8]HISTOAOUT21!$A$6:$AU$39,30,0) -> 75000 | S11: =IF(R11=0,0,(R11-75000)) -> 0
A12: AS201619 | B12: =VLOOKUP(A12,[6]LISTADHERENT!A$5:H$60,3,0) -> KOUATCHO MESSACK | C12: =IF(E12="ECHEC",0,VLOOKUP($A12,[8]HISTOAOUT21!$A$6:$AU$39,13,0)) -> 75000 | E12: =VLOOKUP($A12,[8]HISTOAOUT21!$A$6:$AU$39,8,0) -> BANQUE | F12: =IF(N12="ECHEC",L12+(TONTJUIL21!I12*2),0) -> 0 | H12: =VLOOKUP($A12,[8]HISTOAOUT21!$A$6:$AU$39,36,0) -> 0 | I12: =VLOOKUP($A12,[8]HISTOAOUT21!$A$6:$AU$39,39,0) -> 0 | J12: =IF(H12<>0,VLOOKUP($A12,[8]HISTOAOUT21!$A$6:$AU$39,8,0),"ECHEC") -> ECHEC | K12: =VLOOKUP($A12,[8]HISTOAOUT21!$A$6:$AU$39,41,0) -> 0 | L12: =TONTJUIL21!H12+TONTJUIL21!I12+TONTJUIL21!F12 -> 202000 | M12: =VLOOKUP(A12,[8]HISTOAOUT21!$A$6:$AZ$37,17,0) -> 202000 | N12: =IF(M12<>0,VLOOKUP($A12,[8]HISTOAOUT21!$A$6:$AU$39,8,0),"ECHEC") -> BANQUE | O12: =IF(R12<>0,VLOOKUP($A12,[8]HISTOAOUT21!$A$6:$AU$39,8,0),"ECHEC") -> ECHEC | P12: =VLOOKUP($A12,[8]HISTOAOUT21!$A$6:$AU$39,33,0) -> 0 | Q12: =IF(R12=0,0,($C$37-R12)) -> 0 | R12: =VLOOKUP($A12,[8]HISTOAOUT21!$A$6:$AU$39,30,0) -> 0 | S12: =IF(R12=0,0,(R12-75000)) -> 0
A13: AS201621 | B13: =VLOOKUP(A13,[6]LISTADHERENT!A$5:H$60,3,0) -> NANKAM APPOLINAIRE | C13: =IF(E13="ECHEC",0,VLOOKUP($A13,[8]HISTOAOUT21!$A$6:$AU$39,13,0)) -> 75000 | E13: =VLOOKUP($A13,[8]HISTOAOUT21!$A$6:$AU$39,8,0) -> BANQUE | F13: =IF(N13="ECHEC",L13+(TONTJUIL21!I13*2),0) -> 0 | H13: =VLOOKUP($A13,[8]HISTOAOUT21!$A$6:$AU$39,36,0) -> 0 | I13: =VLOOKUP($A13,[8]HISTOAOUT21!$A$6:$AU$39,39,0) -> 0 | J13: =IF(H13<>0,VLOOKUP($A13,[8]HISTOAOUT21!$A$6:$AU$39,8,0),"ECHEC") -> ECHEC | K13: =VLOOKUP($A13,[8]HISTOAOUT21!$A$6:$AU$39,41,0) -> 0 | L13: =TONTJUIL21!H13+TONTJUIL21!I13+TONTJUIL21!F13 -> 0 | M13: =VLOOKUP(A13,[8]HISTOAOUT21!$A$6:$AZ$37,17,0) -> 0 | N13: =IF(M13<>0,VLOOKUP($A13,[8]HISTOAOUT21!$A$6:$AU$39,8,0),"ECHEC") -> ECHEC | O13: =IF(R13<>0,VLOOKUP($A13,[8]HISTOAOUT21!$A$6:$AU$39,8,0),"ECHEC") -> BANQUE | P13: =VLOOKUP($A13,[8]HISTOAOUT21!$A$6:$AU$39,33,0) -> 0 | Q13: =IF(R13=0,0,($C$37-R13)) -> 1125000 | R13: =VLOOKUP($A13,[8]HISTOAOUT21!$A$6:$AU$39,30,0) -> 75000 | S13: =IF(R13=0,0,(R13-75000)) -> 0
A14: AS201649 | B14: =VLOOKUP(A14,[6]LISTADHERENT!A$5:H$60,3,0) -> MBOGNING TUGMA GUY | C14: =IF(E14="ECHEC",0,VLOOKUP($A14,[8]HISTOAOUT21!$A$6:$AU$39,13,0)) -> 225000 | E14: =VLOOKUP($A14,[8]HISTOAOUT21!$A$6:$AU$39,8,0) -> BANQUE | F14: =IF(N14="ECHEC",L14+(TONTJUIL21!I14*2),0) -> 0 | H14: =VLOOKUP($A14,[8]HISTOAOUT21!$A$6:$AU$39,36,0) -> 0 | I14: =VLOOKUP($A14,[8]HISTOAOUT21!$A$6:$AU$39,39,0) -> 0 | J14: =IF(H14<>0,VLOOKUP($A14,[8]HISTOAOUT21!$A$6:$AU$39,8,0),"ECHEC") -> ECHEC | K14: =VLOOKUP($A14,[8]HISTOAOUT21!$A$6:$AU$39,41,0) -> 0 | L14: =TONTJUIL21!H14+TONTJUIL21!I14+TONTJUIL21!F14 -> 0 | M14: =VLOOKUP(A14,[8]HISTOAOUT21!$A$6:$AZ$37,17,0) -> 0 | N14: =IF(M14<>0,VLOOKUP($A14,[8]HISTOAOUT21!$A$6:$AU$39,8,0),"ECHEC") -> ECHEC | O14: =IF(R14<>0,VLOOKUP($A14,[8]HISTOAOUT21!$A$6:$AU$39,8,0),"ECHEC") -> ECHEC | P14: =VLOOKUP($A14,[8]HISTOAOUT21!$A$6:$AU$39,33,0) -> 0 | Q14: =IF(R14=0,0,($C$37-R14)) -> 0 | R14: =VLOOKUP($A14,[8]HISTOAOUT21!$A$6:$AU$39,30,0) -> 0 | S14: =IF(R14=0,0,(R14-75000)) -> 0
A15: AS201649 | B15: =VLOOKUP(A15,[6]LISTADHERENT!A$5:H$60,3,0) -> MBOGNING TUGMA GUY | F15: =IF(N15="ECHEC",L15+(TONTJUIL21!I15*2),0) -> 0 | L15: =TONTJUIL21!H15+TONTJUIL21!I15+TONTJUIL21!F15 -> 0 | P15: =VLOOKUP($A15,[8]HISTOAOUT21!$A$6:$AU$39,33,0) -> 0 | R15: =VLOOKUP($A15,[8]HISTOAOUT21!$A$6:$AU$39,30,0) -> 0 | S15: =IF(R15=0,0,(R15-75000)) -> 0
A16: AS201649 | B16: =VLOOKUP(A16,[6]LISTADHERENT!A$5:H$60,3,0) -> MBOGNING TUGMA GUY | F16: =IF(N16="ECHEC",L16+(TONTJUIL21!I16*2),0) -> 0 | L16: =TONTJUIL21!H16+TONTJUIL21!I16+TONTJUIL21!F16 -> 0 | S16: =IF(R16=0,0,(R16-75000)) -> 0
A17: AS201626 | B17: =VLOOKUP(A17,[6]LISTADHERENT!A$5:H$60,3,0) -> NGUIEMEGNI MATHIEU BLAISE | C17: =IF(E17="ECHEC",0,VLOOKUP($A17,[8]HISTOAOUT21!$A$6:$AU$39,13,0)) -> 150000 | E17: =VLOOKUP($A17,[8]HISTOAOUT21!$A$6:$AU$39,8,0) -> BANQUE | F17: =IF(N17="ECHEC",L17+(TONTJUIL21!I17*2),0) -> 0 | H17: =VLOOKUP($A17,[8]HISTOAOUT21!$A$6:$AU$39,36,0) -> 0 | I17: =VLOOKUP($A17,[8]HISTOAOUT21!$A$6:$AU$39,39,0) -> 0 | J17: =IF(H17<>0,VLOOKUP($A17,[8]HISTOAOUT21!$A$6:$AU$39,8,0),"ECHEC") -> ECHEC | K17: =VLOOKUP($A17,[8]HISTOAOUT21!$A$6:$AU$39,41,0) -> 0 | L17: =TONTJUIL21!H17+TONTJUIL21!I17+TONTJUIL21!F17 -> 101000 | M17: =VLOOKUP(A17,[8]HISTOAOUT21!$A$6:$AZ$37,17,0) -> 101000 | N17: =IF(M17<>0,VLOOKUP($A17,[8]HISTOAOUT21!$A$6:$AU$39,8,0),"ECHEC") -> BANQUE | O17: =IF(R17<>0,VLOOKUP($A17,[8]HISTOAOUT21!$A$6:$AU$39,8,0),"ECHEC") -> ECHEC | P17: =VLOOKUP($A17,[8]HISTOAOUT21!$A$6:$AU$39,33,0) -> 0 | Q17: =IF(R17=0,0,($C$37-R17)) -> 0 | R17: =VLOOKUP($A17,[8]HISTOAOUT21!$A$6:$AU$39,30,0) -> 0 | S17: =IF(R17=0,0,(R17-75000)) -> 0
A18: AS201626 | B18: =VLOOKUP(A18,[6]LISTADHERENT!A$5:H$60,3,0) -> NGUIEMEGNI MATHIEU BLAISE | F18: =IF(N18="ECHEC",L18+(TONTJUIL21!I18*2),0) -> 0 | L18: =TONTJUIL21!H18+TONTJUIL21!I18+TONTJUIL21!F18 -> 0 | N18: =IF(M18<>0,VLOOKUP($A18,[8]HISTOAOUT21!$A$6:$AU$39,8,0),"ECHEC") -> ECHEC | O18: =IF(R18<>0,VLOOKUP($A18,[8]HISTOAOUT21!$A$6:$AU$39,8,0),"ECHEC") -> ECHEC | S18: =IF(R18=0,0,(R18-75000)) -> 0
A19: AS201628 | B19: =VLOOKUP(A19,[6]LISTADHERENT!A$5:H$60,3,0) -> NKAMGANG JUSTIN DEJOLIE | C19: =IF(E19="ECHEC",0,VLOOKUP($A19,[8]HISTOAOUT21!$A$6:$AU$39,13,0)) -> 75000 | E19: =VLOOKUP($A19,[8]HISTOAOUT21!$A$6:$AU$39,8,0) -> BANQUE | F19: =IF(N19="ECHEC",L19+(TONTJUIL21!I19*2),0) -> 0 | H19: =VLOOKUP($A19,[8]HISTOAOUT21!$A$6:$AU$39,36,0) -> 0 | I19: =VLOOKUP($A19,[8]HISTOAOUT21!$A$6:$AU$39,39,0) -> 0 | J19: =IF(H19<>0,VLOOKUP($A19,[8]HISTOAOUT21!$A$6:$AU$39,8,0),"ECHEC") -> ECHEC | K19: =VLOOKUP($A19,[8]HISTOAOUT21!$A$6:$AU$39,41,0) -> 0 | L19: =TONTJUIL21!H19+TONTJUIL21!I19+TONTJUIL21!F19 -> 202000 | M19: =VLOOKUP(A19,[8]HISTOAOUT21!$A$6:$AZ$37,17,0) -> 202000 | N19: =IF(M19<>0,VLOOKUP($A19,[8]HISTOAOUT21!$A$6:$AU$39,8,0),"ECHEC") -> BANQUE | O19: =IF(R19<>0,VLOOKUP($A19,[8]HISTOAOUT21!$A$6:$AU$39,8,0),"ECHEC") -> ECHEC | P19: =VLOOKUP($A19,[8]HISTOAOUT21!$A$6:$AU$39,33,0) -> 0 | Q19: =IF(R19=0,0,($C$37-R19)) -> 0 | R19: =VLOOKUP($A19,[8]HISTOAOUT21!$A$6:$AU$39,30,0) -> 0 | S19: =IF(R19=0,0,(R19-75000)) -> 0
A20: AS201633 | B20: =VLOOKUP(A20,[6]LISTADHERENT!A$5:H$60,3,0) -> PATEGO NJOSSU GUSTAVE | C20: =IF(E20="ECHEC",0,VLOOKUP($A20,[8]HISTOAOUT21!$A$6:$AU$39,13,0)) -> 75000 | E20: =VLOOKUP($A20,[8]HISTOAOUT21!$A$6:$AU$39,8,0) -> BANQUE | F20: =IF(N20="ECHEC",L20+(TONTJUIL21!I20*2),0) -> 0 | H20: =VLOOKUP($A20,[8]HISTOAOUT21!$A$6:$AU$39,36,0) -> 0 | I20: =VLOOKUP($A20,[8]HISTOAOUT21!$A$6:$AU$39,39,0) -> 0 | J20: =IF(H20<>0,VLOOKUP($A20,[8]HISTOAOUT21!$A$6:$AU$39,8,0),"ECHEC") -> ECHEC | K20: =VLOOKUP($A20,[8]HISTOAOUT21!$A$6:$AU$39,41,0) -> 0 | L20: =TONTJUIL21!H20+TONTJUIL21!I20+TONTJUIL21!F20 -> 0 | M20: =VLOOKUP(A20,[8]HISTOAOUT21!$A$6:$AZ$37,17,0) -> 0 | N20: =IF(M20<>0,VLOOKUP($A20,[8]HISTOAOUT21!$A$6:$AU$39,8,0),"ECHEC") -> ECHEC | O20: =IF(R20<>0,VLOOKUP($A20,[8]HISTOAOUT21!$A$6:$AU$39,8,0),"ECHEC") -> ECHEC | P20: =VLOOKUP($A20,[8]HISTOAOUT21!$A$6:$AU$39,33,0) -> 0 | Q20: =IF(R20=0,0,($C$37-R20)) -> 0 | R20: =VLOOKUP($A20,[8]HISTOAOUT21!$A$6:$AU$39,30,0) -> 0 | S20: =IF(R20=0,0,(R20-75000)) -> 0
A21: AS201638 | B21: =VLOOKUP(A21,[6]LISTADHERENT!A$5:H$60,3,0) -> SIMO PIERRE | C21: =IF(E21="ECHEC",0,VLOOKUP($A21,[8]HISTOAOUT21!$A$6:$AU$39,13,0)) -> 75000 | E21: =VLOOKUP($A21,[8]HISTOAOUT21!$A$6:$AU$39,8,0) -> BANQUE | F21: =IF(N21="ECHEC",L21+(TONTJUIL21!I21*2),0) -> 0 | H21: =VLOOKUP($A21,[8]HISTOAOUT21!$A$6:$AU$39,36,0) -> 0 | I21: =VLOOKUP($A21,[8]HISTOAOUT21!$A$6:$AU$39,39,0) -> 0 | J21: =IF(H21<>0,VLOOKUP($A21,[8]HISTOAOUT21!$A$6:$AU$39,8,0),"ECHEC") -> ECHEC | K21: =VLOOKUP($A21,[8]HISTOAOUT21!$A$6:$AU$39,41,0) -> 0 | L21: =TONTJUIL21!H21+TONTJUIL21!I21+TONTJUIL21!F21 -> 0 | M21: =VLOOKUP(A21,[8]HISTOAOUT21!$A$6:$AZ$37,17,0) -> 0 | N21: =IF(M21<>0,VLOOKUP($A21,[8]HISTOAOUT21!$A$6:$AU$39,8,0),"ECHEC") -> ECHEC | O21: =IF(R21<>0,VLOOKUP($A21,[8]HISTOAOUT21!$A$6:$AU$39,8,0),"ECHEC") -> ECHEC | P21: =VLOOKUP($A21,[8]HISTOAOUT21!$A$6:$AU$39,33,0) -> 0 | Q21: =IF(R21=0,0,($C$37-R21)) -> 0 | R21: =VLOOKUP($A21,[8]HISTOAOUT21!$A$6:$AU$39,30,0) -> 0 | S21: =IF(R21=0,0,(R21-75000)) -> 0
A22: AS201655 | B22: =VLOOKUP(A22,[6]LISTADHERENT!A$5:H$60,3,0) -> TCHEMHOU EMMANUEL | C22: =IF(E22="ECHEC",0,VLOOKUP($A22,[8]HISTOAOUT21!$A$6:$AU$39,13,0)) -> 0 | F22: =IF(N22="ECHEC",L22+(TONTJUIL21!I22*2),0) -> 0 | H22: =VLOOKUP($A22,[8]HISTOAOUT21!$A$6:$AU$39,36,0) -> 0 | I22: =VLOOKUP($A22,[8]HISTOAOUT21!$A$6:$AU$39,39,0) -> 0 | J22: =IF(H22<>0,VLOOKUP($A22,[8]HISTOAOUT21!$A$6:$AU$39,8,0),"ECHEC") -> ECHEC | K22: =VLOOKUP($A22,[8]HISTOAOUT21!$A$6:$AU$39,41,0) -> 0 | L22: =TONTJUIL21!H22+TONTJUIL21!I22+TONTJUIL21!F22 -> 0 | M22: =VLOOKUP(A22,[8]HISTOAOUT21!$A$6:$AZ$37,17,0) -> 0 | N22: =IF(M22<>0,VLOOKUP($A22,[8]HISTOAOUT21!$A$6:$AU$39,8,0),"ECHEC") -> ECHEC | O22: =IF(R22<>0,VLOOKUP($A22,[8]HISTOAOUT21!$A$6:$AU$39,8,0),"ECHEC") -> ECHEC | P22: =VLOOKUP($A22,[8]HISTOAOUT21!$A$6:$AU$39,33,0) -> 0 | Q22: =IF(R22=0,0,($C$37-R22)) -> 0 | R22: =VLOOKUP($A22,[8]HISTOAOUT21!$A$6:$AU$39,30,0) -> 0 | S22: =IF(R22=0,0,(R22-75000)) -> 0
A23: AS201647 | B23: =VLOOKUP(A23,[6]LISTADHERENT!A$5:H$60,3,0) -> YOUMBI EMMANUEL | C23: =IF(E23="ECHEC",0,VLOOKUP($A23,[8]HISTOAOUT21!$A$6:$AU$39,13,0)) -> 150000 | E23: =VLOOKUP($A23,[8]HISTOAOUT21!$A$6:$AU$39,8,0) -> BANQUE | F23: =IF(N23="ECHEC",L23+(TONTJUIL21!I23*2),0) -> 0 | H23: =VLOOKUP($A23,[8]HISTOAOUT21!$A$6:$AU$39,36,0) -> 0 | I23: =VLOOKUP($A23,[8]HISTOAOUT21!$A$6:$AU$39,39,0) -> 0 | J23: =IF(H23<>0,VLOOKUP($A23,[8]HISTOAOUT21!$A$6:$AU$39,8,0),"ECHEC") -> ECHEC | K23: =VLOOKUP($A23,[8]HISTOAOUT21!$A$6:$AU$39,41,0) -> 0 | L23: =TONTJUIL21!H23+TONTJUIL21!I23+TONTJUIL21!F23 -> 0 | N23: =IF(M23<>0,VLOOKUP($A23,[8]HISTOAOUT21!$A$6:$AU$39,8,0),"ECHEC") -> ECHEC | O23: =IF(R23<>0,VLOOKUP($A23,[8]HISTOAOUT21!$A$6:$AU$39,8,0),"ECHEC") -> ECHEC | P23: =VLOOKUP($A23,[8]HISTOAOUT21!$A$6:$AU$39,33,0) -> 0 | Q23: =IF(R23=0,0,($C$37-R23)) -> 0 | R23: =VLOOKUP($A23,[8]HISTOAOUT21!$A$6:$AU$39,30,0) -> 0 | S23: =IF(R23=0,0,(R23-75000)) -> 0
A24: AS201647 | B24: =VLOOKUP(A24,[6]LISTADHERENT!A$5:H$60,3,0) -> YOUMBI EMMANUEL | F24: =IF(N24="ECHEC",L24+(TONTJUIL21!I24*2),0) -> 0 | S24: =IF(R24=0,0,(R24-75000)) -> 0
S26: =SUM(S6:S24) -> 0
B27: TOTAL | C27: =SUM(C6:C26) -> 1275000 | D27: =SUM(D6:D26) -> 0 | E27: =SUM(E6:E26) -> 0 | F27: =SUM(F6:F26) -> 0 | G27: =SUM(G6:G26) -> 0 | H27: =SUM(H6:H26) -> 0 | I27: =SUM(I6:I26) -> 0 | J27: =SUM(J6:J26) -> 0 | ... R27: =SUM(R6:R26) -> 150000
C29: TONTINE | D29: REMBOURSEMENT PETIT LOT | E29: VENTE PETIT LOT | F29: VENTE LOT PRINCIPAL | G29: SOLDE EN CAISSE | K29: TONTINE + REMB + INTERET VENTE | L29: =C34+D34+R27+TONTJUIL21!M34 -> 2284500
K30: LOT PRINCIPAL | L30: =C3*COUNTIF(Q6:Q26,">0") -> 2400000 | M30: =D3 -> 1
B31: ESPECES | C31: =SUMIFS(C6:C25,E6:E25,"ESPECES") -> 0 | D31: =SUMIFS(L2:L21,N2:N21,"ESPECES")+SUMIFS(F2:F21,G2:G21,"ESPECES") -> 0 | E31: =SUMIFS(H6:H25,J6:J25,"ESPECES") -> 0 | F31: =SUMIFS(Q6:Q25,O6:O25,"ESPECES") -> 0 | G31: =C31+D31-E31-F31 -> 0
B32: BANQUE | C32: =SUMIFS(C6:C25,E6:E25,"BANQUE") -> 1275000 | D32: =SUMIFS(M3:M22,N3:N22,"BANQUE")+SUMIFS(F3:F22,G3:G22,"BANQUE") -> 858500 | E32: =SUMIFS(H6:H25,J6:J25,"BANQUE") -> 0 | F32: =SUMIFS(Q6:Q25,O6:O25,"BANQUE") -> 2250000 | G32: =C32+D32-E32-F32 -> -116500 | K32: PETIT LOT | L32: =L29-L30 -> -115500 | M32: 1200000
B34: TOTAL | C34: =C31+C32 -> 1275000 | D34: =D31+D32 -> 858500 | E34: =E31+E32 -> 0 | F34: =F31+F32 -> 2250000 | G34: =G31+G32 -> -116500 | K34: RELIQUAT | L34: =L32-H27 -> -115500 | M34: =L34 -> -115500 | N34: CUMUL
K36: ECHEC TONTINE | L36: =COUNTIFS(E6:E25,"ECHEC")*75000 -> 0 | M36: =L36+TONTJUIL21!M36 -> 0 | N36: CUMUL
B37: MONTANT TONTINE | C37: 1200000 | K37: ECHEC REMBOURSEMENT | L37: =SUMIFS(F3:F22,G3:G22,"ECHEC") -> 0 | M37: =L37+TONTJUIL21!M37 -> 0 | N37: CUMUL

Sheet TONTSEPT21
A1: ASSOCIATION | B1: ASELBY
A2: ANNEE | B2: 2021 | C2: TONIINE | D2: NBRE PART
A3: TAUX TONTINE | B3: 75000 | C3: =B3*16 -> 1200000 | D3: =ROUNDDOWN(L29/C3,0) -> 0
C4: 44460
A5: MATRICULE | B5: NOM ET PRENOM | C5: MONTANT TONTINE | D5: PENALITE | E5: MODE VERSEMENT TONTINE | F5: REPORT ECHEC PETIT LOT | G5: MODE VERSEMENT VENTE PETIT LOT | H5: VENTE PETIT LOT | I5: INTERET PETIT LOT | J5: MODE VERSEMENT VENTE PETIT LOT | K5: NUMERO CHEQUE | L5: MONTANT A REMBOURSER | M5: MONTANT REMBOURSE | N5: MODE VERSEMENT REMBOURSEMENT | O5: MODE VERSEMENT TONTINE PRINCIPAL | P5: NUMERO CHEQUE | Q5: MONTANT TONTINE LOT PRINCIPAL | R5: INTERET LOT PRINCIPAL | S5: INTERET DU
A6: AS201602 | B6: =VLOOKUP(A6,[6]LISTADHERENT!A$5:H$60,3,0) -> BOUTCHOUANG WILLIAM | C6: =IF(E6="ECHEC",0,VLOOKUP($A6,[8]HISTOSEPT21!$A$6:$AU$39,13,0)) -> 75000 | E6: =VLOOKUP($A6,[8]HISTOSEPT21!$A$6:$AU$39,8,0) -> BANQUE | F6: =IF(N6="ECHEC",L6+(TONTAOUT21!I6*2),0) -> 0 | H6: =VLOOKUP($A6,[8]HISTOSEPT21!$A$6:$AU$39,36,0) -> 0 | I6: =VLOOKUP($A6,[8]HISTOSEPT21!$A$6:$AU$39,39,0) -> 0 | J6: =IF(H6<>0,VLOOKUP($A6,[8]HISTOSEPT21!$A$6:$AU$39,8,0),"ECHEC") -> ECHEC | K6: =VLOOKUP($A6,[8]HISTOSEPT21!$A$6:$AU$39,41,0) -> 0 | L6: =TONTAOUT21!H6+TONTAOUT21!I6+TONTAOUT21!F6 -> 0 | M6: =VLOOKUP(A6,[8]HISTOSEPT21!$A$6:$AZ$37,17,0) -> 0 | N6: =IF(L6<>0,VLOOKUP($A6,[8]HISTOSEPT21!$A$6:$AU$39,8,0),"ECHEC") -> ECHEC | O6: =IF(R6<>0,VLOOKUP($A6,[8]HISTOSEPT21!$A$6:$AU$39,8,0),"ECHEC") -> ECHEC | P6: =VLOOKUP($A6,[8]HISTOSEPT21!$A$6:$AU$39,33,0) -> 0 | Q6: =IF(R6=0,0,($C$37-R6)) -> 0 | R6: =VLOOKUP($A6,[8]HISTOSEPT21!$A$6:$AU$39,30,0) -> 0 | S6: =IF(R6=0,0,(R6-75000)) -> 0
A7: AS201603 | B7: =VLOOKUP(A7,[6]LISTADHERENT!A$5:H$60,3,0) -> CHINGUE FABRICE | F7: =IF(N7="ECHEC",L7+(TONTAOUT21!I7*2),0) -> 0 | L7: =TONTAOUT21!H7+TONTAOUT21!I7+TONTAOUT21!F7 -> 0 | S7: =IF(R7=0,0,(R7-75000)) -> 0
A8: AS201604 | B8: =VLOOKUP(A8,[6]LISTADHERENT!A$5:H$60,3,0) -> DJOMO JEAN PAUL | C8: =IF(E8="ECHEC",0,VLOOKUP($A8,[8]HISTOSEPT21!$A$6:$AU$39,13,0)) -> 75000 | E8: =VLOOKUP($A8,[8]HISTOSEPT21!$A$6:$AU$39,8,0) -> BANQUE | F8: =IF(N8="ECHEC",L8+(TONTAOUT21!I8*2),0) -> 0 | H8: =VLOOKUP($A8,[8]HISTOSEPT21!$A$6:$AU$39,36,0) -> 0 | I8: =VLOOKUP($A8,[8]HISTOSEPT21!$A$6:$AU$39,39,0) -> 0 | J8: =IF(H8<>0,VLOOKUP($A8,[8]HISTOSEPT21!$A$6:$AU$39,8,0),"ECHEC") -> ECHEC | K8: =VLOOKUP($A8,[8]HISTOSEPT21!$A$6:$AU$39,41,0) -> 0 | L8: =TONTAOUT21!H8+TONTAOUT21!I8+TONTAOUT21!F8 -> 0 | M8: =VLOOKUP(A8,[8]HISTOSEPT21!$A$6:$AZ$37,17,0) -> 0 | N8: =IF(M8<>0,VLOOKUP($A8,[8]HISTOSEPT21!$A$6:$AU$39,8,0),"ECHEC") -> ECHEC | O8: =IF(R8<>0,VLOOKUP($A8,[8]HISTOSEPT21!$A$6:$AU$39,8,0),"ECHEC") -> ECHEC | P8: =VLOOKUP($A8,[8]HISTOSEPT21!$A$6:$AU$39,33,0) -> 0 | Q8: =IF(R8=0,0,($C$37-R8)) -> 0 | R8: =VLOOKUP($A8,[8]HISTOSEPT21!$A$6:$AU$39,30,0) -> 0 | S8: =IF(R8=0,0,(R8-75000)) -> 0
A9: AS201605 | B9: =VLOOKUP(A9,[6]LISTADHERENT!A$5:H$60,3,0) -> DJOUKWE NANGUEN GUY BLAISE | C9: =IF(E9="ECHEC",0,VLOOKUP($A9,[8]HISTOSEPT21!$A$6:$AU$39,13,0)) -> 75000 | E9: =VLOOKUP($A9,[8]HISTOSEPT21!$A$6:$AU$39,8,0) -> BANQUE | F9: =IF(N9="ECHEC",L9+(TONTAOUT21!I9*2),0) -> 0 | H9: =VLOOKUP($A9,[8]HISTOSEPT21!$A$6:$AU$39,36,0) -> 0 | I9: =VLOOKUP($A9,[8]HISTOSEPT21!$A$6:$AU$39,39,0) -> 0 | J9: =IF(H9<>0,VLOOKUP($A9,[8]HISTOSEPT21!$A$6:$AU$39,8,0),"ECHEC") -> ECHEC | K9: =VLOOKUP($A9,[8]HISTOSEPT21!$A$6:$AU$39,41,0) -> 0 | L9: =TONTAOUT21!H9+TONTAOUT21!I9+TONTAOUT21!F9 -> 0 | M9: =VLOOKUP(A9,[8]HISTOSEPT21!$A$6:$AZ$37,17,0) -> 0 | N9: =IF(M9<>0,VLOOKUP($A9,[8]HISTOSEPT21!$A$6:$AU$39,8,0),"ECHEC") -> ECHEC | O9: =IF(R9<>0,VLOOKUP($A9,[8]HISTOSEPT21!$A$6:$AU$39,8,0),"ECHEC") -> ECHEC | P9: =VLOOKUP($A9,[8]HISTOSEPT21!$A$6:$AU$39,33,0) -> 0 | Q9: =IF(R9=0,0,($C$37-R9)) -> 0 | R9: =VLOOKUP($A9,[8]HISTOSEPT21!$A$6:$AU$39,30,0) -> 0 | S9: =IF(R9=0,0,(R9-75000)) -> 0
