Workbook

Sheet Sheet1
A1: AIDE
A2: PRÊT
A3: REMBOURSEMENT
A4: AGIOS BANCAIRE
A5: DETAIL CHEQUE
A6: RAPPORT FINANCIER

Sheet Sheet2
A1: BANQUE
A2: ESPECES
A3: ECHEC

Sheet Sheet3
A1: BANQUE
A2: ESPECES
A3: ECHEC

Sheet Sheet4
A1: ASSOCIATION | B1: ASELBY | G1: K
A2: ANNEE | B2: 2022
A3: TONTINE
J4: 44578
A5: MATRICULE | B5: NOM ET PRENOM | C5: FONDES DE DEPART | D5: RELIQUAT | E5: RETRAIT PARTIEL | F5: FONDS DEFINITIF | G5: REPARTITION INTERET | H5: CAPITAL COMPOSE | I5: SANCTION | J5: RESTE | K5: EPARGNE | L5: FONDS DE ROULEMENT | M5: FRAIS EXCEPTIONNEL | N5: COLLATION | O5: PENALITE VST ESPECES | P5: INSCRISPTION | Q5: MUTUELLE | R5: PRÊT FONDS | S5: INTERETPRET FONDS | T5: NUMERO CHEQUE | U5: REMBOURSEMENTPRET FONDS | V5: MODE VERSEMENT REMBOURSEMENT | W5: MODE VERSEMENT PRÊT | X5: NUMERO CHEQUE | Y5: PENALITE PRET FONDS | Z5: PENALITE FONDS | AA5: PENALITE ECHEC TONTINE | AB5: PENALITE RETARD TONTINE | AC5: REMBOURSEMENT TRANSPORT | AD5: CONTRIBUTION FOYER | AE5: DEPENSE FONCTIONNEMENT
A6: AS201648 | B6: =VLOOKUP(A6,[15]LISTADHERENT!$A$5:$J$50,3,0) -> ASELBY | C6: =#REF! -> #REF! | D6: =#REF! -> #REF! | F6: =C6+D6-E6+K6 -> #REF! | G6: =$S$40/$H$40*H6 -> #REF! | H6: =F6+D6+K6 -> #REF! | AE6: =[16]HISTOMVTDEPENSE!$T$39 -> 0
A7: AS201601 | B7: =VLOOKUP(A7,[15]LISTADHERENT!$A$5:$J$50,3,0) -> BAKOP ACHILLE | C7: =#REF! -> #REF! | D7: =#REF! -> #REF! | F7: =C7+D7-E7+K7 -> #REF! | G7: =$S$40/$H$40*H7 -> #REF! | H7: =F7+D7+K7 -> #REF! | Y7: 4000
A8: AS201602 | B8: =VLOOKUP(A8,[15]LISTADHERENT!$A$5:$J$50,3,0) -> BOUTCHOUANG WILLIAM | C8: =#REF! -> #REF! | D8: =#REF! -> #REF! | F8: =C8+D8-E8+K8 -> #REF! | G8: =$S$40/$H$40*H8 -> #REF! | H8: =F8+D8+K8 -> #REF! | I8: =VLOOKUP($A8,[16]HISTOJANV22!$A$6:$AQ$37,22,0) -> 0 | J8: =VLOOKUP($A8,[16]HISTOJANV22!$A$6:$AU$39,45,0) -> 7000 | K8: =IF(J8=0,0,J8-(L8+M8+N8)) -> 3000 | L8: =IF(J8=0,0,500) -> 500 | M8: =IF(J8=0,0,1000) -> 1000 | N8: =IF(J8=0,0,2500) -> 2500 | O8: =VLOOKUP($A8,[16]HISTOJANV22!$A$6:$AU$39,7,0) -> 0 | P8: =VLOOKUP($A8,[16]HISTOJANV22!$A$6:$AU$39,23,0) -> 0 | Q8: =VLOOKUP($A8,[16]HISTOJANV22!$A$6:$AU$39,46,0) -> 0 | R8: =VLOOKUP($A8,[16]HISTODEC21!$A$6:$AU$39,26,0) -> 525000 | S8: =R8*12/1200*12 -> 63000 | T8: =VLOOKUP($A8,[16]HISTOJANV22!$A$6:$AU$39,28,0) -> 0 | U8: =VLOOKUP($A8,[16]HISTOJANV22!$A$6:$AU$39,19,0) -> 0 | V8: =VLOOKUP($A8,[16]HISTOJANV22!$A$6:$AU$39,20,0) -> 0 | W8: =VLOOKUP($A8,[16]HISTOJANV22!$A$6:$AU$39,27,0) -> 0 | X8: =VLOOKUP($A8,[16]HISTOJANV22!$A$6:$AU$39,33,0) -> 0 | AA8: =VLOOKUP($A8,[16]HISTOJANV22!$A$6:$AU$39,43,0) -> 0 | AB8: =VLOOKUP($A8,[16]HISTOJANV22!$A$6:$AU$39,44,0) -> 0 | AC8: =VLOOKUP($A8,[16]HISTOJANV22!$A$6:$AU$39,47,0) -> 0 | AD8: =VLOOKUP(A8,[16]HISTOJANV22!$A$6:$BB$36,54,0) -> 0
A9: AS201604 | B9: =VLOOKUP(A9,[15]LISTADHERENT!$A$5:$J$50,3,0) -> DJOMO JEAN PAUL | C9: =#REF! -> #REF! | D9: =#REF! -> #REF! | F9: =C9+D9-E9+K9 -> #REF! | G9: =$S$40/$H$40*H9 -> #REF! | H9: =F9+D9+K9 -> #REF! | I9: =VLOOKUP($A9,[16]HISTOJANV22!$A$6:$AQ$37,22,0) -> 0 | J9: =VLOOKUP($A9,[16]HISTOJANV22!$A$6:$AU$39,45,0) -> 52000 | K9: =IF(J9=0,0,J9-(L9+M9+N9)) -> 48000 | L9: =IF(J9=0,0,500) -> 500 | M9: =IF(J9=0,0,1000) -> 1000 | N9: =IF(J9=0,0,2500) -> 2500 | O9: =VLOOKUP($A9,[16]HISTOJANV22!$A$6:$AU$39,7,0) -> 0 | P9: =VLOOKUP($A9,[16]HISTOJANV22!$A$6:$AU$39,23,0) -> 0 | Q9: =VLOOKUP($A9,[16]HISTOJANV22!$A$6:$AU$39,46,0) -> 0 | R9: =VLOOKUP($A9,[16]HISTODEC21!$A$6:$AU$39,26,0) -> 1000000 | S9: =R9*12/1200*12 -> 120000 | T9: =VLOOKUP($A9,[16]HISTOJANV22!$A$6:$AU$39,28,0) -> OKK | U9: =VLOOKUP($A9,[16]HISTOJANV22!$A$6:$AU$39,19,0) -> 0 | V9: =VLOOKUP($A9,[16]HISTOJANV22!$A$6:$AU$39,20,0) -> 0 | W9: =VLOOKUP($A9,[16]HISTOJANV22!$A$6:$AU$39,27,0) -> BANQUE | X9: =VLOOKUP($A9,[16]HISTOJANV22!$A$6:$AU$39,33,0) -> 0 | AA9: =VLOOKUP($A9,[16]HISTOJANV22!$A$6:$AU$39,43,0) -> 0 | AB9: =VLOOKUP($A9,[16]HISTOJANV22!$A$6:$AU$39,44,0) -> 0 | AC9: =VLOOKUP($A9,[16]HISTOJANV22!$A$6:$AU$39,47,0) -> 0 | AD9: =VLOOKUP(A9,[16]HISTOJANV22!$A$6:$BB$36,54,0) -> 0
A10: AS201654 | B10: =VLOOKUP(A10,[15]LISTADHERENT!$A$5:$J$50,3,0) -> DJOMOU TCHAPDA | C10: =#REF! -> #REF! | D10: =#REF! -> #REF! | F10: =C10+D10-E10+K10 -> #REF! | G10: =$S$40/$H$40*H10 -> #REF! | H10: =F10+D10+K10 -> #REF! | I10: =VLOOKUP($A10,[16]HISTOJANV22!$A$6:$AQ$37,22,0) -> 0 | J10: =VLOOKUP($A10,[16]HISTOJANV22!$A$6:$AU$39,45,0) -> 7000 | K10: =IF(J10=0,0,J10-(L10+M10+N10)) -> 3000 | L10: =IF(J10=0,0,500) -> 500 | M10: =IF(J10=0,0,1000) -> 1000 | N10: =IF(J10=0,0,2500) -> 2500 | O10: =VLOOKUP($A10,[16]HISTOJANV22!$A$6:$AU$39,7,0) -> 0 | P10: =VLOOKUP($A10,[16]HISTOJANV22!$A$6:$AU$39,23,0) -> 0 | Q10: =VLOOKUP($A10,[16]HISTOJANV22!$A$6:$AU$39,46,0) -> 0 | R10: =VLOOKUP($A10,[16]HISTODEC21!$A$6:$AU$39,26,0) -> #REF! | S10: =R10*1/1200*12 -> #REF! | T10: =VLOOKUP($A10,[16]HISTOJANV22!$A$6:$AU$39,28,0) -> 0 | U10: =VLOOKUP($A10,[16]HISTOJANV22!$A$6:$AU$39,19,0) -> 0 | V10: =VLOOKUP($A10,[16]HISTOJANV22!$A$6:$AU$39,20,0) -> 0 | W10: =VLOOKUP($A10,[16]HISTOJANV22!$A$6:$AU$39,27,0) -> 0 | X10: =VLOOKUP($A10,[16]HISTOJANV22!$A$6:$AU$39,33,0) -> 0 | AA10: =VLOOKUP($A10,[16]HISTOJANV22!$A$6:$AU$39,43,0) -> 0 | AB10: =VLOOKUP($A10,[16]HISTOJANV22!$A$6:$AU$39,44,0) -> 0 | AC10: =VLOOKUP($A10,[16]HISTOJANV22!$A$6:$AU$39,47,0) -> 0 | AD10: =VLOOKUP(A10,[16]HISTOJANV22!$A$6:$BB$36,54,0) -> 0
A11: AS201605 | B11: =VLOOKUP(A11,[15]LISTADHERENT!$A$5:$J$50,3,0) -> DJOUKWE NANGUEN GUY BLAISE | C11: =#REF! -> #REF! | D11: =#REF! -> #REF! | F11: =C11+D11-E11+K11 -> #REF! | G11: =$S$40/$H$40*H11 -> #REF! | H11: =F11+D11+K11 -> #REF! | I11: =VLOOKUP($A11,[16]HISTOJANV22!$A$6:$AQ$37,22,0) -> 0 | J11: =VLOOKUP($A11,[16]HISTOJANV22!$A$6:$AU$39,45,0) -> 12000 | K11: =IF(J11=0,0,J11-(L11+M11+N11)) -> 8000 | L11: =IF(J11=0,0,500) -> 500 | M11: =IF(J11=0,0,1000) -> 1000 | N11: =IF(J11=0,0,2500) -> 2500 | O11: =VLOOKUP($A11,[16]HISTOJANV22!$A$6:$AU$39,7,0) -> 0 | P11: =VLOOKUP($A11,[16]HISTOJANV22!$A$6:$AU$39,23,0) -> 0 | Q11: =VLOOKUP($A11,[16]HISTOJANV22!$A$6:$AU$39,46,0) -> 0 | R11: =VLOOKUP($A11,[16]HISTODEC21!$A$6:$AU$39,26,0) -> 1000000 | S11: =R11*1/1200*12 -> 10000 | T11: =VLOOKUP($A11,[16]HISTOJANV22!$A$6:$AU$39,28,0) -> OKK | U11: =VLOOKUP($A11,[16]HISTOJANV22!$A$6:$AU$39,19,0) -> 0 | V11: =VLOOKUP($A11,[16]HISTOJANV22!$A$6:$AU$39,20,0) -> 0 | W11: =VLOOKUP($A11,[16]HISTOJANV22!$A$6:$AU$39,27,0) -> BANQUE | X11: =VLOOKUP($A11,[16]HISTOJANV22!$A$6:$AU$39,33,0) -> 0 | Y11: 29000 | AA11: =VLOOKUP($A11,[16]HISTOJANV22!$A$6:$AU$39,43,0) -> 0 | AB11: =VLOOKUP($A11,[16]HISTOJANV22!$A$6:$AU$39,44,0) -> 0 | AC11: =VLOOKUP($A11,[16]HISTOJANV22!$A$6:$AU$39,47,0) -> 0 | AD11: =VLOOKUP(A11,[16]HISTOJANV22!$A$6:$BB$36,54,0) -> 0
A12: AS201608 | B12: =VLOOKUP(A12,[15]LISTADHERENT!$A$5:$J$50,3,0) -> DJUOMBESSY ANTOINE | C12: =#REF! -> #REF! | D12: =#REF! -> #REF! | F12: =C12+D12-E12+K12 -> #REF! | G12: =$S$40/$H$40*H12 -> #REF! | H12: =F12+D12+K12 -> #REF! | I12: =VLOOKUP($A12,[16]HISTOJANV22!$A$6:$AQ$37,22,0) -> 0 | J12: =VLOOKUP($A12,[16]HISTOJANV22!$A$6:$AU$39,45,0) -> 7000 | K12: =IF(J12=0,0,J12-(L12+M12+N12)) -> 3000 | L12: =IF(J12=0,0,500) -> 500 | M12: =IF(J12=0,0,1000) -> 1000 | N12: =IF(J12=0,0,2500) -> 2500 | O12: =VLOOKUP($A12,[16]HISTOJANV22!$A$6:$AU$39,7,0) -> 0 | P12: =VLOOKUP($A12,[16]HISTOJANV22!$A$6:$AU$39,23,0) -> 0 | Q12: =VLOOKUP($A12,[16]HISTOJANV22!$A$6:$AU$39,46,0) -> 0 | R12: =VLOOKUP($A12,[16]HISTODEC21!$A$6:$AU$39,26,0) -> 1029000 | S12: =R12*12/1200*12 -> 123480 | T12: =VLOOKUP($A12,[16]HISTOJANV22!$A$6:$AU$39,28,0) -> 0 | U12: =VLOOKUP($A12,[16]HISTOJANV22!$A$6:$AU$39,19,0) -> 1000000 | V12: =VLOOKUP($A12,[16]HISTOJANV22!$A$6:$AU$39,20,0) -> BANQUE | W12: =VLOOKUP($A12,[16]HISTOJANV22!$A$6:$AU$39,27,0) -> 0 | X12: =VLOOKUP($A12,[16]HISTOJANV22!$A$6:$AU$39,33,0) -> 0 | AA12: =VLOOKUP($A12,[16]HISTOJANV22!$A$6:$AU$39,43,0) -> 0 | AB12: =VLOOKUP($A12,[16]HISTOJANV22!$A$6:$AU$39,44,0) -> 0 | AC12: =VLOOKUP($A12,[16]HISTOJANV22!$A$6:$AU$39,47,0) -> 0 | AD12: =VLOOKUP(A12,[16]HISTOJANV22!$A$6:$BB$36,54,0) -> 61000
A13: AS201651 | B13: =VLOOKUP(A13,[15]LISTADHERENT!$A$5:$J$50,3,0) -> DOMOU FABIEN | C13: =#REF! -> #REF! | D13: =#REF! -> #REF! | F13: =C13+D13-E13+K13 -> #REF! | G13: =$S$40/$H$40*H13 -> #REF! | H13: =F13+D13+K13 -> #REF! | I13: =VLOOKUP($A13,[16]HISTOJANV22!$A$6:$AQ$37,22,0) -> 0 | J13: =VLOOKUP($A13,[16]HISTOJANV22!$A$6:$AU$39,45,0) -> 12000 | K13: =IF(J13=0,0,J13-(L13+M13+N13)) -> 8000 | L13: =IF(J13=0,0,500) -> 500 | M13: =IF(J13=0,0,1000) -> 1000 | N13: =IF(J13=0,0,2500) -> 2500 | O13: =VLOOKUP($A13,[16]HISTOJANV22!$A$6:$AU$39,7,0) -> 0 | P13: =VLOOKUP($A13,[16]HISTOJANV22!$A$6:$AU$39,23,0) -> 0 | Q13: =VLOOKUP($A13,[16]HISTOJANV22!$A$6:$AU$39,46,0) -> 0 | R13: =VLOOKUP($A13,[16]HISTODEC21!$A$6:$AU$39,26,0) -> 1000000 | S13: =R13*12/1200*12 -> 120000 | T13: =VLOOKUP($A13,[16]HISTOJANV22!$A$6:$AU$39,28,0) -> OKK | U13: =VLOOKUP($A13,[16]HISTOJANV22!$A$6:$AU$39,19,0) -> 0 | V13: =VLOOKUP($A13,[16]HISTOJANV22!$A$6:$AU$39,20,0) -> 0 | W13: =VLOOKUP($A13,[16]HISTOJANV22!$A$6:$AU$39,27,0) -> BANQUE | X13: =VLOOKUP($A13,[16]HISTOJANV22!$A$6:$AU$39,33,0) -> 0 | AA13: =VLOOKUP($A13,[16]HISTOJANV22!$A$6:$AU$39,43,0) -> 0 | AB13: =VLOOKUP($A13,[16]HISTOJANV22!$A$6:$AU$39,44,0) -> 0 | AC13: =VLOOKUP($A13,[16]HISTOJANV22!$A$6:$AU$39,47,0) -> 0 | AD13: =VLOOKUP(A13,[16]HISTOJANV22!$A$6:$BB$36,54,0) -> 57000
A14: AS201609 | B14: =VLOOKUP(A14,[15]LISTADHERENT!$A$5:$J$50,3,0) -> DONHOU DAVID | C14: =#REF! -> #REF! | D14: =#REF! -> #REF! | F14: =C14+D14-E14+K14 -> #REF! | G14: =$S$40/$H$40*H14 -> #REF! | H14: =F14+D14+K14 -> #REF! | I14: =VLOOKUP($A14,[16]HISTOJANV22!$A$6:$AQ$37,22,0) -> 0 | J14: =VLOOKUP($A14,[16]HISTOJANV22!$A$6:$AU$39,45,0) -> 7000 | K14: =IF(J14=0,0,J14-(L14+M14+N14)) -> 3000 | L14: =IF(J14=0,0,500) -> 500 | M14: =IF(J14=0,0,1000) -> 1000 | N14: =IF(J14=0,0,2500) -> 2500 | O14: =VLOOKUP($A14,[16]HISTOJANV22!$A$6:$AU$39,7,0) -> 0 | P14: =VLOOKUP($A14,[16]HISTOJANV22!$A$6:$AU$39,23,0) -> 0 | Q14: =VLOOKUP($A14,[16]HISTOJANV22!$A$6:$AU$39,46,0) -> 0 | R14: =VLOOKUP($A14,[16]HISTODEC21!$A$6:$AU$39,26,0) -> #REF! | S14: =R14*0/1200*12 -> #REF! | T14: =VLOOKUP($A14,[16]HISTOJANV22!$A$6:$AU$39,28,0) -> 0 | U14: =VLOOKUP($A14,[16]HISTOJANV22!$A$6:$AU$39,19,0) -> 0 | V14: =VLOOKUP($A14,[16]HISTOJANV22!$A$6:$AU$39,20,0) -> 0 | W14: =VLOOKUP($A14,[16]HISTOJANV22!$A$6:$AU$39,27,0) -> 0 | X14: =VLOOKUP($A14,[16]HISTOJANV22!$A$6:$AU$39,33,0) -> 0 | Y14: 155000 | AA14: =VLOOKUP($A14,[16]HISTOJANV22!$A$6:$AU$39,43,0) -> 0 | AB14: =VLOOKUP($A14,[16]HISTOJANV22!$A$6:$AU$39,44,0) -> 0 | AC14: =VLOOKUP($A14,[16]HISTOJANV22!$A$6:$AU$39,47,0) -> 0 | AD14: =VLOOKUP(A14,[16]HISTOJANV22!$A$6:$BB$36,54,0) -> 70000
A15: AS201611 | B15: =VLOOKUP(A15,[15]LISTADHERENT!$A$5:$J$50,3,0) -> HENGUE PAUL OMER | C15: =#REF! -> #REF! | D15: =#REF! -> #REF! | F15: =C15+D15-E15+K15 -> #REF! | G15: =$S$40/$H$40*H15 -> #REF! | H15: =F15+D15+K15 -> #REF! | I15: =VLOOKUP($A15,[16]HISTOJANV22!$A$6:$AQ$37,22,0) -> 0 | J15: =VLOOKUP($A15,[16]HISTOJANV22!$A$6:$AU$39,45,0) -> 7000 | K15: =IF(J15=0,0,J15-(L15+M15+N15)) -> 3000 | L15: =IF(J15=0,0,500) -> 500 | M15: =IF(J15=0,0,1000) -> 1000 | N15: =IF(J15=0,0,2500) -> 2500 | O15: =VLOOKUP($A15,[16]HISTOJANV22!$A$6:$AU$39,7,0) -> 0 | P15: =VLOOKUP($A15,[16]HISTOJANV22!$A$6:$AU$39,23,0) -> 0 | Q15: =VLOOKUP($A15,[16]HISTOJANV22!$A$6:$AU$39,46,0) -> 0 | R15: =VLOOKUP($A15,[16]HISTODEC21!$A$6:$AU$39,26,0) -> #REF! | S15: =R15*12/1200*12 -> #REF! | T15: =VLOOKUP($A15,[16]HISTOJANV22!$A$6:$AU$39,28,0) -> 0 | U15: =VLOOKUP($A15,[16]HISTOJANV22!$A$6:$AU$39,19,0) -> 0 | V15: =VLOOKUP($A15,[16]HISTOJANV22!$A$6:$AU$39,20,0) -> 0 | W15: =VLOOKUP($A15,[16]HISTOJANV22!$A$6:$AU$39,27,0) -> 0 | X15: =VLOOKUP($A15,[16]HISTOJANV22!$A$6:$AU$39,33,0) -> 0 | AA15: =VLOOKUP($A15,[16]HISTOJANV22!$A$6:$AU$39,43,0) -> 0 | AB15: =VLOOKUP($A15,[16]HISTOJANV22!$A$6:$AU$39,44,0) -> 0 | AC15: =VLOOKUP($A15,[16]HISTOJANV22!$A$6:$AU$39,47,0) -> 0 | AD15: =VLOOKUP(A15,[16]HISTOJANV22!$A$6:$BB$36,54,0) -> 0
A16: AS201613 | B16: =VLOOKUP(A16,[15]LISTADHERENT!$A$5:$J$50,3,0) -> HOTCHO BENJAMIN | C16: =#REF! -> #REF! | D16: =#REF! -> #REF! | F16: =C16+D16-E16+K16 -> #REF! | G16: =$S$40/$H$40*H16 -> #REF! | H16: =F16+D16+K16 -> #REF! | I16: =VLOOKUP($A16,[16]HISTOJANV22!$A$6:$AQ$37,22,0) -> 0 | J16: =VLOOKUP($A16,[16]HISTOJANV22!$A$6:$AU$39,45,0) -> 52000 | K16: =IF(J16=0,0,J16-(L16+M16+N16)) -> 48000 | L16: =IF(J16=0,0,500) -> 500 | M16: =IF(J16=0,0,1000) -> 1000 | N16: =IF(J16=0,0,2500) -> 2500 | O16: =VLOOKUP($A16,[16]HISTOJANV22!$A$6:$AU$39,7,0) -> 0 | P16: =VLOOKUP($A16,[16]HISTOJANV22!$A$6:$AU$39,23,0) -> 0 | Q16: =VLOOKUP($A16,[16]HISTOJANV22!$A$6:$AU$39,46,0) -> 0 | R16: =VLOOKUP($A16,[16]HISTODEC21!$A$6:$AU$39,26,0) -> #REF! | S16: =R16*12/1200*12 -> #REF! | T16: =VLOOKUP($A16,[16]HISTOJANV22!$A$6:$AU$39,28,0) -> 0 | U16: =VLOOKUP($A16,[16]HISTOJANV22!$A$6:$AU$39,19,0) -> 0 | V16: =VLOOKUP($A16,[16]HISTOJANV22!$A$6:$AU$39,20,0) -> 0 | W16: =VLOOKUP($A16,[16]HISTOJANV22!$A$6:$AU$39,27,0) -> 0 | X16: =VLOOKUP($A16,[16]HISTOJANV22!$A$6:$AU$39,33,0) -> 0 | AA16: =VLOOKUP($A16,[16]HISTOJANV22!$A$6:$AU$39,43,0) -> 0 | AB16: =VLOOKUP($A16,[16]HISTOJANV22!$A$6:$AU$39,44,0) -> 0 | AC16: =VLOOKUP($A16,[16]HISTOJANV22!$A$6:$AU$39,47,0) -> 0 | AD16: =VLOOKUP(A16,[16]HISTOJANV22!$A$6:$BB$36,54,0) -> 70000
A17: AS201617 | B17: =VLOOKUP(A17,[15]LISTADHERENT!$A$5:$J$50,3,0) -> KOUAMOU MOISE | C17: =#REF! -> #REF! | D17: =#REF! -> #REF! | F17: =C17+D17-E17+K17 -> #REF! | G17: =$S$40/$H$40*H17 -> #REF! | H17: =F17+D17+K17 -> #REF! | I17: =VLOOKUP($A17,[16]HISTOJANV22!$A$6:$AQ$37,22,0) -> 0 | J17: =VLOOKUP($A17,[16]HISTOJANV22!$A$6:$AU$39,45,0) -> 7000 | K17: =IF(J17=0,0,J17-(L17+M17+N17)) -> 3000 | L17: =IF(J17=0,0,500) -> 500 | M17: =IF(J17=0,0,1000) -> 1000 | N17: =IF(J17=0,0,2500) -> 2500 | O17: =VLOOKUP($A17,[16]HISTOJANV22!$A$6:$AU$39,7,0) -> 0 | P17: =VLOOKUP($A17,[16]HISTOJANV22!$A$6:$AU$39,23,0) -> 0 | Q17: =VLOOKUP($A17,[16]HISTOJANV22!$A$6:$AU$39,46,0) -> 0 | R17: =VLOOKUP($A17,[16]HISTODEC21!$A$6:$AU$39,26,0) -> #REF! | S17: =R17*12/1200*12 -> #REF! | T17: =VLOOKUP($A17,[16]HISTOJANV22!$A$6:$AU$39,28,0) -> 0 | U17: =VLOOKUP($A17,[16]HISTOJANV22!$A$6:$AU$39,19,0) -> 0 | V17: =VLOOKUP($A17,[16]HISTOJANV22!$A$6:$AU$39,20,0) -> 0 | W17: =VLOOKUP($A17,[16]HISTOJANV22!$A$6:$AU$39,27,0) -> 0 | X17: =VLOOKUP($A17,[16]HISTOJANV22!$A$6:$AU$39,33,0) -> 0 | AA17: =VLOOKUP($A17,[16]HISTOJANV22!$A$6:$AU$39,43,0) -> 0 | AB17: =VLOOKUP($A17,[16]HISTOJANV22!$A$6:$AU$39,44,0) -> 0 | AC17: =VLOOKUP($A17,[16]HISTOJANV22!$A$6:$AU$39,47,0) -> 0 | AD17: =VLOOKUP(A17,[16]HISTOJANV22!$A$6:$BB$36,54,0) -> 0
A18: AS201619 | B18: =VLOOKUP(A18,[15]LISTADHERENT!$A$5:$J$50,3,0) -> KOUATCHO MESSACK | C18: =#REF! -> #REF! | D18: =#REF! -> #REF! | F18: =C18+D18-E18+K18 -> #REF! | G18: =$S$40/$H$40*H18 -> #REF! | H18: =F18+D18+K18 -> #REF! | I18: =VLOOKUP($A18,[16]HISTOJANV22!$A$6:$AQ$37,22,0) -> 0 | J18: =VLOOKUP($A18,[16]HISTOJANV22!$A$6:$AU$39,45,0) -> 7000 | K18: =IF(J18=0,0,J18-(L18+M18+N18)) -> 3000 | L18: =IF(J18=0,0,500) -> 500 | M18: =IF(J18=0,0,1000) -> 1000 | N18: =IF(J18=0,0,2500) -> 2500 | O18: =VLOOKUP($A18,[16]HISTOJANV22!$A$6:$AU$39,7,0) -> 0 | P18: =VLOOKUP($A18,[16]HISTOJANV22!$A$6:$AU$39,23,0) -> 0 | Q18: =VLOOKUP($A18,[16]HISTOJANV22!$A$6:$AU$39,46,0) -> 0 | R18: =VLOOKUP($A18,[16]HISTODEC21!$A$6:$AU$39,26,0) -> 1000000 | S18: =R18*12/1200*12 -> 120000 | T18: =VLOOKUP($A18,[16]HISTOJANV22!$A$6:$AU$39,28,0) -> OKK | U18: =VLOOKUP($A18,[16]HISTOJANV22!$A$6:$AU$39,19,0) -> 0 | V18: =VLOOKUP($A18,[16]HISTOJANV22!$A$6:$AU$39,20,0) -> 0 | W18: =VLOOKUP($A18,[16]HISTOJANV22!$A$6:$AU$39,27,0) -> BANQUE | X18: =VLOOKUP($A18,[16]HISTOJANV22!$A$6:$AU$39,33,0) -> 0 | AA18: =VLOOKUP($A18,[16]HISTOJANV22!$A$6:$AU$39,43,0) -> 0 | AB18: =VLOOKUP($A18,[16]HISTOJANV22!$A$6:$AU$39,44,0) -> 0 | AC18: =VLOOKUP($A18,[16]HISTOJANV22!$A$6:$AU$39,47,0) -> 0 | AD18: =VLOOKUP(A18,[16]HISTOJANV22!$A$6:$BB$36,54,0) -> 0
A19: AS201620 | B19: =VLOOKUP(A19,[15]LISTADHERENT!$A$5:$J$50,3,0) -> LOWE JEAN | C19: =#REF! -> #REF! | D19: =#REF! -> #REF! | F19: =C19+D19-E19+K19 -> #REF! | G19: =$S$40/$H$40*H19 -> #REF! | H19: =F19+D19+K19 -> #REF! | I19: =VLOOKUP($A19,[16]HISTOJANV22!$A$6:$AQ$37,22,0) -> 0 | J19: =VLOOKUP($A19,[16]HISTOJANV22!$A$6:$AU$39,45,0) -> 7000 | K19: =IF(J19=0,0,J19-(L19+M19+N19)) -> 3000 | L19: =IF(J19=0,0,500) -> 500 | M19: =IF(J19=0,0,1000) -> 1000 | N19: =IF(J19=0,0,2500) -> 2500 | O19: =VLOOKUP($A19,[16]HISTOJANV22!$A$6:$AU$39,7,0) -> 0 | P19: =VLOOKUP($A19,[16]HISTOJANV22!$A$6:$AU$39,23,0) -> 0 | Q19: =VLOOKUP($A19,[16]HISTOJANV22!$A$6:$AU$39,46,0) -> 0 | R19: =VLOOKUP($A19,[16]HISTODEC21!$A$6:$AU$39,26,0) -> 500000 | S19: =R19*12/1200*12 -> 60000 | T19: =VLOOKUP($A19,[16]HISTOJANV22!$A$6:$AU$39,28,0) -> OKK | U19: =VLOOKUP($A19,[16]HISTOJANV22!$A$6:$AU$39,19,0) -> 0 | V19: =VLOOKUP($A19,[16]HISTOJANV22!$A$6:$AU$39,20,0) -> 0 | W19: =VLOOKUP($A19,[16]HISTOJANV22!$A$6:$AU$39,27,0) -> BANQUE | X19: =VLOOKUP($A19,[16]HISTOJANV22!$A$6:$AU$39,33,0) -> 0 | AA19: =VLOOKUP($A19,[16]HISTOJANV22!$A$6:$AU$39,43,0) -> 0 | AB19: =VLOOKUP($A19,[16]HISTOJANV22!$A$6:$AU$39,44,0) -> 0 | AC19: =VLOOKUP($A19,[16]HISTOJANV22!$A$6:$AU$39,47,0) -> 0 | AD19: =VLOOKUP(A19,[16]HISTOJANV22!$A$6:$BB$36,54,0) -> 0
A20: AS201649 | B20: =VLOOKUP(A20,[15]LISTADHERENT!$A$5:$J$50,3,0) -> MBOGNING TUGMA GUY | C20: =#REF! -> #REF! | D20: =#REF! -> #REF! | F20: =C20+D20-E20+K20 -> #REF! | G20: =$S$40/$H$40*H20 -> #REF! | H20: =F20+D20+K20 -> #REF! | I20: =VLOOKUP($A20,[16]HISTOJANV22!$A$6:$AQ$37,22,0) -> 0 | J20: =VLOOKUP($A20,[16]HISTOJANV22!$A$6:$AU$39,45,0) -> 7000 | K20: =IF(J20=0,0,J20-(L20+M20+N20)) -> 3000 | L20: =IF(J20=0,0,500) -> 500 | M20: =IF(J20=0,0,1000) -> 1000 | N20: =IF(J20=0,0,2500) -> 2500 | O20: =VLOOKUP($A20,[16]HISTOJANV22!$A$6:$AU$39,7,0) -> 0 | P20: =VLOOKUP($A20,[16]HISTOJANV22!$A$6:$AU$39,23,0) -> 0 | Q20: =VLOOKUP($A20,[16]HISTOJANV22!$A$6:$AU$39,46,0) -> 0 | R20: =VLOOKUP($A20,[16]HISTODEC21!$A$6:$AU$39,26,0) -> 1050000 | S20: =R20*12/1200*12 -> 126000 | T20: =VLOOKUP($A20,[16]HISTOJANV22!$A$6:$AU$39,28,0) -> 0 | U20: =VLOOKUP($A20,[16]HISTOJANV22!$A$6:$AU$39,19,0) -> 1050000 | V20: =VLOOKUP($A20,[16]HISTOJANV22!$A$6:$AU$39,20,0) -> BANQUE | W20: =VLOOKUP($A20,[16]HISTOJANV22!$A$6:$AU$39,27,0) -> BANQUE | X20: =VLOOKUP($A20,[16]HISTOJANV22!$A$6:$AU$39,33,0) -> 0 | AA20: =VLOOKUP($A20,[16]HISTOJANV22!$A$6:$AU$39,43,0) -> 0 | AB20: =VLOOKUP($A20,[16]HISTOJANV22!$A$6:$AU$39,44,0) -> 0 | AC20: =VLOOKUP($A20,[16]HISTOJANV22!$A$6:$AU$39,47,0) -> 0 | AD20: =VLOOKUP(A20,[16]HISTOJANV22!$A$6:$BB$36,54,0) -> 0
A21: AS201639 | B21: =VLOOKUP(A21,[15]LISTADHERENT!$A$5:$J$50,3,0) -> NANGUEN MARTIN | C21: =#REF! -> #REF! | D21: =#REF! -> #REF! | F21: =C21+D21-E21+K21 -> #REF! | G21: =$S$40/$H$40*H21 -> #REF! | H21: =F21+D21+K21 -> #REF! | I21: =VLOOKUP($A21,[16]HISTOJANV22!$A$6:$AQ$37,22,0) -> 0 | J21: =VLOOKUP($A21,[16]HISTOJANV22!$A$6:$AU$39,45,0) -> 7000 | K21: =IF(J21=0,0,J21-(L21+M21+N21)) -> 3000 | L21: =IF(J21=0,0,500) -> 500 | M21: =IF(J21=0,0,1000) -> 1000 | N21: =IF(J21=0,0,2500) -> 2500 | O21: =VLOOKUP($A21,[16]HISTOJANV22!$A$6:$AU$39,7,0) -> 0 | P21: =VLOOKUP($A21,[16]HISTOJANV22!$A$6:$AU$39,23,0) -> 0 | Q21: =VLOOKUP($A21,[16]HISTOJANV22!$A$6:$AU$39,46,0) -> 0 | R21: =VLOOKUP($A21,[16]HISTODEC21!$A$6:$AU$39,26,0) -> #REF! | S21: =R21*12/1200*12 -> #REF! | T21: =VLOOKUP($A21,[16]HISTOJANV22!$A$6:$AU$39,28,0) -> 0 | U21: =VLOOKUP($A21,[16]HISTOJANV22!$A$6:$AU$39,19,0) -> 0 | V21: =VLOOKUP($A21,[16]HISTOJANV22!$A$6:$AU$39,20,0) -> 0 | W21: =VLOOKUP($A21,[16]HISTOJANV22!$A$6:$AU$39,27,0) -> 0 | X21: =VLOOKUP($A21,[16]HISTOJANV22!$A$6:$AU$39,33,0) -> 0 | AA21: =VLOOKUP($A21,[16]HISTOJANV22!$A$6:$AU$39,43,0) -> 0 | AB21: =VLOOKUP($A21,[16]HISTOJANV22!$A$6:$AU$39,44,0) -> 0 | AC21: =VLOOKUP($A21,[16]HISTOJANV22!$A$6:$AU$39,47,0) -> 0 | AD21: =VLOOKUP(A21,[16]HISTOJANV22!$A$6:$BB$36,54,0) -> 0
A22: AS201621 | B22: =VLOOKUP(A22,[15]LISTADHERENT!$A$5:$J$50,3,0) -> NANKAM APPOLINAIRE | C22: =#REF! -> #REF! | D22: =#REF! -> #REF! | F22: =C22+D22-E22+K22 -> #REF! | G22: =$S$40/$H$40*H22 -> #REF! | H22: =F22+D22+K22 -> #REF! | I22: =VLOOKUP($A22,[16]HISTOJANV22!$A$6:$AQ$37,22,0) -> 0 | J22: =VLOOKUP($A22,[16]HISTOJANV22!$A$6:$AU$39,45,0) -> 7000 | K22: =IF(J22=0,0,J22-(L22+M22+N22)) -> 3000 | L22: =IF(J22=0,0,500) -> 500 | M22: =IF(J22=0,0,1000) -> 1000 | N22: =IF(J22=0,0,2500) -> 2500 | O22: =VLOOKUP($A22,[16]HISTOJANV22!$A$6:$AU$39,7,0) -> 0 | P22: =VLOOKUP($A22,[16]HISTOJANV22!$A$6:$AU$39,23,0) -> 0 | Q22: =VLOOKUP($A22,[16]HISTOJANV22!$A$6:$AU$39,46,0) -> 0 | R22: =VLOOKUP($A22,[16]HISTODEC21!$A$6:$AU$39,26,0) -> 924000 | S22: =R22*12/1200*12 -> 110880 | T22: =VLOOKUP($A22,[16]HISTOJANV22!$A$6:$AU$39,28,0) -> 0 | U22: =VLOOKUP($A22,[16]HISTOJANV22!$A$6:$AU$39,19,0) -> 924000 | V22: =VLOOKUP($A22,[16]HISTOJANV22!$A$6:$AU$39,20,0) -> BANQUE | W22: =VLOOKUP($A22,[16]HISTOJANV22!$A$6:$AU$39,27,0) -> 0 | X22: =VLOOKUP($A22,[16]HISTOJANV22!$A$6:$AU$39,33,0) -> 0 | Y22: 50000 | AA22: =VLOOKUP($A22,[16]HISTOJANV22!$A$6:$AU$39,43,0) -> 0 | AB22: =VLOOKUP($A22,[16]HISTOJANV22!$A$6:$AU$39,44,0) -> 0 | AC22: =VLOOKUP($A22,[16]HISTOJANV22!$A$6:$AU$39,47,0) -> 0 | AD22: =VLOOKUP(A22,[16]HISTOJANV22!$A$6:$BB$36,54,0) -> 0
A23: AS201622 | B23: =VLOOKUP(A23,[15]LISTADHERENT!$A$5:$J$50,3,0) -> NDJOMO ETIENNE | C23: =#REF! -> #REF! | D23: =#REF! -> #REF! | F23: =C23+D23-E23+K23 -> #REF! | G23: =$S$40/$H$40*H23 -> #REF! | H23: =F23+D23+K23 -> #REF! | I23: =VLOOKUP($A23,[16]HISTOJANV22!$A$6:$AQ$37,22,0) -> 0 | J23: =VLOOKUP($A23,[16]HISTOJANV22!$A$6:$AU$39,45,0) -> 17000 | K23: =IF(J23=0,0,J23-(L23+M23+N23)) -> 13000 | L23: =IF(J23=0,0,500) -> 500 | M23: =IF(J23=0,0,1000) -> 1000 | N23: =IF(J23=0,0,2500) -> 2500 | O23: =VLOOKUP($A23,[16]HISTOJANV22!$A$6:$AU$39,7,0) -> 0 | P23: =VLOOKUP($A23,[16]HISTOJANV22!$A$6:$AU$39,23,0) -> 0 | Q23: =VLOOKUP($A23,[16]HISTOJANV22!$A$6:$AU$39,46,0) -> 0 | R23: =VLOOKUP($A23,[16]HISTODEC21!$A$6:$AU$39,26,0) -> 500000 | S23: =R23*12/1200*12 -> 60000 | T23: =VLOOKUP($A23,[16]HISTOJANV22!$A$6:$AU$39,28,0) -> OKK | U23: =VLOOKUP($A23,[16]HISTOJANV22!$A$6:$AU$39,19,0) -> 0 | V23: =VLOOKUP($A23,[16]HISTOJANV22!$A$6:$AU$39,20,0) -> 0 | W23: =VLOOKUP($A23,[16]HISTOJANV22!$A$6:$AU$39,27,0) -> BANQUE | X23: =VLOOKUP($A23,[16]HISTOJANV22!$A$6:$AU$39,33,0) -> 0 | AA23: =VLOOKUP($A23,[16]HISTOJANV22!$A$6:$AU$39,43,0) -> 0 | AB23: =VLOOKUP($A23,[16]HISTOJANV22!$A$6:$AU$39,44,0) -> 0 | AC23: =VLOOKUP($A23,[16]HISTOJANV22!$A$6:$AU$39,47,0) -> 0 | AD23: =VLOOKUP(A23,[16]HISTOJANV22!$A$6:$BB$36,54,0) -> 0
A24: AS201624 | B24: =VLOOKUP(A24,[15]LISTADHERENT!$A$5:$J$50,3,0) -> NGONDIEP CLAUDE | C24: =#REF! -> #REF! | D24: =#REF! -> #REF! | F24: =C24+D24-E24+K24 -> #REF! | G24: =$S$40/$H$40*H24 -> #REF! | H24: =F24+D24+K24 -> #REF! | I24: =VLOOKUP($A24,[16]HISTOJANV22!$A$6:$AQ$37,22,0) -> 0 | J24: =VLOOKUP($A24,[16]HISTOJANV22!$A$6:$AU$39,45,0) -> 12000 | K24: =IF(J24=0,0,J24-(L24+M24+N24)) -> 8000 | L24: =IF(J24=0,0,500) -> 500 | M24: =IF(J24=0,0,1000) -> 1000 | N24: =IF(J24=0,0,2500) -> 2500 | O24: =VLOOKUP($A24,[16]HISTOJANV22!$A$6:$AU$39,7,0) -> 0 | P24: =VLOOKUP($A24,[16]HISTOJANV22!$A$6:$AU$39,23,0) -> 0 | Q24: =VLOOKUP($A24,[16]HISTOJANV22!$A$6:$AU$39,46,0) -> 0 | R24: =VLOOKUP($A24,[16]HISTODEC21!$A$6:$AU$39,26,0) -> 1000000 | S24: =R24*12/1200*12 -> 120000 | T24: =VLOOKUP($A24,[16]HISTOJANV22!$A$6:$AU$39,28,0) -> OKK | U24: =VLOOKUP($A24,[16]HISTOJANV22!$A$6:$AU$39,19,0) -> 0 | V24: =VLOOKUP($A24,[16]HISTOJANV22!$A$6:$AU$39,20,0) -> 0 | W24: =VLOOKUP($A24,[16]HISTOJANV22!$A$6:$AU$39,27,0) -> BANQUE | X24: =VLOOKUP($A24,[16]HISTOJANV22!$A$6:$AU$39,33,0) -> 0 | AA24: =VLOOKUP($A24,[16]HISTOJANV22!$A$6:$AU$39,43,0) -> 0 | AB24: =VLOOKUP($A24,[16]HISTOJANV22!$A$6:$AU$39,44,0) -> 0 | AC24: =VLOOKUP($A24,[16]HISTOJANV22!$A$6:$AU$39,47,0) -> 0 | AD24: =VLOOKUP(A24,[16]HISTOJANV22!$A$6:$BB$36,54,0) -> 70000
A25: AS201626 | B25: =VLOOKUP(A25,[15]LISTADHERENT!$A$5:$J$50,3,0) -> NGUIEMEGNI MATHIEU BLAISE | C25: =#REF! -> #REF! | D25: =#REF! -> #REF! | F25: =C25+D25-E25+K25 -> #REF! | G25: =$S$40/$H$40*H25 -> #REF! | H25: =F25+D25+K25 -> #REF! | I25: =VLOOKUP($A25,[16]HISTOJANV22!$A$6:$AQ$37,22,0) -> 0 | J25: =VLOOKUP($A25,[16]HISTOJANV22!$A$6:$AU$39,45,0) -> 7000 | K25: =IF(J25=0,0,J25-(L25+M25+N25)) -> 3000 | L25: =IF(J25=0,0,500) -> 500 | M25: =IF(J25=0,0,1000) -> 1000 | N25: =IF(J25=0,0,2500) -> 2500 | O25: =VLOOKUP($A25,[16]HISTOJANV22!$A$6:$AU$39,7,0) -> 0 | P25: =VLOOKUP($A25,[16]HISTOJANV22!$A$6:$AU$39,23,0) -> 0 | Q25: =VLOOKUP($A25,[16]HISTOJANV22!$A$6:$AU$39,46,0) -> 0 | R25: =VLOOKUP($A25,[16]HISTODEC21!$A$6:$AU$39,26,0) -> 1000000 | S25: =R25*12/1200*12 -> 120000 | T25: =VLOOKUP($A25,[16]HISTOJANV22!$A$6:$AU$39,28,0) -> OKK | U25: =VLOOKUP($A25,[16]HISTOJANV22!$A$6:$AU$39,19,0) -> 0 | V25: =VLOOKUP($A25,[16]HISTOJANV22!$A$6:$AU$39,20,0) -> 0 | W25: =VLOOKUP($A25,[16]HISTOJANV22!$A$6:$AU$39,27,0) -> BANQUE | X25: =VLOOKUP($A25,[16]HISTOJANV22!$A$6:$AU$39,33,0) -> 0 | AA25: =VLOOKUP($A25,[16]HISTOJANV22!$A$6:$AU$39,43,0) -> 0 | AB25: =VLOOKUP($A25,[16]HISTOJANV22!$A$6:$AU$39,44,0) -> 0 | AC25: =VLOOKUP($A25,[16]HISTOJANV22!$A$6:$AU$39,47,0) -> 0 | AD25: =VLOOKUP(A25,[16]HISTOJANV22!$A$6:$BB$36,54,0) -> 70000
A26: AS201628 | B26: =VLOOKUP(A26,[15]LISTADHERENT!$A$5:$J$50,3,0) -> NKAMGANG JUSTIN DEJOLIE | C26: =#REF! -> #REF! | D26: =#REF! -> #REF! | F26: =C26+D26-E26+K26 -> #REF! | G26: =$S$40/$H$40*H26 -> #REF! | H26: =F26+D26+K26 -> #REF! | I26: =VLOOKUP($A26,[16]HISTOJANV22!$A$6:$AQ$37,22,0) -> 0 | J26: =VLOOKUP($A26,[16]HISTOJANV22!$A$6:$AU$39,45,0) -> 7000 | K26: =IF(J26=0,0,J26-(L26+M26+N26)) -> 3000 | L26: =IF(J26=0,0,500) -> 500 | M26: =IF(J26=0,0,1000) -> 1000 | N26: =IF(J26=0,0,2500) -> 2500 | O26: =VLOOKUP($A26,[16]HISTOJANV22!$A$6:$AU$39,7,0) -> 0 | P26: =VLOOKUP($A26,[16]HISTOJANV22!$A$6:$AU$39,23,0) -> 0 | Q26: =VLOOKUP($A26,[16]HISTOJANV22!$A$6:$AU$39,46,0) -> 0 | R26: =VLOOKUP($A26,[16]HISTODEC21!$A$6:$AU$39,26,0) -> 1155000 | S26: =R26*0/1200*12 -> 0 | T26: =VLOOKUP($A26,[16]HISTOJANV22!$A$6:$AU$39,28,0) -> 0 | U26: =VLOOKUP($A26,[16]HISTOJANV22!$A$6:$AU$39,19,0) -> 0 | V26: =VLOOKUP($A26,[16]HISTOJANV22!$A$6:$AU$39,20,0) -> 0 | W26: =VLOOKUP($A26,[16]HISTOJANV22!$A$6:$AU$39,27,0) -> BANQUE | X26: =VLOOKUP($A26,[16]HISTOJANV22!$A$6:$AU$39,33,0) -> 0 | Y26: 155000 | AA26: =VLOOKUP($A26,[16]HISTOJANV22!$A$6:$AU$39,43,0) -> 0 | AB26: =VLOOKUP($A26,[16]HISTOJANV22!$A$6:$AU$39,44,0) -> 0 | AC26: =VLOOKUP($A26,[16]HISTOJANV22!$A$6:$AU$39,47,0) -> 0 | AD26: =VLOOKUP(A26,[16]HISTOJANV22!$A$6:$BB$36,54,0) -> 0
A27: AS201656 | B27: =VLOOKUP(A27,[15]LISTADHERENT!$A$5:$J$50,3,0) -> NOUBE ETIENNE | C27: =#REF! -> #REF! | D27: =#REF! -> #REF! | F27: =C27+D27-E27+K27 -> #REF! | G27: =$S$40/$H$40*H27 -> #REF! | H27: =F27+D27+K27 -> #REF! | I27: =VLOOKUP($A27,[16]HISTOJANV22!$A$6:$AQ$37,22,0) -> #N/A | J27: =VLOOKUP($A27,[16]HISTOJANV22!$A$6:$AU$39,45,0) -> #N/A | K27: =IF(J27=0,0,J27-(L27+M27+N27)) -> #N/A | L27: =IF(J27=0,0,500) -> #N/A | M27: =IF(J27=0,0,1000) -> #N/A | N27: =IF(J27=0,0,2500) -> #N/A | O27: =VLOOKUP($A27,[16]HISTOJANV22!$A$6:$AU$39,7,0) -> #N/A | P27: =VLOOKUP($A27,[16]HISTOJANV22!$A$6:$AU$39,23,0) -> #N/A | Q27: =VLOOKUP($A27,[16]HISTOJANV22!$A$6:$AU$39,46,0) -> #N/A | R27: =VLOOKUP($A27,[16]HISTODEC21!$A$6:$AU$39,26,0) -> #N/A | S27: =R27*12/1200*12 -> #N/A | T27: =VLOOKUP($A27,[16]HISTOJANV22!$A$6:$AU$39,28,0) -> #N/A | U27: =VLOOKUP($A27,[16]HISTOJANV22!$A$6:$AU$39,19,0) -> #N/A | V27: =VLOOKUP($A27,[16]HISTOJANV22!$A$6:$AU$39,20,0) -> #N/A | W27: =VLOOKUP($A27,[16]HISTOJANV22!$A$6:$AU$39,27,0) -> #N/A | X27: =VLOOKUP($A27,[16]HISTOJANV22!$A$6:$AU$39,33,0) -> #N/A | AA27: =VLOOKUP($A27,[16]HISTOJANV22!$A$6:$AU$39,43,0) -> #N/A | AB27: =VLOOKUP($A27,[16]HISTOJANV22!$A$6:$AU$39,44,0) -> #N/A | AC27: =VLOOKUP($A27,[16]HISTOJANV22!$A$6:$AU$39,47,0) -> #N/A | AD27: =VLOOKUP(A27,[16]HISTOJANV22!$A$6:$BB$36,54,0) -> #N/A
A28: AS201633 | B28: =VLOOKUP(A28,[15]LISTADHERENT!$A$5:$J$50,3,0) -> PATEGO NJOSSU GUSTAVE | C28: =#REF! -> #REF! | D28: =#REF! -> #REF! | F28: =C28+D28-E28+K28 -> #REF! | G28: =$S$40/$H$40*H28 -> #REF! | H28: =F28+D28+K28 -> #REF! | I28: =VLOOKUP($A28,[16]HISTOJANV22!$A$6:$AQ$37,22,0) -> 0 | J28: =VLOOKUP($A28,[16]HISTOJANV22!$A$6:$AU$39,45,0) -> 7000 | K28: =IF(J28=0,0,J28-(L28+M28+N28)) -> 3000 | L28: =IF(J28=0,0,500) -> 500 | M28: =IF(J28=0,0,1000) -> 1000 | N28: =IF(J28=0,0,2500) -> 2500 | O28: =VLOOKUP($A28,[16]HISTOJANV22!$A$6:$AU$39,7,0) -> 0 | P28: =VLOOKUP($A28,[16]HISTOJANV22!$A$6:$AU$39,23,0) -> 0 | Q28: =VLOOKUP($A28,[16]HISTOJANV22!$A$6:$AU$39,46,0) -> 0 | R28: =VLOOKUP($A28,[16]HISTODEC21!$A$6:$AU$39,26,0) -> #REF! | S28: =R28*12/1200*12 -> #REF! | T28: =VLOOKUP($A28,[16]HISTOJANV22!$A$6:$AU$39,28,0) -> 0 | U28: =VLOOKUP($A28,[16]HISTOJANV22!$A$6:$AU$39,19,0) -> 0 | V28: =VLOOKUP($A28,[16]HISTOJANV22!$A$6:$AU$39,20,0) -> 0 | W28: =VLOOKUP($A28,[16]HISTOJANV22!$A$6:$AU$39,27,0) -> 0 | X28: =VLOOKUP($A28,[16]HISTOJANV22!$A$6:$AU$39,33,0) -> 0 | AA28: =VLOOKUP($A28,[16]HISTOJANV22!$A$6:$AU$39,43,0) -> 0 | AB28: =VLOOKUP($A28,[16]HISTOJANV22!$A$6:$AU$39,44,0) -> 0 | AC28: =VLOOKUP($A28,[16]HISTOJANV22!$A$6:$AU$39,47,0) -> 0 | AD28: =VLOOKUP(A28,[16]HISTOJANV22!$A$6:$BB$36,54,0) -> 0
A29: AS201657 | B29: =VLOOKUP(A29,[15]LISTADHERENT!$A$5:$J$50,3,0) -> SEUMO POLYCARPE | C29: =#REF! -> #REF! | D29: =#REF! -> #REF! | F29: =C29+D29-E29+K29 -> #REF! | G29: =$S$40/$H$40*H29 -> #REF! | H29: =F29+D29+K29 -> #REF! | I29: =VLOOKUP($A29,[16]HISTOJANV22!$A$6:$AQ$37,22,0) -> #N/A | J29: =VLOOKUP($A29,[16]HISTOJANV22!$A$6:$AU$39,45,0) -> #N/A | K29: =IF(J29=0,0,J29-(L29+M29+N29)) -> #N/A | L29: =IF(J29=0,0,500) -> #N/A | M29: =IF(J29=0,0,1000) -> #N/A | N29: =IF(J29=0,0,2500) -> #N/A | O29: =VLOOKUP($A29,[16]HISTOJANV22!$A$6:$AU$39,7,0) -> #N/A | P29: =VLOOKUP($A29,[16]HISTOJANV22!$A$6:$AU$39,23,0) -> #N/A | Q29: =VLOOKUP($A29,[16]HISTOJANV22!$A$6:$AU$39,46,0) -> #N/A | R29: =VLOOKUP($A29,[16]HISTODEC21!$A$6:$AU$39,26,0) -> #N/A | S29: =R29*12/1200*12 -> #N/A | T29: =VLOOKUP($A29,[16]HISTOJANV22!$A$6:$AU$39,28,0) -> #N/A | U29: =VLOOKUP($A29,[16]HISTOJANV22!$A$6:$AU$39,19,0) -> #N/A | V29: =VLOOKUP($A29,[16]HISTOJANV22!$A$6:$AU$39,20,0) -> #N/A | W29: =VLOOKUP($A29,[16]HISTOJANV22!$A$6:$AU$39,27,0) -> #N/A | X29: =VLOOKUP($A29,[16]HISTOJANV22!$A$6:$AU$39,33,0) -> #N/A | AA29: =VLOOKUP($A29,[16]HISTOJANV22!$A$6:$AU$39,43,0) -> #N/A | AB29: =VLOOKUP($A29,[16]HISTOJANV22!$A$6:$AU$39,44,0) -> #N/A | AC29: =VLOOKUP($A29,[16]HISTOJANV22!$A$6:$AU$39,47,0) -> #N/A | AD29: =VLOOKUP(A29,[16]HISTOJANV22!$A$6:$BB$36,54,0) -> #N/A
A30: AS201653 | B30: =VLOOKUP(A30,[15]LISTADHERENT!$A$5:$J$50,3,0) -> SIME BRICE | C30: =#REF! -> #REF! | D30: =#REF! -> #REF! | F30: =C30+D30-E30+K30 -> #REF! | G30: =$S$40/$H$40*H30 -> #REF! | H30: =F30+D30+K30 -> #REF! | I30: =VLOOKUP($A30,[16]HISTOJANV22!$A$6:$AQ$37,22,0) -> 0 | J30: =VLOOKUP($A30,[16]HISTOJANV22!$A$6:$AU$39,45,0) -> 7000 | K30: =IF(J30=0,0,J30-(L30+M30+N30)) -> 3000 | L30: =IF(J30=0,0,500) -> 500 | M30: =IF(J30=0,0,1000) -> 1000 | N30: =IF(J30=0,0,2500) -> 2500 | O30: =VLOOKUP($A30,[16]HISTOJANV22!$A$6:$AU$39,7,0) -> 0 | P30: =VLOOKUP($A30,[16]HISTOJANV22!$A$6:$AU$39,23,0) -> 0 | Q30: =VLOOKUP($A30,[16]HISTOJANV22!$A$6:$AU$39,46,0) -> 0 | R30: =VLOOKUP($A30,[16]HISTODEC21!$A$6:$AU$39,26,0) -> #REF! | S30: =R30*12/1200*12 -> #REF! | T30: =VLOOKUP($A30,[16]HISTOJANV22!$A$6:$AU$39,28,0) -> 0 | U30: =VLOOKUP($A30,[16]HISTOJANV22!$A$6:$AU$39,19,0) -> 0 | V30: =VLOOKUP($A30,[16]HISTOJANV22!$A$6:$AU$39,20,0) -> 0 | W30: =VLOOKUP($A30,[16]HISTOJANV22!$A$6:$AU$39,27,0) -> 0 | X30: =VLOOKUP($A30,[16]HISTOJANV22!$A$6:$AU$39,33,0) -> 0 | AA30: =VLOOKUP($A30,[16]HISTOJANV22!$A$6:$AU$39,43,0) -> 0 | AB30: =VLOOKUP($A30,[16]HISTOJANV22!$A$6:$AU$39,44,0) -> 0 | AC30: =VLOOKUP($A30,[16]HISTOJANV22!$A$6:$AU$39,47,0) -> 0 | AD30: =VLOOKUP(A30,[16]HISTOJANV22!$A$6:$BB$36,54,0) -> 0
A31: AS201638 | B31: =VLOOKUP(A31,[15]LISTADHERENT!$A$5:$J$50,3,0) -> SIMO PIERRE | C31: =#REF! -> #REF! | D31: =#REF! -> #REF! | F31: =C31+D31-E31+K31 -> #REF! | G31: =$S$40/$H$40*H31 -> #REF! | H31: =F31+D31+K31 -> #REF! | I31: =VLOOKUP($A31,[16]HISTOJANV22!$A$6:$AQ$37,22,0) -> 0 | J31: =VLOOKUP($A31,[16]HISTOJANV22!$A$6:$AU$39,45,0) -> 22000 | K31: =IF(J31=0,0,J31-(L31+M31+N31)) -> 18000 | L31: =IF(J31=0,0,500) -> 500 | M31: =IF(J31=0,0,1000) -> 1000 | N31: =IF(J31=0,0,2500) -> 2500 | O31: =VLOOKUP($A31,[16]HISTOJANV22!$A$6:$AU$39,7,0) -> 0 | P31: =VLOOKUP($A31,[16]HISTOJANV22!$A$6:$AU$39,23,0) -> 0 | Q31: =VLOOKUP($A31,[16]HISTOJANV22!$A$6:$AU$39,46,0) -> 0 | R31: =VLOOKUP($A31,[16]HISTODEC21!$A$6:$AU$39,26,0) -> #REF! | S31: =R31*12/1200*12 -> #REF! | T31: =VLOOKUP($A31,[16]HISTOJANV22!$A$6:$AU$39,28,0) -> 0 | U31: =VLOOKUP($A31,[16]HISTOJANV22!$A$6:$AU$39,19,0) -> 0 | V31: =VLOOKUP($A31,[16]HISTOJANV22!$A$6:$AU$39,20,0) -> 0 | W31: =VLOOKUP($A31,[16]HISTOJANV22!$A$6:$AU$39,27,0) -> BANQUE | X31: =VLOOKUP($A31,[16]HISTOJANV22!$A$6:$AU$39,33,0) -> 0 | AA31: =VLOOKUP($A31,[16]HISTOJANV22!$A$6:$AU$39,43,0) -> 0 | AB31: =VLOOKUP($A31,[16]HISTOJANV22!$A$6:$AU$39,44,0) -> 0 | AC31: =VLOOKUP($A31,[16]HISTOJANV22!$A$6:$AU$39,47,0) -> 0 | AD31: =VLOOKUP(A31,[16]HISTOJANV22!$A$6:$BB$36,54,0) -> 70000
A32: AS201641 | B32: =VLOOKUP(A32,[15]LISTADHERENT!$A$5:$J$50,3,0) -> TCHOUAMOU MATHIEU | C32: =#REF! -> #REF! | D32: =#REF! -> #REF! | F32: =C32+D32-E32+K32 -> #REF! | G32: =$S$40/$H$40*H32 -> #REF! | H32: =F32+D32+K32 -> #REF! | I32: =VLOOKUP($A32,[16]HISTOJANV22!$A$6:$AQ$37,22,0) -> 0 | J32: =VLOOKUP($A32,[16]HISTOJANV22!$A$6:$AU$39,45,0) -> 7000 | K32: =IF(J32=0,0,J32-(L32+M32+N32)) -> 3000 | L32: =IF(J32=0,0,500) -> 500 | M32: =IF(J32=0,0,1000) -> 1000 | N32: =IF(J32=0,0,2500) -> 2500 | O32: =VLOOKUP($A32,[16]HISTOJANV22!$A$6:$AU$39,7,0) -> 0 | P32: =VLOOKUP($A32,[16]HISTOJANV22!$A$6:$AU$39,23,0) -> 0 | Q32: =VLOOKUP($A32,[16]HISTOJANV22!$A$6:$AU$39,46,0) -> 0 | R32: =VLOOKUP($A32,[16]HISTODEC21!$A$6:$AU$39,26,0) -> 560000 | S32: =R32*12/1200*12 -> 67200 | T32: =VLOOKUP($A32,[16]HISTOJANV22!$A$6:$AU$39,28,0) -> OKK | U32: =VLOOKUP($A32,[16]HISTOJANV22!$A$6:$AU$39,19,0) -> 0 | V32: =VLOOKUP($A32,[16]HISTOJANV22!$A$6:$AU$39,20,0) -> 0 | W32: =VLOOKUP($A32,[16]HISTOJANV22!$A$6:$AU$39,27,0) -> BANQUE | X32: =VLOOKUP($A32,[16]HISTOJANV22!$A$6:$AU$39,33,0) -> 0 | AA32: =VLOOKUP($A32,[16]HISTOJANV22!$A$6:$AU$39,43,0) -> 0 | AB32: =VLOOKUP($A32,[16]HISTOJANV22!$A$6:$AU$39,44,0) -> 0 | AC32: =VLOOKUP($A32,[16]HISTOJANV22!$A$6:$AU$39,47,0) -> 0 | AD32: =VLOOKUP(A32,[16]HISTOJANV22!$A$6:$BB$36,54,0) -> 0
A33: AS201643 | B33: =VLOOKUP(A33,[15]LISTADHERENT!$A$5:$J$50,3,0) -> TCHOUTOU NANA CLAUDE | C33: =#REF! -> #REF! | D33: =#REF! -> #REF! | F33: =C33+D33-E33+K33 -> #REF! | G33: =$S$40/$H$40*H33 -> #REF! | H33: =F33+D33+K33 -> #REF! | I33: =VLOOKUP($A33,[16]HISTOJANV22!$A$6:$AQ$37,22,0) -> #N/A | J33: =VLOOKUP($A33,[16]HISTOJANV22!$A$6:$AU$39,45,0) -> #N/A | K33: =IF(J33=0,0,J33-(L33+M33+N33)) -> #N/A | L33: =IF(J33=0,0,500) -> #N/A | M33: =IF(J33=0,0,1000) -> #N/A | N33: =IF(J33=0,0,2500) -> #N/A | O33: =VLOOKUP($A33,[16]HISTOJANV22!$A$6:$AU$39,7,0) -> #N/A | P33: =VLOOKUP($A33,[16]HISTOJANV22!$A$6:$AU$39,23,0) -> #N/A | Q33: =VLOOKUP($A33,[16]HISTOJANV22!$A$6:$AU$39,46,0) -> #N/A | R33: =VLOOKUP($A33,[16]HISTODEC21!$A$6:$AU$39,26,0) -> #N/A | S33: =R33*12/1200*12 -> #N/A | T33: =VLOOKUP($A33,[16]HISTOJANV22!$A$6:$AU$39,28,0) -> #N/A | U33: =VLOOKUP($A33,[16]HISTOJANV22!$A$6:$AU$39,19,0) -> #N/A | V33: =VLOOKUP($A33,[16]HISTOJANV22!$A$6:$AU$39,20,0) -> #N/A | W33: =VLOOKUP($A33,[16]HISTOJANV22!$A$6:$AU$39,27,0) -> #N/A | X33: =VLOOKUP($A33,[16]HISTOJANV22!$A$6:$AU$39,33,0) -> #N/A | AA33: =VLOOKUP($A33,[16]HISTOJANV22!$A$6:$AU$39,43,0) -> #N/A | AB33: =VLOOKUP($A33,[16]HISTOJANV22!$A$6:$AU$39,44,0) -> #N/A | AC33: =VLOOKUP($A33,[16]HISTOJANV22!$A$6:$AU$39,47,0) -> #N/A | AD33: =VLOOKUP(A33,[16]HISTOJANV22!$A$6:$BB$36,54,0) -> #N/A
A34: AS201658 | B34: =VLOOKUP(A34,[15]LISTADHERENT!$A$5:$J$50,3,0) -> YANTCHOU GERVAIS | C34: =#REF! -> #REF! | D34: =#REF! -> #REF! | F34: =C34+D34-E34+K34 -> #REF! | G34: =$S$40/$H$40*H34 -> #REF! | H34: =F34+D34+K34 -> #REF! | I34: =VLOOKUP($A34,[16]HISTOJANV22!$A$6:$AQ$37,22,0) -> #N/A | J34: =VLOOKUP($A34,[16]HISTOJANV22!$A$6:$AU$39,45,0) -> #N/A | K34: =IF(J34=0,0,J34-(L34+M34+N34)) -> #N/A | L34: =IF(J34=0,0,500) -> #N/A | M34: =IF(J34=0,0,1000) -> #N/A | N34: =IF(J34=0,0,2500) -> #N/A | O34: =VLOOKUP($A34,[16]HISTOJANV22!$A$6:$AU$39,7,0) -> #N/A | P34: =VLOOKUP($A34,[16]HISTOJANV22!$A$6:$AU$39,23,0) -> #N/A | Q34: =VLOOKUP($A34,[16]HISTOJANV22!$A$6:$AU$39,46,0) -> #N/A | R34: =VLOOKUP($A34,[16]HISTODEC21!$A$6:$AU$39,26,0) -> #N/A | S34: =R34*12/1200*12 -> #N/A | T34: =VLOOKUP($A34,[16]HISTOJANV22!$A$6:$AU$39,28,0) -> #N/A | U34: =VLOOKUP($A34,[16]HISTOJANV22!$A$6:$AU$39,19,0) -> #N/A | V34: =VLOOKUP($A34,[16]HISTOJANV22!$A$6:$AU$39,20,0) -> #N/A | W34: =VLOOKUP($A34,[16]HISTOJANV22!$A$6:$AU$39,27,0) -> #N/A | X34: =VLOOKUP($A34,[16]HISTOJANV22!$A$6:$AU$39,33,0) -> #N/A | AA34: =VLOOKUP($A34,[16]HISTOJANV22!$A$6:$AU$39,43,0) -> #N/A | AB34: =VLOOKUP($A34,[16]HISTOJANV22!$A$6:$AU$39,44,0) -> #N/A | AC34: =VLOOKUP($A34,[16]HISTOJANV22!$A$6:$AU$39,47,0) -> #N/A | AD34: =VLOOKUP(A34,[16]HISTOJANV22!$A$6:$BB$36,54,0) -> #N/A
A35: AS201646 | B35: =VLOOKUP(A35,[15]LISTADHERENT!$A$5:$J$50,3,0) -> YEPMOU JEAN JACQUES | C35: =#REF! -> #REF! | D35: =#REF! -> #REF! | F35: =C35+D35-E35+K35 -> #REF! | G35: =$S$40/$H$40*H35 -> #REF! | H35: =F35+D35+K35 -> #REF! | I35: =VLOOKUP($A35,[16]HISTOJANV22!$A$6:$AQ$37,22,0) -> 0 | J35: =VLOOKUP($A35,[16]HISTOJANV22!$A$6:$AU$39,45,0) -> 7000 | K35: =IF(J35=0,0,J35-(L35+M35+N35)) -> 3000 | L35: =IF(J35=0,0,500) -> 500 | M35: =IF(J35=0,0,1000) -> 1000 | N35: =IF(J35=0,0,2500) -> 2500 | O35: =VLOOKUP($A35,[16]HISTOJANV22!$A$6:$AU$39,7,0) -> 3000 | P35: =VLOOKUP($A35,[16]HISTOJANV22!$A$6:$AU$39,23,0) -> 0 | Q35: =VLOOKUP($A35,[16]HISTOJANV22!$A$6:$AU$39,46,0) -> 0 | R35: =VLOOKUP($A35,[16]HISTODEC21!$A$6:$AU$39,26,0) -> 1155000 | S35: =R35*0/1200*12 -> 0 | T35: =VLOOKUP($A35,[16]HISTOJANV22!$A$6:$AU$39,28,0) -> 0 | U35: =VLOOKUP($A35,[16]HISTOJANV22!$A$6:$AU$39,19,0) -> 0 | V35: =VLOOKUP($A35,[16]HISTOJANV22!$A$6:$AU$39,20,0) -> 0 | W35: =VLOOKUP($A35,[16]HISTOJANV22!$A$6:$AU$39,27,0) -> BANQUE | X35: =VLOOKUP($A35,[16]HISTOJANV22!$A$6:$AU$39,33,0) -> 0 | Y35: 155000 | AA35: =VLOOKUP($A35,[16]HISTOJANV22!$A$6:$AU$39,43,0) -> 0 | AB35: =VLOOKUP($A35,[16]HISTOJANV22!$A$6:$AU$39,44,0) -> 0 | AC35: =VLOOKUP($A35,[16]HISTOJANV22!$A$6:$AU$39,47,0) -> 0 | AD35: =VLOOKUP(A35,[16]HISTOJANV22!$A$6:$BB$36,54,0) -> 0
A36: AS201647 | B36: =VLOOKUP(A36,[15]LISTADHERENT!$A$5:$J$50,3,0) -> YOUMBI EMMANUEL | C36: =#REF! -> #REF! | D36: =#REF! -> #REF! | F36: =C36+D36-E36+K36 -> #REF! | G36: =$S$40/$H$40*H36 -> #REF! | H36: =F36+D36+K36 -> #REF! | I36: =VLOOKUP($A36,[16]HISTOJANV22!$A$6:$AQ$37,22,0) -> 0 | J36: =VLOOKUP($A36,[16]HISTOJANV22!$A$6:$AU$39,45,0) -> 7000 | K36: =IF(J36=0,0,J36-(L36+M36+N36)) -> 3000 | L36: =IF(J36=0,0,500) -> 500 | M36: =IF(J36=0,0,1000) -> 1000 | N36: =IF(J36=0,0,2500) -> 2500 | O36: =VLOOKUP($A36,[16]HISTOJANV22!$A$6:$AU$39,7,0) -> 0 | P36: =VLOOKUP($A36,[16]HISTOJANV22!$A$6:$AU$39,23,0) -> 0 | Q36: =VLOOKUP($A36,[16]HISTOJANV22!$A$6:$AU$39,46,0) -> 0 | R36: =VLOOKUP($A36,[16]HISTODEC21!$A$6:$AU$39,26,0) -> #REF! | S36: =R36*12/1200*12 -> #REF! | T36: =VLOOKUP($A36,[16]HISTOJANV22!$A$6:$AU$39,28,0) -> 0 | U36: =VLOOKUP($A36,[16]HISTOJANV22!$A$6:$AU$39,19,0) -> 0 | V36: =VLOOKUP($A36,[16]HISTOJANV22!$A$6:$AU$39,20,0) -> 0 | W36: =VLOOKUP($A36,[16]HISTOJANV22!$A$6:$AU$39,27,0) -> 0 | X36: =VLOOKUP($A36,[16]HISTOJANV22!$A$6:$AU$39,33,0) -> 0 | AA36: =VLOOKUP($A36,[16]HISTOJANV22!$A$6:$AU$39,43,0) -> 0 | AB36: =VLOOKUP($A36,[16]HISTOJANV22!$A$6:$AU$39,44,0) -> 0 | AC36: =VLOOKUP($A36,[16]HISTOJANV22!$A$6:$AU$39,47,0) -> 0 | AD36: =VLOOKUP(A36,[16]HISTOJANV22!$A$6:$BB$36,54,0) -> 70000
A40: TOTAL | C40: =SUM(C6:C39) -> #REF! | D40: =SUM(D6:D39) -> #REF! | E40: =SUM(E6:E39) -> 0 | F40: =SUM(F6:F39) -> #REF! | G40: =SUM(G6:G39) -> #REF! | H40: =SUM(H6:H39) -> #REF! | I40: =SUM(I6:I39) -> #N/A | J40: =SUM(J6:J39) -> #N/A | ... AE40: =SUM(AE6:AE39) -> 0

Sheet Sheet5
A1: ASSOCIATION | B1: ASELBY | G1: K
A2: ANNEE | B2: 2022
A3: TONTINE
J4: 44912
A5: MATRICULE | B5: NOM ET PRENOM | C5: FONDES DE DEPART | D5: RELIQUAT | E5: RETRAIT PARTIEL | F5: FONDS DEFINITIF | G5: REPARTITION INTERET | H5: CAPITAL COMPOSE | I5: SANCTION | J5: RESTE | K5: EPARGNE | L5: FONDS DE ROULEMENT | M5: FRAIS EXCEPTIONNEL | N5: COLLATION | O5: PENALITE VST ESPECES | P5: INSCRISPTION | Q5: MUTUELLE | R5: PRÊT FONDS | S5: INTERETPRET FONDS | T5: NUMERO CHEQUE | U5: REMBOURSEMENTPRET FONDS | V5: MODE VERSEMENT REMBOURSEMENT | W5: MODE VERSEMENT PRÊT | X5: NUMERO CHEQUE | Y5: PENALITE PRET FONDS | Z5: PENALITE FONDS | AA5: PENALITE ECHEC TONTINE | AB5: PENALITE RETARD TONTINE | AC5: REMBOURSEMENT TRANSPORT | AD5: CONTRIBUTION FOYER | AE5: FONDS DE ROULEMENT | AF5: FRAIS EXCEPTIONNEL | AG5: FONDS MUTUELLE | AH5: COLLATION RECEPTION | AI5: PENALITE PRET FONDS | AJ5: DEPENSE PENALITE VERSEMENT BANQUE
A6: AS201648 | B6: =VLOOKUP(A6,[15]LISTADHERENT!$A$5:$J$45,3,0) -> ASELBY | C6: 0 | D6: =VLOOKUP(A6,'[17]EPARGNE 2023'!$A$5:$BF$47,4,0) -> 816543.52 | F6: =C6+D6-E6 -> 816543.52 | G6: 51868.55 | H6: =+F6+G6 -> 868412.07 | AE6: =VLOOKUP($A6,[16]HISTODEC22!$A$6:$CA$36,60,0) -> 6000 | AF6: =VLOOKUP($A6,[16]HISTODEC22!$A$6:$CA$36,61,0) -> 0 | AG6: =VLOOKUP($A6,[16]HISTODEC22!$A$6:$CA$36,62,0) -> 0 | AH6: =VLOOKUP($A6,[16]HISTODEC22!$A$6:$CA$36,63,0) -> 0 | AI6: =VLOOKUP($A6,[16]HISTODEC22!$A$6:$CA$36,64,0) -> 0 | AJ6: =VLOOKUP($A6,[16]HISTODEC22!$A$6:$CA$36,65,0) -> 0
A7: AS201601 | B7: =VLOOKUP(A7,[15]LISTADHERENT!$A$5:$J$45,3,0) -> BAKOP ACHILLE | C7: 0 | D7: =VLOOKUP(A7,'[17]EPARGNE 2023'!$A$5:$BF$47,4,0) -> 0 | F7: =C7+D7-E7 -> 0 | G7: 0 | H7: =+F7+G7 -> 0
A8: AS201602 | B8: =VLOOKUP(A8,[15]LISTADHERENT!$A$5:$J$45,3,0) -> BOUTCHOUANG WILLIAM | C8: 600000 | D8: =VLOOKUP(A8,'[17]EPARGNE 2023'!$A$5:$BF$47,4,0) -> 7023.6611 | F8: =C8+D8-E8 -> 607023.66 | G8: 38559.411 | H8: =+F8+G8 -> 645583.07 | I8: =VLOOKUP($A8,[16]HISTODEC22!$A$6:$AQ$37,22,0) -> 0 | J8: =VLOOKUP($A8,[16]HISTODEC22!$A$6:$AU$39,45,0) -> 7000 | L8: =IF(J8=0,0,500) -> 500 | M8: =IF(J8=0,0,1000) -> 1000 | N8: =IF(J8=0,0,2500) -> 2500 | O8: =VLOOKUP($A8,[16]HISTODEC22!$A$6:$AU$39,7,0) -> 0 | P8: =VLOOKUP($A8,[16]HISTODEC22!$A$6:$AU$39,23,0) -> 0 | Q8: =VLOOKUP($A8,[16]HISTODEC22!$A$6:$AU$39,46,0) -> 0 | R8: =VLOOKUP($A8,[18]HISTODEC22!$A$6:$AU$39,26,0) -> 500000 | S8: =VLOOKUP($A8,[18]HISTODEC22!$A$6:$BG$39,58,0) -> 10000 | T8: =VLOOKUP($A8,[16]HISTODEC22!$A$6:$AU$39,28,0) -> 0 | U8: =VLOOKUP($A8,[16]HISTODEC22!$A$6:$AU$39,19,0) -> 0 | V8: =VLOOKUP($A8,[16]HISTODEC22!$A$6:$AU$39,20,0) -> 0 | W8: =VLOOKUP($A8,[16]HISTODEC22!$A$6:$AU$39,27,0) -> BANQUE | X8: =VLOOKUP($A8,[16]HISTODEC22!$A$6:$AU$39,33,0) -> 0 | Y8: =VLOOKUP($A8,[16]HISTODEC22!$A$6:$BP$39,65,0) -> 0 | AA8: =VLOOKUP($A8,[16]HISTODEC22!$A$6:$AU$39,43,0) -> 0 | AB8: =VLOOKUP($A8,[16]HISTODEC22!$A$6:$AU$39,44,0) -> 0 | AC8: =VLOOKUP($A8,[16]HISTODEC22!$A$6:$AU$39,47,0) -> 0 | AD8: =VLOOKUP(A8,[16]HISTODEC22!$A$6:$BB$36,54,0) -> 0 | AE8: =VLOOKUP($A8,[16]HISTODEC22!$A$6:$CA$36,60,0) -> 0 | AF8: =VLOOKUP($A8,[16]HISTODEC22!$A$6:$CA$36,61,0) -> 0 | AG8: =VLOOKUP($A8,[16]HISTODEC22!$A$6:$CA$36,62,0) -> 0 | AH8: =VLOOKUP($A8,[16]HISTODEC22!$A$6:$CA$36,63,0) -> 0 | AI8: =VLOOKUP($A8,[16]HISTODEC22!$A$6:$CA$36,64,0) -> 0 | AJ8: =VLOOKUP($A8,[16]HISTODEC22!$A$6:$CA$36,65,0) -> 0
A9: AS201604 | B9: =VLOOKUP(A9,[15]LISTADHERENT!$A$5:$J$45,3,0) -> DJOMO JEAN PAUL | C9: 600000 | D9: =VLOOKUP(A9,'[17]EPARGNE 2023'!$A$5:$BF$47,4,0) -> 4809.807 | F9: =C9+D9-E9 -> 604809.81 | G9: 38418.782 | H9: =+F9+G9 -> 643228.59 | I9: =VLOOKUP($A9,[16]HISTODEC22!$A$6:$AQ$37,22,0) -> 0 | J9: =VLOOKUP($A9,[16]HISTODEC22!$A$6:$AU$39,45,0) -> 7000 | L9: =IF(J9=0,0,500) -> 500 | M9: =IF(J9=0,0,1000) -> 1000 | N9: =IF(J9=0,0,2500) -> 2500 | O9: =VLOOKUP($A9,[16]HISTODEC22!$A$6:$AU$39,7,0) -> 0 | P9: =VLOOKUP($A9,[16]HISTODEC22!$A$6:$AU$39,23,0) -> 0 | Q9: =VLOOKUP($A9,[16]HISTODEC22!$A$6:$AU$39,46,0) -> 0 | R9: =VLOOKUP($A9,[18]HISTODEC22!$A$6:$AU$39,26,0) -> 1000000 | S9: =VLOOKUP($A9,[18]HISTODEC22!$A$6:$BG$39,58,0) -> 120000 | T9: =VLOOKUP($A9,[16]HISTODEC22!$A$6:$AU$39,28,0) -> 0 | U9: =VLOOKUP($A9,[16]HISTODEC22!$A$6:$AU$39,19,0) -> 1000000 | V9: =VLOOKUP($A9,[16]HISTODEC22!$A$6:$AU$39,20,0) -> BANQUE | W9: =VLOOKUP($A9,[16]HISTODEC22!$A$6:$AU$39,27,0) -> BANQUE | X9: =VLOOKUP($A9,[16]HISTODEC22!$A$6:$AU$39,33,0) -> 0 | Y9: =VLOOKUP($A9,[16]HISTODEC22!$A$6:$BP$39,65,0) -> 0 | AA9: =VLOOKUP($A9,[16]HISTODEC22!$A$6:$AU$39,43,0) -> 0 | AB9: =VLOOKUP($A9,[16]HISTODEC22!$A$6:$AU$39,44,0) -> 0 | AC9: =VLOOKUP($A9,[16]HISTODEC22!$A$6:$AU$39,47,0) -> 0 | AD9: =VLOOKUP(A9,[16]HISTODEC22!$A$6:$BB$36,54,0) -> 0 | AE9: =VLOOKUP($A9,[16]HISTODEC22!$A$6:$CA$36,60,0) -> 0 | AF9: =VLOOKUP($A9,[16]HISTODEC22!$A$6:$CA$36,61,0) -> 0 | AG9: =VLOOKUP($A9,[16]HISTODEC22!$A$6:$CA$36,62,0) -> 0 | AH9: =VLOOKUP($A9,[16]HISTODEC22!$A$6:$CA$36,63,0) -> 0 | AI9: =VLOOKUP($A9,[16]HISTODEC22!$A$6:$CA$36,64,0) -> 0 | AJ9: =VLOOKUP($A9,[16]HISTODEC22!$A$6:$CA$36,65,0) -> 0
A10: AS201654 | B10: =VLOOKUP(A10,[15]LISTADHERENT!$A$5:$J$45,3,0) -> DJOMOU TCHAPDA | C10: 600000 | D10: =VLOOKUP(A10,'[17]EPARGNE 2023'!$A$5:$BF$47,4,0) -> 48710.412 | F10: =C10+D10-E10 -> 648710.41 | G10: 41207.44 | H10: =+F10+G10 -> 689917.85 | I10: =VLOOKUP($A10,[16]HISTODEC22!$A$6:$AQ$37,22,0) -> 0 | J10: =VLOOKUP($A10,[16]HISTODEC22!$A$6:$AU$39,45,0) -> 7000 | L10: =IF(J10=0,0,500) -> 500 | M10: =IF(J10=0,0,1000) -> 1000 | N10: =IF(J10=0,0,2500) -> 2500 | O10: =VLOOKUP($A10,[16]HISTODEC22!$A$6:$AU$39,7,0) -> 0 | P10: =VLOOKUP($A10,[16]HISTODEC22!$A$6:$AU$39,23,0) -> 0 | Q10: =VLOOKUP($A10,[16]HISTODEC22!$A$6:$AU$39,46,0) -> 0 | R10: =VLOOKUP($A10,[18]HISTODEC22!$A$6:$AU$39,26,0) -> 0 | S10: =VLOOKUP($A10,[18]HISTODEC22!$A$6:$BG$39,58,0) -> 0 | T10: =VLOOKUP($A10,[16]HISTODEC22!$A$6:$AU$39,28,0) -> 0 | U10: =VLOOKUP($A10,[16]HISTODEC22!$A$6:$AU$39,19,0) -> 0 | V10: =VLOOKUP($A10,[16]HISTODEC22!$A$6:$AU$39,20,0) -> 0 | W10: =VLOOKUP($A10,[16]HISTODEC22!$A$6:$AU$39,27,0) -> 0 | X10: =VLOOKUP($A10,[16]HISTODEC22!$A$6:$AU$39,33,0) -> 0 | Y10: =VLOOKUP($A10,[16]HISTODEC22!$A$6:$BP$39,65,0) -> 0 | AA10: =VLOOKUP($A10,[16]HISTODEC22!$A$6:$AU$39,43,0) -> 0 | AB10: =VLOOKUP($A10,[16]HISTODEC22!$A$6:$AU$39,44,0) -> 0 | AC10: =VLOOKUP($A10,[16]HISTODEC22!$A$6:$AU$39,47,0) -> 0 | AD10: =VLOOKUP(A10,[16]HISTODEC22!$A$6:$BB$36,54,0) -> 0 | AE10: =VLOOKUP($A10,[16]HISTODEC22!$A$6:$CA$36,60,0) -> 0 | AF10: =VLOOKUP($A10,[16]HISTODEC22!$A$6:$CA$36,61,0) -> 0 | AG10: =VLOOKUP($A10,[16]HISTODEC22!$A$6:$CA$36,62,0) -> 0 | AH10: =VLOOKUP($A10,[16]HISTODEC22!$A$6:$CA$36,63,0) -> 0 | AI10: =VLOOKUP($A10,[16]HISTODEC22!$A$6:$CA$36,64,0) -> 0 | AJ10: =VLOOKUP($A10,[16]HISTODEC22!$A$6:$CA$36,65,0) -> 0
A11: AS201605 | B11: =VLOOKUP(A11,[15]LISTADHERENT!$A$5:$J$45,3,0) -> DJOUKWE NANGUEN GUY BLAISE | C11: 600000 | D11: =VLOOKUP(A11,'[17]EPARGNE 2023'!$A$5:$BF$47,4,0) -> 4750.0783 | F11: =C11+D11-E11 -> 604750.08 | G11: 38414.988 | H11: =+F11+G11 -> 643165.07 | I11: =VLOOKUP($A11,[16]HISTODEC22!$A$6:$AQ$37,22,0) -> 0 | J11: =VLOOKUP($A11,[16]HISTODEC22!$A$6:$AU$39,45,0) -> 7000 | L11: =IF(J11=0,0,500) -> 500 | M11: =IF(J11=0,0,1000) -> 1000 | N11: =IF(J11=0,0,2500) -> 2500 | O11: =VLOOKUP($A11,[16]HISTODEC22!$A$6:$AU$39,7,0) -> 0 | P11: =VLOOKUP($A11,[16]HISTODEC22!$A$6:$AU$39,23,0) -> 0 | Q11: =VLOOKUP($A11,[16]HISTODEC22!$A$6:$AU$39,46,0) -> 0 | R11: =VLOOKUP($A11,[18]HISTODEC22!$A$6:$AU$39,26,0) -> 1000000 | S11: =VLOOKUP($A11,[18]HISTODEC22!$A$6:$BG$39,58,0) -> 40000 | T11: =VLOOKUP($A11,[16]HISTODEC22!$A$6:$AU$39,28,0) -> 0 | U11: =VLOOKUP($A11,[16]HISTODEC22!$A$6:$AU$39,19,0) -> 1000000 | V11: =VLOOKUP($A11,[16]HISTODEC22!$A$6:$AU$39,20,0) -> BANQUE | W11: =VLOOKUP($A11,[16]HISTODEC22!$A$6:$AU$39,27,0) -> BANQUE | X11: =VLOOKUP($A11,[16]HISTODEC22!$A$6:$AU$39,33,0) -> 0 | Y11: =VLOOKUP($A11,[16]HISTODEC22!$A$6:$BP$39,65,0) -> 0 | AA11: =VLOOKUP($A11,[16]HISTODEC22!$A$6:$AU$39,43,0) -> 0 | AB11: =VLOOKUP($A11,[16]HISTODEC22!$A$6:$AU$39,44,0) -> 0 | AC11: =VLOOKUP($A11,[16]HISTODEC22!$A$6:$AU$39,47,0) -> 0 | AD11: =VLOOKUP(A11,[16]HISTODEC22!$A$6:$BB$36,54,0) -> 0 | AE11: =VLOOKUP($A11,[16]HISTODEC22!$A$6:$CA$36,60,0) -> 0 | AF11: =VLOOKUP($A11,[16]HISTODEC22!$A$6:$CA$36,61,0) -> 0 | AG11: =VLOOKUP($A11,[16]HISTODEC22!$A$6:$CA$36,62,0) -> 0 | AH11: =VLOOKUP($A11,[16]HISTODEC22!$A$6:$CA$36,63,0) -> 0 | AI11: =VLOOKUP($A11,[16]HISTODEC22!$A$6:$CA$36,64,0) -> 0 | AJ11: =VLOOKUP($A11,[16]HISTODEC22!$A$6:$CA$36,65,0) -> 0
A12: AS201608 | B12: =VLOOKUP(A12,[15]LISTADHERENT!$A$5:$J$45,3,0) -> DJUOMBESSY ANTOINE | C12: 600000 | D12: =VLOOKUP(A12,'[17]EPARGNE 2023'!$A$5:$BF$47,4,0) -> 10718.85 | F12: =C12+D12-E12 -> 610718.85 | G12: 38794.137 | H12: =+F12+G12 -> 649512.99 | I12: =VLOOKUP($A12,[16]HISTODEC22!$A$6:$AQ$37,22,0) -> 0 | J12: =VLOOKUP($A12,[16]HISTODEC22!$A$6:$AU$39,45,0) -> 8000 | L12: =IF(J12=0,0,500) -> 500 | M12: =IF(J12=0,0,1000) -> 1000 | N12: =IF(J12=0,0,2500) -> 2500 | O12: =VLOOKUP($A12,[16]HISTODEC22!$A$6:$AU$39,7,0) -> 0 | P12: =VLOOKUP($A12,[16]HISTODEC22!$A$6:$AU$39,23,0) -> 0 | Q12: =VLOOKUP($A12,[16]HISTODEC22!$A$6:$AU$39,46,0) -> 0 | R12: =VLOOKUP($A12,[18]HISTODEC22!$A$6:$AU$39,26,0) -> 1000000 | S12: =VLOOKUP($A12,[18]HISTODEC22!$A$6:$BG$39,58,0) -> 60000 | T12: =VLOOKUP($A12,[16]HISTODEC22!$A$6:$AU$39,28,0) -> 0 | U12: =VLOOKUP($A12,[16]HISTODEC22!$A$6:$AU$39,19,0) -> 0 | V12: =VLOOKUP($A12,[16]HISTODEC22!$A$6:$AU$39,20,0) -> 0 | W12: =VLOOKUP($A12,[16]HISTODEC22!$A$6:$AU$39,27,0) -> BANQUE | X12: =VLOOKUP($A12,[16]HISTODEC22!$A$6:$AU$39,33,0) -> 0 | Y12: =VLOOKUP($A12,[16]HISTODEC22!$A$6:$BP$39,65,0) -> 0 | AA12: =VLOOKUP($A12,[16]HISTODEC22!$A$6:$AU$39,43,0) -> 0 | AB12: =VLOOKUP($A12,[16]HISTODEC22!$A$6:$AU$39,44,0) -> 0 | AC12: =VLOOKUP($A12,[16]HISTODEC22!$A$6:$AU$39,47,0) -> 0 | AD12: =VLOOKUP(A12,[16]HISTODEC22!$A$6:$BB$36,54,0) -> 9000 | AE12: =VLOOKUP($A12,[16]HISTODEC22!$A$6:$CA$36,60,0) -> 0 | AF12: =VLOOKUP($A12,[16]HISTODEC22!$A$6:$CA$36,61,0) -> 0 | AG12: =VLOOKUP($A12,[16]HISTODEC22!$A$6:$CA$36,62,0) -> 0 | AH12: =VLOOKUP($A12,[16]HISTODEC22!$A$6:$CA$36,63,0) -> 0 | AI12: =VLOOKUP($A12,[16]HISTODEC22!$A$6:$CA$36,64,0) -> 0 | AJ12: =VLOOKUP($A12,[16]HISTODEC22!$A$6:$CA$36,65,0) -> 0
A13: AS201651 | B13: =VLOOKUP(A13,[15]LISTADHERENT!$A$5:$J$45,3,0) -> DOMOU FABIEN | C13: 600000 | D13: =VLOOKUP(A13,'[17]EPARGNE 2023'!$A$5:$BF$47,4,0) -> 584.046 | F13: =C13+D13-E13 -> 600584.05 | G13: 38150.353 | H13: =+F13+G13 -> 638734.4 | I13: =VLOOKUP($A13,[16]HISTODEC22!$A$6:$AQ$37,22,0) -> 0 | J13: =VLOOKUP($A13,[16]HISTODEC22!$A$6:$AU$39,45,0) -> 12000 | L13: =IF(J13=0,0,500) -> 500 | M13: =IF(J13=0,0,1000) -> 1000 | N13: =IF(J13=0,0,2500) -> 2500 | O13: =VLOOKUP($A13,[16]HISTODEC22!$A$6:$AU$39,7,0) -> 0 | P13: =VLOOKUP($A13,[16]HISTODEC22!$A$6:$AU$39,23,0) -> 0 | Q13: =VLOOKUP($A13,[16]HISTODEC22!$A$6:$AU$39,46,0) -> 0 | R13: =VLOOKUP($A13,[18]HISTODEC22!$A$6:$AU$39,26,0) -> 1000000 | S13: =VLOOKUP($A13,[18]HISTODEC22!$A$6:$BG$39,58,0) -> 120000 | T13: =VLOOKUP($A13,[16]HISTODEC22!$A$6:$AU$39,28,0) -> 0 | U13: =VLOOKUP($A13,[16]HISTODEC22!$A$6:$AU$39,19,0) -> 1000000 | V13: =VLOOKUP($A13,[16]HISTODEC22!$A$6:$AU$39,20,0) -> BANQUE | W13: =VLOOKUP($A13,[16]HISTODEC22!$A$6:$AU$39,27,0) -> BANQUE | X13: =VLOOKUP($A13,[16]HISTODEC22!$A$6:$AU$39,33,0) -> 0 | Y13: =VLOOKUP($A13,[16]HISTODEC22!$A$6:$BP$39,65,0) -> 0 | AA13: =VLOOKUP($A13,[16]HISTODEC22!$A$6:$AU$39,43,0) -> 0 | AB13: =VLOOKUP($A13,[16]HISTODEC22!$A$6:$AU$39,44,0) -> 0 | AC13: =VLOOKUP($A13,[16]HISTODEC22!$A$6:$AU$39,47,0) -> 0 | AD13: =VLOOKUP(A13,[16]HISTODEC22!$A$6:$BB$36,54,0) -> 0 | AE13: =VLOOKUP($A13,[16]HISTODEC22!$A$6:$CA$36,60,0) -> 0 | AF13: =VLOOKUP($A13,[16]HISTODEC22!$A$6:$CA$36,61,0) -> 0 | AG13: =VLOOKUP($A13,[16]HISTODEC22!$A$6:$CA$36,62,0) -> 0 | AH13: =VLOOKUP($A13,[16]HISTODEC22!$A$6:$CA$36,63,0) -> 0 | AI13: =VLOOKUP($A13,[16]HISTODEC22!$A$6:$CA$36,64,0) -> 0 | AJ13: =VLOOKUP($A13,[16]HISTODEC22!$A$6:$CA$36,65,0) -> 0
A14: AS201609 | B14: =VLOOKUP(A14,[15]LISTADHERENT!$A$5:$J$45,3,0) -> DONHOU DAVID | C14: 600000 | D14: =VLOOKUP(A14,'[17]EPARGNE 2023'!$A$5:$BF$47,4,0) -> 458343.18 | F14: =C14+D14-E14 -> 1058343.2 | G14: 67228.169 | H14: =+F14+G14 -> 1125571.3 | I14: =VLOOKUP($A14,[16]HISTODEC22!$A$6:$AQ$37,22,0) -> 0 | J14: =VLOOKUP($A14,[16]HISTODEC22!$A$6:$AU$39,45,0) -> 12000 | L14: =IF(J14=0,0,500) -> 500 | M14: =IF(J14=0,0,1000) -> 1000 | N14: =IF(J14=0,0,2500) -> 2500 | O14: =VLOOKUP($A14,[16]HISTODEC22!$A$6:$AU$39,7,0) -> 0 | P14: =VLOOKUP($A14,[16]HISTODEC22!$A$6:$AU$39,23,0) -> 0 | Q14: =VLOOKUP($A14,[16]HISTODEC22!$A$6:$AU$39,46,0) -> 0 | R14: =VLOOKUP($A14,[18]HISTODEC22!$A$6:$AU$39,26,0) -> 0 | S14: =VLOOKUP($A14,[18]HISTODEC22!$A$6:$BG$39,58,0) -> 0 | T14: =VLOOKUP($A14,[16]HISTODEC22!$A$6:$AU$39,28,0) -> 0 | U14: =VLOOKUP($A14,[16]HISTODEC22!$A$6:$AU$39,19,0) -> 0 | V14: =VLOOKUP($A14,[16]HISTODEC22!$A$6:$AU$39,20,0) -> 0 | W14: =VLOOKUP($A14,[16]HISTODEC22!$A$6:$AU$39,27,0) -> 0 | X14: =VLOOKUP($A14,[16]HISTODEC22!$A$6:$AU$39,33,0) -> 0 | Y14: =VLOOKUP($A14,[16]HISTODEC22!$A$6:$BP$39,65,0) -> 0 | AA14: =VLOOKUP($A14,[16]HISTODEC22!$A$6:$AU$39,43,0) -> 0 | AB14: =VLOOKUP($A14,[16]HISTODEC22!$A$6:$AU$39,44,0) -> 0 | AC14: =VLOOKUP($A14,[16]HISTODEC22!$A$6:$AU$39,47,0) -> 0 | AD14: =VLOOKUP(A14,[16]HISTODEC22!$A$6:$BB$36,54,0) -> 0 | AE14: =VLOOKUP($A14,[16]HISTODEC22!$A$6:$CA$36,60,0) -> 0 | AF14: =VLOOKUP($A14,[16]HISTODEC22!$A$6:$CA$36,61,0) -> 0 | AG14: =VLOOKUP($A14,[16]HISTODEC22!$A$6:$CA$36,62,0) -> 0 | AH14: =VLOOKUP($A14,[16]HISTODEC22!$A$6:$CA$36,63,0) -> 0 | AI14: =VLOOKUP($A14,[16]HISTODEC22!$A$6:$CA$36,64,0) -> 0 | AJ14: =VLOOKUP($A14,[16]HISTODEC22!$A$6:$CA$36,65,0) -> 0
A15: AS201611 | B15: =VLOOKUP(A15,[15]LISTADHERENT!$A$5:$J$45,3,0) -> HENGUE PAUL OMER | C15: 600000 | D15: =VLOOKUP(A15,'[17]EPARGNE 2023'!$A$5:$BF$47,4,0) -> 51112.01 | F15: =C15+D15-E15 -> 651112.01 | G15: 41359.995 | H15: =+F15+G15 -> 692472.01 | I15: =VLOOKUP($A15,[16]HISTODEC22!$A$6:$AQ$37,22,0) -> 0 | J15: =VLOOKUP($A15,[16]HISTODEC22!$A$6:$AU$39,45,0) -> 7000 | L15: =IF(J15=0,0,500) -> 500 | M15: =IF(J15=0,0,1000) -> 1000 | N15: =IF(J15=0,0,2500) -> 2500 | O15: =VLOOKUP($A15,[16]HISTODEC22!$A$6:$AU$39,7,0) -> 0 | P15: =VLOOKUP($A15,[16]HISTODEC22!$A$6:$AU$39,23,0) -> 0 | Q15: =VLOOKUP($A15,[16]HISTODEC22!$A$6:$AU$39,46,0) -> 0 | R15: =VLOOKUP($A15,[18]HISTODEC22!$A$6:$AU$39,26,0) -> 0 | S15: =VLOOKUP($A15,[18]HISTODEC22!$A$6:$BG$39,58,0) -> 0 | T15: =VLOOKUP($A15,[16]HISTODEC22!$A$6:$AU$39,28,0) -> 0 | U15: =VLOOKUP($A15,[16]HISTODEC22!$A$6:$AU$39,19,0) -> 0 | V15: =VLOOKUP($A15,[16]HISTODEC22!$A$6:$AU$39,20,0) -> 0 | W15: =VLOOKUP($A15,[16]HISTODEC22!$A$6:$AU$39,27,0) -> 0 | X15: =VLOOKUP($A15,[16]HISTODEC22!$A$6:$AU$39,33,0) -> 0 | Y15: =VLOOKUP($A15,[16]HISTODEC22!$A$6:$BP$39,65,0) -> 0 | AA15: =VLOOKUP($A15,[16]HISTODEC22!$A$6:$AU$39,43,0) -> 0 | AB15: =VLOOKUP($A15,[16]HISTODEC22!$A$6:$AU$39,44,0) -> 0 | AC15: =VLOOKUP($A15,[16]HISTODEC22!$A$6:$AU$39,47,0) -> 0 | AD15: =VLOOKUP(A15,[16]HISTODEC22!$A$6:$BB$36,54,0) -> 0 | AE15: =VLOOKUP($A15,[16]HISTODEC22!$A$6:$CA$36,60,0) -> 0 | AF15: =VLOOKUP($A15,[16]HISTODEC22!$A$6:$CA$36,61,0) -> 0 | AG15: =VLOOKUP($A15,[16]HISTODEC22!$A$6:$CA$36,62,0) -> 0 | AH15: =VLOOKUP($A15,[16]HISTODEC22!$A$6:$CA$36,63,0) -> 0 | AI15: =VLOOKUP($A15,[16]HISTODEC22!$A$6:$CA$36,64,0) -> 0 | AJ15: =VLOOKUP($A15,[16]HISTODEC22!$A$6:$CA$36,65,0) -> 0
A16: AS201613 | B16: =VLOOKUP(A16,[15]LISTADHERENT!$A$5:$J$45,3,0) -> HOTCHO BENJAMIN | C16: 600000 | D16: =VLOOKUP(A16,'[17]EPARGNE 2023'!$A$5:$BF$47,4,0) -> 16229.566 | F16: =C16+D16-E16 -> 616229.57 | G16: 39144.189 | H16: =+F16+G16 -> 655373.76 | I16: =VLOOKUP($A16,[16]HISTODEC22!$A$6:$AQ$37,22,0) -> 0 | J16: =VLOOKUP($A16,[16]HISTODEC22!$A$6:$AU$39,45,0) -> 52000 | L16: =IF(J16=0,0,500) -> 500 | M16: =IF(J16=0,0,1000) -> 1000 | N16: =IF(J16=0,0,2500) -> 2500 | O16: =VLOOKUP($A16,[16]HISTODEC22!$A$6:$AU$39,7,0) -> 0 | P16: =VLOOKUP($A16,[16]HISTODEC22!$A$6:$AU$39,23,0) -> 0 | Q16: =VLOOKUP($A16,[16]HISTODEC22!$A$6:$AU$39,46,0) -> 0 | R16: =VLOOKUP($A16,[18]HISTODEC22!$A$6:$AU$39,26,0) -> 1000000 | S16: =VLOOKUP($A16,[18]HISTODEC22!$A$6:$BG$39,58,0) -> 120000 | T16: =VLOOKUP($A16,[16]HISTODEC22!$A$6:$AU$39,28,0) -> 0 | U16: =VLOOKUP($A16,[16]HISTODEC22!$A$6:$AU$39,19,0) -> 1000000 | V16: =VLOOKUP($A16,[16]HISTODEC22!$A$6:$AU$39,20,0) -> BANQUE | W16: =VLOOKUP($A16,[16]HISTODEC22!$A$6:$AU$39,27,0) -> BANQUE | X16: =VLOOKUP($A16,[16]HISTODEC22!$A$6:$AU$39,33,0) -> 0 | Y16: =VLOOKUP($A16,[16]HISTODEC22!$A$6:$BP$39,65,0) -> 0 | AA16: =VLOOKUP($A16,[16]HISTODEC22!$A$6:$AU$39,43,0) -> 0 | AB16: =VLOOKUP($A16,[16]HISTODEC22!$A$6:$AU$39,44,0) -> 0 | AC16: =VLOOKUP($A16,[16]HISTODEC22!$A$6:$AU$39,47,0) -> 0 | AD16: =VLOOKUP(A16,[16]HISTODEC22!$A$6:$BB$36,54,0) -> 0 | AE16: =VLOOKUP($A16,[16]HISTODEC22!$A$6:$CA$36,60,0) -> 0 | AF16: =VLOOKUP($A16,[16]HISTODEC22!$A$6:$CA$36,61,0) -> 0 | AG16: =VLOOKUP($A16,[16]HISTODEC22!$A$6:$CA$36,62,0) -> 0 | AH16: =VLOOKUP($A16,[16]HISTODEC22!$A$6:$CA$36,63,0) -> 0 | AI16: =VLOOKUP($A16,[16]HISTODEC22!$A$6:$CA$36,64,0) -> 0 | AJ16: =VLOOKUP($A16,[16]HISTODEC22!$A$6:$CA$36,65,0) -> 0
A17: AS201617 | B17: =VLOOKUP(A17,[15]LISTADHERENT!$A$5:$J$45,3,0) -> KOUAMOU MOISE | C17: 600000 | D17: =VLOOKUP(A17,'[17]EPARGNE 2023'!$A$5:$BF$47,4,0) -> 53292.832 | F17: =C17+D17-E17 -> 653292.83 | G17: 41498.525 | H17: =+F17+G17 -> 694791.36 | I17: =VLOOKUP($A17,[16]HISTODEC22!$A$6:$AQ$37,22,0) -> 0 | J17: =VLOOKUP($A17,[16]HISTODEC22!$A$6:$AU$39,45,0) -> 7000 | L17: =IF(J17=0,0,500) -> 500 | M17: =IF(J17=0,0,1000) -> 1000 | N17: =IF(J17=0,0,2500) -> 2500 | O17: =VLOOKUP($A17,[16]HISTODEC22!$A$6:$AU$39,7,0) -> 0 | P17: =VLOOKUP($A17,[16]HISTODEC22!$A$6:$AU$39,23,0) -> 0 | Q17: =VLOOKUP($A17,[16]HISTODEC22!$A$6:$AU$39,46,0) -> 0 | R17: =VLOOKUP($A17,[18]HISTODEC22!$A$6:$AU$39,26,0) -> 0 | S17: =VLOOKUP($A17,[18]HISTODEC22!$A$6:$BG$39,58,0) -> 0 | T17: =VLOOKUP($A17,[16]HISTODEC22!$A$6:$AU$39,28,0) -> 0 | U17: =VLOOKUP($A17,[16]HISTODEC22!$A$6:$AU$39,19,0) -> 700000 | V17: =VLOOKUP($A17,[16]HISTODEC22!$A$6:$AU$39,20,0) -> BANQUE | W17: =VLOOKUP($A17,[16]HISTODEC22!$A$6:$AU$39,27,0) -> 0 | X17: =VLOOKUP($A17,[16]HISTODEC22!$A$6:$AU$39,33,0) -> 0 | Y17: =VLOOKUP($A17,[16]HISTODEC22!$A$6:$BP$39,65,0) -> 0 | AA17: =VLOOKUP($A17,[16]HISTODEC22!$A$6:$AU$39,43,0) -> 0 | AB17: =VLOOKUP($A17,[16]HISTODEC22!$A$6:$AU$39,44,0) -> 0 | AC17: =VLOOKUP($A17,[16]HISTODEC22!$A$6:$AU$39,47,0) -> 0 | AD17: =VLOOKUP(A17,[16]HISTODEC22!$A$6:$BB$36,54,0) -> 0 | AE17: =VLOOKUP($A17,[16]HISTODEC22!$A$6:$CA$36,60,0) -> 0 | AF17: =VLOOKUP($A17,[16]HISTODEC22!$A$6:$CA$36,61,0) -> 0 | AG17: =VLOOKUP($A17,[16]HISTODEC22!$A$6:$CA$36,62,0) -> 0 | AH17: =VLOOKUP($A17,[16]HISTODEC22!$A$6:$CA$36,63,0) -> 0 | AI17: =VLOOKUP($A17,[16]HISTODEC22!$A$6:$CA$36,64,0) -> 0 | AJ17: =VLOOKUP($A17,[16]HISTODEC22!$A$6:$CA$36,65,0) -> 0
A18: AS201619 | B18: =VLOOKUP(A18,[15]LISTADHERENT!$A$5:$J$45,3,0) -> KOUATCHO MESSACK | C18: 600000 | D18: =VLOOKUP(A18,'[17]EPARGNE 2023'!$A$5:$BF$47,4,0) -> 6459.0432 | F18: =C18+D18-E18 -> 606459.04 | G18: 38523.545 | H18: =+F18+G18 -> 644982.59 | I18: =VLOOKUP($A18,[16]HISTODEC22!$A$6:$AQ$37,22,0) -> 0 | J18: =VLOOKUP($A18,[16]HISTODEC22!$A$6:$AU$39,45,0) -> 7000 | L18: =IF(J18=0,0,500) -> 500 | M18: =IF(J18=0,0,1000) -> 1000 | N18: =IF(J18=0,0,2500) -> 2500 | O18: =VLOOKUP($A18,[16]HISTODEC22!$A$6:$AU$39,7,0) -> 0 | P18: =VLOOKUP($A18,[16]HISTODEC22!$A$6:$AU$39,23,0) -> 0 | Q18: =VLOOKUP($A18,[16]HISTODEC22!$A$6:$AU$39,46,0) -> 0 | R18: =VLOOKUP($A18,[18]HISTODEC22!$A$6:$AU$39,26,0) -> 1000000 | S18: =VLOOKUP($A18,[18]HISTODEC22!$A$6:$BG$39,58,0) -> 60000 | T18: =VLOOKUP($A18,[16]HISTODEC22!$A$6:$AU$39,28,0) -> 0 | U18: =VLOOKUP($A18,[16]HISTODEC22!$A$6:$AU$39,19,0) -> 1000000 | V18: =VLOOKUP($A18,[16]HISTODEC22!$A$6:$AU$39,20,0) -> BANQUE | W18: =VLOOKUP($A18,[16]HISTODEC22!$A$6:$AU$39,27,0) -> BANQUE | X18: =VLOOKUP($A18,[16]HISTODEC22!$A$6:$AU$39,33,0) -> 0 | Y18: =VLOOKUP($A18,[16]HISTODEC22!$A$6:$BP$39,65,0) -> 0 | AA18: =VLOOKUP($A18,[16]HISTODEC22!$A$6:$AU$39,43,0) -> 0 | AB18: =VLOOKUP($A18,[16]HISTODEC22!$A$6:$AU$39,44,0) -> 0 | AC18: =VLOOKUP($A18,[16]HISTODEC22!$A$6:$AU$39,47,0) -> 0 | AD18: =VLOOKUP(A18,[16]HISTODEC22!$A$6:$BB$36,54,0) -> 0 | AE18: =VLOOKUP($A18,[16]HISTODEC22!$A$6:$CA$36,60,0) -> 0 | AF18: =VLOOKUP($A18,[16]HISTODEC22!$A$6:$CA$36,61,0) -> 0 | AG18: =VLOOKUP($A18,[16]HISTODEC22!$A$6:$CA$36,62,0) -> 0 | AH18: =VLOOKUP($A18,[16]HISTODEC22!$A$6:$CA$36,63,0) -> 0 | AI18: =VLOOKUP($A18,[16]HISTODEC22!$A$6:$CA$36,64,0) -> 0 | AJ18: =VLOOKUP($A18,[16]HISTODEC22!$A$6:$CA$36,65,0) -> 0
A19: AS201620 | B19: =VLOOKUP(A19,[15]LISTADHERENT!$A$5:$J$45,3,0) -> LOWE JEAN | C19: 600000 | D19: =VLOOKUP(A19,'[17]EPARGNE 2023'!$A$5:$BF$47,4,0) -> 746.1759 | F19: =C19+D19-E19 -> 600746.18 | G19: 38160.652 | H19: =+F19+G19 -> 638906.83 | I19: =VLOOKUP($A19,[16]HISTODEC22!$A$6:$AQ$37,22,0) -> 0 | J19: =VLOOKUP($A19,[16]HISTODEC22!$A$6:$AU$39,45,0) -> 7000 | L19: =IF(J19=0,0,500) -> 500 | M19: =IF(J19=0,0,1000) -> 1000 | N19: =IF(J19=0,0,2500) -> 2500 | O19: =VLOOKUP($A19,[16]HISTODEC22!$A$6:$AU$39,7,0) -> 0 | P19: =VLOOKUP($A19,[16]HISTODEC22!$A$6:$AU$39,23,0) -> 0 | Q19: =VLOOKUP($A19,[16]HISTODEC22!$A$6:$AU$39,46,0) -> 0 | R19: =VLOOKUP($A19,[18]HISTODEC22!$A$6:$AU$39,26,0) -> 1000000 | S19: =VLOOKUP($A19,[18]HISTODEC22!$A$6:$BG$39,58,0) -> 40000 | T19: =VLOOKUP($A19,[16]HISTODEC22!$A$6:$AU$39,28,0) -> 0 | U19: =VLOOKUP($A19,[16]HISTODEC22!$A$6:$AU$39,19,0) -> 1000000 | V19: =VLOOKUP($A19,[16]HISTODEC22!$A$6:$AU$39,20,0) -> BANQUE | W19: =VLOOKUP($A19,[16]HISTODEC22!$A$6:$AU$39,27,0) -> BANQUE | X19: =VLOOKUP($A19,[16]HISTODEC22!$A$6:$AU$39,33,0) -> 0 | Y19: =VLOOKUP($A19,[16]HISTODEC22!$A$6:$BP$39,65,0) -> 0 | AA19: =VLOOKUP($A19,[16]HISTODEC22!$A$6:$AU$39,43,0) -> 0 | AB19: =VLOOKUP($A19,[16]HISTODEC22!$A$6:$AU$39,44,0) -> 0 | AC19: =VLOOKUP($A19,[16]HISTODEC22!$A$6:$AU$39,47,0) -> 0 | AD19: =VLOOKUP(A19,[16]HISTODEC22!$A$6:$BB$36,54,0) -> 0 | AE19: =VLOOKUP($A19,[16]HISTODEC22!$A$6:$CA$36,60,0) -> 0 | AF19: =VLOOKUP($A19,[16]HISTODEC22!$A$6:$CA$36,61,0) -> 0 | AG19: =VLOOKUP($A19,[16]HISTODEC22!$A$6:$CA$36,62,0) -> 0 | AH19: =VLOOKUP($A19,[16]HISTODEC22!$A$6:$CA$36,63,0) -> 0 | AI19: =VLOOKUP($A19,[16]HISTODEC22!$A$6:$CA$36,64,0) -> 0 | AJ19: =VLOOKUP($A19,[16]HISTODEC22!$A$6:$CA$36,65,0) -> 0
... A26: AS201628 | B26: =VLOOKUP(A26,[15]LISTADHERENT!$A$5:$J$45,3,0) -> NKAMGANG JUSTIN DEJOLIE | C26: 600000 | D26: =VLOOKUP(A26,'[17]EPARGNE 2023'!$A$5:$BF$47,4,0) -> 575.28053 | F26: =C26+D26-E26 -> 600575.28 | G26: 38149.796 | H26: =+F26+G26 -> 638725.08 | I26: =VLOOKUP($A26,[16]HISTODEC22!$A$6:$AQ$37,22,0) -> 0 | J26: =VLOOKUP($A26,[16]HISTODEC22!$A$6:$AU$39,45,0) -> 7000 | L26: =IF(J26=0,0,500) -> 500 | M26: =IF(J26=0,0,1000) -> 1000 | N26: =IF(J26=0,0,2500) -> 2500 | O26: =VLOOKUP($A26,[16]HISTODEC22!$A$6:$AU$39,7,0) -> 0 | P26: =VLOOKUP($A26,[16]HISTODEC22!$A$6:$AU$39,23,0) -> 0 | Q26: =VLOOKUP($A26,[16]HISTODEC22!$A$6:$AU$39,46,0) -> 0 | R26: =VLOOKUP($A26,[18]HISTODEC22!$A$6:$AU$39,26,0) -> 1000000 | S26: =VLOOKUP($A26,[18]HISTODEC22!$A$6:$BG$39,58,0) -> 20000 | T26: =VLOOKUP($A26,[16]HISTODEC22!$A$6:$AU$39,28,0) -> 0 | U26: =VLOOKUP($A26,[16]HISTODEC22!$A$6:$AU$39,19,0) -> 1000000 | V26: =VLOOKUP($A26,[16]HISTODEC22!$A$6:$AU$39,20,0) -> BANQUE | W26: =VLOOKUP($A26,[16]HISTODEC22!$A$6:$AU$39,27,0) -> BANQUE | X26: =VLOOKUP($A26,[16]HISTODEC22!$A$6:$AU$39,33,0) -> 0 | Y26: =VLOOKUP($A26,[16]HISTODEC22!$A$6:$BP$39,65,0) -> 0 | AA26: =VLOOKUP($A26,[16]HISTODEC22!$A$6:$AU$39,43,0) -> 0 | AB26: =VLOOKUP($A26,[16]HISTODEC22!$A$6:$AU$39,44,0) -> 0 | AC26: =VLOOKUP($A26,[16]HISTODEC22!$A$6:$AU$39,47,0) -> 0 | AD26: =VLOOKUP(A26,[16]HISTODEC22!$A$6:$BB$36,54,0) -> 0 | AE26: =VLOOKUP($A26,[16]HISTODEC22!$A$6:$CA$36,60,0) -> 0 | AF26: =VLOOKUP($A26,[16]HISTODEC22!$A$6:$CA$36,61,0) -> 0 | AG26: =VLOOKUP($A26,[16]HISTODEC22!$A$6:$CA$36,62,0) -> 0 | AH26: =VLOOKUP($A26,[16]HISTODEC22!$A$6:$CA$36,63,0) -> 0 | AI26: =VLOOKUP($A26,[16]HISTODEC22!$A$6:$CA$36,64,0) -> 0 | AJ26: =VLOOKUP($A26,[16]HISTODEC22!$A$6:$CA$36,65,0) -> 0
A27: AS201656 | B27: =VLOOKUP(A27,[15]LISTADHERENT!$A$5:$J$45,3,0) -> NOUBE ETIENNE | C27: 0 | D27: =VLOOKUP(A27,'[17]EPARGNE 2023'!$A$5:$BF$47,4,0) -> 0 | F27: =C27+D27-E27 -> 0 | G27: 0 | H27: =+F27+G27 -> 0
A28: AS201633 | B28: =VLOOKUP(A28,[15]LISTADHERENT!$A$5:$J$45,3,0) -> PATEGO NJOSSU GUSTAVE | C28: 600000 | D28: =VLOOKUP(A28,'[17]EPARGNE 2023'!$A$5:$BF$47,4,0) -> 21451.963 | F28: =C28+D28-E28 -> 621451.96 | G28: 39475.927 | H28: =+F28+G28 -> 660927.89 | I28: =VLOOKUP($A28,[16]HISTODEC22!$A$6:$AQ$37,22,0) -> 0 | J28: =VLOOKUP($A28,[16]HISTODEC22!$A$6:$AU$39,45,0) -> 7000 | L28: =IF(J28=0,0,500) -> 500 | M28: =IF(J28=0,0,1000) -> 1000 | N28: =IF(J28=0,0,2500) -> 2500 | O28: =VLOOKUP($A28,[16]HISTODEC22!$A$6:$AU$39,7,0) -> 0 | P28: =VLOOKUP($A28,[16]HISTODEC22!$A$6:$AU$39,23,0) -> 0 | Q28: =VLOOKUP($A28,[16]HISTODEC22!$A$6:$AU$39,46,0) -> 0 | R28: =VLOOKUP($A28,[18]HISTODEC22!$A$6:$AU$39,26,0) -> 0 | S28: =VLOOKUP($A28,[18]HISTODEC22!$A$6:$BG$39,58,0) -> 0 | T28: =VLOOKUP($A28,[16]HISTODEC22!$A$6:$AU$39,28,0) -> 0 | U28: =VLOOKUP($A28,[16]HISTODEC22!$A$6:$AU$39,19,0) -> 0 | V28: =VLOOKUP($A28,[16]HISTODEC22!$A$6:$AU$39,20,0) -> 0 | W28: =VLOOKUP($A28,[16]HISTODEC22!$A$6:$AU$39,27,0) -> 0 | X28: =VLOOKUP($A28,[16]HISTODEC22!$A$6:$AU$39,33,0) -> 0 | Y28: =VLOOKUP($A28,[16]HISTODEC22!$A$6:$BP$39,65,0) -> 0 | AA28: =VLOOKUP($A28,[16]HISTODEC22!$A$6:$AU$39,43,0) -> 0 | AB28: =VLOOKUP($A28,[16]HISTODEC22!$A$6:$AU$39,44,0) -> 0 | AC28: =VLOOKUP($A28,[16]HISTODEC22!$A$6:$AU$39,47,0) -> 0 | AD28: =VLOOKUP(A28,[16]HISTODEC22!$A$6:$BB$36,54,0) -> 0 | AE28: =VLOOKUP($A28,[16]HISTODEC22!$A$6:$CA$36,60,0) -> 0 | AF28: =VLOOKUP($A28,[16]HISTODEC22!$A$6:$CA$36,61,0) -> 0 | AG28: =VLOOKUP($A28,[16]HISTODEC22!$A$6:$CA$36,62,0) -> 0 | AH28: =VLOOKUP($A28,[16]HISTODEC22!$A$6:$CA$36,63,0) -> 0 | AI28: =VLOOKUP($A28,[16]HISTODEC22!$A$6:$CA$36,64,0) -> 0 | AJ28: =VLOOKUP($A28,[16]HISTODEC22!$A$6:$CA$36,65,0) -> 0
A29: AS201657 | B29: =VLOOKUP(A29,[15]LISTADHERENT!$A$5:$J$45,3,0) -> SEUMO POLYCARPE | C29: 0 | D29: =VLOOKUP(A29,'[17]EPARGNE 2023'!$A$5:$BF$47,4,0) -> 0 | F29: =C29+D29-E29 -> 0 | G29: 0 | H29: =+F29+G29 -> 0
A30: AS201653 | B30: =VLOOKUP(A30,[15]LISTADHERENT!$A$5:$J$45,3,0) -> SIME BRICE | C30: 600000 | D30: =VLOOKUP(A30,'[17]EPARGNE 2023'!$A$5:$BF$47,4,0) -> 200752.48 | F30: =C30+D30-E30 -> 800752.48 | G30: 50865.47 | H30: =+F30+G30 -> 851617.95 | I30: =VLOOKUP($A30,[16]HISTODEC22!$A$6:$AQ$37,22,0) -> 0 | J30: =VLOOKUP($A30,[16]HISTODEC22!$A$6:$AU$39,45,0) -> 7000 | L30: =IF(J30=0,0,500) -> 500 | M30: =IF(J30=0,0,1000) -> 1000 | N30: =IF(J30=0,0,2500) -> 2500 | O30: =VLOOKUP($A30,[16]HISTODEC22!$A$6:$AU$39,7,0) -> 0 | P30: =VLOOKUP($A30,[16]HISTODEC22!$A$6:$AU$39,23,0) -> 0 | Q30: =VLOOKUP($A30,[16]HISTODEC22!$A$6:$AU$39,46,0) -> 0 | R30: =VLOOKUP($A30,[18]HISTODEC22!$A$6:$AU$39,26,0) -> 0 | S30: =VLOOKUP($A30,[18]HISTODEC22!$A$6:$BG$39,58,0) -> 0 | T30: =VLOOKUP($A30,[16]HISTODEC22!$A$6:$AU$39,28,0) -> 0 | U30: =VLOOKUP($A30,[16]HISTODEC22!$A$6:$AU$39,19,0) -> 0 | V30: =VLOOKUP($A30,[16]HISTODEC22!$A$6:$AU$39,20,0) -> 0 | W30: =VLOOKUP($A30,[16]HISTODEC22!$A$6:$AU$39,27,0) -> 0 | X30: =VLOOKUP($A30,[16]HISTODEC22!$A$6:$AU$39,33,0) -> 0 | Y30: =VLOOKUP($A30,[16]HISTODEC22!$A$6:$BP$39,65,0) -> 0 | AA30: =VLOOKUP($A30,[16]HISTODEC22!$A$6:$AU$39,43,0) -> 0 | AB30: =VLOOKUP($A30,[16]HISTODEC22!$A$6:$AU$39,44,0) -> 0 | AC30: =VLOOKUP($A30,[16]HISTODEC22!$A$6:$AU$39,47,0) -> 0 | AD30: =VLOOKUP(A30,[16]HISTODEC22!$A$6:$BB$36,54,0) -> 0 | AE30: =VLOOKUP($A30,[16]HISTODEC22!$A$6:$CA$36,60,0) -> 0 | AF30: =VLOOKUP($A30,[16]HISTODEC22!$A$6:$CA$36,61,0) -> 0 | AG30: =VLOOKUP($A30,[16]HISTODEC22!$A$6:$CA$36,62,0) -> 0 | AH30: =VLOOKUP($A30,[16]HISTODEC22!$A$6:$CA$36,63,0) -> 0 | AI30: =VLOOKUP($A30,[16]HISTODEC22!$A$6:$CA$36,64,0) -> 0 | AJ30: =VLOOKUP($A30,[16]HISTODEC22!$A$6:$CA$36,65,0) -> 0
A31: AS201638 | B31: =VLOOKUP(A31,[15]LISTADHERENT!$A$5:$J$45,3,0) -> SIMO PIERRE | C31: 600000 | D31: =VLOOKUP(A31,'[17]EPARGNE 2023'!$A$5:$BF$47,4,0) -> 103606.47 | F31: =C31+D31-E31 -> 703606.47 | G31: 44694.553 | H31: =+F31+G31 -> 748301.02 | I31: =VLOOKUP($A31,[16]HISTODEC22!$A$6:$AQ$37,22,0) -> 0 | J31: =VLOOKUP($A31,[16]HISTODEC22!$A$6:$AU$39,45,0) -> 7000 | L31: =IF(J31=0,0,500) -> 500 | M31: =IF(J31=0,0,1000) -> 1000 | N31: =IF(J31=0,0,2500) -> 2500 | O31: =VLOOKUP($A31,[16]HISTODEC22!$A$6:$AU$39,7,0) -> 0 | P31: =VLOOKUP($A31,[16]HISTODEC22!$A$6:$AU$39,23,0) -> 0 | Q31: =VLOOKUP($A31,[16]HISTODEC22!$A$6:$AU$39,46,0) -> 0 | R31: =VLOOKUP($A31,[18]HISTODEC22!$A$6:$AU$39,26,0) -> 1000000 | S31: =VLOOKUP($A31,[18]HISTODEC22!$A$6:$BG$39,58,0) -> 120000 | T31: =VLOOKUP($A31,[16]HISTODEC22!$A$6:$AU$39,28,0) -> 0 | U31: =VLOOKUP($A31,[16]HISTODEC22!$A$6:$AU$39,19,0) -> 800000 | V31: =VLOOKUP($A31,[16]HISTODEC22!$A$6:$AU$39,20,0) -> BANQUE | W31: =VLOOKUP($A31,[16]HISTODEC22!$A$6:$AU$39,27,0) -> BANQUE | X31: =VLOOKUP($A31,[16]HISTODEC22!$A$6:$AU$39,33,0) -> 0 | Y31: =VLOOKUP($A31,[16]HISTODEC22!$A$6:$BP$39,65,0) -> 0 | AA31: =VLOOKUP($A31,[16]HISTODEC22!$A$6:$AU$39,43,0) -> 0 | AB31: =VLOOKUP($A31,[16]HISTODEC22!$A$6:$AU$39,44,0) -> 0 | AC31: =VLOOKUP($A31,[16]HISTODEC22!$A$6:$AU$39,47,0) -> 0 | AD31: =VLOOKUP(A31,[16]HISTODEC22!$A$6:$BB$36,54,0) -> 0 | AE31: =VLOOKUP($A31,[16]HISTODEC22!$A$6:$CA$36,60,0) -> 0 | AF31: =VLOOKUP($A31,[16]HISTODEC22!$A$6:$CA$36,61,0) -> 0 | AG31: =VLOOKUP($A31,[16]HISTODEC22!$A$6:$CA$36,62,0) -> 0 | AH31: =VLOOKUP($A31,[16]HISTODEC22!$A$6:$CA$36,63,0) -> 0 | AI31: =VLOOKUP($A31,[16]HISTODEC22!$A$6:$CA$36,64,0) -> 0 | AJ31: =VLOOKUP($A31,[16]HISTODEC22!$A$6:$CA$36,65,0) -> 0
A32: AS201641 | B32: =VLOOKUP(A32,[15]LISTADHERENT!$A$5:$J$45,3,0) -> TCHOUAMOU MATHIEU | C32: 600000 | D32: =VLOOKUP(A32,'[17]EPARGNE 2023'!$A$5:$BF$47,4,0) -> 4207.8699 | F32: =C32+D32-E32 -> 604207.87 | G32: 38380.546 | H32: =+F32+G32 -> 642588.42 | I32: =VLOOKUP($A32,[16]HISTODEC22!$A$6:$AQ$37,22,0) -> 0 | J32: =VLOOKUP($A32,[16]HISTODEC22!$A$6:$AU$39,45,0) -> 7000 | L32: =IF(J32=0,0,500) -> 500 | M32: =IF(J32=0,0,1000) -> 1000 | N32: =IF(J32=0,0,2500) -> 2500 | O32: =VLOOKUP($A32,[16]HISTODEC22!$A$6:$AU$39,7,0) -> 0 | P32: =VLOOKUP($A32,[16]HISTODEC22!$A$6:$AU$39,23,0) -> 0 | Q32: =VLOOKUP($A32,[16]HISTODEC22!$A$6:$AU$39,46,0) -> 0 | R32: =VLOOKUP($A32,[18]HISTODEC22!$A$6:$AU$39,26,0) -> 1000000 | S32: =VLOOKUP($A32,[18]HISTODEC22!$A$6:$BG$39,58,0) -> 30000 | T32: =VLOOKUP($A32,[16]HISTODEC22!$A$6:$AU$39,28,0) -> 0 | U32: =VLOOKUP($A32,[16]HISTODEC22!$A$6:$AU$39,19,0) -> 1000000 | V32: =VLOOKUP($A32,[16]HISTODEC22!$A$6:$AU$39,20,0) -> BANQUE | W32: =VLOOKUP($A32,[16]HISTODEC22!$A$6:$AU$39,27,0) -> 0 | X32: =VLOOKUP($A32,[16]HISTODEC22!$A$6:$AU$39,33,0) -> 0 | Y32: =VLOOKUP($A32,[16]HISTODEC22!$A$6:$BP$39,65,0) -> 0 | AA32: =VLOOKUP($A32,[16]HISTODEC22!$A$6:$AU$39,43,0) -> 0 | AB32: =VLOOKUP($A32,[16]HISTODEC22!$A$6:$AU$39,44,0) -> 0 | AC32: =VLOOKUP($A32,[16]HISTODEC22!$A$6:$AU$39,47,0) -> 0 | AD32: =VLOOKUP(A32,[16]HISTODEC22!$A$6:$BB$36,54,0) -> 0 | AE32: =VLOOKUP($A32,[16]HISTODEC22!$A$6:$CA$36,60,0) -> 0 | AF32: =VLOOKUP($A32,[16]HISTODEC22!$A$6:$CA$36,61,0) -> 0 | AG32: =VLOOKUP($A32,[16]HISTODEC22!$A$6:$CA$36,62,0) -> 0 | AH32: =VLOOKUP($A32,[16]HISTODEC22!$A$6:$CA$36,63,0) -> 0 | AI32: =VLOOKUP($A32,[16]HISTODEC22!$A$6:$CA$36,64,0) -> 0 | AJ32: =VLOOKUP($A32,[16]HISTODEC22!$A$6:$CA$36,65,0) -> 0
A33: AS201643 | B33: =VLOOKUP(A33,[15]LISTADHERENT!$A$5:$J$45,3,0) -> TCHOUTOU NANA CLAUDE | C33: 0 | D33: =VLOOKUP(A33,'[17]EPARGNE 2023'!$A$5:$BF$47,4,0) -> 0 | F33: =C33+D33-E33 -> 0 | G33: 0 | H33: =+F33+G33 -> 0
A34: AS201658 | B34: =VLOOKUP(A34,[15]LISTADHERENT!$A$5:$J$45,3,0) -> YANTCHOU GERVAIS | C34: 0 | D34: =VLOOKUP(A34,'[17]EPARGNE 2023'!$A$5:$BF$47,4,0) -> 0 | F34: =C34+D34-E34 -> 0 | G34: 0 | H34: =+F34+G34 -> 0
A35: AS201646 | B35: =VLOOKUP(A35,[15]LISTADHERENT!$A$5:$J$45,3,0) -> YEPMOU JEAN JACQUES | C35: 600000 | D35: =VLOOKUP(A35,'[17]EPARGNE 2023'!$A$5:$BF$47,4,0) -> 914734.42 | F35: =C35+D35-E35 -> 1514734.4 | G35: 96219.095 | H35: =+F35+G35 -> 1610953.5 | I35: =VLOOKUP($A35,[16]HISTODEC22!$A$6:$AQ$37,22,0) -> 0 | J35: =VLOOKUP($A35,[16]HISTODEC22!$A$6:$AU$39,45,0) -> 7000 | L35: =IF(J35=0,0,500) -> 500 | M35: =IF(J35=0,0,1000) -> 1000 | N35: =IF(J35=0,0,2500) -> 2500 | O35: =VLOOKUP($A35,[16]HISTODEC22!$A$6:$AU$39,7,0) -> 0 | P35: =VLOOKUP($A35,[16]HISTODEC22!$A$6:$AU$39,23,0) -> 0 | Q35: =VLOOKUP($A35,[16]HISTODEC22!$A$6:$AU$39,46,0) -> 0 | R35: =VLOOKUP($A35,[18]HISTODEC22!$A$6:$AU$39,26,0) -> 0 | S35: =VLOOKUP($A35,[18]HISTODEC22!$A$6:$BG$39,58,0) -> 0 | T35: =VLOOKUP($A35,[16]HISTODEC22!$A$6:$AU$39,28,0) -> 0 | U35: =VLOOKUP($A35,[16]HISTODEC22!$A$6:$AU$39,19,0) -> 1011250 | V35: =VLOOKUP($A35,[16]HISTODEC22!$A$6:$AU$39,20,0) -> BANQUE | W35: =VLOOKUP($A35,[16]HISTODEC22!$A$6:$AU$39,27,0) -> 0 | X35: =VLOOKUP($A35,[16]HISTODEC22!$A$6:$AU$39,33,0) -> 0 | Y35: =VLOOKUP($A35,[16]HISTODEC22!$A$6:$BP$39,65,0) -> 0 | AA35: =VLOOKUP($A35,[16]HISTODEC22!$A$6:$AU$39,43,0) -> 0 | AB35: =VLOOKUP($A35,[16]HISTODEC22!$A$6:$AU$39,44,0) -> 0 | AC35: =VLOOKUP($A35,[16]HISTODEC22!$A$6:$AU$39,47,0) -> 0 | AD35: =VLOOKUP(A35,[16]HISTODEC22!$A$6:$BB$36,54,0) -> 0 | AE35: =VLOOKUP($A35,[16]HISTODEC22!$A$6:$CA$36,60,0) -> 0 | AF35: =VLOOKUP($A35,[16]HISTODEC22!$A$6:$CA$36,61,0) -> 0 | AG35: =VLOOKUP($A35,[16]HISTODEC22!$A$6:$CA$36,62,0) -> 0 | AH35: =VLOOKUP($A35,[16]HISTODEC22!$A$6:$CA$36,63,0) -> 0 | AI35: =VLOOKUP($A35,[16]HISTODEC22!$A$6:$CA$36,64,0) -> 0 | AJ35: =VLOOKUP($A35,[16]HISTODEC22!$A$6:$CA$36,65,0) -> 0
A36: AS201647 | B36: =VLOOKUP(A36,[15]LISTADHERENT!$A$5:$J$45,3,0) -> YOUMBI EMMANUEL | C36: 600000 | D36: =VLOOKUP(A36,'[17]EPARGNE 2023'!$A$5:$BF$47,4,0) -> 1057774.2 | F36: =C36+D36-E36 -> 1657774.2 | G36: 105305.28 | H36: =+F36+G36 -> 1763079.5 | I36: =VLOOKUP($A36,[16]HISTODEC22!$A$6:$AQ$37,22,0) -> 0 | J36: =VLOOKUP($A36,[16]HISTODEC22!$A$6:$AU$39,45,0) -> 7000 | L36: =IF(J36=0,0,500) -> 500 | M36: =IF(J36=0,0,1000) -> 1000 | N36: =IF(J36=0,0,2500) -> 2500 | O36: =VLOOKUP($A36,[16]HISTODEC22!$A$6:$AU$39,7,0) -> 0 | P36: =VLOOKUP($A36,[16]HISTODEC22!$A$6:$AU$39,23,0) -> 0 | Q36: =VLOOKUP($A36,[16]HISTODEC22!$A$6:$AU$39,46,0) -> 0 | R36: =VLOOKUP($A36,[18]HISTODEC22!$A$6:$AU$39,26,0) -> 0 | S36: =VLOOKUP($A36,[18]HISTODEC22!$A$6:$BG$39,58,0) -> 0 | T36: =VLOOKUP($A36,[16]HISTODEC22!$A$6:$AU$39,28,0) -> 0 | U36: =VLOOKUP($A36,[16]HISTODEC22!$A$6:$AU$39,19,0) -> 0 | V36: =VLOOKUP($A36,[16]HISTODEC22!$A$6:$AU$39,20,0) -> 0 | W36: =VLOOKUP($A36,[16]HISTODEC22!$A$6:$AU$39,27,0) -> 0 | X36: =VLOOKUP($A36,[16]HISTODEC22!$A$6:$AU$39,33,0) -> 0 | Y36: =VLOOKUP($A36,[16]HISTODEC22!$A$6:$BP$39,65,0) -> 0 | AA36: =VLOOKUP($A36,[16]HISTODEC22!$A$6:$AU$39,43,0) -> 0 | AB36: =VLOOKUP($A36,[16]HISTODEC22!$A$6:$AU$39,44,0) -> 0 | AC36: =VLOOKUP($A36,[16]HISTODEC22!$A$6:$AU$39,47,0) -> 0 | AD36: =VLOOKUP(A36,[16]HISTODEC22!$A$6:$BB$36,54,0) -> 0 | AE36: =VLOOKUP($A36,[16]HISTODEC22!$A$6:$CA$36,60,0) -> 0 | AF36: =VLOOKUP($A36,[16]HISTODEC22!$A$6:$CA$36,61,0) -> 0 | AG36: =VLOOKUP($A36,[16]HISTODEC22!$A$6:$CA$36,62,0) -> 0 | AH36: =VLOOKUP($A36,[16]HISTODEC22!$A$6:$CA$36,63,0) -> 0 | AI36: =VLOOKUP($A36,[16]HISTODEC22!$A$6:$CA$36,64,0) -> 0 | AJ36: =VLOOKUP($A36,[16]HISTODEC22!$A$6:$CA$36,65,0) -> 0
A37: AS201629 | B37: =VLOOKUP(A37,[15]LISTADHERENT!$A$5:$J$45,3,0) -> NKEPSEU DIEUDONNE | C37: 600000 | D37: 2434 | F37: =C37+D37-E37 -> 602434 | G37: 38267.866 | H37: =+F37+G37 -> 640701.87
A39: TOTAL | C39: =SUM(C6:C37) -> 15600000 | D39: =SUM(D6:D37) -> 4361560.2 | E39: =SUM(E6:E37) -> 0 | F39: =SUM(F6:F37) -> 19961560 | G39: =SUM(G6:G37) -> 1268000 | H39: =SUM(H6:H37) -> 21229560 | I39: =SUM(I6:I37) -> 0 | J39: =SUM(J6:J37) -> 286000 | ... AJ39: =SUM(AJ6:AJ37) -> 0
C41: 536000 | D41: 4361500
C42: =C39-C41 -> 15064000 | D42: =D39-D41 -> 60.190811 | F42: 19359126
H43: =H39-H41 -> 21229560

Sheet Sheet6

Sheet Sheet7

Sheet Sheet8

Sheet Sheet9
A1: ANNEE | B1: TONTINE
A2: MATRICULE | B2: 2024
A3: 1 | B3: 2 | C3: 3 | D3: 4 | E3: 5 | F3: 6 | G3: 7 | H3: 8 | I3: 9 | J3: 10 | K3: 11 | L3: 12 | M3: 13 | N3: 14 | O3: 15 | P3: 16 | Q3: 17 | R3: 18 | S3: 19 | T3: 20 | U3: 21 | V3: 22 | W3: 23 | X3: 24 | Y3: 25 | Z3: 26 | AA3: 27 | AB3: 28 | AC3: 29 | AD3: 30 | AE3: 31 | AF3: 32 | AG3: 33 | AH3: 34 | AI3: 35 | AJ3: 36 | AK3: 37 | AL3: 38 | AM3: 39 | AN3: 40 | AO3: 41 | AP3: 42 | AQ3: 43 | AR3: 44 | AS3: 45 | AT3: 46 | AU3: 47 | AV3: 48 | AW3: 49 | AX3: 50 | AY3: 51 | AZ3: 52 | BA3: 53 | BB3: 54 | BC3: 55 | BD3: 56 | BE3: 57 | BF3: 58 | BG3: 59 | BH3: 60 | BI3: 61 | BJ3: 62 | BK3: 63 | BL3: 64 | BM3: 65 | BN3: 66 | BO3: 67 | BP3: 68
B4: AS201628
A5: ASSOCIATION | B5: ASELBY | C5: AS201636 | D5: PENALITE VST ESPECES | E5: INSCRIPTION | F5: INSCRISPTION | G5: AS201633 | H5: AS201637 | I5: FONDS DE CAISSE | J5: AS201634 | K5: RECAPITULATIF 2020 | L5: AS201634 | M5: NOM ET PRENOM | N5: AS201634 | O5: REPARTITION INTERET | P5: MARS | Q5: FONDS DE ROULEMENT | R5: FRAIS EXCEPTIONNEL | S5: PRET FONDS | T5: PENALITE VERST ESPECES | U5: FRAIS EXCEPTIONNELS | V5: CAPITAL COMPOSE | W5: AS201641 | X5: TONTINE | Y5: RESTE | Z5: AS201642 | AA5: PRÊT FONDS | AB5: TOTAL | AC5: JUIN | AD5: AS201627 | AE5: INTERET PRÊT FONDS | AF5: AS201638 | AG5: TOTAL | AH5: AS201633 | AI5: AVRIL | AJ5: AS201643 | AK5: AS201644 | AL5: MAI | AM5: AS201646 | AN5: AS201647 | AO5: TOTAL | AP5: OCTOBRE | AQ5: REMBOURSEMENTPRET FONDS | AR5: PENALITE PRET FONDS | AS5: RELIQUAT | AT5: AS201639 | AU5: DOMOU FABIEN | AV5: MONTANT EPARGNE+INTERET | AW5: JUILLET | AX5: NUMERO CHEQUE | AY5: AS201653 | AZ5: 2018/2019 | BA5: NKEPSEU DIEUDONNE | BB5: KOUAMOU MOISE | BC5: COMPLEMENT FONDS | BD5: MONTANT A VERSER | BE5: KOUAMO VICTOR PEGUY | BF5: T100 | BG5: TABLEAU RECAPITULATIF DISTRIBUTION EPARGNE 2019 | BH5: 2019/2020 | BI5: INTERET ANTERIEUR | BJ5: NET_ A_ PAYER | BK5: PRÊT_FONDS_ENCOURS | BL5: DISTRIBUTION INTERET 2018 ET 2019 | BM5: DJOMO JEAN PAUL AVANCE 80 000 DJOMO JEAN PAUL | BN5: 2017/2018 | BO5: PRÊT_FONDS | BP5: AS201654
A6: KOUAMOU EMMANUEL | B6: =VLOOKUP(A6,[11]LISTADHERENT!A$5:H$50,3,0) -> ASELBY | C6: =D6+E6+F6-U6-BB6 -> 0 | D6: =VLOOKUP(A6,[12]HISTOBQUEAVRIL24!$A$6:$G$46,3,0) -> 0 | E6: =VLOOKUP(A6,[12]HISTOBQUEAVRIL24!$A$6:$G$41,4,0) -> 0 | F6: =VLOOKUP(A6,[12]HISTOBQUEAVRIL24!$A$6:$G$41,5,0) -> 0 | G6: =IF(H6="ESPECES",3000,0) -> 0 | H6: =IF($D6<>0,"BANQUE",IF($E6<>0,"ESPECES","ECHEC")) -> ECHEC | K6: =IF($D6<>0,J6*50000,IF($E6<>0,J6*50000,0)) -> 0 | L6: 1 | M6: =IF($D6<>0,L6*75000,IF($E6<>0,L6*75000,0)) -> 0 | N6: 1 | O6: =IF($D6<>0,N6*100000,IF($E6<>0,N6*100000,0)) -> 0 | U6: =G6+S6++R6+P6+O6+M6+I6+K6+Q6+V6+W6 -> 0 | AQ6: =IF(H6="ECHEC",((K6+M6+O6)*20/100),0) -> 0 | AR6: =IF(H6="ECHEC",((K6+M6+O6)*20/100),0) -> 0 | AW6: =IF(AC6=0,AI6,(1*25000*12)+AI6-AC6) -> 0 | AX6: =IF(AD6=0,AJ6,(1*75000*12)+(AJ6)-AD6) -> 0 | AY6: =IF(AE6=0,AK6,(1*100000*12)+(AK6)-AE6) -> 0 | AZ6: =SUM(AV6:AY6)-BF6+Z6-F6+BH6+BI6+BJ6+BK6+BL6+BM6 -> 0 | BD6: =IF(AZ6=0,(AZ6-BA6-BC6),(AZ6-BA6-BB6-BC6)) -> 0 | BF6: =Z6*1/100*BG6 -> 0 | BG6: 7 | BH6: =BP16 -> 0 | BI6: =BP28 -> 0 | BJ6: =BP33 -> 0 | BK6: =+BP40 -> 0 | BM6: =BP22 -> 0 | BN6: NKEHE DAVID | BO6: NGONGANG JEAN THEODORE
A7: DATE | B7: =VLOOKUP(A7,[11]LISTADHERENT!A$5:H$50,3,0) -> BAKOP ACHILLE | C7: =D7+E7+F7-U7-BB7 -> 0 | D7: =VLOOKUP(A7,[12]HISTOBQUEAVRIL24!$A$6:$G$46,3,0) -> 0 | E7: =VLOOKUP(A7,[12]HISTOBQUEAVRIL24!$A$6:$G$41,4,0) -> 0 | F7: =VLOOKUP(A7,[12]HISTOBQUEAVRIL24!$A$6:$G$41,5,0) -> 0 | G7: =IF(H7="ESPECES",3000,0) -> 0 | H7: =IF($D7<>0,"BANQUE",IF($E7<>0,"ESPECES","ECHEC")) -> ECHEC | J7: 1 | K7: =IF($D7<>0,J7*50000,IF($E7<>0,J7*50000,0)) -> 0 | M7: =IF($D7<>0,L7*75000,IF($E7<>0,L7*75000,0)) -> 0 | O7: =IF($D7<>0,N7*100000,IF($E7<>0,N7*100000,0)) -> 0 | P7: =VLOOKUP(A7,[14]TONTMAI24!$A$6:$R$39,12,0) -> 0 | U7: =G7+S7++R7+P7+O7+M7+I7+K7+Q7+V7+W7 -> 0 | AQ7: =IF(H7="ECHEC",((K7+M7+O7)*20/100),0) -> 0 | AR7: =IF(H7="ECHEC",((K7+M7+O7)*20/100),0) -> 0 | AS7: =IF(H7="ECHEC",0,(K7+I7-25000)) -> 0 | AW7: =IF(AC7=0,AI7,(1*25000*12)+AI7-AC7) -> 0 | AX7: =IF(AD7=0,AJ7,(1*75000*12)+(AJ7)-AD7) -> 0 | AY7: =IF(AE7=0,AK7,(1*100000*12)+(AK7)-AE7) -> 0 | AZ7: =SUM(AV7:AY7)-BF7+Z7-F7+BH7+BI7+BJ7+BK7+BL7+BM7 -> 0 | BD7: =IF(AZ7=0,(AZ7-BA7-BC7),(AZ7-BA7-BB7-BC7)) -> 0 | BF7: =Z7*1/100*BG7 -> 0 | BG7: 7 | BN7: PATEGO NJOSSU GUSTAVE | BO7: NGONGANG JEAN THEODORE
A8: COLLATION | B8: =VLOOKUP(A8,[11]LISTADHERENT!A$5:H$50,3,0) -> BOUTCHOUANG WILLIAM | C8: =D8+E8+F8-U8-BB8 -> 0 | D8: =VLOOKUP(A8,[12]HISTOBQUEAVRIL24!$A$6:$G$46,3,0) -> 0 | E8: =VLOOKUP(A8,[12]HISTOBQUEAVRIL24!$A$6:$G$41,4,0) -> 0 | F8: =VLOOKUP(A8,[12]HISTOBQUEAVRIL24!$A$6:$G$41,5,0) -> 0 | G8: =IF(H8="ESPECES",3000,0) -> 0 | H8: =IF($D8<>0,"BANQUE",IF($E8<>0,"ESPECES","ECHEC")) -> ECHEC | J8: 1 | K8: =IF($D8<>0,J8*50000,IF($E8<>0,J8*50000,0)) -> 0 | L8: 1 | M8: =IF($D8<>0,L8*75000,IF($E8<>0,L8*75000,0)) -> 0 | O8: =IF($D8<>0,N8*100000,IF($E8<>0,N8*100000,0)) -> 0 | P8: =VLOOKUP(A8,[14]TONTMAI24!$A$6:$R$39,12,0) -> 0 | Q8: =VLOOKUP(A8,[15]TONTMAI24!$A$7:$P$23,10,0) -> 0 | U8: =G8+S8++R8+P8+O8+M8+I8+K8+Q8+V8+W8 -> 0 | AQ8: =IF(H8="ECHEC",((K8+M8+O8)*20/100),0) -> 0 | AR8: =IF(H8="ECHEC",((K8+M8+O8)*20/100),0) -> 0 | AS8: =IF(H8="ECHEC",0,(K8+I8-25000)) -> 0 | AW8: =IF(AC8=0,AI8,(1*25000*12)+AI8-AC8) -> 0 | AX8: =IF(AD8=0,AJ8,(1*75000*12)+(AJ8)-AD8) -> 0 | AY8: =IF(AE8=0,AK8,(1*100000*12)+(AK8)-AE8) -> 0 | AZ8: =SUM(AV8:AY8)-BF8+Z8-F8+BH8+BI8+BJ8+BK8+BL8+BM8 -> 0 | BD8: =IF(AZ8=0,(AZ8-BA8-BC8),(AZ8-BA8-BB8-BC8)) -> 0 | BF8: =Z8*1/100*BG8 -> 0 | BG8: 7 | BN8: SEUNOU RICHELOT | BO8: NGONGANG JEAN THEODORE
A9: MUTUELLE | B9: =VLOOKUP(A9,[11]LISTADHERENT!A$5:H$50,3,0) -> DJOMO JEAN PAUL | C9: =D9+E9+F9-U9-BB9 -> 0 | D9: =VLOOKUP(A9,[12]HISTOBQUEAVRIL24!$A$6:$G$46,3,0) -> 0 | E9: =VLOOKUP(A9,[12]HISTOBQUEAVRIL24!$A$6:$G$41,4,0) -> 0 | F9: =VLOOKUP(A9,[12]HISTOBQUEAVRIL24!$A$6:$G$41,5,0) -> 0 | G9: =IF(H9="ESPECES",3000,0) -> 0 | H9: =IF($D9<>0,"BANQUE",IF($E9<>0,"ESPECES","ECHEC")) -> ECHEC | J9: 1 | K9: =IF($D9<>0,J9*50000,IF($E9<>0,J9*50000,0)) -> 0 | M9: =IF($D9<>0,L9*75000,IF($E9<>0,L9*75000,0)) -> 0 | N9: 2 | O9: =IF($D9<>0,N9*100000,IF($E9<>0,N9*100000,0)) -> 0 | P9: =VLOOKUP(A9,[14]TONTMAI24!$A$6:$R$39,12,0) -> 0 | R9: =VLOOKUP(A9,[16]TONTMAI24!$A$7:$P$20,10,0) -> 0 | U9: =G9+S9++R9+P9+O9+M9+I9+K9+Q9+V9+W9 -> 0 | AQ9: =IF(H9="ECHEC",((K9+M9+O9)*20/100),0) -> 0 | AR9: =IF(H9="ECHEC",((K9+M9+O9)*20/100),0) -> 0 | AS9: =IF(H9="ECHEC",0,(K9+I9-25000)) -> 0 | AW9: =IF(AC9=0,AI9,(1*25000*12)+AI9-AC9) -> 0 | AX9: =IF(AD9=0,AJ9,(1*75000*12)+(AJ9)-AD9) -> 0 | AY9: =IF(AE9=0,AK9,(1*100000*12)+(AK9)-AE9) -> 0 | AZ9: =SUM(AV9:AY9)-BF9+Z9-F9+BH9+BI9+BJ9+BK9+BL9+BM9 -> 0 | BD9: =IF(AZ9=0,(AZ9-BA9-BC9),(AZ9-BA9-BB9-BC9)) -> 0 | BF9: =Z9*1/100*BG9 -> 0 | BG9: 7 | BN9: JANVIER | BO9: NGONGANG JEAN THEODORE
A10: PENALITE FONDS | B10: =VLOOKUP(A10,[11]LISTADHERENT!A$5:H$50,3,0) -> DJOMOU TCHAPDA | C10: =D10+E10+F10-U10-BB10 -> 0 | D10: =VLOOKUP(A10,[12]HISTOBQUEAVRIL24!$A$6:$G$46,3,0) -> 0 | E10: =VLOOKUP(A10,[12]HISTOBQUEAVRIL24!$A$6:$G$41,4,0) -> 0 | F10: =VLOOKUP(A10,[12]HISTOBQUEAVRIL24!$A$6:$G$41,5,0) -> 0 | G10: =IF(H10="ESPECES",3000,0) -> 0 | H10: =IF($D10<>0,"BANQUE",IF($E10<>0,"ESPECES","ECHEC")) -> ECHEC | J10: 1 | K10: =IF($D10<>0,J10*50000,IF($E10<>0,J10*50000,0)) -> 0 | L10: 1 | M10: =IF($D10<>0,L10*75000,IF($E10<>0,L10*75000,0)) -> 0 | O10: =IF($D10<>0,N10*100000,IF($E10<>0,N10*100000,0)) -> 0 | P10: =VLOOKUP(A10,[14]TONTMAI24!$A$6:$R$39,12,0) -> 0 | Q10: =VLOOKUP(A10,[15]TONTMAI24!$A$7:$P$23,10,0) -> 0 | U10: =G10+S10++R10+P10+O10+M10+I10+K10+Q10+V10+W10 -> 0 | AQ10: =IF(H10="ECHEC",((K10+M10+O10)*20/100),0) -> 0 | AR10: =IF(H10="ECHEC",((K10+M10+O10)*20/100),0) -> 0 | AS10: =IF(H10="ECHEC",0,(K10+I10-25000)) -> 0 | AW10: =IF(AC10=0,AI10,(1*25000*12)+AI10-AC10) -> 0 | AX10: =IF(AD10=0,AJ10,(1*75000*12)+(AJ10)-AD10) -> 0 | AY10: =IF(AE10=0,AK10,(1*100000*12)+(AK10)-AE10) -> 0 | AZ10: =SUM(AV10:AY10)-BF10+Z10-F10+BH10+BI10+BJ10+BK10+BL10+BM10 -> 0 | BD10: =IF(AZ10=0,(AZ10-BA10-BC10),(AZ10-BA10-BB10-BC10)) -> 0 | BF10: =Z10*1/100*BG10 -> 0 | BG10: 7 | BN10: SIME BRICE | BO10: NGONGANG JEAN THEODORE
A11: AVALISTE | B11: =VLOOKUP(A11,[11]LISTADHERENT!A$5:H$50,3,0) -> DJOUKWE NANGUEN GUY BLAISE | C11: =D11+E11+F11-U11-BB11 -> 0 | D11: =VLOOKUP(A11,[12]HISTOBQUEAVRIL24!$A$6:$G$46,3,0) -> 0 | E11: =VLOOKUP(A11,[12]HISTOBQUEAVRIL24!$A$6:$G$41,4,0) -> 0 | F11: =VLOOKUP(A11,[12]HISTOBQUEAVRIL24!$A$6:$G$41,5,0) -> 0 | G11: =IF(H11="ESPECES",3000,0) -> 0 | H11: =IF($D11<>0,"BANQUE",IF($E11<>0,"ESPECES","ECHEC")) -> ECHEC | J11: 1 | K11: =IF($D11<>0,J11*50000,IF($E11<>0,J11*50000,0)) -> 0 | L11: 1 | M11: =IF($D11<>0,L11*75000,IF($E11<>0,L11*75000,0)) -> 0 | O11: =IF($D11<>0,N11*100000,IF($E11<>0,N11*100000,0)) -> 0 | P11: =VLOOKUP(A11,[14]TONTMAI24!$A$6:$R$39,12,0) -> 0 | Q11: =VLOOKUP(A11,[15]TONTMAI24!$A$7:$P$23,10,0) -> 0 | U11: =G11+S11++R11+P11+O11+M11+I11+K11+Q11+V11+W11 -> 0 | AQ11: =IF(H11="ECHEC",((K11+M11+O11)*20/100),0) -> 0 | AR11: =IF(H11="ECHEC",((K11+M11+O11)*20/100),0) -> 0 | AS11: =IF(H11="ECHEC",0,(K11+I11-25000)) -> 0 | AW11: =IF(AC11=0,AI11,(1*25000*12)+AI11-AC11) -> 0 | AX11: =IF(AD11=0,AJ11,(1*75000*12)+(AJ11)-AD11) -> 0 | AY11: =IF(AE11=0,AK11,(1*100000*12)+(AK11)-AE11) -> 0 | AZ11: =SUM(AV11:AY11)-BF11+Z11-F11+BH11+BI11+BJ11+BK11+BL11+BM11 -> 0 | BD11: =IF(AZ11=0,(AZ11-BA11-BC11),(AZ11-BA11-BB11-BC11)) -> 0 | BF11: =Z11*1/100*BG11 -> 0 | BG11: 7 | BN11: SIME FONGANG ERIC | BO11: NGONGANG JEAN THEODORE
A12: AS201648 | B12: =VLOOKUP(A12,[11]LISTADHERENT!A$5:H$50,3,0) -> DJUOMBESSY ANTOINE | C12: =D12+E12+F12-U12-BB12 -> 0 | D12: =VLOOKUP(A12,[12]HISTOBQUEAVRIL24!$A$6:$G$46,3,0) -> 0 | E12: =VLOOKUP(A12,[12]HISTOBQUEAVRIL24!$A$6:$G$41,4,0) -> 0 | F12: =VLOOKUP(A12,[12]HISTOBQUEAVRIL24!$A$6:$G$41,5,0) -> 0 | G12: =IF(H12="ESPECES",3000,0) -> 0 | H12: =IF($D12<>0,"BANQUE",IF($E12<>0,"ESPECES","ECHEC")) -> ECHEC | J12: 1 | K12: =IF($D12<>0,J12*50000,IF($E12<>0,J12*50000,0)) -> 0 | L12: 1 | M12: =IF($D12<>0,L12*75000,IF($E12<>0,L12*75000,0)) -> 0 | N12: 2 | O12: =IF($D12<>0,N12*100000,IF($E12<>0,N12*100000,0)) -> 0 | P12: =VLOOKUP(A12,[14]TONTMAI24!$A$6:$R$39,12,0) -> 0 | Q12: =VLOOKUP(A12,[15]TONTMAI24!$A$7:$P$23,10,0) -> 0 | R12: =VLOOKUP(A12,[16]TONTMAI24!$A$7:$P$20,10,0) -> 0 | U12: =G12+S12++R12+P12+O12+M12+I12+K12+Q12+V12+W12 -> 0 | AQ12: =IF(H12="ECHEC",((K12+M12+O12)*20/100),0) -> 0 | AR12: =IF(H12="ECHEC",((K12+M12+O12)*20/100),0) -> 0 | AS12: =IF(H12="ECHEC",0,(K12+I12-25000)) -> 0 | AW12: =IF(AC12=0,AI12,(1*25000*12)+AI12-AC12) -> 0 | AX12: =IF(AD12=0,AJ12,(1*75000*12)+(AJ12)-AD12) -> 0 | AY12: =IF(AE12=0,AK12,(1*100000*12)+(AK12)-AE12) -> 0 | AZ12: =SUM(AV12:AY12)-BF12+Z12-F12+BH12+BI12+BJ12+BK12+BL12+BM12 -> 0 | BD12: =IF(AZ12=0,(AZ12-BA12-BC12),(AZ12-BA12-BB12-BC12)) -> 0 | BF12: =Z12*1/100*BG12 -> 0 | BG12: 7 | BN12: SIME MATHIEU | BO12: NGONGANG JEAN THEODORE
A13: AS201601 | B13: =VLOOKUP(A13,[11]LISTADHERENT!A$5:H$50,3,0) -> DOMOU FABIEN | C13: =D13+E13+F13-U13-BB13 -> 0 | D13: =VLOOKUP(A13,[12]HISTOBQUEAVRIL24!$A$6:$G$46,3,0) -> 0 | E13: =VLOOKUP(A13,[12]HISTOBQUEAVRIL24!$A$6:$G$41,4,0) -> 0 | F13: =VLOOKUP(A13,[12]HISTOBQUEAVRIL24!$A$6:$G$41,5,0) -> 0 | G13: =IF(H13="ESPECES",3000,0) -> 0 | H13: =IF($D13<>0,"BANQUE",IF($E13<>0,"ESPECES","ECHEC")) -> ECHEC | J13: 1 | K13: =IF($D13<>0,J13*50000,IF($E13<>0,J13*50000,0)) -> 0 | M13: =IF($D13<>0,L13*75000,IF($E13<>0,L13*75000,0)) -> 0 | O13: =IF($D13<>0,N13*100000,IF($E13<>0,N13*100000,0)) -> 0 | P13: =VLOOKUP(A13,[14]TONTMAI24!$A$6:$R$39,12,0) -> 0 | U13: =G13+S13++R13+P13+O13+M13+I13+K13+Q13+V13+W13 -> 0 | AQ13: =IF(H13="ECHEC",((K13+M13+O13)*20/100),0) -> 0 | AR13: =IF(H13="ECHEC",((K13+M13+O13)*20/100),0) -> 0 | AS13: =IF(H13="ECHEC",0,(K13+I13-25000)) -> 0 | AW13: =IF(AC13=0,AI13,(1*25000*12)+AI13-AC13) -> 0 | AX13: =IF(AD13=0,AJ13,(1*75000*12)+(AJ13)-AD13) -> 0 | AY13: =IF(AE13=0,AK13,(1*100000*12)+(AK13)-AE13) -> 0 | AZ13: =SUM(AV13:AY13)-BF13+Z13-F13+BH13+BI13+BJ13+BK13+BL13+BM13 -> 0 | BD13: =IF(AZ13=0,(AZ13-BA13-BC13),(AZ13-BA13-BB13-BC13)) -> 0 | BF13: =Z13*1/100*BG13 -> 0 | BG13: 7 | BN13: FONDSCAISSE | BO13: NGONGANG JEAN THEODORE
A14: ECHEC | B14: =VLOOKUP(A14,[11]LISTADHERENT!A$5:H$50,3,0) -> DONHOU DAVID | C14: =D14+E14+F14-U14-BB14 -> 0 | D14: =VLOOKUP(A14,[12]HISTOBQUEAVRIL24!$A$6:$G$46,3,0) -> 0 | E14: =VLOOKUP(A14,[12]HISTOBQUEAVRIL24!$A$6:$G$41,4,0) -> 0 | F14: =VLOOKUP(A14,[12]HISTOBQUEAVRIL24!$A$6:$G$41,5,0) -> 0 | G14: =IF(H14="ESPECES",3000,0) -> 0 | H14: =IF($D14<>0,"BANQUE",IF($E14<>0,"ESPECES","ECHEC")) -> ECHEC | J14: 1 | K14: =IF($D14<>0,J14*50000,IF($E14<>0,J14*50000,0)) -> 0 | M14: =IF($D14<>0,L14*75000,IF($E14<>0,L14*75000,0)) -> 0 | O14: =IF($D14<>0,N14*100000,IF($E14<>0,N14*100000,0)) -> 0 | P14: =VLOOKUP(A14,[14]TONTMAI24!$A$6:$R$39,12,0) -> 0 | U14: =G14+S14++R14+P14+O14+M14+I14+K14+Q14+V14+W14 -> 0 | AQ14: =IF(H14="ECHEC",((K14+M14+O14)*20/100),0) -> 0 | AR14: =IF(H14="ECHEC",((K14+M14+O14)*20/100),0) -> 0 | AS14: =IF(H14="ECHEC",0,(K14+I14-25000)) -> 0 | AW14: =IF(AC14=0,AI14,(1*25000*12)+AI14-AC14) -> 0 | AX14: =IF(AD14=0,AJ14,(1*75000*12)+(AJ14)-AD14) -> 0 | AY14: =IF(AE14=0,AK14,(1*100000*12)+(AK14)-AE14) -> 0 | AZ14: =SUM(AV14:AY14)-BF14+Z14-F14+BH14+BI14+BJ14+BK14+BL14+BM14 -> 0 | BD14: =IF(AZ14=0,(AZ14-BA14-BC14),(AZ14-BA14-BB14-BC14)) -> 0 | BF14: =Z14*1/100*BG14 -> 0 | BG14: 7 | BN14: TCHOUAMOU MATHIEU | BO14: NGONGANG JEAN THEODORE
A15: ESPECES | B15: =VLOOKUP(A15,[11]LISTADHERENT!A$5:H$50,3,0) -> HENGUE PAUL OMER | C15: =D15+E15+F15-U15-BB15 -> 0 | D15: =VLOOKUP(A15,[12]HISTOBQUEAVRIL24!$A$6:$G$46,3,0) -> 0 | E15: =VLOOKUP(A15,[12]HISTOBQUEAVRIL24!$A$6:$G$41,4,0) -> 0 | F15: =VLOOKUP(A15,[12]HISTOBQUEAVRIL24!$A$6:$G$41,5,0) -> 0 | G15: =IF(H15="ESPECES",3000,0) -> 0 | H15: =IF($D15<>0,"BANQUE",IF($E15<>0,"ESPECES","ECHEC")) -> ECHEC | J15: 1 | K15: =IF($D15<>0,J15*50000,IF($E15<>0,J15*50000,0)) -> 0 | L15: 1 | M15: =IF($D15<>0,L15*75000,IF($E15<>0,L15*75000,0)) -> 0 | O15: =IF($D15<>0,N15*100000,IF($E15<>0,N15*100000,0)) -> 0 | P15: =VLOOKUP(A15,[14]TONTMAI24!$A$6:$R$39,12,0) -> 0 | Q15: =VLOOKUP(A15,[15]TONTMAI24!$A$7:$P$23,10,0) -> 0 | U15: =G15+S15++R15+P15+O15+M15+I15+K15+Q15+V15+W15 -> 0 | AQ15: =IF(H15="ECHEC",((K15+M15+O15)*20/100),0) -> 0 | AR15: =IF(H15="ECHEC",((K15+M15+O15)*20/100),0) -> 0 | AS15: =IF(H15="ECHEC",0,(K15+I15-25000)) -> 0 | AW15: =IF(AC15=0,AI15,(1*25000*12)+AI15-AC15) -> 0 | AX15: =IF(AD15=0,AJ15,(1*75000*12)+(AJ15)-AD15) -> 0 | AY15: =IF(AE15=0,AK15,(1*100000*12)+(AK15)-AE15) -> 0 | AZ15: =SUM(AV15:AY15)-BF15+Z15-F15+BH15+BI15+BJ15+BK15+BL15+BM15 -> 0 | BD15: =IF(AZ15=0,(AZ15-BA15-BC15),(AZ15-BA15-BB15-BC15)) -> 0 | BF15: =Z15*1/100*BG15 -> 0 | BG15: 7
A16: AS201603 | B16: =VLOOKUP(A16,[11]LISTADHERENT!A$5:H$50,3,0) -> HOTCHO BENJAMIN | C16: =D16+E16+F16-U16-BB16 -> 0 | D16: =VLOOKUP(A16,[12]HISTOBQUEAVRIL24!$A$6:$G$46,3,0) -> 0 | E16: =VLOOKUP(A16,[12]HISTOBQUEAVRIL24!$A$6:$G$41,4,0) -> 0 | F16: =VLOOKUP(A16,[12]HISTOBQUEAVRIL24!$A$6:$G$41,5,0) -> 0 | G16: =IF(H16="ESPECES",3000,0) -> 0 | H16: =IF($D16<>0,"BANQUE",IF($E16<>0,"ESPECES","ECHEC")) -> ECHEC | J16: 1 | K16: =IF($D16<>0,J16*50000,IF($E16<>0,J16*50000,0)) -> 0 | L16: 1 | M16: =IF($D16<>0,L16*75000,IF($E16<>0,L16*75000,0)) -> 0 | N16: 1 | O16: =IF($D16<>0,N16*100000,IF($E16<>0,N16*100000,0)) -> 0 | P16: =VLOOKUP(A16,[14]TONTMAI24!$A$6:$R$39,12,0) -> 0 | Q16: =VLOOKUP(A16,[15]TONTMAI24!$A$7:$P$23,10,0) -> 0 | R16: =VLOOKUP(A16,[16]TONTFEV24!$A$7:$P$20,10,0) -> 0 | U16: =G16+S16++R16+P16+O16+M16+I16+K16+Q16+V16+W16 -> 0 | AQ16: =IF(H16="ECHEC",((K16+M16+O16)*20/100),0) -> 0 | AR16: =IF(H16="ECHEC",((K16+M16+O16)*20/100),0) -> 0 | AS16: =IF(H16="ECHEC",0,(K16+I16-25000)) -> 0 | AW16: =IF(AC16=0,AI16,(1*25000*12)+AI16-AC16) -> 0 | AX16: =IF(AD16=0,AJ16,(1*75000*12)+(AJ16)-AD16) -> 0 | AY16: =IF(AE16=0,AK16,(1*100000*12)+(AK16)-AE16) -> 0 | AZ16: =SUM(AV16:AY16)-BF16+Z16-F16+BH16+BI16+BJ16+BK16+BL16+BM16 -> 0 | BD16: =IF(AZ16=0,(AZ16-BA16-BC16),(AZ16-BA16-BB16-BC16)) -> 0 | BF16: =Z16*1/100*BG16 -> 0 | BG16: 7 | BN16: INTERET | BP16: =SUM(BP6:BP15) -> 0
A17: BANQUE | B17: =VLOOKUP(A17,[11]LISTADHERENT!A$5:H$50,3,0) -> KOUAMOU MOISE | C17: =D17+E17+F17-U17-BB17 -> 0 | D17: =VLOOKUP(A17,[12]HISTOBQUEAVRIL24!$A$6:$G$46,3,0) -> 0 | E17: =VLOOKUP(A17,[12]HISTOBQUEAVRIL24!$A$6:$G$41,4,0) -> 0 | F17: =VLOOKUP(A17,[12]HISTOBQUEAVRIL24!$A$6:$G$41,5,0) -> 0 | G17: =IF(H17="ESPECES",3000,0) -> 0 | H17: =IF($D17<>0,"BANQUE",IF($E17<>0,"ESPECES","ECHEC")) -> ECHEC | J17: 1 | K17: =IF($D17<>0,J17*50000,IF($E17<>0,J17*50000,0)) -> 0 | M17: =IF($D17<>0,L17*75000,IF($E17<>0,L17*75000,0)) -> 0 | N17: 1 | O17: =IF($D17<>0,N17*100000,IF($E17<>0,N17*100000,0)) -> 0 | P17: =VLOOKUP(A17,[14]TONTMAI24!$A$6:$R$39,12,0) -> 0 | R17: =VLOOKUP(A17,[16]TONTMAI24!$A$7:$P$20,10,0) -> 0 | U17: =G17+S17++R17+P17+O17+M17+I17+K17+Q17+V17+W17 -> 0 | AQ17: =IF(H17="ECHEC",((K17+M17+O17)*20/100),0) -> 0 | AR17: =IF(H17="ECHEC",((K17+M17+O17)*20/100),0) -> 0 | AS17: =IF(H17="ECHEC",0,(K17+I17-25000)) -> 0 | AW17: =IF(AC17=0,AI17,(1*25000*12)+AI17-AC17) -> 0 | AX17: =IF(AD17=0,AJ17,(1*75000*12)+(AJ17)-AD17) -> 0 | AY17: =IF(AE17=0,AK17,(1*100000*12)+(AK17)-AE17) -> 0 | AZ17: =SUM(AV17:AY17)-BF17+Z17-F17+BH17+BI17+BJ17+BK17+BL17+BM17 -> 0 | BD17: =IF(AZ17=0,(AZ17-BA17-BC17),(AZ17-BA17-BB17-BC17)) -> 0 | BF17: =Z17*1/100*BG17 -> 0 | BG17: 7
A18: AS201604 | B18: =VLOOKUP(A18,[11]LISTADHERENT!A$5:H$50,3,0) -> KOUATCHO MESSACK | C18: =D18+E18+F18-U18-BB18 -> 0 | D18: =VLOOKUP(A18,[12]HISTOBQUEAVRIL24!$A$6:$G$46,3,0) -> 0 | E18: =VLOOKUP(A18,[12]HISTOBQUEAVRIL24!$A$6:$G$41,4,0) -> 0 | F18: =VLOOKUP(A18,[12]HISTOBQUEAVRIL24!$A$6:$G$41,5,0) -> 0 | G18: =IF(H18="ESPECES",3000,0) -> 0 | H18: =IF($D18<>0,"BANQUE",IF($E18<>0,"ESPECES","ECHEC")) -> ECHEC | J18: 1 | K18: =IF($D18<>0,J18*50000,IF($E18<>0,J18*50000,0)) -> 0 | M18: =IF($D18<>0,L18*75000,IF($E18<>0,L18*75000,0)) -> 0 | N18: 1 | O18: =IF($D18<>0,N18*100000,IF($E18<>0,N18*100000,0)) -> 0 | P18: =VLOOKUP(A18,[14]TONTMAI24!$A$6:$R$39,12,0) -> 0 | R18: =VLOOKUP(A18,[16]TONTMAI24!$A$7:$P$20,10,0) -> 0 | U18: =G18+S18++R18+P18+O18+M18+I18+K18+Q18+V18+W18 -> 0 | AQ18: =IF(H18="ECHEC",((K18+M18+O18)*20/100),0) -> 0 | AR18: =IF(H18="ECHEC",((K18+M18+O18)*20/100),0) -> 0 | AS18: =IF(H18="ECHEC",0,(K18+I18-25000)) -> 0 | AW18: =IF(AC18=0,AI18,(1*25000*12)+AI18-AC18) -> 0 | AX18: =IF(AD18=0,AJ18,(1*75000*12)+(AJ18)-AD18) -> 0 | AY18: =IF(AE18=0,AK18,(1*100000*12)+(AK18)-AE18) -> 0 | AZ18: =SUM(AV18:AY18)-BF18+Z18-F18+BH18+BI18+BJ18+BK18+BL18+BM18 -> 0 | BD18: =IF(AZ18=0,(AZ18-BA18-BC18),(AZ18-BA18-BB18-BC18)) -> 0 | BF18: =Z18*1/100*BG18 -> 0 | BG18: 7 | BN18: MONTANT_MUTUELLE | BO18: AS201633
A19: MOIS | B19: =VLOOKUP(A19,[11]LISTADHERENT!A$5:H$50,3,0) -> MASSEUNGOUE DAGOBERT | C19: =D19+E19+F19-U19-BB19 -> 0 | D19: =VLOOKUP(A19,[12]HISTOBQUEAVRIL24!$A$6:$G$46,3,0) -> 0 | E19: =VLOOKUP(A19,[12]HISTOBQUEAVRIL24!$A$6:$G$41,4,0) -> 0 | F19: =VLOOKUP(A19,[12]HISTOBQUEAVRIL24!$A$6:$G$41,5,0) -> 0 | G19: =IF(H19="ESPECES",3000,0) -> 0 | H19: =IF($D19<>0,"BANQUE",IF($E19<>0,"ESPECES","ECHEC")) -> ECHEC | J19: 1 | K19: =IF($D19<>0,J19*50000,IF($E19<>0,J19*50000,0)) -> 0 | M19: =IF($D19<>0,L19*75000,IF($E19<>0,L19*75000,0)) -> 0 | O19: =IF($D19<>0,N19*100000,IF($E19<>0,N19*100000,0)) -> 0 | P19: =VLOOKUP(A19,[14]TONTMAI24!$A$6:$R$39,12,0) -> 0 | U19: =G19+S19++R19+P19+O19+M19+I19+K19+Q19+V19+W19 -> 0 | AQ19: =IF(H19="ECHEC",((K19+M19+O19)*20/100),0) -> 0 | AR19: =IF(H19="ECHEC",((K19+M19+O19)*20/100),0) -> 0 | AS19: =IF(H19="ECHEC",0,(K19+I19-25000)) -> 0 | AW19: =IF(AC19=0,AI19,(1*25000*12)+AI19-AC19) -> 0 | AX19: =IF(AD19=0,AJ19,(1*75000*12)+(AJ19)-AD19) -> 0 | AY19: =IF(AE19=0,AK19,(1*100000*12)+(AK19)-AE19) -> 0 | AZ19: =SUM(AV19:AY19)-BF19+Z19-F19+BH19+BI19+BJ19+BK19+BL19+BM19 -> 0 | BD19: =IF(AZ19=0,(AZ19-BA19-BC19),(AZ19-BA19-BB19-BC19)) -> 0 | BF19: =Z19*1/100*BG19 -> 0 | BG19: 7
A20: AS201608 | B20: =VLOOKUP(A20,[11]LISTADHERENT!A$5:H$50,3,0) -> MBOGNING TUGMA GUY | C20: =D20+E20+F20-U20-BB20 -> 0 | D20: =VLOOKUP(A20,[12]HISTOBQUEAVRIL24!$A$6:$G$46,3,0) -> 0 | E20: =VLOOKUP(A20,[12]HISTOBQUEAVRIL24!$A$6:$G$41,4,0) -> 0 | F20: =VLOOKUP(A20,[12]HISTOBQUEAVRIL24!$A$6:$G$41,5,0) -> 0 | G20: =IF(H20="ESPECES",3000,0) -> 0 | H20: =IF($D20<>0,"BANQUE",IF($E20<>0,"ESPECES","ECHEC")) -> ECHEC | J20: 1 | K20: =IF($D20<>0,J20*50000,IF($E20<>0,J20*50000,0)) -> 0 | L20: 1 | M20: =IF($D20<>0,L20*75000,IF($E20<>0,L20*75000,0)) -> 0 | N20: 1 | O20: =IF($D20<>0,N20*100000,IF($E20<>0,N20*100000,0)) -> 0 | P20: =VLOOKUP(A20,[14]TONTMAI24!$A$6:$R$39,12,0) -> 0 | Q20: =VLOOKUP(A20,[15]TONTMAI24!$A$7:$P$23,10,0) -> 0 | R20: =VLOOKUP(A20,[16]TONTMAI24!$A$7:$P$20,10,0) -> 0 | U20: =G20+S20++R20+P20+O20+M20+I20+K20+Q20+V20+W20 -> 0 | AQ20: =IF(H20="ECHEC",((K20+M20+O20)*20/100),0) -> 0 | AR20: =IF(H20="ECHEC",((K20+M20+O20)*20/100),0) -> 0 | AS20: =IF(H20="ECHEC",0,(K20+I20-25000)) -> 0 | AW20: =IF(AC20=0,AI20,(1*25000*12)+AI20-AC20) -> 0 | AX20: =IF(AD20=0,AJ20,(1*75000*12)+(AJ20)-AD20) -> 0 | AY20: =IF(AE20=0,AK20,(1*100000*12)+(AK20)-AE20) -> 0 | AZ20: =SUM(AV20:AY20)-BF20+Z20-F20+BH20+BI20+BJ20+BK20+BL20+BM20 -> 0 | BD20: =IF(AZ20=0,(AZ20-BA20-BC20),(AZ20-BA20-BB20-BC20)) -> 0 | BF20: =Z20*1/100*BG20 -> 0 | BG20: 7
A21: AS201609 | B21: =VLOOKUP(A21,[11]LISTADHERENT!A$5:H$50,3,0) -> NANGUEN MARTIN | C21: =D21+E21+F21-U21-BB21 -> 0 | D21: =VLOOKUP(A21,[12]HISTOBQUEAVRIL24!$A$6:$G$46,3,0) -> 0 | E21: =VLOOKUP(A21,[12]HISTOBQUEAVRIL24!$A$6:$G$41,4,0) -> 0 | F21: =VLOOKUP(A21,[12]HISTOBQUEAVRIL24!$A$6:$G$41,5,0) -> 0 | G21: =IF(H21="ESPECES",3000,0) -> 0 | H21: =IF($D21<>0,"BANQUE",IF($E21<>0,"ESPECES","ECHEC")) -> ECHEC | J21: 1 | K21: =IF($D21<>0,J21*50000,IF($E21<>0,J21*50000,0)) -> 0 | M21: =IF($D21<>0,L21*75000,IF($E21<>0,L21*75000,0)) -> 0 | O21: =IF($D21<>0,N21*100000,IF($E21<>0,N21*100000,0)) -> 0 | P21: =VLOOKUP(A21,[14]TONTMAI24!$A$6:$R$39,12,0) -> 0 | U21: =G21+S21++R21+P21+O21+M21+I21+K21+Q21+V21+W21 -> 0 | AQ21: =IF(H21="ECHEC",((K21+M21+O21)*20/100),0) -> 0 | AR21: =IF(H21="ECHEC",((K21+M21+O21)*20/100),0) -> 0 | AS21: =IF(H21="ECHEC",0,(K21+I21-25000)) -> 0 | AW21: =IF(AC21=0,AI21,(1*25000*12)+AI21-AC21) -> 0 | AX21: =IF(AD21=0,AJ21,(1*75000*12)+(AJ21)-AD21) -> 0 | AY21: =IF(AE21=0,AK21,(1*100000*12)+(AK21)-AE21) -> 0 | AZ21: =SUM(AV21:AY21)-BF21+Z21-F21+BH21+BI21+BJ21+BK21+BL21+BM21 -> 0 | BD21: =IF(AZ21=0,(AZ21-BA21-BC21),(AZ21-BA21-BB21-BC21)) -> 0 | BF21: =Z21*1/100*BG21 -> 0 | BG21: 7
A22: AS201610 | B22: =VLOOKUP(A22,[11]LISTADHERENT!A$5:H$50,3,0) -> NANKAM APPOLINAIRE | C22: =D22+E22+F22-U22-BB22 -> 0 | D22: =VLOOKUP(A22,[12]HISTOBQUEAVRIL24!$A$6:$G$46,3,0) -> 0 | E22: =VLOOKUP(A22,[12]HISTOBQUEAVRIL24!$A$6:$G$41,4,0) -> 0 | F22: =VLOOKUP(A22,[12]HISTOBQUEAVRIL24!$A$6:$G$41,5,0) -> 0 | G22: =IF(H22="ESPECES",3000,0) -> 0 | H22: =IF($D22<>0,"BANQUE",IF($E22<>0,"ESPECES","ECHEC")) -> ECHEC | J22: 1 | K22: =IF($D22<>0,J22*50000,IF($E22<>0,J22*50000,0)) -> 0 | L22: 1 | M22: =IF($D22<>0,L22*75000,IF($E22<>0,L22*75000,0)) -> 0 | O22: =IF($D22<>0,N22*100000,IF($E22<>0,N22*100000,0)) -> 0 | P22: =VLOOKUP(A22,[14]TONTMAI24!$A$6:$R$39,12,0) -> 0 | Q22: =VLOOKUP(A22,[15]TONTMAI24!$A$7:$P$23,10,0) -> 0 | U22: =G22+S22++R22+P22+O22+M22+I22+K22+Q22+V22+W22 -> 0 | AQ22: =IF(H22="ECHEC",((K22+M22+O22)*20/100),0) -> 0 | AR22: =IF(H22="ECHEC",((K22+M22+O22)*20/100),0) -> 0 | AS22: =IF(H22="ECHEC",0,(K22+I22-25000)) -> 0 | AW22: =IF(AC22=0,AI22,(1*25000*12)+AI22-AC22) -> 0 | AX22: =IF(AD22=0,AJ22,(1*75000*12)+(AJ22)-AD22) -> 0 | AY22: =IF(AE22=0,AK22,(1*100000*12)+(AK22)-AE22) -> 0 | AZ22: =SUM(AV22:AY22)-BF22+Z22-F22+BH22+BI22+BJ22+BK22+BL22+BM22 -> 0 | BD22: =IF(AZ22=0,(AZ22-BA22-BC22),(AZ22-BA22-BB22-BC22)) -> 0 | BF22: =Z22*1/100*BG22 -> 0 | BG22: 7 | BN22: INTERET | BP22: =SUM(BP18:BP21) -> 0
A23: AS201611 | B23: =VLOOKUP(A23,[11]LISTADHERENT!A$5:H$50,3,0) -> NDJOMO ETIENNE | C23: =D23+E23+F23-U23-BB23 -> 0 | D23: =VLOOKUP(A23,[12]HISTOBQUEAVRIL24!$A$6:$G$46,3,0) -> 0 | E23: =VLOOKUP(A23,[12]HISTOBQUEAVRIL24!$A$6:$G$41,4,0) -> 0 | F23: =VLOOKUP(A23,[12]HISTOBQUEAVRIL24!$A$6:$G$41,5,0) -> 0 | G23: =IF(H23="ESPECES",3000,0) -> 0 | H23: =IF($D23<>0,"BANQUE",IF($E23<>0,"ESPECES","ECHEC")) -> ECHEC | J23: 1 | K23: =IF($D23<>0,J23*50000,IF($E23<>0,J23*50000,0)) -> 0 | M23: =IF($D23<>0,L23*75000,IF($E23<>0,L23*75000,0)) -> 0 | N23: 2 | O23: =IF($D23<>0,N23*100000,IF($E23<>0,N23*100000,0)) -> 0 | P23: =VLOOKUP(A23,[14]TONTMAI24!$A$6:$R$39,12,0) -> 0 | R23: =VLOOKUP(A23,[16]TONTMAI24!$A$7:$P$20,10,0) -> 0 | U23: =G23+S23++R23+P23+O23+M23+I23+K23+Q23+V23+W23 -> 0 | AQ23: =IF(H23="ECHEC",((K23+M23+O23)*20/100),0) -> 0 | AR23: =IF(H23="ECHEC",((K23+M23+O23)*20/100),0) -> 0 | AS23: =IF(H23="ECHEC",0,(K23+I23-25000)) -> 0 | AW23: =IF(AC23=0,AI23,(1*25000*12)+AI23-AC23) -> 0 | AX23: =IF(AD23=0,AJ23,(1*75000*12)+(AJ23)-AD23) -> 0 | AY23: =IF(AE23=0,AK23,(1*100000*12)+(AK23)-AE23) -> 0 | AZ23: =SUM(AV23:AY23)-BF23+Z23-F23+BH23+BI23+BJ23+BK23+BL23+BM23 -> 0 | BD23: =IF(AZ23=0,(AZ23-BA23-BC23),(AZ23-BA23-BB23-BC23)) -> 0 | BF23: =Z23*1/100*BG23 -> 0 | BG23: 7
A24: AS201613 | B24: =VLOOKUP(A24,[11]LISTADHERENT!A$5:H$50,3,0) -> NGONDIEP CLAUDE | C24: =D24+E24+F24-U24-BB24 -> 0 | D24: =VLOOKUP(A24,[12]HISTOBQUEAVRIL24!$A$6:$G$46,3,0) -> 0 | E24: =VLOOKUP(A24,[12]HISTOBQUEAVRIL24!$A$6:$G$41,4,0) -> 0 | F24: =VLOOKUP(A24,[12]HISTOBQUEAVRIL24!$A$6:$G$41,5,0) -> 0 | G24: =IF(H24="ESPECES",3000,0) -> 0 | H24: =IF($D24<>0,"BANQUE",IF($E24<>0,"ESPECES","ECHEC")) -> ECHEC | J24: 1 | K24: =IF($D24<>0,J24*50000,IF($E24<>0,J24*50000,0)) -> 0 | L24: 1 | M24: =IF($D24<>0,L24*75000,IF($E24<>0,L24*75000,0)) -> 0 | N24: 1 | O24: =IF($D24<>0,N24*100000,IF($E24<>0,N24*100000,0)) -> 0 | P24: =VLOOKUP(A24,[14]TONTMAI24!$A$6:$R$39,12,0) -> 0 | Q24: =VLOOKUP(A24,[15]TONTMAI24!$A$7:$P$23,10,0) -> 0 | R24: =VLOOKUP(A24,[16]TONTMAI24!$A$7:$P$20,10,0) -> 0 | U24: =G24+S24++R24+P24+O24+M24+I24+K24+Q24+V24+W24 -> 0 | AQ24: =IF(H24="ECHEC",((K24+M24+O24)*20/100),0) -> 0 | AR24: =IF(H24="ECHEC",((K24+M24+O24)*20/100),0) -> 0 | AS24: =IF(H24="ECHEC",0,(K24+I24-25000)) -> 0 | AW24: =IF(AC24=0,AI24,(1*25000*12)+AI24-AC24) -> 0 | AX24: =IF(AD24=0,AJ24,(1*75000*12)+(AJ24)-AD24) -> 0 | AY24: =IF(AE24=0,AK24,(1*100000*12)+(AK24)-AE24) -> 0 | AZ24: =SUM(AV24:AY24)-BF24+Z24-F24+BH24+BI24+BJ24+BK24+BL24+BM24 -> 0 | BD24: =IF(AZ24=0,(AZ24-BA24-BC24),(AZ24-BA24-BB24-BC24)) -> 0 | BF24: =Z24*1/100*BG24 -> 0 | BG24: 7 | BN24: MONTANT_MUTUELLE | BO24: SIMO FONGANG ERIC
A25: AS201614 | B25: =VLOOKUP(A25,[11]LISTADHERENT!A$5:H$50,3,0) -> NGUIEMEGNI MATHIEU BLAISE | C25: =D25+E25+F25-U25-BB25 -> 0 | D25: =VLOOKUP(A25,[12]HISTOBQUEAVRIL24!$A$6:$G$46,3,0) -> 0 | E25: =VLOOKUP(A25,[12]HISTOBQUEAVRIL24!$A$6:$G$41,4,0) -> 0 | F25: =VLOOKUP(A25,[12]HISTOBQUEAVRIL24!$A$6:$G$41,5,0) -> 0 | G25: =IF(H25="ESPECES",3000,0) -> 0 | H25: =IF($D25<>0,"BANQUE",IF($E25<>0,"ESPECES","ECHEC")) -> ECHEC | J25: 1 | K25: =IF($D25<>0,J25*50000,IF($E25<>0,J25*50000,0)) -> 0 | L25: 3 | M25: =IF($D25<>0,L25*75000,IF($E25<>0,L25*75000,0)) -> 0 | N25: 1 | O25: =IF($D25<>0,N25*100000,IF($E25<>0,N25*100000,0)) -> 0 | P25: =VLOOKUP(A25,[14]TONTMAI24!$A$6:$R$39,12,0) -> 0 | Q25: =VLOOKUP(A25,[15]TONTMAI24!$A$7:$P$23,10,0) -> 0 | R25: =VLOOKUP(A25,[16]TONTMAI24!$A$7:$P$20,10,0) -> 0 | U25: =G25+S25++R25+P25+O25+M25+I25+K25+Q25+V25+W25 -> 0 | AQ25: =IF(H25="ECHEC",((K25+M25+O25)*20/100),0) -> 0 | AR25: =IF(H25="ECHEC",((K25+M25+O25)*20/100),0) -> 0 | AS25: =IF(H25="ECHEC",0,(K25+I25-25000)) -> 0 | AW25: =IF(AC25=0,AI25,(1*25000*12)+AI25-AC25) -> 0 | AX25: =IF(AD25=0,AJ25,(1*75000*12)+(AJ25)-AD25) -> 0 | AY25: =IF(AE25=0,AK25,(1*100000*12)+(AK25)-AE25) -> 0 | AZ25: =SUM(AV25:AY25)-BF25+Z25-F25+BH25+BI25+BJ25+BK25+BL25+BM25 -> 0 | BD25: =IF(AZ25=0,(AZ25-BA25-BC25),(AZ25-BA25-BB25-BC25)) -> 0 | BF25: =Z25*1/100*BG25 -> 0 | BG25: 7 | BN25: TIEYAM ERNEST | BO25: SIMO FONGANG ERIC
A26: AS201615 | B26: =VLOOKUP(A26,[11]LISTADHERENT!A$5:H$50,3,0) -> NKAMGANG JUSTIN DEJOLIE | C26: =D26+E26+F26-U26-BB26 -> 0 | D26: =VLOOKUP(A26,[12]HISTOBQUEAVRIL24!$A$6:$G$46,3,0) -> 0 | E26: =VLOOKUP(A26,[12]HISTOBQUEAVRIL24!$A$6:$G$41,4,0) -> 0 | F26: =VLOOKUP(A26,[12]HISTOBQUEAVRIL24!$A$6:$G$41,5,0) -> 0 | G26: =IF(H26="ESPECES",3000,0) -> 0 | H26: =IF($D26<>0,"BANQUE",IF($E26<>0,"ESPECES","ECHEC")) -> ECHEC | J26: 1 | K26: =IF($D26<>0,J26*50000,IF($E26<>0,J26*50000,0)) -> 0 | M26: =IF($D26<>0,L26*75000,IF($E26<>0,L26*75000,0)) -> 0 | O26: =IF($D26<>0,N26*100000,IF($E26<>0,N26*100000,0)) -> 0 | P26: =VLOOKUP(A26,[14]TONTMAI24!$A$6:$R$39,12,0) -> 0 | U26: =G26+S26++R26+P26+O26+M26+I26+K26+Q26+V26+W26 -> 0 | AQ26: =IF(H26="ECHEC",((K26+M26+O26)*20/100),0) -> 0 | AR26: =IF(H26="ECHEC",((K26+M26+O26)*20/100),0) -> 0 | AS26: =IF(H26="ECHEC",0,(K26+I26-25000)) -> 0 | AW26: =IF(AC26=0,AI26,(1*25000*12)+AI26-AC26) -> 0 | AX26: =IF(AD26=0,AJ26,(1*75000*12)+(AJ26)-AD26) -> 0 | AY26: =IF(AE26=0,AK26,(1*100000*12)+(AK26)-AE26) -> 0 | AZ26: =SUM(AV26:AY26)-BF26+Z26-F26+BH26+BI26+BJ26+BK26+BL26+BM26 -> 0 | BD26: =IF(AZ26=0,(AZ26-BA26-BC26),(AZ26-BA26-BB26-BC26)) -> 0 | BF26: =Z26*1/100*BG26 -> 0 | BG26: 7 | BN26: NOM_ET_PRENOM | BO26: SIMO FONGANG ERIC
A27: DETTE CHINGUE | B27: =VLOOKUP(A27,[11]LISTADHERENT!A$5:H$50,3,0) -> NOUBE ETIENNE | C27: =D27+E27+F27-U27-BB27 -> 0 | D27: =VLOOKUP(A27,[12]HISTOBQUEAVRIL24!$A$6:$G$46,3,0) -> 0 | E27: =VLOOKUP(A27,[12]HISTOBQUEAVRIL24!$A$6:$G$41,4,0) -> 0 | F27: =VLOOKUP(A27,[12]HISTOBQUEAVRIL24!$A$6:$G$41,5,0) -> 0 | G27: =IF(H27="ESPECES",3000,0) -> 0 | H27: =IF($D27<>0,"BANQUE",IF($E27<>0,"ESPECES","ECHEC")) -> ECHEC | J27: 1 | K27: =IF($D27<>0,J27*50000,IF($E27<>0,J27*50000,0)) -> 0 | M27: =IF($D27<>0,L27*75000,IF($E27<>0,L27*75000,0)) -> 0 | O27: =IF($D27<>0,N27*100000,IF($E27<>0,N27*100000,0)) -> 0 | P27: =VLOOKUP(A27,[14]TONTMAI24!$A$6:$R$39,12,0) -> 0 | U27: =G27+S27++R27+P27+O27+M27+I27+K27+Q27+V27+W27 -> 0 | AQ27: =IF(H27="ECHEC",((K27+M27+O27)*20/100),0) -> 0 | AR27: =IF(H27="ECHEC",((K27+M27+O27)*20/100),0) -> 0 | AS27: =IF(H27="ECHEC",0,(K27+I27-25000)) -> 0 | AW27: =IF(AC27=0,AI27,(1*25000*12)+AI27-AC27) -> 0 | AX27: =IF(AD27=0,AJ27,(1*75000*12)+(AJ27)-AD27) -> 0 | AY27: =IF(AE27=0,AK27,(1*100000*12)+(AK27)-AE27) -> 0 | AZ27: =SUM(AV27:AY27)-BF27+Z27-F27+BH27+BI27+BJ27+BK27+BL27+BM27 -> 0 | BD27: =IF(AZ27=0,(AZ27-BA27-BC27),(AZ27-BA27-BB27-BC27)) -> 0 | BF27: =Z27*1/100*BG27 -> 0 | BG27: 7
A28: AS201618 | B28: =VLOOKUP(A28,[11]LISTADHERENT!A$5:H$50,3,0) -> PATEGO NJOSSU GUSTAVE | C28: =D28+E28+F28-U28-BB28 -> 0 | D28: =VLOOKUP(A28,[12]HISTOBQUEAVRIL24!$A$6:$G$46,3,0) -> 0 | E28: =VLOOKUP(A28,[12]HISTOBQUEAVRIL24!$A$6:$G$41,4,0) -> 0 | F28: =VLOOKUP(A28,[12]HISTOBQUEAVRIL24!$A$6:$G$41,5,0) -> 0 | G28: =IF(H28="ESPECES",3000,0) -> 0 | H28: =IF($D28<>0,"BANQUE",IF($E28<>0,"ESPECES","ECHEC")) -> ECHEC | J28: 1 | K28: =IF($D28<>0,J28*50000,IF($E28<>0,J28*50000,0)) -> 0 | L28: 1 | M28: =IF($D28<>0,L28*75000,IF($E28<>0,L28*75000,0)) -> 0 | O28: =IF($D28<>0,N28*100000,IF($E28<>0,N28*100000,0)) -> 0 | P28: =VLOOKUP(A28,[14]TONTMAI24!$A$6:$R$39,12,0) -> 0 | Q28: =VLOOKUP(A28,[15]TONTMAI24!$A$7:$P$23,10,0) -> 0 | U28: =G28+S28++R28+P28+O28+M28+I28+K28+Q28+V28+W28 -> 0 | AQ28: =IF(H28="ECHEC",((K28+M28+O28)*20/100),0) -> 0 | AR28: =IF(H28="ECHEC",((K28+M28+O28)*20/100),0) -> 0 | AS28: =IF(H28="ECHEC",0,(K28+I28-25000)) -> 0 | AW28: =IF(AC28=0,AI28,(1*25000*12)+AI28-AC28) -> 0 | AX28: =IF(AD28=0,AJ28,(1*75000*12)+(AJ28)-AD28) -> 0 | AY28: =IF(AE28=0,AK28,(1*100000*12)+(AK28)-AE28) -> 0 | AZ28: =SUM(AV28:AY28)-BF28+Z28-F28+BH28+BI28+BJ28+BK28+BL28+BM28 -> 0 | BD28: =IF(AZ28=0,(AZ28-BA28-BC28),(AZ28-BA28-BB28-BC28)) -> 0 | BF28: =Z28*1/100*BG28 -> 0 | BG28: 7 | BN28: INTERET | BP28: =SUM(BP24:BP26) -> 0
A29: MONTANT DETTE | B29: =VLOOKUP(A29,[11]LISTADHERENT!A$5:H$50,3,0) -> SEUMO POLYCARPE | C29: =D29+E29+F29-U29-BB29 -> 0 | D29: =VLOOKUP(A29,[12]HISTOBQUEAVRIL24!$A$6:$G$46,3,0) -> 0 | E29: =VLOOKUP(A29,[12]HISTOBQUEAVRIL24!$A$6:$G$41,4,0) -> 0 | F29: =VLOOKUP(A29,[12]HISTOBQUEAVRIL24!$A$6:$G$41,5,0) -> 0 | G29: =IF(H29="ESPECES",3000,0) -> 0 | H29: =IF($D29<>0,"BANQUE",IF($E29<>0,"ESPECES","ECHEC")) -> ECHEC | J29: 1 | K29: =IF($D29<>0,J29*50000,IF($E29<>0,J29*50000,0)) -> 0 | M29: =IF($D29<>0,L29*75000,IF($E29<>0,L29*75000,0)) -> 0 | O29: =IF($D29<>0,N29*100000,IF($E29<>0,N29*100000,0)) -> 0 | P29: =VLOOKUP(A29,[14]TONTMAI24!$A$6:$R$39,12,0) -> 0 | U29: =G29+S29++R29+P29+O29+M29+I29+K29+Q29+V29+W29 -> 0 | AQ29: =IF(H29="ECHEC",((K29+M29+O29)*20/100),0) -> 0 | AR29: =IF(H29="ECHEC",((K29+M29+O29)*20/100),0) -> 0 | AS29: =IF(H29="ECHEC",0,(K29+I29-25000)) -> 0 | AW29: =IF(AC29=0,AI29,(1*25000*12)+AI29-AC29) -> 0 | AX29: =IF(AD29=0,AJ29,(1*75000*12)+(AJ29)-AD29) -> 0 | AY29: =IF(AE29=0,AK29,(1*100000*12)+(AK29)-AE29) -> 0 | AZ29: =SUM(AV29:AY29)-BF29+Z29-F29+BH29+BI29+BJ29+BK29+BL29+BM29 -> 0 | BD29: =IF(AZ29=0,(AZ29-BA29-BC29),(AZ29-BA29-BB29-BC29)) -> 0 | BF29: =Z29*1/100*BG29 -> 0 | BG29: 7
A30: AS201619 | B30: =VLOOKUP(A30,[11]LISTADHERENT!A$5:H$50,3,0) -> SIME BRICE | C30: =D30+E30+F30-U30-BB30 -> 0 | D30: =VLOOKUP(A30,[12]HISTOBQUEAVRIL24!$A$6:$G$46,3,0) -> 0 | E30: =VLOOKUP(A30,[12]HISTOBQUEAVRIL24!$A$6:$G$41,4,0) -> 0 | F30: =VLOOKUP(A30,[12]HISTOBQUEAVRIL24!$A$6:$G$41,5,0) -> 0 | G30: =IF(H30="ESPECES",3000,0) -> 0 | H30: =IF($D30<>0,"BANQUE",IF($E30<>0,"ESPECES","ECHEC")) -> ECHEC | J30: 1 | K30: =IF($D30<>0,J30*50000,IF($E30<>0,J30*50000,0)) -> 0 | M30: =IF($D30<>0,L30*75000,IF($E30<>0,L30*75000,0)) -> 0 | N30: 2 | O30: =IF($D30<>0,N30*100000,IF($E30<>0,N30*100000,0)) -> 0 | P30: =VLOOKUP(A30,[14]TONTMAI24!$A$6:$R$39,12,0) -> 0 | R30: =VLOOKUP(A30,[16]TONTMAI24!$A$7:$P$20,10,0) -> 0 | U30: =G30+S30++R30+P30+O30+M30+I30+K30+Q30+V30+W30 -> 0 | AQ30: =IF(H30="ECHEC",((K30+M30+O30)*20/100),0) -> 0 | AR30: =IF(H30="ECHEC",((K30+M30+O30)*20/100),0) -> 0 | AS30: =IF(H30="ECHEC",0,(K30+I30-25000)) -> 0 | AW30: =IF(AC30=0,AI30,(1*25000*12)+AI30-AC30) -> 0 | AX30: =IF(AD30=0,AJ30,(1*75000*12)+(AJ30)-AD30) -> 0 | AY30: =IF(AE30=0,AK30,(1*100000*12)+(AK30)-AE30) -> 0 | AZ30: =SUM(AV30:AY30)-BF30+Z30-F30+BH30+BI30+BJ30+BK30+BL30+BM30 -> 0 | BD30: =IF(AZ30=0,(AZ30-BA30-BC30),(AZ30-BA30-BB30-BC30)) -> 0 | BF30: =Z30*1/100*BG30 -> 0 | BG30: 7 | BN30: TABLEAU RECAPITULATIF PRÊT | BO30: AS201639
A31: AS201621 | B31: =VLOOKUP(A31,[11]LISTADHERENT!A$5:H$50,3,0) -> SIMO PIERRE | C31: =D31+E31+F31-U31-BB31 -> 0 | D31: =VLOOKUP(A31,[12]HISTOBQUEAVRIL24!$A$6:$G$46,3,0) -> 0 | E31: =VLOOKUP(A31,[12]HISTOBQUEAVRIL24!$A$6:$G$41,4,0) -> 0 | F31: =VLOOKUP(A31,[12]HISTOBQUEAVRIL24!$A$6:$G$41,5,0) -> 0 | G31: =IF(H31="ESPECES",3000,0) -> 0 | H31: =IF($D31<>0,"BANQUE",IF($E31<>0,"ESPECES","ECHEC")) -> ECHEC | J31: 1 | K31: =IF($D31<>0,J31*50000,IF($E31<>0,J31*50000,0)) -> 0 | M31: =IF($D31<>0,L31*75000,IF($E31<>0,L31*75000,0)) -> 0 | N31: 1 | O31: =IF($D31<>0,N31*100000,IF($E31<>0,N31*100000,0)) -> 0 | P31: =VLOOKUP(A31,[14]TONTMAI24!$A$6:$R$39,12,0) -> 0 | R31: =VLOOKUP(A31,[16]TONTMAI24!$A$7:$P$20,10,0) -> 0 | U31: =G31+S31++R31+P31+O31+M31+I31+K31+Q31+V31+W31 -> 0 | AQ31: =IF(H31="ECHEC",((K31+M31+O31)*20/100),0) -> 0 | AR31: =IF(H31="ECHEC",((K31+M31+O31)*20/100),0) -> 0 | AS31: =IF(H31="ECHEC",0,(K31+I31-25000)) -> 0 | AW31: =IF(AC31=0,AI31,(1*25000*12)+AI31-AC31) -> 0 | AX31: =IF(AD31=0,AJ31,(1*75000*12)+(AJ31)-AD31) -> 0 | AY31: =IF(AE31=0,AK31,(1*100000*12)+(AK31)-AE31) -> 0 | AZ31: =SUM(AV31:AY31)-BF31+Z31-F31+BH31+BI31+BJ31+BK31+BL31+BM31 -> 0 | BD31: =IF(AZ31=0,(AZ31-BA31-BC31),(AZ31-BA31-BB31-BC31)) -> 0 | BF31: =Z31*1/100*BG31 -> 0 | BG31: 7 | BN31: A APURER | BO31: AS201639
A32: AS201622 | B32: =VLOOKUP(A32,[11]LISTADHERENT!A$5:H$50,3,0) -> TCHOUAMOU MATHIEU | C32: =D32+E32+F32-U32-BB32 -> 0 | D32: =VLOOKUP(A32,[12]HISTOBQUEAVRIL24!$A$6:$G$46,3,0) -> 0 | E32: =VLOOKUP(A32,[12]HISTOBQUEAVRIL24!$A$6:$G$41,4,0) -> 0 | F32: =VLOOKUP(A32,[12]HISTOBQUEAVRIL24!$A$6:$G$41,5,0) -> 0 | G32: =IF(H32="ESPECES",3000,0) -> 0 | H32: =IF($D32<>0,"BANQUE",IF($E32<>0,"ESPECES","ECHEC")) -> ECHEC | J32: 1 | K32: =IF($D32<>0,J32*50000,IF($E32<>0,J32*50000,0)) -> 0 | L32: 1 | M32: =IF($D32<>0,L32*75000,IF($E32<>0,L32*75000,0)) -> 0 | O32: =IF($D32<>0,N32*100000,IF($E32<>0,N32*100000,0)) -> 0 | P32: =VLOOKUP(A32,[14]TONTMAI24!$A$6:$R$39,12,0) -> 0 | Q32: =VLOOKUP(A32,[15]TONTMAI24!$A$7:$P$23,10,0) -> 0 | U32: =G32+S32++R32+P32+O32+M32+I32+K32+Q32+V32+W32 -> 0 | AQ32: =IF(H32="ECHEC",((K32+M32+O32)*20/100),0) -> 0 | AR32: =IF(H32="ECHEC",((K32+M32+O32)*20/100),0) -> 0 | AS32: =IF(H32="ECHEC",0,(K32+I32-25000)) -> 0 | AW32: =IF(AC32=0,AI32,(1*25000*12)+AI32-AC32) -> 0 | AX32: =IF(AD32=0,AJ32,(1*75000*12)+(AJ32)-AD32) -> 0 | AY32: =IF(AE32=0,AK32,(1*100000*12)+(AK32)-AE32) -> 0 | AZ32: =SUM(AV32:AY32)-BF32+Z32-F32+BH32+BI32+BJ32+BK32+BL32+BM32 -> 0 | BD32: =IF(AZ32=0,(AZ32-BA32-BC32),(AZ32-BA32-BB32-BC32)) -> 0 | BF32: =Z32*1/100*BG32 -> 0 | BG32: 7 | BN32: AOÛT
A33: SOLDE | B33: =VLOOKUP(A33,[11]LISTADHERENT!A$5:H$50,3,0) -> TCHOUATEU AUGUSTIN | C33: =D33+E33+F33-U33-BB33 -> 0 | D33: =VLOOKUP(A33,[12]HISTOBQUEAVRIL24!$A$6:$G$46,3,0) -> 0 | E33: =VLOOKUP(A33,[12]HISTOBQUEAVRIL24!$A$6:$G$41,4,0) -> 0 | F33: =VLOOKUP(A33,[12]HISTOBQUEAVRIL24!$A$6:$G$41,5,0) -> 0 | G33: =IF(H33="ESPECES",3000,0) -> 0 | H33: =IF($D33<>0,"BANQUE",IF($E33<>0,"ESPECES","ECHEC")) -> ECHEC | J33: 1 | K33: =IF($D33<>0,J33*50000,IF($E33<>0,J33*50000,0)) -> 0 | M33: =IF($D33<>0,L33*75000,IF($E33<>0,L33*75000,0)) -> 0 | N33: 1 | O33: =IF($D33<>0,N33*100000,IF($E33<>0,N33*100000,0)) -> 0 | P33: =VLOOKUP(A33,[14]TONTMAI24!$A$6:$R$39,12,0) -> 0 | R33: =VLOOKUP(A33,[16]TONTMAI24!$A$7:$P$20,10,0) -> 0 | U33: =G33+S33++R33+P33+O33+M33+I33+K33+Q33+V33+W33 -> 0 | AQ33: =IF(H33="ECHEC",((K33+M33+O33)*20/100),0) -> 0 | AR33: =IF(H33="ECHEC",((K33+M33+O33)*20/100),0) -> 0 | AS33: =IF(H33="ECHEC",0,(K33+I33-25000)) -> 0 | AW33: =IF(AC33=0,AI33,(1*25000*12)+AI33-AC33) -> 0 | AX33: =IF(AD33=0,AJ33,(1*75000*12)+(AJ33)-AD33) -> 0 | AY33: =IF(AE33=0,AK33,(1*100000*12)+(AK33)-AE33) -> 0 | AZ33: =SUM(AV33:AY33)-BF33+Z33-F33+BH33+BI33+BJ33+BK33+BL33+BM33 -> 0 | BD33: =IF(AZ33=0,(AZ33-BA33-BC33),(AZ33-BA33-BB33-BC33)) -> 0 | BF33: =Z33*1/100*BG33 -> 0 | BG33: 7 | BN33: INTERET | BP33: =SUM(BP30:BP32) -> 0
A34: AOUT 2018 A NOVEMBRE 2019 | B34: =VLOOKUP(A34,[11]LISTADHERENT!A$5:H$50,3,0) -> TCHOUTOU NANA CLAUDE | C34: =D34+E34+F34-U34-BB34 -> 0 | D34: =VLOOKUP(A34,[12]HISTOBQUEAVRIL24!$A$6:$G$46,3,0) -> 0 | E34: =VLOOKUP(A34,[12]HISTOBQUEAVRIL24!$A$6:$G$41,4,0) -> 0 | F34: =VLOOKUP(A34,[12]HISTOBQUEAVRIL24!$A$6:$G$41,5,0) -> 0 | G34: =IF(H34="ESPECES",3000,0) -> 0 | H34: =IF($D34<>0,"BANQUE",IF($E34<>0,"ESPECES","ECHEC")) -> ECHEC | J34: 1 | K34: =IF($D34<>0,J34*50000,IF($E34<>0,J34*50000,0)) -> 0 | M34: =IF($D34<>0,L34*75000,IF($E34<>0,L34*75000,0)) -> 0 | O34: =IF($D34<>0,N34*100000,IF($E34<>0,N34*100000,0)) -> 0 | P34: =VLOOKUP(A34,[14]TONTMAI24!$A$6:$R$39,12,0) -> 0 | U34: =G34+S34++R34+P34+O34+M34+I34+K34+Q34+V34+W34 -> 0 | AQ34: =IF(H34="ECHEC",((K34+M34+O34)*20/100),0) -> 0 | AR34: =IF(H34="ECHEC",((K34+M34+O34)*20/100),0) -> 0 | AS34: =IF(H34="ECHEC",0,(K34+I34-25000)) -> 0 | AW34: =IF(AC34=0,AI34,(1*25000*12)+AI34-AC34) -> 0 | AX34: =IF(AD34=0,AJ34,(1*75000*12)+(AJ34)-AD34) -> 0 | AY34: =IF(AE34=0,AK34,(1*100000*12)+(AK34)-AE34) -> 0 | AZ34: =SUM(AV34:AY34)-BF34+Z34-F34+BH34+BI34+BJ34+BK34+BL34+BM34 -> 0 | BD34: =IF(AZ34=0,(AZ34-BA34-BC34),(AZ34-BA34-BB34-BC34)) -> 0 | BF34: =Z34*1/100*BG34 -> 0 | BG34: 7 | BN34: INTERET | BP34: =SUM(BP31:BP33) -> 0
A35: REMBOURSEMENT | B35: =VLOOKUP(A35,[11]LISTADHERENT!A$5:H$50,3,0) -> YANTCHOU GERVAIS | C35: =D35+E35+F35-U35-BB35 -> 0 | D35: =VLOOKUP(A35,[12]HISTOBQUEAVRIL24!$A$6:$G$46,3,0) -> 0 | E35: =VLOOKUP(A35,[12]HISTOBQUEAVRIL24!$A$6:$G$41,4,0) -> 0 | F35: =VLOOKUP(A35,[12]HISTOBQUEAVRIL24!$A$6:$G$41,5,0) -> 0 | G35: =IF(H35="ESPECES",3000,0) -> 0 | H35: =IF($D35<>0,"BANQUE",IF($E35<>0,"ESPECES","ECHEC")) -> ECHEC | J35: 1 | K35: =IF($D35<>0,J35*50000,IF($E35<>0,J35*50000,0)) -> 0 | M35: =IF($D35<>0,L35*75000,IF($E35<>0,L35*75000,0)) -> 0 | O35: =IF($D35<>0,N35*100000,IF($E35<>0,N35*100000,0)) -> 0 | P35: =VLOOKUP(A35,[14]TONTMAI24!$A$6:$R$39,12,0) -> 0 | U35: =G35+S35++R35+P35+O35+M35+I35+K35+Q35+V35+W35 -> 0 | AQ35: =IF(H35="ECHEC",((K35+M35+O35)*20/100),0) -> 0 | AR35: =IF(H35="ECHEC",((K35+M35+O35)*20/100),0) -> 0 | AS35: =IF(H35="ECHEC",0,(K35+I35-25000)) -> 0 | AW35: =IF(AC35=0,AI35,(1*25000*12)+AI35-AC35) -> 0 | AX35: =IF(AD35=0,AJ35,(1*75000*12)+(AJ35)-AD35) -> 0 | AY35: =IF(AE35=0,AK35,(1*100000*12)+(AK35)-AE35) -> 0 | AZ35: =SUM(AV35:AY35)-BF35+Z35-F35+BH35+BI35+BJ35+BK35+BL35+BM35 -> 0 | BD35: =IF(AZ35=0,(AZ35-BA35-BC35),(AZ35-BA35-BB35-BC35)) -> 0 | BF35: =Z35*1/100*BG35 -> 0 | BG35: 7
A36: AS201625 | B36: =VLOOKUP(A36,[11]LISTADHERENT!A$5:H$50,3,0) -> YEPMOU JEAN JACQUES | C36: =D36+E36+F36-U36-BB36 -> 0 | D36: =VLOOKUP(A36,[12]HISTOBQUEAVRIL24!$A$6:$G$46,3,0) -> 0 | E36: =VLOOKUP(A36,[12]HISTOBQUEAVRIL24!$A$6:$G$41,4,0) -> 0 | F36: =VLOOKUP(A36,[12]HISTOBQUEAVRIL24!$A$6:$G$41,5,0) -> 0 | G36: =IF(H36="ESPECES",3000,0) -> 0 | H36: =IF($D36<>0,"BANQUE",IF($E36<>0,"ESPECES","ECHEC")) -> ECHEC | J36: 1 | K36: =IF($D36<>0,J36*50000,IF($E36<>0,J36*50000,0)) -> 0 | M36: =IF($D36<>0,L36*75000,IF($E36<>0,L36*75000,0)) -> 0 | O36: =IF($D36<>0,N36*100000,IF($E36<>0,N36*100000,0)) -> 0 | P36: =VLOOKUP(A36,[14]TONTMAI24!$A$6:$R$39,12,0) -> 0 | U36: =G36+S36++R36+P36+O36+M36+I36+K36+Q36+V36+W36 -> 0 | AQ36: =IF(H36="ECHEC",((K36+M36+O36)*20/100),0) -> 0 | AR36: =IF(H36="ECHEC",((K36+M36+O36)*20/100),0) -> 0 | AS36: =IF(H36="ECHEC",0,(K36+I36-25000)) -> 0 | AW36: =IF(AC36=0,AI36,(1*25000*12)+AI36-AC36) -> 0 | AX36: =IF(AD36=0,AJ36,(1*75000*12)+(AJ36)-AD36) -> 0 | AY36: =IF(AE36=0,AK36,(1*100000*12)+(AK36)-AE36) -> 0 | AZ36: =SUM(AV36:AY36)-BF36+Z36-F36+BH36+BI36+BJ36+BK36+BL36+BM36 -> 0 | BD36: =IF(AZ36=0,(AZ36-BA36-BC36),(AZ36-BA36-BB36-BC36)) -> 0 | BF36: =Z36*1/100*BG36 -> 0 | BG36: 7 | BN36: YEPMOU JEAN JACQUES | BO36: YEPMOU JEAN JACQUES
A37: SORTIE | B37: =VLOOKUP(A37,[11]LISTADHERENT!A$5:H$50,3,0) -> YIALA ALAIN OSCAR | C37: =D37+E37+F37-U37-BB37 -> 0 | D37: =VLOOKUP(A37,[12]HISTOBQUEAVRIL24!$A$6:$G$46,3,0) -> 0 | E37: =VLOOKUP(A37,[12]HISTOBQUEAVRIL24!$A$6:$G$41,4,0) -> 0 | F37: =VLOOKUP(A37,[12]HISTOBQUEAVRIL24!$A$6:$G$41,5,0) -> 0 | G37: =IF(H37="ESPECES",3000,0) -> 0 | H37: =IF($D37<>0,"BANQUE",IF($E37<>0,"ESPECES","ECHEC")) -> ECHEC | J37: 1 | K37: =IF($D37<>0,J37*50000,IF($E37<>0,J37*50000,0)) -> 0 | M37: =IF($D37<>0,L37*75000,IF($E37<>0,L37*75000,0)) -> 0 | N37: 1 | O37: =IF($D37<>0,N37*100000,IF($E37<>0,N37*100000,0)) -> 0 | P37: =VLOOKUP(A37,[14]TONTMAI24!$A$6:$R$39,12,0) -> 0 | R37: =VLOOKUP(A37,[16]TONTMAI24!$A$7:$P$20,10,0) -> 0 | U37: =G37+S37++R37+P37+O37+M37+I37+K37+Q37+V37+W37 -> 0 | AQ37: =IF(H37="ECHEC",((K37+M37+O37)*20/100),0) -> 0 | AR37: =IF(H37="ECHEC",((K37+M37+O37)*20/100),0) -> 0 | AS37: =IF(H37="ECHEC",0,(K37+I37-25000)) -> 0 | AW37: =IF(AC37=0,AI37,(1*25000*12)+AI37-AC37) -> 0 | AX37: =IF(AD37=0,AJ37,(1*75000*12)+(AJ37)-AD37) -> 0 | AY37: =IF(AE37=0,AK37,(1*100000*12)+(AK37)-AE37) -> 0 | AZ37: =SUM(AV37:AY37)-BF37+Z37-F37+BH37+BI37+BJ37+BK37+BL37+BM37 -> 0 | BD37: =IF(AZ37=0,(AZ37-BA37-BC37),(AZ37-BA37-BB37-BC37)) -> 0 | BF37: =Z37*1/100*BG37 -> 0 | BG37: 7 | BN37: YOUMBI EMMANUEL | BO37: YEPMOU JEAN JACQUES
A38: AS201626 | B38: =VLOOKUP(A38,[11]LISTADHERENT!A$5:H$50,3,0) -> YOUMBI EMMANUEL | C38: =D38+E38+F38-U38-BB38 -> 0 | D38: =VLOOKUP(A38,[12]HISTOBQUEAVRIL24!$A$6:$G$46,3,0) -> 0 | E38: =VLOOKUP(A38,[12]HISTOBQUEAVRIL24!$A$6:$G$41,4,0) -> 0 | F38: =VLOOKUP(A38,[12]HISTOBQUEAVRIL24!$A$6:$G$41,5,0) -> 0 | G38: =IF(H38="ESPECES",3000,0) -> 0 | H38: =IF($D38<>0,"BANQUE",IF($E38<>0,"ESPECES","ECHEC")) -> ECHEC | J38: 1 | K38: =IF($D38<>0,J38*50000,IF($E38<>0,J38*50000,0)) -> 0 | L38: 1 | M38: =IF($D38<>0,L38*75000,IF($E38<>0,L38*75000,0)) -> 0 | O38: =IF($D38<>0,N38*100000,IF($E38<>0,N38*100000,0)) -> 0 | P38: =VLOOKUP(A38,[14]TONTMAI24!$A$6:$R$39,12,0) -> 0 | Q38: =VLOOKUP(A38,[15]TONTMAI24!$A$7:$P$23,10,0) -> 0 | U38: =G38+S38++R38+P38+O38+M38+I38+K38+Q38+V38+W38 -> 0 | AQ38: =IF(H38="ECHEC",((K38+M38+O38)*20/100),0) -> 0 | AR38: =IF(H38="ECHEC",((K38+M38+O38)*20/100),0) -> 0 | AS38: =IF(H38="ECHEC",0,(K38+I38-25000)) -> 0 | AW38: =IF(AC38=0,AI38,(1*25000*12)+AI38-AC38) -> 0 | AX38: =IF(AD38=0,AJ38,(1*75000*12)+(AJ38)-AD38) -> 0 | AY38: =IF(AE38=0,AK38,(1*100000*12)+(AK38)-AE38) -> 0 | AZ38: =SUM(AV38:AY38)-BF38+Z38-F38+BH38+BI38+BJ38+BK38+BL38+BM38 -> 0 | BD38: =IF(AZ38=0,(AZ38-BA38-BC38),(AZ38-BA38-BB38-BC38)) -> 0 | BF38: =Z38*1/100*BG38 -> 0 | BG38: 7 | BN38: YOUMBI EMMANUEL | BO38: YEPMOU JEAN JACQUES
B40: AS201629 | C40: =SUM(C6:C39) -> 0 | D40: =SUM(D6:D39) -> 0 | E40: =SUM(E6:E39) -> 0 | F40: =SUM(F6:F39) -> 0 | G40: =SUM(G6:G39) -> 0 | H40: =SUM(H6:H39) -> 0 | I40: =SUM(I6:I39) -> 0 | J40: =SUM(J6:J39) -> 32 | ... S40: =SUM(S6:S39) -> 0 | U40: =SUM(U6:U39) -> 0 | V40: =SUM(V6:V39) -> 0 | W40: =SUM(W6:W39) -> 0 | X40: =SUM(X6:X39) -> 0 | Y40: =SUM(Y6:Y39) -> 0 | Z40: =SUM(Z6:Z39) -> 0 | AA40: =SUM(AA6:AA39) -> 0 | AC40: =SUM(AC6:AC39) -> 0 | AD40: =SUM(AD6:AD39) -> 0 | AE40: =SUM(AE6:AE39) -> 0 | AF40: =SUM(AF6:AF39) -> 0 | AG40: =SUM(AG6:AG39) -> 0 | AI40: =SUM(AI6:AI39) -> 0 | AJ40: =SUM(AJ6:AJ39) -> 0 | AK40: =SUM(AK6:AK39) -> 0 | AL40: =SUM(AL6:AL39) -> 0 | AM40: =SUM(AM6:AM39) -> 0 | AN40: =SUM(AN6:AN39) -> 0 | AO40: =SUM(AO6:AO39) -> 0 | AP40: =SUM(AP6:AP39) -> 0 | ... BF40: =SUM(BF6:BF39) -> 0 | BH40: =SUM(BH6:BH39) -> 0 | BI40: =SUM(BI6:BI39) -> 0 | BJ40: =SUM(BJ6:BJ39) -> 0 | BK40: =SUM(BK6:BK39) -> 0 | BL40: =SUM(BL6:BL39) -> 0 | BM40: =SUM(BM6:BM39) -> 0 | BN40: INTERET | BP40: =SUM(BP36:BP38) -> 0
B43: AOUT 2018 A NOVEMBRE 2019 | BN43: A APURER | BO43: AS201639
C44: SANCTION | F44: EPARGNE
B45: 2017/2018 | C45: MBOGNING TUGMA GUY | D45: AS201649 | E45: AS201650 | F45: AS201649 | G45: MBOGNING TUGMA GUY | H45: AS201650 | BN45: INTERET | BP45: =SUM(BP42:BP44) -> 0
B46: DJOMO DOMO
B47: AS201651 | C47: =AZ40 -> 0 | D47: =SUMIFS(D8:D40,H8:H40,"BANQUE") -> 0 | F47: =E40 -> 0
AZ85: =SUM(AZ8:AZ84) -> 0

Sheet Sheet10
A1: ANNEE | B1: TONTINE
A2: MATRICULE | B2: 2024
A3: 1 | B3: 2 | C3: 3 | D3: 4 | E3: 5 | F3: 6 | G3: 7 | H3: 8 | I3: 9 | J3: 10 | K3: 11 | L3: 12 | M3: 13 | N3: 14 | O3: 15 | P3: 16 | Q3: 17 | R3: 18 | S3: 19 | T3: 20 | U3: 21 | V3: 22 | W3: 23 | X3: 24 | Y3: 25 | Z3: 26 | AA3: 27 | AB3: 28 | AC3: 29 | AD3: 30 | AE3: 31 | AF3: 32 | AG3: 33 | AH3: 34 | AI3: 35 | AJ3: 36 | AK3: 37 | AL3: 38 | AM3: 39 | AN3: 40 | AO3: 41 | AP3: 42 | AQ3: 43 | AR3: 44 | AS3: 45 | AT3: 46 | AU3: 47 | AV3: 48 | AW3: 49 | AX3: 50 | AY3: 51 | AZ3: 52 | BA3: 53 | BB3: 54 | BC3: 55 | BD3: 56 | BE3: 57 | BF3: 58 | BG3: 59 | BH3: 60 | BI3: 61 | BJ3: 62 | BK3: 63 | BL3: 64 | BM3: 65 | BN3: 66 | BO3: 67 | BP3: 68
B4: AS201628
A5: ASSOCIATION | B5: ASELBY | C5: AS201636 | D5: PENALITE VST ESPECES | E5: INSCRIPTION | F5: INSCRISPTION | G5: AS201633 | H5: AS201637 | I5: FONDS DE CAISSE | J5: AS201634 | K5: RECAPITULATIF 2020 | L5: AS201634 | M5: NOM ET PRENOM | N5: AS201634 | O5: REPARTITION INTERET | P5: MARS | Q5: FONDS DE ROULEMENT | R5: FRAIS EXCEPTIONNEL | S5: PRET FONDS | T5: PENALITE VERST ESPECES | U5: FRAIS EXCEPTIONNELS | V5: CAPITAL COMPOSE | W5: AS201641 | X5: TONTINE | Y5: RESTE | Z5: AS201642 | AA5: PRÊT FONDS | AB5: TOTAL | AC5: JUIN | AD5: AS201627 | AE5: INTERET PRÊT FONDS | AF5: AS201638 | AG5: TOTAL | AH5: AS201633 | AI5: AVRIL | AJ5: AS201643 | AK5: AS201644 | AL5: MAI | AM5: AS201646 | AN5: AS201647 | AO5: TOTAL | AP5: OCTOBRE | AQ5: REMBOURSEMENTPRET FONDS | AR5: PENALITE PRET FONDS | AS5: RELIQUAT | AT5: AS201639 | AU5: DOMOU FABIEN | AV5: MONTANT EPARGNE+INTERET | AW5: JUILLET | AX5: NUMERO CHEQUE | AY5: AS201653 | AZ5: 2018/2019 | BA5: NKEPSEU DIEUDONNE | BB5: KOUAMOU MOISE | BC5: COMPLEMENT FONDS | BD5: MONTANT A VERSER | BE5: KOUAMO VICTOR PEGUY | BF5: T100 | BG5: TABLEAU RECAPITULATIF DISTRIBUTION EPARGNE 2019 | BH5: 2019/2020 | BI5: INTERET ANTERIEUR | BJ5: NET_ A_ PAYER | BK5: PRÊT_FONDS_ENCOURS | BL5: DISTRIBUTION INTERET 2018 ET 2019 | BM5: DJOMO JEAN PAUL AVANCE 80 000 DJOMO JEAN PAUL | BN5: 2017/2018 | BO5: PRÊT_FONDS | BP5: AS201654
A6: KOUAMOU EMMANUEL | B6: =VLOOKUP(A6,[11]LISTADHERENT!A$5:H$50,3,0) -> ASELBY | C6: =D6+E6+F6-U6-BB6 -> 0 | D6: =VLOOKUP(A6,[12]HISTOBQUEAVRIL24!$A$6:$G$46,3,0) -> 0 | E6: =VLOOKUP(A6,[12]HISTOBQUEAVRIL24!$A$6:$G$41,4,0) -> 0 | F6: =VLOOKUP(A6,[12]HISTOBQUEAVRIL24!$A$6:$G$41,5,0) -> 0 | G6: =IF(H6="ESPECES",3000,0) -> 0 | H6: =IF($D6<>0,"BANQUE",IF($E6<>0,"ESPECES","ECHEC")) -> ECHEC | K6: =IF($D6<>0,J6*50000,IF($E6<>0,J6*50000,0)) -> 0 | L6: 1 | M6: =IF($D6<>0,L6*75000,IF($E6<>0,L6*75000,0)) -> 0 | N6: 1 | O6: =IF($D6<>0,N6*100000,IF($E6<>0,N6*100000,0)) -> 0 | U6: =G6+S6++R6+P6+O6+M6+I6+K6+Q6+V6+W6 -> 0 | AQ6: =IF(H6="ECHEC",((K6+M6+O6)*20/100),0) -> 0 | AR6: =IF(H6="ECHEC",((K6+M6+O6)*20/100),0) -> 0 | AW6: =IF(AC6=0,AI6,(1*25000*12)+AI6-AC6) -> 0 | AX6: =IF(AD6=0,AJ6,(1*75000*12)+(AJ6)-AD6) -> 0 | AY6: =IF(AE6=0,AK6,(1*100000*12)+(AK6)-AE6) -> 0 | AZ6: =SUM(AV6:AY6)-BF6+Z6-F6+BH6+BI6+BJ6+BK6+BL6+BM6 -> 0 | BD6: =IF(AZ6=0,(AZ6-BA6-BC6),(AZ6-BA6-BB6-BC6)) -> 0 | BF6: =Z6*1/100*BG6 -> 0 | BG6: 6 | BH6: =BP16 -> 0 | BI6: =BP28 -> 0 | BJ6: =BP33 -> 0 | BK6: =+BP40 -> 0 | BM6: =BP22 -> 0 | BN6: NKEHE DAVID | BO6: NGONGANG JEAN THEODORE
A7: DATE | B7: =VLOOKUP(A7,[11]LISTADHERENT!A$5:H$50,3,0) -> BAKOP ACHILLE | C7: =D7+E7+F7-U7-BB7 -> 0 | D7: =VLOOKUP(A7,[12]HISTOBQUEAVRIL24!$A$6:$G$46,3,0) -> 0 | E7: =VLOOKUP(A7,[12]HISTOBQUEAVRIL24!$A$6:$G$41,4,0) -> 0 | F7: =VLOOKUP(A7,[12]HISTOBQUEAVRIL24!$A$6:$G$41,5,0) -> 0 | G7: =IF(H7="ESPECES",3000,0) -> 0 | H7: =IF($D7<>0,"BANQUE",IF($E7<>0,"ESPECES","ECHEC")) -> ECHEC | J7: 1 | K7: =IF($D7<>0,J7*50000,IF($E7<>0,J7*50000,0)) -> 0 | M7: =IF($D7<>0,L7*75000,IF($E7<>0,L7*75000,0)) -> 0 | O7: =IF($D7<>0,N7*100000,IF($E7<>0,N7*100000,0)) -> 0 | P7: =VLOOKUP(A7,[14]TONTJUIN24!$A$6:$R$39,12,0) -> 0 | U7: =G7+S7++R7+P7+O7+M7+I7+K7+Q7+V7+W7 -> 0 | AQ7: =IF(H7="ECHEC",((K7+M7+O7)*20/100),0) -> 0 | AR7: =IF(H7="ECHEC",((K7+M7+O7)*20/100),0) -> 0 | AS7: =IF(H7="ECHEC",0,(K7+I7-25000)) -> 0 | AW7: =IF(AC7=0,AI7,(1*25000*12)+AI7-AC7) -> 0 | AX7: =IF(AD7=0,AJ7,(1*75000*12)+(AJ7)-AD7) -> 0 | AY7: =IF(AE7=0,AK7,(1*100000*12)+(AK7)-AE7) -> 0 | AZ7: =SUM(AV7:AY7)-BF7+Z7-F7+BH7+BI7+BJ7+BK7+BL7+BM7 -> 0 | BD7: =IF(AZ7=0,(AZ7-BA7-BC7),(AZ7-BA7-BB7-BC7)) -> 0 | BF7: =Z7*1/100*BG7 -> 0 | BG7: 6 | BN7: PATEGO NJOSSU GUSTAVE | BO7: NGONGANG JEAN THEODORE
A8: COLLATION | B8: =VLOOKUP(A8,[11]LISTADHERENT!A$5:H$50,3,0) -> BOUTCHOUANG WILLIAM | C8: =D8+E8+F8-U8-BB8 -> 0 | D8: =VLOOKUP(A8,[12]HISTOBQUEAVRIL24!$A$6:$G$46,3,0) -> 0 | E8: =VLOOKUP(A8,[12]HISTOBQUEAVRIL24!$A$6:$G$41,4,0) -> 0 | F8: =VLOOKUP(A8,[12]HISTOBQUEAVRIL24!$A$6:$G$41,5,0) -> 0 | G8: =IF(H8="ESPECES",3000,0) -> 0 | H8: =IF($D8<>0,"BANQUE",IF($E8<>0,"ESPECES","ECHEC")) -> ECHEC | J8: 1 | K8: =IF($D8<>0,J8*50000,IF($E8<>0,J8*50000,0)) -> 0 | L8: 1 | M8: =IF($D8<>0,L8*75000,IF($E8<>0,L8*75000,0)) -> 0 | O8: =IF($D8<>0,N8*100000,IF($E8<>0,N8*100000,0)) -> 0 | P8: =VLOOKUP(A8,[14]TONTJUIN24!$A$6:$R$39,12,0) -> 0 | Q8: =VLOOKUP(A8,[15]TONTJUIN24!$A$7:$P$23,10,0) -> 0 | U8: =G8+S8++R8+P8+O8+M8+I8+K8+Q8+V8+W8 -> 0 | AQ8: =IF(H8="ECHEC",((K8+M8+O8)*20/100),0) -> 0 | AR8: =IF(H8="ECHEC",((K8+M8+O8)*20/100),0) -> 0 | AS8: =IF(H8="ECHEC",0,(K8+I8-25000)) -> 0 | AW8: =IF(AC8=0,AI8,(1*25000*12)+AI8-AC8) -> 0 | AX8: =IF(AD8=0,AJ8,(1*75000*12)+(AJ8)-AD8) -> 0 | AY8: =IF(AE8=0,AK8,(1*100000*12)+(AK8)-AE8) -> 0 | AZ8: =SUM(AV8:AY8)-BF8+Z8-F8+BH8+BI8+BJ8+BK8+BL8+BM8 -> 0 | BD8: =IF(AZ8=0,(AZ8-BA8-BC8),(AZ8-BA8-BB8-BC8)) -> 0 | BF8: =Z8*1/100*BG8 -> 0 | BG8: 6 | BN8: SEUNOU RICHELOT | BO8: NGONGANG JEAN THEODORE
A9: MUTUELLE | B9: =VLOOKUP(A9,[11]LISTADHERENT!A$5:H$50,3,0) -> DJOMO JEAN PAUL | C9: =D9+E9+F9-U9-BB9 -> 0 | D9: =VLOOKUP(A9,[12]HISTOBQUEAVRIL24!$A$6:$G$46,3,0) -> 0 | E9: =VLOOKUP(A9,[12]HISTOBQUEAVRIL24!$A$6:$G$41,4,0) -> 0 | F9: =VLOOKUP(A9,[12]HISTOBQUEAVRIL24!$A$6:$G$41,5,0) -> 0 | G9: =IF(H9="ESPECES",3000,0) -> 0 | H9: =IF($D9<>0,"BANQUE",IF($E9<>0,"ESPECES","ECHEC")) -> ECHEC | J9: 1 | K9: =IF($D9<>0,J9*50000,IF($E9<>0,J9*50000,0)) -> 0 | M9: =IF($D9<>0,L9*75000,IF($E9<>0,L9*75000,0)) -> 0 | N9: 2 | O9: =IF($D9<>0,N9*100000,IF($E9<>0,N9*100000,0)) -> 0 | P9: =VLOOKUP(A9,[14]TONTJUIN24!$A$6:$R$39,12,0) -> 0 | R9: =VLOOKUP(A9,[16]TONTJUIN24!$A$7:$P$20,10,0) -> 0 | U9: =G9+S9++R9+P9+O9+M9+I9+K9+Q9+V9+W9 -> 0 | AQ9: =IF(H9="ECHEC",((K9+M9+O9)*20/100),0) -> 0 | AR9: =IF(H9="ECHEC",((K9+M9+O9)*20/100),0) -> 0 | AS9: =IF(H9="ECHEC",0,(K9+I9-25000)) -> 0 | AW9: =IF(AC9=0,AI9,(1*25000*12)+AI9-AC9) -> 0 | AX9: =IF(AD9=0,AJ9,(1*75000*12)+(AJ9)-AD9) -> 0 | AY9: =IF(AE9=0,AK9,(1*100000*12)+(AK9)-AE9) -> 0 | AZ9: =SUM(AV9:AY9)-BF9+Z9-F9+BH9+BI9+BJ9+BK9+BL9+BM9 -> 0 | BD9: =IF(AZ9=0,(AZ9-BA9-BC9),(AZ9-BA9-BB9-BC9)) -> 0 | BF9: =Z9*1/100*BG9 -> 0 | BG9: 6 | BN9: JANVIER | BO9: NGONGANG JEAN THEODORE
A10: PENALITE FONDS | B10: =VLOOKUP(A10,[11]LISTADHERENT!A$5:H$50,3,0) -> DJOMOU TCHAPDA | C10: =D10+E10+F10-U10-BB10 -> 0 | D10: =VLOOKUP(A10,[12]HISTOBQUEAVRIL24!$A$6:$G$46,3,0) -> 0 | E10: =VLOOKUP(A10,[12]HISTOBQUEAVRIL24!$A$6:$G$41,4,0) -> 0 | F10: =VLOOKUP(A10,[12]HISTOBQUEAVRIL24!$A$6:$G$41,5,0) -> 0 | G10: =IF(H10="ESPECES",3000,0) -> 0 | H10: =IF($D10<>0,"BANQUE",IF($E10<>0,"ESPECES","ECHEC")) -> ECHEC | J10: 1 | K10: =IF($D10<>0,J10*50000,IF($E10<>0,J10*50000,0)) -> 0 | L10: 1 | M10: =IF($D10<>0,L10*75000,IF($E10<>0,L10*75000,0)) -> 0 | O10: =IF($D10<>0,N10*100000,IF($E10<>0,N10*100000,0)) -> 0 | P10: =VLOOKUP(A10,[14]TONTJUIN24!$A$6:$R$39,12,0) -> 0 | Q10: =VLOOKUP(A10,[15]TONTJUIN24!$A$7:$P$23,10,0) -> 0 | U10: =G10+S10++R10+P10+O10+M10+I10+K10+Q10+V10+W10 -> 0 | AQ10: =IF(H10="ECHEC",((K10+M10+O10)*20/100),0) -> 0 | AR10: =IF(H10="ECHEC",((K10+M10+O10)*20/100),0) -> 0 | AS10: =IF(H10="ECHEC",0,(K10+I10-25000)) -> 0 | AW10: =IF(AC10=0,AI10,(1*25000*12)+AI10-AC10) -> 0 | AX10: =IF(AD10=0,AJ10,(1*75000*12)+(AJ10)-AD10) -> 0 | AY10: =IF(AE10=0,AK10,(1*100000*12)+(AK10)-AE10) -> 0 | AZ10: =SUM(AV10:AY10)-BF10+Z10-F10+BH10+BI10+BJ10+BK10+BL10+BM10 -> 0 | BD10: =IF(AZ10=0,(AZ10-BA10-BC10),(AZ10-BA10-BB10-BC10)) -> 0 | BF10: =Z10*1/100*BG10 -> 0 | BG10: 6 | BN10: SIME BRICE | BO10: NGONGANG JEAN THEODORE
A11: AVALISTE | B11: =VLOOKUP(A11,[11]LISTADHERENT!A$5:H$50,3,0) -> DJOUKWE NANGUEN GUY BLAISE | C11: =D11+E11+F11-U11-BB11 -> 0 | D11: =VLOOKUP(A11,[12]HISTOBQUEAVRIL24!$A$6:$G$46,3,0) -> 0 | E11: =VLOOKUP(A11,[12]HISTOBQUEAVRIL24!$A$6:$G$41,4,0) -> 0 | F11: =VLOOKUP(A11,[12]HISTOBQUEAVRIL24!$A$6:$G$41,5,0) -> 0 | G11: =IF(H11="ESPECES",3000,0) -> 0 | H11: =IF($D11<>0,"BANQUE",IF($E11<>0,"ESPECES","ECHEC")) -> ECHEC | J11: 1 | K11: =IF($D11<>0,J11*50000,IF($E11<>0,J11*50000,0)) -> 0 | L11: 1 | M11: =IF($D11<>0,L11*75000,IF($E11<>0,L11*75000,0)) -> 0 | O11: =IF($D11<>0,N11*100000,IF($E11<>0,N11*100000,0)) -> 0 | P11: =VLOOKUP(A11,[14]TONTJUIN24!$A$6:$R$39,12,0) -> 0 | Q11: =VLOOKUP(A11,[15]TONTJUIN24!$A$7:$P$23,10,0) -> 0 | U11: =G11+S11++R11+P11+O11+M11+I11+K11+Q11+V11+W11 -> 0 | AQ11: =IF(H11="ECHEC",((K11+M11+O11)*20/100),0) -> 0 | AR11: =IF(H11="ECHEC",((K11+M11+O11)*20/100),0) -> 0 | AS11: =IF(H11="ECHEC",0,(K11+I11-25000)) -> 0 | AW11: =IF(AC11=0,AI11,(1*25000*12)+AI11-AC11) -> 0 | AX11: =IF(AD11=0,AJ11,(1*75000*12)+(AJ11)-AD11) -> 0 | AY11: =IF(AE11=0,AK11,(1*100000*12)+(AK11)-AE11) -> 0 | AZ11: =SUM(AV11:AY11)-BF11+Z11-F11+BH11+BI11+BJ11+BK11+BL11+BM11 -> 0 | BD11: =IF(AZ11=0,(AZ11-BA11-BC11),(AZ11-BA11-BB11-BC11)) -> 0 | BF11: =Z11*1/100*BG11 -> 0 | BG11: 6 | BN11: SIME FONGANG ERIC | BO11: NGONGANG JEAN THEODORE
A12: AS201648 | B12: =VLOOKUP(A12,[11]LISTADHERENT!A$5:H$50,3,0) -> DJUOMBESSY ANTOINE | C12: =D12+E12+F12-U12-BB12 -> 0 | D12: =VLOOKUP(A12,[12]HISTOBQUEAVRIL24!$A$6:$G$46,3,0) -> 0 | E12: =VLOOKUP(A12,[12]HISTOBQUEAVRIL24!$A$6:$G$41,4,0) -> 0 | F12: =VLOOKUP(A12,[12]HISTOBQUEAVRIL24!$A$6:$G$41,5,0) -> 0 | G12: =IF(H12="ESPECES",3000,0) -> 0 | H12: =IF($D12<>0,"BANQUE",IF($E12<>0,"ESPECES","ECHEC")) -> ECHEC | J12: 1 | K12: =IF($D12<>0,J12*50000,IF($E12<>0,J12*50000,0)) -> 0 | L12: 1 | M12: =IF($D12<>0,L12*75000,IF($E12<>0,L12*75000,0)) -> 0 | N12: 2 | O12: =IF($D12<>0,N12*100000,IF($E12<>0,N12*100000,0)) -> 0 | P12: =VLOOKUP(A12,[14]TONTJUIN24!$A$6:$R$39,12,0) -> 0 | Q12: =VLOOKUP(A12,[15]TONTJUIN24!$A$7:$P$23,10,0) -> 0 | R12: =VLOOKUP(A12,[16]TONTJUIN24!$A$7:$P$20,10,0) -> 0 | U12: =G12+S12++R12+P12+O12+M12+I12+K12+Q12+V12+W12 -> 0 | AQ12: =IF(H12="ECHEC",((K12+M12+O12)*20/100),0) -> 0 | AR12: =IF(H12="ECHEC",((K12+M12+O12)*20/100),0) -> 0 | AS12: =IF(H12="ECHEC",0,(K12+I12-25000)) -> 0 | AW12: =IF(AC12=0,AI12,(1*25000*12)+AI12-AC12) -> 0 | AX12: =IF(AD12=0,AJ12,(1*75000*12)+(AJ12)-AD12) -> 0 | AY12: =IF(AE12=0,AK12,(1*100000*12)+(AK12)-AE12) -> 0 | AZ12: =SUM(AV12:AY12)-BF12+Z12-F12+BH12+BI12+BJ12+BK12+BL12+BM12 -> 0 | BD12: =IF(AZ12=0,(AZ12-BA12-BC12),(AZ12-BA12-BB12-BC12)) -> 0 | BF12: =Z12*1/100*BG12 -> 0 | BG12: 6 | BN12: SIME MATHIEU | BO12: NGONGANG JEAN THEODORE
A13: AS201601 | B13: =VLOOKUP(A13,[11]LISTADHERENT!A$5:H$50,3,0) -> DOMOU FABIEN | C13: =D13+E13+F13-U13-BB13 -> 0 | D13: =VLOOKUP(A13,[12]HISTOBQUEAVRIL24!$A$6:$G$46,3,0) -> 0 | E13: =VLOOKUP(A13,[12]HISTOBQUEAVRIL24!$A$6:$G$41,4,0) -> 0 | F13: =VLOOKUP(A13,[12]HISTOBQUEAVRIL24!$A$6:$G$41,5,0) -> 0 | G13: =IF(H13="ESPECES",3000,0) -> 0 | H13: =IF($D13<>0,"BANQUE",IF($E13<>0,"ESPECES","ECHEC")) -> ECHEC | J13: 1 | K13: =IF($D13<>0,J13*50000,IF($E13<>0,J13*50000,0)) -> 0 | M13: =IF($D13<>0,L13*75000,IF($E13<>0,L13*75000,0)) -> 0 | O13: =IF($D13<>0,N13*100000,IF($E13<>0,N13*100000,0)) -> 0 | P13: =VLOOKUP(A13,[14]TONTJUIN24!$A$6:$R$39,12,0) -> 0 | U13: =G13+S13++R13+P13+O13+M13+I13+K13+Q13+V13+W13 -> 0 | AQ13: =IF(H13="ECHEC",((K13+M13+O13)*20/100),0) -> 0 | AR13: =IF(H13="ECHEC",((K13+M13+O13)*20/100),0) -> 0 | AS13: =IF(H13="ECHEC",0,(K13+I13-25000)) -> 0 | AW13: =IF(AC13=0,AI13,(1*25000*12)+AI13-AC13) -> 0 | AX13: =IF(AD13=0,AJ13,(1*75000*12)+(AJ13)-AD13) -> 0 | AY13: =IF(AE13=0,AK13,(1*100000*12)+(AK13)-AE13) -> 0 | AZ13: =SUM(AV13:AY13)-BF13+Z13-F13+BH13+BI13+BJ13+BK13+BL13+BM13 -> 0 | BD13: =IF(AZ13=0,(AZ13-BA13-BC13),(AZ13-BA13-BB13-BC13)) -> 0 | BF13: =Z13*1/100*BG13 -> 0 | BG13: 6 | BN13: FONDSCAISSE | BO13: NGONGANG JEAN THEODORE
A14: ECHEC | B14: =VLOOKUP(A14,[11]LISTADHERENT!A$5:H$50,3,0) -> DONHOU DAVID | C14: =D14+E14+F14-U14-BB14 -> 0 | D14: =VLOOKUP(A14,[12]HISTOBQUEAVRIL24!$A$6:$G$46,3,0) -> 0 | E14: =VLOOKUP(A14,[12]HISTOBQUEAVRIL24!$A$6:$G$41,4,0) -> 0 | F14: =VLOOKUP(A14,[12]HISTOBQUEAVRIL24!$A$6:$G$41,5,0) -> 0 | G14: =IF(H14="ESPECES",3000,0) -> 0 | H14: =IF($D14<>0,"BANQUE",IF($E14<>0,"ESPECES","ECHEC")) -> ECHEC | J14: 1 | K14: =IF($D14<>0,J14*50000,IF($E14<>0,J14*50000,0)) -> 0 | M14: =IF($D14<>0,L14*75000,IF($E14<>0,L14*75000,0)) -> 0 | O14: =IF($D14<>0,N14*100000,IF($E14<>0,N14*100000,0)) -> 0 | P14: =VLOOKUP(A14,[14]TONTJUIN24!$A$6:$R$39,12,0) -> 0 | U14: =G14+S14++R14+P14+O14+M14+I14+K14+Q14+V14+W14 -> 0 | AQ14: =IF(H14="ECHEC",((K14+M14+O14)*20/100),0) -> 0 | AR14: =IF(H14="ECHEC",((K14+M14+O14)*20/100),0) -> 0 | AS14: =IF(H14="ECHEC",0,(K14+I14-25000)) -> 0 | AW14: =IF(AC14=0,AI14,(1*25000*12)+AI14-AC14) -> 0 | AX14: =IF(AD14=0,AJ14,(1*75000*12)+(AJ14)-AD14) -> 0 | AY14: =IF(AE14=0,AK14,(1*100000*12)+(AK14)-AE14) -> 0 | AZ14: =SUM(AV14:AY14)-BF14+Z14-F14+BH14+BI14+BJ14+BK14+BL14+BM14 -> 0 | BD14: =IF(AZ14=0,(AZ14-BA14-BC14),(AZ14-BA14-BB14-BC14)) -> 0 | BF14: =Z14*1/100*BG14 -> 0 | BG14: 6 | BN14: TCHOUAMOU MATHIEU | BO14: NGONGANG JEAN THEODORE
A15: ESPECES | B15: =VLOOKUP(A15,[11]LISTADHERENT!A$5:H$50,3,0) -> HENGUE PAUL OMER | C15: =D15+E15+F15-U15-BB15 -> 0 | D15: =VLOOKUP(A15,[12]HISTOBQUEAVRIL24!$A$6:$G$46,3,0) -> 0 | E15: =VLOOKUP(A15,[12]HISTOBQUEAVRIL24!$A$6:$G$41,4,0) -> 0 | F15: =VLOOKUP(A15,[12]HISTOBQUEAVRIL24!$A$6:$G$41,5,0) -> 0 | G15: =IF(H15="ESPECES",3000,0) -> 0 | H15: =IF($D15<>0,"BANQUE",IF($E15<>0,"ESPECES","ECHEC")) -> ECHEC | J15: 1 | K15: =IF($D15<>0,J15*50000,IF($E15<>0,J15*50000,0)) -> 0 | L15: 1 | M15: =IF($D15<>0,L15*75000,IF($E15<>0,L15*75000,0)) -> 0 | O15: =IF($D15<>0,N15*100000,IF($E15<>0,N15*100000,0)) -> 0 | P15: =VLOOKUP(A15,[14]TONTJUIN24!$A$6:$R$39,12,0) -> 0 | Q15: =VLOOKUP(A15,[15]TONTJUIN24!$A$7:$P$23,10,0) -> 0 | U15: =G15+S15++R15+P15+O15+M15+I15+K15+Q15+V15+W15 -> 0 | AQ15: =IF(H15="ECHEC",((K15+M15+O15)*20/100),0) -> 0 | AR15: =IF(H15="ECHEC",((K15+M15+O15)*20/100),0) -> 0 | AS15: =IF(H15="ECHEC",0,(K15+I15-25000)) -> 0 | AW15: =IF(AC15=0,AI15,(1*25000*12)+AI15-AC15) -> 0 | AX15: =IF(AD15=0,AJ15,(1*75000*12)+(AJ15)-AD15) -> 0 | AY15: =IF(AE15=0,AK15,(1*100000*12)+(AK15)-AE15) -> 0 | AZ15: =SUM(AV15:AY15)-BF15+Z15-F15+BH15+BI15+BJ15+BK15+BL15+BM15 -> 0 | BD15: =IF(AZ15=0,(AZ15-BA15-BC15),(AZ15-BA15-BB15-BC15)) -> 0 | BF15: =Z15*1/100*BG15 -> 0 | BG15: 6
A16: AS201603 | B16: =VLOOKUP(A16,[11]LISTADHERENT!A$5:H$50,3,0) -> HOTCHO BENJAMIN | C16: =D16+E16+F16-U16-BB16 -> 0 | D16: =VLOOKUP(A16,[12]HISTOBQUEAVRIL24!$A$6:$G$46,3,0) -> 0 | E16: =VLOOKUP(A16,[12]HISTOBQUEAVRIL24!$A$6:$G$41,4,0) -> 0 | F16: =VLOOKUP(A16,[12]HISTOBQUEAVRIL24!$A$6:$G$41,5,0) -> 0 | G16: =IF(H16="ESPECES",3000,0) -> 0 | H16: =IF($D16<>0,"BANQUE",IF($E16<>0,"ESPECES","ECHEC")) -> ECHEC | J16: 1 | K16: =IF($D16<>0,J16*50000,IF($E16<>0,J16*50000,0)) -> 0 | L16: 1 | M16: =IF($D16<>0,L16*75000,IF($E16<>0,L16*75000,0)) -> 0 | N16: 1 | O16: =IF($D16<>0,N16*100000,IF($E16<>0,N16*100000,0)) -> 0 | P16: =VLOOKUP(A16,[14]TONTJUIN24!$A$6:$R$39,12,0) -> 0 | Q16: =VLOOKUP(A16,[15]TONTJUIN24!$A$7:$P$23,10,0) -> 0 | R16: =VLOOKUP(A16,[16]TONTFEV24!$A$7:$P$20,10,0) -> 0 | U16: =G16+S16++R16+P16+O16+M16+I16+K16+Q16+V16+W16 -> 0 | AQ16: =IF(H16="ECHEC",((K16+M16+O16)*20/100),0) -> 0 | AR16: =IF(H16="ECHEC",((K16+M16+O16)*20/100),0) -> 0 | AS16: =IF(H16="ECHEC",0,(K16+I16-25000)) -> 0 | AW16: =IF(AC16=0,AI16,(1*25000*12)+AI16-AC16) -> 0 | AX16: =IF(AD16=0,AJ16,(1*75000*12)+(AJ16)-AD16) -> 0 | AY16: =IF(AE16=0,AK16,(1*100000*12)+(AK16)-AE16) -> 0 | AZ16: =SUM(AV16:AY16)-BF16+Z16-F16+BH16+BI16+BJ16+BK16+BL16+BM16 -> 0 | BD16: =IF(AZ16=0,(AZ16-BA16-BC16),(AZ16-BA16-BB16-BC16)) -> 0 | BF16: =Z16*1/100*BG16 -> 0 | BG16: 6 | BN16: INTERET | BP16: =SUM(BP6:BP15) -> 0
A17: BANQUE | B17: =VLOOKUP(A17,[11]LISTADHERENT!A$5:H$50,3,0) -> KOUAMOU MOISE | C17: =D17+E17+F17-U17-BB17 -> 0 | D17: =VLOOKUP(A17,[12]HISTOBQUEAVRIL24!$A$6:$G$46,3,0) -> 0 | E17: =VLOOKUP(A17,[12]HISTOBQUEAVRIL24!$A$6:$G$41,4,0) -> 0 | F17: =VLOOKUP(A17,[12]HISTOBQUEAVRIL24!$A$6:$G$41,5,0) -> 0 | G17: =IF(H17="ESPECES",3000,0) -> 0 | H17: =IF($D17<>0,"BANQUE",IF($E17<>0,"ESPECES","ECHEC")) -> ECHEC | J17: 1 | K17: =IF($D17<>0,J17*50000,IF($E17<>0,J17*50000,0)) -> 0 | M17: =IF($D17<>0,L17*75000,IF($E17<>0,L17*75000,0)) -> 0 | N17: 1 | O17: =IF($D17<>0,N17*100000,IF($E17<>0,N17*100000,0)) -> 0 | P17: =VLOOKUP(A17,[14]TONTJUIN24!$A$6:$R$39,12,0) -> 0 | R17: =VLOOKUP(A17,[16]TONTJUIN24!$A$7:$P$20,10,0) -> 0 | U17: =G17+S17++R17+P17+O17+M17+I17+K17+Q17+V17+W17 -> 0 | AQ17: =IF(H17="ECHEC",((K17+M17+O17)*20/100),0) -> 0 | AR17: =IF(H17="ECHEC",((K17+M17+O17)*20/100),0) -> 0 | AS17: =IF(H17="ECHEC",0,(K17+I17-25000)) -> 0 | AW17: =IF(AC17=0,AI17,(1*25000*12)+AI17-AC17) -> 0 | AX17: =IF(AD17=0,AJ17,(1*75000*12)+(AJ17)-AD17) -> 0 | AY17: =IF(AE17=0,AK17,(1*100000*12)+(AK17)-AE17) -> 0 | AZ17: =SUM(AV17:AY17)-BF17+Z17-F17+BH17+BI17+BJ17+BK17+BL17+BM17 -> 0 | BD17: =IF(AZ17=0,(AZ17-BA17-BC17),(AZ17-BA17-BB17-BC17)) -> 0 | BF17: =Z17*1/100*BG17 -> 0 | BG17: 6
A18: AS201604 | B18: =VLOOKUP(A18,[11]LISTADHERENT!A$5:H$50,3,0) -> KOUATCHO MESSACK | C18: =D18+E18+F18-U18-BB18 -> 0 | D18: =VLOOKUP(A18,[12]HISTOBQUEAVRIL24!$A$6:$G$46,3,0) -> 0 | E18: =VLOOKUP(A18,[12]HISTOBQUEAVRIL24!$A$6:$G$41,4,0) -> 0 | F18: =VLOOKUP(A18,[12]HISTOBQUEAVRIL24!$A$6:$G$41,5,0) -> 0 | G18: =IF(H18="ESPECES",3000,0) -> 0 | H18: =IF($D18<>0,"BANQUE",IF($E18<>0,"ESPECES","ECHEC")) -> ECHEC | J18: 1 | K18: =IF($D18<>0,J18*50000,IF($E18<>0,J18*50000,0)) -> 0 | M18: =IF($D18<>0,L18*75000,IF($E18<>0,L18*75000,0)) -> 0 | N18: 1 | O18: =IF($D18<>0,N18*100000,IF($E18<>0,N18*100000,0)) -> 0 | P18: =VLOOKUP(A18,[14]TONTJUIN24!$A$6:$R$39,12,0) -> 0 | R18: =VLOOKUP(A18,[16]TONTJUIN24!$A$7:$P$20,10,0) -> 0 | U18: =G18+S18++R18+P18+O18+M18+I18+K18+Q18+V18+W18 -> 0 | AQ18: =IF(H18="ECHEC",((K18+M18+O18)*20/100),0) -> 0 | AR18: =IF(H18="ECHEC",((K18+M18+O18)*20/100),0) -> 0 | AS18: =IF(H18="ECHEC",0,(K18+I18-25000)) -> 0 | AW18: =IF(AC18=0,AI18,(1*25000*12)+AI18-AC18) -> 0 | AX18: =IF(AD18=0,AJ18,(1*75000*12)+(AJ18)-AD18) -> 0 | AY18: =IF(AE18=0,AK18,(1*100000*12)+(AK18)-AE18) -> 0 | AZ18: =SUM(AV18:AY18)-BF18+Z18-F18+BH18+BI18+BJ18+BK18+BL18+BM18 -> 0 | BD18: =IF(AZ18=0,(AZ18-BA18-BC18),(AZ18-BA18-BB18-BC18)) -> 0 | BF18: =Z18*1/100*BG18 -> 0 | BG18: 6 | BN18: MONTANT_MUTUELLE | BO18: AS201633
A19: MOIS | B19: =VLOOKUP(A19,[11]LISTADHERENT!A$5:H$50,3,0) -> MASSEUNGOUE DAGOBERT | C19: =D19+E19+F19-U19-BB19 -> 0 | D19: =VLOOKUP(A19,[12]HISTOBQUEAVRIL24!$A$6:$G$46,3,0) -> 0 | E19: =VLOOKUP(A19,[12]HISTOBQUEAVRIL24!$A$6:$G$41,4,0) -> 0 | F19: =VLOOKUP(A19,[12]HISTOBQUEAVRIL24!$A$6:$G$41,5,0) -> 0 | G19: =IF(H19="ESPECES",3000,0) -> 0 | H19: =IF($D19<>0,"BANQUE",IF($E19<>0,"ESPECES","ECHEC")) -> ECHEC | J19: 1 | K19: =IF($D19<>0,J19*50000,IF($E19<>0,J19*50000,0)) -> 0 | M19: =IF($D19<>0,L19*75000,IF($E19<>0,L19*75000,0)) -> 0 | O19: =IF($D19<>0,N19*100000,IF($E19<>0,N19*100000,0)) -> 0 | P19: =VLOOKUP(A19,[14]TONTJUIN24!$A$6:$R$39,12,0) -> 0 | U19: =G19+S19++R19+P19+O19+M19+I19+K19+Q19+V19+W19 -> 0 | AQ19: =IF(H19="ECHEC",((K19+M19+O19)*20/100),0) -> 0 | AR19: =IF(H19="ECHEC",((K19+M19+O19)*20/100),0) -> 0 | AS19: =IF(H19="ECHEC",0,(K19+I19-25000)) -> 0 | AW19: =IF(AC19=0,AI19,(1*25000*12)+AI19-AC19) -> 0 | AX19: =IF(AD19=0,AJ19,(1*75000*12)+(AJ19)-AD19) -> 0 | AY19: =IF(AE19=0,AK19,(1*100000*12)+(AK19)-AE19) -> 0 | AZ19: =SUM(AV19:AY19)-BF19+Z19-F19+BH19+BI19+BJ19+BK19+BL19+BM19 -> 0 | BD19: =IF(AZ19=0,(AZ19-BA19-BC19),(AZ19-BA19-BB19-BC19)) -> 0 | BF19: =Z19*1/100*BG19 -> 0 | BG19: 6
A20: AS201608 | B20: =VLOOKUP(A20,[11]LISTADHERENT!A$5:H$50,3,0) -> MBOGNING TUGMA GUY | C20: =D20+E20+F20-U20-BB20 -> 0 | D20: =VLOOKUP(A20,[12]HISTOBQUEAVRIL24!$A$6:$G$46,3,0) -> 0 | E20: =VLOOKUP(A20,[12]HISTOBQUEAVRIL24!$A$6:$G$41,4,0) -> 0 | F20: =VLOOKUP(A20,[12]HISTOBQUEAVRIL24!$A$6:$G$41,5,0) -> 0 | G20: =IF(H20="ESPECES",3000,0) -> 0 | H20: =IF($D20<>0,"BANQUE",IF($E20<>0,"ESPECES","ECHEC")) -> ECHEC | J20: 1 | K20: =IF($D20<>0,J20*50000,IF($E20<>0,J20*50000,0)) -> 0 | L20: 1 | M20: =IF($D20<>0,L20*75000,IF($E20<>0,L20*75000,0)) -> 0 | N20: 1 | O20: =IF($D20<>0,N20*100000,IF($E20<>0,N20*100000,0)) -> 0 | P20: =VLOOKUP(A20,[14]TONTJUIN24!$A$6:$R$39,12,0) -> 0 | Q20: =VLOOKUP(A20,[15]TONTJUIN24!$A$7:$P$23,10,0) -> 0 | R20: =VLOOKUP(A20,[16]TONTJUIN24!$A$7:$P$20,10,0) -> 0 | U20: =G20+S20++R20+P20+O20+M20+I20+K20+Q20+V20+W20 -> 0 | AQ20: =IF(H20="ECHEC",((K20+M20+O20)*20/100),0) -> 0 | AR20: =IF(H20="ECHEC",((K20+M20+O20)*20/100),0) -> 0 | AS20: =IF(H20="ECHEC",0,(K20+I20-25000)) -> 0 | AW20: =IF(AC20=0,AI20,(1*25000*12)+AI20-AC20) -> 0 | AX20: =IF(AD20=0,AJ20,(1*75000*12)+(AJ20)-AD20) -> 0 | AY20: =IF(AE20=0,AK20,(1*100000*12)+(AK20)-AE20) -> 0 | AZ20: =SUM(AV20:AY20)-BF20+Z20-F20+BH20+BI20+BJ20+BK20+BL20+BM20 -> 0 | BD20: =IF(AZ20=0,(AZ20-BA20-BC20),(AZ20-BA20-BB20-BC20)) -> 0 | BF20: =Z20*1/100*BG20 -> 0 | BG20: 6
A21: AS201609 | B21: =VLOOKUP(A21,[11]LISTADHERENT!A$5:H$50,3,0) -> NANGUEN MARTIN | C21: =D21+E21+F21-U21-BB21 -> 0 | D21: =VLOOKUP(A21,[12]HISTOBQUEAVRIL24!$A$6:$G$46,3,0) -> 0 | E21: =VLOOKUP(A21,[12]HISTOBQUEAVRIL24!$A$6:$G$41,4,0) -> 0 | F21: =VLOOKUP(A21,[12]HISTOBQUEAVRIL24!$A$6:$G$41,5,0) -> 0 | G21: =IF(H21="ESPECES",3000,0) -> 0 | H21: =IF($D21<>0,"BANQUE",IF($E21<>0,"ESPECES","ECHEC")) -> ECHEC | J21: 1 | K21: =IF($D21<>0,J21*50000,IF($E21<>0,J21*50000,0)) -> 0 | M21: =IF($D21<>0,L21*75000,IF($E21<>0,L21*75000,0)) -> 0 | O21: =IF($D21<>0,N21*100000,IF($E21<>0,N21*100000,0)) -> 0 | P21: =VLOOKUP(A21,[14]TONTJUIN24!$A$6:$R$39,12,0) -> 0 | U21: =G21+S21++R21+P21+O21+M21+I21+K21+Q21+V21+W21 -> 0 | AQ21: =IF(H21="ECHEC",((K21+M21+O21)*20/100),0) -> 0 | AR21: =IF(H21="ECHEC",((K21+M21+O21)*20/100),0) -> 0 | AS21: =IF(H21="ECHEC",0,(K21+I21-25000)) -> 0 | AW21: =IF(AC21=0,AI21,(1*25000*12)+AI21-AC21) -> 0 | AX21: =IF(AD21=0,AJ21,(1*75000*12)+(AJ21)-AD21) -> 0 | AY21: =IF(AE21=0,AK21,(1*100000*12)+(AK21)-AE21) -> 0 | AZ21: =SUM(AV21:AY21)-BF21+Z21-F21+BH21+BI21+BJ21+BK21+BL21+BM21 -> 0 | BD21: =IF(AZ21=0,(AZ21-BA21-BC21),(AZ21-BA21-BB21-BC21)) -> 0 | BF21: =Z21*1/100*BG21 -> 0 | BG21: 6
A22: AS201610 | B22: =VLOOKUP(A22,[11]LISTADHERENT!A$5:H$50,3,0) -> NANKAM APPOLINAIRE | C22: =D22+E22+F22-U22-BB22 -> 0 | D22: =VLOOKUP(A22,[12]HISTOBQUEAVRIL24!$A$6:$G$46,3,0) -> 0 | E22: =VLOOKUP(A22,[12]HISTOBQUEAVRIL24!$A$6:$G$41,4,0) -> 0 | F22: =VLOOKUP(A22,[12]HISTOBQUEAVRIL24!$A$6:$G$41,5,0) -> 0 | G22: =IF(H22="ESPECES",3000,0) -> 0 | H22: =IF($D22<>0,"BANQUE",IF($E22<>0,"ESPECES","ECHEC")) -> ECHEC | J22: 1 | K22: =IF($D22<>0,J22*50000,IF($E22<>0,J22*50000,0)) -> 0 | L22: 1 | M22: =IF($D22<>0,L22*75000,IF($E22<>0,L22*75000,0)) -> 0 | O22: =IF($D22<>0,N22*100000,IF($E22<>0,N22*100000,0)) -> 0 | P22: =VLOOKUP(A22,[14]TONTJUIN24!$A$6:$R$39,12,0) -> 0 | Q22: =VLOOKUP(A22,[15]TONTJUIN24!$A$7:$P$23,10,0) -> 0 | U22: =G22+S22++R22+P22+O22+M22+I22+K22+Q22+V22+W22 -> 0 | AQ22: =IF(H22="ECHEC",((K22+M22+O22)*20/100),0) -> 0 | AR22: =IF(H22="ECHEC",((K22+M22+O22)*20/100),0) -> 0 | AS22: =IF(H22="ECHEC",0,(K22+I22-25000)) -> 0 | AW22: =IF(AC22=0,AI22,(1*25000*12)+AI22-AC22) -> 0 | AX22: =IF(AD22=0,AJ22,(1*75000*12)+(AJ22)-AD22) -> 0 | AY22: =IF(AE22=0,AK22,(1*100000*12)+(AK22)-AE22) -> 0 | AZ22: =SUM(AV22:AY22)-BF22+Z22-F22+BH22+BI22+BJ22+BK22+BL22+BM22 -> 0 | BD22: =IF(AZ22=0,(AZ22-BA22-BC22),(AZ22-BA22-BB22-BC22)) -> 0 | BF22: =Z22*1/100*BG22 -> 0 | BG22: 6 | BN22: INTERET | BP22: =SUM(BP18:BP21) -> 0
A23: AS201611 | B23: =VLOOKUP(A23,[11]LISTADHERENT!A$5:H$50,3,0) -> NDJOMO ETIENNE | C23: =D23+E23+F23-U23-BB23 -> 0 | D23: =VLOOKUP(A23,[12]HISTOBQUEAVRIL24!$A$6:$G$46,3,0) -> 0 | E23: =VLOOKUP(A23,[12]HISTOBQUEAVRIL24!$A$6:$G$41,4,0) -> 0 | F23: =VLOOKUP(A23,[12]HISTOBQUEAVRIL24!$A$6:$G$41,5,0) -> 0 | G23: =IF(H23="ESPECES",3000,0) -> 0 | H23: =IF($D23<>0,"BANQUE",IF($E23<>0,"ESPECES","ECHEC")) -> ECHEC | J23: 1 | K23: =IF($D23<>0,J23*50000,IF($E23<>0,J23*50000,0)) -> 0 | M23: =IF($D23<>0,L23*75000,IF($E23<>0,L23*75000,0)) -> 0 | N23: 2 | O23: =IF($D23<>0,N23*100000,IF($E23<>0,N23*100000,0)) -> 0 | P23: =VLOOKUP(A23,[14]TONTJUIN24!$A$6:$R$39,12,0) -> 0 | R23: =VLOOKUP(A23,[16]TONTJUIN24!$A$7:$P$20,10,0) -> 0 | U23: =G23+S23++R23+P23+O23+M23+I23+K23+Q23+V23+W23 -> 0 | AQ23: =IF(H23="ECHEC",((K23+M23+O23)*20/100),0) -> 0 | AR23: =IF(H23="ECHEC",((K23+M23+O23)*20/100),0) -> 0 | AS23: =IF(H23="ECHEC",0,(K23+I23-25000)) -> 0 | AW23: =IF(AC23=0,AI23,(1*25000*12)+AI23-AC23) -> 0 | AX23: =IF(AD23=0,AJ23,(1*75000*12)+(AJ23)-AD23) -> 0 | AY23: =IF(AE23=0,AK23,(1*100000*12)+(AK23)-AE23) -> 0 | AZ23: =SUM(AV23:AY23)-BF23+Z23-F23+BH23+BI23+BJ23+BK23+BL23+BM23 -> 0 | BD23: =IF(AZ23=0,(AZ23-BA23-BC23),(AZ23-BA23-BB23-BC23)) -> 0 | BF23: =Z23*1/100*BG23 -> 0 | BG23: 6
A24: AS201613 | B24: =VLOOKUP(A24,[11]LISTADHERENT!A$5:H$50,3,0) -> NGONDIEP CLAUDE | C24: =D24+E24+F24-U24-BB24 -> 0 | D24: =VLOOKUP(A24,[12]HISTOBQUEAVRIL24!$A$6:$G$46,3,0) -> 0 | E24: =VLOOKUP(A24,[12]HISTOBQUEAVRIL24!$A$6:$G$41,4,0) -> 0 | F24: =VLOOKUP(A24,[12]HISTOBQUEAVRIL24!$A$6:$G$41,5,0) -> 0 | G24: =IF(H24="ESPECES",3000,0) -> 0 | H24: =IF($D24<>0,"BANQUE",IF($E24<>0,"ESPECES","ECHEC")) -> ECHEC | J24: 1 | K24: =IF($D24<>0,J24*50000,IF($E24<>0,J24*50000,0)) -> 0 | L24: 1 | M24: =IF($D24<>0,L24*75000,IF($E24<>0,L24*75000,0)) -> 0 | N24: 1 | O24: =IF($D24<>0,N24*100000,IF($E24<>0,N24*100000,0)) -> 0 | P24: =VLOOKUP(A24,[14]TONTJUIN24!$A$6:$R$39,12,0) -> 0 | Q24: =VLOOKUP(A24,[15]TONTJUIN24!$A$7:$P$23,10,0) -> 0 | R24: =VLOOKUP(A24,[16]TONTJUIN24!$A$7:$P$20,10,0) -> 0 | U24: =G24+S24++R24+P24+O24+M24+I24+K24+Q24+V24+W24 -> 0 | AQ24: =IF(H24="ECHEC",((K24+M24+O24)*20/100),0) -> 0 | AR24: =IF(H24="ECHEC",((K24+M24+O24)*20/100),0) -> 0 | AS24: =IF(H24="ECHEC",0,(K24+I24-25000)) -> 0 | AW24: =IF(AC24=0,AI24,(1*25000*12)+AI24-AC24) -> 0 | AX24: =IF(AD24=0,AJ24,(1*75000*12)+(AJ24)-AD24) -> 0 | AY24: =IF(AE24=0,AK24,(1*100000*12)+(AK24)-AE24) -> 0 | AZ24: =SUM(AV24:AY24)-BF24+Z24-F24+BH24+BI24+BJ24+BK24+BL24+BM24 -> 0 | BD24: =IF(AZ24=0,(AZ24-BA24-BC24),(AZ24-BA24-BB24-BC24)) -> 0 | BF24: =Z24*1/100*BG24 -> 0 | BG24: 6 | BN24: MONTANT_MUTUELLE | BO24: SIMO FONGANG ERIC
A25: AS201614 | B25: =VLOOKUP(A25,[11]LISTADHERENT!A$5:H$50,3,0) -> NGUIEMEGNI MATHIEU BLAISE | C25: =D25+E25+F25-U25-BB25 -> 0 | D25: =VLOOKUP(A25,[12]HISTOBQUEAVRIL24!$A$6:$G$46,3,0) -> 0 | E25: =VLOOKUP(A25,[12]HISTOBQUEAVRIL24!$A$6:$G$41,4,0) -> 0 | F25: =VLOOKUP(A25,[12]HISTOBQUEAVRIL24!$A$6:$G$41,5,0) -> 0 | G25: =IF(H25="ESPECES",3000,0) -> 0 | H25: =IF($D25<>0,"BANQUE",IF($E25<>0,"ESPECES","ECHEC")) -> ECHEC | J25: 1 | K25: =IF($D25<>0,J25*50000,IF($E25<>0,J25*50000,0)) -> 0 | L25: 3 | M25: =IF($D25<>0,L25*75000,IF($E25<>0,L25*75000,0)) -> 0 | N25: 1 | O25: =IF($D25<>0,N25*100000,IF($E25<>0,N25*100000,0)) -> 0 | P25: =VLOOKUP(A25,[14]TONTJUIN24!$A$6:$R$39,12,0) -> 0 | Q25: =VLOOKUP(A25,[15]TONTJUIN24!$A$7:$P$23,10,0) -> 0 | R25: =VLOOKUP(A25,[16]TONTJUIN24!$A$7:$P$20,10,0) -> 0 | U25: =G25+S25++R25+P25+O25+M25+I25+K25+Q25+V25+W25 -> 0 | AQ25: =IF(H25="ECHEC",((K25+M25+O25)*20/100),0) -> 0 | AR25: =IF(H25="ECHEC",((K25+M25+O25)*20/100),0) -> 0 | AS25: =IF(H25="ECHEC",0,(K25+I25-25000)) -> 0 | AW25: =IF(AC25=0,AI25,(1*25000*12)+AI25-AC25) -> 0 | AX25: =IF(AD25=0,AJ25,(1*75000*12)+(AJ25)-AD25) -> 0 | AY25: =IF(AE25=0,AK25,(1*100000*12)+(AK25)-AE25) -> 0 | AZ25: =SUM(AV25:AY25)-BF25+Z25-F25+BH25+BI25+BJ25+BK25+BL25+BM25 -> 0 | BD25: =IF(AZ25=0,(AZ25-BA25-BC25),(AZ25-BA25-BB25-BC25)) -> 0 | BF25: =Z25*1/100*BG25 -> 0 | BG25: 6 | BN25: TIEYAM ERNEST | BO25: SIMO FONGANG ERIC
A26: AS201615 | B26: =VLOOKUP(A26,[11]LISTADHERENT!A$5:H$50,3,0) -> NKAMGANG JUSTIN DEJOLIE | C26: =D26+E26+F26-U26-BB26 -> 0 | D26: =VLOOKUP(A26,[12]HISTOBQUEAVRIL24!$A$6:$G$46,3,0) -> 0 | E26: =VLOOKUP(A26,[12]HISTOBQUEAVRIL24!$A$6:$G$41,4,0) -> 0 | F26: =VLOOKUP(A26,[12]HISTOBQUEAVRIL24!$A$6:$G$41,5,0) -> 0 | G26: =IF(H26="ESPECES",3000,0) -> 0 | H26: =IF($D26<>0,"BANQUE",IF($E26<>0,"ESPECES","ECHEC")) -> ECHEC | J26: 1 | K26: =IF($D26<>0,J26*50000,IF($E26<>0,J26*50000,0)) -> 0 | M26: =IF($D26<>0,L26*75000,IF($E26<>0,L26*75000,0)) -> 0 | O26: =IF($D26<>0,N26*100000,IF($E26<>0,N26*100000,0)) -> 0 | P26: =VLOOKUP(A26,[14]TONTJUIN24!$A$6:$R$39,12,0) -> 0 | U26: =G26+S26++R26+P26+O26+M26+I26+K26+Q26+V26+W26 -> 0 | AQ26: =IF(H26="ECHEC",((K26+M26+O26)*20/100),0) -> 0 | AR26: =IF(H26="ECHEC",((K26+M26+O26)*20/100),0) -> 0 | AS26: =IF(H26="ECHEC",0,(K26+I26-25000)) -> 0 | AW26: =IF(AC26=0,AI26,(1*25000*12)+AI26-AC26) -> 0 | AX26: =IF(AD26=0,AJ26,(1*75000*12)+(AJ26)-AD26) -> 0 | AY26: =IF(AE26=0,AK26,(1*100000*12)+(AK26)-AE26) -> 0 | AZ26: =SUM(AV26:AY26)-BF26+Z26-F26+BH26+BI26+BJ26+BK26+BL26+BM26 -> 0 | BD26: =IF(AZ26=0,(AZ26-BA26-BC26),(AZ26-BA26-BB26-BC26)) -> 0 | BF26: =Z26*1/100*BG26 -> 0 | BG26: 6 | BN26: NOM_ET_PRENOM | BO26: SIMO FONGANG ERIC
A27: DETTE CHINGUE | B27: =VLOOKUP(A27,[11]LISTADHERENT!A$5:H$50,3,0) -> NOUBE ETIENNE | C27: =D27+E27+F27-U27-BB27 -> 0 | D27: =VLOOKUP(A27,[12]HISTOBQUEAVRIL24!$A$6:$G$46,3,0) -> 0 | E27: =VLOOKUP(A27,[12]HISTOBQUEAVRIL24!$A$6:$G$41,4,0) -> 0 | F27: =VLOOKUP(A27,[12]HISTOBQUEAVRIL24!$A$6:$G$41,5,0) -> 0 | G27: =IF(H27="ESPECES",3000,0) -> 0 | H27: =IF($D27<>0,"BANQUE",IF($E27<>0,"ESPECES","ECHEC")) -> ECHEC | J27: 1 | K27: =IF($D27<>0,J27*50000,IF($E27<>0,J27*50000,0)) -> 0 | M27: =IF($D27<>0,L27*75000,IF($E27<>0,L27*75000,0)) -> 0 | O27: =IF($D27<>0,N27*100000,IF($E27<>0,N27*100000,0)) -> 0 | P27: =VLOOKUP(A27,[14]TONTJUIN24!$A$6:$R$39,12,0) -> 0 | U27: =G27+S27++R27+P27+O27+M27+I27+K27+Q27+V27+W27 -> 0 | AQ27: =IF(H27="ECHEC",((K27+M27+O27)*20/100),0) -> 0 | AR27: =IF(H27="ECHEC",((K27+M27+O27)*20/100),0) -> 0 | AS27: =IF(H27="ECHEC",0,(K27+I27-25000)) -> 0 | AW27: =IF(AC27=0,AI27,(1*25000*12)+AI27-AC27) -> 0 | AX27: =IF(AD27=0,AJ27,(1*75000*12)+(AJ27)-AD27) -> 0 | AY27: =IF(AE27=0,AK27,(1*100000*12)+(AK27)-AE27) -> 0 | AZ27: =SUM(AV27:AY27)-BF27+Z27-F27+BH27+BI27+BJ27+BK27+BL27+BM27 -> 0 | BD27: =IF(AZ27=0,(AZ27-BA27-BC27),(AZ27-BA27-BB27-BC27)) -> 0 | BF27: =Z27*1/100*BG27 -> 0 | BG27: 6
A28: AS201618 | B28: =VLOOKUP(A28,[11]LISTADHERENT!A$5:H$50,3,0) -> PATEGO NJOSSU GUSTAVE | C28: =D28+E28+F28-U28-BB28 -> 0 | D28: =VLOOKUP(A28,[12]HISTOBQUEAVRIL24!$A$6:$G$46,3,0) -> 0 | E28: =VLOOKUP(A28,[12]HISTOBQUEAVRIL24!$A$6:$G$41,4,0) -> 0 | F28: =VLOOKUP(A28,[12]HISTOBQUEAVRIL24!$A$6:$G$41,5,0) -> 0 | G28: =IF(H28="ESPECES",3000,0) -> 0 | H28: =IF($D28<>0,"BANQUE",IF($E28<>0,"ESPECES","ECHEC")) -> ECHEC | J28: 1 | K28: =IF($D28<>0,J28*50000,IF($E28<>0,J28*50000,0)) -> 0 | L28: 1 | M28: =IF($D28<>0,L28*75000,IF($E28<>0,L28*75000,0)) -> 0 | O28: =IF($D28<>0,N28*100000,IF($E28<>0,N28*100000,0)) -> 0 | P28: =VLOOKUP(A28,[14]TONTJUIN24!$A$6:$R$39,12,0) -> 0 | Q28: =VLOOKUP(A28,[15]TONTJUIN24!$A$7:$P$23,10,0) -> 0 | U28: =G28+S28++R28+P28+O28+M28+I28+K28+Q28+V28+W28 -> 0 | AQ28: =IF(H28="ECHEC",((K28+M28+O28)*20/100),0) -> 0 | AR28: =IF(H28="ECHEC",((K28+M28+O28)*20/100),0) -> 0 | AS28: =IF(H28="ECHEC",0,(K28+I28-25000)) -> 0 | AW28: =IF(AC28=0,AI28,(1*25000*12)+AI28-AC28) -> 0 | AX28: =IF(AD28=0,AJ28,(1*75000*12)+(AJ28)-AD28) -> 0 | AY28: =IF(AE28=0,AK28,(1*100000*12)+(AK28)-AE28) -> 0 | AZ28: =SUM(AV28:AY28)-BF28+Z28-F28+BH28+BI28+BJ28+BK28+BL28+BM28 -> 0 | BD28: =IF(AZ28=0,(AZ28-BA28-BC28),(AZ28-BA28-BB28-BC28)) -> 0 | BF28: =Z28*1/100*BG28 -> 0 | BG28: 6 | BN28: INTERET | BP28: =SUM(BP24:BP26) -> 0
A29: MONTANT DETTE | B29: =VLOOKUP(A29,[11]LISTADHERENT!A$5:H$50,3,0) -> SEUMO POLYCARPE | C29: =D29+E29+F29-U29-BB29 -> 0 | D29: =VLOOKUP(A29,[12]HISTOBQUEAVRIL24!$A$6:$G$46,3,0) -> 0 | E29: =VLOOKUP(A29,[12]HISTOBQUEAVRIL24!$A$6:$G$41,4,0) -> 0 | F29: =VLOOKUP(A29,[12]HISTOBQUEAVRIL24!$A$6:$G$41,5,0) -> 0 | G29: =IF(H29="ESPECES",3000,0) -> 0 | H29: =IF($D29<>0,"BANQUE",IF($E29<>0,"ESPECES","ECHEC")) -> ECHEC | J29: 1 | K29: =IF($D29<>0,J29*50000,IF($E29<>0,J29*50000,0)) -> 0 | M29: =IF($D29<>0,L29*75000,IF($E29<>0,L29*75000,0)) -> 0 | O29: =IF($D29<>0,N29*100000,IF($E29<>0,N29*100000,0)) -> 0 | P29: =VLOOKUP(A29,[14]TONTJUIN24!$A$6:$R$39,12,0) -> 0 | U29: =G29+S29++R29+P29+O29+M29+I29+K29+Q29+V29+W29 -> 0 | AQ29: =IF(H29="ECHEC",((K29+M29+O29)*20/100),0) -> 0 | AR29: =IF(H29="ECHEC",((K29+M29+O29)*20/100),0) -> 0 | AS29: =IF(H29="ECHEC",0,(K29+I29-25000)) -> 0 | AW29: =IF(AC29=0,AI29,(1*25000*12)+AI29-AC29) -> 0 | AX29: =IF(AD29=0,AJ29,(1*75000*12)+(AJ29)-AD29) -> 0 | AY29: =IF(AE29=0,AK29,(1*100000*12)+(AK29)-AE29) -> 0 | AZ29: =SUM(AV29:AY29)-BF29+Z29-F29+BH29+BI29+BJ29+BK29+BL29+BM29 -> 0 | BD29: =IF(AZ29=0,(AZ29-BA29-BC29),(AZ29-BA29-BB29-BC29)) -> 0 | BF29: =Z29*1/100*BG29 -> 0 | BG29: 6
A30: AS201619 | B30: =VLOOKUP(A30,[11]LISTADHERENT!A$5:H$50,3,0) -> SIME BRICE | C30: =D30+E30+F30-U30-BB30 -> 0 | D30: =VLOOKUP(A30,[12]HISTOBQUEAVRIL24!$A$6:$G$46,3,0) -> 0 | E30: =VLOOKUP(A30,[12]HISTOBQUEAVRIL24!$A$6:$G$41,4,0) -> 0 | F30: =VLOOKUP(A30,[12]HISTOBQUEAVRIL24!$A$6:$G$41,5,0) -> 0 | G30: =IF(H30="ESPECES",3000,0) -> 0 | H30: =IF($D30<>0,"BANQUE",IF($E30<>0,"ESPECES","ECHEC")) -> ECHEC | J30: 1 | K30: =IF($D30<>0,J30*50000,IF($E30<>0,J30*50000,0)) -> 0 | M30: =IF($D30<>0,L30*75000,IF($E30<>0,L30*75000,0)) -> 0 | N30: 2 | O30: =IF($D30<>0,N30*100000,IF($E30<>0,N30*100000,0)) -> 0 | P30: =VLOOKUP(A30,[14]TONTJUIN24!$A$6:$R$39,12,0) -> 0 | R30: =VLOOKUP(A30,[16]TONTJUIN24!$A$7:$P$20,10,0) -> 0 | U30: =G30+S30++R30+P30+O30+M30+I30+K30+Q30+V30+W30 -> 0 | AQ30: =IF(H30="ECHEC",((K30+M30+O30)*20/100),0) -> 0 | AR30: =IF(H30="ECHEC",((K30+M30+O30)*20/100),0) -> 0 | AS30: =IF(H30="ECHEC",0,(K30+I30-25000)) -> 0 | AW30: =IF(AC30=0,AI30,(1*25000*12)+AI30-AC30) -> 0 | AX30: =IF(AD30=0,AJ30,(1*75000*12)+(AJ30)-AD30) -> 0 | AY30: =IF(AE30=0,AK30,(1*100000*12)+(AK30)-AE30) -> 0 | AZ30: =SUM(AV30:AY30)-BF30+Z30-F30+BH30+BI30+BJ30+BK30+BL30+BM30 -> 0 | BD30: =IF(AZ30=0,(AZ30-BA30-BC30),(AZ30-BA30-BB30-BC30)) -> 0 | BF30: =Z30*1/100*BG30 -> 0 | BG30: 6 | BN30: TABLEAU RECAPITULATIF PRÊT | BO30: AS201639
A31: AS201621 | B31: =VLOOKUP(A31,[11]LISTADHERENT!A$5:H$50,3,0) -> SIMO PIERRE | C31: =D31+E31+F31-U31-BB31 -> 0 | D31: =VLOOKUP(A31,[12]HISTOBQUEAVRIL24!$A$6:$G$46,3,0) -> 0 | E31: =VLOOKUP(A31,[12]HISTOBQUEAVRIL24!$A$6:$G$41,4,0) -> 0 | F31: =VLOOKUP(A31,[12]HISTOBQUEAVRIL24!$A$6:$G$41,5,0) -> 0 | G31: =IF(H31="ESPECES",3000,0) -> 0 | H31: =IF($D31<>0,"BANQUE",IF($E31<>0,"ESPECES","ECHEC")) -> ECHEC | J31: 1 | K31: =IF($D31<>0,J31*50000,IF($E31<>0,J31*50000,0)) -> 0 | M31: =IF($D31<>0,L31*75000,IF($E31<>0,L31*75000,0)) -> 0 | N31: 1 | O31: =IF($D31<>0,N31*100000,IF($E31<>0,N31*100000,0)) -> 0 | P31: =VLOOKUP(A31,[14]TONTJUIN24!$A$6:$R$39,12,0) -> 0 | R31: =VLOOKUP(A31,[16]TONTJUIN24!$A$7:$P$20,10,0) -> 0 | U31: =G31+S31++R31+P31+O31+M31+I31+K31+Q31+V31+W31 -> 0 | AQ31: =IF(H31="ECHEC",((K31+M31+O31)*20/100),0) -> 0 | AR31: =IF(H31="ECHEC",((K31+M31+O31)*20/100),0) -> 0 | AS31: =IF(H31="ECHEC",0,(K31+I31-25000)) -> 0 | AW31: =IF(AC31=0,AI31,(1*25000*12)+AI31-AC31) -> 0 | AX31: =IF(AD31=0,AJ31,(1*75000*12)+(AJ31)-AD31) -> 0 | AY31: =IF(AE31=0,AK31,(1*100000*12)+(AK31)-AE31) -> 0 | AZ31: =SUM(AV31:AY31)-BF31+Z31-F31+BH31+BI31+BJ31+BK31+BL31+BM31 -> 0 | BD31: =IF(AZ31=0,(AZ31-BA31-BC31),(AZ31-BA31-BB31-BC31)) -> 0 | BF31: =Z31*1/100*BG31 -> 0 | BG31: 6 | BN31: A APURER | BO31: AS201639
A32: AS201622 | B32: =VLOOKUP(A32,[11]LISTADHERENT!A$5:H$50,3,0) -> TCHOUAMOU MATHIEU | C32: =D32+E32+F32-U32-BB32 -> 0 | D32: =VLOOKUP(A32,[12]HISTOBQUEAVRIL24!$A$6:$G$46,3,0) -> 0 | E32: =VLOOKUP(A32,[12]HISTOBQUEAVRIL24!$A$6:$G$41,4,0) -> 0 | F32: =VLOOKUP(A32,[12]HISTOBQUEAVRIL24!$A$6:$G$41,5,0) -> 0 | G32: =IF(H32="ESPECES",3000,0) -> 0 | H32: =IF($D32<>0,"BANQUE",IF($E32<>0,"ESPECES","ECHEC")) -> ECHEC | J32: 1 | K32: =IF($D32<>0,J32*50000,IF($E32<>0,J32*50000,0)) -> 0 | L32: 1 | M32: =IF($D32<>0,L32*75000,IF($E32<>0,L32*75000,0)) -> 0 | O32: =IF($D32<>0,N32*100000,IF($E32<>0,N32*100000,0)) -> 0 | P32: =VLOOKUP(A32,[14]TONTJUIN24!$A$6:$R$39,12,0) -> 0 | Q32: =VLOOKUP(A32,[15]TONTJUIN24!$A$7:$P$23,10,0) -> 0 | U32: =G32+S32++R32+P32+O32+M32+I32+K32+Q32+V32+W32 -> 0 | AQ32: =IF(H32="ECHEC",((K32+M32+O32)*20/100),0) -> 0 | AR32: =IF(H32="ECHEC",((K32+M32+O32)*20/100),0) -> 0 | AS32: =IF(H32="ECHEC",0,(K32+I32-25000)) -> 0 | AW32: =IF(AC32=0,AI32,(1*25000*12)+AI32-AC32) -> 0 | AX32: =IF(AD32=0,AJ32,(1*75000*12)+(AJ32)-AD32) -> 0 | AY32: =IF(AE32=0,AK32,(1*100000*12)+(AK32)-AE32) -> 0 | AZ32: =SUM(AV32:AY32)-BF32+Z32-F32+BH32+BI32+BJ32+BK32+BL32+BM32 -> 0 | BD32: =IF(AZ32=0,(AZ32-BA32-BC32),(AZ32-BA32-BB32-BC32)) -> 0 | BF32: =Z32*1/100*BG32 -> 0 | BG32: 6 | BN32: AOÛT
A33: SOLDE | B33: =VLOOKUP(A33,[11]LISTADHERENT!A$5:H$50,3,0) -> TCHOUATEU AUGUSTIN | C33: =D33+E33+F33-U33-BB33 -> 0 | D33: =VLOOKUP(A33,[12]HISTOBQUEAVRIL24!$A$6:$G$46,3,0) -> 0 | E33: =VLOOKUP(A33,[12]HISTOBQUEAVRIL24!$A$6:$G$41,4,0) -> 0 | F33: =VLOOKUP(A33,[12]HISTOBQUEAVRIL24!$A$6:$G$41,5,0) -> 0 | G33: =IF(H33="ESPECES",3000,0) -> 0 | H33: =IF($D33<>0,"BANQUE",IF($E33<>0,"ESPECES","ECHEC")) -> ECHEC | J33: 1 | K33: =IF($D33<>0,J33*50000,IF($E33<>0,J33*50000,0)) -> 0 | M33: =IF($D33<>0,L33*75000,IF($E33<>0,L33*75000,0)) -> 0 | N33: 1 | O33: =IF($D33<>0,N33*100000,IF($E33<>0,N33*100000,0)) -> 0 | P33: =VLOOKUP(A33,[14]TONTJUIN24!$A$6:$R$39,12,0) -> 0 | R33: =VLOOKUP(A33,[16]TONTJUIN24!$A$7:$P$20,10,0) -> 0 | U33: =G33+S33++R33+P33+O33+M33+I33+K33+Q33+V33+W33 -> 0 | AQ33: =IF(H33="ECHEC",((K33+M33+O33)*20/100),0) -> 0 | AR33: =IF(H33="ECHEC",((K33+M33+O33)*20/100),0) -> 0 | AS33: =IF(H33="ECHEC",0,(K33+I33-25000)) -> 0 | AW33: =IF(AC33=0,AI33,(1*25000*12)+AI33-AC33) -> 0 | AX33: =IF(AD33=0,AJ33,(1*75000*12)+(AJ33)-AD33) -> 0 | AY33: =IF(AE33=0,AK33,(1*100000*12)+(AK33)-AE33) -> 0 | AZ33: =SUM(AV33:AY33)-BF33+Z33-F33+BH33+BI33+BJ33+BK33+BL33+BM33 -> 0 | BD33: =IF(AZ33=0,(AZ33-BA33-BC33),(AZ33-BA33-BB33-BC33)) -> 0 | BF33: =Z33*1/100*BG33 -> 0 | BG33: 6 | BN33: INTERET | BP33: =SUM(BP30:BP32) -> 0
A34: AOUT 2018 A NOVEMBRE 2019 | B34: =VLOOKUP(A34,[11]LISTADHERENT!A$5:H$50,3,0) -> TCHOUTOU NANA CLAUDE | C34: =D34+E34+F34-U34-BB34 -> 0 | D34: =VLOOKUP(A34,[12]HISTOBQUEAVRIL24!$A$6:$G$46,3,0) -> 0 | E34: =VLOOKUP(A34,[12]HISTOBQUEAVRIL24!$A$6:$G$41,4,0) -> 0 | F34: =VLOOKUP(A34,[12]HISTOBQUEAVRIL24!$A$6:$G$41,5,0) -> 0 | G34: =IF(H34="ESPECES",3000,0) -> 0 | H34: =IF($D34<>0,"BANQUE",IF($E34<>0,"ESPECES","ECHEC")) -> ECHEC | J34: 1 | K34: =IF($D34<>0,J34*50000,IF($E34<>0,J34*50000,0)) -> 0 | M34: =IF($D34<>0,L34*75000,IF($E34<>0,L34*75000,0)) -> 0 | O34: =IF($D34<>0,N34*100000,IF($E34<>0,N34*100000,0)) -> 0 | P34: =VLOOKUP(A34,[14]TONTJUIN24!$A$6:$R$39,12,0) -> 0 | U34: =G34+S34++R34+P34+O34+M34+I34+K34+Q34+V34+W34 -> 0 | AQ34: =IF(H34="ECHEC",((K34+M34+O34)*20/100),0) -> 0 | AR34: =IF(H34="ECHEC",((K34+M34+O34)*20/100),0) -> 0 | AS34: =IF(H34="ECHEC",0,(K34+I34-25000)) -> 0 | AW34: =IF(AC34=0,AI34,(1*25000*12)+AI34-AC34) -> 0 | AX34: =IF(AD34=0,AJ34,(1*75000*12)+(AJ34)-AD34) -> 0 | AY34: =IF(AE34=0,AK34,(1*100000*12)+(AK34)-AE34) -> 0 | AZ34: =SUM(AV34:AY34)-BF34+Z34-F34+BH34+BI34+BJ34+BK34+BL34+BM34 -> 0 | BD34: =IF(AZ34=0,(AZ34-BA34-BC34),(AZ34-BA34-BB34-BC34)) -> 0 | BF34: =Z34*1/100*BG34 -> 0 | BG34: 6 | BN34: INTERET | BP34: =SUM(BP31:BP33) -> 0
A35: REMBOURSEMENT | B35: =VLOOKUP(A35,[11]LISTADHERENT!A$5:H$50,3,0) -> YANTCHOU GERVAIS | C35: =D35+E35+F35-U35-BB35 -> 0 | D35: =VLOOKUP(A35,[12]HISTOBQUEAVRIL24!$A$6:$G$46,3,0) -> 0 | E35: =VLOOKUP(A35,[12]HISTOBQUEAVRIL24!$A$6:$G$41,4,0) -> 0 | F35: =VLOOKUP(A35,[12]HISTOBQUEAVRIL24!$A$6:$G$41,5,0) -> 0 | G35: =IF(H35="ESPECES",3000,0) -> 0 | H35: =IF($D35<>0,"BANQUE",IF($E35<>0,"ESPECES","ECHEC")) -> ECHEC | J35: 1 | K35: =IF($D35<>0,J35*50000,IF($E35<>0,J35*50000,0)) -> 0 | M35: =IF($D35<>0,L35*75000,IF($E35<>0,L35*75000,0)) -> 0 | O35: =IF($D35<>0,N35*100000,IF($E35<>0,N35*100000,0)) -> 0 | P35: =VLOOKUP(A35,[14]TONTJUIN24!$A$6:$R$39,12,0) -> 0 | U35: =G35+S35++R35+P35+O35+M35+I35+K35+Q35+V35+W35 -> 0 | AQ35: =IF(H35="ECHEC",((K35+M35+O35)*20/100),0) -> 0 | AR35: =IF(H35="ECHEC",((K35+M35+O35)*20/100),0) -> 0 | AS35: =IF(H35="ECHEC",0,(K35+I35-25000)) -> 0 | AW35: =IF(AC35=0,AI35,(1*25000*12)+AI35-AC35) -> 0 | AX35: =IF(AD35=0,AJ35,(1*75000*12)+(AJ35)-AD35) -> 0 | AY35: =IF(AE35=0,AK35,(1*100000*12)+(AK35)-AE35) -> 0 | AZ35: =SUM(AV35:AY35)-BF35+Z35-F35+BH35+BI35+BJ35+BK35+BL35+BM35 -> 0 | BD35: =IF(AZ35=0,(AZ35-BA35-BC35),(AZ35-BA35-BB35-BC35)) -> 0 | BF35: =Z35*1/100*BG35 -> 0 | BG35: 6
A36: AS201625 | B36: =VLOOKUP(A36,[11]LISTADHERENT!A$5:H$50,3,0) -> YEPMOU JEAN JACQUES | C36: =D36+E36+F36-U36-BB36 -> 0 | D36: =VLOOKUP(A36,[12]HISTOBQUEAVRIL24!$A$6:$G$46,3,0) -> 0 | E36: =VLOOKUP(A36,[12]HISTOBQUEAVRIL24!$A$6:$G$41,4,0) -> 0 | F36: =VLOOKUP(A36,[12]HISTOBQUEAVRIL24!$A$6:$G$41,5,0) -> 0 | G36: =IF(H36="ESPECES",3000,0) -> 0 | H36: =IF($D36<>0,"BANQUE",IF($E36<>0,"ESPECES","ECHEC")) -> ECHEC | J36: 1 | K36: =IF($D36<>0,J36*50000,IF($E36<>0,J36*50000,0)) -> 0 | M36: =IF($D36<>0,L36*75000,IF($E36<>0,L36*75000,0)) -> 0 | O36: =IF($D36<>0,N36*100000,IF($E36<>0,N36*100000,0)) -> 0 | P36: =VLOOKUP(A36,[14]TONTJUIN24!$A$6:$R$39,12,0) -> 0 | U36: =G36+S36++R36+P36+O36+M36+I36+K36+Q36+V36+W36 -> 0 | AQ36: =IF(H36="ECHEC",((K36+M36+O36)*20/100),0) -> 0 | AR36: =IF(H36="ECHEC",((K36+M36+O36)*20/100),0) -> 0 | AS36: =IF(H36="ECHEC",0,(K36+I36-25000)) -> 0 | AW36: =IF(AC36=0,AI36,(1*25000*12)+AI36-AC36) -> 0 | AX36: =IF(AD36=0,AJ36,(1*75000*12)+(AJ36)-AD36) -> 0 | AY36: =IF(AE36=0,AK36,(1*100000*12)+(AK36)-AE36) -> 0 | AZ36: =SUM(AV36:AY36)-BF36+Z36-F36+BH36+BI36+BJ36+BK36+BL36+BM36 -> 0 | BD36: =IF(AZ36=0,(AZ36-BA36-BC36),(AZ36-BA36-BB36-BC36)) -> 0 | BF36: =Z36*1/100*BG36 -> 0 | BG36: 6 | BN36: YEPMOU JEAN JACQUES | BO36: YEPMOU JEAN JACQUES
A37: SORTIE | B37: =VLOOKUP(A37,[11]LISTADHERENT!A$5:H$50,3,0) -> YIALA ALAIN OSCAR | C37: =D37+E37+F37-U37-BB37 -> 0 | D37: =VLOOKUP(A37,[12]HISTOBQUEAVRIL24!$A$6:$G$46,3,0) -> 0 | E37: =VLOOKUP(A37,[12]HISTOBQUEAVRIL24!$A$6:$G$41,4,0) -> 0 | F37: =VLOOKUP(A37,[12]HISTOBQUEAVRIL24!$A$6:$G$41,5,0) -> 0 | G37: =IF(H37="ESPECES",3000,0) -> 0 | H37: =IF($D37<>0,"BANQUE",IF($E37<>0,"ESPECES","ECHEC")) -> ECHEC | J37: 1 | K37: =IF($D37<>0,J37*50000,IF($E37<>0,J37*50000,0)) -> 0 | M37: =IF($D37<>0,L37*75000,IF($E37<>0,L37*75000,0)) -> 0 | N37: 1 | O37: =IF($D37<>0,N37*100000,IF($E37<>0,N37*100000,0)) -> 0 | P37: =VLOOKUP(A37,[14]TONTJUIN24!$A$6:$R$39,12,0) -> 0 | R37: =VLOOKUP(A37,[16]TONTJUIN24!$A$7:$P$20,10,0) -> 0 | U37: =G37+S37++R37+P37+O37+M37+I37+K37+Q37+V37+W37 -> 0 | AQ37: =IF(H37="ECHEC",((K37+M37+O37)*20/100),0) -> 0 | AR37: =IF(H37="ECHEC",((K37+M37+O37)*20/100),0) -> 0 | AS37: =IF(H37="ECHEC",0,(K37+I37-25000)) -> 0 | AW37: =IF(AC37=0,AI37,(1*25000*12)+AI37-AC37) -> 0 | AX37: =IF(AD37=0,AJ37,(1*75000*12)+(AJ37)-AD37) -> 0 | AY37: =IF(AE37=0,AK37,(1*100000*12)+(AK37)-AE37) -> 0 | AZ37: =SUM(AV37:AY37)-BF37+Z37-F37+BH37+BI37+BJ37+BK37+BL37+BM37 -> 0 | BD37: =IF(AZ37=0,(AZ37-BA37-BC37),(AZ37-BA37-BB37-BC37)) -> 0 | BF37: =Z37*1/100*BG37 -> 0 | BG37: 6 | BN37: YOUMBI EMMANUEL | BO37: YEPMOU JEAN JACQUES
A38: AS201626 | B38: =VLOOKUP(A38,[11]LISTADHERENT!A$5:H$50,3,0) -> YOUMBI EMMANUEL | C38: =D38+E38+F38-U38-BB38 -> 0 | D38: =VLOOKUP(A38,[12]HISTOBQUEAVRIL24!$A$6:$G$46,3,0) -> 0 | E38: =VLOOKUP(A38,[12]HISTOBQUEAVRIL24!$A$6:$G$41,4,0) -> 0 | F38: =VLOOKUP(A38,[12]HISTOBQUEAVRIL24!$A$6:$G$41,5,0) -> 0 | G38: =IF(H38="ESPECES",3000,0) -> 0 | H38: =IF($D38<>0,"BANQUE",IF($E38<>0,"ESPECES","ECHEC")) -> ECHEC | J38: 1 | K38: =IF($D38<>0,J38*50000,IF($E38<>0,J38*50000,0)) -> 0 | L38: 1 | M38: =IF($D38<>0,L38*75000,IF($E38<>0,L38*75000,0)) -> 0 | O38: =IF($D38<>0,N38*100000,IF($E38<>0,N38*100000,0)) -> 0 | P38: =VLOOKUP(A38,[14]TONTJUIN24!$A$6:$R$39,12,0) -> 0 | Q38: =VLOOKUP(A38,[15]TONTJUIN24!$A$7:$P$23,10,0) -> 0 | U38: =G38+S38++R38+P38+O38+M38+I38+K38+Q38+V38+W38 -> 0 | AQ38: =IF(H38="ECHEC",((K38+M38+O38)*20/100),0) -> 0 | AR38: =IF(H38="ECHEC",((K38+M38+O38)*20/100),0) -> 0 | AS38: =IF(H38="ECHEC",0,(K38+I38-25000)) -> 0 | AW38: =IF(AC38=0,AI38,(1*25000*12)+AI38-AC38) -> 0 | AX38: =IF(AD38=0,AJ38,(1*75000*12)+(AJ38)-AD38) -> 0 | AY38: =IF(AE38=0,AK38,(1*100000*12)+(AK38)-AE38) -> 0 | AZ38: =SUM(AV38:AY38)-BF38+Z38-F38+BH38+BI38+BJ38+BK38+BL38+BM38 -> 0 | BD38: =IF(AZ38=0,(AZ38-BA38-BC38),(AZ38-BA38-BB38-BC38)) -> 0 | BF38: =Z38*1/100*BG38 -> 0 | BG38: 6 | BN38: YOUMBI EMMANUEL | BO38: YEPMOU JEAN JACQUES
B40: AS201629 | C40: =SUM(C6:C39) -> 0 | D40: =SUM(D6:D39) -> 0 | E40: =SUM(E6:E39) -> 0 | F40: =SUM(F6:F39) -> 0 | G40: =SUM(G6:G39) -> 0 | H40: =SUM(H6:H39) -> 0 | I40: =SUM(I6:I39) -> 0 | J40: =SUM(J6:J39) -> 32 | ... S40: =SUM(S6:S39) -> 0 | U40: =SUM(U6:U39) -> 0 | V40: =SUM(V6:V39) -> 0 | W40: =SUM(W6:W39) -> 0 | X40: =SUM(X6:X39) -> 0 | Y40: =SUM(Y6:Y39) -> 0 | Z40: =SUM(Z6:Z39) -> 0 | AA40: =SUM(AA6:AA39) -> 0 | AC40: =SUM(AC6:AC39) -> 0 | AD40: =SUM(AD6:AD39) -> 0 | AE40: =SUM(AE6:AE39) -> 0 | AF40: =SUM(AF6:AF39) -> 0 | AG40: =SUM(AG6:AG39) -> 0 | AI40: =SUM(AI6:AI39) -> 0 | AJ40: =SUM(AJ6:AJ39) -> 0 | AK40: =SUM(AK6:AK39) -> 0 | AL40: =SUM(AL6:AL39) -> 0 | AM40: =SUM(AM6:AM39) -> 0 | AN40: =SUM(AN6:AN39) -> 0 | AO40: =SUM(AO6:AO39) -> 0 | AP40: =SUM(AP6:AP39) -> 0 | ... BF40: =SUM(BF6:BF39) -> 0 | BH40: =SUM(BH6:BH39) -> 0 | BI40: =SUM(BI6:BI39) -> 0 | BJ40: =SUM(BJ6:BJ39) -> 0 | BK40: =SUM(BK6:BK39) -> 0 | BL40: =SUM(BL6:BL39) -> 0 | BM40: =SUM(BM6:BM39) -> 0 | BN40: INTERET | BP40: =SUM(BP36:BP38) -> 0
B43: AOUT 2018 A NOVEMBRE 2019 | BN43: A APURER | BO43: AS201639
C44: SANCTION | F44: EPARGNE
B45: 2017/2018 | C45: MBOGNING TUGMA GUY | D45: AS201649 | E45: AS201650 | F45: AS201649 | G45: MBOGNING TUGMA GUY | H45: AS201650 | BN45: INTERET | BP45: =SUM(BP42:BP44) -> 0
B46: DJOMO DOMO
B47: AS201651 | C47: =AZ40 -> 0 | D47: =SUMIFS(D8:D40,H8:H40,"BANQUE") -> 0 | F47: =E40 -> 0
AZ85: =SUM(AZ8:AZ84) -> 0

Sheet Sheet11
A1: ANNEE | B1: TONTINE
A2: MATRICULE | B2: 2024
A3: 1 | B3: 2 | C3: 3 | D3: 4 | E3: 5 | F3: 6 | G3: 7 | H3: 8 | I3: 9 | J3: 10 | K3: 11 | L3: 12 | M3: 13 | N3: 14 | O3: 15 | P3: 16 | Q3: 17 | R3: 18 | S3: 19 | T3: 20 | U3: 21 | V3: 22 | W3: 23 | X3: 24 | Y3: 25 | Z3: 26 | AA3: 27 | AB3: 28 | AC3: 29 | AD3: 30 | AE3: 31 | AF3: 32 | AG3: 33 | AH3: 34 | AI3: 35 | AJ3: 36 | AK3: 37 | AL3: 38 | AM3: 39 | AN3: 40 | AO3: 41 | AP3: 42 | AQ3: 43 | AR3: 44 | AS3: 45 | AT3: 46 | AU3: 47 | AV3: 48 | AW3: 49 | AX3: 50 | AY3: 51 | AZ3: 52 | BA3: 53 | BB3: 54 | BC3: 55 | BD3: 56 | BE3: 57 | BF3: 58 | BG3: 59 | BH3: 60 | BI3: 61 | BJ3: 62 | BK3: 63 | BL3: 64 | BM3: 65 | BN3: 66 | BO3: 67 | BP3: 68
B4: AS201628
A5: ASSOCIATION | B5: ASELBY | C5: AS201636 | D5: PENALITE VST ESPECES | E5: INSCRIPTION | F5: INSCRISPTION | G5: AS201633 | H5: AS201637 | I5: FONDS DE CAISSE | J5: AS201634 | K5: RECAPITULATIF 2020 | L5: AS201634 | M5: NOM ET PRENOM | N5: AS201634 | O5: REPARTITION INTERET | P5: MARS | Q5: FONDS DE ROULEMENT | R5: FRAIS EXCEPTIONNEL | S5: PRET FONDS | T5: PENALITE VERST ESPECES | U5: FRAIS EXCEPTIONNELS | V5: CAPITAL COMPOSE | W5: AS201641 | X5: TONTINE | Y5: RESTE | Z5: AS201642 | AA5: PRÊT FONDS | AB5: TOTAL | AC5: JUIN | AD5: AS201627 | AE5: INTERET PRÊT FONDS | AF5: AS201638 | AG5: TOTAL | AH5: AS201633 | AI5: AVRIL | AJ5: AS201643 | AK5: AS201644 | AL5: MAI | AM5: AS201646 | AN5: AS201647 | AO5: TOTAL | AP5: OCTOBRE | AQ5: REMBOURSEMENTPRET FONDS | AR5: PENALITE PRET FONDS | AS5: RELIQUAT | AT5: AS201639 | AU5: DOMOU FABIEN | AV5: MONTANT EPARGNE+INTERET | AW5: JUILLET | AX5: NUMERO CHEQUE | AY5: AS201653 | AZ5: 2018/2019 | BA5: NKEPSEU DIEUDONNE | BB5: KOUAMOU MOISE | BC5: COMPLEMENT FONDS | BD5: MONTANT A VERSER | BE5: KOUAMO VICTOR PEGUY | BF5: T100 | BG5: TABLEAU RECAPITULATIF DISTRIBUTION EPARGNE 2019 | BH5: 2019/2020 | BI5: INTERET ANTERIEUR | BJ5: NET_ A_ PAYER | BK5: PRÊT_FONDS_ENCOURS | BL5: DISTRIBUTION INTERET 2018 ET 2019 | BM5: DJOMO JEAN PAUL AVANCE 80 000 DJOMO JEAN PAUL | BN5: 2017/2018 | BO5: PRÊT_FONDS | BP5: AS201654
A6: KOUAMOU EMMANUEL | B6: =VLOOKUP(A6,[11]LISTADHERENT!A$5:H$50,3,0) -> ASELBY | C6: =D6+E6+F6-U6-BB6 -> 0 | D6: =VLOOKUP(A6,[12]HISTOBQUEAVRIL24!$A$6:$G$46,3,0) -> 0 | E6: =VLOOKUP(A6,[12]HISTOBQUEAVRIL24!$A$6:$G$41,4,0) -> 0 | F6: =VLOOKUP(A6,[12]HISTOBQUEAVRIL24!$A$6:$G$41,5,0) -> 0 | G6: =IF(H6="ESPECES",3000,0) -> 0 | H6: =IF($D6<>0,"BANQUE",IF($E6<>0,"ESPECES","ECHEC")) -> ECHEC | K6: =IF($D6<>0,J6*50000,IF($E6<>0,J6*50000,0)) -> 0 | L6: 1 | M6: =IF($D6<>0,L6*75000,IF($E6<>0,L6*75000,0)) -> 0 | N6: 1 | O6: =IF($D6<>0,N6*100000,IF($E6<>0,N6*100000,0)) -> 0 | U6: =G6+S6++R6+P6+O6+M6+I6+K6+Q6+V6+W6 -> 0 | AQ6: =IF(H6="ECHEC",((K6+M6+O6)*20/100),0) -> 0 | AR6: =IF(H6="ECHEC",((K6+M6+O6)*20/100),0) -> 0 | AW6: =IF(AC6=0,AI6,(1*25000*12)+AI6-AC6) -> 0 | AX6: =IF(AD6=0,AJ6,(1*75000*12)+(AJ6)-AD6) -> 0 | AY6: =IF(AE6=0,AK6,(1*100000*12)+(AK6)-AE6) -> 0 | AZ6: =SUM(AV6:AY6)-BF6+Z6-F6+BH6+BI6+BJ6+BK6+BL6+BM6 -> 0 | BD6: =IF(AZ6=0,(AZ6-BA6-BC6),(AZ6-BA6-BB6-BC6)) -> 0 | BF6: =Z6*1/100*BG6 -> 0 | BG6: 5 | BH6: =BP16 -> 0 | BI6: =BP28 -> 0 | BJ6: =BP33 -> 0 | BK6: =+BP40 -> 0 | BM6: =BP22 -> 0 | BN6: NKEHE DAVID | BO6: NGONGANG JEAN THEODORE
A7: DATE | B7: =VLOOKUP(A7,[11]LISTADHERENT!A$5:H$50,3,0) -> BAKOP ACHILLE | C7: =D7+E7+F7-U7-BB7 -> 0 | D7: =VLOOKUP(A7,[12]HISTOBQUEAVRIL24!$A$6:$G$46,3,0) -> 0 | E7: =VLOOKUP(A7,[12]HISTOBQUEAVRIL24!$A$6:$G$41,4,0) -> 0 | F7: =VLOOKUP(A7,[12]HISTOBQUEAVRIL24!$A$6:$G$41,5,0) -> 0 | G7: =IF(H7="ESPECES",3000,0) -> 0 | H7: =IF($D7<>0,"BANQUE",IF($E7<>0,"ESPECES","ECHEC")) -> ECHEC | J7: 1 | K7: =IF($D7<>0,J7*50000,IF($E7<>0,J7*50000,0)) -> 0 | M7: =IF($D7<>0,L7*75000,IF($E7<>0,L7*75000,0)) -> 0 | O7: =IF($D7<>0,N7*100000,IF($E7<>0,N7*100000,0)) -> 0 | P7: =VLOOKUP(A7,[14]TONTJUIL24!$A$6:$R$39,12,0) -> 0 | U7: =G7+S7++R7+P7+O7+M7+I7+K7+Q7+V7+W7 -> 0 | AQ7: =IF(H7="ECHEC",((K7+M7+O7)*20/100),0) -> 0 | AR7: =IF(H7="ECHEC",((K7+M7+O7)*20/100),0) -> 0 | AS7: =IF(H7="ECHEC",0,(K7+I7-25000)) -> 0 | AW7: =IF(AC7=0,AI7,(1*25000*12)+AI7-AC7) -> 0 | AX7: =IF(AD7=0,AJ7,(1*75000*12)+(AJ7)-AD7) -> 0 | AY7: =IF(AE7=0,AK7,(1*100000*12)+(AK7)-AE7) -> 0 | AZ7: =SUM(AV7:AY7)-BF7+Z7-F7+BH7+BI7+BJ7+BK7+BL7+BM7 -> 0 | BD7: =IF(AZ7=0,(AZ7-BA7-BC7),(AZ7-BA7-BB7-BC7)) -> 0 | BF7: =Z7*1/100*BG7 -> 0 | BG7: 5 | BN7: PATEGO NJOSSU GUSTAVE | BO7: NGONGANG JEAN THEODORE
A8: COLLATION | B8: =VLOOKUP(A8,[11]LISTADHERENT!A$5:H$50,3,0) -> BOUTCHOUANG WILLIAM | C8: =D8+E8+F8-U8-BB8 -> 0 | D8: =VLOOKUP(A8,[12]HISTOBQUEAVRIL24!$A$6:$G$46,3,0) -> 0 | E8: =VLOOKUP(A8,[12]HISTOBQUEAVRIL24!$A$6:$G$41,4,0) -> 0 | F8: =VLOOKUP(A8,[12]HISTOBQUEAVRIL24!$A$6:$G$41,5,0) -> 0 | G8: =IF(H8="ESPECES",3000,0) -> 0 | H8: =IF($D8<>0,"BANQUE",IF($E8<>0,"ESPECES","ECHEC")) -> ECHEC | J8: 1 | K8: =IF($D8<>0,J8*50000,IF($E8<>0,J8*50000,0)) -> 0 | L8: 1 | M8: =IF($D8<>0,L8*75000,IF($E8<>0,L8*75000,0)) -> 0 | O8: =IF($D8<>0,N8*100000,IF($E8<>0,N8*100000,0)) -> 0 | P8: =VLOOKUP(A8,[14]TONTJUIL24!$A$6:$R$39,12,0) -> 0 | Q8: =VLOOKUP(A8,[15]TONTJUIL24!$A$7:$P$23,10,0) -> 0 | U8: =G8+S8++R8+P8+O8+M8+I8+K8+Q8+V8+W8 -> 0 | AQ8: =IF(H8="ECHEC",((K8+M8+O8)*20/100),0) -> 0 | AR8: =IF(H8="ECHEC",((K8+M8+O8)*20/100),0) -> 0 | AS8: =IF(H8="ECHEC",0,(K8+I8-25000)) -> 0 | AW8: =IF(AC8=0,AI8,(1*25000*12)+AI8-AC8) -> 0 | AX8: =IF(AD8=0,AJ8,(1*75000*12)+(AJ8)-AD8) -> 0 | AY8: =IF(AE8=0,AK8,(1*100000*12)+(AK8)-AE8) -> 0 | AZ8: =SUM(AV8:AY8)-BF8+Z8-F8+BH8+BI8+BJ8+BK8+BL8+BM8 -> 0 | BD8: =IF(AZ8=0,(AZ8-BA8-BC8),(AZ8-BA8-BB8-BC8)) -> 0 | BF8: =Z8*1/100*BG8 -> 0 | BG8: 5 | BN8: SEUNOU RICHELOT | BO8: NGONGANG JEAN THEODORE
A9: MUTUELLE | B9: =VLOOKUP(A9,[11]LISTADHERENT!A$5:H$50,3,0) -> DJOMO JEAN PAUL | C9: =D9+E9+F9-U9-BB9 -> 0 | D9: =VLOOKUP(A9,[12]HISTOBQUEAVRIL24!$A$6:$G$46,3,0) -> 0 | E9: =VLOOKUP(A9,[12]HISTOBQUEAVRIL24!$A$6:$G$41,4,0) -> 0 | F9: =VLOOKUP(A9,[12]HISTOBQUEAVRIL24!$A$6:$G$41,5,0) -> 0 | G9: =IF(H9="ESPECES",3000,0) -> 0 | H9: =IF($D9<>0,"BANQUE",IF($E9<>0,"ESPECES","ECHEC")) -> ECHEC | J9: 1 | K9: =IF($D9<>0,J9*50000,IF($E9<>0,J9*50000,0)) -> 0 | M9: =IF($D9<>0,L9*75000,IF($E9<>0,L9*75000,0)) -> 0 | N9: 2 | O9: =IF($D9<>0,N9*100000,IF($E9<>0,N9*100000,0)) -> 0 | P9: =VLOOKUP(A9,[14]TONTJUIL24!$A$6:$R$39,12,0) -> 0 | R9: =VLOOKUP(A9,[16]TONTJUIL24!$A$7:$P$20,10,0) -> 0 | U9: =G9+S9++R9+P9+O9+M9+I9+K9+Q9+V9+W9 -> 0 | AQ9: =IF(H9="ECHEC",((K9+M9+O9)*20/100),0) -> 0 | AR9: =IF(H9="ECHEC",((K9+M9+O9)*20/100),0) -> 0 | AS9: =IF(H9="ECHEC",0,(K9+I9-25000)) -> 0 | AW9: =IF(AC9=0,AI9,(1*25000*12)+AI9-AC9) -> 0 | AX9: =IF(AD9=0,AJ9,(1*75000*12)+(AJ9)-AD9) -> 0 | AY9: =IF(AE9=0,AK9,(1*100000*12)+(AK9)-AE9) -> 0 | AZ9: =SUM(AV9:AY9)-BF9+Z9-F9+BH9+BI9+BJ9+BK9+BL9+BM9 -> 0 | BD9: =IF(AZ9=0,(AZ9-BA9-BC9),(AZ9-BA9-BB9-BC9)) -> 0 | BF9: =Z9*1/100*BG9 -> 0 | BG9: 5 | BN9: JANVIER | BO9: NGONGANG JEAN THEODORE
A10: PENALITE FONDS | B10: =VLOOKUP(A10,[11]LISTADHERENT!A$5:H$50,3,0) -> DJOMOU TCHAPDA | C10: =D10+E10+F10-U10-BB10 -> 0 | D10: =VLOOKUP(A10,[12]HISTOBQUEAVRIL24!$A$6:$G$46,3,0) -> 0 | E10: =VLOOKUP(A10,[12]HISTOBQUEAVRIL24!$A$6:$G$41,4,0) -> 0 | F10: =VLOOKUP(A10,[12]HISTOBQUEAVRIL24!$A$6:$G$41,5,0) -> 0 | G10: =IF(H10="ESPECES",3000,0) -> 0 | H10: =IF($D10<>0,"BANQUE",IF($E10<>0,"ESPECES","ECHEC")) -> ECHEC | J10: 1 | K10: =IF($D10<>0,J10*50000,IF($E10<>0,J10*50000,0)) -> 0 | L10: 1 | M10: =IF($D10<>0,L10*75000,IF($E10<>0,L10*75000,0)) -> 0 | O10: =IF($D10<>0,N10*100000,IF($E10<>0,N10*100000,0)) -> 0 | P10: =VLOOKUP(A10,[14]TONTJUIL24!$A$6:$R$39,12,0) -> 0 | Q10: =VLOOKUP(A10,[15]TONTJUIL24!$A$7:$P$23,10,0) -> 0 | U10: =G10+S10++R10+P10+O10+M10+I10+K10+Q10+V10+W10 -> 0 | AQ10: =IF(H10="ECHEC",((K10+M10+O10)*20/100),0) -> 0 | AR10: =IF(H10="ECHEC",((K10+M10+O10)*20/100),0) -> 0 | AS10: =IF(H10="ECHEC",0,(K10+I10-25000)) -> 0 | AW10: =IF(AC10=0,AI10,(1*25000*12)+AI10-AC10) -> 0 | AX10: =IF(AD10=0,AJ10,(1*75000*12)+(AJ10)-AD10) -> 0 | AY10: =IF(AE10=0,AK10,(1*100000*12)+(AK10)-AE10) -> 0 | AZ10: =SUM(AV10:AY10)-BF10+Z10-F10+BH10+BI10+BJ10+BK10+BL10+BM10 -> 0 | BD10: =IF(AZ10=0,(AZ10-BA10-BC10),(AZ10-BA10-BB10-BC10)) -> 0 | BF10: =Z10*1/100*BG10 -> 0 | BG10: 5 | BN10: SIME BRICE | BO10: NGONGANG JEAN THEODORE
A11: AVALISTE | B11: =VLOOKUP(A11,[11]LISTADHERENT!A$5:H$50,3,0) -> DJOUKWE NANGUEN GUY BLAISE | C11: =D11+E11+F11-U11-BB11 -> 0 | D11: =VLOOKUP(A11,[12]HISTOBQUEAVRIL24!$A$6:$G$46,3,0) -> 0 | E11: =VLOOKUP(A11,[12]HISTOBQUEAVRIL24!$A$6:$G$41,4,0) -> 0 | F11: =VLOOKUP(A11,[12]HISTOBQUEAVRIL24!$A$6:$G$41,5,0) -> 0 | G11: =IF(H11="ESPECES",3000,0) -> 0 | H11: =IF($D11<>0,"BANQUE",IF($E11<>0,"ESPECES","ECHEC")) -> ECHEC | J11: 1 | K11: =IF($D11<>0,J11*50000,IF($E11<>0,J11*50000,0)) -> 0 | L11: 1 | M11: =IF($D11<>0,L11*75000,IF($E11<>0,L11*75000,0)) -> 0 | O11: =IF($D11<>0,N11*100000,IF($E11<>0,N11*100000,0)) -> 0 | P11: =VLOOKUP(A11,[14]TONTJUIL24!$A$6:$R$39,12,0) -> 0 | Q11: =VLOOKUP(A11,[15]TONTJUIL24!$A$7:$P$23,10,0) -> 0 | U11: =G11+S11++R11+P11+O11+M11+I11+K11+Q11+V11+W11 -> 0 | AQ11: =IF(H11="ECHEC",((K11+M11+O11)*20/100),0) -> 0 | AR11: =IF(H11="ECHEC",((K11+M11+O11)*20/100),0) -> 0 | AS11: =IF(H11="ECHEC",0,(K11+I11-25000)) -> 0 | AW11: =IF(AC11=0,AI11,(1*25000*12)+AI11-AC11) -> 0 | AX11: =IF(AD11=0,AJ11,(1*75000*12)+(AJ11)-AD11) -> 0 | AY11: =IF(AE11=0,AK11,(1*100000*12)+(AK11)-AE11) -> 0 | AZ11: =SUM(AV11:AY11)-BF11+Z11-F11+BH11+BI11+BJ11+BK11+BL11+BM11 -> 0 | BD11: =IF(AZ11=0,(AZ11-BA11-BC11),(AZ11-BA11-BB11-BC11)) -> 0 | BF11: =Z11*1/100*BG11 -> 0 | BG11: 5 | BN11: SIME FONGANG ERIC | BO11: NGONGANG JEAN THEODORE
A12: AS201648 | B12: =VLOOKUP(A12,[11]LISTADHERENT!A$5:H$50,3,0) -> DJUOMBESSY ANTOINE | C12: =D12+E12+F12-U12-BB12 -> 0 | D12: =VLOOKUP(A12,[12]HISTOBQUEAVRIL24!$A$6:$G$46,3,0) -> 0 | E12: =VLOOKUP(A12,[12]HISTOBQUEAVRIL24!$A$6:$G$41,4,0) -> 0 | F12: =VLOOKUP(A12,[12]HISTOBQUEAVRIL24!$A$6:$G$41,5,0) -> 0 | G12: =IF(H12="ESPECES",3000,0) -> 0 | H12: =IF($D12<>0,"BANQUE",IF($E12<>0,"ESPECES","ECHEC")) -> ECHEC | J12: 1 | K12: =IF($D12<>0,J12*50000,IF($E12<>0,J12*50000,0)) -> 0 | L12: 1 | M12: =IF($D12<>0,L12*75000,IF($E12<>0,L12*75000,0)) -> 0 | N12: 2 | O12: =IF($D12<>0,N12*100000,IF($E12<>0,N12*100000,0)) -> 0 | P12: =VLOOKUP(A12,[14]TONTJUIL24!$A$6:$R$39,12,0) -> 0 | Q12: =VLOOKUP(A12,[15]TONTJUIL24!$A$7:$P$23,10,0) -> 0 | R12: =VLOOKUP(A12,[16]TONTJUIL24!$A$7:$P$20,10,0) -> 0 | U12: =G12+S12++R12+P12+O12+M12+I12+K12+Q12+V12+W12 -> 0 | AQ12: =IF(H12="ECHEC",((K12+M12+O12)*20/100),0) -> 0 | AR12: =IF(H12="ECHEC",((K12+M12+O12)*20/100),0) -> 0 | AS12: =IF(H12="ECHEC",0,(K12+I12-25000)) -> 0 | AW12: =IF(AC12=0,AI12,(1*25000*12)+AI12-AC12) -> 0 | AX12: =IF(AD12=0,AJ12,(1*75000*12)+(AJ12)-AD12) -> 0 | AY12: =IF(AE12=0,AK12,(1*100000*12)+(AK12)-AE12) -> 0 | AZ12: =SUM(AV12:AY12)-BF12+Z12-F12+BH12+BI12+BJ12+BK12+BL12+BM12 -> 0 | BD12: =IF(AZ12=0,(AZ12-BA12-BC12),(AZ12-BA12-BB12-BC12)) -> 0 | BF12: =Z12*1/100*BG12 -> 0 | BG12: 5 | BN12: SIME MATHIEU | BO12: NGONGANG JEAN THEODORE
A13: AS201601 | B13: =VLOOKUP(A13,[11]LISTADHERENT!A$5:H$50,3,0) -> DOMOU FABIEN | C13: =D13+E13+F13-U13-BB13 -> 0 | D13: =VLOOKUP(A13,[12]HISTOBQUEAVRIL24!$A$6:$G$46,3,0) -> 0 | E13: =VLOOKUP(A13,[12]HISTOBQUEAVRIL24!$A$6:$G$41,4,0) -> 0 | F13: =VLOOKUP(A13,[12]HISTOBQUEAVRIL24!$A$6:$G$41,5,0) -> 0 | G13: =IF(H13="ESPECES",3000,0) -> 0 | H13: =IF($D13<>0,"BANQUE",IF($E13<>0,"ESPECES","ECHEC")) -> ECHEC | J13: 1 | K13: =IF($D13<>0,J13*50000,IF($E13<>0,J13*50000,0)) -> 0 | M13: =IF($D13<>0,L13*75000,IF($E13<>0,L13*75000,0)) -> 0 | O13: =IF($D13<>0,N13*100000,IF($E13<>0,N13*100000,0)) -> 0 | P13: =VLOOKUP(A13,[14]TONTJUIL24!$A$6:$R$39,12,0) -> 0 | U13: =G13+S13++R13+P13+O13+M13+I13+K13+Q13+V13+W13 -> 0 | AQ13: =IF(H13="ECHEC",((K13+M13+O13)*20/100),0) -> 0 | AR13: =IF(H13="ECHEC",((K13+M13+O13)*20/100),0) -> 0 | AS13: =IF(H13="ECHEC",0,(K13+I13-25000)) -> 0 | AW13: =IF(AC13=0,AI13,(1*25000*12)+AI13-AC13) -> 0 | AX13: =IF(AD13=0,AJ13,(1*75000*12)+(AJ13)-AD13) -> 0 | AY13: =IF(AE13=0,AK13,(1*100000*12)+(AK13)-AE13) -> 0 | AZ13: =SUM(AV13:AY13)-BF13+Z13-F13+BH13+BI13+BJ13+BK13+BL13+BM13 -> 0 | BD13: =IF(AZ13=0,(AZ13-BA13-BC13),(AZ13-BA13-BB13-BC13)) -> 0 | BF13: =Z13*1/100*BG13 -> 0 | BG13: 5 | BN13: FONDSCAISSE | BO13: NGONGANG JEAN THEODORE
A14: ECHEC | B14: =VLOOKUP(A14,[11]LISTADHERENT!A$5:H$50,3,0) -> DONHOU DAVID | C14: =D14+E14+F14-U14-BB14 -> 0 | D14: =VLOOKUP(A14,[12]HISTOBQUEAVRIL24!$A$6:$G$46,3,0) -> 0 | E14: =VLOOKUP(A14,[12]HISTOBQUEAVRIL24!$A$6:$G$41,4,0) -> 0 | F14: =VLOOKUP(A14,[12]HISTOBQUEAVRIL24!$A$6:$G$41,5,0) -> 0 | G14: =IF(H14="ESPECES",3000,0) -> 0 | H14: =IF($D14<>0,"BANQUE",IF($E14<>0,"ESPECES","ECHEC")) -> ECHEC | J14: 1 | K14: =IF($D14<>0,J14*50000,IF($E14<>0,J14*50000,0)) -> 0 | M14: =IF($D14<>0,L14*75000,IF($E14<>0,L14*75000,0)) -> 0 | O14: =IF($D14<>0,N14*100000,IF($E14<>0,N14*100000,0)) -> 0 | P14: =VLOOKUP(A14,[14]TONTJUIL24!$A$6:$R$39,12,0) -> 0 | U14: =G14+S14++R14+P14+O14+M14+I14+K14+Q14+V14+W14 -> 0 | AQ14: =IF(H14="ECHEC",((K14+M14+O14)*20/100),0) -> 0 | AR14: =IF(H14="ECHEC",((K14+M14+O14)*20/100),0) -> 0 | AS14: =IF(H14="ECHEC",0,(K14+I14-25000)) -> 0 | AW14: =IF(AC14=0,AI14,(1*25000*12)+AI14-AC14) -> 0 | AX14: =IF(AD14=0,AJ14,(1*75000*12)+(AJ14)-AD14) -> 0 | AY14: =IF(AE14=0,AK14,(1*100000*12)+(AK14)-AE14) -> 0 | AZ14: =SUM(AV14:AY14)-BF14+Z14-F14+BH14+BI14+BJ14+BK14+BL14+BM14 -> 0 | BD14: =IF(AZ14=0,(AZ14-BA14-BC14),(AZ14-BA14-BB14-BC14)) -> 0 | BF14: =Z14*1/100*BG14 -> 0 | BG14: 5 | BN14: TCHOUAMOU MATHIEU | BO14: NGONGANG JEAN THEODORE
A15: ESPECES | B15: =VLOOKUP(A15,[11]LISTADHERENT!A$5:H$50,3,0) -> HENGUE PAUL OMER | C15: =D15+E15+F15-U15-BB15 -> 0 | D15: =VLOOKUP(A15,[12]HISTOBQUEAVRIL24!$A$6:$G$46,3,0) -> 0 | E15: =VLOOKUP(A15,[12]HISTOBQUEAVRIL24!$A$6:$G$41,4,0) -> 0 | F15: =VLOOKUP(A15,[12]HISTOBQUEAVRIL24!$A$6:$G$41,5,0) -> 0 | G15: =IF(H15="ESPECES",3000,0) -> 0 | H15: =IF($D15<>0,"BANQUE",IF($E15<>0,"ESPECES","ECHEC")) -> ECHEC | J15: 1 | K15: =IF($D15<>0,J15*50000,IF($E15<>0,J15*50000,0)) -> 0 | L15: 1 | M15: =IF($D15<>0,L15*75000,IF($E15<>0,L15*75000,0)) -> 0 | O15: =IF($D15<>0,N15*100000,IF($E15<>0,N15*100000,0)) -> 0 | P15: =VLOOKUP(A15,[14]TONTJUIL24!$A$6:$R$39,12,0) -> 0 | Q15: =VLOOKUP(A15,[15]TONTJUIL24!$A$7:$P$23,10,0) -> 0 | U15: =G15+S15++R15+P15+O15+M15+I15+K15+Q15+V15+W15 -> 0 | AQ15: =IF(H15="ECHEC",((K15+M15+O15)*20/100),0) -> 0 | AR15: =IF(H15="ECHEC",((K15+M15+O15)*20/100),0) -> 0 | AS15: =IF(H15="ECHEC",0,(K15+I15-25000)) -> 0 | AW15: =IF(AC15=0,AI15,(1*25000*12)+AI15-AC15) -> 0 | AX15: =IF(AD15=0,AJ15,(1*75000*12)+(AJ15)-AD15) -> 0 | AY15: =IF(AE15=0,AK15,(1*100000*12)+(AK15)-AE15) -> 0 | AZ15: =SUM(AV15:AY15)-BF15+Z15-F15+BH15+BI15+BJ15+BK15+BL15+BM15 -> 0 | BD15: =IF(AZ15=0,(AZ15-BA15-BC15),(AZ15-BA15-BB15-BC15)) -> 0 | BF15: =Z15*1/100*BG15 -> 0 | BG15: 5
A16: AS201603 | B16: =VLOOKUP(A16,[11]LISTADHERENT!A$5:H$50,3,0) -> HOTCHO BENJAMIN | C16: =D16+E16+F16-U16-BB16 -> 0 | D16: =VLOOKUP(A16,[12]HISTOBQUEAVRIL24!$A$6:$G$46,3,0) -> 0 | E16: =VLOOKUP(A16,[12]HISTOBQUEAVRIL24!$A$6:$G$41,4,0) -> 0 | F16: =VLOOKUP(A16,[12]HISTOBQUEAVRIL24!$A$6:$G$41,5,0) -> 0 | G16: =IF(H16="ESPECES",3000,0) -> 0 | H16: =IF($D16<>0,"BANQUE",IF($E16<>0,"ESPECES","ECHEC")) -> ECHEC | J16: 1 | K16: =IF($D16<>0,J16*50000,IF($E16<>0,J16*50000,0)) -> 0 | L16: 1 | M16: =IF($D16<>0,L16*75000,IF($E16<>0,L16*75000,0)) -> 0 | N16: 1 | O16: =IF($D16<>0,N16*100000,IF($E16<>0,N16*100000,0)) -> 0 | P16: =VLOOKUP(A16,[14]TONTJUIL24!$A$6:$R$39,12,0) -> 0 | Q16: =VLOOKUP(A16,[15]TONTJUIL24!$A$7:$P$23,10,0) -> 0 | R16: =VLOOKUP(A16,[16]TONTFEV24!$A$7:$P$20,10,0) -> 0 | U16: =G16+S16++R16+P16+O16+M16+I16+K16+Q16+V16+W16 -> 0 | AQ16: =IF(H16="ECHEC",((K16+M16+O16)*20/100),0) -> 0 | AR16: =IF(H16="ECHEC",((K16+M16+O16)*20/100),0) -> 0 | AS16: =IF(H16="ECHEC",0,(K16+I16-25000)) -> 0 | AW16: =IF(AC16=0,AI16,(1*25000*12)+AI16-AC16) -> 0 | AX16: =IF(AD16=0,AJ16,(1*75000*12)+(AJ16)-AD16) -> 0 | AY16: =IF(AE16=0,AK16,(1*100000*12)+(AK16)-AE16) -> 0 | AZ16: =SUM(AV16:AY16)-BF16+Z16-F16+BH16+BI16+BJ16+BK16+BL16+BM16 -> 0 | BD16: =IF(AZ16=0,(AZ16-BA16-BC16),(AZ16-BA16-BB16-BC16)) -> 0 | BF16: =Z16*1/100*BG16 -> 0 | BG16: 5 | BN16: INTERET | BP16: =SUM(BP6:BP15) -> 0
A17: BANQUE | B17: =VLOOKUP(A17,[11]LISTADHERENT!A$5:H$50,3,0) -> KOUAMOU MOISE | C17: =D17+E17+F17-U17-BB17 -> 0 | D17: =VLOOKUP(A17,[12]HISTOBQUEAVRIL24!$A$6:$G$46,3,0) -> 0 | E17: =VLOOKUP(A17,[12]HISTOBQUEAVRIL24!$A$6:$G$41,4,0) -> 0 | F17: =VLOOKUP(A17,[12]HISTOBQUEAVRIL24!$A$6:$G$41,5,0) -> 0 | G17: =IF(H17="ESPECES",3000,0) -> 0 | H17: =IF($D17<>0,"BANQUE",IF($E17<>0,"ESPECES","ECHEC")) -> ECHEC | J17: 1 | K17: =IF($D17<>0,J17*50000,IF($E17<>0,J17*50000,0)) -> 0 | M17: =IF($D17<>0,L17*75000,IF($E17<>0,L17*75000,0)) -> 0 | N17: 1 | O17: =IF($D17<>0,N17*100000,IF($E17<>0,N17*100000,0)) -> 0 | P17: =VLOOKUP(A17,[14]TONTJUIL24!$A$6:$R$39,12,0) -> 0 | R17: =VLOOKUP(A17,[16]TONTJUIL24!$A$7:$P$20,10,0) -> 0 | U17: =G17+S17++R17+P17+O17+M17+I17+K17+Q17+V17+W17 -> 0 | AQ17: =IF(H17="ECHEC",((K17+M17+O17)*20/100),0) -> 0 | AR17: =IF(H17="ECHEC",((K17+M17+O17)*20/100),0) -> 0 | AS17: =IF(H17="ECHEC",0,(K17+I17-25000)) -> 0 | AW17: =IF(AC17=0,AI17,(1*25000*12)+AI17-AC17) -> 0 | AX17: =IF(AD17=0,AJ17,(1*75000*12)+(AJ17)-AD17) -> 0 | AY17: =IF(AE17=0,AK17,(1*100000*12)+(AK17)-AE17) -> 0 | AZ17: =SUM(AV17:AY17)-BF17+Z17-F17+BH17+BI17+BJ17+BK17+BL17+BM17 -> 0 | BD17: =IF(AZ17=0,(AZ17-BA17-BC17),(AZ17-BA17-BB17-BC17)) -> 0 | BF17: =Z17*1/100*BG17 -> 0 | BG17: 5
A18: AS201604 | B18: =VLOOKUP(A18,[11]LISTADHERENT!A$5:H$50,3,0) -> KOUATCHO MESSACK | C18: =D18+E18+F18-U18-BB18 -> 0 | D18: =VLOOKUP(A18,[12]HISTOBQUEAVRIL24!$A$6:$G$46,3,0) -> 0 | E18: =VLOOKUP(A18,[12]HISTOBQUEAVRIL24!$A$6:$G$41,4,0) -> 0 | F18: =VLOOKUP(A18,[12]HISTOBQUEAVRIL24!$A$6:$G$41,5,0) -> 0 | G18: =IF(H18="ESPECES",3000,0) -> 0 | H18: =IF($D18<>0,"BANQUE",IF($E18<>0,"ESPECES","ECHEC")) -> ECHEC | J18: 1 | K18: =IF($D18<>0,J18*50000,IF($E18<>0,J18*50000,0)) -> 0 | M18: =IF($D18<>0,L18*75000,IF($E18<>0,L18*75000,0)) -> 0 | N18: 1 | O18: =IF($D18<>0,N18*100000,IF($E18<>0,N18*100000,0)) -> 0 | P18: =VLOOKUP(A18,[14]TONTJUIL24!$A$6:$R$39,12,0) -> 0 | R18: =VLOOKUP(A18,[16]TONTJUIL24!$A$7:$P$20,10,0) -> 0 | U18: =G18+S18++R18+P18+O18+M18+I18+K18+Q18+V18+W18 -> 0 | AQ18: =IF(H18="ECHEC",((K18+M18+O18)*20/100),0) -> 0 | AR18: =IF(H18="ECHEC",((K18+M18+O18)*20/100),0) -> 0 | AS18: =IF(H18="ECHEC",0,(K18+I18-25000)) -> 0 | AW18: =IF(AC18=0,AI18,(1*25000*12)+AI18-AC18) -> 0 | AX18: =IF(AD18=0,AJ18,(1*75000*12)+(AJ18)-AD18) -> 0 | AY18: =IF(AE18=0,AK18,(1*100000*12)+(AK18)-AE18) -> 0 | AZ18: =SUM(AV18:AY18)-BF18+Z18-F18+BH18+BI18+BJ18+BK18+BL18+BM18 -> 0 | BD18: =IF(AZ18=0,(AZ18-BA18-BC18),(AZ18-BA18-BB18-BC18)) -> 0 | BF18: =Z18*1/100*BG18 -> 0 | BG18: 5 | BN18: MONTANT_MUTUELLE | BO18: AS201633
A19: MOIS | B19: =VLOOKUP(A19,[11]LISTADHERENT!A$5:H$50,3,0) -> MASSEUNGOUE DAGOBERT | C19: =D19+E19+F19-U19-BB19 -> 0 | D19: =VLOOKUP(A19,[12]HISTOBQUEAVRIL24!$A$6:$G$46,3,0) -> 0 | E19: =VLOOKUP(A19,[12]HISTOBQUEAVRIL24!$A$6:$G$41,4,0) -> 0 | F19: =VLOOKUP(A19,[12]HISTOBQUEAVRIL24!$A$6:$G$41,5,0) -> 0 | G19: =IF(H19="ESPECES",3000,0) -> 0 | H19: =IF($D19<>0,"BANQUE",IF($E19<>0,"ESPECES","ECHEC")) -> ECHEC | J19: 1 | K19: =IF($D19<>0,J19*50000,IF($E19<>0,J19*50000,0)) -> 0 | M19: =IF($D19<>0,L19*75000,IF($E19<>0,L19*75000,0)) -> 0 | O19: =IF($D19<>0,N19*100000,IF($E19<>0,N19*100000,0)) -> 0 | P19: =VLOOKUP(A19,[14]TONTJUIL24!$A$6:$R$39,12,0) -> 0 | U19: =G19+S19++R19+P19+O19+M19+I19+K19+Q19+V19+W19 -> 0 | AQ19: =IF(H19="ECHEC",((K19+M19+O19)*20/100),0) -> 0 | AR19: =IF(H19="ECHEC",((K19+M19+O19)*20/100),0) -> 0 | AS19: =IF(H19="ECHEC",0,(K19+I19-25000)) -> 0 | AW19: =IF(AC19=0,AI19,(1*25000*12)+AI19-AC19) -> 0 | AX19: =IF(AD19=0,AJ19,(1*75000*12)+(AJ19)-AD19) -> 0 | AY19: =IF(AE19=0,AK19,(1*100000*12)+(AK19)-AE19) -> 0 | AZ19: =SUM(AV19:AY19)-BF19+Z19-F19+BH19+BI19+BJ19+BK19+BL19+BM19 -> 0 | BD19: =IF(AZ19=0,(AZ19-BA19-BC19),(AZ19-BA19-BB19-BC19)) -> 0 | BF19: =Z19*1/100*BG19 -> 0 | BG19: 5
A20: AS201608 | B20: =VLOOKUP(A20,[11]LISTADHERENT!A$5:H$50,3,0) -> MBOGNING TUGMA GUY | C20: =D20+E20+F20-U20-BB20 -> 0 | D20: =VLOOKUP(A20,[12]HISTOBQUEAVRIL24!$A$6:$G$46,3,0) -> 0 | E20: =VLOOKUP(A20,[12]HISTOBQUEAVRIL24!$A$6:$G$41,4,0) -> 0 | F20: =VLOOKUP(A20,[12]HISTOBQUEAVRIL24!$A$6:$G$41,5,0) -> 0 | G20: =IF(H20="ESPECES",3000,0) -> 0 | H20: =IF($D20<>0,"BANQUE",IF($E20<>0,"ESPECES","ECHEC")) -> ECHEC | J20: 1 | K20: =IF($D20<>0,J20*50000,IF($E20<>0,J20*50000,0)) -> 0 | L20: 1 | M20: =IF($D20<>0,L20*75000,IF($E20<>0,L20*75000,0)) -> 0 | N20: 1 | O20: =IF($D20<>0,N20*100000,IF($E20<>0,N20*100000,0)) -> 0 | P20: =VLOOKUP(A20,[14]TONTJUIL24!$A$6:$R$39,12,0) -> 0 | Q20: =VLOOKUP(A20,[15]TONTJUIL24!$A$7:$P$23,10,0) -> 0 | R20: =VLOOKUP(A20,[16]TONTJUIL24!$A$7:$P$20,10,0) -> 0 | U20: =G20+S20++R20+P20+O20+M20+I20+K20+Q20+V20+W20 -> 0 | AQ20: =IF(H20="ECHEC",((K20+M20+O20)*20/100),0) -> 0 | AR20: =IF(H20="ECHEC",((K20+M20+O20)*20/100),0) -> 0 | AS20: =IF(H20="ECHEC",0,(K20+I20-25000)) -> 0 | AW20: =IF(AC20=0,AI20,(1*25000*12)+AI20-AC20) -> 0 | AX20: =IF(AD20=0,AJ20,(1*75000*12)+(AJ20)-AD20) -> 0 | AY20: =IF(AE20=0,AK20,(1*100000*12)+(AK20)-AE20) -> 0 | AZ20: =SUM(AV20:AY20)-BF20+Z20-F20+BH20+BI20+BJ20+BK20+BL20+BM20 -> 0 | BD20: =IF(AZ20=0,(AZ20-BA20-BC20),(AZ20-BA20-BB20-BC20)) -> 0 | BF20: =Z20*1/100*BG20 -> 0 | BG20: 5
A21: AS201609 | B21: =VLOOKUP(A21,[11]LISTADHERENT!A$5:H$50,3,0) -> NANGUEN MARTIN | C21: =D21+E21+F21-U21-BB21 -> 0 | D21: =VLOOKUP(A21,[12]HISTOBQUEAVRIL24!$A$6:$G$46,3,0) -> 0 | E21: =VLOOKUP(A21,[12]HISTOBQUEAVRIL24!$A$6:$G$41,4,0) -> 0 | F21: =VLOOKUP(A21,[12]HISTOBQUEAVRIL24!$A$6:$G$41,5,0) -> 0 | G21: =IF(H21="ESPECES",3000,0) -> 0 | H21: =IF($D21<>0,"BANQUE",IF($E21<>0,"ESPECES","ECHEC")) -> ECHEC | J21: 1 | K21: =IF($D21<>0,J21*50000,IF($E21<>0,J21*50000,0)) -> 0 | M21: =IF($D21<>0,L21*75000,IF($E21<>0,L21*75000,0)) -> 0 | O21: =IF($D21<>0,N21*100000,IF($E21<>0,N21*100000,0)) -> 0 | P21: =VLOOKUP(A21,[14]TONTJUIL24!$A$6:$R$39,12,0) -> 0 | U21: =G21+S21++R21+P21+O21+M21+I21+K21+Q21+V21+W21 -> 0 | AQ21: =IF(H21="ECHEC",((K21+M21+O21)*20/100),0) -> 0 | AR21: =IF(H21="ECHEC",((K21+M21+O21)*20/100),0) -> 0 | AS21: =IF(H21="ECHEC",0,(K21+I21-25000)) -> 0 | AW21: =IF(AC21=0,AI21,(1*25000*12)+AI21-AC21) -> 0 | AX21: =IF(AD21=0,AJ21,(1*75000*12)+(AJ21)-AD21) -> 0 | AY21: =IF(AE21=0,AK21,(1*100000*12)+(AK21)-AE21) -> 0 | AZ21: =SUM(AV21:AY21)-BF21+Z21-F21+BH21+BI21+BJ21+BK21+BL21+BM21 -> 0 | BD21: =IF(AZ21=0,(AZ21-BA21-BC21),(AZ21-BA21-BB21-BC21)) -> 0 | BF21: =Z21*1/100*BG21 -> 0 | BG21: 5
A22: AS201610 | B22: =VLOOKUP(A22,[11]LISTADHERENT!A$5:H$50,3,0) -> NANKAM APPOLINAIRE | C22: =D22+E22+F22-U22-BB22 -> 0 | D22: =VLOOKUP(A22,[12]HISTOBQUEAVRIL24!$A$6:$G$46,3,0) -> 0 | E22: =VLOOKUP(A22,[12]HISTOBQUEAVRIL24!$A$6:$G$41,4,0) -> 0 | F22: =VLOOKUP(A22,[12]HISTOBQUEAVRIL24!$A$6:$G$41,5,0) -> 0 | G22: =IF(H22="ESPECES",3000,0) -> 0 | H22: =IF($D22<>0,"BANQUE",IF($E22<>0,"ESPECES","ECHEC")) -> ECHEC | J22: 1 | K22: =IF($D22<>0,J22*50000,IF($E22<>0,J22*50000,0)) -> 0 | L22: 1 | M22: =IF($D22<>0,L22*75000,IF($E22<>0,L22*75000,0)) -> 0 | O22: =IF($D22<>0,N22*100000,IF($E22<>0,N22*100000,0)) -> 0 | P22: =VLOOKUP(A22,[14]TONTJUIL24!$A$6:$R$39,12,0) -> 0 | Q22: =VLOOKUP(A22,[15]TONTJUIL24!$A$7:$P$23,10,0) -> 0 | U22: =G22+S22++R22+P22+O22+M22+I22+K22+Q22+V22+W22 -> 0 | AQ22: =IF(H22="ECHEC",((K22+M22+O22)*20/100),0) -> 0 | AR22: =IF(H22="ECHEC",((K22+M22+O22)*20/100),0) -> 0 | AS22: =IF(H22="ECHEC",0,(K22+I22-25000)) -> 0 | AW22: =IF(AC22=0,AI22,(1*25000*12)+AI22-AC22) -> 0 | AX22: =IF(AD22=0,AJ22,(1*75000*12)+(AJ22)-AD22) -> 0 | AY22: =IF(AE22=0,AK22,(1*100000*12)+(AK22)-AE22) -> 0 | AZ22: =SUM(AV22:AY22)-BF22+Z22-F22+BH22+BI22+BJ22+BK22+BL22+BM22 -> 0 | BD22: =IF(AZ22=0,(AZ22-BA22-BC22),(AZ22-BA22-BB22-BC22)) -> 0 | BF22: =Z22*1/100*BG22 -> 0 | BG22: 5 | BN22: INTERET | BP22: =SUM(BP18:BP21) -> 0
A23: AS201611 | B23: =VLOOKUP(A23,[11]LISTADHERENT!A$5:H$50,3,0) -> NDJOMO ETIENNE | C23: =D23+E23+F23-U23-BB23 -> 0 | D23: =VLOOKUP(A23,[12]HISTOBQUEAVRIL24!$A$6:$G$46,3,0) -> 0 | E23: =VLOOKUP(A23,[12]HISTOBQUEAVRIL24!$A$6:$G$41,4,0) -> 0 | F23: =VLOOKUP(A23,[12]HISTOBQUEAVRIL24!$A$6:$G$41,5,0) -> 0 | G23: =IF(H23="ESPECES",3000,0) -> 0 | H23: =IF($D23<>0,"BANQUE",IF($E23<>0,"ESPECES","ECHEC")) -> ECHEC | J23: 1 | K23: =IF($D23<>0,J23*50000,IF($E23<>0,J23*50000,0)) -> 0 | M23: =IF($D23<>0,L23*75000,IF($E23<>0,L23*75000,0)) -> 0 | N23: 2 | O23: =IF($D23<>0,N23*100000,IF($E23<>0,N23*100000,0)) -> 0 | P23: =VLOOKUP(A23,[14]TONTJUIL24!$A$6:$R$39,12,0) -> 0 | R23: =VLOOKUP(A23,[16]TONTJUIL24!$A$7:$P$20,10,0) -> 0 | U23: =G23+S23++R23+P23+O23+M23+I23+K23+Q23+V23+W23 -> 0 | AQ23: =IF(H23="ECHEC",((K23+M23+O23)*20/100),0) -> 0 | AR23: =IF(H23="ECHEC",((K23+M23+O23)*20/100),0) -> 0 | AS23: =IF(H23="ECHEC",0,(K23+I23-25000)) -> 0 | AW23: =IF(AC23=0,AI23,(1*25000*12)+AI23-AC23) -> 0 | AX23: =IF(AD23=0,AJ23,(1*75000*12)+(AJ23)-AD23) -> 0 | AY23: =IF(AE23=0,AK23,(1*100000*12)+(AK23)-AE23) -> 0 | AZ23: =SUM(AV23:AY23)-BF23+Z23-F23+BH23+BI23+BJ23+BK23+BL23+BM23 -> 0 | BD23: =IF(AZ23=0,(AZ23-BA23-BC23),(AZ23-BA23-BB23-BC23)) -> 0 | BF23: =Z23*1/100*BG23 -> 0 | BG23: 5
A24: AS201613 | B24: =VLOOKUP(A24,[11]LISTADHERENT!A$5:H$50,3,0) -> NGONDIEP CLAUDE | C24: =D24+E24+F24-U24-BB24 -> 0 | D24: =VLOOKUP(A24,[12]HISTOBQUEAVRIL24!$A$6:$G$46,3,0) -> 0 | E24: =VLOOKUP(A24,[12]HISTOBQUEAVRIL24!$A$6:$G$41,4,0) -> 0 | F24: =VLOOKUP(A24,[12]HISTOBQUEAVRIL24!$A$6:$G$41,5,0) -> 0 | G24: =IF(H24="ESPECES",3000,0) -> 0 | H24: =IF($D24<>0,"BANQUE",IF($E24<>0,"ESPECES","ECHEC")) -> ECHEC | J24: 1 | K24: =IF($D24<>0,J24*50000,IF($E24<>0,J24*50000,0)) -> 0 | L24: 1 | M24: =IF($D24<>0,L24*75000,IF($E24<>0,L24*75000,0)) -> 0 | N24: 1 | O24: =IF($D24<>0,N24*100000,IF($E24<>0,N24*100000,0)) -> 0 | P24: =VLOOKUP(A24,[14]TONTJUIL24!$A$6:$R$39,12,0) -> 0 | Q24: =VLOOKUP(A24,[15]TONTJUIL24!$A$7:$P$23,10,0) -> 0 | R24: =VLOOKUP(A24,[16]TONTJUIL24!$A$7:$P$20,10,0) -> 0 | U24: =G24+S24++R24+P24+O24+M24+I24+K24+Q24+V24+W24 -> 0 | AQ24: =IF(H24="ECHEC",((K24+M24+O24)*20/100),0) -> 0 | AR24: =IF(H24="ECHEC",((K24+M24+O24)*20/100),0) -> 0 | AS24: =IF(H24="ECHEC",0,(K24+I24-25000)) -> 0 | AW24: =IF(AC24=0,AI24,(1*25000*12)+AI24-AC24) -> 0 | AX24: =IF(AD24=0,AJ24,(1*75000*12)+(AJ24)-AD24) -> 0 | AY24: =IF(AE24=0,AK24,(1*100000*12)+(AK24)-AE24) -> 0 | AZ24: =SUM(AV24:AY24)-BF24+Z24-F24+BH24+BI24+BJ24+BK24+BL24+BM24 -> 0 | BD24: =IF(AZ24=0,(AZ24-BA24-BC24),(AZ24-BA24-BB24-BC24)) -> 0 | BF24: =Z24*1/100*BG24 -> 0 | BG24: 5 | BN24: MONTANT_MUTUELLE | BO24: SIMO FONGANG ERIC
A25: AS201614 | B25: =VLOOKUP(A25,[11]LISTADHERENT!A$5:H$50,3,0) -> NGUIEMEGNI MATHIEU BLAISE | C25: =D25+E25+F25-U25-BB25 -> 0 | D25: =VLOOKUP(A25,[12]HISTOBQUEAVRIL24!$A$6:$G$46,3,0) -> 0 | E25: =VLOOKUP(A25,[12]HISTOBQUEAVRIL24!$A$6:$G$41,4,0) -> 0 | F25: =VLOOKUP(A25,[12]HISTOBQUEAVRIL24!$A$6:$G$41,5,0) -> 0 | G25: =IF(H25="ESPECES",3000,0) -> 0 | H25: =IF($D25<>0,"BANQUE",IF($E25<>0,"ESPECES","ECHEC")) -> ECHEC | J25: 1 | K25: =IF($D25<>0,J25*50000,IF($E25<>0,J25*50000,0)) -> 0 | L25: 3 | M25: =IF($D25<>0,L25*75000,IF($E25<>0,L25*75000,0)) -> 0 | N25: 1 | O25: =IF($D25<>0,N25*100000,IF($E25<>0,N25*100000,0)) -> 0 | P25: =VLOOKUP(A25,[14]TONTJUIL24!$A$6:$R$39,12,0) -> 0 | Q25: =VLOOKUP(A25,[15]TONTJUIL24!$A$7:$P$23,10,0) -> 0 | R25: =VLOOKUP(A25,[16]TONTJUIL24!$A$7:$P$20,10,0) -> 0 | U25: =G25+S25++R25+P25+O25+M25+I25+K25+Q25+V25+W25 -> 0 | AQ25: =IF(H25="ECHEC",((K25+M25+O25)*20/100),0) -> 0 | AR25: =IF(H25="ECHEC",((K25+M25+O25)*20/100),0) -> 0 | AS25: =IF(H25="ECHEC",0,(K25+I25-25000)) -> 0 | AW25: =IF(AC25=0,AI25,(1*25000*12)+AI25-AC25) -> 0 | AX25: =IF(AD25=0,AJ25,(1*75000*12)+(AJ25)-AD25) -> 0 | AY25: =IF(AE25=0,AK25,(1*100000*12)+(AK25)-AE25) -> 0 | AZ25: =SUM(AV25:AY25)-BF25+Z25-F25+BH25+BI25+BJ25+BK25+BL25+BM25 -> 0 | BD25: =IF(AZ25=0,(AZ25-BA25-BC25),(AZ25-BA25-BB25-BC25)) -> 0 | BF25: =Z25*1/100*BG25 -> 0 | BG25: 5 | BN25: TIEYAM ERNEST | BO25: SIMO FONGANG ERIC
A26: AS201615 | B26: =VLOOKUP(A26,[11]LISTADHERENT!A$5:H$50,3,0) -> NKAMGANG JUSTIN DEJOLIE | C26: =D26+E26+F26-U26-BB26 -> 0 | D26: =VLOOKUP(A26,[12]HISTOBQUEAVRIL24!$A$6:$G$46,3,0) -> 0 | E26: =VLOOKUP(A26,[12]HISTOBQUEAVRIL24!$A$6:$G$41,4,0) -> 0 | F26: =VLOOKUP(A26,[12]HISTOBQUEAVRIL24!$A$6:$G$41,5,0) -> 0 | G26: =IF(H26="ESPECES",3000,0) -> 0 | H26: =IF($D26<>0,"BANQUE",IF($E26<>0,"ESPECES","ECHEC")) -> ECHEC | J26: 1 | K26: =IF($D26<>0,J26*50000,IF($E26<>0,J26*50000,0)) -> 0 | M26: =IF($D26<>0,L26*75000,IF($E26<>0,L26*75000,0)) -> 0 | O26: =IF($D26<>0,N26*100000,IF($E26<>0,N26*100000,0)) -> 0 | P26: =VLOOKUP(A26,[14]TONTJUIL24!$A$6:$R$39,12,0) -> 0 | U26: =G26+S26++R26+P26+O26+M26+I26+K26+Q26+V26+W26 -> 0 | AQ26: =IF(H26="ECHEC",((K26+M26+O26)*20/100),0) -> 0 | AR26: =IF(H26="ECHEC",((K26+M26+O26)*20/100),0) -> 0 | AS26: =IF(H26="ECHEC",0,(K26+I26-25000)) -> 0 | AW26: =IF(AC26=0,AI26,(1*25000*12)+AI26-AC26) -> 0 | AX26: =IF(AD26=0,AJ26,(1*75000*12)+(AJ26)-AD26) -> 0 | AY26: =IF(AE26=0,AK26,(1*100000*12)+(AK26)-AE26) -> 0 | AZ26: =SUM(AV26:AY26)-BF26+Z26-F26+BH26+BI26+BJ26+BK26+BL26+BM26 -> 0 | BD26: =IF(AZ26=0,(AZ26-BA26-BC26),(AZ26-BA26-BB26-BC26)) -> 0 | BF26: =Z26*1/100*BG26 -> 0 | BG26: 5 | BN26: NOM_ET_PRENOM | BO26: SIMO FONGANG ERIC
A27: DETTE CHINGUE | B27: =VLOOKUP(A27,[11]LISTADHERENT!A$5:H$50,3,0) -> NOUBE ETIENNE | C27: =D27+E27+F27-U27-BB27 -> 0 | D27: =VLOOKUP(A27,[12]HISTOBQUEAVRIL24!$A$6:$G$46,3,0) -> 0 | E27: =VLOOKUP(A27,[12]HISTOBQUEAVRIL24!$A$6:$G$41,4,0) -> 0 | F27: =VLOOKUP(A27,[12]HISTOBQUEAVRIL24!$A$6:$G$41,5,0) -> 0 | G27: =IF(H27="ESPECES",3000,0) -> 0 | H27: =IF($D27<>0,"BANQUE",IF($E27<>0,"ESPECES","ECHEC")) -> ECHEC | J27: 1 | K27: =IF($D27<>0,J27*50000,IF($E27<>0,J27*50000,0)) -> 0 | M27: =IF($D27<>0,L27*75000,IF($E27<>0,L27*75000,0)) -> 0 | O27: =IF($D27<>0,N27*100000,IF($E27<>0,N27*100000,0)) -> 0 | P27: =VLOOKUP(A27,[14]TONTJUIL24!$A$6:$R$39,12,0) -> 0 | U27: =G27+S27++R27+P27+O27+M27+I27+K27+Q27+V27+W27 -> 0 | AQ27: =IF(H27="ECHEC",((K27+M27+O27)*20/100),0) -> 0 | AR27: =IF(H27="ECHEC",((K27+M27+O27)*20/100),0) -> 0 | AS27: =IF(H27="ECHEC",0,(K27+I27-25000)) -> 0 | AW27: =IF(AC27=0,AI27,(1*25000*12)+AI27-AC27) -> 0 | AX27: =IF(AD27=0,AJ27,(1*75000*12)+(AJ27)-AD27) -> 0 | AY27: =IF(AE27=0,AK27,(1*100000*12)+(AK27)-AE27) -> 0 | AZ27: =SUM(AV27:AY27)-BF27+Z27-F27+BH27+BI27+BJ27+BK27+BL27+BM27 -> 0 | BD27: =IF(AZ27=0,(AZ27-BA27-BC27),(AZ27-BA27-BB27-BC27)) -> 0 | BF27: =Z27*1/100*BG27 -> 0 | BG27: 5
A28: AS201618 | B28: =VLOOKUP(A28,[11]LISTADHERENT!A$5:H$50,3,0) -> PATEGO NJOSSU GUSTAVE | C28: =D28+E28+F28-U28-BB28 -> 0 | D28: =VLOOKUP(A28,[12]HISTOBQUEAVRIL24!$A$6:$G$46,3,0) -> 0 | E28: =VLOOKUP(A28,[12]HISTOBQUEAVRIL24!$A$6:$G$41,4,0) -> 0 | F28: =VLOOKUP(A28,[12]HISTOBQUEAVRIL24!$A$6:$G$41,5,0) -> 0 | G28: =IF(H28="ESPECES",3000,0) -> 0 | H28: =IF($D28<>0,"BANQUE",IF($E28<>0,"ESPECES","ECHEC")) -> ECHEC | J28: 1 | K28: =IF($D28<>0,J28*50000,IF($E28<>0,J28*50000,0)) -> 0 | L28: 1 | M28: =IF($D28<>0,L28*75000,IF($E28<>0,L28*75000,0)) -> 0 | O28: =IF($D28<>0,N28*100000,IF($E28<>0,N28*100000,0)) -> 0 | P28: =VLOOKUP(A28,[14]TONTJUIL24!$A$6:$R$39,12,0) -> 0 | Q28: =VLOOKUP(A28,[15]TONTJUIL24!$A$7:$P$23,10,0) -> 0 | U28: =G28+S28++R28+P28+O28+M28+I28+K28+Q28+V28+W28 -> 0 | AQ28: =IF(H28="ECHEC",((K28+M28+O28)*20/100),0) -> 0 | AR28: =IF(H28="ECHEC",((K28+M28+O28)*20/100),0) -> 0 | AS28: =IF(H28="ECHEC",0,(K28+I28-25000)) -> 0 | AW28: =IF(AC28=0,AI28,(1*25000*12)+AI28-AC28) -> 0 | AX28: =IF(AD28=0,AJ28,(1*75000*12)+(AJ28)-AD28) -> 0 | AY28: =IF(AE28=0,AK28,(1*100000*12)+(AK28)-AE28) -> 0 | AZ28: =SUM(AV28:AY28)-BF28+Z28-F28+BH28+BI28+BJ28+BK28+BL28+BM28 -> 0 | BD28: =IF(AZ28=0,(AZ28-BA28-BC28),(AZ28-BA28-BB28-BC28)) -> 0 | BF28: =Z28*1/100*BG28 -> 0 | BG28: 5 | BN28: INTERET | BP28: =SUM(BP24:BP26) -> 0
