Workbook

Sheet Sheet1

Sheet Sheet2

Sheet Sheet3

Sheet Sheet4

Sheet Sheet5

Sheet Sheet6

Sheet Sheet7

Sheet Sheet8

Sheet Sheet9

Sheet Sheet10

Sheet Sheet11

Sheet Sheet12

Sheet Sheet13

Sheet Sheet14

Sheet Sheet15

Sheet Sheet16
A1: ASSOCIATION | B1: ASELBY
A2: ANNEE | B2: 2024
A3: 1 | B3: 2 | C3: 3 | D3: 4 | E3: 5 | F3: 6 | G3: 7 | H3: 8 | I3: 9 | J3: 10 | K3: 11 | L3: 12 | M3: 13 | N3: 14 | O3: 15 | P3: 16 | Q3: 17 | R3: 18 | S3: 19 | T3: 20 | U3: 21 | V3: 22 | W3: 23 | X3: 24 | Y3: 25 | Z3: 26 | AA3: 27 | AB3: 28 | AC3: 29 | AD3: 30 | AE3: 31 | AF3: 32 | AG3: 33 | AH3: 34 | AI3: 35 | AJ3: 36 | AK3: 37 | AL3: 38 | AM3: 39 | AN3: 40 | AO3: 41 | AP3: 42 | AQ3: 43 | AR3: 44 | AS3: 45 | AT3: 46 | AU3: 47 | AV3: 48 | AW3: 49 | AX3: 50 | AY3: 51 | AZ3: 52 | BA3: 53 | BB3: 54 | BC3: 55 | BD3: 56 | BE3: 57 | BF3: 58 | BG3: 59 | BH3: 60 | BI3: 61 | BJ3: 62 | BK3: 63 | BL3: 64 | BM3: 65 | BN3: 66 | BO3: 67 | BP3: 68
B4: TABLEAU DE BORD SAISIE DES DONNEES
A5: MATRICULE | B5: NOM ET PRENOM | C5: BONUS MALUS | D5: HISTORIQUE BANQUE | E5: HITORIQUE ESPECES | F5: HITORIQUE TONTINE | G5: PENALITE VERSEMENT ESPECES | H5: MODE PAIEMENT TONTINE | I5: COMPLEMENT EPARGNE | J5: NBRE DE LOT | K5: TONTINE 40 000 | L5: NBRE DE LOT | M5: TONTINE 75 000 | N5: NBRE DE LOT | O5: TONTINE 100 000 | P5: REMBOURSEMENT PETIT LOT T50 | Q5: REMBOURSEMENT PETIT LOT T75 | R5: REMBOURSEMENT PETIT LOT T100 | S5: REMBOURSEMENT PRÊT FONDS | T5: MODE PAIEMENT REMBOURSEMENT PRÊT FONDS | U5: MONTANT ENGAGEMENT | V5: SANCTION | W5: INSCRIPTION | X5: EPARGNE ASSURANCE | Y5: RECONSTITUTION FONDS | Z5: PRÊT FONDS | AA5: MODE PAIEMENT PRÊT | AB5: NUM CHEQUE | AC5: ACHAT LOT PRINCIPAL T50 | AD5: ACHAT LOT PRINCIPAL T75 | AE5: ACHAT LOT PRINCIPAL T100 | AF5: MODE PAIEMENT LOT PRINCIPAL | AG5: NUM CHEQUE | AH5: PENALITE VERSEMENT ESPECES | AI5: VENTE PETIT LOT T50 | AJ5: VENTE PETIT LOT T75 | AK5: VENTE PETIT LOT T100 | AL5: INTERET PETIT LOT T50 | AM5: INTERET PETIT LOT T75 | AN5: INTERET PETIT LOT T100 | AO5: NUM CHEQUE | AP5: MODE PAIEMENT PETIT LOT | AQ5: PENELAITE RETARD TONTINE | AR5: PENELAITE ECHEC TONTINE | AS5: RESTE | AT5: MUTUELLE | AU5: REMBOURSEMENT TRANSPORT | AV5: RETRAIT PARTIEL FONDS | AW5: MONTANT T50 | AX5: MONTANT T75 | AY5: MONTANT T100 | AZ5: MONTANT CHEQUE | BA5: MONTANT ESPECES | BB5: CONTRIBUTION FOYER | BC5: AUTRES SOTIES | BD5: MONTANT CHEQUE EFFECTIF | BE5: NUMERO CHEQUE | BF5: INTERET PRÊT | BG5: NBRE MOIS | BH5: DEPENSE FONDS DE ROULEMENT | BI5: DEPENSE FRAIS EXCEPTIONNEL | BJ5: DEPENSE FONDS MUTUEL | BK5: DEPENSE COLLATION RECEPTION | BL5: PENALITE PRET FONDS | BM5: DEPENSE PENALITE VERSEMENT BANQUE | BN5: LIBELLE | BO5: COMPTE | BP5: MONTANT
A6: AS201648 | B6: =VLOOKUP(A6,[11]LISTADHERENT!A$5:H$50,3,0) -> ASELBY | C6: =D6+E6+F6-U6-BB6 -> 0 | D6: =VLOOKUP(A6,[12]HISTOBQUEAVRIL24!$A$6:$G$46,3,0) -> 0 | E6: =VLOOKUP(A6,[12]HISTOBQUEAVRIL24!$A$6:$G$41,4,0) -> 0 | F6: =VLOOKUP(A6,[12]HISTOBQUEAVRIL24!$A$6:$G$41,5,0) -> 0 | G6: =IF(H6="ESPECES",3000,0) -> 0 | H6: =IF($D6<>0,"BANQUE",IF($E6<>0,"ESPECES","ECHEC")) -> ECHEC | K6: =IF($D6<>0,J6*50000,IF($E6<>0,J6*50000,0)) -> 0 | L6: 1 | M6: =IF($D6<>0,L6*75000,IF($E6<>0,L6*75000,0)) -> 0 | N6: 1 | O6: =IF($D6<>0,N6*100000,IF($E6<>0,N6*100000,0)) -> 0 | U6: =G6+S6++R6+P6+O6+M6+I6+K6+Q6+V6+W6 -> 0 | AQ6: =IF(H6="ECHEC",((K6+M6+O6)*20/100),0) -> 0 | AR6: =IF(H6="ECHEC",((K6+M6+O6)*20/100),0) -> 0 | AW6: =IF(AC6=0,AI6,(1*25000*12)+AI6-AC6) -> 0 | AX6: =IF(AD6=0,AJ6,(1*75000*12)+(AJ6)-AD6) -> 0 | AY6: =IF(AE6=0,AK6,(1*100000*12)+(AK6)-AE6) -> 0 | AZ6: =SUM(AV6:AY6)-BF6+Z6-F6+BH6+BI6+BJ6+BK6+BL6+BM6 -> 0 | BD6: =IF(AZ6=0,(AZ6-BA6-BC6),(AZ6-BA6-BB6-BC6)) -> 0 | BF6: =Z6*1/100*BG6 -> 0 | BG6: 11 | BH6: =BP16 -> 0 | BI6: =BP28 -> 0 | BJ6: =BP33 -> 0 | BK6: =+BP40 -> 0 | BM6: =BP22 -> 0 | BN6: ACHAT FOURNITURE | BO6: FONDS DE ROULEMENT
A7: AS201601 | B7: =VLOOKUP(A7,[11]LISTADHERENT!A$5:H$50,3,0) -> BAKOP ACHILLE | C7: =D7+E7+F7-U7-BB7 -> 0 | D7: =VLOOKUP(A7,[12]HISTOBQUEAVRIL24!$A$6:$G$46,3,0) -> 0 | E7: =VLOOKUP(A7,[12]HISTOBQUEAVRIL24!$A$6:$G$41,4,0) -> 0 | F7: =VLOOKUP(A7,[12]HISTOBQUEAVRIL24!$A$6:$G$41,5,0) -> 0 | G7: =IF(H7="ESPECES",3000,0) -> 0 | H7: =IF($D7<>0,"BANQUE",IF($E7<>0,"ESPECES","ECHEC")) -> ECHEC | J7: 1 | K7: =IF($D7<>0,J7*50000,IF($E7<>0,J7*50000,0)) -> 0 | M7: =IF($D7<>0,L7*75000,IF($E7<>0,L7*75000,0)) -> 0 | O7: =IF($D7<>0,N7*100000,IF($E7<>0,N7*100000,0)) -> 0 | P7: =VLOOKUP(A7,[14]TONTDEC24!$A$6:$R$39,12,0) -> 0 | U7: =G7+S7++R7+P7+O7+M7+I7+K7+Q7+V7+W7 -> 0 | AQ7: =IF(H7="ECHEC",((K7+M7+O7)*20/100),0) -> 0 | AR7: =IF(H7="ECHEC",((K7+M7+O7)*20/100),0) -> 0 | AS7: =IF(H7="ECHEC",0,(K7+I7-25000)) -> 0 | AW7: =IF(AC7=0,AI7,(1*25000*12)+AI7-AC7) -> 0 | AX7: =IF(AD7=0,AJ7,(1*75000*12)+(AJ7)-AD7) -> 0 | AY7: =IF(AE7=0,AK7,(1*100000*12)+(AK7)-AE7) -> 0 | AZ7: =SUM(AV7:AY7)-BF7+Z7-F7+BH7+BI7+BJ7+BK7+BL7+BM7 -> 0 | BD7: =IF(AZ7=0,(AZ7-BA7-BC7),(AZ7-BA7-BB7-BC7)) -> 0 | BF7: =Z7*1/100*BG7 -> 0 | BG7: 11 | BN7: COMMUNICATION | BO7: FONDS DE ROULEMENT
A8: AS201602 | B8: =VLOOKUP(A8,[11]LISTADHERENT!A$5:H$50,3,0) -> BOUTCHOUANG WILLIAM | C8: =D8+E8+F8-U8-BB8 -> 0 | D8: =VLOOKUP(A8,[12]HISTOBQUEAVRIL24!$A$6:$G$46,3,0) -> 0 | E8: =VLOOKUP(A8,[12]HISTOBQUEAVRIL24!$A$6:$G$41,4,0) -> 0 | F8: =VLOOKUP(A8,[12]HISTOBQUEAVRIL24!$A$6:$G$41,5,0) -> 0 | G8: =IF(H8="ESPECES",3000,0) -> 0 | H8: =IF($D8<>0,"BANQUE",IF($E8<>0,"ESPECES","ECHEC")) -> ECHEC | J8: 1 | K8: =IF($D8<>0,J8*50000,IF($E8<>0,J8*50000,0)) -> 0 | L8: 1 | M8: =IF($D8<>0,L8*75000,IF($E8<>0,L8*75000,0)) -> 0 | O8: =IF($D8<>0,N8*100000,IF($E8<>0,N8*100000,0)) -> 0 | P8: =VLOOKUP(A8,[14]TONTDEC24!$A$6:$R$39,12,0) -> 0 | Q8: =VLOOKUP(A8,[15]TONTDEC24!$A$7:$P$23,10,0) -> 0 | U8: =G8+S8++R8+P8+O8+M8+I8+K8+Q8+V8+W8 -> 0 | AQ8: =IF(H8="ECHEC",((K8+M8+O8)*20/100),0) -> 0 | AR8: =IF(H8="ECHEC",((K8+M8+O8)*20/100),0) -> 0 | AS8: =IF(H8="ECHEC",0,(K8+I8-25000)) -> 0 | AW8: =IF(AC8=0,AI8,(1*25000*12)+AI8-AC8) -> 0 | AX8: =IF(AD8=0,AJ8,(1*75000*12)+(AJ8)-AD8) -> 0 | AY8: =IF(AE8=0,AK8,(1*100000*12)+(AK8)-AE8) -> 0 | AZ8: =SUM(AV8:AY8)-BF8+Z8-F8+BH8+BI8+BJ8+BK8+BL8+BM8 -> 0 | BD8: =IF(AZ8=0,(AZ8-BA8-BC8),(AZ8-BA8-BB8-BC8)) -> 0 | BF8: =Z8*1/100*BG8 -> 0 | BG8: 11 | BN8: COMMISSION | BO8: FONDS DE ROULEMENT
A9: AS201604 | B9: =VLOOKUP(A9,[11]LISTADHERENT!A$5:H$50,3,0) -> DJOMO JEAN PAUL | C9: =D9+E9+F9-U9-BB9 -> 0 | D9: =VLOOKUP(A9,[12]HISTOBQUEAVRIL24!$A$6:$G$46,3,0) -> 0 | E9: =VLOOKUP(A9,[12]HISTOBQUEAVRIL24!$A$6:$G$41,4,0) -> 0 | F9: =VLOOKUP(A9,[12]HISTOBQUEAVRIL24!$A$6:$G$41,5,0) -> 0 | G9: =IF(H9="ESPECES",3000,0) -> 0 | H9: =IF($D9<>0,"BANQUE",IF($E9<>0,"ESPECES","ECHEC")) -> ECHEC | J9: 1 | K9: =IF($D9<>0,J9*50000,IF($E9<>0,J9*50000,0)) -> 0 | M9: =IF($D9<>0,L9*75000,IF($E9<>0,L9*75000,0)) -> 0 | N9: 2 | O9: =IF($D9<>0,N9*100000,IF($E9<>0,N9*100000,0)) -> 0 | P9: =VLOOKUP(A9,[14]TONTDEC24!$A$6:$R$39,12,0) -> 0 | R9: =VLOOKUP(A9,[16]TONTDEC24!$A$7:$P$20,10,0) -> 0 | U9: =G9+S9++R9+P9+O9+M9+I9+K9+Q9+V9+W9 -> 0 | AQ9: =IF(H9="ECHEC",((K9+M9+O9)*20/100),0) -> 0 | AR9: =IF(H9="ECHEC",((K9+M9+O9)*20/100),0) -> 0 | AS9: =IF(H9="ECHEC",0,(K9+I9-25000)) -> 0 | AW9: =IF(AC9=0,AI9,(1*25000*12)+AI9-AC9) -> 0 | AX9: =IF(AD9=0,AJ9,(1*75000*12)+(AJ9)-AD9) -> 0 | AY9: =IF(AE9=0,AK9,(1*100000*12)+(AK9)-AE9) -> 0 | AZ9: =SUM(AV9:AY9)-BF9+Z9-F9+BH9+BI9+BJ9+BK9+BL9+BM9 -> 0 | BD9: =IF(AZ9=0,(AZ9-BA9-BC9),(AZ9-BA9-BB9-BC9)) -> 0 | BF9: =Z9*1/100*BG9 -> 0 | BG9: 11 | BN9: OUVERTURE COMPTE | BO9: FONDS DE ROULEMENT
A10: AS201654 | B10: =VLOOKUP(A10,[11]LISTADHERENT!A$5:H$50,3,0) -> DJOMOU TCHAPDA | C10: =D10+E10+F10-U10-BB10 -> 0 | D10: =VLOOKUP(A10,[12]HISTOBQUEAVRIL24!$A$6:$G$46,3,0) -> 0 | E10: =VLOOKUP(A10,[12]HISTOBQUEAVRIL24!$A$6:$G$41,4,0) -> 0 | F10: =VLOOKUP(A10,[12]HISTOBQUEAVRIL24!$A$6:$G$41,5,0) -> 0 | G10: =IF(H10="ESPECES",3000,0) -> 0 | H10: =IF($D10<>0,"BANQUE",IF($E10<>0,"ESPECES","ECHEC")) -> ECHEC | J10: 1 | K10: =IF($D10<>0,J10*50000,IF($E10<>0,J10*50000,0)) -> 0 | L10: 1 | M10: =IF($D10<>0,L10*75000,IF($E10<>0,L10*75000,0)) -> 0 | O10: =IF($D10<>0,N10*100000,IF($E10<>0,N10*100000,0)) -> 0 | P10: =VLOOKUP(A10,[14]TONTDEC24!$A$6:$R$39,12,0) -> 0 | Q10: =VLOOKUP(A10,[15]TONTDEC24!$A$7:$P$23,10,0) -> 0 | U10: =G10+S10++R10+P10+O10+M10+I10+K10+Q10+V10+W10 -> 0 | AQ10: =IF(H10="ECHEC",((K10+M10+O10)*20/100),0) -> 0 | AR10: =IF(H10="ECHEC",((K10+M10+O10)*20/100),0) -> 0 | AS10: =IF(H10="ECHEC",0,(K10+I10-25000)) -> 0 | AW10: =IF(AC10=0,AI10,(1*25000*12)+AI10-AC10) -> 0 | AX10: =IF(AD10=0,AJ10,(1*75000*12)+(AJ10)-AD10) -> 0 | AY10: =IF(AE10=0,AK10,(1*100000*12)+(AK10)-AE10) -> 0 | AZ10: =SUM(AV10:AY10)-BF10+Z10-F10+BH10+BI10+BJ10+BK10+BL10+BM10 -> 0 | BD10: =IF(AZ10=0,(AZ10-BA10-BC10),(AZ10-BA10-BB10-BC10)) -> 0 | BF10: =Z10*1/100*BG10 -> 0 | BG10: 11 | BN10: CREDIT TELEPHONE | BO10: FONDS DE ROULEMENT
A11: AS201605 | B11: =VLOOKUP(A11,[11]LISTADHERENT!A$5:H$50,3,0) -> DJOUKWE NANGUEN GUY BLAISE | C11: =D11+E11+F11-U11-BB11 -> 0 | D11: =VLOOKUP(A11,[12]HISTOBQUEAVRIL24!$A$6:$G$46,3,0) -> 0 | E11: =VLOOKUP(A11,[12]HISTOBQUEAVRIL24!$A$6:$G$41,4,0) -> 0 | F11: =VLOOKUP(A11,[12]HISTOBQUEAVRIL24!$A$6:$G$41,5,0) -> 0 | G11: =IF(H11="ESPECES",3000,0) -> 0 | H11: =IF($D11<>0,"BANQUE",IF($E11<>0,"ESPECES","ECHEC")) -> ECHEC | J11: 1 | K11: =IF($D11<>0,J11*50000,IF($E11<>0,J11*50000,0)) -> 0 | L11: 1 | M11: =IF($D11<>0,L11*75000,IF($E11<>0,L11*75000,0)) -> 0 | O11: =IF($D11<>0,N11*100000,IF($E11<>0,N11*100000,0)) -> 0 | P11: =VLOOKUP(A11,[14]TONTDEC24!$A$6:$R$39,12,0) -> 0 | Q11: =VLOOKUP(A11,[15]TONTDEC24!$A$7:$P$23,10,0) -> 0 | U11: =G11+S11++R11+P11+O11+M11+I11+K11+Q11+V11+W11 -> 0 | AQ11: =IF(H11="ECHEC",((K11+M11+O11)*20/100),0) -> 0 | AR11: =IF(H11="ECHEC",((K11+M11+O11)*20/100),0) -> 0 | AS11: =IF(H11="ECHEC",0,(K11+I11-25000)) -> 0 | AW11: =IF(AC11=0,AI11,(1*25000*12)+AI11-AC11) -> 0 | AX11: =IF(AD11=0,AJ11,(1*75000*12)+(AJ11)-AD11) -> 0 | AY11: =IF(AE11=0,AK11,(1*100000*12)+(AK11)-AE11) -> 0 | AZ11: =SUM(AV11:AY11)-BF11+Z11-F11+BH11+BI11+BJ11+BK11+BL11+BM11 -> 0 | BD11: =IF(AZ11=0,(AZ11-BA11-BC11),(AZ11-BA11-BB11-BC11)) -> 0 | BF11: =Z11*1/100*BG11 -> 0 | BG11: 11 | BN11: PRODUCTION RAPPORT | BO11: FONDS DE ROULEMENT
A12: AS201608 | B12: =VLOOKUP(A12,[11]LISTADHERENT!A$5:H$50,3,0) -> DJUOMBESSY ANTOINE | C12: =D12+E12+F12-U12-BB12 -> 0 | D12: =VLOOKUP(A12,[12]HISTOBQUEAVRIL24!$A$6:$G$46,3,0) -> 0 | E12: =VLOOKUP(A12,[12]HISTOBQUEAVRIL24!$A$6:$G$41,4,0) -> 0 | F12: =VLOOKUP(A12,[12]HISTOBQUEAVRIL24!$A$6:$G$41,5,0) -> 0 | G12: =IF(H12="ESPECES",3000,0) -> 0 | H12: =IF($D12<>0,"BANQUE",IF($E12<>0,"ESPECES","ECHEC")) -> ECHEC | J12: 1 | K12: =IF($D12<>0,J12*50000,IF($E12<>0,J12*50000,0)) -> 0 | L12: 1 | M12: =IF($D12<>0,L12*75000,IF($E12<>0,L12*75000,0)) -> 0 | N12: 2 | O12: =IF($D12<>0,N12*100000,IF($E12<>0,N12*100000,0)) -> 0 | P12: =VLOOKUP(A12,[14]TONTDEC24!$A$6:$R$39,12,0) -> 0 | Q12: =VLOOKUP(A12,[15]TONTDEC24!$A$7:$P$23,10,0) -> 0 | R12: =VLOOKUP(A12,[16]TONTDEC24!$A$7:$P$20,10,0) -> 0 | U12: =G12+S12++R12+P12+O12+M12+I12+K12+Q12+V12+W12 -> 0 | AQ12: =IF(H12="ECHEC",((K12+M12+O12)*20/100),0) -> 0 | AR12: =IF(H12="ECHEC",((K12+M12+O12)*20/100),0) -> 0 | AS12: =IF(H12="ECHEC",0,(K12+I12-25000)) -> 0 | AW12: =IF(AC12=0,AI12,(1*25000*12)+AI12-AC12) -> 0 | AX12: =IF(AD12=0,AJ12,(1*75000*12)+(AJ12)-AD12) -> 0 | AY12: =IF(AE12=0,AK12,(1*100000*12)+(AK12)-AE12) -> 0 | AZ12: =SUM(AV12:AY12)-BF12+Z12-F12+BH12+BI12+BJ12+BK12+BL12+BM12 -> 0 | BD12: =IF(AZ12=0,(AZ12-BA12-BC12),(AZ12-BA12-BB12-BC12)) -> 0 | BF12: =Z12*1/100*BG12 -> 0 | BG12: 11 | BN12: ACHAT SOURIS ET PHOTOCOPIE | BO12: FONDS DE ROULEMENT
A13: AS201651 | B13: =VLOOKUP(A13,[11]LISTADHERENT!A$5:H$50,3,0) -> DOMOU FABIEN | C13: =D13+E13+F13-U13-BB13 -> 0 | D13: =VLOOKUP(A13,[12]HISTOBQUEAVRIL24!$A$6:$G$46,3,0) -> 0 | E13: =VLOOKUP(A13,[12]HISTOBQUEAVRIL24!$A$6:$G$41,4,0) -> 0 | F13: =VLOOKUP(A13,[12]HISTOBQUEAVRIL24!$A$6:$G$41,5,0) -> 0 | G13: =IF(H13="ESPECES",3000,0) -> 0 | H13: =IF($D13<>0,"BANQUE",IF($E13<>0,"ESPECES","ECHEC")) -> ECHEC | J13: 1 | K13: =IF($D13<>0,J13*50000,IF($E13<>0,J13*50000,0)) -> 0 | M13: =IF($D13<>0,L13*75000,IF($E13<>0,L13*75000,0)) -> 0 | O13: =IF($D13<>0,N13*100000,IF($E13<>0,N13*100000,0)) -> 0 | P13: =VLOOKUP(A13,[14]TONTDEC24!$A$6:$R$39,12,0) -> 0 | U13: =G13+S13++R13+P13+O13+M13+I13+K13+Q13+V13+W13 -> 0 | AQ13: =IF(H13="ECHEC",((K13+M13+O13)*20/100),0) -> 0 | AR13: =IF(H13="ECHEC",((K13+M13+O13)*20/100),0) -> 0 | AS13: =IF(H13="ECHEC",0,(K13+I13-25000)) -> 0 | AW13: =IF(AC13=0,AI13,(1*25000*12)+AI13-AC13) -> 0 | AX13: =IF(AD13=0,AJ13,(1*75000*12)+(AJ13)-AD13) -> 0 | AY13: =IF(AE13=0,AK13,(1*100000*12)+(AK13)-AE13) -> 0 | AZ13: =SUM(AV13:AY13)-BF13+Z13-F13+BH13+BI13+BJ13+BK13+BL13+BM13 -> 0 | BD13: =IF(AZ13=0,(AZ13-BA13-BC13),(AZ13-BA13-BB13-BC13)) -> 0 | BF13: =Z13*1/100*BG13 -> 0 | BG13: 11 | BN13: TAXI BANQUE | BO13: FONDS DE ROULEMENT
A14: AS201609 | B14: =VLOOKUP(A14,[11]LISTADHERENT!A$5:H$50,3,0) -> DONHOU DAVID | C14: =D14+E14+F14-U14-BB14 -> 0 | D14: =VLOOKUP(A14,[12]HISTOBQUEAVRIL24!$A$6:$G$46,3,0) -> 0 | E14: =VLOOKUP(A14,[12]HISTOBQUEAVRIL24!$A$6:$G$41,4,0) -> 0 | F14: =VLOOKUP(A14,[12]HISTOBQUEAVRIL24!$A$6:$G$41,5,0) -> 0 | G14: =IF(H14="ESPECES",3000,0) -> 0 | H14: =IF($D14<>0,"BANQUE",IF($E14<>0,"ESPECES","ECHEC")) -> ECHEC | J14: 1 | K14: =IF($D14<>0,J14*50000,IF($E14<>0,J14*50000,0)) -> 0 | M14: =IF($D14<>0,L14*75000,IF($E14<>0,L14*75000,0)) -> 0 | O14: =IF($D14<>0,N14*100000,IF($E14<>0,N14*100000,0)) -> 0 | P14: =VLOOKUP(A14,[14]TONTDEC24!$A$6:$R$39,12,0) -> 0 | U14: =G14+S14++R14+P14+O14+M14+I14+K14+Q14+V14+W14 -> 0 | AQ14: =IF(H14="ECHEC",((K14+M14+O14)*20/100),0) -> 0 | AR14: =IF(H14="ECHEC",((K14+M14+O14)*20/100),0) -> 0 | AS14: =IF(H14="ECHEC",0,(K14+I14-25000)) -> 0 | AW14: =IF(AC14=0,AI14,(1*25000*12)+AI14-AC14) -> 0 | AX14: =IF(AD14=0,AJ14,(1*75000*12)+(AJ14)-AD14) -> 0 | AY14: =IF(AE14=0,AK14,(1*100000*12)+(AK14)-AE14) -> 0 | AZ14: =SUM(AV14:AY14)-BF14+Z14-F14+BH14+BI14+BJ14+BK14+BL14+BM14 -> 0 | BD14: =IF(AZ14=0,(AZ14-BA14-BC14),(AZ14-BA14-BB14-BC14)) -> 0 | BF14: =Z14*1/100*BG14 -> 0 | BG14: 11 | BN14: CONFECTION CACHET | BO14: FONDS DE ROULEMENT
A15: AS201611 | B15: =VLOOKUP(A15,[11]LISTADHERENT!A$5:H$50,3,0) -> HENGUE PAUL OMER | C15: =D15+E15+F15-U15-BB15 -> 0 | D15: =VLOOKUP(A15,[12]HISTOBQUEAVRIL24!$A$6:$G$46,3,0) -> 0 | E15: =VLOOKUP(A15,[12]HISTOBQUEAVRIL24!$A$6:$G$41,4,0) -> 0 | F15: =VLOOKUP(A15,[12]HISTOBQUEAVRIL24!$A$6:$G$41,5,0) -> 0 | G15: =IF(H15="ESPECES",3000,0) -> 0 | H15: =IF($D15<>0,"BANQUE",IF($E15<>0,"ESPECES","ECHEC")) -> ECHEC | J15: 1 | K15: =IF($D15<>0,J15*50000,IF($E15<>0,J15*50000,0)) -> 0 | L15: 1 | M15: =IF($D15<>0,L15*75000,IF($E15<>0,L15*75000,0)) -> 0 | O15: =IF($D15<>0,N15*100000,IF($E15<>0,N15*100000,0)) -> 0 | P15: =VLOOKUP(A15,[14]TONTDEC24!$A$6:$R$39,12,0) -> 0 | Q15: =VLOOKUP(A15,[15]TONTDEC24!$A$7:$P$23,10,0) -> 0 | U15: =G15+S15++R15+P15+O15+M15+I15+K15+Q15+V15+W15 -> 0 | AQ15: =IF(H15="ECHEC",((K15+M15+O15)*20/100),0) -> 0 | AR15: =IF(H15="ECHEC",((K15+M15+O15)*20/100),0) -> 0 | AS15: =IF(H15="ECHEC",0,(K15+I15-25000)) -> 0 | AW15: =IF(AC15=0,AI15,(1*25000*12)+AI15-AC15) -> 0 | AX15: =IF(AD15=0,AJ15,(1*75000*12)+(AJ15)-AD15) -> 0 | AY15: =IF(AE15=0,AK15,(1*100000*12)+(AK15)-AE15) -> 0 | AZ15: =SUM(AV15:AY15)-BF15+Z15-F15+BH15+BI15+BJ15+BK15+BL15+BM15 -> 0 | BD15: =IF(AZ15=0,(AZ15-BA15-BC15),(AZ15-BA15-BB15-BC15)) -> 0 | BF15: =Z15*1/100*BG15 -> 0 | BG15: 11
A16: AS201613 | B16: =VLOOKUP(A16,[11]LISTADHERENT!A$5:H$50,3,0) -> HOTCHO BENJAMIN | C16: =D16+E16+F16-U16-BB16 -> 0 | D16: =VLOOKUP(A16,[12]HISTOBQUEAVRIL24!$A$6:$G$46,3,0) -> 0 | E16: =VLOOKUP(A16,[12]HISTOBQUEAVRIL24!$A$6:$G$41,4,0) -> 0 | F16: =VLOOKUP(A16,[12]HISTOBQUEAVRIL24!$A$6:$G$41,5,0) -> 0 | G16: =IF(H16="ESPECES",3000,0) -> 0 | H16: =IF($D16<>0,"BANQUE",IF($E16<>0,"ESPECES","ECHEC")) -> ECHEC | J16: 1 | K16: =IF($D16<>0,J16*50000,IF($E16<>0,J16*50000,0)) -> 0 | L16: 1 | M16: =IF($D16<>0,L16*75000,IF($E16<>0,L16*75000,0)) -> 0 | N16: 1 | O16: =IF($D16<>0,N16*100000,IF($E16<>0,N16*100000,0)) -> 0 | P16: =VLOOKUP(A16,[14]TONTDEC24!$A$6:$R$39,12,0) -> 0 | Q16: =VLOOKUP(A16,[15]TONTDEC24!$A$7:$P$23,10,0) -> 0 | R16: =VLOOKUP(A16,[16]TONTFEV24!$A$7:$P$20,10,0) -> 0 | U16: =G16+S16++R16+P16+O16+M16+I16+K16+Q16+V16+W16 -> 0 | AQ16: =IF(H16="ECHEC",((K16+M16+O16)*20/100),0) -> 0 | AR16: =IF(H16="ECHEC",((K16+M16+O16)*20/100),0) -> 0 | AS16: =IF(H16="ECHEC",0,(K16+I16-25000)) -> 0 | AW16: =IF(AC16=0,AI16,(1*25000*12)+AI16-AC16) -> 0 | AX16: =IF(AD16=0,AJ16,(1*75000*12)+(AJ16)-AD16) -> 0 | AY16: =IF(AE16=0,AK16,(1*100000*12)+(AK16)-AE16) -> 0 | AZ16: =SUM(AV16:AY16)-BF16+Z16-F16+BH16+BI16+BJ16+BK16+BL16+BM16 -> 0 | BD16: =IF(AZ16=0,(AZ16-BA16-BC16),(AZ16-BA16-BB16-BC16)) -> 0 | BF16: =Z16*1/100*BG16 -> 0 | BG16: 11 | BN16: S/TOTAL | BP16: =SUM(BP6:BP15) -> 0
A17: AS201617 | B17: =VLOOKUP(A17,[11]LISTADHERENT!A$5:H$50,3,0) -> KOUAMOU MOISE | C17: =D17+E17+F17-U17-BB17 -> 0 | D17: =VLOOKUP(A17,[12]HISTOBQUEAVRIL24!$A$6:$G$46,3,0) -> 0 | E17: =VLOOKUP(A17,[12]HISTOBQUEAVRIL24!$A$6:$G$41,4,0) -> 0 | F17: =VLOOKUP(A17,[12]HISTOBQUEAVRIL24!$A$6:$G$41,5,0) -> 0 | G17: =IF(H17="ESPECES",3000,0) -> 0 | H17: =IF($D17<>0,"BANQUE",IF($E17<>0,"ESPECES","ECHEC")) -> ECHEC | J17: 1 | K17: =IF($D17<>0,J17*50000,IF($E17<>0,J17*50000,0)) -> 0 | M17: =IF($D17<>0,L17*75000,IF($E17<>0,L17*75000,0)) -> 0 | N17: 1 | O17: =IF($D17<>0,N17*100000,IF($E17<>0,N17*100000,0)) -> 0 | P17: =VLOOKUP(A17,[14]TONTDEC24!$A$6:$R$39,12,0) -> 0 | R17: =VLOOKUP(A17,[16]TONTDEC24!$A$7:$P$20,10,0) -> 0 | U17: =G17+S17++R17+P17+O17+M17+I17+K17+Q17+V17+W17 -> 0 | AQ17: =IF(H17="ECHEC",((K17+M17+O17)*20/100),0) -> 0 | AR17: =IF(H17="ECHEC",((K17+M17+O17)*20/100),0) -> 0 | AS17: =IF(H17="ECHEC",0,(K17+I17-25000)) -> 0 | AW17: =IF(AC17=0,AI17,(1*25000*12)+AI17-AC17) -> 0 | AX17: =IF(AD17=0,AJ17,(1*75000*12)+(AJ17)-AD17) -> 0 | AY17: =IF(AE17=0,AK17,(1*100000*12)+(AK17)-AE17) -> 0 | AZ17: =SUM(AV17:AY17)-BF17+Z17-F17+BH17+BI17+BJ17+BK17+BL17+BM17 -> 0 | BD17: =IF(AZ17=0,(AZ17-BA17-BC17),(AZ17-BA17-BB17-BC17)) -> 0 | BF17: =Z17*1/100*BG17 -> 0 | BG17: 11
A18: AS201619 | B18: =VLOOKUP(A18,[11]LISTADHERENT!A$5:H$50,3,0) -> KOUATCHO MESSACK | C18: =D18+E18+F18-U18-BB18 -> 0 | D18: =VLOOKUP(A18,[12]HISTOBQUEAVRIL24!$A$6:$G$46,3,0) -> 0 | E18: =VLOOKUP(A18,[12]HISTOBQUEAVRIL24!$A$6:$G$41,4,0) -> 0 | F18: =VLOOKUP(A18,[12]HISTOBQUEAVRIL24!$A$6:$G$41,5,0) -> 0 | G18: =IF(H18="ESPECES",3000,0) -> 0 | H18: =IF($D18<>0,"BANQUE",IF($E18<>0,"ESPECES","ECHEC")) -> ECHEC | J18: 1 | K18: =IF($D18<>0,J18*50000,IF($E18<>0,J18*50000,0)) -> 0 | M18: =IF($D18<>0,L18*75000,IF($E18<>0,L18*75000,0)) -> 0 | N18: 1 | O18: =IF($D18<>0,N18*100000,IF($E18<>0,N18*100000,0)) -> 0 | P18: =VLOOKUP(A18,[14]TONTDEC24!$A$6:$R$39,12,0) -> 0 | R18: =VLOOKUP(A18,[16]TONTDEC24!$A$7:$P$20,10,0) -> 0 | U18: =G18+S18++R18+P18+O18+M18+I18+K18+Q18+V18+W18 -> 0 | AQ18: =IF(H18="ECHEC",((K18+M18+O18)*20/100),0) -> 0 | AR18: =IF(H18="ECHEC",((K18+M18+O18)*20/100),0) -> 0 | AS18: =IF(H18="ECHEC",0,(K18+I18-25000)) -> 0 | AW18: =IF(AC18=0,AI18,(1*25000*12)+AI18-AC18) -> 0 | AX18: =IF(AD18=0,AJ18,(1*75000*12)+(AJ18)-AD18) -> 0 | AY18: =IF(AE18=0,AK18,(1*100000*12)+(AK18)-AE18) -> 0 | AZ18: =SUM(AV18:AY18)-BF18+Z18-F18+BH18+BI18+BJ18+BK18+BL18+BM18 -> 0 | BD18: =IF(AZ18=0,(AZ18-BA18-BC18),(AZ18-BA18-BB18-BC18)) -> 0 | BF18: =Z18*1/100*BG18 -> 0 | BG18: 11 | BN18: GRATIFICATION BUREAU 2021 | BO18: PENALITE VERSEMENT ESPECES
A19: AS201661 | B19: =VLOOKUP(A19,[11]LISTADHERENT!A$5:H$50,3,0) -> MASSEUNGOUE DAGOBERT | C19: =D19+E19+F19-U19-BB19 -> 0 | D19: =VLOOKUP(A19,[12]HISTOBQUEAVRIL24!$A$6:$G$46,3,0) -> 0 | E19: =VLOOKUP(A19,[12]HISTOBQUEAVRIL24!$A$6:$G$41,4,0) -> 0 | F19: =VLOOKUP(A19,[12]HISTOBQUEAVRIL24!$A$6:$G$41,5,0) -> 0 | G19: =IF(H19="ESPECES",3000,0) -> 0 | H19: =IF($D19<>0,"BANQUE",IF($E19<>0,"ESPECES","ECHEC")) -> ECHEC | J19: 1 | K19: =IF($D19<>0,J19*50000,IF($E19<>0,J19*50000,0)) -> 0 | M19: =IF($D19<>0,L19*75000,IF($E19<>0,L19*75000,0)) -> 0 | O19: =IF($D19<>0,N19*100000,IF($E19<>0,N19*100000,0)) -> 0 | P19: =VLOOKUP(A19,[14]TONTDEC24!$A$6:$R$39,12,0) -> 0 | U19: =G19+S19++R19+P19+O19+M19+I19+K19+Q19+V19+W19 -> 0 | AQ19: =IF(H19="ECHEC",((K19+M19+O19)*20/100),0) -> 0 | AR19: =IF(H19="ECHEC",((K19+M19+O19)*20/100),0) -> 0 | AS19: =IF(H19="ECHEC",0,(K19+I19-25000)) -> 0 | AW19: =IF(AC19=0,AI19,(1*25000*12)+AI19-AC19) -> 0 | AX19: =IF(AD19=0,AJ19,(1*75000*12)+(AJ19)-AD19) -> 0 | AY19: =IF(AE19=0,AK19,(1*100000*12)+(AK19)-AE19) -> 0 | AZ19: =SUM(AV19:AY19)-BF19+Z19-F19+BH19+BI19+BJ19+BK19+BL19+BM19 -> 0 | BD19: =IF(AZ19=0,(AZ19-BA19-BC19),(AZ19-BA19-BB19-BC19)) -> 0 | BF19: =Z19*1/100*BG19 -> 0 | BG19: 11
A20: AS201649 | B20: =VLOOKUP(A20,[11]LISTADHERENT!A$5:H$50,3,0) -> MBOGNING TUGMA GUY | C20: =D20+E20+F20-U20-BB20 -> 0 | D20: =VLOOKUP(A20,[12]HISTOBQUEAVRIL24!$A$6:$G$46,3,0) -> 0 | E20: =VLOOKUP(A20,[12]HISTOBQUEAVRIL24!$A$6:$G$41,4,0) -> 0 | F20: =VLOOKUP(A20,[12]HISTOBQUEAVRIL24!$A$6:$G$41,5,0) -> 0 | G20: =IF(H20="ESPECES",3000,0) -> 0 | H20: =IF($D20<>0,"BANQUE",IF($E20<>0,"ESPECES","ECHEC")) -> ECHEC | J20: 1 | K20: =IF($D20<>0,J20*50000,IF($E20<>0,J20*50000,0)) -> 0 | L20: 1 | M20: =IF($D20<>0,L20*75000,IF($E20<>0,L20*75000,0)) -> 0 | N20: 1 | O20: =IF($D20<>0,N20*100000,IF($E20<>0,N20*100000,0)) -> 0 | P20: =VLOOKUP(A20,[14]TONTDEC24!$A$6:$R$39,12,0) -> 0 | Q20: =VLOOKUP(A20,[15]TONTDEC24!$A$7:$P$23,10,0) -> 0 | R20: =VLOOKUP(A20,[16]TONTDEC24!$A$7:$P$20,10,0) -> 0 | U20: =G20+S20++R20+P20+O20+M20+I20+K20+Q20+V20+W20 -> 0 | AQ20: =IF(H20="ECHEC",((K20+M20+O20)*20/100),0) -> 0 | AR20: =IF(H20="ECHEC",((K20+M20+O20)*20/100),0) -> 0 | AS20: =IF(H20="ECHEC",0,(K20+I20-25000)) -> 0 | AW20: =IF(AC20=0,AI20,(1*25000*12)+AI20-AC20) -> 0 | AX20: =IF(AD20=0,AJ20,(1*75000*12)+(AJ20)-AD20) -> 0 | AY20: =IF(AE20=0,AK20,(1*100000*12)+(AK20)-AE20) -> 0 | AZ20: =SUM(AV20:AY20)-BF20+Z20-F20+BH20+BI20+BJ20+BK20+BL20+BM20 -> 0 | BD20: =IF(AZ20=0,(AZ20-BA20-BC20),(AZ20-BA20-BB20-BC20)) -> 0 | BF20: =Z20*1/100*BG20 -> 0 | BG20: 11
A21: AS201639 | B21: =VLOOKUP(A21,[11]LISTADHERENT!A$5:H$50,3,0) -> NANGUEN MARTIN | C21: =D21+E21+F21-U21-BB21 -> 0 | D21: =VLOOKUP(A21,[12]HISTOBQUEAVRIL24!$A$6:$G$46,3,0) -> 0 | E21: =VLOOKUP(A21,[12]HISTOBQUEAVRIL24!$A$6:$G$41,4,0) -> 0 | F21: =VLOOKUP(A21,[12]HISTOBQUEAVRIL24!$A$6:$G$41,5,0) -> 0 | G21: =IF(H21="ESPECES",3000,0) -> 0 | H21: =IF($D21<>0,"BANQUE",IF($E21<>0,"ESPECES","ECHEC")) -> ECHEC | J21: 1 | K21: =IF($D21<>0,J21*50000,IF($E21<>0,J21*50000,0)) -> 0 | M21: =IF($D21<>0,L21*75000,IF($E21<>0,L21*75000,0)) -> 0 | O21: =IF($D21<>0,N21*100000,IF($E21<>0,N21*100000,0)) -> 0 | P21: =VLOOKUP(A21,[14]TONTDEC24!$A$6:$R$39,12,0) -> 0 | U21: =G21+S21++R21+P21+O21+M21+I21+K21+Q21+V21+W21 -> 0 | AQ21: =IF(H21="ECHEC",((K21+M21+O21)*20/100),0) -> 0 | AR21: =IF(H21="ECHEC",((K21+M21+O21)*20/100),0) -> 0 | AS21: =IF(H21="ECHEC",0,(K21+I21-25000)) -> 0 | AW21: =IF(AC21=0,AI21,(1*25000*12)+AI21-AC21) -> 0 | AX21: =IF(AD21=0,AJ21,(1*75000*12)+(AJ21)-AD21) -> 0 | AY21: =IF(AE21=0,AK21,(1*100000*12)+(AK21)-AE21) -> 0 | AZ21: =SUM(AV21:AY21)-BF21+Z21-F21+BH21+BI21+BJ21+BK21+BL21+BM21 -> 0 | BD21: =IF(AZ21=0,(AZ21-BA21-BC21),(AZ21-BA21-BB21-BC21)) -> 0 | BF21: =Z21*1/100*BG21 -> 0 | BG21: 11
A22: AS201621 | B22: =VLOOKUP(A22,[11]LISTADHERENT!A$5:H$50,3,0) -> NANKAM APPOLINAIRE | C22: =D22+E22+F22-U22-BB22 -> 0 | D22: =VLOOKUP(A22,[12]HISTOBQUEAVRIL24!$A$6:$G$46,3,0) -> 0 | E22: =VLOOKUP(A22,[12]HISTOBQUEAVRIL24!$A$6:$G$41,4,0) -> 0 | F22: =VLOOKUP(A22,[12]HISTOBQUEAVRIL24!$A$6:$G$41,5,0) -> 0 | G22: =IF(H22="ESPECES",3000,0) -> 0 | H22: =IF($D22<>0,"BANQUE",IF($E22<>0,"ESPECES","ECHEC")) -> ECHEC | J22: 1 | K22: =IF($D22<>0,J22*50000,IF($E22<>0,J22*50000,0)) -> 0 | L22: 1 | M22: =IF($D22<>0,L22*75000,IF($E22<>0,L22*75000,0)) -> 0 | O22: =IF($D22<>0,N22*100000,IF($E22<>0,N22*100000,0)) -> 0 | P22: =VLOOKUP(A22,[14]TONTDEC24!$A$6:$R$39,12,0) -> 0 | Q22: =VLOOKUP(A22,[15]TONTDEC24!$A$7:$P$23,10,0) -> 0 | U22: =G22+S22++R22+P22+O22+M22+I22+K22+Q22+V22+W22 -> 0 | AQ22: =IF(H22="ECHEC",((K22+M22+O22)*20/100),0) -> 0 | AR22: =IF(H22="ECHEC",((K22+M22+O22)*20/100),0) -> 0 | AS22: =IF(H22="ECHEC",0,(K22+I22-25000)) -> 0 | AW22: =IF(AC22=0,AI22,(1*25000*12)+AI22-AC22) -> 0 | AX22: =IF(AD22=0,AJ22,(1*75000*12)+(AJ22)-AD22) -> 0 | AY22: =IF(AE22=0,AK22,(1*100000*12)+(AK22)-AE22) -> 0 | AZ22: =SUM(AV22:AY22)-BF22+Z22-F22+BH22+BI22+BJ22+BK22+BL22+BM22 -> 0 | BD22: =IF(AZ22=0,(AZ22-BA22-BC22),(AZ22-BA22-BB22-BC22)) -> 0 | BF22: =Z22*1/100*BG22 -> 0 | BG22: 11 | BN22: S/TOTAL | BP22: =SUM(BP18:BP21) -> 0
A23: AS201622 | B23: =VLOOKUP(A23,[11]LISTADHERENT!A$5:H$50,3,0) -> NDJOMO ETIENNE | C23: =D23+E23+F23-U23-BB23 -> 0 | D23: =VLOOKUP(A23,[12]HISTOBQUEAVRIL24!$A$6:$G$46,3,0) -> 0 | E23: =VLOOKUP(A23,[12]HISTOBQUEAVRIL24!$A$6:$G$41,4,0) -> 0 | F23: =VLOOKUP(A23,[12]HISTOBQUEAVRIL24!$A$6:$G$41,5,0) -> 0 | G23: =IF(H23="ESPECES",3000,0) -> 0 | H23: =IF($D23<>0,"BANQUE",IF($E23<>0,"ESPECES","ECHEC")) -> ECHEC | J23: 1 | K23: =IF($D23<>0,J23*50000,IF($E23<>0,J23*50000,0)) -> 0 | M23: =IF($D23<>0,L23*75000,IF($E23<>0,L23*75000,0)) -> 0 | N23: 2 | O23: =IF($D23<>0,N23*100000,IF($E23<>0,N23*100000,0)) -> 0 | P23: =VLOOKUP(A23,[14]TONTDEC24!$A$6:$R$39,12,0) -> 0 | R23: =VLOOKUP(A23,[16]TONTDEC24!$A$7:$P$20,10,0) -> 0 | U23: =G23+S23++R23+P23+O23+M23+I23+K23+Q23+V23+W23 -> 0 | AQ23: =IF(H23="ECHEC",((K23+M23+O23)*20/100),0) -> 0 | AR23: =IF(H23="ECHEC",((K23+M23+O23)*20/100),0) -> 0 | AS23: =IF(H23="ECHEC",0,(K23+I23-25000)) -> 0 | AW23: =IF(AC23=0,AI23,(1*25000*12)+AI23-AC23) -> 0 | AX23: =IF(AD23=0,AJ23,(1*75000*12)+(AJ23)-AD23) -> 0 | AY23: =IF(AE23=0,AK23,(1*100000*12)+(AK23)-AE23) -> 0 | AZ23: =SUM(AV23:AY23)-BF23+Z23-F23+BH23+BI23+BJ23+BK23+BL23+BM23 -> 0 | BD23: =IF(AZ23=0,(AZ23-BA23-BC23),(AZ23-BA23-BB23-BC23)) -> 0 | BF23: =Z23*1/100*BG23 -> 0 | BG23: 11
A24: AS201624 | B24: =VLOOKUP(A24,[11]LISTADHERENT!A$5:H$50,3,0) -> NGONDIEP CLAUDE | C24: =D24+E24+F24-U24-BB24 -> 0 | D24: =VLOOKUP(A24,[12]HISTOBQUEAVRIL24!$A$6:$G$46,3,0) -> 0 | E24: =VLOOKUP(A24,[12]HISTOBQUEAVRIL24!$A$6:$G$41,4,0) -> 0 | F24: =VLOOKUP(A24,[12]HISTOBQUEAVRIL24!$A$6:$G$41,5,0) -> 0 | G24: =IF(H24="ESPECES",3000,0) -> 0 | H24: =IF($D24<>0,"BANQUE",IF($E24<>0,"ESPECES","ECHEC")) -> ECHEC | J24: 1 | K24: =IF($D24<>0,J24*50000,IF($E24<>0,J24*50000,0)) -> 0 | L24: 1 | M24: =IF($D24<>0,L24*75000,IF($E24<>0,L24*75000,0)) -> 0 | N24: 1 | O24: =IF($D24<>0,N24*100000,IF($E24<>0,N24*100000,0)) -> 0 | P24: =VLOOKUP(A24,[14]TONTDEC24!$A$6:$R$39,12,0) -> 0 | Q24: =VLOOKUP(A24,[15]TONTDEC24!$A$7:$P$23,10,0) -> 0 | R24: =VLOOKUP(A24,[16]TONTDEC24!$A$7:$P$20,10,0) -> 0 | U24: =G24+S24++R24+P24+O24+M24+I24+K24+Q24+V24+W24 -> 0 | AQ24: =IF(H24="ECHEC",((K24+M24+O24)*20/100),0) -> 0 | AR24: =IF(H24="ECHEC",((K24+M24+O24)*20/100),0) -> 0 | AS24: =IF(H24="ECHEC",0,(K24+I24-25000)) -> 0 | AW24: =IF(AC24=0,AI24,(1*25000*12)+AI24-AC24) -> 0 | AX24: =IF(AD24=0,AJ24,(1*75000*12)+(AJ24)-AD24) -> 0 | AY24: =IF(AE24=0,AK24,(1*100000*12)+(AK24)-AE24) -> 0 | AZ24: =SUM(AV24:AY24)-BF24+Z24-F24+BH24+BI24+BJ24+BK24+BL24+BM24 -> 0 | BD24: =IF(AZ24=0,(AZ24-BA24-BC24),(AZ24-BA24-BB24-BC24)) -> 0 | BF24: =Z24*1/100*BG24 -> 0 | BG24: 11 | BN24: GRATIFICATION BUREAU 2021 | BO24: FRAIS EXEPTIONNEL
A25: AS201626 | B25: =VLOOKUP(A25,[11]LISTADHERENT!A$5:H$50,3,0) -> NGUIEMEGNI MATHIEU BLAISE | C25: =D25+E25+F25-U25-BB25 -> 0 | D25: =VLOOKUP(A25,[12]HISTOBQUEAVRIL24!$A$6:$G$46,3,0) -> 0 | E25: =VLOOKUP(A25,[12]HISTOBQUEAVRIL24!$A$6:$G$41,4,0) -> 0 | F25: =VLOOKUP(A25,[12]HISTOBQUEAVRIL24!$A$6:$G$41,5,0) -> 0 | G25: =IF(H25="ESPECES",3000,0) -> 0 | H25: =IF($D25<>0,"BANQUE",IF($E25<>0,"ESPECES","ECHEC")) -> ECHEC | J25: 1 | K25: =IF($D25<>0,J25*50000,IF($E25<>0,J25*50000,0)) -> 0 | L25: 3 | M25: =IF($D25<>0,L25*75000,IF($E25<>0,L25*75000,0)) -> 0 | N25: 1 | O25: =IF($D25<>0,N25*100000,IF($E25<>0,N25*100000,0)) -> 0 | P25: =VLOOKUP(A25,[14]TONTDEC24!$A$6:$R$39,12,0) -> 0 | Q25: =VLOOKUP(A25,[15]TONTDEC24!$A$7:$P$23,10,0) -> 0 | R25: =VLOOKUP(A25,[16]TONTDEC24!$A$7:$P$20,10,0) -> 0 | U25: =G25+S25++R25+P25+O25+M25+I25+K25+Q25+V25+W25 -> 0 | AQ25: =IF(H25="ECHEC",((K25+M25+O25)*20/100),0) -> 0 | AR25: =IF(H25="ECHEC",((K25+M25+O25)*20/100),0) -> 0 | AS25: =IF(H25="ECHEC",0,(K25+I25-25000)) -> 0 | AW25: =IF(AC25=0,AI25,(1*25000*12)+AI25-AC25) -> 0 | AX25: =IF(AD25=0,AJ25,(1*75000*12)+(AJ25)-AD25) -> 0 | AY25: =IF(AE25=0,AK25,(1*100000*12)+(AK25)-AE25) -> 0 | AZ25: =SUM(AV25:AY25)-BF25+Z25-F25+BH25+BI25+BJ25+BK25+BL25+BM25 -> 0 | BD25: =IF(AZ25=0,(AZ25-BA25-BC25),(AZ25-BA25-BB25-BC25)) -> 0 | BF25: =Z25*1/100*BG25 -> 0 | BG25: 11 | BN25: DEVELOPPEMENT LAGWEU | BO25: FRAIS EXEPTIONNEL
A26: AS201628 | B26: =VLOOKUP(A26,[11]LISTADHERENT!A$5:H$50,3,0) -> NKAMGANG JUSTIN DEJOLIE | C26: =D26+E26+F26-U26-BB26 -> 0 | D26: =VLOOKUP(A26,[12]HISTOBQUEAVRIL24!$A$6:$G$46,3,0) -> 0 | E26: =VLOOKUP(A26,[12]HISTOBQUEAVRIL24!$A$6:$G$41,4,0) -> 0 | F26: =VLOOKUP(A26,[12]HISTOBQUEAVRIL24!$A$6:$G$41,5,0) -> 0 | G26: =IF(H26="ESPECES",3000,0) -> 0 | H26: =IF($D26<>0,"BANQUE",IF($E26<>0,"ESPECES","ECHEC")) -> ECHEC | J26: 1 | K26: =IF($D26<>0,J26*50000,IF($E26<>0,J26*50000,0)) -> 0 | M26: =IF($D26<>0,L26*75000,IF($E26<>0,L26*75000,0)) -> 0 | O26: =IF($D26<>0,N26*100000,IF($E26<>0,N26*100000,0)) -> 0 | P26: =VLOOKUP(A26,[14]TONTDEC24!$A$6:$R$39,12,0) -> 0 | U26: =G26+S26++R26+P26+O26+M26+I26+K26+Q26+V26+W26 -> 0 | AQ26: =IF(H26="ECHEC",((K26+M26+O26)*20/100),0) -> 0 | AR26: =IF(H26="ECHEC",((K26+M26+O26)*20/100),0) -> 0 | AS26: =IF(H26="ECHEC",0,(K26+I26-25000)) -> 0 | AW26: =IF(AC26=0,AI26,(1*25000*12)+AI26-AC26) -> 0 | AX26: =IF(AD26=0,AJ26,(1*75000*12)+(AJ26)-AD26) -> 0 | AY26: =IF(AE26=0,AK26,(1*100000*12)+(AK26)-AE26) -> 0 | AZ26: =SUM(AV26:AY26)-BF26+Z26-F26+BH26+BI26+BJ26+BK26+BL26+BM26 -> 0 | BD26: =IF(AZ26=0,(AZ26-BA26-BC26),(AZ26-BA26-BB26-BC26)) -> 0 | BF26: =Z26*1/100*BG26 -> 0 | BG26: 11 | BN26: DEUIL TCHEMNOU EMMANUEL | BO26: FRAIS EXEPTIONNEL
A27: AS201656 | B27: =VLOOKUP(A27,[11]LISTADHERENT!A$5:H$50,3,0) -> NOUBE ETIENNE | C27: =D27+E27+F27-U27-BB27 -> 0 | D27: =VLOOKUP(A27,[12]HISTOBQUEAVRIL24!$A$6:$G$46,3,0) -> 0 | E27: =VLOOKUP(A27,[12]HISTOBQUEAVRIL24!$A$6:$G$41,4,0) -> 0 | F27: =VLOOKUP(A27,[12]HISTOBQUEAVRIL24!$A$6:$G$41,5,0) -> 0 | G27: =IF(H27="ESPECES",3000,0) -> 0 | H27: =IF($D27<>0,"BANQUE",IF($E27<>0,"ESPECES","ECHEC")) -> ECHEC | J27: 1 | K27: =IF($D27<>0,J27*50000,IF($E27<>0,J27*50000,0)) -> 0 | M27: =IF($D27<>0,L27*75000,IF($E27<>0,L27*75000,0)) -> 0 | O27: =IF($D27<>0,N27*100000,IF($E27<>0,N27*100000,0)) -> 0 | P27: =VLOOKUP(A27,[14]TONTDEC24!$A$6:$R$39,12,0) -> 0 | U27: =G27+S27++R27+P27+O27+M27+I27+K27+Q27+V27+W27 -> 0 | AQ27: =IF(H27="ECHEC",((K27+M27+O27)*20/100),0) -> 0 | AR27: =IF(H27="ECHEC",((K27+M27+O27)*20/100),0) -> 0 | AS27: =IF(H27="ECHEC",0,(K27+I27-25000)) -> 0 | AW27: =IF(AC27=0,AI27,(1*25000*12)+AI27-AC27) -> 0 | AX27: =IF(AD27=0,AJ27,(1*75000*12)+(AJ27)-AD27) -> 0 | AY27: =IF(AE27=0,AK27,(1*100000*12)+(AK27)-AE27) -> 0 | AZ27: =SUM(AV27:AY27)-BF27+Z27-F27+BH27+BI27+BJ27+BK27+BL27+BM27 -> 0 | BD27: =IF(AZ27=0,(AZ27-BA27-BC27),(AZ27-BA27-BB27-BC27)) -> 0 | BF27: =Z27*1/100*BG27 -> 0 | BG27: 3
A28: AS201633 | B28: =VLOOKUP(A28,[11]LISTADHERENT!A$5:H$50,3,0) -> PATEGO NJOSSU GUSTAVE | C28: =D28+E28+F28-U28-BB28 -> 0 | D28: =VLOOKUP(A28,[12]HISTOBQUEAVRIL24!$A$6:$G$46,3,0) -> 0 | E28: =VLOOKUP(A28,[12]HISTOBQUEAVRIL24!$A$6:$G$41,4,0) -> 0 | F28: =VLOOKUP(A28,[12]HISTOBQUEAVRIL24!$A$6:$G$41,5,0) -> 0 | G28: =IF(H28="ESPECES",3000,0) -> 0 | H28: =IF($D28<>0,"BANQUE",IF($E28<>0,"ESPECES","ECHEC")) -> ECHEC | J28: 1 | K28: =IF($D28<>0,J28*50000,IF($E28<>0,J28*50000,0)) -> 0 | L28: 1 | M28: =IF($D28<>0,L28*75000,IF($E28<>0,L28*75000,0)) -> 0 | O28: =IF($D28<>0,N28*100000,IF($E28<>0,N28*100000,0)) -> 0 | P28: =VLOOKUP(A28,[14]TONTDEC24!$A$6:$R$39,12,0) -> 0 | Q28: =VLOOKUP(A28,[15]TONTDEC24!$A$7:$P$23,10,0) -> 0 | U28: =G28+S28++R28+P28+O28+M28+I28+K28+Q28+V28+W28 -> 0 | AQ28: =IF(H28="ECHEC",((K28+M28+O28)*20/100),0) -> 0 | AR28: =IF(H28="ECHEC",((K28+M28+O28)*20/100),0) -> 0 | AS28: =IF(H28="ECHEC",0,(K28+I28-25000)) -> 0 | AW28: =IF(AC28=0,AI28,(1*25000*12)+AI28-AC28) -> 0 | AX28: =IF(AD28=0,AJ28,(1*75000*12)+(AJ28)-AD28) -> 0 | AY28: =IF(AE28=0,AK28,(1*100000*12)+(AK28)-AE28) -> 0 | AZ28: =SUM(AV28:AY28)-BF28+Z28-F28+BH28+BI28+BJ28+BK28+BL28+BM28 -> 0 | BD28: =IF(AZ28=0,(AZ28-BA28-BC28),(AZ28-BA28-BB28-BC28)) -> 0 | BF28: =Z28*1/100*BG28 -> 0 | BG28: 11 | BN28: S/TOTAL | BP28: =SUM(BP24:BP26) -> 0
A29: AS201657 | B29: =VLOOKUP(A29,[11]LISTADHERENT!A$5:H$50,3,0) -> SEUMO POLYCARPE | C29: =D29+E29+F29-U29-BB29 -> 0 | D29: =VLOOKUP(A29,[12]HISTOBQUEAVRIL24!$A$6:$G$46,3,0) -> 0 | E29: =VLOOKUP(A29,[12]HISTOBQUEAVRIL24!$A$6:$G$41,4,0) -> 0 | F29: =VLOOKUP(A29,[12]HISTOBQUEAVRIL24!$A$6:$G$41,5,0) -> 0 | G29: =IF(H29="ESPECES",3000,0) -> 0 | H29: =IF($D29<>0,"BANQUE",IF($E29<>0,"ESPECES","ECHEC")) -> ECHEC | J29: 1 | K29: =IF($D29<>0,J29*50000,IF($E29<>0,J29*50000,0)) -> 0 | M29: =IF($D29<>0,L29*75000,IF($E29<>0,L29*75000,0)) -> 0 | O29: =IF($D29<>0,N29*100000,IF($E29<>0,N29*100000,0)) -> 0 | P29: =VLOOKUP(A29,[14]TONTDEC24!$A$6:$R$39,12,0) -> 0 | U29: =G29+S29++R29+P29+O29+M29+I29+K29+Q29+V29+W29 -> 0 | AQ29: =IF(H29="ECHEC",((K29+M29+O29)*20/100),0) -> 0 | AR29: =IF(H29="ECHEC",((K29+M29+O29)*20/100),0) -> 0 | AS29: =IF(H29="ECHEC",0,(K29+I29-25000)) -> 0 | AW29: =IF(AC29=0,AI29,(1*25000*12)+AI29-AC29) -> 0 | AX29: =IF(AD29=0,AJ29,(1*75000*12)+(AJ29)-AD29) -> 0 | AY29: =IF(AE29=0,AK29,(1*100000*12)+(AK29)-AE29) -> 0 | AZ29: =SUM(AV29:AY29)-BF29+Z29-F29+BH29+BI29+BJ29+BK29+BL29+BM29 -> 0 | BD29: =IF(AZ29=0,(AZ29-BA29-BC29),(AZ29-BA29-BB29-BC29)) -> 0 | BF29: =Z29*1/100*BG29 -> 0 | BG29: 11
A30: AS201653 | B30: =VLOOKUP(A30,[11]LISTADHERENT!A$5:H$50,3,0) -> SIME BRICE | C30: =D30+E30+F30-U30-BB30 -> 0 | D30: =VLOOKUP(A30,[12]HISTOBQUEAVRIL24!$A$6:$G$46,3,0) -> 0 | E30: =VLOOKUP(A30,[12]HISTOBQUEAVRIL24!$A$6:$G$41,4,0) -> 0 | F30: =VLOOKUP(A30,[12]HISTOBQUEAVRIL24!$A$6:$G$41,5,0) -> 0 | G30: =IF(H30="ESPECES",3000,0) -> 0 | H30: =IF($D30<>0,"BANQUE",IF($E30<>0,"ESPECES","ECHEC")) -> ECHEC | J30: 1 | K30: =IF($D30<>0,J30*50000,IF($E30<>0,J30*50000,0)) -> 0 | M30: =IF($D30<>0,L30*75000,IF($E30<>0,L30*75000,0)) -> 0 | N30: 2 | O30: =IF($D30<>0,N30*100000,IF($E30<>0,N30*100000,0)) -> 0 | P30: =VLOOKUP(A30,[14]TONTDEC24!$A$6:$R$39,12,0) -> 0 | R30: =VLOOKUP(A30,[16]TONTDEC24!$A$7:$P$20,10,0) -> 0 | U30: =G30+S30++R30+P30+O30+M30+I30+K30+Q30+V30+W30 -> 0 | AQ30: =IF(H30="ECHEC",((K30+M30+O30)*20/100),0) -> 0 | AR30: =IF(H30="ECHEC",((K30+M30+O30)*20/100),0) -> 0 | AS30: =IF(H30="ECHEC",0,(K30+I30-25000)) -> 0 | AW30: =IF(AC30=0,AI30,(1*25000*12)+AI30-AC30) -> 0 | AX30: =IF(AD30=0,AJ30,(1*75000*12)+(AJ30)-AD30) -> 0 | AY30: =IF(AE30=0,AK30,(1*100000*12)+(AK30)-AE30) -> 0 | AZ30: =SUM(AV30:AY30)-BF30+Z30-F30+BH30+BI30+BJ30+BK30+BL30+BM30 -> 0 | BD30: =IF(AZ30=0,(AZ30-BA30-BC30),(AZ30-BA30-BB30-BC30)) -> 0 | BF30: =Z30*1/100*BG30 -> 0 | BG30: 11 | BN30: DECES | BO30: MUTUELLE
A31: AS201638 | B31: =VLOOKUP(A31,[11]LISTADHERENT!A$5:H$50,3,0) -> SIMO PIERRE | C31: =D31+E31+F31-U31-BB31 -> 0 | D31: =VLOOKUP(A31,[12]HISTOBQUEAVRIL24!$A$6:$G$46,3,0) -> 0 | E31: =VLOOKUP(A31,[12]HISTOBQUEAVRIL24!$A$6:$G$41,4,0) -> 0 | F31: =VLOOKUP(A31,[12]HISTOBQUEAVRIL24!$A$6:$G$41,5,0) -> 0 | G31: =IF(H31="ESPECES",3000,0) -> 0 | H31: =IF($D31<>0,"BANQUE",IF($E31<>0,"ESPECES","ECHEC")) -> ECHEC | J31: 1 | K31: =IF($D31<>0,J31*50000,IF($E31<>0,J31*50000,0)) -> 0 | M31: =IF($D31<>0,L31*75000,IF($E31<>0,L31*75000,0)) -> 0 | N31: 1 | O31: =IF($D31<>0,N31*100000,IF($E31<>0,N31*100000,0)) -> 0 | P31: =VLOOKUP(A31,[14]TONTDEC24!$A$6:$R$39,12,0) -> 0 | R31: =VLOOKUP(A31,[16]TONTDEC24!$A$7:$P$20,10,0) -> 0 | U31: =G31+S31++R31+P31+O31+M31+I31+K31+Q31+V31+W31 -> 0 | AQ31: =IF(H31="ECHEC",((K31+M31+O31)*20/100),0) -> 0 | AR31: =IF(H31="ECHEC",((K31+M31+O31)*20/100),0) -> 0 | AS31: =IF(H31="ECHEC",0,(K31+I31-25000)) -> 0 | AW31: =IF(AC31=0,AI31,(1*25000*12)+AI31-AC31) -> 0 | AX31: =IF(AD31=0,AJ31,(1*75000*12)+(AJ31)-AD31) -> 0 | AY31: =IF(AE31=0,AK31,(1*100000*12)+(AK31)-AE31) -> 0 | AZ31: =SUM(AV31:AY31)-BF31+Z31-F31+BH31+BI31+BJ31+BK31+BL31+BM31 -> 0 | BD31: =IF(AZ31=0,(AZ31-BA31-BC31),(AZ31-BA31-BB31-BC31)) -> 0 | BF31: =Z31*1/100*BG31 -> 0 | BG31: 3 | BN31: TRANSPORT DELEGUE | BO31: MUTUELLE
A32: AS201641 | B32: =VLOOKUP(A32,[11]LISTADHERENT!A$5:H$50,3,0) -> TCHOUAMOU MATHIEU | C32: =D32+E32+F32-U32-BB32 -> 0 | D32: =VLOOKUP(A32,[12]HISTOBQUEAVRIL24!$A$6:$G$46,3,0) -> 0 | E32: =VLOOKUP(A32,[12]HISTOBQUEAVRIL24!$A$6:$G$41,4,0) -> 0 | F32: =VLOOKUP(A32,[12]HISTOBQUEAVRIL24!$A$6:$G$41,5,0) -> 0 | G32: =IF(H32="ESPECES",3000,0) -> 0 | H32: =IF($D32<>0,"BANQUE",IF($E32<>0,"ESPECES","ECHEC")) -> ECHEC | J32: 1 | K32: =IF($D32<>0,J32*50000,IF($E32<>0,J32*50000,0)) -> 0 | L32: 1 | M32: =IF($D32<>0,L32*75000,IF($E32<>0,L32*75000,0)) -> 0 | O32: =IF($D32<>0,N32*100000,IF($E32<>0,N32*100000,0)) -> 0 | P32: =VLOOKUP(A32,[14]TONTDEC24!$A$6:$R$39,12,0) -> 0 | Q32: =VLOOKUP(A32,[15]TONTDEC24!$A$7:$P$23,10,0) -> 0 | U32: =G32+S32++R32+P32+O32+M32+I32+K32+Q32+V32+W32 -> 0 | AQ32: =IF(H32="ECHEC",((K32+M32+O32)*20/100),0) -> 0 | AR32: =IF(H32="ECHEC",((K32+M32+O32)*20/100),0) -> 0 | AS32: =IF(H32="ECHEC",0,(K32+I32-25000)) -> 0 | AW32: =IF(AC32=0,AI32,(1*25000*12)+AI32-AC32) -> 0 | AX32: =IF(AD32=0,AJ32,(1*75000*12)+(AJ32)-AD32) -> 0 | AY32: =IF(AE32=0,AK32,(1*100000*12)+(AK32)-AE32) -> 0 | AZ32: =SUM(AV32:AY32)-BF32+Z32-F32+BH32+BI32+BJ32+BK32+BL32+BM32 -> 0 | BD32: =IF(AZ32=0,(AZ32-BA32-BC32),(AZ32-BA32-BB32-BC32)) -> 0 | BF32: =Z32*1/100*BG32 -> 0 | BG32: 11 | BN32: FUNERAILLE JOSUE DJOSSE
A33: AS201660 | B33: =VLOOKUP(A33,[11]LISTADHERENT!A$5:H$50,3,0) -> TCHOUATEU AUGUSTIN | C33: =D33+E33+F33-U33-BB33 -> 0 | D33: =VLOOKUP(A33,[12]HISTOBQUEAVRIL24!$A$6:$G$46,3,0) -> 0 | E33: =VLOOKUP(A33,[12]HISTOBQUEAVRIL24!$A$6:$G$41,4,0) -> 0 | F33: =VLOOKUP(A33,[12]HISTOBQUEAVRIL24!$A$6:$G$41,5,0) -> 0 | G33: =IF(H33="ESPECES",3000,0) -> 0 | H33: =IF($D33<>0,"BANQUE",IF($E33<>0,"ESPECES","ECHEC")) -> ECHEC | J33: 1 | K33: =IF($D33<>0,J33*50000,IF($E33<>0,J33*50000,0)) -> 0 | M33: =IF($D33<>0,L33*75000,IF($E33<>0,L33*75000,0)) -> 0 | N33: 1 | O33: =IF($D33<>0,N33*100000,IF($E33<>0,N33*100000,0)) -> 0 | P33: =VLOOKUP(A33,[14]TONTDEC24!$A$6:$R$39,12,0) -> 0 | R33: =VLOOKUP(A33,[16]TONTDEC24!$A$7:$P$20,10,0) -> 0 | U33: =G33+S33++R33+P33+O33+M33+I33+K33+Q33+V33+W33 -> 0 | AQ33: =IF(H33="ECHEC",((K33+M33+O33)*20/100),0) -> 0 | AR33: =IF(H33="ECHEC",((K33+M33+O33)*20/100),0) -> 0 | AS33: =IF(H33="ECHEC",0,(K33+I33-25000)) -> 0 | AW33: =IF(AC33=0,AI33,(1*25000*12)+AI33-AC33) -> 0 | AX33: =IF(AD33=0,AJ33,(1*75000*12)+(AJ33)-AD33) -> 0 | AY33: =IF(AE33=0,AK33,(1*100000*12)+(AK33)-AE33) -> 0 | AZ33: =SUM(AV33:AY33)-BF33+Z33-F33+BH33+BI33+BJ33+BK33+BL33+BM33 -> 0 | BD33: =IF(AZ33=0,(AZ33-BA33-BC33),(AZ33-BA33-BB33-BC33)) -> 0 | BF33: =Z33*1/100*BG33 -> 0 | BG33: 11 | BN33: S/TOTAL | BP33: =SUM(BP30:BP32) -> 0
A34: AS201643 | B34: =VLOOKUP(A34,[11]LISTADHERENT!A$5:H$50,3,0) -> TCHOUTOU NANA CLAUDE | C34: =D34+E34+F34-U34-BB34 -> 0 | D34: =VLOOKUP(A34,[12]HISTOBQUEAVRIL24!$A$6:$G$46,3,0) -> 0 | E34: =VLOOKUP(A34,[12]HISTOBQUEAVRIL24!$A$6:$G$41,4,0) -> 0 | F34: =VLOOKUP(A34,[12]HISTOBQUEAVRIL24!$A$6:$G$41,5,0) -> 0 | G34: =IF(H34="ESPECES",3000,0) -> 0 | H34: =IF($D34<>0,"BANQUE",IF($E34<>0,"ESPECES","ECHEC")) -> ECHEC | J34: 1 | K34: =IF($D34<>0,J34*50000,IF($E34<>0,J34*50000,0)) -> 0 | M34: =IF($D34<>0,L34*75000,IF($E34<>0,L34*75000,0)) -> 0 | O34: =IF($D34<>0,N34*100000,IF($E34<>0,N34*100000,0)) -> 0 | P34: =VLOOKUP(A34,[14]TONTDEC24!$A$6:$R$39,12,0) -> 0 | U34: =G34+S34++R34+P34+O34+M34+I34+K34+Q34+V34+W34 -> 0 | AQ34: =IF(H34="ECHEC",((K34+M34+O34)*20/100),0) -> 0 | AR34: =IF(H34="ECHEC",((K34+M34+O34)*20/100),0) -> 0 | AS34: =IF(H34="ECHEC",0,(K34+I34-25000)) -> 0 | AW34: =IF(AC34=0,AI34,(1*25000*12)+AI34-AC34) -> 0 | AX34: =IF(AD34=0,AJ34,(1*75000*12)+(AJ34)-AD34) -> 0 | AY34: =IF(AE34=0,AK34,(1*100000*12)+(AK34)-AE34) -> 0 | AZ34: =SUM(AV34:AY34)-BF34+Z34-F34+BH34+BI34+BJ34+BK34+BL34+BM34 -> 0 | BD34: =IF(AZ34=0,(AZ34-BA34-BC34),(AZ34-BA34-BB34-BC34)) -> 0 | BF34: =Z34*1/100*BG34 -> 0 | BG34: 11 | BN34: S/TOTAL | BP34: =SUM(BP31:BP33) -> 0
A35: AS201658 | B35: =VLOOKUP(A35,[11]LISTADHERENT!A$5:H$50,3,0) -> YANTCHOU GERVAIS | C35: =D35+E35+F35-U35-BB35 -> 0 | D35: =VLOOKUP(A35,[12]HISTOBQUEAVRIL24!$A$6:$G$46,3,0) -> 0 | E35: =VLOOKUP(A35,[12]HISTOBQUEAVRIL24!$A$6:$G$41,4,0) -> 0 | F35: =VLOOKUP(A35,[12]HISTOBQUEAVRIL24!$A$6:$G$41,5,0) -> 0 | G35: =IF(H35="ESPECES",3000,0) -> 0 | H35: =IF($D35<>0,"BANQUE",IF($E35<>0,"ESPECES","ECHEC")) -> ECHEC | J35: 1 | K35: =IF($D35<>0,J35*50000,IF($E35<>0,J35*50000,0)) -> 0 | M35: =IF($D35<>0,L35*75000,IF($E35<>0,L35*75000,0)) -> 0 | O35: =IF($D35<>0,N35*100000,IF($E35<>0,N35*100000,0)) -> 0 | P35: =VLOOKUP(A35,[14]TONTDEC24!$A$6:$R$39,12,0) -> 0 | U35: =G35+S35++R35+P35+O35+M35+I35+K35+Q35+V35+W35 -> 0 | AQ35: =IF(H35="ECHEC",((K35+M35+O35)*20/100),0) -> 0 | AR35: =IF(H35="ECHEC",((K35+M35+O35)*20/100),0) -> 0 | AS35: =IF(H35="ECHEC",0,(K35+I35-25000)) -> 0 | AW35: =IF(AC35=0,AI35,(1*25000*12)+AI35-AC35) -> 0 | AX35: =IF(AD35=0,AJ35,(1*75000*12)+(AJ35)-AD35) -> 0 | AY35: =IF(AE35=0,AK35,(1*100000*12)+(AK35)-AE35) -> 0 | AZ35: =SUM(AV35:AY35)-BF35+Z35-F35+BH35+BI35+BJ35+BK35+BL35+BM35 -> 0 | BD35: =IF(AZ35=0,(AZ35-BA35-BC35),(AZ35-BA35-BB35-BC35)) -> 0 | BF35: =Z35*1/100*BG35 -> 0 | BG35: 11
A36: AS201646 | B36: =VLOOKUP(A36,[11]LISTADHERENT!A$5:H$50,3,0) -> YEPMOU JEAN JACQUES | C36: =D36+E36+F36-U36-BB36 -> 0 | D36: =VLOOKUP(A36,[12]HISTOBQUEAVRIL24!$A$6:$G$46,3,0) -> 0 | E36: =VLOOKUP(A36,[12]HISTOBQUEAVRIL24!$A$6:$G$41,4,0) -> 0 | F36: =VLOOKUP(A36,[12]HISTOBQUEAVRIL24!$A$6:$G$41,5,0) -> 0 | G36: =IF(H36="ESPECES",3000,0) -> 0 | H36: =IF($D36<>0,"BANQUE",IF($E36<>0,"ESPECES","ECHEC")) -> ECHEC | J36: 1 | K36: =IF($D36<>0,J36*50000,IF($E36<>0,J36*50000,0)) -> 0 | M36: =IF($D36<>0,L36*75000,IF($E36<>0,L36*75000,0)) -> 0 | O36: =IF($D36<>0,N36*100000,IF($E36<>0,N36*100000,0)) -> 0 | P36: =VLOOKUP(A36,[14]TONTDEC24!$A$6:$R$39,12,0) -> 0 | U36: =G36+S36++R36+P36+O36+M36+I36+K36+Q36+V36+W36 -> 0 | AQ36: =IF(H36="ECHEC",((K36+M36+O36)*20/100),0) -> 0 | AR36: =IF(H36="ECHEC",((K36+M36+O36)*20/100),0) -> 0 | AS36: =IF(H36="ECHEC",0,(K36+I36-25000)) -> 0 | AW36: =IF(AC36=0,AI36,(1*25000*12)+AI36-AC36) -> 0 | AX36: =IF(AD36=0,AJ36,(1*75000*12)+(AJ36)-AD36) -> 0 | AY36: =IF(AE36=0,AK36,(1*100000*12)+(AK36)-AE36) -> 0 | AZ36: =SUM(AV36:AY36)-BF36+Z36-F36+BH36+BI36+BJ36+BK36+BL36+BM36 -> 0 | BD36: =IF(AZ36=0,(AZ36-BA36-BC36),(AZ36-BA36-BB36-BC36)) -> 0 | BF36: =Z36*1/100*BG36 -> 0 | BG36: 11 | BN36: COLLATION | BO36: COLLATION
A37: AS201659 | B37: =VLOOKUP(A37,[11]LISTADHERENT!A$5:H$50,3,0) -> YIALA ALAIN OSCAR | C37: =D37+E37+F37-U37-BB37 -> 0 | D37: =VLOOKUP(A37,[12]HISTOBQUEAVRIL24!$A$6:$G$46,3,0) -> 0 | E37: =VLOOKUP(A37,[12]HISTOBQUEAVRIL24!$A$6:$G$41,4,0) -> 0 | F37: =VLOOKUP(A37,[12]HISTOBQUEAVRIL24!$A$6:$G$41,5,0) -> 0 | G37: =IF(H37="ESPECES",3000,0) -> 0 | H37: =IF($D37<>0,"BANQUE",IF($E37<>0,"ESPECES","ECHEC")) -> ECHEC | J37: 1 | K37: =IF($D37<>0,J37*50000,IF($E37<>0,J37*50000,0)) -> 0 | M37: =IF($D37<>0,L37*75000,IF($E37<>0,L37*75000,0)) -> 0 | N37: 1 | O37: =IF($D37<>0,N37*100000,IF($E37<>0,N37*100000,0)) -> 0 | P37: =VLOOKUP(A37,[14]TONTDEC24!$A$6:$R$39,12,0) -> 0 | R37: =VLOOKUP(A37,[16]TONTDEC24!$A$7:$P$20,10,0) -> 0 | U37: =G37+S37++R37+P37+O37+M37+I37+K37+Q37+V37+W37 -> 0 | AQ37: =IF(H37="ECHEC",((K37+M37+O37)*20/100),0) -> 0 | AR37: =IF(H37="ECHEC",((K37+M37+O37)*20/100),0) -> 0 | AS37: =IF(H37="ECHEC",0,(K37+I37-25000)) -> 0 | AW37: =IF(AC37=0,AI37,(1*25000*12)+AI37-AC37) -> 0 | AX37: =IF(AD37=0,AJ37,(1*75000*12)+(AJ37)-AD37) -> 0 | AY37: =IF(AE37=0,AK37,(1*100000*12)+(AK37)-AE37) -> 0 | AZ37: =SUM(AV37:AY37)-BF37+Z37-F37+BH37+BI37+BJ37+BK37+BL37+BM37 -> 0 | BD37: =IF(AZ37=0,(AZ37-BA37-BC37),(AZ37-BA37-BB37-BC37)) -> 0 | BF37: =Z37*1/100*BG37 -> 0 | BG37: 11 | BN37: BOISSON | BO37: COLLATION
A38: AS201647 | B38: =VLOOKUP(A38,[11]LISTADHERENT!A$5:H$50,3,0) -> YOUMBI EMMANUEL | C38: =D38+E38+F38-U38-BB38 -> 0 | D38: =VLOOKUP(A38,[12]HISTOBQUEAVRIL24!$A$6:$G$46,3,0) -> 0 | E38: =VLOOKUP(A38,[12]HISTOBQUEAVRIL24!$A$6:$G$41,4,0) -> 0 | F38: =VLOOKUP(A38,[12]HISTOBQUEAVRIL24!$A$6:$G$41,5,0) -> 0 | G38: =IF(H38="ESPECES",3000,0) -> 0 | H38: =IF($D38<>0,"BANQUE",IF($E38<>0,"ESPECES","ECHEC")) -> ECHEC | J38: 1 | K38: =IF($D38<>0,J38*50000,IF($E38<>0,J38*50000,0)) -> 0 | L38: 1 | M38: =IF($D38<>0,L38*75000,IF($E38<>0,L38*75000,0)) -> 0 | O38: =IF($D38<>0,N38*100000,IF($E38<>0,N38*100000,0)) -> 0 | P38: =VLOOKUP(A38,[14]TONTDEC24!$A$6:$R$39,12,0) -> 0 | Q38: =VLOOKUP(A38,[15]TONTDEC24!$A$7:$P$23,10,0) -> 0 | U38: =G38+S38++R38+P38+O38+M38+I38+K38+Q38+V38+W38 -> 0 | AQ38: =IF(H38="ECHEC",((K38+M38+O38)*20/100),0) -> 0 | AR38: =IF(H38="ECHEC",((K38+M38+O38)*20/100),0) -> 0 | AS38: =IF(H38="ECHEC",0,(K38+I38-25000)) -> 0 | AW38: =IF(AC38=0,AI38,(1*25000*12)+AI38-AC38) -> 0 | AX38: =IF(AD38=0,AJ38,(1*75000*12)+(AJ38)-AD38) -> 0 | AY38: =IF(AE38=0,AK38,(1*100000*12)+(AK38)-AE38) -> 0 | AZ38: =SUM(AV38:AY38)-BF38+Z38-F38+BH38+BI38+BJ38+BK38+BL38+BM38 -> 0 | BD38: =IF(AZ38=0,(AZ38-BA38-BC38),(AZ38-BA38-BB38-BC38)) -> 0 | BF38: =Z38*1/100*BG38 -> 0 | BG38: 11 | BN38: BOISSON | BO38: COLLATION
B40: TOTAUX | C40: =SUM(C6:C39) -> 0 | D40: =SUM(D6:D39) -> 0 | E40: =SUM(E6:E39) -> 0 | F40: =SUM(F6:F39) -> 0 | G40: =SUM(G6:G39) -> 0 | H40: =SUM(H6:H39) -> 0 | I40: =SUM(I6:I39) -> 0 | J40: =SUM(J6:J39) -> 32 | ... S40: =SUM(S6:S39) -> 0 | U40: =SUM(U6:U39) -> 0 | V40: =SUM(V6:V39) -> 0 | W40: =SUM(W6:W39) -> 0 | X40: =SUM(X6:X39) -> 0 | Y40: =SUM(Y6:Y39) -> 0 | Z40: =SUM(Z6:Z39) -> 0 | AA40: =SUM(AA6:AA39) -> 0 | AC40: =SUM(AC6:AC39) -> 0 | AD40: =SUM(AD6:AD39) -> 0 | AE40: =SUM(AE6:AE39) -> 0 | AF40: =SUM(AF6:AF39) -> 0 | AG40: =SUM(AG6:AG39) -> 0 | AI40: =SUM(AI6:AI39) -> 0 | AJ40: =SUM(AJ6:AJ39) -> 0 | AK40: =SUM(AK6:AK39) -> 0 | AL40: =SUM(AL6:AL39) -> 0 | AM40: =SUM(AM6:AM39) -> 0 | AN40: =SUM(AN6:AN39) -> 0 | AO40: =SUM(AO6:AO39) -> 0 | AP40: =SUM(AP6:AP39) -> 0 | ... BF40: =SUM(BF6:BF39) -> 0 | BH40: =SUM(BH6:BH39) -> 0 | BI40: =SUM(BI6:BI39) -> 0 | BJ40: =SUM(BJ6:BJ39) -> 0 | BK40: =SUM(BK6:BK39) -> 0 | BL40: =SUM(BL6:BL39) -> 0 | BM40: =SUM(BM6:BM39) -> 0 | BN40: S/TOTAL | BP40: =SUM(BP36:BP38) -> 0
B43: AS201643 | BN43: TRANSPORT DELEGUE | BO43: MUTUELLE
C44: BANQUE | F44: ESPECES
B45: LIBELLE | C45: SORTIE | D45: ENTREE | E45: SOLDE | F45: ENTREE | G45: SORTIE | H45: SOLDE | BN45: S/TOTAL | BP45: =SUM(BP42:BP44) -> 0
B46: REPORT
B47: TONTINE | C47: =AZ40 -> 0 | D47: =SUMIFS(D8:D40,H8:H40,"BANQUE") -> 0 | F47: =E40 -> 0
AZ85: =SUM(AZ8:AZ84) -> 0

Sheet Sheet17
A1: ASSOCIATION | B1: ASELBY
A2: ANNEE | B2: 2024
A3: 1 | B3: 2 | C3: 3 | D3: 4 | E3: 5 | F3: 6 | G3: 7 | H3: 8 | I3: 9 | J3: 10 | K3: 11 | L3: 12 | M3: 13 | N3: 14 | O3: 15 | P3: 16 | Q3: 17 | R3: 18 | S3: 19 | T3: 20 | U3: 21 | V3: 22 | W3: 23 | X3: 24 | Y3: 25 | Z3: 26 | AA3: 27 | AB3: 28 | AC3: 29 | AD3: 30 | AE3: 31 | AF3: 32 | AG3: 33 | AH3: 34 | AI3: 35 | AJ3: 36 | AK3: 37 | AL3: 38 | AM3: 39 | AN3: 40 | AO3: 41 | AP3: 42 | AQ3: 43 | AR3: 44 | AS3: 45 | AT3: 46 | AU3: 47 | AV3: 48 | AW3: 49 | AX3: 50 | AY3: 51 | AZ3: 52 | BA3: 53 | BB3: 54 | BC3: 55 | BD3: 56 | BE3: 57 | BF3: 58 | BG3: 59 | BH3: 60 | BI3: 61 | BJ3: 62 | BK3: 63 | BL3: 64 | BM3: 65 | BN3: 66 | BO3: 67 | BP3: 68
B4: TABLEAU DE BORD SAISIE DES DONNEES
A5: MATRICULE | B5: NOM ET PRENOM | C5: BONUS MALUS | D5: HISTORIQUE BANQUE | E5: HITORIQUE ESPECES | F5: HITORIQUE TONTINE | G5: PENALITE VERSEMENT ESPECES | H5: MODE PAIEMENT TONTINE | I5: COMPLEMENT EPARGNE | J5: NBRE DE LOT | K5: TONTINE 40 000 | L5: NBRE DE LOT | M5: TONTINE 75 000 | N5: NBRE DE LOT | O5: TONTINE 100 000 | P5: REMBOURSEMENT PETIT LOT T50 | Q5: REMBOURSEMENT PETIT LOT T75 | R5: REMBOURSEMENT PETIT LOT T100 | S5: REMBOURSEMENT PRÊT FONDS | T5: MODE PAIEMENT REMBOURSEMENT PRÊT FONDS | U5: MONTANT ENGAGEMENT | V5: SANCTION | W5: INSCRIPTION | X5: EPARGNE ASSURANCE | Y5: RECONSTITUTION FONDS | Z5: PRÊT FONDS | AA5: MODE PAIEMENT PRÊT | AB5: NUM CHEQUE | AC5: ACHAT LOT PRINCIPAL T50 | AD5: ACHAT LOT PRINCIPAL T75 | AE5: ACHAT LOT PRINCIPAL T100 | AF5: MODE PAIEMENT LOT PRINCIPAL | AG5: NUM CHEQUE | AH5: PENALITE VERSEMENT ESPECES | AI5: VENTE PETIT LOT T50 | AJ5: VENTE PETIT LOT T75 | AK5: VENTE PETIT LOT T100 | AL5: INTERET PETIT LOT T50 | AM5: INTERET PETIT LOT T75 | AN5: INTERET PETIT LOT T100 | AO5: NUM CHEQUE | AP5: MODE PAIEMENT PETIT LOT | AQ5: PENELAITE RETARD TONTINE | AR5: PENELAITE ECHEC TONTINE | AS5: RESTE | AT5: MUTUELLE | AU5: REMBOURSEMENT TRANSPORT | AV5: RETRAIT PARTIEL FONDS | AW5: MONTANT T50 | AX5: MONTANT T75 | AY5: MONTANT T100 | AZ5: MONTANT CHEQUE | BA5: MONTANT ESPECES | BB5: CONTRIBUTION FOYER | BC5: AUTRES SOTIES | BD5: MONTANT CHEQUE EFFECTIF | BE5: NUMERO CHEQUE | BF5: INTERET PRÊT | BG5: NBRE MOIS | BH5: DEPENSE FONDS DE ROULEMENT | BI5: DEPENSE FRAIS EXCEPTIONNEL | BJ5: DEPENSE FONDS MUTUEL | BK5: DEPENSE COLLATION RECEPTION | BL5: PENALITE PRET FONDS | BM5: DEPENSE PENALITE VERSEMENT BANQUE | BN5: LIBELLE | BO5: COMPTE | BP5: MONTANT
A6: AS201648 | B6: =VLOOKUP(A6,[11]LISTADHERENT!A$5:H$50,3,0) -> ASELBY | D6: =HISTOJANV24!D6+HISTOFEV24!D6+HISTOMARS24!D6+HISTOAVRIL24!D6+HISTOMAI24!D6+HISTOJUIN24!D6+HISTOJUIL24!D6+HISTOAOUT24!D6+HISTOSEPT24!D6+HISTOOCT24!D6+HISTONOV24!D6+HISTODEC24!D6 -> 525000 | E6: =HISTOJANV24!E6+HISTOFEV24!E6+HISTOMARS24!E6+HISTOAVRIL24!E6+HISTOMAI24!E6+HISTOJUIN24!E6+HISTOJUIL24!E6+HISTOAOUT24!E6+HISTOSEPT24!E6+HISTOOCT24!E6+HISTONOV24!E6+HISTODEC24!E6 -> 0 | F6: =HISTOJANV24!F6+HISTOFEV24!F6+HISTOMARS24!F6+HISTOAVRIL24!F6+HISTOMAI24!F6+HISTOJUIN24!F6+HISTOJUIL24!F6+HISTOAOUT24!F6+HISTOSEPT24!F6+HISTOOCT24!F6+HISTONOV24!F6+HISTODEC24!F6 -> 0 | G6: =HISTOJANV24!G6+HISTOFEV24!G6+HISTOMARS24!G6+HISTOAVRIL24!G6+HISTOMAI24!G6+HISTOJUIN24!G6+HISTOJUIL24!G6+HISTOAOUT24!G6+HISTOSEPT24!G6+HISTOOCT24!G6+HISTONOV24!G6+HISTODEC24!G6 -> 0 | I6: =HISTOJANV24!I6+HISTOFEV24!I6+HISTOMARS24!I6+HISTOAVRIL24!I6+HISTOMAI24!I6+HISTOJUIN24!I6+HISTOJUIL24!I6+HISTOAOUT24!I6+HISTOSEPT24!I6+HISTOOCT24!I6+HISTONOV24!I6+HISTODEC24!I6 -> 0 | K6: =IF($D6<>0,J6*50000,IF($E6<>0,J6*50000,0)) -> 0 | L6: 1 | M6: =IF($D6<>0,L6*75000,IF($E6<>0,L6*75000,0)) -> 75000 | N6: 1 | O6: =IF($D6<>0,N6*100000,IF($E6<>0,N6*100000,0)) -> 100000 | P6: =HISTOJANV24!P6+HISTOFEV24!P6+HISTOMARS24!P6+HISTOAVRIL24!P6+HISTOMAI24!P6+HISTOJUIN24!P6+HISTOJUIL24!P6+HISTOAOUT24!P6+HISTOSEPT24!P6+HISTOOCT24!P6+HISTONOV24!P6+HISTODEC24!P6 -> 0 | Q6: =HISTOJANV24!Q6+HISTOFEV24!Q6+HISTOMARS24!Q6+HISTOAVRIL24!Q6+HISTOMAI24!Q6+HISTOJUIN24!Q6+HISTOJUIL24!Q6+HISTOAOUT24!Q6+HISTOSEPT24!Q6+HISTOOCT24!Q6+HISTONOV24!Q6+HISTODEC24!Q6 -> 0 | R6: =HISTOJANV24!R6+HISTOFEV24!R6+HISTOMARS24!R6+HISTOAVRIL24!R6+HISTOMAI24!R6+HISTOJUIN24!R6+HISTOJUIL24!R6+HISTOAOUT24!R6+HISTOSEPT24!R6+HISTOOCT24!R6+HISTONOV24!R6+HISTODEC24!R6 -> 0 | S6: =HISTOJANV24!S6+HISTOFEV24!S6+HISTOMARS24!S6+HISTOAVRIL24!S6+HISTOMAI24!S6+HISTOJUIN24!S6+HISTOJUIL24!S6+HISTOAOUT24!S6+HISTOSEPT24!S6+HISTOOCT24!S6+HISTONOV24!S6+HISTODEC24!S6 -> 0 | U6: =G6+S6++R6+P6+O6+M6+I6+K6+Q6+V6+W6 -> 175000 | V6: =HISTOJANV24!V6+HISTOFEV24!V6+HISTOMARS24!V6+HISTOAVRIL24!V6+HISTOMAI24!V6+HISTOJUIN24!V6+HISTOJUIL24!V6+HISTOAOUT24!V6+HISTOSEPT24!V6+HISTOOCT24!V6+HISTONOV24!V6+HISTODEC24!V6 -> 0 | W6: =HISTOJANV24!W6+HISTOFEV24!W6+HISTOMARS24!W6+HISTOAVRIL24!W6+HISTOMAI24!W6+HISTOJUIN24!W6+HISTOJUIL24!W6+HISTOAOUT24!W6+HISTOSEPT24!W6+HISTOOCT24!W6+HISTONOV24!W6+HISTODEC24!W6 -> 0 | X6: =HISTOJANV24!X6+HISTOFEV24!X6+HISTOMARS24!X6+HISTOAVRIL24!X6+HISTOMAI24!X6+HISTOJUIN24!X6+HISTOJUIL24!X6+HISTOAOUT24!X6+HISTOSEPT24!X6+HISTOOCT24!X6+HISTONOV24!X6+HISTODEC24!X6 -> 0 | Y6: =HISTOJANV24!Y6+HISTOFEV24!Y6+HISTOMARS24!Y6+HISTOAVRIL24!Y6+HISTOMAI24!Y6+HISTOJUIN24!Y6+HISTOJUIL24!Y6+HISTOAOUT24!Y6+HISTOSEPT24!Y6+HISTOOCT24!Y6+HISTONOV24!Y6+HISTODEC24!Y6 -> 0 | Z6: =HISTOJANV24!Z6+HISTOFEV24!Z6+HISTOMARS24!Z6+HISTOAVRIL24!Z6+HISTOMAI24!Z6+HISTOJUIN24!Z6+HISTOJUIL24!Z6+HISTOAOUT24!Z6+HISTOSEPT24!Z6+HISTOOCT24!Z6+HISTONOV24!Z6+HISTODEC24!Z6 -> 0 | AC6: =HISTOJANV24!AC6+HISTOFEV24!AC6+HISTOMARS24!AC6+HISTOAVRIL24!AC6+HISTOMAI24!AC6+HISTOJUIN24!AC6+HISTOJUIL24!AC6+HISTOAOUT24!AC6+HISTOSEPT24!AC6+HISTOOCT24!AC6+HISTONOV24!AC6+HISTODEC24!AC6 -> 0 | AD6: =HISTOJANV24!AD6+HISTOFEV24!AD6+HISTOMARS24!AD6+HISTOAVRIL24!AD6+HISTOMAI24!AD6+HISTOJUIN24!AD6+HISTOJUIL24!AD6+HISTOAOUT24!AD6+HISTOSEPT24!AD6+HISTOOCT24!AD6+HISTONOV24!AD6+HISTODEC24!AD6 -> 0 | AE6: =HISTOJANV24!AE6+HISTOFEV24!AE6+HISTOMARS24!AE6+HISTOAVRIL24!AE6+HISTOMAI24!AE6+HISTOJUIN24!AE6+HISTOJUIL24!AE6+HISTOAOUT24!AE6+HISTOSEPT24!AE6+HISTOOCT24!AE6+HISTONOV24!AE6+HISTODEC24!AE6 -> 0 | AH6: =HISTOJANV24!AH6+HISTOFEV24!AH6+HISTOMARS24!AH6+HISTOAVRIL24!AH6+HISTOMAI24!AH6+HISTOJUIN24!AH6+HISTOJUIL24!AH6+HISTOAOUT24!AH6+HISTOSEPT24!AH6+HISTOOCT24!AH6+HISTONOV24!AH6+HISTODEC24!AH6 -> 0 | AI6: =HISTOJANV24!AI6+HISTOFEV24!AI6+HISTOMARS24!AI6+HISTOAVRIL24!AI6+HISTOMAI24!AI6+HISTOJUIN24!AI6+HISTOJUIL24!AI6+HISTOAOUT24!AI6+HISTOSEPT24!AI6+HISTOOCT24!AI6+HISTONOV24!AI6+HISTODEC24!AI6 -> 0 | AJ6: =HISTOJANV24!AJ6+HISTOFEV24!AJ6+HISTOMARS24!AJ6+HISTOAVRIL24!AJ6+HISTOMAI24!AJ6+HISTOJUIN24!AJ6+HISTOJUIL24!AJ6+HISTOAOUT24!AJ6+HISTOSEPT24!AJ6+HISTOOCT24!AJ6+HISTONOV24!AJ6+HISTODEC24!AJ6 -> 0 | AK6: =HISTOJANV24!AK6+HISTOFEV24!AK6+HISTOMARS24!AK6+HISTOAVRIL24!AK6+HISTOMAI24!AK6+HISTOJUIN24!AK6+HISTOJUIL24!AK6+HISTOAOUT24!AK6+HISTOSEPT24!AK6+HISTOOCT24!AK6+HISTONOV24!AK6+HISTODEC24!AK6 -> 0 | AL6: =HISTOJANV24!AL6+HISTOFEV24!AL6+HISTOMARS24!AL6+HISTOAVRIL24!AL6+HISTOMAI24!AL6+HISTOJUIN24!AL6+HISTOJUIL24!AL6+HISTOAOUT24!AL6+HISTOSEPT24!AL6+HISTOOCT24!AL6+HISTONOV24!AL6+HISTODEC24!AL6 -> 0 | AM6: =HISTOJANV24!AM6+HISTOFEV24!AM6+HISTOMARS24!AM6+HISTOAVRIL24!AM6+HISTOMAI24!AM6+HISTOJUIN24!AM6+HISTOJUIL24!AM6+HISTOAOUT24!AM6+HISTOSEPT24!AM6+HISTOOCT24!AM6+HISTONOV24!AM6+HISTODEC24!AM6 -> 0 | AN6: =HISTOJANV24!AN6+HISTOFEV24!AN6+HISTOMARS24!AN6+HISTOAVRIL24!AN6+HISTOMAI24!AN6+HISTOJUIN24!AN6+HISTOJUIL24!AN6+HISTOAOUT24!AN6+HISTOSEPT24!AN6+HISTOOCT24!AN6+HISTONOV24!AN6+HISTODEC24!AN6 -> 0 | AQ6: =IF(H6="ECHEC",((K6+M6+O6)*20/100),0) -> 0 | AR6: =IF(H6="ECHEC",((K6+M6+O6)*20/100),0) -> 0 | AW6: =HISTOJANV24!AW6+HISTOFEV24!AW6+HISTOMARS24!AW6+HISTOAVRIL24!AW6+HISTOMAI24!AW6+HISTOJUIN24!AW6+HISTOJUIL24!AW6+HISTOAOUT24!AW6+HISTOSEPT24!AW6+HISTOOCT24!AW6+HISTONOV24!AW6+HISTODEC24!AW6 -> 0 | AX6: =HISTOJANV24!AX6+HISTOFEV24!AX6+HISTOMARS24!AX6+HISTOAVRIL24!AX6+HISTOMAI24!AX6+HISTOJUIN24!AX6+HISTOJUIL24!AX6+HISTOAOUT24!AX6+HISTOSEPT24!AX6+HISTOOCT24!AX6+HISTONOV24!AX6+HISTODEC24!AX6 -> 0 | AY6: =HISTOJANV24!AY6+HISTOFEV24!AY6+HISTOMARS24!AY6+HISTOAVRIL24!AY6+HISTOMAI24!AY6+HISTOJUIN24!AY6+HISTOJUIL24!AY6+HISTOAOUT24!AY6+HISTOSEPT24!AY6+HISTOOCT24!AY6+HISTONOV24!AY6+HISTODEC24!AY6 -> 0 | AZ6: =HISTOJANV24!AZ6+HISTOFEV24!AZ6+HISTOMARS24!AZ6+HISTOAVRIL24!AZ6+HISTOMAI24!AZ6+HISTOJUIN24!AZ6+HISTOJUIL24!AZ6+HISTOAOUT24!AZ6+HISTOSEPT24!AZ6+HISTOOCT24!AZ6+HISTONOV24!AZ6+HISTODEC24!AZ6 -> 1002000 | BA6: =HISTOJANV24!BA6+HISTOFEV24!BA6+HISTOMARS24!BA6+HISTOAVRIL24!BA6+HISTOMAI24!BA6+HISTOJUIN24!BA6+HISTOJUIL24!BA6+HISTOAOUT24!BA6+HISTOSEPT24!BA6+HISTOOCT24!BA6+HISTONOV24!BA6+HISTODEC24!BA6 -> 27000 | BB6: =HISTOJANV24!BB6+HISTOFEV24!BB6+HISTOMARS24!BB6+HISTOAVRIL24!BB6+HISTOMAI24!BB6+HISTOJUIN24!BB6+HISTOJUIL24!BB6+HISTOAOUT24!BB6+HISTOSEPT24!BB6+HISTOOCT24!BB6+HISTONOV24!BB6+HISTODEC24!BB6 -> 0 | BD6: =HISTOJANV24!BD6+HISTOFEV24!BD6+HISTOMARS24!BD6+HISTOAVRIL24!BD6+HISTOMAI24!BD6+HISTOJUIN24!BD6+HISTOJUIL24!BD6+HISTOAOUT24!BD6+HISTOSEPT24!BD6+HISTOOCT24!BD6+HISTONOV24!BD6+HISTODEC24!BD6 -> 975000 | BF6: =HISTOJANV24!BF6+HISTOFEV24!BF6+HISTOMARS24!BF6+HISTOAVRIL24!BF6+HISTOMAI24!BF6+HISTOJUIN24!BF6+HISTOJUIL24!BF6+HISTOAOUT24!BF6+HISTOSEPT24!BF6+HISTOOCT24!BF6+HISTONOV24!BF6+HISTODEC24!BF6 -> 0 | BH6: =HISTOJANV24!BH6+HISTOFEV24!BH6+HISTOMARS24!BH6+HISTOAVRIL24!BH6+HISTOMAI24!BH6+HISTOJUIN24!BH6+HISTOJUIL24!BH6+HISTOAOUT24!BH6+HISTOSEPT24!BH6+HISTOOCT24!BH6+HISTONOV24!BH6+HISTODEC24!BH6 -> 102000 | BI6: =HISTOJANV24!BI6+HISTOFEV24!BI6+HISTOMARS24!BI6+HISTOAVRIL24!BI6+HISTOMAI24!BI6+HISTOJUIN24!BI6+HISTOJUIL24!BI6+HISTOAOUT24!BI6+HISTOSEPT24!BI6+HISTOOCT24!BI6+HISTONOV24!BI6+HISTODEC24!BI6 -> 500000 | BJ6: =HISTOJANV24!BJ6+HISTOFEV24!BJ6+HISTOMARS24!BJ6+HISTOAVRIL24!BJ6+HISTOMAI24!BJ6+HISTOJUIN24!BJ6+HISTOJUIL24!BJ6+HISTOAOUT24!BJ6+HISTOSEPT24!BJ6+HISTOOCT24!BJ6+HISTONOV24!BJ6+HISTODEC24!BJ6 -> 100000 | BK6: =HISTOJANV24!BK6+HISTOFEV24!BK6+HISTOMARS24!BK6+HISTOAVRIL24!BK6+HISTOMAI24!BK6+HISTOJUIN24!BK6+HISTOJUIL24!BK6+HISTOAOUT24!BK6+HISTOSEPT24!BK6+HISTOOCT24!BK6+HISTONOV24!BK6+HISTODEC24!BK6 -> 300000 | BM6: =BP22 -> 0 | BN6: ACHAT FOURNITURE | BO6: FONDS DE ROULEMENT
A7: AS201601 | B7: =VLOOKUP(A7,[11]LISTADHERENT!A$5:H$50,3,0) -> BAKOP ACHILLE | D7: =HISTOJANV24!D7+HISTOFEV24!D7+HISTOMARS24!D7+HISTOAVRIL24!D7+HISTOMAI24!D7+HISTOJUIN24!D7+HISTOJUIL24!D7+HISTOAOUT24!D7+HISTOSEPT24!D7+HISTOOCT24!D7+HISTONOV24!D7+HISTODEC24!D7 -> 190000 | E7: =HISTOJANV24!E7+HISTOFEV24!E7+HISTOMARS24!E7+HISTOAVRIL24!E7+HISTOMAI24!E7+HISTOJUIN24!E7+HISTOJUIL24!E7+HISTOAOUT24!E7+HISTOSEPT24!E7+HISTOOCT24!E7+HISTONOV24!E7+HISTODEC24!E7 -> 61000 | F7: =HISTOJANV24!F7+HISTOFEV24!F7+HISTOMARS24!F7+HISTOAVRIL24!F7+HISTOMAI24!F7+HISTOJUIN24!F7+HISTOJUIL24!F7+HISTOAOUT24!F7+HISTOSEPT24!F7+HISTOOCT24!F7+HISTONOV24!F7+HISTODEC24!F7 -> 0 | G7: =HISTOJANV24!G7+HISTOFEV24!G7+HISTOMARS24!G7+HISTOAVRIL24!G7+HISTOMAI24!G7+HISTOJUIN24!G7+HISTOJUIL24!G7+HISTOAOUT24!G7+HISTOSEPT24!G7+HISTOOCT24!G7+HISTONOV24!G7+HISTODEC24!G7 -> 0 | I7: =HISTOJANV24!I7+HISTOFEV24!I7+HISTOMARS24!I7+HISTOAVRIL24!I7+HISTOMAI24!I7+HISTOJUIN24!I7+HISTOJUIL24!I7+HISTOAOUT24!I7+HISTOSEPT24!I7+HISTOOCT24!I7+HISTONOV24!I7+HISTODEC24!I7 -> 22000 | J7: 1 | K7: =IF($D7<>0,J7*50000,IF($E7<>0,J7*50000,0)) -> 50000 | M7: =IF($D7<>0,L7*75000,IF($E7<>0,L7*75000,0)) -> 0 | O7: =IF($D7<>0,N7*100000,IF($E7<>0,N7*100000,0)) -> 0 | P7: =HISTOJANV24!P7+HISTOFEV24!P7+HISTOMARS24!P7+HISTOAVRIL24!P7+HISTOMAI24!P7+HISTOJUIN24!P7+HISTOJUIL24!P7+HISTOAOUT24!P7+HISTOSEPT24!P7+HISTOOCT24!P7+HISTONOV24!P7+HISTODEC24!P7 -> 61000 | Q7: =HISTOJANV24!Q7+HISTOFEV24!Q7+HISTOMARS24!Q7+HISTOAVRIL24!Q7+HISTOMAI24!Q7+HISTOJUIN24!Q7+HISTOJUIL24!Q7+HISTOAOUT24!Q7+HISTOSEPT24!Q7+HISTOOCT24!Q7+HISTONOV24!Q7+HISTODEC24!Q7 -> 0 | R7: =HISTOJANV24!R7+HISTOFEV24!R7+HISTOMARS24!R7+HISTOAVRIL24!R7+HISTOMAI24!R7+HISTOJUIN24!R7+HISTOJUIL24!R7+HISTOAOUT24!R7+HISTOSEPT24!R7+HISTOOCT24!R7+HISTONOV24!R7+HISTODEC24!R7 -> 0 | S7: =HISTOJANV24!S7+HISTOFEV24!S7+HISTOMARS24!S7+HISTOAVRIL24!S7+HISTOMAI24!S7+HISTOJUIN24!S7+HISTOJUIL24!S7+HISTOAOUT24!S7+HISTOSEPT24!S7+HISTOOCT24!S7+HISTONOV24!S7+HISTODEC24!S7 -> 0 | U7: =G7+S7++R7+P7+O7+M7+I7+K7+Q7+V7+W7 -> 133000 | V7: =HISTOJANV24!V7+HISTOFEV24!V7+HISTOMARS24!V7+HISTOAVRIL24!V7+HISTOMAI24!V7+HISTOJUIN24!V7+HISTOJUIL24!V7+HISTOAOUT24!V7+HISTOSEPT24!V7+HISTOOCT24!V7+HISTONOV24!V7+HISTODEC24!V7 -> 0 | W7: =HISTOJANV24!W7+HISTOFEV24!W7+HISTOMARS24!W7+HISTOAVRIL24!W7+HISTOMAI24!W7+HISTOJUIN24!W7+HISTOJUIL24!W7+HISTOAOUT24!W7+HISTOSEPT24!W7+HISTOOCT24!W7+HISTONOV24!W7+HISTODEC24!W7 -> 0 | X7: =HISTOJANV24!X7+HISTOFEV24!X7+HISTOMARS24!X7+HISTOAVRIL24!X7+HISTOMAI24!X7+HISTOJUIN24!X7+HISTOJUIL24!X7+HISTOAOUT24!X7+HISTOSEPT24!X7+HISTOOCT24!X7+HISTONOV24!X7+HISTODEC24!X7 -> 0 | Y7: =HISTOJANV24!Y7+HISTOFEV24!Y7+HISTOMARS24!Y7+HISTOAVRIL24!Y7+HISTOMAI24!Y7+HISTOJUIN24!Y7+HISTOJUIL24!Y7+HISTOAOUT24!Y7+HISTOSEPT24!Y7+HISTOOCT24!Y7+HISTONOV24!Y7+HISTODEC24!Y7 -> 0 | Z7: =HISTOJANV24!Z7+HISTOFEV24!Z7+HISTOMARS24!Z7+HISTOAVRIL24!Z7+HISTOMAI24!Z7+HISTOJUIN24!Z7+HISTOJUIL24!Z7+HISTOAOUT24!Z7+HISTOSEPT24!Z7+HISTOOCT24!Z7+HISTONOV24!Z7+HISTODEC24!Z7 -> 0 | AC7: =HISTOJANV24!AC7+HISTOFEV24!AC7+HISTOMARS24!AC7+HISTOAVRIL24!AC7+HISTOMAI24!AC7+HISTOJUIN24!AC7+HISTOJUIL24!AC7+HISTOAOUT24!AC7+HISTOSEPT24!AC7+HISTOOCT24!AC7+HISTONOV24!AC7+HISTODEC24!AC7 -> 10000 | AD7: =HISTOJANV24!AD7+HISTOFEV24!AD7+HISTOMARS24!AD7+HISTOAVRIL24!AD7+HISTOMAI24!AD7+HISTOJUIN24!AD7+HISTOJUIL24!AD7+HISTOAOUT24!AD7+HISTOSEPT24!AD7+HISTOOCT24!AD7+HISTONOV24!AD7+HISTODEC24!AD7 -> 0 | AE7: =HISTOJANV24!AE7+HISTOFEV24!AE7+HISTOMARS24!AE7+HISTOAVRIL24!AE7+HISTOMAI24!AE7+HISTOJUIN24!AE7+HISTOJUIL24!AE7+HISTOAOUT24!AE7+HISTOSEPT24!AE7+HISTOOCT24!AE7+HISTONOV24!AE7+HISTODEC24!AE7 -> 0 | AH7: =HISTOJANV24!AH7+HISTOFEV24!AH7+HISTOMARS24!AH7+HISTOAVRIL24!AH7+HISTOMAI24!AH7+HISTOJUIN24!AH7+HISTOJUIL24!AH7+HISTOAOUT24!AH7+HISTOSEPT24!AH7+HISTOOCT24!AH7+HISTONOV24!AH7+HISTODEC24!AH7 -> 0 | AI7: =HISTOJANV24!AI7+HISTOFEV24!AI7+HISTOMARS24!AI7+HISTOAVRIL24!AI7+HISTOMAI24!AI7+HISTOJUIN24!AI7+HISTOJUIL24!AI7+HISTOAOUT24!AI7+HISTOSEPT24!AI7+HISTOOCT24!AI7+HISTONOV24!AI7+HISTODEC24!AI7 -> 60000 | AJ7: =HISTOJANV24!AJ7+HISTOFEV24!AJ7+HISTOMARS24!AJ7+HISTOAVRIL24!AJ7+HISTOMAI24!AJ7+HISTOJUIN24!AJ7+HISTOJUIL24!AJ7+HISTOAOUT24!AJ7+HISTOSEPT24!AJ7+HISTOOCT24!AJ7+HISTONOV24!AJ7+HISTODEC24!AJ7 -> 0 | AK7: =HISTOJANV24!AK7+HISTOFEV24!AK7+HISTOMARS24!AK7+HISTOAVRIL24!AK7+HISTOMAI24!AK7+HISTOJUIN24!AK7+HISTOJUIL24!AK7+HISTOAOUT24!AK7+HISTOSEPT24!AK7+HISTOOCT24!AK7+HISTONOV24!AK7+HISTODEC24!AK7 -> 0 | AL7: =HISTOJANV24!AL7+HISTOFEV24!AL7+HISTOMARS24!AL7+HISTOAVRIL24!AL7+HISTOMAI24!AL7+HISTOJUIN24!AL7+HISTOJUIL24!AL7+HISTOAOUT24!AL7+HISTOSEPT24!AL7+HISTOOCT24!AL7+HISTONOV24!AL7+HISTODEC24!AL7 -> 1000 | AM7: =HISTOJANV24!AM7+HISTOFEV24!AM7+HISTOMARS24!AM7+HISTOAVRIL24!AM7+HISTOMAI24!AM7+HISTOJUIN24!AM7+HISTOJUIL24!AM7+HISTOAOUT24!AM7+HISTOSEPT24!AM7+HISTOOCT24!AM7+HISTONOV24!AM7+HISTODEC24!AM7 -> 0 | AN7: =HISTOJANV24!AN7+HISTOFEV24!AN7+HISTOMARS24!AN7+HISTOAVRIL24!AN7+HISTOMAI24!AN7+HISTOJUIN24!AN7+HISTOJUIL24!AN7+HISTOAOUT24!AN7+HISTOSEPT24!AN7+HISTOOCT24!AN7+HISTONOV24!AN7+HISTODEC24!AN7 -> 0 | AQ7: =IF(H7="ECHEC",((K7+M7+O7)*20/100),0) -> 0 | AR7: =IF(H7="ECHEC",((K7+M7+O7)*20/100),0) -> 0 | AS7: =IF(H7="ECHEC",0,(K7+I7-25000)) -> 47000 | AW7: =HISTOJANV24!AW7+HISTOFEV24!AW7+HISTOMARS24!AW7+HISTOAVRIL24!AW7+HISTOMAI24!AW7+HISTOJUIN24!AW7+HISTOJUIL24!AW7+HISTOAOUT24!AW7+HISTOSEPT24!AW7+HISTOOCT24!AW7+HISTONOV24!AW7+HISTODEC24!AW7 -> 350000 | AX7: =HISTOJANV24!AX7+HISTOFEV24!AX7+HISTOMARS24!AX7+HISTOAVRIL24!AX7+HISTOMAI24!AX7+HISTOJUIN24!AX7+HISTOJUIL24!AX7+HISTOAOUT24!AX7+HISTOSEPT24!AX7+HISTOOCT24!AX7+HISTONOV24!AX7+HISTODEC24!AX7 -> 0 | AY7: =HISTOJANV24!AY7+HISTOFEV24!AY7+HISTOMARS24!AY7+HISTOAVRIL24!AY7+HISTOMAI24!AY7+HISTOJUIN24!AY7+HISTOJUIL24!AY7+HISTOAOUT24!AY7+HISTOSEPT24!AY7+HISTOOCT24!AY7+HISTONOV24!AY7+HISTODEC24!AY7 -> 0 | AZ7: =HISTOJANV24!AZ7+HISTOFEV24!AZ7+HISTOMARS24!AZ7+HISTOAVRIL24!AZ7+HISTOMAI24!AZ7+HISTOJUIN24!AZ7+HISTOJUIL24!AZ7+HISTOAOUT24!AZ7+HISTOSEPT24!AZ7+HISTOOCT24!AZ7+HISTONOV24!AZ7+HISTODEC24!AZ7 -> 344000 | BA7: =HISTOJANV24!BA7+HISTOFEV24!BA7+HISTOMARS24!BA7+HISTOAVRIL24!BA7+HISTOMAI24!BA7+HISTOJUIN24!BA7+HISTOJUIL24!BA7+HISTOAOUT24!BA7+HISTOSEPT24!BA7+HISTOOCT24!BA7+HISTONOV24!BA7+HISTODEC24!BA7 -> 0 | BB7: =HISTOJANV24!BB7+HISTOFEV24!BB7+HISTOMARS24!BB7+HISTOAVRIL24!BB7+HISTOMAI24!BB7+HISTOJUIN24!BB7+HISTOJUIL24!BB7+HISTOAOUT24!BB7+HISTOSEPT24!BB7+HISTOOCT24!BB7+HISTONOV24!BB7+HISTODEC24!BB7 -> 0 | BD7: =HISTOJANV24!BD7+HISTOFEV24!BD7+HISTOMARS24!BD7+HISTOAVRIL24!BD7+HISTOMAI24!BD7+HISTOJUIN24!BD7+HISTOJUIL24!BD7+HISTOAOUT24!BD7+HISTOSEPT24!BD7+HISTOOCT24!BD7+HISTONOV24!BD7+HISTODEC24!BD7 -> 350000 | BF7: =HISTOJANV24!BF7+HISTOFEV24!BF7+HISTOMARS24!BF7+HISTOAVRIL24!BF7+HISTOMAI24!BF7+HISTOJUIN24!BF7+HISTOJUIL24!BF7+HISTOAOUT24!BF7+HISTOSEPT24!BF7+HISTOOCT24!BF7+HISTONOV24!BF7+HISTODEC24!BF7 -> 18000 | BN7: COMMUNICATION | BO7: FONDS DE ROULEMENT
A8: AS201602 | B8: =VLOOKUP(A8,[11]LISTADHERENT!A$5:H$50,3,0) -> BOUTCHOUANG WILLIAM | D8: =HISTOJANV24!D8+HISTOFEV24!D8+HISTOMARS24!D8+HISTOAVRIL24!D8+HISTOMAI24!D8+HISTOJUIN24!D8+HISTOJUIL24!D8+HISTOAOUT24!D8+HISTOSEPT24!D8+HISTOOCT24!D8+HISTONOV24!D8+HISTODEC24!D8 -> 375000 | E8: =HISTOJANV24!E8+HISTOFEV24!E8+HISTOMARS24!E8+HISTOAVRIL24!E8+HISTOMAI24!E8+HISTOJUIN24!E8+HISTOJUIL24!E8+HISTOAOUT24!E8+HISTOSEPT24!E8+HISTOOCT24!E8+HISTONOV24!E8+HISTODEC24!E8 -> 25000 | F8: =HISTOJANV24!F8+HISTOFEV24!F8+HISTOMARS24!F8+HISTOAVRIL24!F8+HISTOMAI24!F8+HISTOJUIN24!F8+HISTOJUIL24!F8+HISTOAOUT24!F8+HISTOSEPT24!F8+HISTOOCT24!F8+HISTONOV24!F8+HISTODEC24!F8 -> 0 | G8: =HISTOJANV24!G8+HISTOFEV24!G8+HISTOMARS24!G8+HISTOAVRIL24!G8+HISTOMAI24!G8+HISTOJUIN24!G8+HISTOJUIL24!G8+HISTOAOUT24!G8+HISTOSEPT24!G8+HISTOOCT24!G8+HISTONOV24!G8+HISTODEC24!G8 -> 0 | I8: =HISTOJANV24!I8+HISTOFEV24!I8+HISTOMARS24!I8+HISTOAVRIL24!I8+HISTOMAI24!I8+HISTOJUIN24!I8+HISTOJUIL24!I8+HISTOAOUT24!I8+HISTOSEPT24!I8+HISTOOCT24!I8+HISTONOV24!I8+HISTODEC24!I8 -> -3000 | J8: 1 | K8: =IF($D8<>0,J8*50000,IF($E8<>0,J8*50000,0)) -> 50000 | L8: 1 | M8: =IF($D8<>0,L8*75000,IF($E8<>0,L8*75000,0)) -> 75000 | O8: =IF($D8<>0,N8*100000,IF($E8<>0,N8*100000,0)) -> 0 | P8: =HISTOJANV24!P8+HISTOFEV24!P8+HISTOMARS24!P8+HISTOAVRIL24!P8+HISTOMAI24!P8+HISTOJUIN24!P8+HISTOJUIL24!P8+HISTOAOUT24!P8+HISTOSEPT24!P8+HISTOOCT24!P8+HISTONOV24!P8+HISTODEC24!P8 -> 0 | Q8: =HISTOJANV24!Q8+HISTOFEV24!Q8+HISTOMARS24!Q8+HISTOAVRIL24!Q8+HISTOMAI24!Q8+HISTOJUIN24!Q8+HISTOJUIL24!Q8+HISTOAOUT24!Q8+HISTOSEPT24!Q8+HISTOOCT24!Q8+HISTONOV24!Q8+HISTODEC24!Q8 -> 0 | R8: =HISTOJANV24!R8+HISTOFEV24!R8+HISTOMARS24!R8+HISTOAVRIL24!R8+HISTOMAI24!R8+HISTOJUIN24!R8+HISTOJUIL24!R8+HISTOAOUT24!R8+HISTOSEPT24!R8+HISTOOCT24!R8+HISTONOV24!R8+HISTODEC24!R8 -> 0 | S8: =HISTOJANV24!S8+HISTOFEV24!S8+HISTOMARS24!S8+HISTOAVRIL24!S8+HISTOMAI24!S8+HISTOJUIN24!S8+HISTOJUIL24!S8+HISTOAOUT24!S8+HISTOSEPT24!S8+HISTOOCT24!S8+HISTONOV24!S8+HISTODEC24!S8 -> 0 | U8: =G8+S8++R8+P8+O8+M8+I8+K8+Q8+V8+W8 -> 122000 | V8: =HISTOJANV24!V8+HISTOFEV24!V8+HISTOMARS24!V8+HISTOAVRIL24!V8+HISTOMAI24!V8+HISTOJUIN24!V8+HISTOJUIL24!V8+HISTOAOUT24!V8+HISTOSEPT24!V8+HISTOOCT24!V8+HISTONOV24!V8+HISTODEC24!V8 -> 0 | W8: =HISTOJANV24!W8+HISTOFEV24!W8+HISTOMARS24!W8+HISTOAVRIL24!W8+HISTOMAI24!W8+HISTOJUIN24!W8+HISTOJUIL24!W8+HISTOAOUT24!W8+HISTOSEPT24!W8+HISTOOCT24!W8+HISTONOV24!W8+HISTODEC24!W8 -> 0 | X8: =HISTOJANV24!X8+HISTOFEV24!X8+HISTOMARS24!X8+HISTOAVRIL24!X8+HISTOMAI24!X8+HISTOJUIN24!X8+HISTOJUIL24!X8+HISTOAOUT24!X8+HISTOSEPT24!X8+HISTOOCT24!X8+HISTONOV24!X8+HISTODEC24!X8 -> 0 | Y8: =HISTOJANV24!Y8+HISTOFEV24!Y8+HISTOMARS24!Y8+HISTOAVRIL24!Y8+HISTOMAI24!Y8+HISTOJUIN24!Y8+HISTOJUIL24!Y8+HISTOAOUT24!Y8+HISTOSEPT24!Y8+HISTOOCT24!Y8+HISTONOV24!Y8+HISTODEC24!Y8 -> 0 | Z8: =HISTOJANV24!Z8+HISTOFEV24!Z8+HISTOMARS24!Z8+HISTOAVRIL24!Z8+HISTOMAI24!Z8+HISTOJUIN24!Z8+HISTOJUIL24!Z8+HISTOAOUT24!Z8+HISTOSEPT24!Z8+HISTOOCT24!Z8+HISTONOV24!Z8+HISTODEC24!Z8 -> 0 | AC8: =HISTOJANV24!AC8+HISTOFEV24!AC8+HISTOMARS24!AC8+HISTOAVRIL24!AC8+HISTOMAI24!AC8+HISTOJUIN24!AC8+HISTOJUIL24!AC8+HISTOAOUT24!AC8+HISTOSEPT24!AC8+HISTOOCT24!AC8+HISTONOV24!AC8+HISTODEC24!AC8 -> 0 | AD8: =HISTOJANV24!AD8+HISTOFEV24!AD8+HISTOMARS24!AD8+HISTOAVRIL24!AD8+HISTOMAI24!AD8+HISTOJUIN24!AD8+HISTOJUIL24!AD8+HISTOAOUT24!AD8+HISTOSEPT24!AD8+HISTOOCT24!AD8+HISTONOV24!AD8+HISTODEC24!AD8 -> 0 | AE8: =HISTOJANV24!AE8+HISTOFEV24!AE8+HISTOMARS24!AE8+HISTOAVRIL24!AE8+HISTOMAI24!AE8+HISTOJUIN24!AE8+HISTOJUIL24!AE8+HISTOAOUT24!AE8+HISTOSEPT24!AE8+HISTOOCT24!AE8+HISTONOV24!AE8+HISTODEC24!AE8 -> 0 | AH8: =HISTOJANV24!AH8+HISTOFEV24!AH8+HISTOMARS24!AH8+HISTOAVRIL24!AH8+HISTOMAI24!AH8+HISTOJUIN24!AH8+HISTOJUIL24!AH8+HISTOAOUT24!AH8+HISTOSEPT24!AH8+HISTOOCT24!AH8+HISTONOV24!AH8+HISTODEC24!AH8 -> 0 | AI8: =HISTOJANV24!AI8+HISTOFEV24!AI8+HISTOMARS24!AI8+HISTOAVRIL24!AI8+HISTOMAI24!AI8+HISTOJUIN24!AI8+HISTOJUIL24!AI8+HISTOAOUT24!AI8+HISTOSEPT24!AI8+HISTOOCT24!AI8+HISTONOV24!AI8+HISTODEC24!AI8 -> 0 | AJ8: =HISTOJANV24!AJ8+HISTOFEV24!AJ8+HISTOMARS24!AJ8+HISTOAVRIL24!AJ8+HISTOMAI24!AJ8+HISTOJUIN24!AJ8+HISTOJUIL24!AJ8+HISTOAOUT24!AJ8+HISTOSEPT24!AJ8+HISTOOCT24!AJ8+HISTONOV24!AJ8+HISTODEC24!AJ8 -> 0 | AK8: =HISTOJANV24!AK8+HISTOFEV24!AK8+HISTOMARS24!AK8+HISTOAVRIL24!AK8+HISTOMAI24!AK8+HISTOJUIN24!AK8+HISTOJUIL24!AK8+HISTOAOUT24!AK8+HISTOSEPT24!AK8+HISTOOCT24!AK8+HISTONOV24!AK8+HISTODEC24!AK8 -> 0 | AL8: =HISTOJANV24!AL8+HISTOFEV24!AL8+HISTOMARS24!AL8+HISTOAVRIL24!AL8+HISTOMAI24!AL8+HISTOJUIN24!AL8+HISTOJUIL24!AL8+HISTOAOUT24!AL8+HISTOSEPT24!AL8+HISTOOCT24!AL8+HISTONOV24!AL8+HISTODEC24!AL8 -> 0 | AM8: =HISTOJANV24!AM8+HISTOFEV24!AM8+HISTOMARS24!AM8+HISTOAVRIL24!AM8+HISTOMAI24!AM8+HISTOJUIN24!AM8+HISTOJUIL24!AM8+HISTOAOUT24!AM8+HISTOSEPT24!AM8+HISTOOCT24!AM8+HISTONOV24!AM8+HISTODEC24!AM8 -> 0 | AN8: =HISTOJANV24!AN8+HISTOFEV24!AN8+HISTOMARS24!AN8+HISTOAVRIL24!AN8+HISTOMAI24!AN8+HISTOJUIN24!AN8+HISTOJUIL24!AN8+HISTOAOUT24!AN8+HISTOSEPT24!AN8+HISTOOCT24!AN8+HISTONOV24!AN8+HISTODEC24!AN8 -> 0 | AQ8: =IF(H8="ECHEC",((K8+M8+O8)*20/100),0) -> 0 | AR8: =IF(H8="ECHEC",((K8+M8+O8)*20/100),0) -> 0 | AS8: =IF(H8="ECHEC",0,(K8+I8-25000)) -> 22000 | AW8: =HISTOJANV24!AW8+HISTOFEV24!AW8+HISTOMARS24!AW8+HISTOAVRIL24!AW8+HISTOMAI24!AW8+HISTOJUIN24!AW8+HISTOJUIL24!AW8+HISTOAOUT24!AW8+HISTOSEPT24!AW8+HISTOOCT24!AW8+HISTONOV24!AW8+HISTODEC24!AW8 -> 0 | AX8: =HISTOJANV24!AX8+HISTOFEV24!AX8+HISTOMARS24!AX8+HISTOAVRIL24!AX8+HISTOMAI24!AX8+HISTOJUIN24!AX8+HISTOJUIL24!AX8+HISTOAOUT24!AX8+HISTOSEPT24!AX8+HISTOOCT24!AX8+HISTONOV24!AX8+HISTODEC24!AX8 -> 0 | AY8: =HISTOJANV24!AY8+HISTOFEV24!AY8+HISTOMARS24!AY8+HISTOAVRIL24!AY8+HISTOMAI24!AY8+HISTOJUIN24!AY8+HISTOJUIL24!AY8+HISTOAOUT24!AY8+HISTOSEPT24!AY8+HISTOOCT24!AY8+HISTONOV24!AY8+HISTODEC24!AY8 -> 0 | AZ8: =HISTOJANV24!AZ8+HISTOFEV24!AZ8+HISTOMARS24!AZ8+HISTOAVRIL24!AZ8+HISTOMAI24!AZ8+HISTOJUIN24!AZ8+HISTOJUIL24!AZ8+HISTOAOUT24!AZ8+HISTOSEPT24!AZ8+HISTOOCT24!AZ8+HISTONOV24!AZ8+HISTODEC24!AZ8 -> 0 | BA8: =HISTOJANV24!BA8+HISTOFEV24!BA8+HISTOMARS24!BA8+HISTOAVRIL24!BA8+HISTOMAI24!BA8+HISTOJUIN24!BA8+HISTOJUIL24!BA8+HISTOAOUT24!BA8+HISTOSEPT24!BA8+HISTOOCT24!BA8+HISTONOV24!BA8+HISTODEC24!BA8 -> 0 | BB8: =HISTOJANV24!BB8+HISTOFEV24!BB8+HISTOMARS24!BB8+HISTOAVRIL24!BB8+HISTOMAI24!BB8+HISTOJUIN24!BB8+HISTOJUIL24!BB8+HISTOAOUT24!BB8+HISTOSEPT24!BB8+HISTOOCT24!BB8+HISTONOV24!BB8+HISTODEC24!BB8 -> 0 | BD8: =HISTOJANV24!BD8+HISTOFEV24!BD8+HISTOMARS24!BD8+HISTOAVRIL24!BD8+HISTOMAI24!BD8+HISTOJUIN24!BD8+HISTOJUIL24!BD8+HISTOAOUT24!BD8+HISTOSEPT24!BD8+HISTOOCT24!BD8+HISTONOV24!BD8+HISTODEC24!BD8 -> 0 | BF8: =HISTOJANV24!BF8+HISTOFEV24!BF8+HISTOMARS24!BF8+HISTOAVRIL24!BF8+HISTOMAI24!BF8+HISTOJUIN24!BF8+HISTOJUIL24!BF8+HISTOAOUT24!BF8+HISTOSEPT24!BF8+HISTOOCT24!BF8+HISTONOV24!BF8+HISTODEC24!BF8 -> 25000 | BN8: COMMISSION | BO8: FONDS DE ROULEMENT
A9: AS201604 | B9: =VLOOKUP(A9,[11]LISTADHERENT!A$5:H$50,3,0) -> DJOMO JEAN PAUL | D9: =HISTOJANV24!D9+HISTOFEV24!D9+HISTOMARS24!D9+HISTOAVRIL24!D9+HISTOMAI24!D9+HISTOJUIN24!D9+HISTOJUIL24!D9+HISTOAOUT24!D9+HISTOSEPT24!D9+HISTOOCT24!D9+HISTONOV24!D9+HISTODEC24!D9 -> 750000 | E9: =HISTOJANV24!E9+HISTOFEV24!E9+HISTOMARS24!E9+HISTOAVRIL24!E9+HISTOMAI24!E9+HISTOJUIN24!E9+HISTOJUIL24!E9+HISTOAOUT24!E9+HISTOSEPT24!E9+HISTOOCT24!E9+HISTONOV24!E9+HISTODEC24!E9 -> 0 | F9: =HISTOJANV24!F9+HISTOFEV24!F9+HISTOMARS24!F9+HISTOAVRIL24!F9+HISTOMAI24!F9+HISTOJUIN24!F9+HISTOJUIL24!F9+HISTOAOUT24!F9+HISTOSEPT24!F9+HISTOOCT24!F9+HISTONOV24!F9+HISTODEC24!F9 -> 0 | G9: =HISTOJANV24!G9+HISTOFEV24!G9+HISTOMARS24!G9+HISTOAVRIL24!G9+HISTOMAI24!G9+HISTOJUIN24!G9+HISTOJUIL24!G9+HISTOAOUT24!G9+HISTOSEPT24!G9+HISTOOCT24!G9+HISTONOV24!G9+HISTODEC24!G9 -> 0 | I9: =HISTOJANV24!I9+HISTOFEV24!I9+HISTOMARS24!I9+HISTOAVRIL24!I9+HISTOMAI24!I9+HISTOJUIN24!I9+HISTOJUIL24!I9+HISTOAOUT24!I9+HISTOSEPT24!I9+HISTOOCT24!I9+HISTONOV24!I9+HISTODEC24!I9 -> 0 | J9: 1 | K9: =IF($D9<>0,J9*50000,IF($E9<>0,J9*50000,0)) -> 50000 | M9: =IF($D9<>0,L9*75000,IF($E9<>0,L9*75000,0)) -> 0 | N9: 2 | O9: =IF($D9<>0,N9*100000,IF($E9<>0,N9*100000,0)) -> 200000 | P9: =HISTOJANV24!P9+HISTOFEV24!P9+HISTOMARS24!P9+HISTOAVRIL24!P9+HISTOMAI24!P9+HISTOJUIN24!P9+HISTOJUIL24!P9+HISTOAOUT24!P9+HISTOSEPT24!P9+HISTOOCT24!P9+HISTONOV24!P9+HISTODEC24!P9 -> 0 | Q9: =HISTOJANV24!Q9+HISTOFEV24!Q9+HISTOMARS24!Q9+HISTOAVRIL24!Q9+HISTOMAI24!Q9+HISTOJUIN24!Q9+HISTOJUIL24!Q9+HISTOAOUT24!Q9+HISTOSEPT24!Q9+HISTOOCT24!Q9+HISTONOV24!Q9+HISTODEC24!Q9 -> 0 | R9: =HISTOJANV24!R9+HISTOFEV24!R9+HISTOMARS24!R9+HISTOAVRIL24!R9+HISTOMAI24!R9+HISTOJUIN24!R9+HISTOJUIL24!R9+HISTOAOUT24!R9+HISTOSEPT24!R9+HISTOOCT24!R9+HISTONOV24!R9+HISTODEC24!R9 -> 207500 | S9: =HISTOJANV24!S9+HISTOFEV24!S9+HISTOMARS24!S9+HISTOAVRIL24!S9+HISTOMAI24!S9+HISTOJUIN24!S9+HISTOJUIL24!S9+HISTOAOUT24!S9+HISTOSEPT24!S9+HISTOOCT24!S9+HISTONOV24!S9+HISTODEC24!S9 -> 0 | U9: =G9+S9++R9+P9+O9+M9+I9+K9+Q9+V9+W9 -> 457500 | V9: =HISTOJANV24!V9+HISTOFEV24!V9+HISTOMARS24!V9+HISTOAVRIL24!V9+HISTOMAI24!V9+HISTOJUIN24!V9+HISTOJUIL24!V9+HISTOAOUT24!V9+HISTOSEPT24!V9+HISTOOCT24!V9+HISTONOV24!V9+HISTODEC24!V9 -> 0 | W9: =HISTOJANV24!W9+HISTOFEV24!W9+HISTOMARS24!W9+HISTOAVRIL24!W9+HISTOMAI24!W9+HISTOJUIN24!W9+HISTOJUIL24!W9+HISTOAOUT24!W9+HISTOSEPT24!W9+HISTOOCT24!W9+HISTONOV24!W9+HISTODEC24!W9 -> 0 | X9: =HISTOJANV24!X9+HISTOFEV24!X9+HISTOMARS24!X9+HISTOAVRIL24!X9+HISTOMAI24!X9+HISTOJUIN24!X9+HISTOJUIL24!X9+HISTOAOUT24!X9+HISTOSEPT24!X9+HISTOOCT24!X9+HISTONOV24!X9+HISTODEC24!X9 -> 0 | Y9: =HISTOJANV24!Y9+HISTOFEV24!Y9+HISTOMARS24!Y9+HISTOAVRIL24!Y9+HISTOMAI24!Y9+HISTOJUIN24!Y9+HISTOJUIL24!Y9+HISTOAOUT24!Y9+HISTOSEPT24!Y9+HISTOOCT24!Y9+HISTONOV24!Y9+HISTODEC24!Y9 -> 0 | Z9: =HISTOJANV24!Z9+HISTOFEV24!Z9+HISTOMARS24!Z9+HISTOAVRIL24!Z9+HISTOMAI24!Z9+HISTOJUIN24!Z9+HISTOJUIL24!Z9+HISTOAOUT24!Z9+HISTOSEPT24!Z9+HISTOOCT24!Z9+HISTONOV24!Z9+HISTODEC24!Z9 -> 0 | AC9: =HISTOJANV24!AC9+HISTOFEV24!AC9+HISTOMARS24!AC9+HISTOAVRIL24!AC9+HISTOMAI24!AC9+HISTOJUIN24!AC9+HISTOJUIL24!AC9+HISTOAOUT24!AC9+HISTOSEPT24!AC9+HISTOOCT24!AC9+HISTONOV24!AC9+HISTODEC24!AC9 -> 18000 | AD9: =HISTOJANV24!AD9+HISTOFEV24!AD9+HISTOMARS24!AD9+HISTOAVRIL24!AD9+HISTOMAI24!AD9+HISTOJUIN24!AD9+HISTOJUIL24!AD9+HISTOAOUT24!AD9+HISTOSEPT24!AD9+HISTOOCT24!AD9+HISTONOV24!AD9+HISTODEC24!AD9 -> 0 | AE9: =HISTOJANV24!AE9+HISTOFEV24!AE9+HISTOMARS24!AE9+HISTOAVRIL24!AE9+HISTOMAI24!AE9+HISTOJUIN24!AE9+HISTOJUIL24!AE9+HISTOAOUT24!AE9+HISTOSEPT24!AE9+HISTOOCT24!AE9+HISTONOV24!AE9+HISTODEC24!AE9 -> 115000 | AH9: =HISTOJANV24!AH9+HISTOFEV24!AH9+HISTOMARS24!AH9+HISTOAVRIL24!AH9+HISTOMAI24!AH9+HISTOJUIN24!AH9+HISTOJUIL24!AH9+HISTOAOUT24!AH9+HISTOSEPT24!AH9+HISTOOCT24!AH9+HISTONOV24!AH9+HISTODEC24!AH9 -> 0 | AI9: =HISTOJANV24!AI9+HISTOFEV24!AI9+HISTOMARS24!AI9+HISTOAVRIL24!AI9+HISTOMAI24!AI9+HISTOJUIN24!AI9+HISTOJUIL24!AI9+HISTOAOUT24!AI9+HISTOSEPT24!AI9+HISTOOCT24!AI9+HISTONOV24!AI9+HISTODEC24!AI9 -> 0 | AJ9: =HISTOJANV24!AJ9+HISTOFEV24!AJ9+HISTOMARS24!AJ9+HISTOAVRIL24!AJ9+HISTOMAI24!AJ9+HISTOJUIN24!AJ9+HISTOJUIL24!AJ9+HISTOAOUT24!AJ9+HISTOSEPT24!AJ9+HISTOOCT24!AJ9+HISTONOV24!AJ9+HISTODEC24!AJ9 -> 0 | AK9: =HISTOJANV24!AK9+HISTOFEV24!AK9+HISTOMARS24!AK9+HISTOAVRIL24!AK9+HISTOMAI24!AK9+HISTOJUIN24!AK9+HISTOJUIL24!AK9+HISTOAOUT24!AK9+HISTOSEPT24!AK9+HISTOOCT24!AK9+HISTONOV24!AK9+HISTODEC24!AK9 -> 205500 | AL9: =HISTOJANV24!AL9+HISTOFEV24!AL9+HISTOMARS24!AL9+HISTOAVRIL24!AL9+HISTOMAI24!AL9+HISTOJUIN24!AL9+HISTOJUIL24!AL9+HISTOAOUT24!AL9+HISTOSEPT24!AL9+HISTOOCT24!AL9+HISTONOV24!AL9+HISTODEC24!AL9 -> 0 | AM9: =HISTOJANV24!AM9+HISTOFEV24!AM9+HISTOMARS24!AM9+HISTOAVRIL24!AM9+HISTOMAI24!AM9+HISTOJUIN24!AM9+HISTOJUIL24!AM9+HISTOAOUT24!AM9+HISTOSEPT24!AM9+HISTOOCT24!AM9+HISTONOV24!AM9+HISTODEC24!AM9 -> 0 | AN9: =HISTOJANV24!AN9+HISTOFEV24!AN9+HISTOMARS24!AN9+HISTOAVRIL24!AN9+HISTOMAI24!AN9+HISTOJUIN24!AN9+HISTOJUIL24!AN9+HISTOAOUT24!AN9+HISTOSEPT24!AN9+HISTOOCT24!AN9+HISTONOV24!AN9+HISTODEC24!AN9 -> 2000 | AQ9: =IF(H9="ECHEC",((K9+M9+O9)*20/100),0) -> 0 | AR9: =IF(H9="ECHEC",((K9+M9+O9)*20/100),0) -> 0 | AS9: =IF(H9="ECHEC",0,(K9+I9-25000)) -> 25000 | AW9: =HISTOJANV24!AW9+HISTOFEV24!AW9+HISTOMARS24!AW9+HISTOAVRIL24!AW9+HISTOMAI24!AW9+HISTOJUIN24!AW9+HISTOJUIL24!AW9+HISTOAOUT24!AW9+HISTOSEPT24!AW9+HISTOOCT24!AW9+HISTONOV24!AW9+HISTODEC24!AW9 -> 282000 | AX9: =HISTOJANV24!AX9+HISTOFEV24!AX9+HISTOMARS24!AX9+HISTOAVRIL24!AX9+HISTOMAI24!AX9+HISTOJUIN24!AX9+HISTOJUIL24!AX9+HISTOAOUT24!AX9+HISTOSEPT24!AX9+HISTOOCT24!AX9+HISTONOV24!AX9+HISTODEC24!AX9 -> 0 | AY9: =HISTOJANV24!AY9+HISTOFEV24!AY9+HISTOMARS24!AY9+HISTOAVRIL24!AY9+HISTOMAI24!AY9+HISTOJUIN24!AY9+HISTOJUIL24!AY9+HISTOAOUT24!AY9+HISTOSEPT24!AY9+HISTOOCT24!AY9+HISTONOV24!AY9+HISTODEC24!AY9 -> 1290500 | AZ9: =HISTOJANV24!AZ9+HISTOFEV24!AZ9+HISTOMARS24!AZ9+HISTOAVRIL24!AZ9+HISTOMAI24!AZ9+HISTOJUIN24!AZ9+HISTOJUIL24!AZ9+HISTOAOUT24!AZ9+HISTOSEPT24!AZ9+HISTOOCT24!AZ9+HISTONOV24!AZ9+HISTODEC24!AZ9 -> 1572500 | BA9: =HISTOJANV24!BA9+HISTOFEV24!BA9+HISTOMARS24!BA9+HISTOAVRIL24!BA9+HISTOMAI24!BA9+HISTOJUIN24!BA9+HISTOJUIL24!BA9+HISTOAOUT24!BA9+HISTOSEPT24!BA9+HISTOOCT24!BA9+HISTONOV24!BA9+HISTODEC24!BA9 -> 782000 | BB9: =HISTOJANV24!BB9+HISTOFEV24!BB9+HISTOMARS24!BB9+HISTOAVRIL24!BB9+HISTOMAI24!BB9+HISTOJUIN24!BB9+HISTOJUIL24!BB9+HISTOAOUT24!BB9+HISTOSEPT24!BB9+HISTOOCT24!BB9+HISTONOV24!BB9+HISTODEC24!BB9 -> 0 | BD9: =HISTOJANV24!BD9+HISTOFEV24!BD9+HISTOMARS24!BD9+HISTOAVRIL24!BD9+HISTOMAI24!BD9+HISTOJUIN24!BD9+HISTOJUIL24!BD9+HISTOAOUT24!BD9+HISTOSEPT24!BD9+HISTOOCT24!BD9+HISTONOV24!BD9+HISTODEC24!BD9 -> 790500 | BF9: =HISTOJANV24!BF9+HISTOFEV24!BF9+HISTOMARS24!BF9+HISTOAVRIL24!BF9+HISTOMAI24!BF9+HISTOJUIN24!BF9+HISTOJUIL24!BF9+HISTOAOUT24!BF9+HISTOSEPT24!BF9+HISTOOCT24!BF9+HISTONOV24!BF9+HISTODEC24!BF9 -> 0 | BN9: OUVERTURE COMPTE | BO9: FONDS DE ROULEMENT
A10: AS201654 | B10: =VLOOKUP(A10,[11]LISTADHERENT!A$5:H$50,3,0) -> DJOMOU TCHAPDA | D10: =HISTOJANV24!D10+HISTOFEV24!D10+HISTOMARS24!D10+HISTOAVRIL24!D10+HISTOMAI24!D10+HISTOJUIN24!D10+HISTOJUIL24!D10+HISTOAOUT24!D10+HISTOSEPT24!D10+HISTOOCT24!D10+HISTONOV24!D10+HISTODEC24!D10 -> 430000 | E10: =HISTOJANV24!E10+HISTOFEV24!E10+HISTOMARS24!E10+HISTOAVRIL24!E10+HISTOMAI24!E10+HISTOJUIN24!E10+HISTOJUIL24!E10+HISTOAOUT24!E10+HISTOSEPT24!E10+HISTOOCT24!E10+HISTONOV24!E10+HISTODEC24!E10 -> 105000 | F10: =HISTOJANV24!F10+HISTOFEV24!F10+HISTOMARS24!F10+HISTOAVRIL24!F10+HISTOMAI24!F10+HISTOJUIN24!F10+HISTOJUIL24!F10+HISTOAOUT24!F10+HISTOSEPT24!F10+HISTOOCT24!F10+HISTONOV24!F10+HISTODEC24!F10 -> 0 | G10: =HISTOJANV24!G10+HISTOFEV24!G10+HISTOMARS24!G10+HISTOAVRIL24!G10+HISTOMAI24!G10+HISTOJUIN24!G10+HISTOJUIL24!G10+HISTOAOUT24!G10+HISTOSEPT24!G10+HISTOOCT24!G10+HISTONOV24!G10+HISTODEC24!G10 -> 3000 | I10: =HISTOJANV24!I10+HISTOFEV24!I10+HISTOMARS24!I10+HISTOAVRIL24!I10+HISTOMAI24!I10+HISTOJUIN24!I10+HISTOJUIL24!I10+HISTOAOUT24!I10+HISTOSEPT24!I10+HISTOOCT24!I10+HISTONOV24!I10+HISTODEC24!I10 -> -6000 | J10: 1 | K10: =IF($D10<>0,J10*50000,IF($E10<>0,J10*50000,0)) -> 50000 | L10: 1 | M10: =IF($D10<>0,L10*75000,IF($E10<>0,L10*75000,0)) -> 75000 | O10: =IF($D10<>0,N10*100000,IF($E10<>0,N10*100000,0)) -> 0 | P10: =HISTOJANV24!P10+HISTOFEV24!P10+HISTOMARS24!P10+HISTOAVRIL24!P10+HISTOMAI24!P10+HISTOJUIN24!P10+HISTOJUIL24!P10+HISTOAOUT24!P10+HISTOSEPT24!P10+HISTOOCT24!P10+HISTONOV24!P10+HISTODEC24!P10 -> 102000 | Q10: =HISTOJANV24!Q10+HISTOFEV24!Q10+HISTOMARS24!Q10+HISTOAVRIL24!Q10+HISTOMAI24!Q10+HISTOJUIN24!Q10+HISTOJUIL24!Q10+HISTOAOUT24!Q10+HISTOSEPT24!Q10+HISTOOCT24!Q10+HISTONOV24!Q10+HISTODEC24!Q10 -> 102000 | R10: =HISTOJANV24!R10+HISTOFEV24!R10+HISTOMARS24!R10+HISTOAVRIL24!R10+HISTOMAI24!R10+HISTOJUIN24!R10+HISTOJUIL24!R10+HISTOAOUT24!R10+HISTOSEPT24!R10+HISTOOCT24!R10+HISTONOV24!R10+HISTODEC24!R10 -> 0 | S10: =HISTOJANV24!S10+HISTOFEV24!S10+HISTOMARS24!S10+HISTOAVRIL24!S10+HISTOMAI24!S10+HISTOJUIN24!S10+HISTOJUIL24!S10+HISTOAOUT24!S10+HISTOSEPT24!S10+HISTOOCT24!S10+HISTONOV24!S10+HISTODEC24!S10 -> 0 | U10: =G10+S10++R10+P10+O10+M10+I10+K10+Q10+V10+W10 -> 326000 | V10: =HISTOJANV24!V10+HISTOFEV24!V10+HISTOMARS24!V10+HISTOAVRIL24!V10+HISTOMAI24!V10+HISTOJUIN24!V10+HISTOJUIL24!V10+HISTOAOUT24!V10+HISTOSEPT24!V10+HISTOOCT24!V10+HISTONOV24!V10+HISTODEC24!V10 -> 0 | W10: =HISTOJANV24!W10+HISTOFEV24!W10+HISTOMARS24!W10+HISTOAVRIL24!W10+HISTOMAI24!W10+HISTOJUIN24!W10+HISTOJUIL24!W10+HISTOAOUT24!W10+HISTOSEPT24!W10+HISTOOCT24!W10+HISTONOV24!W10+HISTODEC24!W10 -> 0 | X10: =HISTOJANV24!X10+HISTOFEV24!X10+HISTOMARS24!X10+HISTOAVRIL24!X10+HISTOMAI24!X10+HISTOJUIN24!X10+HISTOJUIL24!X10+HISTOAOUT24!X10+HISTOSEPT24!X10+HISTOOCT24!X10+HISTONOV24!X10+HISTODEC24!X10 -> 0 | Y10: =HISTOJANV24!Y10+HISTOFEV24!Y10+HISTOMARS24!Y10+HISTOAVRIL24!Y10+HISTOMAI24!Y10+HISTOJUIN24!Y10+HISTOJUIL24!Y10+HISTOAOUT24!Y10+HISTOSEPT24!Y10+HISTOOCT24!Y10+HISTONOV24!Y10+HISTODEC24!Y10 -> 0 | Z10: =HISTOJANV24!Z10+HISTOFEV24!Z10+HISTOMARS24!Z10+HISTOAVRIL24!Z10+HISTOMAI24!Z10+HISTOJUIN24!Z10+HISTOJUIL24!Z10+HISTOAOUT24!Z10+HISTOSEPT24!Z10+HISTOOCT24!Z10+HISTONOV24!Z10+HISTODEC24!Z10 -> 0 | AC10: =HISTOJANV24!AC10+HISTOFEV24!AC10+HISTOMARS24!AC10+HISTOAVRIL24!AC10+HISTOMAI24!AC10+HISTOJUIN24!AC10+HISTOJUIL24!AC10+HISTOAOUT24!AC10+HISTOSEPT24!AC10+HISTOOCT24!AC10+HISTONOV24!AC10+HISTODEC24!AC10 -> 0 | AD10: =HISTOJANV24!AD10+HISTOFEV24!AD10+HISTOMARS24!AD10+HISTOAVRIL24!AD10+HISTOMAI24!AD10+HISTOJUIN24!AD10+HISTOJUIL24!AD10+HISTOAOUT24!AD10+HISTOSEPT24!AD10+HISTOOCT24!AD10+HISTONOV24!AD10+HISTODEC24!AD10 -> 28000 | AE10: =HISTOJANV24!AE10+HISTOFEV24!AE10+HISTOMARS24!AE10+HISTOAVRIL24!AE10+HISTOMAI24!AE10+HISTOJUIN24!AE10+HISTOJUIL24!AE10+HISTOAOUT24!AE10+HISTOSEPT24!AE10+HISTOOCT24!AE10+HISTONOV24!AE10+HISTODEC24!AE10 -> 0 | AH10: =HISTOJANV24!AH10+HISTOFEV24!AH10+HISTOMARS24!AH10+HISTOAVRIL24!AH10+HISTOMAI24!AH10+HISTOJUIN24!AH10+HISTOJUIL24!AH10+HISTOAOUT24!AH10+HISTOSEPT24!AH10+HISTOOCT24!AH10+HISTONOV24!AH10+HISTODEC24!AH10 -> 0 | AI10: =HISTOJANV24!AI10+HISTOFEV24!AI10+HISTOMARS24!AI10+HISTOAVRIL24!AI10+HISTOMAI24!AI10+HISTOJUIN24!AI10+HISTOJUIL24!AI10+HISTOAOUT24!AI10+HISTOSEPT24!AI10+HISTOOCT24!AI10+HISTONOV24!AI10+HISTODEC24!AI10 -> 100000 | AJ10: =HISTOJANV24!AJ10+HISTOFEV24!AJ10+HISTOMARS24!AJ10+HISTOAVRIL24!AJ10+HISTOMAI24!AJ10+HISTOJUIN24!AJ10+HISTOJUIL24!AJ10+HISTOAOUT24!AJ10+HISTOSEPT24!AJ10+HISTOOCT24!AJ10+HISTONOV24!AJ10+HISTODEC24!AJ10 -> 100000 | AK10: =HISTOJANV24!AK10+HISTOFEV24!AK10+HISTOMARS24!AK10+HISTOAVRIL24!AK10+HISTOMAI24!AK10+HISTOJUIN24!AK10+HISTOJUIL24!AK10+HISTOAOUT24!AK10+HISTOSEPT24!AK10+HISTOOCT24!AK10+HISTONOV24!AK10+HISTODEC24!AK10 -> 0 | AL10: =HISTOJANV24!AL10+HISTOFEV24!AL10+HISTOMARS24!AL10+HISTOAVRIL24!AL10+HISTOMAI24!AL10+HISTOJUIN24!AL10+HISTOJUIL24!AL10+HISTOAOUT24!AL10+HISTOSEPT24!AL10+HISTOOCT24!AL10+HISTONOV24!AL10+HISTODEC24!AL10 -> 2000 | AM10: =HISTOJANV24!AM10+HISTOFEV24!AM10+HISTOMARS24!AM10+HISTOAVRIL24!AM10+HISTOMAI24!AM10+HISTOJUIN24!AM10+HISTOJUIL24!AM10+HISTOAOUT24!AM10+HISTOSEPT24!AM10+HISTOOCT24!AM10+HISTONOV24!AM10+HISTODEC24!AM10 -> 2000 | AN10: =HISTOJANV24!AN10+HISTOFEV24!AN10+HISTOMARS24!AN10+HISTOAVRIL24!AN10+HISTOMAI24!AN10+HISTOJUIN24!AN10+HISTOJUIL24!AN10+HISTOAOUT24!AN10+HISTOSEPT24!AN10+HISTOOCT24!AN10+HISTONOV24!AN10+HISTODEC24!AN10 -> 0 | AQ10: =IF(H10="ECHEC",((K10+M10+O10)*20/100),0) -> 0 | AR10: =IF(H10="ECHEC",((K10+M10+O10)*20/100),0) -> 0 | AS10: =IF(H10="ECHEC",0,(K10+I10-25000)) -> 19000 | AW10: =HISTOJANV24!AW10+HISTOFEV24!AW10+HISTOMARS24!AW10+HISTOAVRIL24!AW10+HISTOMAI24!AW10+HISTOJUIN24!AW10+HISTOJUIL24!AW10+HISTOAOUT24!AW10+HISTOSEPT24!AW10+HISTOOCT24!AW10+HISTONOV24!AW10+HISTODEC24!AW10 -> 100000 | AX10: =HISTOJANV24!AX10+HISTOFEV24!AX10+HISTOMARS24!AX10+HISTOAVRIL24!AX10+HISTOMAI24!AX10+HISTOJUIN24!AX10+HISTOJUIL24!AX10+HISTOAOUT24!AX10+HISTOSEPT24!AX10+HISTOOCT24!AX10+HISTONOV24!AX10+HISTODEC24!AX10 -> 972000 | AY10: =HISTOJANV24!AY10+HISTOFEV24!AY10+HISTOMARS24!AY10+HISTOAVRIL24!AY10+HISTOMAI24!AY10+HISTOJUIN24!AY10+HISTOJUIL24!AY10+HISTOAOUT24!AY10+HISTOSEPT24!AY10+HISTOOCT24!AY10+HISTONOV24!AY10+HISTODEC24!AY10 -> 0 | AZ10: =HISTOJANV24!AZ10+HISTOFEV24!AZ10+HISTOMARS24!AZ10+HISTOAVRIL24!AZ10+HISTOMAI24!AZ10+HISTOJUIN24!AZ10+HISTOJUIL24!AZ10+HISTOAOUT24!AZ10+HISTOSEPT24!AZ10+HISTOOCT24!AZ10+HISTONOV24!AZ10+HISTODEC24!AZ10 -> 1072000 | BA10: =HISTOJANV24!BA10+HISTOFEV24!BA10+HISTOMARS24!BA10+HISTOAVRIL24!BA10+HISTOMAI24!BA10+HISTOJUIN24!BA10+HISTOJUIL24!BA10+HISTOAOUT24!BA10+HISTOSEPT24!BA10+HISTOOCT24!BA10+HISTONOV24!BA10+HISTODEC24!BA10 -> 39000 | BB10: =HISTOJANV24!BB10+HISTOFEV24!BB10+HISTOMARS24!BB10+HISTOAVRIL24!BB10+HISTOMAI24!BB10+HISTOJUIN24!BB10+HISTOJUIL24!BB10+HISTOAOUT24!BB10+HISTOSEPT24!BB10+HISTOOCT24!BB10+HISTONOV24!BB10+HISTODEC24!BB10 -> 0 | BD10: =HISTOJANV24!BD10+HISTOFEV24!BD10+HISTOMARS24!BD10+HISTOAVRIL24!BD10+HISTOMAI24!BD10+HISTOJUIN24!BD10+HISTOJUIL24!BD10+HISTOAOUT24!BD10+HISTOSEPT24!BD10+HISTOOCT24!BD10+HISTONOV24!BD10+HISTODEC24!BD10 -> 1033000 | BF10: =HISTOJANV24!BF10+HISTOFEV24!BF10+HISTOMARS24!BF10+HISTOAVRIL24!BF10+HISTOMAI24!BF10+HISTOJUIN24!BF10+HISTOJUIL24!BF10+HISTOAOUT24!BF10+HISTOSEPT24!BF10+HISTOOCT24!BF10+HISTONOV24!BF10+HISTODEC24!BF10 -> 0 | BN10: CREDIT TELEPHONE | BO10: FONDS DE ROULEMENT
A11: AS201605 | B11: =VLOOKUP(A11,[11]LISTADHERENT!A$5:H$50,3,0) -> DJOUKWE NANGUEN GUY BLAISE | D11: =HISTOJANV24!D11+HISTOFEV24!D11+HISTOMARS24!D11+HISTOAVRIL24!D11+HISTOMAI24!D11+HISTOJUIN24!D11+HISTOJUIL24!D11+HISTOAOUT24!D11+HISTOSEPT24!D11+HISTOOCT24!D11+HISTONOV24!D11+HISTODEC24!D11 -> 477000 | E11: =HISTOJANV24!E11+HISTOFEV24!E11+HISTOMARS24!E11+HISTOAVRIL24!E11+HISTOMAI24!E11+HISTOJUIN24!E11+HISTOJUIL24!E11+HISTOAOUT24!E11+HISTOSEPT24!E11+HISTOOCT24!E11+HISTONOV24!E11+HISTODEC24!E11 -> 0 | F11: =HISTOJANV24!F11+HISTOFEV24!F11+HISTOMARS24!F11+HISTOAVRIL24!F11+HISTOMAI24!F11+HISTOJUIN24!F11+HISTOJUIL24!F11+HISTOAOUT24!F11+HISTOSEPT24!F11+HISTOOCT24!F11+HISTONOV24!F11+HISTODEC24!F11 -> 1000000 | G11: =HISTOJANV24!G11+HISTOFEV24!G11+HISTOMARS24!G11+HISTOAVRIL24!G11+HISTOMAI24!G11+HISTOJUIN24!G11+HISTOJUIL24!G11+HISTOAOUT24!G11+HISTOSEPT24!G11+HISTOOCT24!G11+HISTONOV24!G11+HISTODEC24!G11 -> 0 | I11: =HISTOJANV24!I11+HISTOFEV24!I11+HISTOMARS24!I11+HISTOAVRIL24!I11+HISTOMAI24!I11+HISTOJUIN24!I11+HISTOJUIL24!I11+HISTOAOUT24!I11+HISTOSEPT24!I11+HISTOOCT24!I11+HISTONOV24!I11+HISTODEC24!I11 -> 0 | J11: 1 | K11: =IF($D11<>0,J11*50000,IF($E11<>0,J11*50000,0)) -> 50000 | L11: 1 | M11: =IF($D11<>0,L11*75000,IF($E11<>0,L11*75000,0)) -> 75000 | O11: =IF($D11<>0,N11*100000,IF($E11<>0,N11*100000,0)) -> 0 | P11: =HISTOJANV24!P11+HISTOFEV24!P11+HISTOMARS24!P11+HISTOAVRIL24!P11+HISTOMAI24!P11+HISTOJUIN24!P11+HISTOJUIL24!P11+HISTOAOUT24!P11+HISTOSEPT24!P11+HISTOOCT24!P11+HISTONOV24!P11+HISTODEC24!P11 -> 41000 | Q11: =HISTOJANV24!Q11+HISTOFEV24!Q11+HISTOMARS24!Q11+HISTOAVRIL24!Q11+HISTOMAI24!Q11+HISTOJUIN24!Q11+HISTOJUIL24!Q11+HISTOAOUT24!Q11+HISTOSEPT24!Q11+HISTOOCT24!Q11+HISTONOV24!Q11+HISTODEC24!Q11 -> 205000 | R11: =HISTOJANV24!R11+HISTOFEV24!R11+HISTOMARS24!R11+HISTOAVRIL24!R11+HISTOMAI24!R11+HISTOJUIN24!R11+HISTOJUIL24!R11+HISTOAOUT24!R11+HISTOSEPT24!R11+HISTOOCT24!R11+HISTONOV24!R11+HISTODEC24!R11 -> 0 | S11: =HISTOJANV24!S11+HISTOFEV24!S11+HISTOMARS24!S11+HISTOAVRIL24!S11+HISTOMAI24!S11+HISTOJUIN24!S11+HISTOJUIL24!S11+HISTOAOUT24!S11+HISTOSEPT24!S11+HISTOOCT24!S11+HISTONOV24!S11+HISTODEC24!S11 -> 1000000 | U11: =G11+S11++R11+P11+O11+M11+I11+K11+Q11+V11+W11 -> 1371000 | V11: =HISTOJANV24!V11+HISTOFEV24!V11+HISTOMARS24!V11+HISTOAVRIL24!V11+HISTOMAI24!V11+HISTOJUIN24!V11+HISTOJUIL24!V11+HISTOAOUT24!V11+HISTOSEPT24!V11+HISTOOCT24!V11+HISTONOV24!V11+HISTODEC24!V11 -> 0 | W11: =HISTOJANV24!W11+HISTOFEV24!W11+HISTOMARS24!W11+HISTOAVRIL24!W11+HISTOMAI24!W11+HISTOJUIN24!W11+HISTOJUIL24!W11+HISTOAOUT24!W11+HISTOSEPT24!W11+HISTOOCT24!W11+HISTONOV24!W11+HISTODEC24!W11 -> 0 | X11: =HISTOJANV24!X11+HISTOFEV24!X11+HISTOMARS24!X11+HISTOAVRIL24!X11+HISTOMAI24!X11+HISTOJUIN24!X11+HISTOJUIL24!X11+HISTOAOUT24!X11+HISTOSEPT24!X11+HISTOOCT24!X11+HISTONOV24!X11+HISTODEC24!X11 -> 0 | Y11: =HISTOJANV24!Y11+HISTOFEV24!Y11+HISTOMARS24!Y11+HISTOAVRIL24!Y11+HISTOMAI24!Y11+HISTOJUIN24!Y11+HISTOJUIL24!Y11+HISTOAOUT24!Y11+HISTOSEPT24!Y11+HISTOOCT24!Y11+HISTONOV24!Y11+HISTODEC24!Y11 -> 0 | Z11: =HISTOJANV24!Z11+HISTOFEV24!Z11+HISTOMARS24!Z11+HISTOAVRIL24!Z11+HISTOMAI24!Z11+HISTOJUIN24!Z11+HISTOJUIL24!Z11+HISTOAOUT24!Z11+HISTOSEPT24!Z11+HISTOOCT24!Z11+HISTONOV24!Z11+HISTODEC24!Z11 -> 1000000 | AC11: =HISTOJANV24!AC11+HISTOFEV24!AC11+HISTOMARS24!AC11+HISTOAVRIL24!AC11+HISTOMAI24!AC11+HISTOJUIN24!AC11+HISTOJUIL24!AC11+HISTOAOUT24!AC11+HISTOSEPT24!AC11+HISTOOCT24!AC11+HISTONOV24!AC11+HISTODEC24!AC11 -> 16000 | AD11: =HISTOJANV24!AD11+HISTOFEV24!AD11+HISTOMARS24!AD11+HISTOAVRIL24!AD11+HISTOMAI24!AD11+HISTOJUIN24!AD11+HISTOJUIL24!AD11+HISTOAOUT24!AD11+HISTOSEPT24!AD11+HISTOOCT24!AD11+HISTONOV24!AD11+HISTODEC24!AD11 -> 16000 | AE11: =HISTOJANV24!AE11+HISTOFEV24!AE11+HISTOMARS24!AE11+HISTOAVRIL24!AE11+HISTOMAI24!AE11+HISTOJUIN24!AE11+HISTOJUIL24!AE11+HISTOAOUT24!AE11+HISTOSEPT24!AE11+HISTOOCT24!AE11+HISTONOV24!AE11+HISTODEC24!AE11 -> 0 | AH11: =HISTOJANV24!AH11+HISTOFEV24!AH11+HISTOMARS24!AH11+HISTOAVRIL24!AH11+HISTOMAI24!AH11+HISTOJUIN24!AH11+HISTOJUIL24!AH11+HISTOAOUT24!AH11+HISTOSEPT24!AH11+HISTOOCT24!AH11+HISTONOV24!AH11+HISTODEC24!AH11 -> 0 | AI11: =HISTOJANV24!AI11+HISTOFEV24!AI11+HISTOMARS24!AI11+HISTOAVRIL24!AI11+HISTOMAI24!AI11+HISTOJUIN24!AI11+HISTOJUIL24!AI11+HISTOAOUT24!AI11+HISTOSEPT24!AI11+HISTOOCT24!AI11+HISTONOV24!AI11+HISTODEC24!AI11 -> 40000 | AJ11: =HISTOJANV24!AJ11+HISTOFEV24!AJ11+HISTOMARS24!AJ11+HISTOAVRIL24!AJ11+HISTOMAI24!AJ11+HISTOJUIN24!AJ11+HISTOJUIL24!AJ11+HISTOAOUT24!AJ11+HISTOSEPT24!AJ11+HISTOOCT24!AJ11+HISTONOV24!AJ11+HISTODEC24!AJ11 -> 200000 | AK11: =HISTOJANV24!AK11+HISTOFEV24!AK11+HISTOMARS24!AK11+HISTOAVRIL24!AK11+HISTOMAI24!AK11+HISTOJUIN24!AK11+HISTOJUIL24!AK11+HISTOAOUT24!AK11+HISTOSEPT24!AK11+HISTOOCT24!AK11+HISTONOV24!AK11+HISTODEC24!AK11 -> 0 | AL11: =HISTOJANV24!AL11+HISTOFEV24!AL11+HISTOMARS24!AL11+HISTOAVRIL24!AL11+HISTOMAI24!AL11+HISTOJUIN24!AL11+HISTOJUIL24!AL11+HISTOAOUT24!AL11+HISTOSEPT24!AL11+HISTOOCT24!AL11+HISTONOV24!AL11+HISTODEC24!AL11 -> 1000 | AM11: =HISTOJANV24!AM11+HISTOFEV24!AM11+HISTOMARS24!AM11+HISTOAVRIL24!AM11+HISTOMAI24!AM11+HISTOJUIN24!AM11+HISTOJUIL24!AM11+HISTOAOUT24!AM11+HISTOSEPT24!AM11+HISTOOCT24!AM11+HISTONOV24!AM11+HISTODEC24!AM11 -> 5000 | AN11: =HISTOJANV24!AN11+HISTOFEV24!AN11+HISTOMARS24!AN11+HISTOAVRIL24!AN11+HISTOMAI24!AN11+HISTOJUIN24!AN11+HISTOJUIL24!AN11+HISTOAOUT24!AN11+HISTOSEPT24!AN11+HISTOOCT24!AN11+HISTONOV24!AN11+HISTODEC24!AN11 -> 0 | AQ11: =IF(H11="ECHEC",((K11+M11+O11)*20/100),0) -> 0 | AR11: =IF(H11="ECHEC",((K11+M11+O11)*20/100),0) -> 0 | AS11: =IF(H11="ECHEC",0,(K11+I11-25000)) -> 25000 | AW11: =HISTOJANV24!AW11+HISTOFEV24!AW11+HISTOMARS24!AW11+HISTOAVRIL24!AW11+HISTOMAI24!AW11+HISTOJUIN24!AW11+HISTOJUIL24!AW11+HISTOAOUT24!AW11+HISTOSEPT24!AW11+HISTOOCT24!AW11+HISTONOV24!AW11+HISTODEC24!AW11 -> 324000 | AX11: =HISTOJANV24!AX11+HISTOFEV24!AX11+HISTOMARS24!AX11+HISTOAVRIL24!AX11+HISTOMAI24!AX11+HISTOJUIN24!AX11+HISTOJUIL24!AX11+HISTOAOUT24!AX11+HISTOSEPT24!AX11+HISTOOCT24!AX11+HISTONOV24!AX11+HISTODEC24!AX11 -> 1084000 | AY11: =HISTOJANV24!AY11+HISTOFEV24!AY11+HISTOMARS24!AY11+HISTOAVRIL24!AY11+HISTOMAI24!AY11+HISTOJUIN24!AY11+HISTOJUIL24!AY11+HISTOAOUT24!AY11+HISTOSEPT24!AY11+HISTOOCT24!AY11+HISTONOV24!AY11+HISTODEC24!AY11 -> 0 | AZ11: =HISTOJANV24!AZ11+HISTOFEV24!AZ11+HISTOMARS24!AZ11+HISTOAVRIL24!AZ11+HISTOMAI24!AZ11+HISTOJUIN24!AZ11+HISTOJUIL24!AZ11+HISTOAOUT24!AZ11+HISTOSEPT24!AZ11+HISTOOCT24!AZ11+HISTONOV24!AZ11+HISTODEC24!AZ11 -> 1388000 | BA11: =HISTOJANV24!BA11+HISTOFEV24!BA11+HISTOMARS24!BA11+HISTOAVRIL24!BA11+HISTOMAI24!BA11+HISTOJUIN24!BA11+HISTOJUIL24!BA11+HISTOAOUT24!BA11+HISTOSEPT24!BA11+HISTOOCT24!BA11+HISTONOV24!BA11+HISTODEC24!BA11 -> 368000 | BB11: =HISTOJANV24!BB11+HISTOFEV24!BB11+HISTOMARS24!BB11+HISTOAVRIL24!BB11+HISTOMAI24!BB11+HISTOJUIN24!BB11+HISTOJUIL24!BB11+HISTOAOUT24!BB11+HISTOSEPT24!BB11+HISTOOCT24!BB11+HISTONOV24!BB11+HISTODEC24!BB11 -> 0 | BD11: =HISTOJANV24!BD11+HISTOFEV24!BD11+HISTOMARS24!BD11+HISTOAVRIL24!BD11+HISTOMAI24!BD11+HISTOJUIN24!BD11+HISTOJUIL24!BD11+HISTOAOUT24!BD11+HISTOSEPT24!BD11+HISTOOCT24!BD11+HISTONOV24!BD11+HISTODEC24!BD11 -> 918000 | BF11: =HISTOJANV24!BF11+HISTOFEV24!BF11+HISTOMARS24!BF11+HISTOAVRIL24!BF11+HISTOMAI24!BF11+HISTOJUIN24!BF11+HISTOJUIL24!BF11+HISTOAOUT24!BF11+HISTOSEPT24!BF11+HISTOOCT24!BF11+HISTONOV24!BF11+HISTODEC24!BF11 -> 20000 | BN11: PRODUCTION RAPPORT | BO11: FONDS DE ROULEMENT
A12: AS201608 | B12: =VLOOKUP(A12,[11]LISTADHERENT!A$5:H$50,3,0) -> DJUOMBESSY ANTOINE | D12: =HISTOJANV24!D12+HISTOFEV24!D12+HISTOMARS24!D12+HISTOAVRIL24!D12+HISTOMAI24!D12+HISTOJUIN24!D12+HISTOJUIL24!D12+HISTOAOUT24!D12+HISTOSEPT24!D12+HISTOOCT24!D12+HISTONOV24!D12+HISTODEC24!D12 -> 1122000 | E12: =HISTOJANV24!E12+HISTOFEV24!E12+HISTOMARS24!E12+HISTOAVRIL24!E12+HISTOMAI24!E12+HISTOJUIN24!E12+HISTOJUIL24!E12+HISTOAOUT24!E12+HISTOSEPT24!E12+HISTOOCT24!E12+HISTONOV24!E12+HISTODEC24!E12 -> 0 | F12: =HISTOJANV24!F12+HISTOFEV24!F12+HISTOMARS24!F12+HISTOAVRIL24!F12+HISTOMAI24!F12+HISTOJUIN24!F12+HISTOJUIL24!F12+HISTOAOUT24!F12+HISTOSEPT24!F12+HISTOOCT24!F12+HISTONOV24!F12+HISTODEC24!F12 -> 0 | G12: =HISTOJANV24!G12+HISTOFEV24!G12+HISTOMARS24!G12+HISTOAVRIL24!G12+HISTOMAI24!G12+HISTOJUIN24!G12+HISTOJUIL24!G12+HISTOAOUT24!G12+HISTOSEPT24!G12+HISTOOCT24!G12+HISTONOV24!G12+HISTODEC24!G12 -> 0 | I12: =HISTOJANV24!I12+HISTOFEV24!I12+HISTOMARS24!I12+HISTOAVRIL24!I12+HISTOMAI24!I12+HISTOJUIN24!I12+HISTOJUIL24!I12+HISTOAOUT24!I12+HISTOSEPT24!I12+HISTOOCT24!I12+HISTONOV24!I12+HISTODEC24!I12 -> 15000 | J12: 1 | K12: =IF($D12<>0,J12*50000,IF($E12<>0,J12*50000,0)) -> 50000 | L12: 1 | M12: =IF($D12<>0,L12*75000,IF($E12<>0,L12*75000,0)) -> 75000 | N12: 2 | O12: =IF($D12<>0,N12*100000,IF($E12<>0,N12*100000,0)) -> 200000 | P12: =HISTOJANV24!P12+HISTOFEV24!P12+HISTOMARS24!P12+HISTOAVRIL24!P12+HISTOMAI24!P12+HISTOJUIN24!P12+HISTOJUIL24!P12+HISTOAOUT24!P12+HISTOSEPT24!P12+HISTOOCT24!P12+HISTONOV24!P12+HISTODEC24!P12 -> 0 | Q12: =HISTOJANV24!Q12+HISTOFEV24!Q12+HISTOMARS24!Q12+HISTOAVRIL24!Q12+HISTOMAI24!Q12+HISTOJUIN24!Q12+HISTOJUIL24!Q12+HISTOAOUT24!Q12+HISTOSEPT24!Q12+HISTOOCT24!Q12+HISTONOV24!Q12+HISTODEC24!Q12 -> 0 | R12: =HISTOJANV24!R12+HISTOFEV24!R12+HISTOMARS24!R12+HISTOAVRIL24!R12+HISTOMAI24!R12+HISTOJUIN24!R12+HISTOJUIL24!R12+HISTOAOUT24!R12+HISTOSEPT24!R12+HISTOOCT24!R12+HISTONOV24!R12+HISTODEC24!R12 -> 132000 | S12: =HISTOJANV24!S12+HISTOFEV24!S12+HISTOMARS24!S12+HISTOAVRIL24!S12+HISTOMAI24!S12+HISTOJUIN24!S12+HISTOJUIL24!S12+HISTOAOUT24!S12+HISTOSEPT24!S12+HISTOOCT24!S12+HISTONOV24!S12+HISTODEC24!S12 -> 0 | U12: =G12+S12++R12+P12+O12+M12+I12+K12+Q12+V12+W12 -> 472000 | V12: =HISTOJANV24!V12+HISTOFEV24!V12+HISTOMARS24!V12+HISTOAVRIL24!V12+HISTOMAI24!V12+HISTOJUIN24!V12+HISTOJUIL24!V12+HISTOAOUT24!V12+HISTOSEPT24!V12+HISTOOCT24!V12+HISTONOV24!V12+HISTODEC24!V12 -> 0 | W12: =HISTOJANV24!W12+HISTOFEV24!W12+HISTOMARS24!W12+HISTOAVRIL24!W12+HISTOMAI24!W12+HISTOJUIN24!W12+HISTOJUIL24!W12+HISTOAOUT24!W12+HISTOSEPT24!W12+HISTOOCT24!W12+HISTONOV24!W12+HISTODEC24!W12 -> 0 | X12: =HISTOJANV24!X12+HISTOFEV24!X12+HISTOMARS24!X12+HISTOAVRIL24!X12+HISTOMAI24!X12+HISTOJUIN24!X12+HISTOJUIL24!X12+HISTOAOUT24!X12+HISTOSEPT24!X12+HISTOOCT24!X12+HISTONOV24!X12+HISTODEC24!X12 -> 0 | Y12: =HISTOJANV24!Y12+HISTOFEV24!Y12+HISTOMARS24!Y12+HISTOAVRIL24!Y12+HISTOMAI24!Y12+HISTOJUIN24!Y12+HISTOJUIL24!Y12+HISTOAOUT24!Y12+HISTOSEPT24!Y12+HISTOOCT24!Y12+HISTONOV24!Y12+HISTODEC24!Y12 -> 0 | Z12: =HISTOJANV24!Z12+HISTOFEV24!Z12+HISTOMARS24!Z12+HISTOAVRIL24!Z12+HISTOMAI24!Z12+HISTOJUIN24!Z12+HISTOJUIL24!Z12+HISTOAOUT24!Z12+HISTOSEPT24!Z12+HISTOOCT24!Z12+HISTONOV24!Z12+HISTODEC24!Z12 -> 0 | AC12: =HISTOJANV24!AC12+HISTOFEV24!AC12+HISTOMARS24!AC12+HISTOAVRIL24!AC12+HISTOMAI24!AC12+HISTOJUIN24!AC12+HISTOJUIL24!AC12+HISTOAOUT24!AC12+HISTOSEPT24!AC12+HISTOOCT24!AC12+HISTONOV24!AC12+HISTODEC24!AC12 -> 0 | AD12: =HISTOJANV24!AD12+HISTOFEV24!AD12+HISTOMARS24!AD12+HISTOAVRIL24!AD12+HISTOMAI24!AD12+HISTOJUIN24!AD12+HISTOJUIL24!AD12+HISTOAOUT24!AD12+HISTOSEPT24!AD12+HISTOOCT24!AD12+HISTONOV24!AD12+HISTODEC24!AD12 -> 60000 | AE12: =HISTOJANV24!AE12+HISTOFEV24!AE12+HISTOMARS24!AE12+HISTOAVRIL24!AE12+HISTOMAI24!AE12+HISTOJUIN24!AE12+HISTOJUIL24!AE12+HISTOAOUT24!AE12+HISTOSEPT24!AE12+HISTOOCT24!AE12+HISTONOV24!AE12+HISTODEC24!AE12 -> 0 | AH12: =HISTOJANV24!AH12+HISTOFEV24!AH12+HISTOMARS24!AH12+HISTOAVRIL24!AH12+HISTOMAI24!AH12+HISTOJUIN24!AH12+HISTOJUIL24!AH12+HISTOAOUT24!AH12+HISTOSEPT24!AH12+HISTOOCT24!AH12+HISTONOV24!AH12+HISTODEC24!AH12 -> 0 | AI12: =HISTOJANV24!AI12+HISTOFEV24!AI12+HISTOMARS24!AI12+HISTOAVRIL24!AI12+HISTOMAI24!AI12+HISTOJUIN24!AI12+HISTOJUIL24!AI12+HISTOAOUT24!AI12+HISTOSEPT24!AI12+HISTOOCT24!AI12+HISTONOV24!AI12+HISTODEC24!AI12 -> 0 | AJ12: =HISTOJANV24!AJ12+HISTOFEV24!AJ12+HISTOMARS24!AJ12+HISTOAVRIL24!AJ12+HISTOMAI24!AJ12+HISTOJUIN24!AJ12+HISTOJUIL24!AJ12+HISTOAOUT24!AJ12+HISTOSEPT24!AJ12+HISTOOCT24!AJ12+HISTONOV24!AJ12+HISTODEC24!AJ12 -> 0 | AK12: =HISTOJANV24!AK12+HISTOFEV24!AK12+HISTOMARS24!AK12+HISTOAVRIL24!AK12+HISTOMAI24!AK12+HISTOJUIN24!AK12+HISTOJUIL24!AK12+HISTOAOUT24!AK12+HISTOSEPT24!AK12+HISTOOCT24!AK12+HISTONOV24!AK12+HISTODEC24!AK12 -> 131000 | AL12: =HISTOJANV24!AL12+HISTOFEV24!AL12+HISTOMARS24!AL12+HISTOAVRIL24!AL12+HISTOMAI24!AL12+HISTOJUIN24!AL12+HISTOJUIL24!AL12+HISTOAOUT24!AL12+HISTOSEPT24!AL12+HISTOOCT24!AL12+HISTONOV24!AL12+HISTODEC24!AL12 -> 0 | AM12: =HISTOJANV24!AM12+HISTOFEV24!AM12+HISTOMARS24!AM12+HISTOAVRIL24!AM12+HISTOMAI24!AM12+HISTOJUIN24!AM12+HISTOJUIL24!AM12+HISTOAOUT24!AM12+HISTOSEPT24!AM12+HISTOOCT24!AM12+HISTONOV24!AM12+HISTODEC24!AM12 -> 0 | AN12: =HISTOJANV24!AN12+HISTOFEV24!AN12+HISTOMARS24!AN12+HISTOAVRIL24!AN12+HISTOMAI24!AN12+HISTOJUIN24!AN12+HISTOJUIL24!AN12+HISTOAOUT24!AN12+HISTOSEPT24!AN12+HISTOOCT24!AN12+HISTONOV24!AN12+HISTODEC24!AN12 -> 1000 | AQ12: =IF(H12="ECHEC",((K12+M12+O12)*20/100),0) -> 0 | AR12: =IF(H12="ECHEC",((K12+M12+O12)*20/100),0) -> 0 | AS12: =IF(H12="ECHEC",0,(K12+I12-25000)) -> 40000 | AW12: =HISTOJANV24!AW12+HISTOFEV24!AW12+HISTOMARS24!AW12+HISTOAVRIL24!AW12+HISTOMAI24!AW12+HISTOJUIN24!AW12+HISTOJUIL24!AW12+HISTOAOUT24!AW12+HISTOSEPT24!AW12+HISTOOCT24!AW12+HISTONOV24!AW12+HISTODEC24!AW12 -> 0 | AX12: =HISTOJANV24!AX12+HISTOFEV24!AX12+HISTOMARS24!AX12+HISTOAVRIL24!AX12+HISTOMAI24!AX12+HISTOJUIN24!AX12+HISTOJUIL24!AX12+HISTOAOUT24!AX12+HISTOSEPT24!AX12+HISTOOCT24!AX12+HISTONOV24!AX12+HISTODEC24!AX12 -> 840000 | AY12: =HISTOJANV24!AY12+HISTOFEV24!AY12+HISTOMARS24!AY12+HISTOAVRIL24!AY12+HISTOMAI24!AY12+HISTOJUIN24!AY12+HISTOJUIL24!AY12+HISTOAOUT24!AY12+HISTOSEPT24!AY12+HISTOOCT24!AY12+HISTONOV24!AY12+HISTODEC24!AY12 -> 131000 | AZ12: =HISTOJANV24!AZ12+HISTOFEV24!AZ12+HISTOMARS24!AZ12+HISTOAVRIL24!AZ12+HISTOMAI24!AZ12+HISTOJUIN24!AZ12+HISTOJUIL24!AZ12+HISTOAOUT24!AZ12+HISTOSEPT24!AZ12+HISTOOCT24!AZ12+HISTONOV24!AZ12+HISTODEC24!AZ12 -> 971000 | BA12: =HISTOJANV24!BA12+HISTOFEV24!BA12+HISTOMARS24!BA12+HISTOAVRIL24!BA12+HISTOMAI24!BA12+HISTOJUIN24!BA12+HISTOJUIL24!BA12+HISTOAOUT24!BA12+HISTOSEPT24!BA12+HISTOOCT24!BA12+HISTONOV24!BA12+HISTODEC24!BA12 -> 66700 | BB12: =HISTOJANV24!BB12+HISTOFEV24!BB12+HISTOMARS24!BB12+HISTOAVRIL24!BB12+HISTOMAI24!BB12+HISTOJUIN24!BB12+HISTOJUIL24!BB12+HISTOAOUT24!BB12+HISTOSEPT24!BB12+HISTOOCT24!BB12+HISTONOV24!BB12+HISTODEC24!BB12 -> 0 | BD12: =HISTOJANV24!BD12+HISTOFEV24!BD12+HISTOMARS24!BD12+HISTOAVRIL24!BD12+HISTOMAI24!BD12+HISTOJUIN24!BD12+HISTOJUIL24!BD12+HISTOAOUT24!BD12+HISTOSEPT24!BD12+HISTOOCT24!BD12+HISTONOV24!BD12+HISTODEC24!BD12 -> 909300 | BF12: =HISTOJANV24!BF12+HISTOFEV24!BF12+HISTOMARS24!BF12+HISTOAVRIL24!BF12+HISTOMAI24!BF12+HISTOJUIN24!BF12+HISTOJUIL24!BF12+HISTOAOUT24!BF12+HISTOSEPT24!BF12+HISTOOCT24!BF12+HISTONOV24!BF12+HISTODEC24!BF12 -> 0 | BN12: ACHAT SOURIS ET PHOTOCOPIE | BO12: FONDS DE ROULEMENT
A13: AS201651 | B13: =VLOOKUP(A13,[11]LISTADHERENT!A$5:H$50,3,0) -> DOMOU FABIEN | D13: =HISTOJANV24!D13+HISTOFEV24!D13+HISTOMARS24!D13+HISTOAVRIL24!D13+HISTOMAI24!D13+HISTOJUIN24!D13+HISTOJUIL24!D13+HISTOAOUT24!D13+HISTOSEPT24!D13+HISTOOCT24!D13+HISTONOV24!D13+HISTODEC24!D13 -> 150000 | E13: =HISTOJANV24!E13+HISTOFEV24!E13+HISTOMARS24!E13+HISTOAVRIL24!E13+HISTOMAI24!E13+HISTOJUIN24!E13+HISTOJUIL24!E13+HISTOAOUT24!E13+HISTOSEPT24!E13+HISTOOCT24!E13+HISTONOV24!E13+HISTODEC24!E13 -> 0 | F13: =HISTOJANV24!F13+HISTOFEV24!F13+HISTOMARS24!F13+HISTOAVRIL24!F13+HISTOMAI24!F13+HISTOJUIN24!F13+HISTOJUIL24!F13+HISTOAOUT24!F13+HISTOSEPT24!F13+HISTOOCT24!F13+HISTONOV24!F13+HISTODEC24!F13 -> 0 | G13: =HISTOJANV24!G13+HISTOFEV24!G13+HISTOMARS24!G13+HISTOAVRIL24!G13+HISTOMAI24!G13+HISTOJUIN24!G13+HISTOJUIL24!G13+HISTOAOUT24!G13+HISTOSEPT24!G13+HISTOOCT24!G13+HISTONOV24!G13+HISTODEC24!G13 -> 0 | I13: =HISTOJANV24!I13+HISTOFEV24!I13+HISTOMARS24!I13+HISTOAVRIL24!I13+HISTOMAI24!I13+HISTOJUIN24!I13+HISTOJUIL24!I13+HISTOAOUT24!I13+HISTOSEPT24!I13+HISTOOCT24!I13+HISTONOV24!I13+HISTODEC24!I13 -> 0 | J13: 1 | K13: =IF($D13<>0,J13*50000,IF($E13<>0,J13*50000,0)) -> 50000 | M13: =IF($D13<>0,L13*75000,IF($E13<>0,L13*75000,0)) -> 0 | O13: =IF($D13<>0,N13*100000,IF($E13<>0,N13*100000,0)) -> 0 | P13: =HISTOJANV24!P13+HISTOFEV24!P13+HISTOMARS24!P13+HISTOAVRIL24!P13+HISTOMAI24!P13+HISTOJUIN24!P13+HISTOJUIL24!P13+HISTOAOUT24!P13+HISTOSEPT24!P13+HISTOOCT24!P13+HISTONOV24!P13+HISTODEC24!P13 -> 0 | Q13: =HISTOJANV24!Q13+HISTOFEV24!Q13+HISTOMARS24!Q13+HISTOAVRIL24!Q13+HISTOMAI24!Q13+HISTOJUIN24!Q13+HISTOJUIL24!Q13+HISTOAOUT24!Q13+HISTOSEPT24!Q13+HISTOOCT24!Q13+HISTONOV24!Q13+HISTODEC24!Q13 -> 0 | R13: =HISTOJANV24!R13+HISTOFEV24!R13+HISTOMARS24!R13+HISTOAVRIL24!R13+HISTOMAI24!R13+HISTOJUIN24!R13+HISTOJUIL24!R13+HISTOAOUT24!R13+HISTOSEPT24!R13+HISTOOCT24!R13+HISTONOV24!R13+HISTODEC24!R13 -> 0 | S13: =HISTOJANV24!S13+HISTOFEV24!S13+HISTOMARS24!S13+HISTOAVRIL24!S13+HISTOMAI24!S13+HISTOJUIN24!S13+HISTOJUIL24!S13+HISTOAOUT24!S13+HISTOSEPT24!S13+HISTOOCT24!S13+HISTONOV24!S13+HISTODEC24!S13 -> 0 | U13: =G13+S13++R13+P13+O13+M13+I13+K13+Q13+V13+W13 -> 50000 | V13: =HISTOJANV24!V13+HISTOFEV24!V13+HISTOMARS24!V13+HISTOAVRIL24!V13+HISTOMAI24!V13+HISTOJUIN24!V13+HISTOJUIL24!V13+HISTOAOUT24!V13+HISTOSEPT24!V13+HISTOOCT24!V13+HISTONOV24!V13+HISTODEC24!V13 -> 0 | W13: =HISTOJANV24!W13+HISTOFEV24!W13+HISTOMARS24!W13+HISTOAVRIL24!W13+HISTOMAI24!W13+HISTOJUIN24!W13+HISTOJUIL24!W13+HISTOAOUT24!W13+HISTOSEPT24!W13+HISTOOCT24!W13+HISTONOV24!W13+HISTODEC24!W13 -> 0 | X13: =HISTOJANV24!X13+HISTOFEV24!X13+HISTOMARS24!X13+HISTOAVRIL24!X13+HISTOMAI24!X13+HISTOJUIN24!X13+HISTOJUIL24!X13+HISTOAOUT24!X13+HISTOSEPT24!X13+HISTOOCT24!X13+HISTONOV24!X13+HISTODEC24!X13 -> 0 | Y13: =HISTOJANV24!Y13+HISTOFEV24!Y13+HISTOMARS24!Y13+HISTOAVRIL24!Y13+HISTOMAI24!Y13+HISTOJUIN24!Y13+HISTOJUIL24!Y13+HISTOAOUT24!Y13+HISTOSEPT24!Y13+HISTOOCT24!Y13+HISTONOV24!Y13+HISTODEC24!Y13 -> 0 | Z13: =HISTOJANV24!Z13+HISTOFEV24!Z13+HISTOMARS24!Z13+HISTOAVRIL24!Z13+HISTOMAI24!Z13+HISTOJUIN24!Z13+HISTOJUIL24!Z13+HISTOAOUT24!Z13+HISTOSEPT24!Z13+HISTOOCT24!Z13+HISTONOV24!Z13+HISTODEC24!Z13 -> 0 | AC13: =HISTOJANV24!AC13+HISTOFEV24!AC13+HISTOMARS24!AC13+HISTOAVRIL24!AC13+HISTOMAI24!AC13+HISTOJUIN24!AC13+HISTOJUIL24!AC13+HISTOAOUT24!AC13+HISTOSEPT24!AC13+HISTOOCT24!AC13+HISTONOV24!AC13+HISTODEC24!AC13 -> 0 | AD13: =HISTOJANV24!AD13+HISTOFEV24!AD13+HISTOMARS24!AD13+HISTOAVRIL24!AD13+HISTOMAI24!AD13+HISTOJUIN24!AD13+HISTOJUIL24!AD13+HISTOAOUT24!AD13+HISTOSEPT24!AD13+HISTOOCT24!AD13+HISTONOV24!AD13+HISTODEC24!AD13 -> 0 | AE13: =HISTOJANV24!AE13+HISTOFEV24!AE13+HISTOMARS24!AE13+HISTOAVRIL24!AE13+HISTOMAI24!AE13+HISTOJUIN24!AE13+HISTOJUIL24!AE13+HISTOAOUT24!AE13+HISTOSEPT24!AE13+HISTOOCT24!AE13+HISTONOV24!AE13+HISTODEC24!AE13 -> 0 | AH13: =HISTOJANV24!AH13+HISTOFEV24!AH13+HISTOMARS24!AH13+HISTOAVRIL24!AH13+HISTOMAI24!AH13+HISTOJUIN24!AH13+HISTOJUIL24!AH13+HISTOAOUT24!AH13+HISTOSEPT24!AH13+HISTOOCT24!AH13+HISTONOV24!AH13+HISTODEC24!AH13 -> 0 | AI13: =HISTOJANV24!AI13+HISTOFEV24!AI13+HISTOMARS24!AI13+HISTOAVRIL24!AI13+HISTOMAI24!AI13+HISTOJUIN24!AI13+HISTOJUIL24!AI13+HISTOAOUT24!AI13+HISTOSEPT24!AI13+HISTOOCT24!AI13+HISTONOV24!AI13+HISTODEC24!AI13 -> 0 | AJ13: =HISTOJANV24!AJ13+HISTOFEV24!AJ13+HISTOMARS24!AJ13+HISTOAVRIL24!AJ13+HISTOMAI24!AJ13+HISTOJUIN24!AJ13+HISTOJUIL24!AJ13+HISTOAOUT24!AJ13+HISTOSEPT24!AJ13+HISTOOCT24!AJ13+HISTONOV24!AJ13+HISTODEC24!AJ13 -> 0 | AK13: =HISTOJANV24!AK13+HISTOFEV24!AK13+HISTOMARS24!AK13+HISTOAVRIL24!AK13+HISTOMAI24!AK13+HISTOJUIN24!AK13+HISTOJUIL24!AK13+HISTOAOUT24!AK13+HISTOSEPT24!AK13+HISTOOCT24!AK13+HISTONOV24!AK13+HISTODEC24!AK13 -> 0 | AL13: =HISTOJANV24!AL13+HISTOFEV24!AL13+HISTOMARS24!AL13+HISTOAVRIL24!AL13+HISTOMAI24!AL13+HISTOJUIN24!AL13+HISTOJUIL24!AL13+HISTOAOUT24!AL13+HISTOSEPT24!AL13+HISTOOCT24!AL13+HISTONOV24!AL13+HISTODEC24!AL13 -> 0 | AM13: =HISTOJANV24!AM13+HISTOFEV24!AM13+HISTOMARS24!AM13+HISTOAVRIL24!AM13+HISTOMAI24!AM13+HISTOJUIN24!AM13+HISTOJUIL24!AM13+HISTOAOUT24!AM13+HISTOSEPT24!AM13+HISTOOCT24!AM13+HISTONOV24!AM13+HISTODEC24!AM13 -> 0 | AN13: =HISTOJANV24!AN13+HISTOFEV24!AN13+HISTOMARS24!AN13+HISTOAVRIL24!AN13+HISTOMAI24!AN13+HISTOJUIN24!AN13+HISTOJUIL24!AN13+HISTOAOUT24!AN13+HISTOSEPT24!AN13+HISTOOCT24!AN13+HISTONOV24!AN13+HISTODEC24!AN13 -> 0 | AQ13: =IF(H13="ECHEC",((K13+M13+O13)*20/100),0) -> 0 | AR13: =IF(H13="ECHEC",((K13+M13+O13)*20/100),0) -> 0 | AS13: =IF(H13="ECHEC",0,(K13+I13-25000)) -> 25000 | AW13: =HISTOJANV24!AW13+HISTOFEV24!AW13+HISTOMARS24!AW13+HISTOAVRIL24!AW13+HISTOMAI24!AW13+HISTOJUIN24!AW13+HISTOJUIL24!AW13+HISTOAOUT24!AW13+HISTOSEPT24!AW13+HISTOOCT24!AW13+HISTONOV24!AW13+HISTODEC24!AW13 -> 0 | AX13: =HISTOJANV24!AX13+HISTOFEV24!AX13+HISTOMARS24!AX13+HISTOAVRIL24!AX13+HISTOMAI24!AX13+HISTOJUIN24!AX13+HISTOJUIL24!AX13+HISTOAOUT24!AX13+HISTOSEPT24!AX13+HISTOOCT24!AX13+HISTONOV24!AX13+HISTODEC24!AX13 -> 0 | AY13: =HISTOJANV24!AY13+HISTOFEV24!AY13+HISTOMARS24!AY13+HISTOAVRIL24!AY13+HISTOMAI24!AY13+HISTOJUIN24!AY13+HISTOJUIL24!AY13+HISTOAOUT24!AY13+HISTOSEPT24!AY13+HISTOOCT24!AY13+HISTONOV24!AY13+HISTODEC24!AY13 -> 0 | AZ13: =HISTOJANV24!AZ13+HISTOFEV24!AZ13+HISTOMARS24!AZ13+HISTOAVRIL24!AZ13+HISTOMAI24!AZ13+HISTOJUIN24!AZ13+HISTOJUIL24!AZ13+HISTOAOUT24!AZ13+HISTOSEPT24!AZ13+HISTOOCT24!AZ13+HISTONOV24!AZ13+HISTODEC24!AZ13 -> 0 | BA13: =HISTOJANV24!BA13+HISTOFEV24!BA13+HISTOMARS24!BA13+HISTOAVRIL24!BA13+HISTOMAI24!BA13+HISTOJUIN24!BA13+HISTOJUIL24!BA13+HISTOAOUT24!BA13+HISTOSEPT24!BA13+HISTOOCT24!BA13+HISTONOV24!BA13+HISTODEC24!BA13 -> 0 | BB13: =HISTOJANV24!BB13+HISTOFEV24!BB13+HISTOMARS24!BB13+HISTOAVRIL24!BB13+HISTOMAI24!BB13+HISTOJUIN24!BB13+HISTOJUIL24!BB13+HISTOAOUT24!BB13+HISTOSEPT24!BB13+HISTOOCT24!BB13+HISTONOV24!BB13+HISTODEC24!BB13 -> 0 | BD13: =HISTOJANV24!BD13+HISTOFEV24!BD13+HISTOMARS24!BD13+HISTOAVRIL24!BD13+HISTOMAI24!BD13+HISTOJUIN24!BD13+HISTOJUIL24!BD13+HISTOAOUT24!BD13+HISTOSEPT24!BD13+HISTOOCT24!BD13+HISTONOV24!BD13+HISTODEC24!BD13 -> 0 | BF13: =HISTOJANV24!BF13+HISTOFEV24!BF13+HISTOMARS24!BF13+HISTOAVRIL24!BF13+HISTOMAI24!BF13+HISTOJUIN24!BF13+HISTOJUIL24!BF13+HISTOAOUT24!BF13+HISTOSEPT24!BF13+HISTOOCT24!BF13+HISTONOV24!BF13+HISTODEC24!BF13 -> 0 | BN13: TAXI BANQUE | BO13: FONDS DE ROULEMENT
A14: AS201609 | B14: =VLOOKUP(A14,[11]LISTADHERENT!A$5:H$50,3,0) -> DONHOU DAVID | D14: =HISTOJANV24!D14+HISTOFEV24!D14+HISTOMARS24!D14+HISTOAVRIL24!D14+HISTOMAI24!D14+HISTOJUIN24!D14+HISTOJUIL24!D14+HISTOAOUT24!D14+HISTOSEPT24!D14+HISTOOCT24!D14+HISTONOV24!D14+HISTODEC24!D14 -> 100000 | E14: =HISTOJANV24!E14+HISTOFEV24!E14+HISTOMARS24!E14+HISTOAVRIL24!E14+HISTOMAI24!E14+HISTOJUIN24!E14+HISTOJUIL24!E14+HISTOAOUT24!E14+HISTOSEPT24!E14+HISTOOCT24!E14+HISTONOV24!E14+HISTODEC24!E14 -> 50000 | F14: =HISTOJANV24!F14+HISTOFEV24!F14+HISTOMARS24!F14+HISTOAVRIL24!F14+HISTOMAI24!F14+HISTOJUIN24!F14+HISTOJUIL24!F14+HISTOAOUT24!F14+HISTOSEPT24!F14+HISTOOCT24!F14+HISTONOV24!F14+HISTODEC24!F14 -> 0 | G14: =HISTOJANV24!G14+HISTOFEV24!G14+HISTOMARS24!G14+HISTOAVRIL24!G14+HISTOMAI24!G14+HISTOJUIN24!G14+HISTOJUIL24!G14+HISTOAOUT24!G14+HISTOSEPT24!G14+HISTOOCT24!G14+HISTONOV24!G14+HISTODEC24!G14 -> 0 | I14: =HISTOJANV24!I14+HISTOFEV24!I14+HISTOMARS24!I14+HISTOAVRIL24!I14+HISTOMAI24!I14+HISTOJUIN24!I14+HISTOJUIL24!I14+HISTOAOUT24!I14+HISTOSEPT24!I14+HISTOOCT24!I14+HISTONOV24!I14+HISTODEC24!I14 -> 0 | J14: 1 | K14: =IF($D14<>0,J14*50000,IF($E14<>0,J14*50000,0)) -> 50000 | M14: =IF($D14<>0,L14*75000,IF($E14<>0,L14*75000,0)) -> 0 | O14: =IF($D14<>0,N14*100000,IF($E14<>0,N14*100000,0)) -> 0 | P14: =HISTOJANV24!P14+HISTOFEV24!P14+HISTOMARS24!P14+HISTOAVRIL24!P14+HISTOMAI24!P14+HISTOJUIN24!P14+HISTOJUIL24!P14+HISTOAOUT24!P14+HISTOSEPT24!P14+HISTOOCT24!P14+HISTONOV24!P14+HISTODEC24!P14 -> 0 | Q14: =HISTOJANV24!Q14+HISTOFEV24!Q14+HISTOMARS24!Q14+HISTOAVRIL24!Q14+HISTOMAI24!Q14+HISTOJUIN24!Q14+HISTOJUIL24!Q14+HISTOAOUT24!Q14+HISTOSEPT24!Q14+HISTOOCT24!Q14+HISTONOV24!Q14+HISTODEC24!Q14 -> 0 | R14: =HISTOJANV24!R14+HISTOFEV24!R14+HISTOMARS24!R14+HISTOAVRIL24!R14+HISTOMAI24!R14+HISTOJUIN24!R14+HISTOJUIL24!R14+HISTOAOUT24!R14+HISTOSEPT24!R14+HISTOOCT24!R14+HISTONOV24!R14+HISTODEC24!R14 -> 0 | S14: =HISTOJANV24!S14+HISTOFEV24!S14+HISTOMARS24!S14+HISTOAVRIL24!S14+HISTOMAI24!S14+HISTOJUIN24!S14+HISTOJUIL24!S14+HISTOAOUT24!S14+HISTOSEPT24!S14+HISTOOCT24!S14+HISTONOV24!S14+HISTODEC24!S14 -> 0 | U14: =G14+S14++R14+P14+O14+M14+I14+K14+Q14+V14+W14 -> 50000 | V14: =HISTOJANV24!V14+HISTOFEV24!V14+HISTOMARS24!V14+HISTOAVRIL24!V14+HISTOMAI24!V14+HISTOJUIN24!V14+HISTOJUIL24!V14+HISTOAOUT24!V14+HISTOSEPT24!V14+HISTOOCT24!V14+HISTONOV24!V14+HISTODEC24!V14 -> 0 | W14: =HISTOJANV24!W14+HISTOFEV24!W14+HISTOMARS24!W14+HISTOAVRIL24!W14+HISTOMAI24!W14+HISTOJUIN24!W14+HISTOJUIL24!W14+HISTOAOUT24!W14+HISTOSEPT24!W14+HISTOOCT24!W14+HISTONOV24!W14+HISTODEC24!W14 -> 0 | X14: =HISTOJANV24!X14+HISTOFEV24!X14+HISTOMARS24!X14+HISTOAVRIL24!X14+HISTOMAI24!X14+HISTOJUIN24!X14+HISTOJUIL24!X14+HISTOAOUT24!X14+HISTOSEPT24!X14+HISTOOCT24!X14+HISTONOV24!X14+HISTODEC24!X14 -> 0 | Y14: =HISTOJANV24!Y14+HISTOFEV24!Y14+HISTOMARS24!Y14+HISTOAVRIL24!Y14+HISTOMAI24!Y14+HISTOJUIN24!Y14+HISTOJUIL24!Y14+HISTOAOUT24!Y14+HISTOSEPT24!Y14+HISTOOCT24!Y14+HISTONOV24!Y14+HISTODEC24!Y14 -> 0 | Z14: =HISTOJANV24!Z14+HISTOFEV24!Z14+HISTOMARS24!Z14+HISTOAVRIL24!Z14+HISTOMAI24!Z14+HISTOJUIN24!Z14+HISTOJUIL24!Z14+HISTOAOUT24!Z14+HISTOSEPT24!Z14+HISTOOCT24!Z14+HISTONOV24!Z14+HISTODEC24!Z14 -> 0 | AC14: =HISTOJANV24!AC14+HISTOFEV24!AC14+HISTOMARS24!AC14+HISTOAVRIL24!AC14+HISTOMAI24!AC14+HISTOJUIN24!AC14+HISTOJUIL24!AC14+HISTOAOUT24!AC14+HISTOSEPT24!AC14+HISTOOCT24!AC14+HISTONOV24!AC14+HISTODEC24!AC14 -> 0 | AD14: =HISTOJANV24!AD14+HISTOFEV24!AD14+HISTOMARS24!AD14+HISTOAVRIL24!AD14+HISTOMAI24!AD14+HISTOJUIN24!AD14+HISTOJUIL24!AD14+HISTOAOUT24!AD14+HISTOSEPT24!AD14+HISTOOCT24!AD14+HISTONOV24!AD14+HISTODEC24!AD14 -> 0 | AE14: =HISTOJANV24!AE14+HISTOFEV24!AE14+HISTOMARS24!AE14+HISTOAVRIL24!AE14+HISTOMAI24!AE14+HISTOJUIN24!AE14+HISTOJUIL24!AE14+HISTOAOUT24!AE14+HISTOSEPT24!AE14+HISTOOCT24!AE14+HISTONOV24!AE14+HISTODEC24!AE14 -> 0 | AH14: =HISTOJANV24!AH14+HISTOFEV24!AH14+HISTOMARS24!AH14+HISTOAVRIL24!AH14+HISTOMAI24!AH14+HISTOJUIN24!AH14+HISTOJUIL24!AH14+HISTOAOUT24!AH14+HISTOSEPT24!AH14+HISTOOCT24!AH14+HISTONOV24!AH14+HISTODEC24!AH14 -> 0 | AI14: =HISTOJANV24!AI14+HISTOFEV24!AI14+HISTOMARS24!AI14+HISTOAVRIL24!AI14+HISTOMAI24!AI14+HISTOJUIN24!AI14+HISTOJUIL24!AI14+HISTOAOUT24!AI14+HISTOSEPT24!AI14+HISTOOCT24!AI14+HISTONOV24!AI14+HISTODEC24!AI14 -> 0 | AJ14: =HISTOJANV24!AJ14+HISTOFEV24!AJ14+HISTOMARS24!AJ14+HISTOAVRIL24!AJ14+HISTOMAI24!AJ14+HISTOJUIN24!AJ14+HISTOJUIL24!AJ14+HISTOAOUT24!AJ14+HISTOSEPT24!AJ14+HISTOOCT24!AJ14+HISTONOV24!AJ14+HISTODEC24!AJ14 -> 0 | AK14: =HISTOJANV24!AK14+HISTOFEV24!AK14+HISTOMARS24!AK14+HISTOAVRIL24!AK14+HISTOMAI24!AK14+HISTOJUIN24!AK14+HISTOJUIL24!AK14+HISTOAOUT24!AK14+HISTOSEPT24!AK14+HISTOOCT24!AK14+HISTONOV24!AK14+HISTODEC24!AK14 -> 0 | AL14: =HISTOJANV24!AL14+HISTOFEV24!AL14+HISTOMARS24!AL14+HISTOAVRIL24!AL14+HISTOMAI24!AL14+HISTOJUIN24!AL14+HISTOJUIL24!AL14+HISTOAOUT24!AL14+HISTOSEPT24!AL14+HISTOOCT24!AL14+HISTONOV24!AL14+HISTODEC24!AL14 -> 0 | AM14: =HISTOJANV24!AM14+HISTOFEV24!AM14+HISTOMARS24!AM14+HISTOAVRIL24!AM14+HISTOMAI24!AM14+HISTOJUIN24!AM14+HISTOJUIL24!AM14+HISTOAOUT24!AM14+HISTOSEPT24!AM14+HISTOOCT24!AM14+HISTONOV24!AM14+HISTODEC24!AM14 -> 0 | AN14: =HISTOJANV24!AN14+HISTOFEV24!AN14+HISTOMARS24!AN14+HISTOAVRIL24!AN14+HISTOMAI24!AN14+HISTOJUIN24!AN14+HISTOJUIL24!AN14+HISTOAOUT24!AN14+HISTOSEPT24!AN14+HISTOOCT24!AN14+HISTONOV24!AN14+HISTODEC24!AN14 -> 0 | AQ14: =IF(H14="ECHEC",((K14+M14+O14)*20/100),0) -> 0 | AR14: =IF(H14="ECHEC",((K14+M14+O14)*20/100),0) -> 0 | AS14: =IF(H14="ECHEC",0,(K14+I14-25000)) -> 25000 | AW14: =HISTOJANV24!AW14+HISTOFEV24!AW14+HISTOMARS24!AW14+HISTOAVRIL24!AW14+HISTOMAI24!AW14+HISTOJUIN24!AW14+HISTOJUIL24!AW14+HISTOAOUT24!AW14+HISTOSEPT24!AW14+HISTOOCT24!AW14+HISTONOV24!AW14+HISTODEC24!AW14 -> 0 | AX14: =HISTOJANV24!AX14+HISTOFEV24!AX14+HISTOMARS24!AX14+HISTOAVRIL24!AX14+HISTOMAI24!AX14+HISTOJUIN24!AX14+HISTOJUIL24!AX14+HISTOAOUT24!AX14+HISTOSEPT24!AX14+HISTOOCT24!AX14+HISTONOV24!AX14+HISTODEC24!AX14 -> 0 | AY14: =HISTOJANV24!AY14+HISTOFEV24!AY14+HISTOMARS24!AY14+HISTOAVRIL24!AY14+HISTOMAI24!AY14+HISTOJUIN24!AY14+HISTOJUIL24!AY14+HISTOAOUT24!AY14+HISTOSEPT24!AY14+HISTOOCT24!AY14+HISTONOV24!AY14+HISTODEC24!AY14 -> 0 | AZ14: =HISTOJANV24!AZ14+HISTOFEV24!AZ14+HISTOMARS24!AZ14+HISTOAVRIL24!AZ14+HISTOMAI24!AZ14+HISTOJUIN24!AZ14+HISTOJUIL24!AZ14+HISTOAOUT24!AZ14+HISTOSEPT24!AZ14+HISTOOCT24!AZ14+HISTONOV24!AZ14+HISTODEC24!AZ14 -> 0 | BA14: =HISTOJANV24!BA14+HISTOFEV24!BA14+HISTOMARS24!BA14+HISTOAVRIL24!BA14+HISTOMAI24!BA14+HISTOJUIN24!BA14+HISTOJUIL24!BA14+HISTOAOUT24!BA14+HISTOSEPT24!BA14+HISTOOCT24!BA14+HISTONOV24!BA14+HISTODEC24!BA14 -> 0 | BB14: =HISTOJANV24!BB14+HISTOFEV24!BB14+HISTOMARS24!BB14+HISTOAVRIL24!BB14+HISTOMAI24!BB14+HISTOJUIN24!BB14+HISTOJUIL24!BB14+HISTOAOUT24!BB14+HISTOSEPT24!BB14+HISTOOCT24!BB14+HISTONOV24!BB14+HISTODEC24!BB14 -> 0 | BD14: =HISTOJANV24!BD14+HISTOFEV24!BD14+HISTOMARS24!BD14+HISTOAVRIL24!BD14+HISTOMAI24!BD14+HISTOJUIN24!BD14+HISTOJUIL24!BD14+HISTOAOUT24!BD14+HISTOSEPT24!BD14+HISTOOCT24!BD14+HISTONOV24!BD14+HISTODEC24!BD14 -> 0 | BF14: =HISTOJANV24!BF14+HISTOFEV24!BF14+HISTOMARS24!BF14+HISTOAVRIL24!BF14+HISTOMAI24!BF14+HISTOJUIN24!BF14+HISTOJUIL24!BF14+HISTOAOUT24!BF14+HISTOSEPT24!BF14+HISTOOCT24!BF14+HISTONOV24!BF14+HISTODEC24!BF14 -> 0 | BN14: CONFECTION CACHET | BO14: FONDS DE ROULEMENT
A15: AS201611 | B15: =VLOOKUP(A15,[11]LISTADHERENT!A$5:H$50,3,0) -> HENGUE PAUL OMER | D15: =HISTOJANV24!D15+HISTOFEV24!D15+HISTOMARS24!D15+HISTOAVRIL24!D15+HISTOMAI24!D15+HISTOJUIN24!D15+HISTOJUIL24!D15+HISTOAOUT24!D15+HISTOSEPT24!D15+HISTOOCT24!D15+HISTONOV24!D15+HISTODEC24!D15 -> 375000 | E15: =HISTOJANV24!E15+HISTOFEV24!E15+HISTOMARS24!E15+HISTOAVRIL24!E15+HISTOMAI24!E15+HISTOJUIN24!E15+HISTOJUIL24!E15+HISTOAOUT24!E15+HISTOSEPT24!E15+HISTOOCT24!E15+HISTONOV24!E15+HISTODEC24!E15 -> 0 | F15: =HISTOJANV24!F15+HISTOFEV24!F15+HISTOMARS24!F15+HISTOAVRIL24!F15+HISTOMAI24!F15+HISTOJUIN24!F15+HISTOJUIL24!F15+HISTOAOUT24!F15+HISTOSEPT24!F15+HISTOOCT24!F15+HISTONOV24!F15+HISTODEC24!F15 -> 0 | G15: =HISTOJANV24!G15+HISTOFEV24!G15+HISTOMARS24!G15+HISTOAVRIL24!G15+HISTOMAI24!G15+HISTOJUIN24!G15+HISTOJUIL24!G15+HISTOAOUT24!G15+HISTOSEPT24!G15+HISTOOCT24!G15+HISTONOV24!G15+HISTODEC24!G15 -> 0 | I15: =HISTOJANV24!I15+HISTOFEV24!I15+HISTOMARS24!I15+HISTOAVRIL24!I15+HISTOMAI24!I15+HISTOJUIN24!I15+HISTOJUIL24!I15+HISTOAOUT24!I15+HISTOSEPT24!I15+HISTOOCT24!I15+HISTONOV24!I15+HISTODEC24!I15 -> 0 | J15: 1 | K15: =IF($D15<>0,J15*50000,IF($E15<>0,J15*50000,0)) -> 50000 | L15: 1 | M15: =IF($D15<>0,L15*75000,IF($E15<>0,L15*75000,0)) -> 75000 | O15: =IF($D15<>0,N15*100000,IF($E15<>0,N15*100000,0)) -> 0 | P15: =HISTOJANV24!P15+HISTOFEV24!P15+HISTOMARS24!P15+HISTOAVRIL24!P15+HISTOMAI24!P15+HISTOJUIN24!P15+HISTOJUIL24!P15+HISTOAOUT24!P15+HISTOSEPT24!P15+HISTOOCT24!P15+HISTONOV24!P15+HISTODEC24!P15 -> 0 | Q15: =HISTOJANV24!Q15+HISTOFEV24!Q15+HISTOMARS24!Q15+HISTOAVRIL24!Q15+HISTOMAI24!Q15+HISTOJUIN24!Q15+HISTOJUIL24!Q15+HISTOAOUT24!Q15+HISTOSEPT24!Q15+HISTOOCT24!Q15+HISTONOV24!Q15+HISTODEC24!Q15 -> 0 | R15: =HISTOJANV24!R15+HISTOFEV24!R15+HISTOMARS24!R15+HISTOAVRIL24!R15+HISTOMAI24!R15+HISTOJUIN24!R15+HISTOJUIL24!R15+HISTOAOUT24!R15+HISTOSEPT24!R15+HISTOOCT24!R15+HISTONOV24!R15+HISTODEC24!R15 -> 0 | S15: =HISTOJANV24!S15+HISTOFEV24!S15+HISTOMARS24!S15+HISTOAVRIL24!S15+HISTOMAI24!S15+HISTOJUIN24!S15+HISTOJUIL24!S15+HISTOAOUT24!S15+HISTOSEPT24!S15+HISTOOCT24!S15+HISTONOV24!S15+HISTODEC24!S15 -> 0 | U15: =G15+S15++R15+P15+O15+M15+I15+K15+Q15+V15+W15 -> 125000 | V15: =HISTOJANV24!V15+HISTOFEV24!V15+HISTOMARS24!V15+HISTOAVRIL24!V15+HISTOMAI24!V15+HISTOJUIN24!V15+HISTOJUIL24!V15+HISTOAOUT24!V15+HISTOSEPT24!V15+HISTOOCT24!V15+HISTONOV24!V15+HISTODEC24!V15 -> 0 | W15: =HISTOJANV24!W15+HISTOFEV24!W15+HISTOMARS24!W15+HISTOAVRIL24!W15+HISTOMAI24!W15+HISTOJUIN24!W15+HISTOJUIL24!W15+HISTOAOUT24!W15+HISTOSEPT24!W15+HISTOOCT24!W15+HISTONOV24!W15+HISTODEC24!W15 -> 0 | X15: =HISTOJANV24!X15+HISTOFEV24!X15+HISTOMARS24!X15+HISTOAVRIL24!X15+HISTOMAI24!X15+HISTOJUIN24!X15+HISTOJUIL24!X15+HISTOAOUT24!X15+HISTOSEPT24!X15+HISTOOCT24!X15+HISTONOV24!X15+HISTODEC24!X15 -> 0 | Y15: =HISTOJANV24!Y15+HISTOFEV24!Y15+HISTOMARS24!Y15+HISTOAVRIL24!Y15+HISTOMAI24!Y15+HISTOJUIN24!Y15+HISTOJUIL24!Y15+HISTOAOUT24!Y15+HISTOSEPT24!Y15+HISTOOCT24!Y15+HISTONOV24!Y15+HISTODEC24!Y15 -> 0 | Z15: =HISTOJANV24!Z15+HISTOFEV24!Z15+HISTOMARS24!Z15+HISTOAVRIL24!Z15+HISTOMAI24!Z15+HISTOJUIN24!Z15+HISTOJUIL24!Z15+HISTOAOUT24!Z15+HISTOSEPT24!Z15+HISTOOCT24!Z15+HISTONOV24!Z15+HISTODEC24!Z15 -> 0 | AC15: =HISTOJANV24!AC15+HISTOFEV24!AC15+HISTOMARS24!AC15+HISTOAVRIL24!AC15+HISTOMAI24!AC15+HISTOJUIN24!AC15+HISTOJUIL24!AC15+HISTOAOUT24!AC15+HISTOSEPT24!AC15+HISTOOCT24!AC15+HISTONOV24!AC15+HISTODEC24!AC15 -> 0 | AD15: =HISTOJANV24!AD15+HISTOFEV24!AD15+HISTOMARS24!AD15+HISTOAVRIL24!AD15+HISTOMAI24!AD15+HISTOJUIN24!AD15+HISTOJUIL24!AD15+HISTOAOUT24!AD15+HISTOSEPT24!AD15+HISTOOCT24!AD15+HISTONOV24!AD15+HISTODEC24!AD15 -> 0 | AE15: =HISTOJANV24!AE15+HISTOFEV24!AE15+HISTOMARS24!AE15+HISTOAVRIL24!AE15+HISTOMAI24!AE15+HISTOJUIN24!AE15+HISTOJUIL24!AE15+HISTOAOUT24!AE15+HISTOSEPT24!AE15+HISTOOCT24!AE15+HISTONOV24!AE15+HISTODEC24!AE15 -> 0 | AH15: =HISTOJANV24!AH15+HISTOFEV24!AH15+HISTOMARS24!AH15+HISTOAVRIL24!AH15+HISTOMAI24!AH15+HISTOJUIN24!AH15+HISTOJUIL24!AH15+HISTOAOUT24!AH15+HISTOSEPT24!AH15+HISTOOCT24!AH15+HISTONOV24!AH15+HISTODEC24!AH15 -> 0 | AI15: =HISTOJANV24!AI15+HISTOFEV24!AI15+HISTOMARS24!AI15+HISTOAVRIL24!AI15+HISTOMAI24!AI15+HISTOJUIN24!AI15+HISTOJUIL24!AI15+HISTOAOUT24!AI15+HISTOSEPT24!AI15+HISTOOCT24!AI15+HISTONOV24!AI15+HISTODEC24!AI15 -> 0 | AJ15: =HISTOJANV24!AJ15+HISTOFEV24!AJ15+HISTOMARS24!AJ15+HISTOAVRIL24!AJ15+HISTOMAI24!AJ15+HISTOJUIN24!AJ15+HISTOJUIL24!AJ15+HISTOAOUT24!AJ15+HISTOSEPT24!AJ15+HISTOOCT24!AJ15+HISTONOV24!AJ15+HISTODEC24!AJ15 -> 0 | AK15: =HISTOJANV24!AK15+HISTOFEV24!AK15+HISTOMARS24!AK15+HISTOAVRIL24!AK15+HISTOMAI24!AK15+HISTOJUIN24!AK15+HISTOJUIL24!AK15+HISTOAOUT24!AK15+HISTOSEPT24!AK15+HISTOOCT24!AK15+HISTONOV24!AK15+HISTODEC24!AK15 -> 0 | AL15: =HISTOJANV24!AL15+HISTOFEV24!AL15+HISTOMARS24!AL15+HISTOAVRIL24!AL15+HISTOMAI24!AL15+HISTOJUIN24!AL15+HISTOJUIL24!AL15+HISTOAOUT24!AL15+HISTOSEPT24!AL15+HISTOOCT24!AL15+HISTONOV24!AL15+HISTODEC24!AL15 -> 0 | AM15: =HISTOJANV24!AM15+HISTOFEV24!AM15+HISTOMARS24!AM15+HISTOAVRIL24!AM15+HISTOMAI24!AM15+HISTOJUIN24!AM15+HISTOJUIL24!AM15+HISTOAOUT24!AM15+HISTOSEPT24!AM15+HISTOOCT24!AM15+HISTONOV24!AM15+HISTODEC24!AM15 -> 0 | AN15: =HISTOJANV24!AN15+HISTOFEV24!AN15+HISTOMARS24!AN15+HISTOAVRIL24!AN15+HISTOMAI24!AN15+HISTOJUIN24!AN15+HISTOJUIL24!AN15+HISTOAOUT24!AN15+HISTOSEPT24!AN15+HISTOOCT24!AN15+HISTONOV24!AN15+HISTODEC24!AN15 -> 0 | AQ15: =IF(H15="ECHEC",((K15+M15+O15)*20/100),0) -> 0 | AR15: =IF(H15="ECHEC",((K15+M15+O15)*20/100),0) -> 0 | AS15: =IF(H15="ECHEC",0,(K15+I15-25000)) -> 25000 | AW15: =HISTOJANV24!AW15+HISTOFEV24!AW15+HISTOMARS24!AW15+HISTOAVRIL24!AW15+HISTOMAI24!AW15+HISTOJUIN24!AW15+HISTOJUIL24!AW15+HISTOAOUT24!AW15+HISTOSEPT24!AW15+HISTOOCT24!AW15+HISTONOV24!AW15+HISTODEC24!AW15 -> 0 | AX15: =HISTOJANV24!AX15+HISTOFEV24!AX15+HISTOMARS24!AX15+HISTOAVRIL24!AX15+HISTOMAI24!AX15+HISTOJUIN24!AX15+HISTOJUIL24!AX15+HISTOAOUT24!AX15+HISTOSEPT24!AX15+HISTOOCT24!AX15+HISTONOV24!AX15+HISTODEC24!AX15 -> 0 | AY15: =HISTOJANV24!AY15+HISTOFEV24!AY15+HISTOMARS24!AY15+HISTOAVRIL24!AY15+HISTOMAI24!AY15+HISTOJUIN24!AY15+HISTOJUIL24!AY15+HISTOAOUT24!AY15+HISTOSEPT24!AY15+HISTOOCT24!AY15+HISTONOV24!AY15+HISTODEC24!AY15 -> 0 | AZ15: =HISTOJANV24!AZ15+HISTOFEV24!AZ15+HISTOMARS24!AZ15+HISTOAVRIL24!AZ15+HISTOMAI24!AZ15+HISTOJUIN24!AZ15+HISTOJUIL24!AZ15+HISTOAOUT24!AZ15+HISTOSEPT24!AZ15+HISTOOCT24!AZ15+HISTONOV24!AZ15+HISTODEC24!AZ15 -> 0 | BA15: =HISTOJANV24!BA15+HISTOFEV24!BA15+HISTOMARS24!BA15+HISTOAVRIL24!BA15+HISTOMAI24!BA15+HISTOJUIN24!BA15+HISTOJUIL24!BA15+HISTOAOUT24!BA15+HISTOSEPT24!BA15+HISTOOCT24!BA15+HISTONOV24!BA15+HISTODEC24!BA15 -> 0 | BB15: =HISTOJANV24!BB15+HISTOFEV24!BB15+HISTOMARS24!BB15+HISTOAVRIL24!BB15+HISTOMAI24!BB15+HISTOJUIN24!BB15+HISTOJUIL24!BB15+HISTOAOUT24!BB15+HISTOSEPT24!BB15+HISTOOCT24!BB15+HISTONOV24!BB15+HISTODEC24!BB15 -> 0 | BD15: =HISTOJANV24!BD15+HISTOFEV24!BD15+HISTOMARS24!BD15+HISTOAVRIL24!BD15+HISTOMAI24!BD15+HISTOJUIN24!BD15+HISTOJUIL24!BD15+HISTOAOUT24!BD15+HISTOSEPT24!BD15+HISTOOCT24!BD15+HISTONOV24!BD15+HISTODEC24!BD15 -> 0 | BF15: =HISTOJANV24!BF15+HISTOFEV24!BF15+HISTOMARS24!BF15+HISTOAVRIL24!BF15+HISTOMAI24!BF15+HISTOJUIN24!BF15+HISTOJUIL24!BF15+HISTOAOUT24!BF15+HISTOSEPT24!BF15+HISTOOCT24!BF15+HISTONOV24!BF15+HISTODEC24!BF15 -> 0
A16: AS201613 | B16: =VLOOKUP(A16,[11]LISTADHERENT!A$5:H$50,3,0) -> HOTCHO BENJAMIN | D16: =HISTOJANV24!D16+HISTOFEV24!D16+HISTOMARS24!D16+HISTOAVRIL24!D16+HISTOMAI24!D16+HISTOJUIN24!D16+HISTOJUIL24!D16+HISTOAOUT24!D16+HISTOSEPT24!D16+HISTOOCT24!D16+HISTONOV24!D16+HISTODEC24!D16 -> 780000 | E16: =HISTOJANV24!E16+HISTOFEV24!E16+HISTOMARS24!E16+HISTOAVRIL24!E16+HISTOMAI24!E16+HISTOJUIN24!E16+HISTOJUIL24!E16+HISTOAOUT24!E16+HISTOSEPT24!E16+HISTOOCT24!E16+HISTONOV24!E16+HISTODEC24!E16 -> 0 | F16: =HISTOJANV24!F16+HISTOFEV24!F16+HISTOMARS24!F16+HISTOAVRIL24!F16+HISTOMAI24!F16+HISTOJUIN24!F16+HISTOJUIL24!F16+HISTOAOUT24!F16+HISTOSEPT24!F16+HISTOOCT24!F16+HISTONOV24!F16+HISTODEC24!F16 -> 0 | G16: =HISTOJANV24!G16+HISTOFEV24!G16+HISTOMARS24!G16+HISTOAVRIL24!G16+HISTOMAI24!G16+HISTOJUIN24!G16+HISTOJUIL24!G16+HISTOAOUT24!G16+HISTOSEPT24!G16+HISTOOCT24!G16+HISTONOV24!G16+HISTODEC24!G16 -> 0 | I16: =HISTOJANV24!I16+HISTOFEV24!I16+HISTOMARS24!I16+HISTOAVRIL24!I16+HISTOMAI24!I16+HISTOJUIN24!I16+HISTOJUIL24!I16+HISTOAOUT24!I16+HISTOSEPT24!I16+HISTOOCT24!I16+HISTONOV24!I16+HISTODEC24!I16 -> 105000 | J16: 1 | K16: =IF($D16<>0,J16*50000,IF($E16<>0,J16*50000,0)) -> 50000 | L16: 1 | M16: =IF($D16<>0,L16*75000,IF($E16<>0,L16*75000,0)) -> 75000 | N16: 1 | O16: =IF($D16<>0,N16*100000,IF($E16<>0,N16*100000,0)) -> 100000 | P16: =HISTOJANV24!P16+HISTOFEV24!P16+HISTOMARS24!P16+HISTOAVRIL24!P16+HISTOMAI24!P16+HISTOJUIN24!P16+HISTOJUIL24!P16+HISTOAOUT24!P16+HISTOSEPT24!P16+HISTOOCT24!P16+HISTONOV24!P16+HISTODEC24!P16 -> 0 | Q16: =HISTOJANV24!Q16+HISTOFEV24!Q16+HISTOMARS24!Q16+HISTOAVRIL24!Q16+HISTOMAI24!Q16+HISTOJUIN24!Q16+HISTOJUIL24!Q16+HISTOAOUT24!Q16+HISTOSEPT24!Q16+HISTOOCT24!Q16+HISTONOV24!Q16+HISTODEC24!Q16 -> 0 | R16: =HISTOJANV24!R16+HISTOFEV24!R16+HISTOMARS24!R16+HISTOAVRIL24!R16+HISTOMAI24!R16+HISTOJUIN24!R16+HISTOJUIL24!R16+HISTOAOUT24!R16+HISTOSEPT24!R16+HISTOOCT24!R16+HISTONOV24!R16+HISTODEC24!R16 -> 0 | S16: =HISTOJANV24!S16+HISTOFEV24!S16+HISTOMARS24!S16+HISTOAVRIL24!S16+HISTOMAI24!S16+HISTOJUIN24!S16+HISTOJUIL24!S16+HISTOAOUT24!S16+HISTOSEPT24!S16+HISTOOCT24!S16+HISTONOV24!S16+HISTODEC24!S16 -> 0 | U16: =G16+S16++R16+P16+O16+M16+I16+K16+Q16+V16+W16 -> 330000 | V16: =HISTOJANV24!V16+HISTOFEV24!V16+HISTOMARS24!V16+HISTOAVRIL24!V16+HISTOMAI24!V16+HISTOJUIN24!V16+HISTOJUIL24!V16+HISTOAOUT24!V16+HISTOSEPT24!V16+HISTOOCT24!V16+HISTONOV24!V16+HISTODEC24!V16 -> 0 | W16: =HISTOJANV24!W16+HISTOFEV24!W16+HISTOMARS24!W16+HISTOAVRIL24!W16+HISTOMAI24!W16+HISTOJUIN24!W16+HISTOJUIL24!W16+HISTOAOUT24!W16+HISTOSEPT24!W16+HISTOOCT24!W16+HISTONOV24!W16+HISTODEC24!W16 -> 0 | X16: =HISTOJANV24!X16+HISTOFEV24!X16+HISTOMARS24!X16+HISTOAVRIL24!X16+HISTOMAI24!X16+HISTOJUIN24!X16+HISTOJUIL24!X16+HISTOAOUT24!X16+HISTOSEPT24!X16+HISTOOCT24!X16+HISTONOV24!X16+HISTODEC24!X16 -> 0 | Y16: =HISTOJANV24!Y16+HISTOFEV24!Y16+HISTOMARS24!Y16+HISTOAVRIL24!Y16+HISTOMAI24!Y16+HISTOJUIN24!Y16+HISTOJUIL24!Y16+HISTOAOUT24!Y16+HISTOSEPT24!Y16+HISTOOCT24!Y16+HISTONOV24!Y16+HISTODEC24!Y16 -> 0 | Z16: =HISTOJANV24!Z16+HISTOFEV24!Z16+HISTOMARS24!Z16+HISTOAVRIL24!Z16+HISTOMAI24!Z16+HISTOJUIN24!Z16+HISTOJUIL24!Z16+HISTOAOUT24!Z16+HISTOSEPT24!Z16+HISTOOCT24!Z16+HISTONOV24!Z16+HISTODEC24!Z16 -> 0 | AC16: =HISTOJANV24!AC16+HISTOFEV24!AC16+HISTOMARS24!AC16+HISTOAVRIL24!AC16+HISTOMAI24!AC16+HISTOJUIN24!AC16+HISTOJUIL24!AC16+HISTOAOUT24!AC16+HISTOSEPT24!AC16+HISTOOCT24!AC16+HISTONOV24!AC16+HISTODEC24!AC16 -> 12000 | AD16: =HISTOJANV24!AD16+HISTOFEV24!AD16+HISTOMARS24!AD16+HISTOAVRIL24!AD16+HISTOMAI24!AD16+HISTOJUIN24!AD16+HISTOJUIL24!AD16+HISTOAOUT24!AD16+HISTOSEPT24!AD16+HISTOOCT24!AD16+HISTONOV24!AD16+HISTODEC24!AD16 -> 0 | AE16: =HISTOJANV24!AE16+HISTOFEV24!AE16+HISTOMARS24!AE16+HISTOAVRIL24!AE16+HISTOMAI24!AE16+HISTOJUIN24!AE16+HISTOJUIL24!AE16+HISTOAOUT24!AE16+HISTOSEPT24!AE16+HISTOOCT24!AE16+HISTONOV24!AE16+HISTODEC24!AE16 -> 0 | AH16: =HISTOJANV24!AH16+HISTOFEV24!AH16+HISTOMARS24!AH16+HISTOAVRIL24!AH16+HISTOMAI24!AH16+HISTOJUIN24!AH16+HISTOJUIL24!AH16+HISTOAOUT24!AH16+HISTOSEPT24!AH16+HISTOOCT24!AH16+HISTONOV24!AH16+HISTODEC24!AH16 -> 0 | AI16: =HISTOJANV24!AI16+HISTOFEV24!AI16+HISTOMARS24!AI16+HISTOAVRIL24!AI16+HISTOMAI24!AI16+HISTOJUIN24!AI16+HISTOJUIL24!AI16+HISTOAOUT24!AI16+HISTOSEPT24!AI16+HISTOOCT24!AI16+HISTONOV24!AI16+HISTODEC24!AI16 -> 0 | AJ16: =HISTOJANV24!AJ16+HISTOFEV24!AJ16+HISTOMARS24!AJ16+HISTOAVRIL24!AJ16+HISTOMAI24!AJ16+HISTOJUIN24!AJ16+HISTOJUIL24!AJ16+HISTOAOUT24!AJ16+HISTOSEPT24!AJ16+HISTOOCT24!AJ16+HISTONOV24!AJ16+HISTODEC24!AJ16 -> 0 | AK16: =HISTOJANV24!AK16+HISTOFEV24!AK16+HISTOMARS24!AK16+HISTOAVRIL24!AK16+HISTOMAI24!AK16+HISTOJUIN24!AK16+HISTOJUIL24!AK16+HISTOAOUT24!AK16+HISTOSEPT24!AK16+HISTOOCT24!AK16+HISTONOV24!AK16+HISTODEC24!AK16 -> 0 | AL16: =HISTOJANV24!AL16+HISTOFEV24!AL16+HISTOMARS24!AL16+HISTOAVRIL24!AL16+HISTOMAI24!AL16+HISTOJUIN24!AL16+HISTOJUIL24!AL16+HISTOAOUT24!AL16+HISTOSEPT24!AL16+HISTOOCT24!AL16+HISTONOV24!AL16+HISTODEC24!AL16 -> 0 | AM16: =HISTOJANV24!AM16+HISTOFEV24!AM16+HISTOMARS24!AM16+HISTOAVRIL24!AM16+HISTOMAI24!AM16+HISTOJUIN24!AM16+HISTOJUIL24!AM16+HISTOAOUT24!AM16+HISTOSEPT24!AM16+HISTOOCT24!AM16+HISTONOV24!AM16+HISTODEC24!AM16 -> 0 | AN16: =HISTOJANV24!AN16+HISTOFEV24!AN16+HISTOMARS24!AN16+HISTOAVRIL24!AN16+HISTOMAI24!AN16+HISTOJUIN24!AN16+HISTOJUIL24!AN16+HISTOAOUT24!AN16+HISTOSEPT24!AN16+HISTOOCT24!AN16+HISTONOV24!AN16+HISTODEC24!AN16 -> 0 | AQ16: =IF(H16="ECHEC",((K16+M16+O16)*20/100),0) -> 0 | AR16: =IF(H16="ECHEC",((K16+M16+O16)*20/100),0) -> 0 | AS16: =IF(H16="ECHEC",0,(K16+I16-25000)) -> 130000 | AW16: =HISTOJANV24!AW16+HISTOFEV24!AW16+HISTOMARS24!AW16+HISTOAVRIL24!AW16+HISTOMAI24!AW16+HISTOJUIN24!AW16+HISTOJUIL24!AW16+HISTOAOUT24!AW16+HISTOSEPT24!AW16+HISTOOCT24!AW16+HISTONOV24!AW16+HISTODEC24!AW16 -> 288000 | AX16: =HISTOJANV24!AX16+HISTOFEV24!AX16+HISTOMARS24!AX16+HISTOAVRIL24!AX16+HISTOMAI24!AX16+HISTOJUIN24!AX16+HISTOJUIL24!AX16+HISTOAOUT24!AX16+HISTOSEPT24!AX16+HISTOOCT24!AX16+HISTONOV24!AX16+HISTODEC24!AX16 -> 0 | AY16: =HISTOJANV24!AY16+HISTOFEV24!AY16+HISTOMARS24!AY16+HISTOAVRIL24!AY16+HISTOMAI24!AY16+HISTOJUIN24!AY16+HISTOJUIL24!AY16+HISTOAOUT24!AY16+HISTOSEPT24!AY16+HISTOOCT24!AY16+HISTONOV24!AY16+HISTODEC24!AY16 -> 0 | AZ16: =HISTOJANV24!AZ16+HISTOFEV24!AZ16+HISTOMARS24!AZ16+HISTOAVRIL24!AZ16+HISTOMAI24!AZ16+HISTOJUIN24!AZ16+HISTOJUIL24!AZ16+HISTOAOUT24!AZ16+HISTOSEPT24!AZ16+HISTOOCT24!AZ16+HISTONOV24!AZ16+HISTODEC24!AZ16 -> 288000 | BA16: =HISTOJANV24!BA16+HISTOFEV24!BA16+HISTOMARS24!BA16+HISTOAVRIL24!BA16+HISTOMAI24!BA16+HISTOJUIN24!BA16+HISTOJUIL24!BA16+HISTOAOUT24!BA16+HISTOSEPT24!BA16+HISTOOCT24!BA16+HISTONOV24!BA16+HISTODEC24!BA16 -> 0 | BB16: =HISTOJANV24!BB16+HISTOFEV24!BB16+HISTOMARS24!BB16+HISTOAVRIL24!BB16+HISTOMAI24!BB16+HISTOJUIN24!BB16+HISTOJUIL24!BB16+HISTOAOUT24!BB16+HISTOSEPT24!BB16+HISTOOCT24!BB16+HISTONOV24!BB16+HISTODEC24!BB16 -> 0 | BD16: =HISTOJANV24!BD16+HISTOFEV24!BD16+HISTOMARS24!BD16+HISTOAVRIL24!BD16+HISTOMAI24!BD16+HISTOJUIN24!BD16+HISTOJUIL24!BD16+HISTOAOUT24!BD16+HISTOSEPT24!BD16+HISTOOCT24!BD16+HISTONOV24!BD16+HISTODEC24!BD16 -> 288000 | BF16: =HISTOJANV24!BF16+HISTOFEV24!BF16+HISTOMARS24!BF16+HISTOAVRIL24!BF16+HISTOMAI24!BF16+HISTOJUIN24!BF16+HISTOJUIL24!BF16+HISTOAOUT24!BF16+HISTOSEPT24!BF16+HISTOOCT24!BF16+HISTONOV24!BF16+HISTODEC24!BF16 -> 0 | BN16: S/TOTAL | BP16: =SUM(BP6:BP15) -> 0
A17: AS201617 | B17: =VLOOKUP(A17,[11]LISTADHERENT!A$5:H$50,3,0) -> KOUAMOU MOISE | D17: =HISTOJANV24!D17+HISTOFEV24!D17+HISTOMARS24!D17+HISTOAVRIL24!D17+HISTOMAI24!D17+HISTOJUIN24!D17+HISTOJUIL24!D17+HISTOAOUT24!D17+HISTOSEPT24!D17+HISTOOCT24!D17+HISTONOV24!D17+HISTODEC24!D17 -> 551000 | E17: =HISTOJANV24!E17+HISTOFEV24!E17+HISTOMARS24!E17+HISTOAVRIL24!E17+HISTOMAI24!E17+HISTOJUIN24!E17+HISTOJUIL24!E17+HISTOAOUT24!E17+HISTOSEPT24!E17+HISTOOCT24!E17+HISTONOV24!E17+HISTODEC24!E17 -> 0 | F17: =HISTOJANV24!F17+HISTOFEV24!F17+HISTOMARS24!F17+HISTOAVRIL24!F17+HISTOMAI24!F17+HISTOJUIN24!F17+HISTOJUIL24!F17+HISTOAOUT24!F17+HISTOSEPT24!F17+HISTOOCT24!F17+HISTONOV24!F17+HISTODEC24!F17 -> 500000 | G17: =HISTOJANV24!G17+HISTOFEV24!G17+HISTOMARS24!G17+HISTOAVRIL24!G17+HISTOMAI24!G17+HISTOJUIN24!G17+HISTOJUIL24!G17+HISTOAOUT24!G17+HISTOSEPT24!G17+HISTOOCT24!G17+HISTONOV24!G17+HISTODEC24!G17 -> 0 | I17: =HISTOJANV24!I17+HISTOFEV24!I17+HISTOMARS24!I17+HISTOAVRIL24!I17+HISTOMAI24!I17+HISTOJUIN24!I17+HISTOJUIL24!I17+HISTOAOUT24!I17+HISTOSEPT24!I17+HISTOOCT24!I17+HISTONOV24!I17+HISTODEC24!I17 -> 0 | J17: 1 | K17: =IF($D17<>0,J17*50000,IF($E17<>0,J17*50000,0)) -> 50000 | M17: =IF($D17<>0,L17*75000,IF($E17<>0,L17*75000,0)) -> 0 | N17: 1 | O17: =IF($D17<>0,N17*100000,IF($E17<>0,N17*100000,0)) -> 100000 | P17: =HISTOJANV24!P17+HISTOFEV24!P17+HISTOMARS24!P17+HISTOAVRIL24!P17+HISTOMAI24!P17+HISTOJUIN24!P17+HISTOJUIL24!P17+HISTOAOUT24!P17+HISTOSEPT24!P17+HISTOOCT24!P17+HISTONOV24!P17+HISTODEC24!P17 -> 0 | Q17: =HISTOJANV24!Q17+HISTOFEV24!Q17+HISTOMARS24!Q17+HISTOAVRIL24!Q17+HISTOMAI24!Q17+HISTOJUIN24!Q17+HISTOJUIL24!Q17+HISTOAOUT24!Q17+HISTOSEPT24!Q17+HISTOOCT24!Q17+HISTONOV24!Q17+HISTODEC24!Q17 -> 0 | R17: =HISTOJANV24!R17+HISTOFEV24!R17+HISTOMARS24!R17+HISTOAVRIL24!R17+HISTOMAI24!R17+HISTOJUIN24!R17+HISTOJUIL24!R17+HISTOAOUT24!R17+HISTOSEPT24!R17+HISTOOCT24!R17+HISTONOV24!R17+HISTODEC24!R17 -> 101000 | S17: =HISTOJANV24!S17+HISTOFEV24!S17+HISTOMARS24!S17+HISTOAVRIL24!S17+HISTOMAI24!S17+HISTOJUIN24!S17+HISTOJUIL24!S17+HISTOAOUT24!S17+HISTOSEPT24!S17+HISTOOCT24!S17+HISTONOV24!S17+HISTODEC24!S17 -> 500000 | U17: =G17+S17++R17+P17+O17+M17+I17+K17+Q17+V17+W17 -> 751000 | V17: =HISTOJANV24!V17+HISTOFEV24!V17+HISTOMARS24!V17+HISTOAVRIL24!V17+HISTOMAI24!V17+HISTOJUIN24!V17+HISTOJUIL24!V17+HISTOAOUT24!V17+HISTOSEPT24!V17+HISTOOCT24!V17+HISTONOV24!V17+HISTODEC24!V17 -> 0 | W17: =HISTOJANV24!W17+HISTOFEV24!W17+HISTOMARS24!W17+HISTOAVRIL24!W17+HISTOMAI24!W17+HISTOJUIN24!W17+HISTOJUIL24!W17+HISTOAOUT24!W17+HISTOSEPT24!W17+HISTOOCT24!W17+HISTONOV24!W17+HISTODEC24!W17 -> 0 | X17: =HISTOJANV24!X17+HISTOFEV24!X17+HISTOMARS24!X17+HISTOAVRIL24!X17+HISTOMAI24!X17+HISTOJUIN24!X17+HISTOJUIL24!X17+HISTOAOUT24!X17+HISTOSEPT24!X17+HISTOOCT24!X17+HISTONOV24!X17+HISTODEC24!X17 -> 0 | Y17: =HISTOJANV24!Y17+HISTOFEV24!Y17+HISTOMARS24!Y17+HISTOAVRIL24!Y17+HISTOMAI24!Y17+HISTOJUIN24!Y17+HISTOJUIL24!Y17+HISTOAOUT24!Y17+HISTOSEPT24!Y17+HISTOOCT24!Y17+HISTONOV24!Y17+HISTODEC24!Y17 -> 0 | Z17: =HISTOJANV24!Z17+HISTOFEV24!Z17+HISTOMARS24!Z17+HISTOAVRIL24!Z17+HISTOMAI24!Z17+HISTOJUIN24!Z17+HISTOJUIL24!Z17+HISTOAOUT24!Z17+HISTOSEPT24!Z17+HISTOOCT24!Z17+HISTONOV24!Z17+HISTODEC24!Z17 -> 1000000 | AC17: =HISTOJANV24!AC17+HISTOFEV24!AC17+HISTOMARS24!AC17+HISTOAVRIL24!AC17+HISTOMAI24!AC17+HISTOJUIN24!AC17+HISTOJUIL24!AC17+HISTOAOUT24!AC17+HISTOSEPT24!AC17+HISTOOCT24!AC17+HISTONOV24!AC17+HISTODEC24!AC17 -> 17000 | AD17: =HISTOJANV24!AD17+HISTOFEV24!AD17+HISTOMARS24!AD17+HISTOAVRIL24!AD17+HISTOMAI24!AD17+HISTOJUIN24!AD17+HISTOJUIL24!AD17+HISTOAOUT24!AD17+HISTOSEPT24!AD17+HISTOOCT24!AD17+HISTONOV24!AD17+HISTODEC24!AD17 -> 0 | AE17: =HISTOJANV24!AE17+HISTOFEV24!AE17+HISTOMARS24!AE17+HISTOAVRIL24!AE17+HISTOMAI24!AE17+HISTOJUIN24!AE17+HISTOJUIL24!AE17+HISTOAOUT24!AE17+HISTOSEPT24!AE17+HISTOOCT24!AE17+HISTONOV24!AE17+HISTODEC24!AE17 -> 70000 | AH17: =HISTOJANV24!AH17+HISTOFEV24!AH17+HISTOMARS24!AH17+HISTOAVRIL24!AH17+HISTOMAI24!AH17+HISTOJUIN24!AH17+HISTOJUIL24!AH17+HISTOAOUT24!AH17+HISTOSEPT24!AH17+HISTOOCT24!AH17+HISTONOV24!AH17+HISTODEC24!AH17 -> 0 | AI17: =HISTOJANV24!AI17+HISTOFEV24!AI17+HISTOMARS24!AI17+HISTOAVRIL24!AI17+HISTOMAI24!AI17+HISTOJUIN24!AI17+HISTOJUIL24!AI17+HISTOAOUT24!AI17+HISTOSEPT24!AI17+HISTOOCT24!AI17+HISTONOV24!AI17+HISTODEC24!AI17 -> 0 | AJ17: =HISTOJANV24!AJ17+HISTOFEV24!AJ17+HISTOMARS24!AJ17+HISTOAVRIL24!AJ17+HISTOMAI24!AJ17+HISTOJUIN24!AJ17+HISTOJUIL24!AJ17+HISTOAOUT24!AJ17+HISTOSEPT24!AJ17+HISTOOCT24!AJ17+HISTONOV24!AJ17+HISTODEC24!AJ17 -> 0 | AK17: =HISTOJANV24!AK17+HISTOFEV24!AK17+HISTOMARS24!AK17+HISTOAVRIL24!AK17+HISTOMAI24!AK17+HISTOJUIN24!AK17+HISTOJUIL24!AK17+HISTOAOUT24!AK17+HISTOSEPT24!AK17+HISTOOCT24!AK17+HISTONOV24!AK17+HISTODEC24!AK17 -> 100000 | AL17: =HISTOJANV24!AL17+HISTOFEV24!AL17+HISTOMARS24!AL17+HISTOAVRIL24!AL17+HISTOMAI24!AL17+HISTOJUIN24!AL17+HISTOJUIL24!AL17+HISTOAOUT24!AL17+HISTOSEPT24!AL17+HISTOOCT24!AL17+HISTONOV24!AL17+HISTODEC24!AL17 -> 0 | AM17: =HISTOJANV24!AM17+HISTOFEV24!AM17+HISTOMARS24!AM17+HISTOAVRIL24!AM17+HISTOMAI24!AM17+HISTOJUIN24!AM17+HISTOJUIL24!AM17+HISTOAOUT24!AM17+HISTOSEPT24!AM17+HISTOOCT24!AM17+HISTONOV24!AM17+HISTODEC24!AM17 -> 0 | AN17: =HISTOJANV24!AN17+HISTOFEV24!AN17+HISTOMARS24!AN17+HISTOAVRIL24!AN17+HISTOMAI24!AN17+HISTOJUIN24!AN17+HISTOJUIL24!AN17+HISTOAOUT24!AN17+HISTOSEPT24!AN17+HISTOOCT24!AN17+HISTONOV24!AN17+HISTODEC24!AN17 -> 1000 | AQ17: =IF(H17="ECHEC",((K17+M17+O17)*20/100),0) -> 0 | AR17: =IF(H17="ECHEC",((K17+M17+O17)*20/100),0) -> 0 | AS17: =IF(H17="ECHEC",0,(K17+I17-25000)) -> 25000 | AW17: =HISTOJANV24!AW17+HISTOFEV24!AW17+HISTOMARS24!AW17+HISTOAVRIL24!AW17+HISTOMAI24!AW17+HISTOJUIN24!AW17+HISTOJUIL24!AW17+HISTOAOUT24!AW17+HISTOSEPT24!AW17+HISTOOCT24!AW17+HISTONOV24!AW17+HISTODEC24!AW17 -> 283000 | AX17: =HISTOJANV24!AX17+HISTOFEV24!AX17+HISTOMARS24!AX17+HISTOAVRIL24!AX17+HISTOMAI24!AX17+HISTOJUIN24!AX17+HISTOJUIL24!AX17+HISTOAOUT24!AX17+HISTOSEPT24!AX17+HISTOOCT24!AX17+HISTONOV24!AX17+HISTODEC24!AX17 -> 0 | AY17: =HISTOJANV24!AY17+HISTOFEV24!AY17+HISTOMARS24!AY17+HISTOAVRIL24!AY17+HISTOMAI24!AY17+HISTOJUIN24!AY17+HISTOJUIL24!AY17+HISTOAOUT24!AY17+HISTOSEPT24!AY17+HISTOOCT24!AY17+HISTONOV24!AY17+HISTODEC24!AY17 -> 1230000 | AZ17: =HISTOJANV24!AZ17+HISTOFEV24!AZ17+HISTOMARS24!AZ17+HISTOAVRIL24!AZ17+HISTOMAI24!AZ17+HISTOJUIN24!AZ17+HISTOJUIL24!AZ17+HISTOAOUT24!AZ17+HISTOSEPT24!AZ17+HISTOOCT24!AZ17+HISTONOV24!AZ17+HISTODEC24!AZ17 -> 2063000 | BA17: =HISTOJANV24!BA17+HISTOFEV24!BA17+HISTOMARS24!BA17+HISTOAVRIL24!BA17+HISTOMAI24!BA17+HISTOJUIN24!BA17+HISTOJUIL24!BA17+HISTOAOUT24!BA17+HISTOSEPT24!BA17+HISTOOCT24!BA17+HISTONOV24!BA17+HISTODEC24!BA17 -> 100000 | BB17: =HISTOJANV24!BB17+HISTOFEV24!BB17+HISTOMARS24!BB17+HISTOAVRIL24!BB17+HISTOMAI24!BB17+HISTOJUIN24!BB17+HISTOJUIL24!BB17+HISTOAOUT24!BB17+HISTOSEPT24!BB17+HISTOOCT24!BB17+HISTONOV24!BB17+HISTODEC24!BB17 -> 0 | BD17: =HISTOJANV24!BD17+HISTOFEV24!BD17+HISTOMARS24!BD17+HISTOAVRIL24!BD17+HISTOMAI24!BD17+HISTOJUIN24!BD17+HISTOJUIL24!BD17+HISTOAOUT24!BD17+HISTOSEPT24!BD17+HISTOOCT24!BD17+HISTONOV24!BD17+HISTODEC24!BD17 -> 1963000 | BF17: =HISTOJANV24!BF17+HISTOFEV24!BF17+HISTOMARS24!BF17+HISTOAVRIL24!BF17+HISTOMAI24!BF17+HISTOJUIN24!BF17+HISTOJUIL24!BF17+HISTOAOUT24!BF17+HISTOSEPT24!BF17+HISTOOCT24!BF17+HISTONOV24!BF17+HISTODEC24!BF17 -> 110000
A18: AS201619 | B18: =VLOOKUP(A18,[11]LISTADHERENT!A$5:H$50,3,0) -> KOUATCHO MESSACK | D18: =HISTOJANV24!D18+HISTOFEV24!D18+HISTOMARS24!D18+HISTOAVRIL24!D18+HISTOMAI24!D18+HISTOJUIN24!D18+HISTOJUIL24!D18+HISTOAOUT24!D18+HISTOSEPT24!D18+HISTOOCT24!D18+HISTONOV24!D18+HISTODEC24!D18 -> 470000 | E18: =HISTOJANV24!E18+HISTOFEV24!E18+HISTOMARS24!E18+HISTOAVRIL24!E18+HISTOMAI24!E18+HISTOJUIN24!E18+HISTOJUIL24!E18+HISTOAOUT24!E18+HISTOSEPT24!E18+HISTOOCT24!E18+HISTONOV24!E18+HISTODEC24!E18 -> 0 | F18: =HISTOJANV24!F18+HISTOFEV24!F18+HISTOMARS24!F18+HISTOAVRIL24!F18+HISTOMAI24!F18+HISTOJUIN24!F18+HISTOJUIL24!F18+HISTOAOUT24!F18+HISTOSEPT24!F18+HISTOOCT24!F18+HISTONOV24!F18+HISTODEC24!F18 -> 0 | G18: =HISTOJANV24!G18+HISTOFEV24!G18+HISTOMARS24!G18+HISTOAVRIL24!G18+HISTOMAI24!G18+HISTOJUIN24!G18+HISTOJUIL24!G18+HISTOAOUT24!G18+HISTOSEPT24!G18+HISTOOCT24!G18+HISTONOV24!G18+HISTODEC24!G18 -> 0 | I18: =HISTOJANV24!I18+HISTOFEV24!I18+HISTOMARS24!I18+HISTOAVRIL24!I18+HISTOMAI24!I18+HISTOJUIN24!I18+HISTOJUIL24!I18+HISTOAOUT24!I18+HISTOSEPT24!I18+HISTOOCT24!I18+HISTONOV24!I18+HISTODEC24!I18 -> 20000 | J18: 1 | K18: =IF($D18<>0,J18*50000,IF($E18<>0,J18*50000,0)) -> 50000 | M18: =IF($D18<>0,L18*75000,IF($E18<>0,L18*75000,0)) -> 0 | N18: 1 | O18: =IF($D18<>0,N18*100000,IF($E18<>0,N18*100000,0)) -> 100000 | P18: =HISTOJANV24!P18+HISTOFEV24!P18+HISTOMARS24!P18+HISTOAVRIL24!P18+HISTOMAI24!P18+HISTOJUIN24!P18+HISTOJUIL24!P18+HISTOAOUT24!P18+HISTOSEPT24!P18+HISTOOCT24!P18+HISTONOV24!P18+HISTODEC24!P18 -> 0 | Q18: =HISTOJANV24!Q18+HISTOFEV24!Q18+HISTOMARS24!Q18+HISTOAVRIL24!Q18+HISTOMAI24!Q18+HISTOJUIN24!Q18+HISTOJUIL24!Q18+HISTOAOUT24!Q18+HISTOSEPT24!Q18+HISTOOCT24!Q18+HISTONOV24!Q18+HISTODEC24!Q18 -> 0 | R18: =HISTOJANV24!R18+HISTOFEV24!R18+HISTOMARS24!R18+HISTOAVRIL24!R18+HISTOMAI24!R18+HISTOJUIN24!R18+HISTOJUIL24!R18+HISTOAOUT24!R18+HISTOSEPT24!R18+HISTOOCT24!R18+HISTONOV24!R18+HISTODEC24!R18 -> 202000 | S18: =HISTOJANV24!S18+HISTOFEV24!S18+HISTOMARS24!S18+HISTOAVRIL24!S18+HISTOMAI24!S18+HISTOJUIN24!S18+HISTOJUIL24!S18+HISTOAOUT24!S18+HISTOSEPT24!S18+HISTOOCT24!S18+HISTONOV24!S18+HISTODEC24!S18 -> 0 | U18: =G18+S18++R18+P18+O18+M18+I18+K18+Q18+V18+W18 -> 372000 | V18: =HISTOJANV24!V18+HISTOFEV24!V18+HISTOMARS24!V18+HISTOAVRIL24!V18+HISTOMAI24!V18+HISTOJUIN24!V18+HISTOJUIL24!V18+HISTOAOUT24!V18+HISTOSEPT24!V18+HISTOOCT24!V18+HISTONOV24!V18+HISTODEC24!V18 -> 0 | W18: =HISTOJANV24!W18+HISTOFEV24!W18+HISTOMARS24!W18+HISTOAVRIL24!W18+HISTOMAI24!W18+HISTOJUIN24!W18+HISTOJUIL24!W18+HISTOAOUT24!W18+HISTOSEPT24!W18+HISTOOCT24!W18+HISTONOV24!W18+HISTODEC24!W18 -> 0 | X18: =HISTOJANV24!X18+HISTOFEV24!X18+HISTOMARS24!X18+HISTOAVRIL24!X18+HISTOMAI24!X18+HISTOJUIN24!X18+HISTOJUIL24!X18+HISTOAOUT24!X18+HISTOSEPT24!X18+HISTOOCT24!X18+HISTONOV24!X18+HISTODEC24!X18 -> 0 | Y18: =HISTOJANV24!Y18+HISTOFEV24!Y18+HISTOMARS24!Y18+HISTOAVRIL24!Y18+HISTOMAI24!Y18+HISTOJUIN24!Y18+HISTOJUIL24!Y18+HISTOAOUT24!Y18+HISTOSEPT24!Y18+HISTOOCT24!Y18+HISTONOV24!Y18+HISTODEC24!Y18 -> 0 | Z18: =HISTOJANV24!Z18+HISTOFEV24!Z18+HISTOMARS24!Z18+HISTOAVRIL24!Z18+HISTOMAI24!Z18+HISTOJUIN24!Z18+HISTOJUIL24!Z18+HISTOAOUT24!Z18+HISTOSEPT24!Z18+HISTOOCT24!Z18+HISTONOV24!Z18+HISTODEC24!Z18 -> 0 | AC18: =HISTOJANV24!AC18+HISTOFEV24!AC18+HISTOMARS24!AC18+HISTOAVRIL24!AC18+HISTOMAI24!AC18+HISTOJUIN24!AC18+HISTOJUIL24!AC18+HISTOAOUT24!AC18+HISTOSEPT24!AC18+HISTOOCT24!AC18+HISTONOV24!AC18+HISTODEC24!AC18 -> 13000 | AD18: =HISTOJANV24!AD18+HISTOFEV24!AD18+HISTOMARS24!AD18+HISTOAVRIL24!AD18+HISTOMAI24!AD18+HISTOJUIN24!AD18+HISTOJUIL24!AD18+HISTOAOUT24!AD18+HISTOSEPT24!AD18+HISTOOCT24!AD18+HISTONOV24!AD18+HISTODEC24!AD18 -> 0 | AE18: =HISTOJANV24!AE18+HISTOFEV24!AE18+HISTOMARS24!AE18+HISTOAVRIL24!AE18+HISTOMAI24!AE18+HISTOJUIN24!AE18+HISTOJUIL24!AE18+HISTOAOUT24!AE18+HISTOSEPT24!AE18+HISTOOCT24!AE18+HISTONOV24!AE18+HISTODEC24!AE18 -> 40000 | AH18: =HISTOJANV24!AH18+HISTOFEV24!AH18+HISTOMARS24!AH18+HISTOAVRIL24!AH18+HISTOMAI24!AH18+HISTOJUIN24!AH18+HISTOJUIL24!AH18+HISTOAOUT24!AH18+HISTOSEPT24!AH18+HISTOOCT24!AH18+HISTONOV24!AH18+HISTODEC24!AH18 -> 0 | AI18: =HISTOJANV24!AI18+HISTOFEV24!AI18+HISTOMARS24!AI18+HISTOAVRIL24!AI18+HISTOMAI24!AI18+HISTOJUIN24!AI18+HISTOJUIL24!AI18+HISTOAOUT24!AI18+HISTOSEPT24!AI18+HISTOOCT24!AI18+HISTONOV24!AI18+HISTODEC24!AI18 -> 0 | AJ18: =HISTOJANV24!AJ18+HISTOFEV24!AJ18+HISTOMARS24!AJ18+HISTOAVRIL24!AJ18+HISTOMAI24!AJ18+HISTOJUIN24!AJ18+HISTOJUIL24!AJ18+HISTOAOUT24!AJ18+HISTOSEPT24!AJ18+HISTOOCT24!AJ18+HISTONOV24!AJ18+HISTODEC24!AJ18 -> 0 | AK18: =HISTOJANV24!AK18+HISTOFEV24!AK18+HISTOMARS24!AK18+HISTOAVRIL24!AK18+HISTOMAI24!AK18+HISTOJUIN24!AK18+HISTOJUIL24!AK18+HISTOAOUT24!AK18+HISTOSEPT24!AK18+HISTOOCT24!AK18+HISTONOV24!AK18+HISTODEC24!AK18 -> 200000 | AL18: =HISTOJANV24!AL18+HISTOFEV24!AL18+HISTOMARS24!AL18+HISTOAVRIL24!AL18+HISTOMAI24!AL18+HISTOJUIN24!AL18+HISTOJUIL24!AL18+HISTOAOUT24!AL18+HISTOSEPT24!AL18+HISTOOCT24!AL18+HISTONOV24!AL18+HISTODEC24!AL18 -> 0 | AM18: =HISTOJANV24!AM18+HISTOFEV24!AM18+HISTOMARS24!AM18+HISTOAVRIL24!AM18+HISTOMAI24!AM18+HISTOJUIN24!AM18+HISTOJUIL24!AM18+HISTOAOUT24!AM18+HISTOSEPT24!AM18+HISTOOCT24!AM18+HISTONOV24!AM18+HISTODEC24!AM18 -> 0 | AN18: =HISTOJANV24!AN18+HISTOFEV24!AN18+HISTOMARS24!AN18+HISTOAVRIL24!AN18+HISTOMAI24!AN18+HISTOJUIN24!AN18+HISTOJUIL24!AN18+HISTOAOUT24!AN18+HISTOSEPT24!AN18+HISTOOCT24!AN18+HISTONOV24!AN18+HISTODEC24!AN18 -> 2000 | AQ18: =IF(H18="ECHEC",((K18+M18+O18)*20/100),0) -> 0 | AR18: =IF(H18="ECHEC",((K18+M18+O18)*20/100),0) -> 0 | AS18: =IF(H18="ECHEC",0,(K18+I18-25000)) -> 45000 | AW18: =HISTOJANV24!AW18+HISTOFEV24!AW18+HISTOMARS24!AW18+HISTOAVRIL24!AW18+HISTOMAI24!AW18+HISTOJUIN24!AW18+HISTOJUIL24!AW18+HISTOAOUT24!AW18+HISTOSEPT24!AW18+HISTOOCT24!AW18+HISTONOV24!AW18+HISTODEC24!AW18 -> 287000 | AX18: =HISTOJANV24!AX18+HISTOFEV24!AX18+HISTOMARS24!AX18+HISTOAVRIL24!AX18+HISTOMAI24!AX18+HISTOJUIN24!AX18+HISTOJUIL24!AX18+HISTOAOUT24!AX18+HISTOSEPT24!AX18+HISTOOCT24!AX18+HISTONOV24!AX18+HISTODEC24!AX18 -> 0 | AY18: =HISTOJANV24!AY18+HISTOFEV24!AY18+HISTOMARS24!AY18+HISTOAVRIL24!AY18+HISTOMAI24!AY18+HISTOJUIN24!AY18+HISTOJUIL24!AY18+HISTOAOUT24!AY18+HISTOSEPT24!AY18+HISTOOCT24!AY18+HISTONOV24!AY18+HISTODEC24!AY18 -> 1360000 | AZ18: =HISTOJANV24!AZ18+HISTOFEV24!AZ18+HISTOMARS24!AZ18+HISTOAVRIL24!AZ18+HISTOMAI24!AZ18+HISTOJUIN24!AZ18+HISTOJUIL24!AZ18+HISTOAOUT24!AZ18+HISTOSEPT24!AZ18+HISTOOCT24!AZ18+HISTONOV24!AZ18+HISTODEC24!AZ18 -> 1647000 | BA18: =HISTOJANV24!BA18+HISTOFEV24!BA18+HISTOMARS24!BA18+HISTOAVRIL24!BA18+HISTOMAI24!BA18+HISTOJUIN24!BA18+HISTOJUIL24!BA18+HISTOAOUT24!BA18+HISTOSEPT24!BA18+HISTOOCT24!BA18+HISTONOV24!BA18+HISTODEC24!BA18 -> 0 | BB18: =HISTOJANV24!BB18+HISTOFEV24!BB18+HISTOMARS24!BB18+HISTOAVRIL24!BB18+HISTOMAI24!BB18+HISTOJUIN24!BB18+HISTOJUIL24!BB18+HISTOAOUT24!BB18+HISTOSEPT24!BB18+HISTOOCT24!BB18+HISTONOV24!BB18+HISTODEC24!BB18 -> 0 | BD18: =HISTOJANV24!BD18+HISTOFEV24!BD18+HISTOMARS24!BD18+HISTOAVRIL24!BD18+HISTOMAI24!BD18+HISTOJUIN24!BD18+HISTOJUIL24!BD18+HISTOAOUT24!BD18+HISTOSEPT24!BD18+HISTOOCT24!BD18+HISTONOV24!BD18+HISTODEC24!BD18 -> 1647000 | BF18: =HISTOJANV24!BF18+HISTOFEV24!BF18+HISTOMARS24!BF18+HISTOAVRIL24!BF18+HISTOMAI24!BF18+HISTOJUIN24!BF18+HISTOJUIL24!BF18+HISTOAOUT24!BF18+HISTOSEPT24!BF18+HISTOOCT24!BF18+HISTONOV24!BF18+HISTODEC24!BF18 -> 0 | BN18: GRATIFICATION BUREAU 2021 | BO18: PENALITE VERSEMENT ESPECES
A19: AS201661 | B19: =VLOOKUP(A19,[11]LISTADHERENT!A$5:H$50,3,0) -> MASSEUNGOUE DAGOBERT | D19: =HISTOJANV24!D19+HISTOFEV24!D19+HISTOMARS24!D19+HISTOAVRIL24!D19+HISTOMAI24!D19+HISTOJUIN24!D19+HISTOJUIL24!D19+HISTOAOUT24!D19+HISTOSEPT24!D19+HISTOOCT24!D19+HISTONOV24!D19+HISTODEC24!D19 -> 150000 | E19: =HISTOJANV24!E19+HISTOFEV24!E19+HISTOMARS24!E19+HISTOAVRIL24!E19+HISTOMAI24!E19+HISTOJUIN24!E19+HISTOJUIL24!E19+HISTOAOUT24!E19+HISTOSEPT24!E19+HISTOOCT24!E19+HISTONOV24!E19+HISTODEC24!E19 -> 25000 | F19: =HISTOJANV24!F19+HISTOFEV24!F19+HISTOMARS24!F19+HISTOAVRIL24!F19+HISTOMAI24!F19+HISTOJUIN24!F19+HISTOJUIL24!F19+HISTOAOUT24!F19+HISTOSEPT24!F19+HISTOOCT24!F19+HISTONOV24!F19+HISTODEC24!F19 -> 0 | G19: =HISTOJANV24!G19+HISTOFEV24!G19+HISTOMARS24!G19+HISTOAVRIL24!G19+HISTOMAI24!G19+HISTOJUIN24!G19+HISTOJUIL24!G19+HISTOAOUT24!G19+HISTOSEPT24!G19+HISTOOCT24!G19+HISTONOV24!G19+HISTODEC24!G19 -> 0 | I19: =HISTOJANV24!I19+HISTOFEV24!I19+HISTOMARS24!I19+HISTOAVRIL24!I19+HISTOMAI24!I19+HISTOJUIN24!I19+HISTOJUIL24!I19+HISTOAOUT24!I19+HISTOSEPT24!I19+HISTOOCT24!I19+HISTONOV24!I19+HISTODEC24!I19 -> 0 | J19: 1 | K19: =IF($D19<>0,J19*50000,IF($E19<>0,J19*50000,0)) -> 50000 | M19: =IF($D19<>0,L19*75000,IF($E19<>0,L19*75000,0)) -> 0 | O19: =IF($D19<>0,N19*100000,IF($E19<>0,N19*100000,0)) -> 0 | P19: =HISTOJANV24!P19+HISTOFEV24!P19+HISTOMARS24!P19+HISTOAVRIL24!P19+HISTOMAI24!P19+HISTOJUIN24!P19+HISTOJUIL24!P19+HISTOAOUT24!P19+HISTOSEPT24!P19+HISTOOCT24!P19+HISTONOV24!P19+HISTODEC24!P19 -> 0 | Q19: =HISTOJANV24!Q19+HISTOFEV24!Q19+HISTOMARS24!Q19+HISTOAVRIL24!Q19+HISTOMAI24!Q19+HISTOJUIN24!Q19+HISTOJUIL24!Q19+HISTOAOUT24!Q19+HISTOSEPT24!Q19+HISTOOCT24!Q19+HISTONOV24!Q19+HISTODEC24!Q19 -> 0 | R19: =HISTOJANV24!R19+HISTOFEV24!R19+HISTOMARS24!R19+HISTOAVRIL24!R19+HISTOMAI24!R19+HISTOJUIN24!R19+HISTOJUIL24!R19+HISTOAOUT24!R19+HISTOSEPT24!R19+HISTOOCT24!R19+HISTONOV24!R19+HISTODEC24!R19 -> 0 | S19: =HISTOJANV24!S19+HISTOFEV24!S19+HISTOMARS24!S19+HISTOAVRIL24!S19+HISTOMAI24!S19+HISTOJUIN24!S19+HISTOJUIL24!S19+HISTOAOUT24!S19+HISTOSEPT24!S19+HISTOOCT24!S19+HISTONOV24!S19+HISTODEC24!S19 -> 0 | U19: =G19+S19++R19+P19+O19+M19+I19+K19+Q19+V19+W19 -> 75000 | V19: =HISTOJANV24!V19+HISTOFEV24!V19+HISTOMARS24!V19+HISTOAVRIL24!V19+HISTOMAI24!V19+HISTOJUIN24!V19+HISTOJUIL24!V19+HISTOAOUT24!V19+HISTOSEPT24!V19+HISTOOCT24!V19+HISTONOV24!V19+HISTODEC24!V19 -> 0 | W19: =HISTOJANV24!W19+HISTOFEV24!W19+HISTOMARS24!W19+HISTOAVRIL24!W19+HISTOMAI24!W19+HISTOJUIN24!W19+HISTOJUIL24!W19+HISTOAOUT24!W19+HISTOSEPT24!W19+HISTOOCT24!W19+HISTONOV24!W19+HISTODEC24!W19 -> 25000 | X19: =HISTOJANV24!X19+HISTOFEV24!X19+HISTOMARS24!X19+HISTOAVRIL24!X19+HISTOMAI24!X19+HISTOJUIN24!X19+HISTOJUIL24!X19+HISTOAOUT24!X19+HISTOSEPT24!X19+HISTOOCT24!X19+HISTONOV24!X19+HISTODEC24!X19 -> 0 | Y19: =HISTOJANV24!Y19+HISTOFEV24!Y19+HISTOMARS24!Y19+HISTOAVRIL24!Y19+HISTOMAI24!Y19+HISTOJUIN24!Y19+HISTOJUIL24!Y19+HISTOAOUT24!Y19+HISTOSEPT24!Y19+HISTOOCT24!Y19+HISTONOV24!Y19+HISTODEC24!Y19 -> 0 | Z19: =HISTOJANV24!Z19+HISTOFEV24!Z19+HISTOMARS24!Z19+HISTOAVRIL24!Z19+HISTOMAI24!Z19+HISTOJUIN24!Z19+HISTOJUIL24!Z19+HISTOAOUT24!Z19+HISTOSEPT24!Z19+HISTOOCT24!Z19+HISTONOV24!Z19+HISTODEC24!Z19 -> 0 | AC19: =HISTOJANV24!AC19+HISTOFEV24!AC19+HISTOMARS24!AC19+HISTOAVRIL24!AC19+HISTOMAI24!AC19+HISTOJUIN24!AC19+HISTOJUIL24!AC19+HISTOAOUT24!AC19+HISTOSEPT24!AC19+HISTOOCT24!AC19+HISTONOV24!AC19+HISTODEC24!AC19 -> 0 | AD19: =HISTOJANV24!AD19+HISTOFEV24!AD19+HISTOMARS24!AD19+HISTOAVRIL24!AD19+HISTOMAI24!AD19+HISTOJUIN24!AD19+HISTOJUIL24!AD19+HISTOAOUT24!AD19+HISTOSEPT24!AD19+HISTOOCT24!AD19+HISTONOV24!AD19+HISTODEC24!AD19 -> 0 | AE19: =HISTOJANV24!AE19+HISTOFEV24!AE19+HISTOMARS24!AE19+HISTOAVRIL24!AE19+HISTOMAI24!AE19+HISTOJUIN24!AE19+HISTOJUIL24!AE19+HISTOAOUT24!AE19+HISTOSEPT24!AE19+HISTOOCT24!AE19+HISTONOV24!AE19+HISTODEC24!AE19 -> 0 | AH19: =HISTOJANV24!AH19+HISTOFEV24!AH19+HISTOMARS24!AH19+HISTOAVRIL24!AH19+HISTOMAI24!AH19+HISTOJUIN24!AH19+HISTOJUIL24!AH19+HISTOAOUT24!AH19+HISTOSEPT24!AH19+HISTOOCT24!AH19+HISTONOV24!AH19+HISTODEC24!AH19 -> 0 | AI19: =HISTOJANV24!AI19+HISTOFEV24!AI19+HISTOMARS24!AI19+HISTOAVRIL24!AI19+HISTOMAI24!AI19+HISTOJUIN24!AI19+HISTOJUIL24!AI19+HISTOAOUT24!AI19+HISTOSEPT24!AI19+HISTOOCT24!AI19+HISTONOV24!AI19+HISTODEC24!AI19 -> 0 | AJ19: =HISTOJANV24!AJ19+HISTOFEV24!AJ19+HISTOMARS24!AJ19+HISTOAVRIL24!AJ19+HISTOMAI24!AJ19+HISTOJUIN24!AJ19+HISTOJUIL24!AJ19+HISTOAOUT24!AJ19+HISTOSEPT24!AJ19+HISTOOCT24!AJ19+HISTONOV24!AJ19+HISTODEC24!AJ19 -> 0 | AK19: =HISTOJANV24!AK19+HISTOFEV24!AK19+HISTOMARS24!AK19+HISTOAVRIL24!AK19+HISTOMAI24!AK19+HISTOJUIN24!AK19+HISTOJUIL24!AK19+HISTOAOUT24!AK19+HISTOSEPT24!AK19+HISTOOCT24!AK19+HISTONOV24!AK19+HISTODEC24!AK19 -> 0 | AL19: =HISTOJANV24!AL19+HISTOFEV24!AL19+HISTOMARS24!AL19+HISTOAVRIL24!AL19+HISTOMAI24!AL19+HISTOJUIN24!AL19+HISTOJUIL24!AL19+HISTOAOUT24!AL19+HISTOSEPT24!AL19+HISTOOCT24!AL19+HISTONOV24!AL19+HISTODEC24!AL19 -> 0 | AM19: =HISTOJANV24!AM19+HISTOFEV24!AM19+HISTOMARS24!AM19+HISTOAVRIL24!AM19+HISTOMAI24!AM19+HISTOJUIN24!AM19+HISTOJUIL24!AM19+HISTOAOUT24!AM19+HISTOSEPT24!AM19+HISTOOCT24!AM19+HISTONOV24!AM19+HISTODEC24!AM19 -> 0 | AN19: =HISTOJANV24!AN19+HISTOFEV24!AN19+HISTOMARS24!AN19+HISTOAVRIL24!AN19+HISTOMAI24!AN19+HISTOJUIN24!AN19+HISTOJUIL24!AN19+HISTOAOUT24!AN19+HISTOSEPT24!AN19+HISTOOCT24!AN19+HISTONOV24!AN19+HISTODEC24!AN19 -> 0 | AQ19: =IF(H19="ECHEC",((K19+M19+O19)*20/100),0) -> 0 | AR19: =IF(H19="ECHEC",((K19+M19+O19)*20/100),0) -> 0 | AS19: =IF(H19="ECHEC",0,(K19+I19-25000)) -> 25000 | AW19: =HISTOJANV24!AW19+HISTOFEV24!AW19+HISTOMARS24!AW19+HISTOAVRIL24!AW19+HISTOMAI24!AW19+HISTOJUIN24!AW19+HISTOJUIL24!AW19+HISTOAOUT24!AW19+HISTOSEPT24!AW19+HISTOOCT24!AW19+HISTONOV24!AW19+HISTODEC24!AW19 -> 0 | AX19: =HISTOJANV24!AX19+HISTOFEV24!AX19+HISTOMARS24!AX19+HISTOAVRIL24!AX19+HISTOMAI24!AX19+HISTOJUIN24!AX19+HISTOJUIL24!AX19+HISTOAOUT24!AX19+HISTOSEPT24!AX19+HISTOOCT24!AX19+HISTONOV24!AX19+HISTODEC24!AX19 -> 0 | AY19: =HISTOJANV24!AY19+HISTOFEV24!AY19+HISTOMARS24!AY19+HISTOAVRIL24!AY19+HISTOMAI24!AY19+HISTOJUIN24!AY19+HISTOJUIL24!AY19+HISTOAOUT24!AY19+HISTOSEPT24!AY19+HISTOOCT24!AY19+HISTONOV24!AY19+HISTODEC24!AY19 -> 0 | AZ19: =HISTOJANV24!AZ19+HISTOFEV24!AZ19+HISTOMARS24!AZ19+HISTOAVRIL24!AZ19+HISTOMAI24!AZ19+HISTOJUIN24!AZ19+HISTOJUIL24!AZ19+HISTOAOUT24!AZ19+HISTOSEPT24!AZ19+HISTOOCT24!AZ19+HISTONOV24!AZ19+HISTODEC24!AZ19 -> 0 | BA19: =HISTOJANV24!BA19+HISTOFEV24!BA19+HISTOMARS24!BA19+HISTOAVRIL24!BA19+HISTOMAI24!BA19+HISTOJUIN24!BA19+HISTOJUIL24!BA19+HISTOAOUT24!BA19+HISTOSEPT24!BA19+HISTOOCT24!BA19+HISTONOV24!BA19+HISTODEC24!BA19 -> 0 | BB19: =HISTOJANV24!BB19+HISTOFEV24!BB19+HISTOMARS24!BB19+HISTOAVRIL24!BB19+HISTOMAI24!BB19+HISTOJUIN24!BB19+HISTOJUIL24!BB19+HISTOAOUT24!BB19+HISTOSEPT24!BB19+HISTOOCT24!BB19+HISTONOV24!BB19+HISTODEC24!BB19 -> 0 | BD19: =HISTOJANV24!BD19+HISTOFEV24!BD19+HISTOMARS24!BD19+HISTOAVRIL24!BD19+HISTOMAI24!BD19+HISTOJUIN24!BD19+HISTOJUIL24!BD19+HISTOAOUT24!BD19+HISTOSEPT24!BD19+HISTOOCT24!BD19+HISTONOV24!BD19+HISTODEC24!BD19 -> 0 | BF19: =HISTOJANV24!BF19+HISTOFEV24!BF19+HISTOMARS24!BF19+HISTOAVRIL24!BF19+HISTOMAI24!BF19+HISTOJUIN24!BF19+HISTOJUIL24!BF19+HISTOAOUT24!BF19+HISTOSEPT24!BF19+HISTOOCT24!BF19+HISTONOV24!BF19+HISTODEC24!BF19 -> 0
A20: AS201649 | B20: =VLOOKUP(A20,[11]LISTADHERENT!A$5:H$50,3,0) -> MBOGNING TUGMA GUY | D20: =HISTOJANV24!D20+HISTOFEV24!D20+HISTOMARS24!D20+HISTOAVRIL24!D20+HISTOMAI24!D20+HISTOJUIN24!D20+HISTOJUIL24!D20+HISTOAOUT24!D20+HISTOSEPT24!D20+HISTOOCT24!D20+HISTONOV24!D20+HISTODEC24!D20 -> 877000 | E20: =HISTOJANV24!E20+HISTOFEV24!E20+HISTOMARS24!E20+HISTOAVRIL24!E20+HISTOMAI24!E20+HISTOJUIN24!E20+HISTOJUIL24!E20+HISTOAOUT24!E20+HISTOSEPT24!E20+HISTOOCT24!E20+HISTONOV24!E20+HISTODEC24!E20 -> 0 | F20: =HISTOJANV24!F20+HISTOFEV24!F20+HISTOMARS24!F20+HISTOAVRIL24!F20+HISTOMAI24!F20+HISTOJUIN24!F20+HISTOJUIL24!F20+HISTOAOUT24!F20+HISTOSEPT24!F20+HISTOOCT24!F20+HISTONOV24!F20+HISTODEC24!F20 -> 0 | G20: =HISTOJANV24!G20+HISTOFEV24!G20+HISTOMARS24!G20+HISTOAVRIL24!G20+HISTOMAI24!G20+HISTOJUIN24!G20+HISTOJUIL24!G20+HISTOAOUT24!G20+HISTOSEPT24!G20+HISTOOCT24!G20+HISTONOV24!G20+HISTODEC24!G20 -> 0 | I20: =HISTOJANV24!I20+HISTOFEV24!I20+HISTOMARS24!I20+HISTOAVRIL24!I20+HISTOMAI24!I20+HISTOJUIN24!I20+HISTOJUIL24!I20+HISTOAOUT24!I20+HISTOSEPT24!I20+HISTOOCT24!I20+HISTONOV24!I20+HISTODEC24!I20 -> 0 | J20: 1 | K20: =IF($D20<>0,J20*50000,IF($E20<>0,J20*50000,0)) -> 50000 | L20: 1 | M20: =IF($D20<>0,L20*75000,IF($E20<>0,L20*75000,0)) -> 75000 | N20: 1 | O20: =IF($D20<>0,N20*100000,IF($E20<>0,N20*100000,0)) -> 100000 | P20: =HISTOJANV24!P20+HISTOFEV24!P20+HISTOMARS24!P20+HISTOAVRIL24!P20+HISTOMAI24!P20+HISTOJUIN24!P20+HISTOJUIL24!P20+HISTOAOUT24!P20+HISTOSEPT24!P20+HISTOOCT24!P20+HISTONOV24!P20+HISTODEC24!P20 -> 0 | Q20: =HISTOJANV24!Q20+HISTOFEV24!Q20+HISTOMARS24!Q20+HISTOAVRIL24!Q20+HISTOMAI24!Q20+HISTOJUIN24!Q20+HISTOJUIL24!Q20+HISTOAOUT24!Q20+HISTOSEPT24!Q20+HISTOOCT24!Q20+HISTONOV24!Q20+HISTODEC24!Q20 -> 91000 | R20: =HISTOJANV24!R20+HISTOFEV24!R20+HISTOMARS24!R20+HISTOAVRIL24!R20+HISTOMAI24!R20+HISTOJUIN24!R20+HISTOJUIL24!R20+HISTOAOUT24!R20+HISTOSEPT24!R20+HISTOOCT24!R20+HISTONOV24!R20+HISTODEC24!R20 -> 404000 | S20: =HISTOJANV24!S20+HISTOFEV24!S20+HISTOMARS24!S20+HISTOAVRIL24!S20+HISTOMAI24!S20+HISTOJUIN24!S20+HISTOJUIL24!S20+HISTOAOUT24!S20+HISTOSEPT24!S20+HISTOOCT24!S20+HISTONOV24!S20+HISTODEC24!S20 -> 0 | U20: =G20+S20++R20+P20+O20+M20+I20+K20+Q20+V20+W20 -> 720000 | V20: =HISTOJANV24!V20+HISTOFEV24!V20+HISTOMARS24!V20+HISTOAVRIL24!V20+HISTOMAI24!V20+HISTOJUIN24!V20+HISTOJUIL24!V20+HISTOAOUT24!V20+HISTOSEPT24!V20+HISTOOCT24!V20+HISTONOV24!V20+HISTODEC24!V20 -> 0 | W20: =HISTOJANV24!W20+HISTOFEV24!W20+HISTOMARS24!W20+HISTOAVRIL24!W20+HISTOMAI24!W20+HISTOJUIN24!W20+HISTOJUIL24!W20+HISTOAOUT24!W20+HISTOSEPT24!W20+HISTOOCT24!W20+HISTONOV24!W20+HISTODEC24!W20 -> 0 | X20: =HISTOJANV24!X20+HISTOFEV24!X20+HISTOMARS24!X20+HISTOAVRIL24!X20+HISTOMAI24!X20+HISTOJUIN24!X20+HISTOJUIL24!X20+HISTOAOUT24!X20+HISTOSEPT24!X20+HISTOOCT24!X20+HISTONOV24!X20+HISTODEC24!X20 -> 0 | Y20: =HISTOJANV24!Y20+HISTOFEV24!Y20+HISTOMARS24!Y20+HISTOAVRIL24!Y20+HISTOMAI24!Y20+HISTOJUIN24!Y20+HISTOJUIL24!Y20+HISTOAOUT24!Y20+HISTOSEPT24!Y20+HISTOOCT24!Y20+HISTONOV24!Y20+HISTODEC24!Y20 -> 0 | Z20: =HISTOJANV24!Z20+HISTOFEV24!Z20+HISTOMARS24!Z20+HISTOAVRIL24!Z20+HISTOMAI24!Z20+HISTOJUIN24!Z20+HISTOJUIL24!Z20+HISTOAOUT24!Z20+HISTOSEPT24!Z20+HISTOOCT24!Z20+HISTONOV24!Z20+HISTODEC24!Z20 -> 0 | AC20: =HISTOJANV24!AC20+HISTOFEV24!AC20+HISTOMARS24!AC20+HISTOAVRIL24!AC20+HISTOMAI24!AC20+HISTOJUIN24!AC20+HISTOJUIL24!AC20+HISTOAOUT24!AC20+HISTOSEPT24!AC20+HISTOOCT24!AC20+HISTONOV24!AC20+HISTODEC24!AC20 -> 0 | AD20: =HISTOJANV24!AD20+HISTOFEV24!AD20+HISTOMARS24!AD20+HISTOAVRIL24!AD20+HISTOMAI24!AD20+HISTOJUIN24!AD20+HISTOJUIL24!AD20+HISTOAOUT24!AD20+HISTOSEPT24!AD20+HISTOOCT24!AD20+HISTONOV24!AD20+HISTODEC24!AD20 -> 16000 | AE20: =HISTOJANV24!AE20+HISTOFEV24!AE20+HISTOMARS24!AE20+HISTOAVRIL24!AE20+HISTOMAI24!AE20+HISTOJUIN24!AE20+HISTOJUIL24!AE20+HISTOAOUT24!AE20+HISTOSEPT24!AE20+HISTOOCT24!AE20+HISTONOV24!AE20+HISTODEC24!AE20 -> 115000 | AH20: =HISTOJANV24!AH20+HISTOFEV24!AH20+HISTOMARS24!AH20+HISTOAVRIL24!AH20+HISTOMAI24!AH20+HISTOJUIN24!AH20+HISTOJUIL24!AH20+HISTOAOUT24!AH20+HISTOSEPT24!AH20+HISTOOCT24!AH20+HISTONOV24!AH20+HISTODEC24!AH20 -> 0 | AI20: =HISTOJANV24!AI20+HISTOFEV24!AI20+HISTOMARS24!AI20+HISTOAVRIL24!AI20+HISTOMAI24!AI20+HISTOJUIN24!AI20+HISTOJUIL24!AI20+HISTOAOUT24!AI20+HISTOSEPT24!AI20+HISTOOCT24!AI20+HISTONOV24!AI20+HISTODEC24!AI20 -> 0 | AJ20: =HISTOJANV24!AJ20+HISTOFEV24!AJ20+HISTOMARS24!AJ20+HISTOAVRIL24!AJ20+HISTOMAI24!AJ20+HISTOJUIN24!AJ20+HISTOJUIL24!AJ20+HISTOAOUT24!AJ20+HISTOSEPT24!AJ20+HISTOOCT24!AJ20+HISTONOV24!AJ20+HISTODEC24!AJ20 -> 89000 | AK20: =HISTOJANV24!AK20+HISTOFEV24!AK20+HISTOMARS24!AK20+HISTOAVRIL24!AK20+HISTOMAI24!AK20+HISTOJUIN24!AK20+HISTOJUIL24!AK20+HISTOAOUT24!AK20+HISTOSEPT24!AK20+HISTOOCT24!AK20+HISTONOV24!AK20+HISTODEC24!AK20 -> 400000 | AL20: =HISTOJANV24!AL20+HISTOFEV24!AL20+HISTOMARS24!AL20+HISTOAVRIL24!AL20+HISTOMAI24!AL20+HISTOJUIN24!AL20+HISTOJUIL24!AL20+HISTOAOUT24!AL20+HISTOSEPT24!AL20+HISTOOCT24!AL20+HISTONOV24!AL20+HISTODEC24!AL20 -> 0 | AM20: =HISTOJANV24!AM20+HISTOFEV24!AM20+HISTOMARS24!AM20+HISTOAVRIL24!AM20+HISTOMAI24!AM20+HISTOJUIN24!AM20+HISTOJUIL24!AM20+HISTOAOUT24!AM20+HISTOSEPT24!AM20+HISTOOCT24!AM20+HISTONOV24!AM20+HISTODEC24!AM20 -> 2000 | AN20: =HISTOJANV24!AN20+HISTOFEV24!AN20+HISTOMARS24!AN20+HISTOAVRIL24!AN20+HISTOMAI24!AN20+HISTOJUIN24!AN20+HISTOJUIL24!AN20+HISTOAOUT24!AN20+HISTOSEPT24!AN20+HISTOOCT24!AN20+HISTONOV24!AN20+HISTODEC24!AN20 -> 4000 | AQ20: =IF(H20="ECHEC",((K20+M20+O20)*20/100),0) -> 0 | AR20: =IF(H20="ECHEC",((K20+M20+O20)*20/100),0) -> 0 | AS20: =IF(H20="ECHEC",0,(K20+I20-25000)) -> 25000 | AW20: =HISTOJANV24!AW20+HISTOFEV24!AW20+HISTOMARS24!AW20+HISTOAVRIL24!AW20+HISTOMAI24!AW20+HISTOJUIN24!AW20+HISTOJUIL24!AW20+HISTOAOUT24!AW20+HISTOSEPT24!AW20+HISTOOCT24!AW20+HISTONOV24!AW20+HISTODEC24!AW20 -> 0 | AX20: =HISTOJANV24!AX20+HISTOFEV24!AX20+HISTOMARS24!AX20+HISTOAVRIL24!AX20+HISTOMAI24!AX20+HISTOJUIN24!AX20+HISTOJUIL24!AX20+HISTOAOUT24!AX20+HISTOSEPT24!AX20+HISTOOCT24!AX20+HISTONOV24!AX20+HISTODEC24!AX20 -> 973000 | AY20: =HISTOJANV24!AY20+HISTOFEV24!AY20+HISTOMARS24!AY20+HISTOAVRIL24!AY20+HISTOMAI24!AY20+HISTOJUIN24!AY20+HISTOJUIL24!AY20+HISTOAOUT24!AY20+HISTOSEPT24!AY20+HISTOOCT24!AY20+HISTONOV24!AY20+HISTODEC24!AY20 -> 1485000 | AZ20: =HISTOJANV24!AZ20+HISTOFEV24!AZ20+HISTOMARS24!AZ20+HISTOAVRIL24!AZ20+HISTOMAI24!AZ20+HISTOJUIN24!AZ20+HISTOJUIL24!AZ20+HISTOAOUT24!AZ20+HISTOSEPT24!AZ20+HISTOOCT24!AZ20+HISTONOV24!AZ20+HISTODEC24!AZ20 -> 2458000 | BA20: =HISTOJANV24!BA20+HISTOFEV24!BA20+HISTOMARS24!BA20+HISTOAVRIL24!BA20+HISTOMAI24!BA20+HISTOJUIN24!BA20+HISTOJUIL24!BA20+HISTOAOUT24!BA20+HISTOSEPT24!BA20+HISTOOCT24!BA20+HISTONOV24!BA20+HISTODEC24!BA20 -> 345500 | BB20: =HISTOJANV24!BB20+HISTOFEV24!BB20+HISTOMARS24!BB20+HISTOAVRIL24!BB20+HISTOMAI24!BB20+HISTOJUIN24!BB20+HISTOJUIL24!BB20+HISTOAOUT24!BB20+HISTOSEPT24!BB20+HISTOOCT24!BB20+HISTONOV24!BB20+HISTODEC24!BB20 -> 0 | BD20: =HISTOJANV24!BD20+HISTOFEV24!BD20+HISTOMARS24!BD20+HISTOAVRIL24!BD20+HISTOMAI24!BD20+HISTOJUIN24!BD20+HISTOJUIL24!BD20+HISTOAOUT24!BD20+HISTOSEPT24!BD20+HISTOOCT24!BD20+HISTONOV24!BD20+HISTODEC24!BD20 -> 2112500 | BF20: =HISTOJANV24!BF20+HISTOFEV24!BF20+HISTOMARS24!BF20+HISTOAVRIL24!BF20+HISTOMAI24!BF20+HISTOJUIN24!BF20+HISTOJUIL24!BF20+HISTOAOUT24!BF20+HISTOSEPT24!BF20+HISTOOCT24!BF20+HISTONOV24!BF20+HISTODEC24!BF20 -> 0
A21: AS201639 | B21: =VLOOKUP(A21,[11]LISTADHERENT!A$5:H$50,3,0) -> NANGUEN MARTIN | D21: =HISTOJANV24!D21+HISTOFEV24!D21+HISTOMARS24!D21+HISTOAVRIL24!D21+HISTOMAI24!D21+HISTOJUIN24!D21+HISTOJUIL24!D21+HISTOAOUT24!D21+HISTOSEPT24!D21+HISTOOCT24!D21+HISTONOV24!D21+HISTODEC24!D21 -> 150000 | E21: =HISTOJANV24!E21+HISTOFEV24!E21+HISTOMARS24!E21+HISTOAVRIL24!E21+HISTOMAI24!E21+HISTOJUIN24!E21+HISTOJUIL24!E21+HISTOAOUT24!E21+HISTOSEPT24!E21+HISTOOCT24!E21+HISTONOV24!E21+HISTODEC24!E21 -> 0 | F21: =HISTOJANV24!F21+HISTOFEV24!F21+HISTOMARS24!F21+HISTOAVRIL24!F21+HISTOMAI24!F21+HISTOJUIN24!F21+HISTOJUIL24!F21+HISTOAOUT24!F21+HISTOSEPT24!F21+HISTOOCT24!F21+HISTONOV24!F21+HISTODEC24!F21 -> 0 | G21: =HISTOJANV24!G21+HISTOFEV24!G21+HISTOMARS24!G21+HISTOAVRIL24!G21+HISTOMAI24!G21+HISTOJUIN24!G21+HISTOJUIL24!G21+HISTOAOUT24!G21+HISTOSEPT24!G21+HISTOOCT24!G21+HISTONOV24!G21+HISTODEC24!G21 -> 0 | I21: =HISTOJANV24!I21+HISTOFEV24!I21+HISTOMARS24!I21+HISTOAVRIL24!I21+HISTOMAI24!I21+HISTOJUIN24!I21+HISTOJUIL24!I21+HISTOAOUT24!I21+HISTOSEPT24!I21+HISTOOCT24!I21+HISTONOV24!I21+HISTODEC24!I21 -> 0 | J21: 1 | K21: =IF($D21<>0,J21*50000,IF($E21<>0,J21*50000,0)) -> 50000 | M21: =IF($D21<>0,L21*75000,IF($E21<>0,L21*75000,0)) -> 0 | O21: =IF($D21<>0,N21*100000,IF($E21<>0,N21*100000,0)) -> 0 | P21: =HISTOJANV24!P21+HISTOFEV24!P21+HISTOMARS24!P21+HISTOAVRIL24!P21+HISTOMAI24!P21+HISTOJUIN24!P21+HISTOJUIL24!P21+HISTOAOUT24!P21+HISTOSEPT24!P21+HISTOOCT24!P21+HISTONOV24!P21+HISTODEC24!P21 -> 0 | Q21: =HISTOJANV24!Q21+HISTOFEV24!Q21+HISTOMARS24!Q21+HISTOAVRIL24!Q21+HISTOMAI24!Q21+HISTOJUIN24!Q21+HISTOJUIL24!Q21+HISTOAOUT24!Q21+HISTOSEPT24!Q21+HISTOOCT24!Q21+HISTONOV24!Q21+HISTODEC24!Q21 -> 0 | R21: =HISTOJANV24!R21+HISTOFEV24!R21+HISTOMARS24!R21+HISTOAVRIL24!R21+HISTOMAI24!R21+HISTOJUIN24!R21+HISTOJUIL24!R21+HISTOAOUT24!R21+HISTOSEPT24!R21+HISTOOCT24!R21+HISTONOV24!R21+HISTODEC24!R21 -> 0 | S21: =HISTOJANV24!S21+HISTOFEV24!S21+HISTOMARS24!S21+HISTOAVRIL24!S21+HISTOMAI24!S21+HISTOJUIN24!S21+HISTOJUIL24!S21+HISTOAOUT24!S21+HISTOSEPT24!S21+HISTOOCT24!S21+HISTONOV24!S21+HISTODEC24!S21 -> 0 | U21: =G21+S21++R21+P21+O21+M21+I21+K21+Q21+V21+W21 -> 50000 | V21: =HISTOJANV24!V21+HISTOFEV24!V21+HISTOMARS24!V21+HISTOAVRIL24!V21+HISTOMAI24!V21+HISTOJUIN24!V21+HISTOJUIL24!V21+HISTOAOUT24!V21+HISTOSEPT24!V21+HISTOOCT24!V21+HISTONOV24!V21+HISTODEC24!V21 -> 0 | W21: =HISTOJANV24!W21+HISTOFEV24!W21+HISTOMARS24!W21+HISTOAVRIL24!W21+HISTOMAI24!W21+HISTOJUIN24!W21+HISTOJUIL24!W21+HISTOAOUT24!W21+HISTOSEPT24!W21+HISTOOCT24!W21+HISTONOV24!W21+HISTODEC24!W21 -> 0 | X21: =HISTOJANV24!X21+HISTOFEV24!X21+HISTOMARS24!X21+HISTOAVRIL24!X21+HISTOMAI24!X21+HISTOJUIN24!X21+HISTOJUIL24!X21+HISTOAOUT24!X21+HISTOSEPT24!X21+HISTOOCT24!X21+HISTONOV24!X21+HISTODEC24!X21 -> 0 | Y21: =HISTOJANV24!Y21+HISTOFEV24!Y21+HISTOMARS24!Y21+HISTOAVRIL24!Y21+HISTOMAI24!Y21+HISTOJUIN24!Y21+HISTOJUIL24!Y21+HISTOAOUT24!Y21+HISTOSEPT24!Y21+HISTOOCT24!Y21+HISTONOV24!Y21+HISTODEC24!Y21 -> 0 | Z21: =HISTOJANV24!Z21+HISTOFEV24!Z21+HISTOMARS24!Z21+HISTOAVRIL24!Z21+HISTOMAI24!Z21+HISTOJUIN24!Z21+HISTOJUIL24!Z21+HISTOAOUT24!Z21+HISTOSEPT24!Z21+HISTOOCT24!Z21+HISTONOV24!Z21+HISTODEC24!Z21 -> 0 | AC21: =HISTOJANV24!AC21+HISTOFEV24!AC21+HISTOMARS24!AC21+HISTOAVRIL24!AC21+HISTOMAI24!AC21+HISTOJUIN24!AC21+HISTOJUIL24!AC21+HISTOAOUT24!AC21+HISTOSEPT24!AC21+HISTOOCT24!AC21+HISTONOV24!AC21+HISTODEC24!AC21 -> 0 | AD21: =HISTOJANV24!AD21+HISTOFEV24!AD21+HISTOMARS24!AD21+HISTOAVRIL24!AD21+HISTOMAI24!AD21+HISTOJUIN24!AD21+HISTOJUIL24!AD21+HISTOAOUT24!AD21+HISTOSEPT24!AD21+HISTOOCT24!AD21+HISTONOV24!AD21+HISTODEC24!AD21 -> 0 | AE21: =HISTOJANV24!AE21+HISTOFEV24!AE21+HISTOMARS24!AE21+HISTOAVRIL24!AE21+HISTOMAI24!AE21+HISTOJUIN24!AE21+HISTOJUIL24!AE21+HISTOAOUT24!AE21+HISTOSEPT24!AE21+HISTOOCT24!AE21+HISTONOV24!AE21+HISTODEC24!AE21 -> 0 | AH21: =HISTOJANV24!AH21+HISTOFEV24!AH21+HISTOMARS24!AH21+HISTOAVRIL24!AH21+HISTOMAI24!AH21+HISTOJUIN24!AH21+HISTOJUIL24!AH21+HISTOAOUT24!AH21+HISTOSEPT24!AH21+HISTOOCT24!AH21+HISTONOV24!AH21+HISTODEC24!AH21 -> 0 | AI21: =HISTOJANV24!AI21+HISTOFEV24!AI21+HISTOMARS24!AI21+HISTOAVRIL24!AI21+HISTOMAI24!AI21+HISTOJUIN24!AI21+HISTOJUIL24!AI21+HISTOAOUT24!AI21+HISTOSEPT24!AI21+HISTOOCT24!AI21+HISTONOV24!AI21+HISTODEC24!AI21 -> 0 | AJ21: =HISTOJANV24!AJ21+HISTOFEV24!AJ21+HISTOMARS24!AJ21+HISTOAVRIL24!AJ21+HISTOMAI24!AJ21+HISTOJUIN24!AJ21+HISTOJUIL24!AJ21+HISTOAOUT24!AJ21+HISTOSEPT24!AJ21+HISTOOCT24!AJ21+HISTONOV24!AJ21+HISTODEC24!AJ21 -> 0 | AK21: =HISTOJANV24!AK21+HISTOFEV24!AK21+HISTOMARS24!AK21+HISTOAVRIL24!AK21+HISTOMAI24!AK21+HISTOJUIN24!AK21+HISTOJUIL24!AK21+HISTOAOUT24!AK21+HISTOSEPT24!AK21+HISTOOCT24!AK21+HISTONOV24!AK21+HISTODEC24!AK21 -> 0 | AL21: =HISTOJANV24!AL21+HISTOFEV24!AL21+HISTOMARS24!AL21+HISTOAVRIL24!AL21+HISTOMAI24!AL21+HISTOJUIN24!AL21+HISTOJUIL24!AL21+HISTOAOUT24!AL21+HISTOSEPT24!AL21+HISTOOCT24!AL21+HISTONOV24!AL21+HISTODEC24!AL21 -> 0 | AM21: =HISTOJANV24!AM21+HISTOFEV24!AM21+HISTOMARS24!AM21+HISTOAVRIL24!AM21+HISTOMAI24!AM21+HISTOJUIN24!AM21+HISTOJUIL24!AM21+HISTOAOUT24!AM21+HISTOSEPT24!AM21+HISTOOCT24!AM21+HISTONOV24!AM21+HISTODEC24!AM21 -> 0 | AN21: =HISTOJANV24!AN21+HISTOFEV24!AN21+HISTOMARS24!AN21+HISTOAVRIL24!AN21+HISTOMAI24!AN21+HISTOJUIN24!AN21+HISTOJUIL24!AN21+HISTOAOUT24!AN21+HISTOSEPT24!AN21+HISTOOCT24!AN21+HISTONOV24!AN21+HISTODEC24!AN21 -> 0 | AQ21: =IF(H21="ECHEC",((K21+M21+O21)*20/100),0) -> 0 | AR21: =IF(H21="ECHEC",((K21+M21+O21)*20/100),0) -> 0 | AS21: =IF(H21="ECHEC",0,(K21+I21-25000)) -> 25000 | AW21: =HISTOJANV24!AW21+HISTOFEV24!AW21+HISTOMARS24!AW21+HISTOAVRIL24!AW21+HISTOMAI24!AW21+HISTOJUIN24!AW21+HISTOJUIL24!AW21+HISTOAOUT24!AW21+HISTOSEPT24!AW21+HISTOOCT24!AW21+HISTONOV24!AW21+HISTODEC24!AW21 -> 0 | AX21: =HISTOJANV24!AX21+HISTOFEV24!AX21+HISTOMARS24!AX21+HISTOAVRIL24!AX21+HISTOMAI24!AX21+HISTOJUIN24!AX21+HISTOJUIL24!AX21+HISTOAOUT24!AX21+HISTOSEPT24!AX21+HISTOOCT24!AX21+HISTONOV24!AX21+HISTODEC24!AX21 -> 0 | AY21: =HISTOJANV24!AY21+HISTOFEV24!AY21+HISTOMARS24!AY21+HISTOAVRIL24!AY21+HISTOMAI24!AY21+HISTOJUIN24!AY21+HISTOJUIL24!AY21+HISTOAOUT24!AY21+HISTOSEPT24!AY21+HISTOOCT24!AY21+HISTONOV24!AY21+HISTODEC24!AY21 -> 0 | AZ21: =HISTOJANV24!AZ21+HISTOFEV24!AZ21+HISTOMARS24!AZ21+HISTOAVRIL24!AZ21+HISTOMAI24!AZ21+HISTOJUIN24!AZ21+HISTOJUIL24!AZ21+HISTOAOUT24!AZ21+HISTOSEPT24!AZ21+HISTOOCT24!AZ21+HISTONOV24!AZ21+HISTODEC24!AZ21 -> 0 | BA21: =HISTOJANV24!BA21+HISTOFEV24!BA21+HISTOMARS24!BA21+HISTOAVRIL24!BA21+HISTOMAI24!BA21+HISTOJUIN24!BA21+HISTOJUIL24!BA21+HISTOAOUT24!BA21+HISTOSEPT24!BA21+HISTOOCT24!BA21+HISTONOV24!BA21+HISTODEC24!BA21 -> 0 | BB21: =HISTOJANV24!BB21+HISTOFEV24!BB21+HISTOMARS24!BB21+HISTOAVRIL24!BB21+HISTOMAI24!BB21+HISTOJUIN24!BB21+HISTOJUIL24!BB21+HISTOAOUT24!BB21+HISTOSEPT24!BB21+HISTOOCT24!BB21+HISTONOV24!BB21+HISTODEC24!BB21 -> 0 | BD21: =HISTOJANV24!BD21+HISTOFEV24!BD21+HISTOMARS24!BD21+HISTOAVRIL24!BD21+HISTOMAI24!BD21+HISTOJUIN24!BD21+HISTOJUIL24!BD21+HISTOAOUT24!BD21+HISTOSEPT24!BD21+HISTOOCT24!BD21+HISTONOV24!BD21+HISTODEC24!BD21 -> 0 | BF21: =HISTOJANV24!BF21+HISTOFEV24!BF21+HISTOMARS24!BF21+HISTOAVRIL24!BF21+HISTOMAI24!BF21+HISTOJUIN24!BF21+HISTOJUIL24!BF21+HISTOAOUT24!BF21+HISTOSEPT24!BF21+HISTOOCT24!BF21+HISTONOV24!BF21+HISTODEC24!BF21 -> 0
A22: AS201621 | B22: =VLOOKUP(A22,[11]LISTADHERENT!A$5:H$50,3,0) -> NANKAM APPOLINAIRE | D22: =HISTOJANV24!D22+HISTOFEV24!D22+HISTOMARS24!D22+HISTOAVRIL24!D22+HISTOMAI24!D22+HISTOJUIN24!D22+HISTOJUIL24!D22+HISTOAOUT24!D22+HISTOSEPT24!D22+HISTOOCT24!D22+HISTONOV24!D22+HISTODEC24!D22 -> 375000 | E22: =HISTOJANV24!E22+HISTOFEV24!E22+HISTOMARS24!E22+HISTOAVRIL24!E22+HISTOMAI24!E22+HISTOJUIN24!E22+HISTOJUIL24!E22+HISTOAOUT24!E22+HISTOSEPT24!E22+HISTOOCT24!E22+HISTONOV24!E22+HISTODEC24!E22 -> 0 | F22: =HISTOJANV24!F22+HISTOFEV24!F22+HISTOMARS24!F22+HISTOAVRIL24!F22+HISTOMAI24!F22+HISTOJUIN24!F22+HISTOJUIL24!F22+HISTOAOUT24!F22+HISTOSEPT24!F22+HISTOOCT24!F22+HISTONOV24!F22+HISTODEC24!F22 -> 0 | G22: =HISTOJANV24!G22+HISTOFEV24!G22+HISTOMARS24!G22+HISTOAVRIL24!G22+HISTOMAI24!G22+HISTOJUIN24!G22+HISTOJUIL24!G22+HISTOAOUT24!G22+HISTOSEPT24!G22+HISTOOCT24!G22+HISTONOV24!G22+HISTODEC24!G22 -> 0 | I22: =HISTOJANV24!I22+HISTOFEV24!I22+HISTOMARS24!I22+HISTOAVRIL24!I22+HISTOMAI24!I22+HISTOJUIN24!I22+HISTOJUIL24!I22+HISTOAOUT24!I22+HISTOSEPT24!I22+HISTOOCT24!I22+HISTONOV24!I22+HISTODEC24!I22 -> 0 | J22: 1 | K22: =IF($D22<>0,J22*50000,IF($E22<>0,J22*50000,0)) -> 50000 | L22: 1 | M22: =IF($D22<>0,L22*75000,IF($E22<>0,L22*75000,0)) -> 75000 | O22: =IF($D22<>0,N22*100000,IF($E22<>0,N22*100000,0)) -> 0 | P22: =HISTOJANV24!P22+HISTOFEV24!P22+HISTOMARS24!P22+HISTOAVRIL24!P22+HISTOMAI24!P22+HISTOJUIN24!P22+HISTOJUIL24!P22+HISTOAOUT24!P22+HISTOSEPT24!P22+HISTOOCT24!P22+HISTONOV24!P22+HISTODEC24!P22 -> 0 | Q22: =HISTOJANV24!Q22+HISTOFEV24!Q22+HISTOMARS24!Q22+HISTOAVRIL24!Q22+HISTOMAI24!Q22+HISTOJUIN24!Q22+HISTOJUIL24!Q22+HISTOAOUT24!Q22+HISTOSEPT24!Q22+HISTOOCT24!Q22+HISTONOV24!Q22+HISTODEC24!Q22 -> 0 | R22: =HISTOJANV24!R22+HISTOFEV24!R22+HISTOMARS24!R22+HISTOAVRIL24!R22+HISTOMAI24!R22+HISTOJUIN24!R22+HISTOJUIL24!R22+HISTOAOUT24!R22+HISTOSEPT24!R22+HISTOOCT24!R22+HISTONOV24!R22+HISTODEC24!R22 -> 0 | S22: =HISTOJANV24!S22+HISTOFEV24!S22+HISTOMARS24!S22+HISTOAVRIL24!S22+HISTOMAI24!S22+HISTOJUIN24!S22+HISTOJUIL24!S22+HISTOAOUT24!S22+HISTOSEPT24!S22+HISTOOCT24!S22+HISTONOV24!S22+HISTODEC24!S22 -> 0 | U22: =G22+S22++R22+P22+O22+M22+I22+K22+Q22+V22+W22 -> 125000 | V22: =HISTOJANV24!V22+HISTOFEV24!V22+HISTOMARS24!V22+HISTOAVRIL24!V22+HISTOMAI24!V22+HISTOJUIN24!V22+HISTOJUIL24!V22+HISTOAOUT24!V22+HISTOSEPT24!V22+HISTOOCT24!V22+HISTONOV24!V22+HISTODEC24!V22 -> 0 | W22: =HISTOJANV24!W22+HISTOFEV24!W22+HISTOMARS24!W22+HISTOAVRIL24!W22+HISTOMAI24!W22+HISTOJUIN24!W22+HISTOJUIL24!W22+HISTOAOUT24!W22+HISTOSEPT24!W22+HISTOOCT24!W22+HISTONOV24!W22+HISTODEC24!W22 -> 0 | X22: =HISTOJANV24!X22+HISTOFEV24!X22+HISTOMARS24!X22+HISTOAVRIL24!X22+HISTOMAI24!X22+HISTOJUIN24!X22+HISTOJUIL24!X22+HISTOAOUT24!X22+HISTOSEPT24!X22+HISTOOCT24!X22+HISTONOV24!X22+HISTODEC24!X22 -> 0 | Y22: =HISTOJANV24!Y22+HISTOFEV24!Y22+HISTOMARS24!Y22+HISTOAVRIL24!Y22+HISTOMAI24!Y22+HISTOJUIN24!Y22+HISTOJUIL24!Y22+HISTOAOUT24!Y22+HISTOSEPT24!Y22+HISTOOCT24!Y22+HISTONOV24!Y22+HISTODEC24!Y22 -> 0 | Z22: =HISTOJANV24!Z22+HISTOFEV24!Z22+HISTOMARS24!Z22+HISTOAVRIL24!Z22+HISTOMAI24!Z22+HISTOJUIN24!Z22+HISTOJUIL24!Z22+HISTOAOUT24!Z22+HISTOSEPT24!Z22+HISTOOCT24!Z22+HISTONOV24!Z22+HISTODEC24!Z22 -> 0 | AC22: =HISTOJANV24!AC22+HISTOFEV24!AC22+HISTOMARS24!AC22+HISTOAVRIL24!AC22+HISTOMAI24!AC22+HISTOJUIN24!AC22+HISTOJUIL24!AC22+HISTOAOUT24!AC22+HISTOSEPT24!AC22+HISTOOCT24!AC22+HISTONOV24!AC22+HISTODEC24!AC22 -> 17000 | AD22: =HISTOJANV24!AD22+HISTOFEV24!AD22+HISTOMARS24!AD22+HISTOAVRIL24!AD22+HISTOMAI24!AD22+HISTOJUIN24!AD22+HISTOJUIL24!AD22+HISTOAOUT24!AD22+HISTOSEPT24!AD22+HISTOOCT24!AD22+HISTONOV24!AD22+HISTODEC24!AD22 -> 0 | AE22: =HISTOJANV24!AE22+HISTOFEV24!AE22+HISTOMARS24!AE22+HISTOAVRIL24!AE22+HISTOMAI24!AE22+HISTOJUIN24!AE22+HISTOJUIL24!AE22+HISTOAOUT24!AE22+HISTOSEPT24!AE22+HISTOOCT24!AE22+HISTONOV24!AE22+HISTODEC24!AE22 -> 0 | AH22: =HISTOJANV24!AH22+HISTOFEV24!AH22+HISTOMARS24!AH22+HISTOAVRIL24!AH22+HISTOMAI24!AH22+HISTOJUIN24!AH22+HISTOJUIL24!AH22+HISTOAOUT24!AH22+HISTOSEPT24!AH22+HISTOOCT24!AH22+HISTONOV24!AH22+HISTODEC24!AH22 -> 0 | AI22: =HISTOJANV24!AI22+HISTOFEV24!AI22+HISTOMARS24!AI22+HISTOAVRIL24!AI22+HISTOMAI24!AI22+HISTOJUIN24!AI22+HISTOJUIL24!AI22+HISTOAOUT24!AI22+HISTOSEPT24!AI22+HISTOOCT24!AI22+HISTONOV24!AI22+HISTODEC24!AI22 -> 0 | AJ22: =HISTOJANV24!AJ22+HISTOFEV24!AJ22+HISTOMARS24!AJ22+HISTOAVRIL24!AJ22+HISTOMAI24!AJ22+HISTOJUIN24!AJ22+HISTOJUIL24!AJ22+HISTOAOUT24!AJ22+HISTOSEPT24!AJ22+HISTOOCT24!AJ22+HISTONOV24!AJ22+HISTODEC24!AJ22 -> 0 | AK22: =HISTOJANV24!AK22+HISTOFEV24!AK22+HISTOMARS24!AK22+HISTOAVRIL24!AK22+HISTOMAI24!AK22+HISTOJUIN24!AK22+HISTOJUIL24!AK22+HISTOAOUT24!AK22+HISTOSEPT24!AK22+HISTOOCT24!AK22+HISTONOV24!AK22+HISTODEC24!AK22 -> 0 | AL22: =HISTOJANV24!AL22+HISTOFEV24!AL22+HISTOMARS24!AL22+HISTOAVRIL24!AL22+HISTOMAI24!AL22+HISTOJUIN24!AL22+HISTOJUIL24!AL22+HISTOAOUT24!AL22+HISTOSEPT24!AL22+HISTOOCT24!AL22+HISTONOV24!AL22+HISTODEC24!AL22 -> 0 | AM22: =HISTOJANV24!AM22+HISTOFEV24!AM22+HISTOMARS24!AM22+HISTOAVRIL24!AM22+HISTOMAI24!AM22+HISTOJUIN24!AM22+HISTOJUIL24!AM22+HISTOAOUT24!AM22+HISTOSEPT24!AM22+HISTOOCT24!AM22+HISTONOV24!AM22+HISTODEC24!AM22 -> 0 | AN22: =HISTOJANV24!AN22+HISTOFEV24!AN22+HISTOMARS24!AN22+HISTOAVRIL24!AN22+HISTOMAI24!AN22+HISTOJUIN24!AN22+HISTOJUIL24!AN22+HISTOAOUT24!AN22+HISTOSEPT24!AN22+HISTOOCT24!AN22+HISTONOV24!AN22+HISTODEC24!AN22 -> 0 | AQ22: =IF(H22="ECHEC",((K22+M22+O22)*20/100),0) -> 0 | AR22: =IF(H22="ECHEC",((K22+M22+O22)*20/100),0) -> 0 | AS22: =IF(H22="ECHEC",0,(K22+I22-25000)) -> 25000 | AW22: =HISTOJANV24!AW22+HISTOFEV24!AW22+HISTOMARS24!AW22+HISTOAVRIL24!AW22+HISTOMAI24!AW22+HISTOJUIN24!AW22+HISTOJUIL24!AW22+HISTOAOUT24!AW22+HISTOSEPT24!AW22+HISTOOCT24!AW22+HISTONOV24!AW22+HISTODEC24!AW22 -> 283000 | AX22: =HISTOJANV24!AX22+HISTOFEV24!AX22+HISTOMARS24!AX22+HISTOAVRIL24!AX22+HISTOMAI24!AX22+HISTOJUIN24!AX22+HISTOJUIL24!AX22+HISTOAOUT24!AX22+HISTOSEPT24!AX22+HISTOOCT24!AX22+HISTONOV24!AX22+HISTODEC24!AX22 -> 0 | AY22: =HISTOJANV24!AY22+HISTOFEV24!AY22+HISTOMARS24!AY22+HISTOAVRIL24!AY22+HISTOMAI24!AY22+HISTOJUIN24!AY22+HISTOJUIL24!AY22+HISTOAOUT24!AY22+HISTOSEPT24!AY22+HISTOOCT24!AY22+HISTONOV24!AY22+HISTODEC24!AY22 -> 0 | AZ22: =HISTOJANV24!AZ22+HISTOFEV24!AZ22+HISTOMARS24!AZ22+HISTOAVRIL24!AZ22+HISTOMAI24!AZ22+HISTOJUIN24!AZ22+HISTOJUIL24!AZ22+HISTOAOUT24!AZ22+HISTOSEPT24!AZ22+HISTOOCT24!AZ22+HISTONOV24!AZ22+HISTODEC24!AZ22 -> 283000 | BA22: =HISTOJANV24!BA22+HISTOFEV24!BA22+HISTOMARS24!BA22+HISTOAVRIL24!BA22+HISTOMAI24!BA22+HISTOJUIN24!BA22+HISTOJUIL24!BA22+HISTOAOUT24!BA22+HISTOSEPT24!BA22+HISTOOCT24!BA22+HISTONOV24!BA22+HISTODEC24!BA22 -> 0 | BB22: =HISTOJANV24!BB22+HISTOFEV24!BB22+HISTOMARS24!BB22+HISTOAVRIL24!BB22+HISTOMAI24!BB22+HISTOJUIN24!BB22+HISTOJUIL24!BB22+HISTOAOUT24!BB22+HISTOSEPT24!BB22+HISTOOCT24!BB22+HISTONOV24!BB22+HISTODEC24!BB22 -> 0 | BD22: =HISTOJANV24!BD22+HISTOFEV24!BD22+HISTOMARS24!BD22+HISTOAVRIL24!BD22+HISTOMAI24!BD22+HISTOJUIN24!BD22+HISTOJUIL24!BD22+HISTOAOUT24!BD22+HISTOSEPT24!BD22+HISTOOCT24!BD22+HISTONOV24!BD22+HISTODEC24!BD22 -> 283000 | BF22: =HISTOJANV24!BF22+HISTOFEV24!BF22+HISTOMARS24!BF22+HISTOAVRIL24!BF22+HISTOMAI24!BF22+HISTOJUIN24!BF22+HISTOJUIL24!BF22+HISTOAOUT24!BF22+HISTOSEPT24!BF22+HISTOOCT24!BF22+HISTONOV24!BF22+HISTODEC24!BF22 -> 0 | BN22: S/TOTAL | BP22: =SUM(BP18:BP21) -> 0
A23: AS201622 | B23: =VLOOKUP(A23,[11]LISTADHERENT!A$5:H$50,3,0) -> NDJOMO ETIENNE | D23: =HISTOJANV24!D23+HISTOFEV24!D23+HISTOMARS24!D23+HISTOAVRIL24!D23+HISTOMAI24!D23+HISTOJUIN24!D23+HISTOJUIL24!D23+HISTOAOUT24!D23+HISTOSEPT24!D23+HISTOOCT24!D23+HISTONOV24!D23+HISTODEC24!D23 -> 780000 | E23: =HISTOJANV24!E23+HISTOFEV24!E23+HISTOMARS24!E23+HISTOAVRIL24!E23+HISTOMAI24!E23+HISTOJUIN24!E23+HISTOJUIL24!E23+HISTOAOUT24!E23+HISTOSEPT24!E23+HISTOOCT24!E23+HISTONOV24!E23+HISTODEC24!E23 -> 0 | F23: =HISTOJANV24!F23+HISTOFEV24!F23+HISTOMARS24!F23+HISTOAVRIL24!F23+HISTOMAI24!F23+HISTOJUIN24!F23+HISTOJUIL24!F23+HISTOAOUT24!F23+HISTOSEPT24!F23+HISTOOCT24!F23+HISTONOV24!F23+HISTODEC24!F23 -> 0 | G23: =HISTOJANV24!G23+HISTOFEV24!G23+HISTOMARS24!G23+HISTOAVRIL24!G23+HISTOMAI24!G23+HISTOJUIN24!G23+HISTOJUIL24!G23+HISTOAOUT24!G23+HISTOSEPT24!G23+HISTOOCT24!G23+HISTONOV24!G23+HISTODEC24!G23 -> 0 | I23: =HISTOJANV24!I23+HISTOFEV24!I23+HISTOMARS24!I23+HISTOAVRIL24!I23+HISTOMAI24!I23+HISTOJUIN24!I23+HISTOJUIL24!I23+HISTOAOUT24!I23+HISTOSEPT24!I23+HISTOOCT24!I23+HISTONOV24!I23+HISTODEC24!I23 -> 30000 | J23: 1 | K23: =IF($D23<>0,J23*50000,IF($E23<>0,J23*50000,0)) -> 50000 | M23: =IF($D23<>0,L23*75000,IF($E23<>0,L23*75000,0)) -> 0 | N23: 2 | O23: =IF($D23<>0,N23*100000,IF($E23<>0,N23*100000,0)) -> 200000 | P23: =HISTOJANV24!P23+HISTOFEV24!P23+HISTOMARS24!P23+HISTOAVRIL24!P23+HISTOMAI24!P23+HISTOJUIN24!P23+HISTOJUIL24!P23+HISTOAOUT24!P23+HISTOSEPT24!P23+HISTOOCT24!P23+HISTONOV24!P23+HISTODEC24!P23 -> 0 | Q23: =HISTOJANV24!Q23+HISTOFEV24!Q23+HISTOMARS24!Q23+HISTOAVRIL24!Q23+HISTOMAI24!Q23+HISTOJUIN24!Q23+HISTOJUIL24!Q23+HISTOAOUT24!Q23+HISTOSEPT24!Q23+HISTOOCT24!Q23+HISTONOV24!Q23+HISTODEC24!Q23 -> 0 | R23: =HISTOJANV24!R23+HISTOFEV24!R23+HISTOMARS24!R23+HISTOAVRIL24!R23+HISTOMAI24!R23+HISTOJUIN24!R23+HISTOJUIL24!R23+HISTOAOUT24!R23+HISTOSEPT24!R23+HISTOOCT24!R23+HISTONOV24!R23+HISTODEC24!R23 -> 202000 | S23: =HISTOJANV24!S23+HISTOFEV24!S23+HISTOMARS24!S23+HISTOAVRIL24!S23+HISTOMAI24!S23+HISTOJUIN24!S23+HISTOJUIL24!S23+HISTOAOUT24!S23+HISTOSEPT24!S23+HISTOOCT24!S23+HISTONOV24!S23+HISTODEC24!S23 -> 0 | U23: =G23+S23++R23+P23+O23+M23+I23+K23+Q23+V23+W23 -> 482000 | V23: =HISTOJANV24!V23+HISTOFEV24!V23+HISTOMARS24!V23+HISTOAVRIL24!V23+HISTOMAI24!V23+HISTOJUIN24!V23+HISTOJUIL24!V23+HISTOAOUT24!V23+HISTOSEPT24!V23+HISTOOCT24!V23+HISTONOV24!V23+HISTODEC24!V23 -> 0 | W23: =HISTOJANV24!W23+HISTOFEV24!W23+HISTOMARS24!W23+HISTOAVRIL24!W23+HISTOMAI24!W23+HISTOJUIN24!W23+HISTOJUIL24!W23+HISTOAOUT24!W23+HISTOSEPT24!W23+HISTOOCT24!W23+HISTONOV24!W23+HISTODEC24!W23 -> 0 | X23: =HISTOJANV24!X23+HISTOFEV24!X23+HISTOMARS24!X23+HISTOAVRIL24!X23+HISTOMAI24!X23+HISTOJUIN24!X23+HISTOJUIL24!X23+HISTOAOUT24!X23+HISTOSEPT24!X23+HISTOOCT24!X23+HISTONOV24!X23+HISTODEC24!X23 -> 0 | Y23: =HISTOJANV24!Y23+HISTOFEV24!Y23+HISTOMARS24!Y23+HISTOAVRIL24!Y23+HISTOMAI24!Y23+HISTOJUIN24!Y23+HISTOJUIL24!Y23+HISTOAOUT24!Y23+HISTOSEPT24!Y23+HISTOOCT24!Y23+HISTONOV24!Y23+HISTODEC24!Y23 -> 0 | Z23: =HISTOJANV24!Z23+HISTOFEV24!Z23+HISTOMARS24!Z23+HISTOAVRIL24!Z23+HISTOMAI24!Z23+HISTOJUIN24!Z23+HISTOJUIL24!Z23+HISTOAOUT24!Z23+HISTOSEPT24!Z23+HISTOOCT24!Z23+HISTONOV24!Z23+HISTODEC24!Z23 -> 0 | AC23: =HISTOJANV24!AC23+HISTOFEV24!AC23+HISTOMARS24!AC23+HISTOAVRIL24!AC23+HISTOMAI24!AC23+HISTOJUIN24!AC23+HISTOJUIL24!AC23+HISTOAOUT24!AC23+HISTOSEPT24!AC23+HISTOOCT24!AC23+HISTONOV24!AC23+HISTODEC24!AC23 -> 0 | AD23: =HISTOJANV24!AD23+HISTOFEV24!AD23+HISTOMARS24!AD23+HISTOAVRIL24!AD23+HISTOMAI24!AD23+HISTOJUIN24!AD23+HISTOJUIL24!AD23+HISTOAOUT24!AD23+HISTOSEPT24!AD23+HISTOOCT24!AD23+HISTONOV24!AD23+HISTODEC24!AD23 -> 0 | AE23: =HISTOJANV24!AE23+HISTOFEV24!AE23+HISTOMARS24!AE23+HISTOAVRIL24!AE23+HISTOMAI24!AE23+HISTOJUIN24!AE23+HISTOJUIL24!AE23+HISTOAOUT24!AE23+HISTOSEPT24!AE23+HISTOOCT24!AE23+HISTONOV24!AE23+HISTODEC24!AE23 -> 0 | AH23: =HISTOJANV24!AH23+HISTOFEV24!AH23+HISTOMARS24!AH23+HISTOAVRIL24!AH23+HISTOMAI24!AH23+HISTOJUIN24!AH23+HISTOJUIL24!AH23+HISTOAOUT24!AH23+HISTOSEPT24!AH23+HISTOOCT24!AH23+HISTONOV24!AH23+HISTODEC24!AH23 -> 0 | AI23: =HISTOJANV24!AI23+HISTOFEV24!AI23+HISTOMARS24!AI23+HISTOAVRIL24!AI23+HISTOMAI24!AI23+HISTOJUIN24!AI23+HISTOJUIL24!AI23+HISTOAOUT24!AI23+HISTOSEPT24!AI23+HISTOOCT24!AI23+HISTONOV24!AI23+HISTODEC24!AI23 -> 0 | AJ23: =HISTOJANV24!AJ23+HISTOFEV24!AJ23+HISTOMARS24!AJ23+HISTOAVRIL24!AJ23+HISTOMAI24!AJ23+HISTOJUIN24!AJ23+HISTOJUIL24!AJ23+HISTOAOUT24!AJ23+HISTOSEPT24!AJ23+HISTOOCT24!AJ23+HISTONOV24!AJ23+HISTODEC24!AJ23 -> 0 | AK23: =HISTOJANV24!AK23+HISTOFEV24!AK23+HISTOMARS24!AK23+HISTOAVRIL24!AK23+HISTOMAI24!AK23+HISTOJUIN24!AK23+HISTOJUIL24!AK23+HISTOAOUT24!AK23+HISTOSEPT24!AK23+HISTOOCT24!AK23+HISTONOV24!AK23+HISTODEC24!AK23 -> 200000 | AL23: =HISTOJANV24!AL23+HISTOFEV24!AL23+HISTOMARS24!AL23+HISTOAVRIL24!AL23+HISTOMAI24!AL23+HISTOJUIN24!AL23+HISTOJUIL24!AL23+HISTOAOUT24!AL23+HISTOSEPT24!AL23+HISTOOCT24!AL23+HISTONOV24!AL23+HISTODEC24!AL23 -> 0 | AM23: =HISTOJANV24!AM23+HISTOFEV24!AM23+HISTOMARS24!AM23+HISTOAVRIL24!AM23+HISTOMAI24!AM23+HISTOJUIN24!AM23+HISTOJUIL24!AM23+HISTOAOUT24!AM23+HISTOSEPT24!AM23+HISTOOCT24!AM23+HISTONOV24!AM23+HISTODEC24!AM23 -> 0 | AN23: =HISTOJANV24!AN23+HISTOFEV24!AN23+HISTOMARS24!AN23+HISTOAVRIL24!AN23+HISTOMAI24!AN23+HISTOJUIN24!AN23+HISTOJUIL24!AN23+HISTOAOUT24!AN23+HISTOSEPT24!AN23+HISTOOCT24!AN23+HISTONOV24!AN23+HISTODEC24!AN23 -> 2000 | AQ23: =IF(H23="ECHEC",((K23+M23+O23)*20/100),0) -> 0 | AR23: =IF(H23="ECHEC",((K23+M23+O23)*20/100),0) -> 0 | AS23: =IF(H23="ECHEC",0,(K23+I23-25000)) -> 55000 | AW23: =HISTOJANV24!AW23+HISTOFEV24!AW23+HISTOMARS24!AW23+HISTOAVRIL24!AW23+HISTOMAI24!AW23+HISTOJUIN24!AW23+HISTOJUIL24!AW23+HISTOAOUT24!AW23+HISTOSEPT24!AW23+HISTOOCT24!AW23+HISTONOV24!AW23+HISTODEC24!AW23 -> 0 | AX23: =HISTOJANV24!AX23+HISTOFEV24!AX23+HISTOMARS24!AX23+HISTOAVRIL24!AX23+HISTOMAI24!AX23+HISTOJUIN24!AX23+HISTOJUIL24!AX23+HISTOAOUT24!AX23+HISTOSEPT24!AX23+HISTOOCT24!AX23+HISTONOV24!AX23+HISTODEC24!AX23 -> 0 | AY23: =HISTOJANV24!AY23+HISTOFEV24!AY23+HISTOMARS24!AY23+HISTOAVRIL24!AY23+HISTOMAI24!AY23+HISTOJUIN24!AY23+HISTOJUIL24!AY23+HISTOAOUT24!AY23+HISTOSEPT24!AY23+HISTOOCT24!AY23+HISTONOV24!AY23+HISTODEC24!AY23 -> 200000 | AZ23: =HISTOJANV24!AZ23+HISTOFEV24!AZ23+HISTOMARS24!AZ23+HISTOAVRIL24!AZ23+HISTOMAI24!AZ23+HISTOJUIN24!AZ23+HISTOJUIL24!AZ23+HISTOAOUT24!AZ23+HISTOSEPT24!AZ23+HISTOOCT24!AZ23+HISTONOV24!AZ23+HISTODEC24!AZ23 -> 200000 | BA23: =HISTOJANV24!BA23+HISTOFEV24!BA23+HISTOMARS24!BA23+HISTOAVRIL24!BA23+HISTOMAI24!BA23+HISTOJUIN24!BA23+HISTOJUIL24!BA23+HISTOAOUT24!BA23+HISTOSEPT24!BA23+HISTOOCT24!BA23+HISTONOV24!BA23+HISTODEC24!BA23 -> 56000 | BB23: =HISTOJANV24!BB23+HISTOFEV24!BB23+HISTOMARS24!BB23+HISTOAVRIL24!BB23+HISTOMAI24!BB23+HISTOJUIN24!BB23+HISTOJUIL24!BB23+HISTOAOUT24!BB23+HISTOSEPT24!BB23+HISTOOCT24!BB23+HISTONOV24!BB23+HISTODEC24!BB23 -> 0 | BD23: =HISTOJANV24!BD23+HISTOFEV24!BD23+HISTOMARS24!BD23+HISTOAVRIL24!BD23+HISTOMAI24!BD23+HISTOJUIN24!BD23+HISTOJUIL24!BD23+HISTOAOUT24!BD23+HISTOSEPT24!BD23+HISTOOCT24!BD23+HISTONOV24!BD23+HISTODEC24!BD23 -> 170000 | BF23: =HISTOJANV24!BF23+HISTOFEV24!BF23+HISTOMARS24!BF23+HISTOAVRIL24!BF23+HISTOMAI24!BF23+HISTOJUIN24!BF23+HISTOJUIL24!BF23+HISTOAOUT24!BF23+HISTOSEPT24!BF23+HISTOOCT24!BF23+HISTONOV24!BF23+HISTODEC24!BF23 -> 0
A24: AS201624 | B24: =VLOOKUP(A24,[11]LISTADHERENT!A$5:H$50,3,0) -> NGONDIEP CLAUDE | D24: =HISTOJANV24!D24+HISTOFEV24!D24+HISTOMARS24!D24+HISTOAVRIL24!D24+HISTOMAI24!D24+HISTOJUIN24!D24+HISTOJUIL24!D24+HISTOAOUT24!D24+HISTOSEPT24!D24+HISTOOCT24!D24+HISTONOV24!D24+HISTODEC24!D24 -> 705000 | E24: =HISTOJANV24!E24+HISTOFEV24!E24+HISTOMARS24!E24+HISTOAVRIL24!E24+HISTOMAI24!E24+HISTOJUIN24!E24+HISTOJUIL24!E24+HISTOAOUT24!E24+HISTOSEPT24!E24+HISTOOCT24!E24+HISTONOV24!E24+HISTODEC24!E24 -> 0 | F24: =HISTOJANV24!F24+HISTOFEV24!F24+HISTOMARS24!F24+HISTOAVRIL24!F24+HISTOMAI24!F24+HISTOJUIN24!F24+HISTOJUIL24!F24+HISTOAOUT24!F24+HISTOSEPT24!F24+HISTOOCT24!F24+HISTONOV24!F24+HISTODEC24!F24 -> 0 | G24: =HISTOJANV24!G24+HISTOFEV24!G24+HISTOMARS24!G24+HISTOAVRIL24!G24+HISTOMAI24!G24+HISTOJUIN24!G24+HISTOJUIL24!G24+HISTOAOUT24!G24+HISTOSEPT24!G24+HISTOOCT24!G24+HISTONOV24!G24+HISTODEC24!G24 -> 0 | I24: =HISTOJANV24!I24+HISTOFEV24!I24+HISTOMARS24!I24+HISTOAVRIL24!I24+HISTOMAI24!I24+HISTOJUIN24!I24+HISTOJUIL24!I24+HISTOAOUT24!I24+HISTOSEPT24!I24+HISTOOCT24!I24+HISTONOV24!I24+HISTODEC24!I24 -> 30000 | J24: 1 | K24: =IF($D24<>0,J24*50000,IF($E24<>0,J24*50000,0)) -> 50000 | L24: 1 | M24: =IF($D24<>0,L24*75000,IF($E24<>0,L24*75000,0)) -> 75000 | N24: 1 | O24: =IF($D24<>0,N24*100000,IF($E24<>0,N24*100000,0)) -> 100000 | P24: =HISTOJANV24!P24+HISTOFEV24!P24+HISTOMARS24!P24+HISTOAVRIL24!P24+HISTOMAI24!P24+HISTOJUIN24!P24+HISTOJUIL24!P24+HISTOAOUT24!P24+HISTOSEPT24!P24+HISTOOCT24!P24+HISTONOV24!P24+HISTODEC24!P24 -> 0 | Q24: =HISTOJANV24!Q24+HISTOFEV24!Q24+HISTOMARS24!Q24+HISTOAVRIL24!Q24+HISTOMAI24!Q24+HISTOJUIN24!Q24+HISTOJUIL24!Q24+HISTOAOUT24!Q24+HISTOSEPT24!Q24+HISTOOCT24!Q24+HISTONOV24!Q24+HISTODEC24!Q24 -> 0 | R24: =HISTOJANV24!R24+HISTOFEV24!R24+HISTOMARS24!R24+HISTOAVRIL24!R24+HISTOMAI24!R24+HISTOJUIN24!R24+HISTOJUIL24!R24+HISTOAOUT24!R24+HISTOSEPT24!R24+HISTOOCT24!R24+HISTONOV24!R24+HISTODEC24!R24 -> 102000 | S24: =HISTOJANV24!S24+HISTOFEV24!S24+HISTOMARS24!S24+HISTOAVRIL24!S24+HISTOMAI24!S24+HISTOJUIN24!S24+HISTOJUIL24!S24+HISTOAOUT24!S24+HISTOSEPT24!S24+HISTOOCT24!S24+HISTONOV24!S24+HISTODEC24!S24 -> 0 | U24: =G24+S24++R24+P24+O24+M24+I24+K24+Q24+V24+W24 -> 357000 | V24: =HISTOJANV24!V24+HISTOFEV24!V24+HISTOMARS24!V24+HISTOAVRIL24!V24+HISTOMAI24!V24+HISTOJUIN24!V24+HISTOJUIL24!V24+HISTOAOUT24!V24+HISTOSEPT24!V24+HISTOOCT24!V24+HISTONOV24!V24+HISTODEC24!V24 -> 0 | W24: =HISTOJANV24!W24+HISTOFEV24!W24+HISTOMARS24!W24+HISTOAVRIL24!W24+HISTOMAI24!W24+HISTOJUIN24!W24+HISTOJUIL24!W24+HISTOAOUT24!W24+HISTOSEPT24!W24+HISTOOCT24!W24+HISTONOV24!W24+HISTODEC24!W24 -> 0 | X24: =HISTOJANV24!X24+HISTOFEV24!X24+HISTOMARS24!X24+HISTOAVRIL24!X24+HISTOMAI24!X24+HISTOJUIN24!X24+HISTOJUIL24!X24+HISTOAOUT24!X24+HISTOSEPT24!X24+HISTOOCT24!X24+HISTONOV24!X24+HISTODEC24!X24 -> 0 | Y24: =HISTOJANV24!Y24+HISTOFEV24!Y24+HISTOMARS24!Y24+HISTOAVRIL24!Y24+HISTOMAI24!Y24+HISTOJUIN24!Y24+HISTOJUIL24!Y24+HISTOAOUT24!Y24+HISTOSEPT24!Y24+HISTOOCT24!Y24+HISTONOV24!Y24+HISTODEC24!Y24 -> 0 | Z24: =HISTOJANV24!Z24+HISTOFEV24!Z24+HISTOMARS24!Z24+HISTOAVRIL24!Z24+HISTOMAI24!Z24+HISTOJUIN24!Z24+HISTOJUIL24!Z24+HISTOAOUT24!Z24+HISTOSEPT24!Z24+HISTOOCT24!Z24+HISTONOV24!Z24+HISTODEC24!Z24 -> 0 | AC24: =HISTOJANV24!AC24+HISTOFEV24!AC24+HISTOMARS24!AC24+HISTOAVRIL24!AC24+HISTOMAI24!AC24+HISTOJUIN24!AC24+HISTOJUIL24!AC24+HISTOAOUT24!AC24+HISTOSEPT24!AC24+HISTOOCT24!AC24+HISTONOV24!AC24+HISTODEC24!AC24 -> 0 | AD24: =HISTOJANV24!AD24+HISTOFEV24!AD24+HISTOMARS24!AD24+HISTOAVRIL24!AD24+HISTOMAI24!AD24+HISTOJUIN24!AD24+HISTOJUIL24!AD24+HISTOAOUT24!AD24+HISTOSEPT24!AD24+HISTOOCT24!AD24+HISTONOV24!AD24+HISTODEC24!AD24 -> 0 | AE24: =HISTOJANV24!AE24+HISTOFEV24!AE24+HISTOMARS24!AE24+HISTOAVRIL24!AE24+HISTOMAI24!AE24+HISTOJUIN24!AE24+HISTOJUIL24!AE24+HISTOAOUT24!AE24+HISTOSEPT24!AE24+HISTOOCT24!AE24+HISTONOV24!AE24+HISTODEC24!AE24 -> 0 | AH24: =HISTOJANV24!AH24+HISTOFEV24!AH24+HISTOMARS24!AH24+HISTOAVRIL24!AH24+HISTOMAI24!AH24+HISTOJUIN24!AH24+HISTOJUIL24!AH24+HISTOAOUT24!AH24+HISTOSEPT24!AH24+HISTOOCT24!AH24+HISTONOV24!AH24+HISTODEC24!AH24 -> 0 | AI24: =HISTOJANV24!AI24+HISTOFEV24!AI24+HISTOMARS24!AI24+HISTOAVRIL24!AI24+HISTOMAI24!AI24+HISTOJUIN24!AI24+HISTOJUIL24!AI24+HISTOAOUT24!AI24+HISTOSEPT24!AI24+HISTOOCT24!AI24+HISTONOV24!AI24+HISTODEC24!AI24 -> 0 | AJ24: =HISTOJANV24!AJ24+HISTOFEV24!AJ24+HISTOMARS24!AJ24+HISTOAVRIL24!AJ24+HISTOMAI24!AJ24+HISTOJUIN24!AJ24+HISTOJUIL24!AJ24+HISTOAOUT24!AJ24+HISTOSEPT24!AJ24+HISTOOCT24!AJ24+HISTONOV24!AJ24+HISTODEC24!AJ24 -> 0 | AK24: =HISTOJANV24!AK24+HISTOFEV24!AK24+HISTOMARS24!AK24+HISTOAVRIL24!AK24+HISTOMAI24!AK24+HISTOJUIN24!AK24+HISTOJUIL24!AK24+HISTOAOUT24!AK24+HISTOSEPT24!AK24+HISTOOCT24!AK24+HISTONOV24!AK24+HISTODEC24!AK24 -> 100000 | AL24: =HISTOJANV24!AL24+HISTOFEV24!AL24+HISTOMARS24!AL24+HISTOAVRIL24!AL24+HISTOMAI24!AL24+HISTOJUIN24!AL24+HISTOJUIL24!AL24+HISTOAOUT24!AL24+HISTOSEPT24!AL24+HISTOOCT24!AL24+HISTONOV24!AL24+HISTODEC24!AL24 -> 0 | AM24: =HISTOJANV24!AM24+HISTOFEV24!AM24+HISTOMARS24!AM24+HISTOAVRIL24!AM24+HISTOMAI24!AM24+HISTOJUIN24!AM24+HISTOJUIL24!AM24+HISTOAOUT24!AM24+HISTOSEPT24!AM24+HISTOOCT24!AM24+HISTONOV24!AM24+HISTODEC24!AM24 -> 0 | AN24: =HISTOJANV24!AN24+HISTOFEV24!AN24+HISTOMARS24!AN24+HISTOAVRIL24!AN24+HISTOMAI24!AN24+HISTOJUIN24!AN24+HISTOJUIL24!AN24+HISTOAOUT24!AN24+HISTOSEPT24!AN24+HISTOOCT24!AN24+HISTONOV24!AN24+HISTODEC24!AN24 -> 2000 | AQ24: =IF(H24="ECHEC",((K24+M24+O24)*20/100),0) -> 0 | AR24: =IF(H24="ECHEC",((K24+M24+O24)*20/100),0) -> 0 | AS24: =IF(H24="ECHEC",0,(K24+I24-25000)) -> 55000 | AW24: =HISTOJANV24!AW24+HISTOFEV24!AW24+HISTOMARS24!AW24+HISTOAVRIL24!AW24+HISTOMAI24!AW24+HISTOJUIN24!AW24+HISTOJUIL24!AW24+HISTOAOUT24!AW24+HISTOSEPT24!AW24+HISTOOCT24!AW24+HISTONOV24!AW24+HISTODEC24!AW24 -> 0 | AX24: =HISTOJANV24!AX24+HISTOFEV24!AX24+HISTOMARS24!AX24+HISTOAVRIL24!AX24+HISTOMAI24!AX24+HISTOJUIN24!AX24+HISTOJUIL24!AX24+HISTOAOUT24!AX24+HISTOSEPT24!AX24+HISTOOCT24!AX24+HISTONOV24!AX24+HISTODEC24!AX24 -> 0 | AY24: =HISTOJANV24!AY24+HISTOFEV24!AY24+HISTOMARS24!AY24+HISTOAVRIL24!AY24+HISTOMAI24!AY24+HISTOJUIN24!AY24+HISTOJUIL24!AY24+HISTOAOUT24!AY24+HISTOSEPT24!AY24+HISTOOCT24!AY24+HISTONOV24!AY24+HISTODEC24!AY24 -> 100000 | AZ24: =HISTOJANV24!AZ24+HISTOFEV24!AZ24+HISTOMARS24!AZ24+HISTOAVRIL24!AZ24+HISTOMAI24!AZ24+HISTOJUIN24!AZ24+HISTOJUIL24!AZ24+HISTOAOUT24!AZ24+HISTOSEPT24!AZ24+HISTOOCT24!AZ24+HISTONOV24!AZ24+HISTODEC24!AZ24 -> 100000 | BA24: =HISTOJANV24!BA24+HISTOFEV24!BA24+HISTOMARS24!BA24+HISTOAVRIL24!BA24+HISTOMAI24!BA24+HISTOJUIN24!BA24+HISTOJUIL24!BA24+HISTOAOUT24!BA24+HISTOSEPT24!BA24+HISTOOCT24!BA24+HISTONOV24!BA24+HISTODEC24!BA24 -> 0 | BB24: =HISTOJANV24!BB24+HISTOFEV24!BB24+HISTOMARS24!BB24+HISTOAVRIL24!BB24+HISTOMAI24!BB24+HISTOJUIN24!BB24+HISTOJUIL24!BB24+HISTOAOUT24!BB24+HISTOSEPT24!BB24+HISTOOCT24!BB24+HISTONOV24!BB24+HISTODEC24!BB24 -> 0 | BD24: =HISTOJANV24!BD24+HISTOFEV24!BD24+HISTOMARS24!BD24+HISTOAVRIL24!BD24+HISTOMAI24!BD24+HISTOJUIN24!BD24+HISTOJUIL24!BD24+HISTOAOUT24!BD24+HISTOSEPT24!BD24+HISTOOCT24!BD24+HISTONOV24!BD24+HISTODEC24!BD24 -> 100000 | BF24: =HISTOJANV24!BF24+HISTOFEV24!BF24+HISTOMARS24!BF24+HISTOAVRIL24!BF24+HISTOMAI24!BF24+HISTOJUIN24!BF24+HISTOJUIL24!BF24+HISTOAOUT24!BF24+HISTOSEPT24!BF24+HISTOOCT24!BF24+HISTONOV24!BF24+HISTODEC24!BF24 -> 0 | BN24: GRATIFICATION BUREAU 2021 | BO24: FRAIS EXEPTIONNEL
A25: AS201626 | B25: =VLOOKUP(A25,[11]LISTADHERENT!A$5:H$50,3,0) -> NGUIEMEGNI MATHIEU BLAISE | D25: =HISTOJANV24!D25+HISTOFEV24!D25+HISTOMARS24!D25+HISTOAVRIL24!D25+HISTOMAI24!D25+HISTOJUIN24!D25+HISTOJUIL24!D25+HISTOAOUT24!D25+HISTOSEPT24!D25+HISTOOCT24!D25+HISTONOV24!D25+HISTODEC24!D25 -> 1125000 | E25: =HISTOJANV24!E25+HISTOFEV24!E25+HISTOMARS24!E25+HISTOAVRIL24!E25+HISTOMAI24!E25+HISTOJUIN24!E25+HISTOJUIL24!E25+HISTOAOUT24!E25+HISTOSEPT24!E25+HISTOOCT24!E25+HISTONOV24!E25+HISTODEC24!E25 -> 104500 | F25: =HISTOJANV24!F25+HISTOFEV24!F25+HISTOMARS24!F25+HISTOAVRIL24!F25+HISTOMAI24!F25+HISTOJUIN24!F25+HISTOJUIL24!F25+HISTOAOUT24!F25+HISTOSEPT24!F25+HISTOOCT24!F25+HISTONOV24!F25+HISTODEC24!F25 -> 0 | G25: =HISTOJANV24!G25+HISTOFEV24!G25+HISTOMARS24!G25+HISTOAVRIL24!G25+HISTOMAI24!G25+HISTOJUIN24!G25+HISTOJUIL24!G25+HISTOAOUT24!G25+HISTOSEPT24!G25+HISTOOCT24!G25+HISTONOV24!G25+HISTODEC24!G25 -> 3000 | I25: =HISTOJANV24!I25+HISTOFEV24!I25+HISTOMARS24!I25+HISTOAVRIL24!I25+HISTOMAI24!I25+HISTOJUIN24!I25+HISTOJUIL24!I25+HISTOAOUT24!I25+HISTOSEPT24!I25+HISTOOCT24!I25+HISTONOV24!I25+HISTODEC24!I25 -> 0 | J25: 1 | K25: =IF($D25<>0,J25*50000,IF($E25<>0,J25*50000,0)) -> 50000 | L25: 3 | M25: =IF($D25<>0,L25*75000,IF($E25<>0,L25*75000,0)) -> 225000 | N25: 1 | O25: =IF($D25<>0,N25*100000,IF($E25<>0,N25*100000,0)) -> 100000 | P25: =HISTOJANV24!P25+HISTOFEV24!P25+HISTOMARS24!P25+HISTOAVRIL24!P25+HISTOMAI24!P25+HISTOJUIN24!P25+HISTOJUIL24!P25+HISTOAOUT24!P25+HISTOSEPT24!P25+HISTOOCT24!P25+HISTONOV24!P25+HISTODEC24!P25 -> 0 | Q25: =HISTOJANV24!Q25+HISTOFEV24!Q25+HISTOMARS24!Q25+HISTOAVRIL24!Q25+HISTOMAI24!Q25+HISTOJUIN24!Q25+HISTOJUIL24!Q25+HISTOAOUT24!Q25+HISTOSEPT24!Q25+HISTOOCT24!Q25+HISTONOV24!Q25+HISTODEC24!Q25 -> 0 | R25: =HISTOJANV24!R25+HISTOFEV24!R25+HISTOMARS24!R25+HISTOAVRIL24!R25+HISTOMAI24!R25+HISTOJUIN24!R25+HISTOJUIL24!R25+HISTOAOUT24!R25+HISTOSEPT24!R25+HISTOOCT24!R25+HISTONOV24!R25+HISTODEC24!R25 -> 303500 | S25: =HISTOJANV24!S25+HISTOFEV24!S25+HISTOMARS24!S25+HISTOAVRIL24!S25+HISTOMAI24!S25+HISTOJUIN24!S25+HISTOJUIL24!S25+HISTOAOUT24!S25+HISTOSEPT24!S25+HISTOOCT24!S25+HISTONOV24!S25+HISTODEC24!S25 -> 0 | U25: =G25+S25++R25+P25+O25+M25+I25+K25+Q25+V25+W25 -> 681500 | V25: =HISTOJANV24!V25+HISTOFEV24!V25+HISTOMARS24!V25+HISTOAVRIL24!V25+HISTOMAI24!V25+HISTOJUIN24!V25+HISTOJUIL24!V25+HISTOAOUT24!V25+HISTOSEPT24!V25+HISTOOCT24!V25+HISTONOV24!V25+HISTODEC24!V25 -> 0 | W25: =HISTOJANV24!W25+HISTOFEV24!W25+HISTOMARS24!W25+HISTOAVRIL24!W25+HISTOMAI24!W25+HISTOJUIN24!W25+HISTOJUIL24!W25+HISTOAOUT24!W25+HISTOSEPT24!W25+HISTOOCT24!W25+HISTONOV24!W25+HISTODEC24!W25 -> 0 | X25: =HISTOJANV24!X25+HISTOFEV24!X25+HISTOMARS24!X25+HISTOAVRIL24!X25+HISTOMAI24!X25+HISTOJUIN24!X25+HISTOJUIL24!X25+HISTOAOUT24!X25+HISTOSEPT24!X25+HISTOOCT24!X25+HISTONOV24!X25+HISTODEC24!X25 -> 0 | Y25: =HISTOJANV24!Y25+HISTOFEV24!Y25+HISTOMARS24!Y25+HISTOAVRIL24!Y25+HISTOMAI24!Y25+HISTOJUIN24!Y25+HISTOJUIL24!Y25+HISTOAOUT24!Y25+HISTOSEPT24!Y25+HISTOOCT24!Y25+HISTONOV24!Y25+HISTODEC24!Y25 -> 0 | Z25: =HISTOJANV24!Z25+HISTOFEV24!Z25+HISTOMARS24!Z25+HISTOAVRIL24!Z25+HISTOMAI24!Z25+HISTOJUIN24!Z25+HISTOJUIL24!Z25+HISTOAOUT24!Z25+HISTOSEPT24!Z25+HISTOOCT24!Z25+HISTONOV24!Z25+HISTODEC24!Z25 -> 0 | AC25: =HISTOJANV24!AC25+HISTOFEV24!AC25+HISTOMARS24!AC25+HISTOAVRIL24!AC25+HISTOMAI24!AC25+HISTOJUIN24!AC25+HISTOJUIL24!AC25+HISTOAOUT24!AC25+HISTOSEPT24!AC25+HISTOOCT24!AC25+HISTONOV24!AC25+HISTODEC24!AC25 -> 0 | AD25: =HISTOJANV24!AD25+HISTOFEV24!AD25+HISTOMARS24!AD25+HISTOAVRIL24!AD25+HISTOMAI24!AD25+HISTOJUIN24!AD25+HISTOJUIL24!AD25+HISTOAOUT24!AD25+HISTOSEPT24!AD25+HISTOOCT24!AD25+HISTONOV24!AD25+HISTODEC24!AD25 -> 65000 | AE25: =HISTOJANV24!AE25+HISTOFEV24!AE25+HISTOMARS24!AE25+HISTOAVRIL24!AE25+HISTOMAI24!AE25+HISTOJUIN24!AE25+HISTOJUIL24!AE25+HISTOAOUT24!AE25+HISTOSEPT24!AE25+HISTOOCT24!AE25+HISTONOV24!AE25+HISTODEC24!AE25 -> 125000 | AH25: =HISTOJANV24!AH25+HISTOFEV24!AH25+HISTOMARS24!AH25+HISTOAVRIL24!AH25+HISTOMAI24!AH25+HISTOJUIN24!AH25+HISTOJUIL24!AH25+HISTOAOUT24!AH25+HISTOSEPT24!AH25+HISTOOCT24!AH25+HISTONOV24!AH25+HISTODEC24!AH25 -> 0 | AI25: =HISTOJANV24!AI25+HISTOFEV24!AI25+HISTOMARS24!AI25+HISTOAVRIL24!AI25+HISTOMAI24!AI25+HISTOJUIN24!AI25+HISTOJUIL24!AI25+HISTOAOUT24!AI25+HISTOSEPT24!AI25+HISTOOCT24!AI25+HISTONOV24!AI25+HISTODEC24!AI25 -> 0 | AJ25: =HISTOJANV24!AJ25+HISTOFEV24!AJ25+HISTOMARS24!AJ25+HISTOAVRIL24!AJ25+HISTOMAI24!AJ25+HISTOJUIN24!AJ25+HISTOJUIL24!AJ25+HISTOAOUT24!AJ25+HISTOSEPT24!AJ25+HISTOOCT24!AJ25+HISTONOV24!AJ25+HISTODEC24!AJ25 -> 0 | AK25: =HISTOJANV24!AK25+HISTOFEV24!AK25+HISTOMARS24!AK25+HISTOAVRIL24!AK25+HISTOMAI24!AK25+HISTOJUIN24!AK25+HISTOJUIL24!AK25+HISTOAOUT24!AK25+HISTOSEPT24!AK25+HISTOOCT24!AK25+HISTONOV24!AK25+HISTODEC24!AK25 -> 300000 | AL25: =HISTOJANV24!AL25+HISTOFEV24!AL25+HISTOMARS24!AL25+HISTOAVRIL24!AL25+HISTOMAI24!AL25+HISTOJUIN24!AL25+HISTOJUIL24!AL25+HISTOAOUT24!AL25+HISTOSEPT24!AL25+HISTOOCT24!AL25+HISTONOV24!AL25+HISTODEC24!AL25 -> 0 | AM25: =HISTOJANV24!AM25+HISTOFEV24!AM25+HISTOMARS24!AM25+HISTOAVRIL24!AM25+HISTOMAI24!AM25+HISTOJUIN24!AM25+HISTOJUIL24!AM25+HISTOAOUT24!AM25+HISTOSEPT24!AM25+HISTOOCT24!AM25+HISTONOV24!AM25+HISTODEC24!AM25 -> 0 | AN25: =HISTOJANV24!AN25+HISTOFEV24!AN25+HISTOMARS24!AN25+HISTOAVRIL24!AN25+HISTOMAI24!AN25+HISTOJUIN24!AN25+HISTOJUIL24!AN25+HISTOAOUT24!AN25+HISTOSEPT24!AN25+HISTOOCT24!AN25+HISTONOV24!AN25+HISTODEC24!AN25 -> 3500 | AQ25: =IF(H25="ECHEC",((K25+M25+O25)*20/100),0) -> 0 | AR25: =IF(H25="ECHEC",((K25+M25+O25)*20/100),0) -> 0 | AS25: =IF(H25="ECHEC",0,(K25+I25-25000)) -> 25000 | AW25: =HISTOJANV24!AW25+HISTOFEV24!AW25+HISTOMARS24!AW25+HISTOAVRIL24!AW25+HISTOMAI24!AW25+HISTOJUIN24!AW25+HISTOJUIL24!AW25+HISTOAOUT24!AW25+HISTOSEPT24!AW25+HISTOOCT24!AW25+HISTONOV24!AW25+HISTODEC24!AW25 -> 0 | AX25: =HISTOJANV24!AX25+HISTOFEV24!AX25+HISTOMARS24!AX25+HISTOAVRIL24!AX25+HISTOMAI24!AX25+HISTOJUIN24!AX25+HISTOJUIL24!AX25+HISTOAOUT24!AX25+HISTOSEPT24!AX25+HISTOOCT24!AX25+HISTONOV24!AX25+HISTODEC24!AX25 -> 835000 | AY25: =HISTOJANV24!AY25+HISTOFEV24!AY25+HISTOMARS24!AY25+HISTOAVRIL24!AY25+HISTOMAI24!AY25+HISTOJUIN24!AY25+HISTOJUIL24!AY25+HISTOAOUT24!AY25+HISTOSEPT24!AY25+HISTOOCT24!AY25+HISTONOV24!AY25+HISTODEC24!AY25 -> 1375000 | AZ25: =HISTOJANV24!AZ25+HISTOFEV24!AZ25+HISTOMARS24!AZ25+HISTOAVRIL24!AZ25+HISTOMAI24!AZ25+HISTOJUIN24!AZ25+HISTOJUIL24!AZ25+HISTOAOUT24!AZ25+HISTOSEPT24!AZ25+HISTOOCT24!AZ25+HISTONOV24!AZ25+HISTODEC24!AZ25 -> 2210000 | BA25: =HISTOJANV24!BA25+HISTOFEV24!BA25+HISTOMARS24!BA25+HISTOAVRIL24!BA25+HISTOMAI24!BA25+HISTOJUIN24!BA25+HISTOJUIL24!BA25+HISTOAOUT24!BA25+HISTOSEPT24!BA25+HISTOOCT24!BA25+HISTONOV24!BA25+HISTODEC24!BA25 -> 100000 | BB25: =HISTOJANV24!BB25+HISTOFEV24!BB25+HISTOMARS24!BB25+HISTOAVRIL24!BB25+HISTOMAI24!BB25+HISTOJUIN24!BB25+HISTOJUIL24!BB25+HISTOAOUT24!BB25+HISTOSEPT24!BB25+HISTOOCT24!BB25+HISTONOV24!BB25+HISTODEC24!BB25 -> 0 | BD25: =HISTOJANV24!BD25+HISTOFEV24!BD25+HISTOMARS24!BD25+HISTOAVRIL24!BD25+HISTOMAI24!BD25+HISTOJUIN24!BD25+HISTOJUIL24!BD25+HISTOAOUT24!BD25+HISTOSEPT24!BD25+HISTOOCT24!BD25+HISTONOV24!BD25+HISTODEC24!BD25 -> 2110000 | BF25: =HISTOJANV24!BF25+HISTOFEV24!BF25+HISTOMARS24!BF25+HISTOAVRIL24!BF25+HISTOMAI24!BF25+HISTOJUIN24!BF25+HISTOJUIL24!BF25+HISTOAOUT24!BF25+HISTOSEPT24!BF25+HISTOOCT24!BF25+HISTONOV24!BF25+HISTODEC24!BF25 -> 0 | BN25: DEVELOPPEMENT LAGWEU | BO25: FRAIS EXEPTIONNEL
