Workbook
Name BANQUE: #REF!
Name BANQUE: #REF!
Name BANQUE: #REF!
Name BANQUE: #REF!
Name BANQUE: #REF!
Name BANQUE: #REF!
Name BANQUE: #REF!
Name BANQUE: #REF!
Name MODEPAID: [1]Feuil2!$A$1:$A$3
Name MODEPAID: [1]Feuil2!$A$1:$A$3
Name MODEPAID: [2]Feuil2!$A$1:$A$3
Name MODEPAID: [2]Feuil2!$A$1:$A$3
Name MODEPAID: [2]Feuil2!$A$1:$A$3
Name MODEPAID: [2]Feuil2!$A$1:$A$3
Name MODEPAID: [2]Feuil2!$A$1:$A$3
Name MODEPAID: [1]Feuil2!$A$1:$A$3
Name MODEPAID: [3]Feuil2!$A$1:$A$3
Name MODET25000: [4]MODEVERSEMENT!$A$1:$A$3
Name MODEVERSEMENT: #REF!
Name MODEVERSEMENT: #REF!
Name MODEVERSEMENT: #REF!
Name MODEVERSEMENT: #REF!
Name MODEVERSEMENT: #REF!
Name MODEVERSEMENT: #REF!
Name MODEVERSEMENT: #REF!
Name MODEVERSEMENT: #REF!
Name MODEVERSEMENTS: #REF!
Name MODEVERSEMENTS: #REF!
Name MODEVERSEMENTS: #REF!
Name MODEVERSEMENTS: #REF!
Name MODEVERSEMENTS: #REF!
Name MODEVERSEMENTS: [5]MODEVERSEMENT!$A$1:$A$3
Name VALMODEPAID: [6]MODEPAID!$A$1:$A$3
Name VALMODEPAID: [6]MODEPAID!$A$1:$A$3
Name VALMODEPAID: [6]MODEPAID!$A$1:$A$3
Name VALMODEPAID: [6]MODEPAID!$A$1:$A$3
Name VALMODEPAID: [6]MODEPAID!$A$1:$A$3
Name VALMODEPAID: [7]MODEPAID!$A$1:$A$3

Sheet BILAN 2016
A2: BILAN ALLANT DE LA PERIODE DU 01 DECEMBRE 2015 AU 30 NOVEMBRE 2016
A5: RUBRIQUE | B5: REPORT A NOUVEAU | C5: ENTREES | D5: SORTIES | E5: SOLDE
A7: EPARGNE\RELIQUAT2015 | B7: 29756024 | C7: =[8]TRAVAUXINVENTAIRE!R54+C20+1050000+2230668 -> 7101809 | E7: =B7+C7-D7 -> 36857833
A8: FONDS DE CAISSE | C8: 28382451 | D8: 39386431 | E8: =B8+C8-D8 -> -11003980
A9: FONDS DE ROULEMENT | B9: 3031178 | C9: =[8]TRAVAUXINVENTAIRE!S54 -> 250500 | D9: ='[9]BILAN 2016'!$D$9 -> 224500 | E9: =B9+C9-D9 -> 3057178
A10: FRAIS EXCEPTIONNELS | B10: 1267460 | C10: =[8]TRAVAUXINVENTAIRE!T54 -> 501000 | D10: =[8]TRAVAUXINVENTAIREDEC!B6 -> 1100000 | E10: =B10+C10-D10 -> 668460
A11: COLLATION | B11: 940125 | C11: =[8]TRAVAUXINVENTAIRE!U54 -> 1252500 | D11: =[8]TRAVAUXINVENTAIREDEC!B7 -> 1260000 | E11: =B11+C11-D11 -> 932625
A12: MUTUELLE\COMPLEMENT MUTUEL | B12: =-101500 -> -101500 | C12: =[8]TRAVAUXINVENTAIRE!V54+[8]TRAVAUXINVENTAIRE!O54 -> 1954860 | D12: =[8]TRAVAUXINVENTAIREDEC!B8 -> 2595000 | E12: =B12+C12-D12 -> -741640
A13: INSCRIPTION | B13: 530000 | E13: =B13+C13-D13 -> 530000
A14: FONDS GELE | B14: 54508 | E14: =B14+C14-D14 -> 54508
A15: CHAISE | B15: -164500 | E15: =B15+C15-D15 -> -164500
A16: TENUE | B16: -75000 | E16: =B16+C16-D16 -> -75000
A17: FOYER | E17: =B17+C17-D17 -> 0
A18: RECOUVREMENT POUR LAGWEU GENERAL | C18: =320750+16500 -> 337250 | E18: =B18+C18-D18 -> 337250 | F18: 1711250
A19: AUTRES | E19: =B19+C19-D19 -> 0
A20: INTERET EMPRUNT | E20: =B20+C20-D20 -> 0
A22: EMPRUNT
A24: RELIQUAT 2016
A27: COMPTE CCA
A28: COMPTE AFRILAND
A29: INTERET BQUE AFRILAND | B29: 1779594 | E29: =B29+C29-D29 -> 1779594
A30: COMPTE MC2
A31: ASELBY CAISSE(NDJOMO ETIENNE)
A33: RETRAIT DISTRIBUTION EPARGNE
A35: SOUS TOTAL
A37: MONTANT DISPONIBLE | B37: =SUM(B7:B36) -> 37017889 | C37: =SUM(C7:C36) -> 39780370 | D37: =SUM(D7:D36) -> 44565931 | E37: =B37+C37-D37 -> 32232328

Sheet BILAN 2017
A2: BILAN ALLANT DE LA PERIODE DU 01 DECEMBRE 2016 AU 30 AOUT 2017
A5: RUBRIQUE | B5: REPORT A NOUVEAU | C5: ENTREES | D5: SORTIES | E5: SOLDE
A7: EPARGNE\RELIQUAT2016 | B7: ='BILAN 2016'!E7 -> 36857833 | C7: =[10]BILANFINAOUT2017!E56 -> 3963693 | D7: 13500000 | E7: =B7+C7-D7 -> 27321526
A8: FONDS DE CAISSE | B8: ='BILAN 2016'!E8 -> -11003980 | C8: =[10]BILANFINAOUT2017!C56 -> 16310819 | E8: =B8+C8-D8 -> 5306839
A9: FONDS DE ROULEMENT | B9: ='BILAN 2016'!E9 -> 3057178 | C9: =[10]BILANFINAOUT2017!F56 -> 182000 | D9: =89000+84000+12000+10000+6000+48000+13000+5000 -> 267000 | E9: =B9+C9-D9 -> 2972178
A10: FRAIS EXCEPTIONNELS | B10: ='BILAN 2016'!E10 -> 668460 | C10: =[10]BILANFINAOUT2017!G56 -> 364000 | D10: =200000+345000 -> 545000 | E10: =B10+C10-D10 -> 487460
A11: COLLATION | B11: ='BILAN 2016'!E11 -> 932625 | C11: =[10]BILANFINAOUT2017!H56 -> 910000 | D11: =100000+110000+100000+100000+100000+100000+100000+100000+100000 -> 910000 | E11: =B11+C11-D11 -> 932625
A12: MUTUELLE\COMPLEMENT MUTUEL | B12: ='BILAN 2016'!E12 -> -741640 | C12: =[10]BILANFINAOUT2017!I56 -> 2009927 | D12: =200000+100000+640000 -> 940000 | E12: =B12+C12-D12 -> 328287
A13: PENALITE VERSEMENT EN ESPECES | C13: =[10]BILANFINAOUT2017!R56 -> 125000 | E13: =B13+C13-D13 -> 125000
A14: SANCTION | C14: =+[10]BILANFINAOUT2017!J56 -> 0
A15: INSCRIPTION | B15: ='BILAN 2016'!E13 -> 530000 | E15: =B15+C15-D15 -> 530000
A16: FONDS GELE | B16: ='BILAN 2016'!E14 -> 54508 | E16: =B16+C16-D16 -> 54508
A17: CHAISE | B17: ='BILAN 2016'!E15 -> -164500 | E17: =B17+C17-D17 -> -164500
A18: TENUE | B18: ='BILAN 2016'!E16 -> -75000 | E18: =B18+C18-D18 -> -75000
E19: =B19+C19-D19 -> 0
A20: FOYER | E20: =B20+C20-D20 -> 0
A21: RECOUVREMENT POUR LAGWEU GENERAL | B21: ='BILAN 2016'!E18 -> 337250 | E21: =B21+C21-D21 -> 337250
A22: AUTRES
A23: INTERET EMPRUNT
A25: EMPRUNT | E25: =B25+C25-D25 -> 0
A27: RELIQUAT 2016
A29: INTERET BQUE AFRILAND | B29: 1779594 | E29: =B29+C29-D29 -> 1779594
A30: COMPTE CCA
A31: COMPTE AFRILAND
A32: COMPTE MC2
A33: ASELBY CAISSE(NDJOMO ETIENNE)
A35: RETRAIT DISTRIBUTION EPARGNE
A39: MONTANT DISPONIBLE | B39: =SUM(B7:B38) -> 32232328 | C39: =SUM(C7:C38) -> 23865439 | D39: =SUM(D7:D38) -> 16162000 | E39: =B39+C39-D39 -> 39935767

Sheet SITFINANCIERE
A2: SITUATION TRESORERIE ALLANT DE LA PERIODE DU 01 SEPTEMBRE 2017 AU 30 AOUT 2018
A5: RUBRIQUE | B5: MOUVEMENT ASELBY | C5: TRESORERIE | D5: SOLDE
A7: CAISSE | C7: 0
A8: COMPTE CCA | C8: 10660936
A9: COMPTE AFRILAND | C9: 4817411
A10: COMPTE MC2 | C10: 630005
A11: FRAIS EXCEPTIONNELS | B11: ='BILAN 2018'!E7 -> 9719176.9
A12: FONDS DE CAISSE | B12: ='BILAN 2018'!E8 -> 6536839
A13: EPARGNE | B13: =INVENT2017_2018!K56 -> 8164348.9
A14: FONDS DE ROULEMENT | B14: ='BILAN 2018'!E10 -> 2895678
A15: FRAIS EXCEPTIONNELS | B15: ='BILAN 2018'!E11 -> 331960
A16: COLLATION | B16: ='BILAN 2018'!E12 -> 927625
A17: MUTUELLE\COMPLEMENT MUTUEL | B17: ='BILAN 2018'!E13 -> 88287
A18: PENALITE VERSEMENT EN ESPECES | B18: ='BILAN 2018'!E14 -> 323500
A19: INSCRIPTION | B19: ='BILAN 2018'!E15 -> 580000
A20: SANCTION | B20: ='BILAN 2018'!E16 -> 0
A21: AUTRES
A22: PRET EN COURS | C22: =INVENT2017_2018!S56 -> 10310500
A24: MONTANT DISPONIBLE | B24: =SUM(B11:B23) -> 29567415 | C24: =SUM(C7:C23) -> 26418852 | D24: =B24-C24 -> 3148562.8

Sheet BILAN 2018
A2: BILAN ALLANT DE LA PERIODE DU 01 SEPTEMBRE 2017 AU 30 AOUT 2018
A5: RUBRIQUE | B5: REPORT A NOUVEAU | C5: ENTREES | D5: SORTIES | E5: SOLDE
A7: RELIQUAT 2017/EPARGNE | B7: ='BILAN 2017'!E7 -> 27321526 | C7: =INVENT2017_2018!C56+3860500 -> 10034614 | D7: =24505800+3131163 -> 27636963 | E7: =B7+C7-D7 -> 9719176.9
A8: FONDS DE CAISSE | B8: ='BILAN 2017'!E8 -> 5306839 | C8: =INVENT2017_2018!J56 -> 1230000 | E8: =B8+C8-D8 -> 6536839
A9: EPARGNE | E9: =B9+C9-D9 -> 0
A10: FONDS DE ROULEMENT | B10: ='BILAN 2017'!E9 -> 2972178 | C10: =ENTREE!C22 -> 229000 | D10: =SORTIE!C22 -> 305500 | E10: =B10+C10-D10 -> 2895678
A11: FRAIS EXCEPTIONNELS | B11: ='BILAN 2017'!E10 -> 487460 | C11: =ENTREE!D22 -> 458000 | D11: =SORTIE!D22 -> 613500 | E11: =B11+C11-D11 -> 331960
A12: COLLATION | B12: ='BILAN 2017'!E11 -> 932625 | C12: =ENTREE!E22 -> 1145000 | D12: =SORTIE!E22 -> 1150000 | E12: =B12+C12-D12 -> 927625
A13: MUTUELLE\COMPLEMENT MUTUEL | B13: ='BILAN 2017'!E12 -> 328287 | C13: =ENTREE!H22 -> 860000 | D13: =SORTIE!H22 -> 1100000 | E13: =B13+C13-D13 -> 88287
A14: PENALITE VERSEMENT EN ESPECES | B14: =+'BILAN 2017'!E13 -> 125000 | C14: =ENTREE!F22 -> 198500 | E14: =B14+C14-D14 -> 323500
A15: INSCRIPTION | B15: ='BILAN 2017'!E15 -> 530000 | C15: =ENTREE!G22 -> 50000 | E15: =B15+C15-D15 -> 580000
A16: SANCTION | E16: =B16+C16-D16 -> 0
A17: FONDS GELE | B17: ='BILAN 2017'!E16 -> 54508 | E17: =B17+C17-D17 -> 54508
A18: CHAISE | B18: ='BILAN 2017'!E17 -> -164500 | E18: =B18+C18-D18 -> -164500
A19: TENUE | B19: ='BILAN 2017'!E18 -> -75000 | E19: =B19+C19-D19 -> -75000
E20: =B20+C20-D20 -> 0
A21: RECOUVREMENT POUR LAGWEU GENERAL 2 | C21: =+'INVENT2017_2018 (4)'!L58 -> 655300 | D21: 1400000 | E21: =B21+C21-D21 -> -744700
A22: RECOUVREMENT POUR LAGWEU GENERAL | B22: ='BILAN 2017'!E21 -> 337250 | E22: =B22+C22-D22 -> 337250
A23: AUTRES | E23: =B23+C23-D23 -> 0
A24: PRET EN COURS | B24: ='BILAN 2017'!E25 -> 0 | E24: =B24+C24-D24 -> 0
A25: INTERET PRET 18 MOIS | E25: =B25+C25-D25 -> 0
E26: =B26+C26-D26 -> 0
E27: =B27+C27-D27 -> 0
E28: =B28+C28-D28 -> 0
E29: =B29+C29-D29 -> 0
E30: =B30+C30-D30 -> 0
A31: COMPTE CCA | C31: 13614473 | E31: =B31+C31-D31 -> 13614473
A32: COMPTE AFRILAND | C32: 4817411 | E32: =B32+C32-D32 -> 4817411
A33: INTERET BQUE AFRILAND | B33: ='BILAN 2017'!B29 -> 1779594 | E33: =B33+C33-D33 -> 1779594
A34: COMPTE MC2 | C34: 630005 | E34: =B34+C34-D34 -> 630005
E35: =B35+C35-D35 -> 0
A36: RETRAIT DISTRIBUTION EPARGNE | E36: =B36+C36-D36 -> 0
E37: =B37+C37-D37 -> 0
E38: =B38+C38-D38 -> 0
A40: MONTANT DISPONIBLE | B40: =SUM(B7:B39) -> 39935767 | C40: =SUM(C7:C30) -> 14860414 | D40: =SUM(D7:D30) -> 32205963 | E40: =B40+C40-D40 -> 22590218

Sheet ENTREE
B2: ENTREE DES DIFFERENTES RUBRIQUES
A3: ANNEE | B3: 2017-2018
A6: MOIS | B6: EPARGNE | C6: FONDS DE ROULEMENT | D6: FRAIS EXCEPTIONNEL | E6: COLLATION | F6: PENALITE VST ESPECES | G6: INSCRIPTION | H6: MUTUELLE | I6: TOTAL
A7: REPORT
A8: AOUT | B8: =+[11]MVTAOUT!H$54 -> 359000 | C8: =+[11]MVTAOUT!I$54 -> 23000 | D8: =+[11]MVTAOUT!J$54 -> 46000 | E8: =+[11]MVTAOUT!K$54 -> 115000 | F8: =+[11]MVTAOUT!L$54 -> 27500 | G8: =+[11]MVTAOUT!M$54 -> 0 | H8: =+[11]MVTAOUT!N$54 -> 30000 | I8: =SUM(B8:H8) -> 600500
A9: SEPTEMBRE | B9: =+[11]MVTSEPT!I$54 -> 233000 | C9: =+[11]MVTSEPT!J$54 -> 18000 | D9: =+[11]MVTSEPT!K$54 -> 36000 | E9: =+[11]MVTSEPT!L$54 -> 90000 | F9: =+[11]MVTSEPT!M$54 -> 15000 | G9: =+[11]MVTSEPT!N$54 -> 0 | H9: =+[11]MVTSEPT!O$54 -> 0 | I9: =SUM(B9:H9) -> 392000
A10: OCTOBRE | B10: =+[11]MVTOCT!G$54 -> 182000 | C10: =+[11]MVTOCT!H$54 -> 18500 | D10: =+[11]MVTOCT!I$54 -> 37000 | E10: =+[11]MVTOCT!J$54 -> 92500 | F10: =+[11]MVTOCT!K$54 -> 14000 | G10: =+[11]MVTOCT!L$54 -> 0 | H10: =+[11]MVTOCT!M$54 -> 0 | I10: =SUM(B10:H10) -> 344000
A11: NOVEMBRE | B11: =+[11]MVTNOV!G$54 -> 182500 | C11: =+[11]MVTNOV!H$54 -> 18500 | D11: =+[11]MVTNOV!I$54 -> 37000 | E11: =+[11]MVTNOV!J$54 -> 92500 | F11: =+[11]MVTNOV!K$54 -> 17000 | G11: =+[11]MVTNOV!L$54 -> 25000 | H11: =+[11]MVTNOV!M$54 -> 0 | I11: =SUM(B11:H11) -> 372500
A12: DÉCEMBRE | B12: =+[11]MVTDEC!G$54 -> 212000 | C12: =+[11]MVTDEC!H$54 -> 18000 | D12: =+[11]MVTDEC!I$54 -> 36000 | E12: =+[11]MVTDEC!J$54 -> 90000 | F12: =+[11]MVTDEC!K$54 -> 17000 | G12: =+[11]MVTDEC!L$54 -> 0 | H12: =+[11]MVTDEC!M$54 -> 220000 | I12: =SUM(B12:H12) -> 593000
A13: JANVIER | B13: =+[11]MVTJANV!G$54 -> 138000 | C13: =+[11]MVTJANV!H$54 -> 19500 | D13: =+[11]MVTJANV!I$54 -> 39000 | E13: =+[11]MVTJANV!J$54 -> 97500 | F13: =+[11]MVTJANV!K$54 -> 17000 | G13: =+[11]MVTJANV!L$54 -> 0 | H13: =+[11]MVTJANV!M$54 -> 50000 | I13: =SUM(B13:H13) -> 361000
A14: FÉVRIER | B14: =+[11]MVTFEV!G$54 -> 192000 | C14: =+[11]MVTFEV!H$54 -> 18500 | D14: =+[11]MVTFEV!I$54 -> 37000 | E14: =+[11]MVTFEV!J$54 -> 92500 | F14: =+[11]MVTFEV!K$54 -> 17000 | G14: =+[11]MVTFEV!L$54 -> 0 | H14: =+[11]MVTFEV!M$54 -> 0 | I14: =SUM(B14:H14) -> 357000
A15: MARS | B15: =+[11]MVTMARS!G$54 -> 191000 | C15: =+[11]MVTMARS!H$54 -> 18500 | D15: =+[11]MVTMARS!I$54 -> 37000 | E15: =+[11]MVTMARS!J$54 -> 92500 | F15: =+[11]MVTMARS!K$54 -> 12000 | G15: =+[11]MVTMARS!L$54 -> 0 | H15: =+[11]MVTMARS!M$54 -> 20000 | I15: =SUM(B15:H15) -> 371000
A16: AVRIL | B16: =+[11]MVTAVRIL!G$54 -> 345000 | C16: =+[11]MVTAVRIL!H$54 -> 20000 | D16: =+[11]MVTAVRIL!I$54 -> 40000 | E16: =+[11]MVTAVRIL!J$54 -> 100000 | F16: =+[11]MVTAVRIL!K$54 -> 13000 | G16: =+[11]MVTAVRIL!L$54 -> 25000 | H16: =+[11]MVTAVRIL!M$54 -> 170000 | I16: =SUM(B16:H16) -> 713000
A17: MAI | B17: =+[11]MVTMAI!G$54 -> 1389000 | C17: =+[11]MVTMAI!H$54 -> 19000 | D17: =+[11]MVTMAI!I$54 -> 38000 | E17: =+[11]MVTMAI!J$54 -> 95000 | F17: =+[11]MVTMAI!K$54 -> 14000 | G17: =+[11]MVTMAI!L$54 -> 0 | H17: =+[11]MVTMAI!M$54 -> 200000 | I17: =SUM(B17:H17) -> 1755000
A18: JUIN | B18: =+[11]MVTJUIN!G$54 -> 135000 | C18: =+[11]MVTJUIN!H$54 -> 19000 | D18: =+[11]MVTJUIN!I$54 -> 38000 | E18: =+[11]MVTJUIN!J$54 -> 95000 | F18: =+[11]MVTJUIN!K$54 -> 19000 | G18: =+[11]MVTJUIN!L$54 -> 0 | H18: =+[11]MVTJUIN!M$54 -> 170000 | I18: =SUM(B18:H18) -> 476000
A19: JUILLET | B19: =+[11]MVTJUIL!G$54 -> 148000 | C19: =+[11]MVTJUIL!H$54 -> 18500 | D19: =+[11]MVTJUIL!I$54 -> 37000 | E19: =+[11]MVTJUIL!J$54 -> 92500 | F19: =+[11]MVTJUIL!K$54 -> 16000 | G19: =+[11]MVTJUIL!L$54 -> 0 | H19: =+[11]MVTJUIL!M$54 -> 0 | I19: =SUM(B19:H19) -> 312000
A20: AOÛT | B20: =+[12]MVTAOUT!G$54 -> 0 | C20: =+[12]MVTAOUT!H$54 -> 0 | D20: =+[12]MVTAOUT!I$54 -> 0 | E20: =+[12]MVTAOUT!J$54 -> 0 | F20: =+[12]MVTAOUT!K$54 -> 0 | G20: =+[12]MVTAOUT!L$54 -> 0 | H20: =+[12]MVTAOUT!M$54 -> 0 | I20: =SUM(B20:H20) -> 0
A22: TOTAL | B22: =SUM(B8:B21) -> 3706500 | C22: =SUM(C8:C21) -> 229000 | D22: =SUM(D8:D21) -> 458000 | E22: =SUM(E8:E21) -> 1145000 | F22: =SUM(F8:F21) -> 198500 | G22: =SUM(G8:G21) -> 50000 | H22: =SUM(H8:H21) -> 860000 | I22: =SUM(I8:I21) -> 6647000
C25: =+INVENT2017_2018!D56-ENTREE!B22 -> 154000

Sheet SORTIE
B2: SORTIE DES DIFFERENTES RUBRIQUES
A3: ANNEE | B3: 2017-2018
A6: MOIS | B6: EPARGNE | C6: FONDS DE ROULEMENT | D6: FRAIS EXCEPTIONNEL | E6: COLLATION | F6: PENALITE VST ESPECES | G6: INSCRIPTION | H6: MUTUELLE | I6: TOTAL
A7: REPORT
A8: AOUT | C8: =SORTIEDETAILLE!$C$13 -> 5000 | D8: =SORTIEDETAILLE!$C$20 -> 0 | E8: =SORTIEDETAILLE!$C$24 -> 100000 | H8: =SORTIEDETAILLE!$C$26 -> 0 | I8: =SUM(B8:H8) -> 105000
A9: SEPTEMBRE | C9: =SORTIEDETAILLE!$D$13 -> 60500 | D9: =SORTIEDETAILLE!$D$20 -> 0 | E9: =SORTIEDETAILLE!$D$24 -> 100000 | H9: =SORTIEDETAILLE!$D$26 -> 0 | I9: =SUM(B9:H9) -> 160500
A10: OCTOBRE | C10: =SORTIEDETAILLE!$E$13 -> 0 | D10: =SORTIEDETAILLE!$E$20 -> 0 | E10: =SORTIEDETAILLE!$E$24 -> 0 | H10: =SORTIEDETAILLE!$E$26 -> 0 | I10: =SUM(B10:H10) -> 0
A11: NOVEMBRE | C11: =SORTIEDETAILLE!$F$13 -> 18000 | D11: =SORTIEDETAILLE!$F$20 -> 300000 | E11: =SORTIEDETAILLE!$F$24 -> 110000 | H11: =SORTIEDETAILLE!$F$26 -> 100000 | I11: =SUM(B11:H11) -> 528000
A12: DÉCEMBRE | C12: =SORTIEDETAILLE!$G$13 -> 29000 | D12: =SORTIEDETAILLE!$G$20 -> 0 | E12: =SORTIEDETAILLE!$G$24 -> 100000 | H12: =SORTIEDETAILLE!$G$26 -> 0 | I12: =SUM(B12:H12) -> 129000
A13: JANVIER | C13: =SORTIEDETAILLE!$H$13 -> 18000 | D13: =SORTIEDETAILLE!$H$20 -> 3500 | E13: =SORTIEDETAILLE!$H$24 -> 100000 | H13: =SORTIEDETAILLE!$H$26 -> 100000 | I13: =SUM(B13:H13) -> 221500
A14: FÉVRIER | C14: =SORTIEDETAILLE!$I$13 -> 0 | D14: =SORTIEDETAILLE!$I$20 -> 310000 | E14: =SORTIEDETAILLE!$I$24 -> 0 | H14: =SORTIEDETAILLE!$I$26 -> 0 | I14: =SUM(B14:H14) -> 310000
A15: MARS | C15: =SORTIEDETAILLE!$J$13 -> 14000 | D15: =SORTIEDETAILLE!$J$20 -> 0 | E15: =SORTIEDETAILLE!$J$24 -> 100000 | H15: =SORTIEDETAILLE!$J$26 -> 0 | I15: =SUM(B15:H15) -> 114000
A16: AVRIL | C16: =SORTIEDETAILLE!$K$13 -> 12000 | D16: =SORTIEDETAILLE!$K$20 -> 0 | E16: =SORTIEDETAILLE!$K$24 -> 100000 | H16: =SORTIEDETAILLE!$K$26 -> 0 | I16: =SUM(B16:H16) -> 112000
A17: MAI | C17: =SORTIEDETAILLE!$L$13 -> 15000 | D17: =SORTIEDETAILLE!$L$20 -> 0 | E17: =SORTIEDETAILLE!$L$24 -> 100000 | H17: =SORTIEDETAILLE!$L$26 -> 100000 | I17: =SUM(B17:H17) -> 215000
A18: JUIN | C18: =SORTIEDETAILLE!$M$13 -> 93000 | D18: =SORTIEDETAILLE!$M$20 -> 0 | E18: =SORTIEDETAILLE!$M$24 -> 100000 | H18: =SORTIEDETAILLE!$M$26 -> 100000 | I18: =SUM(B18:H18) -> 293000
A19: JUILLET | C19: =SORTIEDETAILLE!$N$13 -> 0 | D19: =SORTIEDETAILLE!$N$20 -> 0 | E19: =SORTIEDETAILLE!$N$24 -> 140000 | H19: =SORTIEDETAILLE!$N$26 -> 500000 | I19: =SUM(B19:H19) -> 640000
A20: AOÛT | B20: 4862745.3 | C20: =SORTIEDETAILLE!$O$13 -> 41000 | D20: =SORTIEDETAILLE!$O$20 -> 0 | E20: =SORTIEDETAILLE!$O$24 -> 100000 | H20: =SORTIEDETAILLE!$O$26 -> 200000 | I20: =SUM(B20:H20) -> 5203745.3
A22: TOTAL | B22: =SUM(B8:B21) -> 4862745.3 | C22: =SUM(C8:C21) -> 305500 | D22: =SUM(D8:D21) -> 613500 | E22: =SUM(E8:E21) -> 1150000 | F22: =SUM(F8:F21) -> 0 | G22: =SUM(G8:G21) -> 0 | H22: =SUM(H8:H21) -> 1100000 | I22: =SUM(I8:I21) -> 8031745.3

Sheet SORTIEDETAILLE
B1: SORTIE DETAILLEES DES DIFFERENTES RUBRIQUES
A2: ANNEE | B2: 2017-2018
A6: LIBELLE | B6: COMPTE | C6: AOUT 2017 | D6: SEPTEMBRE | E6: OCTOBRE | F6: NOVEMBRE | G6: DÉCEMBRE | H6: JANVIER | I6: FÉVRIER | J6: MARS | K6: AVRIL | L6: MAI | M6: JUIN | N6: JUILLET | O6: AOÛT
A8: PRÊT | C8: 150000 | D8: 600000 | E8: MUET | F8: 1000000 | G8: 600000 | H8: 990000 | I8: 1850000 | J8: 700000 | K8: 2000000 | L8: 2000000 | M8: 500000
A9: COMMUNICATION | B9: FONDS DE ROULEMENT | C9: 5000 | D9: 3000 | F9: 18000 | G9: 5000 | M9: 3000
A10: COMMISSION | B10: FONDS DE ROULEMENT | D10: 57500 | G10: 24000 | H10: 18000 | J10: 14000 | K10: 12000 | L10: 15000 | O10: =33000+8000 -> 41000
A11: AIDE UEEB ET CONT FEMME | B11: FONDS DE ROULEMENT | M11: 90000
A13: S/TOTAL | C13: =SUM(C9:C11) -> 5000 | D13: =SUM(D9:D11) -> 60500 | E13: =SUM(E9:E11) -> 0 | F13: =SUM(F9:F11) -> 18000 | G13: =SUM(G9:G11) -> 29000 | H13: =SUM(H9:H11) -> 18000 | I13: =SUM(I9:I11) -> 0 | J13: =SUM(J9:J11) -> 14000 | ... O13: =SUM(O9:O11) -> 41000
A15: ACHAT SOURIS ET PHOTOCOPIE | B15: FRAIS EXEPTIONNEL | H15: 3500
A16: GRATIFICATION BUREAU | B16: FRAIS EXEPTIONNEL | I16: 200000
A17: CONTRIBUTION ET PRÊT CONSEIL | B17: FRAIS EXEPTIONNEL | I17: 110000
A18: FESTAC | B18: FRAIS EXEPTIONNEL | F18: 300000
A20: S/TOTAL | C20: =SUM(C15:C18) -> 0 | D20: =SUM(D15:D18) -> 0 | E20: =SUM(E15:E18) -> 0 | F20: =SUM(F15:F18) -> 300000 | G20: =SUM(G15:G18) -> 0 | H20: =SUM(H15:H18) -> 3500 | I20: =SUM(I15:I18) -> 310000 | J20: =SUM(J15:J18) -> 0 | ... O20: =SUM(O15:O18) -> 0
A22: COLLATION | B22: COLLATION | C22: 100000 | D22: 100000 | F22: 100000 | G22: 100000 | H22: 100000 | J22: 100000 | K22: 100000 | L22: 100000 | M22: 100000 | N22: 100000 | O22: 100000
A23: BOISSON | B23: COLLATION | F23: 10000 | N23: 40000
A24: S/TOTAL | C24: =SUM(C22:C23) -> 100000 | D24: =SUM(D22:D23) -> 100000 | E24: =SUM(E22:E23) -> 0 | F24: =SUM(F22:F23) -> 110000 | G24: =SUM(G22:G23) -> 100000 | H24: =SUM(H22:H23) -> 100000 | I24: =SUM(I22:I23) -> 0 | J24: =SUM(J22:J23) -> 100000 | ... O24: =SUM(O22:O23) -> 100000
A26: DECES | B26: MUTUELLE | F26: 100000 | H26: 100000 | L26: 100000 | M26: 100000 | N26: 500000 | O26: 200000
A28: S/TOTAL | C28: =C13+C20+C24+C26 -> 105000 | D28: =D13+D20+D24+D26 -> 160500 | E28: =E13+E20+E24+E26 -> 0 | F28: =F13+F20+F24+F26 -> 528000 | G28: =G13+G20+G24+G26 -> 129000 | H28: =H13+H20+H24+H26 -> 221500 | I28: =I13+I20+I24+I26 -> 310000 | J28: =J13+J20+J24+J26 -> 114000 | ... O28: =O13+O20+O24+O26 -> 341000

Sheet INVENT2016_2017
B1: CALCUL INTERET EPARGNE DECEMBRE 2016- JUILLET 2017
A3: NOM ET PRENOM | B3: FONDS CAISSE | C3: RELIQUAT | D3: EPARGNE | E3: INTERETEPARGNE | F3: TOTAL AVOIR | G3: SANCTION | H3: AVANCE | I3: TOTAL A PERCEVOIR | J3: NOUVEAU FONDS | K3: SOLDE TOUT COMPTE | L3: EMPRUNT | M3: INTERET EMPRUNT | N3: A REMBOURSER AOUT 2017
A4: ASELBY | B4: 0 | C4: =[5]TONT20000DEC2016!$D5 -> 355097 | E4: =[5]TONT20000DEC2016!$E5+[5]TONT20000JANV2017!$C5+[5]TONT20000FEV2017!$C5+[5]TONT20000MARS2017!$C5+[5]TONT20000AVRIL2017!$C5+[5]TONT20000MAI2017!$C5+[5]TONT20000JUIN2017!$C5+[5]TONT20000JUIL2017!$C5 -> 23403.204 | F4: =+C4+D4+E4 -> 378500.2 | K4: =B4+I4-N4 -> 0
A5: BAKOP ACHILLE | B5: 420000 | C5: =[5]TONT20000DEC2016!$D6 -> 51993 | E5: =[5]TONT20000DEC2016!$E6+[5]TONT20000JANV2017!$C6+[5]TONT20000FEV2017!$C6+[5]TONT20000MARS2017!$C6+[5]TONT20000AVRIL2017!$C6+[5]TONT20000MAI2017!$C6+[5]TONT20000JUIN2017!$C6+[5]TONT20000JUIL2017!$C6 -> 31107.412 | F5: =+C5+D5+E5 -> 83100.412 | G5: 23250 | J5: =[11]MVTSEPT!$C6 -> 450000 | K5: =B5+I5-N5 -> -168000 | M5: =[5]TONT20000DEC2016!R6+[5]TONT20000JANV2017!P6+[5]TONT20000FEV2017!P6+[5]TONT20000MARS2017!P6+[5]TONT20000AVRIL2017!P6+[5]TONT20000MAI2017!P6+[5]TONT20000JUIN2017!P6+[5]TONT20000JUIL2017!P6 -> 0 | N5: =[8]EMPRUNT!$D6 -> 588000
A6: BOUTCHOUANG WILLIAM | B6: 420000 | C6: =[5]TONT20000DEC2016!$D7 -> 2720 | D6: =+[5]TONT20000DEC2016!$L7+[5]TONT20000JANV2017!$J7+[5]TONT20000FEV2017!$J7+[5]TONT20000MARS2017!$J7+[5]TONT20000AVRIL2017!$J7+[5]TONT20000MAI2017!$J7+[5]TONT20000JUIN2017!$J7+[5]TONT20000JUIL2017!$J7 -> 24000 | E6: =[5]TONT20000DEC2016!$E7+[5]TONT20000JANV2017!$C7+[5]TONT20000FEV2017!$C7+[5]TONT20000MARS2017!$C7+[5]TONT20000AVRIL2017!$C7+[5]TONT20000MAI2017!$C7+[5]TONT20000JUIN2017!$C7+[5]TONT20000JUIL2017!$C7 -> 28906.871 | F6: =+C6+D6+E6 -> 55626.871 | G6: 100 | H6: 8000 | I6: =F6-G6-H6 -> 47526.871 | J6: =[11]MVTSEPT!$C7 -> 450000 | K6: =B6+I6-N6 -> -316473.13 | M6: =[5]TONT20000DEC2016!R7+[5]TONT20000JANV2017!P7+[5]TONT20000FEV2017!P7+[5]TONT20000MARS2017!P7+[5]TONT20000AVRIL2017!P7+[5]TONT20000MAI2017!P7+[5]TONT20000JUIN2017!P7+[5]TONT20000JUIL2017!P7 -> 0 | N6: =[8]EMPRUNT!$D7 -> 784000
A7: CHINGUE FABRICE | B7: 420000 | C7: =[5]TONT20000DEC2016!$D8 -> 5874 | D7: =+[5]TONT20000DEC2016!$L8+[5]TONT20000JANV2017!$J8+[5]TONT20000FEV2017!$J8+[5]TONT20000MARS2017!$J8+[5]TONT20000AVRIL2017!$J8+[5]TONT20000MAI2017!$J8+[5]TONT20000JUIN2017!$J8+[5]TONT20000JUIL2017!$J8 -> 24000 | E7: =[5]TONT20000DEC2016!$E8+[5]TONT20000JANV2017!$C8+[5]TONT20000FEV2017!$C8+[5]TONT20000MARS2017!$C8+[5]TONT20000AVRIL2017!$C8+[5]TONT20000MAI2017!$C8+[5]TONT20000JUIN2017!$C8+[5]TONT20000JUIL2017!$C8 -> 29114.74 | F7: =+C7+D7+E7 -> 58988.74 | G7: 19100 | I7: =F7-G7-H7 -> 39888.74 | J7: =[11]MVTSEPT!$C8 -> 450000 | K7: =B7+I7-N7 -> -833711.26 | M7: =[5]TONT20000DEC2016!R8+[5]TONT20000JANV2017!P8+[5]TONT20000FEV2017!P8+[5]TONT20000MARS2017!P8+[5]TONT20000AVRIL2017!P8+[5]TONT20000MAI2017!P8+[5]TONT20000JUIN2017!P8+[5]TONT20000JUIL2017!P8 -> 0 | N7: =[8]EMPRUNT!$D8 -> 1293600
A8: DJOMO JEAN PAUL | B8: 420000 | C8: =[5]TONT20000DEC2016!$D9 -> 2570 | D8: =+[5]TONT20000DEC2016!$L9+[5]TONT20000JANV2017!$J9+[5]TONT20000FEV2017!$J9+[5]TONT20000MARS2017!$J9+[5]TONT20000AVRIL2017!$J9+[5]TONT20000MAI2017!$J9+[5]TONT20000JUIN2017!$J9+[5]TONT20000JUIL2017!$J9 -> 34500 | E8: =[5]TONT20000DEC2016!$E9+[5]TONT20000JANV2017!$C9+[5]TONT20000FEV2017!$C9+[5]TONT20000MARS2017!$C9+[5]TONT20000AVRIL2017!$C9+[5]TONT20000MAI2017!$C9+[5]TONT20000JUIN2017!$C9+[5]TONT20000JUIL2017!$C9 -> 29354.098 | F8: =+C8+D8+E8 -> 66424.098 | G8: 43200 | I8: =F8-G8-H8 -> 23224.098 | J8: =[11]MVTSEPT!$C9 -> 450000 | K8: =B8+I8-N8 -> -573775.9 | M8: =[5]TONT20000DEC2016!R9+[5]TONT20000JANV2017!P9+[5]TONT20000FEV2017!P9+[5]TONT20000MARS2017!P9+[5]TONT20000AVRIL2017!P9+[5]TONT20000MAI2017!P9+[5]TONT20000JUIN2017!P9+[5]TONT20000JUIL2017!P9 -> 120000 | N8: =[8]EMPRUNT!$D9 -> 1017000
A9: DJOUKWE NANGUEN GUY BLAISE | B9: 420000 | C9: =[5]TONT20000DEC2016!$D10 -> 2697 | D9: =+[5]TONT20000DEC2016!$L10+[5]TONT20000JANV2017!$J10+[5]TONT20000FEV2017!$J10+[5]TONT20000MARS2017!$J10+[5]TONT20000AVRIL2017!$J10+[5]TONT20000MAI2017!$J10+[5]TONT20000JUIN2017!$J10+[5]TONT20000JUIL2017!$J10 -> 37000 | E9: =[5]TONT20000DEC2016!$E10+[5]TONT20000JANV2017!$C10+[5]TONT20000FEV2017!$C10+[5]TONT20000MARS2017!$C10+[5]TONT20000AVRIL2017!$C10+[5]TONT20000MAI2017!$C10+[5]TONT20000JUIN2017!$C10+[5]TONT20000JUIL2017!$C10 -> 29309.04 | F9: =+C9+D9+E9 -> 69006.04 | I9: =F9-G9-H9 -> 69006.04 | J9: =[11]MVTSEPT!$C10 -> 450000 | K9: =B9+I9-N9 -> 349006.04 | M9: =[5]TONT20000DEC2016!R10+[5]TONT20000JANV2017!P10+[5]TONT20000FEV2017!P10+[5]TONT20000MARS2017!P10+[5]TONT20000AVRIL2017!P10+[5]TONT20000MAI2017!P10+[5]TONT20000JUIN2017!P10+[5]TONT20000JUIL2017!P10 -> 0 | N9: =[8]EMPRUNT!$D10 -> 140000
A10: DJOSSEU JOSUE | B10: 0 | C10: =[5]TONT20000DEC2016!$D11 -> 0 | K10: =B10+I10-N10 -> 0
A11: DJOUNKEP SAMUEL | B11: 420000 | C11: =[5]TONT20000DEC2016!$D12 -> 635540 | D11: =+[5]TONT20000DEC2016!$L12+[5]TONT20000JANV2017!$J12+[5]TONT20000FEV2017!$J12+[5]TONT20000MARS2017!$J12+[5]TONT20000AVRIL2017!$J12+[5]TONT20000MAI2017!$J12+[5]TONT20000JUIN2017!$J12+[5]TONT20000JUIL2017!$J12 -> 24000 | E11: =[5]TONT20000DEC2016!$E12+[5]TONT20000JANV2017!$C12+[5]TONT20000FEV2017!$C12+[5]TONT20000MARS2017!$C12+[5]TONT20000AVRIL2017!$C12+[5]TONT20000MAI2017!$C12+[5]TONT20000JUIN2017!$C12+[5]TONT20000JUIL2017!$C12 -> 70613.828 | F11: =+C11+D11+E11 -> 730153.83 | G11: 0 | I11: =F11-G11-H11 -> 730153.83 | J11: =[11]MVTSEPT!$C11 -> 450000 | K11: =B11+I11-N11 -> 30153.828 | M11: =[5]TONT20000DEC2016!R12+[5]TONT20000JANV2017!P12+[5]TONT20000FEV2017!P12+[5]TONT20000MARS2017!P12+[5]TONT20000AVRIL2017!P12+[5]TONT20000MAI2017!P12+[5]TONT20000JUIN2017!P12+[5]TONT20000JUIL2017!P12 -> 100000 | N11: =[8]EMPRUNT!$D11 -> 1120000
A12: DJUOMBESSY ANTOINE | B12: 420000 | C12: =[5]TONT20000DEC2016!$D13 -> 2746 | D12: =+[5]TONT20000DEC2016!$L13+[5]TONT20000JANV2017!$J13+[5]TONT20000FEV2017!$J13+[5]TONT20000MARS2017!$J13+[5]TONT20000AVRIL2017!$J13+[5]TONT20000MAI2017!$J13+[5]TONT20000JUIN2017!$J13+[5]TONT20000JUIL2017!$J13 -> 24000 | E12: =[5]TONT20000DEC2016!$E13+[5]TONT20000JANV2017!$C13+[5]TONT20000FEV2017!$C13+[5]TONT20000MARS2017!$C13+[5]TONT20000AVRIL2017!$C13+[5]TONT20000MAI2017!$C13+[5]TONT20000JUIN2017!$C13+[5]TONT20000JUIL2017!$C13 -> 28908.584 | F12: =+C12+D12+E12 -> 55654.584 | G12: 8000 | I12: =F12-G12-H12 -> 47654.584 | J12: =[11]MVTSEPT!$C12 -> 450000 | K12: =B12+I12-N12 -> -316345.42 | M12: =[5]TONT20000DEC2016!R13+[5]TONT20000JANV2017!P13+[5]TONT20000FEV2017!P13+[5]TONT20000MARS2017!P13+[5]TONT20000AVRIL2017!P13+[5]TONT20000MAI2017!P13+[5]TONT20000JUIN2017!P13+[5]TONT20000JUIL2017!P13 -> 70000 | N12: =[8]EMPRUNT!$D12 -> 784000
A13: DONHOU DAVID | B13: 420000 | C13: =[5]TONT20000DEC2016!$D14 -> 53748 | D13: =+[5]TONT20000DEC2016!$L14+[5]TONT20000JANV2017!$J14+[5]TONT20000FEV2017!$J14+[5]TONT20000MARS2017!$J14+[5]TONT20000AVRIL2017!$J14+[5]TONT20000MAI2017!$J14+[5]TONT20000JUIN2017!$J14+[5]TONT20000JUIL2017!$J14 -> 24000 | E13: =[5]TONT20000DEC2016!$E14+[5]TONT20000JANV2017!$C14+[5]TONT20000FEV2017!$C14+[5]TONT20000MARS2017!$C14+[5]TONT20000AVRIL2017!$C14+[5]TONT20000MAI2017!$C14+[5]TONT20000JUIN2017!$C14+[5]TONT20000JUIL2017!$C14 -> 32269.948 | F13: =+C13+D13+E13 -> 110017.95 | G13: 0 | I13: =F13-G13-H13 -> 110017.95 | J13: =[11]MVTSEPT!$C13 -> 450000 | K13: =B13+I13-N13 -> 530017.95 | M13: =[5]TONT20000DEC2016!R14+[5]TONT20000JANV2017!P14+[5]TONT20000FEV2017!P14+[5]TONT20000MARS2017!P14+[5]TONT20000AVRIL2017!P14+[5]TONT20000MAI2017!P14+[5]TONT20000JUIN2017!P14+[5]TONT20000JUIL2017!P14 -> 0 | N13: =[8]EMPRUNT!$D13 -> 0
A14: FOTSO THOMAS | B14: 420000 | C14: =[5]TONT20000DEC2016!$D15 -> 2522 | D14: =+[5]TONT20000DEC2016!$L15+[5]TONT20000JANV2017!$J15+[5]TONT20000FEV2017!$J15+[5]TONT20000MARS2017!$J15+[5]TONT20000AVRIL2017!$J15+[5]TONT20000MAI2017!$J15+[5]TONT20000JUIN2017!$J15+[5]TONT20000JUIL2017!$J15 -> 24000 | E14: =[5]TONT20000DEC2016!$E15+[5]TONT20000JANV2017!$C15+[5]TONT20000FEV2017!$C15+[5]TONT20000MARS2017!$C15+[5]TONT20000AVRIL2017!$C15+[5]TONT20000MAI2017!$C15+[5]TONT20000JUIN2017!$C15+[5]TONT20000JUIL2017!$C15 -> 28893.821 | F14: =+C14+D14+E14 -> 55415.821 | G14: 8000 | I14: =F14-G14-H14 -> 47415.821 | J14: =[11]MVTSEPT!$C14 -> 450000 | K14: =B14+I14-N14 -> -826184.18 | M14: =[5]TONT20000DEC2016!R15+[5]TONT20000JANV2017!P15+[5]TONT20000FEV2017!P15+[5]TONT20000MARS2017!P15+[5]TONT20000AVRIL2017!P15+[5]TONT20000MAI2017!P15+[5]TONT20000JUIN2017!P15+[5]TONT20000JUIL2017!P15 -> 0 | N14: =[8]EMPRUNT!$D14 -> 1293600
A15: HENGUE PAUL OMER | B15: 420000 | D15: =+[5]TONT20000DEC2016!$L16+[5]TONT20000JANV2017!$J16+[5]TONT20000FEV2017!$J16+[5]TONT20000MARS2017!$J16+[5]TONT20000AVRIL2017!$J16+[5]TONT20000MAI2017!$J16+[5]TONT20000JUIN2017!$J16+[5]TONT20000JUIL2017!$J16 -> 90000 | E15: =[5]TONT20000DEC2016!$E16+[5]TONT20000JANV2017!$C16+[5]TONT20000FEV2017!$C16+[5]TONT20000MARS2017!$C16+[5]TONT20000AVRIL2017!$C16+[5]TONT20000MAI2017!$C16+[5]TONT20000JUIN2017!$C16+[5]TONT20000JUIL2017!$C16 -> 33077.435 | F15: =+C15+D15+E15 -> 123077.43 | G15: 8100 | J15: =[11]MVTSEPT!$C15 -> 450000 | K15: =B15+I15-N15 -> 420000 | M15: =[5]TONT20000DEC2016!R16+[5]TONT20000JANV2017!P16+[5]TONT20000FEV2017!P16+[5]TONT20000MARS2017!P16+[5]TONT20000AVRIL2017!P16+[5]TONT20000MAI2017!P16+[5]TONT20000JUIN2017!P16+[5]TONT20000JUIL2017!P16 -> 0 | N15: =[8]EMPRUNT!$D15 -> 0
A16: HODIEP JULES | B16: 50000 | C16: =[5]TONT20000DEC2016!$D17 -> 260 | E16: =[5]TONT20000DEC2016!$E17+[5]TONT20000JANV2017!$C17+[5]TONT20000FEV2017!$C17+[5]TONT20000MARS2017!$C17+[5]TONT20000AVRIL2017!$C17+[5]TONT20000MAI2017!$C17+[5]TONT20000JUIN2017!$C17+[5]TONT20000JUIL2017!$C17 -> 3312.4612 | F16: =+C16+D16+E16 -> 3572.4612 | G16: 0 | J16: =[11]MVTSEPT!$C16 -> 80000 | K16: =B16+I16-N16 -> 50000 | M16: =[5]TONT20000DEC2016!R17+[5]TONT20000JANV2017!P17+[5]TONT20000FEV2017!P17+[5]TONT20000MARS2017!P17+[5]TONT20000AVRIL2017!P17+[5]TONT20000MAI2017!P17+[5]TONT20000JUIN2017!P17+[5]TONT20000JUIL2017!P17 -> 0 | N16: =[8]EMPRUNT!$D16 -> 0
A17: HOTCHO BENJAMIN | B17: 420000 | C17: =[5]TONT20000DEC2016!$D18 -> 112685 | D17: =+[5]TONT20000DEC2016!$L18+[5]TONT20000JANV2017!$J18+[5]TONT20000FEV2017!$J18+[5]TONT20000MARS2017!$J18+[5]TONT20000AVRIL2017!$J18+[5]TONT20000MAI2017!$J18+[5]TONT20000JUIN2017!$J18+[5]TONT20000JUIL2017!$J18 -> 24000 | E17: =[5]TONT20000DEC2016!$E18+[5]TONT20000JANV2017!$C18+[5]TONT20000FEV2017!$C18+[5]TONT20000MARS2017!$C18+[5]TONT20000AVRIL2017!$C18+[5]TONT20000MAI2017!$C18+[5]TONT20000JUIN2017!$C18+[5]TONT20000JUIL2017!$C18 -> 36154.28 | F17: =+C17+D17+E17 -> 172839.28 | G17: 20000 | H17: 70000 | I17: =F17-G17-H17 -> 82839.28 | J17: =[11]MVTSEPT!$C17 -> 450000 | K17: =B17+I17-N17 -> -281160.72 | M17: =[5]TONT20000DEC2016!R18+[5]TONT20000JANV2017!P18+[5]TONT20000FEV2017!P18+[5]TONT20000MARS2017!P18+[5]TONT20000AVRIL2017!P18+[5]TONT20000MAI2017!P18+[5]TONT20000JUIN2017!P18+[5]TONT20000JUIL2017!P18 -> 84000 | N17: =[8]EMPRUNT!$D17 -> 784000
A18: KEPHE DAVID | B18: 357000 | C18: =[5]TONT20000DEC2016!$D19 -> 177 | D18: =+[5]TONT20000DEC2016!$L19+[5]TONT20000JANV2017!$J19+[5]TONT20000FEV2017!$J19+[5]TONT20000MARS2017!$J19+[5]TONT20000AVRIL2017!$J19+[5]TONT20000MAI2017!$J19+[5]TONT20000JUIN2017!$J19+[5]TONT20000JUIL2017!$J19 -> 24000 | E18: =[5]TONT20000DEC2016!$E19+[5]TONT20000JANV2017!$C19+[5]TONT20000FEV2017!$C19+[5]TONT20000MARS2017!$C19+[5]TONT20000AVRIL2017!$C19+[5]TONT20000MAI2017!$C19+[5]TONT20000JUIN2017!$C19+[5]TONT20000JUIL2017!$C19 -> 24587.16 | F18: =+C18+D18+E18 -> 48764.16 | G18: 100 | I18: =F18-G18-H18 -> 48664.16 | J18: =[11]MVTSEPT!$C18 -> 387000 | K18: =B18+I18-N18 -> 405664.16 | M18: =[5]TONT20000DEC2016!R19+[5]TONT20000JANV2017!P19+[5]TONT20000FEV2017!P19+[5]TONT20000MARS2017!P19+[5]TONT20000AVRIL2017!P19+[5]TONT20000MAI2017!P19+[5]TONT20000JUIN2017!P19+[5]TONT20000JUIL2017!P19 -> 0 | N18: =[8]EMPRUNT!$D18 -> 0
A19: KEPSEU FRANCIS | B19: 420000 | C19: =[5]TONT20000DEC2016!$D20 -> 705425 | D19: =+[5]TONT20000DEC2016!$L20+[5]TONT20000JANV2017!$J20+[5]TONT20000FEV2017!$J20+[5]TONT20000MARS2017!$J20+[5]TONT20000AVRIL2017!$J20+[5]TONT20000MAI2017!$J20+[5]TONT20000JUIN2017!$J20+[5]TONT20000JUIL2017!$J20 -> 2048000 | E19: =[5]TONT20000DEC2016!$E20+[5]TONT20000JANV2017!$C20+[5]TONT20000FEV2017!$C20+[5]TONT20000MARS2017!$C20+[5]TONT20000AVRIL2017!$C20+[5]TONT20000MAI2017!$C20+[5]TONT20000JUIN2017!$C20+[5]TONT20000JUIL2017!$C20 -> 158003.91 | F19: =+C19+D19+E19 -> 2911428.9 | G19: 0 | H19: 1000000 | I19: =F19-G19-H19 -> 1911428.9 | J19: =[11]MVTSEPT!$C19 -> 450000 | K19: =B19+I19-N19 -> 2331428.9 | M19: =[5]TONT20000DEC2016!R20+[5]TONT20000JANV2017!P20+[5]TONT20000FEV2017!P20+[5]TONT20000MARS2017!P20+[5]TONT20000AVRIL2017!P20+[5]TONT20000MAI2017!P20+[5]TONT20000JUIN2017!P20+[5]TONT20000JUIL2017!P20 -> 0 | N19: =[8]EMPRUNT!$D19 -> 0
A20: KOUAMOU EMMANUEL | B20: 420000 | C20: =[5]TONT20000DEC2016!$D21 -> 2357 | D20: =+[5]TONT20000DEC2016!$L21+[5]TONT20000JANV2017!$J21+[5]TONT20000FEV2017!$J21+[5]TONT20000MARS2017!$J21+[5]TONT20000AVRIL2017!$J21+[5]TONT20000MAI2017!$J21+[5]TONT20000JUIN2017!$J21+[5]TONT20000JUIL2017!$J21 -> 24000 | E20: =[5]TONT20000DEC2016!$E21+[5]TONT20000JANV2017!$C21+[5]TONT20000FEV2017!$C21+[5]TONT20000MARS2017!$C21+[5]TONT20000AVRIL2017!$C21+[5]TONT20000MAI2017!$C21+[5]TONT20000JUIN2017!$C21+[5]TONT20000JUIL2017!$C21 -> 28882.947 | F20: =+C20+D20+E20 -> 55239.947 | G20: 0 | H20: 8000 | I20: =F20-G20-H20 -> 47239.947 | J20: =[11]MVTSEPT!$C20 -> 450000 | K20: =B20+I20-N20 -> -632760.05 | M20: =[5]TONT20000DEC2016!R21+[5]TONT20000JANV2017!P21+[5]TONT20000FEV2017!P21+[5]TONT20000MARS2017!P21+[5]TONT20000AVRIL2017!P21+[5]TONT20000MAI2017!P21+[5]TONT20000JUIN2017!P21+[5]TONT20000JUIL2017!P21 -> 0 | N20: =[8]EMPRUNT!$D20 -> 1100000
A21: KOUAMOU MOISE | B21: 420000 | C21: =[5]TONT20000DEC2016!$D22 -> 3048 | D21: =+[5]TONT20000DEC2016!$L22+[5]TONT20000JANV2017!$J22+[5]TONT20000FEV2017!$J22+[5]TONT20000MARS2017!$J22+[5]TONT20000AVRIL2017!$J22+[5]TONT20000MAI2017!$J22+[5]TONT20000JUIN2017!$J22+[5]TONT20000JUIL2017!$J22 -> 24000 | E21: =[5]TONT20000DEC2016!$E22+[5]TONT20000JANV2017!$C22+[5]TONT20000FEV2017!$C22+[5]TONT20000MARS2017!$C22+[5]TONT20000AVRIL2017!$C22+[5]TONT20000MAI2017!$C22+[5]TONT20000JUIN2017!$C22+[5]TONT20000JUIL2017!$C22 -> 28860.893 | F21: =+C21+D21+E21 -> 55908.893 | G21: 2100 | I21: =F21-G21-H21 -> 53808.893 | J21: =[11]MVTSEPT!$C21 -> 450000 | K21: =B21+I21-N21 -> -118191.11 | M21: =[5]TONT20000DEC2016!R22+[5]TONT20000JANV2017!P22+[5]TONT20000FEV2017!P22+[5]TONT20000MARS2017!P22+[5]TONT20000AVRIL2017!P22+[5]TONT20000MAI2017!P22+[5]TONT20000JUIN2017!P22+[5]TONT20000JUIL2017!P22 -> 15000 | N21: =[8]EMPRUNT!$D21 -> 592000
A22: KOUAMO VICTOR PEGUY | B22: 420000 | C22: =[5]TONT20000DEC2016!$D23 -> 2686 | D22: =+[5]TONT20000DEC2016!$L23+[5]TONT20000JANV2017!$J23+[5]TONT20000FEV2017!$J23+[5]TONT20000MARS2017!$J23+[5]TONT20000AVRIL2017!$J23+[5]TONT20000MAI2017!$J23+[5]TONT20000JUIN2017!$J23+[5]TONT20000JUIL2017!$J23 -> 24000 | E22: =[5]TONT20000DEC2016!$E23+[5]TONT20000JANV2017!$C23+[5]TONT20000FEV2017!$C23+[5]TONT20000MARS2017!$C23+[5]TONT20000AVRIL2017!$C23+[5]TONT20000MAI2017!$C23+[5]TONT20000JUIN2017!$C23+[5]TONT20000JUIL2017!$C23 -> 28904.63 | F22: =+C22+D22+E22 -> 55590.63 | G22: 16500 | I22: =F22-G22-H22 -> 39090.63 | J22: =[11]MVTSEPT!$C22 -> 450000 | K22: =B22+I22-N22 -> -436909.37 | M22: =[5]TONT20000DEC2016!R23+[5]TONT20000JANV2017!P23+[5]TONT20000FEV2017!P23+[5]TONT20000MARS2017!P23+[5]TONT20000AVRIL2017!P23+[5]TONT20000MAI2017!P23+[5]TONT20000JUIN2017!P23+[5]TONT20000JUIL2017!P23 -> 0 | N22: =[8]EMPRUNT!$D22 -> 896000
A23: KOUATCHO MESSACK | B23: 420000 | C23: =[5]TONT20000DEC2016!$D24 -> 3818 | D23: =+[5]TONT20000DEC2016!$L24+[5]TONT20000JANV2017!$J24+[5]TONT20000FEV2017!$J24+[5]TONT20000MARS2017!$J24+[5]TONT20000AVRIL2017!$J24+[5]TONT20000MAI2017!$J24+[5]TONT20000JUIN2017!$J24+[5]TONT20000JUIL2017!$J24 -> 24000 | E23: =[5]TONT20000DEC2016!$E24+[5]TONT20000JANV2017!$C24+[5]TONT20000FEV2017!$C24+[5]TONT20000MARS2017!$C24+[5]TONT20000AVRIL2017!$C24+[5]TONT20000MAI2017!$C24+[5]TONT20000JUIN2017!$C24+[5]TONT20000JUIL2017!$C24 -> 28979.236 | F23: =+C23+D23+E23 -> 56797.236 | G23: 20000 | I23: =F23-G23-H23 -> 36797.236 | J23: =[11]MVTSEPT!$C23 -> 450000 | K23: =B23+I23-N23 -> -663202.76 | M23: =[5]TONT20000DEC2016!R24+[5]TONT20000JANV2017!P24+[5]TONT20000FEV2017!P24+[5]TONT20000MARS2017!P24+[5]TONT20000AVRIL2017!P24+[5]TONT20000MAI2017!P24+[5]TONT20000JUIN2017!P24+[5]TONT20000JUIL2017!P24 -> 120000 | N23: =[8]EMPRUNT!$D23 -> 1120000
A24: LOWE JEAN | B24: 420000 | C24: =[5]TONT20000DEC2016!$D25 -> 2652 | D24: =+[5]TONT20000DEC2016!$L25+[5]TONT20000JANV2017!$J25+[5]TONT20000FEV2017!$J25+[5]TONT20000MARS2017!$J25+[5]TONT20000AVRIL2017!$J25+[5]TONT20000MAI2017!$J25+[5]TONT20000JUIN2017!$J25+[5]TONT20000JUIL2017!$J25 -> 21000 | E24: =[5]TONT20000DEC2016!$E25+[5]TONT20000JANV2017!$C25+[5]TONT20000FEV2017!$C25+[5]TONT20000MARS2017!$C25+[5]TONT20000AVRIL2017!$C25+[5]TONT20000MAI2017!$C25+[5]TONT20000JUIN2017!$C25+[5]TONT20000JUIL2017!$C25 -> 28854.896 | F24: =+C24+D24+E24 -> 52506.896 | G24: 0 | H24: 5000 | I24: =F24-G24-H24 -> 47506.896 | J24: =[11]MVTSEPT!$C24 -> 450000 | K24: =B24+I24-N24 -> 313006.9 | M24: =[5]TONT20000DEC2016!R25+[5]TONT20000JANV2017!P25+[5]TONT20000FEV2017!P25+[5]TONT20000MARS2017!P25+[5]TONT20000AVRIL2017!P25+[5]TONT20000MAI2017!P25+[5]TONT20000JUIN2017!P25+[5]TONT20000JUIL2017!P25 -> 0 | N24: =[8]EMPRUNT!$D24 -> 154500
A25: NANKAM APPOLINAIRE | B25: 420000 | C25: =[5]TONT20000DEC2016!$D26 -> 2741 | D25: =+[5]TONT20000DEC2016!$L26+[5]TONT20000JANV2017!$J26+[5]TONT20000FEV2017!$J26+[5]TONT20000MARS2017!$J26+[5]TONT20000AVRIL2017!$J26+[5]TONT20000MAI2017!$J26+[5]TONT20000JUIN2017!$J26+[5]TONT20000JUIL2017!$J26 -> 24000 | E25: =[5]TONT20000DEC2016!$E26+[5]TONT20000JANV2017!$C26+[5]TONT20000FEV2017!$C26+[5]TONT20000MARS2017!$C26+[5]TONT20000AVRIL2017!$C26+[5]TONT20000MAI2017!$C26+[5]TONT20000JUIN2017!$C26+[5]TONT20000JUIL2017!$C26 -> 28908.255 | F25: =+C25+D25+E25 -> 55649.255 | G25: 100 | H25: 8000 | I25: =F25-G25-H25 -> 47549.255 | J25: =[11]MVTSEPT!$C25 -> 450000 | K25: =B25+I25-N25 -> 467549.25 | M25: =[5]TONT20000DEC2016!R26+[5]TONT20000JANV2017!P26+[5]TONT20000FEV2017!P26+[5]TONT20000MARS2017!P26+[5]TONT20000AVRIL2017!P26+[5]TONT20000MAI2017!P26+[5]TONT20000JUIN2017!P26+[5]TONT20000JUIL2017!P26 -> 0 | N25: =[8]EMPRUNT!$D25 -> 0
A26: NDJOMO ETIENNE | B26: 420000 | C26: =[5]TONT20000DEC2016!$D27 -> 2818 | D26: =+[5]TONT20000DEC2016!$L27+[5]TONT20000JANV2017!$J27+[5]TONT20000FEV2017!$J27+[5]TONT20000MARS2017!$J27+[5]TONT20000AVRIL2017!$J27+[5]TONT20000MAI2017!$J27+[5]TONT20000JUIN2017!$J27+[5]TONT20000JUIL2017!$J27 -> 64000 | E26: =[5]TONT20000DEC2016!$E27+[5]TONT20000JANV2017!$C27+[5]TONT20000FEV2017!$C27+[5]TONT20000MARS2017!$C27+[5]TONT20000AVRIL2017!$C27+[5]TONT20000MAI2017!$C27+[5]TONT20000JUIN2017!$C27+[5]TONT20000JUIL2017!$C27 -> 30658.114 | F26: =+C26+D26+E26 -> 97476.114 | G26: 0 | H26: 50000 | I26: =F26-G26-H26 -> 47476.114 | J26: =[11]MVTSEPT!$C26 -> 450000 | K26: =B26+I26-N26 -> -204523.89 | M26: =[5]TONT20000DEC2016!R27+[5]TONT20000JANV2017!P27+[5]TONT20000FEV2017!P27+[5]TONT20000MARS2017!P27+[5]TONT20000AVRIL2017!P27+[5]TONT20000MAI2017!P27+[5]TONT20000JUIN2017!P27+[5]TONT20000JUIL2017!P27 -> 84000 | N26: =[8]EMPRUNT!$D26 -> 672000
A27: NDOMBOU JEAN CLAUDE | B27: 420000 | C27: =[5]TONT20000DEC2016!$D28 -> 0 | E27: =[5]TONT20000DEC2016!$E28+[5]TONT20000JANV2017!$C28+[5]TONT20000FEV2017!$C28+[5]TONT20000MARS2017!$C28+[5]TONT20000AVRIL2017!$C28+[5]TONT20000MAI2017!$C28+[5]TONT20000JUIN2017!$C28+[5]TONT20000JUIL2017!$C28 -> 27680.734 | F27: =+C27+D27+E27 -> 27680.734 | G27: 0 | I27: =F27-G27-H27 -> 27680.734 | J27: =[11]MVTSEPT!$C27 -> 450000 | K27: =B27+I27-N27 -> 447680.73 | N27: =[8]EMPRUNT!$D27 -> 0
A28: NGONDIEP CLAUDE | B28: 420000 | C28: =[5]TONT20000DEC2016!$D29 -> 3250 | D28: =+[5]TONT20000DEC2016!$L29+[5]TONT20000JANV2017!$J29+[5]TONT20000FEV2017!$J29+[5]TONT20000MARS2017!$J29+[5]TONT20000AVRIL2017!$J29+[5]TONT20000MAI2017!$J29+[5]TONT20000JUIN2017!$J29+[5]TONT20000JUIL2017!$J29 -> 33000 | E28: =[5]TONT20000DEC2016!$E29+[5]TONT20000JANV2017!$C29+[5]TONT20000FEV2017!$C29+[5]TONT20000MARS2017!$C29+[5]TONT20000AVRIL2017!$C29+[5]TONT20000MAI2017!$C29+[5]TONT20000JUIN2017!$C29+[5]TONT20000JUIL2017!$C29 -> 29529.518 | F28: =+C28+D28+E28 -> 65779.518 | G28: 18100 | I28: =F28-G28-H28 -> 47679.518 | J28: =[11]MVTSEPT!$C28 -> 450000 | K28: =B28+I28-N28 -> -652320.48 | M28: =[5]TONT20000DEC2016!R29+[5]TONT20000JANV2017!P29+[5]TONT20000FEV2017!P29+[5]TONT20000MARS2017!P29+[5]TONT20000AVRIL2017!P29+[5]TONT20000MAI2017!P29+[5]TONT20000JUIN2017!P29+[5]TONT20000JUIL2017!P29 -> 120000 | N28: =[8]EMPRUNT!$D28 -> 1120000
A29: NGONGANG JEAN THEODORE | B29: 0 | C29: =[5]TONT20000DEC2016!$D30 -> 106 | E29: =[5]TONT20000DEC2016!$E30+[5]TONT20000JANV2017!$C30+[5]TONT20000FEV2017!$C30+[5]TONT20000MARS2017!$C30+[5]TONT20000AVRIL2017!$C30+[5]TONT20000MAI2017!$C30+[5]TONT20000JUIN2017!$C30+[5]TONT20000JUIL2017!$C30 -> 969.65037 | F29: =+C29+D29+E29 -> 1075.6504 | G29: 5250 | I29: =F29-G29-H29 -> -4174.3496 | J29: =[11]MVTSEPT!$C29 -> 30000 | K29: =B29+I29-N29 -> -4174.3496 | M29: =[5]TONT20000DEC2016!R30+[5]TONT20000JANV2017!P30+[5]TONT20000FEV2017!P30+[5]TONT20000MARS2017!P30+[5]TONT20000AVRIL2017!P30+[5]TONT20000MAI2017!P30+[5]TONT20000JUIN2017!P30+[5]TONT20000JUIL2017!P30 -> 0 | N29: =[8]EMPRUNT!$D29 -> 0
A30: NGUIEMEGNI MATHIEU BLAISE | B30: 420000 | C30: =[5]TONT20000DEC2016!$D31 -> 40133 | D30: =+[5]TONT20000DEC2016!$L31+[5]TONT20000JANV2017!$J31+[5]TONT20000FEV2017!$J31+[5]TONT20000MARS2017!$J31+[5]TONT20000AVRIL2017!$J31+[5]TONT20000MAI2017!$J31+[5]TONT20000JUIN2017!$J31+[5]TONT20000JUIL2017!$J31 -> 24000 | E30: =[5]TONT20000DEC2016!$E31+[5]TONT20000JANV2017!$C31+[5]TONT20000FEV2017!$C31+[5]TONT20000MARS2017!$C31+[5]TONT20000AVRIL2017!$C31+[5]TONT20000MAI2017!$C31+[5]TONT20000JUIN2017!$C31+[5]TONT20000JUIL2017!$C31 -> 31372.631 | F30: =+C30+D30+E30 -> 95505.631 | G30: 2300 | I30: =F30-G30-H30 -> 93205.631 | J30: =[11]MVTSEPT!$C30 -> 450000 | K30: =B30+I30-N30 -> 513205.63 | M30: =[5]TONT20000DEC2016!R31+[5]TONT20000JANV2017!P31+[5]TONT20000FEV2017!P31+[5]TONT20000MARS2017!P31+[5]TONT20000AVRIL2017!P31+[5]TONT20000MAI2017!P31+[5]TONT20000JUIN2017!P31+[5]TONT20000JUIL2017!P31 -> 0 | N30: =[8]EMPRUNT!$D30 -> 0
A31: NJEPDJIO MBOUKAM DELUXE | B31: 420000 | C31: =[5]TONT20000DEC2016!$D32 -> 2773 | D31: =+[5]TONT20000DEC2016!$L32+[5]TONT20000JANV2017!$J32+[5]TONT20000FEV2017!$J32+[5]TONT20000MARS2017!$J32+[5]TONT20000AVRIL2017!$J32+[5]TONT20000MAI2017!$J32+[5]TONT20000JUIN2017!$J32+[5]TONT20000JUIL2017!$J32 -> 29000 | E31: =[5]TONT20000DEC2016!$E32+[5]TONT20000JANV2017!$C32+[5]TONT20000FEV2017!$C32+[5]TONT20000MARS2017!$C32+[5]TONT20000AVRIL2017!$C32+[5]TONT20000MAI2017!$C32+[5]TONT20000JUIN2017!$C32+[5]TONT20000JUIL2017!$C32 -> 29236.873 | F31: =+C31+D31+E31 -> 61009.873 | G31: 200 | H31: 13900 | I31: =F31-G31-H31 -> 46909.873 | J31: =[11]MVTSEPT!$C31 -> 450000 | K31: =B31+I31-N31 -> -429090.13 | M31: =[5]TONT20000DEC2016!R32+[5]TONT20000JANV2017!P32+[5]TONT20000FEV2017!P32+[5]TONT20000MARS2017!P32+[5]TONT20000AVRIL2017!P32+[5]TONT20000MAI2017!P32+[5]TONT20000JUIN2017!P32+[5]TONT20000JUIL2017!P32 -> 96000 | N31: =[8]EMPRUNT!$D31 -> 896000
A32: NKAMGANG JUSTIN DEJOLIE | B32: 420000 | C32: =[5]TONT20000DEC2016!$D33 -> 69808 | D32: =+[5]TONT20000DEC2016!$L33+[5]TONT20000JANV2017!$J33+[5]TONT20000FEV2017!$J33+[5]TONT20000MARS2017!$J33+[5]TONT20000AVRIL2017!$J33+[5]TONT20000MAI2017!$J33+[5]TONT20000JUIN2017!$J33+[5]TONT20000JUIL2017!$J33 -> 50000 | E32: =[5]TONT20000DEC2016!$E33+[5]TONT20000JANV2017!$C33+[5]TONT20000FEV2017!$C33+[5]TONT20000MARS2017!$C33+[5]TONT20000AVRIL2017!$C33+[5]TONT20000MAI2017!$C33+[5]TONT20000JUIN2017!$C33+[5]TONT20000JUIL2017!$C33 -> 34505.881 | F32: =+C32+D32+E32 -> 154313.88 | G32: 0 | H32: 100000 | I32: =F32-G32-H32 -> 54313.881 | J32: =[11]MVTSEPT!$C32 -> 450000 | K32: =B32+I32-N32 -> -645686.12 | M32: =[5]TONT20000DEC2016!R33+[5]TONT20000JANV2017!P33+[5]TONT20000FEV2017!P33+[5]TONT20000MARS2017!P33+[5]TONT20000AVRIL2017!P33+[5]TONT20000MAI2017!P33+[5]TONT20000JUIN2017!P33+[5]TONT20000JUIL2017!P33 -> 0 | N32: =[8]EMPRUNT!$D32 -> 1120000
A33: NKEPSEU DIEUDONNE | B33: 420000 | C33: =[5]TONT20000DEC2016!$D34 -> 2772 | D33: =+[5]TONT20000DEC2016!$L34+[5]TONT20000JANV2017!$J34+[5]TONT20000FEV2017!$J34+[5]TONT20000MARS2017!$J34+[5]TONT20000AVRIL2017!$J34+[5]TONT20000MAI2017!$J34+[5]TONT20000JUIN2017!$J34+[5]TONT20000JUIL2017!$J34 -> 164000 | E33: =[5]TONT20000DEC2016!$E34+[5]TONT20000JANV2017!$C34+[5]TONT20000FEV2017!$C34+[5]TONT20000MARS2017!$C34+[5]TONT20000AVRIL2017!$C34+[5]TONT20000MAI2017!$C34+[5]TONT20000JUIN2017!$C34+[5]TONT20000JUIL2017!$C34 -> 37245.733 | F33: =+C33+D33+E33 -> 204017.73 | G33: 4000 | H33: 150000 | I33: =F33-G33-H33 -> 50017.733 | J33: =[11]MVTSEPT!$C33 -> 450000 | K33: =B33+I33-N33 -> -1982.267 | M33: =[5]TONT20000DEC2016!R34+[5]TONT20000JANV2017!P34+[5]TONT20000FEV2017!P34+[5]TONT20000MARS2017!P34+[5]TONT20000AVRIL2017!P34+[5]TONT20000MAI2017!P34+[5]TONT20000JUIN2017!P34+[5]TONT20000JUIL2017!P34 -> 0 | N33: =[8]EMPRUNT!$D33 -> 472000
A34: NKEPSEU HENANG RENE | B34: 0 | C34: =[5]TONT20000DEC2016!$D35 -> 0 | F34: =+C34+D34+E34 -> 0 | I34: =F34-G34-H34 -> 0 | K34: =B34+I34-N34 -> 0 | N34: 0
A35: NTEPDIE TUEMAC MZ | B35: 0 | E35: =[5]TONT20000DEC2016!$E36+[5]TONT20000JANV2017!$C36+[5]TONT20000FEV2017!$C36+[5]TONT20000MARS2017!$C36+[5]TONT20000AVRIL2017!$C36+[5]TONT20000MAI2017!$C36+[5]TONT20000JUIN2017!$C36+[5]TONT20000JUIL2017!$C36 -> 0 | F35: =+C35+D35+E35 -> 0 | I35: =F35-G35-H35 -> 0 | K35: =B35+I35-N35 -> 0 | M35: =[5]TONT20000DEC2016!R36+[5]TONT20000JANV2017!P36+[5]TONT20000FEV2017!P36+[5]TONT20000MARS2017!P36+[5]TONT20000AVRIL2017!P36+[5]TONT20000MAI2017!P36+[5]TONT20000JUIN2017!P36+[5]TONT20000JUIL2017!P36 -> 0 | N35: 0
A36: NTOMBOU ADOLPHE | B36: 0 | C36: =[5]TONT20000DEC2016!$D37 -> 0 | F36: =+C36+D36+E36 -> 0 | I36: =F36-G36-H36 -> 0 | K36: =B36+I36-N36 -> 0 | N36: 0
A37: PATEGO NJOSSU GUSTAVE | B37: 420000 | C37: =[5]TONT20000DEC2016!$D38 -> 2474 | D37: =+[5]TONT20000DEC2016!$L38+[5]TONT20000JANV2017!$J38+[5]TONT20000FEV2017!$J38+[5]TONT20000MARS2017!$J38+[5]TONT20000AVRIL2017!$J38+[5]TONT20000MAI2017!$J38+[5]TONT20000JUIN2017!$J38+[5]TONT20000JUIL2017!$J38 -> 24000 | E37: =[5]TONT20000DEC2016!$E38+[5]TONT20000JANV2017!$C38+[5]TONT20000FEV2017!$C38+[5]TONT20000MARS2017!$C38+[5]TONT20000AVRIL2017!$C38+[5]TONT20000MAI2017!$C38+[5]TONT20000JUIN2017!$C38+[5]TONT20000JUIL2017!$C38 -> 28890.658 | F37: =+C37+D37+E37 -> 55364.658 | G37: 8200 | I37: =F37-G37-H37 -> 47164.658 | J37: =[11]MVTSEPT!$C35 -> 450000 | K37: =B37+I37-N37 -> 467164.66 | M37: =[5]TONT20000DEC2016!R38+[5]TONT20000JANV2017!P38+[5]TONT20000FEV2017!P38+[5]TONT20000MARS2017!P38+[5]TONT20000AVRIL2017!P38+[5]TONT20000MAI2017!P38+[5]TONT20000JUIN2017!P38+[5]TONT20000JUIL2017!P38 -> 0 | N37: =[8]EMPRUNT!$D35 -> 0
A38: SEUNOU RICHELOT | B38: 420000 | C38: =[5]TONT20000DEC2016!$D39 -> 6756 | D38: =+[5]TONT20000DEC2016!$L39+[5]TONT20000JANV2017!$J39+[5]TONT20000FEV2017!$J39+[5]TONT20000MARS2017!$J39+[5]TONT20000AVRIL2017!$J39+[5]TONT20000MAI2017!$J39+[5]TONT20000JUIN2017!$J39+[5]TONT20000JUIL2017!$J39 -> 24000 | E38: =[5]TONT20000DEC2016!$E39+[5]TONT20000JANV2017!$C39+[5]TONT20000FEV2017!$C39+[5]TONT20000MARS2017!$C39+[5]TONT20000AVRIL2017!$C39+[5]TONT20000MAI2017!$C39+[5]TONT20000JUIN2017!$C39+[5]TONT20000JUIL2017!$C39 -> 29172.869 | F38: =+C38+D38+E38 -> 59928.869 | G38: 20500 | I38: =F38-G38-H38 -> 39428.869 | J38: =[11]MVTSEPT!$C36 -> 450000 | K38: =B38+I38-N38 -> -660571.13 | M38: =[5]TONT20000DEC2016!R39+[5]TONT20000JANV2017!P39+[5]TONT20000FEV2017!P39+[5]TONT20000MARS2017!P39+[5]TONT20000AVRIL2017!P39+[5]TONT20000MAI2017!P39+[5]TONT20000JUIN2017!P39+[5]TONT20000JUIL2017!P39 -> 0 | N38: =[8]EMPRUNT!$D36 -> 1120000
A39: SIME ABEL | B39: 390000 | C39: =[5]TONT20000DEC2016!$D40 -> 488 | D39: =+[5]TONT20000DEC2016!$L40+[5]TONT20000JANV2017!$J40+[5]TONT20000FEV2017!$J40+[5]TONT20000MARS2017!$J40+[5]TONT20000AVRIL2017!$J40+[5]TONT20000MAI2017!$J40+[5]TONT20000JUIN2017!$J40+[5]TONT20000JUIL2017!$J40 -> 21000 | E39: =[5]TONT20000DEC2016!$E40+[5]TONT20000JANV2017!$C40+[5]TONT20000FEV2017!$C40+[5]TONT20000MARS2017!$C40+[5]TONT20000AVRIL2017!$C40+[5]TONT20000MAI2017!$C40+[5]TONT20000JUIN2017!$C40+[5]TONT20000JUIL2017!$C40 -> 26648.781 | F39: =+C39+D39+E39 -> 48136.781 | G39: 5250 | I39: =F39-G39-H39 -> 42886.781 | J39: =[11]MVTSEPT!$C37+30000-106000 -> 344000 | K39: =B39+I39-N39 -> -351113.22 | M39: =[5]TONT20000DEC2016!R40+[5]TONT20000JANV2017!P40+[5]TONT20000FEV2017!P40+[5]TONT20000MARS2017!P40+[5]TONT20000AVRIL2017!P40+[5]TONT20000MAI2017!P40+[5]TONT20000JUIN2017!P40+[5]TONT20000JUIL2017!P40 -> 84000 | N39: =[8]EMPRUNT!$D37 -> 784000
A40: SIME FONGANG ERIC | B40: 420000 | C40: =[5]TONT20000DEC2016!$D41 -> 4914 | D40: =+[5]TONT20000DEC2016!$L41+[5]TONT20000JANV2017!$J41+[5]TONT20000FEV2017!$J41+[5]TONT20000MARS2017!$J41+[5]TONT20000AVRIL2017!$J41+[5]TONT20000MAI2017!$J41+[5]TONT20000JUIN2017!$J41+[5]TONT20000JUIL2017!$J41 -> 24000 | E40: =[5]TONT20000DEC2016!$E41+[5]TONT20000JANV2017!$C41+[5]TONT20000FEV2017!$C41+[5]TONT20000MARS2017!$C41+[5]TONT20000AVRIL2017!$C41+[5]TONT20000MAI2017!$C41+[5]TONT20000JUIN2017!$C41+[5]TONT20000JUIL2017!$C41 -> 29051.469 | F40: =+C40+D40+E40 -> 57965.469 | G40: 4000 | I40: =F40-G40-H40 -> 53965.469 | J40: =[11]MVTSEPT!$C38 -> 450000 | K40: =B40+I40-N40 -> -646034.53 | M40: =[5]TONT20000DEC2016!R41+[5]TONT20000JANV2017!P41+[5]TONT20000FEV2017!P41+[5]TONT20000MARS2017!P41+[5]TONT20000AVRIL2017!P41+[5]TONT20000MAI2017!P41+[5]TONT20000JUIN2017!P41+[5]TONT20000JUIL2017!P41 -> 120000 | N40: =[8]EMPRUNT!$D38 -> 1120000
A41: SIME MATHIEU | B41: 420000 | C41: =[5]TONT20000DEC2016!$D42 -> 4528 | D41: =+[5]TONT20000DEC2016!$L42+[5]TONT20000JANV2017!$J42+[5]TONT20000FEV2017!$J42+[5]TONT20000MARS2017!$J42+[5]TONT20000AVRIL2017!$J42+[5]TONT20000MAI2017!$J42+[5]TONT20000JUIN2017!$J42+[5]TONT20000JUIL2017!$J42 -> 24000 | E41: =[5]TONT20000DEC2016!$E42+[5]TONT20000JANV2017!$C42+[5]TONT20000FEV2017!$C42+[5]TONT20000MARS2017!$C42+[5]TONT20000AVRIL2017!$C42+[5]TONT20000MAI2017!$C42+[5]TONT20000JUIN2017!$C42+[5]TONT20000JUIL2017!$C42 -> 29026.03 | F41: =+C41+D41+E41 -> 57554.03 | G41: 8100 | I41: =F41-G41-H41 -> 49454.03 | J41: =[11]MVTSEPT!$C39 -> 450000 | K41: =B41+I41-N41 -> -493545.97 | M41: =[5]TONT20000DEC2016!R42+[5]TONT20000JANV2017!P42+[5]TONT20000FEV2017!P42+[5]TONT20000MARS2017!P42+[5]TONT20000AVRIL2017!P42+[5]TONT20000MAI2017!P42+[5]TONT20000JUIN2017!P42+[5]TONT20000JUIL2017!P42 -> 120000 | N41: =[8]EMPRUNT!$D39 -> 963000
A42: SIME PIERRE | B42: 420000 | C42: =[5]TONT20000DEC2016!$D43 -> 105975 | D42: =+[5]TONT20000DEC2016!$L43+[5]TONT20000JANV2017!$J43+[5]TONT20000FEV2017!$J43+[5]TONT20000MARS2017!$J43+[5]TONT20000AVRIL2017!$J43+[5]TONT20000MAI2017!$J43+[5]TONT20000JUIN2017!$J43+[5]TONT20000JUIL2017!$J43 -> 79000 | E42: =[5]TONT20000DEC2016!$E43+[5]TONT20000JANV2017!$C43+[5]TONT20000FEV2017!$C43+[5]TONT20000MARS2017!$C43+[5]TONT20000AVRIL2017!$C43+[5]TONT20000MAI2017!$C43+[5]TONT20000JUIN2017!$C43+[5]TONT20000JUIL2017!$C43 -> 38409.306 | F42: =+C42+D42+E42 -> 223384.31 | G42: 1200 | H42: 70000 | I42: =F42-G42-H42 -> 152184.31 | J42: =[11]MVTSEPT!$C40 -> 450000 | K42: =B42+I42-N42 -> 484984.31 | M42: =[5]TONT20000DEC2016!R43+[5]TONT20000JANV2017!P43+[5]TONT20000FEV2017!P43+[5]TONT20000MARS2017!P43+[5]TONT20000AVRIL2017!P43+[5]TONT20000MAI2017!P43+[5]TONT20000JUIN2017!P43+[5]TONT20000JUIL2017!P43 -> 12000 | N42: =[8]EMPRUNT!$D40 -> 87200
A43: TAGNE NANGUEN MARTIN | B43: 390000 | C43: =[5]TONT20000DEC2016!$D44 -> 1621 | D43: =+[5]TONT20000DEC2016!$L44+[5]TONT20000JANV2017!$J44+[5]TONT20000FEV2017!$J44+[5]TONT20000MARS2017!$J44+[5]TONT20000AVRIL2017!$J44+[5]TONT20000MAI2017!$J44+[5]TONT20000JUIN2017!$J44+[5]TONT20000JUIL2017!$J44 -> 24000 | E43: =[5]TONT20000DEC2016!$E44+[5]TONT20000JANV2017!$C44+[5]TONT20000FEV2017!$C44+[5]TONT20000MARS2017!$C44+[5]TONT20000AVRIL2017!$C44+[5]TONT20000MAI2017!$C44+[5]TONT20000JUIN2017!$C44+[5]TONT20000JUIL2017!$C44 -> 26857.244 | F43: =+C43+D43+E43 -> 52478.244 | G43: 2100 | I43: =F43-G43-H43 -> 50378.244 | J43: =[11]MVTSEPT!$C41+30000 -> 450000 | K43: =B43+I43-N43 -> 440378.24 | M43: =[5]TONT20000DEC2016!R44+[5]TONT20000JANV2017!P44+[5]TONT20000FEV2017!P44+[5]TONT20000MARS2017!P44+[5]TONT20000AVRIL2017!P44+[5]TONT20000MAI2017!P44+[5]TONT20000JUIN2017!P44+[5]TONT20000JUIL2017!P44 -> 0 | N43: =[8]EMPRUNT!$D41 -> 0
A44: TCHOUAMOU JEAN PAUL | B44: 20000 | C44: =[5]TONT20000DEC2016!$D45 -> 14843 | E44: =[5]TONT20000DEC2016!$E45+[5]TONT20000JANV2017!$C45+[5]TONT20000FEV2017!$C45+[5]TONT20000MARS2017!$C45+[5]TONT20000AVRIL2017!$C45+[5]TONT20000MAI2017!$C45+[5]TONT20000JUIN2017!$C45+[5]TONT20000JUIL2017!$C45 -> 3343.2511 | F44: =+C44+D44+E44 -> 18186.251 | G44: 5250 | J44: =[11]MVTSEPT!$C42 -> 50000 | K44: =B44+I44-N44 -> 20000 | M44: =[5]TONT20000DEC2016!R45+[5]TONT20000JANV2017!P45+[5]TONT20000FEV2017!P45+[5]TONT20000MARS2017!P45+[5]TONT20000AVRIL2017!P45+[5]TONT20000MAI2017!P45+[5]TONT20000JUIN2017!P45+[5]TONT20000JUIL2017!P45 -> 0 | N44: =[8]EMPRUNT!$D42 -> 0
A45: TCHOUAMOU MATHIEU | B45: 420000 | C45: =[5]TONT20000DEC2016!$D46 -> 2654 | D45: =+[5]TONT20000DEC2016!$L46+[5]TONT20000JANV2017!$J46+[5]TONT20000FEV2017!$J46+[5]TONT20000MARS2017!$J46+[5]TONT20000AVRIL2017!$J46+[5]TONT20000MAI2017!$J46+[5]TONT20000JUIN2017!$J46+[5]TONT20000JUIL2017!$J46 -> 24000 | E45: =[5]TONT20000DEC2016!$E46+[5]TONT20000JANV2017!$C46+[5]TONT20000FEV2017!$C46+[5]TONT20000MARS2017!$C46+[5]TONT20000AVRIL2017!$C46+[5]TONT20000MAI2017!$C46+[5]TONT20000JUIN2017!$C46+[5]TONT20000JUIL2017!$C46 -> 28902.521 | F45: =+C45+D45+E45 -> 55556.521 | G45: 0 | H45: 8000 | I45: =F45-G45-H45 -> 47556.521 | J45: =[11]MVTSEPT!$C43 -> 450000 | K45: =B45+I45-N45 -> 467556.52 | M45: =[5]TONT20000DEC2016!R46+[5]TONT20000JANV2017!P46+[5]TONT20000FEV2017!P46+[5]TONT20000MARS2017!P46+[5]TONT20000AVRIL2017!P46+[5]TONT20000MAI2017!P46+[5]TONT20000JUIN2017!P46+[5]TONT20000JUIL2017!P46 -> 0 | N45: =[8]EMPRUNT!$D43 -> 0
A46: TCHOUANTE FRANCOIS | B46: 403819 | C46: =[5]TONT20000DEC2016!$D47 -> 25832 | D46: =+[5]TONT20000DEC2016!$L47+[5]TONT20000JANV2017!$J47+[5]TONT20000FEV2017!$J47+[5]TONT20000MARS2017!$J47+[5]TONT20000AVRIL2017!$J47+[5]TONT20000MAI2017!$J47+[5]TONT20000JUIN2017!$J47+[5]TONT20000JUIL2017!$J47 -> 81000 | E46: =[5]TONT20000DEC2016!$E47+[5]TONT20000JANV2017!$C47+[5]TONT20000FEV2017!$C47+[5]TONT20000MARS2017!$C47+[5]TONT20000AVRIL2017!$C47+[5]TONT20000MAI2017!$C47+[5]TONT20000JUIN2017!$C47+[5]TONT20000JUIL2017!$C47 -> 32627.904 | F46: =+C46+D46+E46 -> 139459.9 | G46: 1000 | H46: 23000 | I46: =F46-G46-H46 -> 115459.9 | J46: =[11]MVTSEPT!$C44+16181 -> 450000 | K46: =B46+I46-N46 -> -332221.1 | M46: =[5]TONT20000DEC2016!R47+[5]TONT20000JANV2017!P47+[5]TONT20000FEV2017!P47+[5]TONT20000MARS2017!P47+[5]TONT20000AVRIL2017!P47+[5]TONT20000MAI2017!P47+[5]TONT20000JUIN2017!P47+[5]TONT20000JUIL2017!P47 -> 84000 | N46: =[8]EMPRUNT!$D44 -> 851500
A47: TCHOUTOU NANA CLAUDE | B47: 0 | D47: =+[5]TONT20000DEC2016!$L48+[5]TONT20000JANV2017!$J48+[5]TONT20000FEV2017!$J48+[5]TONT20000MARS2017!$J48+[5]TONT20000AVRIL2017!$J48+[5]TONT20000MAI2017!$J48+[5]TONT20000JUIN2017!$J48+[5]TONT20000JUIL2017!$J48 -> 6000 | E47: =[5]TONT20000DEC2016!$E48+[5]TONT20000JANV2017!$C48+[5]TONT20000FEV2017!$C48+[5]TONT20000MARS2017!$C48+[5]TONT20000AVRIL2017!$C48+[5]TONT20000MAI2017!$C48+[5]TONT20000JUIN2017!$C48+[5]TONT20000JUIL2017!$C48 -> 356.34917 | F47: =+C47+D47+E47 -> 6356.3492 | G47: 0 | J47: =[11]MVTSEPT!$C45 -> 30000 | K47: =B47+I47-N47 -> 0 | M47: =[5]TONT20000DEC2016!R48+[5]TONT20000JANV2017!P48+[5]TONT20000FEV2017!P48+[5]TONT20000MARS2017!P48+[5]TONT20000AVRIL2017!P48+[5]TONT20000MAI2017!P48+[5]TONT20000JUIN2017!P48+[5]TONT20000JUIL2017!P48 -> 0
A48: TIEYAM ERNEST | B48: 420000 | C48: =[5]TONT20000DEC2016!$D49 -> 2593 | D48: =+[5]TONT20000DEC2016!$L49+[5]TONT20000JANV2017!$J49+[5]TONT20000FEV2017!$J49+[5]TONT20000MARS2017!$J49+[5]TONT20000AVRIL2017!$J49+[5]TONT20000MAI2017!$J49+[5]TONT20000JUIN2017!$J49+[5]TONT20000JUIL2017!$J49 -> 58000 | E48: =[5]TONT20000DEC2016!$E49+[5]TONT20000JANV2017!$C49+[5]TONT20000FEV2017!$C49+[5]TONT20000MARS2017!$C49+[5]TONT20000AVRIL2017!$C49+[5]TONT20000MAI2017!$C49+[5]TONT20000JUIN2017!$C49+[5]TONT20000JUIL2017!$C49 -> 30495.865 | F48: =+C48+D48+E48 -> 91088.865 | G48: 27000 | I48: =F48-G48-H48 -> 64088.865 | J48: =[11]MVTSEPT!$C46 -> 450000 | K48: =B48+I48-N48 -> -579911.14 | M48: =[5]TONT20000DEC2016!R49+[5]TONT20000JANV2017!P49+[5]TONT20000FEV2017!P49+[5]TONT20000MARS2017!P49+[5]TONT20000AVRIL2017!P49+[5]TONT20000MAI2017!P49+[5]TONT20000JUIN2017!P49+[5]TONT20000JUIL2017!P49 -> 120000 | N48: =[8]EMPRUNT!$D46 -> 1064000
A49: TUGMA PIERRE LOTI | B49: 420000 | C49: =[5]TONT20000DEC2016!$D50 -> 2503 | D49: =+[5]TONT20000DEC2016!$L50+[5]TONT20000JANV2017!$J50+[5]TONT20000FEV2017!$J50+[5]TONT20000MARS2017!$J50+[5]TONT20000AVRIL2017!$J50+[5]TONT20000MAI2017!$J50+[5]TONT20000JUIN2017!$J50+[5]TONT20000JUIL2017!$J50 -> 21000 | E49: =[5]TONT20000DEC2016!$E50+[5]TONT20000JANV2017!$C50+[5]TONT20000FEV2017!$C50+[5]TONT20000MARS2017!$C50+[5]TONT20000AVRIL2017!$C50+[5]TONT20000MAI2017!$C50+[5]TONT20000JUIN2017!$C50+[5]TONT20000JUIL2017!$C50 -> 28892.569 | F49: =+C49+D49+E49 -> 52395.569 | I49: =F49-G49-H49 -> 52395.569 | J49: =[11]MVTSEPT!$C47 -> 450000 | K49: =B49+I49-N49 -> -647604.43 | M49: =[5]TONT20000DEC2016!R50+[5]TONT20000JANV2017!P50+[5]TONT20000FEV2017!P50+[5]TONT20000MARS2017!P50+[5]TONT20000AVRIL2017!P50+[5]TONT20000MAI2017!P50+[5]TONT20000JUIN2017!P50+[5]TONT20000JUIL2017!P50 -> 120000 | N49: =[8]EMPRUNT!$D47 -> 1120000
A50: YEPMOU JEAN JACQUES | B50: 420000 | C50: =[5]TONT20000DEC2016!$D51 -> 393982 | D50: =+[5]TONT20000DEC2016!$L51+[5]TONT20000JANV2017!$J51+[5]TONT20000FEV2017!$J51+[5]TONT20000MARS2017!$J51+[5]TONT20000AVRIL2017!$J51+[5]TONT20000MAI2017!$J51+[5]TONT20000JUIN2017!$J51+[5]TONT20000JUIL2017!$J51 -> 24000 | E50: =[5]TONT20000DEC2016!$E51+[5]TONT20000JANV2017!$C51+[5]TONT20000FEV2017!$C51+[5]TONT20000MARS2017!$C51+[5]TONT20000AVRIL2017!$C51+[5]TONT20000MAI2017!$C51+[5]TONT20000JUIN2017!$C51+[5]TONT20000JUIL2017!$C51 -> 54693.584 | F50: =+C50+D50+E50 -> 472675.58 | G50: 12100 | I50: =F50-G50-H50 -> 460575.58 | J50: =[11]MVTSEPT!$C48 -> 450000 | K50: =B50+I50-N50 -> 880575.58 | M50: =[5]TONT20000DEC2016!R51+[5]TONT20000JANV2017!P51+[5]TONT20000FEV2017!P51+[5]TONT20000MARS2017!P51+[5]TONT20000AVRIL2017!P51+[5]TONT20000MAI2017!P51+[5]TONT20000JUIN2017!P51+[5]TONT20000JUIL2017!P51 -> 0 | N50: =[8]EMPRUNT!$D48 -> 0
A51: YOUMBI EMMANUEL | B51: 420000 | C51: =[5]TONT20000DEC2016!$D52 -> 883628 | D51: =+[5]TONT20000DEC2016!$L52+[5]TONT20000JANV2017!$J52+[5]TONT20000FEV2017!$J52+[5]TONT20000MARS2017!$J52+[5]TONT20000AVRIL2017!$J52+[5]TONT20000MAI2017!$J52+[5]TONT20000JUIN2017!$J52+[5]TONT20000JUIL2017!$J52 -> 224000 | E51: =[5]TONT20000DEC2016!$E52+[5]TONT20000JANV2017!$C52+[5]TONT20000FEV2017!$C52+[5]TONT20000MARS2017!$C52+[5]TONT20000AVRIL2017!$C52+[5]TONT20000MAI2017!$C52+[5]TONT20000JUIN2017!$C52+[5]TONT20000JUIL2017!$C52 -> 100024.82 | F51: =+C51+D51+E51 -> 1207652.8 | G51: 2000 | I51: =F51-G51-H51 -> 1205652.8 | J51: =[11]MVTSEPT!$C49 -> 450000 | K51: =B51+I51-N51 -> 1625652.8 | M51: =[5]TONT20000DEC2016!R52+[5]TONT20000JANV2017!P52+[5]TONT20000FEV2017!P52+[5]TONT20000MARS2017!P52+[5]TONT20000AVRIL2017!P52+[5]TONT20000MAI2017!P52+[5]TONT20000JUIN2017!P52+[5]TONT20000JUIL2017!P52 -> 0 | N51: =[8]EMPRUNT!$D49 -> 0
A52: MBOGNING TUGMA GUY | F52: =+C52+D52+E52 -> 0 | J52: 450000
A53: DJOMO DOMO | F53: =+C53+D53+E53 -> 0
A54: DOMOU FABIEN | F54: =+C54+D54+E54 -> 0 | J54: 450000
B56: =SUM(B4:B54) -> 16310819 | C56: =SUM(C4:C54) -> 3525807 | D56: =SUM(D4:D54) -> 3564500 | E56: =SUM(E4:E54) -> 1469000 | F56: =SUM(F4:F54) -> 8559307 | G56: =SUM(G4:G54) -> 295100 | H56: =SUM(H4:H54) -> 1513900 | I56: =SUM(I4:I54) -> 6174113.9 | ... N56: =SUM(N4:N54) -> 23056400

Sheet INVENT2017_2018
B1: CALCUL INTERET EPARGNE AOUT 2017- JUILLET 2018
A3: NOM ET PRENOM | B3: FONDS CAISSE | C3: RELIQUAT | D3: EPARGNE | E3: INTERETEPARGNE | F3: TOTAL AVOIR | G3: SANCTION | H3: AVANCE | I3: COMPLEMENT MUTUELLE | J3: COMPLEMENT FONDS | K3: TOTAL A PERCEVOIR | L3: NOUVEAU FONDS | M3: SOLDE TOUT COMPTE | N3: AVANCE | O3: EMPRUNT 2018 | P3: INTERET EMPRUNT | Q3: REPORT EMPRUNT 2017 | R3: REMBOURSEMENT 2017-2018 | S3: EMPRUNT EN COURS 2018 | T3: PENALITE | U3: EMPRUNT EN COURS 2018 PENALITE | V3: DATE REMBOURSEMENT | X3: OBSERVATION | Z3: PENALITE | AA3: REMBOURSEMENT
A4: ASELBY | C4: =+INVENT2016_2017!I4 -> 0 | D4: =[11]MVTAOUT!$H5+[11]MVTSEPT!$I5+[11]MVTOCT!$G5+[11]MVTNOV!$G5+[11]MVTDEC!$G5+[11]MVTJANV!$G5+[11]MVTFEV!$G5+[11]MVTMARS!$G5+[11]MVTAVRIL!$G5+[11]MVTMAI!$G5+[11]MVTJUIN!$G5+[11]MVTJUIL!$G5+[11]MVTAOUT2018!$G5 -> 0 | E4: =+[11]MVTAOUT!$D5+[11]MVTSEPT!$E5+[11]MVTOCT!$C5+[11]MVTNOV!$C5+[11]MVTDEC!$C5+[11]MVTJANV!$C5+[11]MVTFEV!$C5+[11]MVTMARS!$C5+[11]MVTAVRIL!$C5+[11]MVTMAI!$C5+[11]MVTJUIN!$C5+[11]MVTJUIL!$C5 -> 15580.723 | F4: =+C4+D4+E4 -> 15580.723 | K4: =F4-G4-H4-I4-J4 -> 15580.723 | M4: =K4+L4 -> 15580.723 | O4: =[11]MVTAOUT!O5+[11]MVTSEPT!P5+[11]MVTOCT!N5+[11]MVTNOV!N5+[11]MVTDEC!N5+[11]MVTJANV!N5+[11]MVTFEV!N5+[11]MVTMARS!N5+[11]MVTAVRIL!N5+[11]MVTMAI!N5+[11]MVTJUIN!N5+[11]MVTJUIL!N5 -> 0 | P4: =[11]MVTAOUT!P5+[11]MVTSEPT!Q5+[11]MVTOCT!O5+[11]MVTNOV!O5+[11]MVTDEC!O5+[11]MVTJANV!O5+[11]MVTFEV!O5+[11]MVTMARS!O5+[11]MVTAVRIL!O5+[11]MVTMAI!O5+[11]MVTJUIN!O5+[11]MVTJUIL!O5 -> 0 | Q4: =+INVENT2016_2017!N4 -> 0 | R4: =[11]MVTAOUT!$Q5+[11]MVTSEPT!$R5+[11]MVTOCT!$P5+[11]MVTNOV!$P5+[11]MVTDEC!$P5+[11]MVTJANV!$P5+[11]MVTFEV!$P5+[11]MVTMARS!$P5+[11]MVTAVRIL!$P5+[11]MVTMAI!$P5+[11]MVTJUIN!$P5+[11]MVTJUIL!$P5+[11]MVTAOUT2018!$P$5 -> 0
A5: BAKOP ACHILLE | B5: =+INVENT2016_2017!J5 -> 450000 | C5: =+INVENT2016_2017!I5 -> 0 | D5: =[11]MVTAOUT!$H6+[11]MVTSEPT!$I6+[11]MVTOCT!$G6+[11]MVTNOV!$G6+[11]MVTDEC!$G6+[11]MVTJANV!$G6+[11]MVTFEV!$G6+[11]MVTMARS!$G6+[11]MVTAVRIL!$G6+[11]MVTMAI!$G6+[11]MVTJUIN!$G6+[11]MVTJUIL!$G6+[11]MVTAOUT2018!$G6 -> 68000 | E5: =+[11]MVTAOUT!$D6+[11]MVTSEPT!$E6+[11]MVTOCT!$C6+[11]MVTNOV!$C6+[11]MVTDEC!$C6+[11]MVTJANV!$C6+[11]MVTFEV!$C6+[11]MVTMARS!$C6+[11]MVTAVRIL!$C6+[11]MVTMAI!$C6+[11]MVTJUIN!$C6+[11]MVTJUIL!$C6 -> 19643.082 | F5: =+C5+D5+E5 -> 87643.082 | I5: 25000 | J5: 30000 | K5: =F5-G5-H5-I5-J5 -> 32643.082 | L5: =B5+J5 -> 480000 | M5: =K5+L5 -> 512643.08 | O5: =[11]MVTAOUT!O6+[11]MVTSEPT!P6+[11]MVTOCT!N6+[11]MVTNOV!N6+[11]MVTDEC!N6+[11]MVTJANV!N6+[11]MVTFEV!N6+[11]MVTMARS!N6+[11]MVTAVRIL!N6+[11]MVTMAI!N6+[11]MVTJUIN!N6+[11]MVTJUIL!N6 -> 0 | P5: =[11]MVTAOUT!P6+[11]MVTSEPT!Q6+[11]MVTOCT!O6+[11]MVTNOV!O6+[11]MVTDEC!O6+[11]MVTJANV!O6+[11]MVTFEV!O6+[11]MVTMARS!O6+[11]MVTAVRIL!O6+[11]MVTMAI!O6+[11]MVTJUIN!O6+[11]MVTJUIL!O6 -> 0 | Q5: =+INVENT2016_2017!N5 -> 588000 | R5: =[11]MVTAOUT!$Q6+[11]MVTSEPT!$R6+[11]MVTOCT!$P6+[11]MVTNOV!$P6+[11]MVTDEC!$P6+[11]MVTJANV!$P6+[11]MVTFEV!$P6+[11]MVTMARS!$P6+[11]MVTAVRIL!$P6+[11]MVTMAI!$P6+[11]MVTJUIN!$P6+[11]MVTJUIL!$P6+[11]MVTAOUT2018!$P$6 -> 0 | S5: 588000 | T5: 88000 | U5: =+S5 -> 588000 | V5: 42904 | Z5: 88000 | AA5: =S5 -> 588000
A6: BOUTCHOUANG WILLIAM | B6: =+INVENT2016_2017!J6 -> 450000 | C6: =+INVENT2016_2017!I6 -> 47526.871 | D6: =[11]MVTAOUT!$H7+[11]MVTSEPT!$I7+[11]MVTOCT!$G7+[11]MVTNOV!$G7+[11]MVTDEC!$G7+[11]MVTJANV!$G7+[11]MVTFEV!$G7+[11]MVTMARS!$G7+[11]MVTAVRIL!$G7+[11]MVTMAI!$G7+[11]MVTJUIN!$G7+[11]MVTJUIL!$G7+[11]MVTAOUT2018!$G7 -> 39000 | E6: =+[11]MVTAOUT!$D7+[11]MVTSEPT!$E7+[11]MVTOCT!$C7+[11]MVTNOV!$C7+[11]MVTDEC!$C7+[11]MVTJANV!$C7+[11]MVTFEV!$C7+[11]MVTMARS!$C7+[11]MVTAVRIL!$C7+[11]MVTMAI!$C7+[11]MVTJUIN!$C7+[11]MVTJUIL!$C7 -> 19804.409 | F6: =+C6+D6+E6 -> 106331.28 | I6: 25000 | J6: 30000 | K6: =F6-G6-H6-I6-J6 -> 51331.28 | L6: =B6+J6 -> 480000 | M6: =K6+L6 -> 531331.28 | O6: =[11]MVTAOUT!O7+[11]MVTSEPT!P7+[11]MVTOCT!N7+[11]MVTNOV!N7+[11]MVTDEC!N7+[11]MVTJANV!N7+[11]MVTFEV!N7+[11]MVTMARS!N7+[11]MVTAVRIL!N7+[11]MVTMAI!N7+[11]MVTJUIN!N7+[11]MVTJUIL!N7 -> 0 | P6: =[11]MVTAOUT!P7+[11]MVTSEPT!Q7+[11]MVTOCT!O7+[11]MVTNOV!O7+[11]MVTDEC!O7+[11]MVTJANV!O7+[11]MVTFEV!O7+[11]MVTMARS!O7+[11]MVTAVRIL!O7+[11]MVTMAI!O7+[11]MVTJUIN!O7+[11]MVTJUIL!O7 -> 0 | Q6: =+INVENT2016_2017!N6 -> 784000 | R6: =[11]MVTAOUT!$Q7+[11]MVTSEPT!$R7+[11]MVTOCT!$P7+[11]MVTNOV!$P7+[11]MVTDEC!$P7+[11]MVTJANV!$P7+[11]MVTFEV!$P7+[11]MVTMARS!$P7+[11]MVTAVRIL!$P7+[11]MVTMAI!$P7+[11]MVTJUIN!$P7+[11]MVTJUIL!$P7+[11]MVTAOUT2018!$P$7 -> 823200 | S6: 0 | X6: OK
A7: CHINGUE FABRICE | B7: =+INVENT2016_2017!J7 -> 450000 | C7: =+INVENT2016_2017!I7 -> 39888.74 | D7: =[11]MVTAOUT!$H8+[11]MVTSEPT!$I8+[11]MVTOCT!$G8+[11]MVTNOV!$G8+[11]MVTDEC!$G8+[11]MVTJANV!$G8+[11]MVTFEV!$G8+[11]MVTMARS!$G8+[11]MVTAVRIL!$G8+[11]MVTMAI!$G8+[11]MVTJUIN!$G8+[11]MVTJUIL!$G8+[11]MVTAOUT2018!$G8 -> 39000 | E7: =+[11]MVTAOUT!$D8+[11]MVTSEPT!$E8+[11]MVTOCT!$C8+[11]MVTNOV!$C8+[11]MVTDEC!$C8+[11]MVTJANV!$C8+[11]MVTFEV!$C8+[11]MVTMARS!$C8+[11]MVTAVRIL!$C8+[11]MVTMAI!$C8+[11]MVTJUIN!$C8+[11]MVTJUIL!$C8 -> 19815.212 | F7: =+C7+D7+E7 -> 98703.952 | I7: 25000 | J7: 30000 | K7: =F7-G7-H7-I7-J7 -> 43703.952 | L7: =B7+J7 -> 480000 | M7: =K7+L7 -> 523703.95 | O7: =[11]MVTAOUT!O8+[11]MVTSEPT!P8+[11]MVTOCT!N8+[11]MVTNOV!N8+[11]MVTDEC!N8+[11]MVTJANV!N8+[11]MVTFEV!N8+[11]MVTMARS!N8+[11]MVTAVRIL!N8+[11]MVTMAI!N8+[11]MVTJUIN!N8+[11]MVTJUIL!N8 -> 0 | P7: =[11]MVTAOUT!P8+[11]MVTSEPT!Q8+[11]MVTOCT!O8+[11]MVTNOV!O8+[11]MVTDEC!O8+[11]MVTJANV!O8+[11]MVTFEV!O8+[11]MVTMARS!O8+[11]MVTAVRIL!O8+[11]MVTMAI!O8+[11]MVTJUIN!O8+[11]MVTJUIL!O8 -> 0 | Q7: =+INVENT2016_2017!N7 -> 1293600 | R7: =[11]MVTAOUT!$Q8+[11]MVTSEPT!$R8+[11]MVTOCT!$P8+[11]MVTNOV!$P8+[11]MVTDEC!$P8+[11]MVTJANV!$P8+[11]MVTFEV!$P8+[11]MVTMARS!$P8+[11]MVTAVRIL!$P8+[11]MVTMAI!$P8+[11]MVTJUIN!$P8+[11]MVTJUIL!$P8+[11]MVTAOUT2018!$P$8 -> 1293500
A8: DJOMO JEAN PAUL | B8: =+INVENT2016_2017!J8 -> 450000 | C8: =+INVENT2016_2017!I8 -> 23224.098 | D8: =[11]MVTAOUT!$H9+[11]MVTSEPT!$I9+[11]MVTOCT!$G9+[11]MVTNOV!$G9+[11]MVTDEC!$G9+[11]MVTJANV!$G9+[11]MVTFEV!$G9+[11]MVTMARS!$G9+[11]MVTAVRIL!$G9+[11]MVTMAI!$G9+[11]MVTJUIN!$G9+[11]MVTJUIL!$G9+[11]MVTAOUT2018!$G9 -> 39000 | E8: =+[11]MVTAOUT!$D9+[11]MVTSEPT!$E9+[11]MVTOCT!$C9+[11]MVTNOV!$C9+[11]MVTDEC!$C9+[11]MVTJANV!$C9+[11]MVTFEV!$C9+[11]MVTMARS!$C9+[11]MVTAVRIL!$C9+[11]MVTMAI!$C9+[11]MVTJUIN!$C9+[11]MVTJUIL!$C9 -> 19830.392 | F8: =+C8+D8+E8 -> 82054.49 | I8: 25000 | J8: 30000 | K8: =F8-G8-H8-I8-J8 -> 27054.49 | L8: =B8+J8 -> 480000 | M8: =K8+L8 -> 507054.49 | O8: =[11]MVTAOUT!O9+[11]MVTSEPT!P9+[11]MVTOCT!N9+[11]MVTNOV!N9+[11]MVTDEC!N9+[11]MVTJANV!N9+[11]MVTFEV!N9+[11]MVTMARS!N9+[11]MVTAVRIL!N9+[11]MVTMAI!N9+[11]MVTJUIN!N9+[11]MVTJUIL!N9 -> 693000 | P8: =[11]MVTAOUT!P9+[11]MVTSEPT!Q9+[11]MVTOCT!O9+[11]MVTNOV!O9+[11]MVTDEC!O9+[11]MVTJANV!O9+[11]MVTFEV!O9+[11]MVTMARS!O9+[11]MVTAVRIL!O9+[11]MVTMAI!O9+[11]MVTJUIN!O9+[11]MVTJUIL!O9 -> 49000 | Q8: =+INVENT2016_2017!N8 -> 1017000 | R8: =[11]MVTAOUT!$Q9+[11]MVTSEPT!$R9+[11]MVTOCT!$P9+[11]MVTNOV!$P9+[11]MVTDEC!$P9+[11]MVTJANV!$P9+[11]MVTFEV!$P9+[11]MVTMARS!$P9+[11]MVTAVRIL!$P9+[11]MVTMAI!$P9+[11]MVTJUIN!$P9+[11]MVTJUIL!$P9+[11]MVTAOUT2018!$P$9 -> 1040000 | S8: 693000 | T8: =S8*5/100 -> 34650 | U8: =+S8+T8 -> 727650 | V8: 43121 | X8: OK | Z8: =+AA8-S8 -> 34650 | AA8: =S8+(S8*5/100) -> 727650
A9: DJOUKWE NANGUEN GUY BLAISE | B9: =+INVENT2016_2017!J9 -> 450000 | C9: =+INVENT2016_2017!I9 -> 69006.04 | D9: =[11]MVTAOUT!$H10+[11]MVTSEPT!$I10+[11]MVTOCT!$G10+[11]MVTNOV!$G10+[11]MVTDEC!$G10+[11]MVTJANV!$G10+[11]MVTFEV!$G10+[11]MVTMARS!$G10+[11]MVTAVRIL!$G10+[11]MVTMAI!$G10+[11]MVTJUIN!$G10+[11]MVTJUIL!$G10+[11]MVTAOUT2018!$G10 -> 51000 | E9: =+[11]MVTAOUT!$D10+[11]MVTSEPT!$E10+[11]MVTOCT!$C10+[11]MVTNOV!$C10+[11]MVTDEC!$C10+[11]MVTJANV!$C10+[11]MVTFEV!$C10+[11]MVTMARS!$C10+[11]MVTAVRIL!$C10+[11]MVTMAI!$C10+[11]MVTJUIN!$C10+[11]MVTJUIL!$C10 -> 20026.542 | F9: =+C9+D9+E9 -> 140032.58 | I9: 25000 | J9: 30000 | K9: =F9-G9-H9-I9-J9 -> 85032.582 | L9: =B9+J9 -> 480000 | M9: =K9+L9 -> 565032.58 | O9: =[11]MVTAOUT!O10+[11]MVTSEPT!P10+[11]MVTOCT!N10+[11]MVTNOV!N10+[11]MVTDEC!N10+[11]MVTJANV!N10+[11]MVTFEV!N10+[11]MVTMARS!N10+[11]MVTAVRIL!N10+[11]MVTMAI!N10+[11]MVTJUIN!N10+[11]MVTJUIL!N10 -> 0 | P9: =[11]MVTAOUT!P10+[11]MVTSEPT!Q10+[11]MVTOCT!O10+[11]MVTNOV!O10+[11]MVTDEC!O10+[11]MVTJANV!O10+[11]MVTFEV!O10+[11]MVTMARS!O10+[11]MVTAVRIL!O10+[11]MVTMAI!O10+[11]MVTJUIN!O10+[11]MVTJUIL!O10 -> 0 | Q9: =+INVENT2016_2017!N9 -> 140000 | R9: =[11]MVTAOUT!$Q10+[11]MVTSEPT!$R10+[11]MVTOCT!$P10+[11]MVTNOV!$P10+[11]MVTDEC!$P10+[11]MVTJANV!$P10+[11]MVTFEV!$P10+[11]MVTMARS!$P10+[11]MVTAVRIL!$P10+[11]MVTMAI!$P10+[11]MVTJUIN!$P10+[11]MVTJUIL!$P10+[11]MVTAOUT2018!$P$10 -> 210000
A11: DJOUNKEP SAMUEL | B11: =+INVENT2016_2017!J11 -> 450000 | C11: =+INVENT2016_2017!I11 -> 730153.83 | D11: =[11]MVTAOUT!$H11+[11]MVTSEPT!$I11+[11]MVTOCT!$G11+[11]MVTNOV!$G11+[11]MVTDEC!$G11+[11]MVTJANV!$G11+[11]MVTFEV!$G11+[11]MVTMARS!$G11+[11]MVTAVRIL!$G11+[11]MVTMAI!$G11+[11]MVTJUIN!$G11+[11]MVTJUIL!$G11+[11]MVTAOUT2018!$G11 -> 233000 | E11: =+[11]MVTAOUT!$D11+[11]MVTSEPT!$E11+[11]MVTOCT!$C11+[11]MVTNOV!$C11+[11]MVTDEC!$C11+[11]MVTJANV!$C11+[11]MVTFEV!$C11+[11]MVTMARS!$C11+[11]MVTAVRIL!$C11+[11]MVTMAI!$C11+[11]MVTJUIN!$C11+[11]MVTJUIL!$C11 -> 22119.98 | F11: =+C11+D11+E11 -> 985273.81 | K11: =F11-G11-H11-I11-J11 -> 985273.81 | L11: =B11+J11 -> 450000 | M11: =K11+L11 -> 1435273.8 | O11: =[11]MVTAOUT!O11+[11]MVTSEPT!P11+[11]MVTOCT!N11+[11]MVTNOV!N11+[11]MVTDEC!N11+[11]MVTJANV!N11+[11]MVTFEV!N11+[11]MVTMARS!N11+[11]MVTAVRIL!N11+[11]MVTMAI!N11+[11]MVTJUIN!N11+[11]MVTJUIL!N11 -> 0 | P11: =[11]MVTAOUT!P11+[11]MVTSEPT!Q11+[11]MVTOCT!O11+[11]MVTNOV!O11+[11]MVTDEC!O11+[11]MVTJANV!O11+[11]MVTFEV!O11+[11]MVTMARS!O11+[11]MVTAVRIL!O11+[11]MVTMAI!O11+[11]MVTJUIN!O11+[11]MVTJUIL!O11 -> 0 | Q11: =+INVENT2016_2017!N11 -> 1120000 | R11: =[11]MVTAOUT!$Q11+[11]MVTSEPT!$R11+[11]MVTOCT!$P11+[11]MVTNOV!$P11+[11]MVTDEC!$P11+[11]MVTJANV!$P11+[11]MVTFEV!$P11+[11]MVTMARS!$P11+[11]MVTAVRIL!$P11+[11]MVTMAI!$P11+[11]MVTJUIN!$P11+[11]MVTJUIL!$P11+[11]MVTAOUT2018!$P$11 -> 1100000 | S11: 0 | W11: =Q11-R11 -> 20000 | X11: OK
A12: DJUOMBESSY ANTOINE | B12: =+INVENT2016_2017!J12 -> 450000 | C12: =+INVENT2016_2017!I12 -> 47654.584 | D12: =[11]MVTAOUT!$H12+[11]MVTSEPT!$I12+[11]MVTOCT!$G12+[11]MVTNOV!$G12+[11]MVTDEC!$G12+[11]MVTJANV!$G12+[11]MVTFEV!$G12+[11]MVTMARS!$G12+[11]MVTAVRIL!$G12+[11]MVTMAI!$G12+[11]MVTJUIN!$G12+[11]MVTJUIL!$G12+[11]MVTAOUT2018!$G12 -> 39000 | E12: =+[11]MVTAOUT!$D12+[11]MVTSEPT!$E12+[11]MVTOCT!$C12+[11]MVTNOV!$C12+[11]MVTDEC!$C12+[11]MVTJANV!$C12+[11]MVTFEV!$C12+[11]MVTMARS!$C12+[11]MVTAVRIL!$C12+[11]MVTMAI!$C12+[11]MVTJUIN!$C12+[11]MVTJUIL!$C12 -> 19804.498 | F12: =+C12+D12+E12 -> 106459.08 | I12: 25000 | J12: 30000 | K12: =F12-G12-H12-I12-J12 -> 51459.082 | L12: =B12+J12 -> 480000 | M12: =K12+L12 -> 531459.08 | O12: =[11]MVTAOUT!O12+[11]MVTSEPT!P12+[11]MVTOCT!N12+[11]MVTNOV!N12+[11]MVTDEC!N12+[11]MVTJANV!N12+[11]MVTFEV!N12+[11]MVTMARS!N12+[11]MVTAVRIL!N12+[11]MVTMAI!N12+[11]MVTJUIN!N12+[11]MVTJUIL!N12 -> 1000000 | P12: =[11]MVTAOUT!P12+[11]MVTSEPT!Q12+[11]MVTOCT!O12+[11]MVTNOV!O12+[11]MVTDEC!O12+[11]MVTJANV!O12+[11]MVTFEV!O12+[11]MVTMARS!O12+[11]MVTAVRIL!O12+[11]MVTMAI!O12+[11]MVTJUIN!O12+[11]MVTJUIL!O12 -> 40000 | Q12: =+INVENT2016_2017!N12 -> 784000 | R12: =[11]MVTAOUT!$Q12+[11]MVTSEPT!$R12+[11]MVTOCT!$P12+[11]MVTNOV!$P12+[11]MVTDEC!$P12+[11]MVTJANV!$P12+[11]MVTFEV!$P12+[11]MVTMARS!$P12+[11]MVTAVRIL!$P12+[11]MVTMAI!$P12+[11]MVTJUIN!$P12+[11]MVTJUIL!$P12+[11]MVTAOUT2018!$P$12 -> 770000 | S12: 1000000 | T12: =S12*5/100 -> 50000 | U12: =+S12+T12 -> 1050000 | V12: 43205 | W12: =Q12-R12 -> 14000 | X12: OK | Y12: 40000 | Z12: =+AA12-S12 -> 50000 | AA12: =S12+(S12*5/100) -> 1050000
A13: DONHOU DAVID | B13: =+INVENT2016_2017!J13 -> 450000 | C13: =+INVENT2016_2017!I13 -> 110017.95 | D13: =[11]MVTAOUT!$H13+[11]MVTSEPT!$I13+[11]MVTOCT!$G13+[11]MVTNOV!$G13+[11]MVTDEC!$G13+[11]MVTJANV!$G13+[11]MVTFEV!$G13+[11]MVTMARS!$G13+[11]MVTAVRIL!$G13+[11]MVTMAI!$G13+[11]MVTJUIN!$G13+[11]MVTJUIL!$G13+[11]MVTAOUT2018!$G13 -> 39000 | E13: =+[11]MVTAOUT!$D13+[11]MVTSEPT!$E13+[11]MVTOCT!$C13+[11]MVTNOV!$C13+[11]MVTDEC!$C13+[11]MVTJANV!$C13+[11]MVTFEV!$C13+[11]MVTMARS!$C13+[11]MVTAVRIL!$C13+[11]MVTMAI!$C13+[11]MVTJUIN!$C13+[11]MVTJUIL!$C13 -> 19979.185 | F13: =+C13+D13+E13 -> 168997.13 | I13: 25000 | J13: 30000 | K13: =F13-G13-H13-I13-J13 -> 113997.13 | L13: =B13+J13 -> 480000 | M13: =K13+L13 -> 593997.13 | O13: =[11]MVTAOUT!O13+[11]MVTSEPT!P13+[11]MVTOCT!N13+[11]MVTNOV!N13+[11]MVTDEC!N13+[11]MVTJANV!N13+[11]MVTFEV!N13+[11]MVTMARS!N13+[11]MVTAVRIL!N13+[11]MVTMAI!N13+[11]MVTJUIN!N13+[11]MVTJUIL!N13 -> 700000 | P13: =[11]MVTAOUT!P13+[11]MVTSEPT!Q13+[11]MVTOCT!O13+[11]MVTNOV!O13+[11]MVTDEC!O13+[11]MVTJANV!O13+[11]MVTFEV!O13+[11]MVTMARS!O13+[11]MVTAVRIL!O13+[11]MVTMAI!O13+[11]MVTJUIN!O13+[11]MVTJUIL!O13 -> 42000 | Q13: =+INVENT2016_2017!N13 -> 0 | R13: =[11]MVTAOUT!$Q13+[11]MVTSEPT!$R13+[11]MVTOCT!$P13+[11]MVTNOV!$P13+[11]MVTDEC!$P13+[11]MVTJANV!$P13+[11]MVTFEV!$P13+[11]MVTMARS!$P13+[11]MVTAVRIL!$P13+[11]MVTMAI!$P13+[11]MVTJUIN!$P13+[11]MVTJUIL!$P13+[11]MVTAOUT2018!$P$13 -> 0 | S13: 700000 | T13: =S13*5/100 -> 35000 | U13: =+S13+T13 -> 735000 | V13: 43148 | Z13: =+AA13-S13 -> 35000 | AA13: =S13+(S13*5/100) -> 735000
A14: FOTSO THOMAS | B14: =+INVENT2016_2017!J14 -> 450000 | C14: =+INVENT2016_2017!I14 -> 47415.821 | D14: =[11]MVTAOUT!$H14+[11]MVTSEPT!$I14+[11]MVTOCT!$G14+[11]MVTNOV!$G14+[11]MVTDEC!$G14+[11]MVTJANV!$G14+[11]MVTFEV!$G14+[11]MVTMARS!$G14+[11]MVTAVRIL!$G14+[11]MVTMAI!$G14+[11]MVTJUIN!$G14+[11]MVTJUIL!$G14+[11]MVTAOUT2018!$G14 -> 40000 | E14: =+[11]MVTAOUT!$D14+[11]MVTSEPT!$E14+[11]MVTOCT!$C14+[11]MVTNOV!$C14+[11]MVTDEC!$C14+[11]MVTJANV!$C14+[11]MVTFEV!$C14+[11]MVTMARS!$C14+[11]MVTAVRIL!$C14+[11]MVTMAI!$C14+[11]MVTJUIN!$C14+[11]MVTJUIL!$C14 -> 19803.731 | F14: =+C14+D14+E14 -> 107219.55 | I14: 25000 | J14: 30000 | K14: =F14-G14-H14-I14-J14 -> 52219.552 | L14: =B14+J14 -> 480000 | M14: =K14+L14 -> 532219.55 | O14: =[11]MVTAOUT!O14+[11]MVTSEPT!P14+[11]MVTOCT!N14+[11]MVTNOV!N14+[11]MVTDEC!N14+[11]MVTJANV!N14+[11]MVTFEV!N14+[11]MVTMARS!N14+[11]MVTAVRIL!N14+[11]MVTMAI!N14+[11]MVTJUIN!N14+[11]MVTJUIL!N14 -> 600000 | P14: =[11]MVTAOUT!P14+[11]MVTSEPT!Q14+[11]MVTOCT!O14+[11]MVTNOV!O14+[11]MVTDEC!O14+[11]MVTJANV!O14+[11]MVTFEV!O14+[11]MVTMARS!O14+[11]MVTAVRIL!O14+[11]MVTMAI!O14+[11]MVTJUIN!O14+[11]MVTJUIL!O14 -> 66000 | Q14: =+INVENT2016_2017!N14 -> 1293600 | R14: =[11]MVTAOUT!$Q14+[11]MVTSEPT!$R14+[11]MVTOCT!$P14+[11]MVTNOV!$P14+[11]MVTDEC!$P14+[11]MVTJANV!$P14+[11]MVTFEV!$P14+[11]MVTMARS!$P14+[11]MVTAVRIL!$P14+[11]MVTMAI!$P14+[11]MVTJUIN!$P14+[11]MVTJUIL!$P14+[11]MVTAOUT2018!$P$14 -> 1959000 | S14: =666000-666000 -> 0 | V14: 42993 | X14: OK
A15: HENGUE PAUL OMER | B15: =+INVENT2016_2017!J15 -> 450000 | C15: =+INVENT2016_2017!I15 -> 0 | D15: =[11]MVTAOUT!$H15+[11]MVTSEPT!$I15+[11]MVTOCT!$G15+[11]MVTNOV!$G15+[11]MVTDEC!$G15+[11]MVTJANV!$G15+[11]MVTFEV!$G15+[11]MVTMARS!$G15+[11]MVTAVRIL!$G15+[11]MVTMAI!$G15+[11]MVTJUIN!$G15+[11]MVTJUIL!$G15+[11]MVTAOUT2018!$G15 -> 39000 | E15: =+[11]MVTAOUT!$D15+[11]MVTSEPT!$E15+[11]MVTOCT!$C15+[11]MVTNOV!$C15+[11]MVTDEC!$C15+[11]MVTJANV!$C15+[11]MVTFEV!$C15+[11]MVTMARS!$C15+[11]MVTAVRIL!$C15+[11]MVTMAI!$C15+[11]MVTJUIN!$C15+[11]MVTJUIL!$C15 -> 20021.15 | F15: =+C15+D15+E15 -> 59021.15 | I15: 25000 | J15: 30000 | K15: =F15-G15-H15-I15-J15 -> 4021.1496 | L15: =B15+J15 -> 480000 | M15: =K15+L15 -> 484021.15 | O15: =[11]MVTAOUT!O15+[11]MVTSEPT!P15+[11]MVTOCT!N15+[11]MVTNOV!N15+[11]MVTDEC!N15+[11]MVTJANV!N15+[11]MVTFEV!N15+[11]MVTMARS!N15+[11]MVTAVRIL!N15+[11]MVTMAI!N15+[11]MVTJUIN!N15+[11]MVTJUIL!N15 -> 0 | P15: =[11]MVTAOUT!P15+[11]MVTSEPT!Q15+[11]MVTOCT!O15+[11]MVTNOV!O15+[11]MVTDEC!O15+[11]MVTJANV!O15+[11]MVTFEV!O15+[11]MVTMARS!O15+[11]MVTAVRIL!O15+[11]MVTMAI!O15+[11]MVTJUIN!O15+[11]MVTJUIL!O15 -> 0 | Q15: =+INVENT2016_2017!N15 -> 0 | R15: =[11]MVTAOUT!$Q15+[11]MVTSEPT!$R15+[11]MVTOCT!$P15+[11]MVTNOV!$P15+[11]MVTDEC!$P15+[11]MVTJANV!$P15+[11]MVTFEV!$P15+[11]MVTMARS!$P15+[11]MVTAVRIL!$P15+[11]MVTMAI!$P15+[11]MVTJUIN!$P15+[11]MVTJUIL!$P15+[11]MVTAOUT2018!$P$15 -> 0
A16: HODIEP JULES | B16: 80000 | C16: =+INVENT2016_2017!I16 -> 0 | D16: =[11]MVTAOUT!$H16+[11]MVTSEPT!$I16+[11]MVTOCT!$G16+[11]MVTNOV!$G16+[11]MVTDEC!$G16+[11]MVTJANV!$G16+[11]MVTFEV!$G16+[11]MVTMARS!$G16+[11]MVTAVRIL!$G16+[11]MVTMAI!$G16+[11]MVTJUIN!$G16+[11]MVTJUIL!$G16+[11]MVTAOUT2018!$G16 -> 0 | E16: =+[11]MVTAOUT!$D16+[11]MVTSEPT!$E16+[11]MVTOCT!$C16+[11]MVTNOV!$C16+[11]MVTDEC!$C16+[11]MVTJANV!$C16+[11]MVTFEV!$C16+[11]MVTMARS!$C16+[11]MVTAVRIL!$C16+[11]MVTMAI!$C16+[11]MVTJUIN!$C16+[11]MVTJUIL!$C16 -> 3334.7558 | F16: =+C16+D16+E16 -> 3334.7558 | I16: 6848 | J16: 0 | K16: =F16-G16-H16-I16-J16 -> -3513.2442 | L16: 80000 | M16: =K16+L16 -> 76486.756 | O16: =[11]MVTAOUT!O16+[11]MVTSEPT!P16+[11]MVTOCT!N16+[11]MVTNOV!N16+[11]MVTDEC!N16+[11]MVTJANV!N16+[11]MVTFEV!N16+[11]MVTMARS!N16+[11]MVTAVRIL!N16+[11]MVTMAI!N16+[11]MVTJUIN!N16+[11]MVTJUIL!N16 -> 0 | P16: =[11]MVTAOUT!P16+[11]MVTSEPT!Q16+[11]MVTOCT!O16+[11]MVTNOV!O16+[11]MVTDEC!O16+[11]MVTJANV!O16+[11]MVTFEV!O16+[11]MVTMARS!O16+[11]MVTAVRIL!O16+[11]MVTMAI!O16+[11]MVTJUIN!O16+[11]MVTJUIL!O16 -> 0 | Q16: =+INVENT2016_2017!N16 -> 0 | R16: =[11]MVTAOUT!$Q16+[11]MVTSEPT!$R16+[11]MVTOCT!$P16+[11]MVTNOV!$P16+[11]MVTDEC!$P16+[11]MVTJANV!$P16+[11]MVTFEV!$P16+[11]MVTMARS!$P16+[11]MVTAVRIL!$P16+[11]MVTMAI!$P16+[11]MVTJUIN!$P16+[11]MVTJUIL!$P16+[11]MVTAOUT2018!$P$16 -> 0
A17: HOTCHO BENJAMIN | B17: =+INVENT2016_2017!J17 -> 450000 | C17: =+INVENT2016_2017!I17 -> 82839.28 | D17: =[11]MVTAOUT!$H17+[11]MVTSEPT!$I17+[11]MVTOCT!$G17+[11]MVTNOV!$G17+[11]MVTDEC!$G17+[11]MVTJANV!$G17+[11]MVTFEV!$G17+[11]MVTMARS!$G17+[11]MVTAVRIL!$G17+[11]MVTMAI!$G17+[11]MVTJUIN!$G17+[11]MVTJUIL!$G17+[11]MVTAOUT2018!$G17 -> 54000 | E17: =+[11]MVTAOUT!$D17+[11]MVTSEPT!$E17+[11]MVTOCT!$C17+[11]MVTNOV!$C17+[11]MVTDEC!$C17+[11]MVTJANV!$C17+[11]MVTFEV!$C17+[11]MVTMARS!$C17+[11]MVTAVRIL!$C17+[11]MVTMAI!$C17+[11]MVTJUIN!$C17+[11]MVTJUIL!$C17 -> 20317.163 | F17: =+C17+D17+E17 -> 157156.44 | I17: 25000 | J17: 30000 | K17: =F17-G17-H17-I17-J17 -> 102156.44 | L17: =B17+J17 -> 480000 | M17: =K17+L17 -> 582156.44 | O17: =[11]MVTAOUT!O17+[11]MVTSEPT!P17+[11]MVTOCT!N17+[11]MVTNOV!N17+[11]MVTDEC!N17+[11]MVTJANV!N17+[11]MVTFEV!N17+[11]MVTMARS!N17+[11]MVTAVRIL!N17+[11]MVTMAI!N17+[11]MVTJUIN!N17+[11]MVTJUIL!N17 -> 0 | P17: =[11]MVTAOUT!P17+[11]MVTSEPT!Q17+[11]MVTOCT!O17+[11]MVTNOV!O17+[11]MVTDEC!O17+[11]MVTJANV!O17+[11]MVTFEV!O17+[11]MVTMARS!O17+[11]MVTAVRIL!O17+[11]MVTMAI!O17+[11]MVTJUIN!O17+[11]MVTJUIL!O17 -> 0 | Q17: =+INVENT2016_2017!N17 -> 784000 | R17: =[11]MVTAOUT!$Q17+[11]MVTSEPT!$R17+[11]MVTOCT!$P17+[11]MVTNOV!$P17+[11]MVTDEC!$P17+[11]MVTJANV!$P17+[11]MVTFEV!$P17+[11]MVTMARS!$P17+[11]MVTAVRIL!$P17+[11]MVTMAI!$P17+[11]MVTJUIN!$P17+[11]MVTJUIL!$P17+[11]MVTAOUT2018!$P$17 -> 565000 | S17: =+W17 -> 219000 | T17: =S17*5/100 -> 10950 | U17: =+S17+T17 -> 229950 | V17: 42904 | W17: =Q17-R17 -> 219000 | X17: A ANALYSER | Z17: =+AA17-S17 -> 10950 | AA17: =S17+(S17*5/100) -> 229950
A18: KEPHE DAVID | B18: 387000 | C18: =+INVENT2016_2017!I18 -> 48664.16 | D18: =[11]MVTAOUT!$H18+[11]MVTSEPT!$I18+[11]MVTOCT!$G18+[11]MVTNOV!$G18+[11]MVTDEC!$G18+[11]MVTJANV!$G18+[11]MVTFEV!$G18+[11]MVTMARS!$G18+[11]MVTAVRIL!$G18+[11]MVTMAI!$G18+[11]MVTJUIN!$G18+[11]MVTJUIL!$G18+[11]MVTAOUT2018!$G18 -> 0 | E18: =+[11]MVTAOUT!$D18+[11]MVTSEPT!$E18+[11]MVTOCT!$C18+[11]MVTNOV!$C18+[11]MVTDEC!$C18+[11]MVTJANV!$C18+[11]MVTFEV!$C18+[11]MVTMARS!$C18+[11]MVTAVRIL!$C18+[11]MVTMAI!$C18+[11]MVTJUIN!$C18+[11]MVTJUIL!$C18 -> 16583.14 | F18: =+C18+D18+E18 -> 65247.3 | I18: 25000 | J18: 30000 | K18: =F18-G18-H18-I18-J18-3000 -> 7247.3004 | L18: =447000+30000+3000 -> 480000 | M18: =K18+L18 -> 487247.3 | O18: =[11]MVTAOUT!O18+[11]MVTSEPT!P18+[11]MVTOCT!N18+[11]MVTNOV!N18+[11]MVTDEC!N18+[11]MVTJANV!N18+[11]MVTFEV!N18+[11]MVTMARS!N18+[11]MVTAVRIL!N18+[11]MVTMAI!N18+[11]MVTJUIN!N18+[11]MVTJUIL!N18 -> 0 | P18: =[11]MVTAOUT!P18+[11]MVTSEPT!Q18+[11]MVTOCT!O18+[11]MVTNOV!O18+[11]MVTDEC!O18+[11]MVTJANV!O18+[11]MVTFEV!O18+[11]MVTMARS!O18+[11]MVTAVRIL!O18+[11]MVTMAI!O18+[11]MVTJUIN!O18+[11]MVTJUIL!O18 -> 0 | Q18: =+INVENT2016_2017!N18 -> 0 | R18: =[11]MVTAOUT!$Q18+[11]MVTSEPT!$R18+[11]MVTOCT!$P18+[11]MVTNOV!$P18+[11]MVTDEC!$P18+[11]MVTJANV!$P18+[11]MVTFEV!$P18+[11]MVTMARS!$P18+[11]MVTAVRIL!$P18+[11]MVTMAI!$P18+[11]MVTJUIN!$P18+[11]MVTJUIL!$P18+[11]MVTAOUT2018!$P$18 -> 0
A19: KEPSEU FRANCIS | B19: =+INVENT2016_2017!J19 -> 450000 | C19: =+INVENT2016_2017!I19 -> 1911428.9 | D19: =[11]MVTAOUT!$H19+[11]MVTSEPT!$I19+[11]MVTOCT!$G19+[11]MVTNOV!$G19+[11]MVTDEC!$G19+[11]MVTJANV!$G19+[11]MVTFEV!$G19+[11]MVTMARS!$G19+[11]MVTAVRIL!$G19+[11]MVTMAI!$G19+[11]MVTJUIN!$G19+[11]MVTJUIL!$G19+[11]MVTAOUT2018!$G19 -> 1078000 | E19: =+[11]MVTAOUT!$D19+[11]MVTSEPT!$E19+[11]MVTOCT!$C19+[11]MVTNOV!$C19+[11]MVTDEC!$C19+[11]MVTJANV!$C19+[11]MVTFEV!$C19+[11]MVTMARS!$C19+[11]MVTAVRIL!$C19+[11]MVTMAI!$C19+[11]MVTJUIN!$C19+[11]MVTJUIL!$C19 -> 29469.823 | F19: =+C19+D19+E19 -> 3018898.7 | I19: 25000 | J19: 30000 | K19: =F19-G19-H19-I19-J19 -> 2963898.7 | L19: =B19+J19 -> 480000 | M19: =K19+L19 -> 3443898.7 | O19: =[11]MVTAOUT!O19+[11]MVTSEPT!P19+[11]MVTOCT!N19+[11]MVTNOV!N19+[11]MVTDEC!N19+[11]MVTJANV!N19+[11]MVTFEV!N19+[11]MVTMARS!N19+[11]MVTAVRIL!N19+[11]MVTMAI!N19+[11]MVTJUIN!N19+[11]MVTJUIL!N19 -> 0 | P19: =[11]MVTAOUT!P19+[11]MVTSEPT!Q19+[11]MVTOCT!O19+[11]MVTNOV!O19+[11]MVTDEC!O19+[11]MVTJANV!O19+[11]MVTFEV!O19+[11]MVTMARS!O19+[11]MVTAVRIL!O19+[11]MVTMAI!O19+[11]MVTJUIN!O19+[11]MVTJUIL!O19 -> 0 | Q19: =+INVENT2016_2017!N19 -> 0 | R19: =[11]MVTAOUT!$Q19+[11]MVTSEPT!$R19+[11]MVTOCT!$P19+[11]MVTNOV!$P19+[11]MVTDEC!$P19+[11]MVTJANV!$P19+[11]MVTFEV!$P19+[11]MVTMARS!$P19+[11]MVTAVRIL!$P19+[11]MVTMAI!$P19+[11]MVTJUIN!$P19+[11]MVTJUIL!$P19+[11]MVTAOUT2018!$P$19 -> 0
A20: KOUAMOU EMMANUEL | B20: =+INVENT2016_2017!J20 -> 450000 | C20: =+INVENT2016_2017!I20 -> 47239.947 | D20: =[11]MVTAOUT!$H20+[11]MVTSEPT!$I20+[11]MVTOCT!$G20+[11]MVTNOV!$G20+[11]MVTDEC!$G20+[11]MVTJANV!$G20+[11]MVTFEV!$G20+[11]MVTMARS!$G20+[11]MVTAVRIL!$G20+[11]MVTMAI!$G20+[11]MVTJUIN!$G20+[11]MVTJUIL!$G20+[11]MVTAOUT2018!$G20 -> 39000 | E20: =+[11]MVTAOUT!$D20+[11]MVTSEPT!$E20+[11]MVTOCT!$C20+[11]MVTNOV!$C20+[11]MVTDEC!$C20+[11]MVTJANV!$C20+[11]MVTFEV!$C20+[11]MVTMARS!$C20+[11]MVTAVRIL!$C20+[11]MVTMAI!$C20+[11]MVTJUIN!$C20+[11]MVTJUIL!$C20 -> 19803.166 | F20: =+C20+D20+E20 -> 106043.11 | I20: 25000 | J20: 30000 | K20: =F20-G20-H20-I20-J20 -> 51043.112 | L20: =B20+J20 -> 480000 | M20: =K20+L20 -> 531043.11 | O20: =[11]MVTAOUT!O20+[11]MVTSEPT!P20+[11]MVTOCT!N20+[11]MVTNOV!N20+[11]MVTDEC!N20+[11]MVTJANV!N20+[11]MVTFEV!N20+[11]MVTMARS!N20+[11]MVTAVRIL!N20+[11]MVTMAI!N20+[11]MVTJUIN!N20+[11]MVTJUIL!N20 -> 600000 | P20: =[11]MVTAOUT!P20+[11]MVTSEPT!Q20+[11]MVTOCT!O20+[11]MVTNOV!O20+[11]MVTDEC!O20+[11]MVTJANV!O20+[11]MVTFEV!O20+[11]MVTMARS!O20+[11]MVTAVRIL!O20+[11]MVTMAI!O20+[11]MVTJUIN!O20+[11]MVTJUIL!O20 -> 48000 | Q20: =+INVENT2016_2017!N20 -> 1100000 | R20: =[11]MVTAOUT!$Q20+[11]MVTSEPT!$R20+[11]MVTOCT!$P20+[11]MVTNOV!$P20+[11]MVTDEC!$P20+[11]MVTJANV!$P20+[11]MVTFEV!$P20+[11]MVTMARS!$P20+[11]MVTAVRIL!$P20+[11]MVTMAI!$P20+[11]MVTJUIN!$P20+[11]MVTJUIL!$P20+[11]MVTAOUT2018!$P$20 -> 1150000 | S20: 648000 | T20: =S20*5/100 -> 32400 | U20: =+S20+T20 -> 680400 | V20: 43086 | X20: OK | Z20: =+AA20-S20 -> 32400 | AA20: =S20+(S20*5/100) -> 680400
A21: KOUAMOU MOISE | B21: =+INVENT2016_2017!J21 -> 450000 | C21: =+INVENT2016_2017!I21 -> 53808.893 | D21: =[11]MVTAOUT!$H21+[11]MVTSEPT!$I21+[11]MVTOCT!$G21+[11]MVTNOV!$G21+[11]MVTDEC!$G21+[11]MVTJANV!$G21+[11]MVTFEV!$G21+[11]MVTMARS!$G21+[11]MVTAVRIL!$G21+[11]MVTMAI!$G21+[11]MVTJUIN!$G21+[11]MVTJUIL!$G21+[11]MVTAOUT2018!$G21 -> 39000 | E21: =+[11]MVTAOUT!$D21+[11]MVTSEPT!$E21+[11]MVTOCT!$C21+[11]MVTNOV!$C21+[11]MVTDEC!$C21+[11]MVTJANV!$C21+[11]MVTFEV!$C21+[11]MVTMARS!$C21+[11]MVTAVRIL!$C21+[11]MVTMAI!$C21+[11]MVTJUIN!$C21+[11]MVTJUIL!$C21 -> 19802.808 | F21: =+C21+D21+E21 -> 112611.7 | I21: 25000 | J21: 30000 | K21: =F21-G21-H21-I21-J21 -> 57611.702 | L21: =B21+J21 -> 480000 | M21: =K21+L21 -> 537611.7 | O21: =[11]MVTAOUT!O21+[11]MVTSEPT!P21+[11]MVTOCT!N21+[11]MVTNOV!N21+[11]MVTDEC!N21+[11]MVTJANV!N21+[11]MVTFEV!N21+[11]MVTMARS!N21+[11]MVTAVRIL!N21+[11]MVTMAI!N21+[11]MVTJUIN!N21+[11]MVTJUIL!N21 -> 110000 | P21: =[11]MVTAOUT!P21+[11]MVTSEPT!Q21+[11]MVTOCT!O21+[11]MVTNOV!O21+[11]MVTDEC!O21+[11]MVTJANV!O21+[11]MVTFEV!O21+[11]MVTMARS!O21+[11]MVTAVRIL!O21+[11]MVTMAI!O21+[11]MVTJUIN!O21+[11]MVTJUIL!O21 -> 3300 | Q21: =+INVENT2016_2017!N21 -> 592000 | R21: =[11]MVTAOUT!$Q21+[11]MVTSEPT!$R21+[11]MVTOCT!$P21+[11]MVTNOV!$P21+[11]MVTDEC!$P21+[11]MVTJANV!$P21+[11]MVTFEV!$P21+[11]MVTMARS!$P21+[11]MVTAVRIL!$P21+[11]MVTMAI!$P21+[11]MVTJUIN!$P21+[11]MVTJUIL!$P21+[11]MVTAOUT2018!$P$21 -> 493000 | S21: =110000-94000 -> 16000 | T21: =S21*5/100 -> 800 | U21: =+S21+T21 -> 16800 | V21: 43241 | X21: OK | Z21: =+AA21-S21 -> 800 | AA21: =S21+(S21*5/100) -> 16800
A22: KOUAMO VICTOR PEGUY | B22: =+INVENT2016_2017!J22 -> 450000 | C22: =+INVENT2016_2017!I22 -> 39090.63 | D22: =[11]MVTAOUT!$H22+[11]MVTSEPT!$I22+[11]MVTOCT!$G22+[11]MVTNOV!$G22+[11]MVTDEC!$G22+[11]MVTJANV!$G22+[11]MVTFEV!$G22+[11]MVTMARS!$G22+[11]MVTAVRIL!$G22+[11]MVTMAI!$G22+[11]MVTJUIN!$G22+[11]MVTJUIL!$G22+[11]MVTAOUT2018!$G22 -> 38000 | E22: =+[11]MVTAOUT!$D22+[11]MVTSEPT!$E22+[11]MVTOCT!$C22+[11]MVTNOV!$C22+[11]MVTDEC!$C22+[11]MVTJANV!$C22+[11]MVTFEV!$C22+[11]MVTMARS!$C22+[11]MVTAVRIL!$C22+[11]MVTMAI!$C22+[11]MVTJUIN!$C22+[11]MVTJUIL!$C22 -> 19797.11 | F22: =+C22+D22+E22 -> 96887.739 | I22: 25000 | J22: 30000 | K22: =F22-G22-H22-I22-J22 -> 41887.739 | L22: =B22+J22 -> 480000 | M22: =K22+L22 -> 521887.74 | O22: =[11]MVTAOUT!O22+[11]MVTSEPT!P22+[11]MVTOCT!N22+[11]MVTNOV!N22+[11]MVTDEC!N22+[11]MVTJANV!N22+[11]MVTFEV!N22+[11]MVTMARS!N22+[11]MVTAVRIL!N22+[11]MVTMAI!N22+[11]MVTJUIN!N22+[11]MVTJUIL!N22 -> 700000 | P22: =[11]MVTAOUT!P22+[11]MVTSEPT!Q22+[11]MVTOCT!O22+[11]MVTNOV!O22+[11]MVTDEC!O22+[11]MVTJANV!O22+[11]MVTFEV!O22+[11]MVTMARS!O22+[11]MVTAVRIL!O22+[11]MVTMAI!O22+[11]MVTJUIN!O22+[11]MVTJUIL!O22 -> 70000 | Q22: =+INVENT2016_2017!N22 -> 896000 | R22: =[11]MVTAOUT!$Q22+[11]MVTSEPT!$R22+[11]MVTOCT!$P22+[11]MVTNOV!$P22+[11]MVTDEC!$P22+[11]MVTJANV!$P22+[11]MVTFEV!$P22+[11]MVTMARS!$P22+[11]MVTAVRIL!$P22+[11]MVTMAI!$P22+[11]MVTJUIN!$P22+[11]MVTJUIL!$P22+[11]MVTAOUT2018!$P$22 -> 896000 | S22: 700000 | T22: =S22*5/100 -> 35000 | U22: =+S22+T22 -> 735000 | V22: 43121 | X22: OK | Z22: =+AA22-S22 -> 35000 | AA22: =S22+(S22*5/100) -> 735000
A23: KOUATCHO MESSACK | B23: =+INVENT2016_2017!J23 -> 450000 | C23: =+INVENT2016_2017!I23 -> 36797.236 | D23: =[11]MVTAOUT!$H23+[11]MVTSEPT!$I23+[11]MVTOCT!$G23+[11]MVTNOV!$G23+[11]MVTDEC!$G23+[11]MVTJANV!$G23+[11]MVTFEV!$G23+[11]MVTMARS!$G23+[11]MVTAVRIL!$G23+[11]MVTMAI!$G23+[11]MVTJUIN!$G23+[11]MVTJUIL!$G23+[11]MVTAOUT2018!$G23 -> 39000 | E23: =+[11]MVTAOUT!$D23+[11]MVTSEPT!$E23+[11]MVTOCT!$C23+[11]MVTNOV!$C23+[11]MVTDEC!$C23+[11]MVTJANV!$C23+[11]MVTFEV!$C23+[11]MVTMARS!$C23+[11]MVTAVRIL!$C23+[11]MVTMAI!$C23+[11]MVTJUIN!$C23+[11]MVTJUIL!$C23 -> 19808.17 | F23: =+C23+D23+E23 -> 95605.406 | I23: 25000 | J23: 30000 | K23: =F23-G23-H23-I23-J23 -> 40605.406 | L23: =B23+J23 -> 480000 | M23: =K23+L23 -> 520605.41 | O23: =[11]MVTAOUT!O23+[11]MVTSEPT!P23+[11]MVTOCT!N23+[11]MVTNOV!N23+[11]MVTDEC!N23+[11]MVTJANV!N23+[11]MVTFEV!N23+[11]MVTMARS!N23+[11]MVTAVRIL!N23+[11]MVTMAI!N23+[11]MVTJUIN!N23+[11]MVTJUIL!N23 -> 850000 | P23: =[11]MVTAOUT!P23+[11]MVTSEPT!Q23+[11]MVTOCT!O23+[11]MVTNOV!O23+[11]MVTDEC!O23+[11]MVTJANV!O23+[11]MVTFEV!O23+[11]MVTMARS!O23+[11]MVTAVRIL!O23+[11]MVTMAI!O23+[11]MVTJUIN!O23+[11]MVTJUIL!O23 -> 51000 | Q23: =+INVENT2016_2017!N23 -> 1120000 | R23: =[11]MVTAOUT!$Q23+[11]MVTSEPT!$R23+[11]MVTOCT!$P23+[11]MVTNOV!$P23+[11]MVTDEC!$P23+[11]MVTJANV!$P23+[11]MVTFEV!$P23+[11]MVTMARS!$P23+[11]MVTAVRIL!$P23+[11]MVTMAI!$P23+[11]MVTJUIN!$P23+[11]MVTJUIL!$P23+[11]MVTAOUT2018!$P$23 -> 1950000 | S23: =850000-850000 -> 0 | V23: 43241 | X23: OK | Y23: 20000
A24: LOWE JEAN | B24: =+INVENT2016_2017!J24 -> 450000 | C24: =+INVENT2016_2017!I24 -> 47506.896 | D24: =[11]MVTAOUT!$H24+[11]MVTSEPT!$I24+[11]MVTOCT!$G24+[11]MVTNOV!$G24+[11]MVTDEC!$G24+[11]MVTJANV!$G24+[11]MVTFEV!$G24+[11]MVTMARS!$G24+[11]MVTAVRIL!$G24+[11]MVTMAI!$G24+[11]MVTJUIN!$G24+[11]MVTJUIL!$G24+[11]MVTAOUT2018!$G24 -> 39000 | E24: =+[11]MVTAOUT!$D24+[11]MVTSEPT!$E24+[11]MVTOCT!$C24+[11]MVTNOV!$C24+[11]MVTDEC!$C24+[11]MVTJANV!$C24+[11]MVTFEV!$C24+[11]MVTMARS!$C24+[11]MVTAVRIL!$C24+[11]MVTMAI!$C24+[11]MVTJUIN!$C24+[11]MVTJUIL!$C24 -> 19799.955 | F24: =+C24+D24+E24 -> 106306.85 | I24: 25000 | J24: 30000 | K24: =F24-G24-H24-I24-J24 -> 51306.852 | L24: =B24+J24 -> 480000 | M24: =K24+L24 -> 531306.85 | O24: =[11]MVTAOUT!O24+[11]MVTSEPT!P24+[11]MVTOCT!N24+[11]MVTNOV!N24+[11]MVTDEC!N24+[11]MVTJANV!N24+[11]MVTFEV!N24+[11]MVTMARS!N24+[11]MVTAVRIL!N24+[11]MVTMAI!N24+[11]MVTJUIN!N24+[11]MVTJUIL!N24 -> 150000 | P24: =[11]MVTAOUT!P24+[11]MVTSEPT!Q24+[11]MVTOCT!O24+[11]MVTNOV!O24+[11]MVTDEC!O24+[11]MVTJANV!O24+[11]MVTFEV!O24+[11]MVTMARS!O24+[11]MVTAVRIL!O24+[11]MVTMAI!O24+[11]MVTJUIN!O24+[11]MVTJUIL!O24 -> 18000 | Q24: =+INVENT2016_2017!N24 -> 154500 | R24: =[11]MVTAOUT!$Q24+[11]MVTSEPT!$R24+[11]MVTOCT!$P24+[11]MVTNOV!$P24+[11]MVTDEC!$P24+[11]MVTJANV!$P24+[11]MVTFEV!$P24+[11]MVTMARS!$P24+[11]MVTAVRIL!$P24+[11]MVTMAI!$P24+[11]MVTJUIN!$P24+[11]MVTJUIL!$P24+[11]MVTAOUT2018!$P$24 -> 157500 | S24: 168000 | T24: =S24*5/100 -> 8400 | U24: =+S24+T24 -> 176400 | V24: 42967 | X24: OK | Z24: =+AA24-S24 -> 8400 | AA24: =S24+(S24*5/100) -> 176400
A25: NANKAM APPOLINAIRE | B25: =+INVENT2016_2017!J25 -> 450000 | C25: =+INVENT2016_2017!I25 -> 47549.255 | D25: =[11]MVTAOUT!$H25+[11]MVTSEPT!$I25+[11]MVTOCT!$G25+[11]MVTNOV!$G25+[11]MVTDEC!$G25+[11]MVTJANV!$G25+[11]MVTFEV!$G25+[11]MVTMARS!$G25+[11]MVTAVRIL!$G25+[11]MVTMAI!$G25+[11]MVTJUIN!$G25+[11]MVTJUIL!$G25+[11]MVTAOUT2018!$G25 -> 39000 | E25: =+[11]MVTAOUT!$D25+[11]MVTSEPT!$E25+[11]MVTOCT!$C25+[11]MVTNOV!$C25+[11]MVTDEC!$C25+[11]MVTJANV!$C25+[11]MVTFEV!$C25+[11]MVTMARS!$C25+[11]MVTAVRIL!$C25+[11]MVTMAI!$C25+[11]MVTJUIN!$C25+[11]MVTJUIL!$C25 -> 19804.481 | F25: =+C25+D25+E25 -> 106353.74 | I25: 25000 | J25: 30000 | K25: =F25-G25-H25-I25-J25 -> 51353.736 | L25: =B25+J25 -> 480000 | M25: =K25+L25 -> 531353.74 | O25: =[11]MVTAOUT!O25+[11]MVTSEPT!P25+[11]MVTOCT!N25+[11]MVTNOV!N25+[11]MVTDEC!N25+[11]MVTJANV!N25+[11]MVTFEV!N25+[11]MVTMARS!N25+[11]MVTAVRIL!N25+[11]MVTMAI!N25+[11]MVTJUIN!N25+[11]MVTJUIL!N25 -> 0 | P25: =[11]MVTAOUT!P25+[11]MVTSEPT!Q25+[11]MVTOCT!O25+[11]MVTNOV!O25+[11]MVTDEC!O25+[11]MVTJANV!O25+[11]MVTFEV!O25+[11]MVTMARS!O25+[11]MVTAVRIL!O25+[11]MVTMAI!O25+[11]MVTJUIN!O25+[11]MVTJUIL!O25 -> 0 | Q25: =+INVENT2016_2017!N25 -> 0 | R25: =[11]MVTAOUT!$Q25+[11]MVTSEPT!$R25+[11]MVTOCT!$P25+[11]MVTNOV!$P25+[11]MVTDEC!$P25+[11]MVTJANV!$P25+[11]MVTFEV!$P25+[11]MVTMARS!$P25+[11]MVTAVRIL!$P25+[11]MVTMAI!$P25+[11]MVTJUIN!$P25+[11]MVTJUIL!$P25+[11]MVTAOUT2018!$P$25 -> 21000 | X25: A ANALYSER
A26: NDJOMO ETIENNE | B26: =+INVENT2016_2017!J26 -> 450000 | C26: =+INVENT2016_2017!I26 -> 47476.114 | D26: =[11]MVTAOUT!$H26+[11]MVTSEPT!$I26+[11]MVTOCT!$G26+[11]MVTNOV!$G26+[11]MVTDEC!$G26+[11]MVTJANV!$G26+[11]MVTFEV!$G26+[11]MVTMARS!$G26+[11]MVTAVRIL!$G26+[11]MVTMAI!$G26+[11]MVTJUIN!$G26+[11]MVTJUIL!$G26+[11]MVTAOUT2018!$G26 -> 104000 | E26: =+[11]MVTAOUT!$D26+[11]MVTSEPT!$E26+[11]MVTOCT!$C26+[11]MVTNOV!$C26+[11]MVTDEC!$C26+[11]MVTJANV!$C26+[11]MVTFEV!$C26+[11]MVTMARS!$C26+[11]MVTAVRIL!$C26+[11]MVTMAI!$C26+[11]MVTJUIN!$C26+[11]MVTJUIL!$C26 -> 20749.5 | F26: =+C26+D26+E26 -> 172225.61 | I26: 25000 | J26: 30000 | K26: =F26-G26-H26-I26-J26 -> 117225.61 | L26: =B26+J26 -> 480000 | M26: =K26+L26 -> 597225.61 | O26: =[11]MVTAOUT!O26+[11]MVTSEPT!P26+[11]MVTOCT!N26+[11]MVTNOV!N26+[11]MVTDEC!N26+[11]MVTJANV!N26+[11]MVTFEV!N26+[11]MVTMARS!N26+[11]MVTAVRIL!N26+[11]MVTMAI!N26+[11]MVTJUIN!N26+[11]MVTJUIL!N26 -> 700000 | P26: =[11]MVTAOUT!P26+[11]MVTSEPT!Q26+[11]MVTOCT!O26+[11]MVTNOV!O26+[11]MVTDEC!O26+[11]MVTJANV!O26+[11]MVTFEV!O26+[11]MVTMARS!O26+[11]MVTAVRIL!O26+[11]MVTMAI!O26+[11]MVTJUIN!O26+[11]MVTJUIL!O26 -> 35000 | Q26: =+INVENT2016_2017!N26 -> 672000 | R26: =[11]MVTAOUT!$Q26+[11]MVTSEPT!$R26+[11]MVTOCT!$P26+[11]MVTNOV!$P26+[11]MVTDEC!$P26+[11]MVTJANV!$P26+[11]MVTFEV!$P26+[11]MVTMARS!$P26+[11]MVTAVRIL!$P26+[11]MVTMAI!$P26+[11]MVTJUIN!$P26+[11]MVTJUIL!$P26+[11]MVTAOUT2018!$P$26 -> 1372000 | S26: 0 | V26: 43169 | X26: OK
A27: NDOMBOU JEAN CLAUDE | B27: =+INVENT2016_2017!J27 -> 450000 | C27: =+INVENT2016_2017!I27 -> 27680.734 | D27: =[11]MVTAOUT!$H27+[11]MVTSEPT!$I27+[11]MVTOCT!$G27+[11]MVTNOV!$G27+[11]MVTDEC!$G27+[11]MVTJANV!$G27+[11]MVTFEV!$G27+[11]MVTMARS!$G27+[11]MVTAVRIL!$G27+[11]MVTMAI!$G27+[11]MVTJUIN!$G27+[11]MVTJUIL!$G27+[11]MVTAOUT2018!$G27 -> 39000 | E27: =+[11]MVTAOUT!$D27+[11]MVTSEPT!$E27+[11]MVTOCT!$C27+[11]MVTNOV!$C27+[11]MVTDEC!$C27+[11]MVTJANV!$C27+[11]MVTFEV!$C27+[11]MVTMARS!$C27+[11]MVTAVRIL!$C27+[11]MVTMAI!$C27+[11]MVTJUIN!$C27+[11]MVTJUIL!$C27 -> 19734.447 | F27: =+C27+D27+E27 -> 86415.181 | I27: 25000 | J27: 30000 | K27: =F27-G27-H27-I27-J27 -> 31415.181 | L27: =B27+J27 -> 480000 | M27: =K27+L27 -> 511415.18 | O27: =[11]MVTAOUT!O27+[11]MVTSEPT!P27+[11]MVTOCT!N27+[11]MVTNOV!N27+[11]MVTDEC!N27+[11]MVTJANV!N27+[11]MVTFEV!N27+[11]MVTMARS!N27+[11]MVTAVRIL!N27+[11]MVTMAI!N27+[11]MVTJUIN!N27+[11]MVTJUIL!N27 -> 0 | P27: =[11]MVTAOUT!P27+[11]MVTSEPT!Q27+[11]MVTOCT!O27+[11]MVTNOV!O27+[11]MVTDEC!O27+[11]MVTJANV!O27+[11]MVTFEV!O27+[11]MVTMARS!O27+[11]MVTAVRIL!O27+[11]MVTMAI!O27+[11]MVTJUIN!O27+[11]MVTJUIL!O27 -> 0 | Q27: =+INVENT2016_2017!N27 -> 0 | R27: =[11]MVTAOUT!$Q27+[11]MVTSEPT!$R27+[11]MVTOCT!$P27+[11]MVTNOV!$P27+[11]MVTDEC!$P27+[11]MVTJANV!$P27+[11]MVTFEV!$P27+[11]MVTMARS!$P27+[11]MVTAVRIL!$P27+[11]MVTMAI!$P27+[11]MVTJUIN!$P27+[11]MVTJUIL!$P27+[11]MVTAOUT2018!$P$27 -> 0
A28: NGONDIEP CLAUDE | B28: =+INVENT2016_2017!J28 -> 450000 | C28: =+INVENT2016_2017!I28 -> 47679.518 | D28: =[11]MVTAOUT!$H28+[11]MVTSEPT!$I28+[11]MVTOCT!$G28+[11]MVTNOV!$G28+[11]MVTDEC!$G28+[11]MVTJANV!$G28+[11]MVTFEV!$G28+[11]MVTMARS!$G28+[11]MVTAVRIL!$G28+[11]MVTMAI!$G28+[11]MVTJUIN!$G28+[11]MVTJUIL!$G28+[11]MVTAOUT2018!$G28 -> 105500 | E28: =+[11]MVTAOUT!$D28+[11]MVTSEPT!$E28+[11]MVTOCT!$C28+[11]MVTNOV!$C28+[11]MVTDEC!$C28+[11]MVTJANV!$C28+[11]MVTFEV!$C28+[11]MVTMARS!$C28+[11]MVTAVRIL!$C28+[11]MVTMAI!$C28+[11]MVTJUIN!$C28+[11]MVTJUIL!$C28 -> 22120.769 | F28: =+C28+D28+E28 -> 175300.29 | H28: 100000 | I28: 25000 | J28: 30000 | K28: =F28-G28-H28-I28-J28 -> 20300.287 | L28: =B28+J28 -> 480000 | M28: =K28+L28 -> 500300.29 | O28: =[11]MVTAOUT!O28+[11]MVTSEPT!P28+[11]MVTOCT!N28+[11]MVTNOV!N28+[11]MVTDEC!N28+[11]MVTJANV!N28+[11]MVTFEV!N28+[11]MVTMARS!N28+[11]MVTAVRIL!N28+[11]MVTMAI!N28+[11]MVTJUIN!N28+[11]MVTJUIL!N28 -> 0 | P28: =[11]MVTAOUT!P28+[11]MVTSEPT!Q28+[11]MVTOCT!O28+[11]MVTNOV!O28+[11]MVTDEC!O28+[11]MVTJANV!O28+[11]MVTFEV!O28+[11]MVTMARS!O28+[11]MVTAVRIL!O28+[11]MVTMAI!O28+[11]MVTJUIN!O28+[11]MVTJUIL!O28 -> 0 | Q28: =+INVENT2016_2017!N28 -> 1120000 | R28: =[11]MVTAOUT!$Q28+[11]MVTSEPT!$R28+[11]MVTOCT!$P28+[11]MVTNOV!$P28+[11]MVTDEC!$P28+[11]MVTJANV!$P28+[11]MVTFEV!$P28+[11]MVTMARS!$P28+[11]MVTAVRIL!$P28+[11]MVTMAI!$P28+[11]MVTJUIN!$P28+[11]MVTJUIL!$P28+[11]MVTAOUT2018!$P$28 -> 0 | S28: 1120000 | T28: =S28*5/100 -> 56000 | U28: =+S28+T28 -> 1176000 | V28: 42904 | Z28: =+AA28-S28 -> 56000 | AA28: =S28+(S28*5/100) -> 1176000
A29: NGONGANG JEAN THEODORE | B29: 30000 | C29: =+INVENT2016_2017!I29 -> -4174.3496 | D29: =[11]MVTAOUT!$H29+[11]MVTSEPT!$I29+[11]MVTOCT!$G29+[11]MVTNOV!$G29+[11]MVTDEC!$G29+[11]MVTJANV!$G29+[11]MVTFEV!$G29+[11]MVTMARS!$G29+[11]MVTAVRIL!$G29+[11]MVTMAI!$G29+[11]MVTJUIN!$G29+[11]MVTJUIL!$G29+[11]MVTAOUT2018!$G29 -> 0 | E29: =+[11]MVTAOUT!$D29+[11]MVTSEPT!$E29+[11]MVTOCT!$C29+[11]MVTNOV!$C29+[11]MVTDEC!$C29+[11]MVTJANV!$C29+[11]MVTFEV!$C29+[11]MVTMARS!$C29+[11]MVTAVRIL!$C29+[11]MVTMAI!$C29+[11]MVTJUIN!$C29+[11]MVTJUIL!$C29 -> 1237.5906 | F29: =+C29+D29+E29 -> -2936.759 | I29: 13234 | J29: 0 | K29: =F29-G29-H29-I29-J29 -> -16170.759 | L29: 30000 | M29: =K29+L29 -> 13829.241 | O29: =[11]MVTAOUT!O29+[11]MVTSEPT!P29+[11]MVTOCT!N29+[11]MVTNOV!N29+[11]MVTDEC!N29+[11]MVTJANV!N29+[11]MVTFEV!N29+[11]MVTMARS!N29+[11]MVTAVRIL!N29+[11]MVTMAI!N29+[11]MVTJUIN!N29+[11]MVTJUIL!N29 -> 0 | P29: =[11]MVTAOUT!P29+[11]MVTSEPT!Q29+[11]MVTOCT!O29+[11]MVTNOV!O29+[11]MVTDEC!O29+[11]MVTJANV!O29+[11]MVTFEV!O29+[11]MVTMARS!O29+[11]MVTAVRIL!O29+[11]MVTMAI!O29+[11]MVTJUIN!O29+[11]MVTJUIL!O29 -> 0 | Q29: =+INVENT2016_2017!N29 -> 0 | R29: =[11]MVTAOUT!$Q29+[11]MVTSEPT!$R29+[11]MVTOCT!$P29+[11]MVTNOV!$P29+[11]MVTDEC!$P29+[11]MVTJANV!$P29+[11]MVTFEV!$P29+[11]MVTMARS!$P29+[11]MVTAVRIL!$P29+[11]MVTMAI!$P29+[11]MVTJUIN!$P29+[11]MVTJUIL!$P29+[11]MVTAOUT2018!$P$29 -> 50000 | X29: A ANALYSER
A30: NGUIEMEGNI MATHIEU BLAISE | B30: =+INVENT2016_2017!J30 -> 450000 | C30: =+INVENT2016_2017!I30 -> 93205.631 | D30: =[11]MVTAOUT!$H30+[11]MVTSEPT!$I30+[11]MVTOCT!$G30+[11]MVTNOV!$G30+[11]MVTDEC!$G30+[11]MVTJANV!$G30+[11]MVTFEV!$G30+[11]MVTMARS!$G30+[11]MVTAVRIL!$G30+[11]MVTMAI!$G30+[11]MVTJUIN!$G30+[11]MVTJUIL!$G30+[11]MVTAOUT2018!$G30 -> 39000 | E30: =+[11]MVTAOUT!$D30+[11]MVTSEPT!$E30+[11]MVTOCT!$C30+[11]MVTNOV!$C30+[11]MVTDEC!$C30+[11]MVTJANV!$C30+[11]MVTFEV!$C30+[11]MVTMARS!$C30+[11]MVTAVRIL!$C30+[11]MVTMAI!$C30+[11]MVTJUIN!$C30+[11]MVTJUIL!$C30 -> 19932.624 | F30: =+C30+D30+E30 -> 152138.25 | I30: 25000 | J30: 30000 | K30: =F30-G30-H30-I30-J30 -> 97138.255 | L30: =B30+J30 -> 480000 | M30: =K30+L30 -> 577138.25 | O30: =[11]MVTAOUT!O30+[11]MVTSEPT!P30+[11]MVTOCT!N30+[11]MVTNOV!N30+[11]MVTDEC!N30+[11]MVTJANV!N30+[11]MVTFEV!N30+[11]MVTMARS!N30+[11]MVTAVRIL!N30+[11]MVTMAI!N30+[11]MVTJUIN!N30+[11]MVTJUIL!N30 -> 0 | P30: =[11]MVTAOUT!P30+[11]MVTSEPT!Q30+[11]MVTOCT!O30+[11]MVTNOV!O30+[11]MVTDEC!O30+[11]MVTJANV!O30+[11]MVTFEV!O30+[11]MVTMARS!O30+[11]MVTAVRIL!O30+[11]MVTMAI!O30+[11]MVTJUIN!O30+[11]MVTJUIL!O30 -> 0 | Q30: =+INVENT2016_2017!N30 -> 0 | R30: =[11]MVTAOUT!$Q30+[11]MVTSEPT!$R30+[11]MVTOCT!$P30+[11]MVTNOV!$P30+[11]MVTDEC!$P30+[11]MVTJANV!$P30+[11]MVTFEV!$P30+[11]MVTMARS!$P30+[11]MVTAVRIL!$P30+[11]MVTMAI!$P30+[11]MVTJUIN!$P30+[11]MVTJUIL!$P30+[11]MVTAOUT2018!$P$30 -> 0
A31: NJEPDJIO MBOUKAM DELUXE | B31: =+INVENT2016_2017!J31 -> 450000 | C31: =+INVENT2016_2017!I31 -> 46909.873 | D31: =[11]MVTAOUT!$H31+[11]MVTSEPT!$I31+[11]MVTOCT!$G31+[11]MVTNOV!$G31+[11]MVTDEC!$G31+[11]MVTJANV!$G31+[11]MVTFEV!$G31+[11]MVTMARS!$G31+[11]MVTAVRIL!$G31+[11]MVTMAI!$G31+[11]MVTJUIN!$G31+[11]MVTJUIL!$G31+[11]MVTAOUT2018!$G31 -> 39000 | E31: =+[11]MVTAOUT!$D31+[11]MVTSEPT!$E31+[11]MVTOCT!$C31+[11]MVTNOV!$C31+[11]MVTDEC!$C31+[11]MVTJANV!$C31+[11]MVTFEV!$C31+[11]MVTMARS!$C31+[11]MVTAVRIL!$C31+[11]MVTMAI!$C31+[11]MVTJUIN!$C31+[11]MVTJUIL!$C31 -> 19779.445 | F31: =+C31+D31+E31 -> 105689.32 | I31: 25000 | J31: 30000 | K31: =F31-G31-H31-I31-J31 -> 50689.319 | L31: =B31+J31 -> 480000 | M31: =K31+L31 -> 530689.32 | O31: =[11]MVTAOUT!O31+[11]MVTSEPT!P31+[11]MVTOCT!N31+[11]MVTNOV!N31+[11]MVTDEC!N31+[11]MVTJANV!N31+[11]MVTFEV!N31+[11]MVTMARS!N31+[11]MVTAVRIL!N31+[11]MVTMAI!N31+[11]MVTJUIN!N31+[11]MVTJUIL!N31 -> 500000 | P31: =[11]MVTAOUT!P31+[11]MVTSEPT!Q31+[11]MVTOCT!O31+[11]MVTNOV!O31+[11]MVTDEC!O31+[11]MVTJANV!O31+[11]MVTFEV!O31+[11]MVTMARS!O31+[11]MVTAVRIL!O31+[11]MVTMAI!O31+[11]MVTJUIN!O31+[11]MVTJUIL!O31 -> 10000 | Q31: =+INVENT2016_2017!N31 -> 896000 | R31: =[11]MVTAOUT!$Q31+[11]MVTSEPT!$R31+[11]MVTOCT!$P31+[11]MVTNOV!$P31+[11]MVTDEC!$P31+[11]MVTJANV!$P31+[11]MVTFEV!$P31+[11]MVTMARS!$P31+[11]MVTAVRIL!$P31+[11]MVTMAI!$P31+[11]MVTJUIN!$P31+[11]MVTJUIL!$P31+[11]MVTAOUT2018!$P$31 -> 1440800 | S31: =500000-500000 -> 0 | V31: 43268 | X31: OK
A32: NKAMGANG JUSTIN DEJOLIE | B32: =+INVENT2016_2017!J32 -> 450000 | C32: =+INVENT2016_2017!I32 -> 54313.881 | D32: =[11]MVTAOUT!$H32+[11]MVTSEPT!$I32+[11]MVTOCT!$G32+[11]MVTNOV!$G32+[11]MVTDEC!$G32+[11]MVTJANV!$G32+[11]MVTFEV!$G32+[11]MVTMARS!$G32+[11]MVTAVRIL!$G32+[11]MVTMAI!$G32+[11]MVTJUIN!$G32+[11]MVTJUIL!$G32+[11]MVTAOUT2018!$G32 -> 378000 | E32: =+[11]MVTAOUT!$D32+[11]MVTSEPT!$E32+[11]MVTOCT!$C32+[11]MVTNOV!$C32+[11]MVTDEC!$C32+[11]MVTJANV!$C32+[11]MVTFEV!$C32+[11]MVTMARS!$C32+[11]MVTAVRIL!$C32+[11]MVTMAI!$C32+[11]MVTJUIN!$C32+[11]MVTJUIL!$C32 -> 27722.47 | F32: =+C32+D32+E32 -> 460036.35 | I32: 25000 | J32: 30000 | K32: =F32-G32-H32-I32-J32 -> 405036.35 | L32: =B32+J32 -> 480000 | M32: =K32+L32 -> 885036.35 | O32: =[11]MVTAOUT!O32+[11]MVTSEPT!P32+[11]MVTOCT!N32+[11]MVTNOV!N32+[11]MVTDEC!N32+[11]MVTJANV!N32+[11]MVTFEV!N32+[11]MVTMARS!N32+[11]MVTAVRIL!N32+[11]MVTMAI!N32+[11]MVTJUIN!N32+[11]MVTJUIL!N32 -> 1000000 | P32: =[11]MVTAOUT!P32+[11]MVTSEPT!Q32+[11]MVTOCT!O32+[11]MVTNOV!O32+[11]MVTDEC!O32+[11]MVTJANV!O32+[11]MVTFEV!O32+[11]MVTMARS!O32+[11]MVTAVRIL!O32+[11]MVTMAI!O32+[11]MVTJUIN!O32+[11]MVTJUIL!O32 -> 90000 | Q32: =+INVENT2016_2017!N32 -> 1120000 | R32: =[11]MVTAOUT!$Q32+[11]MVTSEPT!$R32+[11]MVTOCT!$P32+[11]MVTNOV!$P32+[11]MVTDEC!$P32+[11]MVTJANV!$P32+[11]MVTFEV!$P32+[11]MVTMARS!$P32+[11]MVTAVRIL!$P32+[11]MVTMAI!$P32+[11]MVTJUIN!$P32+[11]MVTJUIL!$P32+[11]MVTAOUT2018!$P$32 -> 2210000 | S32: =1090000-1090000 -> 0 | V32: 43057 | X32: OK
A33: NKEPSEU DIEUDONNE | B33: =+INVENT2016_2017!J33 -> 450000 | C33: =+INVENT2016_2017!I33 -> 50017.733 | D33: =[11]MVTAOUT!$H33+[11]MVTSEPT!$I33+[11]MVTOCT!$G33+[11]MVTNOV!$G33+[11]MVTDEC!$G33+[11]MVTJANV!$G33+[11]MVTFEV!$G33+[11]MVTMARS!$G33+[11]MVTAVRIL!$G33+[11]MVTMAI!$G33+[11]MVTJUIN!$G33+[11]MVTJUIL!$G33+[11]MVTAOUT2018!$G33 -> 104000 | E33: =+[11]MVTAOUT!$D33+[11]MVTSEPT!$E33+[11]MVTOCT!$C33+[11]MVTNOV!$C33+[11]MVTDEC!$C33+[11]MVTJANV!$C33+[11]MVTFEV!$C33+[11]MVTMARS!$C33+[11]MVTAVRIL!$C33+[11]MVTMAI!$C33+[11]MVTJUIN!$C33+[11]MVTJUIL!$C33 -> 21092.067 | F33: =+C33+D33+E33 -> 175109.8 | H33: 100000 | I33: 25000 | J33: 30000 | K33: =F33-G33-H33-I33-J33 -> 20109.8 | L33: =B33+J33 -> 480000 | M33: =K33+L33 -> 500109.8 | O33: =[11]MVTAOUT!O33+[11]MVTSEPT!P33+[11]MVTOCT!N33+[11]MVTNOV!N33+[11]MVTDEC!N33+[11]MVTJANV!N33+[11]MVTFEV!N33+[11]MVTMARS!N33+[11]MVTAVRIL!N33+[11]MVTMAI!N33+[11]MVTJUIN!N33+[11]MVTJUIL!N33 -> 500000 | P33: =[11]MVTAOUT!P33+[11]MVTSEPT!Q33+[11]MVTOCT!O33+[11]MVTNOV!O33+[11]MVTDEC!O33+[11]MVTJANV!O33+[11]MVTFEV!O33+[11]MVTMARS!O33+[11]MVTAVRIL!O33+[11]MVTMAI!O33+[11]MVTJUIN!O33+[11]MVTJUIL!O33 -> 50000 | Q33: =+INVENT2016_2017!N33 -> 472000 | R33: =[11]MVTAOUT!$Q33+[11]MVTSEPT!$R33+[11]MVTOCT!$P33+[11]MVTNOV!$P33+[11]MVTDEC!$P33+[11]MVTJANV!$P33+[11]MVTFEV!$P33+[11]MVTMARS!$P33+[11]MVTAVRIL!$P33+[11]MVTMAI!$P33+[11]MVTJUIN!$P33+[11]MVTJUIL!$P33+[11]MVTAOUT2018!$P$33 -> 1594000 | S33: =420000-320000-100000 -> 0 | V33: 43374 | X33: OK
A37: PATEGO NJOSSU GUSTAVE | B37: =+INVENT2016_2017!J37 -> 450000 | C37: =+INVENT2016_2017!I37 -> 47164.658 | D37: =[11]MVTAOUT!$H35+[11]MVTSEPT!$I35+[11]MVTOCT!$G35+[11]MVTNOV!$G35+[11]MVTDEC!$G35+[11]MVTJANV!$G35+[11]MVTFEV!$G35+[11]MVTMARS!$G35+[11]MVTAVRIL!$G35+[11]MVTMAI!$G35+[11]MVTJUIN!$G35+[11]MVTJUIL!$G35+[11]MVTAOUT2018!$G35 -> 39000 | E37: =+[11]MVTAOUT!$D35+[11]MVTSEPT!$E35+[11]MVTOCT!$C35+[11]MVTNOV!$C35+[11]MVTDEC!$C35+[11]MVTJANV!$C35+[11]MVTFEV!$C35+[11]MVTMARS!$C35+[11]MVTAVRIL!$C35+[11]MVTMAI!$C35+[11]MVTJUIN!$C35+[11]MVTJUIL!$C35 -> 19803.638 | F37: =+C37+D37+E37 -> 105968.3 | I37: 25000 | J37: 30000 | K37: =F37-G37-H37-I37-J37 -> 50968.295 | L37: =B37+J37 -> 480000 | M37: =K37+L37 -> 530968.3 | O37: =[11]MVTAOUT!O35+[11]MVTSEPT!P35+[11]MVTOCT!N35+[11]MVTNOV!N35+[11]MVTDEC!N35+[11]MVTJANV!N35+[11]MVTFEV!N35+[11]MVTMARS!N35+[11]MVTAVRIL!N35+[11]MVTMAI!N35+[11]MVTJUIN!N35+[11]MVTJUIL!N35 -> 0 | P37: =[11]MVTAOUT!P35+[11]MVTSEPT!Q35+[11]MVTOCT!O35+[11]MVTNOV!O35+[11]MVTDEC!O35+[11]MVTJANV!O35+[11]MVTFEV!O35+[11]MVTMARS!O35+[11]MVTAVRIL!O35+[11]MVTMAI!O35+[11]MVTJUIN!O35+[11]MVTJUIL!O35 -> 0 | Q37: =+INVENT2016_2017!N37 -> 0 | R37: =[11]MVTAOUT!$Q35+[11]MVTSEPT!$R35+[11]MVTOCT!$P35+[11]MVTNOV!$P35+[11]MVTDEC!$P35+[11]MVTJANV!$P35+[11]MVTFEV!$P35+[11]MVTMARS!$P35+[11]MVTAVRIL!$P35+[11]MVTMAI!$P35+[11]MVTJUIN!$P35+[11]MVTJUIL!$P35+[11]MVTAOUT2018!$P$35 -> 0
A38: SEUNOU RICHELOT | B38: =+INVENT2016_2017!J38 -> 450000 | C38: =+INVENT2016_2017!I38 -> 39428.869 | D38: =[11]MVTAOUT!$H36+[11]MVTSEPT!$I36+[11]MVTOCT!$G36+[11]MVTNOV!$G36+[11]MVTDEC!$G36+[11]MVTJANV!$G36+[11]MVTFEV!$G36+[11]MVTMARS!$G36+[11]MVTAVRIL!$G36+[11]MVTMAI!$G36+[11]MVTJUIN!$G36+[11]MVTJUIL!$G36+[11]MVTAOUT2018!$G36 -> 39000 | E38: =+[11]MVTAOUT!$D36+[11]MVTSEPT!$E36+[11]MVTOCT!$C36+[11]MVTNOV!$C36+[11]MVTDEC!$C36+[11]MVTJANV!$C36+[11]MVTFEV!$C36+[11]MVTMARS!$C36+[11]MVTAVRIL!$C36+[11]MVTMAI!$C36+[11]MVTJUIN!$C36+[11]MVTJUIL!$C36 -> 19818.304 | F38: =+C38+D38+E38 -> 98247.173 | I38: 25000 | J38: 30000 | K38: =F38-G38-H38-I38-J38 -> 43247.173 | L38: =B38+J38 -> 480000 | M38: =K38+L38 -> 523247.17 | O38: =[11]MVTAOUT!O36+[11]MVTSEPT!P36+[11]MVTOCT!N36+[11]MVTNOV!N36+[11]MVTDEC!N36+[11]MVTJANV!N36+[11]MVTFEV!N36+[11]MVTMARS!N36+[11]MVTAVRIL!N36+[11]MVTMAI!N36+[11]MVTJUIN!N36+[11]MVTJUIL!N36 -> 2000000 | P38: =[11]MVTAOUT!P36+[11]MVTSEPT!Q36+[11]MVTOCT!O36+[11]MVTNOV!O36+[11]MVTDEC!O36+[11]MVTJANV!O36+[11]MVTFEV!O36+[11]MVTMARS!O36+[11]MVTAVRIL!O36+[11]MVTMAI!O36+[11]MVTJUIN!O36+[11]MVTJUIL!O36 -> 140000 | Q38: =+INVENT2016_2017!N38 -> 1120000 | R38: =[11]MVTAOUT!$Q36+[11]MVTSEPT!$R36+[11]MVTOCT!$P36+[11]MVTNOV!$P36+[11]MVTDEC!$P36+[11]MVTJANV!$P36+[11]MVTFEV!$P36+[11]MVTMARS!$P36+[11]MVTAVRIL!$P36+[11]MVTMAI!$P36+[11]MVTJUIN!$P36+[11]MVTJUIL!$P36+[11]MVTAOUT2018!$P$36 -> 2200000 | S38: 1040000 | T38: =S38*5/100 -> 52000 | U38: =+S38+T38 -> 1092000 | V38: 43009 | W38: 40000 | X38: OK | Z38: =+AA38-S38 -> 52000 | AA38: =S38+(S38*5/100) -> 1092000
A39: SIME ABEL | B39: 344000 | C39: =+INVENT2016_2017!I39 -> 42886.781 | D39: =[11]MVTAOUT!$H37+[11]MVTSEPT!$I37+[11]MVTOCT!$G37+[11]MVTNOV!$G37+[11]MVTDEC!$G37+[11]MVTJANV!$G37+[11]MVTFEV!$G37+[11]MVTMARS!$G37+[11]MVTAVRIL!$G37+[11]MVTMAI!$G37+[11]MVTJUIN!$G37+[11]MVTJUIL!$G37+[11]MVTAOUT2018!$G37 -> 21000 | E39: =+[11]MVTAOUT!$D37+[11]MVTSEPT!$E37+[11]MVTOCT!$C37+[11]MVTNOV!$C37+[11]MVTDEC!$C37+[11]MVTJANV!$C37+[11]MVTFEV!$C37+[11]MVTMARS!$C37+[11]MVTAVRIL!$C37+[11]MVTMAI!$C37+[11]MVTJUIN!$C37+[11]MVTJUIL!$C37 -> 18455.379 | F39: =+C39+D39+E39 -> 82342.16 | I39: 25000 | J39: 30000 | K39: =F39-G39-H39-I39-J39 -> 27342.16 | L39: 344000 | M39: =L39+K39 -> 371342.16 | O39: =[11]MVTAOUT!O37+[11]MVTSEPT!P37+[11]MVTOCT!N37+[11]MVTNOV!N37+[11]MVTDEC!N37+[11]MVTJANV!N37+[11]MVTFEV!N37+[11]MVTMARS!N37+[11]MVTAVRIL!N37+[11]MVTMAI!N37+[11]MVTJUIN!N37+[11]MVTJUIL!N37 -> 0 | P39: =[11]MVTAOUT!P37+[11]MVTSEPT!Q37+[11]MVTOCT!O37+[11]MVTNOV!O37+[11]MVTDEC!O37+[11]MVTJANV!O37+[11]MVTFEV!O37+[11]MVTMARS!O37+[11]MVTAVRIL!O37+[11]MVTMAI!O37+[11]MVTJUIN!O37+[11]MVTJUIL!O37 -> 0 | Q39: =+INVENT2016_2017!N39 -> 784000 | R39: =[11]MVTAOUT!$Q37+[11]MVTSEPT!$R37+[11]MVTOCT!$P37+[11]MVTNOV!$P37+[11]MVTDEC!$P37+[11]MVTJANV!$P37+[11]MVTFEV!$P37+[11]MVTMARS!$P37+[11]MVTAVRIL!$P37+[11]MVTMAI!$P37+[11]MVTJUIN!$P37+[11]MVTJUIL!$P37+[11]MVTAOUT2018!$P$37 -> 0 | S39: 84000 | T39: =S39*5/100 -> 4200 | U39: =+S39+T39 -> 88200 | V39: 42873 | Z39: =+AA39-S39 -> 4200 | AA39: =S39+(S39*5/100) -> 88200
A40: SIME FONGANG ERIC | B40: =+INVENT2016_2017!J40 -> 450000 | C40: =+INVENT2016_2017!I40 -> 53965.469 | D40: =[11]MVTAOUT!$H38+[11]MVTSEPT!$I38+[11]MVTOCT!$G38+[11]MVTNOV!$G38+[11]MVTDEC!$G38+[11]MVTJANV!$G38+[11]MVTFEV!$G38+[11]MVTMARS!$G38+[11]MVTAVRIL!$G38+[11]MVTMAI!$G38+[11]MVTJUIN!$G38+[11]MVTJUIL!$G38+[11]MVTAOUT2018!$G38 -> 39000 | E40: =+[11]MVTAOUT!$D38+[11]MVTSEPT!$E38+[11]MVTOCT!$C38+[11]MVTNOV!$C38+[11]MVTDEC!$C38+[11]MVTJANV!$C38+[11]MVTFEV!$C38+[11]MVTMARS!$C38+[11]MVTAVRIL!$C38+[11]MVTMAI!$C38+[11]MVTJUIN!$C38+[11]MVTJUIL!$C38 -> 19811.995 | F40: =+C40+D40+E40 -> 112777.46 | I40: 25000 | J40: 30000 | K40: =F40-G40-H40-I40-J40 -> 57777.464 | L40: =B40+J40 -> 480000 | M40: =K40+L40 -> 537777.46 | O40: =[11]MVTAOUT!O38+[11]MVTSEPT!P38+[11]MVTOCT!N38+[11]MVTNOV!N38+[11]MVTDEC!N38+[11]MVTJANV!N38+[11]MVTFEV!N38+[11]MVTMARS!N38+[11]MVTAVRIL!N38+[11]MVTMAI!N38+[11]MVTJUIN!N38+[11]MVTJUIL!N38 -> 0 | P40: =[11]MVTAOUT!P38+[11]MVTSEPT!Q38+[11]MVTOCT!O38+[11]MVTNOV!O38+[11]MVTDEC!O38+[11]MVTJANV!O38+[11]MVTFEV!O38+[11]MVTMARS!O38+[11]MVTAVRIL!O38+[11]MVTMAI!O38+[11]MVTJUIN!O38+[11]MVTJUIL!O38 -> 0 | Q40: =+INVENT2016_2017!N40 -> 1120000 | R40: =[11]MVTAOUT!$Q38+[11]MVTSEPT!$R38+[11]MVTOCT!$P38+[11]MVTNOV!$P38+[11]MVTDEC!$P38+[11]MVTJANV!$P38+[11]MVTFEV!$P38+[11]MVTMARS!$P38+[11]MVTAVRIL!$P38+[11]MVTMAI!$P38+[11]MVTJUIN!$P38+[11]MVTJUIL!$P38+[11]MVTAOUT2018!$P$38 -> 0 | S40: =1000000-R40 -> 1000000 | T40: =S40*5/100 -> 50000 | U40: =+S40+T40 -> 1050000 | V40: 43169 | Z40: =+AA40-S40 -> 50000 | AA40: =S40+(S40*5/100) -> 1050000
A41: SIME MATHIEU | B41: =+INVENT2016_2017!J41 -> 450000 | C41: =+INVENT2016_2017!I41 -> 49454.03 | D41: =[11]MVTAOUT!$H39+[11]MVTSEPT!$I39+[11]MVTOCT!$G39+[11]MVTNOV!$G39+[11]MVTDEC!$G39+[11]MVTJANV!$G39+[11]MVTFEV!$G39+[11]MVTMARS!$G39+[11]MVTAVRIL!$G39+[11]MVTMAI!$G39+[11]MVTJUIN!$G39+[11]MVTJUIL!$G39+[11]MVTAOUT2018!$G39 -> 39000 | E41: =+[11]MVTAOUT!$D39+[11]MVTSEPT!$E39+[11]MVTOCT!$C39+[11]MVTNOV!$C39+[11]MVTDEC!$C39+[11]MVTJANV!$C39+[11]MVTFEV!$C39+[11]MVTMARS!$C39+[11]MVTAVRIL!$C39+[11]MVTMAI!$C39+[11]MVTJUIN!$C39+[11]MVTJUIL!$C39 -> 19810.673 | F41: =+C41+D41+E41 -> 108264.7 | I41: 25000 | J41: 30000 | K41: =F41-G41-H41-I41-J41 -> 53264.702 | L41: =B41+J41 -> 480000 | M41: =K41+L41 -> 533264.7 | O41: =[11]MVTAOUT!O39+[11]MVTSEPT!P39+[11]MVTOCT!N39+[11]MVTNOV!N39+[11]MVTDEC!N39+[11]MVTJANV!N39+[11]MVTFEV!N39+[11]MVTMARS!N39+[11]MVTAVRIL!N39+[11]MVTMAI!N39+[11]MVTJUIN!N39+[11]MVTJUIL!N39 -> 0 | P41: =[11]MVTAOUT!P39+[11]MVTSEPT!Q39+[11]MVTOCT!O39+[11]MVTNOV!O39+[11]MVTDEC!O39+[11]MVTJANV!O39+[11]MVTFEV!O39+[11]MVTMARS!O39+[11]MVTAVRIL!O39+[11]MVTMAI!O39+[11]MVTJUIN!O39+[11]MVTJUIL!O39 -> 0 | Q41: =+INVENT2016_2017!N41 -> 963000 | R41: =[11]MVTAOUT!$Q39+[11]MVTSEPT!$R39+[11]MVTOCT!$P39+[11]MVTNOV!$P39+[11]MVTDEC!$P39+[11]MVTJANV!$P39+[11]MVTFEV!$P39+[11]MVTMARS!$P39+[11]MVTAVRIL!$P39+[11]MVTMAI!$P39+[11]MVTJUIN!$P39+[11]MVTJUIL!$P39+[11]MVTAOUT2018!$P$39 -> 770000 | S41: =Q41-R41 -> 193000 | T41: =S41*5/100 -> 9650 | U41: =+S41+T41 -> 202650 | X41: A ANALYSER | Z41: =+AA41-S41 -> 9650 | AA41: =S41+(S41*5/100) -> 202650
A42: SIME PIERRE | B42: =+INVENT2016_2017!J42 -> 450000 | C42: =+INVENT2016_2017!I42 -> 152184.31 | D42: =[11]MVTAOUT!$H40+[11]MVTSEPT!$I40+[11]MVTOCT!$G40+[11]MVTNOV!$G40+[11]MVTDEC!$G40+[11]MVTJANV!$G40+[11]MVTFEV!$G40+[11]MVTMARS!$G40+[11]MVTAVRIL!$G40+[11]MVTMAI!$G40+[11]MVTJUIN!$G40+[11]MVTJUIL!$G40+[11]MVTAOUT2018!$G40 -> 119000 | E42: =+[11]MVTAOUT!$D40+[11]MVTSEPT!$E40+[11]MVTOCT!$C40+[11]MVTNOV!$C40+[11]MVTDEC!$C40+[11]MVTJANV!$C40+[11]MVTFEV!$C40+[11]MVTMARS!$C40+[11]MVTAVRIL!$C40+[11]MVTMAI!$C40+[11]MVTJUIN!$C40+[11]MVTJUIL!$C40 -> 20955.295 | F42: =+C42+D42+E42 -> 292139.6 | H42: 200000 | I42: 25000 | J42: 30000 | K42: =F42-G42-H42-I42-J42 -> 37139.601 | L42: =B42+J42 -> 480000 | M42: =K42+L42 -> 517139.6 | O42: =[11]MVTAOUT!O40+[11]MVTSEPT!P40+[11]MVTOCT!N40+[11]MVTNOV!N40+[11]MVTDEC!N40+[11]MVTJANV!N40+[11]MVTFEV!N40+[11]MVTMARS!N40+[11]MVTAVRIL!N40+[11]MVTMAI!N40+[11]MVTJUIN!N40+[11]MVTJUIL!N40 -> 290000 | P42: =[11]MVTAOUT!P40+[11]MVTSEPT!Q40+[11]MVTOCT!O40+[11]MVTNOV!O40+[11]MVTDEC!O40+[11]MVTJANV!O40+[11]MVTFEV!O40+[11]MVTMARS!O40+[11]MVTAVRIL!O40+[11]MVTMAI!O40+[11]MVTJUIN!O40+[11]MVTJUIL!O40 -> 20300 | Q42: =+INVENT2016_2017!N42 -> 87200 | R42: =[11]MVTAOUT!$Q40+[11]MVTSEPT!$R40+[11]MVTOCT!$P40+[11]MVTNOV!$P40+[11]MVTDEC!$P40+[11]MVTJANV!$P40+[11]MVTFEV!$P40+[11]MVTMARS!$P40+[11]MVTAVRIL!$P40+[11]MVTMAI!$P40+[11]MVTJUIN!$P40+[11]MVTJUIL!$P40+[11]MVTAOUT2018!$P$40 -> 87200 | S42: 290000 | T42: =S42*5/100 -> 14500 | U42: =+S42+T42 -> 304500 | V42: 43121 | X42: OK | Z42: =+AA42-S42 -> 14500 | AA42: =S42+(S42*5/100) -> 304500
A43: TAGNE NANGUEN MARTIN | B43: =+INVENT2016_2017!J43 -> 450000 | C43: =+INVENT2016_2017!I43 -> 50378.244 | D43: =[11]MVTAOUT!$H41+[11]MVTSEPT!$I41+[11]MVTOCT!$G41+[11]MVTNOV!$G41+[11]MVTDEC!$G41+[11]MVTJANV!$G41+[11]MVTFEV!$G41+[11]MVTMARS!$G41+[11]MVTAVRIL!$G41+[11]MVTMAI!$G41+[11]MVTJUIN!$G41+[11]MVTJUIL!$G41+[11]MVTAOUT2018!$G41 -> 39000 | E43: =+[11]MVTAOUT!$D41+[11]MVTSEPT!$E41+[11]MVTOCT!$C41+[11]MVTNOV!$C41+[11]MVTDEC!$C41+[11]MVTJANV!$C41+[11]MVTFEV!$C41+[11]MVTMARS!$C41+[11]MVTAVRIL!$C41+[11]MVTMAI!$C41+[11]MVTJUIN!$C41+[11]MVTJUIL!$C41 -> 18511.984 | F43: =+C43+D43+E43 -> 107890.23 | I43: 25000 | J43: 30000 | K43: =F43-G43-H43-I43-J43 -> 52890.228 | L43: =B43+J43 -> 480000 | M43: =K43+L43 -> 532890.23 | O43: =[11]MVTAOUT!O41+[11]MVTSEPT!P41+[11]MVTOCT!N41+[11]MVTNOV!N41+[11]MVTDEC!N41+[11]MVTJANV!N41+[11]MVTFEV!N41+[11]MVTMARS!N41+[11]MVTAVRIL!N41+[11]MVTMAI!N41+[11]MVTJUIN!N41+[11]MVTJUIL!N41 -> 0 | P43: =[11]MVTAOUT!P41+[11]MVTSEPT!Q41+[11]MVTOCT!O41+[11]MVTNOV!O41+[11]MVTDEC!O41+[11]MVTJANV!O41+[11]MVTFEV!O41+[11]MVTMARS!O41+[11]MVTAVRIL!O41+[11]MVTMAI!O41+[11]MVTJUIN!O41+[11]MVTJUIL!O41 -> 0 | Q43: =+INVENT2016_2017!N43 -> 0 | R43: =[11]MVTAOUT!$Q41+[11]MVTSEPT!$R41+[11]MVTOCT!$P41+[11]MVTNOV!$P41+[11]MVTDEC!$P41+[11]MVTJANV!$P41+[11]MVTFEV!$P41+[11]MVTMARS!$P41+[11]MVTAVRIL!$P41+[11]MVTMAI!$P41+[11]MVTJUIN!$P41+[11]MVTJUIL!$P41+[11]MVTAOUT2018!$P$41 -> 0
A44: TCHOUAMOU JEAN PAUL | B44: 50000 | C44: =+INVENT2016_2017!I44 -> 0 | D44: =[11]MVTAOUT!$H42+[11]MVTSEPT!$I42+[11]MVTOCT!$G42+[11]MVTNOV!$G42+[11]MVTDEC!$G42+[11]MVTJANV!$G42+[11]MVTFEV!$G42+[11]MVTMARS!$G42+[11]MVTAVRIL!$G42+[11]MVTMAI!$G42+[11]MVTJUIN!$G42+[11]MVTJUIL!$G42+[11]MVTAOUT2018!$G42 -> 0 | E44: =+[11]MVTAOUT!$D42+[11]MVTSEPT!$E42+[11]MVTOCT!$C42+[11]MVTNOV!$C42+[11]MVTDEC!$C42+[11]MVTJANV!$C42+[11]MVTFEV!$C42+[11]MVTMARS!$C42+[11]MVTAVRIL!$C42+[11]MVTMAI!$C42+[11]MVTJUIN!$C42+[11]MVTJUIL!$C42 -> 2156.6179 | F44: =+C44+D44+E44 -> 2156.6179 | I44: 9055 | J44: 30000 | K44: =F44-G44-H44-I44-J44 -> -36898.382 | L44: 50000 | M44: =K44+L44 -> 13101.618 | O44: =[11]MVTAOUT!O42+[11]MVTSEPT!P42+[11]MVTOCT!N42+[11]MVTNOV!N42+[11]MVTDEC!N42+[11]MVTJANV!N42+[11]MVTFEV!N42+[11]MVTMARS!N42+[11]MVTAVRIL!N42+[11]MVTMAI!N42+[11]MVTJUIN!N42+[11]MVTJUIL!N42 -> 0 | P44: =[11]MVTAOUT!P42+[11]MVTSEPT!Q42+[11]MVTOCT!O42+[11]MVTNOV!O42+[11]MVTDEC!O42+[11]MVTJANV!O42+[11]MVTFEV!O42+[11]MVTMARS!O42+[11]MVTAVRIL!O42+[11]MVTMAI!O42+[11]MVTJUIN!O42+[11]MVTJUIL!O42 -> 0 | Q44: =+INVENT2016_2017!N44 -> 0 | R44: =[11]MVTAOUT!$Q42+[11]MVTSEPT!$R42+[11]MVTOCT!$P42+[11]MVTNOV!$P42+[11]MVTDEC!$P42+[11]MVTJANV!$P42+[11]MVTFEV!$P42+[11]MVTMARS!$P42+[11]MVTAVRIL!$P42+[11]MVTMAI!$P42+[11]MVTJUIN!$P42+[11]MVTJUIL!$P42+[11]MVTAOUT2018!$P$42 -> 0
A45: TCHOUAMOU MATHIEU | B45: =+INVENT2016_2017!J45 -> 450000 | C45: =+INVENT2016_2017!I45 -> 47556.521 | D45: =[11]MVTAOUT!$H43+[11]MVTSEPT!$I43+[11]MVTOCT!$G43+[11]MVTNOV!$G43+[11]MVTDEC!$G43+[11]MVTJANV!$G43+[11]MVTFEV!$G43+[11]MVTMARS!$G43+[11]MVTAVRIL!$G43+[11]MVTMAI!$G43+[11]MVTJUIN!$G43+[11]MVTJUIL!$G43+[11]MVTAOUT2018!$G43 -> 39000 | E45: =+[11]MVTAOUT!$D43+[11]MVTSEPT!$E43+[11]MVTOCT!$C43+[11]MVTNOV!$C43+[11]MVTDEC!$C43+[11]MVTJANV!$C43+[11]MVTFEV!$C43+[11]MVTMARS!$C43+[11]MVTAVRIL!$C43+[11]MVTMAI!$C43+[11]MVTJUIN!$C43+[11]MVTJUIL!$C43 -> 19804.254 | F45: =+C45+D45+E45 -> 106360.78 | I45: 25000 | J45: 30000 | K45: =F45-G45-H45-I45-J45 -> 51360.775 | L45: =B45+J45 -> 480000 | M45: =K45+L45 -> 531360.78 | O45: =[11]MVTAOUT!O43+[11]MVTSEPT!P43+[11]MVTOCT!N43+[11]MVTNOV!N43+[11]MVTDEC!N43+[11]MVTJANV!N43+[11]MVTFEV!N43+[11]MVTMARS!N43+[11]MVTAVRIL!N43+[11]MVTMAI!N43+[11]MVTJUIN!N43+[11]MVTJUIL!N43 -> 0 | P45: =[11]MVTAOUT!P43+[11]MVTSEPT!Q43+[11]MVTOCT!O43+[11]MVTNOV!O43+[11]MVTDEC!O43+[11]MVTJANV!O43+[11]MVTFEV!O43+[11]MVTMARS!O43+[11]MVTAVRIL!O43+[11]MVTMAI!O43+[11]MVTJUIN!O43+[11]MVTJUIL!O43 -> 0 | Q45: =+INVENT2016_2017!N45 -> 0 | R45: =[11]MVTAOUT!$Q43+[11]MVTSEPT!$R43+[11]MVTOCT!$P43+[11]MVTNOV!$P43+[11]MVTDEC!$P43+[11]MVTJANV!$P43+[11]MVTFEV!$P43+[11]MVTMARS!$P43+[11]MVTAVRIL!$P43+[11]MVTMAI!$P43+[11]MVTJUIN!$P43+[11]MVTJUIL!$P43+[11]MVTAOUT2018!$P$43 -> 0
A46: TCHOUANTE FRANCOIS | B46: =+INVENT2016_2017!J46 -> 450000 | C46: =+INVENT2016_2017!I46 -> 115459.9 | D46: =[11]MVTAOUT!$H44+[11]MVTSEPT!$I44+[11]MVTOCT!$G44+[11]MVTNOV!$G44+[11]MVTDEC!$G44+[11]MVTJANV!$G44+[11]MVTFEV!$G44+[11]MVTMARS!$G44+[11]MVTAVRIL!$G44+[11]MVTMAI!$G44+[11]MVTJUIN!$G44+[11]MVTJUIL!$G44+[11]MVTAOUT2018!$G44 -> 24000 | E46: =+[11]MVTAOUT!$D44+[11]MVTSEPT!$E44+[11]MVTOCT!$C44+[11]MVTNOV!$C44+[11]MVTDEC!$C44+[11]MVTJANV!$C44+[11]MVTFEV!$C44+[11]MVTMARS!$C44+[11]MVTAVRIL!$C44+[11]MVTMAI!$C44+[11]MVTJUIN!$C44+[11]MVTJUIL!$C44 -> 19340.451 | F46: =+C46+D46+E46 -> 158800.35 | I46: 25000 | J46: 30000 | K46: =F46-G46-H46-I46-J46 -> 103800.35 | L46: =B46+J46 -> 480000 | M46: =K46+L46 -> 583800.35 | O46: =[11]MVTAOUT!O44+[11]MVTSEPT!P44+[11]MVTOCT!N44+[11]MVTNOV!N44+[11]MVTDEC!N44+[11]MVTJANV!N44+[11]MVTFEV!N44+[11]MVTMARS!N44+[11]MVTAVRIL!N44+[11]MVTMAI!N44+[11]MVTJUIN!N44+[11]MVTJUIL!N44 -> 0 | P46: =[11]MVTAOUT!P44+[11]MVTSEPT!Q44+[11]MVTOCT!O44+[11]MVTNOV!O44+[11]MVTDEC!O44+[11]MVTJANV!O44+[11]MVTFEV!O44+[11]MVTMARS!O44+[11]MVTAVRIL!O44+[11]MVTMAI!O44+[11]MVTJUIN!O44+[11]MVTJUIL!O44 -> 0 | Q46: =+INVENT2016_2017!N46 -> 851500 | R46: =[11]MVTAOUT!$Q44+[11]MVTSEPT!$R44+[11]MVTOCT!$P44+[11]MVTNOV!$P44+[11]MVTDEC!$P44+[11]MVTJANV!$P44+[11]MVTFEV!$P44+[11]MVTMARS!$P44+[11]MVTAVRIL!$P44+[11]MVTMAI!$P44+[11]MVTJUIN!$P44+[11]MVTJUIL!$P44+[11]MVTAOUT2018!$P$44 -> 0 | S46: 851500 | T46: =S46*5/100 -> 42575 | U46: =+S46+T46 -> 894075 | V46: 42876 | Z46: =+AA46-S46 -> 42575 | AA46: =S46+(S46*5/100) -> 894075
A47: TCHOUTOU NANA CLAUDE | B47: 30000 | C47: =+INVENT2016_2017!I47 -> 0 | D47: =[11]MVTAOUT!$H45+[11]MVTSEPT!$I45+[11]MVTOCT!$G45+[11]MVTNOV!$G45+[11]MVTDEC!$G45+[11]MVTJANV!$G45+[11]MVTFEV!$G45+[11]MVTMARS!$G45+[11]MVTAVRIL!$G45+[11]MVTMAI!$G45+[11]MVTJUIN!$G45+[11]MVTJUIL!$G45+[11]MVTAOUT2018!$G45 -> 0 | E47: =+[11]MVTAOUT!$D45+[11]MVTSEPT!$E45+[11]MVTOCT!$C45+[11]MVTNOV!$C45+[11]MVTDEC!$C45+[11]MVTJANV!$C45+[11]MVTFEV!$C45+[11]MVTMARS!$C45+[11]MVTAVRIL!$C45+[11]MVTMAI!$C45+[11]MVTJUIN!$C45+[11]MVTJUIL!$C45 -> 1204.954 | F47: =+C47+D47+E47 -> 1204.954 | I47: 7540 | J47: 0 | K47: =F47-G47-H47-I47-J47 -> -6335.046 | L47: 30000 | M47: =K47+L47 -> 23664.954 | O47: =[11]MVTAOUT!O45+[11]MVTSEPT!P45+[11]MVTOCT!N45+[11]MVTNOV!N45+[11]MVTDEC!N45+[11]MVTJANV!N45+[11]MVTFEV!N45+[11]MVTMARS!N45+[11]MVTAVRIL!N45+[11]MVTMAI!N45+[11]MVTJUIN!N45+[11]MVTJUIL!N45 -> 0 | P47: =[11]MVTAOUT!P45+[11]MVTSEPT!Q45+[11]MVTOCT!O45+[11]MVTNOV!O45+[11]MVTDEC!O45+[11]MVTJANV!O45+[11]MVTFEV!O45+[11]MVTMARS!O45+[11]MVTAVRIL!O45+[11]MVTMAI!O45+[11]MVTJUIN!O45+[11]MVTJUIL!O45 -> 0 | Q47: =+INVENT2016_2017!N47 -> 0 | R47: =[11]MVTAOUT!$Q45+[11]MVTSEPT!$R45+[11]MVTOCT!$P45+[11]MVTNOV!$P45+[11]MVTDEC!$P45+[11]MVTJANV!$P45+[11]MVTFEV!$P45+[11]MVTMARS!$P45+[11]MVTAVRIL!$P45+[11]MVTMAI!$P45+[11]MVTJUIN!$P45+[11]MVTJUIL!$P45+[11]MVTAOUT2018!$P$45 -> 0
A48: TIEYAM ERNEST | B48: =+INVENT2016_2017!J48 -> 450000 | C48: =+INVENT2016_2017!I48 -> 64088.865 | D48: =[11]MVTAOUT!$H46+[11]MVTSEPT!$I46+[11]MVTOCT!$G46+[11]MVTNOV!$G46+[11]MVTDEC!$G46+[11]MVTJANV!$G46+[11]MVTFEV!$G46+[11]MVTMARS!$G46+[11]MVTAVRIL!$G46+[11]MVTMAI!$G46+[11]MVTJUIN!$G46+[11]MVTJUIL!$G46+[11]MVTAOUT2018!$G46 -> 36000 | E48: =+[11]MVTAOUT!$D46+[11]MVTSEPT!$E46+[11]MVTOCT!$C46+[11]MVTNOV!$C46+[11]MVTDEC!$C46+[11]MVTJANV!$C46+[11]MVTFEV!$C46+[11]MVTMARS!$C46+[11]MVTAVRIL!$C46+[11]MVTMAI!$C46+[11]MVTJUIN!$C46+[11]MVTJUIL!$C46 -> 19893.286 | F48: =+C48+D48+E48 -> 119982.15 | I48: 25000 | J48: 30000 | K48: =F48-G48-H48-I48-J48 -> 64982.15 | L48: =B48+J48 -> 480000 | M48: =K48+L48 -> 544982.15 | O48: =[11]MVTAOUT!O46+[11]MVTSEPT!P46+[11]MVTOCT!N46+[11]MVTNOV!N46+[11]MVTDEC!N46+[11]MVTJANV!N46+[11]MVTFEV!N46+[11]MVTMARS!N46+[11]MVTAVRIL!N46+[11]MVTMAI!N46+[11]MVTJUIN!N46+[11]MVTJUIL!N46 -> 1000000 | P48: =[11]MVTAOUT!P46+[11]MVTSEPT!Q46+[11]MVTOCT!O46+[11]MVTNOV!O46+[11]MVTDEC!O46+[11]MVTJANV!O46+[11]MVTFEV!O46+[11]MVTMARS!O46+[11]MVTAVRIL!O46+[11]MVTMAI!O46+[11]MVTJUIN!O46+[11]MVTJUIL!O46 -> 30000 | Q48: =+INVENT2016_2017!N48 -> 1064000 | R48: =[11]MVTAOUT!$Q46+[11]MVTSEPT!$R46+[11]MVTOCT!$P46+[11]MVTNOV!$P46+[11]MVTDEC!$P46+[11]MVTJANV!$P46+[11]MVTFEV!$P46+[11]MVTMARS!$P46+[11]MVTAVRIL!$P46+[11]MVTMAI!$P46+[11]MVTJUIN!$P46+[11]MVTJUIL!$P46+[11]MVTAOUT2018!$P$46 -> 1293600 | S48: =1885600-885600 -> 1000000 | T48: =S48*5/100 -> 50000 | U48: =+S48+T48 -> 1050000 | V48: 43241 | X48: OK | Z48: =+AA48-S48 -> 50000 | AA48: =S48+(S48*5/100) -> 1050000
A49: TUGMA PIERRE LOTI | B49: =+INVENT2016_2017!J49 -> 450000 | C49: =+INVENT2016_2017!I49 -> 52395.569 | D49: =[11]MVTAOUT!$H47+[11]MVTSEPT!$I47+[11]MVTOCT!$G47+[11]MVTNOV!$G47+[11]MVTDEC!$G47+[11]MVTJANV!$G47+[11]MVTFEV!$G47+[11]MVTMARS!$G47+[11]MVTAVRIL!$G47+[11]MVTMAI!$G47+[11]MVTJUIN!$G47+[11]MVTJUIL!$G47+[11]MVTAOUT2018!$G47 -> 0 | E49: =+[11]MVTAOUT!$D47+[11]MVTSEPT!$E47+[11]MVTOCT!$C47+[11]MVTNOV!$C47+[11]MVTDEC!$C47+[11]MVTJANV!$C47+[11]MVTFEV!$C47+[11]MVTMARS!$C47+[11]MVTAVRIL!$C47+[11]MVTMAI!$C47+[11]MVTJUIN!$C47+[11]MVTJUIL!$C47 -> 19295.137 | F49: =+C49+D49+E49 -> 71690.706 | I49: 25000 | J49: 30000 | K49: =F49-G49-H49-I49-J49 -> 16690.706 | L49: =B49+J49 -> 480000 | M49: =K49+L49 -> 496690.71 | O49: =[11]MVTAOUT!O47+[11]MVTSEPT!P47+[11]MVTOCT!N47+[11]MVTNOV!N47+[11]MVTDEC!N47+[11]MVTJANV!N47+[11]MVTFEV!N47+[11]MVTMARS!N47+[11]MVTAVRIL!N47+[11]MVTMAI!N47+[11]MVTJUIN!N47+[11]MVTJUIL!N47 -> 0 | P49: =[11]MVTAOUT!P47+[11]MVTSEPT!Q47+[11]MVTOCT!O47+[11]MVTNOV!O47+[11]MVTDEC!O47+[11]MVTJANV!O47+[11]MVTFEV!O47+[11]MVTMARS!O47+[11]MVTAVRIL!O47+[11]MVTMAI!O47+[11]MVTJUIN!O47+[11]MVTJUIL!O47 -> 0 | Q49: =+INVENT2016_2017!N49 -> 1120000 | R49: =[11]MVTAOUT!$Q47+[11]MVTSEPT!$R47+[11]MVTOCT!$P47+[11]MVTNOV!$P47+[11]MVTDEC!$P47+[11]MVTJANV!$P47+[11]MVTFEV!$P47+[11]MVTMARS!$P47+[11]MVTAVRIL!$P47+[11]MVTMAI!$P47+[11]MVTJUIN!$P47+[11]MVTJUIL!$P47+[11]MVTAOUT2018!$P$47 -> 0 | S49: 0 | X49: A REVOIR
A50: YEPMOU JEAN JACQUES | B50: =+INVENT2016_2017!J50 -> 450000 | C50: =+INVENT2016_2017!I50 -> 460575.58 | D50: =[11]MVTAOUT!$H48+[11]MVTSEPT!$I48+[11]MVTOCT!$G48+[11]MVTNOV!$G48+[11]MVTDEC!$G48+[11]MVTJANV!$G48+[11]MVTFEV!$G48+[11]MVTMARS!$G48+[11]MVTAVRIL!$G48+[11]MVTMAI!$G48+[11]MVTJUIN!$G48+[11]MVTJUIL!$G48+[11]MVTAOUT2018!$G48 -> 39000 | E50: =+[11]MVTAOUT!$D48+[11]MVTSEPT!$E48+[11]MVTOCT!$C48+[11]MVTNOV!$C48+[11]MVTDEC!$C48+[11]MVTJANV!$C48+[11]MVTFEV!$C48+[11]MVTMARS!$C48+[11]MVTAVRIL!$C48+[11]MVTMAI!$C48+[11]MVTJUIN!$C48+[11]MVTJUIL!$C48 -> 21144.593 | F50: =+C50+D50+E50 -> 520720.18 | I50: 25000 | J50: 30000 | K50: =F50-G50-H50-I50-J50 -> 465720.18 | L50: =B50+J50 -> 480000 | M50: =K50+L50 -> 945720.18 | O50: =[11]MVTAOUT!O48+[11]MVTSEPT!P48+[11]MVTOCT!N48+[11]MVTNOV!N48+[11]MVTDEC!N48+[11]MVTJANV!N48+[11]MVTFEV!N48+[11]MVTMARS!N48+[11]MVTAVRIL!N48+[11]MVTMAI!N48+[11]MVTJUIN!N48+[11]MVTJUIL!N48 -> 0 | P50: =[11]MVTAOUT!P48+[11]MVTSEPT!Q48+[11]MVTOCT!O48+[11]MVTNOV!O48+[11]MVTDEC!O48+[11]MVTJANV!O48+[11]MVTFEV!O48+[11]MVTMARS!O48+[11]MVTAVRIL!O48+[11]MVTMAI!O48+[11]MVTJUIN!O48+[11]MVTJUIL!O48 -> 0 | Q50: =+INVENT2016_2017!N50 -> 0 | R50: =[11]MVTAOUT!$Q48+[11]MVTSEPT!$R48+[11]MVTOCT!$P48+[11]MVTNOV!$P48+[11]MVTDEC!$P48+[11]MVTJANV!$P48+[11]MVTFEV!$P48+[11]MVTMARS!$P48+[11]MVTAVRIL!$P48+[11]MVTMAI!$P48+[11]MVTJUIN!$P48+[11]MVTJUIL!$P48+[11]MVTAOUT2018!$P$48 -> 0
A51: YOUMBI EMMANUEL | B51: =+INVENT2016_2017!J51 -> 450000 | C51: =+INVENT2016_2017!I51 -> 1205652.8 | D51: =[11]MVTAOUT!$H49+[11]MVTSEPT!$I49+[11]MVTOCT!$G49+[11]MVTNOV!$G49+[11]MVTDEC!$G49+[11]MVTJANV!$G49+[11]MVTFEV!$G49+[11]MVTMARS!$G49+[11]MVTAVRIL!$G49+[11]MVTMAI!$G49+[11]MVTJUIN!$G49+[11]MVTJUIL!$G49+[11]MVTAOUT2018!$G49 -> 39000 | E51: =+[11]MVTAOUT!$D49+[11]MVTSEPT!$E49+[11]MVTOCT!$C49+[11]MVTNOV!$C49+[11]MVTDEC!$C49+[11]MVTJANV!$C49+[11]MVTFEV!$C49+[11]MVTMARS!$C49+[11]MVTAVRIL!$C49+[11]MVTMAI!$C49+[11]MVTJUIN!$C49+[11]MVTJUIL!$C49 -> 23501.828 | F51: =+C51+D51+E51 -> 1268154.7 | I51: 25000 | J51: 30000 | K51: =F51-G51-H51-I51-J51 -> 1213154.7 | L51: =B51+J51 -> 480000 | M51: =K51+L51 -> 1693154.7 | O51: =[11]MVTAOUT!O49+[11]MVTSEPT!P49+[11]MVTOCT!N49+[11]MVTNOV!N49+[11]MVTDEC!N49+[11]MVTJANV!N49+[11]MVTFEV!N49+[11]MVTMARS!N49+[11]MVTAVRIL!N49+[11]MVTMAI!N49+[11]MVTJUIN!N49+[11]MVTJUIL!N49 -> 0 | P51: =[11]MVTAOUT!P49+[11]MVTSEPT!Q49+[11]MVTOCT!O49+[11]MVTNOV!O49+[11]MVTDEC!O49+[11]MVTJANV!O49+[11]MVTFEV!O49+[11]MVTMARS!O49+[11]MVTAVRIL!O49+[11]MVTMAI!O49+[11]MVTJUIN!O49+[11]MVTJUIL!O49 -> 0 | Q51: =+INVENT2016_2017!N51 -> 0 | R51: =[11]MVTAOUT!$Q49+[11]MVTSEPT!$R49+[11]MVTOCT!$P49+[11]MVTNOV!$P49+[11]MVTDEC!$P49+[11]MVTJANV!$P49+[11]MVTFEV!$P49+[11]MVTMARS!$P49+[11]MVTAVRIL!$P49+[11]MVTMAI!$P49+[11]MVTJUIN!$P49+[11]MVTJUIL!$P49+[11]MVTAOUT2018!$P$49 -> 0
A52: MBOGNING TUGMA GUY | B52: =+INVENT2016_2017!J52 -> 450000 | C52: =+INVENT2016_2017!I52 -> 0 | D52: =[11]MVTAOUT!$H50+[11]MVTSEPT!$I50+[11]MVTOCT!$G50+[11]MVTNOV!$G50+[11]MVTDEC!$G50+[11]MVTJANV!$G50+[11]MVTFEV!$G50+[11]MVTMARS!$G50+[11]MVTAVRIL!$G50+[11]MVTMAI!$G50+[11]MVTJUIN!$G50+[11]MVTJUIL!$G50+[11]MVTAOUT2018!$G50 -> 57000 | E52: =+[11]MVTAOUT!$D50+[11]MVTSEPT!$E50+[11]MVTOCT!$C50+[11]MVTNOV!$C50+[11]MVTDEC!$C50+[11]MVTJANV!$C50+[11]MVTFEV!$C50+[11]MVTMARS!$C50+[11]MVTAVRIL!$C50+[11]MVTMAI!$C50+[11]MVTJUIN!$C50+[11]MVTJUIL!$C50 -> 88.527006 | F52: =+C52+D52+E52 -> 57088.527 | I52: 24094 | J52: 30000 | K52: =F52-G52-H52-I52-J52 -> 2994.527 | L52: =B52+J52 -> 480000 | M52: =K52+L52 -> 482994.53 | O52: =[11]MVTAOUT!O50+[11]MVTSEPT!P50+[11]MVTOCT!N50+[11]MVTNOV!N50+[11]MVTDEC!N50+[11]MVTJANV!N50+[11]MVTFEV!N50+[11]MVTMARS!N50+[11]MVTAVRIL!N50+[11]MVTMAI!N50+[11]MVTJUIN!N50+[11]MVTJUIL!N50 -> 1000000 | P52: =[11]MVTAOUT!P50+[11]MVTSEPT!Q50+[11]MVTOCT!O50+[11]MVTNOV!O50+[11]MVTDEC!O50+[11]MVTJANV!O50+[11]MVTFEV!O50+[11]MVTMARS!O50+[11]MVTAVRIL!O50+[11]MVTMAI!O50+[11]MVTJUIN!O50+[11]MVTJUIL!O50 -> 60000 | Q52: =+INVENT2016_2017!N52 -> 0 | R52: =[11]MVTAOUT!$Q50+[11]MVTSEPT!$R50+[11]MVTOCT!$P50+[11]MVTNOV!$P50+[11]MVTDEC!$P50+[11]MVTJANV!$P50+[11]MVTFEV!$P50+[11]MVTMARS!$P50+[11]MVTAVRIL!$P50+[11]MVTMAI!$P50+[11]MVTJUIN!$P50+[11]MVTJUIL!$P50+[11]MVTAOUT2018!$P$50 -> 1060000 | S52: =1060000-1060000 -> 0 | V52: 43148 | Y52: 60000
A53: DJOMO DOMO | B53: 0 | C53: =+INVENT2016_2017!I53 -> 0 | D53: =[11]MVTAOUT!$H51+[11]MVTSEPT!$I51+[11]MVTOCT!$G51+[11]MVTNOV!$G51+[11]MVTDEC!$G51+[11]MVTJANV!$G51+[11]MVTFEV!$G51+[11]MVTMARS!$G51+[11]MVTAVRIL!$G51+[11]MVTMAI!$G51+[11]MVTJUIN!$G51+[11]MVTJUIL!$G51+[11]MVTAOUT2018!$G51 -> 27000 | E53: =+[11]MVTAOUT!$D51+[11]MVTSEPT!$E51+[11]MVTOCT!$C51+[11]MVTNOV!$C51+[11]MVTDEC!$C51+[11]MVTJANV!$C51+[11]MVTFEV!$C51+[11]MVTMARS!$C51+[11]MVTAVRIL!$C51+[11]MVTMAI!$C51+[11]MVTJUIN!$C51+[11]MVTJUIL!$C51 -> 88.527006 | F53: =+C53+D53+E53 -> 27088.527 | I53: 24094 | K53: =F53-G53-H53-I53-J53 -> 2994.527 | L53: 0 | M53: =L53+K53 -> 2994.527 | O53: =[11]MVTAOUT!O51+[11]MVTSEPT!P51+[11]MVTOCT!N51+[11]MVTNOV!N51+[11]MVTDEC!N51+[11]MVTJANV!N51+[11]MVTFEV!N51+[11]MVTMARS!N51+[11]MVTAVRIL!N51+[11]MVTMAI!N51+[11]MVTJUIN!N51+[11]MVTJUIL!N51 -> 0 | P53: =[11]MVTAOUT!P51+[11]MVTSEPT!Q51+[11]MVTOCT!O51+[11]MVTNOV!O51+[11]MVTDEC!O51+[11]MVTJANV!O51+[11]MVTFEV!O51+[11]MVTMARS!O51+[11]MVTAVRIL!O51+[11]MVTMAI!O51+[11]MVTJUIN!O51+[11]MVTJUIL!O51 -> 0 | Q53: =+INVENT2016_2017!N53 -> 0 | R53: =[11]MVTAOUT!$Q51+[11]MVTSEPT!$R51+[11]MVTOCT!$P51+[11]MVTNOV!$P51+[11]MVTDEC!$P51+[11]MVTJANV!$P51+[11]MVTFEV!$P51+[11]MVTMARS!$P51+[11]MVTAVRIL!$P51+[11]MVTMAI!$P51+[11]MVTJUIN!$P51+[11]MVTJUIL!$P51+[11]MVTAOUT2018!$P$51 -> 0
A54: DOMOU FABIEN | B54: 0 | C54: =+INVENT2016_2017!I54 -> 0 | D54: =[11]MVTAOUT!$H52+[11]MVTSEPT!$I52+[11]MVTOCT!$G52+[11]MVTNOV!$G52+[11]MVTDEC!$G52+[11]MVTJANV!$G52+[11]MVTFEV!$G52+[11]MVTMARS!$G52+[11]MVTAVRIL!$G52+[11]MVTMAI!$G52+[11]MVTJUIN!$G52+[11]MVTJUIL!$G52+[11]MVTAOUT2018!$G52 -> 465000 | E54: =+[11]MVTAOUT!$D52+[11]MVTSEPT!$E52+[11]MVTOCT!$C52+[11]MVTNOV!$C52+[11]MVTDEC!$C52+[11]MVTJANV!$C52+[11]MVTFEV!$C52+[11]MVTMARS!$C52+[11]MVTAVRIL!$C52+[11]MVTMAI!$C52+[11]MVTJUIN!$C52+[11]MVTJUIL!$C52 -> 1596.169 | F54: =+C54+D54+E54 -> 466596.17 | I54: 25000 | J54: 30000 | K54: =F54-G54-H54-I54-J54 -> 411596.17 | L54: =B54+J54 -> 30000 | M54: =K54+L54 -> 441596.17 | O54: =[11]MVTAOUT!O52+[11]MVTSEPT!P52+[11]MVTOCT!N52+[11]MVTNOV!N52+[11]MVTDEC!N52+[11]MVTJANV!N52+[11]MVTFEV!N52+[11]MVTMARS!N52+[11]MVTAVRIL!N52+[11]MVTMAI!N52+[11]MVTJUIN!N52+[11]MVTJUIL!N52 -> 0 | P54: =[11]MVTAOUT!P52+[11]MVTSEPT!Q52+[11]MVTOCT!O52+[11]MVTNOV!O52+[11]MVTDEC!O52+[11]MVTJANV!O52+[11]MVTFEV!O52+[11]MVTMARS!O52+[11]MVTAVRIL!O52+[11]MVTMAI!O52+[11]MVTJUIN!O52+[11]MVTJUIL!O52 -> 0 | Q54: =+INVENT2016_2017!N54 -> 0 | R54: =[11]MVTAOUT!$Q52+[11]MVTSEPT!$R52+[11]MVTOCT!$P52+[11]MVTNOV!$P52+[11]MVTDEC!$P52+[11]MVTJANV!$P52+[11]MVTFEV!$P52+[11]MVTMARS!$P52+[11]MVTAVRIL!$P52+[11]MVTMAI!$P52+[11]MVTJUIN!$P52+[11]MVTJUIL!$P52+[11]MVTAOUT2018!$P$52 -> 0
B56: =SUM(B4:B54) -> 18021000 | C56: =SUM(C4:C54) -> 6174113.9 | D56: =SUM(D4:D54) -> 3860500 | E56: =SUM(E4:E54) -> 822600 | F56: =SUM(F4:F54) -> 10857214 | G56: =SUM(G4:G54) -> 0 | H56: =SUM(H4:H54) -> 400000 | I56: =SUM(I4:I54) -> 1059865 | ... U56: =SUM(U4:U54) -> 10796625
W58: 940000 | X58: 12521899
N59: FONDS DE CAISSE 2017 | P59: =B56 -> 18021000 | W59: 1200000 | X59: 85000
N60: RELIQUAT 2017 | P60: =C56 -> 6174113.9 | W60: 5000 | X60: 145000
N61: EPARGNE 2018 | P61: =D56 -> 3860500 | Q61: 1513900 | W61: 963 | X61: 125000
N62: AVANCE | W62: 70000
P63: =SUM(P59:P62) -> 28055614 | W63: =SUM(W58:W62) -> 2215963 | X63: =SUM(X58:X62) -> 12876899
N64: PRÊT 2018 | P64: =S56 -> 10310500
X65: =X63-W63 -> 10660936

Sheet INVENT2017_2018 (4)
B1: CALCUL INTERET EPARGNE AOUT 2017- JUILLET 2018
A3: NOM ET PRENOM | B3: FONDS CAISSE | C3: RELIQUAT | D3: EPARGNE | E3: INTERETEPARGNE | F3: TOTAL AVOIR | G3: SANCTION | H3: AVANCE | I3: COMPLEMENT MUTUELLE | J3: COMPLEMENT FONDS | K3: TOTAL A PERCEVOIR | L3: SAISIE LANGWE GENERALE | M3: SAISIE PENALITE REMBOURSEMENT | N3: AVANCE | O3: NOUVEAU FONDS | P3: SOLDE TOUT COMPTE | Q3: AVANCE | R3: EMPRUNT 2018 | S3: INTERET EMPRUNT | T3: REPORT EMPRUNT 2017 | U3: REMBOURSEMENT 2017-2018 | V3: EMPRUNT EN COURS 2018 | W3: PENALITE | X3: EMPRUNT EN COURS 2018 PENALITE | Y3: DATE REMBOURSEMENT | AA3: TOTAL A PERCEVOIR | AB3: RELIQUAT | AC3: TOTAL PERCU
A4: ASELBY | C4: =+INVENT2016_2017!I4 -> 0 | D4: =[11]MVTAOUT!$H5+[11]MVTSEPT!$I5+[11]MVTOCT!$G5+[11]MVTNOV!$G5+[11]MVTDEC!$G5+[11]MVTJANV!$G5+[11]MVTFEV!$G5+[11]MVTMARS!$G5+[11]MVTAVRIL!$G5+[11]MVTMAI!$G5+[11]MVTJUIN!$G5+[11]MVTJUIL!$G5+[11]MVTAOUT2018!$G5 -> 0 | E4: =+[11]MVTAOUT!$D5+[11]MVTSEPT!$E5+[11]MVTOCT!$C5+[11]MVTNOV!$C5+[11]MVTDEC!$C5+[11]MVTJANV!$C5+[11]MVTFEV!$C5+[11]MVTMARS!$C5+[11]MVTAVRIL!$C5+[11]MVTMAI!$C5+[11]MVTJUIN!$C5+[11]MVTJUIL!$C5 -> 15580.723 | F4: =+C4+D4+E4 -> 15580.723 | K4: =F4-G4-H4-I4-J4 -> 15580.723 | P4: =K4+O4 -> 15580.723 | R4: =[11]MVTAOUT!O5+[11]MVTSEPT!P5+[11]MVTOCT!N5+[11]MVTNOV!N5+[11]MVTDEC!N5+[11]MVTJANV!N5+[11]MVTFEV!N5+[11]MVTMARS!N5+[11]MVTAVRIL!N5+[11]MVTMAI!N5+[11]MVTJUIN!N5+[11]MVTJUIL!N5 -> 0 | S4: =[11]MVTAOUT!P5+[11]MVTSEPT!Q5+[11]MVTOCT!O5+[11]MVTNOV!O5+[11]MVTDEC!O5+[11]MVTJANV!O5+[11]MVTFEV!O5+[11]MVTMARS!O5+[11]MVTAVRIL!O5+[11]MVTMAI!O5+[11]MVTJUIN!O5+[11]MVTJUIL!O5 -> 0 | T4: =+INVENT2016_2017!N4 -> 0 | U4: =[11]MVTAOUT!$Q5+[11]MVTSEPT!$R5+[11]MVTOCT!$P5+[11]MVTNOV!$P5+[11]MVTDEC!$P5+[11]MVTJANV!$P5+[11]MVTFEV!$P5+[11]MVTMARS!$P5+[11]MVTAVRIL!$P5+[11]MVTMAI!$P5+[11]MVTJUIN!$P5+[11]MVTJUIL!$P5+[11]MVTAOUT2018!$P$5 -> 0 | AA4: 394080.93 | AB4: 394081 | AC4: =AA4-AB4 -> -0.072616834
A5: BAKOP ACHILLE | B5: =+INVENT2016_2017!J5 -> 450000 | C5: =+INVENT2016_2017!I5 -> 0 | D5: =[11]MVTAOUT!$H6+[11]MVTSEPT!$I6+[11]MVTOCT!$G6+[11]MVTNOV!$G6+[11]MVTDEC!$G6+[11]MVTJANV!$G6+[11]MVTFEV!$G6+[11]MVTMARS!$G6+[11]MVTAVRIL!$G6+[11]MVTMAI!$G6+[11]MVTJUIN!$G6+[11]MVTJUIL!$G6+[11]MVTAOUT2018!$G6 -> 68000 | E5: =+[11]MVTAOUT!$D6+[11]MVTSEPT!$E6+[11]MVTOCT!$C6+[11]MVTNOV!$C6+[11]MVTDEC!$C6+[11]MVTJANV!$C6+[11]MVTFEV!$C6+[11]MVTMARS!$C6+[11]MVTAVRIL!$C6+[11]MVTMAI!$C6+[11]MVTJUIN!$C6+[11]MVTJUIL!$C6 -> 19643.082 | F5: =+C5+D5+E5 -> 87643.082 | I5: 25000 | J5: 30000 | K5: =F5-G5-H5-I5-J5-92493 -> -59849.918 | O5: =B5+J5 -> 480000 | P5: =K5+O5 -> 420150.08 | R5: =[11]MVTAOUT!O6+[11]MVTSEPT!P6+[11]MVTOCT!N6+[11]MVTNOV!N6+[11]MVTDEC!N6+[11]MVTJANV!N6+[11]MVTFEV!N6+[11]MVTMARS!N6+[11]MVTAVRIL!N6+[11]MVTMAI!N6+[11]MVTJUIN!N6+[11]MVTJUIL!N6 -> 0 | S5: =[11]MVTAOUT!P6+[11]MVTSEPT!Q6+[11]MVTOCT!O6+[11]MVTNOV!O6+[11]MVTDEC!O6+[11]MVTJANV!O6+[11]MVTFEV!O6+[11]MVTMARS!O6+[11]MVTAVRIL!O6+[11]MVTMAI!O6+[11]MVTJUIN!O6+[11]MVTJUIL!O6 -> 0 | T5: =+INVENT2016_2017!N5 -> 588000 | U5: =[11]MVTAOUT!$Q6+[11]MVTSEPT!$R6+[11]MVTOCT!$P6+[11]MVTNOV!$P6+[11]MVTDEC!$P6+[11]MVTJANV!$P6+[11]MVTFEV!$P6+[11]MVTMARS!$P6+[11]MVTAVRIL!$P6+[11]MVTMAI!$P6+[11]MVTJUIN!$P6+[11]MVTJUIL!$P6+[11]MVTAOUT2018!$P$6 -> 0 | V5: 588000 | W5: 88000 | X5: =+V5 -> 588000 | Y5: 42904 | AA5: 0.49369671 | AB5: =+[12]MVTSEPT!$D7 -> 648642.05 | AC5: =AA5-AB5 -> -648641.55
A6: BOUTCHOUANG WILLIAM | B6: =+INVENT2016_2017!J6 -> 450000 | C6: =+INVENT2016_2017!I6 -> 47526.871 | D6: =[11]MVTAOUT!$H7+[11]MVTSEPT!$I7+[11]MVTOCT!$G7+[11]MVTNOV!$G7+[11]MVTDEC!$G7+[11]MVTJANV!$G7+[11]MVTFEV!$G7+[11]MVTMARS!$G7+[11]MVTAVRIL!$G7+[11]MVTMAI!$G7+[11]MVTJUIN!$G7+[11]MVTJUIL!$G7+[11]MVTAOUT2018!$G7 -> 39000 | E6: =+[11]MVTAOUT!$D7+[11]MVTSEPT!$E7+[11]MVTOCT!$C7+[11]MVTNOV!$C7+[11]MVTDEC!$C7+[11]MVTJANV!$C7+[11]MVTFEV!$C7+[11]MVTMARS!$C7+[11]MVTAVRIL!$C7+[11]MVTMAI!$C7+[11]MVTJUIN!$C7+[11]MVTJUIL!$C7 -> 19804.409 | F6: =+C6+D6+E6 -> 106331.28 | I6: 25000 | J6: 30000 | K6: =F6-G6-H6-I6-J6-15000 -> 36331.28 | L6: 15000 | N6: 35000 | O6: =B6+J6 -> 480000 | P6: =K6+O6 -> 516331.28 | R6: =[11]MVTAOUT!O7+[11]MVTSEPT!P7+[11]MVTOCT!N7+[11]MVTNOV!N7+[11]MVTDEC!N7+[11]MVTJANV!N7+[11]MVTFEV!N7+[11]MVTMARS!N7+[11]MVTAVRIL!N7+[11]MVTMAI!N7+[11]MVTJUIN!N7+[11]MVTJUIL!N7 -> 0 | S6: =[11]MVTAOUT!P7+[11]MVTSEPT!Q7+[11]MVTOCT!O7+[11]MVTNOV!O7+[11]MVTDEC!O7+[11]MVTJANV!O7+[11]MVTFEV!O7+[11]MVTMARS!O7+[11]MVTAVRIL!O7+[11]MVTMAI!O7+[11]MVTJUIN!O7+[11]MVTJUIL!O7 -> 0 | T6: =+INVENT2016_2017!N6 -> 784000 | U6: =[11]MVTAOUT!$Q7+[11]MVTSEPT!$R7+[11]MVTOCT!$P7+[11]MVTNOV!$P7+[11]MVTDEC!$P7+[11]MVTJANV!$P7+[11]MVTFEV!$P7+[11]MVTMARS!$P7+[11]MVTAVRIL!$P7+[11]MVTMAI!$P7+[11]MVTJUIN!$P7+[11]MVTJUIL!$P7+[11]MVTAOUT2018!$P$7 -> 823200 | V6: 0 | AA6: 36331.28 | AB6: =+[12]MVTSEPT!$D8 -> 671889.77 | AC6: =AA6-AB6 -> -635558.49
A7: CHINGUE FABRICE | B7: =+INVENT2016_2017!J7 -> 450000 | C7: =+INVENT2016_2017!I7 -> 39888.74 | D7: =[11]MVTAOUT!$H8+[11]MVTSEPT!$I8+[11]MVTOCT!$G8+[11]MVTNOV!$G8+[11]MVTDEC!$G8+[11]MVTJANV!$G8+[11]MVTFEV!$G8+[11]MVTMARS!$G8+[11]MVTAVRIL!$G8+[11]MVTMAI!$G8+[11]MVTJUIN!$G8+[11]MVTJUIL!$G8+[11]MVTAOUT2018!$G8 -> 39000 | E7: =+[11]MVTAOUT!$D8+[11]MVTSEPT!$E8+[11]MVTOCT!$C8+[11]MVTNOV!$C8+[11]MVTDEC!$C8+[11]MVTJANV!$C8+[11]MVTFEV!$C8+[11]MVTMARS!$C8+[11]MVTAVRIL!$C8+[11]MVTMAI!$C8+[11]MVTJUIN!$C8+[11]MVTJUIL!$C8 -> 19815.212 | F7: =+C7+D7+E7 -> 98703.952 | I7: 25000 | J7: 30000 | K7: =F7-G7-H7-I7-J7-15000 -> 28703.952 | L7: 15000 | N7: 25000 | O7: =B7+J7 -> 480000 | P7: =K7+O7 -> 508703.95 | R7: =[11]MVTAOUT!O8+[11]MVTSEPT!P8+[11]MVTOCT!N8+[11]MVTNOV!N8+[11]MVTDEC!N8+[11]MVTJANV!N8+[11]MVTFEV!N8+[11]MVTMARS!N8+[11]MVTAVRIL!N8+[11]MVTMAI!N8+[11]MVTJUIN!N8+[11]MVTJUIL!N8 -> 0 | S7: =[11]MVTAOUT!P8+[11]MVTSEPT!Q8+[11]MVTOCT!O8+[11]MVTNOV!O8+[11]MVTDEC!O8+[11]MVTJANV!O8+[11]MVTFEV!O8+[11]MVTMARS!O8+[11]MVTAVRIL!O8+[11]MVTMAI!O8+[11]MVTJUIN!O8+[11]MVTJUIL!O8 -> 0 | T7: =+INVENT2016_2017!N7 -> 1293600 | U7: =[11]MVTAOUT!$Q8+[11]MVTSEPT!$R8+[11]MVTOCT!$P8+[11]MVTNOV!$P8+[11]MVTDEC!$P8+[11]MVTJANV!$P8+[11]MVTFEV!$P8+[11]MVTMARS!$P8+[11]MVTAVRIL!$P8+[11]MVTMAI!$P8+[11]MVTJUIN!$P8+[11]MVTJUIL!$P8+[11]MVTAOUT2018!$P$8 -> 1293500 | AA7: 28703.952 | AB7: =+[12]MVTSEPT!$D9 -> 312839.89 | AC7: =AA7-AB7 -> -284135.94
A8: DJOMO DOMO | AA8: 2994.527 | AB8: =+[12]MVTSEPT!$D10 -> 1119730.2 | AC8: =AA8-AB8 -> -1116735.7
A9: DJOMO JEAN PAUL | B9: =+INVENT2016_2017!J8 -> 450000 | C9: =+INVENT2016_2017!I8 -> 23224.098 | D9: =[11]MVTAOUT!$H9+[11]MVTSEPT!$I9+[11]MVTOCT!$G9+[11]MVTNOV!$G9+[11]MVTDEC!$G9+[11]MVTJANV!$G9+[11]MVTFEV!$G9+[11]MVTMARS!$G9+[11]MVTAVRIL!$G9+[11]MVTMAI!$G9+[11]MVTJUIN!$G9+[11]MVTJUIL!$G9+[11]MVTAOUT2018!$G9 -> 39000 | E9: =+[11]MVTAOUT!$D9+[11]MVTSEPT!$E9+[11]MVTOCT!$C9+[11]MVTNOV!$C9+[11]MVTDEC!$C9+[11]MVTJANV!$C9+[11]MVTFEV!$C9+[11]MVTMARS!$C9+[11]MVTAVRIL!$C9+[11]MVTMAI!$C9+[11]MVTJUIN!$C9+[11]MVTJUIL!$C9 -> 19830.392 | F9: =+C9+D9+E9 -> 82054.49 | I9: 25000 | J9: 30000 | K9: =F9-G9-H9-I9-J9+33000-34650-15000 -> 10404.49 | L9: 15000 | M9: 34650 | N9: 10000 | O9: =B9+J9 -> 480000 | P9: =K9+O9 -> 490404.49 | R9: =[11]MVTAOUT!O9+[11]MVTSEPT!P9+[11]MVTOCT!N9+[11]MVTNOV!N9+[11]MVTDEC!N9+[11]MVTJANV!N9+[11]MVTFEV!N9+[11]MVTMARS!N9+[11]MVTAVRIL!N9+[11]MVTMAI!N9+[11]MVTJUIN!N9+[11]MVTJUIL!N9 -> 693000 | S9: =[11]MVTAOUT!P9+[11]MVTSEPT!Q9+[11]MVTOCT!O9+[11]MVTNOV!O9+[11]MVTDEC!O9+[11]MVTJANV!O9+[11]MVTFEV!O9+[11]MVTMARS!O9+[11]MVTAVRIL!O9+[11]MVTMAI!O9+[11]MVTJUIN!O9+[11]MVTJUIL!O9 -> 49000 | T9: =+INVENT2016_2017!N8 -> 1017000 | U9: =[11]MVTAOUT!$Q9+[11]MVTSEPT!$R9+[11]MVTOCT!$P9+[11]MVTNOV!$P9+[11]MVTDEC!$P9+[11]MVTJANV!$P9+[11]MVTFEV!$P9+[11]MVTMARS!$P9+[11]MVTAVRIL!$P9+[11]MVTMAI!$P9+[11]MVTJUIN!$P9+[11]MVTJUIL!$P9+[11]MVTAOUT2018!$P$9 -> 1040000 | V9: 693000 | W9: 0 | X9: =+V9+W9 -> 693000 | Y9: 43121 | AA9: 10404.49 | AB9: =+[12]MVTSEPT!$D11 -> 653645.29 | AC9: =AA9-AB9 -> -643240.8
A10: DJOUKWE NANGUEN GUY BLAISE | B10: =+INVENT2016_2017!J9 -> 450000 | C10: =+INVENT2016_2017!I9 -> 69006.04 | D10: =[11]MVTAOUT!$H10+[11]MVTSEPT!$I10+[11]MVTOCT!$G10+[11]MVTNOV!$G10+[11]MVTDEC!$G10+[11]MVTJANV!$G10+[11]MVTFEV!$G10+[11]MVTMARS!$G10+[11]MVTAVRIL!$G10+[11]MVTMAI!$G10+[11]MVTJUIN!$G10+[11]MVTJUIL!$G10+[11]MVTAOUT2018!$G10 -> 51000 | E10: =+[11]MVTAOUT!$D10+[11]MVTSEPT!$E10+[11]MVTOCT!$C10+[11]MVTNOV!$C10+[11]MVTDEC!$C10+[11]MVTJANV!$C10+[11]MVTFEV!$C10+[11]MVTMARS!$C10+[11]MVTAVRIL!$C10+[11]MVTMAI!$C10+[11]MVTJUIN!$C10+[11]MVTJUIL!$C10 -> 20026.542 | F10: =+C10+D10+E10 -> 140032.58 | I10: 25000 | J10: 30000 | K10: =F10-G10-H10-I10-J10-15000 -> 70032.582 | L10: 15000 | N10: 70000 | O10: =B10+J10 -> 480000 | P10: =K10+O10 -> 550032.58 | R10: =[11]MVTAOUT!O10+[11]MVTSEPT!P10+[11]MVTOCT!N10+[11]MVTNOV!N10+[11]MVTDEC!N10+[11]MVTJANV!N10+[11]MVTFEV!N10+[11]MVTMARS!N10+[11]MVTAVRIL!N10+[11]MVTMAI!N10+[11]MVTJUIN!N10+[11]MVTJUIL!N10 -> 0 | S10: =[11]MVTAOUT!P10+[11]MVTSEPT!Q10+[11]MVTOCT!O10+[11]MVTNOV!O10+[11]MVTDEC!O10+[11]MVTJANV!O10+[11]MVTFEV!O10+[11]MVTMARS!O10+[11]MVTAVRIL!O10+[11]MVTMAI!O10+[11]MVTJUIN!O10+[11]MVTJUIL!O10 -> 0 | T10: =+INVENT2016_2017!N9 -> 140000 | U10: =[11]MVTAOUT!$Q10+[11]MVTSEPT!$R10+[11]MVTOCT!$P10+[11]MVTNOV!$P10+[11]MVTDEC!$P10+[11]MVTJANV!$P10+[11]MVTFEV!$P10+[11]MVTMARS!$P10+[11]MVTAVRIL!$P10+[11]MVTMAI!$P10+[11]MVTJUIN!$P10+[11]MVTJUIL!$P10+[11]MVTAOUT2018!$P$10 -> 210000 | AA10: 70032.582 | AB10: =+[12]MVTSEPT!$D12 -> 644946.59 | AC10: =AA10-AB10 -> -574914.01
AC11: =AA11-AB11 -> 0
A12: DJOUNKEP SAMUEL | B12: =+INVENT2016_2017!J11 -> 450000 | C12: =+INVENT2016_2017!I11 -> 730153.83 | D12: =[11]MVTAOUT!$H11+[11]MVTSEPT!$I11+[11]MVTOCT!$G11+[11]MVTNOV!$G11+[11]MVTDEC!$G11+[11]MVTJANV!$G11+[11]MVTFEV!$G11+[11]MVTMARS!$G11+[11]MVTAVRIL!$G11+[11]MVTMAI!$G11+[11]MVTJUIN!$G11+[11]MVTJUIL!$G11+[11]MVTAOUT2018!$G11 -> 233000 | E12: =+[11]MVTAOUT!$D11+[11]MVTSEPT!$E11+[11]MVTOCT!$C11+[11]MVTNOV!$C11+[11]MVTDEC!$C11+[11]MVTJANV!$C11+[11]MVTFEV!$C11+[11]MVTMARS!$C11+[11]MVTAVRIL!$C11+[11]MVTMAI!$C11+[11]MVTJUIN!$C11+[11]MVTJUIL!$C11 -> 22119.98 | F12: =+C12+D12+E12 -> 985273.81 | K12: =F12-G12-H12-I12-J12-35000 -> 950273.81 | O12: =B12+J12 -> 450000 | P12: =K12+O12 -> 1400273.8 | R12: =[11]MVTAOUT!O11+[11]MVTSEPT!P11+[11]MVTOCT!N11+[11]MVTNOV!N11+[11]MVTDEC!N11+[11]MVTJANV!N11+[11]MVTFEV!N11+[11]MVTMARS!N11+[11]MVTAVRIL!N11+[11]MVTMAI!N11+[11]MVTJUIN!N11+[11]MVTJUIL!N11 -> 0 | S12: =[11]MVTAOUT!P11+[11]MVTSEPT!Q11+[11]MVTOCT!O11+[11]MVTNOV!O11+[11]MVTDEC!O11+[11]MVTJANV!O11+[11]MVTFEV!O11+[11]MVTMARS!O11+[11]MVTAVRIL!O11+[11]MVTMAI!O11+[11]MVTJUIN!O11+[11]MVTJUIL!O11 -> 0 | T12: =+INVENT2016_2017!N11 -> 1120000 | U12: =[11]MVTAOUT!$Q11+[11]MVTSEPT!$R11+[11]MVTOCT!$P11+[11]MVTNOV!$P11+[11]MVTDEC!$P11+[11]MVTJANV!$P11+[11]MVTFEV!$P11+[11]MVTMARS!$P11+[11]MVTAVRIL!$P11+[11]MVTMAI!$P11+[11]MVTJUIN!$P11+[11]MVTJUIL!$P11+[11]MVTAOUT2018!$P$11 -> 1100000 | V12: 0 | AA12: 950273.81 | AB12: 0 | AC12: =AA12-AB12 -> 950273.81
A13: DJUOMBESSY ANTOINE | B13: =+INVENT2016_2017!J12 -> 450000 | C13: =+INVENT2016_2017!I12 -> 47654.584 | D13: =[11]MVTAOUT!$H12+[11]MVTSEPT!$I12+[11]MVTOCT!$G12+[11]MVTNOV!$G12+[11]MVTDEC!$G12+[11]MVTJANV!$G12+[11]MVTFEV!$G12+[11]MVTMARS!$G12+[11]MVTAVRIL!$G12+[11]MVTMAI!$G12+[11]MVTJUIN!$G12+[11]MVTJUIL!$G12+[11]MVTAOUT2018!$G12 -> 39000 | E13: =+[11]MVTAOUT!$D12+[11]MVTSEPT!$E12+[11]MVTOCT!$C12+[11]MVTNOV!$C12+[11]MVTDEC!$C12+[11]MVTJANV!$C12+[11]MVTFEV!$C12+[11]MVTMARS!$C12+[11]MVTAVRIL!$C12+[11]MVTMAI!$C12+[11]MVTJUIN!$C12+[11]MVTJUIL!$C12 -> 19804.498 | F13: =+C13+D13+E13 -> 106459.08 | I13: 25000 | J13: 30000 | K13: =F13-G13-H13-I13-J13-51459 -> 0.082340617 | L13: 25000 | M13: 26459 | O13: =B13+J13 -> 480000 | P13: =K13+O13 -> 480000.08 | R13: =[11]MVTAOUT!O12+[11]MVTSEPT!P12+[11]MVTOCT!N12+[11]MVTNOV!N12+[11]MVTDEC!N12+[11]MVTJANV!N12+[11]MVTFEV!N12+[11]MVTMARS!N12+[11]MVTAVRIL!N12+[11]MVTMAI!N12+[11]MVTJUIN!N12+[11]MVTJUIL!N12 -> 1000000 | S13: =[11]MVTAOUT!P12+[11]MVTSEPT!Q12+[11]MVTOCT!O12+[11]MVTNOV!O12+[11]MVTDEC!O12+[11]MVTJANV!O12+[11]MVTFEV!O12+[11]MVTMARS!O12+[11]MVTAVRIL!O12+[11]MVTMAI!O12+[11]MVTJUIN!O12+[11]MVTJUIL!O12 -> 40000 | T13: =+INVENT2016_2017!N12 -> 784000 | U13: =[11]MVTAOUT!$Q12+[11]MVTSEPT!$R12+[11]MVTOCT!$P12+[11]MVTNOV!$P12+[11]MVTDEC!$P12+[11]MVTJANV!$P12+[11]MVTFEV!$P12+[11]MVTMARS!$P12+[11]MVTAVRIL!$P12+[11]MVTMAI!$P12+[11]MVTJUIN!$P12+[11]MVTJUIL!$P12+[11]MVTAOUT2018!$P$12 -> 770000 | V13: 1000000 | W13: =V13*5/100 -> 50000 | X13: =+V13+W128 -> 1000000 | Y13: 43205 | AA13: 0.082340617 | AB13: =+[12]MVTSEPT!$D13 -> 912642.47 | AC13: =AA13-AB13 -> -912642.38
A14: DOMOU FABIEN | AB14: =+[12]MVTSEPT!$D14 -> 634013.91 | AC14: =AA14-AB14 -> -634013.91
A15: DONHOU DAVID | B15: =+INVENT2016_2017!J13 -> 450000 | C15: =+INVENT2016_2017!I13 -> 110017.95 | D15: =[11]MVTAOUT!$H13+[11]MVTSEPT!$I13+[11]MVTOCT!$G13+[11]MVTNOV!$G13+[11]MVTDEC!$G13+[11]MVTJANV!$G13+[11]MVTFEV!$G13+[11]MVTMARS!$G13+[11]MVTAVRIL!$G13+[11]MVTMAI!$G13+[11]MVTJUIN!$G13+[11]MVTJUIL!$G13+[11]MVTAOUT2018!$G13 -> 39000 | E15: =+[11]MVTAOUT!$D13+[11]MVTSEPT!$E13+[11]MVTOCT!$C13+[11]MVTNOV!$C13+[11]MVTDEC!$C13+[11]MVTJANV!$C13+[11]MVTFEV!$C13+[11]MVTMARS!$C13+[11]MVTAVRIL!$C13+[11]MVTMAI!$C13+[11]MVTJUIN!$C13+[11]MVTJUIL!$C13 -> 19979.185 | F15: =+C15+D15+E15 -> 168997.13 | I15: 25000 | J15: 30000 | K15: =F15-G15-H15-I15-J15 -> 113997.13 | O15: =B15+J15 -> 480000 | P15: =K15+O15 -> 593997.13 | R15: =[11]MVTAOUT!O13+[11]MVTSEPT!P13+[11]MVTOCT!N13+[11]MVTNOV!N13+[11]MVTDEC!N13+[11]MVTJANV!N13+[11]MVTFEV!N13+[11]MVTMARS!N13+[11]MVTAVRIL!N13+[11]MVTMAI!N13+[11]MVTJUIN!N13+[11]MVTJUIL!N13 -> 700000 | S15: =[11]MVTAOUT!P13+[11]MVTSEPT!Q13+[11]MVTOCT!O13+[11]MVTNOV!O13+[11]MVTDEC!O13+[11]MVTJANV!O13+[11]MVTFEV!O13+[11]MVTMARS!O13+[11]MVTAVRIL!O13+[11]MVTMAI!O13+[11]MVTJUIN!O13+[11]MVTJUIL!O13 -> 42000 | T15: =+INVENT2016_2017!N13 -> 0 | U15: =[11]MVTAOUT!$Q13+[11]MVTSEPT!$R13+[11]MVTOCT!$P13+[11]MVTNOV!$P13+[11]MVTDEC!$P13+[11]MVTJANV!$P13+[11]MVTFEV!$P13+[11]MVTMARS!$P13+[11]MVTAVRIL!$P13+[11]MVTMAI!$P13+[11]MVTJUIN!$P13+[11]MVTJUIL!$P13+[11]MVTAOUT2018!$P$13 -> 0 | V15: 700000 | W15: 0 | X15: =+V15+W15 -> 700000 | Y15: 43148 | AA15: 113997.13 | AB15: =+[12]MVTSEPT!$D15 -> 761566.84 | AC15: =AA15-AB15 -> -647569.71
A16: FOTSO THOMAS | B16: =+INVENT2016_2017!J14 -> 450000 | C16: =+INVENT2016_2017!I14 -> 47415.821 | D16: =[11]MVTAOUT!$H14+[11]MVTSEPT!$I14+[11]MVTOCT!$G14+[11]MVTNOV!$G14+[11]MVTDEC!$G14+[11]MVTJANV!$G14+[11]MVTFEV!$G14+[11]MVTMARS!$G14+[11]MVTAVRIL!$G14+[11]MVTMAI!$G14+[11]MVTJUIN!$G14+[11]MVTJUIL!$G14+[11]MVTAOUT2018!$G14 -> 40000 | E16: =+[11]MVTAOUT!$D14+[11]MVTSEPT!$E14+[11]MVTOCT!$C14+[11]MVTNOV!$C14+[11]MVTDEC!$C14+[11]MVTJANV!$C14+[11]MVTFEV!$C14+[11]MVTMARS!$C14+[11]MVTAVRIL!$C14+[11]MVTMAI!$C14+[11]MVTJUIN!$C14+[11]MVTJUIL!$C14 -> 19803.731 | F16: =+C16+D16+E16 -> 107219.55 | I16: 25000 | J16: 30000 | K16: =F16-G16-H16-I16-J16-25000 -> 27219.552 | L16: 25000 | N16: 25000 | O16: =B16+J16 -> 480000 | P16: =K16+O16 -> 507219.55 | R16: =[11]MVTAOUT!O14+[11]MVTSEPT!P14+[11]MVTOCT!N14+[11]MVTNOV!N14+[11]MVTDEC!N14+[11]MVTJANV!N14+[11]MVTFEV!N14+[11]MVTMARS!N14+[11]MVTAVRIL!N14+[11]MVTMAI!N14+[11]MVTJUIN!N14+[11]MVTJUIL!N14 -> 600000 | S16: =[11]MVTAOUT!P14+[11]MVTSEPT!Q14+[11]MVTOCT!O14+[11]MVTNOV!O14+[11]MVTDEC!O14+[11]MVTJANV!O14+[11]MVTFEV!O14+[11]MVTMARS!O14+[11]MVTAVRIL!O14+[11]MVTMAI!O14+[11]MVTJUIN!O14+[11]MVTJUIL!O14 -> 66000 | T16: =+INVENT2016_2017!N14 -> 1293600 | U16: =[11]MVTAOUT!$Q14+[11]MVTSEPT!$R14+[11]MVTOCT!$P14+[11]MVTNOV!$P14+[11]MVTDEC!$P14+[11]MVTJANV!$P14+[11]MVTFEV!$P14+[11]MVTMARS!$P14+[11]MVTAVRIL!$P14+[11]MVTMAI!$P14+[11]MVTJUIN!$P14+[11]MVTJUIL!$P14+[11]MVTAOUT2018!$P$14 -> 1959000 | V16: =666000-666000 -> 0 | Y16: 42993 | AA16: 27219.552 | AB16: =+[12]MVTSEPT!$D16 -> 861035.46 | AC16: =AA16-AB16 -> -833815.91
A17: HENGUE PAUL OMER | B17: =+INVENT2016_2017!J15 -> 450000 | C17: =+INVENT2016_2017!I15 -> 0 | D17: =[11]MVTAOUT!$H15+[11]MVTSEPT!$I15+[11]MVTOCT!$G15+[11]MVTNOV!$G15+[11]MVTDEC!$G15+[11]MVTJANV!$G15+[11]MVTFEV!$G15+[11]MVTMARS!$G15+[11]MVTAVRIL!$G15+[11]MVTMAI!$G15+[11]MVTJUIN!$G15+[11]MVTJUIL!$G15+[11]MVTAOUT2018!$G15 -> 39000 | E17: =+[11]MVTAOUT!$D15+[11]MVTSEPT!$E15+[11]MVTOCT!$C15+[11]MVTNOV!$C15+[11]MVTDEC!$C15+[11]MVTJANV!$C15+[11]MVTFEV!$C15+[11]MVTMARS!$C15+[11]MVTAVRIL!$C15+[11]MVTMAI!$C15+[11]MVTJUIN!$C15+[11]MVTJUIL!$C15 -> 20021.15 | F17: =+C17+D17+E17 -> 59021.15 | I17: 25000 | J17: 30000 | K17: =F17-G17-H17-I17-J17-25000-90000 -> -110978.85 | L17: 25000 | O17: =B17+J17 -> 480000 | P17: =K17+O17 -> 369021.15 | R17: =[11]MVTAOUT!O15+[11]MVTSEPT!P15+[11]MVTOCT!N15+[11]MVTNOV!N15+[11]MVTDEC!N15+[11]MVTJANV!N15+[11]MVTFEV!N15+[11]MVTMARS!N15+[11]MVTAVRIL!N15+[11]MVTMAI!N15+[11]MVTJUIN!N15+[11]MVTJUIL!N15 -> 0 | S17: =[11]MVTAOUT!P15+[11]MVTSEPT!Q15+[11]MVTOCT!O15+[11]MVTNOV!O15+[11]MVTDEC!O15+[11]MVTJANV!O15+[11]MVTFEV!O15+[11]MVTMARS!O15+[11]MVTAVRIL!O15+[11]MVTMAI!O15+[11]MVTJUIN!O15+[11]MVTJUIL!O15 -> 0 | T17: =+INVENT2016_2017!N15 -> 0 | U17: =[11]MVTAOUT!$Q15+[11]MVTSEPT!$R15+[11]MVTOCT!$P15+[11]MVTNOV!$P15+[11]MVTDEC!$P15+[11]MVTJANV!$P15+[11]MVTFEV!$P15+[11]MVTMARS!$P15+[11]MVTAVRIL!$P15+[11]MVTMAI!$P15+[11]MVTJUIN!$P15+[11]MVTJUIL!$P15+[11]MVTAOUT2018!$P$15 -> 0 | AA17: 3998.5842 | AB17: =+[12]MVTSEPT!$D17 -> 6032356.6 | AC17: =AA17-AB17 -> -6028358
A18: HODIEP JULES | B18: 80000 | C18: =+INVENT2016_2017!I16 -> 0 | D18: =[11]MVTAOUT!$H16+[11]MVTSEPT!$I16+[11]MVTOCT!$G16+[11]MVTNOV!$G16+[11]MVTDEC!$G16+[11]MVTJANV!$G16+[11]MVTFEV!$G16+[11]MVTMARS!$G16+[11]MVTAVRIL!$G16+[11]MVTMAI!$G16+[11]MVTJUIN!$G16+[11]MVTJUIL!$G16+[11]MVTAOUT2018!$G16 -> 0 | E18: =+[11]MVTAOUT!$D16+[11]MVTSEPT!$E16+[11]MVTOCT!$C16+[11]MVTNOV!$C16+[11]MVTDEC!$C16+[11]MVTJANV!$C16+[11]MVTFEV!$C16+[11]MVTMARS!$C16+[11]MVTAVRIL!$C16+[11]MVTMAI!$C16+[11]MVTJUIN!$C16+[11]MVTJUIL!$C16 -> 3334.7558 | F18: =+C18+D18+E18 -> 3334.7558 | I18: 6848 | J18: 0 | K18: =F18-G18-H18-I18-J18 -> -3513.2442 | O18: 80000 | P18: =K18+O18 -> 76486.756 | R18: =[11]MVTAOUT!O16+[11]MVTSEPT!P16+[11]MVTOCT!N16+[11]MVTNOV!N16+[11]MVTDEC!N16+[11]MVTJANV!N16+[11]MVTFEV!N16+[11]MVTMARS!N16+[11]MVTAVRIL!N16+[11]MVTMAI!N16+[11]MVTJUIN!N16+[11]MVTJUIL!N16 -> 0 | S18: =[11]MVTAOUT!P16+[11]MVTSEPT!Q16+[11]MVTOCT!O16+[11]MVTNOV!O16+[11]MVTDEC!O16+[11]MVTJANV!O16+[11]MVTFEV!O16+[11]MVTMARS!O16+[11]MVTAVRIL!O16+[11]MVTMAI!O16+[11]MVTJUIN!O16+[11]MVTJUIL!O16 -> 0 | T18: =+INVENT2016_2017!N16 -> 0 | U18: =[11]MVTAOUT!$Q16+[11]MVTSEPT!$R16+[11]MVTOCT!$P16+[11]MVTNOV!$P16+[11]MVTDEC!$P16+[11]MVTJANV!$P16+[11]MVTFEV!$P16+[11]MVTMARS!$P16+[11]MVTAVRIL!$P16+[11]MVTMAI!$P16+[11]MVTJUIN!$P16+[11]MVTJUIL!$P16+[11]MVTAOUT2018!$P$16 -> 0 | AA18: 59.217017 | AB18: =+[12]MVTSEPT!$D18 -> 660968.36 | AC18: =AA18-AB18 -> -660909.15
A19: HOTCHO BENJAMIN | B19: =+INVENT2016_2017!J17 -> 450000 | C19: =+INVENT2016_2017!I17 -> 82839.28 | D19: =[11]MVTAOUT!$H17+[11]MVTSEPT!$I17+[11]MVTOCT!$G17+[11]MVTNOV!$G17+[11]MVTDEC!$G17+[11]MVTJANV!$G17+[11]MVTFEV!$G17+[11]MVTMARS!$G17+[11]MVTAVRIL!$G17+[11]MVTMAI!$G17+[11]MVTJUIN!$G17+[11]MVTJUIL!$G17+[11]MVTAOUT2018!$G17 -> 54000 | E19: =+[11]MVTAOUT!$D17+[11]MVTSEPT!$E17+[11]MVTOCT!$C17+[11]MVTNOV!$C17+[11]MVTDEC!$C17+[11]MVTJANV!$C17+[11]MVTFEV!$C17+[11]MVTMARS!$C17+[11]MVTAVRIL!$C17+[11]MVTMAI!$C17+[11]MVTJUIN!$C17+[11]MVTJUIL!$C17 -> 20317.163 | F19: =+C19+D19+E19 -> 157156.44 | I19: 25000 | J19: 30000 | K19: =F19-G19-H19-I19-J19-102156 -> 0.44251227 | L19: 25000 | M19: 77156 | O19: =B19+J19 -> 480000 | P19: =K19+O19 -> 480000.44 | R19: =[11]MVTAOUT!O17+[11]MVTSEPT!P17+[11]MVTOCT!N17+[11]MVTNOV!N17+[11]MVTDEC!N17+[11]MVTJANV!N17+[11]MVTFEV!N17+[11]MVTMARS!N17+[11]MVTAVRIL!N17+[11]MVTMAI!N17+[11]MVTJUIN!N17+[11]MVTJUIL!N17 -> 0 | S19: =[11]MVTAOUT!P17+[11]MVTSEPT!Q17+[11]MVTOCT!O17+[11]MVTNOV!O17+[11]MVTDEC!O17+[11]MVTJANV!O17+[11]MVTFEV!O17+[11]MVTMARS!O17+[11]MVTAVRIL!O17+[11]MVTMAI!O17+[11]MVTJUIN!O17+[11]MVTJUIL!O17 -> 0 | T19: =+INVENT2016_2017!N17 -> 784000 | U19: =[11]MVTAOUT!$Q17+[11]MVTSEPT!$R17+[11]MVTOCT!$P17+[11]MVTNOV!$P17+[11]MVTDEC!$P17+[11]MVTJANV!$P17+[11]MVTFEV!$P17+[11]MVTMARS!$P17+[11]MVTAVRIL!$P17+[11]MVTMAI!$P17+[11]MVTJUIN!$P17+[11]MVTJUIL!$P17+[11]MVTAOUT2018!$P$17 -> 565000 | V19: 219000 | W19: =V19*5/100 -> 10950 | X19: =+V19+W19 -> 229950 | Y19: 42904 | AA19: 0.44251227 | AB19: =+[12]MVTSEPT!$D18 -> 660968.36 | AC19: =AA19-AB19 -> -660967.92
A20: KEPHE DAVID | B20: 387000 | C20: =+INVENT2016_2017!I18 -> 48664.16 | D20: =[11]MVTAOUT!$H18+[11]MVTSEPT!$I18+[11]MVTOCT!$G18+[11]MVTNOV!$G18+[11]MVTDEC!$G18+[11]MVTJANV!$G18+[11]MVTFEV!$G18+[11]MVTMARS!$G18+[11]MVTAVRIL!$G18+[11]MVTMAI!$G18+[11]MVTJUIN!$G18+[11]MVTJUIL!$G18+[11]MVTAOUT2018!$G18 -> 0 | E20: =+[11]MVTAOUT!$D18+[11]MVTSEPT!$E18+[11]MVTOCT!$C18+[11]MVTNOV!$C18+[11]MVTDEC!$C18+[11]MVTJANV!$C18+[11]MVTFEV!$C18+[11]MVTMARS!$C18+[11]MVTAVRIL!$C18+[11]MVTMAI!$C18+[11]MVTJUIN!$C18+[11]MVTJUIL!$C18 -> 16583.14 | F20: =+C20+D20+E20 -> 65247.3 | I20: 25000 | J20: 30000 | K20: =F20-G20-H20-I20-J20-3000-7247 -> 0.30040659 | O20: =447000+30000+3000 -> 480000 | P20: =K20+O20 -> 480000.3 | R20: =[11]MVTAOUT!O18+[11]MVTSEPT!P18+[11]MVTOCT!N18+[11]MVTNOV!N18+[11]MVTDEC!N18+[11]MVTJANV!N18+[11]MVTFEV!N18+[11]MVTMARS!N18+[11]MVTAVRIL!N18+[11]MVTMAI!N18+[11]MVTJUIN!N18+[11]MVTJUIL!N18 -> 0 | S20: =[11]MVTAOUT!P18+[11]MVTSEPT!Q18+[11]MVTOCT!O18+[11]MVTNOV!O18+[11]MVTDEC!O18+[11]MVTJANV!O18+[11]MVTFEV!O18+[11]MVTMARS!O18+[11]MVTAVRIL!O18+[11]MVTMAI!O18+[11]MVTJUIN!O18+[11]MVTJUIL!O18 -> 0 | T20: =+INVENT2016_2017!N18 -> 0 | U20: =[11]MVTAOUT!$Q18+[11]MVTSEPT!$R18+[11]MVTOCT!$P18+[11]MVTNOV!$P18+[11]MVTDEC!$P18+[11]MVTJANV!$P18+[11]MVTFEV!$P18+[11]MVTMARS!$P18+[11]MVTAVRIL!$P18+[11]MVTMAI!$P18+[11]MVTJUIN!$P18+[11]MVTJUIL!$P18+[11]MVTAOUT2018!$P$18 -> 0 | AA20: 0.30040659 | AB20: 0 | AC20: =AA20-AB20 -> 0.30040659
A21: KEPSEU FRANCIS | B21: =+INVENT2016_2017!J19 -> 450000 | C21: =+INVENT2016_2017!I19 -> 1911428.9 | D21: =[11]MVTAOUT!$H19+[11]MVTSEPT!$I19+[11]MVTOCT!$G19+[11]MVTNOV!$G19+[11]MVTDEC!$G19+[11]MVTJANV!$G19+[11]MVTFEV!$G19+[11]MVTMARS!$G19+[11]MVTAVRIL!$G19+[11]MVTMAI!$G19+[11]MVTJUIN!$G19+[11]MVTJUIL!$G19+[11]MVTAOUT2018!$G19 -> 1078000 | E21: =+[11]MVTAOUT!$D19+[11]MVTSEPT!$E19+[11]MVTOCT!$C19+[11]MVTNOV!$C19+[11]MVTDEC!$C19+[11]MVTJANV!$C19+[11]MVTFEV!$C19+[11]MVTMARS!$C19+[11]MVTAVRIL!$C19+[11]MVTMAI!$C19+[11]MVTJUIN!$C19+[11]MVTJUIL!$C19 -> 29469.823 | F21: =+C21+D21+E21 -> 3018898.7 | I21: 25000 | J21: 30000 | K21: =F21-G21-H21-I21-J21-15000 -> 2948898.7 | L21: 15000 | N21: 45000 | O21: =B21+J21 -> 480000 | P21: =K21+O21 -> 3428898.7 | R21: =[11]MVTAOUT!O19+[11]MVTSEPT!P19+[11]MVTOCT!N19+[11]MVTNOV!N19+[11]MVTDEC!N19+[11]MVTJANV!N19+[11]MVTFEV!N19+[11]MVTMARS!N19+[11]MVTAVRIL!N19+[11]MVTMAI!N19+[11]MVTJUIN!N19+[11]MVTJUIL!N19 -> 0 | S21: =[11]MVTAOUT!P19+[11]MVTSEPT!Q19+[11]MVTOCT!O19+[11]MVTNOV!O19+[11]MVTDEC!O19+[11]MVTJANV!O19+[11]MVTFEV!O19+[11]MVTMARS!O19+[11]MVTAVRIL!O19+[11]MVTMAI!O19+[11]MVTJUIN!O19+[11]MVTJUIL!O19 -> 0 | T21: =+INVENT2016_2017!N19 -> 0 | U21: =[11]MVTAOUT!$Q19+[11]MVTSEPT!$R19+[11]MVTOCT!$P19+[11]MVTNOV!$P19+[11]MVTDEC!$P19+[11]MVTJANV!$P19+[11]MVTFEV!$P19+[11]MVTMARS!$P19+[11]MVTAVRIL!$P19+[11]MVTMAI!$P19+[11]MVTJUIN!$P19+[11]MVTJUIL!$P19+[11]MVTAOUT2018!$P$19 -> 0 | AA21: 2948898.7 | AB21: =+[12]MVTSEPT!$D19 -> 649452.05 | AC21: =AA21-AB21 -> 2299446.7
A22: KOUAMOU EMMANUEL | B22: =+INVENT2016_2017!J20 -> 450000 | C22: =+INVENT2016_2017!I20 -> 47239.947 | D22: =[11]MVTAOUT!$H20+[11]MVTSEPT!$I20+[11]MVTOCT!$G20+[11]MVTNOV!$G20+[11]MVTDEC!$G20+[11]MVTJANV!$G20+[11]MVTFEV!$G20+[11]MVTMARS!$G20+[11]MVTAVRIL!$G20+[11]MVTMAI!$G20+[11]MVTJUIN!$G20+[11]MVTJUIL!$G20+[11]MVTAOUT2018!$G20 -> 39000 | E22: =+[11]MVTAOUT!$D20+[11]MVTSEPT!$E20+[11]MVTOCT!$C20+[11]MVTNOV!$C20+[11]MVTDEC!$C20+[11]MVTJANV!$C20+[11]MVTFEV!$C20+[11]MVTMARS!$C20+[11]MVTAVRIL!$C20+[11]MVTMAI!$C20+[11]MVTJUIN!$C20+[11]MVTJUIL!$C20 -> 19803.166 | F22: =+C22+D22+E22 -> 106043.11 | I22: 25000 | J22: 30000 | K22: =F22-G22-H22-I22-J22-32400 -> 18643.112 | M22: 32400 | N22: 18000 | O22: =B22+J22 -> 480000 | P22: =K22+O22 -> 498643.11 | R22: =[11]MVTAOUT!O20+[11]MVTSEPT!P20+[11]MVTOCT!N20+[11]MVTNOV!N20+[11]MVTDEC!N20+[11]MVTJANV!N20+[11]MVTFEV!N20+[11]MVTMARS!N20+[11]MVTAVRIL!N20+[11]MVTMAI!N20+[11]MVTJUIN!N20+[11]MVTJUIL!N20 -> 600000 | S22: =[11]MVTAOUT!P20+[11]MVTSEPT!Q20+[11]MVTOCT!O20+[11]MVTNOV!O20+[11]MVTDEC!O20+[11]MVTJANV!O20+[11]MVTFEV!O20+[11]MVTMARS!O20+[11]MVTAVRIL!O20+[11]MVTMAI!O20+[11]MVTJUIN!O20+[11]MVTJUIL!O20 -> 48000 | T22: =+INVENT2016_2017!N20 -> 1100000 | U22: =[11]MVTAOUT!$Q20+[11]MVTSEPT!$R20+[11]MVTOCT!$P20+[11]MVTNOV!$P20+[11]MVTDEC!$P20+[11]MVTJANV!$P20+[11]MVTFEV!$P20+[11]MVTMARS!$P20+[11]MVTAVRIL!$P20+[11]MVTMAI!$P20+[11]MVTJUIN!$P20+[11]MVTJUIL!$P20+[11]MVTAOUT2018!$P$20 -> 1150000 | V22: 648000 | W22: 0 | X22: =+V22+W22 -> 648000 | Y22: 43086 | AA22: 18643.112 | AB22: =+[12]MVTSEPT!$D20 -> 664981.57 | AC22: =AA22-AB22 -> -646338.46
A23: KOUAMOU MOISE | B23: =+INVENT2016_2017!J21 -> 450000 | C23: =+INVENT2016_2017!I21 -> 53808.893 | D23: =[11]MVTAOUT!$H21+[11]MVTSEPT!$I21+[11]MVTOCT!$G21+[11]MVTNOV!$G21+[11]MVTDEC!$G21+[11]MVTJANV!$G21+[11]MVTFEV!$G21+[11]MVTMARS!$G21+[11]MVTAVRIL!$G21+[11]MVTMAI!$G21+[11]MVTJUIN!$G21+[11]MVTJUIL!$G21+[11]MVTAOUT2018!$G21 -> 39000 | E23: =+[11]MVTAOUT!$D21+[11]MVTSEPT!$E21+[11]MVTOCT!$C21+[11]MVTNOV!$C21+[11]MVTDEC!$C21+[11]MVTJANV!$C21+[11]MVTFEV!$C21+[11]MVTMARS!$C21+[11]MVTAVRIL!$C21+[11]MVTMAI!$C21+[11]MVTJUIN!$C21+[11]MVTJUIL!$C21 -> 19802.808 | F23: =+C23+D23+E23 -> 112611.7 | I23: 25000 | J23: 30000 | K23: =F23-G23-H23-I23-J23-25000 -> 32611.702 | L23: 25000 | N23: 30000 | O23: =B23+J23 -> 480000 | P23: =K23+O23 -> 512611.7 | R23: =[11]MVTAOUT!O21+[11]MVTSEPT!P21+[11]MVTOCT!N21+[11]MVTNOV!N21+[11]MVTDEC!N21+[11]MVTJANV!N21+[11]MVTFEV!N21+[11]MVTMARS!N21+[11]MVTAVRIL!N21+[11]MVTMAI!N21+[11]MVTJUIN!N21+[11]MVTJUIL!N21 -> 110000 | S23: =[11]MVTAOUT!P21+[11]MVTSEPT!Q21+[11]MVTOCT!O21+[11]MVTNOV!O21+[11]MVTDEC!O21+[11]MVTJANV!O21+[11]MVTFEV!O21+[11]MVTMARS!O21+[11]MVTAVRIL!O21+[11]MVTMAI!O21+[11]MVTJUIN!O21+[11]MVTJUIL!O21 -> 3300 | T23: =+INVENT2016_2017!N21 -> 592000 | U23: =[11]MVTAOUT!$Q21+[11]MVTSEPT!$R21+[11]MVTOCT!$P21+[11]MVTNOV!$P21+[11]MVTDEC!$P21+[11]MVTJANV!$P21+[11]MVTFEV!$P21+[11]MVTMARS!$P21+[11]MVTAVRIL!$P21+[11]MVTMAI!$P21+[11]MVTJUIN!$P21+[11]MVTJUIL!$P21+[11]MVTAOUT2018!$P$21 -> 493000 | X23: =+V23+W23 -> 0 | Y23: 43241 | AA23: 32611.702 | AB23: =+[12]MVTSEPT!$D22 -> 647639.79 | AC23: =AA23-AB23 -> -615028.09
A24: KOUAMO VICTOR PEGUY | B24: =+INVENT2016_2017!J22 -> 450000 | C24: =+INVENT2016_2017!I22 -> 39090.63 | D24: =[11]MVTAOUT!$H22+[11]MVTSEPT!$I22+[11]MVTOCT!$G22+[11]MVTNOV!$G22+[11]MVTDEC!$G22+[11]MVTJANV!$G22+[11]MVTFEV!$G22+[11]MVTMARS!$G22+[11]MVTAVRIL!$G22+[11]MVTMAI!$G22+[11]MVTJUIN!$G22+[11]MVTJUIL!$G22+[11]MVTAOUT2018!$G22 -> 38000 | E24: =+[11]MVTAOUT!$D22+[11]MVTSEPT!$E22+[11]MVTOCT!$C22+[11]MVTNOV!$C22+[11]MVTDEC!$C22+[11]MVTJANV!$C22+[11]MVTFEV!$C22+[11]MVTMARS!$C22+[11]MVTAVRIL!$C22+[11]MVTMAI!$C22+[11]MVTJUIN!$C22+[11]MVTJUIL!$C22 -> 19797.11 | F24: =+C24+D24+E24 -> 96887.739 | I24: 25000 | J24: 30000 | K24: =F24-G24-H24-I24-J24-35000-6888 -> -0.26072547 | L24: 35000 | M24: 6888 | O24: =B24+J24 -> 480000 | P24: =K24+O24 -> 479999.74 | R24: =[11]MVTAOUT!O22+[11]MVTSEPT!P22+[11]MVTOCT!N22+[11]MVTNOV!N22+[11]MVTDEC!N22+[11]MVTJANV!N22+[11]MVTFEV!N22+[11]MVTMARS!N22+[11]MVTAVRIL!N22+[11]MVTMAI!N22+[11]MVTJUIN!N22+[11]MVTJUIL!N22 -> 700000 | S24: =[11]MVTAOUT!P22+[11]MVTSEPT!Q22+[11]MVTOCT!O22+[11]MVTNOV!O22+[11]MVTDEC!O22+[11]MVTJANV!O22+[11]MVTFEV!O22+[11]MVTMARS!O22+[11]MVTAVRIL!O22+[11]MVTMAI!O22+[11]MVTJUIN!O22+[11]MVTJUIL!O22 -> 70000 | T24: =+INVENT2016_2017!N22 -> 896000 | U24: =[11]MVTAOUT!$Q22+[11]MVTSEPT!$R22+[11]MVTOCT!$P22+[11]MVTNOV!$P22+[11]MVTDEC!$P22+[11]MVTJANV!$P22+[11]MVTFEV!$P22+[11]MVTMARS!$P22+[11]MVTAVRIL!$P22+[11]MVTMAI!$P22+[11]MVTJUIN!$P22+[11]MVTJUIL!$P22+[11]MVTAOUT2018!$P$22 -> 896000 | V24: 700000 | W24: =V24*5/100 -> 35000 | X24: =+V24+W24-35000 -> 700000 | Y24: 43121 | AA24: -0.26072547 | AB24: =+[12]MVTSEPT!$D20 -> 664981.57 | AC24: =AA24-AB24 -> -664981.84
A25: KOUATCHO MESSACK | B25: =+INVENT2016_2017!J23 -> 450000 | C25: =+INVENT2016_2017!I23 -> 36797.236 | D25: =[11]MVTAOUT!$H23+[11]MVTSEPT!$I23+[11]MVTOCT!$G23+[11]MVTNOV!$G23+[11]MVTDEC!$G23+[11]MVTJANV!$G23+[11]MVTFEV!$G23+[11]MVTMARS!$G23+[11]MVTAVRIL!$G23+[11]MVTMAI!$G23+[11]MVTJUIN!$G23+[11]MVTJUIL!$G23+[11]MVTAOUT2018!$G23 -> 39000 | E25: =+[11]MVTAOUT!$D23+[11]MVTSEPT!$E23+[11]MVTOCT!$C23+[11]MVTNOV!$C23+[11]MVTDEC!$C23+[11]MVTJANV!$C23+[11]MVTFEV!$C23+[11]MVTMARS!$C23+[11]MVTAVRIL!$C23+[11]MVTMAI!$C23+[11]MVTJUIN!$C23+[11]MVTJUIL!$C23 -> 19808.17 | F25: =+C25+D25+E25 -> 95605.406 | I25: 25000 | J25: 30000 | K25: =F25-G25-H25-I25-J25-25000 -> 15605.406 | L25: 25000 | N25: 15000 | O25: =B25+J25 -> 480000 | P25: =K25+O25 -> 495605.41 | R25: =[11]MVTAOUT!O23+[11]MVTSEPT!P23+[11]MVTOCT!N23+[11]MVTNOV!N23+[11]MVTDEC!N23+[11]MVTJANV!N23+[11]MVTFEV!N23+[11]MVTMARS!N23+[11]MVTAVRIL!N23+[11]MVTMAI!N23+[11]MVTJUIN!N23+[11]MVTJUIL!N23 -> 850000 | S25: =[11]MVTAOUT!P23+[11]MVTSEPT!Q23+[11]MVTOCT!O23+[11]MVTNOV!O23+[11]MVTDEC!O23+[11]MVTJANV!O23+[11]MVTFEV!O23+[11]MVTMARS!O23+[11]MVTAVRIL!O23+[11]MVTMAI!O23+[11]MVTJUIN!O23+[11]MVTJUIL!O23 -> 51000 | T25: =+INVENT2016_2017!N23 -> 1120000 | U25: =[11]MVTAOUT!$Q23+[11]MVTSEPT!$R23+[11]MVTOCT!$P23+[11]MVTNOV!$P23+[11]MVTDEC!$P23+[11]MVTJANV!$P23+[11]MVTFEV!$P23+[11]MVTMARS!$P23+[11]MVTAVRIL!$P23+[11]MVTMAI!$P23+[11]MVTJUIN!$P23+[11]MVTJUIL!$P23+[11]MVTAOUT2018!$P$23 -> 1950000 | V25: =850000-850000 -> 0 | Y25: 43241 | AA25: 15605.406 | AB25: =+[12]MVTSEPT!$D23 -> 698777.96 | AC25: =AA25-AB25 -> -683172.56
A26: LOWE JEAN | B26: =+INVENT2016_2017!J24 -> 450000 | C26: =+INVENT2016_2017!I24 -> 47506.896 | D26: =[11]MVTAOUT!$H24+[11]MVTSEPT!$I24+[11]MVTOCT!$G24+[11]MVTNOV!$G24+[11]MVTDEC!$G24+[11]MVTJANV!$G24+[11]MVTFEV!$G24+[11]MVTMARS!$G24+[11]MVTAVRIL!$G24+[11]MVTMAI!$G24+[11]MVTJUIN!$G24+[11]MVTJUIL!$G24+[11]MVTAOUT2018!$G24 -> 39000 | E26: =+[11]MVTAOUT!$D24+[11]MVTSEPT!$E24+[11]MVTOCT!$C24+[11]MVTNOV!$C24+[11]MVTDEC!$C24+[11]MVTJANV!$C24+[11]MVTFEV!$C24+[11]MVTMARS!$C24+[11]MVTAVRIL!$C24+[11]MVTMAI!$C24+[11]MVTJUIN!$C24+[11]MVTJUIL!$C24 -> 19799.955 | F26: =+C26+D26+E26 -> 106306.85 | I26: 25000 | J26: 30000 | K26: =F26-G26-H26-I26-J26-51307 -> -0.14820684 | L26: 25000 | M26: 26307 | O26: =B26+J26 -> 480000 | P26: =K26+O26 -> 479999.85 | R26: =[11]MVTAOUT!O24+[11]MVTSEPT!P24+[11]MVTOCT!N24+[11]MVTNOV!N24+[11]MVTDEC!N24+[11]MVTJANV!N24+[11]MVTFEV!N24+[11]MVTMARS!N24+[11]MVTAVRIL!N24+[11]MVTMAI!N24+[11]MVTJUIN!N24+[11]MVTJUIL!N24 -> 150000 | S26: =[11]MVTAOUT!P24+[11]MVTSEPT!Q24+[11]MVTOCT!O24+[11]MVTNOV!O24+[11]MVTDEC!O24+[11]MVTJANV!O24+[11]MVTFEV!O24+[11]MVTMARS!O24+[11]MVTAVRIL!O24+[11]MVTMAI!O24+[11]MVTJUIN!O24+[11]MVTJUIL!O24 -> 18000 | T26: =+INVENT2016_2017!N24 -> 154500 | U26: =[11]MVTAOUT!$Q24+[11]MVTSEPT!$R24+[11]MVTOCT!$P24+[11]MVTNOV!$P24+[11]MVTDEC!$P24+[11]MVTJANV!$P24+[11]MVTFEV!$P24+[11]MVTMARS!$P24+[11]MVTAVRIL!$P24+[11]MVTMAI!$P24+[11]MVTJUIN!$P24+[11]MVTJUIL!$P24+[11]MVTAOUT2018!$P$24 -> 157500 | V26: 168000 | W26: =V26*5/100 -> 8400 | X26: =+V26+W26 -> 176400 | Y26: 42967 | AA26: -0.14820684 | AB26: =+[12]MVTSEPT!$D24 -> 650993.54 | AC26: =AA26-AB26 -> -650993.69
A27: NANKAM APPOLINAIRE | B27: =+INVENT2016_2017!J25 -> 450000 | C27: =+INVENT2016_2017!I25 -> 47549.255 | D27: =[11]MVTAOUT!$H25+[11]MVTSEPT!$I25+[11]MVTOCT!$G25+[11]MVTNOV!$G25+[11]MVTDEC!$G25+[11]MVTJANV!$G25+[11]MVTFEV!$G25+[11]MVTMARS!$G25+[11]MVTAVRIL!$G25+[11]MVTMAI!$G25+[11]MVTJUIN!$G25+[11]MVTJUIL!$G25+[11]MVTAOUT2018!$G25 -> 39000 | E27: =+[11]MVTAOUT!$D25+[11]MVTSEPT!$E25+[11]MVTOCT!$C25+[11]MVTNOV!$C25+[11]MVTDEC!$C25+[11]MVTJANV!$C25+[11]MVTFEV!$C25+[11]MVTMARS!$C25+[11]MVTAVRIL!$C25+[11]MVTMAI!$C25+[11]MVTJUIN!$C25+[11]MVTJUIL!$C25 -> 19804.481 | F27: =+C27+D27+E27 -> 106353.74 | I27: 25000 | J27: 30000 | K27: =F27-G27-H27-I27-J27-25000 -> 26353.736 | L27: 25000 | N27: 25000 | O27: =B27+J27 -> 480000 | P27: =K27+O27 -> 506353.74 | R27: =[11]MVTAOUT!O25+[11]MVTSEPT!P25+[11]MVTOCT!N25+[11]MVTNOV!N25+[11]MVTDEC!N25+[11]MVTJANV!N25+[11]MVTFEV!N25+[11]MVTMARS!N25+[11]MVTAVRIL!N25+[11]MVTMAI!N25+[11]MVTJUIN!N25+[11]MVTJUIL!N25 -> 0 | S27: =[11]MVTAOUT!P25+[11]MVTSEPT!Q25+[11]MVTOCT!O25+[11]MVTNOV!O25+[11]MVTDEC!O25+[11]MVTJANV!O25+[11]MVTFEV!O25+[11]MVTMARS!O25+[11]MVTAVRIL!O25+[11]MVTMAI!O25+[11]MVTJUIN!O25+[11]MVTJUIL!O25 -> 0 | T27: =+INVENT2016_2017!N25 -> 0 | U27: =[11]MVTAOUT!$Q25+[11]MVTSEPT!$R25+[11]MVTOCT!$P25+[11]MVTNOV!$P25+[11]MVTDEC!$P25+[11]MVTJANV!$P25+[11]MVTFEV!$P25+[11]MVTMARS!$P25+[11]MVTAVRIL!$P25+[11]MVTMAI!$P25+[11]MVTJUIN!$P25+[11]MVTJUIL!$P25+[11]MVTAOUT2018!$P$25 -> 21000 | AA27: 26353.736 | AB27: =+[12]MVTSEPT!$D27 -> 662211.19 | AC27: =AA27-AB27 -> -635857.45
A28: NDJOMO ETIENNE | B28: =+INVENT2016_2017!J26 -> 450000 | C28: =+INVENT2016_2017!I26 -> 47476.114 | D28: =[11]MVTAOUT!$H26+[11]MVTSEPT!$I26+[11]MVTOCT!$G26+[11]MVTNOV!$G26+[11]MVTDEC!$G26+[11]MVTJANV!$G26+[11]MVTFEV!$G26+[11]MVTMARS!$G26+[11]MVTAVRIL!$G26+[11]MVTMAI!$G26+[11]MVTJUIN!$G26+[11]MVTJUIL!$G26+[11]MVTAOUT2018!$G26 -> 104000 | E28: =+[11]MVTAOUT!$D26+[11]MVTSEPT!$E26+[11]MVTOCT!$C26+[11]MVTNOV!$C26+[11]MVTDEC!$C26+[11]MVTJANV!$C26+[11]MVTFEV!$C26+[11]MVTMARS!$C26+[11]MVTAVRIL!$C26+[11]MVTMAI!$C26+[11]MVTJUIN!$C26+[11]MVTJUIL!$C26 -> 20749.5 | F28: =+C28+D28+E28 -> 172225.61 | I28: 25000 | J28: 30000 | K28: =F28-G28-H28-I28-J28 -> 117225.61 | N28: 60000 | O28: =B28+J28 -> 480000 | P28: =K28+O28 -> 597225.61 | R28: =[11]MVTAOUT!O26+[11]MVTSEPT!P26+[11]MVTOCT!N26+[11]MVTNOV!N26+[11]MVTDEC!N26+[11]MVTJANV!N26+[11]MVTFEV!N26+[11]MVTMARS!N26+[11]MVTAVRIL!N26+[11]MVTMAI!N26+[11]MVTJUIN!N26+[11]MVTJUIL!N26 -> 700000 | S28: =[11]MVTAOUT!P26+[11]MVTSEPT!Q26+[11]MVTOCT!O26+[11]MVTNOV!O26+[11]MVTDEC!O26+[11]MVTJANV!O26+[11]MVTFEV!O26+[11]MVTMARS!O26+[11]MVTAVRIL!O26+[11]MVTMAI!O26+[11]MVTJUIN!O26+[11]MVTJUIL!O26 -> 35000 | T28: =+INVENT2016_2017!N26 -> 672000 | U28: =[11]MVTAOUT!$Q26+[11]MVTSEPT!$R26+[11]MVTOCT!$P26+[11]MVTNOV!$P26+[11]MVTDEC!$P26+[11]MVTJANV!$P26+[11]MVTFEV!$P26+[11]MVTMARS!$P26+[11]MVTAVRIL!$P26+[11]MVTMAI!$P26+[11]MVTJUIN!$P26+[11]MVTJUIL!$P26+[11]MVTAOUT2018!$P$26 -> 1372000 | V28: 0 | Y28: 43169 | AA28: 117225.61 | AB28: =+[12]MVTSEPT!$D28 -> 732079.69 | AC28: =AA28-AB28 -> -614854.07
A29: NDOMBOU JEAN CLAUDE | B29: =+INVENT2016_2017!J27 -> 450000 | C29: =+INVENT2016_2017!I27 -> 27680.734 | D29: =[11]MVTAOUT!$H27+[11]MVTSEPT!$I27+[11]MVTOCT!$G27+[11]MVTNOV!$G27+[11]MVTDEC!$G27+[11]MVTJANV!$G27+[11]MVTFEV!$G27+[11]MVTMARS!$G27+[11]MVTAVRIL!$G27+[11]MVTMAI!$G27+[11]MVTJUIN!$G27+[11]MVTJUIL!$G27+[11]MVTAOUT2018!$G27 -> 39000 | E29: =+[11]MVTAOUT!$D27+[11]MVTSEPT!$E27+[11]MVTOCT!$C27+[11]MVTNOV!$C27+[11]MVTDEC!$C27+[11]MVTJANV!$C27+[11]MVTFEV!$C27+[11]MVTMARS!$C27+[11]MVTAVRIL!$C27+[11]MVTMAI!$C27+[11]MVTJUIN!$C27+[11]MVTJUIL!$C27 -> 19734.447 | F29: =+C29+D29+E29 -> 86415.181 | I29: 25000 | J29: 30000 | K29: =F29-G29-H29-I29-J29-31415 -> 0.18146182 | L29: 25000 | M29: 6415 | O29: =B29+J29 -> 480000 | P29: =K29+O29 -> 480000.18 | R29: =[11]MVTAOUT!O27+[11]MVTSEPT!P27+[11]MVTOCT!N27+[11]MVTNOV!N27+[11]MVTDEC!N27+[11]MVTJANV!N27+[11]MVTFEV!N27+[11]MVTMARS!N27+[11]MVTAVRIL!N27+[11]MVTMAI!N27+[11]MVTJUIN!N27+[11]MVTJUIL!N27 -> 0 | S29: =[11]MVTAOUT!P27+[11]MVTSEPT!Q27+[11]MVTOCT!O27+[11]MVTNOV!O27+[11]MVTDEC!O27+[11]MVTJANV!O27+[11]MVTFEV!O27+[11]MVTMARS!O27+[11]MVTAVRIL!O27+[11]MVTMAI!O27+[11]MVTJUIN!O27+[11]MVTJUIL!O27 -> 0 | T29: =+INVENT2016_2017!N27 -> 0 | U29: =[11]MVTAOUT!$Q27+[11]MVTSEPT!$R27+[11]MVTOCT!$P27+[11]MVTNOV!$P27+[11]MVTDEC!$P27+[11]MVTJANV!$P27+[11]MVTFEV!$P27+[11]MVTMARS!$P27+[11]MVTAVRIL!$P27+[11]MVTMAI!$P27+[11]MVTJUIN!$P27+[11]MVTJUIL!$P27+[11]MVTAOUT2018!$P$27 -> 0 | AA29: 0.18146182 | AC29: =AA29-AB29 -> 0.18146182
A30: NGONDIEP CLAUDE | B30: =+INVENT2016_2017!J28 -> 450000 | C30: =+INVENT2016_2017!I28 -> 47679.518 | D30: =[11]MVTAOUT!$H28+[11]MVTSEPT!$I28+[11]MVTOCT!$G28+[11]MVTNOV!$G28+[11]MVTDEC!$G28+[11]MVTJANV!$G28+[11]MVTFEV!$G28+[11]MVTMARS!$G28+[11]MVTAVRIL!$G28+[11]MVTMAI!$G28+[11]MVTJUIN!$G28+[11]MVTJUIL!$G28+[11]MVTAOUT2018!$G28 -> 105500 | E30: =+[11]MVTAOUT!$D28+[11]MVTSEPT!$E28+[11]MVTOCT!$C28+[11]MVTNOV!$C28+[11]MVTDEC!$C28+[11]MVTJANV!$C28+[11]MVTFEV!$C28+[11]MVTMARS!$C28+[11]MVTAVRIL!$C28+[11]MVTMAI!$C28+[11]MVTJUIN!$C28+[11]MVTJUIL!$C28 -> 22120.769 | F30: =+C30+D30+E30 -> 175300.29 | H30: 100000 | I30: 25000 | J30: 30000 | K30: =F30-G30-H30-I30-J30-20300 -> 0.28740352 | L30: 20300 | O30: =B30+J30 -> 480000 | P30: =K30+O30 -> 480000.29 | R30: =[11]MVTAOUT!O28+[11]MVTSEPT!P28+[11]MVTOCT!N28+[11]MVTNOV!N28+[11]MVTDEC!N28+[11]MVTJANV!N28+[11]MVTFEV!N28+[11]MVTMARS!N28+[11]MVTAVRIL!N28+[11]MVTMAI!N28+[11]MVTJUIN!N28+[11]MVTJUIL!N28 -> 0 | S30: =[11]MVTAOUT!P28+[11]MVTSEPT!Q28+[11]MVTOCT!O28+[11]MVTNOV!O28+[11]MVTDEC!O28+[11]MVTJANV!O28+[11]MVTFEV!O28+[11]MVTMARS!O28+[11]MVTAVRIL!O28+[11]MVTMAI!O28+[11]MVTJUIN!O28+[11]MVTJUIL!O28 -> 0 | T30: =+INVENT2016_2017!N28 -> 1120000 | U30: =[11]MVTAOUT!$Q28+[11]MVTSEPT!$R28+[11]MVTOCT!$P28+[11]MVTNOV!$P28+[11]MVTDEC!$P28+[11]MVTJANV!$P28+[11]MVTFEV!$P28+[11]MVTMARS!$P28+[11]MVTAVRIL!$P28+[11]MVTMAI!$P28+[11]MVTJUIN!$P28+[11]MVTJUIL!$P28+[11]MVTAOUT2018!$P$28 -> 0 | V30: 1120000 | W30: =V30*5/100 -> 56000 | X30: =+V30+W30 -> 1176000 | Y30: 42904 | AA30: 0.28740352 | AB30: =+[12]MVTSEPT!$D30 -> 657300.98 | AC30: =AA30-AB30 -> -657300.69
A31: NGONGANG JEAN THEODORE | B31: 30000 | C31: =+INVENT2016_2017!I29 -> -4174.3496 | D31: =[11]MVTAOUT!$H29+[11]MVTSEPT!$I29+[11]MVTOCT!$G29+[11]MVTNOV!$G29+[11]MVTDEC!$G29+[11]MVTJANV!$G29+[11]MVTFEV!$G29+[11]MVTMARS!$G29+[11]MVTAVRIL!$G29+[11]MVTMAI!$G29+[11]MVTJUIN!$G29+[11]MVTJUIL!$G29+[11]MVTAOUT2018!$G29 -> 0 | E31: =+[11]MVTAOUT!$D29+[11]MVTSEPT!$E29+[11]MVTOCT!$C29+[11]MVTNOV!$C29+[11]MVTDEC!$C29+[11]MVTJANV!$C29+[11]MVTFEV!$C29+[11]MVTMARS!$C29+[11]MVTAVRIL!$C29+[11]MVTMAI!$C29+[11]MVTJUIN!$C29+[11]MVTJUIL!$C29 -> 1237.5906 | F31: =+C31+D31+E31 -> -2936.759 | I31: 13234 | J31: 0 | K31: =F31-G31-H31-I31-J31 -> -16170.759 | O31: 30000 | P31: =K31+O31 -> 13829.241 | R31: =[11]MVTAOUT!O29+[11]MVTSEPT!P29+[11]MVTOCT!N29+[11]MVTNOV!N29+[11]MVTDEC!N29+[11]MVTJANV!N29+[11]MVTFEV!N29+[11]MVTMARS!N29+[11]MVTAVRIL!N29+[11]MVTMAI!N29+[11]MVTJUIN!N29+[11]MVTJUIL!N29 -> 0 | S31: =[11]MVTAOUT!P29+[11]MVTSEPT!Q29+[11]MVTOCT!O29+[11]MVTNOV!O29+[11]MVTDEC!O29+[11]MVTJANV!O29+[11]MVTFEV!O29+[11]MVTMARS!O29+[11]MVTAVRIL!O29+[11]MVTMAI!O29+[11]MVTJUIN!O29+[11]MVTJUIL!O29 -> 0 | T31: =+INVENT2016_2017!N29 -> 0 | U31: =[11]MVTAOUT!$Q29+[11]MVTSEPT!$R29+[11]MVTOCT!$P29+[11]MVTNOV!$P29+[11]MVTDEC!$P29+[11]MVTJANV!$P29+[11]MVTFEV!$P29+[11]MVTMARS!$P29+[11]MVTAVRIL!$P29+[11]MVTMAI!$P29+[11]MVTJUIN!$P29+[11]MVTJUIL!$P29+[11]MVTAOUT2018!$P$29 -> 50000 | AA31: 22.240997 | AB31: =+[12]MVTSEPT!$D31 -> 812754.94 | AC31: =AA31-AB31 -> -812732.7
A32: NGUIEMEGNI MATHIEU BLAISE | B32: =+INVENT2016_2017!J30 -> 450000 | C32: =+INVENT2016_2017!I30 -> 93205.631 | D32: =[11]MVTAOUT!$H30+[11]MVTSEPT!$I30+[11]MVTOCT!$G30+[11]MVTNOV!$G30+[11]MVTDEC!$G30+[11]MVTJANV!$G30+[11]MVTFEV!$G30+[11]MVTMARS!$G30+[11]MVTAVRIL!$G30+[11]MVTMAI!$G30+[11]MVTJUIN!$G30+[11]MVTJUIL!$G30+[11]MVTAOUT2018!$G30 -> 39000 | E32: =+[11]MVTAOUT!$D30+[11]MVTSEPT!$E30+[11]MVTOCT!$C30+[11]MVTNOV!$C30+[11]MVTDEC!$C30+[11]MVTJANV!$C30+[11]MVTFEV!$C30+[11]MVTMARS!$C30+[11]MVTAVRIL!$C30+[11]MVTMAI!$C30+[11]MVTJUIN!$C30+[11]MVTJUIL!$C30 -> 19932.624 | F32: =+C32+D32+E32 -> 152138.25 | I32: 25000 | J32: 30000 | K32: =F32-G32-H32-I32-J32-25000 -> 72138.255 | L32: 25000 | O32: =B32+J32 -> 480000 | P32: =K32+O32 -> 552138.25 | R32: =[11]MVTAOUT!O30+[11]MVTSEPT!P30+[11]MVTOCT!N30+[11]MVTNOV!N30+[11]MVTDEC!N30+[11]MVTJANV!N30+[11]MVTFEV!N30+[11]MVTMARS!N30+[11]MVTAVRIL!N30+[11]MVTMAI!N30+[11]MVTJUIN!N30+[11]MVTJUIL!N30 -> 0 | S32: =[11]MVTAOUT!P30+[11]MVTSEPT!Q30+[11]MVTOCT!O30+[11]MVTNOV!O30+[11]MVTDEC!O30+[11]MVTJANV!O30+[11]MVTFEV!O30+[11]MVTMARS!O30+[11]MVTAVRIL!O30+[11]MVTMAI!O30+[11]MVTJUIN!O30+[11]MVTJUIL!O30 -> 0 | T32: =+INVENT2016_2017!N30 -> 0 | U32: =[11]MVTAOUT!$Q30+[11]MVTSEPT!$R30+[11]MVTOCT!$P30+[11]MVTNOV!$P30+[11]MVTDEC!$P30+[11]MVTJANV!$P30+[11]MVTFEV!$P30+[11]MVTMARS!$P30+[11]MVTAVRIL!$P30+[11]MVTMAI!$P30+[11]MVTJUIN!$P30+[11]MVTJUIL!$P30+[11]MVTAOUT2018!$P$30 -> 0 | AA32: 72138.255 | AB32: =+[12]MVTSEPT!$D32 -> 488413.95 | AC32: =AA32-AB32 -> -416275.69
A33: NJEPDJIO MBOUKAM DELUXE | B33: =+INVENT2016_2017!J31 -> 450000 | C33: =+INVENT2016_2017!I31 -> 46909.873 | D33: =[11]MVTAOUT!$H31+[11]MVTSEPT!$I31+[11]MVTOCT!$G31+[11]MVTNOV!$G31+[11]MVTDEC!$G31+[11]MVTJANV!$G31+[11]MVTFEV!$G31+[11]MVTMARS!$G31+[11]MVTAVRIL!$G31+[11]MVTMAI!$G31+[11]MVTJUIN!$G31+[11]MVTJUIL!$G31+[11]MVTAOUT2018!$G31 -> 39000 | E33: =+[11]MVTAOUT!$D31+[11]MVTSEPT!$E31+[11]MVTOCT!$C31+[11]MVTNOV!$C31+[11]MVTDEC!$C31+[11]MVTJANV!$C31+[11]MVTFEV!$C31+[11]MVTMARS!$C31+[11]MVTAVRIL!$C31+[11]MVTMAI!$C31+[11]MVTJUIN!$C31+[11]MVTJUIL!$C31 -> 19779.445 | F33: =+C33+D33+E33 -> 105689.32 | I33: 25000 | J33: 30000 | K33: =F33-G33-H33-I33-J33-25000 -> 25689.319 | L33: 25000 | N33: 25000 | O33: =B33+J33 -> 480000 | P33: =K33+O33 -> 505689.32 | R33: =[11]MVTAOUT!O31+[11]MVTSEPT!P31+[11]MVTOCT!N31+[11]MVTNOV!N31+[11]MVTDEC!N31+[11]MVTJANV!N31+[11]MVTFEV!N31+[11]MVTMARS!N31+[11]MVTAVRIL!N31+[11]MVTMAI!N31+[11]MVTJUIN!N31+[11]MVTJUIL!N31 -> 500000 | S33: =[11]MVTAOUT!P31+[11]MVTSEPT!Q31+[11]MVTOCT!O31+[11]MVTNOV!O31+[11]MVTDEC!O31+[11]MVTJANV!O31+[11]MVTFEV!O31+[11]MVTMARS!O31+[11]MVTAVRIL!O31+[11]MVTMAI!O31+[11]MVTJUIN!O31+[11]MVTJUIL!O31 -> 10000 | T33: =+INVENT2016_2017!N31 -> 896000 | U33: =[11]MVTAOUT!$Q31+[11]MVTSEPT!$R31+[11]MVTOCT!$P31+[11]MVTNOV!$P31+[11]MVTDEC!$P31+[11]MVTJANV!$P31+[11]MVTFEV!$P31+[11]MVTMARS!$P31+[11]MVTAVRIL!$P31+[11]MVTMAI!$P31+[11]MVTJUIN!$P31+[11]MVTJUIL!$P31+[11]MVTAOUT2018!$P$31 -> 1440800 | V33: =500000-500000 -> 0 | Y33: 43268 | AA33: 25689.319 | AB33: =+[12]MVTSEPT!$D33 -> 643162.62 | AC33: =AA33-AB33 -> -617473.31
A34: NKAMGANG JUSTIN DEJOLIE | B34: =+INVENT2016_2017!J32 -> 450000 | C34: =+INVENT2016_2017!I32 -> 54313.881 | D34: =[11]MVTAOUT!$H32+[11]MVTSEPT!$I32+[11]MVTOCT!$G32+[11]MVTNOV!$G32+[11]MVTDEC!$G32+[11]MVTJANV!$G32+[11]MVTFEV!$G32+[11]MVTMARS!$G32+[11]MVTAVRIL!$G32+[11]MVTMAI!$G32+[11]MVTJUIN!$G32+[11]MVTJUIL!$G32+[11]MVTAOUT2018!$G32 -> 378000 | E34: =+[11]MVTAOUT!$D32+[11]MVTSEPT!$E32+[11]MVTOCT!$C32+[11]MVTNOV!$C32+[11]MVTDEC!$C32+[11]MVTJANV!$C32+[11]MVTFEV!$C32+[11]MVTMARS!$C32+[11]MVTAVRIL!$C32+[11]MVTMAI!$C32+[11]MVTJUIN!$C32+[11]MVTJUIL!$C32 -> 27722.47 | F34: =+C34+D34+E34 -> 460036.35 | I34: 25000 | J34: 30000 | K34: =F34-G34-H34-I34-J34-25000 -> 380036.35 | L34: 25000 | N34: 380000 | O34: =B34+J34 -> 480000 | P34: =K34+O34 -> 860036.35 | R34: =[11]MVTAOUT!O32+[11]MVTSEPT!P32+[11]MVTOCT!N32+[11]MVTNOV!N32+[11]MVTDEC!N32+[11]MVTJANV!N32+[11]MVTFEV!N32+[11]MVTMARS!N32+[11]MVTAVRIL!N32+[11]MVTMAI!N32+[11]MVTJUIN!N32+[11]MVTJUIL!N32 -> 1000000 | S34: =[11]MVTAOUT!P32+[11]MVTSEPT!Q32+[11]MVTOCT!O32+[11]MVTNOV!O32+[11]MVTDEC!O32+[11]MVTJANV!O32+[11]MVTFEV!O32+[11]MVTMARS!O32+[11]MVTAVRIL!O32+[11]MVTMAI!O32+[11]MVTJUIN!O32+[11]MVTJUIL!O32 -> 90000 | T34: =+INVENT2016_2017!N32 -> 1120000 | U34: =[11]MVTAOUT!$Q32+[11]MVTSEPT!$R32+[11]MVTOCT!$P32+[11]MVTNOV!$P32+[11]MVTDEC!$P32+[11]MVTJANV!$P32+[11]MVTFEV!$P32+[11]MVTMARS!$P32+[11]MVTAVRIL!$P32+[11]MVTMAI!$P32+[11]MVTJUIN!$P32+[11]MVTJUIL!$P32+[11]MVTAOUT2018!$P$32 -> 2210000 | V34: =1090000-1090000 -> 0 | Y34: 43057 | AA34: 380036.35 | AB34: =+[12]MVTSEPT!$D34 -> 795838.38 | AC34: =AA34-AB34 -> -415802.03
A35: NKEPSEU DIEUDONNE | B35: =+INVENT2016_2017!J33 -> 450000 | C35: =+INVENT2016_2017!I33 -> 50017.733 | D35: =[11]MVTAOUT!$H33+[11]MVTSEPT!$I33+[11]MVTOCT!$G33+[11]MVTNOV!$G33+[11]MVTDEC!$G33+[11]MVTJANV!$G33+[11]MVTFEV!$G33+[11]MVTMARS!$G33+[11]MVTAVRIL!$G33+[11]MVTMAI!$G33+[11]MVTJUIN!$G33+[11]MVTJUIL!$G33+[11]MVTAOUT2018!$G33 -> 104000 | E35: =+[11]MVTAOUT!$D33+[11]MVTSEPT!$E33+[11]MVTOCT!$C33+[11]MVTNOV!$C33+[11]MVTDEC!$C33+[11]MVTJANV!$C33+[11]MVTFEV!$C33+[11]MVTMARS!$C33+[11]MVTAVRIL!$C33+[11]MVTMAI!$C33+[11]MVTJUIN!$C33+[11]MVTJUIL!$C33 -> 21092.067 | F35: =+C35+D35+E35 -> 175109.8 | H35: 100000 | I35: 25000 | J35: 30000 | K35: =F35-G35-H35-I35-J35 -> 20109.8 | N35: 20000 | O35: =B35+J35 -> 480000 | P35: =K35+O35 -> 500109.8 | R35: =[11]MVTAOUT!O33+[11]MVTSEPT!P33+[11]MVTOCT!N33+[11]MVTNOV!N33+[11]MVTDEC!N33+[11]MVTJANV!N33+[11]MVTFEV!N33+[11]MVTMARS!N33+[11]MVTAVRIL!N33+[11]MVTMAI!N33+[11]MVTJUIN!N33+[11]MVTJUIL!N33 -> 500000 | S35: =[11]MVTAOUT!P33+[11]MVTSEPT!Q33+[11]MVTOCT!O33+[11]MVTNOV!O33+[11]MVTDEC!O33+[11]MVTJANV!O33+[11]MVTFEV!O33+[11]MVTMARS!O33+[11]MVTAVRIL!O33+[11]MVTMAI!O33+[11]MVTJUIN!O33+[11]MVTJUIL!O33 -> 50000 | T35: =+INVENT2016_2017!N33 -> 472000 | U35: =[11]MVTAOUT!$Q33+[11]MVTSEPT!$R33+[11]MVTOCT!$P33+[11]MVTNOV!$P33+[11]MVTDEC!$P33+[11]MVTJANV!$P33+[11]MVTFEV!$P33+[11]MVTMARS!$P33+[11]MVTAVRIL!$P33+[11]MVTMAI!$P33+[11]MVTJUIN!$P33+[11]MVTJUIL!$P33+[11]MVTAOUT2018!$P$33 -> 1594000 | V35: =420000-320000-100000 -> 0 | Y35: 43374 | AA35: 20109.8 | AB35: =+[12]MVTSEPT!$D36 -> 814964.22 | AC35: =AA35-AB35 -> -794854.42
AC36: =AA36-AB36 -> 0
AC37: =AA37-AB37 -> 0
AC38: =AA38-AB38 -> 0
A39: PATEGO NJOSSU GUSTAVE | B39: =+INVENT2016_2017!J37 -> 450000 | C39: =+INVENT2016_2017!I37 -> 47164.658 | D39: =[11]MVTAOUT!$H35+[11]MVTSEPT!$I35+[11]MVTOCT!$G35+[11]MVTNOV!$G35+[11]MVTDEC!$G35+[11]MVTJANV!$G35+[11]MVTFEV!$G35+[11]MVTMARS!$G35+[11]MVTAVRIL!$G35+[11]MVTMAI!$G35+[11]MVTJUIN!$G35+[11]MVTJUIL!$G35+[11]MVTAOUT2018!$G35 -> 39000 | E39: =+[11]MVTAOUT!$D35+[11]MVTSEPT!$E35+[11]MVTOCT!$C35+[11]MVTNOV!$C35+[11]MVTDEC!$C35+[11]MVTJANV!$C35+[11]MVTFEV!$C35+[11]MVTMARS!$C35+[11]MVTAVRIL!$C35+[11]MVTMAI!$C35+[11]MVTJUIN!$C35+[11]MVTJUIL!$C35 -> 19803.638 | F39: =+C39+D39+E39 -> 105968.3 | I39: 25000 | J39: 30000 | K39: =F39-G39-H39-I39-J39-35000 -> 15968.295 | L39: 35000 | O39: =B39+J39 -> 480000 | P39: =K39+O39 -> 495968.3 | R39: =[11]MVTAOUT!O35+[11]MVTSEPT!P35+[11]MVTOCT!N35+[11]MVTNOV!N35+[11]MVTDEC!N35+[11]MVTJANV!N35+[11]MVTFEV!N35+[11]MVTMARS!N35+[11]MVTAVRIL!N35+[11]MVTMAI!N35+[11]MVTJUIN!N35+[11]MVTJUIL!N35 -> 0 | S39: =[11]MVTAOUT!P35+[11]MVTSEPT!Q35+[11]MVTOCT!O35+[11]MVTNOV!O35+[11]MVTDEC!O35+[11]MVTJANV!O35+[11]MVTFEV!O35+[11]MVTMARS!O35+[11]MVTAVRIL!O35+[11]MVTMAI!O35+[11]MVTJUIN!O35+[11]MVTJUIL!O35 -> 0 | T39: =+INVENT2016_2017!N37 -> 0 | U39: =[11]MVTAOUT!$Q35+[11]MVTSEPT!$R35+[11]MVTOCT!$P35+[11]MVTNOV!$P35+[11]MVTDEC!$P35+[11]MVTJANV!$P35+[11]MVTFEV!$P35+[11]MVTMARS!$P35+[11]MVTAVRIL!$P35+[11]MVTMAI!$P35+[11]MVTJUIN!$P35+[11]MVTJUIL!$P35+[11]MVTAOUT2018!$P$35 -> 0 | AA39: 15968.295 | AB39: =+[12]MVTSEPT!$D37 -> 651185.68 | AC39: =AA39-AB39 -> -635217.39
A40: SEUNOU RICHELOT | B40: =+INVENT2016_2017!J38 -> 450000 | C40: =+INVENT2016_2017!I38 -> 39428.869 | D40: =[11]MVTAOUT!$H36+[11]MVTSEPT!$I36+[11]MVTOCT!$G36+[11]MVTNOV!$G36+[11]MVTDEC!$G36+[11]MVTJANV!$G36+[11]MVTFEV!$G36+[11]MVTMARS!$G36+[11]MVTAVRIL!$G36+[11]MVTMAI!$G36+[11]MVTJUIN!$G36+[11]MVTJUIL!$G36+[11]MVTAOUT2018!$G36 -> 39000 | E40: =+[11]MVTAOUT!$D36+[11]MVTSEPT!$E36+[11]MVTOCT!$C36+[11]MVTNOV!$C36+[11]MVTDEC!$C36+[11]MVTJANV!$C36+[11]MVTFEV!$C36+[11]MVTMARS!$C36+[11]MVTAVRIL!$C36+[11]MVTMAI!$C36+[11]MVTJUIN!$C36+[11]MVTJUIL!$C36 -> 19818.304 | F40: =+C40+D40+E40 -> 98247.173 | I40: 25000 | J40: 30000 | K40: =F40-G40-H40-I40-J40-43247 -> 0.17330694 | L40: 25000 | M40: 18247 | O40: =B40+J40 -> 480000 | P40: =K40+O40 -> 480000.17 | R40: =[11]MVTAOUT!O36+[11]MVTSEPT!P36+[11]MVTOCT!N36+[11]MVTNOV!N36+[11]MVTDEC!N36+[11]MVTJANV!N36+[11]MVTFEV!N36+[11]MVTMARS!N36+[11]MVTAVRIL!N36+[11]MVTMAI!N36+[11]MVTJUIN!N36+[11]MVTJUIL!N36 -> 2000000 | S40: =[11]MVTAOUT!P36+[11]MVTSEPT!Q36+[11]MVTOCT!O36+[11]MVTNOV!O36+[11]MVTDEC!O36+[11]MVTJANV!O36+[11]MVTFEV!O36+[11]MVTMARS!O36+[11]MVTAVRIL!O36+[11]MVTMAI!O36+[11]MVTJUIN!O36+[11]MVTJUIL!O36 -> 140000 | T40: =+INVENT2016_2017!N38 -> 1120000 | U40: =[11]MVTAOUT!$Q36+[11]MVTSEPT!$R36+[11]MVTOCT!$P36+[11]MVTNOV!$P36+[11]MVTDEC!$P36+[11]MVTJANV!$P36+[11]MVTFEV!$P36+[11]MVTMARS!$P36+[11]MVTAVRIL!$P36+[11]MVTMAI!$P36+[11]MVTJUIN!$P36+[11]MVTJUIL!$P36+[11]MVTAOUT2018!$P$36 -> 2200000 | V40: 1040000 | W40: =V40*5/100 -> 52000 | X40: =+V40+W40 -> 1092000 | Y40: 43009 | AA40: 0.17330694 | AB40: =+[12]MVTSEPT!$D38 -> 1371674.3 | AC40: =AA40-AB40 -> -1371674.1
A41: SIME ABEL | B41: 344000 | C41: =+INVENT2016_2017!I39 -> 42886.781 | D41: =[11]MVTAOUT!$H37+[11]MVTSEPT!$I37+[11]MVTOCT!$G37+[11]MVTNOV!$G37+[11]MVTDEC!$G37+[11]MVTJANV!$G37+[11]MVTFEV!$G37+[11]MVTMARS!$G37+[11]MVTAVRIL!$G37+[11]MVTMAI!$G37+[11]MVTJUIN!$G37+[11]MVTJUIL!$G37+[11]MVTAOUT2018!$G37 -> 21000 | E41: =+[11]MVTAOUT!$D37+[11]MVTSEPT!$E37+[11]MVTOCT!$C37+[11]MVTNOV!$C37+[11]MVTDEC!$C37+[11]MVTJANV!$C37+[11]MVTFEV!$C37+[11]MVTMARS!$C37+[11]MVTAVRIL!$C37+[11]MVTMAI!$C37+[11]MVTJUIN!$C37+[11]MVTJUIL!$C37 -> 18455.379 | F41: =+C41+D41+E41 -> 82342.16 | I41: 25000 | J41: 30000 | K41: =F41-G41-H41-I41-J41 -> 27342.16 | O41: 344000 | P41: =O41+K41 -> 371342.16 | R41: =[11]MVTAOUT!O37+[11]MVTSEPT!P37+[11]MVTOCT!N37+[11]MVTNOV!N37+[11]MVTDEC!N37+[11]MVTJANV!N37+[11]MVTFEV!N37+[11]MVTMARS!N37+[11]MVTAVRIL!N37+[11]MVTMAI!N37+[11]MVTJUIN!N37+[11]MVTJUIL!N37 -> 0 | S41: =[11]MVTAOUT!P37+[11]MVTSEPT!Q37+[11]MVTOCT!O37+[11]MVTNOV!O37+[11]MVTDEC!O37+[11]MVTJANV!O37+[11]MVTFEV!O37+[11]MVTMARS!O37+[11]MVTAVRIL!O37+[11]MVTMAI!O37+[11]MVTJUIN!O37+[11]MVTJUIL!O37 -> 0 | T41: =+INVENT2016_2017!N39 -> 784000 | U41: =[11]MVTAOUT!$Q37+[11]MVTSEPT!$R37+[11]MVTOCT!$P37+[11]MVTNOV!$P37+[11]MVTDEC!$P37+[11]MVTJANV!$P37+[11]MVTFEV!$P37+[11]MVTMARS!$P37+[11]MVTAVRIL!$P37+[11]MVTMAI!$P37+[11]MVTJUIN!$P37+[11]MVTJUIL!$P37+[11]MVTAOUT2018!$P$37 -> 0 | V41: 84000 | W41: =V41*5/100 -> 4200 | X41: =+V41+W41 -> 88200 | Y41: 42873 | AA41: 27342.16 | AC41: =AA41-AB41 -> 27342.16
A42: SIME FONGANG ERIC | B42: =+INVENT2016_2017!J40 -> 450000 | C42: =+INVENT2016_2017!I40 -> 53965.469 | D42: =[11]MVTAOUT!$H38+[11]MVTSEPT!$I38+[11]MVTOCT!$G38+[11]MVTNOV!$G38+[11]MVTDEC!$G38+[11]MVTJANV!$G38+[11]MVTFEV!$G38+[11]MVTMARS!$G38+[11]MVTAVRIL!$G38+[11]MVTMAI!$G38+[11]MVTJUIN!$G38+[11]MVTJUIL!$G38+[11]MVTAOUT2018!$G38 -> 39000 | E42: =+[11]MVTAOUT!$D38+[11]MVTSEPT!$E38+[11]MVTOCT!$C38+[11]MVTNOV!$C38+[11]MVTDEC!$C38+[11]MVTJANV!$C38+[11]MVTFEV!$C38+[11]MVTMARS!$C38+[11]MVTAVRIL!$C38+[11]MVTMAI!$C38+[11]MVTJUIN!$C38+[11]MVTJUIL!$C38 -> 19811.995 | F42: =+C42+D42+E42 -> 112777.46 | I42: 25000 | J42: 30000 | K42: =F42-G42-H42-I42-J42-25000 -> 32777.464 | L42: 25000 | N42: 30000 | O42: =B42+J42 -> 480000 | P42: =K42+O42 -> 512777.46 | R42: =[11]MVTAOUT!O38+[11]MVTSEPT!P38+[11]MVTOCT!N38+[11]MVTNOV!N38+[11]MVTDEC!N38+[11]MVTJANV!N38+[11]MVTFEV!N38+[11]MVTMARS!N38+[11]MVTAVRIL!N38+[11]MVTMAI!N38+[11]MVTJUIN!N38+[11]MVTJUIL!N38 -> 0 | S42: =[11]MVTAOUT!P38+[11]MVTSEPT!Q38+[11]MVTOCT!O38+[11]MVTNOV!O38+[11]MVTDEC!O38+[11]MVTJANV!O38+[11]MVTFEV!O38+[11]MVTMARS!O38+[11]MVTAVRIL!O38+[11]MVTMAI!O38+[11]MVTJUIN!O38+[11]MVTJUIL!O38 -> 0 | T42: =+INVENT2016_2017!N40 -> 1120000 | U42: =[11]MVTAOUT!$Q38+[11]MVTSEPT!$R38+[11]MVTOCT!$P38+[11]MVTNOV!$P38+[11]MVTDEC!$P38+[11]MVTJANV!$P38+[11]MVTFEV!$P38+[11]MVTMARS!$P38+[11]MVTAVRIL!$P38+[11]MVTMAI!$P38+[11]MVTJUIN!$P38+[11]MVTJUIL!$P38+[11]MVTAOUT2018!$P$38 -> 0 | V42: =1120000-U42 -> 1120000 | W42: =V42*5/100 -> 56000 | X42: =+V42+W42-32778-234000 -> 909222 | Y42: 42804 | AA42: 32777.464 | AB42: =+[12]MVTSEPT!$D40 -> 0 | AC42: =AA42-AB42 -> 32777.464
A43: SIME MATHIEU | B43: =+INVENT2016_2017!J41 -> 450000 | C43: =+INVENT2016_2017!I41 -> 49454.03 | D43: =[11]MVTAOUT!$H39+[11]MVTSEPT!$I39+[11]MVTOCT!$G39+[11]MVTNOV!$G39+[11]MVTDEC!$G39+[11]MVTJANV!$G39+[11]MVTFEV!$G39+[11]MVTMARS!$G39+[11]MVTAVRIL!$G39+[11]MVTMAI!$G39+[11]MVTJUIN!$G39+[11]MVTJUIL!$G39+[11]MVTAOUT2018!$G39 -> 39000 | E43: =+[11]MVTAOUT!$D39+[11]MVTSEPT!$E39+[11]MVTOCT!$C39+[11]MVTNOV!$C39+[11]MVTDEC!$C39+[11]MVTJANV!$C39+[11]MVTFEV!$C39+[11]MVTMARS!$C39+[11]MVTAVRIL!$C39+[11]MVTMAI!$C39+[11]MVTJUIN!$C39+[11]MVTJUIL!$C39 -> 19810.673 | F43: =+C43+D43+E43 -> 108264.7 | I43: 25000 | J43: 30000 | K43: =F43-G43-H43-I43-J43-25000-9650-18615 -> -0.29752711 | L43: 25000 | M43: 9650 | O43: =B43+J43 -> 480000 | P43: =K43+O43 -> 479999.7 | R43: =[11]MVTAOUT!O39+[11]MVTSEPT!P39+[11]MVTOCT!N39+[11]MVTNOV!N39+[11]MVTDEC!N39+[11]MVTJANV!N39+[11]MVTFEV!N39+[11]MVTMARS!N39+[11]MVTAVRIL!N39+[11]MVTMAI!N39+[11]MVTJUIN!N39+[11]MVTJUIL!N39 -> 0 | S43: =[11]MVTAOUT!P39+[11]MVTSEPT!Q39+[11]MVTOCT!O39+[11]MVTNOV!O39+[11]MVTDEC!O39+[11]MVTJANV!O39+[11]MVTFEV!O39+[11]MVTMARS!O39+[11]MVTAVRIL!O39+[11]MVTMAI!O39+[11]MVTJUIN!O39+[11]MVTJUIL!O39 -> 0 | T43: =+INVENT2016_2017!N41 -> 963000 | U43: =[11]MVTAOUT!$Q39+[11]MVTSEPT!$R39+[11]MVTOCT!$P39+[11]MVTNOV!$P39+[11]MVTDEC!$P39+[11]MVTJANV!$P39+[11]MVTFEV!$P39+[11]MVTMARS!$P39+[11]MVTAVRIL!$P39+[11]MVTMAI!$P39+[11]MVTJUIN!$P39+[11]MVTJUIL!$P39+[11]MVTAOUT2018!$P$39 -> 770000 | V43: =T43-U43 -> 193000 | W43: =V43*5/100 -> 9650 | X43: =+V43+W43-18615 -> 184035 | AA43: -0.29752711 | AB43: =+[12]MVTSEPT!$D41 -> 0 | AC43: =AA43-AB43 -> -0.29752711
A44: SIME PIERRE | B44: =+INVENT2016_2017!J42 -> 450000 | C44: =+INVENT2016_2017!I42 -> 152184.31 | D44: =[11]MVTAOUT!$H40+[11]MVTSEPT!$I40+[11]MVTOCT!$G40+[11]MVTNOV!$G40+[11]MVTDEC!$G40+[11]MVTJANV!$G40+[11]MVTFEV!$G40+[11]MVTMARS!$G40+[11]MVTAVRIL!$G40+[11]MVTMAI!$G40+[11]MVTJUIN!$G40+[11]MVTJUIL!$G40+[11]MVTAOUT2018!$G40 -> 119000 | E44: =+[11]MVTAOUT!$D40+[11]MVTSEPT!$E40+[11]MVTOCT!$C40+[11]MVTNOV!$C40+[11]MVTDEC!$C40+[11]MVTJANV!$C40+[11]MVTFEV!$C40+[11]MVTMARS!$C40+[11]MVTAVRIL!$C40+[11]MVTMAI!$C40+[11]MVTJUIN!$C40+[11]MVTJUIL!$C40 -> 20955.295 | F44: =+C44+D44+E44 -> 292139.6 | H44: 200000 | I44: 25000 | J44: 30000 | K44: =F44-G44-H44-I44-J44-37140 -> -0.39887899 | L44: 25000 | M44: 12140 | O44: =B44+J44 -> 480000 | P44: =K44+O44 -> 479999.6 | R44: =[11]MVTAOUT!O40+[11]MVTSEPT!P40+[11]MVTOCT!N40+[11]MVTNOV!N40+[11]MVTDEC!N40+[11]MVTJANV!N40+[11]MVTFEV!N40+[11]MVTMARS!N40+[11]MVTAVRIL!N40+[11]MVTMAI!N40+[11]MVTJUIN!N40+[11]MVTJUIL!N40 -> 290000 | S44: =[11]MVTAOUT!P40+[11]MVTSEPT!Q40+[11]MVTOCT!O40+[11]MVTNOV!O40+[11]MVTDEC!O40+[11]MVTJANV!O40+[11]MVTFEV!O40+[11]MVTMARS!O40+[11]MVTAVRIL!O40+[11]MVTMAI!O40+[11]MVTJUIN!O40+[11]MVTJUIL!O40 -> 20300 | T44: =+INVENT2016_2017!N42 -> 87200 | U44: =[11]MVTAOUT!$Q40+[11]MVTSEPT!$R40+[11]MVTOCT!$P40+[11]MVTNOV!$P40+[11]MVTDEC!$P40+[11]MVTJANV!$P40+[11]MVTFEV!$P40+[11]MVTMARS!$P40+[11]MVTAVRIL!$P40+[11]MVTMAI!$P40+[11]MVTJUIN!$P40+[11]MVTJUIL!$P40+[11]MVTAOUT2018!$P$40 -> 87200 | V44: 290000 | W44: =V44*5/100 -> 14500 | X44: =+V44+W44 -> 304500 | Y44: 43121 | AA44: -0.39887899 | AB44: =+[12]MVTSEPT!$D42 -> 0 | AC44: =AA44-AB44 -> -0.39887899
A45: TAGNE NANGUEN MARTIN | B45: =+INVENT2016_2017!J43 -> 450000 | C45: =+INVENT2016_2017!I43 -> 50378.244 | D45: =[11]MVTAOUT!$H41+[11]MVTSEPT!$I41+[11]MVTOCT!$G41+[11]MVTNOV!$G41+[11]MVTDEC!$G41+[11]MVTJANV!$G41+[11]MVTFEV!$G41+[11]MVTMARS!$G41+[11]MVTAVRIL!$G41+[11]MVTMAI!$G41+[11]MVTJUIN!$G41+[11]MVTJUIL!$G41+[11]MVTAOUT2018!$G41 -> 39000 | E45: =+[11]MVTAOUT!$D41+[11]MVTSEPT!$E41+[11]MVTOCT!$C41+[11]MVTNOV!$C41+[11]MVTDEC!$C41+[11]MVTJANV!$C41+[11]MVTFEV!$C41+[11]MVTMARS!$C41+[11]MVTAVRIL!$C41+[11]MVTMAI!$C41+[11]MVTJUIN!$C41+[11]MVTJUIL!$C41 -> 18511.984 | F45: =+C45+D45+E45 -> 107890.23 | I45: 25000 | J45: 30000 | K45: =F45-G45-H45-I45-J45 -> 52890.228 | N45: 40000 | O45: =B45+J45 -> 480000 | P45: =K45+O45 -> 532890.23 | R45: =[11]MVTAOUT!O41+[11]MVTSEPT!P41+[11]MVTOCT!N41+[11]MVTNOV!N41+[11]MVTDEC!N41+[11]MVTJANV!N41+[11]MVTFEV!N41+[11]MVTMARS!N41+[11]MVTAVRIL!N41+[11]MVTMAI!N41+[11]MVTJUIN!N41+[11]MVTJUIL!N41 -> 0 | S45: =[11]MVTAOUT!P41+[11]MVTSEPT!Q41+[11]MVTOCT!O41+[11]MVTNOV!O41+[11]MVTDEC!O41+[11]MVTJANV!O41+[11]MVTFEV!O41+[11]MVTMARS!O41+[11]MVTAVRIL!O41+[11]MVTMAI!O41+[11]MVTJUIN!O41+[11]MVTJUIL!O41 -> 0 | T45: =+INVENT2016_2017!N43 -> 0 | U45: =[11]MVTAOUT!$Q41+[11]MVTSEPT!$R41+[11]MVTOCT!$P41+[11]MVTNOV!$P41+[11]MVTDEC!$P41+[11]MVTJANV!$P41+[11]MVTFEV!$P41+[11]MVTMARS!$P41+[11]MVTAVRIL!$P41+[11]MVTMAI!$P41+[11]MVTJUIN!$P41+[11]MVTJUIL!$P41+[11]MVTAOUT2018!$P$41 -> 0 | AA45: 52890.228 | AB45: =+[12]MVTSEPT!$D26 -> 751990.68 | AC45: =AA45-AB45 -> -699100.45
A46: TCHOUAMOU JEAN PAUL | B46: 50000 | C46: =+INVENT2016_2017!I44 -> 0 | D46: =[11]MVTAOUT!$H42+[11]MVTSEPT!$I42+[11]MVTOCT!$G42+[11]MVTNOV!$G42+[11]MVTDEC!$G42+[11]MVTJANV!$G42+[11]MVTFEV!$G42+[11]MVTMARS!$G42+[11]MVTAVRIL!$G42+[11]MVTMAI!$G42+[11]MVTJUIN!$G42+[11]MVTJUIL!$G42+[11]MVTAOUT2018!$G42 -> 0 | E46: =+[11]MVTAOUT!$D42+[11]MVTSEPT!$E42+[11]MVTOCT!$C42+[11]MVTNOV!$C42+[11]MVTDEC!$C42+[11]MVTJANV!$C42+[11]MVTFEV!$C42+[11]MVTMARS!$C42+[11]MVTAVRIL!$C42+[11]MVTMAI!$C42+[11]MVTJUIN!$C42+[11]MVTJUIL!$C42 -> 2156.6179 | F46: =+C46+D46+E46 -> 2156.6179 | I46: 9055 | J46: 30000 | K46: =F46-G46-H46-I46-J46 -> -36898.382 | O46: 50000 | P46: =K46+O46 -> 13101.618 | R46: =[11]MVTAOUT!O42+[11]MVTSEPT!P42+[11]MVTOCT!N42+[11]MVTNOV!N42+[11]MVTDEC!N42+[11]MVTJANV!N42+[11]MVTFEV!N42+[11]MVTMARS!N42+[11]MVTAVRIL!N42+[11]MVTMAI!N42+[11]MVTJUIN!N42+[11]MVTJUIL!N42 -> 0 | S46: =[11]MVTAOUT!P42+[11]MVTSEPT!Q42+[11]MVTOCT!O42+[11]MVTNOV!O42+[11]MVTDEC!O42+[11]MVTJANV!O42+[11]MVTFEV!O42+[11]MVTMARS!O42+[11]MVTAVRIL!O42+[11]MVTMAI!O42+[11]MVTJUIN!O42+[11]MVTJUIL!O42 -> 0 | T46: =+INVENT2016_2017!N44 -> 0 | U46: =[11]MVTAOUT!$Q42+[11]MVTSEPT!$R42+[11]MVTOCT!$P42+[11]MVTNOV!$P42+[11]MVTDEC!$P42+[11]MVTJANV!$P42+[11]MVTFEV!$P42+[11]MVTMARS!$P42+[11]MVTAVRIL!$P42+[11]MVTMAI!$P42+[11]MVTJUIN!$P42+[11]MVTJUIL!$P42+[11]MVTAOUT2018!$P$42 -> 0 | AA46: 37.869003 | AB46: 38 | AC46: =AA46-AB46 -> -0.1309967
A47: TCHOUAMOU MATHIEU | B47: =+INVENT2016_2017!J45 -> 450000 | C47: =+INVENT2016_2017!I45 -> 47556.521 | D47: =[11]MVTAOUT!$H43+[11]MVTSEPT!$I43+[11]MVTOCT!$G43+[11]MVTNOV!$G43+[11]MVTDEC!$G43+[11]MVTJANV!$G43+[11]MVTFEV!$G43+[11]MVTMARS!$G43+[11]MVTAVRIL!$G43+[11]MVTMAI!$G43+[11]MVTJUIN!$G43+[11]MVTJUIL!$G43+[11]MVTAOUT2018!$G43 -> 39000 | E47: =+[11]MVTAOUT!$D43+[11]MVTSEPT!$E43+[11]MVTOCT!$C43+[11]MVTNOV!$C43+[11]MVTDEC!$C43+[11]MVTJANV!$C43+[11]MVTFEV!$C43+[11]MVTMARS!$C43+[11]MVTAVRIL!$C43+[11]MVTMAI!$C43+[11]MVTJUIN!$C43+[11]MVTJUIL!$C43 -> 19804.254 | F47: =+C47+D47+E47 -> 106360.78 | I47: 25000 | J47: 30000 | K47: =F47-G47-H47-I47-J47 -> 51360.775 | N47: 50000 | O47: =B47+J47 -> 480000 | P47: =K47+O47 -> 531360.78 | R47: =[11]MVTAOUT!O43+[11]MVTSEPT!P43+[11]MVTOCT!N43+[11]MVTNOV!N43+[11]MVTDEC!N43+[11]MVTJANV!N43+[11]MVTFEV!N43+[11]MVTMARS!N43+[11]MVTAVRIL!N43+[11]MVTMAI!N43+[11]MVTJUIN!N43+[11]MVTJUIL!N43 -> 0 | S47: =[11]MVTAOUT!P43+[11]MVTSEPT!Q43+[11]MVTOCT!O43+[11]MVTNOV!O43+[11]MVTDEC!O43+[11]MVTJANV!O43+[11]MVTFEV!O43+[11]MVTMARS!O43+[11]MVTAVRIL!O43+[11]MVTMAI!O43+[11]MVTJUIN!O43+[11]MVTJUIL!O43 -> 0 | T47: =+INVENT2016_2017!N45 -> 0 | U47: =[11]MVTAOUT!$Q43+[11]MVTSEPT!$R43+[11]MVTOCT!$P43+[11]MVTNOV!$P43+[11]MVTDEC!$P43+[11]MVTJANV!$P43+[11]MVTFEV!$P43+[11]MVTMARS!$P43+[11]MVTAVRIL!$P43+[11]MVTMAI!$P43+[11]MVTJUIN!$P43+[11]MVTJUIL!$P43+[11]MVTAOUT2018!$P$43 -> 0 | AA47: 51360.775 | AB47: =+[12]MVTSEPT!$D43 -> 0 | AC47: =AA47-AB47 -> 51360.775
A48: TCHOUANTE FRANCOIS | B48: =+INVENT2016_2017!J46 -> 450000 | C48: =+INVENT2016_2017!I46 -> 115459.9 | D48: =[11]MVTAOUT!$H44+[11]MVTSEPT!$I44+[11]MVTOCT!$G44+[11]MVTNOV!$G44+[11]MVTDEC!$G44+[11]MVTJANV!$G44+[11]MVTFEV!$G44+[11]MVTMARS!$G44+[11]MVTAVRIL!$G44+[11]MVTMAI!$G44+[11]MVTJUIN!$G44+[11]MVTJUIL!$G44+[11]MVTAOUT2018!$G44 -> 24000 | E48: =+[11]MVTAOUT!$D44+[11]MVTSEPT!$E44+[11]MVTOCT!$C44+[11]MVTNOV!$C44+[11]MVTDEC!$C44+[11]MVTJANV!$C44+[11]MVTFEV!$C44+[11]MVTMARS!$C44+[11]MVTAVRIL!$C44+[11]MVTMAI!$C44+[11]MVTJUIN!$C44+[11]MVTJUIL!$C44 -> 19340.451 | F48: =+C48+D48+E48 -> 158800.35 | I48: 25000 | J48: 30000 | K48: =F48-G48-H48-I48-J48-42575-25000 -> 36225.354 | L48: 25000 | M48: 42575 | N48: 35000 | O48: =B48+J48 -> 480000 | P48: =K48+O48 -> 516225.35 | R48: =[11]MVTAOUT!O44+[11]MVTSEPT!P44+[11]MVTOCT!N44+[11]MVTNOV!N44+[11]MVTDEC!N44+[11]MVTJANV!N44+[11]MVTFEV!N44+[11]MVTMARS!N44+[11]MVTAVRIL!N44+[11]MVTMAI!N44+[11]MVTJUIN!N44+[11]MVTJUIL!N44 -> 0 | S48: =[11]MVTAOUT!P44+[11]MVTSEPT!Q44+[11]MVTOCT!O44+[11]MVTNOV!O44+[11]MVTDEC!O44+[11]MVTJANV!O44+[11]MVTFEV!O44+[11]MVTMARS!O44+[11]MVTAVRIL!O44+[11]MVTMAI!O44+[11]MVTJUIN!O44+[11]MVTJUIL!O44 -> 0 | T48: =+INVENT2016_2017!N46 -> 851500 | U48: =[11]MVTAOUT!$Q44+[11]MVTSEPT!$R44+[11]MVTOCT!$P44+[11]MVTNOV!$P44+[11]MVTDEC!$P44+[11]MVTJANV!$P44+[11]MVTFEV!$P44+[11]MVTMARS!$P44+[11]MVTAVRIL!$P44+[11]MVTMAI!$P44+[11]MVTJUIN!$P44+[11]MVTJUIL!$P44+[11]MVTAOUT2018!$P$44 -> 0 | V48: 851500 | W48: 0 | X48: =+V48+W48 -> 851500 | Y48: 42876 | AA48: 36225.354 | AB48: =+[12]MVTSEPT!$D44 -> 32545683 | AC48: =AA48-AB48 -> -32509458
A49: TCHOUTOU NANA CLAUDE | B49: 30000 | C49: =+INVENT2016_2017!I47 -> 0 | D49: =[11]MVTAOUT!$H45+[11]MVTSEPT!$I45+[11]MVTOCT!$G45+[11]MVTNOV!$G45+[11]MVTDEC!$G45+[11]MVTJANV!$G45+[11]MVTFEV!$G45+[11]MVTMARS!$G45+[11]MVTAVRIL!$G45+[11]MVTMAI!$G45+[11]MVTJUIN!$G45+[11]MVTJUIL!$G45+[11]MVTAOUT2018!$G45 -> 0 | E49: =+[11]MVTAOUT!$D45+[11]MVTSEPT!$E45+[11]MVTOCT!$C45+[11]MVTNOV!$C45+[11]MVTDEC!$C45+[11]MVTJANV!$C45+[11]MVTFEV!$C45+[11]MVTMARS!$C45+[11]MVTAVRIL!$C45+[11]MVTMAI!$C45+[11]MVTJUIN!$C45+[11]MVTJUIL!$C45 -> 1204.954 | F49: =+C49+D49+E49 -> 1204.954 | I49: 7540 | J49: 0 | K49: =F49-G49-H49-I49-J49 -> -6335.046 | O49: 30000 | P49: =K49+O49 -> 23664.954 | R49: =[11]MVTAOUT!O45+[11]MVTSEPT!P45+[11]MVTOCT!N45+[11]MVTNOV!N45+[11]MVTDEC!N45+[11]MVTJANV!N45+[11]MVTFEV!N45+[11]MVTMARS!N45+[11]MVTAVRIL!N45+[11]MVTMAI!N45+[11]MVTJUIN!N45+[11]MVTJUIL!N45 -> 0 | S49: =[11]MVTAOUT!P45+[11]MVTSEPT!Q45+[11]MVTOCT!O45+[11]MVTNOV!O45+[11]MVTDEC!O45+[11]MVTJANV!O45+[11]MVTFEV!O45+[11]MVTMARS!O45+[11]MVTAVRIL!O45+[11]MVTMAI!O45+[11]MVTJUIN!O45+[11]MVTJUIL!O45 -> 0 | T49: =+INVENT2016_2017!N47 -> 0 | U49: =[11]MVTAOUT!$Q45+[11]MVTSEPT!$R45+[11]MVTOCT!$P45+[11]MVTNOV!$P45+[11]MVTDEC!$P45+[11]MVTJANV!$P45+[11]MVTFEV!$P45+[11]MVTMARS!$P45+[11]MVTAVRIL!$P45+[11]MVTMAI!$P45+[11]MVTJUIN!$P45+[11]MVTJUIL!$P45+[11]MVTAOUT2018!$P$45 -> 0 | AA49: 21.303203 | AB49: =+[12]MVTSEPT!$D45 -> 0 | AC49: =AA49-AB49 -> 21.303203
A50: TIEYAM ERNEST | B50: =+INVENT2016_2017!J48 -> 450000 | C50: =+INVENT2016_2017!I48 -> 64088.865 | D50: =[11]MVTAOUT!$H46+[11]MVTSEPT!$I46+[11]MVTOCT!$G46+[11]MVTNOV!$G46+[11]MVTDEC!$G46+[11]MVTJANV!$G46+[11]MVTFEV!$G46+[11]MVTMARS!$G46+[11]MVTAVRIL!$G46+[11]MVTMAI!$G46+[11]MVTJUIN!$G46+[11]MVTJUIL!$G46+[11]MVTAOUT2018!$G46 -> 36000 | E50: =+[11]MVTAOUT!$D46+[11]MVTSEPT!$E46+[11]MVTOCT!$C46+[11]MVTNOV!$C46+[11]MVTDEC!$C46+[11]MVTJANV!$C46+[11]MVTFEV!$C46+[11]MVTMARS!$C46+[11]MVTAVRIL!$C46+[11]MVTMAI!$C46+[11]MVTJUIN!$C46+[11]MVTJUIL!$C46 -> 19893.286 | F50: =+C50+D50+E50 -> 119982.15 | I50: 25000 | J50: 30000 | K50: =F50-G50-H50-I50-J50-64982 -> 0.15040473 | L50: 25000 | M50: 32982 | O50: =B50+J50 -> 480000 | P50: =K50+O50 -> 480000.15 | R50: =[11]MVTAOUT!O46+[11]MVTSEPT!P46+[11]MVTOCT!N46+[11]MVTNOV!N46+[11]MVTDEC!N46+[11]MVTJANV!N46+[11]MVTFEV!N46+[11]MVTMARS!N46+[11]MVTAVRIL!N46+[11]MVTMAI!N46+[11]MVTJUIN!N46+[11]MVTJUIL!N46 -> 1000000 | S50: =[11]MVTAOUT!P46+[11]MVTSEPT!Q46+[11]MVTOCT!O46+[11]MVTNOV!O46+[11]MVTDEC!O46+[11]MVTJANV!O46+[11]MVTFEV!O46+[11]MVTMARS!O46+[11]MVTAVRIL!O46+[11]MVTMAI!O46+[11]MVTJUIN!O46+[11]MVTJUIL!O46 -> 30000 | T50: =+INVENT2016_2017!N48 -> 1064000 | U50: =[11]MVTAOUT!$Q46+[11]MVTSEPT!$R46+[11]MVTOCT!$P46+[11]MVTNOV!$P46+[11]MVTDEC!$P46+[11]MVTJANV!$P46+[11]MVTFEV!$P46+[11]MVTMARS!$P46+[11]MVTAVRIL!$P46+[11]MVTMAI!$P46+[11]MVTJUIN!$P46+[11]MVTJUIL!$P46+[11]MVTAOUT2018!$P$46 -> 1293600 | V50: =1885600-885600-100000 -> 900000 | W50: =V50*5/100 -> 45000 | X50: =+V50+W50-39983 -> 905017 | Y50: 43241 | AA50: 0.15040473 | AB50: =+[12]MVTSEPT!$D46 -> 0 | AC50: =AA50-AB50 -> 0.15040473
A51: TUGMA PIERRE LOTI | B51: =+INVENT2016_2017!J49 -> 450000 | C51: =+INVENT2016_2017!I49 -> 52395.569 | D51: =[11]MVTAOUT!$H47+[11]MVTSEPT!$I47+[11]MVTOCT!$G47+[11]MVTNOV!$G47+[11]MVTDEC!$G47+[11]MVTJANV!$G47+[11]MVTFEV!$G47+[11]MVTMARS!$G47+[11]MVTAVRIL!$G47+[11]MVTMAI!$G47+[11]MVTJUIN!$G47+[11]MVTJUIL!$G47+[11]MVTAOUT2018!$G47 -> 0 | E51: =+[11]MVTAOUT!$D47+[11]MVTSEPT!$E47+[11]MVTOCT!$C47+[11]MVTNOV!$C47+[11]MVTDEC!$C47+[11]MVTJANV!$C47+[11]MVTFEV!$C47+[11]MVTMARS!$C47+[11]MVTAVRIL!$C47+[11]MVTMAI!$C47+[11]MVTJUIN!$C47+[11]MVTJUIL!$C47 -> 19295.137 | F51: =+C51+D51+E51 -> 71690.706 | I51: 25000 | J51: 30000 | K51: =F51-G51-H51-I51-J51 -> 16690.706 | N51: 15000 | O51: =B51+J51 -> 480000 | P51: =K51+O51 -> 496690.71 | R51: =[11]MVTAOUT!O47+[11]MVTSEPT!P47+[11]MVTOCT!N47+[11]MVTNOV!N47+[11]MVTDEC!N47+[11]MVTJANV!N47+[11]MVTFEV!N47+[11]MVTMARS!N47+[11]MVTAVRIL!N47+[11]MVTMAI!N47+[11]MVTJUIN!N47+[11]MVTJUIL!N47 -> 0 | S51: =[11]MVTAOUT!P47+[11]MVTSEPT!Q47+[11]MVTOCT!O47+[11]MVTNOV!O47+[11]MVTDEC!O47+[11]MVTJANV!O47+[11]MVTFEV!O47+[11]MVTMARS!O47+[11]MVTAVRIL!O47+[11]MVTMAI!O47+[11]MVTJUIN!O47+[11]MVTJUIL!O47 -> 0 | T51: =+INVENT2016_2017!N49 -> 1120000 | U51: =[11]MVTAOUT!$Q47+[11]MVTSEPT!$R47+[11]MVTOCT!$P47+[11]MVTNOV!$P47+[11]MVTDEC!$P47+[11]MVTJANV!$P47+[11]MVTFEV!$P47+[11]MVTMARS!$P47+[11]MVTAVRIL!$P47+[11]MVTMAI!$P47+[11]MVTJUIN!$P47+[11]MVTJUIL!$P47+[11]MVTAOUT2018!$P$47 -> 0 | V51: 0 | AA51: 16690.706 | AB51: 0 | AC51: =AA51-AB51 -> 16690.706
A52: YEPMOU JEAN JACQUES | B52: =+INVENT2016_2017!J50 -> 450000 | C52: =+INVENT2016_2017!I50 -> 460575.58 | D52: =[11]MVTAOUT!$H48+[11]MVTSEPT!$I48+[11]MVTOCT!$G48+[11]MVTNOV!$G48+[11]MVTDEC!$G48+[11]MVTJANV!$G48+[11]MVTFEV!$G48+[11]MVTMARS!$G48+[11]MVTAVRIL!$G48+[11]MVTMAI!$G48+[11]MVTJUIN!$G48+[11]MVTJUIL!$G48+[11]MVTAOUT2018!$G48 -> 39000 | E52: =+[11]MVTAOUT!$D48+[11]MVTSEPT!$E48+[11]MVTOCT!$C48+[11]MVTNOV!$C48+[11]MVTDEC!$C48+[11]MVTJANV!$C48+[11]MVTFEV!$C48+[11]MVTMARS!$C48+[11]MVTAVRIL!$C48+[11]MVTMAI!$C48+[11]MVTJUIN!$C48+[11]MVTJUIL!$C48 -> 21144.593 | F52: =+C52+D52+E52 -> 520720.18 | I52: 25000 | J52: 30000 | K52: =F52-G52-H52-I52-J52-25000 -> 440720.18 | L52: 25000 | O52: =B52+J52 -> 480000 | P52: =K52+O52 -> 920720.18 | R52: =[11]MVTAOUT!O48+[11]MVTSEPT!P48+[11]MVTOCT!N48+[11]MVTNOV!N48+[11]MVTDEC!N48+[11]MVTJANV!N48+[11]MVTFEV!N48+[11]MVTMARS!N48+[11]MVTAVRIL!N48+[11]MVTMAI!N48+[11]MVTJUIN!N48+[11]MVTJUIL!N48 -> 0 | S52: =[11]MVTAOUT!P48+[11]MVTSEPT!Q48+[11]MVTOCT!O48+[11]MVTNOV!O48+[11]MVTDEC!O48+[11]MVTJANV!O48+[11]MVTFEV!O48+[11]MVTMARS!O48+[11]MVTAVRIL!O48+[11]MVTMAI!O48+[11]MVTJUIN!O48+[11]MVTJUIL!O48 -> 0 | T52: =+INVENT2016_2017!N50 -> 0 | U52: =[11]MVTAOUT!$Q48+[11]MVTSEPT!$R48+[11]MVTOCT!$P48+[11]MVTNOV!$P48+[11]MVTDEC!$P48+[11]MVTJANV!$P48+[11]MVTFEV!$P48+[11]MVTMARS!$P48+[11]MVTAVRIL!$P48+[11]MVTMAI!$P48+[11]MVTJUIN!$P48+[11]MVTJUIL!$P48+[11]MVTAOUT2018!$P$48 -> 0 | AA52: 440720.18 | AB52: =+[12]MVTSEPT!$D47 -> TONTINE | AC52: =AA52-AB52 -> #VALUE!
A53: YOUMBI EMMANUEL | B53: =+INVENT2016_2017!J51 -> 450000 | C53: =+INVENT2016_2017!I51 -> 1205652.8 | D53: =[11]MVTAOUT!$H49+[11]MVTSEPT!$I49+[11]MVTOCT!$G49+[11]MVTNOV!$G49+[11]MVTDEC!$G49+[11]MVTJANV!$G49+[11]MVTFEV!$G49+[11]MVTMARS!$G49+[11]MVTAVRIL!$G49+[11]MVTMAI!$G49+[11]MVTJUIN!$G49+[11]MVTJUIL!$G49+[11]MVTAOUT2018!$G49 -> 39000 | E53: =+[11]MVTAOUT!$D49+[11]MVTSEPT!$E49+[11]MVTOCT!$C49+[11]MVTNOV!$C49+[11]MVTDEC!$C49+[11]MVTJANV!$C49+[11]MVTFEV!$C49+[11]MVTMARS!$C49+[11]MVTAVRIL!$C49+[11]MVTMAI!$C49+[11]MVTJUIN!$C49+[11]MVTJUIL!$C49 -> 23501.828 | F53: =+C53+D53+E53 -> 1268154.7 | I53: 25000 | J53: 30000 | K53: =F53-G53-H53-I53-J53-15000 -> 1198154.7 | L53: 15000 | O53: =B53+J53 -> 480000 | P53: =K53+O53 -> 1678154.7 | R53: =[11]MVTAOUT!O49+[11]MVTSEPT!P49+[11]MVTOCT!N49+[11]MVTNOV!N49+[11]MVTDEC!N49+[11]MVTJANV!N49+[11]MVTFEV!N49+[11]MVTMARS!N49+[11]MVTAVRIL!N49+[11]MVTMAI!N49+[11]MVTJUIN!N49+[11]MVTJUIL!N49 -> 0 | S53: =[11]MVTAOUT!P49+[11]MVTSEPT!Q49+[11]MVTOCT!O49+[11]MVTNOV!O49+[11]MVTDEC!O49+[11]MVTJANV!O49+[11]MVTFEV!O49+[11]MVTMARS!O49+[11]MVTAVRIL!O49+[11]MVTMAI!O49+[11]MVTJUIN!O49+[11]MVTJUIL!O49 -> 0 | T53: =+INVENT2016_2017!N51 -> 0 | U53: =[11]MVTAOUT!$Q49+[11]MVTSEPT!$R49+[11]MVTOCT!$P49+[11]MVTNOV!$P49+[11]MVTDEC!$P49+[11]MVTJANV!$P49+[11]MVTFEV!$P49+[11]MVTMARS!$P49+[11]MVTAVRIL!$P49+[11]MVTMAI!$P49+[11]MVTJUIN!$P49+[11]MVTJUIL!$P49+[11]MVTAOUT2018!$P$49 -> 0 | AA53: 1198154.7 | AB53: =+[12]MVTSEPT!$D48 -> PENALITE VERST ESPECES | AC53: =AA53-AB53 -> #VALUE!
A54: MBOGNING TUGMA GUY | B54: =+INVENT2016_2017!J52 -> 450000 | C54: =+INVENT2016_2017!I52 -> 0 | D54: =[11]MVTAOUT!$H50+[11]MVTSEPT!$I50+[11]MVTOCT!$G50+[11]MVTNOV!$G50+[11]MVTDEC!$G50+[11]MVTJANV!$G50+[11]MVTFEV!$G50+[11]MVTMARS!$G50+[11]MVTAVRIL!$G50+[11]MVTMAI!$G50+[11]MVTJUIN!$G50+[11]MVTJUIL!$G50+[11]MVTAOUT2018!$G50 -> 57000 | E54: =+[11]MVTAOUT!$D50+[11]MVTSEPT!$E50+[11]MVTOCT!$C50+[11]MVTNOV!$C50+[11]MVTDEC!$C50+[11]MVTJANV!$C50+[11]MVTFEV!$C50+[11]MVTMARS!$C50+[11]MVTAVRIL!$C50+[11]MVTMAI!$C50+[11]MVTJUIN!$C50+[11]MVTJUIL!$C50 -> 88.527006 | F54: =+C54+D54+E54 -> 57088.527 | I54: 24094 | J54: 30000 | K54: =F54-G54-H54-I54-J54 -> 2994.527 | O54: =B54+J54 -> 480000 | P54: =K54+O54 -> 482994.53 | R54: =[11]MVTAOUT!O50+[11]MVTSEPT!P50+[11]MVTOCT!N50+[11]MVTNOV!N50+[11]MVTDEC!N50+[11]MVTJANV!N50+[11]MVTFEV!N50+[11]MVTMARS!N50+[11]MVTAVRIL!N50+[11]MVTMAI!N50+[11]MVTJUIN!N50+[11]MVTJUIL!N50 -> 1000000 | S54: =[11]MVTAOUT!P50+[11]MVTSEPT!Q50+[11]MVTOCT!O50+[11]MVTNOV!O50+[11]MVTDEC!O50+[11]MVTJANV!O50+[11]MVTFEV!O50+[11]MVTMARS!O50+[11]MVTAVRIL!O50+[11]MVTMAI!O50+[11]MVTJUIN!O50+[11]MVTJUIL!O50 -> 60000 | T54: =+INVENT2016_2017!N52 -> 0 | U54: =[11]MVTAOUT!$Q50+[11]MVTSEPT!$R50+[11]MVTOCT!$P50+[11]MVTNOV!$P50+[11]MVTDEC!$P50+[11]MVTJANV!$P50+[11]MVTFEV!$P50+[11]MVTMARS!$P50+[11]MVTAVRIL!$P50+[11]MVTMAI!$P50+[11]MVTJUIN!$P50+[11]MVTJUIL!$P50+[11]MVTAOUT2018!$P$50 -> 1060000 | V54: =1060000-1060000 -> 0 | Y54: 43148 | AA54: 2994.527 | AB54: =+[12]MVTSEPT!$D50 -> EPARGNE
A55: DJOMO DOMO | B55: 0 | C55: =+INVENT2016_2017!I53 -> 0 | D55: =[11]MVTAOUT!$H51+[11]MVTSEPT!$I51+[11]MVTOCT!$G51+[11]MVTNOV!$G51+[11]MVTDEC!$G51+[11]MVTJANV!$G51+[11]MVTFEV!$G51+[11]MVTMARS!$G51+[11]MVTAVRIL!$G51+[11]MVTMAI!$G51+[11]MVTJUIN!$G51+[11]MVTJUIL!$G51+[11]MVTAOUT2018!$G51 -> 27000 | E55: =+[11]MVTAOUT!$D51+[11]MVTSEPT!$E51+[11]MVTOCT!$C51+[11]MVTNOV!$C51+[11]MVTDEC!$C51+[11]MVTJANV!$C51+[11]MVTFEV!$C51+[11]MVTMARS!$C51+[11]MVTAVRIL!$C51+[11]MVTMAI!$C51+[11]MVTJUIN!$C51+[11]MVTJUIL!$C51 -> 88.527006 | F55: =+C55+D55+E55 -> 27088.527 | I55: 24094 | K55: =F55-G55-H55-I55-J55 -> 2994.527 | O55: 0 | P55: =O55+K55 -> 2994.527 | R55: =[11]MVTAOUT!O51+[11]MVTSEPT!P51+[11]MVTOCT!N51+[11]MVTNOV!N51+[11]MVTDEC!N51+[11]MVTJANV!N51+[11]MVTFEV!N51+[11]MVTMARS!N51+[11]MVTAVRIL!N51+[11]MVTMAI!N51+[11]MVTJUIN!N51+[11]MVTJUIL!N51 -> 0 | S55: =[11]MVTAOUT!P51+[11]MVTSEPT!Q51+[11]MVTOCT!O51+[11]MVTNOV!O51+[11]MVTDEC!O51+[11]MVTJANV!O51+[11]MVTFEV!O51+[11]MVTMARS!O51+[11]MVTAVRIL!O51+[11]MVTMAI!O51+[11]MVTJUIN!O51+[11]MVTJUIL!O51 -> 0 | T55: =+INVENT2016_2017!N53 -> 0 | U55: =[11]MVTAOUT!$Q51+[11]MVTSEPT!$R51+[11]MVTOCT!$P51+[11]MVTNOV!$P51+[11]MVTDEC!$P51+[11]MVTJANV!$P51+[11]MVTFEV!$P51+[11]MVTMARS!$P51+[11]MVTAVRIL!$P51+[11]MVTMAI!$P51+[11]MVTJUIN!$P51+[11]MVTJUIL!$P51+[11]MVTAOUT2018!$P$51 -> 0 | AA55: 2994.527
