Workbook

Sheet Sheet1
A1: AIDE
A2: PRÊT
A3: REMBOURSEMENT
A4: AGIOS BANCAIRE
A5: DETAIL CHEQUE
A6: RAPPORT FINANCIER

Sheet Sheet2
A1: BANQUE
A2: ESPECES
A3: ECHEC

Sheet Sheet3
A1: BANQUE
A2: ESPECES
A3: ECHEC

Sheet Sheet4
A1: ASSOCIATION | B1: ASELBY | G1: K
A2: ANNEE | B2: 2022
A3: TONTINE
J4: 44578
A5: MATRICULE | B5: NOM ET PRENOM | C5: FONDES DE DEPART | D5: RELIQUAT | E5: RETRAIT PARTIEL | F5: FONDS DEFINITIF | G5: REPARTITION INTERET | H5: CAPITAL COMPOSE | I5: SANCTION | J5: RESTE | K5: EPARGNE | L5: FONDS DE ROULEMENT | M5: FRAIS EXCEPTIONNEL | N5: COLLATION | O5: PENALITE VST ESPECES | P5: INSCRISPTION | Q5: MUTUELLE | R5: PRÊT FONDS | S5: INTERETPRET FONDS | T5: NUMERO CHEQUE | U5: REMBOURSEMENTPRET FONDS | V5: MODE VERSEMENT REMBOURSEMENT | W5: MODE VERSEMENT PRÊT | X5: NUMERO CHEQUE | Y5: PENALITE PRET FONDS | Z5: PENALITE FONDS | AA5: PENALITE ECHEC TONTINE | AB5: PENALITE RETARD TONTINE | AC5: REMBOURSEMENT TRANSPORT | AD5: CONTRIBUTION FOYER | AE5: DEPENSE FONCTIONNEMENT
A6: AS201648 | B6: =VLOOKUP(A6,[15]LISTADHERENT!$A$5:$J$50,3,0) -> ASELBY | C6: =#REF! -> #REF! | D6: =#REF! -> #REF! | F6: =C6+D6-E6+K6 -> #REF! | G6: =$S$40/$H$40*H6 -> #REF! | H6: =F6+D6+K6 -> #REF! | AE6: =[16]HISTOMVTDEPENSE!$T$39 -> 0
A7: AS201601 | B7: =VLOOKUP(A7,[15]LISTADHERENT!$A$5:$J$50,3,0) -> BAKOP ACHILLE | C7: =#REF! -> #REF! | D7: =#REF! -> #REF! | F7: =C7+D7-E7+K7 -> #REF! | G7: =$S$40/$H$40*H7 -> #REF! | H7: =F7+D7+K7 -> #REF! | Y7: 4000
A8: AS201602 | B8: =VLOOKUP(A8,[15]LISTADHERENT!$A$5:$J$50,3,0) -> BOUTCHOUANG WILLIAM | C8: =#REF! -> #REF! | D8: =#REF! -> #REF! | F8: =C8+D8-E8+K8 -> #REF! | G8: =$S$40/$H$40*H8 -> #REF! | H8: =F8+D8+K8 -> #REF! | I8: =VLOOKUP($A8,[16]HISTOJANV22!$A$6:$AQ$37,22,0) -> 0 | J8: =VLOOKUP($A8,[16]HISTOJANV22!$A$6:$AU$39,45,0) -> 7000 | K8: =IF(J8=0,0,J8-(L8+M8+N8)) -> 3000 | L8: =IF(J8=0,0,500) -> 500 | M8: =IF(J8=0,0,1000) -> 1000 | N8: =IF(J8=0,0,2500) -> 2500 | O8: =VLOOKUP($A8,[16]HISTOJANV22!$A$6:$AU$39,7,0) -> 0 | P8: =VLOOKUP($A8,[16]HISTOJANV22!$A$6:$AU$39,23,0) -> 0 | Q8: =VLOOKUP($A8,[16]HISTOJANV22!$A$6:$AU$39,46,0) -> 0 | R8: =VLOOKUP($A8,[16]HISTODEC21!$A$6:$AU$39,26,0) -> 525000 | S8: =R8*12/1200*12 -> 63000 | T8: =VLOOKUP($A8,[16]HISTOJANV22!$A$6:$AU$39,28,0) -> 0 | U8: =VLOOKUP($A8,[16]HISTOJANV22!$A$6:$AU$39,19,0) -> 0 | V8: =VLOOKUP($A8,[16]HISTOJANV22!$A$6:$AU$39,20,0) -> 0 | W8: =VLOOKUP($A8,[16]HISTOJANV22!$A$6:$AU$39,27,0) -> 0 | X8: =VLOOKUP($A8,[16]HISTOJANV22!$A$6:$AU$39,33,0) -> 0 | AA8: =VLOOKUP($A8,[16]HISTOJANV22!$A$6:$AU$39,43,0) -> 0 | AB8: =VLOOKUP($A8,[16]HISTOJANV22!$A$6:$AU$39,44,0) -> 0 | AC8: =VLOOKUP($A8,[16]HISTOJANV22!$A$6:$AU$39,47,0) -> 0 | AD8: =VLOOKUP(A8,[16]HISTOJANV22!$A$6:$BB$36,54,0) -> 0
A9: AS201604 | B9: =VLOOKUP(A9,[15]LISTADHERENT!$A$5:$J$50,3,0) -> DJOMO JEAN PAUL | C9: =#REF! -> #REF! | D9: =#REF! -> #REF! | F9: =C9+D9-E9+K9 -> #REF! | G9: =$S$40/$H$40*H9 -> #REF! | H9: =F9+D9+K9 -> #REF! | I9: =VLOOKUP($A9,[16]HISTOJANV22!$A$6:$AQ$37,22,0) -> 0 | J9: =VLOOKUP($A9,[16]HISTOJANV22!$A$6:$AU$39,45,0) -> 52000 | K9: =IF(J9=0,0,J9-(L9+M9+N9)) -> 48000 | L9: =IF(J9=0,0,500) -> 500 | M9: =IF(J9=0,0,1000) -> 1000 | N9: =IF(J9=0,0,2500) -> 2500 | O9: =VLOOKUP($A9,[16]HISTOJANV22!$A$6:$AU$39,7,0) -> 0 | P9: =VLOOKUP($A9,[16]HISTOJANV22!$A$6:$AU$39,23,0) -> 0 | Q9: =VLOOKUP($A9,[16]HISTOJANV22!$A$6:$AU$39,46,0) -> 0 | R9: =VLOOKUP($A9,[16]HISTODEC21!$A$6:$AU$39,26,0) -> 1000000 | S9: =R9*12/1200*12 -> 120000 | T9: =VLOOKUP($A9,[16]HISTOJANV22!$A$6:$AU$39,28,0) -> OKK | U9: =VLOOKUP($A9,[16]HISTOJANV22!$A$6:$AU$39,19,0) -> 0 | V9: =VLOOKUP($A9,[16]HISTOJANV22!$A$6:$AU$39,20,0) -> 0 | W9: =VLOOKUP($A9,[16]HISTOJANV22!$A$6:$AU$39,27,0) -> BANQUE | X9: =VLOOKUP($A9,[16]HISTOJANV22!$A$6:$AU$39,33,0) -> 0 | AA9: =VLOOKUP($A9,[16]HISTOJANV22!$A$6:$AU$39,43,0) -> 0 | AB9: =VLOOKUP($A9,[16]HISTOJANV22!$A$6:$AU$39,44,0) -> 0 | AC9: =VLOOKUP($A9,[16]HISTOJANV22!$A$6:$AU$39,47,0) -> 0 | AD9: =VLOOKUP(A9,[16]HISTOJANV22!$A$6:$BB$36,54,0) -> 0
A10: AS201654 | B10: =VLOOKUP(A10,[15]LISTADHERENT!$A$5:$J$50,3,0) -> DJOMOU TCHAPDA | C10: =#REF! -> #REF! | D10: =#REF! -> #REF! | F10: =C10+D10-E10+K10 -> #REF! | G10: =$S$40/$H$40*H10 -> #REF! | H10: =F10+D10+K10 -> #REF! | I10: =VLOOKUP($A10,[16]HISTOJANV22!$A$6:$AQ$37,22,0) -> 0 | J10: =VLOOKUP($A10,[16]HISTOJANV22!$A$6:$AU$39,45,0) -> 7000 | K10: =IF(J10=0,0,J10-(L10+M10+N10)) -> 3000 | L10: =IF(J10=0,0,500) -> 500 | M10: =IF(J10=0,0,1000) -> 1000 | N10: =IF(J10=0,0,2500) -> 2500 | O10: =VLOOKUP($A10,[16]HISTOJANV22!$A$6:$AU$39,7,0) -> 0 | P10: =VLOOKUP($A10,[16]HISTOJANV22!$A$6:$AU$39,23,0) -> 0 | Q10: =VLOOKUP($A10,[16]HISTOJANV22!$A$6:$AU$39,46,0) -> 0 | R10: =VLOOKUP($A10,[16]HISTODEC21!$A$6:$AU$39,26,0) -> #REF! | S10: =R10*1/1200*12 -> #REF! | T10: =VLOOKUP($A10,[16]HISTOJANV22!$A$6:$AU$39,28,0) -> 0 | U10: =VLOOKUP($A10,[16]HISTOJANV22!$A$6:$AU$39,19,0) -> 0 | V10: =VLOOKUP($A10,[16]HISTOJANV22!$A$6:$AU$39,20,0) -> 0 | W10: =VLOOKUP($A10,[16]HISTOJANV22!$A$6:$AU$39,27,0) -> 0 | X10: =VLOOKUP($A10,[16]HISTOJANV22!$A$6:$AU$39,33,0) -> 0 | AA10: =VLOOKUP($A10,[16]HISTOJANV22!$A$6:$AU$39,43,0) -> 0 | AB10: =VLOOKUP($A10,[16]HISTOJANV22!$A$6:$AU$39,44,0) -> 0 | AC10: =VLOOKUP($A10,[16]HISTOJANV22!$A$6:$AU$39,47,0) -> 0 | AD10: =VLOOKUP(A10,[16]HISTOJANV22!$A$6:$BB$36,54,0) -> 0
A11: AS201605 | B11: =VLOOKUP(A11,[15]LISTADHERENT!$A$5:$J$50,3,0) -> DJOUKWE NANGUEN GUY BLAISE | C11: =#REF! -> #REF! | D11: =#REF! -> #REF! | F11: =C11+D11-E11+K11 -> #REF! | G11: =$S$40/$H$40*H11 -> #REF! | H11: =F11+D11+K11 -> #REF! | I11: =VLOOKUP($A11,[16]HISTOJANV22!$A$6:$AQ$37,22,0) -> 0 | J11: =VLOOKUP($A11,[16]HISTOJANV22!$A$6:$AU$39,45,0) -> 12000 | K11: =IF(J11=0,0,J11-(L11+M11+N11)) -> 8000 | L11: =IF(J11=0,0,500) -> 500 | M11: =IF(J11=0,0,1000) -> 1000 | N11: =IF(J11=0,0,2500) -> 2500 | O11: =VLOOKUP($A11,[16]HISTOJANV22!$A$6:$AU$39,7,0) -> 0 | P11: =VLOOKUP($A11,[16]HISTOJANV22!$A$6:$AU$39,23,0) -> 0 | Q11: =VLOOKUP($A11,[16]HISTOJANV22!$A$6:$AU$39,46,0) -> 0 | R11: =VLOOKUP($A11,[16]HISTODEC21!$A$6:$AU$39,26,0) -> 1000000 | S11: =R11*1/1200*12 -> 10000 | T11: =VLOOKUP($A11,[16]HISTOJANV22!$A$6:$AU$39,28,0) -> OKK | U11: =VLOOKUP($A11,[16]HISTOJANV22!$A$6:$AU$39,19,0) -> 0 | V11: =VLOOKUP($A11,[16]HISTOJANV22!$A$6:$AU$39,20,0) -> 0 | W11: =VLOOKUP($A11,[16]HISTOJANV22!$A$6:$AU$39,27,0) -> BANQUE | X11: =VLOOKUP($A11,[16]HISTOJANV22!$A$6:$AU$39,33,0) -> 0 | Y11: 29000 | AA11: =VLOOKUP($A11,[16]HISTOJANV22!$A$6:$AU$39,43,0) -> 0 | AB11: =VLOOKUP($A11,[16]HISTOJANV22!$A$6:$AU$39,44,0) -> 0 | AC11: =VLOOKUP($A11,[16]HISTOJANV22!$A$6:$AU$39,47,0) -> 0 | AD11: =VLOOKUP(A11,[16]HISTOJANV22!$A$6:$BB$36,54,0) -> 0
A12: AS201608 | B12: =VLOOKUP(A12,[15]LISTADHERENT!$A$5:$J$50,3,0) -> DJUOMBESSY ANTOINE | C12: =#REF! -> #REF! | D12: =#REF! -> #REF! | F12: =C12+D12-E12+K12 -> #REF! | G12: =$S$40/$H$40*H12 -> #REF! | H12: =F12+D12+K12 -> #REF! | I12: =VLOOKUP($A12,[16]HISTOJANV22!$A$6:$AQ$37,22,0) -> 0 | J12: =VLOOKUP($A12,[16]HISTOJANV22!$A$6:$AU$39,45,0) -> 7000 | K12: =IF(J12=0,0,J12-(L12+M12+N12)) -> 3000 | L12: =IF(J12=0,0,500) -> 500 | M12: =IF(J12=0,0,1000) -> 1000 | N12: =IF(J12=0,0,2500) -> 2500 | O12: =VLOOKUP($A12,[16]HISTOJANV22!$A$6:$AU$39,7,0) -> 0 | P12: =VLOOKUP($A12,[16]HISTOJANV22!$A$6:$AU$39,23,0) -> 0 | Q12: =VLOOKUP($A12,[16]HISTOJANV22!$A$6:$AU$39,46,0) -> 0 | R12: =VLOOKUP($A12,[16]HISTODEC21!$A$6:$AU$39,26,0) -> 1029000 | S12: =R12*12/1200*12 -> 123480 | T12: =VLOOKUP($A12,[16]HISTOJANV22!$A$6:$AU$39,28,0) -> 0 | U12: =VLOOKUP($A12,[16]HISTOJANV22!$A$6:$AU$39,19,0) -> 1000000 | V12: =VLOOKUP($A12,[16]HISTOJANV22!$A$6:$AU$39,20,0) -> BANQUE | W12: =VLOOKUP($A12,[16]HISTOJANV22!$A$6:$AU$39,27,0) -> 0 | X12: =VLOOKUP($A12,[16]HISTOJANV22!$A$6:$AU$39,33,0) -> 0 | AA12: =VLOOKUP($A12,[16]HISTOJANV22!$A$6:$AU$39,43,0) -> 0 | AB12: =VLOOKUP($A12,[16]HISTOJANV22!$A$6:$AU$39,44,0) -> 0 | AC12: =VLOOKUP($A12,[16]HISTOJANV22!$A$6:$AU$39,47,0) -> 0 | AD12: =VLOOKUP(A12,[16]HISTOJANV22!$A$6:$BB$36,54,0) -> 61000
A13: AS201651 | B13: =VLOOKUP(A13,[15]LISTADHERENT!$A$5:$J$50,3,0) -> DOMOU FABIEN | C13: =#REF! -> #REF! | D13: =#REF! -> #REF! | F13: =C13+D13-E13+K13 -> #REF! | G13: =$S$40/$H$40*H13 -> #REF! | H13: =F13+D13+K13 -> #REF! | I13: =VLOOKUP($A13,[16]HISTOJANV22!$A$6:$AQ$37,22,0) -> 0 | J13: =VLOOKUP($A13,[16]HISTOJANV22!$A$6:$AU$39,45,0) -> 12000 | K13: =IF(J13=0,0,J13-(L13+M13+N13)) -> 8000 | L13: =IF(J13=0,0,500) -> 500 | M13: =IF(J13=0,0,1000) -> 1000 | N13: =IF(J13=0,0,2500) -> 2500 | O13: =VLOOKUP($A13,[16]HISTOJANV22!$A$6:$AU$39,7,0) -> 0 | P13: =VLOOKUP($A13,[16]HISTOJANV22!$A$6:$AU$39,23,0) -> 0 | Q13: =VLOOKUP($A13,[16]HISTOJANV22!$A$6:$AU$39,46,0) -> 0 | R13: =VLOOKUP($A13,[16]HISTODEC21!$A$6:$AU$39,26,0) -> 1000000 | S13: =R13*12/1200*12 -> 120000 | T13: =VLOOKUP($A13,[16]HISTOJANV22!$A$6:$AU$39,28,0) -> OKK | U13: =VLOOKUP($A13,[16]HISTOJANV22!$A$6:$AU$39,19,0) -> 0 | V13: =VLOOKUP($A13,[16]HISTOJANV22!$A$6:$AU$39,20,0) -> 0 | W13: =VLOOKUP($A13,[16]HISTOJANV22!$A$6:$AU$39,27,0) -> BANQUE | X13: =VLOOKUP($A13,[16]HISTOJANV22!$A$6:$AU$39,33,0) -> 0 | AA13: =VLOOKUP($A13,[16]HISTOJANV22!$A$6:$AU$39,43,0) -> 0 | AB13: =VLOOKUP($A13,[16]HISTOJANV22!$A$6:$AU$39,44,0) -> 0 | AC13: =VLOOKUP($A13,[16]HISTOJANV22!$A$6:$AU$39,47,0) -> 0 | AD13: =VLOOKUP(A13,[16]HISTOJANV22!$A$6:$BB$36,54,0) -> 57000
A14: AS201609 | B14: =VLOOKUP(A14,[15]LISTADHERENT!$A$5:$J$50,3,0) -> DONHOU DAVID | C14: =#REF! -> #REF! | D14: =#REF! -> #REF! | F14: =C14+D14-E14+K14 -> #REF! | G14: =$S$40/$H$40*H14 -> #REF! | H14: =F14+D14+K14 -> #REF! | I14: =VLOOKUP($A14,[16]HISTOJANV22!$A$6:$AQ$37,22,0) -> 0 | J14: =VLOOKUP($A14,[16]HISTOJANV22!$A$6:$AU$39,45,0) -> 7000 | K14: =IF(J14=0,0,J14-(L14+M14+N14)) -> 3000 | L14: =IF(J14=0,0,500) -> 500 | M14: =IF(J14=0,0,1000) -> 1000 | N14: =IF(J14=0,0,2500) -> 2500 | O14: =VLOOKUP($A14,[16]HISTOJANV22!$A$6:$AU$39,7,0) -> 0 | P14: =VLOOKUP($A14,[16]HISTOJANV22!$A$6:$AU$39,23,0) -> 0 | Q14: =VLOOKUP($A14,[16]HISTOJANV22!$A$6:$AU$39,46,0) -> 0 | R14: =VLOOKUP($A14,[16]HISTODEC21!$A$6:$AU$39,26,0) -> #REF! | S14: =R14*0/1200*12 -> #REF! | T14: =VLOOKUP($A14,[16]HISTOJANV22!$A$6:$AU$39,28,0) -> 0 | U14: =VLOOKUP($A14,[16]HISTOJANV22!$A$6:$AU$39,19,0) -> 0 | V14: =VLOOKUP($A14,[16]HISTOJANV22!$A$6:$AU$39,20,0) -> 0 | W14: =VLOOKUP($A14,[16]HISTOJANV22!$A$6:$AU$39,27,0) -> 0 | X14: =VLOOKUP($A14,[16]HISTOJANV22!$A$6:$AU$39,33,0) -> 0 | Y14: 155000 | AA14: =VLOOKUP($A14,[16]HISTOJANV22!$A$6:$AU$39,43,0) -> 0 | AB14: =VLOOKUP($A14,[16]HISTOJANV22!$A$6:$AU$39,44,0) -> 0 | AC14: =VLOOKUP($A14,[16]HISTOJANV22!$A$6:$AU$39,47,0) -> 0 | AD14: =VLOOKUP(A14,[16]HISTOJANV22!$A$6:$BB$36,54,0) -> 70000
A15: AS201611 | B15: =VLOOKUP(A15,[15]LISTADHERENT!$A$5:$J$50,3,0) -> HENGUE PAUL OMER | C15: =#REF! -> #REF! | D15: =#REF! -> #REF! | F15: =C15+D15-E15+K15 -> #REF! | G15: =$S$40/$H$40*H15 -> #REF! | H15: =F15+D15+K15 -> #REF! | I15: =VLOOKUP($A15,[16]HISTOJANV22!$A$6:$AQ$37,22,0) -> 0 | J15: =VLOOKUP($A15,[16]HISTOJANV22!$A$6:$AU$39,45,0) -> 7000 | K15: =IF(J15=0,0,J15-(L15+M15+N15)) -> 3000 | L15: =IF(J15=0,0,500) -> 500 | M15: =IF(J15=0,0,1000) -> 1000 | N15: =IF(J15=0,0,2500) -> 2500 | O15: =VLOOKUP($A15,[16]HISTOJANV22!$A$6:$AU$39,7,0) -> 0 | P15: =VLOOKUP($A15,[16]HISTOJANV22!$A$6:$AU$39,23,0) -> 0 | Q15: =VLOOKUP($A15,[16]HISTOJANV22!$A$6:$AU$39,46,0) -> 0 | R15: =VLOOKUP($A15,[16]HISTODEC21!$A$6:$AU$39,26,0) -> #REF! | S15: =R15*12/1200*12 -> #REF! | T15: =VLOOKUP($A15,[16]HISTOJANV22!$A$6:$AU$39,28,0) -> 0 | U15: =VLOOKUP($A15,[16]HISTOJANV22!$A$6:$AU$39,19,0) -> 0 | V15: =VLOOKUP($A15,[16]HISTOJANV22!$A$6:$AU$39,20,0) -> 0 | W15: =VLOOKUP($A15,[16]HISTOJANV22!$A$6:$AU$39,27,0) -> 0 | X15: =VLOOKUP($A15,[16]HISTOJANV22!$A$6:$AU$39,33,0) -> 0 | AA15: =VLOOKUP($A15,[16]HISTOJANV22!$A$6:$AU$39,43,0) -> 0 | AB15: =VLOOKUP($A15,[16]HISTOJANV22!$A$6:$AU$39,44,0) -> 0 | AC15: =VLOOKUP($A15,[16]HISTOJANV22!$A$6:$AU$39,47,0) -> 0 | AD15: =VLOOKUP(A15,[16]HISTOJANV22!$A$6:$BB$36,54,0) -> 0
A16: AS201613 | B16: =VLOOKUP(A16,[15]LISTADHERENT!$A$5:$J$50,3,0) -> HOTCHO BENJAMIN | C16: =#REF! -> #REF! | D16: =#REF! -> #REF! | F16: =C16+D16-E16+K16 -> #REF! | G16: =$S$40/$H$40*H16 -> #REF! | H16: =F16+D16+K16 -> #REF! | I16: =VLOOKUP($A16,[16]HISTOJANV22!$A$6:$AQ$37,22,0) -> 0 | J16: =VLOOKUP($A16,[16]HISTOJANV22!$A$6:$AU$39,45,0) -> 52000 | K16: =IF(J16=0,0,J16-(L16+M16+N16)) -> 48000 | L16: =IF(J16=0,0,500) -> 500 | M16: =IF(J16=0,0,1000) -> 1000 | N16: =IF(J16=0,0,2500) -> 2500 | O16: =VLOOKUP($A16,[16]HISTOJANV22!$A$6:$AU$39,7,0) -> 0 | P16: =VLOOKUP($A16,[16]HISTOJANV22!$A$6:$AU$39,23,0) -> 0 | Q16: =VLOOKUP($A16,[16]HISTOJANV22!$A$6:$AU$39,46,0) -> 0 | R16: =VLOOKUP($A16,[16]HISTODEC21!$A$6:$AU$39,26,0) -> #REF! | S16: =R16*12/1200*12 -> #REF! | T16: =VLOOKUP($A16,[16]HISTOJANV22!$A$6:$AU$39,28,0) -> 0 | U16: =VLOOKUP($A16,[16]HISTOJANV22!$A$6:$AU$39,19,0) -> 0 | V16: =VLOOKUP($A16,[16]HISTOJANV22!$A$6:$AU$39,20,0) -> 0 | W16: =VLOOKUP($A16,[16]HISTOJANV22!$A$6:$AU$39,27,0) -> 0 | X16: =VLOOKUP($A16,[16]HISTOJANV22!$A$6:$AU$39,33,0) -> 0 | AA16: =VLOOKUP($A16,[16]HISTOJANV22!$A$6:$AU$39,43,0) -> 0 | AB16: =VLOOKUP($A16,[16]HISTOJANV22!$A$6:$AU$39,44,0) -> 0 | AC16: =VLOOKUP($A16,[16]HISTOJANV22!$A$6:$AU$39,47,0) -> 0 | AD16: =VLOOKUP(A16,[16]HISTOJANV22!$A$6:$BB$36,54,0) -> 70000
A17: AS201617 | B17: =VLOOKUP(A17,[15]LISTADHERENT!$A$5:$J$50,3,0) -> KOUAMOU MOISE | C17: =#REF! -> #REF! | D17: =#REF! -> #REF! | F17: =C17+D17-E17+K17 -> #REF! | G17: =$S$40/$H$40*H17 -> #REF! | H17: =F17+D17+K17 -> #REF! | I17: =VLOOKUP($A17,[16]HISTOJANV22!$A$6:$AQ$37,22,0) -> 0 | J17: =VLOOKUP($A17,[16]HISTOJANV22!$A$6:$AU$39,45,0) -> 7000 | K17: =IF(J17=0,0,J17-(L17+M17+N17)) -> 3000 | L17: =IF(J17=0,0,500) -> 500 | M17: =IF(J17=0,0,1000) -> 1000 | N17: =IF(J17=0,0,2500) -> 2500 | O17: =VLOOKUP($A17,[16]HISTOJANV22!$A$6:$AU$39,7,0) -> 0 | P17: =VLOOKUP($A17,[16]HISTOJANV22!$A$6:$AU$39,23,0) -> 0 | Q17: =VLOOKUP($A17,[16]HISTOJANV22!$A$6:$AU$39,46,0) -> 0 | R17: =VLOOKUP($A17,[16]HISTODEC21!$A$6:$AU$39,26,0) -> #REF! | S17: =R17*12/1200*12 -> #REF! | T17: =VLOOKUP($A17,[16]HISTOJANV22!$A$6:$AU$39,28,0) -> 0 | U17: =VLOOKUP($A17,[16]HISTOJANV22!$A$6:$AU$39,19,0) -> 0 | V17: =VLOOKUP($A17,[16]HISTOJANV22!$A$6:$AU$39,20,0) -> 0 | W17: =VLOOKUP($A17,[16]HISTOJANV22!$A$6:$AU$39,27,0) -> 0 | X17: =VLOOKUP($A17,[16]HISTOJANV22!$A$6:$AU$39,33,0) -> 0 | AA17: =VLOOKUP($A17,[16]HISTOJANV22!$A$6:$AU$39,43,0) -> 0 | AB17: =VLOOKUP($A17,[16]HISTOJANV22!$A$6:$AU$39,44,0) -> 0 | AC17: =VLOOKUP($A17,[16]HISTOJANV22!$A$6:$AU$39,47,0) -> 0 | AD17: =VLOOKUP(A17,[16]HISTOJANV22!$A$6:$BB$36,54,0) -> 0
A18: AS201619 | B18: =VLOOKUP(A18,[15]LISTADHERENT!$A$5:$J$50,3,0) -> KOUATCHO MESSACK | C18: =#REF! -> #REF! | D18: =#REF! -> #REF! | F18: =C18+D18-E18+K18 -> #REF! | G18: =$S$40/$H$40*H18 -> #REF! | H18: =F18+D18+K18 -> #REF! | I18: =VLOOKUP($A18,[16]HISTOJANV22!$A$6:$AQ$37,22,0) -> 0 | J18: =VLOOKUP($A18,[16]HISTOJANV22!$A$6:$AU$39,45,0) -> 7000 | K18: =IF(J18=0,0,J18-(L18+M18+N18)) -> 3000 | L18: =IF(J18=0,0,500) -> 500 | M18: =IF(J18=0,0,1000) -> 1000 | N18: =IF(J18=0,0,2500) -> 2500 | O18: =VLOOKUP($A18,[16]HISTOJANV22!$A$6:$AU$39,7,0) -> 0 | P18: =VLOOKUP($A18,[16]HISTOJANV22!$A$6:$AU$39,23,0) -> 0 | Q18: =VLOOKUP($A18,[16]HISTOJANV22!$A$6:$AU$39,46,0) -> 0 | R18: =VLOOKUP($A18,[16]HISTODEC21!$A$6:$AU$39,26,0) -> 1000000 | S18: =R18*12/1200*12 -> 120000 | T18: =VLOOKUP($A18,[16]HISTOJANV22!$A$6:$AU$39,28,0) -> OKK | U18: =VLOOKUP($A18,[16]HISTOJANV22!$A$6:$AU$39,19,0) -> 0 | V18: =VLOOKUP($A18,[16]HISTOJANV22!$A$6:$AU$39,20,0) -> 0 | W18: =VLOOKUP($A18,[16]HISTOJANV22!$A$6:$AU$39,27,0) -> BANQUE | X18: =VLOOKUP($A18,[16]HISTOJANV22!$A$6:$AU$39,33,0) -> 0 | AA18: =VLOOKUP($A18,[16]HISTOJANV22!$A$6:$AU$39,43,0) -> 0 | AB18: =VLOOKUP($A18,[16]HISTOJANV22!$A$6:$AU$39,44,0) -> 0 | AC18: =VLOOKUP($A18,[16]HISTOJANV22!$A$6:$AU$39,47,0) -> 0 | AD18: =VLOOKUP(A18,[16]HISTOJANV22!$A$6:$BB$36,54,0) -> 0
A19: AS201620 | B19: =VLOOKUP(A19,[15]LISTADHERENT!$A$5:$J$50,3,0) -> LOWE JEAN | C19: =#REF! -> #REF! | D19: =#REF! -> #REF! | F19: =C19+D19-E19+K19 -> #REF! | G19: =$S$40/$H$40*H19 -> #REF! | H19: =F19+D19+K19 -> #REF! | I19: =VLOOKUP($A19,[16]HISTOJANV22!$A$6:$AQ$37,22,0) -> 0 | J19: =VLOOKUP($A19,[16]HISTOJANV22!$A$6:$AU$39,45,0) -> 7000 | K19: =IF(J19=0,0,J19-(L19+M19+N19)) -> 3000 | L19: =IF(J19=0,0,500) -> 500 | M19: =IF(J19=0,0,1000) -> 1000 | N19: =IF(J19=0,0,2500) -> 2500 | O19: =VLOOKUP($A19,[16]HISTOJANV22!$A$6:$AU$39,7,0) -> 0 | P19: =VLOOKUP($A19,[16]HISTOJANV22!$A$6:$AU$39,23,0) -> 0 | Q19: =VLOOKUP($A19,[16]HISTOJANV22!$A$6:$AU$39,46,0) -> 0 | R19: =VLOOKUP($A19,[16]HISTODEC21!$A$6:$AU$39,26,0) -> 500000 | S19: =R19*12/1200*12 -> 60000 | T19: =VLOOKUP($A19,[16]HISTOJANV22!$A$6:$AU$39,28,0) -> OKK | U19: =VLOOKUP($A19,[16]HISTOJANV22!$A$6:$AU$39,19,0) -> 0 | V19: =VLOOKUP($A19,[16]HISTOJANV22!$A$6:$AU$39,20,0) -> 0 | W19: =VLOOKUP($A19,[16]HISTOJANV22!$A$6:$AU$39,27,0) -> BANQUE | X19: =VLOOKUP($A19,[16]HISTOJANV22!$A$6:$AU$39,33,0) -> 0 | AA19: =VLOOKUP($A19,[16]HISTOJANV22!$A$6:$AU$39,43,0) -> 0 | AB19: =VLOOKUP($A19,[16]HISTOJANV22!$A$6:$AU$39,44,0) -> 0 | AC19: =VLOOKUP($A19,[16]HISTOJANV22!$A$6:$AU$39,47,0) -> 0 | AD19: =VLOOKUP(A19,[16]HISTOJANV22!$A$6:$BB$36,54,0) -> 0
A20: AS201649 | B20: =VLOOKUP(A20,[15]LISTADHERENT!$A$5:$J$50,3,0) -> MBOGNING TUGMA GUY | C20: =#REF! -> #REF! | D20: =#REF! -> #REF! | F20: =C20+D20-E20+K20 -> #REF! | G20: =$S$40/$H$40*H20 -> #REF! | H20: =F20+D20+K20 -> #REF! | I20: =VLOOKUP($A20,[16]HISTOJANV22!$A$6:$AQ$37,22,0) -> 0 | J20: =VLOOKUP($A20,[16]HISTOJANV22!$A$6:$AU$39,45,0) -> 7000 | K20: =IF(J20=0,0,J20-(L20+M20+N20)) -> 3000 | L20: =IF(J20=0,0,500) -> 500 | M20: =IF(J20=0,0,1000) -> 1000 | N20: =IF(J20=0,0,2500) -> 2500 | O20: =VLOOKUP($A20,[16]HISTOJANV22!$A$6:$AU$39,7,0) -> 0 | P20: =VLOOKUP($A20,[16]HISTOJANV22!$A$6:$AU$39,23,0) -> 0 | Q20: =VLOOKUP($A20,[16]HISTOJANV22!$A$6:$AU$39,46,0) -> 0 | R20: =VLOOKUP($A20,[16]HISTODEC21!$A$6:$AU$39,26,0) -> 1050000 | S20: =R20*12/1200*12 -> 126000 | T20: =VLOOKUP($A20,[16]HISTOJANV22!$A$6:$AU$39,28,0) -> 0 | U20: =VLOOKUP($A20,[16]HISTOJANV22!$A$6:$AU$39,19,0) -> 1050000 | V20: =VLOOKUP($A20,[16]HISTOJANV22!$A$6:$AU$39,20,0) -> BANQUE | W20: =VLOOKUP($A20,[16]HISTOJANV22!$A$6:$AU$39,27,0) -> BANQUE | X20: =VLOOKUP($A20,[16]HISTOJANV22!$A$6:$AU$39,33,0) -> 0 | AA20: =VLOOKUP($A20,[16]HISTOJANV22!$A$6:$AU$39,43,0) -> 0 | AB20: =VLOOKUP($A20,[16]HISTOJANV22!$A$6:$AU$39,44,0) -> 0 | AC20: =VLOOKUP($A20,[16]HISTOJANV22!$A$6:$AU$39,47,0) -> 0 | AD20: =VLOOKUP(A20,[16]HISTOJANV22!$A$6:$BB$36,54,0) -> 0
A21: AS201639 | B21: =VLOOKUP(A21,[15]LISTADHERENT!$A$5:$J$50,3,0) -> NANGUEN MARTIN | C21: =#REF! -> #REF! | D21: =#REF! -> #REF! | F21: =C21+D21-E21+K21 -> #REF! | G21: =$S$40/$H$40*H21 -> #REF! | H21: =F21+D21+K21 -> #REF! | I21: =VLOOKUP($A21,[16]HISTOJANV22!$A$6:$AQ$37,22,0) -> 0 | J21: =VLOOKUP($A21,[16]HISTOJANV22!$A$6:$AU$39,45,0) -> 7000 | K21: =IF(J21=0,0,J21-(L21+M21+N21)) -> 3000 | L21: =IF(J21=0,0,500) -> 500 | M21: =IF(J21=0,0,1000) -> 1000 | N21: =IF(J21=0,0,2500) -> 2500 | O21: =VLOOKUP($A21,[16]HISTOJANV22!$A$6:$AU$39,7,0) -> 0 | P21: =VLOOKUP($A21,[16]HISTOJANV22!$A$6:$AU$39,23,0) -> 0 | Q21: =VLOOKUP($A21,[16]HISTOJANV22!$A$6:$AU$39,46,0) -> 0 | R21: =VLOOKUP($A21,[16]HISTODEC21!$A$6:$AU$39,26,0) -> #REF! | S21: =R21*12/1200*12 -> #REF! | T21: =VLOOKUP($A21,[16]HISTOJANV22!$A$6:$AU$39,28,0) -> 0 | U21: =VLOOKUP($A21,[16]HISTOJANV22!$A$6:$AU$39,19,0) -> 0 | V21: =VLOOKUP($A21,[16]HISTOJANV22!$A$6:$AU$39,20,0) -> 0 | W21: =VLOOKUP($A21,[16]HISTOJANV22!$A$6:$AU$39,27,0) -> 0 | X21: =VLOOKUP($A21,[16]HISTOJANV22!$A$6:$AU$39,33,0) -> 0 | AA21: =VLOOKUP($A21,[16]HISTOJANV22!$A$6:$AU$39,43,0) -> 0 | AB21: =VLOOKUP($A21,[16]HISTOJANV22!$A$6:$AU$39,44,0) -> 0 | AC21: =VLOOKUP($A21,[16]HISTOJANV22!$A$6:$AU$39,47,0) -> 0 | AD21: =VLOOKUP(A21,[16]HISTOJANV22!$A$6:$BB$36,54,0) -> 0
A22: AS201621 | B22: =VLOOKUP(A22,[15]LISTADHERENT!$A$5:$J$50,3,0) -> NANKAM APPOLINAIRE | C22: =#REF! -> #REF! | D22: =#REF! -> #REF! | F22: =C22+D22-E22+K22 -> #REF! | G22: =$S$40/$H$40*H22 -> #REF! | H22: =F22+D22+K22 -> #REF! | I22: =VLOOKUP($A22,[16]HISTOJANV22!$A$6:$AQ$37,22,0) -> 0 | J22: =VLOOKUP($A22,[16]HISTOJANV22!$A$6:$AU$39,45,0) -> 7000 | K22: =IF(J22=0,0,J22-(L22+M22+N22)) -> 3000 | L22: =IF(J22=0,0,500) -> 500 | M22: =IF(J22=0,0,1000) -> 1000 | N22: =IF(J22=0,0,2500) -> 2500 | O22: =VLOOKUP($A22,[16]HISTOJANV22!$A$6:$AU$39,7,0) -> 0 | P22: =VLOOKUP($A22,[16]HISTOJANV22!$A$6:$AU$39,23,0) -> 0 | Q22: =VLOOKUP($A22,[16]HISTOJANV22!$A$6:$AU$39,46,0) -> 0 | R22: =VLOOKUP($A22,[16]HISTODEC21!$A$6:$AU$39,26,0) -> 924000 | S22: =R22*12/1200*12 -> 110880 | T22: =VLOOKUP($A22,[16]HISTOJANV22!$A$6:$AU$39,28,0) -> 0 | U22: =VLOOKUP($A22,[16]HISTOJANV22!$A$6:$AU$39,19,0) -> 924000 | V22: =VLOOKUP($A22,[16]HISTOJANV22!$A$6:$AU$39,20,0) -> BANQUE | W22: =VLOOKUP($A22,[16]HISTOJANV22!$A$6:$AU$39,27,0) -> 0 | X22: =VLOOKUP($A22,[16]HISTOJANV22!$A$6:$AU$39,33,0) -> 0 | Y22: 50000 | AA22: =VLOOKUP($A22,[16]HISTOJANV22!$A$6:$AU$39,43,0) -> 0 | AB22: =VLOOKUP($A22,[16]HISTOJANV22!$A$6:$AU$39,44,0) -> 0 | AC22: =VLOOKUP($A22,[16]HISTOJANV22!$A$6:$AU$39,47,0) -> 0 | AD22: =VLOOKUP(A22,[16]HISTOJANV22!$A$6:$BB$36,54,0) -> 0
A23: AS201622 | B23: =VLOOKUP(A23,[15]LISTADHERENT!$A$5:$J$50,3,0) -> NDJOMO ETIENNE | C23: =#REF! -> #REF! | D23: =#REF! -> #REF! | F23: =C23+D23-E23+K23 -> #REF! | G23: =$S$40/$H$40*H23 -> #REF! | H23: =F23+D23+K23 -> #REF! | I23: =VLOOKUP($A23,[16]HISTOJANV22!$A$6:$AQ$37,22,0) -> 0 | J23: =VLOOKUP($A23,[16]HISTOJANV22!$A$6:$AU$39,45,0) -> 17000 | K23: =IF(J23=0,0,J23-(L23+M23+N23)) -> 13000 | L23: =IF(J23=0,0,500) -> 500 | M23: =IF(J23=0,0,1000) -> 1000 | N23: =IF(J23=0,0,2500) -> 2500 | O23: =VLOOKUP($A23,[16]HISTOJANV22!$A$6:$AU$39,7,0) -> 0 | P23: =VLOOKUP($A23,[16]HISTOJANV22!$A$6:$AU$39,23,0) -> 0 | Q23: =VLOOKUP($A23,[16]HISTOJANV22!$A$6:$AU$39,46,0) -> 0 | R23: =VLOOKUP($A23,[16]HISTODEC21!$A$6:$AU$39,26,0) -> 500000 | S23: =R23*12/1200*12 -> 60000 | T23: =VLOOKUP($A23,[16]HISTOJANV22!$A$6:$AU$39,28,0) -> OKK | U23: =VLOOKUP($A23,[16]HISTOJANV22!$A$6:$AU$39,19,0) -> 0 | V23: =VLOOKUP($A23,[16]HISTOJANV22!$A$6:$AU$39,20,0) -> 0 | W23: =VLOOKUP($A23,[16]HISTOJANV22!$A$6:$AU$39,27,0) -> BANQUE | X23: =VLOOKUP($A23,[16]HISTOJANV22!$A$6:$AU$39,33,0) -> 0 | AA23: =VLOOKUP($A23,[16]HISTOJANV22!$A$6:$AU$39,43,0) -> 0 | AB23: =VLOOKUP($A23,[16]HISTOJANV22!$A$6:$AU$39,44,0) -> 0 | AC23: =VLOOKUP($A23,[16]HISTOJANV22!$A$6:$AU$39,47,0) -> 0 | AD23: =VLOOKUP(A23,[16]HISTOJANV22!$A$6:$BB$36,54,0) -> 0
A24: AS201624 | B24: =VLOOKUP(A24,[15]LISTADHERENT!$A$5:$J$50,3,0) -> NGONDIEP CLAUDE | C24: =#REF! -> #REF! | D24: =#REF! -> #REF! | F24: =C24+D24-E24+K24 -> #REF! | G24: =$S$40/$H$40*H24 -> #REF! | H24: =F24+D24+K24 -> #REF! | I24: =VLOOKUP($A24,[16]HISTOJANV22!$A$6:$AQ$37,22,0) -> 0 | J24: =VLOOKUP($A24,[16]HISTOJANV22!$A$6:$AU$39,45,0) -> 12000 | K24: =IF(J24=0,0,J24-(L24+M24+N24)) -> 8000 | L24: =IF(J24=0,0,500) -> 500 | M24: =IF(J24=0,0,1000) -> 1000 | N24: =IF(J24=0,0,2500) -> 2500 | O24: =VLOOKUP($A24,[16]HISTOJANV22!$A$6:$AU$39,7,0) -> 0 | P24: =VLOOKUP($A24,[16]HISTOJANV22!$A$6:$AU$39,23,0) -> 0 | Q24: =VLOOKUP($A24,[16]HISTOJANV22!$A$6:$AU$39,46,0) -> 0 | R24: =VLOOKUP($A24,[16]HISTODEC21!$A$6:$AU$39,26,0) -> 1000000 | S24: =R24*12/1200*12 -> 120000 | T24: =VLOOKUP($A24,[16]HISTOJANV22!$A$6:$AU$39,28,0) -> OKK | U24: =VLOOKUP($A24,[16]HISTOJANV22!$A$6:$AU$39,19,0) -> 0 | V24: =VLOOKUP($A24,[16]HISTOJANV22!$A$6:$AU$39,20,0) -> 0 | W24: =VLOOKUP($A24,[16]HISTOJANV22!$A$6:$AU$39,27,0) -> BANQUE | X24: =VLOOKUP($A24,[16]HISTOJANV22!$A$6:$AU$39,33,0) -> 0 | AA24: =VLOOKUP($A24,[16]HISTOJANV22!$A$6:$AU$39,43,0) -> 0 | AB24: =VLOOKUP($A24,[16]HISTOJANV22!$A$6:$AU$39,44,0) -> 0 | AC24: =VLOOKUP($A24,[16]HISTOJANV22!$A$6:$AU$39,47,0) -> 0 | AD24: =VLOOKUP(A24,[16]HISTOJANV22!$A$6:$BB$36,54,0) -> 70000
A25: AS201626 | B25: =VLOOKUP(A25,[15]LISTADHERENT!$A$5:$J$50,3,0) -> NGUIEMEGNI MATHIEU BLAISE | C25: =#REF! -> #REF! | D25: =#REF! -> #REF! | F25: =C25+D25-E25+K25 -> #REF! | G25: =$S$40/$H$40*H25 -> #REF! | H25: =F25+D25+K25 -> #REF! | I25: =VLOOKUP($A25,[16]HISTOJANV22!$A$6:$AQ$37,22,0) -> 0 | J25: =VLOOKUP($A25,[16]HISTOJANV22!$A$6:$AU$39,45,0) -> 7000 | K25: =IF(J25=0,0,J25-(L25+M25+N25)) -> 3000 | L25: =IF(J25=0,0,500) -> 500 | M25: =IF(J25=0,0,1000) -> 1000 | N25: =IF(J25=0,0,2500) -> 2500 | O25: =VLOOKUP($A25,[16]HISTOJANV22!$A$6:$AU$39,7,0) -> 0 | P25: =VLOOKUP($A25,[16]HISTOJANV22!$A$6:$AU$39,23,0) -> 0 | Q25: =VLOOKUP($A25,[16]HISTOJANV22!$A$6:$AU$39,46,0) -> 0 | R25: =VLOOKUP($A25,[16]HISTODEC21!$A$6:$AU$39,26,0) -> 1000000 | S25: =R25*12/1200*12 -> 120000 | T25: =VLOOKUP($A25,[16]HISTOJANV22!$A$6:$AU$39,28,0) -> OKK | U25: =VLOOKUP($A25,[16]HISTOJANV22!$A$6:$AU$39,19,0) -> 0 | V25: =VLOOKUP($A25,[16]HISTOJANV22!$A$6:$AU$39,20,0) -> 0 | W25: =VLOOKUP($A25,[16]HISTOJANV22!$A$6:$AU$39,27,0) -> BANQUE | X25: =VLOOKUP($A25,[16]HISTOJANV22!$A$6:$AU$39,33,0) -> 0 | AA25: =VLOOKUP($A25,[16]HISTOJANV22!$A$6:$AU$39,43,0) -> 0 | AB25: =VLOOKUP($A25,[16]HISTOJANV22!$A$6:$AU$39,44,0) -> 0 | AC25: =VLOOKUP($A25,[16]HISTOJANV22!$A$6:$AU$39,47,0) -> 0 | AD25: =VLOOKUP(A25,[16]HISTOJANV22!$A$6:$BB$36,54,0) -> 70000
A26: AS201628 | B26: =VLOOKUP(A26,[15]LISTADHERENT!$A$5:$J$50,3,0) -> NKAMGANG JUSTIN DEJOLIE | C26: =#REF! -> #REF! | D26: =#REF! -> #REF! | F26: =C26+D26-E26+K26 -> #REF! | G26: =$S$40/$H$40*H26 -> #REF! | H26: =F26+D26+K26 -> #REF! | I26: =VLOOKUP($A26,[16]HISTOJANV22!$A$6:$AQ$37,22,0) -> 0 | J26: =VLOOKUP($A26,[16]HISTOJANV22!$A$6:$AU$39,45,0) -> 7000 | K26: =IF(J26=0,0,J26-(L26+M26+N26)) -> 3000 | L26: =IF(J26=0,0,500) -> 500 | M26: =IF(J26=0,0,1000) -> 1000 | N26: =IF(J26=0,0,2500) -> 2500 | O26: =VLOOKUP($A26,[16]HISTOJANV22!$A$6:$AU$39,7,0) -> 0 | P26: =VLOOKUP($A26,[16]HISTOJANV22!$A$6:$AU$39,23,0) -> 0 | Q26: =VLOOKUP($A26,[16]HISTOJANV22!$A$6:$AU$39,46,0) -> 0 | R26: =VLOOKUP($A26,[16]HISTODEC21!$A$6:$AU$39,26,0) -> 1155000 | S26: =R26*0/1200*12 -> 0 | T26: =VLOOKUP($A26,[16]HISTOJANV22!$A$6:$AU$39,28,0) -> 0 | U26: =VLOOKUP($A26,[16]HISTOJANV22!$A$6:$AU$39,19,0) -> 0 | V26: =VLOOKUP($A26,[16]HISTOJANV22!$A$6:$AU$39,20,0) -> 0 | W26: =VLOOKUP($A26,[16]HISTOJANV22!$A$6:$AU$39,27,0) -> BANQUE | X26: =VLOOKUP($A26,[16]HISTOJANV22!$A$6:$AU$39,33,0) -> 0 | Y26: 155000 | AA26: =VLOOKUP($A26,[16]HISTOJANV22!$A$6:$AU$39,43,0) -> 0 | AB26: =VLOOKUP($A26,[16]HISTOJANV22!$A$6:$AU$39,44,0) -> 0 | AC26: =VLOOKUP($A26,[16]HISTOJANV22!$A$6:$AU$39,47,0) -> 0 | AD26: =VLOOKUP(A26,[16]HISTOJANV22!$A$6:$BB$36,54,0) -> 0
A27: AS201656 | B27: =VLOOKUP(A27,[15]LISTADHERENT!$A$5:$J$50,3,0) -> NOUBE ETIENNE | C27: =#REF! -> #REF! | D27: =#REF! -> #REF! | F27: =C27+D27-E27+K27 -> #REF! | G27: =$S$40/$H$40*H27 -> #REF! | H27: =F27+D27+K27 -> #REF! | I27: =VLOOKUP($A27,[16]HISTOJANV22!$A$6:$AQ$37,22,0) -> #N/A | J27: =VLOOKUP($A27,[16]HISTOJANV22!$A$6:$AU$39,45,0) -> #N/A | K27: =IF(J27=0,0,J27-(L27+M27+N27)) -> #N/A | L27: =IF(J27=0,0,500) -> #N/A | M27: =IF(J27=0,0,1000) -> #N/A | N27: =IF(J27=0,0,2500) -> #N/A | O27: =VLOOKUP($A27,[16]HISTOJANV22!$A$6:$AU$39,7,0) -> #N/A | P27: =VLOOKUP($A27,[16]HISTOJANV22!$A$6:$AU$39,23,0) -> #N/A | Q27: =VLOOKUP($A27,[16]HISTOJANV22!$A$6:$AU$39,46,0) -> #N/A | R27: =VLOOKUP($A27,[16]HISTODEC21!$A$6:$AU$39,26,0) -> #N/A | S27: =R27*12/1200*12 -> #N/A | T27: =VLOOKUP($A27,[16]HISTOJANV22!$A$6:$AU$39,28,0) -> #N/A | U27: =VLOOKUP($A27,[16]HISTOJANV22!$A$6:$AU$39,19,0) -> #N/A | V27: =VLOOKUP($A27,[16]HISTOJANV22!$A$6:$AU$39,20,0) -> #N/A | W27: =VLOOKUP($A27,[16]HISTOJANV22!$A$6:$AU$39,27,0) -> #N/A | X27: =VLOOKUP($A27,[16]HISTOJANV22!$A$6:$AU$39,33,0) -> #N/A | AA27: =VLOOKUP($A27,[16]HISTOJANV22!$A$6:$AU$39,43,0) -> #N/A | AB27: =VLOOKUP($A27,[16]HISTOJANV22!$A$6:$AU$39,44,0) -> #N/A | AC27: =VLOOKUP($A27,[16]HISTOJANV22!$A$6:$AU$39,47,0) -> #N/A | AD27: =VLOOKUP(A27,[16]HISTOJANV22!$A$6:$BB$36,54,0) -> #N/A
A28: AS201633 | B28: =VLOOKUP(A28,[15]LISTADHERENT!$A$5:$J$50,3,0) -> PATEGO NJOSSU GUSTAVE | C28: =#REF! -> #REF! | D28: =#REF! -> #REF! | F28: =C28+D28-E28+K28 -> #REF! | G28: =$S$40/$H$40*H28 -> #REF! | H28: =F28+D28+K28 -> #REF! | I28: =VLOOKUP($A28,[16]HISTOJANV22!$A$6:$AQ$37,22,0) -> 0 | J28: =VLOOKUP($A28,[16]HISTOJANV22!$A$6:$AU$39,45,0) -> 7000 | K28: =IF(J28=0,0,J28-(L28+M28+N28)) -> 3000 | L28: =IF(J28=0,0,500) -> 500 | M28: =IF(J28=0,0,1000) -> 1000 | N28: =IF(J28=0,0,2500) -> 2500 | O28: =VLOOKUP($A28,[16]HISTOJANV22!$A$6:$AU$39,7,0) -> 0 | P28: =VLOOKUP($A28,[16]HISTOJANV22!$A$6:$AU$39,23,0) -> 0 | Q28: =VLOOKUP($A28,[16]HISTOJANV22!$A$6:$AU$39,46,0) -> 0 | R28: =VLOOKUP($A28,[16]HISTODEC21!$A$6:$AU$39,26,0) -> #REF! | S28: =R28*12/1200*12 -> #REF! | T28: =VLOOKUP($A28,[16]HISTOJANV22!$A$6:$AU$39,28,0) -> 0 | U28: =VLOOKUP($A28,[16]HISTOJANV22!$A$6:$AU$39,19,0) -> 0 | V28: =VLOOKUP($A28,[16]HISTOJANV22!$A$6:$AU$39,20,0) -> 0 | W28: =VLOOKUP($A28,[16]HISTOJANV22!$A$6:$AU$39,27,0) -> 0 | X28: =VLOOKUP($A28,[16]HISTOJANV22!$A$6:$AU$39,33,0) -> 0 | AA28: =VLOOKUP($A28,[16]HISTOJANV22!$A$6:$AU$39,43,0) -> 0 | AB28: =VLOOKUP($A28,[16]HISTOJANV22!$A$6:$AU$39,44,0) -> 0 | AC28: =VLOOKUP($A28,[16]HISTOJANV22!$A$6:$AU$39,47,0) -> 0 | AD28: =VLOOKUP(A28,[16]HISTOJANV22!$A$6:$BB$36,54,0) -> 0
A29: AS201657 | B29: =VLOOKUP(A29,[15]LISTADHERENT!$A$5:$J$50,3,0) -> SEUMO POLYCARPE | C29: =#REF! -> #REF! | D29: =#REF! -> #REF! | F29: =C29+D29-E29+K29 -> #REF! | G29: =$S$40/$H$40*H29 -> #REF! | H29: =F29+D29+K29 -> #REF! | I29: =VLOOKUP($A29,[16]HISTOJANV22!$A$6:$AQ$37,22,0) -> #N/A | J29: =VLOOKUP($A29,[16]HISTOJANV22!$A$6:$AU$39,45,0) -> #N/A | K29: =IF(J29=0,0,J29-(L29+M29+N29)) -> #N/A | L29: =IF(J29=0,0,500) -> #N/A | M29: =IF(J29=0,0,1000) -> #N/A | N29: =IF(J29=0,0,2500) -> #N/A | O29: =VLOOKUP($A29,[16]HISTOJANV22!$A$6:$AU$39,7,0) -> #N/A | P29: =VLOOKUP($A29,[16]HISTOJANV22!$A$6:$AU$39,23,0) -> #N/A | Q29: =VLOOKUP($A29,[16]HISTOJANV22!$A$6:$AU$39,46,0) -> #N/A | R29: =VLOOKUP($A29,[16]HISTODEC21!$A$6:$AU$39,26,0) -> #N/A | S29: =R29*12/1200*12 -> #N/A | T29: =VLOOKUP($A29,[16]HISTOJANV22!$A$6:$AU$39,28,0) -> #N/A | U29: =VLOOKUP($A29,[16]HISTOJANV22!$A$6:$AU$39,19,0) -> #N/A | V29: =VLOOKUP($A29,[16]HISTOJANV22!$A$6:$AU$39,20,0) -> #N/A | W29: =VLOOKUP($A29,[16]HISTOJANV22!$A$6:$AU$39,27,0) -> #N/A | X29: =VLOOKUP($A29,[16]HISTOJANV22!$A$6:$AU$39,33,0) -> #N/A | AA29: =VLOOKUP($A29,[16]HISTOJANV22!$A$6:$AU$39,43,0) -> #N/A | AB29: =VLOOKUP($A29,[16]HISTOJANV22!$A$6:$AU$39,44,0) -> #N/A | AC29: =VLOOKUP($A29,[16]HISTOJANV22!$A$6:$AU$39,47,0) -> #N/A | AD29: =VLOOKUP(A29,[16]HISTOJANV22!$A$6:$BB$36,54,0) -> #N/A
A30: AS201653 | B30: =VLOOKUP(A30,[15]LISTADHERENT!$A$5:$J$50,3,0) -> SIME BRICE | C30: =#REF! -> #REF! | D30: =#REF! -> #REF! | F30: =C30+D30-E30+K30 -> #REF! | G30: =$S$40/$H$40*H30 -> #REF! | H30: =F30+D30+K30 -> #REF! | I30: =VLOOKUP($A30,[16]HISTOJANV22!$A$6:$AQ$37,22,0) -> 0 | J30: =VLOOKUP($A30,[16]HISTOJANV22!$A$6:$AU$39,45,0) -> 7000 | K30: =IF(J30=0,0,J30-(L30+M30+N30)) -> 3000 | L30: =IF(J30=0,0,500) -> 500 | M30: =IF(J30=0,0,1000) -> 1000 | N30: =IF(J30=0,0,2500) -> 2500 | O30: =VLOOKUP($A30,[16]HISTOJANV22!$A$6:$AU$39,7,0) -> 0 | P30: =VLOOKUP($A30,[16]HISTOJANV22!$A$6:$AU$39,23,0) -> 0 | Q30: =VLOOKUP($A30,[16]HISTOJANV22!$A$6:$AU$39,46,0) -> 0 | R30: =VLOOKUP($A30,[16]HISTODEC21!$A$6:$AU$39,26,0) -> #REF! | S30: =R30*12/1200*12 -> #REF! | T30: =VLOOKUP($A30,[16]HISTOJANV22!$A$6:$AU$39,28,0) -> 0 | U30: =VLOOKUP($A30,[16]HISTOJANV22!$A$6:$AU$39,19,0) -> 0 | V30: =VLOOKUP($A30,[16]HISTOJANV22!$A$6:$AU$39,20,0) -> 0 | W30: =VLOOKUP($A30,[16]HISTOJANV22!$A$6:$AU$39,27,0) -> 0 | X30: =VLOOKUP($A30,[16]HISTOJANV22!$A$6:$AU$39,33,0) -> 0 | AA30: =VLOOKUP($A30,[16]HISTOJANV22!$A$6:$AU$39,43,0) -> 0 | AB30: =VLOOKUP($A30,[16]HISTOJANV22!$A$6:$AU$39,44,0) -> 0 | AC30: =VLOOKUP($A30,[16]HISTOJANV22!$A$6:$AU$39,47,0) -> 0 | AD30: =VLOOKUP(A30,[16]HISTOJANV22!$A$6:$BB$36,54,0) -> 0
A31: AS201638 | B31: =VLOOKUP(A31,[15]LISTADHERENT!$A$5:$J$50,3,0) -> SIMO PIERRE | C31: =#REF! -> #REF! | D31: =#REF! -> #REF! | F31: =C31+D31-E31+K31 -> #REF! | G31: =$S$40/$H$40*H31 -> #REF! | H31: =F31+D31+K31 -> #REF! | I31: =VLOOKUP($A31,[16]HISTOJANV22!$A$6:$AQ$37,22,0) -> 0 | J31: =VLOOKUP($A31,[16]HISTOJANV22!$A$6:$AU$39,45,0) -> 22000 | K31: =IF(J31=0,0,J31-(L31+M31+N31)) -> 18000 | L31: =IF(J31=0,0,500) -> 500 | M31: =IF(J31=0,0,1000) -> 1000 | N31: =IF(J31=0,0,2500) -> 2500 | O31: =VLOOKUP($A31,[16]HISTOJANV22!$A$6:$AU$39,7,0) -> 0 | P31: =VLOOKUP($A31,[16]HISTOJANV22!$A$6:$AU$39,23,0) -> 0 | Q31: =VLOOKUP($A31,[16]HISTOJANV22!$A$6:$AU$39,46,0) -> 0 | R31: =VLOOKUP($A31,[16]HISTODEC21!$A$6:$AU$39,26,0) -> #REF! | S31: =R31*12/1200*12 -> #REF! | T31: =VLOOKUP($A31,[16]HISTOJANV22!$A$6:$AU$39,28,0) -> 0 | U31: =VLOOKUP($A31,[16]HISTOJANV22!$A$6:$AU$39,19,0) -> 0 | V31: =VLOOKUP($A31,[16]HISTOJANV22!$A$6:$AU$39,20,0) -> 0 | W31: =VLOOKUP($A31,[16]HISTOJANV22!$A$6:$AU$39,27,0) -> BANQUE | X31: =VLOOKUP($A31,[16]HISTOJANV22!$A$6:$AU$39,33,0) -> 0 | AA31: =VLOOKUP($A31,[16]HISTOJANV22!$A$6:$AU$39,43,0) -> 0 | AB31: =VLOOKUP($A31,[16]HISTOJANV22!$A$6:$AU$39,44,0) -> 0 | AC31: =VLOOKUP($A31,[16]HISTOJANV22!$A$6:$AU$39,47,0) -> 0 | AD31: =VLOOKUP(A31,[16]HISTOJANV22!$A$6:$BB$36,54,0) -> 70000
A32: AS201641 | B32: =VLOOKUP(A32,[15]LISTADHERENT!$A$5:$J$50,3,0) -> TCHOUAMOU MATHIEU | C32: =#REF! -> #REF! | D32: =#REF! -> #REF! | F32: =C32+D32-E32+K32 -> #REF! | G32: =$S$40/$H$40*H32 -> #REF! | H32: =F32+D32+K32 -> #REF! | I32: =VLOOKUP($A32,[16]HISTOJANV22!$A$6:$AQ$37,22,0) -> 0 | J32: =VLOOKUP($A32,[16]HISTOJANV22!$A$6:$AU$39,45,0) -> 7000 | K32: =IF(J32=0,0,J32-(L32+M32+N32)) -> 3000 | L32: =IF(J32=0,0,500) -> 500 | M32: =IF(J32=0,0,1000) -> 1000 | N32: =IF(J32=0,0,2500) -> 2500 | O32: =VLOOKUP($A32,[16]HISTOJANV22!$A$6:$AU$39,7,0) -> 0 | P32: =VLOOKUP($A32,[16]HISTOJANV22!$A$6:$AU$39,23,0) -> 0 | Q32: =VLOOKUP($A32,[16]HISTOJANV22!$A$6:$AU$39,46,0) -> 0 | R32: =VLOOKUP($A32,[16]HISTODEC21!$A$6:$AU$39,26,0) -> 560000 | S32: =R32*12/1200*12 -> 67200 | T32: =VLOOKUP($A32,[16]HISTOJANV22!$A$6:$AU$39,28,0) -> OKK | U32: =VLOOKUP($A32,[16]HISTOJANV22!$A$6:$AU$39,19,0) -> 0 | V32: =VLOOKUP($A32,[16]HISTOJANV22!$A$6:$AU$39,20,0) -> 0 | W32: =VLOOKUP($A32,[16]HISTOJANV22!$A$6:$AU$39,27,0) -> BANQUE | X32: =VLOOKUP($A32,[16]HISTOJANV22!$A$6:$AU$39,33,0) -> 0 | AA32: =VLOOKUP($A32,[16]HISTOJANV22!$A$6:$AU$39,43,0) -> 0 | AB32: =VLOOKUP($A32,[16]HISTOJANV22!$A$6:$AU$39,44,0) -> 0 | AC32: =VLOOKUP($A32,[16]HISTOJANV22!$A$6:$AU$39,47,0) -> 0 | AD32: =VLOOKUP(A32,[16]HISTOJANV22!$A$6:$BB$36,54,0) -> 0
A33: AS201643 | B33: =VLOOKUP(A33,[15]LISTADHERENT!$A$5:$J$50,3,0) -> TCHOUTOU NANA CLAUDE | C33: =#REF! -> #REF! | D33: =#REF! -> #REF! | F33: =C33+D33-E33+K33 -> #REF! | G33: =$S$40/$H$40*H33 -> #REF! | H33: =F33+D33+K33 -> #REF! | I33: =VLOOKUP($A33,[16]HISTOJANV22!$A$6:$AQ$37,22,0) -> #N/A | J33: =VLOOKUP($A33,[16]HISTOJANV22!$A$6:$AU$39,45,0) -> #N/A | K33: =IF(J33=0,0,J33-(L33+M33+N33)) -> #N/A | L33: =IF(J33=0,0,500) -> #N/A | M33: =IF(J33=0,0,1000) -> #N/A | N33: =IF(J33=0,0,2500) -> #N/A | O33: =VLOOKUP($A33,[16]HISTOJANV22!$A$6:$AU$39,7,0) -> #N/A | P33: =VLOOKUP($A33,[16]HISTOJANV22!$A$6:$AU$39,23,0) -> #N/A | Q33: =VLOOKUP($A33,[16]HISTOJANV22!$A$6:$AU$39,46,0) -> #N/A | R33: =VLOOKUP($A33,[16]HISTODEC21!$A$6:$AU$39,26,0) -> #N/A | S33: =R33*12/1200*12 -> #N/A | T33: =VLOOKUP($A33,[16]HISTOJANV22!$A$6:$AU$39,28,0) -> #N/A | U33: =VLOOKUP($A33,[16]HISTOJANV22!$A$6:$AU$39,19,0) -> #N/A | V33: =VLOOKUP($A33,[16]HISTOJANV22!$A$6:$AU$39,20,0) -> #N/A | W33: =VLOOKUP($A33,[16]HISTOJANV22!$A$6:$AU$39,27,0) -> #N/A | X33: =VLOOKUP($A33,[16]HISTOJANV22!$A$6:$AU$39,33,0) -> #N/A | AA33: =VLOOKUP($A33,[16]HISTOJANV22!$A$6:$AU$39,43,0) -> #N/A | AB33: =VLOOKUP($A33,[16]HISTOJANV22!$A$6:$AU$39,44,0) -> #N/A | AC33: =VLOOKUP($A33,[16]HISTOJANV22!$A$6:$AU$39,47,0) -> #N/A | AD33: =VLOOKUP(A33,[16]HISTOJANV22!$A$6:$BB$36,54,0) -> #N/A
A34: AS201658 | B34: =VLOOKUP(A34,[15]LISTADHERENT!$A$5:$J$50,3,0) -> YANTCHOU GERVAIS | C34: =#REF! -> #REF! | D34: =#REF! -> #REF! | F34: =C34+D34-E34+K34 -> #REF! | G34: =$S$40/$H$40*H34 -> #REF! | H34: =F34+D34+K34 -> #REF! | I34: =VLOOKUP($A34,[16]HISTOJANV22!$A$6:$AQ$37,22,0) -> #N/A | J34: =VLOOKUP($A34,[16]HISTOJANV22!$A$6:$AU$39,45,0) -> #N/A | K34: =IF(J34=0,0,J34-(L34+M34+N34)) -> #N/A | L34: =IF(J34=0,0,500) -> #N/A | M34: =IF(J34=0,0,1000) -> #N/A | N34: =IF(J34=0,0,2500) -> #N/A | O34: =VLOOKUP($A34,[16]HISTOJANV22!$A$6:$AU$39,7,0) -> #N/A | P34: =VLOOKUP($A34,[16]HISTOJANV22!$A$6:$AU$39,23,0) -> #N/A | Q34: =VLOOKUP($A34,[16]HISTOJANV22!$A$6:$AU$39,46,0) -> #N/A | R34: =VLOOKUP($A34,[16]HISTODEC21!$A$6:$AU$39,26,0) -> #N/A | S34: =R34*12/1200*12 -> #N/A | T34: =VLOOKUP($A34,[16]HISTOJANV22!$A$6:$AU$39,28,0) -> #N/A | U34: =VLOOKUP($A34,[16]HISTOJANV22!$A$6:$AU$39,19,0) -> #N/A | V34: =VLOOKUP($A34,[16]HISTOJANV22!$A$6:$AU$39,20,0) -> #N/A | W34: =VLOOKUP($A34,[16]HISTOJANV22!$A$6:$AU$39,27,0) -> #N/A | X34: =VLOOKUP($A34,[16]HISTOJANV22!$A$6:$AU$39,33,0) -> #N/A | AA34: =VLOOKUP($A34,[16]HISTOJANV22!$A$6:$AU$39,43,0) -> #N/A | AB34: =VLOOKUP($A34,[16]HISTOJANV22!$A$6:$AU$39,44,0) -> #N/A | AC34: =VLOOKUP($A34,[16]HISTOJANV22!$A$6:$AU$39,47,0) -> #N/A | AD34: =VLOOKUP(A34,[16]HISTOJANV22!$A$6:$BB$36,54,0) -> #N/A
A35: AS201646 | B35: =VLOOKUP(A35,[15]LISTADHERENT!$A$5:$J$50,3,0) -> YEPMOU JEAN JACQUES | C35: =#REF! -> #REF! | D35: =#REF! -> #REF! | F35: =C35+D35-E35+K35 -> #REF! | G35: =$S$40/$H$40*H35 -> #REF! | H35: =F35+D35+K35 -> #REF! | I35: =VLOOKUP($A35,[16]HISTOJANV22!$A$6:$AQ$37,22,0) -> 0 | J35: =VLOOKUP($A35,[16]HISTOJANV22!$A$6:$AU$39,45,0) -> 7000 | K35: =IF(J35=0,0,J35-(L35+M35+N35)) -> 3000 | L35: =IF(J35=0,0,500) -> 500 | M35: =IF(J35=0,0,1000) -> 1000 | N35: =IF(J35=0,0,2500) -> 2500 | O35: =VLOOKUP($A35,[16]HISTOJANV22!$A$6:$AU$39,7,0) -> 3000 | P35: =VLOOKUP($A35,[16]HISTOJANV22!$A$6:$AU$39,23,0) -> 0 | Q35: =VLOOKUP($A35,[16]HISTOJANV22!$A$6:$AU$39,46,0) -> 0 | R35: =VLOOKUP($A35,[16]HISTODEC21!$A$6:$AU$39,26,0) -> 1155000 | S35: =R35*0/1200*12 -> 0 | T35: =VLOOKUP($A35,[16]HISTOJANV22!$A$6:$AU$39,28,0) -> 0 | U35: =VLOOKUP($A35,[16]HISTOJANV22!$A$6:$AU$39,19,0) -> 0 | V35: =VLOOKUP($A35,[16]HISTOJANV22!$A$6:$AU$39,20,0) -> 0 | W35: =VLOOKUP($A35,[16]HISTOJANV22!$A$6:$AU$39,27,0) -> BANQUE | X35: =VLOOKUP($A35,[16]HISTOJANV22!$A$6:$AU$39,33,0) -> 0 | Y35: 155000 | AA35: =VLOOKUP($A35,[16]HISTOJANV22!$A$6:$AU$39,43,0) -> 0 | AB35: =VLOOKUP($A35,[16]HISTOJANV22!$A$6:$AU$39,44,0) -> 0 | AC35: =VLOOKUP($A35,[16]HISTOJANV22!$A$6:$AU$39,47,0) -> 0 | AD35: =VLOOKUP(A35,[16]HISTOJANV22!$A$6:$BB$36,54,0) -> 0
A36: AS201647 | B36: =VLOOKUP(A36,[15]LISTADHERENT!$A$5:$J$50,3,0) -> YOUMBI EMMANUEL | C36: =#REF! -> #REF! | D36: =#REF! -> #REF! | F36: =C36+D36-E36+K36 -> #REF! | G36: =$S$40/$H$40*H36 -> #REF! | H36: =F36+D36+K36 -> #REF! | I36: =VLOOKUP($A36,[16]HISTOJANV22!$A$6:$AQ$37,22,0) -> 0 | J36: =VLOOKUP($A36,[16]HISTOJANV22!$A$6:$AU$39,45,0) -> 7000 | K36: =IF(J36=0,0,J36-(L36+M36+N36)) -> 3000 | L36: =IF(J36=0,0,500) -> 500 | M36: =IF(J36=0,0,1000) -> 1000 | N36: =IF(J36=0,0,2500) -> 2500 | O36: =VLOOKUP($A36,[16]HISTOJANV22!$A$6:$AU$39,7,0) -> 0 | P36: =VLOOKUP($A36,[16]HISTOJANV22!$A$6:$AU$39,23,0) -> 0 | Q36: =VLOOKUP($A36,[16]HISTOJANV22!$A$6:$AU$39,46,0) -> 0 | R36: =VLOOKUP($A36,[16]HISTODEC21!$A$6:$AU$39,26,0) -> #REF! | S36: =R36*12/1200*12 -> #REF! | T36: =VLOOKUP($A36,[16]HISTOJANV22!$A$6:$AU$39,28,0) -> 0 | U36: =VLOOKUP($A36,[16]HISTOJANV22!$A$6:$AU$39,19,0) -> 0 | V36: =VLOOKUP($A36,[16]HISTOJANV22!$A$6:$AU$39,20,0) -> 0 | W36: =VLOOKUP($A36,[16]HISTOJANV22!$A$6:$AU$39,27,0) -> 0 | X36: =VLOOKUP($A36,[16]HISTOJANV22!$A$6:$AU$39,33,0) -> 0 | AA36: =VLOOKUP($A36,[16]HISTOJANV22!$A$6:$AU$39,43,0) -> 0 | AB36: =VLOOKUP($A36,[16]HISTOJANV22!$A$6:$AU$39,44,0) -> 0 | AC36: =VLOOKUP($A36,[16]HISTOJANV22!$A$6:$AU$39,47,0) -> 0 | AD36: =VLOOKUP(A36,[16]HISTOJANV22!$A$6:$BB$36,54,0) -> 70000
A40: TOTAL | C40: =SUM(C6:C39) -> #REF! | D40: =SUM(D6:D39) -> #REF! | E40: =SUM(E6:E39) -> 0 | F40: =SUM(F6:F39) -> #REF! | G40: =SUM(G6:G39) -> #REF! | H40: =SUM(H6:H39) -> #REF! | I40: =SUM(I6:I39) -> #N/A | J40: =SUM(J6:J39) -> #N/A | ... AE40: =SUM(AE6:AE39) -> 0

Sheet Sheet5
A1: ASSOCIATION | B1: ASELBY | G1: K
A2: ANNEE | B2: 2022
A3: TONTINE
J4: 44912
A5: MATRICULE | B5: NOM ET PRENOM | C5: FONDES DE DEPART | D5: RELIQUAT | E5: RETRAIT PARTIEL | F5: FONDS DEFINITIF | G5: REPARTITION INTERET | H5: CAPITAL COMPOSE | I5: SANCTION | J5: RESTE | K5: EPARGNE | L5: FONDS DE ROULEMENT | M5: FRAIS EXCEPTIONNEL | N5: COLLATION | O5: PENALITE VST ESPECES | P5: INSCRISPTION | Q5: MUTUELLE | R5: PRÊT FONDS | S5: INTERETPRET FONDS | T5: NUMERO CHEQUE | U5: REMBOURSEMENTPRET FONDS | V5: MODE VERSEMENT REMBOURSEMENT | W5: MODE VERSEMENT PRÊT | X5: NUMERO CHEQUE | Y5: PENALITE PRET FONDS | Z5: PENALITE FONDS | AA5: PENALITE ECHEC TONTINE | AB5: PENALITE RETARD TONTINE | AC5: REMBOURSEMENT TRANSPORT | AD5: CONTRIBUTION FOYER | AE5: FONDS DE ROULEMENT | AF5: FRAIS EXCEPTIONNEL | AG5: FONDS MUTUELLE | AH5: COLLATION RECEPTION | AI5: PENALITE PRET FONDS | AJ5: DEPENSE PENALITE VERSEMENT BANQUE
A6: AS201648 | B6: =VLOOKUP(A6,[15]LISTADHERENT!$A$5:$J$45,3,0) -> ASELBY | C6: 0 | D6: =VLOOKUP(A6,'[17]EPARGNE 2023'!$A$5:$BF$47,4,0) -> 816543.52 | F6: =C6+D6-E6 -> 816543.52 | G6: 51868.55 | H6: =+F6+G6 -> 868412.07 | AE6: =VLOOKUP($A6,[16]HISTODEC22!$A$6:$CA$36,60,0) -> 6000 | AF6: =VLOOKUP($A6,[16]HISTODEC22!$A$6:$CA$36,61,0) -> 0 | AG6: =VLOOKUP($A6,[16]HISTODEC22!$A$6:$CA$36,62,0) -> 0 | AH6: =VLOOKUP($A6,[16]HISTODEC22!$A$6:$CA$36,63,0) -> 0 | AI6: =VLOOKUP($A6,[16]HISTODEC22!$A$6:$CA$36,64,0) -> 0 | AJ6: =VLOOKUP($A6,[16]HISTODEC22!$A$6:$CA$36,65,0) -> 0
A7: AS201601 | B7: =VLOOKUP(A7,[15]LISTADHERENT!$A$5:$J$45,3,0) -> BAKOP ACHILLE | C7: 0 | D7: =VLOOKUP(A7,'[17]EPARGNE 2023'!$A$5:$BF$47,4,0) -> 0 | F7: =C7+D7-E7 -> 0 | G7: 0 | H7: =+F7+G7 -> 0
A8: AS201602 | B8: =VLOOKUP(A8,[15]LISTADHERENT!$A$5:$J$45,3,0) -> BOUTCHOUANG WILLIAM | C8: 600000 | D8: =VLOOKUP(A8,'[17]EPARGNE 2023'!$A$5:$BF$47,4,0) -> 7023.6611 | F8: =C8+D8-E8 -> 607023.66 | G8: 38559.411 | H8: =+F8+G8 -> 645583.07 | I8: =VLOOKUP($A8,[16]HISTODEC22!$A$6:$AQ$37,22,0) -> 0 | J8: =VLOOKUP($A8,[16]HISTODEC22!$A$6:$AU$39,45,0) -> 7000 | L8: =IF(J8=0,0,500) -> 500 | M8: =IF(J8=0,0,1000) -> 1000 | N8: =IF(J8=0,0,2500) -> 2500 | O8: =VLOOKUP($A8,[16]HISTODEC22!$A$6:$AU$39,7,0) -> 0 | P8: =VLOOKUP($A8,[16]HISTODEC22!$A$6:$AU$39,23,0) -> 0 | Q8: =VLOOKUP($A8,[16]HISTODEC22!$A$6:$AU$39,46,0) -> 0 | R8: =VLOOKUP($A8,[18]HISTODEC22!$A$6:$AU$39,26,0) -> 500000 | S8: =VLOOKUP($A8,[18]HISTODEC22!$A$6:$BG$39,58,0) -> 10000 | T8: =VLOOKUP($A8,[16]HISTODEC22!$A$6:$AU$39,28,0) -> 0 | U8: =VLOOKUP($A8,[16]HISTODEC22!$A$6:$AU$39,19,0) -> 0 | V8: =VLOOKUP($A8,[16]HISTODEC22!$A$6:$AU$39,20,0) -> 0 | W8: =VLOOKUP($A8,[16]HISTODEC22!$A$6:$AU$39,27,0) -> BANQUE | X8: =VLOOKUP($A8,[16]HISTODEC22!$A$6:$AU$39,33,0) -> 0 | Y8: =VLOOKUP($A8,[16]HISTODEC22!$A$6:$BP$39,65,0) -> 0 | AA8: =VLOOKUP($A8,[16]HISTODEC22!$A$6:$AU$39,43,0) -> 0 | AB8: =VLOOKUP($A8,[16]HISTODEC22!$A$6:$AU$39,44,0) -> 0 | AC8: =VLOOKUP($A8,[16]HISTODEC22!$A$6:$AU$39,47,0) -> 0 | AD8: =VLOOKUP(A8,[16]HISTODEC22!$A$6:$BB$36,54,0) -> 0 | AE8: =VLOOKUP($A8,[16]HISTODEC22!$A$6:$CA$36,60,0) -> 0 | AF8: =VLOOKUP($A8,[16]HISTODEC22!$A$6:$CA$36,61,0) -> 0 | AG8: =VLOOKUP($A8,[16]HISTODEC22!$A$6:$CA$36,62,0) -> 0 | AH8: =VLOOKUP($A8,[16]HISTODEC22!$A$6:$CA$36,63,0) -> 0 | AI8: =VLOOKUP($A8,[16]HISTODEC22!$A$6:$CA$36,64,0) -> 0 | AJ8: =VLOOKUP($A8,[16]HISTODEC22!$A$6:$CA$36,65,0) -> 0
A9: AS201604 | B9: =VLOOKUP(A9,[15]LISTADHERENT!$A$5:$J$45,3,0) -> DJOMO JEAN PAUL | C9: 600000 | D9: =VLOOKUP(A9,'[17]EPARGNE 2023'!$A$5:$BF$47,4,0) -> 4809.807 | F9: =C9+D9-E9 -> 604809.81 | G9: 38418.782 | H9: =+F9+G9 -> 643228.59 | I9: =VLOOKUP($A9,[16]HISTODEC22!$A$6:$AQ$37,22,0) -> 0 | J9: =VLOOKUP($A9,[16]HISTODEC22!$A$6:$AU$39,45,0) -> 7000 | L9: =IF(J9=0,0,500) -> 500 | M9: =IF(J9=0,0,1000) -> 1000 | N9: =IF(J9=0,0,2500) -> 2500 | O9: =VLOOKUP($A9,[16]HISTODEC22!$A$6:$AU$39,7,0) -> 0 | P9: =VLOOKUP($A9,[16]HISTODEC22!$A$6:$AU$39,23,0) -> 0 | Q9: =VLOOKUP($A9,[16]HISTODEC22!$A$6:$AU$39,46,0) -> 0 | R9: =VLOOKUP($A9,[18]HISTODEC22!$A$6:$AU$39,26,0) -> 1000000 | S9: =VLOOKUP($A9,[18]HISTODEC22!$A$6:$BG$39,58,0) -> 120000 | T9: =VLOOKUP($A9,[16]HISTODEC22!$A$6:$AU$39,28,0) -> 0 | U9: =VLOOKUP($A9,[16]HISTODEC22!$A$6:$AU$39,19,0) -> 1000000 | V9: =VLOOKUP($A9,[16]HISTODEC22!$A$6:$AU$39,20,0) -> BANQUE | W9: =VLOOKUP($A9,[16]HISTODEC22!$A$6:$AU$39,27,0) -> BANQUE | X9: =VLOOKUP($A9,[16]HISTODEC22!$A$6:$AU$39,33,0) -> 0 | Y9: =VLOOKUP($A9,[16]HISTODEC22!$A$6:$BP$39,65,0) -> 0 | AA9: =VLOOKUP($A9,[16]HISTODEC22!$A$6:$AU$39,43,0) -> 0 | AB9: =VLOOKUP($A9,[16]HISTODEC22!$A$6:$AU$39,44,0) -> 0 | AC9: =VLOOKUP($A9,[16]HISTODEC22!$A$6:$AU$39,47,0) -> 0 | AD9: =VLOOKUP(A9,[16]HISTODEC22!$A$6:$BB$36,54,0) -> 0 | AE9: =VLOOKUP($A9,[16]HISTODEC22!$A$6:$CA$36,60,0) -> 0 | AF9: =VLOOKUP($A9,[16]HISTODEC22!$A$6:$CA$36,61,0) -> 0 | AG9: =VLOOKUP($A9,[16]HISTODEC22!$A$6:$CA$36,62,0) -> 0 | AH9: =VLOOKUP($A9,[16]HISTODEC22!$A$6:$CA$36,63,0) -> 0 | AI9: =VLOOKUP($A9,[16]HISTODEC22!$A$6:$CA$36,64,0) -> 0 | AJ9: =VLOOKUP($A9,[16]HISTODEC22!$A$6:$CA$36,65,0) -> 0
A10: AS201654 | B10: =VLOOKUP(A10,[15]LISTADHERENT!$A$5:$J$45,3,0) -> DJOMOU TCHAPDA | C10: 600000 | D10: =VLOOKUP(A10,'[17]EPARGNE 2023'!$A$5:$BF$47,4,0) -> 48710.412 | F10: =C10+D10-E10 -> 648710.41 | G10: 41207.44 | H10: =+F10+G10 -> 689917.85 | I10: =VLOOKUP($A10,[16]HISTODEC22!$A$6:$AQ$37,22,0) -> 0 | J10: =VLOOKUP($A10,[16]HISTODEC22!$A$6:$AU$39,45,0) -> 7000 | L10: =IF(J10=0,0,500) -> 500 | M10: =IF(J10=0,0,1000) -> 1000 | N10: =IF(J10=0,0,2500) -> 2500 | O10: =VLOOKUP($A10,[16]HISTODEC22!$A$6:$AU$39,7,0) -> 0 | P10: =VLOOKUP($A10,[16]HISTODEC22!$A$6:$AU$39,23,0) -> 0 | Q10: =VLOOKUP($A10,[16]HISTODEC22!$A$6:$AU$39,46,0) -> 0 | R10: =VLOOKUP($A10,[18]HISTODEC22!$A$6:$AU$39,26,0) -> 0 | S10: =VLOOKUP($A10,[18]HISTODEC22!$A$6:$BG$39,58,0) -> 0 | T10: =VLOOKUP($A10,[16]HISTODEC22!$A$6:$AU$39,28,0) -> 0 | U10: =VLOOKUP($A10,[16]HISTODEC22!$A$6:$AU$39,19,0) -> 0 | V10: =VLOOKUP($A10,[16]HISTODEC22!$A$6:$AU$39,20,0) -> 0 | W10: =VLOOKUP($A10,[16]HISTODEC22!$A$6:$AU$39,27,0) -> 0 | X10: =VLOOKUP($A10,[16]HISTODEC22!$A$6:$AU$39,33,0) -> 0 | Y10: =VLOOKUP($A10,[16]HISTODEC22!$A$6:$BP$39,65,0) -> 0 | AA10: =VLOOKUP($A10,[16]HISTODEC22!$A$6:$AU$39,43,0) -> 0 | AB10: =VLOOKUP($A10,[16]HISTODEC22!$A$6:$AU$39,44,0) -> 0 | AC10: =VLOOKUP($A10,[16]HISTODEC22!$A$6:$AU$39,47,0) -> 0 | AD10: =VLOOKUP(A10,[16]HISTODEC22!$A$6:$BB$36,54,0) -> 0 | AE10: =VLOOKUP($A10,[16]HISTODEC22!$A$6:$CA$36,60,0) -> 0 | AF10: =VLOOKUP($A10,[16]HISTODEC22!$A$6:$CA$36,61,0) -> 0 | AG10: =VLOOKUP($A10,[16]HISTODEC22!$A$6:$CA$36,62,0) -> 0 | AH10: =VLOOKUP($A10,[16]HISTODEC22!$A$6:$CA$36,63,0) -> 0 | AI10: =VLOOKUP($A10,[16]HISTODEC22!$A$6:$CA$36,64,0) -> 0 | AJ10: =VLOOKUP($A10,[16]HISTODEC22!$A$6:$CA$36,65,0) -> 0
A11: AS201605 | B11: =VLOOKUP(A11,[15]LISTADHERENT!$A$5:$J$45,3,0) -> DJOUKWE NANGUEN GUY BLAISE | C11: 600000 | D11: =VLOOKUP(A11,'[17]EPARGNE 2023'!$A$5:$BF$47,4,0) -> 4750.0783 | F11: =C11+D11-E11 -> 604750.08 | G11: 38414.988 | H11: =+F11+G11 -> 643165.07 | I11: =VLOOKUP($A11,[16]HISTODEC22!$A$6:$AQ$37,22,0) -> 0 | J11: =VLOOKUP($A11,[16]HISTODEC22!$A$6:$AU$39,45,0) -> 7000 | L11: =IF(J11=0,0,500) -> 500 | M11: =IF(J11=0,0,1000) -> 1000 | N11: =IF(J11=0,0,2500) -> 2500 | O11: =VLOOKUP($A11,[16]HISTODEC22!$A$6:$AU$39,7,0) -> 0 | P11: =VLOOKUP($A11,[16]HISTODEC22!$A$6:$AU$39,23,0) -> 0 | Q11: =VLOOKUP($A11,[16]HISTODEC22!$A$6:$AU$39,46,0) -> 0 | R11: =VLOOKUP($A11,[18]HISTODEC22!$A$6:$AU$39,26,0) -> 1000000 | S11: =VLOOKUP($A11,[18]HISTODEC22!$A$6:$BG$39,58,0) -> 40000 | T11: =VLOOKUP($A11,[16]HISTODEC22!$A$6:$AU$39,28,0) -> 0 | U11: =VLOOKUP($A11,[16]HISTODEC22!$A$6:$AU$39,19,0) -> 1000000 | V11: =VLOOKUP($A11,[16]HISTODEC22!$A$6:$AU$39,20,0) -> BANQUE | W11: =VLOOKUP($A11,[16]HISTODEC22!$A$6:$AU$39,27,0) -> BANQUE | X11: =VLOOKUP($A11,[16]HISTODEC22!$A$6:$AU$39,33,0) -> 0 | Y11: =VLOOKUP($A11,[16]HISTODEC22!$A$6:$BP$39,65,0) -> 0 | AA11: =VLOOKUP($A11,[16]HISTODEC22!$A$6:$AU$39,43,0) -> 0 | AB11: =VLOOKUP($A11,[16]HISTODEC22!$A$6:$AU$39,44,0) -> 0 | AC11: =VLOOKUP($A11,[16]HISTODEC22!$A$6:$AU$39,47,0) -> 0 | AD11: =VLOOKUP(A11,[16]HISTODEC22!$A$6:$BB$36,54,0) -> 0 | AE11: =VLOOKUP($A11,[16]HISTODEC22!$A$6:$CA$36,60,0) -> 0 | AF11: =VLOOKUP($A11,[16]HISTODEC22!$A$6:$CA$36,61,0) -> 0 | AG11: =VLOOKUP($A11,[16]HISTODEC22!$A$6:$CA$36,62,0) -> 0 | AH11: =VLOOKUP($A11,[16]HISTODEC22!$A$6:$CA$36,63,0) -> 0 | AI11: =VLOOKUP($A11,[16]HISTODEC22!$A$6:$CA$36,64,0) -> 0 | AJ11: =VLOOKUP($A11,[16]HISTODEC22!$A$6:$CA$36,65,0) -> 0
A12: AS201608 | B12: =VLOOKUP(A12,[15]LISTADHERENT!$A$5:$J$45,3,0) -> DJUOMBESSY ANTOINE | C12: 600000 | D12: =VLOOKUP(A12,'[17]EPARGNE 2023'!$A$5:$BF$47,4,0) -> 10718.85 | F12: =C12+D12-E12 -> 610718.85 | G12: 38794.137 | H12: =+F12+G12 -> 649512.99 | I12: =VLOOKUP($A12,[16]HISTODEC22!$A$6:$AQ$37,22,0) -> 0 | J12: =VLOOKUP($A12,[16]HISTODEC22!$A$6:$AU$39,45,0) -> 8000 | L12: =IF(J12=0,0,500) -> 500 | M12: =IF(J12=0,0,1000) -> 1000 | N12: =IF(J12=0,0,2500) -> 2500 | O12: =VLOOKUP($A12,[16]HISTODEC22!$A$6:$AU$39,7,0) -> 0 | P12: =VLOOKUP($A12,[16]HISTODEC22!$A$6:$AU$39,23,0) -> 0 | Q12: =VLOOKUP($A12,[16]HISTODEC22!$A$6:$AU$39,46,0) -> 0 | R12: =VLOOKUP($A12,[18]HISTODEC22!$A$6:$AU$39,26,0) -> 1000000 | S12: =VLOOKUP($A12,[18]HISTODEC22!$A$6:$BG$39,58,0) -> 60000 | T12: =VLOOKUP($A12,[16]HISTODEC22!$A$6:$AU$39,28,0) -> 0 | U12: =VLOOKUP($A12,[16]HISTODEC22!$A$6:$AU$39,19,0) -> 0 | V12: =VLOOKUP($A12,[16]HISTODEC22!$A$6:$AU$39,20,0) -> 0 | W12: =VLOOKUP($A12,[16]HISTODEC22!$A$6:$AU$39,27,0) -> BANQUE | X12: =VLOOKUP($A12,[16]HISTODEC22!$A$6:$AU$39,33,0) -> 0 | Y12: =VLOOKUP($A12,[16]HISTODEC22!$A$6:$BP$39,65,0) -> 0 | AA12: =VLOOKUP($A12,[16]HISTODEC22!$A$6:$AU$39,43,0) -> 0 | AB12: =VLOOKUP($A12,[16]HISTODEC22!$A$6:$AU$39,44,0) -> 0 | AC12: =VLOOKUP($A12,[16]HISTODEC22!$A$6:$AU$39,47,0) -> 0 | AD12: =VLOOKUP(A12,[16]HISTODEC22!$A$6:$BB$36,54,0) -> 9000 | AE12: =VLOOKUP($A12,[16]HISTODEC22!$A$6:$CA$36,60,0) -> 0 | AF12: =VLOOKUP($A12,[16]HISTODEC22!$A$6:$CA$36,61,0) -> 0 | AG12: =VLOOKUP($A12,[16]HISTODEC22!$A$6:$CA$36,62,0) -> 0 | AH12: =VLOOKUP($A12,[16]HISTODEC22!$A$6:$CA$36,63,0) -> 0 | AI12: =VLOOKUP($A12,[16]HISTODEC22!$A$6:$CA$36,64,0) -> 0 | AJ12: =VLOOKUP($A12,[16]HISTODEC22!$A$6:$CA$36,65,0) -> 0
A13: AS201651 | B13: =VLOOKUP(A13,[15]LISTADHERENT!$A$5:$J$45,3,0) -> DOMOU FABIEN | C13: 600000 | D13: =VLOOKUP(A13,'[17]EPARGNE 2023'!$A$5:$BF$47,4,0) -> 584.046 | F13: =C13+D13-E13 -> 600584.05 | G13: 38150.353 | H13: =+F13+G13 -> 638734.4 | I13: =VLOOKUP($A13,[16]HISTODEC22!$A$6:$AQ$37,22,0) -> 0 | J13: =VLOOKUP($A13,[16]HISTODEC22!$A$6:$AU$39,45,0) -> 12000 | L13: =IF(J13=0,0,500) -> 500 | M13: =IF(J13=0,0,1000) -> 1000 | N13: =IF(J13=0,0,2500) -> 2500 | O13: =VLOOKUP($A13,[16]HISTODEC22!$A$6:$AU$39,7,0) -> 0 | P13: =VLOOKUP($A13,[16]HISTODEC22!$A$6:$AU$39,23,0) -> 0 | Q13: =VLOOKUP($A13,[16]HISTODEC22!$A$6:$AU$39,46,0) -> 0 | R13: =VLOOKUP($A13,[18]HISTODEC22!$A$6:$AU$39,26,0) -> 1000000 | S13: =VLOOKUP($A13,[18]HISTODEC22!$A$6:$BG$39,58,0) -> 120000 | T13: =VLOOKUP($A13,[16]HISTODEC22!$A$6:$AU$39,28,0) -> 0 | U13: =VLOOKUP($A13,[16]HISTODEC22!$A$6:$AU$39,19,0) -> 1000000 | V13: =VLOOKUP($A13,[16]HISTODEC22!$A$6:$AU$39,20,0) -> BANQUE | W13: =VLOOKUP($A13,[16]HISTODEC22!$A$6:$AU$39,27,0) -> BANQUE | X13: =VLOOKUP($A13,[16]HISTODEC22!$A$6:$AU$39,33,0) -> 0 | Y13: =VLOOKUP($A13,[16]HISTODEC22!$A$6:$BP$39,65,0) -> 0 | AA13: =VLOOKUP($A13,[16]HISTODEC22!$A$6:$AU$39,43,0) -> 0 | AB13: =VLOOKUP($A13,[16]HISTODEC22!$A$6:$AU$39,44,0) -> 0 | AC13: =VLOOKUP($A13,[16]HISTODEC22!$A$6:$AU$39,47,0) -> 0 | AD13: =VLOOKUP(A13,[16]HISTODEC22!$A$6:$BB$36,54,0) -> 0 | AE13: =VLOOKUP($A13,[16]HISTODEC22!$A$6:$CA$36,60,0) -> 0 | AF13: =VLOOKUP($A13,[16]HISTODEC22!$A$6:$CA$36,61,0) -> 0 | AG13: =VLOOKUP($A13,[16]HISTODEC22!$A$6:$CA$36,62,0) -> 0 | AH13: =VLOOKUP($A13,[16]HISTODEC22!$A$6:$CA$36,63,0) -> 0 | AI13: =VLOOKUP($A13,[16]HISTODEC22!$A$6:$CA$36,64,0) -> 0 | AJ13: =VLOOKUP($A13,[16]HISTODEC22!$A$6:$CA$36,65,0) -> 0
A14: AS201609 | B14: =VLOOKUP(A14,[15]LISTADHERENT!$A$5:$J$45,3,0) -> DONHOU DAVID | C14: 600000 | D14: =VLOOKUP(A14,'[17]EPARGNE 2023'!$A$5:$BF$47,4,0) -> 458343.18 | F14: =C14+D14-E14 -> 1058343.2 | G14: 67228.169 | H14: =+F14+G14 -> 1125571.3 | I14: =VLOOKUP($A14,[16]HISTODEC22!$A$6:$AQ$37,22,0) -> 0 | J14: =VLOOKUP($A14,[16]HISTODEC22!$A$6:$AU$39,45,0) -> 12000 | L14: =IF(J14=0,0,500) -> 500 | M14: =IF(J14=0,0,1000) -> 1000 | N14: =IF(J14=0,0,2500) -> 2500 | O14: =VLOOKUP($A14,[16]HISTODEC22!$A$6:$AU$39,7,0) -> 0 | P14: =VLOOKUP($A14,[16]HISTODEC22!$A$6:$AU$39,23,0) -> 0 | Q14: =VLOOKUP($A14,[16]HISTODEC22!$A$6:$AU$39,46,0) -> 0 | R14: =VLOOKUP($A14,[18]HISTODEC22!$A$6:$AU$39,26,0) -> 0 | S14: =VLOOKUP($A14,[18]HISTODEC22!$A$6:$BG$39,58,0) -> 0 | T14: =VLOOKUP($A14,[16]HISTODEC22!$A$6:$AU$39,28,0) -> 0 | U14: =VLOOKUP($A14,[16]HISTODEC22!$A$6:$AU$39,19,0) -> 0 | V14: =VLOOKUP($A14,[16]HISTODEC22!$A$6:$AU$39,20,0) -> 0 | W14: =VLOOKUP($A14,[16]HISTODEC22!$A$6:$AU$39,27,0) -> 0 | X14: =VLOOKUP($A14,[16]HISTODEC22!$A$6:$AU$39,33,0) -> 0 | Y14: =VLOOKUP($A14,[16]HISTODEC22!$A$6:$BP$39,65,0) -> 0 | AA14: =VLOOKUP($A14,[16]HISTODEC22!$A$6:$AU$39,43,0) -> 0 | AB14: =VLOOKUP($A14,[16]HISTODEC22!$A$6:$AU$39,44,0) -> 0 | AC14: =VLOOKUP($A14,[16]HISTODEC22!$A$6:$AU$39,47,0) -> 0 | AD14: =VLOOKUP(A14,[16]HISTODEC22!$A$6:$BB$36,54,0) -> 0 | AE14: =VLOOKUP($A14,[16]HISTODEC22!$A$6:$CA$36,60,0) -> 0 | AF14: =VLOOKUP($A14,[16]HISTODEC22!$A$6:$CA$36,61,0) -> 0 | AG14: =VLOOKUP($A14,[16]HISTODEC22!$A$6:$CA$36,62,0) -> 0 | AH14: =VLOOKUP($A14,[16]HISTODEC22!$A$6:$CA$36,63,0) -> 0 | AI14: =VLOOKUP($A14,[16]HISTODEC22!$A$6:$CA$36,64,0) -> 0 | AJ14: =VLOOKUP($A14,[16]HISTODEC22!$A$6:$CA$36,65,0) -> 0
A15: AS201611 | B15: =VLOOKUP(A15,[15]LISTADHERENT!$A$5:$J$45,3,0) -> HENGUE PAUL OMER | C15: 600000 | D15: =VLOOKUP(A15,'[17]EPARGNE 2023'!$A$5:$BF$47,4,0) -> 51112.01 | F15: =C15+D15-E15 -> 651112.01 | G15: 41359.995 | H15: =+F15+G15 -> 692472.01 | I15: =VLOOKUP($A15,[16]HISTODEC22!$A$6:$AQ$37,22,0) -> 0 | J15: =VLOOKUP($A15,[16]HISTODEC22!$A$6:$AU$39,45,0) -> 7000 | L15: =IF(J15=0,0,500) -> 500 | M15: =IF(J15=0,0,1000) -> 1000 | N15: =IF(J15=0,0,2500) -> 2500 | O15: =VLOOKUP($A15,[16]HISTODEC22!$A$6:$AU$39,7,0) -> 0 | P15: =VLOOKUP($A15,[16]HISTODEC22!$A$6:$AU$39,23,0) -> 0 | Q15: =VLOOKUP($A15,[16]HISTODEC22!$A$6:$AU$39,46,0) -> 0 | R15: =VLOOKUP($A15,[18]HISTODEC22!$A$6:$AU$39,26,0) -> 0 | S15: =VLOOKUP($A15,[18]HISTODEC22!$A$6:$BG$39,58,0) -> 0 | T15: =VLOOKUP($A15,[16]HISTODEC22!$A$6:$AU$39,28,0) -> 0 | U15: =VLOOKUP($A15,[16]HISTODEC22!$A$6:$AU$39,19,0) -> 0 | V15: =VLOOKUP($A15,[16]HISTODEC22!$A$6:$AU$39,20,0) -> 0 | W15: =VLOOKUP($A15,[16]HISTODEC22!$A$6:$AU$39,27,0) -> 0 | X15: =VLOOKUP($A15,[16]HISTODEC22!$A$6:$AU$39,33,0) -> 0 | Y15: =VLOOKUP($A15,[16]HISTODEC22!$A$6:$BP$39,65,0) -> 0 | AA15: =VLOOKUP($A15,[16]HISTODEC22!$A$6:$AU$39,43,0) -> 0 | AB15: =VLOOKUP($A15,[16]HISTODEC22!$A$6:$AU$39,44,0) -> 0 | AC15: =VLOOKUP($A15,[16]HISTODEC22!$A$6:$AU$39,47,0) -> 0 | AD15: =VLOOKUP(A15,[16]HISTODEC22!$A$6:$BB$36,54,0) -> 0 | AE15: =VLOOKUP($A15,[16]HISTODEC22!$A$6:$CA$36,60,0) -> 0 | AF15: =VLOOKUP($A15,[16]HISTODEC22!$A$6:$CA$36,61,0) -> 0 | AG15: =VLOOKUP($A15,[16]HISTODEC22!$A$6:$CA$36,62,0) -> 0 | AH15: =VLOOKUP($A15,[16]HISTODEC22!$A$6:$CA$36,63,0) -> 0 | AI15: =VLOOKUP($A15,[16]HISTODEC22!$A$6:$CA$36,64,0) -> 0 | AJ15: =VLOOKUP($A15,[16]HISTODEC22!$A$6:$CA$36,65,0) -> 0
A16: AS201613 | B16: =VLOOKUP(A16,[15]LISTADHERENT!$A$5:$J$45,3,0) -> HOTCHO BENJAMIN | C16: 600000 | D16: =VLOOKUP(A16,'[17]EPARGNE 2023'!$A$5:$BF$47,4,0) -> 16229.566 | F16: =C16+D16-E16 -> 616229.57 | G16: 39144.189 | H16: =+F16+G16 -> 655373.76 | I16: =VLOOKUP($A16,[16]HISTODEC22!$A$6:$AQ$37,22,0) -> 0 | J16: =VLOOKUP($A16,[16]HISTODEC22!$A$6:$AU$39,45,0) -> 52000 | L16: =IF(J16=0,0,500) -> 500 | M16: =IF(J16=0,0,1000) -> 1000 | N16: =IF(J16=0,0,2500) -> 2500 | O16: =VLOOKUP($A16,[16]HISTODEC22!$A$6:$AU$39,7,0) -> 0 | P16: =VLOOKUP($A16,[16]HISTODEC22!$A$6:$AU$39,23,0) -> 0 | Q16: =VLOOKUP($A16,[16]HISTODEC22!$A$6:$AU$39,46,0) -> 0 | R16: =VLOOKUP($A16,[18]HISTODEC22!$A$6:$AU$39,26,0) -> 1000000 | S16: =VLOOKUP($A16,[18]HISTODEC22!$A$6:$BG$39,58,0) -> 120000 | T16: =VLOOKUP($A16,[16]HISTODEC22!$A$6:$AU$39,28,0) -> 0 | U16: =VLOOKUP($A16,[16]HISTODEC22!$A$6:$AU$39,19,0) -> 1000000 | V16: =VLOOKUP($A16,[16]HISTODEC22!$A$6:$AU$39,20,0) -> BANQUE | W16: =VLOOKUP($A16,[16]HISTODEC22!$A$6:$AU$39,27,0) -> BANQUE | X16: =VLOOKUP($A16,[16]HISTODEC22!$A$6:$AU$39,33,0) -> 0 | Y16: =VLOOKUP($A16,[16]HISTODEC22!$A$6:$BP$39,65,0) -> 0 | AA16: =VLOOKUP($A16,[16]HISTODEC22!$A$6:$AU$39,43,0) -> 0 | AB16: =VLOOKUP($A16,[16]HISTODEC22!$A$6:$AU$39,44,0) -> 0 | AC16: =VLOOKUP($A16,[16]HISTODEC22!$A$6:$AU$39,47,0) -> 0 | AD16: =VLOOKUP(A16,[16]HISTODEC22!$A$6:$BB$36,54,0) -> 0 | AE16: =VLOOKUP($A16,[16]HISTODEC22!$A$6:$CA$36,60,0) -> 0 | AF16: =VLOOKUP($A16,[16]HISTODEC22!$A$6:$CA$36,61,0) -> 0 | AG16: =VLOOKUP($A16,[16]HISTODEC22!$A$6:$CA$36,62,0) -> 0 | AH16: =VLOOKUP($A16,[16]HISTODEC22!$A$6:$CA$36,63,0) -> 0 | AI16: =VLOOKUP($A16,[16]HISTODEC22!$A$6:$CA$36,64,0) -> 0 | AJ16: =VLOOKUP($A16,[16]HISTODEC22!$A$6:$CA$36,65,0) -> 0
A17: AS201617 | B17: =VLOOKUP(A17,[15]LISTADHERENT!$A$5:$J$45,3,0) -> KOUAMOU MOISE | C17: 600000 | D17: =VLOOKUP(A17,'[17]EPARGNE 2023'!$A$5:$BF$47,4,0) -> 53292.832 | F17: =C17+D17-E17 -> 653292.83 | G17: 41498.525 | H17: =+F17+G17 -> 694791.36 | I17: =VLOOKUP($A17,[16]HISTODEC22!$A$6:$AQ$37,22,0) -> 0 | J17: =VLOOKUP($A17,[16]HISTODEC22!$A$6:$AU$39,45,0) -> 7000 | L17: =IF(J17=0,0,500) -> 500 | M17: =IF(J17=0,0,1000) -> 1000 | N17: =IF(J17=0,0,2500) -> 2500 | O17: =VLOOKUP($A17,[16]HISTODEC22!$A$6:$AU$39,7,0) -> 0 | P17: =VLOOKUP($A17,[16]HISTODEC22!$A$6:$AU$39,23,0) -> 0 | Q17: =VLOOKUP($A17,[16]HISTODEC22!$A$6:$AU$39,46,0) -> 0 | R17: =VLOOKUP($A17,[18]HISTODEC22!$A$6:$AU$39,26,0) -> 0 | S17: =VLOOKUP($A17,[18]HISTODEC22!$A$6:$BG$39,58,0) -> 0 | T17: =VLOOKUP($A17,[16]HISTODEC22!$A$6:$AU$39,28,0) -> 0 | U17: =VLOOKUP($A17,[16]HISTODEC22!$A$6:$AU$39,19,0) -> 700000 | V17: =VLOOKUP($A17,[16]HISTODEC22!$A$6:$AU$39,20,0) -> BANQUE | W17: =VLOOKUP($A17,[16]HISTODEC22!$A$6:$AU$39,27,0) -> 0 | X17: =VLOOKUP($A17,[16]HISTODEC22!$A$6:$AU$39,33,0) -> 0 | Y17: =VLOOKUP($A17,[16]HISTODEC22!$A$6:$BP$39,65,0) -> 0 | AA17: =VLOOKUP($A17,[16]HISTODEC22!$A$6:$AU$39,43,0) -> 0 | AB17: =VLOOKUP($A17,[16]HISTODEC22!$A$6:$AU$39,44,0) -> 0 | AC17: =VLOOKUP($A17,[16]HISTODEC22!$A$6:$AU$39,47,0) -> 0 | AD17: =VLOOKUP(A17,[16]HISTODEC22!$A$6:$BB$36,54,0) -> 0 | AE17: =VLOOKUP($A17,[16]HISTODEC22!$A$6:$CA$36,60,0) -> 0 | AF17: =VLOOKUP($A17,[16]HISTODEC22!$A$6:$CA$36,61,0) -> 0 | AG17: =VLOOKUP($A17,[16]HISTODEC22!$A$6:$CA$36,62,0) -> 0 | AH17: =VLOOKUP($A17,[16]HISTODEC22!$A$6:$CA$36,63,0) -> 0 | AI17: =VLOOKUP($A17,[16]HISTODEC22!$A$6:$CA$36,64,0) -> 0 | AJ17: =VLOOKUP($A17,[16]HISTODEC22!$A$6:$CA$36,65,0) -> 0
A18: AS201619 | B18: =VLOOKUP(A18,[15]LISTADHERENT!$A$5:$J$45,3,0) -> KOUATCHO MESSACK | C18: 600000 | D18: =VLOOKUP(A18,'[17]EPARGNE 2023'!$A$5:$BF$47,4,0) -> 6459.0432 | F18: =C18+D18-E18 -> 606459.04 | G18: 38523.545 | H18: =+F18+G18 -> 644982.59 | I18: =VLOOKUP($A18,[16]HISTODEC22!$A$6:$AQ$37,22,0) -> 0 | J18: =VLOOKUP($A18,[16]HISTODEC22!$A$6:$AU$39,45,0) -> 7000 | L18: =IF(J18=0,0,500) -> 500 | M18: =IF(J18=0,0,1000) -> 1000 | N18: =IF(J18=0,0,2500) -> 2500 | O18: =VLOOKUP($A18,[16]HISTODEC22!$A$6:$AU$39,7,0) -> 0 | P18: =VLOOKUP($A18,[16]HISTODEC22!$A$6:$AU$39,23,0) -> 0 | Q18: =VLOOKUP($A18,[16]HISTODEC22!$A$6:$AU$39,46,0) -> 0 | R18: =VLOOKUP($A18,[18]HISTODEC22!$A$6:$AU$39,26,0) -> 1000000 | S18: =VLOOKUP($A18,[18]HISTODEC22!$A$6:$BG$39,58,0) -> 60000 | T18: =VLOOKUP($A18,[16]HISTODEC22!$A$6:$AU$39,28,0) -> 0 | U18: =VLOOKUP($A18,[16]HISTODEC22!$A$6:$AU$39,19,0) -> 1000000 | V18: =VLOOKUP($A18,[16]HISTODEC22!$A$6:$AU$39,20,0) -> BANQUE | W18: =VLOOKUP($A18,[16]HISTODEC22!$A$6:$AU$39,27,0) -> BANQUE | X18: =VLOOKUP($A18,[16]HISTODEC22!$A$6:$AU$39,33,0) -> 0 | Y18: =VLOOKUP($A18,[16]HISTODEC22!$A$6:$BP$39,65,0) -> 0 | AA18: =VLOOKUP($A18,[16]HISTODEC22!$A$6:$AU$39,43,0) -> 0 | AB18: =VLOOKUP($A18,[16]HISTODEC22!$A$6:$AU$39,44,0) -> 0 | AC18: =VLOOKUP($A18,[16]HISTODEC22!$A$6:$AU$39,47,0) -> 0 | AD18: =VLOOKUP(A18,[16]HISTODEC22!$A$6:$BB$36,54,0) -> 0 | AE18: =VLOOKUP($A18,[16]HISTODEC22!$A$6:$CA$36,60,0) -> 0 | AF18: =VLOOKUP($A18,[16]HISTODEC22!$A$6:$CA$36,61,0) -> 0 | AG18: =VLOOKUP($A18,[16]HISTODEC22!$A$6:$CA$36,62,0) -> 0 | AH18: =VLOOKUP($A18,[16]HISTODEC22!$A$6:$CA$36,63,0) -> 0 | AI18: =VLOOKUP($A18,[16]HISTODEC22!$A$6:$CA$36,64,0) -> 0 | AJ18: =VLOOKUP($A18,[16]HISTODEC22!$A$6:$CA$36,65,0) -> 0
A19: AS201620 | B19: =VLOOKUP(A19,[15]LISTADHERENT!$A$5:$J$45,3,0) -> LOWE JEAN | C19: 600000 | D19: =VLOOKUP(A19,'[17]EPARGNE 2023'!$A$5:$BF$47,4,0) -> 746.1759 | F19: =C19+D19-E19 -> 600746.18 | G19: 38160.652 | H19: =+F19+G19 -> 638906.83 | I19: =VLOOKUP($A19,[16]HISTODEC22!$A$6:$AQ$37,22,0) -> 0 | J19: =VLOOKUP($A19,[16]HISTODEC22!$A$6:$AU$39,45,0) -> 7000 | L19: =IF(J19=0,0,500) -> 500 | M19: =IF(J19=0,0,1000) -> 1000 | N19: =IF(J19=0,0,2500) -> 2500 | O19: =VLOOKUP($A19,[16]HISTODEC22!$A$6:$AU$39,7,0) -> 0 | P19: =VLOOKUP($A19,[16]HISTODEC22!$A$6:$AU$39,23,0) -> 0 | Q19: =VLOOKUP($A19,[16]HISTODEC22!$A$6:$AU$39,46,0) -> 0 | R19: =VLOOKUP($A19,[18]HISTODEC22!$A$6:$AU$39,26,0) -> 1000000 | S19: =VLOOKUP($A19,[18]HISTODEC22!$A$6:$BG$39,58,0) -> 40000 | T19: =VLOOKUP($A19,[16]HISTODEC22!$A$6:$AU$39,28,0) -> 0 | U19: =VLOOKUP($A19,[16]HISTODEC22!$A$6:$AU$39,19,0) -> 1000000 | V19: =VLOOKUP($A19,[16]HISTODEC22!$A$6:$AU$39,20,0) -> BANQUE | W19: =VLOOKUP($A19,[16]HISTODEC22!$A$6:$AU$39,27,0) -> BANQUE | X19: =VLOOKUP($A19,[16]HISTODEC22!$A$6:$AU$39,33,0) -> 0 | Y19: =VLOOKUP($A19,[16]HISTODEC22!$A$6:$BP$39,65,0) -> 0 | AA19: =VLOOKUP($A19,[16]HISTODEC22!$A$6:$AU$39,43,0) -> 0 | AB19: =VLOOKUP($A19,[16]HISTODEC22!$A$6:$AU$39,44,0) -> 0 | AC19: =VLOOKUP($A19,[16]HISTODEC22!$A$6:$AU$39,47,0) -> 0 | AD19: =VLOOKUP(A19,[16]HISTODEC22!$A$6:$BB$36,54,0) -> 0 | AE19: =VLOOKUP($A19,[16]HISTODEC22!$A$6:$CA$36,60,0) -> 0 | AF19: =VLOOKUP($A19,[16]HISTODEC22!$A$6:$CA$36,61,0) -> 0 | AG19: =VLOOKUP($A19,[16]HISTODEC22!$A$6:$CA$36,62,0) -> 0 | AH19: =VLOOKUP($A19,[16]HISTODEC22!$A$6:$CA$36,63,0) -> 0 | AI19: =VLOOKUP($A19,[16]HISTODEC22!$A$6:$CA$36,64,0) -> 0 | AJ19: =VLOOKUP($A19,[16]HISTODEC22!$A$6:$CA$36,65,0) -> 0
... A26: AS201628 | B26: =VLOOKUP(A26,[15]LISTADHERENT!$A$5:$J$45,3,0) -> NKAMGANG JUSTIN DEJOLIE | C26: 600000 | D26: =VLOOKUP(A26,'[17]EPARGNE 2023'!$A$5:$BF$47,4,0) -> 575.28053 | F26: =C26+D26-E26 -> 600575.28 | G26: 38149.796 | H26: =+F26+G26 -> 638725.08 | I26: =VLOOKUP($A26,[16]HISTODEC22!$A$6:$AQ$37,22,0) -> 0 | J26: =VLOOKUP($A26,[16]HISTODEC22!$A$6:$AU$39,45,0) -> 7000 | L26: =IF(J26=0,0,500) -> 500 | M26: =IF(J26=0,0,1000) -> 1000 | N26: =IF(J26=0,0,2500) -> 2500 | O26: =VLOOKUP($A26,[16]HISTODEC22!$A$6:$AU$39,7,0) -> 0 | P26: =VLOOKUP($A26,[16]HISTODEC22!$A$6:$AU$39,23,0) -> 0 | Q26: =VLOOKUP($A26,[16]HISTODEC22!$A$6:$AU$39,46,0) -> 0 | R26: =VLOOKUP($A26,[18]HISTODEC22!$A$6:$AU$39,26,0) -> 1000000 | S26: =VLOOKUP($A26,[18]HISTODEC22!$A$6:$BG$39,58,0) -> 20000 | T26: =VLOOKUP($A26,[16]HISTODEC22!$A$6:$AU$39,28,0) -> 0 | U26: =VLOOKUP($A26,[16]HISTODEC22!$A$6:$AU$39,19,0) -> 1000000 | V26: =VLOOKUP($A26,[16]HISTODEC22!$A$6:$AU$39,20,0) -> BANQUE | W26: =VLOOKUP($A26,[16]HISTODEC22!$A$6:$AU$39,27,0) -> BANQUE | X26: =VLOOKUP($A26,[16]HISTODEC22!$A$6:$AU$39,33,0) -> 0 | Y26: =VLOOKUP($A26,[16]HISTODEC22!$A$6:$BP$39,65,0) -> 0 | AA26: =VLOOKUP($A26,[16]HISTODEC22!$A$6:$AU$39,43,0) -> 0 | AB26: =VLOOKUP($A26,[16]HISTODEC22!$A$6:$AU$39,44,0) -> 0 | AC26: =VLOOKUP($A26,[16]HISTODEC22!$A$6:$AU$39,47,0) -> 0 | AD26: =VLOOKUP(A26,[16]HISTODEC22!$A$6:$BB$36,54,0) -> 0 | AE26: =VLOOKUP($A26,[16]HISTODEC22!$A$6:$CA$36,60,0) -> 0 | AF26: =VLOOKUP($A26,[16]HISTODEC22!$A$6:$CA$36,61,0) -> 0 | AG26: =VLOOKUP($A26,[16]HISTODEC22!$A$6:$CA$36,62,0) -> 0 | AH26: =VLOOKUP($A26,[16]HISTODEC22!$A$6:$CA$36,63,0) -> 0 | AI26: =VLOOKUP($A26,[16]HISTODEC22!$A$6:$CA$36,64,0) -> 0 | AJ26: =VLOOKUP($A26,[16]HISTODEC22!$A$6:$CA$36,65,0) -> 0
A27: AS201656 | B27: =VLOOKUP(A27,[15]LISTADHERENT!$A$5:$J$45,3,0) -> NOUBE ETIENNE | C27: 0 | D27: =VLOOKUP(A27,'[17]EPARGNE 2023'!$A$5:$BF$47,4,0) -> 0 | F27: =C27+D27-E27 -> 0 | G27: 0 | H27: =+F27+G27 -> 0
A28: AS201633 | B28: =VLOOKUP(A28,[15]LISTADHERENT!$A$5:$J$45,3,0) -> PATEGO NJOSSU GUSTAVE | C28: 600000 | D28: =VLOOKUP(A28,'[17]EPARGNE 2023'!$A$5:$BF$47,4,0) -> 21451.963 | F28: =C28+D28-E28 -> 621451.96 | G28: 39475.927 | H28: =+F28+G28 -> 660927.89 | I28: =VLOOKUP($A28,[16]HISTODEC22!$A$6:$AQ$37,22,0) -> 0 | J28: =VLOOKUP($A28,[16]HISTODEC22!$A$6:$AU$39,45,0) -> 7000 | L28: =IF(J28=0,0,500) -> 500 | M28: =IF(J28=0,0,1000) -> 1000 | N28: =IF(J28=0,0,2500) -> 2500 | O28: =VLOOKUP($A28,[16]HISTODEC22!$A$6:$AU$39,7,0) -> 0 | P28: =VLOOKUP($A28,[16]HISTODEC22!$A$6:$AU$39,23,0) -> 0 | Q28: =VLOOKUP($A28,[16]HISTODEC22!$A$6:$AU$39,46,0) -> 0 | R28: =VLOOKUP($A28,[18]HISTODEC22!$A$6:$AU$39,26,0) -> 0 | S28: =VLOOKUP($A28,[18]HISTODEC22!$A$6:$BG$39,58,0) -> 0 | T28: =VLOOKUP($A28,[16]HISTODEC22!$A$6:$AU$39,28,0) -> 0 | U28: =VLOOKUP($A28,[16]HISTODEC22!$A$6:$AU$39,19,0) -> 0 | V28: =VLOOKUP($A28,[16]HISTODEC22!$A$6:$AU$39,20,0) -> 0 | W28: =VLOOKUP($A28,[16]HISTODEC22!$A$6:$AU$39,27,0) -> 0 | X28: =VLOOKUP($A28,[16]HISTODEC22!$A$6:$AU$39,33,0) -> 0 | Y28: =VLOOKUP($A28,[16]HISTODEC22!$A$6:$BP$39,65,0) -> 0 | AA28: =VLOOKUP($A28,[16]HISTODEC22!$A$6:$AU$39,43,0) -> 0 | AB28: =VLOOKUP($A28,[16]HISTODEC22!$A$6:$AU$39,44,0) -> 0 | AC28: =VLOOKUP($A28,[16]HISTODEC22!$A$6:$AU$39,47,0) -> 0 | AD28: =VLOOKUP(A28,[16]HISTODEC22!$A$6:$BB$36,54,0) -> 0 | AE28: =VLOOKUP($A28,[16]HISTODEC22!$A$6:$CA$36,60,0) -> 0 | AF28: =VLOOKUP($A28,[16]HISTODEC22!$A$6:$CA$36,61,0) -> 0 | AG28: =VLOOKUP($A28,[16]HISTODEC22!$A$6:$CA$36,62,0) -> 0 | AH28: =VLOOKUP($A28,[16]HISTODEC22!$A$6:$CA$36,63,0) -> 0 | AI28: =VLOOKUP($A28,[16]HISTODEC22!$A$6:$CA$36,64,0) -> 0 | AJ28: =VLOOKUP($A28,[16]HISTODEC22!$A$6:$CA$36,65,0) -> 0
A29: AS201657 | B29: =VLOOKUP(A29,[15]LISTADHERENT!$A$5:$J$45,3,0) -> SEUMO POLYCARPE | C29: 0 | D29: =VLOOKUP(A29,'[17]EPARGNE 2023'!$A$5:$BF$47,4,0) -> 0 | F29: =C29+D29-E29 -> 0 | G29: 0 | H29: =+F29+G29 -> 0
A30: AS201653 | B30: =VLOOKUP(A30,[15]LISTADHERENT!$A$5:$J$45,3,0) -> SIME BRICE | C30: 600000 | D30: =VLOOKUP(A30,'[17]EPARGNE 2023'!$A$5:$BF$47,4,0) -> 200752.48 | F30: =C30+D30-E30 -> 800752.48 | G30: 50865.47 | H30: =+F30+G30 -> 851617.95 | I30: =VLOOKUP($A30,[16]HISTODEC22!$A$6:$AQ$37,22,0) -> 0 | J30: =VLOOKUP($A30,[16]HISTODEC22!$A$6:$AU$39,45,0) -> 7000 | L30: =IF(J30=0,0,500) -> 500 | M30: =IF(J30=0,0,1000) -> 1000 | N30: =IF(J30=0,0,2500) -> 2500 | O30: =VLOOKUP($A30,[16]HISTODEC22!$A$6:$AU$39,7,0) -> 0 | P30: =VLOOKUP($A30,[16]HISTODEC22!$A$6:$AU$39,23,0) -> 0 | Q30: =VLOOKUP($A30,[16]HISTODEC22!$A$6:$AU$39,46,0) -> 0 | R30: =VLOOKUP($A30,[18]HISTODEC22!$A$6:$AU$39,26,0) -> 0 | S30: =VLOOKUP($A30,[18]HISTODEC22!$A$6:$BG$39,58,0) -> 0 | T30: =VLOOKUP($A30,[16]HISTODEC22!$A$6:$AU$39,28,0) -> 0 | U30: =VLOOKUP($A30,[16]HISTODEC22!$A$6:$AU$39,19,0) -> 0 | V30: =VLOOKUP($A30,[16]HISTODEC22!$A$6:$AU$39,20,0) -> 0 | W30: =VLOOKUP($A30,[16]HISTODEC22!$A$6:$AU$39,27,0) -> 0 | X30: =VLOOKUP($A30,[16]HISTODEC22!$A$6:$AU$39,33,0) -> 0 | Y30: =VLOOKUP($A30,[16]HISTODEC22!$A$6:$BP$39,65,0) -> 0 | AA30: =VLOOKUP($A30,[16]HISTODEC22!$A$6:$AU$39,43,0) -> 0 | AB30: =VLOOKUP($A30,[16]HISTODEC22!$A$6:$AU$39,44,0) -> 0 | AC30: =VLOOKUP($A30,[16]HISTODEC22!$A$6:$AU$39,47,0) -> 0 | AD30: =VLOOKUP(A30,[16]HISTODEC22!$A$6:$BB$36,54,0) -> 0 | AE30: =VLOOKUP($A30,[16]HISTODEC22!$A$6:$CA$36,60,0) -> 0 | AF30: =VLOOKUP($A30,[16]HISTODEC22!$A$6:$CA$36,61,0) -> 0 | AG30: =VLOOKUP($A30,[16]HISTODEC22!$A$6:$CA$36,62,0) -> 0 | AH30: =VLOOKUP($A30,[16]HISTODEC22!$A$6:$CA$36,63,0) -> 0 | AI30: =VLOOKUP($A30,[16]HISTODEC22!$A$6:$CA$36,64,0) -> 0 | AJ30: =VLOOKUP($A30,[16]HISTODEC22!$A$6:$CA$36,65,0) -> 0
A31: AS201638 | B31: =VLOOKUP(A31,[15]LISTADHERENT!$A$5:$J$45,3,0) -> SIMO PIERRE | C31: 600000 | D31: =VLOOKUP(A31,'[17]EPARGNE 2023'!$A$5:$BF$47,4,0) -> 103606.47 | F31: =C31+D31-E31 -> 703606.47 | G31: 44694.553 | H31: =+F31+G31 -> 748301.02 | I31: =VLOOKUP($A31,[16]HISTODEC22!$A$6:$AQ$37,22,0) -> 0 | J31: =VLOOKUP($A31,[16]HISTODEC22!$A$6:$AU$39,45,0) -> 7000 | L31: =IF(J31=0,0,500) -> 500 | M31: =IF(J31=0,0,1000) -> 1000 | N31: =IF(J31=0,0,2500) -> 2500 | O31: =VLOOKUP($A31,[16]HISTODEC22!$A$6:$AU$39,7,0) -> 0 | P31: =VLOOKUP($A31,[16]HISTODEC22!$A$6:$AU$39,23,0) -> 0 | Q31: =VLOOKUP($A31,[16]HISTODEC22!$A$6:$AU$39,46,0) -> 0 | R31: =VLOOKUP($A31,[18]HISTODEC22!$A$6:$AU$39,26,0) -> 1000000 | S31: =VLOOKUP($A31,[18]HISTODEC22!$A$6:$BG$39,58,0) -> 120000 | T31: =VLOOKUP($A31,[16]HISTODEC22!$A$6:$AU$39,28,0) -> 0 | U31: =VLOOKUP($A31,[16]HISTODEC22!$A$6:$AU$39,19,0) -> 800000 | V31: =VLOOKUP($A31,[16]HISTODEC22!$A$6:$AU$39,20,0) -> BANQUE | W31: =VLOOKUP($A31,[16]HISTODEC22!$A$6:$AU$39,27,0) -> BANQUE | X31: =VLOOKUP($A31,[16]HISTODEC22!$A$6:$AU$39,33,0) -> 0 | Y31: =VLOOKUP($A31,[16]HISTODEC22!$A$6:$BP$39,65,0) -> 0 | AA31: =VLOOKUP($A31,[16]HISTODEC22!$A$6:$AU$39,43,0) -> 0 | AB31: =VLOOKUP($A31,[16]HISTODEC22!$A$6:$AU$39,44,0) -> 0 | AC31: =VLOOKUP($A31,[16]HISTODEC22!$A$6:$AU$39,47,0) -> 0 | AD31: =VLOOKUP(A31,[16]HISTODEC22!$A$6:$BB$36,54,0) -> 0 | AE31: =VLOOKUP($A31,[16]HISTODEC22!$A$6:$CA$36,60,0) -> 0 | AF31: =VLOOKUP($A31,[16]HISTODEC22!$A$6:$CA$36,61,0) -> 0 | AG31: =VLOOKUP($A31,[16]HISTODEC22!$A$6:$CA$36,62,0) -> 0 | AH31: =VLOOKUP($A31,[16]HISTODEC22!$A$6:$CA$36,63,0) -> 0 | AI31: =VLOOKUP($A31,[16]HISTODEC22!$A$6:$CA$36,64,0) -> 0 | AJ31: =VLOOKUP($A31,[16]HISTODEC22!$A$6:$CA$36,65,0) -> 0
A32: AS201641 | B32: =VLOOKUP(A32,[15]LISTADHERENT!$A$5:$J$45,3,0) -> TCHOUAMOU MATHIEU | C32: 600000 | D32: =VLOOKUP(A32,'[17]EPARGNE 2023'!$A$5:$BF$47,4,0) -> 4207.8699 | F32: =C32+D32-E32 -> 604207.87 | G32: 38380.546 | H32: =+F32+G32 -> 642588.42 | I32: =VLOOKUP($A32,[16]HISTODEC22!$A$6:$AQ$37,22,0) -> 0 | J32: =VLOOKUP($A32,[16]HISTODEC22!$A$6:$AU$39,45,0) -> 7000 | L32: =IF(J32=0,0,500) -> 500 | M32: =IF(J32=0,0,1000) -> 1000 | N32: =IF(J32=0,0,2500) -> 2500 | O32: =VLOOKUP($A32,[16]HISTODEC22!$A$6:$AU$39,7,0) -> 0 | P32: =VLOOKUP($A32,[16]HISTODEC22!$A$6:$AU$39,23,0) -> 0 | Q32: =VLOOKUP($A32,[16]HISTODEC22!$A$6:$AU$39,46,0) -> 0 | R32: =VLOOKUP($A32,[18]HISTODEC22!$A$6:$AU$39,26,0) -> 1000000 | S32: =VLOOKUP($A32,[18]HISTODEC22!$A$6:$BG$39,58,0) -> 30000 | T32: =VLOOKUP($A32,[16]HISTODEC22!$A$6:$AU$39,28,0) -> 0 | U32: =VLOOKUP($A32,[16]HISTODEC22!$A$6:$AU$39,19,0) -> 1000000 | V32: =VLOOKUP($A32,[16]HISTODEC22!$A$6:$AU$39,20,0) -> BANQUE | W32: =VLOOKUP($A32,[16]HISTODEC22!$A$6:$AU$39,27,0) -> 0 | X32: =VLOOKUP($A32,[16]HISTODEC22!$A$6:$AU$39,33,0) -> 0 | Y32: =VLOOKUP($A32,[16]HISTODEC22!$A$6:$BP$39,65,0) -> 0 | AA32: =VLOOKUP($A32,[16]HISTODEC22!$A$6:$AU$39,43,0) -> 0 | AB32: =VLOOKUP($A32,[16]HISTODEC22!$A$6:$AU$39,44,0) -> 0 | AC32: =VLOOKUP($A32,[16]HISTODEC22!$A$6:$AU$39,47,0) -> 0 | AD32: =VLOOKUP(A32,[16]HISTODEC22!$A$6:$BB$36,54,0) -> 0 | AE32: =VLOOKUP($A32,[16]HISTODEC22!$A$6:$CA$36,60,0) -> 0 | AF32: =VLOOKUP($A32,[16]HISTODEC22!$A$6:$CA$36,61,0) -> 0 | AG32: =VLOOKUP($A32,[16]HISTODEC22!$A$6:$CA$36,62,0) -> 0 | AH32: =VLOOKUP($A32,[16]HISTODEC22!$A$6:$CA$36,63,0) -> 0 | AI32: =VLOOKUP($A32,[16]HISTODEC22!$A$6:$CA$36,64,0) -> 0 | AJ32: =VLOOKUP($A32,[16]HISTODEC22!$A$6:$CA$36,65,0) -> 0
A33: AS201643 | B33: =VLOOKUP(A33,[15]LISTADHERENT!$A$5:$J$45,3,0) -> TCHOUTOU NANA CLAUDE | C33: 0 | D33: =VLOOKUP(A33,'[17]EPARGNE 2023'!$A$5:$BF$47,4,0) -> 0 | F33: =C33+D33-E33 -> 0 | G33: 0 | H33: =+F33+G33 -> 0
A34: AS201658 | B34: =VLOOKUP(A34,[15]LISTADHERENT!$A$5:$J$45,3,0) -> YANTCHOU GERVAIS | C34: 0 | D34: =VLOOKUP(A34,'[17]EPARGNE 2023'!$A$5:$BF$47,4,0) -> 0 | F34: =C34+D34-E34 -> 0 | G34: 0 | H34: =+F34+G34 -> 0
A35: AS201646 | B35: =VLOOKUP(A35,[15]LISTADHERENT!$A$5:$J$45,3,0) -> YEPMOU JEAN JACQUES | C35: 600000 | D35: =VLOOKUP(A35,'[17]EPARGNE 2023'!$A$5:$BF$47,4,0) -> 914734.42 | F35: =C35+D35-E35 -> 1514734.4 | G35: 96219.095 | H35: =+F35+G35 -> 1610953.5 | I35: =VLOOKUP($A35,[16]HISTODEC22!$A$6:$AQ$37,22,0) -> 0 | J35: =VLOOKUP($A35,[16]HISTODEC22!$A$6:$AU$39,45,0) -> 7000 | L35: =IF(J35=0,0,500) -> 500 | M35: =IF(J35=0,0,1000) -> 1000 | N35: =IF(J35=0,0,2500) -> 2500 | O35: =VLOOKUP($A35,[16]HISTODEC22!$A$6:$AU$39,7,0) -> 0 | P35: =VLOOKUP($A35,[16]HISTODEC22!$A$6:$AU$39,23,0) -> 0 | Q35: =VLOOKUP($A35,[16]HISTODEC22!$A$6:$AU$39,46,0) -> 0 | R35: =VLOOKUP($A35,[18]HISTODEC22!$A$6:$AU$39,26,0) -> 0 | S35: =VLOOKUP($A35,[18]HISTODEC22!$A$6:$BG$39,58,0) -> 0 | T35: =VLOOKUP($A35,[16]HISTODEC22!$A$6:$AU$39,28,0) -> 0 | U35: =VLOOKUP($A35,[16]HISTODEC22!$A$6:$AU$39,19,0) -> 1011250 | V35: =VLOOKUP($A35,[16]HISTODEC22!$A$6:$AU$39,20,0) -> BANQUE | W35: =VLOOKUP($A35,[16]HISTODEC22!$A$6:$AU$39,27,0) -> 0 | X35: =VLOOKUP($A35,[16]HISTODEC22!$A$6:$AU$39,33,0) -> 0 | Y35: =VLOOKUP($A35,[16]HISTODEC22!$A$6:$BP$39,65,0) -> 0 | AA35: =VLOOKUP($A35,[16]HISTODEC22!$A$6:$AU$39,43,0) -> 0 | AB35: =VLOOKUP($A35,[16]HISTODEC22!$A$6:$AU$39,44,0) -> 0 | AC35: =VLOOKUP($A35,[16]HISTODEC22!$A$6:$AU$39,47,0) -> 0 | AD35: =VLOOKUP(A35,[16]HISTODEC22!$A$6:$BB$36,54,0) -> 0 | AE35: =VLOOKUP($A35,[16]HISTODEC22!$A$6:$CA$36,60,0) -> 0 | AF35: =VLOOKUP($A35,[16]HISTODEC22!$A$6:$CA$36,61,0) -> 0 | AG35: =VLOOKUP($A35,[16]HISTODEC22!$A$6:$CA$36,62,0) -> 0 | AH35: =VLOOKUP($A35,[16]HISTODEC22!$A$6:$CA$36,63,0) -> 0 | AI35: =VLOOKUP($A35,[16]HISTODEC22!$A$6:$CA$36,64,0) -> 0 | AJ35: =VLOOKUP($A35,[16]HISTODEC22!$A$6:$CA$36,65,0) -> 0
A36: AS201647 | B36: =VLOOKUP(A36,[15]LISTADHERENT!$A$5:$J$45,3,0) -> YOUMBI EMMANUEL | C36: 600000 | D36: =VLOOKUP(A36,'[17]EPARGNE 2023'!$A$5:$BF$47,4,0) -> 1057774.2 | F36: =C36+D36-E36 -> 1657774.2 | G36: 105305.28 | H36: =+F36+G36 -> 1763079.5 | I36: =VLOOKUP($A36,[16]HISTODEC22!$A$6:$AQ$37,22,0) -> 0 | J36: =VLOOKUP($A36,[16]HISTODEC22!$A$6:$AU$39,45,0) -> 7000 | L36: =IF(J36=0,0,500) -> 500 | M36: =IF(J36=0,0,1000) -> 1000 | N36: =IF(J36=0,0,2500) -> 2500 | O36: =VLOOKUP($A36,[16]HISTODEC22!$A$6:$AU$39,7,0) -> 0 | P36: =VLOOKUP($A36,[16]HISTODEC22!$A$6:$AU$39,23,0) -> 0 | Q36: =VLOOKUP($A36,[16]HISTODEC22!$A$6:$AU$39,46,0) -> 0 | R36: =VLOOKUP($A36,[18]HISTODEC22!$A$6:$AU$39,26,0) -> 0 | S36: =VLOOKUP($A36,[18]HISTODEC22!$A$6:$BG$39,58,0) -> 0 | T36: =VLOOKUP($A36,[16]HISTODEC22!$A$6:$AU$39,28,0) -> 0 | U36: =VLOOKUP($A36,[16]HISTODEC22!$A$6:$AU$39,19,0) -> 0 | V36: =VLOOKUP($A36,[16]HISTODEC22!$A$6:$AU$39,20,0) -> 0 | W36: =VLOOKUP($A36,[16]HISTODEC22!$A$6:$AU$39,27,0) -> 0 | X36: =VLOOKUP($A36,[16]HISTODEC22!$A$6:$AU$39,33,0) -> 0 | Y36: =VLOOKUP($A36,[16]HISTODEC22!$A$6:$BP$39,65,0) -> 0 | AA36: =VLOOKUP($A36,[16]HISTODEC22!$A$6:$AU$39,43,0) -> 0 | AB36: =VLOOKUP($A36,[16]HISTODEC22!$A$6:$AU$39,44,0) -> 0 | AC36: =VLOOKUP($A36,[16]HISTODEC22!$A$6:$AU$39,47,0) -> 0 | AD36: =VLOOKUP(A36,[16]HISTODEC22!$A$6:$BB$36,54,0) -> 0 | AE36: =VLOOKUP($A36,[16]HISTODEC22!$A$6:$CA$36,60,0) -> 0 | AF36: =VLOOKUP($A36,[16]HISTODEC22!$A$6:$CA$36,61,0) -> 0 | AG36: =VLOOKUP($A36,[16]HISTODEC22!$A$6:$CA$36,62,0) -> 0 | AH36: =VLOOKUP($A36,[16]HISTODEC22!$A$6:$CA$36,63,0) -> 0 | AI36: =VLOOKUP($A36,[16]HISTODEC22!$A$6:$CA$36,64,0) -> 0 | AJ36: =VLOOKUP($A36,[16]HISTODEC22!$A$6:$CA$36,65,0) -> 0
A37: AS201629 | B37: =VLOOKUP(A37,[15]LISTADHERENT!$A$5:$J$45,3,0) -> NKEPSEU DIEUDONNE | C37: 600000 | D37: 2434 | F37: =C37+D37-E37 -> 602434 | G37: 38267.866 | H37: =+F37+G37 -> 640701.87
A39: TOTAL | C39: =SUM(C6:C37) -> 15600000 | D39: =SUM(D6:D37) -> 4361560.2 | E39: =SUM(E6:E37) -> 0 | F39: =SUM(F6:F37) -> 19961560 | G39: =SUM(G6:G37) -> 1268000 | H39: =SUM(H6:H37) -> 21229560 | I39: =SUM(I6:I37) -> 0 | J39: =SUM(J6:J37) -> 286000 | ... AJ39: =SUM(AJ6:AJ37) -> 0
C41: 536000 | D41: 4361500
C42: =C39-C41 -> 15064000 | D42: =D39-D41 -> 60.190811 | F42: 19359126
H43: =H39-H41 -> 21229560

Sheet Sheet6
A1: ASSOCIATION | B1: ASELBY
A2: ANNEE | B2: 2023 | I2: =IF(E2>=700000,($T$41/$G$41*H2),0) -> 0
A3: TONTINE
H4: =H12+MVTJANV24!H12+MVTFEV24!H12+MVTMARS24!H12 -> 48586.87 | K4: 45277
A5: MATRICULE | B5: NOM ET PRENOM | C5: FONDES DE DEPART | D5: RECONDUCTION | E5: RETRAIT PARTIEL | F5: FONDS DEFINITIF | G5: BASE DE CALCUL INTERET FONDS DEFINITIF | H5: REPARTITION PROVISOIRE INTERET FONDS+EPARGNE | I5: CAPITAL COMPOSE | J5: SANCTION | K5: RESTE | L5: EPARGNE | M5: FONDS DE ROULEMENT | N5: FRAIS EXCEPTIONNEL | O5: COLLATION | P5: PENALITE VST ESPECES | Q5: INSCRISPTION | R5: MUTUELLE | S5: PRÊT FONDS | T5: INTERET PRET FONDS | U5: NUMERO CHEQUE | V5: REMBOURSEMENTPRET FONDS | W5: MODE VERSEMENT REMBOURSEMENT | X5: MODE VERSEMENT PRÊT | Y5: NUMERO CHEQUE | Z5: PENALITE PRET FONDS | AA5: PENALITE FONDS | AB5: PENALITE ECHEC TONTINE | AC5: PENALITE RETARD TONTINE | AD5: REMBOURSEMENT TRANSPORT | AE5: CONTRIBUTION FOYER | AF5: FONDS DE ROULEMENT | AG5: FRAIS EXCEPTIONNEL | AH5: FONDS MUTUELLE | AI5: COLLATION RECEPTION | AJ5: PENALITE PRET FONDS | AK5: DEPENSE PENALITE VERSEMENT BANQUE | AL5: COMPLEMENT
A6: AS201648 | B6: =VLOOKUP(A6,[19]LISTADHERENT!A$5:H$60,3,0) -> ASELBY | D6: =VLOOKUP($A6,[20]DETAILFICHECASSATION!$A$6:$R$36,17,0) -> 886523.26 | F6: =C6+D6-E6 -> 886523.26 | G6: =[21]MVTNOV23!F6+[21]MVTNOV23!G6-[21]MVTDEC23!E6+L6 -> 886523.26 | H6: =($T$41/$G$41*G6) -> 48583.421 | I6: =(F6+H6) -> 935106.68 | AF6: =VLOOKUP($A6,[22]HISTODEC23!$A$6:$CA$36,60,0) -> 6000 | AG6: =VLOOKUP($A6,[22]HISTODEC23!$A$6:$CA$36,61,0) -> 0 | AH6: =VLOOKUP($A6,[22]HISTODEC23!$A$6:$CA$36,62,0) -> 0 | AI6: =VLOOKUP($A6,[22]HISTODEC23!$A$6:$CA$36,63,0) -> 0 | AJ6: =VLOOKUP($A6,[22]HISTODEC23!$A$6:$CA$36,64,0) -> 0 | AK6: =VLOOKUP($A6,[22]HISTODEC23!$A$6:$CA$36,65,0) -> 0 | AL6: =VLOOKUP($A6,[20]DETAILFICHECASSATION!$A$6:$R$36,12,0) -> 0
A7: AS201601 | B7: =VLOOKUP(A7,[19]LISTADHERENT!A$5:H$60,3,0) -> BAKOP ACHILLE | C7: =VLOOKUP($A7,[23]FONDSCAISSE!$A$2:$G$33,4,0) -> 678482.5 | D7: =VLOOKUP($A7,[20]DETAILFICHECASSATION!$A$6:$R$36,17,0) -> 0 | F7: =C7+D7-E7 -> 678482.5 | G7: =IF(F7>=700000,(C7+D7-E7),0) -> 0 | H7: =($T$41/$G$41*G7) -> 0 | I7: =(F7+H7) -> 678482.5 | J7: =VLOOKUP($A7,[22]HISTODEC23!$A$6:$AQ$40,22,0) -> 0 | K7: =VLOOKUP($A7,[22]HISTODEC23!$A$6:$AU$36,45,0) -> 15000 | L7: =IF(K7=0,0,K7-(M7+N7+O7)) -> 9000 | M7: =IF(K7=0,0,1000) -> 1000 | N7: =IF(K7=0,0,1000) -> 1000 | O7: =IF(K7=0,0,4000) -> 4000 | P7: =VLOOKUP($A7,[22]HISTODEC23!$A$6:$AU$36,7,0) -> 0 | Q7: =VLOOKUP($A7,[22]HISTODEC23!$A$6:$AU$36,23,0) -> 0 | R7: =VLOOKUP($A7,[22]HISTODEC23!$A$6:$AU$36,46,0) -> 0 | S7: =VLOOKUP($A7,[22]HISTODEC23!$A$6:$AU$36,26,0) -> 600000 | T7: =VLOOKUP($A7,[22]HISTODEC23!$A$6:$BG$36,58,0) -> 36000 | U7: =VLOOKUP($A7,[22]HISTODEC23!$A$6:$AU$36,28,0) -> 0 | V7: =VLOOKUP($A7,[22]HISTODEC23!$A$6:$AU$36,19,0) -> 600000 | W7: =VLOOKUP($A7,[22]HISTODEC23!$A$6:$AU$36,20,0) -> BANQUE | X7: =VLOOKUP($A7,[22]HISTODEC23!$A$6:$AU$36,27,0) -> BANQUE | Y7: =VLOOKUP($A7,[22]HISTODEC23!$A$6:$BM$36,33,0) -> 0 | Z7: =VLOOKUP($A7,[22]HISTODEC23!$A$6:$BM$36,65,0) -> 0 | AB7: =VLOOKUP($A7,[22]HISTODEC23!$A$6:$AU$36,43,0) -> 0 | AC7: =VLOOKUP($A7,[22]HISTODEC23!$A$6:$AU$36,44,0) -> 0 | AD7: =VLOOKUP($A7,[22]HISTODEC23!$A$6:$AU$36,47,0) -> 0 | AE7: =VLOOKUP(A7,[22]HISTODEC23!$A$6:$BB$36,54,0) -> 0 | AF7: =VLOOKUP($A7,[22]HISTODEC23!$A$6:$CA$36,60,0) -> 0 | AG7: =VLOOKUP($A7,[22]HISTODEC23!$A$6:$CA$36,61,0) -> 0 | AH7: =VLOOKUP($A7,[22]HISTODEC23!$A$6:$CA$36,62,0) -> 0 | AI7: =VLOOKUP($A7,[22]HISTODEC23!$A$6:$CA$36,63,0) -> 0 | AJ7: =VLOOKUP($A7,[22]HISTODEC23!$A$6:$CA$36,64,0) -> 0 | AK7: =VLOOKUP($A7,[22]HISTODEC23!$A$6:$CA$36,65,0) -> 0 | AL7: =VLOOKUP($A7,[20]DETAILFICHECASSATION!$A$6:$R$36,12,0) -> 700000
A8: AS201602 | B8: =VLOOKUP(A8,[19]LISTADHERENT!A$5:H$60,3,0) -> BOUTCHOUANG WILLIAM | C8: =VLOOKUP($A8,[23]FONDSCAISSE!$A$2:$G$33,4,0) -> 700000 | D8: =VLOOKUP($A8,[20]DETAILFICHECASSATION!$A$6:$R$36,17,0) -> 33.126263 | F8: =C8+D8-E8 -> 700033.13 | G8: =IF(C8+D8+L8-E8>=700000,(C8+D8-E8),0) -> 700033.13 | H8: =($T$41/$G$41*G8) -> 38363.352 | I8: =(F8+H8) -> 738396.48 | J8: =VLOOKUP($A8,[22]HISTODEC23!$A$6:$AQ$40,22,0) -> 19000 | K8: =VLOOKUP($A8,[22]HISTODEC23!$A$6:$AU$36,45,0) -> 15000 | L8: =IF(K8=0,0,K8-(M8+N8+O8)) -> 9000 | M8: =IF(K8=0,0,1000) -> 1000 | N8: =IF(K8=0,0,1000) -> 1000 | O8: =IF(K8=0,0,4000) -> 4000 | P8: =VLOOKUP($A8,[22]HISTODEC23!$A$6:$AU$36,7,0) -> 0 | Q8: =VLOOKUP($A8,[22]HISTODEC23!$A$6:$AU$36,23,0) -> 0 | R8: =VLOOKUP($A8,[22]HISTODEC23!$A$6:$AU$36,46,0) -> 0 | S8: =VLOOKUP($A8,[22]HISTODEC23!$A$6:$AU$36,26,0) -> 500000 | T8: =VLOOKUP($A8,[22]HISTODEC23!$A$6:$BG$36,58,0) -> 15000 | U8: =VLOOKUP($A8,[22]HISTODEC23!$A$6:$AU$36,28,0) -> 0 | V8: =VLOOKUP($A8,[22]HISTODEC23!$A$6:$AU$36,19,0) -> 0 | W8: =VLOOKUP($A8,[22]HISTODEC23!$A$6:$AU$36,20,0) -> 0 | X8: =VLOOKUP($A8,[22]HISTODEC23!$A$6:$AU$36,27,0) -> BANQUE | Y8: =VLOOKUP($A8,[22]HISTODEC23!$A$6:$BM$36,33,0) -> 0 | Z8: =VLOOKUP($A8,[22]HISTODEC23!$A$6:$BM$36,65,0) -> 0 | AB8: =VLOOKUP($A8,[22]HISTODEC23!$A$6:$AU$36,43,0) -> 0 | AC8: =VLOOKUP($A8,[22]HISTODEC23!$A$6:$AU$36,44,0) -> 0 | AD8: =VLOOKUP($A8,[22]HISTODEC23!$A$6:$AU$36,47,0) -> 0 | AE8: =VLOOKUP(A8,[22]HISTODEC23!$A$6:$BB$36,54,0) -> 0 | AF8: =VLOOKUP($A8,[22]HISTODEC23!$A$6:$CA$36,60,0) -> 0 | AG8: =VLOOKUP($A8,[22]HISTODEC23!$A$6:$CA$36,61,0) -> 0 | AH8: =VLOOKUP($A8,[22]HISTODEC23!$A$6:$CA$36,62,0) -> 0 | AI8: =VLOOKUP($A8,[22]HISTODEC23!$A$6:$CA$36,63,0) -> 0 | AJ8: =VLOOKUP($A8,[22]HISTODEC23!$A$6:$CA$36,64,0) -> 0 | AK8: =VLOOKUP($A8,[22]HISTODEC23!$A$6:$CA$36,65,0) -> 0 | AL8: =VLOOKUP($A8,[20]DETAILFICHECASSATION!$A$6:$R$36,12,0) -> 100000
A9: AS201604 | B9: =VLOOKUP(A9,[19]LISTADHERENT!A$5:H$60,3,0) -> DJOMO JEAN PAUL | C9: =VLOOKUP($A9,[23]FONDSCAISSE!$A$2:$G$33,4,0) -> 700000 | D9: =VLOOKUP($A9,[20]DETAILFICHECASSATION!$A$6:$R$36,17,0) -> 53357.826 | F9: =C9+D9-E9 -> 753357.83 | G9: =IF(C9+D9+L9-E9>=700000,(C9+D9-E9),0) -> 753357.83 | H9: =($T$41/$G$41*G9) -> 41285.663 | I9: =(F9+H9) -> 794643.49 | J9: =VLOOKUP($A9,[22]HISTODEC23!$A$6:$AQ$40,22,0) -> 9000 | K9: =VLOOKUP($A9,[22]HISTODEC23!$A$6:$AU$36,45,0) -> 40000 | L9: =IF(K9=0,0,K9-(M9+N9+O9)) -> 34000 | M9: =IF(K9=0,0,1000) -> 1000 | N9: =IF(K9=0,0,1000) -> 1000 | O9: =IF(K9=0,0,4000) -> 4000 | P9: =VLOOKUP($A9,[22]HISTODEC23!$A$6:$AU$36,7,0) -> 0 | Q9: =VLOOKUP($A9,[22]HISTODEC23!$A$6:$AU$36,23,0) -> 0 | R9: =VLOOKUP($A9,[22]HISTODEC23!$A$6:$AU$36,46,0) -> 0 | S9: =VLOOKUP($A9,[22]HISTODEC23!$A$6:$AU$36,26,0) -> 1000000 | T9: =VLOOKUP($A9,[22]HISTODEC23!$A$6:$BG$36,58,0) -> 120000 | U9: =VLOOKUP($A9,[22]HISTODEC23!$A$6:$AU$36,28,0) -> 0 | V9: =VLOOKUP($A9,[22]HISTODEC23!$A$6:$AU$36,19,0) -> 1000000 | W9: =VLOOKUP($A9,[22]HISTODEC23!$A$6:$AU$36,20,0) -> BANQUE | X9: =VLOOKUP($A9,[22]HISTODEC23!$A$6:$AU$36,27,0) -> BANQUE | Y9: =VLOOKUP($A9,[22]HISTODEC23!$A$6:$BM$36,33,0) -> 0 | Z9: =VLOOKUP($A9,[22]HISTODEC23!$A$6:$BM$36,65,0) -> 0 | AB9: =VLOOKUP($A9,[22]HISTODEC23!$A$6:$AU$36,43,0) -> 0 | AC9: =VLOOKUP($A9,[22]HISTODEC23!$A$6:$AU$36,44,0) -> 0 | AD9: =VLOOKUP($A9,[22]HISTODEC23!$A$6:$AU$36,47,0) -> 0 | AE9: =VLOOKUP(A9,[22]HISTODEC23!$A$6:$BB$36,54,0) -> 0 | AF9: =VLOOKUP($A9,[22]HISTODEC23!$A$6:$CA$36,60,0) -> 0 | AG9: =VLOOKUP($A9,[22]HISTODEC23!$A$6:$CA$36,61,0) -> 0 | AH9: =VLOOKUP($A9,[22]HISTODEC23!$A$6:$CA$36,62,0) -> 0 | AI9: =VLOOKUP($A9,[22]HISTODEC23!$A$6:$CA$36,63,0) -> 0 | AJ9: =VLOOKUP($A9,[22]HISTODEC23!$A$6:$CA$36,64,0) -> 0 | AK9: =VLOOKUP($A9,[22]HISTODEC23!$A$6:$CA$36,65,0) -> 0 | AL9: =VLOOKUP($A9,[20]DETAILFICHECASSATION!$A$6:$R$36,12,0) -> 100000
A10: AS201654 | B10: =VLOOKUP(A10,[19]LISTADHERENT!A$5:H$60,3,0) -> DJOMOU TCHAPDA | C10: =VLOOKUP($A10,[23]FONDSCAISSE!$A$2:$G$33,4,0) -> 700000 | D10: =VLOOKUP($A10,[20]DETAILFICHECASSATION!$A$6:$R$36,17,0) -> 294.6793 | F10: =C10+D10-E10 -> 700294.68 | G10: =IF(C10+D10+L10-E10>=700000,(C10+D10-E10),0) -> 700294.68 | H10: =($T$41/$G$41*G10) -> 38377.686 | I10: =(F10+H10) -> 738672.36 | J10: =VLOOKUP($A10,[22]HISTODEC23!$A$6:$AQ$40,22,0) -> 22000 | K10: =VLOOKUP($A10,[22]HISTODEC23!$A$6:$AU$36,45,0) -> 15000 | L10: =IF(K10=0,0,K10-(M10+N10+O10)) -> 9000 | M10: =IF(K10=0,0,1000) -> 1000 | N10: =IF(K10=0,0,1000) -> 1000 | O10: =IF(K10=0,0,4000) -> 4000 | P10: =VLOOKUP($A10,[22]HISTODEC23!$A$6:$AU$36,7,0) -> 0 | Q10: =VLOOKUP($A10,[22]HISTODEC23!$A$6:$AU$36,23,0) -> 0 | R10: =VLOOKUP($A10,[22]HISTODEC23!$A$6:$AU$36,46,0) -> 0 | S10: =VLOOKUP($A10,[22]HISTODEC23!$A$6:$AU$36,26,0) -> 1000000 | T10: =VLOOKUP($A10,[22]HISTODEC23!$A$6:$BG$36,58,0) -> 120000 | U10: =VLOOKUP($A10,[22]HISTODEC23!$A$6:$AU$36,28,0) -> 0 | V10: =VLOOKUP($A10,[22]HISTODEC23!$A$6:$AU$36,19,0) -> 0 | W10: =VLOOKUP($A10,[22]HISTODEC23!$A$6:$AU$36,20,0) -> 0 | X10: =VLOOKUP($A10,[22]HISTODEC23!$A$6:$AU$36,27,0) -> BANQUE | Y10: =VLOOKUP($A10,[22]HISTODEC23!$A$6:$BM$36,33,0) -> 0 | Z10: =VLOOKUP($A10,[22]HISTODEC23!$A$6:$BM$36,65,0) -> 0 | AB10: =VLOOKUP($A10,[22]HISTODEC23!$A$6:$AU$36,43,0) -> 0 | AC10: =VLOOKUP($A10,[22]HISTODEC23!$A$6:$AU$36,44,0) -> 0 | AD10: =VLOOKUP($A10,[22]HISTODEC23!$A$6:$AU$36,47,0) -> 0 | AE10: =VLOOKUP(A10,[22]HISTODEC23!$A$6:$BB$36,54,0) -> 0 | AF10: =VLOOKUP($A10,[22]HISTODEC23!$A$6:$CA$36,60,0) -> 0 | AG10: =VLOOKUP($A10,[22]HISTODEC23!$A$6:$CA$36,61,0) -> 0 | AH10: =VLOOKUP($A10,[22]HISTODEC23!$A$6:$CA$36,62,0) -> 0 | AI10: =VLOOKUP($A10,[22]HISTODEC23!$A$6:$CA$36,63,0) -> 0 | AJ10: =VLOOKUP($A10,[22]HISTODEC23!$A$6:$CA$36,64,0) -> 0 | AK10: =VLOOKUP($A10,[22]HISTODEC23!$A$6:$CA$36,65,0) -> 0 | AL10: =VLOOKUP($A10,[20]DETAILFICHECASSATION!$A$6:$R$36,12,0) -> 100000
A11: AS201605 | B11: =VLOOKUP(A11,[19]LISTADHERENT!A$5:H$60,3,0) -> DJOUKWE NANGUEN GUY BLAISE | C11: =VLOOKUP($A11,[23]FONDSCAISSE!$A$2:$G$33,4,0) -> 700000 | D11: =VLOOKUP($A11,[20]DETAILFICHECASSATION!$A$6:$R$36,17,0) -> 2196.7679 | F11: =C11+D11-E11 -> 702196.77 | G11: =IF(C11+D11+L11-E11>=700000,(C11+D11-E11),0) -> 702196.77 | H11: =($T$41/$G$41*G11) -> 38481.924 | I11: =(F11+H11) -> 740678.69 | J11: =VLOOKUP($A11,[22]HISTODEC23!$A$6:$AQ$40,22,0) -> 0 | K11: =VLOOKUP($A11,[22]HISTODEC23!$A$6:$AU$36,45,0) -> 15000 | L11: =IF(K11=0,0,K11-(M11+N11+O11)) -> 9000 | M11: =IF(K11=0,0,1000) -> 1000 | N11: =IF(K11=0,0,1000) -> 1000 | O11: =IF(K11=0,0,4000) -> 4000 | P11: =VLOOKUP($A11,[22]HISTODEC23!$A$6:$AU$36,7,0) -> 0 | Q11: =VLOOKUP($A11,[22]HISTODEC23!$A$6:$AU$36,23,0) -> 0 | R11: =VLOOKUP($A11,[22]HISTODEC23!$A$6:$AU$36,46,0) -> 0 | S11: =VLOOKUP($A11,[22]HISTODEC23!$A$6:$AU$36,26,0) -> 1000000 | T11: =VLOOKUP($A11,[22]HISTODEC23!$A$6:$BG$36,58,0) -> 20000 | U11: =VLOOKUP($A11,[22]HISTODEC23!$A$6:$AU$36,28,0) -> 0 | V11: =VLOOKUP($A11,[22]HISTODEC23!$A$6:$AU$36,19,0) -> 1000000 | W11: =VLOOKUP($A11,[22]HISTODEC23!$A$6:$AU$36,20,0) -> BANQUE | X11: =VLOOKUP($A11,[22]HISTODEC23!$A$6:$AU$36,27,0) -> BANQUE | Y11: =VLOOKUP($A11,[22]HISTODEC23!$A$6:$BM$36,33,0) -> 0 | Z11: =VLOOKUP($A11,[22]HISTODEC23!$A$6:$BM$36,65,0) -> 0 | AB11: =VLOOKUP($A11,[22]HISTODEC23!$A$6:$AU$36,43,0) -> 0 | AC11: =VLOOKUP($A11,[22]HISTODEC23!$A$6:$AU$36,44,0) -> 0 | AD11: =VLOOKUP($A11,[22]HISTODEC23!$A$6:$AU$36,47,0) -> 0 | AE11: =VLOOKUP(A11,[22]HISTODEC23!$A$6:$BB$36,54,0) -> 0 | AF11: =VLOOKUP($A11,[22]HISTODEC23!$A$6:$CA$36,60,0) -> 0 | AG11: =VLOOKUP($A11,[22]HISTODEC23!$A$6:$CA$36,61,0) -> 0 | AH11: =VLOOKUP($A11,[22]HISTODEC23!$A$6:$CA$36,62,0) -> 0 | AI11: =VLOOKUP($A11,[22]HISTODEC23!$A$6:$CA$36,63,0) -> 0 | AJ11: =VLOOKUP($A11,[22]HISTODEC23!$A$6:$CA$36,64,0) -> 0 | AK11: =VLOOKUP($A11,[22]HISTODEC23!$A$6:$CA$36,65,0) -> 0 | AL11: =VLOOKUP($A11,[20]DETAILFICHECASSATION!$A$6:$R$36,12,0) -> 100000
A12: AS201608 | B12: =VLOOKUP(A12,[19]LISTADHERENT!A$5:H$60,3,0) -> DJUOMBESSY ANTOINE | C12: =VLOOKUP($A12,[23]FONDSCAISSE!$A$2:$G$33,4,0) -> 700000 | D12: =VLOOKUP($A12,[20]DETAILFICHECASSATION!$A$6:$R$36,17,0) -> 14513.277 | F12: =C12+D12-E12 -> 714513.28 | G12: =IF(C12+D12+L12-E12>=700000,(C12+D12-E12),0) -> 714513.28 | H12: =($T$41/$G$41*G12) -> 39156.896 | I12: =(F12+H12) -> 753670.17 | J12: =VLOOKUP($A12,[22]HISTODEC23!$A$6:$AQ$40,22,0) -> 0 | K12: =VLOOKUP($A12,[22]HISTODEC23!$A$6:$AU$36,45,0) -> 20800 | L12: =IF(K12=0,0,K12-(M12+N12+O12)) -> 14800 | M12: =IF(K12=0,0,1000) -> 1000 | N12: =IF(K12=0,0,1000) -> 1000 | O12: =IF(K12=0,0,4000) -> 4000 | P12: =VLOOKUP($A12,[22]HISTODEC23!$A$6:$AU$36,7,0) -> 0 | Q12: =VLOOKUP($A12,[22]HISTODEC23!$A$6:$AU$36,23,0) -> 0 | R12: =VLOOKUP($A12,[22]HISTODEC23!$A$6:$AU$36,46,0) -> 0 | S12: =VLOOKUP($A12,[22]HISTODEC23!$A$6:$AU$36,26,0) -> 1000000 | T12: =VLOOKUP($A12,[22]HISTODEC23!$A$6:$BG$36,58,0) -> 60000 | U12: =VLOOKUP($A12,[22]HISTODEC23!$A$6:$AU$36,28,0) -> 0 | V12: =VLOOKUP($A12,[22]HISTODEC23!$A$6:$AU$36,19,0) -> 719200 | W12: =VLOOKUP($A12,[22]HISTODEC23!$A$6:$AU$36,20,0) -> BANQUE | X12: =VLOOKUP($A12,[22]HISTODEC23!$A$6:$AU$36,27,0) -> BANQUE | Y12: =VLOOKUP($A12,[22]HISTODEC23!$A$6:$BM$36,33,0) -> 0 | Z12: =VLOOKUP($A12,[22]HISTODEC23!$A$6:$BM$36,65,0) -> 0 | AB12: =VLOOKUP($A12,[22]HISTODEC23!$A$6:$AU$36,43,0) -> 0 | AC12: =VLOOKUP($A12,[22]HISTODEC23!$A$6:$AU$36,44,0) -> 0 | AD12: =VLOOKUP($A12,[22]HISTODEC23!$A$6:$AU$36,47,0) -> 0 | AE12: =VLOOKUP(A12,[22]HISTODEC23!$A$6:$BB$36,54,0) -> 0 | AF12: =VLOOKUP($A12,[22]HISTODEC23!$A$6:$CA$36,60,0) -> 0 | AG12: =VLOOKUP($A12,[22]HISTODEC23!$A$6:$CA$36,61,0) -> 0 | AH12: =VLOOKUP($A12,[22]HISTODEC23!$A$6:$CA$36,62,0) -> 0 | AI12: =VLOOKUP($A12,[22]HISTODEC23!$A$6:$CA$36,63,0) -> 0 | AJ12: =VLOOKUP($A12,[22]HISTODEC23!$A$6:$CA$36,64,0) -> 0 | AK12: =VLOOKUP($A12,[22]HISTODEC23!$A$6:$CA$36,65,0) -> 0 | AL12: =VLOOKUP($A12,[20]DETAILFICHECASSATION!$A$6:$R$36,12,0) -> 100000
A13: AS201651 | B13: =VLOOKUP(A13,[19]LISTADHERENT!A$5:H$60,3,0) -> DOMOU FABIEN | C13: =VLOOKUP($A13,[23]FONDSCAISSE!$A$2:$G$33,4,0) -> 700000 | D13: =VLOOKUP($A13,[20]DETAILFICHECASSATION!$A$6:$R$36,17,0) -> 41.235806 | F13: =C13+D13-E13 -> 700041.24 | G13: =IF(C13+D13+L13-E13>=700000,(C13+D13-E13),0) -> 700041.24 | H13: =($T$41/$G$41*G13) -> 38363.796 | I13: =(F13+H13) -> 738405.03 | J13: =VLOOKUP($A13,[22]HISTODEC23!$A$6:$AQ$40,22,0) -> 0 | K13: =VLOOKUP($A13,[22]HISTODEC23!$A$6:$AU$36,45,0) -> 15000 | L13: =IF(K13=0,0,K13-(M13+N13+O13)) -> 9000 | M13: =IF(K13=0,0,1000) -> 1000 | N13: =IF(K13=0,0,1000) -> 1000 | O13: =IF(K13=0,0,4000) -> 4000 | P13: =VLOOKUP($A13,[22]HISTODEC23!$A$6:$AU$36,7,0) -> 0 | Q13: =VLOOKUP($A13,[22]HISTODEC23!$A$6:$AU$36,23,0) -> 0 | R13: =VLOOKUP($A13,[22]HISTODEC23!$A$6:$AU$36,46,0) -> 0 | S13: =VLOOKUP($A13,[22]HISTODEC23!$A$6:$AU$36,26,0) -> 1000000 | T13: =VLOOKUP($A13,[22]HISTODEC23!$A$6:$BG$36,58,0) -> 120000 | U13: =VLOOKUP($A13,[22]HISTODEC23!$A$6:$AU$36,28,0) -> 0 | V13: =VLOOKUP($A13,[22]HISTODEC23!$A$6:$AU$36,19,0) -> 1000000 | W13: =VLOOKUP($A13,[22]HISTODEC23!$A$6:$AU$36,20,0) -> BANQUE | X13: =VLOOKUP($A13,[22]HISTODEC23!$A$6:$AU$36,27,0) -> BANQUE | Y13: =VLOOKUP($A13,[22]HISTODEC23!$A$6:$BM$36,33,0) -> 0 | Z13: =VLOOKUP($A13,[22]HISTODEC23!$A$6:$BM$36,65,0) -> 0 | AB13: =VLOOKUP($A13,[22]HISTODEC23!$A$6:$AU$36,43,0) -> 0 | AC13: =VLOOKUP($A13,[22]HISTODEC23!$A$6:$AU$36,44,0) -> 0 | AD13: =VLOOKUP($A13,[22]HISTODEC23!$A$6:$AU$36,47,0) -> 0 | AE13: =VLOOKUP(A13,[22]HISTODEC23!$A$6:$BB$36,54,0) -> 0 | AF13: =VLOOKUP($A13,[22]HISTODEC23!$A$6:$CA$36,60,0) -> 0 | AG13: =VLOOKUP($A13,[22]HISTODEC23!$A$6:$CA$36,61,0) -> 0 | AH13: =VLOOKUP($A13,[22]HISTODEC23!$A$6:$CA$36,62,0) -> 0 | AI13: =VLOOKUP($A13,[22]HISTODEC23!$A$6:$CA$36,63,0) -> 0 | AJ13: =VLOOKUP($A13,[22]HISTODEC23!$A$6:$CA$36,64,0) -> 0 | AK13: =VLOOKUP($A13,[22]HISTODEC23!$A$6:$CA$36,65,0) -> 0 | AL13: =VLOOKUP($A13,[20]DETAILFICHECASSATION!$A$6:$R$36,12,0) -> 100000
A14: AS201609 | B14: =VLOOKUP(A14,[19]LISTADHERENT!A$5:H$60,3,0) -> DONHOU DAVID | C14: =VLOOKUP($A14,[23]FONDSCAISSE!$A$2:$G$33,4,0) -> 700000 | D14: =VLOOKUP($A14,[20]DETAILFICHECASSATION!$A$6:$R$36,17,0) -> 518031.29 | F14: =C14+D14-E14 -> 1218031.3 | G14: =IF(C14+D14+L14-E14>=700000,(C14+D14-E14),0) -> 1218031.3 | H14: =($T$41/$G$41*G14) -> 66750.788 | I14: =(F14+H14) -> 1284782.1 | J14: =VLOOKUP($A14,[22]HISTODEC23!$A$6:$AQ$40,22,0) -> 0 | K14: =VLOOKUP($A14,[22]HISTODEC23!$A$6:$AU$36,45,0) -> 15000 | L14: =IF(K14=0,0,K14-(M14+N14+O14)) -> 9000 | M14: =IF(K14=0,0,1000) -> 1000 | N14: =IF(K14=0,0,1000) -> 1000 | O14: =IF(K14=0,0,4000) -> 4000 | P14: =VLOOKUP($A14,[22]HISTODEC23!$A$6:$AU$36,7,0) -> 0 | Q14: =VLOOKUP($A14,[22]HISTODEC23!$A$6:$AU$36,23,0) -> 0 | R14: =VLOOKUP($A14,[22]HISTODEC23!$A$6:$AU$36,46,0) -> 0 | S14: =VLOOKUP($A14,[22]HISTODEC23!$A$6:$AU$36,26,0) -> 0 | T14: =VLOOKUP($A14,[22]HISTODEC23!$A$6:$BG$36,58,0) -> 0 | U14: =VLOOKUP($A14,[22]HISTODEC23!$A$6:$AU$36,28,0) -> 0 | V14: =VLOOKUP($A14,[22]HISTODEC23!$A$6:$AU$36,19,0) -> 0 | W14: =VLOOKUP($A14,[22]HISTODEC23!$A$6:$AU$36,20,0) -> 0 | X14: =VLOOKUP($A14,[22]HISTODEC23!$A$6:$AU$36,27,0) -> 0 | Y14: =VLOOKUP($A14,[22]HISTODEC23!$A$6:$BM$36,33,0) -> 0 | Z14: =VLOOKUP($A14,[22]HISTODEC23!$A$6:$BM$36,65,0) -> 0 | AB14: =VLOOKUP($A14,[22]HISTODEC23!$A$6:$AU$36,43,0) -> 0 | AC14: =VLOOKUP($A14,[22]HISTODEC23!$A$6:$AU$36,44,0) -> 0 | AD14: =VLOOKUP($A14,[22]HISTODEC23!$A$6:$AU$36,47,0) -> 0 | AE14: =VLOOKUP(A14,[22]HISTODEC23!$A$6:$BB$36,54,0) -> 0 | AF14: =VLOOKUP($A14,[22]HISTODEC23!$A$6:$CA$36,60,0) -> 0 | AG14: =VLOOKUP($A14,[22]HISTODEC23!$A$6:$CA$36,61,0) -> 0 | AH14: =VLOOKUP($A14,[22]HISTODEC23!$A$6:$CA$36,62,0) -> 0 | AI14: =VLOOKUP($A14,[22]HISTODEC23!$A$6:$CA$36,63,0) -> 0 | AJ14: =VLOOKUP($A14,[22]HISTODEC23!$A$6:$CA$36,64,0) -> 0 | AK14: =VLOOKUP($A14,[22]HISTODEC23!$A$6:$CA$36,65,0) -> 0 | AL14: =VLOOKUP($A14,[20]DETAILFICHECASSATION!$A$6:$R$36,12,0) -> 100000
A15: AS201611 | B15: =VLOOKUP(A15,[19]LISTADHERENT!A$5:H$60,3,0) -> HENGUE PAUL OMER | C15: =VLOOKUP($A15,[23]FONDSCAISSE!$A$2:$G$33,4,0) -> 700000 | D15: =VLOOKUP($A15,[20]DETAILFICHECASSATION!$A$6:$R$36,17,0) -> 57899.604 | F15: =C15+D15-E15 -> 757899.6 | G15: =IF(C15+D15+L15-E15>=700000,(C15+D15-E15),0) -> 757899.6 | H15: =($T$41/$G$41*G15) -> 41534.562 | I15: =(F15+H15) -> 799434.17 | J15: =VLOOKUP($A15,[22]HISTODEC23!$A$6:$AQ$40,22,0) -> 18000 | K15: =VLOOKUP($A15,[22]HISTODEC23!$A$6:$AU$36,45,0) -> 15000 | L15: =IF(K15=0,0,K15-(M15+N15+O15)) -> 9000 | M15: =IF(K15=0,0,1000) -> 1000 | N15: =IF(K15=0,0,1000) -> 1000 | O15: =IF(K15=0,0,4000) -> 4000 | P15: =VLOOKUP($A15,[22]HISTODEC23!$A$6:$AU$36,7,0) -> 0 | Q15: =VLOOKUP($A15,[22]HISTODEC23!$A$6:$AU$36,23,0) -> 0 | R15: =VLOOKUP($A15,[22]HISTODEC23!$A$6:$AU$36,46,0) -> 0 | S15: =VLOOKUP($A15,[22]HISTODEC23!$A$6:$AU$36,26,0) -> 0 | T15: =VLOOKUP($A15,[22]HISTODEC23!$A$6:$BG$36,58,0) -> 0 | U15: =VLOOKUP($A15,[22]HISTODEC23!$A$6:$AU$36,28,0) -> 0 | V15: =VLOOKUP($A15,[22]HISTODEC23!$A$6:$AU$36,19,0) -> 0 | W15: =VLOOKUP($A15,[22]HISTODEC23!$A$6:$AU$36,20,0) -> 0 | X15: =VLOOKUP($A15,[22]HISTODEC23!$A$6:$AU$36,27,0) -> 0 | Y15: =VLOOKUP($A15,[22]HISTODEC23!$A$6:$BM$36,33,0) -> 0 | Z15: =VLOOKUP($A15,[22]HISTODEC23!$A$6:$BM$36,65,0) -> 0 | AB15: =VLOOKUP($A15,[22]HISTODEC23!$A$6:$AU$36,43,0) -> 0 | AC15: =VLOOKUP($A15,[22]HISTODEC23!$A$6:$AU$36,44,0) -> 0 | AD15: =VLOOKUP($A15,[22]HISTODEC23!$A$6:$AU$36,47,0) -> 0 | AE15: =VLOOKUP(A15,[22]HISTODEC23!$A$6:$BB$36,54,0) -> 0 | AF15: =VLOOKUP($A15,[22]HISTODEC23!$A$6:$CA$36,60,0) -> 0 | AG15: =VLOOKUP($A15,[22]HISTODEC23!$A$6:$CA$36,61,0) -> 0 | AH15: =VLOOKUP($A15,[22]HISTODEC23!$A$6:$CA$36,62,0) -> 0 | AI15: =VLOOKUP($A15,[22]HISTODEC23!$A$6:$CA$36,63,0) -> 0 | AJ15: =VLOOKUP($A15,[22]HISTODEC23!$A$6:$CA$36,64,0) -> 0 | AK15: =VLOOKUP($A15,[22]HISTODEC23!$A$6:$CA$36,65,0) -> 0 | AL15: =VLOOKUP($A15,[20]DETAILFICHECASSATION!$A$6:$R$36,12,0) -> 100000
A16: AS201613 | B16: =VLOOKUP(A16,[19]LISTADHERENT!A$5:H$60,3,0) -> HOTCHO BENJAMIN | C16: =VLOOKUP($A16,[23]FONDSCAISSE!$A$2:$G$33,4,0) -> 700000 | D16: =VLOOKUP($A16,[20]DETAILFICHECASSATION!$A$6:$R$36,17,0) -> 29661.208 | F16: =C16+D16-E16 -> 729661.21 | G16: =IF(C16+D16+L16-E16>=700000,(C16+D16-E16),0) -> 729661.21 | H16: =($T$41/$G$41*G16) -> 39987.036 | I16: =(F16+H16) -> 769648.24 | J16: =VLOOKUP($A16,[22]HISTODEC23!$A$6:$AQ$40,22,0) -> 12000 | K16: =VLOOKUP($A16,[22]HISTODEC23!$A$6:$AU$36,45,0) -> 50000 | L16: =IF(K16=0,0,K16-(M16+N16+O16)) -> 44000 | M16: =IF(K16=0,0,1000) -> 1000 | N16: =IF(K16=0,0,1000) -> 1000 | O16: =IF(K16=0,0,4000) -> 4000 | P16: =VLOOKUP($A16,[22]HISTODEC23!$A$6:$AU$36,7,0) -> 0 | Q16: =VLOOKUP($A16,[22]HISTODEC23!$A$6:$AU$36,23,0) -> 0 | R16: =VLOOKUP($A16,[22]HISTODEC23!$A$6:$AU$36,46,0) -> 0 | S16: =VLOOKUP($A16,[22]HISTODEC23!$A$6:$AU$36,26,0) -> 363500 | T16: =VLOOKUP($A16,[22]HISTODEC23!$A$6:$BG$36,58,0) -> 0 | U16: =VLOOKUP($A16,[22]HISTODEC23!$A$6:$AU$36,28,0) -> 0 | V16: =VLOOKUP($A16,[22]HISTODEC23!$A$6:$AU$36,19,0) -> 363500 | W16: =VLOOKUP($A16,[22]HISTODEC23!$A$6:$AU$36,20,0) -> BANQUE | X16: =VLOOKUP($A16,[22]HISTODEC23!$A$6:$AU$36,27,0) -> 0 | Y16: =VLOOKUP($A16,[22]HISTODEC23!$A$6:$BM$36,33,0) -> 0 | Z16: =VLOOKUP($A16,[22]HISTODEC23!$A$6:$BM$36,65,0) -> 0 | AB16: =VLOOKUP($A16,[22]HISTODEC23!$A$6:$AU$36,43,0) -> 0 | AC16: =VLOOKUP($A16,[22]HISTODEC23!$A$6:$AU$36,44,0) -> 0 | AD16: =VLOOKUP($A16,[22]HISTODEC23!$A$6:$AU$36,47,0) -> 0 | AE16: =VLOOKUP(A16,[22]HISTODEC23!$A$6:$BB$36,54,0) -> 0 | AF16: =VLOOKUP($A16,[22]HISTODEC23!$A$6:$CA$36,60,0) -> 0 | AG16: =VLOOKUP($A16,[22]HISTODEC23!$A$6:$CA$36,61,0) -> 0 | AH16: =VLOOKUP($A16,[22]HISTODEC23!$A$6:$CA$36,62,0) -> 0 | AI16: =VLOOKUP($A16,[22]HISTODEC23!$A$6:$CA$36,63,0) -> 0 | AJ16: =VLOOKUP($A16,[22]HISTODEC23!$A$6:$CA$36,64,0) -> 0 | AK16: =VLOOKUP($A16,[22]HISTODEC23!$A$6:$CA$36,65,0) -> 0 | AL16: =VLOOKUP($A16,[20]DETAILFICHECASSATION!$A$6:$R$36,12,0) -> 100000
A17: AS201617 | B17: =VLOOKUP(A17,[19]LISTADHERENT!A$5:H$60,3,0) -> KOUAMOU MOISE | C17: =VLOOKUP($A17,[23]FONDSCAISSE!$A$2:$G$33,4,0) -> 700000 | D17: =VLOOKUP($A17,[20]DETAILFICHECASSATION!$A$6:$R$36,17,0) -> 9267.5052 | F17: =C17+D17-E17 -> 709267.51 | G17: =IF(C17+D17+L17-E17>=700000,(C17+D17-E17),0) -> 709267.51 | H17: =($T$41/$G$41*G17) -> 38869.416 | I17: =(F17+H17) -> 748136.92 | J17: =VLOOKUP($A17,[22]HISTODEC23!$A$6:$AQ$40,22,0) -> 9000 | K17: =VLOOKUP($A17,[22]HISTODEC23!$A$6:$AU$36,45,0) -> 15000 | L17: =IF(K17=0,0,K17-(M17+N17+O17)) -> 9000 | M17: =IF(K17=0,0,1000) -> 1000 | N17: =IF(K17=0,0,1000) -> 1000 | O17: =IF(K17=0,0,4000) -> 4000 | P17: =VLOOKUP($A17,[22]HISTODEC23!$A$6:$AU$36,7,0) -> 0 | Q17: =VLOOKUP($A17,[22]HISTODEC23!$A$6:$AU$36,23,0) -> 0 | R17: =VLOOKUP($A17,[22]HISTODEC23!$A$6:$AU$36,46,0) -> 0 | S17: =VLOOKUP($A17,[22]HISTODEC23!$A$6:$AU$36,26,0) -> 0 | T17: =VLOOKUP($A17,[22]HISTODEC23!$A$6:$BG$36,58,0) -> 0 | U17: =VLOOKUP($A17,[22]HISTODEC23!$A$6:$AU$36,28,0) -> 0 | V17: =VLOOKUP($A17,[22]HISTODEC23!$A$6:$AU$36,19,0) -> 1000000 | W17: =VLOOKUP($A17,[22]HISTODEC23!$A$6:$AU$36,20,0) -> BANQUE | X17: =VLOOKUP($A17,[22]HISTODEC23!$A$6:$AU$36,27,0) -> 0 | Y17: =VLOOKUP($A17,[22]HISTODEC23!$A$6:$BM$36,33,0) -> 0 | Z17: =VLOOKUP($A17,[22]HISTODEC23!$A$6:$BM$36,65,0) -> 0 | AB17: =VLOOKUP($A17,[22]HISTODEC23!$A$6:$AU$36,43,0) -> 0 | AC17: =VLOOKUP($A17,[22]HISTODEC23!$A$6:$AU$36,44,0) -> 0 | AD17: =VLOOKUP($A17,[22]HISTODEC23!$A$6:$AU$36,47,0) -> 0 | AE17: =VLOOKUP(A17,[22]HISTODEC23!$A$6:$BB$36,54,0) -> 0 | AF17: =VLOOKUP($A17,[22]HISTODEC23!$A$6:$CA$36,60,0) -> 0 | AG17: =VLOOKUP($A17,[22]HISTODEC23!$A$6:$CA$36,61,0) -> 0 | AH17: =VLOOKUP($A17,[22]HISTODEC23!$A$6:$CA$36,62,0) -> 0 | AI17: =VLOOKUP($A17,[22]HISTODEC23!$A$6:$CA$36,63,0) -> 0 | AJ17: =VLOOKUP($A17,[22]HISTODEC23!$A$6:$CA$36,64,0) -> 0 | AK17: =VLOOKUP($A17,[22]HISTODEC23!$A$6:$CA$36,65,0) -> 0 | AL17: =VLOOKUP($A17,[20]DETAILFICHECASSATION!$A$6:$R$36,12,0) -> 100000
A18: AS201619 | B18: =VLOOKUP(A18,[19]LISTADHERENT!A$5:H$60,3,0) -> KOUATCHO MESSACK | C18: =VLOOKUP($A18,[23]FONDSCAISSE!$A$2:$G$33,4,0) -> 700000 | D18: =VLOOKUP($A18,[20]DETAILFICHECASSATION!$A$6:$R$36,17,0) -> 24428.628 | F18: =C18+D18-E18 -> 724428.63 | G18: =IF(C18+D18+L18-E18>=700000,(C18+D18-E18),0) -> 724428.63 | H18: =($T$41/$G$41*G18) -> 39700.279 | I18: =(F18+H18) -> 764128.91 | J18: =VLOOKUP($A18,[22]HISTODEC23!$A$6:$AQ$40,22,0) -> 3000 | K18: =VLOOKUP($A18,[22]HISTODEC23!$A$6:$AU$36,45,0) -> 15000 | L18: =IF(K18=0,0,K18-(M18+N18+O18)) -> 9000 | M18: =IF(K18=0,0,1000) -> 1000 | N18: =IF(K18=0,0,1000) -> 1000 | O18: =IF(K18=0,0,4000) -> 4000 | P18: =VLOOKUP($A18,[22]HISTODEC23!$A$6:$AU$36,7,0) -> 0 | Q18: =VLOOKUP($A18,[22]HISTODEC23!$A$6:$AU$36,23,0) -> 0 | R18: =VLOOKUP($A18,[22]HISTODEC23!$A$6:$AU$36,46,0) -> 0 | S18: =VLOOKUP($A18,[22]HISTODEC23!$A$6:$AU$36,26,0) -> 1000000 | T18: =VLOOKUP($A18,[22]HISTODEC23!$A$6:$BG$36,58,0) -> 50000 | U18: =VLOOKUP($A18,[22]HISTODEC23!$A$6:$AU$36,28,0) -> 0 | V18: =VLOOKUP($A18,[22]HISTODEC23!$A$6:$AU$36,19,0) -> 1000000 | W18: =VLOOKUP($A18,[22]HISTODEC23!$A$6:$AU$36,20,0) -> BANQUE | X18: =VLOOKUP($A18,[22]HISTODEC23!$A$6:$AU$36,27,0) -> BANQUE | Y18: =VLOOKUP($A18,[22]HISTODEC23!$A$6:$BM$36,33,0) -> 0 | Z18: =VLOOKUP($A18,[22]HISTODEC23!$A$6:$BM$36,65,0) -> 0 | AB18: =VLOOKUP($A18,[22]HISTODEC23!$A$6:$AU$36,43,0) -> 0 | AC18: =VLOOKUP($A18,[22]HISTODEC23!$A$6:$AU$36,44,0) -> 0 | AD18: =VLOOKUP($A18,[22]HISTODEC23!$A$6:$AU$36,47,0) -> 0 | AE18: =VLOOKUP(A18,[22]HISTODEC23!$A$6:$BB$36,54,0) -> 0 | AF18: =VLOOKUP($A18,[22]HISTODEC23!$A$6:$CA$36,60,0) -> 0 | AG18: =VLOOKUP($A18,[22]HISTODEC23!$A$6:$CA$36,61,0) -> 0 | AH18: =VLOOKUP($A18,[22]HISTODEC23!$A$6:$CA$36,62,0) -> 0 | AI18: =VLOOKUP($A18,[22]HISTODEC23!$A$6:$CA$36,63,0) -> 0 | AJ18: =VLOOKUP($A18,[22]HISTODEC23!$A$6:$CA$36,64,0) -> 0 | AK18: =VLOOKUP($A18,[22]HISTODEC23!$A$6:$CA$36,65,0) -> 0 | AL18: =VLOOKUP($A18,[20]DETAILFICHECASSATION!$A$6:$R$36,12,0) -> 100000
A19: AS201620 | B19: =VLOOKUP(A19,[19]LISTADHERENT!A$5:H$60,3,0) -> LOWE JEAN | C19: =VLOOKUP($A19,[23]FONDSCAISSE!$A$2:$G$33,4,0) -> 676217.13 | F19: =C19+D19-E19 -> 676217.13 | G19: =IF(C19+D19+L19-E19>=700000,(C19+D19-E19),0) -> 0 | H19: =($T$41/$G$41*G19) -> 0 | I19: =(F19+H19) -> 676217.13
A20: AS201661 | B20: =VLOOKUP(A20,[19]LISTADHERENT!A$5:H$60,3,0) -> MASSEUNGOUE DAGOBERT | F20: =C20+D20-E20 -> 0 | G20: =IF(C20+D20+L20-E20>=700000,(C20+D20-E20),0) -> 0 | H20: =($T$41/$G$41*G20) -> 0 | I20: =(F20+H20) -> 0
A21: AS201649 | B21: =VLOOKUP(A21,[19]LISTADHERENT!A$5:H$60,3,0) -> MBOGNING TUGMA GUY | C21: =VLOOKUP($A21,[23]FONDSCAISSE!$A$2:$G$33,4,0) -> 700000 | D21: =VLOOKUP($A21,[20]DETAILFICHECASSATION!$A$6:$R$36,17,0) -> 31709.397 | F21: =C21+D21-E21 -> 731709.4 | G21: =IF(C21+D21+L21-E21>=700000,(C21+D21-E21),0) -> 731709.4 | H21: =($T$41/$G$41*G21) -> 40099.281 | I21: =(F21+H21) -> 771808.68 | J21: =VLOOKUP($A21,[22]HISTODEC23!$A$6:$AQ$40,22,0) -> 0 | K21: =VLOOKUP($A21,[22]HISTODEC23!$A$6:$AU$36,45,0) -> 15000 | L21: =IF(K21=0,0,K21-(M21+N21+O21)) -> 9000 | M21: =IF(K21=0,0,1000) -> 1000 | N21: =IF(K21=0,0,1000) -> 1000 | O21: =IF(K21=0,0,4000) -> 4000 | P21: =VLOOKUP($A21,[22]HISTODEC23!$A$6:$AU$36,7,0) -> 0 | Q21: =VLOOKUP($A21,[22]HISTODEC23!$A$6:$AU$36,23,0) -> 0 | R21: =VLOOKUP($A21,[22]HISTODEC23!$A$6:$AU$36,46,0) -> 0 | S21: =VLOOKUP($A21,[22]HISTODEC23!$A$6:$AU$36,26,0) -> 1000000 | T21: =VLOOKUP($A21,[22]HISTODEC23!$A$6:$BG$36,58,0) -> 60000 | U21: =VLOOKUP($A21,[22]HISTODEC23!$A$6:$AU$36,28,0) -> 0 | V21: =VLOOKUP($A21,[22]HISTODEC23!$A$6:$AU$36,19,0) -> 1000000 | W21: =VLOOKUP($A21,[22]HISTODEC23!$A$6:$AU$36,20,0) -> BANQUE | X21: =VLOOKUP($A21,[22]HISTODEC23!$A$6:$AU$36,27,0) -> BANQUE | Y21: =VLOOKUP($A21,[22]HISTODEC23!$A$6:$BM$36,33,0) -> 0 | Z21: =VLOOKUP($A21,[22]HISTODEC23!$A$6:$BM$36,65,0) -> 0 | AB21: =VLOOKUP($A21,[22]HISTODEC23!$A$6:$AU$36,43,0) -> 0 | AC21: =VLOOKUP($A21,[22]HISTODEC23!$A$6:$AU$36,44,0) -> 0 | AD21: =VLOOKUP($A21,[22]HISTODEC23!$A$6:$AU$36,47,0) -> 0 | AE21: =VLOOKUP(A21,[22]HISTODEC23!$A$6:$BB$36,54,0) -> 0 | AF21: =VLOOKUP($A21,[22]HISTODEC23!$A$6:$CA$36,60,0) -> 0 | AG21: =VLOOKUP($A21,[22]HISTODEC23!$A$6:$CA$36,61,0) -> 0 | AH21: =VLOOKUP($A21,[22]HISTODEC23!$A$6:$CA$36,62,0) -> 0 | AI21: =VLOOKUP($A21,[22]HISTODEC23!$A$6:$CA$36,63,0) -> 0 | AJ21: =VLOOKUP($A21,[22]HISTODEC23!$A$6:$CA$36,64,0) -> 0 | AK21: =VLOOKUP($A21,[22]HISTODEC23!$A$6:$CA$36,65,0) -> 0 | AL21: =VLOOKUP($A21,[20]DETAILFICHECASSATION!$A$6:$R$36,12,0) -> 100000
A22: AS201639 | B22: =VLOOKUP(A22,[19]LISTADHERENT!A$5:H$60,3,0) -> NANGUEN MARTIN | C22: =VLOOKUP($A22,[23]FONDSCAISSE!$A$2:$G$33,4,0) -> 700000 | D22: =VLOOKUP($A22,[20]DETAILFICHECASSATION!$A$6:$R$36,17,0) -> 1150.3621 | F22: =C22+D22-E22 -> 701150.36 | G22: =IF(C22+D22+L22-E22>=700000,(C22+D22-E22),0) -> 701150.36 | H22: =($T$41/$G$41*G22) -> 38424.579 | I22: =(F22+H22) -> 739574.94 | J22: =VLOOKUP($A22,[22]HISTODEC23!$A$6:$AQ$40,22,0) -> 0 | K22: =VLOOKUP($A22,[22]HISTODEC23!$A$6:$AU$36,45,0) -> 15000 | L22: =IF(K22=0,0,K22-(M22+N22+O22)) -> 9000 | M22: =IF(K22=0,0,1000) -> 1000 | N22: =IF(K22=0,0,1000) -> 1000 | O22: =IF(K22=0,0,4000) -> 4000 | P22: =VLOOKUP($A22,[22]HISTODEC23!$A$6:$AU$36,7,0) -> 0 | Q22: =VLOOKUP($A22,[22]HISTODEC23!$A$6:$AU$36,23,0) -> 0 | R22: =VLOOKUP($A22,[22]HISTODEC23!$A$6:$AU$36,46,0) -> 0 | S22: =VLOOKUP($A22,[22]HISTODEC23!$A$6:$AU$36,26,0) -> 300000 | T22: =VLOOKUP($A22,[22]HISTODEC23!$A$6:$BG$36,58,0) -> 18000 | U22: =VLOOKUP($A22,[22]HISTODEC23!$A$6:$AU$36,28,0) -> 0 | V22: =VLOOKUP($A22,[22]HISTODEC23!$A$6:$AU$36,19,0) -> 500000 | W22: =VLOOKUP($A22,[22]HISTODEC23!$A$6:$AU$36,20,0) -> BANQUE | X22: =VLOOKUP($A22,[22]HISTODEC23!$A$6:$AU$36,27,0) -> BANQUE | Y22: =VLOOKUP($A22,[22]HISTODEC23!$A$6:$BM$36,33,0) -> 0 | Z22: =VLOOKUP($A22,[22]HISTODEC23!$A$6:$BM$36,65,0) -> 0 | AB22: =VLOOKUP($A22,[22]HISTODEC23!$A$6:$AU$36,43,0) -> 0 | AC22: =VLOOKUP($A22,[22]HISTODEC23!$A$6:$AU$36,44,0) -> 0 | AD22: =VLOOKUP($A22,[22]HISTODEC23!$A$6:$AU$36,47,0) -> 0 | AE22: =VLOOKUP(A22,[22]HISTODEC23!$A$6:$BB$36,54,0) -> 0 | AF22: =VLOOKUP($A22,[22]HISTODEC23!$A$6:$CA$36,60,0) -> 0 | AG22: =VLOOKUP($A22,[22]HISTODEC23!$A$6:$CA$36,61,0) -> 0 | AH22: =VLOOKUP($A22,[22]HISTODEC23!$A$6:$CA$36,62,0) -> 0 | AI22: =VLOOKUP($A22,[22]HISTODEC23!$A$6:$CA$36,63,0) -> 0 | AJ22: =VLOOKUP($A22,[22]HISTODEC23!$A$6:$CA$36,64,0) -> 0 | AK22: =VLOOKUP($A22,[22]HISTODEC23!$A$6:$CA$36,65,0) -> 0 | AL22: =VLOOKUP($A22,[20]DETAILFICHECASSATION!$A$6:$R$36,12,0) -> 100000
A23: AS201621 | B23: =VLOOKUP(A23,[19]LISTADHERENT!A$5:H$60,3,0) -> NANKAM APPOLINAIRE | C23: =VLOOKUP($A23,[23]FONDSCAISSE!$A$2:$G$33,4,0) -> 700000 | D23: =VLOOKUP($A23,[20]DETAILFICHECASSATION!$A$6:$R$36,17,0) -> 100402.23 | F23: =C23+D23-E23 -> 800402.23 | G23: =IF(C23+D23+L23-E23>=700000,(C23+D23-E23),0) -> 800402.23 | H23: =($T$41/$G$41*G23) -> 43863.799 | I23: =(F23+H23) -> 844266.03 | J23: =VLOOKUP($A23,[22]HISTODEC23!$A$6:$AQ$40,22,0) -> 20000 | K23: =VLOOKUP($A23,[22]HISTODEC23!$A$6:$AU$36,45,0) -> 15000 | L23: =IF(K23=0,0,K23-(M23+N23+O23)) -> 9000 | M23: =IF(K23=0,0,1000) -> 1000 | N23: =IF(K23=0,0,1000) -> 1000 | O23: =IF(K23=0,0,4000) -> 4000 | P23: =VLOOKUP($A23,[22]HISTODEC23!$A$6:$AU$36,7,0) -> 0 | Q23: =VLOOKUP($A23,[22]HISTODEC23!$A$6:$AU$36,23,0) -> 0 | R23: =VLOOKUP($A23,[22]HISTODEC23!$A$6:$AU$36,46,0) -> 0 | S23: =VLOOKUP($A23,[22]HISTODEC23!$A$6:$AU$36,26,0) -> 1000000 | T23: =VLOOKUP($A23,[22]HISTODEC23!$A$6:$BG$36,58,0) -> 120000 | U23: =VLOOKUP($A23,[22]HISTODEC23!$A$6:$AU$36,28,0) -> 0 | V23: =VLOOKUP($A23,[22]HISTODEC23!$A$6:$AU$36,19,0) -> 107500 | W23: =VLOOKUP($A23,[22]HISTODEC23!$A$6:$AU$36,20,0) -> BANQUE | X23: =VLOOKUP($A23,[22]HISTODEC23!$A$6:$AU$36,27,0) -> BANQUE | Y23: =VLOOKUP($A23,[22]HISTODEC23!$A$6:$BM$36,33,0) -> 0 | Z23: =VLOOKUP($A23,[22]HISTODEC23!$A$6:$BM$36,65,0) -> 0 | AB23: =VLOOKUP($A23,[22]HISTODEC23!$A$6:$AU$36,43,0) -> 0 | AC23: =VLOOKUP($A23,[22]HISTODEC23!$A$6:$AU$36,44,0) -> 0 | AD23: =VLOOKUP($A23,[22]HISTODEC23!$A$6:$AU$36,47,0) -> 0 | AE23: =VLOOKUP(A23,[22]HISTODEC23!$A$6:$BB$36,54,0) -> 0 | AF23: =VLOOKUP($A23,[22]HISTODEC23!$A$6:$CA$36,60,0) -> 0 | AG23: =VLOOKUP($A23,[22]HISTODEC23!$A$6:$CA$36,61,0) -> 0 | AH23: =VLOOKUP($A23,[22]HISTODEC23!$A$6:$CA$36,62,0) -> 0 | AI23: =VLOOKUP($A23,[22]HISTODEC23!$A$6:$CA$36,63,0) -> 0 | AJ23: =VLOOKUP($A23,[22]HISTODEC23!$A$6:$CA$36,64,0) -> 0 | AK23: =VLOOKUP($A23,[22]HISTODEC23!$A$6:$CA$36,65,0) -> 0 | AL23: =VLOOKUP($A23,[20]DETAILFICHECASSATION!$A$6:$R$36,12,0) -> 100000
A24: AS201622 | B24: =VLOOKUP(A24,[19]LISTADHERENT!A$5:H$60,3,0) -> NDJOMO ETIENNE | C24: =VLOOKUP($A24,[23]FONDSCAISSE!$A$2:$G$33,4,0) -> 700000 | D24: =VLOOKUP($A24,[20]DETAILFICHECASSATION!$A$6:$R$36,17,0) -> 224970.62 | F24: =C24+D24-E24 -> 924970.62 | G24: =IF(C24+D24+L24-E24>=700000,(C24+D24-E24),0) -> 924970.62 | H24: =($T$41/$G$41*G24) -> 50690.42 | I24: =(F24+H24) -> 975661.04 | J24: =VLOOKUP($A24,[22]HISTODEC23!$A$6:$AQ$40,22,0) -> 0 | K24: =VLOOKUP($A24,[22]HISTODEC23!$A$6:$AU$36,45,0) -> 25000 | L24: =IF(K24=0,0,K24-(M24+N24+O24)) -> 19000 | M24: =IF(K24=0,0,1000) -> 1000 | N24: =IF(K24=0,0,1000) -> 1000 | O24: =IF(K24=0,0,4000) -> 4000 | P24: =VLOOKUP($A24,[22]HISTODEC23!$A$6:$AU$36,7,0) -> 0 | Q24: =VLOOKUP($A24,[22]HISTODEC23!$A$6:$AU$36,23,0) -> 0 | R24: =VLOOKUP($A24,[22]HISTODEC23!$A$6:$AU$36,46,0) -> 0 | S24: =VLOOKUP($A24,[22]HISTODEC23!$A$6:$AU$36,26,0) -> 500000 | T24: =VLOOKUP($A24,[22]HISTODEC23!$A$6:$BG$36,58,0) -> 30000 | U24: =VLOOKUP($A24,[22]HISTODEC23!$A$6:$AU$36,28,0) -> 0 | V24: =VLOOKUP($A24,[22]HISTODEC23!$A$6:$AU$36,19,0) -> 600000 | W24: =VLOOKUP($A24,[22]HISTODEC23!$A$6:$AU$36,20,0) -> BANQUE | X24: =VLOOKUP($A24,[22]HISTODEC23!$A$6:$AU$36,27,0) -> BANQUE | Y24: =VLOOKUP($A24,[22]HISTODEC23!$A$6:$BM$36,33,0) -> 0 | Z24: =VLOOKUP($A24,[22]HISTODEC23!$A$6:$BM$36,65,0) -> 0 | AB24: =VLOOKUP($A24,[22]HISTODEC23!$A$6:$AU$36,43,0) -> 0 | AC24: =VLOOKUP($A24,[22]HISTODEC23!$A$6:$AU$36,44,0) -> 0 | AD24: =VLOOKUP($A24,[22]HISTODEC23!$A$6:$AU$36,47,0) -> 0 | AE24: =VLOOKUP(A24,[22]HISTODEC23!$A$6:$BB$36,54,0) -> 0 | AF24: =VLOOKUP($A24,[22]HISTODEC23!$A$6:$CA$36,60,0) -> 0 | AG24: =VLOOKUP($A24,[22]HISTODEC23!$A$6:$CA$36,61,0) -> 0 | AH24: =VLOOKUP($A24,[22]HISTODEC23!$A$6:$CA$36,62,0) -> 0 | AI24: =VLOOKUP($A24,[22]HISTODEC23!$A$6:$CA$36,63,0) -> 0 | AJ24: =VLOOKUP($A24,[22]HISTODEC23!$A$6:$CA$36,64,0) -> 0 | AK24: =VLOOKUP($A24,[22]HISTODEC23!$A$6:$CA$36,65,0) -> 0 | AL24: =VLOOKUP($A24,[20]DETAILFICHECASSATION!$A$6:$R$36,12,0) -> 100000
A25: AS201624 | B25: =VLOOKUP(A25,[19]LISTADHERENT!A$5:H$60,3,0) -> NGONDIEP CLAUDE | C25: =VLOOKUP($A25,[23]FONDSCAISSE!$A$2:$G$33,4,0) -> 700000 | D25: =VLOOKUP($A25,[20]DETAILFICHECASSATION!$A$6:$R$36,17,0) -> 57632.732 | F25: =C25+D25-E25 -> 757632.73 | G25: =IF(C25+D25+L25-E25>=700000,(C25+D25-E25),0) -> 757632.73 | H25: =($T$41/$G$41*G25) -> 41519.937 | I25: =(F25+H25) -> 799152.67 | J25: =VLOOKUP($A25,[22]HISTODEC23!$A$6:$AQ$40,22,0) -> 15000 | K25: =VLOOKUP($A25,[22]HISTODEC23!$A$6:$AU$36,45,0) -> 15000 | L25: =IF(K25=0,0,K25-(M25+N25+O25)) -> 9000 | M25: =IF(K25=0,0,1000) -> 1000 | N25: =IF(K25=0,0,1000) -> 1000 | O25: =IF(K25=0,0,4000) -> 4000 | P25: =VLOOKUP($A25,[22]HISTODEC23!$A$6:$AU$36,7,0) -> 0 | Q25: =VLOOKUP($A25,[22]HISTODEC23!$A$6:$AU$36,23,0) -> 0 | R25: =VLOOKUP($A25,[22]HISTODEC23!$A$6:$AU$36,46,0) -> 0 | S25: =VLOOKUP($A25,[22]HISTODEC23!$A$6:$AU$36,26,0) -> 1000000 | T25: =VLOOKUP($A25,[22]HISTODEC23!$A$6:$BG$36,58,0) -> 120000 | U25: =VLOOKUP($A25,[22]HISTODEC23!$A$6:$AU$36,28,0) -> 0 | V25: =VLOOKUP($A25,[22]HISTODEC23!$A$6:$AU$36,19,0) -> 1000000 | W25: =VLOOKUP($A25,[22]HISTODEC23!$A$6:$AU$36,20,0) -> BANQUE | X25: =VLOOKUP($A25,[22]HISTODEC23!$A$6:$AU$36,27,0) -> BANQUE | Y25: =VLOOKUP($A25,[22]HISTODEC23!$A$6:$BM$36,33,0) -> 0 | Z25: =VLOOKUP($A25,[22]HISTODEC23!$A$6:$BM$36,65,0) -> 0 | AB25: =VLOOKUP($A25,[22]HISTODEC23!$A$6:$AU$36,43,0) -> 0 | AC25: =VLOOKUP($A25,[22]HISTODEC23!$A$6:$AU$36,44,0) -> 0 | AD25: =VLOOKUP($A25,[22]HISTODEC23!$A$6:$AU$36,47,0) -> 0 | AE25: =VLOOKUP(A25,[22]HISTODEC23!$A$6:$BB$36,54,0) -> 0 | AF25: =VLOOKUP($A25,[22]HISTODEC23!$A$6:$CA$36,60,0) -> 0 | AG25: =VLOOKUP($A25,[22]HISTODEC23!$A$6:$CA$36,61,0) -> 0 | AH25: =VLOOKUP($A25,[22]HISTODEC23!$A$6:$CA$36,62,0) -> 0 | AI25: =VLOOKUP($A25,[22]HISTODEC23!$A$6:$CA$36,63,0) -> 0 | AJ25: =VLOOKUP($A25,[22]HISTODEC23!$A$6:$CA$36,64,0) -> 0 | AK25: =VLOOKUP($A25,[22]HISTODEC23!$A$6:$CA$36,65,0) -> 0 | AL25: =VLOOKUP($A25,[20]DETAILFICHECASSATION!$A$6:$R$36,12,0) -> 100000
A26: AS201626 | B26: =VLOOKUP(A26,[19]LISTADHERENT!A$5:H$60,3,0) -> NGUIEMEGNI MATHIEU BLAISE | C26: =VLOOKUP($A26,[23]FONDSCAISSE!$A$2:$G$33,4,0) -> 700000 | D26: =VLOOKUP($A26,[20]DETAILFICHECASSATION!$A$6:$R$36,17,0) -> 20382.784 | F26: =C26+D26-E26 -> 720382.78 | G26: =IF(C26+D26+L26-E26>=700000,(C26+D26-E26),0) -> 720382.78 | H26: =($T$41/$G$41*G26) -> 39478.558 | I26: =(F26+H26) -> 759861.34 | J26: =VLOOKUP($A26,[22]HISTODEC23!$A$6:$AQ$40,22,0) -> 15000 | K26: =VLOOKUP($A26,[22]HISTODEC23!$A$6:$AU$36,45,0) -> 123000 | L26: =IF(K26=0,0,K26-(M26+N26+O26)) -> 117000 | M26: =IF(K26=0,0,1000) -> 1000 | N26: =IF(K26=0,0,1000) -> 1000 | O26: =IF(K26=0,0,4000) -> 4000 | P26: =VLOOKUP($A26,[22]HISTODEC23!$A$6:$AU$36,7,0) -> 0 | Q26: =VLOOKUP($A26,[22]HISTODEC23!$A$6:$AU$36,23,0) -> 0 | R26: =VLOOKUP($A26,[22]HISTODEC23!$A$6:$AU$36,46,0) -> 0 | S26: =VLOOKUP($A26,[22]HISTODEC23!$A$6:$AU$36,26,0) -> 1000000 | T26: =VLOOKUP($A26,[22]HISTODEC23!$A$6:$BG$36,58,0) -> 120000 | U26: =VLOOKUP($A26,[22]HISTODEC23!$A$6:$AU$36,28,0) -> 0 | V26: =VLOOKUP($A26,[22]HISTODEC23!$A$6:$AU$36,19,0) -> 1000000 | W26: =VLOOKUP($A26,[22]HISTODEC23!$A$6:$AU$36,20,0) -> BANQUE | X26: =VLOOKUP($A26,[22]HISTODEC23!$A$6:$AU$36,27,0) -> BANQUE | Y26: =VLOOKUP($A26,[22]HISTODEC23!$A$6:$BM$36,33,0) -> 0 | Z26: =VLOOKUP($A26,[22]HISTODEC23!$A$6:$BM$36,65,0) -> 0 | AB26: =VLOOKUP($A26,[22]HISTODEC23!$A$6:$AU$36,43,0) -> 0 | AC26: =VLOOKUP($A26,[22]HISTODEC23!$A$6:$AU$36,44,0) -> 0 | AD26: =VLOOKUP($A26,[22]HISTODEC23!$A$6:$AU$36,47,0) -> 0 | AE26: =VLOOKUP(A26,[22]HISTODEC23!$A$6:$BB$36,54,0) -> 0 | AF26: =VLOOKUP($A26,[22]HISTODEC23!$A$6:$CA$36,60,0) -> 0 | AG26: =VLOOKUP($A26,[22]HISTODEC23!$A$6:$CA$36,61,0) -> 0 | AH26: =VLOOKUP($A26,[22]HISTODEC23!$A$6:$CA$36,62,0) -> 0 | AI26: =VLOOKUP($A26,[22]HISTODEC23!$A$6:$CA$36,63,0) -> 0 | AJ26: =VLOOKUP($A26,[22]HISTODEC23!$A$6:$CA$36,64,0) -> 0 | AK26: =VLOOKUP($A26,[22]HISTODEC23!$A$6:$CA$36,65,0) -> 0 | AL26: =VLOOKUP($A26,[20]DETAILFICHECASSATION!$A$6:$R$36,12,0) -> 100000
A27: AS201628 | B27: =VLOOKUP(A27,[19]LISTADHERENT!A$5:H$60,3,0) -> NKAMGANG JUSTIN DEJOLIE | C27: =VLOOKUP($A27,[23]FONDSCAISSE!$A$2:$G$33,4,0) -> 700000 | D27: =VLOOKUP($A27,[20]DETAILFICHECASSATION!$A$6:$R$36,17,0) -> 19031.485 | F27: =C27+D27-E27 -> 719031.48 | G27: =IF(C27+D27+L27-E27>=700000,(C27+D27-E27),0) -> 719031.48 | H27: =($T$41/$G$41*G27) -> 39404.504 | I27: =(F27+H27) -> 758435.99 | J27: =VLOOKUP($A27,[22]HISTODEC23!$A$6:$AQ$40,22,0) -> 0 | K27: =VLOOKUP($A27,[22]HISTODEC23!$A$6:$AU$36,45,0) -> 15000 | L27: =IF(K27=0,0,K27-(M27+N27+O27)) -> 9000 | M27: =IF(K27=0,0,1000) -> 1000 | N27: =IF(K27=0,0,1000) -> 1000 | O27: =IF(K27=0,0,4000) -> 4000 | P27: =VLOOKUP($A27,[22]HISTODEC23!$A$6:$AU$36,7,0) -> 0 | Q27: =VLOOKUP($A27,[22]HISTODEC23!$A$6:$AU$36,23,0) -> 0 | R27: =VLOOKUP($A27,[22]HISTODEC23!$A$6:$AU$36,46,0) -> 0 | S27: =VLOOKUP($A27,[22]HISTODEC23!$A$6:$AU$36,26,0) -> 1000000 | T27: =VLOOKUP($A27,[22]HISTODEC23!$A$6:$BG$36,58,0) -> 30000 | U27: =VLOOKUP($A27,[22]HISTODEC23!$A$6:$AU$36,28,0) -> 0 | V27: =VLOOKUP($A27,[22]HISTODEC23!$A$6:$AU$36,19,0) -> 1000000 | W27: =VLOOKUP($A27,[22]HISTODEC23!$A$6:$AU$36,20,0) -> BANQUE | X27: =VLOOKUP($A27,[22]HISTODEC23!$A$6:$AU$36,27,0) -> BANQUE | Y27: =VLOOKUP($A27,[22]HISTODEC23!$A$6:$BM$36,33,0) -> 0 | Z27: =VLOOKUP($A27,[22]HISTODEC23!$A$6:$BM$36,65,0) -> 0 | AB27: =VLOOKUP($A27,[22]HISTODEC23!$A$6:$AU$36,43,0) -> 0 | AC27: =VLOOKUP($A27,[22]HISTODEC23!$A$6:$AU$36,44,0) -> 0 | AD27: =VLOOKUP($A27,[22]HISTODEC23!$A$6:$AU$36,47,0) -> 0 | AE27: =VLOOKUP(A27,[22]HISTODEC23!$A$6:$BB$36,54,0) -> 0 | AF27: =VLOOKUP($A27,[22]HISTODEC23!$A$6:$CA$36,60,0) -> 0 | AG27: =VLOOKUP($A27,[22]HISTODEC23!$A$6:$CA$36,61,0) -> 0 | AH27: =VLOOKUP($A27,[22]HISTODEC23!$A$6:$CA$36,62,0) -> 0 | AI27: =VLOOKUP($A27,[22]HISTODEC23!$A$6:$CA$36,63,0) -> 0 | AJ27: =VLOOKUP($A27,[22]HISTODEC23!$A$6:$CA$36,64,0) -> 0 | AK27: =VLOOKUP($A27,[22]HISTODEC23!$A$6:$CA$36,65,0) -> 0 | AL27: =VLOOKUP($A27,[20]DETAILFICHECASSATION!$A$6:$R$36,12,0) -> 100000
A28: AS201656 | B28: =VLOOKUP(A28,[19]LISTADHERENT!A$5:H$60,3,0) -> NOUBE ETIENNE | C28: =VLOOKUP($A28,[23]FONDSCAISSE!$A$2:$G$33,4,0) -> 666018.82 | D28: =VLOOKUP($A28,[20]DETAILFICHECASSATION!$A$6:$R$36,17,0) -> 0 | F28: =C28+D28-E28 -> 666018.82 | G28: =IF(C28+D28+L28-E28>=700000,(C28+D28-E28),0) -> 0 | H28: =($T$41/$G$41*G28) -> 0 | I28: =(F28+H28) -> 666018.82 | J28: =VLOOKUP($A28,[22]HISTODEC23!$A$6:$AQ$40,22,0) -> 0 | K28: =VLOOKUP($A28,[22]HISTODEC23!$A$6:$AU$36,45,0) -> 25000 | L28: =IF(K28=0,0,K28-(M28+N28+O28)) -> 19000 | M28: =IF(K28=0,0,1000) -> 1000 | N28: =IF(K28=0,0,1000) -> 1000 | O28: =IF(K28=0,0,4000) -> 4000 | P28: =VLOOKUP($A28,[22]HISTODEC23!$A$6:$AU$36,7,0) -> 0 | Q28: =VLOOKUP($A28,[22]HISTODEC23!$A$6:$AU$36,23,0) -> 0 | R28: =VLOOKUP($A28,[22]HISTODEC23!$A$6:$AU$36,46,0) -> 0 | S28: =VLOOKUP($A28,[22]HISTODEC23!$A$6:$AU$36,26,0) -> 0 | T28: =VLOOKUP($A28,[22]HISTODEC23!$A$6:$BG$36,58,0) -> 0 | U28: =VLOOKUP($A28,[22]HISTODEC23!$A$6:$AU$36,28,0) -> 0 | V28: =VLOOKUP($A28,[22]HISTODEC23!$A$6:$AU$36,19,0) -> 0 | W28: =VLOOKUP($A28,[22]HISTODEC23!$A$6:$AU$36,20,0) -> 0 | X28: =VLOOKUP($A28,[22]HISTODEC23!$A$6:$AU$36,27,0) -> 0 | Y28: =VLOOKUP($A28,[22]HISTODEC23!$A$6:$BM$36,33,0) -> 0 | Z28: =VLOOKUP($A28,[22]HISTODEC23!$A$6:$BM$36,65,0) -> 0 | AB28: =VLOOKUP($A28,[22]HISTODEC23!$A$6:$AU$36,43,0) -> 0 | AC28: =VLOOKUP($A28,[22]HISTODEC23!$A$6:$AU$36,44,0) -> 0 | AD28: =VLOOKUP($A28,[22]HISTODEC23!$A$6:$AU$36,47,0) -> 0 | AE28: =VLOOKUP(A28,[22]HISTODEC23!$A$6:$BB$36,54,0) -> 0 | AF28: =VLOOKUP($A28,[22]HISTODEC23!$A$6:$CA$36,60,0) -> 0 | AG28: =VLOOKUP($A28,[22]HISTODEC23!$A$6:$CA$36,61,0) -> 0 | AH28: =VLOOKUP($A28,[22]HISTODEC23!$A$6:$CA$36,62,0) -> 0 | AI28: =VLOOKUP($A28,[22]HISTODEC23!$A$6:$CA$36,63,0) -> 0 | AJ28: =VLOOKUP($A28,[22]HISTODEC23!$A$6:$CA$36,64,0) -> 0 | AK28: =VLOOKUP($A28,[22]HISTODEC23!$A$6:$CA$36,65,0) -> 0 | AL28: =VLOOKUP($A28,[20]DETAILFICHECASSATION!$A$6:$R$36,12,0) -> 700000
A29: AS201633 | B29: =VLOOKUP(A29,[19]LISTADHERENT!A$5:H$60,3,0) -> PATEGO NJOSSU GUSTAVE | C29: =VLOOKUP($A29,[23]FONDSCAISSE!$A$2:$G$33,4,0) -> 700000 | D29: =VLOOKUP($A29,[20]DETAILFICHECASSATION!$A$6:$R$36,17,0) -> 43697.666 | F29: =C29+D29-E29 -> 743697.67 | G29: =IF(C29+D29+L29-E29>=700000,(C29+D29-E29),0) -> 743697.67 | H29: =($T$41/$G$41*G29) -> 40756.265 | I29: =(F29+H29) -> 784453.93 | J29: =VLOOKUP($A29,[22]HISTODEC23!$A$6:$AQ$40,22,0) -> 0 | K29: =VLOOKUP($A29,[22]HISTODEC23!$A$6:$AU$36,45,0) -> 15000 | L29: =IF(K29=0,0,K29-(M29+N29+O29)) -> 9000 | M29: =IF(K29=0,0,1000) -> 1000 | N29: =IF(K29=0,0,1000) -> 1000 | O29: =IF(K29=0,0,4000) -> 4000 | P29: =VLOOKUP($A29,[22]HISTODEC23!$A$6:$AU$36,7,0) -> 0 | Q29: =VLOOKUP($A29,[22]HISTODEC23!$A$6:$AU$36,23,0) -> 0 | R29: =VLOOKUP($A29,[22]HISTODEC23!$A$6:$AU$36,46,0) -> 0 | S29: =VLOOKUP($A29,[22]HISTODEC23!$A$6:$AU$36,26,0) -> 0 | T29: =VLOOKUP($A29,[22]HISTODEC23!$A$6:$BG$36,58,0) -> 0 | U29: =VLOOKUP($A29,[22]HISTODEC23!$A$6:$AU$36,28,0) -> 0 | V29: =VLOOKUP($A29,[22]HISTODEC23!$A$6:$AU$36,19,0) -> 0 | W29: =VLOOKUP($A29,[22]HISTODEC23!$A$6:$AU$36,20,0) -> 0 | X29: =VLOOKUP($A29,[22]HISTODEC23!$A$6:$AU$36,27,0) -> 0 | Y29: =VLOOKUP($A29,[22]HISTODEC23!$A$6:$BM$36,33,0) -> 0 | Z29: =VLOOKUP($A29,[22]HISTODEC23!$A$6:$BM$36,65,0) -> 0 | AB29: =VLOOKUP($A29,[22]HISTODEC23!$A$6:$AU$36,43,0) -> 0 | AC29: =VLOOKUP($A29,[22]HISTODEC23!$A$6:$AU$36,44,0) -> 0 | AD29: =VLOOKUP($A29,[22]HISTODEC23!$A$6:$AU$36,47,0) -> 0 | AE29: =VLOOKUP(A29,[22]HISTODEC23!$A$6:$BB$36,54,0) -> 0 | AF29: =VLOOKUP($A29,[22]HISTODEC23!$A$6:$CA$36,60,0) -> 0 | AG29: =VLOOKUP($A29,[22]HISTODEC23!$A$6:$CA$36,61,0) -> 0 | AH29: =VLOOKUP($A29,[22]HISTODEC23!$A$6:$CA$36,62,0) -> 0 | AI29: =VLOOKUP($A29,[22]HISTODEC23!$A$6:$CA$36,63,0) -> 0 | AJ29: =VLOOKUP($A29,[22]HISTODEC23!$A$6:$CA$36,64,0) -> 0 | AK29: =VLOOKUP($A29,[22]HISTODEC23!$A$6:$CA$36,65,0) -> 0 | AL29: =VLOOKUP($A29,[20]DETAILFICHECASSATION!$A$6:$R$36,12,0) -> 100000
A30: AS201657 | B30: =VLOOKUP(A30,[19]LISTADHERENT!A$5:H$60,3,0) -> SEUMO POLYCARPE | C30: =VLOOKUP($A30,[23]FONDSCAISSE!$A$2:$G$33,4,0) -> 0 | D30: =VLOOKUP($A30,[20]DETAILFICHECASSATION!$A$6:$R$36,17,0) -> 245500 | F30: =C30+D30-E30 -> 245500 | G30: =IF(C30+D30+L30-E30>=700000,(C30+D30-E30),0) -> 0 | H30: =($T$41/$G$41*G30) -> 0 | I30: =(F30+H30) -> 245500 | J30: =VLOOKUP($A30,[22]HISTODEC23!$A$6:$AQ$40,22,0) -> 0 | K30: =VLOOKUP($A30,[22]HISTODEC23!$A$6:$AU$36,45,0) -> 15000 | L30: =IF(K30=0,0,K30-(M30+N30+O30)) -> 9000 | M30: =IF(K30=0,0,1000) -> 1000 | N30: =IF(K30=0,0,1000) -> 1000 | O30: =IF(K30=0,0,4000) -> 4000 | P30: =VLOOKUP($A30,[22]HISTODEC23!$A$6:$AU$36,7,0) -> 0 | Q30: =VLOOKUP($A30,[22]HISTODEC23!$A$6:$AU$36,23,0) -> 0 | R30: =VLOOKUP($A30,[22]HISTODEC23!$A$6:$AU$36,46,0) -> 0 | S30: =VLOOKUP($A30,[22]HISTODEC23!$A$6:$AU$36,26,0) -> 0 | T30: =VLOOKUP($A30,[22]HISTODEC23!$A$6:$BG$36,58,0) -> 0 | U30: =VLOOKUP($A30,[22]HISTODEC23!$A$6:$AU$36,28,0) -> 0 | V30: =VLOOKUP($A30,[22]HISTODEC23!$A$6:$AU$36,19,0) -> 0 | W30: =VLOOKUP($A30,[22]HISTODEC23!$A$6:$AU$36,20,0) -> 0 | X30: =VLOOKUP($A30,[22]HISTODEC23!$A$6:$AU$36,27,0) -> 0 | Y30: =VLOOKUP($A30,[22]HISTODEC23!$A$6:$BM$36,33,0) -> 0 | Z30: =VLOOKUP($A30,[22]HISTODEC23!$A$6:$BM$36,65,0) -> 0 | AB30: =VLOOKUP($A30,[22]HISTODEC23!$A$6:$AU$36,43,0) -> 0 | AC30: =VLOOKUP($A30,[22]HISTODEC23!$A$6:$AU$36,44,0) -> 0 | AD30: =VLOOKUP($A30,[22]HISTODEC23!$A$6:$AU$36,47,0) -> 0 | AE30: =VLOOKUP(A30,[22]HISTODEC23!$A$6:$BB$36,54,0) -> 0 | AF30: =VLOOKUP($A30,[22]HISTODEC23!$A$6:$CA$36,60,0) -> 0 | AG30: =VLOOKUP($A30,[22]HISTODEC23!$A$6:$CA$36,61,0) -> 0 | AH30: =VLOOKUP($A30,[22]HISTODEC23!$A$6:$CA$36,62,0) -> 0 | AI30: =VLOOKUP($A30,[22]HISTODEC23!$A$6:$CA$36,63,0) -> 0 | AJ30: =VLOOKUP($A30,[22]HISTODEC23!$A$6:$CA$36,64,0) -> 0 | AK30: =VLOOKUP($A30,[22]HISTODEC23!$A$6:$CA$36,65,0) -> 0 | AL30: =VLOOKUP($A30,[20]DETAILFICHECASSATION!$A$6:$R$36,12,0) -> 0
A31: AS201653 | B31: =VLOOKUP(A31,[19]LISTADHERENT!A$5:H$60,3,0) -> SIME BRICE | C31: =VLOOKUP($A31,[23]FONDSCAISSE!$A$2:$G$33,4,0) -> 700000 | D31: =VLOOKUP($A31,[20]DETAILFICHECASSATION!$A$6:$R$36,17,0) -> 104364.15 | F31: =C31+D31-E31 -> 804364.15 | G31: =IF(C31+D31+L31-E31>=700000,(C31+D31-E31),0) -> 804364.15 | H31: =($T$41/$G$41*G31) -> 44080.921 | I31: =(F31+H31) -> 848445.07 | J31: =VLOOKUP($A31,[22]HISTODEC23!$A$6:$AQ$40,22,0) -> 34000 | K31: =VLOOKUP($A31,[22]HISTODEC23!$A$6:$AU$36,45,0) -> 15000 | L31: =IF(K31=0,0,K31-(M31+N31+O31)) -> 9000 | M31: =IF(K31=0,0,1000) -> 1000 | N31: =IF(K31=0,0,1000) -> 1000 | O31: =IF(K31=0,0,4000) -> 4000 | P31: =VLOOKUP($A31,[22]HISTODEC23!$A$6:$AU$36,7,0) -> 0 | Q31: =VLOOKUP($A31,[22]HISTODEC23!$A$6:$AU$36,23,0) -> 0 | R31: =VLOOKUP($A31,[22]HISTODEC23!$A$6:$AU$36,46,0) -> 0 | S31: =VLOOKUP($A31,[22]HISTODEC23!$A$6:$AU$36,26,0) -> 1000000 | T31: =VLOOKUP($A31,[22]HISTODEC23!$A$6:$BG$36,58,0) -> 60000 | U31: =VLOOKUP($A31,[22]HISTODEC23!$A$6:$AU$36,28,0) -> 0 | V31: =VLOOKUP($A31,[22]HISTODEC23!$A$6:$AU$36,19,0) -> 0 | W31: =VLOOKUP($A31,[22]HISTODEC23!$A$6:$AU$36,20,0) -> 0 | X31: =VLOOKUP($A31,[22]HISTODEC23!$A$6:$AU$36,27,0) -> BANQUE | Y31: =VLOOKUP($A31,[22]HISTODEC23!$A$6:$BM$36,33,0) -> 0 | Z31: =VLOOKUP($A31,[22]HISTODEC23!$A$6:$BM$36,65,0) -> 0 | AB31: =VLOOKUP($A31,[22]HISTODEC23!$A$6:$AU$36,43,0) -> 0 | AC31: =VLOOKUP($A31,[22]HISTODEC23!$A$6:$AU$36,44,0) -> 0 | AD31: =VLOOKUP($A31,[22]HISTODEC23!$A$6:$AU$36,47,0) -> 0 | AE31: =VLOOKUP(A31,[22]HISTODEC23!$A$6:$BB$36,54,0) -> 0 | AF31: =VLOOKUP($A31,[22]HISTODEC23!$A$6:$CA$36,60,0) -> 0 | AG31: =VLOOKUP($A31,[22]HISTODEC23!$A$6:$CA$36,61,0) -> 0 | AH31: =VLOOKUP($A31,[22]HISTODEC23!$A$6:$CA$36,62,0) -> 0 | AI31: =VLOOKUP($A31,[22]HISTODEC23!$A$6:$CA$36,63,0) -> 0 | AJ31: =VLOOKUP($A31,[22]HISTODEC23!$A$6:$CA$36,64,0) -> 0 | AK31: =VLOOKUP($A31,[22]HISTODEC23!$A$6:$CA$36,65,0) -> 0 | AL31: =VLOOKUP($A31,[20]DETAILFICHECASSATION!$A$6:$R$36,12,0) -> 100000
A32: AS201638 | B32: =VLOOKUP(A32,[19]LISTADHERENT!A$5:H$60,3,0) -> SIMO PIERRE | C32: =VLOOKUP($A32,[23]FONDSCAISSE!$A$2:$G$33,4,0) -> 700000 | D32: =VLOOKUP($A32,[20]DETAILFICHECASSATION!$A$6:$R$36,17,0) -> 686.61218 | F32: =C32+D32-E32 -> 700686.61 | G32: =IF(C32+D32+L32-E32>=700000,(C32+D32-E32),0) -> 700686.61 | H32: =($T$41/$G$41*G32) -> 38399.164 | I32: =(F32+H32) -> 739085.78 | J32: =VLOOKUP($A32,[22]HISTODEC23!$A$6:$AQ$40,22,0) -> 0 | K32: =VLOOKUP($A32,[22]HISTODEC23!$A$6:$AU$36,45,0) -> 15000 | L32: =IF(K32=0,0,K32-(M32+N32+O32)) -> 9000 | M32: =IF(K32=0,0,1000) -> 1000 | N32: =IF(K32=0,0,1000) -> 1000 | O32: =IF(K32=0,0,4000) -> 4000 | P32: =VLOOKUP($A32,[22]HISTODEC23!$A$6:$AU$36,7,0) -> 0 | Q32: =VLOOKUP($A32,[22]HISTODEC23!$A$6:$AU$36,23,0) -> 0 | R32: =VLOOKUP($A32,[22]HISTODEC23!$A$6:$AU$36,46,0) -> 0 | S32: =VLOOKUP($A32,[22]HISTODEC23!$A$6:$AU$36,26,0) -> 250000 | T32: =VLOOKUP($A32,[22]HISTODEC23!$A$6:$BG$36,58,0) -> 15000 | U32: =VLOOKUP($A32,[22]HISTODEC23!$A$6:$AU$36,28,0) -> 0 | V32: =VLOOKUP($A32,[22]HISTODEC23!$A$6:$AU$36,19,0) -> 1000000 | W32: =VLOOKUP($A32,[22]HISTODEC23!$A$6:$AU$36,20,0) -> BANQUE | X32: =VLOOKUP($A32,[22]HISTODEC23!$A$6:$AU$36,27,0) -> BANQUE | Y32: =VLOOKUP($A32,[22]HISTODEC23!$A$6:$BM$36,33,0) -> 0 | Z32: =VLOOKUP($A32,[22]HISTODEC23!$A$6:$BM$36,65,0) -> 0 | AB32: =VLOOKUP($A32,[22]HISTODEC23!$A$6:$AU$36,43,0) -> 0 | AC32: =VLOOKUP($A32,[22]HISTODEC23!$A$6:$AU$36,44,0) -> 0 | AD32: =VLOOKUP($A32,[22]HISTODEC23!$A$6:$AU$36,47,0) -> 0 | AE32: =VLOOKUP(A32,[22]HISTODEC23!$A$6:$BB$36,54,0) -> 0 | AF32: =VLOOKUP($A32,[22]HISTODEC23!$A$6:$CA$36,60,0) -> 0 | AG32: =VLOOKUP($A32,[22]HISTODEC23!$A$6:$CA$36,61,0) -> 0 | AH32: =VLOOKUP($A32,[22]HISTODEC23!$A$6:$CA$36,62,0) -> 0 | AI32: =VLOOKUP($A32,[22]HISTODEC23!$A$6:$CA$36,63,0) -> 0 | AJ32: =VLOOKUP($A32,[22]HISTODEC23!$A$6:$CA$36,64,0) -> 0 | AK32: =VLOOKUP($A32,[22]HISTODEC23!$A$6:$CA$36,65,0) -> 0 | AL32: =VLOOKUP($A32,[20]DETAILFICHECASSATION!$A$6:$R$36,12,0) -> 100000
A33: AS201641 | B33: =VLOOKUP(A33,[19]LISTADHERENT!A$5:H$60,3,0) -> TCHOUAMOU MATHIEU | C33: =VLOOKUP($A33,[23]FONDSCAISSE!$A$2:$G$33,4,0) -> 700000 | D33: =VLOOKUP($A33,[20]DETAILFICHECASSATION!$A$6:$R$36,17,0) -> 975.80621 | F33: =C33+D33-E33 -> 700975.81 | G33: =IF(C33+D33+L33-E33>=700000,(C33+D33-E33),0) -> 700975.81 | H33: =($T$41/$G$41*G33) -> 38415.013 | I33: =(F33+H33) -> 739390.82 | J33: =VLOOKUP($A33,[22]HISTODEC23!$A$6:$AQ$40,22,0) -> 0 | K33: =VLOOKUP($A33,[22]HISTODEC23!$A$6:$AU$36,45,0) -> 15000 | L33: =18000+10000 -> 28000 | M33: =IF(K33=0,0,1000)+1000 -> 2000 | N33: =IF(K33=0,0,1000)+1000 -> 2000 | O33: =IF(K33=0,0,4000)+4000 -> 8000 | P33: =VLOOKUP($A33,[22]HISTODEC23!$A$6:$AU$36,7,0) -> 0 | Q33: =VLOOKUP($A33,[22]HISTODEC23!$A$6:$AU$36,23,0) -> 0 | R33: =VLOOKUP($A33,[22]HISTODEC23!$A$6:$AU$36,46,0) -> 0 | S33: =VLOOKUP($A33,[22]HISTODEC23!$A$6:$AU$36,26,0) -> 0 | T33: =VLOOKUP($A33,[22]HISTODEC23!$A$6:$BG$36,58,0) -> 0 | U33: =VLOOKUP($A33,[22]HISTODEC23!$A$6:$AU$36,28,0) -> 0 | V33: =VLOOKUP($A33,[22]HISTODEC23!$A$6:$AU$36,19,0) -> 200000 | W33: =VLOOKUP($A33,[22]HISTODEC23!$A$6:$AU$36,20,0) -> BANQUE | X33: =VLOOKUP($A33,[22]HISTODEC23!$A$6:$AU$36,27,0) -> 0 | Y33: =VLOOKUP($A33,[22]HISTODEC23!$A$6:$BM$36,33,0) -> 0 | Z33: =VLOOKUP($A33,[22]HISTODEC23!$A$6:$BM$36,65,0) -> 0 | AB33: =VLOOKUP($A33,[22]HISTODEC23!$A$6:$AU$36,43,0) -> 0 | AC33: =VLOOKUP($A33,[22]HISTODEC23!$A$6:$AU$36,44,0) -> 0 | AD33: =VLOOKUP($A33,[22]HISTODEC23!$A$6:$AU$36,47,0) -> 0 | AE33: =VLOOKUP(A33,[22]HISTODEC23!$A$6:$BB$36,54,0) -> 0 | AF33: =VLOOKUP($A33,[22]HISTODEC23!$A$6:$CA$36,60,0) -> 0 | AG33: =VLOOKUP($A33,[22]HISTODEC23!$A$6:$CA$36,61,0) -> 0 | AH33: =VLOOKUP($A33,[22]HISTODEC23!$A$6:$CA$36,62,0) -> 0 | AI33: =VLOOKUP($A33,[22]HISTODEC23!$A$6:$CA$36,63,0) -> 0 | AJ33: =VLOOKUP($A33,[22]HISTODEC23!$A$6:$CA$36,64,0) -> 0 | AK33: =VLOOKUP($A33,[22]HISTODEC23!$A$6:$CA$36,65,0) -> 0 | AL33: =VLOOKUP($A33,[20]DETAILFICHECASSATION!$A$6:$R$36,12,0) -> 100000
A34: AS201660 | B34: =VLOOKUP(A34,[19]LISTADHERENT!A$5:H$60,3,0) -> TCHOUATEU AUGUSTIN | C34: =VLOOKUP($A34,[23]FONDSCAISSE!$A$2:$G$33,4,0) -> 0 | F34: =C34+D34-E34 -> 0 | G34: =IF(C34+D34+L34-E34>=700000,(C34+D34-E34),0) -> 0 | H34: =($T$41/$G$41*G34) -> 0 | I34: =(F34+H34) -> 0
A35: AS201643 | B35: =VLOOKUP(A35,[19]LISTADHERENT!A$5:H$60,3,0) -> TCHOUTOU NANA CLAUDE | C35: =VLOOKUP($A35,[23]FONDSCAISSE!$A$2:$G$33,4,0) -> 0 | D35: =VLOOKUP($A35,[20]DETAILFICHECASSATION!$A$6:$R$36,17,0) -> 103000 | F35: =C35+D35-E35 -> 103000 | G35: =IF(C35+D35+L35-E35>=700000,(C35+D35-E35),0) -> 0 | H35: =($T$41/$G$41*G35) -> 0 | I35: =(F35+H35) -> 103000 | J35: =VLOOKUP($A35,[22]HISTODEC23!$A$6:$AQ$40,22,0) -> 0 | K35: =VLOOKUP($A35,[22]HISTODEC23!$A$6:$AU$36,45,0) -> 25000 | L35: =IF(K35=0,0,K35-(M35+N35+O35)) -> 19000 | M35: =IF(K35=0,0,1000) -> 1000 | N35: =IF(K35=0,0,1000) -> 1000 | O35: =IF(K35=0,0,4000) -> 4000 | P35: =VLOOKUP($A35,[22]HISTODEC23!$A$6:$AU$36,7,0) -> 0 | Q35: =VLOOKUP($A35,[22]HISTODEC23!$A$6:$AU$36,23,0) -> 0 | R35: =VLOOKUP($A35,[22]HISTODEC23!$A$6:$AU$36,46,0) -> 0 | S35: =VLOOKUP($A35,[22]HISTODEC23!$A$6:$AU$36,26,0) -> 0 | T35: =VLOOKUP($A35,[22]HISTODEC23!$A$6:$BG$36,58,0) -> 0 | U35: =VLOOKUP($A35,[22]HISTODEC23!$A$6:$AU$36,28,0) -> 0 | V35: =VLOOKUP($A35,[22]HISTODEC23!$A$6:$AU$36,19,0) -> 0 | W35: =VLOOKUP($A35,[22]HISTODEC23!$A$6:$AU$36,20,0) -> 0 | X35: =VLOOKUP($A35,[22]HISTODEC23!$A$6:$AU$36,27,0) -> 0 | Y35: =VLOOKUP($A35,[22]HISTODEC23!$A$6:$BM$36,33,0) -> 0 | Z35: =VLOOKUP($A35,[22]HISTODEC23!$A$6:$BM$36,65,0) -> 0 | AB35: =VLOOKUP($A35,[22]HISTODEC23!$A$6:$AU$36,43,0) -> 0 | AC35: =VLOOKUP($A35,[22]HISTODEC23!$A$6:$AU$36,44,0) -> 0 | AD35: =VLOOKUP($A35,[22]HISTODEC23!$A$6:$AU$36,47,0) -> 0 | AE35: =VLOOKUP(A35,[22]HISTODEC23!$A$6:$BB$36,54,0) -> 70000 | AF35: =VLOOKUP($A35,[22]HISTODEC23!$A$6:$CA$36,60,0) -> 0 | AG35: =VLOOKUP($A35,[22]HISTODEC23!$A$6:$CA$36,61,0) -> 0 | AH35: =VLOOKUP($A35,[22]HISTODEC23!$A$6:$CA$36,62,0) -> 0 | AI35: =VLOOKUP($A35,[22]HISTODEC23!$A$6:$CA$36,63,0) -> 0 | AJ35: =VLOOKUP($A35,[22]HISTODEC23!$A$6:$CA$36,64,0) -> 0 | AK35: =VLOOKUP($A35,[22]HISTODEC23!$A$6:$CA$36,65,0) -> 0 | AL35: =VLOOKUP($A35,[20]DETAILFICHECASSATION!$A$6:$R$36,12,0) -> 0
A36: AS201658 | B36: =VLOOKUP(A36,[19]LISTADHERENT!A$5:H$60,3,0) -> YANTCHOU GERVAIS | C36: =VLOOKUP($A36,[23]FONDSCAISSE!$A$2:$G$33,4,0) -> 698024.14 | D36: =VLOOKUP($A36,[20]DETAILFICHECASSATION!$A$6:$R$36,17,0) -> 0 | F36: =C36+D36-E36 -> 698024.14 | G36: =IF(C36+D36+L36-E36>=700000,(C36+D36-E36),0) -> 698024.14 | H36: =($T$41/$G$41*G36) -> 38253.255 | I36: =(F36+H36) -> 736277.39 | J36: =VLOOKUP($A36,[22]HISTODEC23!$A$6:$AQ$40,22,0) -> 0 | K36: =VLOOKUP($A36,[22]HISTODEC23!$A$6:$AU$36,45,0) -> 15000 | L36: =IF(K36=0,0,K36-(M36+N36+O36)) -> 9000 | M36: =IF(K36=0,0,1000) -> 1000 | N36: =IF(K36=0,0,1000) -> 1000 | O36: =IF(K36=0,0,4000) -> 4000 | P36: =VLOOKUP($A36,[22]HISTODEC23!$A$6:$AU$36,7,0) -> 0 | Q36: =VLOOKUP($A36,[22]HISTODEC23!$A$6:$AU$36,23,0) -> 0 | R36: =VLOOKUP($A36,[22]HISTODEC23!$A$6:$AU$36,46,0) -> 0 | S36: =VLOOKUP($A36,[22]HISTODEC23!$A$6:$AU$36,26,0) -> 700000 | T36: =VLOOKUP($A36,[22]HISTODEC23!$A$6:$BG$36,58,0) -> 84000 | U36: =VLOOKUP($A36,[22]HISTODEC23!$A$6:$AU$36,28,0) -> 0 | V36: =VLOOKUP($A36,[22]HISTODEC23!$A$6:$AU$36,19,0) -> 0 | W36: =VLOOKUP($A36,[22]HISTODEC23!$A$6:$AU$36,20,0) -> 0 | X36: =VLOOKUP($A36,[22]HISTODEC23!$A$6:$AU$36,27,0) -> BANQUE | Y36: =VLOOKUP($A36,[22]HISTODEC23!$A$6:$BM$36,33,0) -> 0 | Z36: =VLOOKUP($A36,[22]HISTODEC23!$A$6:$BM$36,65,0) -> 0 | AB36: =VLOOKUP($A36,[22]HISTODEC23!$A$6:$AU$36,43,0) -> 0 | AC36: =VLOOKUP($A36,[22]HISTODEC23!$A$6:$AU$36,44,0) -> 0 | AD36: =VLOOKUP($A36,[22]HISTODEC23!$A$6:$AU$36,47,0) -> 0 | AE36: =VLOOKUP(A36,[22]HISTODEC23!$A$6:$BB$36,54,0) -> 0 | AF36: =VLOOKUP($A36,[22]HISTODEC23!$A$6:$CA$36,60,0) -> 0 | AG36: =VLOOKUP($A36,[22]HISTODEC23!$A$6:$CA$36,61,0) -> 0 | AH36: =VLOOKUP($A36,[22]HISTODEC23!$A$6:$CA$36,62,0) -> 0 | AI36: =VLOOKUP($A36,[22]HISTODEC23!$A$6:$CA$36,63,0) -> 0 | AJ36: =VLOOKUP($A36,[22]HISTODEC23!$A$6:$CA$36,64,0) -> 0 | AK36: =VLOOKUP($A36,[22]HISTODEC23!$A$6:$CA$36,65,0) -> 0 | AL36: =VLOOKUP($A36,[20]DETAILFICHECASSATION!$A$6:$R$36,12,0) -> 700000
A37: AS201646 | B37: =VLOOKUP(A37,[19]LISTADHERENT!A$5:H$60,3,0) -> YEPMOU JEAN JACQUES | C37: =VLOOKUP($A37,[23]FONDSCAISSE!$A$2:$G$33,4,0) -> 700000 | D37: =VLOOKUP($A37,[20]DETAILFICHECASSATION!$A$6:$R$36,17,0) -> 1003326.8 | F37: =C37+D37-E37 -> 1703326.8 | G37: =IF(C37+D37+L37-E37>=700000,(C37+D37-E37),0) -> 1703326.8 | H37: =($T$41/$G$41*G37) -> 93346.05 | I37: =(F37+H37) -> 1796672.9 | J37: =VLOOKUP($A37,[22]HISTODEC23!$A$6:$AQ$40,22,0) -> 0 | K37: =VLOOKUP($A37,[22]HISTODEC23!$A$6:$AU$36,45,0) -> 15000 | L37: =IF(K37=0,0,K37-(M37+N37+O37)) -> 9000 | M37: =IF(K37=0,0,1000) -> 1000 | N37: =IF(K37=0,0,1000) -> 1000 | O37: =IF(K37=0,0,4000) -> 4000 | P37: =VLOOKUP($A37,[22]HISTODEC23!$A$6:$AU$36,7,0) -> 0 | Q37: =VLOOKUP($A37,[22]HISTODEC23!$A$6:$AU$36,23,0) -> 0 | R37: =VLOOKUP($A37,[22]HISTODEC23!$A$6:$AU$36,46,0) -> 0 | S37: =VLOOKUP($A37,[22]HISTODEC23!$A$6:$AU$36,26,0) -> 0 | T37: =VLOOKUP($A37,[22]HISTODEC23!$A$6:$BG$36,58,0) -> 0 | U37: =VLOOKUP($A37,[22]HISTODEC23!$A$6:$AU$36,28,0) -> 0 | V37: =VLOOKUP($A37,[22]HISTODEC23!$A$6:$AU$36,19,0) -> 227500 | W37: =VLOOKUP($A37,[22]HISTODEC23!$A$6:$AU$36,20,0) -> BANQUE | X37: =VLOOKUP($A37,[22]HISTODEC23!$A$6:$AU$36,27,0) -> 0 | Y37: =VLOOKUP($A37,[22]HISTODEC23!$A$6:$BM$36,33,0) -> 0 | Z37: =VLOOKUP($A37,[22]HISTODEC23!$A$6:$BM$36,65,0) -> 0 | AB37: =VLOOKUP($A37,[22]HISTODEC23!$A$6:$AU$36,43,0) -> 0 | AC37: =VLOOKUP($A37,[22]HISTODEC23!$A$6:$AU$36,44,0) -> 0 | AD37: =VLOOKUP($A37,[22]HISTODEC23!$A$6:$AU$36,47,0) -> 0 | AE37: =VLOOKUP(A37,[22]HISTODEC23!$A$6:$BB$36,54,0) -> 70000 | AF37: =VLOOKUP($A37,[22]HISTODEC23!$A$6:$CA$36,60,0) -> 0 | AG37: =VLOOKUP($A37,[22]HISTODEC23!$A$6:$CA$36,61,0) -> 0 | AH37: =VLOOKUP($A37,[22]HISTODEC23!$A$6:$CA$36,62,0) -> 0 | AI37: =VLOOKUP($A37,[22]HISTODEC23!$A$6:$CA$36,63,0) -> 0 | AJ37: =VLOOKUP($A37,[22]HISTODEC23!$A$6:$CA$36,64,0) -> 0 | AK37: =VLOOKUP($A37,[22]HISTODEC23!$A$6:$CA$36,65,0) -> 0 | AL37: =VLOOKUP($A37,[20]DETAILFICHECASSATION!$A$6:$R$36,12,0) -> 100000
A38: AS201659 | B38: =VLOOKUP(A38,[19]LISTADHERENT!A$5:H$60,3,0) -> YIALA ALAIN OSCAR | F38: =C38+D38-E38 -> 0 | G38: =IF(C38+D38+L38-E38>=700000,(C38+D38-E38),0) -> 0 | H38: =($T$41/$G$41*G38) -> 0 | I38: =(F38+H38) -> 0
A39: AS201647 | B39: =VLOOKUP(A39,[19]LISTADHERENT!A$5:H$60,3,0) -> YOUMBI EMMANUEL | C39: =VLOOKUP($A39,[23]FONDSCAISSE!$A$2:$G$33,4,0) -> 700000 | D39: =VLOOKUP($A39,[20]DETAILFICHECASSATION!$A$6:$R$36,17,0) -> 1157835 | F39: =C39+D39-E39 -> 1857835 | G39: =IF(C39+D39+L39-E39>=700000,(C39+D39-E39),0) -> 1857835 | H39: =($T$41/$G$41*G39) -> 101813.43 | I39: =(F39+H39) -> 1959648.4 | J39: =VLOOKUP($A39,[22]HISTODEC23!$A$6:$AQ$40,22,0) -> 11000 | K39: =VLOOKUP($A39,[22]HISTODEC23!$A$6:$AU$36,45,0) -> 15000 | L39: =IF(K39=0,0,K39-(M39+N39+O39)) -> 9000 | M39: =IF(K39=0,0,1000) -> 1000 | N39: =IF(K39=0,0,1000) -> 1000 | O39: =IF(K39=0,0,4000) -> 4000 | P39: =VLOOKUP($A39,[22]HISTODEC23!$A$6:$AU$36,7,0) -> 0 | Q39: =VLOOKUP($A39,[22]HISTODEC23!$A$6:$AU$36,23,0) -> 0 | R39: =VLOOKUP($A39,[22]HISTODEC23!$A$6:$AU$36,46,0) -> 0 | S39: =VLOOKUP($A39,[22]HISTODEC23!$A$6:$AU$36,26,0) -> 0 | T39: =VLOOKUP($A39,[22]HISTODEC23!$A$6:$BG$36,58,0) -> 0 | U39: =VLOOKUP($A39,[22]HISTODEC23!$A$6:$AU$36,28,0) -> 0 | V39: =VLOOKUP($A39,[22]HISTODEC23!$A$6:$AU$36,19,0) -> 0 | W39: =VLOOKUP($A39,[22]HISTODEC23!$A$6:$AU$36,20,0) -> 0 | X39: =VLOOKUP($A39,[22]HISTODEC23!$A$6:$AU$36,27,0) -> 0 | Y39: =VLOOKUP($A39,[22]HISTODEC23!$A$6:$BM$36,33,0) -> 0 | Z39: =VLOOKUP($A39,[22]HISTODEC23!$A$6:$BM$36,65,0) -> 0 | AB39: =VLOOKUP($A39,[22]HISTODEC23!$A$6:$AU$36,43,0) -> 0 | AC39: =VLOOKUP($A39,[22]HISTODEC23!$A$6:$AU$36,44,0) -> 0 | AD39: =VLOOKUP($A39,[22]HISTODEC23!$A$6:$AU$36,47,0) -> 0 | AE39: =VLOOKUP(A39,[22]HISTODEC23!$A$6:$BB$36,54,0) -> 0 | AF39: =VLOOKUP($A39,[22]HISTODEC23!$A$6:$CA$36,60,0) -> 0 | AG39: =VLOOKUP($A39,[22]HISTODEC23!$A$6:$CA$36,61,0) -> 0 | AH39: =VLOOKUP($A39,[22]HISTODEC23!$A$6:$CA$36,62,0) -> 0 | AI39: =VLOOKUP($A39,[22]HISTODEC23!$A$6:$CA$36,63,0) -> 0 | AJ39: =VLOOKUP($A39,[22]HISTODEC23!$A$6:$CA$36,64,0) -> 0 | AK39: =VLOOKUP($A39,[22]HISTODEC23!$A$6:$CA$36,65,0) -> 0 | AL39: =VLOOKUP($A39,[20]DETAILFICHECASSATION!$A$6:$R$36,12,0) -> 100000
A41: TOTAL | C41: =SUM(C6:C40) -> 19518743 | D41: =SUM(D6:D40) -> 4710914.1 | E41: =SUM(E6:E40) -> 0 | F41: =SUM(F6:F40) -> 24229657 | G41: =SUM(G6:G40) -> 21860438 | H41: =SUM(H6:H40) -> 1198000 | I41: =SUM(I6:I40) -> 25427657 | J41: =SUM(J6:J40) -> 187000 | ... AL41: =SUM(AL6:AL40) -> 4500000

Sheet Sheet7
A1: ASSOCIATION | B1: ASELBY
A2: ANNEE | B2: 2024
A3: TONTINE
K4: 45308
A5: MATRICULE | B5: NOM ET PRENOM | C5: FONDES DE DEPART | D5: RECONDUCTION | E5: RETRAIT PARTIEL | F5: FONDS DEFINITIF | G5: BASE DE CALCUL INTERET FONDS DEFINITIF | H5: REPARTITION PROVISOIRE INTERET FONDS+EPARGNE | I5: CAPITAL COMPOSE | J5: SANCTION | K5: RESTE | L5: EPARGNE | M5: FONDS DE ROULEMENT | N5: FRAIS EXCEPTIONNEL | O5: COLLATION | P5: PENALITE VST ESPECES | Q5: INSCRISPTION | R5: MUTUELLE | S5: PRÊT FONDS | T5: INTERET PRET FONDS | U5: NUMERO CHEQUE | V5: REMBOURSEMENTPRET FONDS | W5: MODE VERSEMENT REMBOURSEMENT | X5: MODE VERSEMENT PRÊT | Y5: NUMERO CHEQUE | Z5: PENALITE PRET FONDS | AA5: PENALITE FONDS | AB5: PENALITE ECHEC TONTINE | AC5: PENALITE RETARD TONTINE | AD5: REMBOURSEMENT TRANSPORT | AE5: CONTRIBUTION FOYER | AF5: FONDS DE ROULEMENT | AG5: FRAIS EXCEPTIONNEL | AH5: FONDS MUTUELLE | AI5: COLLATION RECEPTION | AJ5: PENALITE PRET FONDS | AK5: DEPENSE PENALITE VERSEMENT BANQUE
A6: AS201648 | B6: =VLOOKUP(A6,[19]LISTADHERENT!A$5:H$60,3,0) -> ASELBY | F6: =MVTDEC23!I6-E6+L6 -> 935106.68 | G6: =IF(MVTDEC23!I6>700000,(MVTDEC23!I6-E6+L6),0) -> 935106.68 | H6: =$T$41/$G$41*G6 -> 6975.6164 | I6: =F6+H6 -> 942082.3 | J6: =VLOOKUP($A6,[24]HISTOJANV24!$A$6:$AQ$42,22,0) -> 0 | K6: =VLOOKUP($A6,[24]HISTOJANV24!$A$6:$AU$38,45,0) -> 0 | L6: =IF(K6=0,0,K6-(M6+N6+O6)) -> 0 | M6: =IF(K6=0,0,1000) -> 0 | N6: =IF(K6=0,0,1000) -> 0 | O6: =IF(K6=0,0,4000) -> 0 | P6: =VLOOKUP($A6,[24]HISTOJANV24!$A$6:$AU$38,7,0) -> 0 | Q6: =VLOOKUP($A6,[24]HISTOJANV24!$A$6:$AU$38,23,0) -> 0 | R6: =VLOOKUP($A6,[24]HISTOJANV24!$A$6:$AU$38,46,0) -> 0 | S6: =VLOOKUP($A6,[24]HISTOJANV24!$A$6:$AU$38,26,0) -> 0 | T6: =VLOOKUP($A6,[24]HISTOJANV24!$A$6:$BG$38,58,0) -> 0 | U6: =VLOOKUP($A6,[24]HISTOJANV24!$A$6:$AU$38,28,0) -> 0 | V6: =VLOOKUP($A6,[24]HISTOJANV24!$A$6:$AU$38,19,0) -> 0 | W6: =VLOOKUP($A6,[24]HISTOJANV24!$A$6:$AU$38,20,0) -> 0 | X6: =VLOOKUP($A6,[24]HISTOJANV24!$A$6:$AU$38,27,0) -> 0 | Y6: =VLOOKUP($A6,[24]HISTOJANV24!$A$6:$BM$38,33,0) -> 0 | Z6: =VLOOKUP($A6,[24]HISTOJANV24!$A$6:$BM$38,65,0) -> 0 | AB6: =VLOOKUP($A6,[24]HISTOJANV24!$A$6:$AU$38,43,0) -> 0 | AC6: =VLOOKUP($A6,[24]HISTOJANV24!$A$6:$AU$38,44,0) -> 0 | AD6: =VLOOKUP($A6,[24]HISTOJANV24!$A$6:$AU$38,47,0) -> 0 | AE6: =VLOOKUP(A6,[24]HISTOJANV24!$A$6:$BB$38,54,0) -> 0 | AF6: =VLOOKUP($A6,[24]HISTOJANV24!$A$6:$CA$38,60,0) -> 27000 | AG6: =VLOOKUP($A6,[24]HISTOJANV24!$A$6:$CA$38,61,0) -> 500000 | AH6: =VLOOKUP($A6,[24]HISTOJANV24!$A$6:$CA$38,62,0) -> 0 | AI6: =VLOOKUP($A6,[24]HISTOJANV24!$A$6:$CA$38,63,0) -> 100000 | AJ6: =VLOOKUP($A6,[24]HISTOJANV24!$A$6:$CA$38,64,0) -> 0 | AK6: =VLOOKUP($A6,[24]HISTOJANV24!$A$6:$CA$38,65,0) -> 0
A7: AS201601 | B7: =VLOOKUP(A7,[19]LISTADHERENT!A$5:H$60,3,0) -> BAKOP ACHILLE | E7: =VLOOKUP($A7,[24]HISTOJANV24!$A$6:$BA$38,48,0) -> 0 | F7: =MVTDEC23!I7-E7+L7 -> 697482.5 | G7: =IF(MVTDEC23!I7>700000,(MVTDEC23!I7-E7+L7),0) -> 0 | H7: =$T$41/$G$41*G7 -> 0 | I7: =F7+H7 -> 697482.5 | J7: =VLOOKUP($A7,[24]HISTOJANV24!$A$6:$AQ$42,22,0) -> 0 | K7: =VLOOKUP($A7,[24]HISTOJANV24!$A$6:$AU$38,45,0) -> 25000 | L7: =IF(K7=0,0,K7-(M7+N7+O7)) -> 19000 | M7: =IF(K7=0,0,1000) -> 1000 | N7: =IF(K7=0,0,1000) -> 1000 | O7: =IF(K7=0,0,4000) -> 4000 | P7: =VLOOKUP($A7,[24]HISTOJANV24!$A$6:$AU$38,7,0) -> 0 | Q7: =VLOOKUP($A7,[24]HISTOJANV24!$A$6:$AU$38,23,0) -> 0 | R7: =VLOOKUP($A7,[24]HISTOJANV24!$A$6:$AU$38,46,0) -> 0 | S7: =VLOOKUP($A7,[24]HISTOJANV24!$A$6:$AU$38,26,0) -> 0 | T7: =VLOOKUP($A7,[24]HISTOJANV24!$A$6:$BG$38,58,0) -> 6000 | U7: =VLOOKUP($A7,[24]HISTOJANV24!$A$6:$AU$38,28,0) -> 0 | V7: =VLOOKUP($A7,[24]HISTOJANV24!$A$6:$AU$38,19,0) -> 0 | W7: =VLOOKUP($A7,[24]HISTOJANV24!$A$6:$AU$38,20,0) -> 0 | X7: =VLOOKUP($A7,[24]HISTOJANV24!$A$6:$AU$38,27,0) -> 0 | Y7: =VLOOKUP($A7,[24]HISTOJANV24!$A$6:$BM$38,33,0) -> 0 | Z7: =VLOOKUP($A7,[24]HISTOJANV24!$A$6:$BM$38,65,0) -> 0 | AB7: =VLOOKUP($A7,[24]HISTOJANV24!$A$6:$AU$38,43,0) -> 0 | AC7: =VLOOKUP($A7,[24]HISTOJANV24!$A$6:$AU$38,44,0) -> 0 | AD7: =VLOOKUP($A7,[24]HISTOJANV24!$A$6:$AU$38,47,0) -> 0 | AE7: =VLOOKUP(A7,[24]HISTOJANV24!$A$6:$BB$38,54,0) -> 0 | AF7: =VLOOKUP($A7,[24]HISTOJANV24!$A$6:$CA$38,60,0) -> 0 | AG7: =VLOOKUP($A7,[24]HISTOJANV24!$A$6:$CA$38,61,0) -> 0 | AH7: =VLOOKUP($A7,[24]HISTOJANV24!$A$6:$CA$38,62,0) -> 0 | AI7: =VLOOKUP($A7,[24]HISTOJANV24!$A$6:$CA$38,63,0) -> 0 | AJ7: =VLOOKUP($A7,[24]HISTOJANV24!$A$6:$CA$38,64,0) -> 0 | AK7: =VLOOKUP($A7,[24]HISTOJANV24!$A$6:$CA$38,65,0) -> 0
A8: AS201602 | B8: =VLOOKUP(A8,[19]LISTADHERENT!A$5:H$60,3,0) -> BOUTCHOUANG WILLIAM | E8: =VLOOKUP($A8,[24]HISTOJANV24!$A$6:$BA$38,48,0) -> 0 | F8: =MVTDEC23!I8-E8+L8 -> 757396.48 | G8: =IF(MVTDEC23!I8>700000,(MVTDEC23!I8-E8+L8),0) -> 757396.48 | H8: =$T$41/$G$41*G8 -> 5649.9514 | I8: =F8+H8 -> 763046.43 | J8: =VLOOKUP($A8,[24]HISTOJANV24!$A$6:$AQ$42,22,0) -> 0 | K8: =VLOOKUP($A8,[24]HISTOJANV24!$A$6:$AU$38,45,0) -> 25000 | L8: =IF(K8=0,0,K8-(M8+N8+O8)) -> 19000 | M8: =IF(K8=0,0,1000) -> 1000 | N8: =IF(K8=0,0,1000) -> 1000 | O8: =IF(K8=0,0,4000) -> 4000 | P8: =VLOOKUP($A8,[24]HISTOJANV24!$A$6:$AU$38,7,0) -> 0 | Q8: =VLOOKUP($A8,[24]HISTOJANV24!$A$6:$AU$38,23,0) -> 0 | R8: =VLOOKUP($A8,[24]HISTOJANV24!$A$6:$AU$38,46,0) -> 0 | S8: =VLOOKUP($A8,[24]HISTOJANV24!$A$6:$AU$38,26,0) -> 0 | T8: =VLOOKUP($A8,[24]HISTOJANV24!$A$6:$BG$38,58,0) -> 0 | U8: =VLOOKUP($A8,[24]HISTOJANV24!$A$6:$AU$38,28,0) -> 0 | V8: =VLOOKUP($A8,[24]HISTOJANV24!$A$6:$AU$38,19,0) -> 0 | W8: =VLOOKUP($A8,[24]HISTOJANV24!$A$6:$AU$38,20,0) -> 0 | X8: =VLOOKUP($A8,[24]HISTOJANV24!$A$6:$AU$38,27,0) -> 0 | Y8: =VLOOKUP($A8,[24]HISTOJANV24!$A$6:$BM$38,33,0) -> 0 | Z8: =VLOOKUP($A8,[24]HISTOJANV24!$A$6:$BM$38,65,0) -> 0 | AB8: =VLOOKUP($A8,[24]HISTOJANV24!$A$6:$AU$38,43,0) -> 0 | AC8: =VLOOKUP($A8,[24]HISTOJANV24!$A$6:$AU$38,44,0) -> 0 | AD8: =VLOOKUP($A8,[24]HISTOJANV24!$A$6:$AU$38,47,0) -> 0 | AE8: =VLOOKUP(A8,[24]HISTOJANV24!$A$6:$BB$38,54,0) -> 0 | AF8: =VLOOKUP($A8,[24]HISTOJANV24!$A$6:$CA$38,60,0) -> 0 | AG8: =VLOOKUP($A8,[24]HISTOJANV24!$A$6:$CA$38,61,0) -> 0 | AH8: =VLOOKUP($A8,[24]HISTOJANV24!$A$6:$CA$38,62,0) -> 0 | AI8: =VLOOKUP($A8,[24]HISTOJANV24!$A$6:$CA$38,63,0) -> 0 | AJ8: =VLOOKUP($A8,[24]HISTOJANV24!$A$6:$CA$38,64,0) -> 0 | AK8: =VLOOKUP($A8,[24]HISTOJANV24!$A$6:$CA$38,65,0) -> 0
A9: AS201604 | B9: =VLOOKUP(A9,[19]LISTADHERENT!A$5:H$60,3,0) -> DJOMO JEAN PAUL | E9: =VLOOKUP($A9,[24]HISTOJANV24!$A$6:$BA$38,48,0) -> 0 | F9: =MVTDEC23!I9-E9+L9 -> 813643.49 | G9: =IF(MVTDEC23!I9>700000,(MVTDEC23!I9-E9+L9),0) -> 813643.49 | H9: =$T$41/$G$41*G9 -> 6069.5373 | I9: =F9+H9 -> 819713.03 | J9: =VLOOKUP($A9,[24]HISTOJANV24!$A$6:$AQ$42,22,0) -> 0 | K9: =VLOOKUP($A9,[24]HISTOJANV24!$A$6:$AU$38,45,0) -> 25000 | L9: =IF(K9=0,0,K9-(M9+N9+O9)) -> 19000 | M9: =IF(K9=0,0,1000) -> 1000 | N9: =IF(K9=0,0,1000) -> 1000 | O9: =IF(K9=0,0,4000) -> 4000 | P9: =VLOOKUP($A9,[24]HISTOJANV24!$A$6:$AU$38,7,0) -> 0 | Q9: =VLOOKUP($A9,[24]HISTOJANV24!$A$6:$AU$38,23,0) -> 0 | R9: =VLOOKUP($A9,[24]HISTOJANV24!$A$6:$AU$38,46,0) -> 0 | S9: =VLOOKUP($A9,[24]HISTOJANV24!$A$6:$AU$38,26,0) -> 0 | T9: =VLOOKUP($A9,[24]HISTOJANV24!$A$6:$BG$38,58,0) -> 0 | U9: =VLOOKUP($A9,[24]HISTOJANV24!$A$6:$AU$38,28,0) -> 0 | V9: =VLOOKUP($A9,[24]HISTOJANV24!$A$6:$AU$38,19,0) -> 0 | W9: =VLOOKUP($A9,[24]HISTOJANV24!$A$6:$AU$38,20,0) -> 0 | X9: =VLOOKUP($A9,[24]HISTOJANV24!$A$6:$AU$38,27,0) -> 0 | Y9: =VLOOKUP($A9,[24]HISTOJANV24!$A$6:$BM$38,33,0) -> 0 | Z9: =VLOOKUP($A9,[24]HISTOJANV24!$A$6:$BM$38,65,0) -> 0 | AB9: =VLOOKUP($A9,[24]HISTOJANV24!$A$6:$AU$38,43,0) -> 0 | AC9: =VLOOKUP($A9,[24]HISTOJANV24!$A$6:$AU$38,44,0) -> 0 | AD9: =VLOOKUP($A9,[24]HISTOJANV24!$A$6:$AU$38,47,0) -> 0 | AE9: =VLOOKUP(A9,[24]HISTOJANV24!$A$6:$BB$38,54,0) -> 0 | AF9: =VLOOKUP($A9,[24]HISTOJANV24!$A$6:$CA$38,60,0) -> 0 | AG9: =VLOOKUP($A9,[24]HISTOJANV24!$A$6:$CA$38,61,0) -> 0 | AH9: =VLOOKUP($A9,[24]HISTOJANV24!$A$6:$CA$38,62,0) -> 0 | AI9: =VLOOKUP($A9,[24]HISTOJANV24!$A$6:$CA$38,63,0) -> 0 | AJ9: =VLOOKUP($A9,[24]HISTOJANV24!$A$6:$CA$38,64,0) -> 0 | AK9: =VLOOKUP($A9,[24]HISTOJANV24!$A$6:$CA$38,65,0) -> 0
A10: AS201654 | B10: =VLOOKUP(A10,[19]LISTADHERENT!A$5:H$60,3,0) -> DJOMOU TCHAPDA | E10: =VLOOKUP($A10,[24]HISTOJANV24!$A$6:$BA$38,48,0) -> 0 | F10: =MVTDEC23!I10-E10+L10 -> 757672.36 | G10: =IF(MVTDEC23!I10>700000,(MVTDEC23!I10-E10+L10),0) -> 757672.36 | H10: =$T$41/$G$41*G10 -> 5652.0095 | I10: =F10+H10 -> 763324.37 | J10: =VLOOKUP($A10,[24]HISTOJANV24!$A$6:$AQ$42,22,0) -> 0 | K10: =VLOOKUP($A10,[24]HISTOJANV24!$A$6:$AU$38,45,0) -> 25000 | L10: =IF(K10=0,0,K10-(M10+N10+O10)) -> 19000 | M10: =IF(K10=0,0,1000) -> 1000 | N10: =IF(K10=0,0,1000) -> 1000 | O10: =IF(K10=0,0,4000) -> 4000 | P10: =VLOOKUP($A10,[24]HISTOJANV24!$A$6:$AU$38,7,0) -> 0 | Q10: =VLOOKUP($A10,[24]HISTOJANV24!$A$6:$AU$38,23,0) -> 0 | R10: =VLOOKUP($A10,[24]HISTOJANV24!$A$6:$AU$38,46,0) -> 0 | S10: =VLOOKUP($A10,[24]HISTOJANV24!$A$6:$AU$38,26,0) -> 0 | T10: =VLOOKUP($A10,[24]HISTOJANV24!$A$6:$BG$38,58,0) -> 0 | U10: =VLOOKUP($A10,[24]HISTOJANV24!$A$6:$AU$38,28,0) -> 0 | V10: =VLOOKUP($A10,[24]HISTOJANV24!$A$6:$AU$38,19,0) -> 0 | W10: =VLOOKUP($A10,[24]HISTOJANV24!$A$6:$AU$38,20,0) -> 0 | X10: =VLOOKUP($A10,[24]HISTOJANV24!$A$6:$AU$38,27,0) -> 0 | Y10: =VLOOKUP($A10,[24]HISTOJANV24!$A$6:$BM$38,33,0) -> 0 | Z10: =VLOOKUP($A10,[24]HISTOJANV24!$A$6:$BM$38,65,0) -> 0 | AB10: =VLOOKUP($A10,[24]HISTOJANV24!$A$6:$AU$38,43,0) -> 0 | AC10: =VLOOKUP($A10,[24]HISTOJANV24!$A$6:$AU$38,44,0) -> 0 | AD10: =VLOOKUP($A10,[24]HISTOJANV24!$A$6:$AU$38,47,0) -> 0 | AE10: =VLOOKUP(A10,[24]HISTOJANV24!$A$6:$BB$38,54,0) -> 0 | AF10: =VLOOKUP($A10,[24]HISTOJANV24!$A$6:$CA$38,60,0) -> 0 | AG10: =VLOOKUP($A10,[24]HISTOJANV24!$A$6:$CA$38,61,0) -> 0 | AH10: =VLOOKUP($A10,[24]HISTOJANV24!$A$6:$CA$38,62,0) -> 0 | AI10: =VLOOKUP($A10,[24]HISTOJANV24!$A$6:$CA$38,63,0) -> 0 | AJ10: =VLOOKUP($A10,[24]HISTOJANV24!$A$6:$CA$38,64,0) -> 0 | AK10: =VLOOKUP($A10,[24]HISTOJANV24!$A$6:$CA$38,65,0) -> 0
A11: AS201605 | B11: =VLOOKUP(A11,[19]LISTADHERENT!A$5:H$60,3,0) -> DJOUKWE NANGUEN GUY BLAISE | E11: =VLOOKUP($A11,[24]HISTOJANV24!$A$6:$BA$38,48,0) -> 0 | F11: =MVTDEC23!I11-E11+L11 -> 759678.69 | G11: =IF(MVTDEC23!I11>700000,(MVTDEC23!I11-E11+L11),0) -> 759678.69 | H11: =$T$41/$G$41*G11 -> 5666.9761 | I11: =F11+H11 -> 765345.67 | J11: =VLOOKUP($A11,[24]HISTOJANV24!$A$6:$AQ$42,22,0) -> 0 | K11: =VLOOKUP($A11,[24]HISTOJANV24!$A$6:$AU$38,45,0) -> 25000 | L11: =IF(K11=0,0,K11-(M11+N11+O11)) -> 19000 | M11: =IF(K11=0,0,1000) -> 1000 | N11: =IF(K11=0,0,1000) -> 1000 | O11: =IF(K11=0,0,4000) -> 4000 | P11: =VLOOKUP($A11,[24]HISTOJANV24!$A$6:$AU$38,7,0) -> 0 | Q11: =VLOOKUP($A11,[24]HISTOJANV24!$A$6:$AU$38,23,0) -> 0 | R11: =VLOOKUP($A11,[24]HISTOJANV24!$A$6:$AU$38,46,0) -> 0 | S11: =VLOOKUP($A11,[24]HISTOJANV24!$A$6:$AU$38,26,0) -> 0 | T11: =VLOOKUP($A11,[24]HISTOJANV24!$A$6:$BG$38,58,0) -> 0 | U11: =VLOOKUP($A11,[24]HISTOJANV24!$A$6:$AU$38,28,0) -> 0 | V11: =VLOOKUP($A11,[24]HISTOJANV24!$A$6:$AU$38,19,0) -> 0 | W11: =VLOOKUP($A11,[24]HISTOJANV24!$A$6:$AU$38,20,0) -> 0 | X11: =VLOOKUP($A11,[24]HISTOJANV24!$A$6:$AU$38,27,0) -> 0 | Y11: =VLOOKUP($A11,[24]HISTOJANV24!$A$6:$BM$38,33,0) -> 0 | Z11: =VLOOKUP($A11,[24]HISTOJANV24!$A$6:$BM$38,65,0) -> 0 | AB11: =VLOOKUP($A11,[24]HISTOJANV24!$A$6:$AU$38,43,0) -> 0 | AC11: =VLOOKUP($A11,[24]HISTOJANV24!$A$6:$AU$38,44,0) -> 0 | AD11: =VLOOKUP($A11,[24]HISTOJANV24!$A$6:$AU$38,47,0) -> 0 | AE11: =VLOOKUP(A11,[24]HISTOJANV24!$A$6:$BB$38,54,0) -> 0 | AF11: =VLOOKUP($A11,[24]HISTOJANV24!$A$6:$CA$38,60,0) -> 0 | AG11: =VLOOKUP($A11,[24]HISTOJANV24!$A$6:$CA$38,61,0) -> 0 | AH11: =VLOOKUP($A11,[24]HISTOJANV24!$A$6:$CA$38,62,0) -> 0 | AI11: =VLOOKUP($A11,[24]HISTOJANV24!$A$6:$CA$38,63,0) -> 0 | AJ11: =VLOOKUP($A11,[24]HISTOJANV24!$A$6:$CA$38,64,0) -> 0 | AK11: =VLOOKUP($A11,[24]HISTOJANV24!$A$6:$CA$38,65,0) -> 0
A12: AS201608 | B12: =VLOOKUP(A12,[19]LISTADHERENT!A$5:H$60,3,0) -> DJUOMBESSY ANTOINE | E12: =VLOOKUP($A12,[24]HISTOJANV24!$A$6:$BA$38,48,0) -> 0 | F12: =MVTDEC23!I12-E12+L12 -> 777670.17 | G12: =IF(MVTDEC23!I12>700000,(MVTDEC23!I12-E12+L12),0) -> 777670.17 | H12: =$T$41/$G$41*G12 -> 5801.1871 | I12: =F12+H12 -> 783471.36 | J12: =VLOOKUP($A12,[24]HISTOJANV24!$A$6:$AQ$42,22,0) -> 0 | K12: =VLOOKUP($A12,[24]HISTOJANV24!$A$6:$AU$38,45,0) -> 30000 | L12: =IF(K12=0,0,K12-(M12+N12+O12)) -> 24000 | M12: =IF(K12=0,0,1000) -> 1000 | N12: =IF(K12=0,0,1000) -> 1000 | O12: =IF(K12=0,0,4000) -> 4000 | P12: =VLOOKUP($A12,[24]HISTOJANV24!$A$6:$AU$38,7,0) -> 0 | Q12: =VLOOKUP($A12,[24]HISTOJANV24!$A$6:$AU$38,23,0) -> 0 | R12: =VLOOKUP($A12,[24]HISTOJANV24!$A$6:$AU$38,46,0) -> 0 | S12: =VLOOKUP($A12,[24]HISTOJANV24!$A$6:$AU$38,26,0) -> 0 | T12: =VLOOKUP($A12,[24]HISTOJANV24!$A$6:$BG$38,58,0) -> 0 | U12: =VLOOKUP($A12,[24]HISTOJANV24!$A$6:$AU$38,28,0) -> 0 | V12: =VLOOKUP($A12,[24]HISTOJANV24!$A$6:$AU$38,19,0) -> 0 | W12: =VLOOKUP($A12,[24]HISTOJANV24!$A$6:$AU$38,20,0) -> 0 | X12: =VLOOKUP($A12,[24]HISTOJANV24!$A$6:$AU$38,27,0) -> 0 | Y12: =VLOOKUP($A12,[24]HISTOJANV24!$A$6:$BM$38,33,0) -> 0 | Z12: =VLOOKUP($A12,[24]HISTOJANV24!$A$6:$BM$38,65,0) -> 0 | AB12: =VLOOKUP($A12,[24]HISTOJANV24!$A$6:$AU$38,43,0) -> 0 | AC12: =VLOOKUP($A12,[24]HISTOJANV24!$A$6:$AU$38,44,0) -> 0 | AD12: =VLOOKUP($A12,[24]HISTOJANV24!$A$6:$AU$38,47,0) -> 0 | AE12: =VLOOKUP(A12,[24]HISTOJANV24!$A$6:$BB$38,54,0) -> 0 | AF12: =VLOOKUP($A12,[24]HISTOJANV24!$A$6:$CA$38,60,0) -> 0 | AG12: =VLOOKUP($A12,[24]HISTOJANV24!$A$6:$CA$38,61,0) -> 0 | AH12: =VLOOKUP($A12,[24]HISTOJANV24!$A$6:$CA$38,62,0) -> 0 | AI12: =VLOOKUP($A12,[24]HISTOJANV24!$A$6:$CA$38,63,0) -> 0 | AJ12: =VLOOKUP($A12,[24]HISTOJANV24!$A$6:$CA$38,64,0) -> 0 | AK12: =VLOOKUP($A12,[24]HISTOJANV24!$A$6:$CA$38,65,0) -> 0
A13: AS201651 | B13: =VLOOKUP(A13,[19]LISTADHERENT!A$5:H$60,3,0) -> DOMOU FABIEN | E13: =VLOOKUP($A13,[24]HISTOJANV24!$A$6:$BA$38,48,0) -> 0 | F13: =MVTDEC23!I13-E13+L13 -> 757405.03 | G13: =IF(MVTDEC23!I13>700000,(MVTDEC23!I13-E13+L13),0) -> 757405.03 | H13: =$T$41/$G$41*G13 -> 5650.0152 | I13: =F13+H13 -> 763055.05 | J13: =VLOOKUP($A13,[24]HISTOJANV24!$A$6:$AQ$42,22,0) -> 0 | K13: =VLOOKUP($A13,[24]HISTOJANV24!$A$6:$AU$38,45,0) -> 25000 | L13: =IF(K13=0,0,K13-(M13+N13+O13)) -> 19000 | M13: =IF(K13=0,0,1000) -> 1000 | N13: =IF(K13=0,0,1000) -> 1000 | O13: =IF(K13=0,0,4000) -> 4000 | P13: =VLOOKUP($A13,[24]HISTOJANV24!$A$6:$AU$38,7,0) -> 0 | Q13: =VLOOKUP($A13,[24]HISTOJANV24!$A$6:$AU$38,23,0) -> 0 | R13: =VLOOKUP($A13,[24]HISTOJANV24!$A$6:$AU$38,46,0) -> 0 | S13: =VLOOKUP($A13,[24]HISTOJANV24!$A$6:$AU$38,26,0) -> 0 | T13: =VLOOKUP($A13,[24]HISTOJANV24!$A$6:$BG$38,58,0) -> 0 | U13: =VLOOKUP($A13,[24]HISTOJANV24!$A$6:$AU$38,28,0) -> 0 | V13: =VLOOKUP($A13,[24]HISTOJANV24!$A$6:$AU$38,19,0) -> 0 | W13: =VLOOKUP($A13,[24]HISTOJANV24!$A$6:$AU$38,20,0) -> 0 | X13: =VLOOKUP($A13,[24]HISTOJANV24!$A$6:$AU$38,27,0) -> 0 | Y13: =VLOOKUP($A13,[24]HISTOJANV24!$A$6:$BM$38,33,0) -> 0 | Z13: =VLOOKUP($A13,[24]HISTOJANV24!$A$6:$BM$38,65,0) -> 0 | AB13: =VLOOKUP($A13,[24]HISTOJANV24!$A$6:$AU$38,43,0) -> 0 | AC13: =VLOOKUP($A13,[24]HISTOJANV24!$A$6:$AU$38,44,0) -> 0 | AD13: =VLOOKUP($A13,[24]HISTOJANV24!$A$6:$AU$38,47,0) -> 0 | AE13: =VLOOKUP(A13,[24]HISTOJANV24!$A$6:$BB$38,54,0) -> 0 | AF13: =VLOOKUP($A13,[24]HISTOJANV24!$A$6:$CA$38,60,0) -> 0 | AG13: =VLOOKUP($A13,[24]HISTOJANV24!$A$6:$CA$38,61,0) -> 0 | AH13: =VLOOKUP($A13,[24]HISTOJANV24!$A$6:$CA$38,62,0) -> 0 | AI13: =VLOOKUP($A13,[24]HISTOJANV24!$A$6:$CA$38,63,0) -> 0 | AJ13: =VLOOKUP($A13,[24]HISTOJANV24!$A$6:$CA$38,64,0) -> 0 | AK13: =VLOOKUP($A13,[24]HISTOJANV24!$A$6:$CA$38,65,0) -> 0
A14: AS201609 | B14: =VLOOKUP(A14,[19]LISTADHERENT!A$5:H$60,3,0) -> DONHOU DAVID | E14: =VLOOKUP($A14,[24]HISTOJANV24!$A$6:$BA$38,48,0) -> 0 | F14: =MVTDEC23!I14-E14+L14 -> 1303782.1 | G14: =IF(MVTDEC23!I14>700000,(MVTDEC23!I14-E14+L14),0) -> 1303782.1 | H14: =$T$41/$G$41*G14 -> 9725.8248 | I14: =F14+H14 -> 1313507.9 | J14: =VLOOKUP($A14,[24]HISTOJANV24!$A$6:$AQ$42,22,0) -> 0 | K14: =VLOOKUP($A14,[24]HISTOJANV24!$A$6:$AU$38,45,0) -> 25000 | L14: =IF(K14=0,0,K14-(M14+N14+O14)) -> 19000 | M14: =IF(K14=0,0,1000) -> 1000 | N14: =IF(K14=0,0,1000) -> 1000 | O14: =IF(K14=0,0,4000) -> 4000 | P14: =VLOOKUP($A14,[24]HISTOJANV24!$A$6:$AU$38,7,0) -> 0 | Q14: =VLOOKUP($A14,[24]HISTOJANV24!$A$6:$AU$38,23,0) -> 0 | R14: =VLOOKUP($A14,[24]HISTOJANV24!$A$6:$AU$38,46,0) -> 0 | S14: =VLOOKUP($A14,[24]HISTOJANV24!$A$6:$AU$38,26,0) -> 0 | T14: =VLOOKUP($A14,[24]HISTOJANV24!$A$6:$BG$38,58,0) -> 0 | U14: =VLOOKUP($A14,[24]HISTOJANV24!$A$6:$AU$38,28,0) -> 0 | V14: =VLOOKUP($A14,[24]HISTOJANV24!$A$6:$AU$38,19,0) -> 0 | W14: =VLOOKUP($A14,[24]HISTOJANV24!$A$6:$AU$38,20,0) -> 0 | X14: =VLOOKUP($A14,[24]HISTOJANV24!$A$6:$AU$38,27,0) -> 0 | Y14: =VLOOKUP($A14,[24]HISTOJANV24!$A$6:$BM$38,33,0) -> 0 | Z14: =VLOOKUP($A14,[24]HISTOJANV24!$A$6:$BM$38,65,0) -> 0 | AB14: =VLOOKUP($A14,[24]HISTOJANV24!$A$6:$AU$38,43,0) -> 0 | AC14: =VLOOKUP($A14,[24]HISTOJANV24!$A$6:$AU$38,44,0) -> 0 | AD14: =VLOOKUP($A14,[24]HISTOJANV24!$A$6:$AU$38,47,0) -> 0 | AE14: =VLOOKUP(A14,[24]HISTOJANV24!$A$6:$BB$38,54,0) -> 0 | AF14: =VLOOKUP($A14,[24]HISTOJANV24!$A$6:$CA$38,60,0) -> 0 | AG14: =VLOOKUP($A14,[24]HISTOJANV24!$A$6:$CA$38,61,0) -> 0 | AH14: =VLOOKUP($A14,[24]HISTOJANV24!$A$6:$CA$38,62,0) -> 0 | AI14: =VLOOKUP($A14,[24]HISTOJANV24!$A$6:$CA$38,63,0) -> 0 | AJ14: =VLOOKUP($A14,[24]HISTOJANV24!$A$6:$CA$38,64,0) -> 0 | AK14: =VLOOKUP($A14,[24]HISTOJANV24!$A$6:$CA$38,65,0) -> 0
A15: AS201611 | B15: =VLOOKUP(A15,[19]LISTADHERENT!A$5:H$60,3,0) -> HENGUE PAUL OMER | E15: =VLOOKUP($A15,[24]HISTOJANV24!$A$6:$BA$38,48,0) -> 0 | F15: =MVTDEC23!I15-E15+L15 -> 818434.17 | G15: =IF(MVTDEC23!I15>700000,(MVTDEC23!I15-E15+L15),0) -> 818434.17 | H15: =$T$41/$G$41*G15 -> 6105.2743 | I15: =F15+H15 -> 824539.44 | J15: =VLOOKUP($A15,[24]HISTOJANV24!$A$6:$AQ$42,22,0) -> 0 | K15: =VLOOKUP($A15,[24]HISTOJANV24!$A$6:$AU$38,45,0) -> 25000 | L15: =IF(K15=0,0,K15-(M15+N15+O15)) -> 19000 | M15: =IF(K15=0,0,1000) -> 1000 | N15: =IF(K15=0,0,1000) -> 1000 | O15: =IF(K15=0,0,4000) -> 4000 | P15: =VLOOKUP($A15,[24]HISTOJANV24!$A$6:$AU$38,7,0) -> 0 | Q15: =VLOOKUP($A15,[24]HISTOJANV24!$A$6:$AU$38,23,0) -> 0 | R15: =VLOOKUP($A15,[24]HISTOJANV24!$A$6:$AU$38,46,0) -> 0 | S15: =VLOOKUP($A15,[24]HISTOJANV24!$A$6:$AU$38,26,0) -> 0 | T15: =VLOOKUP($A15,[24]HISTOJANV24!$A$6:$BG$38,58,0) -> 0 | U15: =VLOOKUP($A15,[24]HISTOJANV24!$A$6:$AU$38,28,0) -> 0 | V15: =VLOOKUP($A15,[24]HISTOJANV24!$A$6:$AU$38,19,0) -> 0 | W15: =VLOOKUP($A15,[24]HISTOJANV24!$A$6:$AU$38,20,0) -> 0 | X15: =VLOOKUP($A15,[24]HISTOJANV24!$A$6:$AU$38,27,0) -> 0 | Y15: =VLOOKUP($A15,[24]HISTOJANV24!$A$6:$BM$38,33,0) -> 0 | Z15: =VLOOKUP($A15,[24]HISTOJANV24!$A$6:$BM$38,65,0) -> 0 | AB15: =VLOOKUP($A15,[24]HISTOJANV24!$A$6:$AU$38,43,0) -> 0 | AC15: =VLOOKUP($A15,[24]HISTOJANV24!$A$6:$AU$38,44,0) -> 0 | AD15: =VLOOKUP($A15,[24]HISTOJANV24!$A$6:$AU$38,47,0) -> 0 | AE15: =VLOOKUP(A15,[24]HISTOJANV24!$A$6:$BB$38,54,0) -> 0 | AF15: =VLOOKUP($A15,[24]HISTOJANV24!$A$6:$CA$38,60,0) -> 0 | AG15: =VLOOKUP($A15,[24]HISTOJANV24!$A$6:$CA$38,61,0) -> 0 | AH15: =VLOOKUP($A15,[24]HISTOJANV24!$A$6:$CA$38,62,0) -> 0 | AI15: =VLOOKUP($A15,[24]HISTOJANV24!$A$6:$CA$38,63,0) -> 0 | AJ15: =VLOOKUP($A15,[24]HISTOJANV24!$A$6:$CA$38,64,0) -> 0 | AK15: =VLOOKUP($A15,[24]HISTOJANV24!$A$6:$CA$38,65,0) -> 0
A16: AS201613 | B16: =VLOOKUP(A16,[19]LISTADHERENT!A$5:H$60,3,0) -> HOTCHO BENJAMIN | E16: =VLOOKUP($A16,[24]HISTOJANV24!$A$6:$BA$38,48,0) -> 0 | F16: =MVTDEC23!I16-E16+L16 -> 823648.24 | G16: =IF(MVTDEC23!I16>700000,(MVTDEC23!I16-E16+L16),0) -> 823648.24 | H16: =$T$41/$G$41*G16 -> 6144.1698 | I16: =F16+H16 -> 829792.41 | J16: =VLOOKUP($A16,[24]HISTOJANV24!$A$6:$AQ$42,22,0) -> 0 | K16: =VLOOKUP($A16,[24]HISTOJANV24!$A$6:$AU$38,45,0) -> 60000 | L16: =IF(K16=0,0,K16-(M16+N16+O16)) -> 54000 | M16: =IF(K16=0,0,1000) -> 1000 | N16: =IF(K16=0,0,1000) -> 1000 | O16: =IF(K16=0,0,4000) -> 4000 | P16: =VLOOKUP($A16,[24]HISTOJANV24!$A$6:$AU$38,7,0) -> 0 | Q16: =VLOOKUP($A16,[24]HISTOJANV24!$A$6:$AU$38,23,0) -> 0 | R16: =VLOOKUP($A16,[24]HISTOJANV24!$A$6:$AU$38,46,0) -> 0 | S16: =VLOOKUP($A16,[24]HISTOJANV24!$A$6:$AU$38,26,0) -> 0 | T16: =VLOOKUP($A16,[24]HISTOJANV24!$A$6:$BG$38,58,0) -> 0 | U16: =VLOOKUP($A16,[24]HISTOJANV24!$A$6:$AU$38,28,0) -> 0 | V16: =VLOOKUP($A16,[24]HISTOJANV24!$A$6:$AU$38,19,0) -> 0 | W16: =VLOOKUP($A16,[24]HISTOJANV24!$A$6:$AU$38,20,0) -> 0 | X16: =VLOOKUP($A16,[24]HISTOJANV24!$A$6:$AU$38,27,0) -> 0 | Y16: =VLOOKUP($A16,[24]HISTOJANV24!$A$6:$BM$38,33,0) -> 0 | Z16: =VLOOKUP($A16,[24]HISTOJANV24!$A$6:$BM$38,65,0) -> 0 | AB16: =VLOOKUP($A16,[24]HISTOJANV24!$A$6:$AU$38,43,0) -> 0 | AC16: =VLOOKUP($A16,[24]HISTOJANV24!$A$6:$AU$38,44,0) -> 0 | AD16: =VLOOKUP($A16,[24]HISTOJANV24!$A$6:$AU$38,47,0) -> 0 | AE16: =VLOOKUP(A16,[24]HISTOJANV24!$A$6:$BB$38,54,0) -> 0 | AF16: =VLOOKUP($A16,[24]HISTOJANV24!$A$6:$CA$38,60,0) -> 0 | AG16: =VLOOKUP($A16,[24]HISTOJANV24!$A$6:$CA$38,61,0) -> 0 | AH16: =VLOOKUP($A16,[24]HISTOJANV24!$A$6:$CA$38,62,0) -> 0 | AI16: =VLOOKUP($A16,[24]HISTOJANV24!$A$6:$CA$38,63,0) -> 0 | AJ16: =VLOOKUP($A16,[24]HISTOJANV24!$A$6:$CA$38,64,0) -> 0 | AK16: =VLOOKUP($A16,[24]HISTOJANV24!$A$6:$CA$38,65,0) -> 0
A17: AS201617 | B17: =VLOOKUP(A17,[19]LISTADHERENT!A$5:H$60,3,0) -> KOUAMOU MOISE | E17: =VLOOKUP($A17,[24]HISTOJANV24!$A$6:$BA$38,48,0) -> 0 | F17: =MVTDEC23!I17-E17+L17 -> 767136.92 | G17: =IF(MVTDEC23!I17>700000,(MVTDEC23!I17-E17+L17),0) -> 767136.92 | H17: =$T$41/$G$41*G17 -> 5722.6122 | I17: =F17+H17 -> 772859.53 | J17: =VLOOKUP($A17,[24]HISTOJANV24!$A$6:$AQ$42,22,0) -> 0 | K17: =VLOOKUP($A17,[24]HISTOJANV24!$A$6:$AU$38,45,0) -> 25000 | L17: =IF(K17=0,0,K17-(M17+N17+O17)) -> 19000 | M17: =IF(K17=0,0,1000) -> 1000 | N17: =IF(K17=0,0,1000) -> 1000 | O17: =IF(K17=0,0,4000) -> 4000 | P17: =VLOOKUP($A17,[24]HISTOJANV24!$A$6:$AU$38,7,0) -> 0 | Q17: =VLOOKUP($A17,[24]HISTOJANV24!$A$6:$AU$38,23,0) -> 0 | R17: =VLOOKUP($A17,[24]HISTOJANV24!$A$6:$AU$38,46,0) -> 0 | S17: =VLOOKUP($A17,[24]HISTOJANV24!$A$6:$AU$38,26,0) -> 1000000 | T17: =VLOOKUP($A17,[24]HISTOJANV24!$A$6:$BG$38,58,0) -> 110000 | U17: =VLOOKUP($A17,[24]HISTOJANV24!$A$6:$AU$38,28,0) -> 0 | V17: =VLOOKUP($A17,[24]HISTOJANV24!$A$6:$AU$38,19,0) -> 0 | W17: =VLOOKUP($A17,[24]HISTOJANV24!$A$6:$AU$38,20,0) -> 0 | X17: =VLOOKUP($A17,[24]HISTOJANV24!$A$6:$AU$38,27,0) -> 0 | Y17: =VLOOKUP($A17,[24]HISTOJANV24!$A$6:$BM$38,33,0) -> 0 | Z17: =VLOOKUP($A17,[24]HISTOJANV24!$A$6:$BM$38,65,0) -> 0 | AB17: =VLOOKUP($A17,[24]HISTOJANV24!$A$6:$AU$38,43,0) -> 0 | AC17: =VLOOKUP($A17,[24]HISTOJANV24!$A$6:$AU$38,44,0) -> 0 | AD17: =VLOOKUP($A17,[24]HISTOJANV24!$A$6:$AU$38,47,0) -> 0 | AE17: =VLOOKUP(A17,[24]HISTOJANV24!$A$6:$BB$38,54,0) -> 0 | AF17: =VLOOKUP($A17,[24]HISTOJANV24!$A$6:$CA$38,60,0) -> 0 | AG17: =VLOOKUP($A17,[24]HISTOJANV24!$A$6:$CA$38,61,0) -> 0 | AH17: =VLOOKUP($A17,[24]HISTOJANV24!$A$6:$CA$38,62,0) -> 0 | AI17: =VLOOKUP($A17,[24]HISTOJANV24!$A$6:$CA$38,63,0) -> 100000 | AJ17: =VLOOKUP($A17,[24]HISTOJANV24!$A$6:$CA$38,64,0) -> 0 | AK17: =VLOOKUP($A17,[24]HISTOJANV24!$A$6:$CA$38,65,0) -> 0
A18: AS201619 | B18: =VLOOKUP(A18,[19]LISTADHERENT!A$5:H$60,3,0) -> KOUATCHO MESSACK | E18: =VLOOKUP($A18,[24]HISTOJANV24!$A$6:$BA$38,48,0) -> 0 | F18: =MVTDEC23!I18-E18+L18 -> 783128.91 | G18: =IF(MVTDEC23!I18>700000,(MVTDEC23!I18-E18+L18),0) -> 783128.91 | H18: =$T$41/$G$41*G18 -> 5841.9077 | I18: =F18+H18 -> 788970.81 | J18: =VLOOKUP($A18,[24]HISTOJANV24!$A$6:$AQ$42,22,0) -> 0 | K18: =VLOOKUP($A18,[24]HISTOJANV24!$A$6:$AU$38,45,0) -> 25000 | L18: =IF(K18=0,0,K18-(M18+N18+O18)) -> 19000 | M18: =IF(K18=0,0,1000) -> 1000 | N18: =IF(K18=0,0,1000) -> 1000 | O18: =IF(K18=0,0,4000) -> 4000 | P18: =VLOOKUP($A18,[24]HISTOJANV24!$A$6:$AU$38,7,0) -> 0 | Q18: =VLOOKUP($A18,[24]HISTOJANV24!$A$6:$AU$38,23,0) -> 0 | R18: =VLOOKUP($A18,[24]HISTOJANV24!$A$6:$AU$38,46,0) -> 0 | S18: =VLOOKUP($A18,[24]HISTOJANV24!$A$6:$AU$38,26,0) -> 0 | T18: =VLOOKUP($A18,[24]HISTOJANV24!$A$6:$BG$38,58,0) -> 0 | U18: =VLOOKUP($A18,[24]HISTOJANV24!$A$6:$AU$38,28,0) -> 0 | V18: =VLOOKUP($A18,[24]HISTOJANV24!$A$6:$AU$38,19,0) -> 0 | W18: =VLOOKUP($A18,[24]HISTOJANV24!$A$6:$AU$38,20,0) -> 0 | X18: =VLOOKUP($A18,[24]HISTOJANV24!$A$6:$AU$38,27,0) -> 0 | Y18: =VLOOKUP($A18,[24]HISTOJANV24!$A$6:$BM$38,33,0) -> 0 | Z18: =VLOOKUP($A18,[24]HISTOJANV24!$A$6:$BM$38,65,0) -> 0 | AB18: =VLOOKUP($A18,[24]HISTOJANV24!$A$6:$AU$38,43,0) -> 0 | AC18: =VLOOKUP($A18,[24]HISTOJANV24!$A$6:$AU$38,44,0) -> 0 | AD18: =VLOOKUP($A18,[24]HISTOJANV24!$A$6:$AU$38,47,0) -> 0 | AE18: =VLOOKUP(A18,[24]HISTOJANV24!$A$6:$BB$38,54,0) -> 0 | AF18: =VLOOKUP($A18,[24]HISTOJANV24!$A$6:$CA$38,60,0) -> 0 | AG18: =VLOOKUP($A18,[24]HISTOJANV24!$A$6:$CA$38,61,0) -> 0 | AH18: =VLOOKUP($A18,[24]HISTOJANV24!$A$6:$CA$38,62,0) -> 0 | AI18: =VLOOKUP($A18,[24]HISTOJANV24!$A$6:$CA$38,63,0) -> 0 | AJ18: =VLOOKUP($A18,[24]HISTOJANV24!$A$6:$CA$38,64,0) -> 0 | AK18: =VLOOKUP($A18,[24]HISTOJANV24!$A$6:$CA$38,65,0) -> 0
A19: AS201620 | B19: =VLOOKUP(A19,[19]LISTADHERENT!A$5:H$60,3,0) -> LOWE JEAN | F19: =MVTDEC23!I19-E19+L19 -> 676217.13 | G19: =IF(MVTDEC23!I19>700000,(MVTDEC23!I19-E19+L19),0) -> 0 | H19: =$T$41/$G$41*G19 -> 0 | I19: =F19+H19 -> 676217.13
A20: AS201661 | B20: =VLOOKUP(A20,[19]LISTADHERENT!A$5:H$60,3,0) -> MASSEUNGOUE DAGOBERT | E20: =VLOOKUP($A20,[24]HISTOJANV24!$A$6:$BA$38,48,0) -> 0 | F20: =MVTDEC23!I20-E20+L20 -> 19000 | G20: =IF(MVTDEC23!I20>700000,(MVTDEC23!I20-E20+L20),0) -> 0 | H20: =$T$41/$G$41*G20 -> 0 | I20: =F20+H20 -> 19000 | J20: =VLOOKUP($A20,[24]HISTOJANV24!$A$6:$AQ$42,22,0) -> 0 | K20: =VLOOKUP($A20,[24]HISTOJANV24!$A$6:$AU$38,45,0) -> 25000 | L20: =IF(K20=0,0,K20-(M20+N20+O20)) -> 19000 | M20: =IF(K20=0,0,1000) -> 1000 | N20: =IF(K20=0,0,1000) -> 1000 | O20: =IF(K20=0,0,4000) -> 4000 | P20: =VLOOKUP($A20,[24]HISTOJANV24!$A$6:$AU$38,7,0) -> 0 | Q20: =VLOOKUP($A20,[24]HISTOJANV24!$A$6:$AU$38,23,0) -> 25000 | R20: =VLOOKUP($A20,[24]HISTOJANV24!$A$6:$AU$38,46,0) -> 0 | S20: =VLOOKUP($A20,[24]HISTOJANV24!$A$6:$AU$38,26,0) -> 0 | T20: =VLOOKUP($A20,[24]HISTOJANV24!$A$6:$BG$38,58,0) -> 0 | U20: =VLOOKUP($A20,[24]HISTOJANV24!$A$6:$AU$38,28,0) -> 0 | V20: =VLOOKUP($A20,[24]HISTOJANV24!$A$6:$AU$38,19,0) -> 0 | W20: =VLOOKUP($A20,[24]HISTOJANV24!$A$6:$AU$38,20,0) -> 0 | X20: =VLOOKUP($A20,[24]HISTOJANV24!$A$6:$AU$38,27,0) -> 0 | Y20: =VLOOKUP($A20,[24]HISTOJANV24!$A$6:$BM$38,33,0) -> 0 | Z20: =VLOOKUP($A20,[24]HISTOJANV24!$A$6:$BM$38,65,0) -> 0 | AB20: =VLOOKUP($A20,[24]HISTOJANV24!$A$6:$AU$38,43,0) -> 0 | AC20: =VLOOKUP($A20,[24]HISTOJANV24!$A$6:$AU$38,44,0) -> 0 | AD20: =VLOOKUP($A20,[24]HISTOJANV24!$A$6:$AU$38,47,0) -> 0 | AE20: =VLOOKUP(A20,[24]HISTOJANV24!$A$6:$BB$38,54,0) -> 0 | AF20: =VLOOKUP($A20,[24]HISTOJANV24!$A$6:$CA$38,60,0) -> 0 | AG20: =VLOOKUP($A20,[24]HISTOJANV24!$A$6:$CA$38,61,0) -> 0 | AH20: =VLOOKUP($A20,[24]HISTOJANV24!$A$6:$CA$38,62,0) -> 0 | AI20: =VLOOKUP($A20,[24]HISTOJANV24!$A$6:$CA$38,63,0) -> 0 | AJ20: =VLOOKUP($A20,[24]HISTOJANV24!$A$6:$CA$38,64,0) -> 0 | AK20: =VLOOKUP($A20,[24]HISTOJANV24!$A$6:$CA$38,65,0) -> 0
A21: AS201649 | B21: =VLOOKUP(A21,[19]LISTADHERENT!A$5:H$60,3,0) -> MBOGNING TUGMA GUY | E21: =VLOOKUP($A21,[24]HISTOJANV24!$A$6:$BA$38,48,0) -> 0 | F21: =MVTDEC23!I21-E21+L21 -> 790808.68 | G21: =IF(MVTDEC23!I21>700000,(MVTDEC23!I21-E21+L21),0) -> 790808.68 | H21: =$T$41/$G$41*G21 -> 5899.1965 | I21: =F21+H21 -> 796707.87 | J21: =VLOOKUP($A21,[24]HISTOJANV24!$A$6:$AQ$42,22,0) -> 0 | K21: =VLOOKUP($A21,[24]HISTOJANV24!$A$6:$AU$38,45,0) -> 25000 | L21: =IF(K21=0,0,K21-(M21+N21+O21)) -> 19000 | M21: =IF(K21=0,0,1000) -> 1000 | N21: =IF(K21=0,0,1000) -> 1000 | O21: =IF(K21=0,0,4000) -> 4000 | P21: =VLOOKUP($A21,[24]HISTOJANV24!$A$6:$AU$38,7,0) -> 0 | Q21: =VLOOKUP($A21,[24]HISTOJANV24!$A$6:$AU$38,23,0) -> 0 | R21: =VLOOKUP($A21,[24]HISTOJANV24!$A$6:$AU$38,46,0) -> 0 | S21: =VLOOKUP($A21,[24]HISTOJANV24!$A$6:$AU$38,26,0) -> 0 | T21: =VLOOKUP($A21,[24]HISTOJANV24!$A$6:$BG$38,58,0) -> 0 | U21: =VLOOKUP($A21,[24]HISTOJANV24!$A$6:$AU$38,28,0) -> 0 | V21: =VLOOKUP($A21,[24]HISTOJANV24!$A$6:$AU$38,19,0) -> 0 | W21: =VLOOKUP($A21,[24]HISTOJANV24!$A$6:$AU$38,20,0) -> 0 | X21: =VLOOKUP($A21,[24]HISTOJANV24!$A$6:$AU$38,27,0) -> 0 | Y21: =VLOOKUP($A21,[24]HISTOJANV24!$A$6:$BM$38,33,0) -> 0 | Z21: =VLOOKUP($A21,[24]HISTOJANV24!$A$6:$BM$38,65,0) -> 0 | AB21: =VLOOKUP($A21,[24]HISTOJANV24!$A$6:$AU$38,43,0) -> 0 | AC21: =VLOOKUP($A21,[24]HISTOJANV24!$A$6:$AU$38,44,0) -> 0 | AD21: =VLOOKUP($A21,[24]HISTOJANV24!$A$6:$AU$38,47,0) -> 0 | AE21: =VLOOKUP(A21,[24]HISTOJANV24!$A$6:$BB$38,54,0) -> 0 | AF21: =VLOOKUP($A21,[24]HISTOJANV24!$A$6:$CA$38,60,0) -> 0 | AG21: =VLOOKUP($A21,[24]HISTOJANV24!$A$6:$CA$38,61,0) -> 0 | AH21: =VLOOKUP($A21,[24]HISTOJANV24!$A$6:$CA$38,62,0) -> 0 | AI21: =VLOOKUP($A21,[24]HISTOJANV24!$A$6:$CA$38,63,0) -> 0 | AJ21: =VLOOKUP($A21,[24]HISTOJANV24!$A$6:$CA$38,64,0) -> 0 | AK21: =VLOOKUP($A21,[24]HISTOJANV24!$A$6:$CA$38,65,0) -> 0
A22: AS201639 | B22: =VLOOKUP(A22,[19]LISTADHERENT!A$5:H$60,3,0) -> NANGUEN MARTIN | E22: =VLOOKUP($A22,[24]HISTOJANV24!$A$6:$BA$38,48,0) -> 0 | F22: =MVTDEC23!I22-E22+L22 -> 758574.94 | G22: =IF(MVTDEC23!I22>700000,(MVTDEC23!I22-E22+L22),0) -> 758574.94 | H22: =$T$41/$G$41*G22 -> 5658.7424 | I22: =F22+H22 -> 764233.68 | J22: =VLOOKUP($A22,[24]HISTOJANV24!$A$6:$AQ$42,22,0) -> 0 | K22: =VLOOKUP($A22,[24]HISTOJANV24!$A$6:$AU$38,45,0) -> 25000 | L22: =IF(K22=0,0,K22-(M22+N22+O22)) -> 19000 | M22: =IF(K22=0,0,1000) -> 1000 | N22: =IF(K22=0,0,1000) -> 1000 | O22: =IF(K22=0,0,4000) -> 4000 | P22: =VLOOKUP($A22,[24]HISTOJANV24!$A$6:$AU$38,7,0) -> 0 | Q22: =VLOOKUP($A22,[24]HISTOJANV24!$A$6:$AU$38,23,0) -> 0 | R22: =VLOOKUP($A22,[24]HISTOJANV24!$A$6:$AU$38,46,0) -> 0 | S22: =VLOOKUP($A22,[24]HISTOJANV24!$A$6:$AU$38,26,0) -> 0 | T22: =VLOOKUP($A22,[24]HISTOJANV24!$A$6:$BG$38,58,0) -> 0 | U22: =VLOOKUP($A22,[24]HISTOJANV24!$A$6:$AU$38,28,0) -> 0 | V22: =VLOOKUP($A22,[24]HISTOJANV24!$A$6:$AU$38,19,0) -> 0 | W22: =VLOOKUP($A22,[24]HISTOJANV24!$A$6:$AU$38,20,0) -> 0 | X22: =VLOOKUP($A22,[24]HISTOJANV24!$A$6:$AU$38,27,0) -> 0 | Y22: =VLOOKUP($A22,[24]HISTOJANV24!$A$6:$BM$38,33,0) -> 0 | Z22: =VLOOKUP($A22,[24]HISTOJANV24!$A$6:$BM$38,65,0) -> 0 | AB22: =VLOOKUP($A22,[24]HISTOJANV24!$A$6:$AU$38,43,0) -> 0 | AC22: =VLOOKUP($A22,[24]HISTOJANV24!$A$6:$AU$38,44,0) -> 0 | AD22: =VLOOKUP($A22,[24]HISTOJANV24!$A$6:$AU$38,47,0) -> 0 | AE22: =VLOOKUP(A22,[24]HISTOJANV24!$A$6:$BB$38,54,0) -> 0 | AF22: =VLOOKUP($A22,[24]HISTOJANV24!$A$6:$CA$38,60,0) -> 0 | AG22: =VLOOKUP($A22,[24]HISTOJANV24!$A$6:$CA$38,61,0) -> 0 | AH22: =VLOOKUP($A22,[24]HISTOJANV24!$A$6:$CA$38,62,0) -> 0 | AI22: =VLOOKUP($A22,[24]HISTOJANV24!$A$6:$CA$38,63,0) -> 0 | AJ22: =VLOOKUP($A22,[24]HISTOJANV24!$A$6:$CA$38,64,0) -> 0 | AK22: =VLOOKUP($A22,[24]HISTOJANV24!$A$6:$CA$38,65,0) -> 0
A23: AS201621 | B23: =VLOOKUP(A23,[19]LISTADHERENT!A$5:H$60,3,0) -> NANKAM APPOLINAIRE | E23: =VLOOKUP($A23,[24]HISTOJANV24!$A$6:$BA$38,48,0) -> 0 | F23: =MVTDEC23!I23-E23+L23 -> 863266.03 | G23: =IF(MVTDEC23!I23>700000,(MVTDEC23!I23-E23+L23),0) -> 863266.03 | H23: =$T$41/$G$41*G23 -> 6439.7067 | I23: =F23+H23 -> 869705.74 | J23: =VLOOKUP($A23,[24]HISTOJANV24!$A$6:$AQ$42,22,0) -> 0 | K23: =VLOOKUP($A23,[24]HISTOJANV24!$A$6:$AU$38,45,0) -> 25000 | L23: =IF(K23=0,0,K23-(M23+N23+O23)) -> 19000 | M23: =IF(K23=0,0,1000) -> 1000 | N23: =IF(K23=0,0,1000) -> 1000 | O23: =IF(K23=0,0,4000) -> 4000 | P23: =VLOOKUP($A23,[24]HISTOJANV24!$A$6:$AU$38,7,0) -> 0 | Q23: =VLOOKUP($A23,[24]HISTOJANV24!$A$6:$AU$38,23,0) -> 0 | R23: =VLOOKUP($A23,[24]HISTOJANV24!$A$6:$AU$38,46,0) -> 0 | S23: =VLOOKUP($A23,[24]HISTOJANV24!$A$6:$AU$38,26,0) -> 0 | T23: =VLOOKUP($A23,[24]HISTOJANV24!$A$6:$BG$38,58,0) -> 0 | U23: =VLOOKUP($A23,[24]HISTOJANV24!$A$6:$AU$38,28,0) -> 0 | V23: =VLOOKUP($A23,[24]HISTOJANV24!$A$6:$AU$38,19,0) -> 0 | W23: =VLOOKUP($A23,[24]HISTOJANV24!$A$6:$AU$38,20,0) -> 0 | X23: =VLOOKUP($A23,[24]HISTOJANV24!$A$6:$AU$38,27,0) -> 0 | Y23: =VLOOKUP($A23,[24]HISTOJANV24!$A$6:$BM$38,33,0) -> 0 | Z23: =VLOOKUP($A23,[24]HISTOJANV24!$A$6:$BM$38,65,0) -> 0 | AB23: =VLOOKUP($A23,[24]HISTOJANV24!$A$6:$AU$38,43,0) -> 0 | AC23: =VLOOKUP($A23,[24]HISTOJANV24!$A$6:$AU$38,44,0) -> 0 | AD23: =VLOOKUP($A23,[24]HISTOJANV24!$A$6:$AU$38,47,0) -> 0 | AE23: =VLOOKUP(A23,[24]HISTOJANV24!$A$6:$BB$38,54,0) -> 0 | AF23: =VLOOKUP($A23,[24]HISTOJANV24!$A$6:$CA$38,60,0) -> 0 | AG23: =VLOOKUP($A23,[24]HISTOJANV24!$A$6:$CA$38,61,0) -> 0 | AH23: =VLOOKUP($A23,[24]HISTOJANV24!$A$6:$CA$38,62,0) -> 0 | AI23: =VLOOKUP($A23,[24]HISTOJANV24!$A$6:$CA$38,63,0) -> 0 | AJ23: =VLOOKUP($A23,[24]HISTOJANV24!$A$6:$CA$38,64,0) -> 0 | AK23: =VLOOKUP($A23,[24]HISTOJANV24!$A$6:$CA$38,65,0) -> 0
A24: AS201622 | B24: =VLOOKUP(A24,[19]LISTADHERENT!A$5:H$60,3,0) -> NDJOMO ETIENNE | E24: =VLOOKUP($A24,[24]HISTOJANV24!$A$6:$BA$38,48,0) -> 0 | F24: =MVTDEC23!I24-E24+L24 -> 1004661 | G24: =IF(MVTDEC23!I24>700000,(MVTDEC23!I24-E24+L24),0) -> 1004661 | H24: =$T$41/$G$41*G24 -> 7494.4712 | I24: =F24+H24 -> 1012155.5 | J24: =VLOOKUP($A24,[24]HISTOJANV24!$A$6:$AQ$42,22,0) -> 0 | K24: =VLOOKUP($A24,[24]HISTOJANV24!$A$6:$AU$38,45,0) -> 35000 | L24: =IF(K24=0,0,K24-(M24+N24+O24)) -> 29000 | M24: =IF(K24=0,0,1000) -> 1000 | N24: =IF(K24=0,0,1000) -> 1000 | O24: =IF(K24=0,0,4000) -> 4000 | P24: =VLOOKUP($A24,[24]HISTOJANV24!$A$6:$AU$38,7,0) -> 0 | Q24: =VLOOKUP($A24,[24]HISTOJANV24!$A$6:$AU$38,23,0) -> 0 | R24: =VLOOKUP($A24,[24]HISTOJANV24!$A$6:$AU$38,46,0) -> 0 | S24: =VLOOKUP($A24,[24]HISTOJANV24!$A$6:$AU$38,26,0) -> 0 | T24: =VLOOKUP($A24,[24]HISTOJANV24!$A$6:$BG$38,58,0) -> 0 | U24: =VLOOKUP($A24,[24]HISTOJANV24!$A$6:$AU$38,28,0) -> 0 | V24: =VLOOKUP($A24,[24]HISTOJANV24!$A$6:$AU$38,19,0) -> 0 | W24: =VLOOKUP($A24,[24]HISTOJANV24!$A$6:$AU$38,20,0) -> 0 | X24: =VLOOKUP($A24,[24]HISTOJANV24!$A$6:$AU$38,27,0) -> 0 | Y24: =VLOOKUP($A24,[24]HISTOJANV24!$A$6:$BM$38,33,0) -> 0 | Z24: =VLOOKUP($A24,[24]HISTOJANV24!$A$6:$BM$38,65,0) -> 0 | AB24: =VLOOKUP($A24,[24]HISTOJANV24!$A$6:$AU$38,43,0) -> 0 | AC24: =VLOOKUP($A24,[24]HISTOJANV24!$A$6:$AU$38,44,0) -> 0 | AD24: =VLOOKUP($A24,[24]HISTOJANV24!$A$6:$AU$38,47,0) -> 0 | AE24: =VLOOKUP(A24,[24]HISTOJANV24!$A$6:$BB$38,54,0) -> 0 | AF24: =VLOOKUP($A24,[24]HISTOJANV24!$A$6:$CA$38,60,0) -> 0 | AG24: =VLOOKUP($A24,[24]HISTOJANV24!$A$6:$CA$38,61,0) -> 0 | AH24: =VLOOKUP($A24,[24]HISTOJANV24!$A$6:$CA$38,62,0) -> 0 | AI24: =VLOOKUP($A24,[24]HISTOJANV24!$A$6:$CA$38,63,0) -> 0 | AJ24: =VLOOKUP($A24,[24]HISTOJANV24!$A$6:$CA$38,64,0) -> 0 | AK24: =VLOOKUP($A24,[24]HISTOJANV24!$A$6:$CA$38,65,0) -> 0
A25: AS201624 | B25: =VLOOKUP(A25,[19]LISTADHERENT!A$5:H$60,3,0) -> NGONDIEP CLAUDE | E25: =VLOOKUP($A25,[24]HISTOJANV24!$A$6:$BA$38,48,0) -> 0 | F25: =MVTDEC23!I25-E25+L25 -> 818152.67 | G25: =IF(MVTDEC23!I25>700000,(MVTDEC23!I25-E25+L25),0) -> 818152.67 | H25: =$T$41/$G$41*G25 -> 6103.1745 | I25: =F25+H25 -> 824255.84 | J25: =VLOOKUP($A25,[24]HISTOJANV24!$A$6:$AQ$42,22,0) -> 0 | K25: =VLOOKUP($A25,[24]HISTOJANV24!$A$6:$AU$38,45,0) -> 25000 | L25: =IF(K25=0,0,K25-(M25+N25+O25)) -> 19000 | M25: =IF(K25=0,0,1000) -> 1000 | N25: =IF(K25=0,0,1000) -> 1000 | O25: =IF(K25=0,0,4000) -> 4000 | P25: =VLOOKUP($A25,[24]HISTOJANV24!$A$6:$AU$38,7,0) -> 0 | Q25: =VLOOKUP($A25,[24]HISTOJANV24!$A$6:$AU$38,23,0) -> 0 | R25: =VLOOKUP($A25,[24]HISTOJANV24!$A$6:$AU$38,46,0) -> 0 | S25: =VLOOKUP($A25,[24]HISTOJANV24!$A$6:$AU$38,26,0) -> 0 | T25: =VLOOKUP($A25,[24]HISTOJANV24!$A$6:$BG$38,58,0) -> 0 | U25: =VLOOKUP($A25,[24]HISTOJANV24!$A$6:$AU$38,28,0) -> 0 | V25: =VLOOKUP($A25,[24]HISTOJANV24!$A$6:$AU$38,19,0) -> 0 | W25: =VLOOKUP($A25,[24]HISTOJANV24!$A$6:$AU$38,20,0) -> 0 | X25: =VLOOKUP($A25,[24]HISTOJANV24!$A$6:$AU$38,27,0) -> 0 | Y25: =VLOOKUP($A25,[24]HISTOJANV24!$A$6:$BM$38,33,0) -> 0 | Z25: =VLOOKUP($A25,[24]HISTOJANV24!$A$6:$BM$38,65,0) -> 0 | AB25: =VLOOKUP($A25,[24]HISTOJANV24!$A$6:$AU$38,43,0) -> 0 | AC25: =VLOOKUP($A25,[24]HISTOJANV24!$A$6:$AU$38,44,0) -> 0 | AD25: =VLOOKUP($A25,[24]HISTOJANV24!$A$6:$AU$38,47,0) -> 0 | AE25: =VLOOKUP(A25,[24]HISTOJANV24!$A$6:$BB$38,54,0) -> 0 | AF25: =VLOOKUP($A25,[24]HISTOJANV24!$A$6:$CA$38,60,0) -> 0 | AG25: =VLOOKUP($A25,[24]HISTOJANV24!$A$6:$CA$38,61,0) -> 0 | AH25: =VLOOKUP($A25,[24]HISTOJANV24!$A$6:$CA$38,62,0) -> 0 | AI25: =VLOOKUP($A25,[24]HISTOJANV24!$A$6:$CA$38,63,0) -> 0 | AJ25: =VLOOKUP($A25,[24]HISTOJANV24!$A$6:$CA$38,64,0) -> 0 | AK25: =VLOOKUP($A25,[24]HISTOJANV24!$A$6:$CA$38,65,0) -> 0
A26: AS201626 | B26: =VLOOKUP(A26,[19]LISTADHERENT!A$5:H$60,3,0) -> NGUIEMEGNI MATHIEU BLAISE | E26: =VLOOKUP($A26,[24]HISTOJANV24!$A$6:$BA$38,48,0) -> 0 | F26: =MVTDEC23!I26-E26+L26 -> 778861.34 | G26: =IF(MVTDEC23!I26>700000,(MVTDEC23!I26-E26+L26),0) -> 778861.34 | H26: =$T$41/$G$41*G26 -> 5810.0729 | I26: =F26+H26 -> 784671.42 | J26: =VLOOKUP($A26,[24]HISTOJANV24!$A$6:$AQ$42,22,0) -> 0 | K26: =VLOOKUP($A26,[24]HISTOJANV24!$A$6:$AU$38,45,0) -> 25000 | L26: =IF(K26=0,0,K26-(M26+N26+O26)) -> 19000 | M26: =IF(K26=0,0,1000) -> 1000 | N26: =IF(K26=0,0,1000) -> 1000 | O26: =IF(K26=0,0,4000) -> 4000 | P26: =VLOOKUP($A26,[24]HISTOJANV24!$A$6:$AU$38,7,0) -> 0 | Q26: =VLOOKUP($A26,[24]HISTOJANV24!$A$6:$AU$38,23,0) -> 0 | R26: =VLOOKUP($A26,[24]HISTOJANV24!$A$6:$AU$38,46,0) -> 0 | S26: =VLOOKUP($A26,[24]HISTOJANV24!$A$6:$AU$38,26,0) -> 0 | T26: =VLOOKUP($A26,[24]HISTOJANV24!$A$6:$BG$38,58,0) -> 0 | U26: =VLOOKUP($A26,[24]HISTOJANV24!$A$6:$AU$38,28,0) -> 0 | V26: =VLOOKUP($A26,[24]HISTOJANV24!$A$6:$AU$38,19,0) -> 0 | W26: =VLOOKUP($A26,[24]HISTOJANV24!$A$6:$AU$38,20,0) -> 0 | X26: =VLOOKUP($A26,[24]HISTOJANV24!$A$6:$AU$38,27,0) -> 0 | Y26: =VLOOKUP($A26,[24]HISTOJANV24!$A$6:$BM$38,33,0) -> 0 | Z26: =VLOOKUP($A26,[24]HISTOJANV24!$A$6:$BM$38,65,0) -> 0 | AB26: =VLOOKUP($A26,[24]HISTOJANV24!$A$6:$AU$38,43,0) -> 0 | AC26: =VLOOKUP($A26,[24]HISTOJANV24!$A$6:$AU$38,44,0) -> 0 | AD26: =VLOOKUP($A26,[24]HISTOJANV24!$A$6:$AU$38,47,0) -> 0 | AE26: =VLOOKUP(A26,[24]HISTOJANV24!$A$6:$BB$38,54,0) -> 0 | AF26: =VLOOKUP($A26,[24]HISTOJANV24!$A$6:$CA$38,60,0) -> 0 | AG26: =VLOOKUP($A26,[24]HISTOJANV24!$A$6:$CA$38,61,0) -> 0 | AH26: =VLOOKUP($A26,[24]HISTOJANV24!$A$6:$CA$38,62,0) -> 0 | AI26: =VLOOKUP($A26,[24]HISTOJANV24!$A$6:$CA$38,63,0) -> 0 | AJ26: =VLOOKUP($A26,[24]HISTOJANV24!$A$6:$CA$38,64,0) -> 0 | AK26: =VLOOKUP($A26,[24]HISTOJANV24!$A$6:$CA$38,65,0) -> 0
A27: AS201628 | B27: =VLOOKUP(A27,[19]LISTADHERENT!A$5:H$60,3,0) -> NKAMGANG JUSTIN DEJOLIE | E27: =VLOOKUP($A27,[24]HISTOJANV24!$A$6:$BA$38,48,0) -> 0 | F27: =MVTDEC23!I27-E27+L27 -> 777435.99 | G27: =IF(MVTDEC23!I27>700000,(MVTDEC23!I27-E27+L27),0) -> 777435.99 | H27: =$T$41/$G$41*G27 -> 5799.4402 | I27: =F27+H27 -> 783235.43 | J27: =VLOOKUP($A27,[24]HISTOJANV24!$A$6:$AQ$42,22,0) -> 0 | K27: =VLOOKUP($A27,[24]HISTOJANV24!$A$6:$AU$38,45,0) -> 25000 | L27: =IF(K27=0,0,K27-(M27+N27+O27)) -> 19000 | M27: =IF(K27=0,0,1000) -> 1000 | N27: =IF(K27=0,0,1000) -> 1000 | O27: =IF(K27=0,0,4000) -> 4000 | P27: =VLOOKUP($A27,[24]HISTOJANV24!$A$6:$AU$38,7,0) -> 0 | Q27: =VLOOKUP($A27,[24]HISTOJANV24!$A$6:$AU$38,23,0) -> 0 | R27: =VLOOKUP($A27,[24]HISTOJANV24!$A$6:$AU$38,46,0) -> 0 | S27: =VLOOKUP($A27,[24]HISTOJANV24!$A$6:$AU$38,26,0) -> 0 | T27: =VLOOKUP($A27,[24]HISTOJANV24!$A$6:$BG$38,58,0) -> 0 | U27: =VLOOKUP($A27,[24]HISTOJANV24!$A$6:$AU$38,28,0) -> 0 | V27: =VLOOKUP($A27,[24]HISTOJANV24!$A$6:$AU$38,19,0) -> 0 | W27: =VLOOKUP($A27,[24]HISTOJANV24!$A$6:$AU$38,20,0) -> 0 | X27: =VLOOKUP($A27,[24]HISTOJANV24!$A$6:$AU$38,27,0) -> 0 | Y27: =VLOOKUP($A27,[24]HISTOJANV24!$A$6:$BM$38,33,0) -> 0 | Z27: =VLOOKUP($A27,[24]HISTOJANV24!$A$6:$BM$38,65,0) -> 0 | AB27: =VLOOKUP($A27,[24]HISTOJANV24!$A$6:$AU$38,43,0) -> 0 | AC27: =VLOOKUP($A27,[24]HISTOJANV24!$A$6:$AU$38,44,0) -> 0 | AD27: =VLOOKUP($A27,[24]HISTOJANV24!$A$6:$AU$38,47,0) -> 0 | AE27: =VLOOKUP(A27,[24]HISTOJANV24!$A$6:$BB$38,54,0) -> 0 | AF27: =VLOOKUP($A27,[24]HISTOJANV24!$A$6:$CA$38,60,0) -> 0 | AG27: =VLOOKUP($A27,[24]HISTOJANV24!$A$6:$CA$38,61,0) -> 0 | AH27: =VLOOKUP($A27,[24]HISTOJANV24!$A$6:$CA$38,62,0) -> 0 | AI27: =VLOOKUP($A27,[24]HISTOJANV24!$A$6:$CA$38,63,0) -> 0 | AJ27: =VLOOKUP($A27,[24]HISTOJANV24!$A$6:$CA$38,64,0) -> 0 | AK27: =VLOOKUP($A27,[24]HISTOJANV24!$A$6:$CA$38,65,0) -> 0
A28: AS201656 | B28: =VLOOKUP(A28,[19]LISTADHERENT!A$5:H$60,3,0) -> NOUBE ETIENNE | E28: =VLOOKUP($A28,[24]HISTOJANV24!$A$6:$BA$38,48,0) -> 0 | F28: =MVTDEC23!I28-E28+L28 -> 685018.82 | G28: =IF(MVTDEC23!I28>700000,(MVTDEC23!I28-E28+L28),0) -> 0 | H28: =$T$41/$G$41*G28 -> 0 | I28: =F28+H28 -> 685018.82 | J28: =VLOOKUP($A28,[24]HISTOJANV24!$A$6:$AQ$42,22,0) -> 0 | K28: =VLOOKUP($A28,[24]HISTOJANV24!$A$6:$AU$38,45,0) -> 25000 | L28: =IF(K28=0,0,K28-(M28+N28+O28)) -> 19000 | M28: =IF(K28=0,0,1000) -> 1000 | N28: =IF(K28=0,0,1000) -> 1000 | O28: =IF(K28=0,0,4000) -> 4000 | P28: =VLOOKUP($A28,[24]HISTOJANV24!$A$6:$AU$38,7,0) -> 0 | Q28: =VLOOKUP($A28,[24]HISTOJANV24!$A$6:$AU$38,23,0) -> 0 | R28: =VLOOKUP($A28,[24]HISTOJANV24!$A$6:$AU$38,46,0) -> 0 | S28: =VLOOKUP($A28,[24]HISTOJANV24!$A$6:$AU$38,26,0) -> 0 | T28: =VLOOKUP($A28,[24]HISTOJANV24!$A$6:$BG$38,58,0) -> 0 | U28: =VLOOKUP($A28,[24]HISTOJANV24!$A$6:$AU$38,28,0) -> 0 | V28: =VLOOKUP($A28,[24]HISTOJANV24!$A$6:$AU$38,19,0) -> 0 | W28: =VLOOKUP($A28,[24]HISTOJANV24!$A$6:$AU$38,20,0) -> 0 | X28: =VLOOKUP($A28,[24]HISTOJANV24!$A$6:$AU$38,27,0) -> 0 | Y28: =VLOOKUP($A28,[24]HISTOJANV24!$A$6:$BM$38,33,0) -> 0 | Z28: =VLOOKUP($A28,[24]HISTOJANV24!$A$6:$BM$38,65,0) -> 0 | AB28: =VLOOKUP($A28,[24]HISTOJANV24!$A$6:$AU$38,43,0) -> 0 | AC28: =VLOOKUP($A28,[24]HISTOJANV24!$A$6:$AU$38,44,0) -> 0 | AD28: =VLOOKUP($A28,[24]HISTOJANV24!$A$6:$AU$38,47,0) -> 0 | AE28: =VLOOKUP(A28,[24]HISTOJANV24!$A$6:$BB$38,54,0) -> 0 | AF28: =VLOOKUP($A28,[24]HISTOJANV24!$A$6:$CA$38,60,0) -> 0 | AG28: =VLOOKUP($A28,[24]HISTOJANV24!$A$6:$CA$38,61,0) -> 0 | AH28: =VLOOKUP($A28,[24]HISTOJANV24!$A$6:$CA$38,62,0) -> 0 | AI28: =VLOOKUP($A28,[24]HISTOJANV24!$A$6:$CA$38,63,0) -> 0 | AJ28: =VLOOKUP($A28,[24]HISTOJANV24!$A$6:$CA$38,64,0) -> 0 | AK28: =VLOOKUP($A28,[24]HISTOJANV24!$A$6:$CA$38,65,0) -> 0
A29: AS201633 | B29: =VLOOKUP(A29,[19]LISTADHERENT!A$5:H$60,3,0) -> PATEGO NJOSSU GUSTAVE | E29: =VLOOKUP($A29,[24]HISTOJANV24!$A$6:$BA$38,48,0) -> 0 | F29: =MVTDEC23!I29-E29+L29 -> 803453.93 | G29: =IF(MVTDEC23!I29>700000,(MVTDEC23!I29-E29+L29),0) -> 803453.93 | H29: =$T$41/$G$41*G29 -> 5993.5263 | I29: =F29+H29 -> 809447.46 | J29: =VLOOKUP($A29,[24]HISTOJANV24!$A$6:$AQ$42,22,0) -> 0 | K29: =VLOOKUP($A29,[24]HISTOJANV24!$A$6:$AU$38,45,0) -> 25000 | L29: =IF(K29=0,0,K29-(M29+N29+O29)) -> 19000 | M29: =IF(K29=0,0,1000) -> 1000 | N29: =IF(K29=0,0,1000) -> 1000 | O29: =IF(K29=0,0,4000) -> 4000 | P29: =VLOOKUP($A29,[24]HISTOJANV24!$A$6:$AU$38,7,0) -> 0 | Q29: =VLOOKUP($A29,[24]HISTOJANV24!$A$6:$AU$38,23,0) -> 0 | R29: =VLOOKUP($A29,[24]HISTOJANV24!$A$6:$AU$38,46,0) -> 0 | S29: =VLOOKUP($A29,[24]HISTOJANV24!$A$6:$AU$38,26,0) -> 0 | T29: =VLOOKUP($A29,[24]HISTOJANV24!$A$6:$BG$38,58,0) -> 0 | U29: =VLOOKUP($A29,[24]HISTOJANV24!$A$6:$AU$38,28,0) -> 0 | V29: =VLOOKUP($A29,[24]HISTOJANV24!$A$6:$AU$38,19,0) -> 0 | W29: =VLOOKUP($A29,[24]HISTOJANV24!$A$6:$AU$38,20,0) -> 0 | X29: =VLOOKUP($A29,[24]HISTOJANV24!$A$6:$AU$38,27,0) -> 0 | Y29: =VLOOKUP($A29,[24]HISTOJANV24!$A$6:$BM$38,33,0) -> 0 | Z29: =VLOOKUP($A29,[24]HISTOJANV24!$A$6:$BM$38,65,0) -> 0 | AB29: =VLOOKUP($A29,[24]HISTOJANV24!$A$6:$AU$38,43,0) -> 0 | AC29: =VLOOKUP($A29,[24]HISTOJANV24!$A$6:$AU$38,44,0) -> 0 | AD29: =VLOOKUP($A29,[24]HISTOJANV24!$A$6:$AU$38,47,0) -> 0 | AE29: =VLOOKUP(A29,[24]HISTOJANV24!$A$6:$BB$38,54,0) -> 0 | AF29: =VLOOKUP($A29,[24]HISTOJANV24!$A$6:$CA$38,60,0) -> 0 | AG29: =VLOOKUP($A29,[24]HISTOJANV24!$A$6:$CA$38,61,0) -> 0 | AH29: =VLOOKUP($A29,[24]HISTOJANV24!$A$6:$CA$38,62,0) -> 0 | AI29: =VLOOKUP($A29,[24]HISTOJANV24!$A$6:$CA$38,63,0) -> 0 | AJ29: =VLOOKUP($A29,[24]HISTOJANV24!$A$6:$CA$38,64,0) -> 0 | AK29: =VLOOKUP($A29,[24]HISTOJANV24!$A$6:$CA$38,65,0) -> 0
A30: AS201657 | B30: =VLOOKUP(A30,[19]LISTADHERENT!A$5:H$60,3,0) -> SEUMO POLYCARPE | E30: =VLOOKUP($A30,[24]HISTOJANV24!$A$6:$BA$38,48,0) -> 0 | F30: =MVTDEC23!I30-E30+L30 -> 714500 | G30: =IF(MVTDEC23!I30>700000,(MVTDEC23!I30-E30+L30),0) -> 0 | H30: =$T$41/$G$41*G30 -> 0 | I30: =F30+H30 -> 714500 | J30: =VLOOKUP($A30,[24]HISTOJANV24!$A$6:$AQ$42,22,0) -> 0 | K30: =VLOOKUP($A30,[24]HISTOJANV24!$A$6:$AU$38,45,0) -> 475000 | L30: =IF(K30=0,0,K30-(M30+N30+O30)) -> 469000 | M30: =IF(K30=0,0,1000) -> 1000 | N30: =IF(K30=0,0,1000) -> 1000 | O30: =IF(K30=0,0,4000) -> 4000 | P30: =VLOOKUP($A30,[24]HISTOJANV24!$A$6:$AU$38,7,0) -> 0 | Q30: =VLOOKUP($A30,[24]HISTOJANV24!$A$6:$AU$38,23,0) -> 0 | R30: =VLOOKUP($A30,[24]HISTOJANV24!$A$6:$AU$38,46,0) -> 0 | S30: =VLOOKUP($A30,[24]HISTOJANV24!$A$6:$AU$38,26,0) -> 0 | T30: =VLOOKUP($A30,[24]HISTOJANV24!$A$6:$BG$38,58,0) -> 0 | U30: =VLOOKUP($A30,[24]HISTOJANV24!$A$6:$AU$38,28,0) -> 0 | V30: =VLOOKUP($A30,[24]HISTOJANV24!$A$6:$AU$38,19,0) -> 0 | W30: =VLOOKUP($A30,[24]HISTOJANV24!$A$6:$AU$38,20,0) -> 0 | X30: =VLOOKUP($A30,[24]HISTOJANV24!$A$6:$AU$38,27,0) -> 0 | Y30: =VLOOKUP($A30,[24]HISTOJANV24!$A$6:$BM$38,33,0) -> 0 | Z30: =VLOOKUP($A30,[24]HISTOJANV24!$A$6:$BM$38,65,0) -> 0 | AB30: =VLOOKUP($A30,[24]HISTOJANV24!$A$6:$AU$38,43,0) -> 0 | AC30: =VLOOKUP($A30,[24]HISTOJANV24!$A$6:$AU$38,44,0) -> 0 | AD30: =VLOOKUP($A30,[24]HISTOJANV24!$A$6:$AU$38,47,0) -> 0 | AE30: =VLOOKUP(A30,[24]HISTOJANV24!$A$6:$BB$38,54,0) -> 0 | AF30: =VLOOKUP($A30,[24]HISTOJANV24!$A$6:$CA$38,60,0) -> 0 | AG30: =VLOOKUP($A30,[24]HISTOJANV24!$A$6:$CA$38,61,0) -> 0 | AH30: =VLOOKUP($A30,[24]HISTOJANV24!$A$6:$CA$38,62,0) -> 0 | AI30: =VLOOKUP($A30,[24]HISTOJANV24!$A$6:$CA$38,63,0) -> 0 | AJ30: =VLOOKUP($A30,[24]HISTOJANV24!$A$6:$CA$38,64,0) -> 0 | AK30: =VLOOKUP($A30,[24]HISTOJANV24!$A$6:$CA$38,65,0) -> 0
A31: AS201653 | B31: =VLOOKUP(A31,[19]LISTADHERENT!A$5:H$60,3,0) -> SIME BRICE | E31: =VLOOKUP($A31,[24]HISTOJANV24!$A$6:$BA$38,48,0) -> 0 | F31: =MVTDEC23!I31-E31+L31 -> 867445.07 | G31: =IF(MVTDEC23!I31>700000,(MVTDEC23!I31-E31+L31),0) -> 867445.07 | H31: =$T$41/$G$41*G31 -> 6470.8811 | I31: =F31+H31 -> 873915.95 | J31: =VLOOKUP($A31,[24]HISTOJANV24!$A$6:$AQ$42,22,0) -> 0 | K31: =VLOOKUP($A31,[24]HISTOJANV24!$A$6:$AU$38,45,0) -> 25000 | L31: =IF(K31=0,0,K31-(M31+N31+O31)) -> 19000 | M31: =IF(K31=0,0,1000) -> 1000 | N31: =IF(K31=0,0,1000) -> 1000 | O31: =IF(K31=0,0,4000) -> 4000 | P31: =VLOOKUP($A31,[24]HISTOJANV24!$A$6:$AU$38,7,0) -> 0 | Q31: =VLOOKUP($A31,[24]HISTOJANV24!$A$6:$AU$38,23,0) -> 0 | R31: =VLOOKUP($A31,[24]HISTOJANV24!$A$6:$AU$38,46,0) -> 0 | S31: =VLOOKUP($A31,[24]HISTOJANV24!$A$6:$AU$38,26,0) -> 0 | T31: =VLOOKUP($A31,[24]HISTOJANV24!$A$6:$BG$38,58,0) -> 0 | U31: =VLOOKUP($A31,[24]HISTOJANV24!$A$6:$AU$38,28,0) -> 0 | V31: =VLOOKUP($A31,[24]HISTOJANV24!$A$6:$AU$38,19,0) -> 0 | W31: =VLOOKUP($A31,[24]HISTOJANV24!$A$6:$AU$38,20,0) -> 0 | X31: =VLOOKUP($A31,[24]HISTOJANV24!$A$6:$AU$38,27,0) -> 0 | Y31: =VLOOKUP($A31,[24]HISTOJANV24!$A$6:$BM$38,33,0) -> 0 | Z31: =VLOOKUP($A31,[24]HISTOJANV24!$A$6:$BM$38,65,0) -> 0 | AB31: =VLOOKUP($A31,[24]HISTOJANV24!$A$6:$AU$38,43,0) -> 0 | AC31: =VLOOKUP($A31,[24]HISTOJANV24!$A$6:$AU$38,44,0) -> 0 | AD31: =VLOOKUP($A31,[24]HISTOJANV24!$A$6:$AU$38,47,0) -> 0 | AE31: =VLOOKUP(A31,[24]HISTOJANV24!$A$6:$BB$38,54,0) -> 0 | AF31: =VLOOKUP($A31,[24]HISTOJANV24!$A$6:$CA$38,60,0) -> 0 | AG31: =VLOOKUP($A31,[24]HISTOJANV24!$A$6:$CA$38,61,0) -> 0 | AH31: =VLOOKUP($A31,[24]HISTOJANV24!$A$6:$CA$38,62,0) -> 0 | AI31: =VLOOKUP($A31,[24]HISTOJANV24!$A$6:$CA$38,63,0) -> 0 | AJ31: =VLOOKUP($A31,[24]HISTOJANV24!$A$6:$CA$38,64,0) -> 0 | AK31: =VLOOKUP($A31,[24]HISTOJANV24!$A$6:$CA$38,65,0) -> 0
... A39: AS201647 | B39: =VLOOKUP(A39,[19]LISTADHERENT!A$5:H$60,3,0) -> YOUMBI EMMANUEL | E39: =VLOOKUP($A39,[24]HISTOJANV24!$A$6:$BA$38,48,0) -> 0 | F39: =MVTDEC23!I39-E39+L39 -> 1978648.4 | G39: =IF(MVTDEC23!I39>700000,(MVTDEC23!I39-E39+L39),0) -> 1978648.4 | H39: =$T$41/$G$41*G39 -> 14760.126 | I39: =F39+H39 -> 1993408.5 | J39: =VLOOKUP($A39,[24]HISTOJANV24!$A$6:$AQ$42,22,0) -> 0 | K39: =VLOOKUP($A39,[24]HISTOJANV24!$A$6:$AU$38,45,0) -> 25000 | L39: =IF(K39=0,0,K39-(M39+N39+O39)) -> 19000 | M39: =IF(K39=0,0,1000) -> 1000 | N39: =IF(K39=0,0,1000) -> 1000 | O39: =IF(K39=0,0,4000) -> 4000 | P39: =VLOOKUP($A39,[24]HISTOJANV24!$A$6:$AU$38,7,0) -> 0 | Q39: =VLOOKUP($A39,[24]HISTOJANV24!$A$6:$AU$38,23,0) -> 0 | R39: =VLOOKUP($A39,[24]HISTOJANV24!$A$6:$AU$38,46,0) -> 0 | S39: =VLOOKUP($A39,[24]HISTOJANV24!$A$6:$AU$38,26,0) -> 0 | T39: =VLOOKUP($A39,[24]HISTOJANV24!$A$6:$BG$38,58,0) -> 0 | U39: =VLOOKUP($A39,[24]HISTOJANV24!$A$6:$AU$38,28,0) -> 0 | V39: =VLOOKUP($A39,[24]HISTOJANV24!$A$6:$AU$38,19,0) -> 0 | W39: =VLOOKUP($A39,[24]HISTOJANV24!$A$6:$AU$38,20,0) -> 0 | X39: =VLOOKUP($A39,[24]HISTOJANV24!$A$6:$AU$38,27,0) -> 0 | Y39: =VLOOKUP($A39,[24]HISTOJANV24!$A$6:$BM$38,33,0) -> 0 | Z39: =VLOOKUP($A39,[24]HISTOJANV24!$A$6:$BM$38,65,0) -> 0 | AB39: =VLOOKUP($A39,[24]HISTOJANV24!$A$6:$AU$38,43,0) -> 0 | AC39: =VLOOKUP($A39,[24]HISTOJANV24!$A$6:$AU$38,44,0) -> 0 | AD39: =VLOOKUP($A39,[24]HISTOJANV24!$A$6:$AU$38,47,0) -> 0 | AE39: =VLOOKUP(A39,[24]HISTOJANV24!$A$6:$BB$38,54,0) -> 0 | AF39: =VLOOKUP($A39,[24]HISTOJANV24!$A$6:$CA$38,60,0) -> 0 | AG39: =VLOOKUP($A39,[24]HISTOJANV24!$A$6:$CA$38,61,0) -> 0 | AH39: =VLOOKUP($A39,[24]HISTOJANV24!$A$6:$CA$38,62,0) -> 0 | AI39: =VLOOKUP($A39,[24]HISTOJANV24!$A$6:$CA$38,63,0) -> 0 | AJ39: =VLOOKUP($A39,[24]HISTOJANV24!$A$6:$CA$38,64,0) -> 0 | AK39: =VLOOKUP($A39,[24]HISTOJANV24!$A$6:$CA$38,65,0) -> 0
A41: TOTAL | C41: =SUM(C6:C40) -> 0 | D41: =SUM(D6:D40) -> 0 | E41: =SUM(E6:E40) -> 0 | F41: =SUM(F6:F40) -> 26790657 | G41: =SUM(G6:G40) -> 23593438 | H41: =SUM(H6:H40) -> 176000 | I41: =SUM(I6:I40) -> 26966657 | J41: =SUM(J6:J40) -> 0 | ... AK41: =SUM(AK6:AK40) -> 0

Sheet Sheet8
A1: ASSOCIATION | B1: ASELBY
A2: ANNEE | B2: 2024
A3: TONTINE
K4: 45339
A5: MATRICULE | B5: NOM ET PRENOM | C5: FONDES DE DEPART | D5: RECONDUCTION | E5: RETRAIT PARTIEL | F5: FONDS DEFINITIF | G5: BASE DE CALCUL INTERET FONDS DEFINITIF | H5: REPARTITION PROVISOIRE INTERET FONDS+EPARGNE | I5: CAPITAL COMPOSE | J5: SANCTION | K5: RESTE | L5: EPARGNE | M5: FONDS DE ROULEMENT | N5: FRAIS EXCEPTIONNEL | O5: COLLATION | P5: PENALITE VST ESPECES | Q5: INSCRISPTION | R5: MUTUELLE | S5: PRÊT FONDS | T5: INTERET PRET FONDS | U5: NUMERO CHEQUE | V5: REMBOURSEMENTPRET FONDS | W5: MODE VERSEMENT REMBOURSEMENT | X5: MODE VERSEMENT PRÊT | Y5: NUMERO CHEQUE | Z5: PENALITE PRET FONDS | AA5: PENALITE FONDS | AB5: PENALITE ECHEC TONTINE | AC5: PENALITE RETARD TONTINE | AD5: REMBOURSEMENT TRANSPORT | AE5: CONTRIBUTION FOYER | AF5: FONDS DE ROULEMENT | AG5: FRAIS EXCEPTIONNEL | AH5: FONDS MUTUELLE | AI5: COLLATION RECEPTION | AJ5: PENALITE PRET FONDS | AK5: DEPENSE PENALITE VERSEMENT BANQUE
A6: AS201648 | B6: =VLOOKUP(A6,[19]LISTADHERENT!A$5:H$60,3,0) -> ASELBY | E6: =VLOOKUP($A6,[24]HISTOFEV24!$A$6:$BA$38,48,0) -> 0 | F6: =MVTJANV24!I6-E6+L6 -> 942082.3 | G6: =IF(MVTJANV24!I6+L6>700000,(MVTJANV24!I6-E6+L6),0) -> 942082.3 | H6: =$T$41/$G$41*G6 -> 924.22208 | I6: =F6+H6 -> 943006.52 | J6: =VLOOKUP($A6,[24]HISTOFEV24!$A$6:$AQ$42,22,0) -> 0 | K6: =VLOOKUP($A6,[24]HISTOFEV24!$A$6:$AU$38,45,0) -> 0 | L6: =IF(K6=0,0,K6-(M6+N6+O6)) -> 0 | M6: =IF(K6=0,0,1000) -> 0 | N6: =IF(K6=0,0,1000) -> 0 | O6: =IF(K6=0,0,4000) -> 0 | P6: =VLOOKUP($A6,[24]HISTOFEV24!$A$6:$AU$38,7,0) -> 0 | Q6: =VLOOKUP($A6,[24]HISTOFEV24!$A$6:$AU$38,23,0) -> 0 | R6: =VLOOKUP($A6,[24]HISTOFEV24!$A$6:$AU$38,46,0) -> 0 | S6: =VLOOKUP($A6,[24]HISTOFEV24!$A$6:$AU$38,26,0) -> 0 | T6: =VLOOKUP($A6,[24]HISTOFEV24!$A$6:$BG$38,58,0) -> 0 | U6: =VLOOKUP($A6,[24]HISTOFEV24!$A$6:$AU$38,28,0) -> 0 | V6: =VLOOKUP($A6,[24]HISTOFEV24!$A$6:$AU$38,19,0) -> 0 | W6: =VLOOKUP($A6,[24]HISTOFEV24!$A$6:$AU$38,20,0) -> 0 | X6: =VLOOKUP($A6,[24]HISTOFEV24!$A$6:$AU$38,27,0) -> 0 | Y6: =VLOOKUP($A6,[24]HISTOFEV24!$A$6:$BM$38,33,0) -> 0 | Z6: =VLOOKUP($A6,[24]HISTOFEV24!$A$6:$BM$38,65,0) -> 0 | AB6: =VLOOKUP($A6,[24]HISTOFEV24!$A$6:$AU$38,43,0) -> 0 | AC6: =VLOOKUP($A6,[24]HISTOFEV24!$A$6:$AU$38,44,0) -> 0 | AD6: =VLOOKUP($A6,[24]HISTOFEV24!$A$6:$AU$38,47,0) -> 0 | AE6: =VLOOKUP(A6,[24]HISTOFEV24!$A$6:$BB$38,54,0) -> 0 | AF6: =VLOOKUP($A6,[24]HISTOFEV24!$A$6:$CA$38,60,0) -> 27000 | AG6: =VLOOKUP($A6,[24]HISTOFEV24!$A$6:$CA$38,61,0) -> 0 | AH6: =VLOOKUP($A6,[24]HISTOFEV24!$A$6:$CA$38,62,0) -> 100000 | AI6: =VLOOKUP($A6,[24]HISTOFEV24!$A$6:$CA$38,63,0) -> 100000 | AJ6: =VLOOKUP($A6,[24]HISTOFEV24!$A$6:$CA$38,64,0) -> 0 | AK6: =VLOOKUP($A6,[24]HISTOFEV24!$A$6:$CA$38,65,0) -> 0
A7: AS201601 | B7: =VLOOKUP(A7,[19]LISTADHERENT!A$5:H$60,3,0) -> BAKOP ACHILLE | E7: =VLOOKUP($A7,[24]HISTOFEV24!$A$6:$BA$38,48,0) -> 0 | F7: =MVTJANV24!I7-E7+L7 -> 738482.5 | G7: =IF(MVTJANV24!I7+L7>700000,(MVTJANV24!I7-E7+L7),0) -> 738482.5 | H7: =$T$41/$G$41*G7 -> 724.48217 | I7: =F7+H7 -> 739206.98 | J7: =VLOOKUP($A7,[24]HISTOFEV24!$A$6:$AQ$42,22,0) -> 0 | K7: =VLOOKUP($A7,[24]HISTOFEV24!$A$6:$AU$38,45,0) -> 47000 | L7: =IF(K7=0,0,K7-(M7+N7+O7)) -> 41000 | M7: =IF(K7=0,0,1000) -> 1000 | N7: =IF(K7=0,0,1000) -> 1000 | O7: =IF(K7=0,0,4000) -> 4000 | P7: =VLOOKUP($A7,[24]HISTOFEV24!$A$6:$AU$38,7,0) -> 0 | Q7: =VLOOKUP($A7,[24]HISTOFEV24!$A$6:$AU$38,23,0) -> 0 | R7: =VLOOKUP($A7,[24]HISTOFEV24!$A$6:$AU$38,46,0) -> 0 | S7: =VLOOKUP($A7,[24]HISTOFEV24!$A$6:$AU$38,26,0) -> 0 | T7: =VLOOKUP($A7,[24]HISTOFEV24!$A$6:$BG$38,58,0) -> 6000 | U7: =VLOOKUP($A7,[24]HISTOFEV24!$A$6:$AU$38,28,0) -> 0 | V7: =VLOOKUP($A7,[24]HISTOFEV24!$A$6:$AU$38,19,0) -> 0 | W7: =VLOOKUP($A7,[24]HISTOFEV24!$A$6:$AU$38,20,0) -> 0 | X7: =VLOOKUP($A7,[24]HISTOFEV24!$A$6:$AU$38,27,0) -> 0 | Y7: =VLOOKUP($A7,[24]HISTOFEV24!$A$6:$BM$38,33,0) -> 0 | Z7: =VLOOKUP($A7,[24]HISTOFEV24!$A$6:$BM$38,65,0) -> 0 | AB7: =VLOOKUP($A7,[24]HISTOFEV24!$A$6:$AU$38,43,0) -> 0 | AC7: =VLOOKUP($A7,[24]HISTOFEV24!$A$6:$AU$38,44,0) -> 0 | AD7: =VLOOKUP($A7,[24]HISTOFEV24!$A$6:$AU$38,47,0) -> 0 | AE7: =VLOOKUP(A7,[24]HISTOFEV24!$A$6:$BB$38,54,0) -> 0 | AF7: =VLOOKUP($A7,[24]HISTOFEV24!$A$6:$CA$38,60,0) -> 0 | AG7: =VLOOKUP($A7,[24]HISTOFEV24!$A$6:$CA$38,61,0) -> 0 | AH7: =VLOOKUP($A7,[24]HISTOFEV24!$A$6:$CA$38,62,0) -> 0 | AI7: =VLOOKUP($A7,[24]HISTOFEV24!$A$6:$CA$38,63,0) -> 0 | AJ7: =VLOOKUP($A7,[24]HISTOFEV24!$A$6:$CA$38,64,0) -> 0 | AK7: =VLOOKUP($A7,[24]HISTOFEV24!$A$6:$CA$38,65,0) -> 0
A8: AS201602 | B8: =VLOOKUP(A8,[19]LISTADHERENT!A$5:H$60,3,0) -> BOUTCHOUANG WILLIAM | E8: =VLOOKUP($A8,[24]HISTOFEV24!$A$6:$BA$38,48,0) -> 0 | F8: =MVTJANV24!I8-E8+L8 -> 779046.43 | G8: =IF(MVTJANV24!I8+L8>700000,(MVTJANV24!I8-E8+L8),0) -> 779046.43 | H8: =$T$41/$G$41*G8 -> 764.27708 | I8: =F8+H8 -> 779810.71 | J8: =VLOOKUP($A8,[24]HISTOFEV24!$A$6:$AQ$42,22,0) -> 0 | K8: =VLOOKUP($A8,[24]HISTOFEV24!$A$6:$AU$38,45,0) -> 22000 | L8: =IF(K8=0,0,K8-(M8+N8+O8)) -> 16000 | M8: =IF(K8=0,0,1000) -> 1000 | N8: =IF(K8=0,0,1000) -> 1000 | O8: =IF(K8=0,0,4000) -> 4000 | P8: =VLOOKUP($A8,[24]HISTOFEV24!$A$6:$AU$38,7,0) -> 0 | Q8: =VLOOKUP($A8,[24]HISTOFEV24!$A$6:$AU$38,23,0) -> 0 | R8: =VLOOKUP($A8,[24]HISTOFEV24!$A$6:$AU$38,46,0) -> 0 | S8: =VLOOKUP($A8,[24]HISTOFEV24!$A$6:$AU$38,26,0) -> 0 | T8: =VLOOKUP($A8,[24]HISTOFEV24!$A$6:$BG$38,58,0) -> 0 | U8: =VLOOKUP($A8,[24]HISTOFEV24!$A$6:$AU$38,28,0) -> 0 | V8: =VLOOKUP($A8,[24]HISTOFEV24!$A$6:$AU$38,19,0) -> 0 | W8: =VLOOKUP($A8,[24]HISTOFEV24!$A$6:$AU$38,20,0) -> 0 | X8: =VLOOKUP($A8,[24]HISTOFEV24!$A$6:$AU$38,27,0) -> 0 | Y8: =VLOOKUP($A8,[24]HISTOFEV24!$A$6:$BM$38,33,0) -> 0 | Z8: =VLOOKUP($A8,[24]HISTOFEV24!$A$6:$BM$38,65,0) -> 0 | AB8: =VLOOKUP($A8,[24]HISTOFEV24!$A$6:$AU$38,43,0) -> 0 | AC8: =VLOOKUP($A8,[24]HISTOFEV24!$A$6:$AU$38,44,0) -> 0 | AD8: =VLOOKUP($A8,[24]HISTOFEV24!$A$6:$AU$38,47,0) -> 0 | AE8: =VLOOKUP(A8,[24]HISTOFEV24!$A$6:$BB$38,54,0) -> 0 | AF8: =VLOOKUP($A8,[24]HISTOFEV24!$A$6:$CA$38,60,0) -> 0 | AG8: =VLOOKUP($A8,[24]HISTOFEV24!$A$6:$CA$38,61,0) -> 0 | AH8: =VLOOKUP($A8,[24]HISTOFEV24!$A$6:$CA$38,62,0) -> 0 | AI8: =VLOOKUP($A8,[24]HISTOFEV24!$A$6:$CA$38,63,0) -> 0 | AJ8: =VLOOKUP($A8,[24]HISTOFEV24!$A$6:$CA$38,64,0) -> 0 | AK8: =VLOOKUP($A8,[24]HISTOFEV24!$A$6:$CA$38,65,0) -> 0
A9: AS201604 | B9: =VLOOKUP(A9,[19]LISTADHERENT!A$5:H$60,3,0) -> DJOMO JEAN PAUL | E9: =VLOOKUP($A9,[24]HISTOFEV24!$A$6:$BA$38,48,0) -> 0 | F9: =MVTJANV24!I9-E9+L9 -> 838713.03 | G9: =IF(MVTJANV24!I9+L9>700000,(MVTJANV24!I9-E9+L9),0) -> 838713.03 | H9: =$T$41/$G$41*G9 -> 822.81251 | I9: =F9+H9 -> 839535.84 | J9: =VLOOKUP($A9,[24]HISTOFEV24!$A$6:$AQ$42,22,0) -> 0 | K9: =VLOOKUP($A9,[24]HISTOFEV24!$A$6:$AU$38,45,0) -> 25000 | L9: =IF(K9=0,0,K9-(M9+N9+O9)) -> 19000 | M9: =IF(K9=0,0,1000) -> 1000 | N9: =IF(K9=0,0,1000) -> 1000 | O9: =IF(K9=0,0,4000) -> 4000 | P9: =VLOOKUP($A9,[24]HISTOFEV24!$A$6:$AU$38,7,0) -> 0 | Q9: =VLOOKUP($A9,[24]HISTOFEV24!$A$6:$AU$38,23,0) -> 0 | R9: =VLOOKUP($A9,[24]HISTOFEV24!$A$6:$AU$38,46,0) -> 0 | S9: =VLOOKUP($A9,[24]HISTOFEV24!$A$6:$AU$38,26,0) -> 0 | T9: =VLOOKUP($A9,[24]HISTOFEV24!$A$6:$BG$38,58,0) -> 0 | U9: =VLOOKUP($A9,[24]HISTOFEV24!$A$6:$AU$38,28,0) -> 0 | V9: =VLOOKUP($A9,[24]HISTOFEV24!$A$6:$AU$38,19,0) -> 0 | W9: =VLOOKUP($A9,[24]HISTOFEV24!$A$6:$AU$38,20,0) -> 0 | X9: =VLOOKUP($A9,[24]HISTOFEV24!$A$6:$AU$38,27,0) -> 0 | Y9: =VLOOKUP($A9,[24]HISTOFEV24!$A$6:$BM$38,33,0) -> 0 | Z9: =VLOOKUP($A9,[24]HISTOFEV24!$A$6:$BM$38,65,0) -> 0 | AB9: =VLOOKUP($A9,[24]HISTOFEV24!$A$6:$AU$38,43,0) -> 0 | AC9: =VLOOKUP($A9,[24]HISTOFEV24!$A$6:$AU$38,44,0) -> 0 | AD9: =VLOOKUP($A9,[24]HISTOFEV24!$A$6:$AU$38,47,0) -> 0 | AE9: =VLOOKUP(A9,[24]HISTOFEV24!$A$6:$BB$38,54,0) -> 0 | AF9: =VLOOKUP($A9,[24]HISTOFEV24!$A$6:$CA$38,60,0) -> 0 | AG9: =VLOOKUP($A9,[24]HISTOFEV24!$A$6:$CA$38,61,0) -> 0 | AH9: =VLOOKUP($A9,[24]HISTOFEV24!$A$6:$CA$38,62,0) -> 0 | AI9: =VLOOKUP($A9,[24]HISTOFEV24!$A$6:$CA$38,63,0) -> 0 | AJ9: =VLOOKUP($A9,[24]HISTOFEV24!$A$6:$CA$38,64,0) -> 0 | AK9: =VLOOKUP($A9,[24]HISTOFEV24!$A$6:$CA$38,65,0) -> 0
A10: AS201654 | B10: =VLOOKUP(A10,[19]LISTADHERENT!A$5:H$60,3,0) -> DJOMOU TCHAPDA | E10: =VLOOKUP($A10,[24]HISTOFEV24!$A$6:$BA$38,48,0) -> 0 | F10: =MVTJANV24!I10-E10+L10 -> 782324.37 | G10: =IF(MVTJANV24!I10+L10>700000,(MVTJANV24!I10-E10+L10),0) -> 782324.37 | H10: =$T$41/$G$41*G10 -> 767.49288 | I10: =F10+H10 -> 783091.87 | J10: =VLOOKUP($A10,[24]HISTOFEV24!$A$6:$AQ$42,22,0) -> 0 | K10: =VLOOKUP($A10,[24]HISTOFEV24!$A$6:$AU$38,45,0) -> 25000 | L10: =IF(K10=0,0,K10-(M10+N10+O10)) -> 19000 | M10: =IF(K10=0,0,1000) -> 1000 | N10: =IF(K10=0,0,1000) -> 1000 | O10: =IF(K10=0,0,4000) -> 4000 | P10: =VLOOKUP($A10,[24]HISTOFEV24!$A$6:$AU$38,7,0) -> 3000 | Q10: =VLOOKUP($A10,[24]HISTOFEV24!$A$6:$AU$38,23,0) -> 0 | R10: =VLOOKUP($A10,[24]HISTOFEV24!$A$6:$AU$38,46,0) -> 0 | S10: =VLOOKUP($A10,[24]HISTOFEV24!$A$6:$AU$38,26,0) -> 0 | T10: =VLOOKUP($A10,[24]HISTOFEV24!$A$6:$BG$38,58,0) -> 0 | U10: =VLOOKUP($A10,[24]HISTOFEV24!$A$6:$AU$38,28,0) -> 0 | V10: =VLOOKUP($A10,[24]HISTOFEV24!$A$6:$AU$38,19,0) -> 0 | W10: =VLOOKUP($A10,[24]HISTOFEV24!$A$6:$AU$38,20,0) -> 0 | X10: =VLOOKUP($A10,[24]HISTOFEV24!$A$6:$AU$38,27,0) -> 0 | Y10: =VLOOKUP($A10,[24]HISTOFEV24!$A$6:$BM$38,33,0) -> 0 | Z10: =VLOOKUP($A10,[24]HISTOFEV24!$A$6:$BM$38,65,0) -> 0 | AB10: =VLOOKUP($A10,[24]HISTOFEV24!$A$6:$AU$38,43,0) -> 0 | AC10: =VLOOKUP($A10,[24]HISTOFEV24!$A$6:$AU$38,44,0) -> 0 | AD10: =VLOOKUP($A10,[24]HISTOFEV24!$A$6:$AU$38,47,0) -> 0 | AE10: =VLOOKUP(A10,[24]HISTOFEV24!$A$6:$BB$38,54,0) -> 0 | AF10: =VLOOKUP($A10,[24]HISTOFEV24!$A$6:$CA$38,60,0) -> 0 | AG10: =VLOOKUP($A10,[24]HISTOFEV24!$A$6:$CA$38,61,0) -> 0 | AH10: =VLOOKUP($A10,[24]HISTOFEV24!$A$6:$CA$38,62,0) -> 0 | AI10: =VLOOKUP($A10,[24]HISTOFEV24!$A$6:$CA$38,63,0) -> 0 | AJ10: =VLOOKUP($A10,[24]HISTOFEV24!$A$6:$CA$38,64,0) -> 0 | AK10: =VLOOKUP($A10,[24]HISTOFEV24!$A$6:$CA$38,65,0) -> 0
A11: AS201605 | B11: =VLOOKUP(A11,[19]LISTADHERENT!A$5:H$60,3,0) -> DJOUKWE NANGUEN GUY BLAISE | E11: =VLOOKUP($A11,[24]HISTOFEV24!$A$6:$BA$38,48,0) -> 0 | F11: =MVTJANV24!I11-E11+L11 -> 784345.67 | G11: =IF(MVTJANV24!I11+L11>700000,(MVTJANV24!I11-E11+L11),0) -> 784345.67 | H11: =$T$41/$G$41*G11 -> 769.47586 | I11: =F11+H11 -> 785115.14 | J11: =VLOOKUP($A11,[24]HISTOFEV24!$A$6:$AQ$42,22,0) -> 0 | K11: =VLOOKUP($A11,[24]HISTOFEV24!$A$6:$AU$38,45,0) -> 25000 | L11: =IF(K11=0,0,K11-(M11+N11+O11)) -> 19000 | M11: =IF(K11=0,0,1000) -> 1000 | N11: =IF(K11=0,0,1000) -> 1000 | O11: =IF(K11=0,0,4000) -> 4000 | P11: =VLOOKUP($A11,[24]HISTOFEV24!$A$6:$AU$38,7,0) -> 0 | Q11: =VLOOKUP($A11,[24]HISTOFEV24!$A$6:$AU$38,23,0) -> 0 | R11: =VLOOKUP($A11,[24]HISTOFEV24!$A$6:$AU$38,46,0) -> 0 | S11: =VLOOKUP($A11,[24]HISTOFEV24!$A$6:$AU$38,26,0) -> 1000000 | T11: =VLOOKUP($A11,[24]HISTOFEV24!$A$6:$BG$38,58,0) -> 20000 | U11: =VLOOKUP($A11,[24]HISTOFEV24!$A$6:$AU$38,28,0) -> 0 | V11: =VLOOKUP($A11,[24]HISTOFEV24!$A$6:$AU$38,19,0) -> 1000000 | W11: =VLOOKUP($A11,[24]HISTOFEV24!$A$6:$AU$38,20,0) -> 0 | X11: =VLOOKUP($A11,[24]HISTOFEV24!$A$6:$AU$38,27,0) -> 0 | Y11: =VLOOKUP($A11,[24]HISTOFEV24!$A$6:$BM$38,33,0) -> 0 | Z11: =VLOOKUP($A11,[24]HISTOFEV24!$A$6:$BM$38,65,0) -> 0 | AB11: =VLOOKUP($A11,[24]HISTOFEV24!$A$6:$AU$38,43,0) -> 0 | AC11: =VLOOKUP($A11,[24]HISTOFEV24!$A$6:$AU$38,44,0) -> 0 | AD11: =VLOOKUP($A11,[24]HISTOFEV24!$A$6:$AU$38,47,0) -> 0 | AE11: =VLOOKUP(A11,[24]HISTOFEV24!$A$6:$BB$38,54,0) -> 0 | AF11: =VLOOKUP($A11,[24]HISTOFEV24!$A$6:$CA$38,60,0) -> 0 | AG11: =VLOOKUP($A11,[24]HISTOFEV24!$A$6:$CA$38,61,0) -> 0 | AH11: =VLOOKUP($A11,[24]HISTOFEV24!$A$6:$CA$38,62,0) -> 0 | AI11: =VLOOKUP($A11,[24]HISTOFEV24!$A$6:$CA$38,63,0) -> 0 | AJ11: =VLOOKUP($A11,[24]HISTOFEV24!$A$6:$CA$38,64,0) -> 0 | AK11: =VLOOKUP($A11,[24]HISTOFEV24!$A$6:$CA$38,65,0) -> 0
A12: AS201608 | B12: =VLOOKUP(A12,[19]LISTADHERENT!A$5:H$60,3,0) -> DJUOMBESSY ANTOINE | E12: =VLOOKUP($A12,[24]HISTOFEV24!$A$6:$BA$38,48,0) -> 0 | F12: =MVTJANV24!I12-E12+L12 -> 807471.36 | G12: =IF(MVTJANV24!I12+L12>700000,(MVTJANV24!I12-E12+L12),0) -> 807471.36 | H12: =$T$41/$G$41*G12 -> 792.16313 | I12: =F12+H12 -> 808263.52 | J12: =VLOOKUP($A12,[24]HISTOFEV24!$A$6:$AQ$42,22,0) -> 0 | K12: =VLOOKUP($A12,[24]HISTOFEV24!$A$6:$AU$38,45,0) -> 30000 | L12: =IF(K12=0,0,K12-(M12+N12+O12)) -> 24000 | M12: =IF(K12=0,0,1000) -> 1000 | N12: =IF(K12=0,0,1000) -> 1000 | O12: =IF(K12=0,0,4000) -> 4000 | P12: =VLOOKUP($A12,[24]HISTOFEV24!$A$6:$AU$38,7,0) -> 0 | Q12: =VLOOKUP($A12,[24]HISTOFEV24!$A$6:$AU$38,23,0) -> 0 | R12: =VLOOKUP($A12,[24]HISTOFEV24!$A$6:$AU$38,46,0) -> 0 | S12: =VLOOKUP($A12,[24]HISTOFEV24!$A$6:$AU$38,26,0) -> 0 | T12: =VLOOKUP($A12,[24]HISTOFEV24!$A$6:$BG$38,58,0) -> 0 | U12: =VLOOKUP($A12,[24]HISTOFEV24!$A$6:$AU$38,28,0) -> 0 | V12: =VLOOKUP($A12,[24]HISTOFEV24!$A$6:$AU$38,19,0) -> 0 | W12: =VLOOKUP($A12,[24]HISTOFEV24!$A$6:$AU$38,20,0) -> 0 | X12: =VLOOKUP($A12,[24]HISTOFEV24!$A$6:$AU$38,27,0) -> 0 | Y12: =VLOOKUP($A12,[24]HISTOFEV24!$A$6:$BM$38,33,0) -> 0 | Z12: =VLOOKUP($A12,[24]HISTOFEV24!$A$6:$BM$38,65,0) -> 0 | AB12: =VLOOKUP($A12,[24]HISTOFEV24!$A$6:$AU$38,43,0) -> 0 | AC12: =VLOOKUP($A12,[24]HISTOFEV24!$A$6:$AU$38,44,0) -> 0 | AD12: =VLOOKUP($A12,[24]HISTOFEV24!$A$6:$AU$38,47,0) -> 0 | AE12: =VLOOKUP(A12,[24]HISTOFEV24!$A$6:$BB$38,54,0) -> 0 | AF12: =VLOOKUP($A12,[24]HISTOFEV24!$A$6:$CA$38,60,0) -> 0 | AG12: =VLOOKUP($A12,[24]HISTOFEV24!$A$6:$CA$38,61,0) -> 0 | AH12: =VLOOKUP($A12,[24]HISTOFEV24!$A$6:$CA$38,62,0) -> 0 | AI12: =VLOOKUP($A12,[24]HISTOFEV24!$A$6:$CA$38,63,0) -> 0 | AJ12: =VLOOKUP($A12,[24]HISTOFEV24!$A$6:$CA$38,64,0) -> 0 | AK12: =VLOOKUP($A12,[24]HISTOFEV24!$A$6:$CA$38,65,0) -> 0
