Workbook

Sheet Sheet1

Sheet Sheet2

Sheet Sheet3

Sheet Sheet4

Sheet Sheet5

Sheet Sheet6

Sheet Sheet7

Sheet Sheet8

Sheet Sheet9

Sheet Sheet10

Sheet Sheet11

Sheet Sheet12

Sheet Sheet13

Sheet Sheet14

Sheet Sheet15

Sheet Sheet16

Sheet Sheet17

Sheet Sheet18

Sheet Sheet19

Sheet Sheet20

Sheet Sheet21

Sheet Sheet22

Sheet Sheet23

Sheet Sheet24

Sheet Sheet25

Sheet Sheet26

Sheet Sheet27

Sheet Sheet28

Sheet Sheet29
A1: ASSOCIATION | B1: ASELBY
A2: ANNEE | B2: 2023
A3: 1 | B3: 2 | C3: 3 | D3: 4 | E3: 5 | F3: 6 | G3: 7 | H3: 8 | I3: 9 | J3: 10 | K3: 11 | L3: 12 | M3: 13 | N3: 14 | O3: 15 | P3: 16 | Q3: 17 | R3: 18 | S3: 19 | T3: 20 | U3: 21 | V3: 22 | W3: 23 | X3: 24 | Y3: 25 | Z3: 26 | AA3: 27 | AB3: 28 | AC3: 29 | AD3: 30 | AE3: 31 | AF3: 32 | AG3: 33 | AH3: 34 | AI3: 35 | AJ3: 36 | AK3: 37 | AL3: 38 | AM3: 39 | AN3: 40 | AO3: 41 | AP3: 42 | AQ3: 43 | AR3: 44 | AS3: 45 | AT3: 46 | AU3: 47 | AV3: 48 | AW3: 49 | AX3: 50 | AY3: 51 | AZ3: 52 | BA3: 53 | BB3: 54 | BC3: 55 | BD3: 56 | BE3: 57 | BF3: 58 | BG3: 59 | BH3: 60 | BI3: 61 | BJ3: 62 | BK3: 63 | BL3: 64 | BM3: 65 | BN3: 66 | BO3: 67 | BP3: 68
B4: TABLEAU DE BORD SAISIE DES DONNEES
A5: MATRICULE | B5: NOM ET PRENOM | C5: BONUS MALUS | D5: HISTORIQUE BANQUE | E5: HITORIQUE ESPECES | F5: HITORIQUE TONTINE | G5: PENALITE VERSEMENT ESPECES | H5: MODE PAIEMENT TONTINE | I5: COMPLEMENT EPARGNE | J5: NBRE DE LOT | K5: TONTINE 40 000 | L5: NBRE DE LOT | M5: TONTINE 75 000 | N5: NBRE DE LOT | O5: TONTINE 100 000 | P5: REMBOURSEMENT PETIT LOT T40 | Q5: REMBOURSEMENT PETIT LOT T75 | R5: REMBOURSEMENT PETIT LOT T100 | S5: REMBOURSEMENT PRÊT FONDS | T5: MODE PAIEMENT REMBOURSEMENT PRÊT FONDS | U5: MONTANT ENGAGEMENT | V5: SANCTION | W5: INSCRIPTION | X5: EPARGNE ASSURANCE | Y5: RECONSTITUTION FONDS | Z5: PRÊT FONDS | AA5: MODE PAIEMENT PRÊT | AB5: NUM CHEQUE | AC5: ACHAT LOT PRINCIPAL T40 | AD5: ACHAT LOT PRINCIPAL T75 | AE5: ACHAT LOT PRINCIPAL T100 | AF5: MODE PAIEMENT LOT PRINCIPAL | AG5: NUM CHEQUE | AH5: PENALITE VERSEMENT ESPECES | AI5: VENTE PETIT LOT T40 | AJ5: VENTE PETIT LOT T75 | AK5: VENTE PETIT LOT T100 | AL5: INTERET PETIT LOT T40 | AM5: INTERET PETIT LOT T75 | AN5: INTERET PETIT LOT T100 | AO5: NUM CHEQUE | AP5: MODE PAIEMENT PETEIT LOT | AQ5: PENELAITE RETARD TONTINE | AR5: PENELAITE ECHEC TONTINE | AS5: RESTE | AT5: MUTUELLE | AU5: REMBOURSEMENT TRANSPORT | AV5: RETRAIT PARTIEL FONDS | AW5: MONTANT T40 | AX5: MONTANT T75 | AY5: MONTANT T100 | AZ5: MONTANT CHEQUE | BA5: MONTANT ESPECES | BB5: CONTRIBUTION FOYER | BC5: AUTRES SOTIES | BD5: MONTANT CHEQUE EFFECTIF | BE5: NUMERO CHEQUE | BF5: INTERET PRÊT | BG5: NBRE MOIS | BH5: DEPENSE FONDS DE ROULEMENT | BI5: DEPENSE FRAIS EXCEPTIONNEL | BJ5: DEPENSE FONDS MUTUEL | BK5: DEPENSE COLLATION RECEPTION | BL5: PENALITE PRET FONDS | BM5: DEPENSE PENALITE VERSEMENT BANQUE | BN5: LIBELLE | BO5: COMPTE | BP5: MONTANT
A6: AS201648 | B6: =VLOOKUP(A6,[17]LISTADHERENT!A$5:H$39,3,0) -> ASELBY | C6: =D6+E6+F6-U6-BB6 -> 0 | D6: =VLOOKUP(A6,[18]HISTOBQUEDEC23!$A$6:$G$44,3,0) -> 175000 | E6: =VLOOKUP(A6,[18]HISTOBQUEDEC23!$A$6:$G$39,4,0) -> 0 | F6: =VLOOKUP(A6,[18]HISTOBQUEDEC23!$A$6:$G$39,5,0) -> 0 | G6: =IF(H6="ESPECES",3000,0) -> 0 | H6: =IF($D6<>0,"BANQUE",IF($E6<>0,"ESPECES","ECHEC")) -> BANQUE | K6: =IF($D6<>0,J6*40000,IF($E6<>0,J6*40000,0)) -> 0 | L6: 1 | M6: =IF($D6<>0,L6*75000,IF($E6<>0,L6*75000,0)) -> 75000 | N6: 1 | O6: =IF($D6<>0,N6*100000,IF($E6<>0,N6*100000,0)) -> 100000 | Q6: =VLOOKUP($A6,[13]TONTDEC23!$A$6:$P$20,10,0) -> 0 | R6: =VLOOKUP($A6,[19]TONTDEC23!$A$6:$P$21,10,0) -> 0 | U6: =G6+S6++R6+P6+O6+M6+I6+K6+Q6+W6 -> 175000 | AD6: 7500 | AE6: 10000 | AQ6: =IF(H6="ECHEC",((K6+M6+O6)*20/100),0) -> 0 | AR6: =IF(H6="ECHEC",((K6+M6+O6)*20/100),0) -> 0 | AW6: =IF(AC6=0,AI6,(1*25000*12)+AI6-AC6) -> 0 | AX6: =IF(AD6=0,AJ6,(1*75000*12)+(AJ6)-AD6) -> 892500 | AY6: =IF(AE6=0,AK6,(1*100000*12)+(AK6)-AE6) -> 1190000 | AZ6: =SUM(AV6:AY6)-BF6+Z6-F6+BH6+BI6+BJ6+BK6+BL6+BM6 -> 2088500 | BD6: =IF(AZ6=0,(AZ6-BA6-BC6),(AZ6-BA6-BB6-BC6))+F6 -> 2088500 | BF6: =Z6*1/100*BG6 -> 0 | BG6: 12 | BH6: =BP16 -> 6000 | BI6: =BP28 -> 0 | BJ6: =BP33 -> 0 | BM6: =BP22 -> 0 | BN6: ACHAT FOURNITURE | BO6: FONDS DE ROULEMENT
A7: AS201601 | B7: =VLOOKUP(A7,[17]LISTADHERENT!A$5:H$39,3,0) -> BAKOP ACHILLE | C7: =D7+E7+F7-U7-BB7 -> 0 | D7: =VLOOKUP(A7,[18]HISTOBQUEDEC23!$A$6:$G$44,3,0) -> 0 | E7: =VLOOKUP(A7,[18]HISTOBQUEDEC23!$A$6:$G$39,4,0) -> 669000 | F7: =VLOOKUP(A7,[18]HISTOBQUEDEC23!$A$6:$G$39,5,0) -> 0 | G7: =IF(H7="ESPECES",3000,0)-3000 -> 0 | H7: =IF($D7<>0,"BANQUE",IF($E7<>0,"ESPECES","ECHEC")) -> ESPECES | J7: 1 | K7: =IF($D7<>0,J7*40000,IF($E7<>0,J7*40000,0)) -> 40000 | M7: =IF($D7<>0,L7*75000,IF($E7<>0,L7*75000,0)) -> 0 | O7: =IF($D7<>0,N7*100000,IF($E7<>0,N7*100000,0)) -> 0 | P7: =VLOOKUP($A7,[20]TONTDEC23!$A$6:$P$35,12,0) -> 29000 | S7: 600000 | T7: BANQUE | U7: =G7+S7++R7+P7+O7+M7+I7+K7+Q7+W7 -> 669000 | AQ7: =IF(H7="ECHEC",((K7+M7+O7)*20/100),0) -> 0 | AR7: =IF(H7="ECHEC",((K7+M7+O7)*20/100),0) -> 0 | AS7: =IF(H7="ECHEC",0,(K7+I7-25000)) -> 15000 | AW7: =IF(AC7=0,AI7,(1*25000*12)+AI7-AC7) -> 0 | AX7: =IF(AD7=0,AJ7,(1*75000*12)+(AJ7)-AD7) -> 0 | AY7: =IF(AE7=0,AK7,(1*100000*12)+(AK7)-AE7) -> 0 | AZ7: =SUM(AV7:AY7)-BF7+Z7-F7+BH7+BI7+BJ7+BK7+BL7+BM7 -> 0 | BD7: =IF(AZ7=0,(AZ7-BA7-BC7),(AZ7-BA7-BB7-BC7))+F7 -> 0 | BF7: =Z7*1/100*BG7 -> 0 | BG7: 12 | BH7: =BP17 -> 0 | BI7: =BP27 -> 0 | BJ7: =BP33 -> 0 | BM7: =BP23 -> 0 | BN7: COMMUNICATION | BO7: FONDS DE ROULEMENT
A8: AS201602 | B8: =VLOOKUP(A8,[17]LISTADHERENT!A$5:H$39,3,0) -> BOUTCHOUANG WILLIAM | C8: =D8+E8+F8-U8-BB8 -> 0 | D8: =VLOOKUP(A8,[18]HISTOBQUEDEC23!$A$6:$G$44,3,0) -> 115000 | E8: =VLOOKUP(A8,[18]HISTOBQUEDEC23!$A$6:$G$39,4,0) -> 0 | F8: =VLOOKUP(A8,[18]HISTOBQUEDEC23!$A$6:$G$39,5,0) -> 0 | G8: =IF(H8="ESPECES",3000,0) -> 0 | H8: =IF($D8<>0,"BANQUE",IF($E8<>0,"ESPECES","ECHEC")) -> BANQUE | J8: 1 | K8: =IF($D8<>0,J8*40000,IF($E8<>0,J8*40000,0)) -> 40000 | L8: 1 | M8: =IF($D8<>0,L8*75000,IF($E8<>0,L8*75000,0)) -> 75000 | O8: =IF($D8<>0,N8*100000,IF($E8<>0,N8*100000,0)) -> 0 | P8: =VLOOKUP($A8,[20]TONTDEC23!$A$6:$P$35,12,0) -> 0 | Q8: =VLOOKUP($A8,[20]TONTDEC23!$A$6:$P$35,12,0) -> 0 | U8: =G8+S8++R8+P8+O8+M8+I8+K8+Q8+W8 -> 115000 | V8: =19000 -> 19000 | Z8: 500000 | AQ8: =IF(H8="ECHEC",((K8+M8+O8)*20/100),0) -> 0 | AR8: =IF(H8="ECHEC",((K8+M8+O8)*20/100),0) -> 0 | AS8: =IF(H8="ECHEC",0,(K8+I8-25000)) -> 15000 | AW8: =IF(AC8=0,AI8,(1*25000*12)+AI8-AC8) -> 0 | AX8: =IF(AD8=0,AJ8,(1*75000*12)+(AJ8)-AD8) -> 0 | AY8: =IF(AE8=0,AK8,(1*100000*12)+(AK8)-AE8) -> 0 | AZ8: =SUM(AV8:AY8)-BF8+Z8-F8+BH8+BI8+BJ8+BK8+BL8+BM8 -> 485000 | BD8: =IF(AZ8=0,(AZ8-BA8-BC8),(AZ8-BA8-BB8-BC8))+F8 -> 485000 | BF8: =Z8*1/100*BG8 -> 15000 | BG8: 3 | BN8: COMMISSION | BO8: FONDS DE ROULEMENT
A9: AS201604 | B9: =VLOOKUP(A9,[17]LISTADHERENT!A$5:H$39,3,0) -> DJOMO JEAN PAUL | C9: =D9+E9+F9-U9-BB9 -> 221000 | D9: =VLOOKUP(A9,[18]HISTOBQUEDEC23!$A$6:$G$44,3,0) -> 386000 | E9: =VLOOKUP(A9,[18]HISTOBQUEDEC23!$A$6:$G$39,4,0) -> 1000000 | F9: =VLOOKUP(A9,[18]HISTOBQUEDEC23!$A$6:$G$39,5,0) -> 0 | G9: =IF(H9="ESPECES",3000,0) -> 0 | H9: =IF($D9<>0,"BANQUE",IF($E9<>0,"ESPECES","ECHEC")) -> BANQUE | I9: 25000 | J9: 1 | K9: =IF($D9<>0,J9*40000,IF($E9<>0,J9*40000,0)) -> 40000 | M9: =IF($D9<>0,L9*75000,IF($E9<>0,L9*75000,0)) -> 0 | N9: 1 | O9: =IF($D9<>0,N9*100000,IF($E9<>0,N9*100000,0)) -> 100000 | P9: =VLOOKUP($A9,[20]TONTDEC23!$A$6:$P$35,12,0) -> 0 | R9: =VLOOKUP($A9,[19]TONTDEC23!$A$6:$P$21,10,0) -> 0 | S9: 1000000 | T9: BANQUE | U9: =G9+S9++R9+P9+O9+M9+I9+K9+Q9+W9 -> 1165000 | V9: 9000 | Z9: 1000000 | AA9: BANQUE | AQ9: =IF(H9="ECHEC",((K9+M9+O9)*20/100),0) -> 0 | AR9: =IF(H9="ECHEC",((K9+M9+O9)*20/100),0) -> 0 | AS9: =IF(H9="ECHEC",0,(K9+I9-25000)) -> 40000 | AW9: =IF(AC9=0,AI9,(1*25000*12)+AI9-AC9) -> 0 | AX9: =IF(AD9=0,AJ9,(1*75000*12)+(AJ9)-AD9) -> 0 | AY9: =IF(AE9=0,AK9,(1*100000*12)+(AK9)-AE9) -> 0 | AZ9: =SUM(AV9:AY9)-BF9+Z9-F9+BH9+BI9+BJ9+BK9+BL9+BM9 -> 880000 | BD9: =IF(AZ9=0,(AZ9-BA9-BC9),(AZ9-BA9-BB9-BC9))+F9 -> 880000 | BF9: =Z9*1/100*BG9 -> 120000 | BG9: 12 | BN9: AIDE UEEB ET CONT FEMME | BO9: FONDS DE ROULEMENT
A10: AS201654 | B10: =VLOOKUP(A10,[17]LISTADHERENT!A$5:H$39,3,0) -> DJOMOU TCHAPDA | C10: =D10+E10+F10-U10-BB10 -> 0 | D10: =VLOOKUP(A10,[18]HISTOBQUEDEC23!$A$6:$G$44,3,0) -> 0 | E10: =VLOOKUP(A10,[18]HISTOBQUEDEC23!$A$6:$G$39,4,0) -> 40000 | F10: =VLOOKUP(A10,[18]HISTOBQUEDEC23!$A$6:$G$39,5,0) -> 0 | G10: =IF(H10="ESPECES",3000,0)-3000 -> 0 | H10: =IF($D10<>0,"BANQUE",IF($E10<>0,"ESPECES","ECHEC")) -> ESPECES | J10: 1 | K10: =IF($D10<>0,J10*40000,IF($E10<>0,J10*40000,0)) -> 40000 | M10: =IF($D10<>0,L10*75000,IF($E10<>0,L10*75000,0)) -> 0 | O10: =IF($D10<>0,N10*100000,IF($E10<>0,N10*100000,0)) -> 0 | P10: =VLOOKUP($A10,[20]TONTDEC23!$A$6:$P$35,12,0) -> 0 | U10: =G10+S10++R10+P10+O10+M10+I10+K10+Q10+W10 -> 40000 | V10: =12000+10000 -> 22000 | Z10: 1000000 | AA10: BANQUE | AQ10: =IF(H10="ECHEC",((K10+M10+O10)*20/100),0) -> 0 | AR10: =IF(H10="ECHEC",((K10+M10+O10)*20/100),0) -> 0 | AS10: =IF(H10="ECHEC",0,(K10+I10-25000)) -> 15000 | AW10: =IF(AC10=0,AI10,(1*25000*12)+AI10-AC10) -> 0 | AX10: =IF(AD10=0,AJ10,(1*75000*12)+(AJ10)-AD10) -> 0 | AY10: =IF(AE10=0,AK10,(1*100000*12)+(AK10)-AE10) -> 0 | AZ10: =SUM(AV10:AY10)-BF10+Z10-F10+BH10+BI10+BJ10+BK10+BL10+BM10 -> 880000 | BD10: =IF(AZ10=0,(AZ10-BA10-BC10),(AZ10-BA10-BB10-BC10))+F10+49000 -> 929000 | BF10: =Z10*1/100*BG10 -> 120000 | BG10: 12 | BN10: CREDIT TELEPHONE | BO10: FONDS DE ROULEMENT
A11: AS201605 | B11: =VLOOKUP(A11,[17]LISTADHERENT!A$5:H$39,3,0) -> DJOUKWE NANGUEN GUY BLAISE | C11: =D11+E11+F11-U11-BB11 -> 0 | D11: =VLOOKUP(A11,[18]HISTOBQUEDEC23!$A$6:$G$44,3,0) -> 115000 | E11: =VLOOKUP(A11,[18]HISTOBQUEDEC23!$A$6:$G$39,4,0)+77000 -> 1077000 | F11: =VLOOKUP(A11,[18]HISTOBQUEDEC23!$A$6:$G$39,5,0) -> 0 | G11: =IF(H11="ESPECES",3000,0) -> 0 | H11: =IF($D11<>0,"BANQUE",IF($E11<>0,"ESPECES","ECHEC")) -> BANQUE | J11: 1 | K11: =IF($D11<>0,J11*40000,IF($E11<>0,J11*40000,0)) -> 40000 | L11: 1 | M11: =IF($D11<>0,L11*75000,IF($E11<>0,L11*75000,0)) -> 75000 | O11: =IF($D11<>0,N11*100000,IF($E11<>0,N11*100000,0)) -> 0 | P11: =VLOOKUP($A11,[20]TONTDEC23!$A$6:$P$35,12,0) -> 0 | Q11: =VLOOKUP($A11,[13]TONTDEC23!$A$6:$P$20,10,0) -> 77000 | S11: 1000000 | T11: BANQUE | U11: =G11+S11++R11+P11+O11+M11+I11+K11+Q11+W11 -> 1192000 | Z11: 1000000 | AA11: BANQUE | AQ11: =IF(H11="ECHEC",((K11+M11+O11)*20/100),0) -> 0 | AR11: =IF(H11="ECHEC",((K11+M11+O11)*20/100),0) -> 0 | AS11: =IF(H11="ECHEC",0,(K11+I11-25000)) -> 15000 | AW11: =IF(AC11=0,AI11,(1*25000*12)+AI11-AC11) -> 0 | AX11: =IF(AD11=0,AJ11,(1*75000*12)+(AJ11)-AD11) -> 0 | AY11: =IF(AE11=0,AK11,(1*100000*12)+(AK11)-AE11) -> 0 | AZ11: =SUM(AV11:AY11)-BF11+Z11-F11+BH11+BI11+BJ11+BK11+BL11+BM11 -> 980000 | BD11: =IF(AZ11=0,(AZ11-BA11-BC11),(AZ11-BA11-BB11-BC11))+F11 -> 980000 | BF11: =Z11*1/100*BG11 -> 20000 | BG11: 2 | BN11: PRODUCTION RAPPORT | BO11: FONDS DE ROULEMENT
A12: AS201608 | B12: =VLOOKUP(A12,[17]LISTADHERENT!A$5:H$39,3,0) -> DJUOMBESSY ANTOINE | C12: =D12+E12+F12-U12-BB12 -> 0 | D12: =VLOOKUP(A12,[18]HISTOBQUEDEC23!$A$6:$G$44,3,0) -> 1040000 | E12: =VLOOKUP(A12,[18]HISTOBQUEDEC23!$A$6:$G$39,4,0)+206000 -> 257000 | F12: =VLOOKUP(A12,[18]HISTOBQUEDEC23!$A$6:$G$39,5,0) -> 0 | G12: =IF(H12="ESPECES",3000,0) -> 0 | H12: =IF($D12<>0,"BANQUE",IF($E12<>0,"ESPECES","ECHEC")) -> BANQUE | I12: =5000+800 -> 5800 | J12: 1 | K12: =IF($D12<>0,J12*40000,IF($E12<>0,J12*40000,0)) -> 40000 | L12: 1 | M12: =IF($D12<>0,L12*75000,IF($E12<>0,L12*75000,0)) -> 75000 | N12: 2 | O12: =IF($D12<>0,N12*100000,IF($E12<>0,N12*100000,0)) -> 200000 | P12: =VLOOKUP($A12,[20]TONTDEC23!$A$6:$P$35,12,0) -> 0 | Q12: =VLOOKUP($A12,[13]TONTDEC23!$A$6:$P$20,10,0) -> 51000 | R12: =VLOOKUP($A12,[19]TONTDEC23!$A$6:$P$21,10,0) -> 206000 | S12: 719200 | T12: BANQUE | U12: =G12+S12++R12+P12+O12+M12+I12+K12+Q12+W12 -> 1297000 | Z12: 1000000 | AA12: BANQUE | AQ12: =IF(H12="ECHEC",((K12+M12+O12)*20/100),0) -> 0 | AR12: =IF(H12="ECHEC",((K12+M12+O12)*20/100),0) -> 0 | AS12: =IF(H12="ECHEC",0,(K12+I12-25000)) -> 20800 | AW12: =IF(AC12=0,AI12,(1*25000*12)+AI12-AC12) -> 0 | AX12: =IF(AD12=0,AJ12,(1*75000*12)+(AJ12)-AD12) -> 0 | AY12: =IF(AE12=0,AK12,(1*100000*12)+(AK12)-AE12) -> 0 | AZ12: =SUM(AV12:AY12)-BF12+Z12-F12+BH12+BI12+BJ12+BK12+BL12+BM12 -> 940000 | BD12: =IF(AZ12=0,(AZ12-BA12-BC12),(AZ12-BA12-BB12-BC12))+F12+150000 -> 1090000 | BF12: =Z12*1/100*BG12 -> 60000 | BG12: 6 | BN12: ACHAT SOURIS ET PHOTOCOPIE | BO12: FONDS DE ROULEMENT
A13: AS201651 | B13: =VLOOKUP(A13,[17]LISTADHERENT!A$5:H$39,3,0) -> DOMOU FABIEN | C13: =D13+E13+F13-U13-BB13 -> 0 | D13: =VLOOKUP(A13,[18]HISTOBQUEDEC23!$A$6:$G$44,3,0) -> 1040000 | E13: =VLOOKUP(A13,[18]HISTOBQUEDEC23!$A$6:$G$39,4,0) -> 0 | F13: =VLOOKUP(A13,[18]HISTOBQUEDEC23!$A$6:$G$39,5,0) -> 0 | G13: =IF(H13="ESPECES",3000,0) -> 0 | H13: =IF($D13<>0,"BANQUE",IF($E13<>0,"ESPECES","ECHEC")) -> BANQUE | J13: 1 | K13: =IF($D13<>0,J13*40000,IF($E13<>0,J13*40000,0)) -> 40000 | M13: =IF($D13<>0,L13*75000,IF($E13<>0,L13*75000,0)) -> 0 | O13: =IF($D13<>0,N13*100000,IF($E13<>0,N13*100000,0)) -> 0 | P13: =VLOOKUP($A13,[20]TONTDEC23!$A$6:$P$35,12,0) -> 0 | S13: 1000000 | T13: BANQUE | U13: =G13+S13++R13+P13+O13+M13+I13+K13+Q13+W13 -> 1040000 | Z13: 1000000 | AA13: BANQUE | AQ13: =IF(H13="ECHEC",((K13+M13+O13)*20/100),0) -> 0 | AR13: =IF(H13="ECHEC",((K13+M13+O13)*20/100),0) -> 0 | AS13: =IF(H13="ECHEC",0,(K13+I13-25000)) -> 15000 | AW13: =IF(AC13=0,AI13,(1*25000*12)+AI13-AC13) -> 0 | AX13: =IF(AD13=0,AJ13,(1*75000*12)+(AJ13)-AD13) -> 0 | AY13: =IF(AE13=0,AK13,(1*100000*12)+(AK13)-AE13) -> 0 | AZ13: =SUM(AV13:AY13)-BF13+Z13-F13+BH13+BI13+BJ13+BK13+BL13+BM13 -> 880000 | BD13: =IF(AZ13=0,(AZ13-BA13-BC13),(AZ13-BA13-BB13-BC13))+F13+21000 -> 901000 | BF13: =Z13*1/100*BG13 -> 120000 | BG13: 12 | BN13: TAXI BANQUE | BO13: FONDS DE ROULEMENT | BP13: 6000
A14: AS201609 | B14: =VLOOKUP(A14,[17]LISTADHERENT!A$5:H$39,3,0) -> DONHOU DAVID | C14: =D14+E14+F14-U14-BB14 -> 0 | D14: =VLOOKUP(A14,[18]HISTOBQUEDEC23!$A$6:$G$44,3,0) -> 40000 | E14: =VLOOKUP(A14,[18]HISTOBQUEDEC23!$A$6:$G$39,4,0) -> 0 | F14: =VLOOKUP(A14,[18]HISTOBQUEDEC23!$A$6:$G$39,5,0) -> 0 | G14: =IF(H14="ESPECES",3000,0) -> 0 | H14: =IF($D14<>0,"BANQUE",IF($E14<>0,"ESPECES","ECHEC")) -> BANQUE | J14: 1 | K14: =IF($D14<>0,J14*40000,IF($E14<>0,J14*40000,0)) -> 40000 | M14: =IF($D14<>0,L14*75000,IF($E14<>0,L14*75000,0)) -> 0 | O14: =IF($D14<>0,N14*100000,IF($E14<>0,N14*100000,0)) -> 0 | P14: =VLOOKUP($A14,[20]TONTDEC23!$A$6:$P$35,12,0) -> 0 | U14: =G14+S14++R14+P14+O14+M14+I14+K14+Q14+W14 -> 40000 | AQ14: =IF(H14="ECHEC",((K14+M14+O14)*20/100),0) -> 0 | AR14: =IF(H14="ECHEC",((K14+M14+O14)*20/100),0) -> 0 | AS14: =IF(H14="ECHEC",0,(K14+I14-25000)) -> 15000 | AW14: =IF(AC14=0,AI14,(1*25000*12)+AI14-AC14) -> 0 | AX14: =IF(AD14=0,AJ14,(1*75000*12)+(AJ14)-AD14) -> 0 | AY14: =IF(AE14=0,AK14,(1*100000*12)+(AK14)-AE14) -> 0 | AZ14: =SUM(AV14:AY14)-BF14+Z14-F14+BH14+BI14+BJ14+BK14+BL14+BM14 -> 0 | BD14: =IF(AZ14=0,(AZ14-BA14-BC14),(AZ14-BA14-BB14-BC14))+F14 -> 0 | BF14: =Z14*1/100*BG14 -> 0 | BG14: 12 | BN14: CONFECTION CACHET | BO14: FONDS DE ROULEMENT
A15: AS201611 | B15: =VLOOKUP(A15,[17]LISTADHERENT!A$5:H$39,3,0) -> HENGUE PAUL OMER | C15: =D15+E15+F15-U15-BB15 -> 0 | D15: =VLOOKUP(A15,[18]HISTOBQUEDEC23!$A$6:$G$44,3,0) -> 115000 | E15: =VLOOKUP(A15,[18]HISTOBQUEDEC23!$A$6:$G$39,4,0) -> 0 | F15: =VLOOKUP(A15,[18]HISTOBQUEDEC23!$A$6:$G$39,5,0) -> 0 | G15: =IF(H15="ESPECES",3000,0) -> 0 | H15: =IF($D15<>0,"BANQUE",IF($E15<>0,"ESPECES","ECHEC")) -> BANQUE | J15: 1 | K15: =IF($D15<>0,J15*40000,IF($E15<>0,J15*40000,0)) -> 40000 | L15: 1 | M15: =IF($D15<>0,L15*75000,IF($E15<>0,L15*75000,0)) -> 75000 | O15: =IF($D15<>0,N15*100000,IF($E15<>0,N15*100000,0)) -> 0 | P15: =VLOOKUP($A15,[20]TONTDEC23!$A$6:$P$35,12,0) -> 0 | Q15: =VLOOKUP($A15,[13]TONTDEC23!$A$6:$P$20,10,0) -> 0 | U15: =G15+S15++R15+P15+O15+M15+I15+K15+Q15+W15 -> 115000 | V15: =9000+9000 -> 18000 | AQ15: =IF(H15="ECHEC",((K15+M15+O15)*20/100),0) -> 0 | AR15: =IF(H15="ECHEC",((K15+M15+O15)*20/100),0) -> 0 | AS15: =IF(H15="ECHEC",0,(K15+I15-25000)) -> 15000 | AW15: =IF(AC15=0,AI15,(1*25000*12)+AI15-AC15) -> 0 | AX15: =IF(AD15=0,AJ15,(1*75000*12)+(AJ15)-AD15) -> 0 | AY15: =IF(AE15=0,AK15,(1*100000*12)+(AK15)-AE15) -> 0 | AZ15: =SUM(AV15:AY15)-BF15+Z15-F15+BH15+BI15+BJ15+BK15+BL15+BM15 -> 0 | BD15: =IF(AZ15=0,(AZ15-BA15-BC15),(AZ15-BA15-BB15-BC15))+F15 -> 0 | BF15: =Z15*1/100*BG15 -> 0 | BG15: 12
A16: AS201613 | B16: =VLOOKUP(A16,[17]LISTADHERENT!A$5:H$39,3,0) -> HOTCHO BENJAMIN | C16: =D16+E16+F16-U16-BB16 -> 0 | D16: =VLOOKUP(A16,[18]HISTOBQUEDEC23!$A$6:$G$44,3,0) -> 250000 | E16: =VLOOKUP(A16,[18]HISTOBQUEDEC23!$A$6:$G$39,4,0)+206000+125000+238500 -> 569500 | F16: =VLOOKUP(A16,[18]HISTOBQUEDEC23!$A$6:$G$39,5,0) -> 0 | G16: =IF(H16="ESPECES",3000,0) -> 0 | H16: =IF($D16<>0,"BANQUE",IF($E16<>0,"ESPECES","ECHEC")) -> BANQUE | I16: 35000 | J16: 1 | K16: =IF($D16<>0,J16*40000,IF($E16<>0,J16*40000,0)) -> 40000 | L16: 1 | M16: =IF($D16<>0,L16*75000,IF($E16<>0,L16*75000,0)) -> 75000 | N16: 1 | O16: =IF($D16<>0,N16*100000,IF($E16<>0,N16*100000,0)) -> 100000 | P16: =VLOOKUP($A16,[20]TONTDEC23!$A$6:$P$35,12,0) -> 0 | Q16: =VLOOKUP($A16,[13]TONTDEC23!$A$6:$P$20,10,0) -> 0 | R16: =VLOOKUP($A16,[19]TONTDEC23!$A$6:$P$21,10,0) -> 206000 | S16: =125000+238500 -> 363500 | T16: BANQUE | U16: =G16+S16++R16+P16+O16+M16+I16+K16+Q16+W16 -> 819500 | V16: =9000+3000 -> 12000 | AQ16: =IF(H16="ECHEC",((K16+M16+O16)*20/100),0) -> 0 | AR16: =IF(H16="ECHEC",((K16+M16+O16)*20/100),0) -> 0 | AS16: =IF(H16="ECHEC",0,(K16+I16-25000)) -> 50000 | AW16: =IF(AC16=0,AI16,(1*25000*12)+AI16-AC16) -> 0 | AX16: =IF(AD16=0,AJ16,(1*75000*12)+(AJ16)-AD16) -> 0 | AY16: =IF(AE16=0,AK16,(1*100000*12)+(AK16)-AE16) -> 0 | AZ16: =SUM(AV16:AY16)-BF16+Z16-F16+BH16+BI16+BJ16+BK16+BL16+BM16 -> 0 | BD16: =IF(AZ16=0,(AZ16-BA16-BC16),(AZ16-BA16-BB16-BC16))+F16+400000 -> 400000 | BF16: =Z16*1/100*BG16 -> 0 | BG16: 12 | BN16: S/TOTAL | BP16: =SUM(BP6:BP15) -> 6000
A17: AS201617 | B17: =VLOOKUP(A17,[17]LISTADHERENT!A$5:H$39,3,0) -> KOUAMOU MOISE | C17: =D17+E17+F17-U17-BB17 -> 0 | D17: =VLOOKUP(A17,[18]HISTOBQUEDEC23!$A$6:$G$44,3,0) -> 1140000 | E17: =VLOOKUP(A17,[18]HISTOBQUEDEC23!$A$6:$G$39,4,0) -> 0 | F17: =VLOOKUP(A17,[18]HISTOBQUEDEC23!$A$6:$G$39,5,0) -> 0 | G17: =IF(H17="ESPECES",3000,0) -> 0 | H17: =IF($D17<>0,"BANQUE",IF($E17<>0,"ESPECES","ECHEC")) -> BANQUE | J17: 1 | K17: =IF($D17<>0,J17*40000,IF($E17<>0,J17*40000,0)) -> 40000 | M17: =IF($D17<>0,L17*75000,IF($E17<>0,L17*75000,0)) -> 0 | N17: 1 | O17: =IF($D17<>0,N17*100000,IF($E17<>0,N17*100000,0)) -> 100000 | P17: =VLOOKUP($A17,[20]TONTDEC23!$A$6:$P$35,12,0) -> 0 | R17: =VLOOKUP($A17,[19]TONTDEC23!$A$6:$P$21,10,0) -> 0 | S17: 1000000 | T17: BANQUE | U17: =G17+S17++R17+P17+O17+M17+I17+K17+Q17+W17 -> 1140000 | V17: 9000 | AQ17: =IF(H17="ECHEC",((K17+M17+O17)*20/100),0) -> 0 | AR17: =IF(H17="ECHEC",((K17+M17+O17)*20/100),0) -> 0 | AS17: =IF(H17="ECHEC",0,(K17+I17-25000)) -> 15000 | AW17: =IF(AC17=0,AI17,(1*25000*12)+AI17-AC17) -> 0 | AX17: =IF(AD17=0,AJ17,(1*75000*12)+(AJ17)-AD17) -> 0 | AY17: =IF(AE17=0,AK17,(1*100000*12)+(AK17)-AE17) -> 0 | AZ17: =SUM(AV17:AY17)-BF17+Z17-F17+BH17+BI17+BJ17+BK17+BL17+BM17 -> 0 | BD17: =IF(AZ17=0,(AZ17-BA17-BC17),(AZ17-BA17-BB17-BC17))+F17 -> 0 | BF17: =Z17*1/100*BG17 -> 0 | BG17: 12
A18: AS201619 | B18: =VLOOKUP(A18,[17]LISTADHERENT!A$5:H$39,3,0) -> KOUATCHO MESSACK | C18: =D18+E18+F18-U18-BB18 -> 0 | D18: =VLOOKUP(A18,[18]HISTOBQUEDEC23!$A$6:$G$44,3,0) -> 1000000 | E18: =VLOOKUP(A18,[18]HISTOBQUEDEC23!$A$6:$G$39,4,0) -> 447500 | F18: =VLOOKUP(A18,[18]HISTOBQUEDEC23!$A$6:$G$39,5,0) -> 0 | G18: =IF(H18="ESPECES",3000,0) -> 0 | H18: =IF($D18<>0,"BANQUE",IF($E18<>0,"ESPECES","ECHEC")) -> BANQUE | J18: 1 | K18: =IF($D18<>0,J18*40000,IF($E18<>0,J18*40000,0)) -> 40000 | L18: 1 | M18: =IF($D18<>0,L18*75000,IF($E18<>0,L18*75000,0)) -> 75000 | N18: 1 | O18: =IF($D18<>0,N18*100000,IF($E18<>0,N18*100000,0)) -> 100000 | P18: =VLOOKUP($A18,[20]TONTDEC23!$A$6:$P$35,12,0) -> 30500 | Q18: =VLOOKUP($A18,[13]TONTDEC23!$A$6:$P$20,10,0) -> 202000 | R18: =VLOOKUP($A18,[19]TONTDEC23!$A$6:$P$21,10,0) -> 0 | S18: 1000000 | T18: BANQUE | U18: =G18+S18++R18+P18+O18+M18+I18+K18+Q18+W18 -> 1447500 | V18: 3000 | Z18: 1000000 | AA18: BANQUE | AQ18: =IF(H18="ECHEC",((K18+M18+O18)*20/100),0) -> 0 | AR18: =IF(H18="ECHEC",((K18+M18+O18)*20/100),0) -> 0 | AS18: =IF(H18="ECHEC",0,(K18+I18-25000)) -> 15000 | AW18: =IF(AC18=0,AI18,(1*25000*12)+AI18-AC18) -> 0 | AX18: =IF(AD18=0,AJ18,(1*75000*12)+(AJ18)-AD18) -> 0 | AY18: =IF(AE18=0,AK18,(1*100000*12)+(AK18)-AE18) -> 0 | AZ18: =SUM(AV18:AY18)-BF18+Z18-F18+BH18+BI18+BJ18+BK18+BL18+BM18 -> 950000 | BD18: =IF(AZ18=0,(AZ18-BA18-BC18),(AZ18-BA18-BB18-BC18))+F18 -> 950000 | BF18: =Z18*1/100*BG18 -> 50000 | BG18: 5 | BN18: GRATIFICATION BUREAU 2021 | BO18: PENALITE VERSEMENT ESPECES
A19: AS201620 | B19: =VLOOKUP(A19,[17]LISTADHERENT!A$5:H$39,3,0) -> LOWE JEAN | C19: =D19+E19+F19-U19-BB19 -> 0 | D19: =VLOOKUP(A19,[18]HISTOBQUEDEC23!$A$6:$G$44,3,0) -> 40000 | E19: =VLOOKUP(A19,[18]HISTOBQUEDEC23!$A$6:$G$39,4,0) -> 0 | F19: =VLOOKUP(A19,[18]HISTOBQUEDEC23!$A$6:$G$39,5,0) -> 0 | G19: =IF(H19="ESPECES",3000,0) -> 0 | H19: =IF($D19<>0,"BANQUE",IF($E19<>0,"ESPECES","ECHEC")) -> BANQUE | J19: 1 | K19: =IF($D19<>0,J19*40000,IF($E19<>0,J19*40000,0)) -> 40000 | M19: =IF($D19<>0,L19*75000,IF($E19<>0,L19*75000,0)) -> 0 | O19: =IF($D19<>0,N19*100000,IF($E19<>0,N19*100000,0)) -> 0 | P19: =VLOOKUP($A19,[20]TONTDEC23!$A$6:$P$35,12,0) -> 0 | U19: =G19+S19++R19+P19+O19+M19+I19+K19+Q19+W19 -> 40000 | V19: =10000+10000 -> 20000 | AQ19: =IF(H19="ECHEC",((K19+M19+O19)*20/100),0) -> 0 | AR19: =IF(H19="ECHEC",((K19+M19+O19)*20/100),0) -> 0 | AS19: =IF(H19="ECHEC",0,(K19+I19-25000)) -> 15000 | AW19: =IF(AC19=0,AI19,(1*25000*12)+AI19-AC19) -> 0 | AX19: =IF(AD19=0,AJ19,(1*75000*12)+(AJ19)-AD19) -> 0 | AY19: =IF(AE19=0,AK19,(1*100000*12)+(AK19)-AE19) -> 0 | AZ19: =SUM(AV19:AY19)-BF19+Z19-F19+BH19+BI19+BJ19+BK19+BL19+BM19 -> 0 | BD19: =IF(AZ19=0,(AZ19-BA19-BC19),(AZ19-BA19-BB19-BC19))+F19 -> 0 | BF19: =Z19*1/100*BG19 -> 0 | BG19: 12 | BN19: ACHAT LAPTOP | BO19: PENALITE VERSEMENT ESPECES
A20: AS201649 | B20: =VLOOKUP(A20,[17]LISTADHERENT!A$5:H$39,3,0) -> MBOGNING TUGMA GUY | C20: =D20+E20+F20-U20-BB20 -> 0 | D20: =VLOOKUP(A20,[18]HISTOBQUEDEC23!$A$6:$G$44,3,0) -> 0 | E20: =VLOOKUP(A20,[18]HISTOBQUEDEC23!$A$6:$G$39,4,0)+300000 -> 1829000 | F20: =VLOOKUP(A20,[18]HISTOBQUEDEC23!$A$6:$G$39,5,0) -> 0 | G20: =IF(H20="ESPECES",3000,0)-3000 -> 0 | H20: =IF($D20<>0,"BANQUE",IF($E20<>0,"ESPECES","ECHEC")) -> ESPECES | J20: 1 | K20: =IF($D20<>0,J20*40000,IF($E20<>0,J20*40000,0)) -> 40000 | L20: 1 | M20: =IF($D20<>0,L20*75000,IF($E20<>0,L20*75000,0)) -> 75000 | N20: 1 | O20: =IF($D20<>0,N20*100000,IF($E20<>0,N20*100000,0)) -> 100000 | P20: =VLOOKUP($A20,[20]TONTDEC23!$A$6:$P$35,12,0) -> 0 | Q20: =VLOOKUP($A20,[13]TONTDEC23!$A$6:$P$20,10,0) -> 307000 | R20: =VLOOKUP($A20,[19]TONTDEC23!$A$6:$P$21,10,0) -> 307000 | S20: 1000000 | T20: BANQUE | U20: =G20+S20++R20+P20+O20+M20+I20+K20+Q20+W20 -> 1829000 | Z20: 1000000 | AA20: BANQUE | AQ20: =IF(H20="ECHEC",((K20+M20+O20)*20/100),0) -> 0 | AR20: =IF(H20="ECHEC",((K20+M20+O20)*20/100),0) -> 0 | AS20: =IF(H20="ECHEC",0,(K20+I20-25000)) -> 15000 | AW20: =IF(AC20=0,AI20,(1*25000*12)+AI20-AC20) -> 0 | AX20: =IF(AD20=0,AJ20,(1*75000*12)+(AJ20)-AD20) -> 0 | AY20: =IF(AE20=0,AK20,(1*100000*12)+(AK20)-AE20) -> 0 | AZ20: =SUM(AV20:AY20)-BF20+Z20-F20+BH20+BI20+BJ20+BK20+BL20+BM20 -> 940000 | BD20: =IF(AZ20=0,(AZ20-BA20-BC20),(AZ20-BA20-BB20-BC20))+F20 -> 940000 | BF20: =Z20*1/100*BG20 -> 60000 | BG20: 6
A21: AS201639 | B21: =VLOOKUP(A21,[17]LISTADHERENT!A$5:H$39,3,0) -> NANGUEN MARTIN | C21: =D21+E21+F21-U21-BB21 -> 0 | D21: =VLOOKUP(A21,[18]HISTOBQUEDEC23!$A$6:$G$44,3,0) -> 540000 | E21: =VLOOKUP(A21,[18]HISTOBQUEDEC23!$A$6:$G$39,4,0) -> 0 | F21: =VLOOKUP(A21,[18]HISTOBQUEDEC23!$A$6:$G$39,5,0) -> 0 | G21: =IF(H21="ESPECES",3000,0) -> 0 | H21: =IF($D21<>0,"BANQUE",IF($E21<>0,"ESPECES","ECHEC")) -> BANQUE | J21: 1 | K21: =IF($D21<>0,J21*40000,IF($E21<>0,J21*40000,0)) -> 40000 | M21: =IF($D21<>0,L21*75000,IF($E21<>0,L21*75000,0)) -> 0 | O21: =IF($D21<>0,N21*100000,IF($E21<>0,N21*100000,0)) -> 0 | P21: =VLOOKUP($A21,[20]TONTDEC23!$A$6:$P$35,12,0) -> 0 | S21: 500000 | T21: BANQUE | U21: =G21+S21++R21+P21+O21+M21+I21+K21+Q21+W21 -> 540000 | Z21: 300000 | AA21: BANQUE | AQ21: =IF(H21="ECHEC",((K21+M21+O21)*20/100),0) -> 0 | AR21: =IF(H21="ECHEC",((K21+M21+O21)*20/100),0) -> 0 | AS21: =IF(H21="ECHEC",0,(K21+I21-25000)) -> 15000 | AW21: =IF(AC21=0,AI21,(1*25000*12)+AI21-AC21) -> 0 | AX21: =IF(AD21=0,AJ21,(1*75000*12)+(AJ21)-AD21) -> 0 | AY21: =IF(AE21=0,AK21,(1*100000*12)+(AK21)-AE21) -> 0 | AZ21: =SUM(AV21:AY21)-BF21+Z21-F21+BH21+BI21+BJ21+BK21+BL21+BM21 -> 282000 | BD21: =IF(AZ21=0,(AZ21-BA21-BC21),(AZ21-BA21-BB21-BC21))+F21 -> 282000 | BF21: =Z21*1/100*BG21 -> 18000 | BG21: 6
A22: AS201621 | B22: =VLOOKUP(A22,[17]LISTADHERENT!A$5:H$39,3,0) -> NANKAM APPOLINAIRE | C22: =D22+E22+F22-U22-BB22 -> 0 | D22: =VLOOKUP(A22,[18]HISTOBQUEDEC23!$A$6:$G$44,3,0) -> 222500 | E22: =VLOOKUP(A22,[18]HISTOBQUEDEC23!$A$6:$G$39,4,0) -> 0 | F22: =VLOOKUP(A22,[18]HISTOBQUEDEC23!$A$6:$G$39,5,0) -> 0 | G22: =IF(H22="ESPECES",3000,0) -> 0 | H22: =IF($D22<>0,"BANQUE",IF($E22<>0,"ESPECES","ECHEC")) -> BANQUE | J22: 1 | K22: =IF($D22<>0,J22*40000,IF($E22<>0,J22*40000,0)) -> 40000 | L22: 1 | M22: =IF($D22<>0,L22*75000,IF($E22<>0,L22*75000,0)) -> 75000 | O22: =IF($D22<>0,N22*100000,IF($E22<>0,N22*100000,0)) -> 0 | P22: =VLOOKUP($A22,[20]TONTDEC23!$A$6:$P$35,12,0) -> 0 | Q22: =VLOOKUP($A22,[13]TONTDEC23!$A$6:$P$20,10,0) -> 0 | S22: 107500 | T22: BANQUE | U22: =G22+S22++R22+P22+O22+M22+I22+K22+Q22+W22 -> 222500 | V22: =5000+6000+9000 -> 20000 | Z22: 1000000 | AA22: BANQUE | AQ22: =IF(H22="ECHEC",((K22+M22+O22)*20/100),0) -> 0 | AR22: =IF(H22="ECHEC",((K22+M22+O22)*20/100),0) -> 0 | AS22: =IF(H22="ECHEC",0,(K22+I22-25000)) -> 15000 | AW22: =IF(AC22=0,AI22,(1*25000*12)+AI22-AC22) -> 0 | AX22: =IF(AD22=0,AJ22,(1*75000*12)+(AJ22)-AD22) -> 0 | AY22: =IF(AE22=0,AK22,(1*100000*12)+(AK22)-AE22) -> 0 | AZ22: =SUM(AV22:AY22)-BF22+Z22-F22+BH22+BI22+BJ22+BK22+BL22+BM22 -> 880000 | BD22: =IF(AZ22=0,(AZ22-BA22-BC22),(AZ22-BA22-BB22-BC22))+F22+53000 -> 933000 | BF22: =Z22*1/100*BG22 -> 120000 | BG22: 12 | BN22: S/TOTAL | BP22: =SUM(BP18:BP21) -> 0
A23: AS201622 | B23: =VLOOKUP(A23,[17]LISTADHERENT!A$5:H$39,3,0) -> NDJOMO ETIENNE | C23: =D23+E23+F23-U23-BB23 -> 0 | D23: =VLOOKUP(A23,[18]HISTOBQUEDEC23!$A$6:$G$44,3,0) -> 850000 | E23: =VLOOKUP(A23,[18]HISTOBQUEDEC23!$A$6:$G$39,4,0) -> 0 | F23: =VLOOKUP(A23,[18]HISTOBQUEDEC23!$A$6:$G$39,5,0) -> 0 | G23: =IF(H23="ESPECES",3000,0) -> 0 | H23: =IF($D23<>0,"BANQUE",IF($E23<>0,"ESPECES","ECHEC")) -> BANQUE | I23: 10000 | J23: 1 | K23: =IF($D23<>0,J23*40000,IF($E23<>0,J23*40000,0)) -> 40000 | M23: =IF($D23<>0,L23*75000,IF($E23<>0,L23*75000,0)) -> 0 | N23: 2 | O23: =IF($D23<>0,N23*100000,IF($E23<>0,N23*100000,0)) -> 200000 | P23: =VLOOKUP($A23,[20]TONTDEC23!$A$6:$P$35,12,0) -> 0 | R23: =VLOOKUP($A23,[19]TONTDEC23!$A$6:$P$21,10,0) -> 0 | S23: 600000 | T23: BANQUE | U23: =G23+S23++R23+P23+O23+M23+I23+K23+Q23+W23 -> 850000 | Z23: 500000 | AA23: BANQUE | AQ23: =IF(H23="ECHEC",((K23+M23+O23)*20/100),0) -> 0 | AR23: =IF(H23="ECHEC",((K23+M23+O23)*20/100),0) -> 0 | AS23: =IF(H23="ECHEC",0,(K23+I23-25000)) -> 25000 | AW23: =IF(AC23=0,AI23,(1*25000*12)+AI23-AC23) -> 0 | AX23: =IF(AD23=0,AJ23,(1*75000*12)+(AJ23)-AD23) -> 0 | AY23: =IF(AE23=0,AK23,(1*100000*12)+(AK23)-AE23) -> 0 | AZ23: =SUM(AV23:AY23)-BF23+Z23-F23+BH23+BI23+BJ23+BK23+BL23+BM23 -> 470000 | BD23: =IF(AZ23=0,(AZ23-BA23-BC23),(AZ23-BA23-BB23-BC23))+F23+220000 -> 690000 | BF23: =Z23*1/100*BG23 -> 30000 | BG23: 6
A24: AS201624 | B24: =VLOOKUP(A24,[17]LISTADHERENT!A$5:H$39,3,0) -> NGONDIEP CLAUDE | C24: =D24+E24+F24-U24-BB24 -> 0 | D24: =VLOOKUP(A24,[18]HISTOBQUEDEC23!$A$6:$G$44,3,0) -> 1215000 | E24: =VLOOKUP(A24,[18]HISTOBQUEDEC23!$A$6:$G$39,4,0) -> 202000 | F24: =VLOOKUP(A24,[18]HISTOBQUEDEC23!$A$6:$G$39,5,0) -> 0 | G24: =IF(H24="ESPECES",3000,0) -> 0 | H24: =IF($D24<>0,"BANQUE",IF($E24<>0,"ESPECES","ECHEC")) -> BANQUE | J24: 1 | K24: =IF($D24<>0,J24*40000,IF($E24<>0,J24*40000,0)) -> 40000 | L24: 1 | M24: =IF($D24<>0,L24*75000,IF($E24<>0,L24*75000,0)) -> 75000 | N24: 1 | O24: =IF($D24<>0,N24*100000,IF($E24<>0,N24*100000,0)) -> 100000 | P24: =VLOOKUP($A24,[20]TONTDEC23!$A$6:$P$35,12,0) -> 0 | Q24: =VLOOKUP($A24,[13]TONTDEC23!$A$6:$P$20,10,0) -> 0 | R24: =VLOOKUP($A24,[19]TONTDEC23!$A$6:$P$21,10,0) -> 202000 | S24: 1000000 | T24: BANQUE | U24: =G24+S24++R24+P24+O24+M24+I24+K24+Q24+W24 -> 1417000 | V24: =9000+6000 -> 15000 | Z24: 1000000 | AA24: BANQUE | AQ24: =IF(H24="ECHEC",((K24+M24+O24)*20/100),0) -> 0 | AR24: =IF(H24="ECHEC",((K24+M24+O24)*20/100),0) -> 0 | AS24: =IF(H24="ECHEC",0,(K24+I24-25000)) -> 15000 | AW24: =IF(AC24=0,AI24,(1*25000*12)+AI24-AC24) -> 0 | AX24: =IF(AD24=0,AJ24,(1*75000*12)+(AJ24)-AD24) -> 0 | AY24: =IF(AE24=0,AK24,(1*100000*12)+(AK24)-AE24) -> 0 | AZ24: =SUM(AV24:AY24)-BF24+Z24-F24+BH24+BI24+BJ24+BK24+BL24+BM24 -> 880000 | BD24: =IF(AZ24=0,(AZ24-BA24-BC24),(AZ24-BA24-BB24-BC24))+F24-202000 -> 678000 | BF24: =Z24*1/100*BG24 -> 120000 | BG24: 12 | BN24: GRATIFICATION BUREAU 2021 | BO24: FRAIS EXEPTIONNEL
A25: AS201626 | B25: =VLOOKUP(A25,[17]LISTADHERENT!A$5:H$39,3,0) -> NGUIEMEGNI MATHIEU BLAISE | C25: =D25+E25+F25-U25-BB25 -> 0 | D25: =VLOOKUP(A25,[18]HISTOBQUEDEC23!$A$6:$G$44,3,0) -> 600000 | E25: =VLOOKUP(A25,[18]HISTOBQUEDEC23!$A$6:$G$39,4,0) -> 1000000 | F25: =VLOOKUP(A25,[18]HISTOBQUEDEC23!$A$6:$G$39,5,0) -> 0 | G25: =IF(H25="ESPECES",3000,0) -> 0 | H25: =IF($D25<>0,"BANQUE",IF($E25<>0,"ESPECES","ECHEC")) -> BANQUE | I25: 108000 | J25: 1 | K25: =IF($D25<>0,J25*40000,IF($E25<>0,J25*40000,0)) -> 40000 | L25: 2 | M25: =IF($D25<>0,L25*75000,IF($E25<>0,L25*75000,0)) -> 150000 | N25: 1 | O25: =IF($D25<>0,N25*100000,IF($E25<>0,N25*100000,0)) -> 100000 | P25: =VLOOKUP($A25,[20]TONTDEC23!$A$6:$P$35,12,0) -> 0 | Q25: =VLOOKUP($A25,[13]TONTDEC23!$A$6:$P$20,10,0) -> 0 | R25: =VLOOKUP($A25,[19]TONTDEC23!$A$6:$P$21,10,0) -> 202000 | S25: 1000000 | T25: BANQUE | U25: =G25+S25++R25+P25+O25+M25+I25+K25+Q25+W25 -> 1600000 | V25: =9000+6000 -> 15000 | Z25: 1000000 | AA25: BANQUE | AQ25: =IF(H25="ECHEC",((K25+M25+O25)*20/100),0) -> 0 | AR25: =IF(H25="ECHEC",((K25+M25+O25)*20/100),0) -> 0 | AS25: =IF(H25="ECHEC",0,(K25+I25-25000)) -> 123000 | AW25: =IF(AC25=0,AI25,(1*25000*12)+AI25-AC25) -> 0 | AX25: =IF(AD25=0,AJ25,(1*75000*12)+(AJ25)-AD25) -> 0 | AY25: =IF(AE25=0,AK25,(1*100000*12)+(AK25)-AE25) -> 0 | AZ25: =SUM(AV25:AY25)-BF25+Z25-F25+BH25+BI25+BJ25+BK25+BL25+BM25 -> 880000 | BD25: =IF(AZ25=0,(AZ25-BA25-BC25),(AZ25-BA25-BB25-BC25))+F25+300000 -> 1180000 | BF25: =Z25*1/100*BG25 -> 120000 | BG25: 12 | BN25: DEVELOPPEMENT LAGWEU | BO25: FRAIS EXEPTIONNEL
A26: AS201628 | B26: =VLOOKUP(A26,[17]LISTADHERENT!A$5:H$39,3,0) -> NKAMGANG JUSTIN DEJOLIE | C26: =D26+E26+F26-U26-BB26 -> 0 | D26: =VLOOKUP(A26,[18]HISTOBQUEDEC23!$A$6:$G$44,3,0) -> 0 | E26: =VLOOKUP(A26,[18]HISTOBQUEDEC23!$A$6:$G$39,4,0) -> 1040000 | F26: =VLOOKUP(A26,[18]HISTOBQUEDEC23!$A$6:$G$39,5,0) -> 0 | G26: =IF(H26="ESPECES",3000,0)-3000 -> 0 | H26: =IF($D26<>0,"BANQUE",IF($E26<>0,"ESPECES","ECHEC")) -> ESPECES | J26: 1 | K26: =IF($D26<>0,J26*40000,IF($E26<>0,J26*40000,0)) -> 40000 | M26: =IF($D26<>0,L26*75000,IF($E26<>0,L26*75000,0)) -> 0 | O26: =IF($D26<>0,N26*100000,IF($E26<>0,N26*100000,0)) -> 0 | P26: =VLOOKUP($A26,[20]TONTDEC23!$A$6:$P$35,12,0) -> 0 | S26: 1000000 | T26: BANQUE | U26: =G26+S26++R26+P26+O26+M26+I26+K26+Q26+W26 -> 1040000 | Z26: 1000000 | AA26: BANQUE | AQ26: =IF(H26="ECHEC",((K26+M26+O26)*20/100),0) -> 0 | AR26: =IF(H26="ECHEC",((K26+M26+O26)*20/100),0) -> 0 | AS26: =IF(H26="ECHEC",0,(K26+I26-25000)) -> 15000 | AW26: =IF(AC26=0,AI26,(1*25000*12)+AI26-AC26) -> 0 | AX26: =IF(AD26=0,AJ26,(1*75000*12)+(AJ26)-AD26) -> 0 | AY26: =IF(AE26=0,AK26,(1*100000*12)+(AK26)-AE26) -> 0 | AZ26: =SUM(AV26:AY26)-BF26+Z26-F26+BH26+BI26+BJ26+BK26+BL26+BM26 -> 970000 | BD26: =IF(AZ26=0,(AZ26-BA26-BC26),(AZ26-BA26-BB26-BC26))+F26 -> 970000 | BF26: =Z26*1/100*BG26 -> 30000 | BG26: 3 | BN26: DEUIL TCHEMNOU EMMANUEL | BO26: FRAIS EXEPTIONNEL
A27: AS201656 | B27: =VLOOKUP(A27,[17]LISTADHERENT!A$5:H$39,3,0) -> NOUBE ETIENNE | C27: =D27+E27+F27-U27-BB27 -> 0 | D27: =VLOOKUP(A27,[18]HISTOBQUEDEC23!$A$6:$G$44,3,0) -> 50000 | E27: =VLOOKUP(A27,[18]HISTOBQUEDEC23!$A$6:$G$39,4,0) -> 0 | F27: =VLOOKUP(A27,[18]HISTOBQUEDEC23!$A$6:$G$39,5,0) -> 0 | G27: =IF(H27="ESPECES",3000,0) -> 0 | H27: =IF($D27<>0,"BANQUE",IF($E27<>0,"ESPECES","ECHEC")) -> BANQUE | I27: 10000 | J27: 1 | K27: =IF($D27<>0,J27*40000,IF($E27<>0,J27*40000,0)) -> 40000 | M27: =IF($D27<>0,L27*75000,IF($E27<>0,L27*75000,0)) -> 0 | O27: =IF($D27<>0,N27*100000,IF($E27<>0,N27*100000,0)) -> 0 | P27: =VLOOKUP($A27,[20]TONTDEC23!$A$6:$P$35,12,0) -> 0 | U27: =G27+S27++R27+P27+O27+M27+I27+K27+Q27+W27 -> 50000 | AQ27: =IF(H27="ECHEC",((K27+M27+O27)*20/100),0) -> 0 | AR27: =IF(H27="ECHEC",((K27+M27+O27)*20/100),0) -> 0 | AS27: =IF(H27="ECHEC",0,(K27+I27-25000)) -> 25000 | AW27: =IF(AC27=0,AI27,(1*25000*12)+AI27-AC27) -> 0 | AX27: =IF(AD27=0,AJ27,(1*75000*12)+(AJ27)-AD27) -> 0 | AY27: =IF(AE27=0,AK27,(1*100000*12)+(AK27)-AE27) -> 0 | AZ27: =SUM(AV27:AY27)-BF27+Z27-F27+BH27+BI27+BJ27+BK27+BL27+BM27 -> 0 | BD27: =IF(AZ27=0,(AZ27-BA27-BC27),(AZ27-BA27-BB27-BC27))+F27 -> 0 | BF27: =Z27*1/100*BG27 -> 0 | BG27: 12
A28: AS201633 | B28: =VLOOKUP(A28,[17]LISTADHERENT!A$5:H$39,3,0) -> PATEGO NJOSSU GUSTAVE | C28: =D28+E28+F28-U28-BB28 -> 0 | D28: =VLOOKUP(A28,[18]HISTOBQUEDEC23!$A$6:$G$44,3,0) -> 115000 | E28: =VLOOKUP(A28,[18]HISTOBQUEDEC23!$A$6:$G$39,4,0) -> 0 | F28: =VLOOKUP(A28,[18]HISTOBQUEDEC23!$A$6:$G$39,5,0) -> 0 | G28: =IF(H28="ESPECES",3000,0) -> 0 | H28: =IF($D28<>0,"BANQUE",IF($E28<>0,"ESPECES","ECHEC")) -> BANQUE | J28: 1 | K28: =IF($D28<>0,J28*40000,IF($E28<>0,J28*40000,0)) -> 40000 | L28: 1 | M28: =IF($D28<>0,L28*75000,IF($E28<>0,L28*75000,0)) -> 75000 | O28: =IF($D28<>0,N28*100000,IF($E28<>0,N28*100000,0)) -> 0 | P28: =VLOOKUP($A28,[20]TONTDEC23!$A$6:$P$35,12,0) -> 0 | Q28: =VLOOKUP($A28,[13]TONTDEC23!$A$6:$P$20,10,0) -> 0 | U28: =G28+S28++R28+P28+O28+M28+I28+K28+Q28+W28 -> 115000 | AQ28: =IF(H28="ECHEC",((K28+M28+O28)*20/100),0) -> 0 | AR28: =IF(H28="ECHEC",((K28+M28+O28)*20/100),0) -> 0 | AS28: =IF(H28="ECHEC",0,(K28+I28-25000)) -> 15000 | AW28: =IF(AC28=0,AI28,(1*25000*12)+AI28-AC28) -> 0 | AX28: =IF(AD28=0,AJ28,(1*75000*12)+(AJ28)-AD28) -> 0 | AY28: =IF(AE28=0,AK28,(1*100000*12)+(AK28)-AE28) -> 0 | AZ28: =SUM(AV28:AY28)-BF28+Z28-F28+BH28+BI28+BJ28+BK28+BL28+BM28 -> 0 | BD28: =IF(AZ28=0,(AZ28-BA28-BC28),(AZ28-BA28-BB28-BC28))+F28 -> 0 | BF28: =Z28*1/100*BG28 -> 0 | BG28: 12 | BN28: S/TOTAL | BP28: =SUM(BP24:BP26) -> 0
A29: AS201657 | B29: =VLOOKUP(A29,[17]LISTADHERENT!A$5:H$39,3,0) -> SEUMO POLYCARPE | C29: =D29+E29+F29-U29-BB29 -> 0 | D29: =VLOOKUP(A29,[18]HISTOBQUEDEC23!$A$6:$G$44,3,0) -> 40000 | E29: =VLOOKUP(A29,[18]HISTOBQUEDEC23!$A$6:$G$39,4,0) -> 0 | F29: =VLOOKUP(A29,[18]HISTOBQUEDEC23!$A$6:$G$39,5,0) -> 0 | G29: =IF(H29="ESPECES",3000,0) -> 0 | H29: =IF($D29<>0,"BANQUE",IF($E29<>0,"ESPECES","ECHEC")) -> BANQUE | J29: 1 | K29: =IF($D29<>0,J29*40000,IF($E29<>0,J29*40000,0)) -> 40000 | M29: =IF($D29<>0,L29*75000,IF($E29<>0,L29*75000,0)) -> 0 | O29: =IF($D29<>0,N29*100000,IF($E29<>0,N29*100000,0)) -> 0 | P29: =VLOOKUP($A29,[20]TONTDEC23!$A$6:$P$35,12,0) -> 0 | U29: =G29+S29++R29+P29+O29+M29+I29+K29+Q29+W29 -> 40000 | AQ29: =IF(H29="ECHEC",((K29+M29+O29)*20/100),0) -> 0 | AR29: =IF(H29="ECHEC",((K29+M29+O29)*20/100),0) -> 0 | AS29: =IF(H29="ECHEC",0,(K29+I29-25000)) -> 15000 | AW29: =IF(AC29=0,AI29,(1*25000*12)+AI29-AC29) -> 0 | AX29: =IF(AD29=0,AJ29,(1*75000*12)+(AJ29)-AD29) -> 0 | AY29: =IF(AE29=0,AK29,(1*100000*12)+(AK29)-AE29) -> 0 | AZ29: =SUM(AV29:AY29)-BF29+Z29-F29+BH29+BI29+BJ29+BK29+BL29+BM29 -> 0 | BD29: =IF(AZ29=0,(AZ29-BA29-BC29),(AZ29-BA29-BB29-BC29))+F29 -> 0 | BF29: =Z29*1/100*BG29 -> 0 | BG29: 12
A30: AS201653 | B30: =VLOOKUP(A30,[17]LISTADHERENT!A$5:H$39,3,0) -> SIME BRICE | C30: =D30+E30+F30-U30-BB30 -> 0 | D30: =VLOOKUP(A30,[18]HISTOBQUEDEC23!$A$6:$G$44,3,0) -> 115000 | E30: =VLOOKUP(A30,[18]HISTOBQUEDEC23!$A$6:$G$39,4,0) -> 0 | F30: =VLOOKUP(A30,[18]HISTOBQUEDEC23!$A$6:$G$39,5,0) -> 0 | G30: =IF(H30="ESPECES",3000,0) -> 0 | H30: =IF($D30<>0,"BANQUE",IF($E30<>0,"ESPECES","ECHEC")) -> BANQUE | J30: 1 | K30: =IF($D30<>0,J30*40000,IF($E30<>0,J30*40000,0)) -> 40000 | L30: 1 | M30: =IF($D30<>0,L30*75000,IF($E30<>0,L30*75000,0)) -> 75000 | O30: =IF($D30<>0,N30*100000,IF($E30<>0,N30*100000,0)) -> 0 | P30: =VLOOKUP($A30,[20]TONTDEC23!$A$6:$P$35,12,0) -> 0 | Q30: =VLOOKUP($A30,[13]TONTDEC23!$A$6:$P$20,10,0) -> 0 | U30: =G30+S30++R30+P30+O30+M30+I30+K30+Q30+W30 -> 115000 | V30: =10000+12000+12000 -> 34000 | Z30: 1000000 | AA30: BANQUE | AQ30: =IF(H30="ECHEC",((K30+M30+O30)*20/100),0) -> 0 | AR30: =IF(H30="ECHEC",((K30+M30+O30)*20/100),0) -> 0 | AS30: =IF(H30="ECHEC",0,(K30+I30-25000)) -> 15000 | AW30: =IF(AC30=0,AI30,(1*25000*12)+AI30-AC30) -> 0 | AX30: =IF(AD30=0,AJ30,(1*75000*12)+(AJ30)-AD30) -> 0 | AY30: =IF(AE30=0,AK30,(1*100000*12)+(AK30)-AE30) -> 0 | AZ30: =SUM(AV30:AY30)-BF30+Z30-F30+BH30+BI30+BJ30+BK30+BL30+BM30 -> 940000 | BD30: =IF(AZ30=0,(AZ30-BA30-BC30),(AZ30-BA30-BB30-BC30))+F30-772000 -> 168000 | BF30: =Z30*1/100*BG30 -> 60000 | BG30: 6 | BN30: DECES | BO30: MUTUELLE
A31: AS201638 | B31: =VLOOKUP(A31,[17]LISTADHERENT!A$5:H$39,3,0) -> SIMO PIERRE | C31: =D31+E31+F31-U31-BB31 -> 0 | D31: =VLOOKUP(A31,[18]HISTOBQUEDEC23!$A$6:$G$44,3,0) -> 1171000 | E31: =VLOOKUP(A31,[18]HISTOBQUEDEC23!$A$6:$G$39,4,0) -> 0 | F31: =VLOOKUP(A31,[18]HISTOBQUEDEC23!$A$6:$G$39,5,0) -> 0 | G31: =IF(H31="ESPECES",3000,0) -> 0 | H31: =IF($D31<>0,"BANQUE",IF($E31<>0,"ESPECES","ECHEC")) -> BANQUE | J31: 1 | K31: =IF($D31<>0,J31*40000,IF($E31<>0,J31*40000,0)) -> 40000 | M31: =IF($D31<>0,L31*75000,IF($E31<>0,L31*75000,0)) -> 0 | N31: 1 | O31: =IF($D31<>0,N31*100000,IF($E31<>0,N31*100000,0)) -> 100000 | P31: =VLOOKUP($A31,[20]TONTDEC23!$A$6:$P$35,12,0) -> 0 | R31: =VLOOKUP($A31,[19]TONTDEC23!$A$6:$P$21,10,0) -> 31000 | S31: 1000000 | T31: BANQUE | U31: =G31+S31++R31+P31+O31+M31+I31+K31+Q31+W31 -> 1171000 | Z31: 250000 | AA31: BANQUE | AQ31: =IF(H31="ECHEC",((K31+M31+O31)*20/100),0) -> 0 | AR31: =IF(H31="ECHEC",((K31+M31+O31)*20/100),0) -> 0 | AS31: =IF(H31="ECHEC",0,(K31+I31-25000)) -> 15000 | AW31: =IF(AC31=0,AI31,(1*25000*12)+AI31-AC31) -> 0 | AX31: =IF(AD31=0,AJ31,(1*75000*12)+(AJ31)-AD31) -> 0 | AY31: =IF(AE31=0,AK31,(1*100000*12)+(AK31)-AE31) -> 0 | AZ31: =SUM(AV31:AY31)-BF31+Z31-F31+BH31+BI31+BJ31+BK31+BL31+BM31 -> 235000 | BD31: =IF(AZ31=0,(AZ31-BA31-BC31),(AZ31-BA31-BB31-BC31))+F31+230000 -> 465000 | BF31: =Z31*1/100*BG31 -> 15000 | BG31: 6 | BN31: TRANSPORT DELEGUE | BO31: MUTUELLE
A32: AS201641 | B32: =VLOOKUP(A32,[17]LISTADHERENT!A$5:H$39,3,0) -> TCHOUAMOU MATHIEU | C32: =D32+E32+F32-U32-BB32 -> 0 | D32: =VLOOKUP(A32,[18]HISTOBQUEDEC23!$A$6:$G$44,3,0) -> 416000 | E32: =VLOOKUP(A32,[18]HISTOBQUEDEC23!$A$6:$G$39,4,0) -> 0 | F32: =VLOOKUP(A32,[18]HISTOBQUEDEC23!$A$6:$G$39,5,0) -> 0 | G32: =IF(H32="ESPECES",3000,0) -> 0 | H32: =IF($D32<>0,"BANQUE",IF($E32<>0,"ESPECES","ECHEC")) -> BANQUE | J32: 1 | K32: =IF($D32<>0,J32*40000,IF($E32<>0,J32*40000,0)) -> 40000 | L32: 1 | M32: =IF($D32<>0,L32*75000,IF($E32<>0,L32*75000,0)) -> 75000 | O32: =IF($D32<>0,N32*100000,IF($E32<>0,N32*100000,0)) -> 0 | P32: =VLOOKUP($A32,[20]TONTDEC23!$A$6:$P$35,12,0) -> 0 | Q32: =VLOOKUP($A32,[13]TONTDEC23!$A$6:$P$20,10,0) -> 101000 | S32: 200000 | T32: BANQUE | U32: =G32+S32++R32+P32+O32+M32+I32+K32+Q32+W32 -> 416000 | AQ32: =IF(H32="ECHEC",((K32+M32+O32)*20/100),0) -> 0 | AR32: =IF(H32="ECHEC",((K32+M32+O32)*20/100),0) -> 0 | AS32: =IF(H32="ECHEC",0,(K32+I32-25000)) -> 15000 | AW32: =IF(AC32=0,AI32,(1*25000*12)+AI32-AC32) -> 0 | AX32: =IF(AD32=0,AJ32,(1*75000*12)+(AJ32)-AD32) -> 0 | AY32: =IF(AE32=0,AK32,(1*100000*12)+(AK32)-AE32) -> 0 | AZ32: =SUM(AV32:AY32)-BF32+Z32-F32+BH32+BI32+BJ32+BK32+BL32+BM32 -> 0 | BD32: =IF(AZ32=0,(AZ32-BA32-BC32),(AZ32-BA32-BB32-BC32))+F32 -> 0 | BF32: =Z32*1/100*BG32 -> 0 | BG32: 12
A33: AS201643 | B33: =VLOOKUP(A33,[17]LISTADHERENT!A$5:H$39,3,0) -> TCHOUTOU NANA CLAUDE | C33: =D33+E33+F33-U33-BB33+70000 -> 40000 | D33: =VLOOKUP(A33,[18]HISTOBQUEDEC23!$A$6:$G$44,3,0) -> 90000 | E33: =VLOOKUP(A33,[18]HISTOBQUEDEC23!$A$6:$G$39,4,0) -> 0 | F33: =VLOOKUP(A33,[18]HISTOBQUEDEC23!$A$6:$G$39,5,0) -> 0 | G33: =IF(H33="ESPECES",3000,0) -> 0 | H33: =IF($D33<>0,"BANQUE",IF($E33<>0,"ESPECES","ECHEC")) -> BANQUE | I33: 10000 | J33: 1 | K33: =IF($D33<>0,J33*40000,IF($E33<>0,J33*40000,0)) -> 40000 | M33: =IF($D33<>0,L33*75000,IF($E33<>0,L33*75000,0)) -> 0 | O33: =IF($D33<>0,N33*100000,IF($E33<>0,N33*100000,0)) -> 0 | P33: =VLOOKUP($A33,[20]TONTDEC23!$A$6:$P$35,12,0) -> 0 | U33: =G33+S33++R33+P33+O33+M33+I33+K33+Q33+W33 -> 50000 | AC33: 2500 | AQ33: =IF(H33="ECHEC",((K33+M33+O33)*20/100),0) -> 0 | AR33: =IF(H33="ECHEC",((K33+M33+O33)*20/100),0) -> 0 | AS33: =IF(H33="ECHEC",0,(K33+I33-25000)) -> 25000 | AW33: =IF(AC33=0,AI33,(1*25000*12)+AI33-AC33) -> 297500 | AX33: =IF(AD33=0,AJ33,(1*75000*12)+(AJ33)-AD33) -> 0 | AY33: =IF(AE33=0,AK33,(1*100000*12)+(AK33)-AE33) -> 0 | AZ33: =SUM(AV33:AY33)-BF33+Z33-F33+BH33+BI33+BJ33+BK33+BL33+BM33 -> 297500 | BB33: 70000 | BD33: =IF(AZ33=0,(AZ33-BA33-BC33),(AZ33-BA33-BB33-BC33))+F33-51500 -> 176000 | BF33: =Z33*1/100*BG33 -> 0 | BG33: 12 | BN33: S/TOTAL | BP33: =SUM(BP30:BP32) -> 0
A34: AS201658 | B34: =VLOOKUP(A34,[17]LISTADHERENT!A$5:H$39,3,0) -> YANTCHOU GERVAIS | C34: =D34+E34+F34-U34-BB34 -> 0 | D34: =VLOOKUP(A34,[18]HISTOBQUEDEC23!$A$6:$G$44,3,0) -> 40000 | E34: =VLOOKUP(A34,[18]HISTOBQUEDEC23!$A$6:$G$39,4,0) -> 0 | F34: =VLOOKUP(A34,[18]HISTOBQUEDEC23!$A$6:$G$39,5,0) -> 0 | G34: =IF(H34="ESPECES",3000,0) -> 0 | H34: =IF($D34<>0,"BANQUE",IF($E34<>0,"ESPECES","ECHEC")) -> BANQUE | J34: 1 | K34: =IF($D34<>0,J34*40000,IF($E34<>0,J34*40000,0)) -> 40000 | M34: =IF($D34<>0,L34*75000,IF($E34<>0,L34*75000,0)) -> 0 | O34: =IF($D34<>0,N34*100000,IF($E34<>0,N34*100000,0)) -> 0 | P34: =VLOOKUP($A34,[20]TONTDEC23!$A$6:$P$35,12,0) -> 0 | U34: =G34+S34++R34+P34+O34+M34+I34+K34+Q34+W34 -> 40000 | Z34: 700000 | AA34: BANQUE | AQ34: =IF(H34="ECHEC",((K34+M34+O34)*20/100),0) -> 0 | AR34: =IF(H34="ECHEC",((K34+M34+O34)*20/100),0) -> 0 | AS34: =IF(H34="ECHEC",0,(K34+I34-25000)) -> 15000 | AW34: =IF(AC34=0,AI34,(1*25000*12)+AI34-AC34) -> 0 | AX34: =IF(AD34=0,AJ34,(1*75000*12)+(AJ34)-AD34) -> 0 | AY34: =IF(AE34=0,AK34,(1*100000*12)+(AK34)-AE34) -> 0 | AZ34: =SUM(AV34:AY34)-BF34+Z34-F34+BH34+BI34+BJ34+BK34+BL34+BM34 -> 616000 | BD34: =IF(AZ34=0,(AZ34-BA34-BC34),(AZ34-BA34-BB34-BC34))+F34 -> 616000 | BF34: =Z34*1/100*BG34 -> 84000 | BG34: 12
A35: AS201646 | B35: =VLOOKUP(A35,[17]LISTADHERENT!A$5:H$39,3,0) -> YEPMOU JEAN JACQUES | C35: =D35+E35+F35-U35-BB35+70000 -> 0 | D35: =VLOOKUP(A35,[18]HISTOBQUEDEC23!$A$6:$G$44,3,0)+227500 -> 227500 | E35: =VLOOKUP(A35,[18]HISTOBQUEDEC23!$A$6:$G$39,4,0) -> 40000 | F35: =VLOOKUP(A35,[18]HISTOBQUEDEC23!$A$6:$G$39,5,0) -> 0 | G35: =IF(H35="ESPECES",3000,0) -> 0 | H35: =IF($D35<>0,"BANQUE",IF($E35<>0,"ESPECES","ECHEC")) -> BANQUE | J35: 1 | K35: =IF($D35<>0,J35*40000,IF($E35<>0,J35*40000,0)) -> 40000 | M35: =IF($D35<>0,L35*75000,IF($E35<>0,L35*75000,0)) -> 0 | O35: =IF($D35<>0,N35*100000,IF($E35<>0,N35*100000,0)) -> 0 | P35: =VLOOKUP($A35,[20]TONTDEC23!$A$6:$P$35,12,0) -> 0 | S35: 227500 | T35: BANQUE | U35: =G35+S35++R35+P35+O35+M35+I35+K35+Q35+W35 -> 267500 | AC35: 2500 | AQ35: =IF(H35="ECHEC",((K35+M35+O35)*20/100),0) -> 0 | AR35: =IF(H35="ECHEC",((K35+M35+O35)*20/100),0) -> 0 | AS35: =IF(H35="ECHEC",0,(K35+I35-25000)) -> 15000 | AW35: =IF(AC35=0,AI35,(1*25000*12)+AI35-AC35) -> 297500 | AX35: =IF(AD35=0,AJ35,(1*75000*12)+(AJ35)-AD35) -> 0 | AY35: =IF(AE35=0,AK35,(1*100000*12)+(AK35)-AE35) -> 0 | AZ35: =SUM(AV35:AY35)-BF35+Z35-F35+BH35+BI35+BJ35+BK35+BL35+BM35 -> 297500 | BB35: 70000 | BD35: =IF(AZ35=0,(AZ35-BA35-BC35),(AZ35-BA35-BB35-BC35))+F35 -> 227500 | BF35: =Z35*1/100*BG35 -> 0 | BG35: 12 | BN35: COLLATION | BO35: COLLATION
A36: AS201647 | B36: =VLOOKUP(A36,[17]LISTADHERENT!A$5:H$39,3,0) -> YOUMBI EMMANUEL | C36: =D36+E36+F36-U36-BB36 -> 0 | D36: =VLOOKUP(A36,[18]HISTOBQUEDEC23!$A$6:$G$44,3,0) -> 290000 | E36: =VLOOKUP(A36,[18]HISTOBQUEDEC23!$A$6:$G$39,4,0) -> 0 | F36: =VLOOKUP(A36,[18]HISTOBQUEDEC23!$A$6:$G$39,5,0) -> 0 | G36: =IF(H36="ESPECES",3000,0) -> 0 | H36: =IF($D36<>0,"BANQUE",IF($E36<>0,"ESPECES","ECHEC")) -> BANQUE | J36: 1 | K36: =IF($D36<>0,J36*40000,IF($E36<>0,J36*40000,0)) -> 40000 | L36: 2 | M36: =IF($D36<>0,L36*75000,IF($E36<>0,L36*75000,0)) -> 150000 | N36: 1 | O36: =IF($D36<>0,N36*100000,IF($E36<>0,N36*100000,0)) -> 100000 | P36: =VLOOKUP($A36,[20]TONTDEC23!$A$6:$P$35,12,0) -> 0 | Q36: =VLOOKUP($A36,[13]TONTDEC23!$A$6:$P$20,10,0) -> 0 | R36: =VLOOKUP($A36,[19]TONTDEC23!$A$6:$P$21,10,0) -> 0 | U36: =G36+S36++R36+P36+O36+M36+I36+K36+Q36+W36 -> 290000 | V36: =5000+6000 -> 11000 | AQ36: =IF(H36="ECHEC",((K36+M36+O36)*20/100),0) -> 0 | AR36: =IF(H36="ECHEC",((K36+M36+O36)*20/100),0) -> 0 | AS36: =IF(H36="ECHEC",0,(K36+I36-25000)) -> 15000 | AW36: =IF(AC36=0,AI36,(1*25000*12)+AI36-AC36) -> 0 | AX36: =IF(AD36=0,AJ36,(1*75000*12)+(AJ36)-AD36) -> 0 | AY36: =IF(AE36=0,AK36,(1*100000*12)+(AK36)-AE36) -> 0 | AZ36: =SUM(AV36:AY36)-BF36+Z36-F36+BH36+BI36+BJ36+BK36+BL36+BM36 -> 0 | BD36: =IF(AZ36=0,(AZ36-BA36-BC36),(AZ36-BA36-BB36-BC36))+F36 -> 0 | BF36: =Z36*1/100*BG36 -> 0 | BG36: 12 | BN36: BOISSON | BO36: COLLATION
B38: TOTAUX | C38: =SUM(C6:C37) -> 261000 | D38: =SUM(D6:D37) -> 11438000 | E38: =SUM(E6:E37) -> 8171000 | F38: =SUM(F6:F37) -> 0 | G38: =SUM(G6:G37) -> 0 | H38: =SUM(H6:H37) -> 0 | I38: =SUM(I6:I37) -> 203800 | J38: =SUM(J6:J37) -> 30 | ... S38: =SUM(S6:S37) -> 13317700 | U38: =SUM(U6:U37) -> 19348000 | V38: =SUM(V6:V37) -> 207000 | W38: =SUM(W6:W37) -> 0 | X38: =SUM(X6:X37) -> 0 | Y38: =SUM(Y6:Y37) -> 0 | Z38: =SUM(Z6:Z37) -> 14250000 | AA38: =SUM(AA6:AA37) -> 0 | AC38: =SUM(AC6:AC37) -> 5000 | AD38: =SUM(AD6:AD37) -> 7500 | AE38: =SUM(AE6:AE37) -> 10000 | AF38: =SUM(AF6:AF37) -> 0 | AG38: =SUM(AG6:AG37) -> 0 | AI38: =SUM(AI6:AI37) -> 0 | AJ38: =SUM(AJ6:AJ37) -> 0 | AK38: =SUM(AK6:AK37) -> 0 | AL38: =SUM(AL6:AL37) -> 0 | AM38: =SUM(AM6:AM37) -> 0 | AN38: =SUM(AN6:AN37) -> 0 | AO38: =SUM(AO6:AO37) -> 0 | AP38: =SUM(AP6:AP37) -> 0 | ... BD38: =SUM(BD6:BD37) -> 16029000 | BF38: =SUM(BF6:BF37) -> 1162000 | BH38: =SUM(BH6:BH37) -> 6000 | BI38: =SUM(BI6:BI37) -> 0 | BJ38: =SUM(BJ6:BJ37) -> 0 | BK38: =SUM(BK6:BK37) -> 0 | BL38: =SUM(BL6:BL37) -> 0 | BM38: =SUM(BM6:BM37) -> 0 | BN38: S/TOTAL | BP38: =SUM(BP35:BP36) -> 0
C40: BANQUE | F40: ESPECES
B41: LIBELLE | C41: SORTIE | D41: ENTREE | E41: SOLDE | F41: ENTREE | G41: SORTIE | H41: SOLDE | BN41: S/TOTAL | BP41: =BP16+BP22+BP28+BP33+BP38 -> 6000
B42: REPORT
B43: TONTINE | C43: =AZ38 -> 15771500 | D43: =SUMIFS(D8:D38,H8:H38,"BANQUE") -> 11263000 | F43: =E38 -> 8171000
AZ81: =SUM(AZ8:AZ80) -> 29454500

Sheet Sheet30
A1: ASSOCIATION | B1: ASELBY
A2: ANNEE | B2: 2023
A3: 1 | B3: 2 | C3: 3 | D3: 4 | E3: 5 | F3: 6 | G3: 7 | H3: 8 | I3: 9 | J3: 10 | K3: 11 | L3: 12 | M3: 13 | N3: 14 | O3: 15 | P3: 16 | Q3: 17 | R3: 18 | S3: 19 | T3: 20 | U3: 21 | V3: 22 | W3: 23 | X3: 24 | Y3: 25 | Z3: 26 | AA3: 27 | AB3: 28 | AC3: 29 | AD3: 30 | AE3: 31 | AF3: 32 | AG3: 33 | AH3: 34 | AI3: 35 | AJ3: 36 | AK3: 37 | AL3: 38 | AM3: 39 | AN3: 40 | AO3: 41 | AP3: 42 | AQ3: 43 | AR3: 44 | AS3: 45 | AT3: 46 | AU3: 47 | AV3: 48 | AW3: 49 | AX3: 50 | AY3: 51 | AZ3: 52 | BA3: 53 | BB3: 54 | BC3: 55 | BD3: 56 | BE3: 57 | BF3: 58 | BG3: 59 | BH3: 60 | BI3: 61 | BJ3: 62 | BK3: 63 | BL3: 64 | BM3: 65 | BN3: 66 | BO3: 67 | BP3: 68
B4: TABLEAU DE BORD SAISIE DES DONNEES
A5: MATRICULE | B5: NOM ET PRENOM | C5: BONUS MALUS | D5: HISTORIQUE BANQUE | E5: HITORIQUE ESPECES | F5: HITORIQUE TONTINE | G5: PENALITE VERSEMENT ESPECES | H5: MODE PAIEMENT TONTINE | I5: COMPLEMENT EPARGNE | J5: NBRE DE LOT | K5: TONTINE 40 000 | L5: NBRE DE LOT | M5: TONTINE 75 000 | N5: NBRE DE LOT | O5: TONTINE 100 000 | P5: REMBOURSEMENT PETIT LOT T40 | Q5: REMBOURSEMENT PETIT LOT T75 | R5: REMBOURSEMENT PETIT LOT T100 | S5: REMBOURSEMENT PRÊT FONDS | T5: MODE PAIEMENT REMBOURSEMENT PRÊT FONDS | U5: MONTANT ENGAGEMENT | V5: SANCTION | W5: INSCRIPTION | X5: EPARGNE ASSURANCE | Y5: RECONSTITUTION FONDS | Z5: PRÊT FONDS | AA5: MODE PAIEMENT PRÊT | AB5: NUM CHEQUE | AC5: ACHAT LOT PRINCIPAL T40 | AD5: ACHAT LOT PRINCIPAL T75 | AE5: ACHAT LOT PRINCIPAL T100 | AF5: MODE PAIEMENT LOT PRINCIPAL | AG5: NUM CHEQUE | AH5: PENALITE VERSEMENT ESPECES | AI5: VENTE PETIT LOT T40 | AJ5: VENTE PETIT LOT T75 | AK5: VENTE PETIT LOT T100 | AL5: INTERET PETIT LOT T40 | AM5: INTERET PETIT LOT T75 | AN5: INTERET PETIT LOT T100 | AO5: NUM CHEQUE | AP5: MODE PAIEMENT PETEIT LOT | AQ5: PENELAITE RETARD TONTINE | AR5: PENELAITE ECHEC TONTINE | AS5: RESTE | AT5: MUTUELLE | AU5: REMBOURSEMENT TRANSPORT | AV5: RETRAIT PARTIEL FONDS | AW5: MONTANT T40 | AX5: MONTANT T75 | AY5: MONTANT T100 | AZ5: MONTANT CHEQUE | BA5: MONTANT ESPECES | BB5: CONTRIBUTION FOYER | BC5: AUTRES SOTIES | BD5: MONTANT CHEQUE EFFECTIF | BE5: NUMERO CHEQUE | BF5: INTERET PRÊT | BG5: NBRE MOIS | BH5: DEPENSE FONDS DE ROULEMENT | BI5: DEPENSE FRAIS EXCEPTIONNEL | BJ5: DEPENSE FONDS MUTUEL | BK5: DEPENSE COLLATION RECEPTION | BL5: PENALITE PRET FONDS | BM5: DEPENSE PENALITE VERSEMENT BANQUE | BN5: LIBELLE | BO5: COMPTE | BP5: MONTANT
A6: AS201648 | B6: =VLOOKUP(A6,[17]LISTADHERENT!A$5:H$39,3,0) -> ASELBY | C6: =HISTOJANV23!C6+HISTOFEV23!C6+HISTOMARS23!C6+HISTOAVRIL23!C6+HISTOMAI23!C6+HISTOJUIN23!C6+HISTOJUIL23!C6+HISTOAOUT23!C6+HISTOSEPT23!C6+HISTOOCT23!C6+HISTONOV23!C6+HISTODEC23!C6 -> 0 | D6: =HISTOJANV23!D6+HISTOFEV23!D6+HISTOMARS23!D6+HISTOAVRIL23!D6+HISTOMAI23!D6+HISTOJUIN23!D6+HISTOJUIL23!D6+HISTOAOUT23!D6+HISTOSEPT23!D6+HISTOOCT23!D6+HISTONOV23!D6+HISTODEC23!D6 -> 2100000 | E6: =HISTOJANV23!E6+HISTOFEV23!E6+HISTOMARS23!E6+HISTOAVRIL23!E6+HISTOMAI23!E6+HISTOJUIN23!E6+HISTOJUIL23!E6+HISTOAOUT23!E6+HISTOSEPT23!E6+HISTOOCT23!E6+HISTONOV23!E6+HISTODEC23!E6 -> 0 | F6: =HISTOJANV23!F6+HISTOFEV23!F6+HISTOMARS23!F6+HISTOAVRIL23!F6+HISTOMAI23!F6+HISTOJUIN23!F6+HISTOJUIL23!F6+HISTOAOUT23!F6+HISTOSEPT23!F6+HISTOOCT23!F6+HISTONOV23!F6+HISTODEC23!F6 -> 0 | G6: =HISTOJANV23!G6+HISTOFEV23!G6+HISTOMARS23!G6+HISTOAVRIL23!G6+HISTOMAI23!G6+HISTOJUIN23!G6+HISTOJUIL23!G6+HISTOAOUT23!G6+HISTOSEPT23!G6+HISTOOCT23!G6+HISTONOV23!G6+HISTODEC23!G6 -> 0 | H6: =IF($D6<>0,"BANQUE",IF($E6<>0,"ESPECES","ECHEC")) -> BANQUE | I6: =HISTOJANV23!I6+HISTOFEV23!I6+HISTOMARS23!I6+HISTOAVRIL23!I6+HISTOMAI23!I6+HISTOJUIN23!I6+HISTOJUIL23!I6+HISTOAOUT23!I6+HISTOSEPT23!I6+HISTOOCT23!I6+HISTONOV23!I6+HISTODEC23!I6 -> 0 | J6: =HISTOJANV23!J6+HISTOFEV23!J6+HISTOMARS23!J6+HISTOAVRIL23!J6+HISTOMAI23!J6+HISTOJUIN23!J6+HISTOJUIL23!J6+HISTOAOUT23!J6+HISTOSEPT23!J6+HISTOOCT23!J6+HISTONOV23!J6+HISTODEC23!J6 -> 0 | K6: =HISTOJANV23!K6+HISTOFEV23!K6+HISTOMARS23!K6+HISTOAVRIL23!K6+HISTOMAI23!K6+HISTOJUIN23!K6+HISTOJUIL23!K6+HISTOAOUT23!K6+HISTOSEPT23!K6+HISTOOCT23!K6+HISTONOV23!K6+HISTODEC23!K6 -> 0 | L6: =HISTOJANV23!L6+HISTOFEV23!L6+HISTOMARS23!L6+HISTOAVRIL23!L6+HISTOMAI23!L6+HISTOJUIN23!L6+HISTOJUIL23!L6+HISTOAOUT23!L6+HISTOSEPT23!L6+HISTOOCT23!L6+HISTONOV23!L6+HISTODEC23!L6 -> 12 | M6: =HISTOJANV23!M6+HISTOFEV23!M6+HISTOMARS23!M6+HISTOAVRIL23!M6+HISTOMAI23!M6+HISTOJUIN23!M6+HISTOJUIL23!M6+HISTOAOUT23!M6+HISTOSEPT23!M6+HISTOOCT23!M6+HISTONOV23!M6+HISTODEC23!M6 -> 900000 | N6: =HISTOJANV23!N6+HISTOFEV23!N6+HISTOMARS23!N6+HISTOAVRIL23!N6+HISTOMAI23!N6+HISTOJUIN23!N6+HISTOJUIL23!N6+HISTOAOUT23!N6+HISTOSEPT23!N6+HISTOOCT23!N6+HISTONOV23!N6+HISTODEC23!N6 -> 12 | O6: =HISTOJANV23!O6+HISTOFEV23!O6+HISTOMARS23!O6+HISTOAVRIL23!O6+HISTOMAI23!O6+HISTOJUIN23!O6+HISTOJUIL23!O6+HISTOAOUT23!O6+HISTOSEPT23!O6+HISTOOCT23!O6+HISTONOV23!O6+HISTODEC23!O6 -> 1200000 | P6: =HISTOJANV23!P6+HISTOFEV23!P6+HISTOMARS23!P6+HISTOAVRIL23!P6+HISTOMAI23!P6+HISTOJUIN23!P6+HISTOJUIL23!P6+HISTOAOUT23!P6+HISTOSEPT23!P6+HISTOOCT23!P6+HISTONOV23!P6+HISTODEC23!P6 -> 0 | ... T6: =HISTOJANV23!T6+HISTOFEV23!T6+HISTOMARS23!T6+HISTOAVRIL23!T6+HISTOMAI23!T6+HISTOJUIN23!T6+HISTOJUIL23!T6+HISTOAOUT23!T6+HISTOSEPT23!T6+HISTOOCT23!T6+HISTONOV23!T6+HISTODEC23!T6 -> 0 | U6: =G6+S6++R6+P6+O6+M6+I6+K6+Q6+V6+W6 -> 2100000 | V6: =HISTOJANV23!V6+HISTOFEV23!V6+HISTOMARS23!V6+HISTOAVRIL23!V6+HISTOMAI23!V6+HISTOJUIN23!V6+HISTOJUIL23!V6+HISTOAOUT23!V6+HISTOSEPT23!V6+HISTOOCT23!V6+HISTONOV23!V6+HISTODEC23!V6 -> 0 | W6: =HISTOJANV23!W6+HISTOFEV23!W6+HISTOMARS23!W6+HISTOAVRIL23!W6+HISTOMAI23!W6+HISTOJUIN23!W6+HISTOJUIL23!W6+HISTOAOUT23!W6+HISTOSEPT23!W6+HISTOOCT23!W6+HISTONOV23!W6+HISTODEC23!W6 -> 0 | X6: =HISTOJANV23!X6+HISTOFEV23!X6+HISTOMARS23!X6+HISTOAVRIL23!X6+HISTOMAI23!X6+HISTOJUIN23!X6+HISTOJUIL23!X6+HISTOAOUT23!X6+HISTOSEPT23!X6+HISTOOCT23!X6+HISTONOV23!X6+HISTODEC23!X6 -> 0 | Y6: =HISTOJANV23!Y6+HISTOFEV23!Y6+HISTOMARS23!Y6+HISTOAVRIL23!Y6+HISTOMAI23!Y6+HISTOJUIN23!Y6+HISTOJUIL23!Y6+HISTOAOUT23!Y6+HISTOSEPT23!Y6+HISTOOCT23!Y6+HISTONOV23!Y6+HISTODEC23!Y6 -> 0 | Z6: =HISTOJANV23!Z6+HISTOFEV23!Z6+HISTOMARS23!Z6+HISTOAVRIL23!Z6+HISTOMAI23!Z6+HISTOJUIN23!Z6+HISTOJUIL23!Z6+HISTOAOUT23!Z6+HISTOSEPT23!Z6+HISTOOCT23!Z6+HISTONOV23!Z6+HISTODEC23!Z6 -> 0 | AA6: =HISTOJANV23!AA6+HISTOFEV23!AA6+HISTOMARS23!AA6+HISTOAVRIL23!AA6+HISTOMAI23!AA6+HISTOJUIN23!AA6+HISTOJUIL23!AA6+HISTOAOUT23!AA6+HISTOSEPT23!AA6+HISTOOCT23!AA6+HISTONOV23!AA6+HISTODEC23!AA6 -> 0 | AB6: =HISTOJANV23!AB6+HISTOFEV23!AB6+HISTOMARS23!AB6+HISTOAVRIL23!AB6+HISTOMAI23!AB6+HISTOJUIN23!AB6+HISTOJUIL23!AB6+HISTOAOUT23!AB6+HISTOSEPT23!AB6+HISTOOCT23!AB6+HISTONOV23!AB6+HISTODEC23!AB6 -> 0 | AC6: =HISTOJANV23!AC6+HISTOFEV23!AC6+HISTOMARS23!AC6+HISTOAVRIL23!AC6+HISTOMAI23!AC6+HISTOJUIN23!AC6+HISTOJUIL23!AC6+HISTOAOUT23!AC6+HISTOSEPT23!AC6+HISTOOCT23!AC6+HISTONOV23!AC6+HISTODEC23!AC6 -> 0 | ... BM6: =HISTOJANV23!BM6+HISTOFEV23!BM6+HISTOMARS23!BM6+HISTOAVRIL23!BM6+HISTOMAI23!BM6+HISTOJUIN23!BM6+HISTOJUIL23!BM6+HISTOAOUT23!BM6+HISTOSEPT23!BM6+HISTOOCT23!BM6+HISTONOV23!BM6+HISTODEC23!BM6 -> 200000 | BN6: ACHAT FOURNITURE | BO6: FONDS DE ROULEMENT | BP6: =HISTOJANV23!BP6+HISTOFEV23!BP6+HISTOMARS23!BP6+HISTOAVRIL23!BP6+HISTOMAI23!BP6+HISTOJUIN23!BP6+HISTOJUIL23!BP6+HISTOAOUT23!BP6+HISTOSEPT23!BP6+HISTOOCT23!BP6+HISTONOV23!BP6+HISTODEC23!BP6 -> 0
A7: AS201601 | B7: =VLOOKUP(A7,[17]LISTADHERENT!A$5:H$39,3,0) -> BAKOP ACHILLE | C7: =HISTOJANV23!C7+HISTOFEV23!C7+HISTOMARS23!C7+HISTOAVRIL23!C7+HISTOMAI23!C7+HISTOJUIN23!C7+HISTOJUIL23!C7+HISTOAOUT23!C7+HISTOSEPT23!C7+HISTOOCT23!C7+HISTONOV23!C7+HISTODEC23!C7 -> 0 | D7: =HISTOJANV23!D7+HISTOFEV23!D7+HISTOMARS23!D7+HISTOAVRIL23!D7+HISTOMAI23!D7+HISTOJUIN23!D7+HISTOJUIL23!D7+HISTOAOUT23!D7+HISTOSEPT23!D7+HISTOOCT23!D7+HISTONOV23!D7+HISTODEC23!D7 -> 388000 | E7: =HISTOJANV23!E7+HISTOFEV23!E7+HISTOMARS23!E7+HISTOAVRIL23!E7+HISTOMAI23!E7+HISTOJUIN23!E7+HISTOJUIL23!E7+HISTOAOUT23!E7+HISTOSEPT23!E7+HISTOOCT23!E7+HISTONOV23!E7+HISTODEC23!E7 -> 846500 | F7: =HISTOJANV23!F7+HISTOFEV23!F7+HISTOMARS23!F7+HISTOAVRIL23!F7+HISTOMAI23!F7+HISTOJUIN23!F7+HISTOJUIL23!F7+HISTOAOUT23!F7+HISTOSEPT23!F7+HISTOOCT23!F7+HISTONOV23!F7+HISTODEC23!F7 -> 140000 | G7: =HISTOJANV23!G7+HISTOFEV23!G7+HISTOMARS23!G7+HISTOAVRIL23!G7+HISTOMAI23!G7+HISTOJUIN23!G7+HISTOJUIL23!G7+HISTOAOUT23!G7+HISTOSEPT23!G7+HISTOOCT23!G7+HISTONOV23!G7+HISTODEC23!G7 -> 3000 | H7: =IF($D7<>0,"BANQUE",IF($E7<>0,"ESPECES","ECHEC")) -> BANQUE | I7: =HISTOJANV23!I7+HISTOFEV23!I7+HISTOMARS23!I7+HISTOAVRIL23!I7+HISTOMAI23!I7+HISTOJUIN23!I7+HISTOJUIL23!I7+HISTOAOUT23!I7+HISTOSEPT23!I7+HISTOOCT23!I7+HISTONOV23!I7+HISTODEC23!I7 -> 64000 | J7: =HISTOJANV23!J7+HISTOFEV23!J7+HISTOMARS23!J7+HISTOAVRIL23!J7+HISTOMAI23!J7+HISTOJUIN23!J7+HISTOJUIL23!J7+HISTOAOUT23!J7+HISTOSEPT23!J7+HISTOOCT23!J7+HISTONOV23!J7+HISTODEC23!J7 -> 12 | K7: =HISTOJANV23!K7+HISTOFEV23!K7+HISTOMARS23!K7+HISTOAVRIL23!K7+HISTOMAI23!K7+HISTOJUIN23!K7+HISTOJUIL23!K7+HISTOAOUT23!K7+HISTOSEPT23!K7+HISTOOCT23!K7+HISTONOV23!K7+HISTODEC23!K7 -> 480000 | L7: =HISTOJANV23!L7+HISTOFEV23!L7+HISTOMARS23!L7+HISTOAVRIL23!L7+HISTOMAI23!L7+HISTOJUIN23!L7+HISTOJUIL23!L7+HISTOAOUT23!L7+HISTOSEPT23!L7+HISTOOCT23!L7+HISTONOV23!L7+HISTODEC23!L7 -> 0 | M7: =HISTOJANV23!M7+HISTOFEV23!M7+HISTOMARS23!M7+HISTOAVRIL23!M7+HISTOMAI23!M7+HISTOJUIN23!M7+HISTOJUIL23!M7+HISTOAOUT23!M7+HISTOSEPT23!M7+HISTOOCT23!M7+HISTONOV23!M7+HISTODEC23!M7 -> 0 | N7: =HISTOJANV23!N7+HISTOFEV23!N7+HISTOMARS23!N7+HISTOAVRIL23!N7+HISTOMAI23!N7+HISTOJUIN23!N7+HISTOJUIL23!N7+HISTOAOUT23!N7+HISTOSEPT23!N7+HISTOOCT23!N7+HISTONOV23!N7+HISTODEC23!N7 -> 0 | O7: =HISTOJANV23!O7+HISTOFEV23!O7+HISTOMARS23!O7+HISTOAVRIL23!O7+HISTOMAI23!O7+HISTOJUIN23!O7+HISTOJUIL23!O7+HISTOAOUT23!O7+HISTOSEPT23!O7+HISTOOCT23!O7+HISTONOV23!O7+HISTODEC23!O7 -> 0 | P7: =HISTOJANV23!P7+HISTOFEV23!P7+HISTOMARS23!P7+HISTOAVRIL23!P7+HISTOMAI23!P7+HISTOJUIN23!P7+HISTOJUIL23!P7+HISTOAOUT23!P7+HISTOSEPT23!P7+HISTOOCT23!P7+HISTONOV23!P7+HISTODEC23!P7 -> 87500 | ... T7: =HISTOJANV23!T7+HISTOFEV23!T7+HISTOMARS23!T7+HISTOAVRIL23!T7+HISTOMAI23!T7+HISTOJUIN23!T7+HISTOJUIL23!T7+HISTOAOUT23!T7+HISTOSEPT23!T7+HISTOOCT23!T7+HISTONOV23!T7+HISTODEC23!T7 -> #VALUE! | U7: =G7+S7++R7+P7+O7+M7+I7+K7+Q7+V7+W7 -> 1234500 | V7: =HISTOJANV23!V7+HISTOFEV23!V7+HISTOMARS23!V7+HISTOAVRIL23!V7+HISTOMAI23!V7+HISTOJUIN23!V7+HISTOJUIL23!V7+HISTOAOUT23!V7+HISTOSEPT23!V7+HISTOOCT23!V7+HISTONOV23!V7+HISTODEC23!V7 -> 0 | W7: =HISTOJANV23!W7+HISTOFEV23!W7+HISTOMARS23!W7+HISTOAVRIL23!W7+HISTOMAI23!W7+HISTOJUIN23!W7+HISTOJUIL23!W7+HISTOAOUT23!W7+HISTOSEPT23!W7+HISTOOCT23!W7+HISTONOV23!W7+HISTODEC23!W7 -> 0 | X7: =HISTOJANV23!X7+HISTOFEV23!X7+HISTOMARS23!X7+HISTOAVRIL23!X7+HISTOMAI23!X7+HISTOJUIN23!X7+HISTOJUIL23!X7+HISTOAOUT23!X7+HISTOSEPT23!X7+HISTOOCT23!X7+HISTONOV23!X7+HISTODEC23!X7 -> 0 | Y7: =HISTOJANV23!Y7+HISTOFEV23!Y7+HISTOMARS23!Y7+HISTOAVRIL23!Y7+HISTOMAI23!Y7+HISTOJUIN23!Y7+HISTOJUIL23!Y7+HISTOAOUT23!Y7+HISTOSEPT23!Y7+HISTOOCT23!Y7+HISTONOV23!Y7+HISTODEC23!Y7 -> 0 | Z7: =HISTOJANV23!Z7+HISTOFEV23!Z7+HISTOMARS23!Z7+HISTOAVRIL23!Z7+HISTOMAI23!Z7+HISTOJUIN23!Z7+HISTOJUIL23!Z7+HISTOAOUT23!Z7+HISTOSEPT23!Z7+HISTOOCT23!Z7+HISTONOV23!Z7+HISTODEC23!Z7 -> 600000 | AA7: =HISTOJANV23!AA7+HISTOFEV23!AA7+HISTOMARS23!AA7+HISTOAVRIL23!AA7+HISTOMAI23!AA7+HISTOJUIN23!AA7+HISTOJUIL23!AA7+HISTOAOUT23!AA7+HISTOSEPT23!AA7+HISTOOCT23!AA7+HISTONOV23!AA7+HISTODEC23!AA7 -> #VALUE! | AB7: =HISTOJANV23!AB7+HISTOFEV23!AB7+HISTOMARS23!AB7+HISTOAVRIL23!AB7+HISTOMAI23!AB7+HISTOJUIN23!AB7+HISTOJUIL23!AB7+HISTOAOUT23!AB7+HISTOSEPT23!AB7+HISTOOCT23!AB7+HISTONOV23!AB7+HISTODEC23!AB7 -> 0 | AC7: =HISTOJANV23!AC7+HISTOFEV23!AC7+HISTOMARS23!AC7+HISTOAVRIL23!AC7+HISTOMAI23!AC7+HISTOJUIN23!AC7+HISTOJUIL23!AC7+HISTOAOUT23!AC7+HISTOSEPT23!AC7+HISTOOCT23!AC7+HISTONOV23!AC7+HISTODEC23!AC7 -> 3000 | ... BM7: =HISTOJANV23!BM7+HISTOFEV23!BM7+HISTOMARS23!BM7+HISTOAVRIL23!BM7+HISTOMAI23!BM7+HISTOJUIN23!BM7+HISTOJUIL23!BM7+HISTOAOUT23!BM7+HISTOSEPT23!BM7+HISTOOCT23!BM7+HISTONOV23!BM7+HISTODEC23!BM7 -> 0 | BN7: COMMUNICATION | BO7: FONDS DE ROULEMENT | BP7: =HISTOJANV23!BP7+HISTOFEV23!BP7+HISTOMARS23!BP7+HISTOAVRIL23!BP7+HISTOMAI23!BP7+HISTOJUIN23!BP7+HISTOJUIL23!BP7+HISTOAOUT23!BP7+HISTOSEPT23!BP7+HISTOOCT23!BP7+HISTONOV23!BP7+HISTODEC23!BP7 -> 0
A8: AS201602 | B8: =VLOOKUP(A8,[17]LISTADHERENT!A$5:H$39,3,0) -> BOUTCHOUANG WILLIAM | C8: =HISTOJANV23!C8+HISTOFEV23!C8+HISTOMARS23!C8+HISTOAVRIL23!C8+HISTOMAI23!C8+HISTOJUIN23!C8+HISTOJUIL23!C8+HISTOAOUT23!C8+HISTOSEPT23!C8+HISTOOCT23!C8+HISTONOV23!C8+HISTODEC23!C8 -> 0 | D8: =HISTOJANV23!D8+HISTOFEV23!D8+HISTOMARS23!D8+HISTOAVRIL23!D8+HISTOMAI23!D8+HISTOJUIN23!D8+HISTOJUIL23!D8+HISTOAOUT23!D8+HISTOSEPT23!D8+HISTOOCT23!D8+HISTONOV23!D8+HISTODEC23!D8 -> 2255000 | E8: =HISTOJANV23!E8+HISTOFEV23!E8+HISTOMARS23!E8+HISTOAVRIL23!E8+HISTOMAI23!E8+HISTOJUIN23!E8+HISTOJUIL23!E8+HISTOAOUT23!E8+HISTOSEPT23!E8+HISTOOCT23!E8+HISTONOV23!E8+HISTODEC23!E8 -> 125000 | F8: =HISTOJANV23!F8+HISTOFEV23!F8+HISTOMARS23!F8+HISTOAVRIL23!F8+HISTOMAI23!F8+HISTOJUIN23!F8+HISTOJUIL23!F8+HISTOAOUT23!F8+HISTOSEPT23!F8+HISTOOCT23!F8+HISTONOV23!F8+HISTODEC23!F8 -> 70000 | G8: =HISTOJANV23!G8+HISTOFEV23!G8+HISTOMARS23!G8+HISTOAVRIL23!G8+HISTOMAI23!G8+HISTOJUIN23!G8+HISTOJUIL23!G8+HISTOAOUT23!G8+HISTOSEPT23!G8+HISTOOCT23!G8+HISTONOV23!G8+HISTODEC23!G8 -> 0 | H8: =IF($D8<>0,"BANQUE",IF($E8<>0,"ESPECES","ECHEC")) -> BANQUE | I8: =HISTOJANV23!I8+HISTOFEV23!I8+HISTOMARS23!I8+HISTOAVRIL23!I8+HISTOMAI23!I8+HISTOJUIN23!I8+HISTOJUIL23!I8+HISTOAOUT23!I8+HISTOSEPT23!I8+HISTOOCT23!I8+HISTONOV23!I8+HISTODEC23!I8 -> 0 | J8: =HISTOJANV23!J8+HISTOFEV23!J8+HISTOMARS23!J8+HISTOAVRIL23!J8+HISTOMAI23!J8+HISTOJUIN23!J8+HISTOJUIL23!J8+HISTOAOUT23!J8+HISTOSEPT23!J8+HISTOOCT23!J8+HISTONOV23!J8+HISTODEC23!J8 -> 12 | K8: =HISTOJANV23!K8+HISTOFEV23!K8+HISTOMARS23!K8+HISTOAVRIL23!K8+HISTOMAI23!K8+HISTOJUIN23!K8+HISTOJUIL23!K8+HISTOAOUT23!K8+HISTOSEPT23!K8+HISTOOCT23!K8+HISTONOV23!K8+HISTODEC23!K8 -> 480000 | L8: =HISTOJANV23!L8+HISTOFEV23!L8+HISTOMARS23!L8+HISTOAVRIL23!L8+HISTOMAI23!L8+HISTOJUIN23!L8+HISTOJUIL23!L8+HISTOAOUT23!L8+HISTOSEPT23!L8+HISTOOCT23!L8+HISTONOV23!L8+HISTODEC23!L8 -> 12 | M8: =HISTOJANV23!M8+HISTOFEV23!M8+HISTOMARS23!M8+HISTOAVRIL23!M8+HISTOMAI23!M8+HISTOJUIN23!M8+HISTOJUIL23!M8+HISTOAOUT23!M8+HISTOSEPT23!M8+HISTOOCT23!M8+HISTONOV23!M8+HISTODEC23!M8 -> 900000 | N8: =HISTOJANV23!N8+HISTOFEV23!N8+HISTOMARS23!N8+HISTOAVRIL23!N8+HISTOMAI23!N8+HISTOJUIN23!N8+HISTOJUIL23!N8+HISTOAOUT23!N8+HISTOSEPT23!N8+HISTOOCT23!N8+HISTONOV23!N8+HISTODEC23!N8 -> 0 | O8: =HISTOJANV23!O8+HISTOFEV23!O8+HISTOMARS23!O8+HISTOAVRIL23!O8+HISTOMAI23!O8+HISTOJUIN23!O8+HISTOJUIL23!O8+HISTOAOUT23!O8+HISTOSEPT23!O8+HISTOOCT23!O8+HISTONOV23!O8+HISTODEC23!O8 -> 0 | P8: =HISTOJANV23!P8+HISTOFEV23!P8+HISTOMARS23!P8+HISTOAVRIL23!P8+HISTOMAI23!P8+HISTOJUIN23!P8+HISTOJUIL23!P8+HISTOAOUT23!P8+HISTOSEPT23!P8+HISTOOCT23!P8+HISTONOV23!P8+HISTODEC23!P8 -> 0 | ... T8: =HISTOJANV23!T8+HISTOFEV23!T8+HISTOMARS23!T8+HISTOAVRIL23!T8+HISTOMAI23!T8+HISTOJUIN23!T8+HISTOJUIL23!T8+HISTOAOUT23!T8+HISTOSEPT23!T8+HISTOOCT23!T8+HISTONOV23!T8+HISTODEC23!T8 -> #VALUE! | U8: =G8+S8++R8+P8+O8+M8+I8+K8+Q8+V8+W8 -> 2399000 | V8: =HISTOJANV23!V8+HISTOFEV23!V8+HISTOMARS23!V8+HISTOAVRIL23!V8+HISTOMAI23!V8+HISTOJUIN23!V8+HISTOJUIL23!V8+HISTOAOUT23!V8+HISTOSEPT23!V8+HISTOOCT23!V8+HISTONOV23!V8+HISTODEC23!V8 -> 19000 | W8: =HISTOJANV23!W8+HISTOFEV23!W8+HISTOMARS23!W8+HISTOAVRIL23!W8+HISTOMAI23!W8+HISTOJUIN23!W8+HISTOJUIL23!W8+HISTOAOUT23!W8+HISTOSEPT23!W8+HISTOOCT23!W8+HISTONOV23!W8+HISTODEC23!W8 -> 0 | X8: =HISTOJANV23!X8+HISTOFEV23!X8+HISTOMARS23!X8+HISTOAVRIL23!X8+HISTOMAI23!X8+HISTOJUIN23!X8+HISTOJUIL23!X8+HISTOAOUT23!X8+HISTOSEPT23!X8+HISTOOCT23!X8+HISTONOV23!X8+HISTODEC23!X8 -> 0 | Y8: =HISTOJANV23!Y8+HISTOFEV23!Y8+HISTOMARS23!Y8+HISTOAVRIL23!Y8+HISTOMAI23!Y8+HISTOJUIN23!Y8+HISTOJUIL23!Y8+HISTOAOUT23!Y8+HISTOSEPT23!Y8+HISTOOCT23!Y8+HISTONOV23!Y8+HISTODEC23!Y8 -> 0 | Z8: =HISTOJANV23!Z8+HISTOFEV23!Z8+HISTOMARS23!Z8+HISTOAVRIL23!Z8+HISTOMAI23!Z8+HISTOJUIN23!Z8+HISTOJUIL23!Z8+HISTOAOUT23!Z8+HISTOSEPT23!Z8+HISTOOCT23!Z8+HISTONOV23!Z8+HISTODEC23!Z8 -> 1000000 | AA8: =HISTOJANV23!AA8+HISTOFEV23!AA8+HISTOMARS23!AA8+HISTOAVRIL23!AA8+HISTOMAI23!AA8+HISTOJUIN23!AA8+HISTOJUIL23!AA8+HISTOAOUT23!AA8+HISTOSEPT23!AA8+HISTOOCT23!AA8+HISTONOV23!AA8+HISTODEC23!AA8 -> #VALUE! | AB8: =HISTOJANV23!AB8+HISTOFEV23!AB8+HISTOMARS23!AB8+HISTOAVRIL23!AB8+HISTOMAI23!AB8+HISTOJUIN23!AB8+HISTOJUIL23!AB8+HISTOAOUT23!AB8+HISTOSEPT23!AB8+HISTOOCT23!AB8+HISTONOV23!AB8+HISTODEC23!AB8 -> 0 | AC8: =HISTOJANV23!AC8+HISTOFEV23!AC8+HISTOMARS23!AC8+HISTOAVRIL23!AC8+HISTOMAI23!AC8+HISTOJUIN23!AC8+HISTOJUIL23!AC8+HISTOAOUT23!AC8+HISTOSEPT23!AC8+HISTOOCT23!AC8+HISTONOV23!AC8+HISTODEC23!AC8 -> 2500 | ... BM8: =HISTOJANV23!BM8+HISTOFEV23!BM8+HISTOMARS23!BM8+HISTOAVRIL23!BM8+HISTOMAI23!BM8+HISTOJUIN23!BM8+HISTOJUIL23!BM8+HISTOAOUT23!BM8+HISTOSEPT23!BM8+HISTOOCT23!BM8+HISTONOV23!BM8+HISTODEC23!BM8 -> 0 | BN8: COMMISSION | BO8: FONDS DE ROULEMENT | BP8: =HISTOJANV23!BP8+HISTOFEV23!BP8+HISTOMARS23!BP8+HISTOAVRIL23!BP8+HISTOMAI23!BP8+HISTOJUIN23!BP8+HISTOJUIL23!BP8+HISTOAOUT23!BP8+HISTOSEPT23!BP8+HISTOOCT23!BP8+HISTONOV23!BP8+HISTODEC23!BP8 -> 83000
A9: AS201604 | B9: =VLOOKUP(A9,[17]LISTADHERENT!A$5:H$39,3,0) -> DJOMO JEAN PAUL | C9: =HISTOJANV23!C9+HISTOFEV23!C9+HISTOMARS23!C9+HISTOAVRIL23!C9+HISTOMAI23!C9+HISTOJUIN23!C9+HISTOJUIL23!C9+HISTOAOUT23!C9+HISTOSEPT23!C9+HISTOOCT23!C9+HISTONOV23!C9+HISTODEC23!C9 -> 221000 | D9: =HISTOJANV23!D9+HISTOFEV23!D9+HISTOMARS23!D9+HISTOAVRIL23!D9+HISTOMAI23!D9+HISTOJUIN23!D9+HISTOJUIL23!D9+HISTOAOUT23!D9+HISTOSEPT23!D9+HISTOOCT23!D9+HISTONOV23!D9+HISTODEC23!D9 -> 2793000 | E9: =HISTOJANV23!E9+HISTOFEV23!E9+HISTOMARS23!E9+HISTOAVRIL23!E9+HISTOMAI23!E9+HISTOJUIN23!E9+HISTOJUIL23!E9+HISTOAOUT23!E9+HISTOSEPT23!E9+HISTOOCT23!E9+HISTONOV23!E9+HISTODEC23!E9 -> 1392500 | F9: =HISTOJANV23!F9+HISTOFEV23!F9+HISTOMARS23!F9+HISTOAVRIL23!F9+HISTOMAI23!F9+HISTOJUIN23!F9+HISTOJUIL23!F9+HISTOAOUT23!F9+HISTOSEPT23!F9+HISTOOCT23!F9+HISTONOV23!F9+HISTODEC23!F9 -> 830000 | G9: =HISTOJANV23!G9+HISTOFEV23!G9+HISTOMARS23!G9+HISTOAVRIL23!G9+HISTOMAI23!G9+HISTOJUIN23!G9+HISTOJUIL23!G9+HISTOAOUT23!G9+HISTOSEPT23!G9+HISTOOCT23!G9+HISTONOV23!G9+HISTODEC23!G9 -> 3000 | H9: =IF($D9<>0,"BANQUE",IF($E9<>0,"ESPECES","ECHEC")) -> BANQUE | I9: =HISTOJANV23!I9+HISTOFEV23!I9+HISTOMARS23!I9+HISTOAVRIL23!I9+HISTOMAI23!I9+HISTOJUIN23!I9+HISTOJUIL23!I9+HISTOAOUT23!I9+HISTOSEPT23!I9+HISTOOCT23!I9+HISTONOV23!I9+HISTODEC23!I9 -> 61000 | J9: =HISTOJANV23!J9+HISTOFEV23!J9+HISTOMARS23!J9+HISTOAVRIL23!J9+HISTOMAI23!J9+HISTOJUIN23!J9+HISTOJUIL23!J9+HISTOAOUT23!J9+HISTOSEPT23!J9+HISTOOCT23!J9+HISTONOV23!J9+HISTODEC23!J9 -> 12 | K9: =HISTOJANV23!K9+HISTOFEV23!K9+HISTOMARS23!K9+HISTOAVRIL23!K9+HISTOMAI23!K9+HISTOJUIN23!K9+HISTOJUIL23!K9+HISTOAOUT23!K9+HISTOSEPT23!K9+HISTOOCT23!K9+HISTONOV23!K9+HISTODEC23!K9 -> 480000 | L9: =HISTOJANV23!L9+HISTOFEV23!L9+HISTOMARS23!L9+HISTOAVRIL23!L9+HISTOMAI23!L9+HISTOJUIN23!L9+HISTOJUIL23!L9+HISTOAOUT23!L9+HISTOSEPT23!L9+HISTOOCT23!L9+HISTONOV23!L9+HISTODEC23!L9 -> 0 | M9: =HISTOJANV23!M9+HISTOFEV23!M9+HISTOMARS23!M9+HISTOAVRIL23!M9+HISTOMAI23!M9+HISTOJUIN23!M9+HISTOJUIL23!M9+HISTOAOUT23!M9+HISTOSEPT23!M9+HISTOOCT23!M9+HISTONOV23!M9+HISTODEC23!M9 -> 0 | N9: =HISTOJANV23!N9+HISTOFEV23!N9+HISTOMARS23!N9+HISTOAVRIL23!N9+HISTOMAI23!N9+HISTOJUIN23!N9+HISTOJUIL23!N9+HISTOAOUT23!N9+HISTOSEPT23!N9+HISTOOCT23!N9+HISTONOV23!N9+HISTODEC23!N9 -> 12 | O9: =HISTOJANV23!O9+HISTOFEV23!O9+HISTOMARS23!O9+HISTOAVRIL23!O9+HISTOMAI23!O9+HISTOJUIN23!O9+HISTOJUIL23!O9+HISTOAOUT23!O9+HISTOSEPT23!O9+HISTOOCT23!O9+HISTONOV23!O9+HISTODEC23!O9 -> 1200000 | P9: =HISTOJANV23!P9+HISTOFEV23!P9+HISTOMARS23!P9+HISTOAVRIL23!P9+HISTOMAI23!P9+HISTOJUIN23!P9+HISTOJUIL23!P9+HISTOAOUT23!P9+HISTOSEPT23!P9+HISTOOCT23!P9+HISTONOV23!P9+HISTODEC23!P9 -> 23000 | ... T9: =HISTOJANV23!T9+HISTOFEV23!T9+HISTOMARS23!T9+HISTOAVRIL23!T9+HISTOMAI23!T9+HISTOJUIN23!T9+HISTOJUIL23!T9+HISTOAOUT23!T9+HISTOSEPT23!T9+HISTOOCT23!T9+HISTONOV23!T9+HISTODEC23!T9 -> #VALUE! | U9: =G9+S9++R9+P9+O9+M9+I9+K9+Q9+V9+W9 -> 4663500 | V9: =HISTOJANV23!V9+HISTOFEV23!V9+HISTOMARS23!V9+HISTOAVRIL23!V9+HISTOMAI23!V9+HISTOJUIN23!V9+HISTOJUIL23!V9+HISTOAOUT23!V9+HISTOSEPT23!V9+HISTOOCT23!V9+HISTONOV23!V9+HISTODEC23!V9 -> 9000 | W9: =HISTOJANV23!W9+HISTOFEV23!W9+HISTOMARS23!W9+HISTOAVRIL23!W9+HISTOMAI23!W9+HISTOJUIN23!W9+HISTOJUIL23!W9+HISTOAOUT23!W9+HISTOSEPT23!W9+HISTOOCT23!W9+HISTONOV23!W9+HISTODEC23!W9 -> 0 | X9: =HISTOJANV23!X9+HISTOFEV23!X9+HISTOMARS23!X9+HISTOAVRIL23!X9+HISTOMAI23!X9+HISTOJUIN23!X9+HISTOJUIL23!X9+HISTOAOUT23!X9+HISTOSEPT23!X9+HISTOOCT23!X9+HISTONOV23!X9+HISTODEC23!X9 -> 0 | Y9: =HISTOJANV23!Y9+HISTOFEV23!Y9+HISTOMARS23!Y9+HISTOAVRIL23!Y9+HISTOMAI23!Y9+HISTOJUIN23!Y9+HISTOJUIL23!Y9+HISTOAOUT23!Y9+HISTOSEPT23!Y9+HISTOOCT23!Y9+HISTONOV23!Y9+HISTODEC23!Y9 -> 0 | Z9: =HISTOJANV23!Z9+HISTOFEV23!Z9+HISTOMARS23!Z9+HISTOAVRIL23!Z9+HISTOMAI23!Z9+HISTOJUIN23!Z9+HISTOJUIL23!Z9+HISTOAOUT23!Z9+HISTOSEPT23!Z9+HISTOOCT23!Z9+HISTONOV23!Z9+HISTODEC23!Z9 -> 1000000 | AA9: =HISTOJANV23!AA9+HISTOFEV23!AA9+HISTOMARS23!AA9+HISTOAVRIL23!AA9+HISTOMAI23!AA9+HISTOJUIN23!AA9+HISTOJUIL23!AA9+HISTOAOUT23!AA9+HISTOSEPT23!AA9+HISTOOCT23!AA9+HISTONOV23!AA9+HISTODEC23!AA9 -> #VALUE! | AB9: =HISTOJANV23!AB9+HISTOFEV23!AB9+HISTOMARS23!AB9+HISTOAVRIL23!AB9+HISTOMAI23!AB9+HISTOJUIN23!AB9+HISTOJUIL23!AB9+HISTOAOUT23!AB9+HISTOSEPT23!AB9+HISTOOCT23!AB9+HISTONOV23!AB9+HISTODEC23!AB9 -> 0 | AC9: =HISTOJANV23!AC9+HISTOFEV23!AC9+HISTOMARS23!AC9+HISTOAVRIL23!AC9+HISTOMAI23!AC9+HISTOJUIN23!AC9+HISTOJUIL23!AC9+HISTOAOUT23!AC9+HISTOSEPT23!AC9+HISTOOCT23!AC9+HISTONOV23!AC9+HISTODEC23!AC9 -> 45000 | ... BM9: =HISTOJANV23!BM9+HISTOFEV23!BM9+HISTOMARS23!BM9+HISTOAVRIL23!BM9+HISTOMAI23!BM9+HISTOJUIN23!BM9+HISTOJUIL23!BM9+HISTOAOUT23!BM9+HISTOSEPT23!BM9+HISTOOCT23!BM9+HISTONOV23!BM9+HISTODEC23!BM9 -> 0 | BN9: AIDE UEEB ET CONT FEMME | BO9: FONDS DE ROULEMENT | BP9: =HISTOJANV23!BP9+HISTOFEV23!BP9+HISTOMARS23!BP9+HISTOAVRIL23!BP9+HISTOMAI23!BP9+HISTOJUIN23!BP9+HISTOJUIL23!BP9+HISTOAOUT23!BP9+HISTOSEPT23!BP9+HISTOOCT23!BP9+HISTONOV23!BP9+HISTODEC23!BP9 -> 0
A10: AS201654 | B10: =VLOOKUP(A10,[17]LISTADHERENT!A$5:H$39,3,0) -> DJOMOU TCHAPDA | C10: =HISTOJANV23!C10+HISTOFEV23!C10+HISTOMARS23!C10+HISTOAVRIL23!C10+HISTOMAI23!C10+HISTOJUIN23!C10+HISTOJUIL23!C10+HISTOAOUT23!C10+HISTOSEPT23!C10+HISTOOCT23!C10+HISTONOV23!C10+HISTODEC23!C10 -> -70000 | D10: =HISTOJANV23!D10+HISTOFEV23!D10+HISTOMARS23!D10+HISTOAVRIL23!D10+HISTOMAI23!D10+HISTOJUIN23!D10+HISTOJUIL23!D10+HISTOAOUT23!D10+HISTOSEPT23!D10+HISTOOCT23!D10+HISTONOV23!D10+HISTODEC23!D10 -> 345000 | E10: =HISTOJANV23!E10+HISTOFEV23!E10+HISTOMARS23!E10+HISTOAVRIL23!E10+HISTOMAI23!E10+HISTOJUIN23!E10+HISTOJUIL23!E10+HISTOAOUT23!E10+HISTOSEPT23!E10+HISTOOCT23!E10+HISTONOV23!E10+HISTODEC23!E10 -> 317000 | F10: =HISTOJANV23!F10+HISTOFEV23!F10+HISTOMARS23!F10+HISTOAVRIL23!F10+HISTOMAI23!F10+HISTOJUIN23!F10+HISTOJUIL23!F10+HISTOAOUT23!F10+HISTOSEPT23!F10+HISTOOCT23!F10+HISTONOV23!F10+HISTODEC23!F10 -> 0 | G10: =HISTOJANV23!G10+HISTOFEV23!G10+HISTOMARS23!G10+HISTOAVRIL23!G10+HISTOMAI23!G10+HISTOJUIN23!G10+HISTOJUIL23!G10+HISTOAOUT23!G10+HISTOSEPT23!G10+HISTOOCT23!G10+HISTONOV23!G10+HISTODEC23!G10 -> 15000 | H10: =IF($D10<>0,"BANQUE",IF($E10<>0,"ESPECES","ECHEC")) -> BANQUE | I10: =HISTOJANV23!I10+HISTOFEV23!I10+HISTOMARS23!I10+HISTOAVRIL23!I10+HISTOMAI23!I10+HISTOJUIN23!I10+HISTOJUIL23!I10+HISTOAOUT23!I10+HISTOSEPT23!I10+HISTOOCT23!I10+HISTONOV23!I10+HISTODEC23!I10 -> 1000 | J10: =HISTOJANV23!J10+HISTOFEV23!J10+HISTOMARS23!J10+HISTOAVRIL23!J10+HISTOMAI23!J10+HISTOJUIN23!J10+HISTOJUIL23!J10+HISTOAOUT23!J10+HISTOSEPT23!J10+HISTOOCT23!J10+HISTONOV23!J10+HISTODEC23!J10 -> 12 | K10: =HISTOJANV23!K10+HISTOFEV23!K10+HISTOMARS23!K10+HISTOAVRIL23!K10+HISTOMAI23!K10+HISTOJUIN23!K10+HISTOJUIL23!K10+HISTOAOUT23!K10+HISTOSEPT23!K10+HISTOOCT23!K10+HISTONOV23!K10+HISTODEC23!K10 -> 480000 | L10: =HISTOJANV23!L10+HISTOFEV23!L10+HISTOMARS23!L10+HISTOAVRIL23!L10+HISTOMAI23!L10+HISTOJUIN23!L10+HISTOJUIL23!L10+HISTOAOUT23!L10+HISTOSEPT23!L10+HISTOOCT23!L10+HISTONOV23!L10+HISTODEC23!L10 -> 0 | M10: =HISTOJANV23!M10+HISTOFEV23!M10+HISTOMARS23!M10+HISTOAVRIL23!M10+HISTOMAI23!M10+HISTOJUIN23!M10+HISTOJUIL23!M10+HISTOAOUT23!M10+HISTOSEPT23!M10+HISTOOCT23!M10+HISTONOV23!M10+HISTODEC23!M10 -> 0 | N10: =HISTOJANV23!N10+HISTOFEV23!N10+HISTOMARS23!N10+HISTOAVRIL23!N10+HISTOMAI23!N10+HISTOJUIN23!N10+HISTOJUIL23!N10+HISTOAOUT23!N10+HISTOSEPT23!N10+HISTOOCT23!N10+HISTONOV23!N10+HISTODEC23!N10 -> 0 | O10: =HISTOJANV23!O10+HISTOFEV23!O10+HISTOMARS23!O10+HISTOAVRIL23!O10+HISTOMAI23!O10+HISTOJUIN23!O10+HISTOJUIL23!O10+HISTOAOUT23!O10+HISTOSEPT23!O10+HISTOOCT23!O10+HISTONOV23!O10+HISTODEC23!O10 -> 0 | P10: =HISTOJANV23!P10+HISTOFEV23!P10+HISTOMARS23!P10+HISTOAVRIL23!P10+HISTOMAI23!P10+HISTOJUIN23!P10+HISTOJUIL23!P10+HISTOAOUT23!P10+HISTOSEPT23!P10+HISTOOCT23!P10+HISTONOV23!P10+HISTODEC23!P10 -> 166000 | ... T10: =HISTOJANV23!T10+HISTOFEV23!T10+HISTOMARS23!T10+HISTOAVRIL23!T10+HISTOMAI23!T10+HISTOJUIN23!T10+HISTOJUIL23!T10+HISTOAOUT23!T10+HISTOSEPT23!T10+HISTOOCT23!T10+HISTONOV23!T10+HISTODEC23!T10 -> 0 | U10: =G10+S10++R10+P10+O10+M10+I10+K10+Q10+V10+W10 -> 684000 | V10: =HISTOJANV23!V10+HISTOFEV23!V10+HISTOMARS23!V10+HISTOAVRIL23!V10+HISTOMAI23!V10+HISTOJUIN23!V10+HISTOJUIL23!V10+HISTOAOUT23!V10+HISTOSEPT23!V10+HISTOOCT23!V10+HISTONOV23!V10+HISTODEC23!V10 -> 22000 | W10: =HISTOJANV23!W10+HISTOFEV23!W10+HISTOMARS23!W10+HISTOAVRIL23!W10+HISTOMAI23!W10+HISTOJUIN23!W10+HISTOJUIL23!W10+HISTOAOUT23!W10+HISTOSEPT23!W10+HISTOOCT23!W10+HISTONOV23!W10+HISTODEC23!W10 -> 0 | X10: =HISTOJANV23!X10+HISTOFEV23!X10+HISTOMARS23!X10+HISTOAVRIL23!X10+HISTOMAI23!X10+HISTOJUIN23!X10+HISTOJUIL23!X10+HISTOAOUT23!X10+HISTOSEPT23!X10+HISTOOCT23!X10+HISTONOV23!X10+HISTODEC23!X10 -> 0 | Y10: =HISTOJANV23!Y10+HISTOFEV23!Y10+HISTOMARS23!Y10+HISTOAVRIL23!Y10+HISTOMAI23!Y10+HISTOJUIN23!Y10+HISTOJUIL23!Y10+HISTOAOUT23!Y10+HISTOSEPT23!Y10+HISTOOCT23!Y10+HISTONOV23!Y10+HISTODEC23!Y10 -> 0 | Z10: =HISTOJANV23!Z10+HISTOFEV23!Z10+HISTOMARS23!Z10+HISTOAVRIL23!Z10+HISTOMAI23!Z10+HISTOJUIN23!Z10+HISTOJUIL23!Z10+HISTOAOUT23!Z10+HISTOSEPT23!Z10+HISTOOCT23!Z10+HISTONOV23!Z10+HISTODEC23!Z10 -> 1000000 | AA10: =HISTOJANV23!AA10+HISTOFEV23!AA10+HISTOMARS23!AA10+HISTOAVRIL23!AA10+HISTOMAI23!AA10+HISTOJUIN23!AA10+HISTOJUIL23!AA10+HISTOAOUT23!AA10+HISTOSEPT23!AA10+HISTOOCT23!AA10+HISTONOV23!AA10+HISTODEC23!AA10 -> #VALUE! | AB10: =HISTOJANV23!AB10+HISTOFEV23!AB10+HISTOMARS23!AB10+HISTOAVRIL23!AB10+HISTOMAI23!AB10+HISTOJUIN23!AB10+HISTOJUIL23!AB10+HISTOAOUT23!AB10+HISTOSEPT23!AB10+HISTOOCT23!AB10+HISTONOV23!AB10+HISTODEC23!AB10 -> 0 | AC10: =HISTOJANV23!AC10+HISTOFEV23!AC10+HISTOMARS23!AC10+HISTOAVRIL23!AC10+HISTOMAI23!AC10+HISTOJUIN23!AC10+HISTOJUIL23!AC10+HISTOAOUT23!AC10+HISTOSEPT23!AC10+HISTOOCT23!AC10+HISTONOV23!AC10+HISTODEC23!AC10 -> 11000 | ... BM10: =HISTOJANV23!BM10+HISTOFEV23!BM10+HISTOMARS23!BM10+HISTOAVRIL23!BM10+HISTOMAI23!BM10+HISTOJUIN23!BM10+HISTOJUIL23!BM10+HISTOAOUT23!BM10+HISTOSEPT23!BM10+HISTOOCT23!BM10+HISTONOV23!BM10+HISTODEC23!BM10 -> 0 | BN10: CREDIT TELEPHONE | BO10: FONDS DE ROULEMENT | BP10: =HISTOJANV23!BP10+HISTOFEV23!BP10+HISTOMARS23!BP10+HISTOAVRIL23!BP10+HISTOMAI23!BP10+HISTOJUIN23!BP10+HISTOJUIL23!BP10+HISTOAOUT23!BP10+HISTOSEPT23!BP10+HISTOOCT23!BP10+HISTONOV23!BP10+HISTODEC23!BP10 -> 0
A11: AS201605 | B11: =VLOOKUP(A11,[17]LISTADHERENT!A$5:H$39,3,0) -> DJOUKWE NANGUEN GUY BLAISE | C11: =HISTOJANV23!C11+HISTOFEV23!C11+HISTOMARS23!C11+HISTOAVRIL23!C11+HISTOMAI23!C11+HISTOJUIN23!C11+HISTOJUIL23!C11+HISTOAOUT23!C11+HISTOSEPT23!C11+HISTOOCT23!C11+HISTONOV23!C11+HISTODEC23!C11 -> -258000 | D11: =HISTOJANV23!D11+HISTOFEV23!D11+HISTOMARS23!D11+HISTOAVRIL23!D11+HISTOMAI23!D11+HISTOJUIN23!D11+HISTOJUIL23!D11+HISTOAOUT23!D11+HISTOSEPT23!D11+HISTOOCT23!D11+HISTONOV23!D11+HISTODEC23!D11 -> 2886000 | E11: =HISTOJANV23!E11+HISTOFEV23!E11+HISTOMARS23!E11+HISTOAVRIL23!E11+HISTOMAI23!E11+HISTOJUIN23!E11+HISTOJUIL23!E11+HISTOAOUT23!E11+HISTOSEPT23!E11+HISTOOCT23!E11+HISTONOV23!E11+HISTODEC23!E11 -> 1221500 | F11: =HISTOJANV23!F11+HISTOFEV23!F11+HISTOMARS23!F11+HISTOAVRIL23!F11+HISTOMAI23!F11+HISTOJUIN23!F11+HISTOJUIL23!F11+HISTOAOUT23!F11+HISTOSEPT23!F11+HISTOOCT23!F11+HISTONOV23!F11+HISTODEC23!F11 -> 70000 | G11: =HISTOJANV23!G11+HISTOFEV23!G11+HISTOMARS23!G11+HISTOAVRIL23!G11+HISTOMAI23!G11+HISTOJUIN23!G11+HISTOJUIL23!G11+HISTOAOUT23!G11+HISTOSEPT23!G11+HISTOOCT23!G11+HISTONOV23!G11+HISTODEC23!G11 -> 3000 | H11: =IF($D11<>0,"BANQUE",IF($E11<>0,"ESPECES","ECHEC")) -> BANQUE | I11: =HISTOJANV23!I11+HISTOFEV23!I11+HISTOMARS23!I11+HISTOAVRIL23!I11+HISTOMAI23!I11+HISTOJUIN23!I11+HISTOJUIL23!I11+HISTOAOUT23!I11+HISTOSEPT23!I11+HISTOOCT23!I11+HISTONOV23!I11+HISTODEC23!I11 -> 9500 | J11: =HISTOJANV23!J11+HISTOFEV23!J11+HISTOMARS23!J11+HISTOAVRIL23!J11+HISTOMAI23!J11+HISTOJUIN23!J11+HISTOJUIL23!J11+HISTOAOUT23!J11+HISTOSEPT23!J11+HISTOOCT23!J11+HISTONOV23!J11+HISTODEC23!J11 -> 12 | K11: =HISTOJANV23!K11+HISTOFEV23!K11+HISTOMARS23!K11+HISTOAVRIL23!K11+HISTOMAI23!K11+HISTOJUIN23!K11+HISTOJUIL23!K11+HISTOAOUT23!K11+HISTOSEPT23!K11+HISTOOCT23!K11+HISTONOV23!K11+HISTODEC23!K11 -> 480000 | L11: =HISTOJANV23!L11+HISTOFEV23!L11+HISTOMARS23!L11+HISTOAVRIL23!L11+HISTOMAI23!L11+HISTOJUIN23!L11+HISTOJUIL23!L11+HISTOAOUT23!L11+HISTOSEPT23!L11+HISTOOCT23!L11+HISTONOV23!L11+HISTODEC23!L11 -> 12 | M11: =HISTOJANV23!M11+HISTOFEV23!M11+HISTOMARS23!M11+HISTOAVRIL23!M11+HISTOMAI23!M11+HISTOJUIN23!M11+HISTOJUIL23!M11+HISTOAOUT23!M11+HISTOSEPT23!M11+HISTOOCT23!M11+HISTONOV23!M11+HISTODEC23!M11 -> 900000 | N11: =HISTOJANV23!N11+HISTOFEV23!N11+HISTOMARS23!N11+HISTOAVRIL23!N11+HISTOMAI23!N11+HISTOJUIN23!N11+HISTOJUIL23!N11+HISTOAOUT23!N11+HISTOSEPT23!N11+HISTOOCT23!N11+HISTONOV23!N11+HISTODEC23!N11 -> 0 | O11: =HISTOJANV23!O11+HISTOFEV23!O11+HISTOMARS23!O11+HISTOAVRIL23!O11+HISTOMAI23!O11+HISTOJUIN23!O11+HISTOJUIL23!O11+HISTOAOUT23!O11+HISTOSEPT23!O11+HISTOOCT23!O11+HISTONOV23!O11+HISTODEC23!O11 -> 0 | P11: =HISTOJANV23!P11+HISTOFEV23!P11+HISTOMARS23!P11+HISTOAVRIL23!P11+HISTOMAI23!P11+HISTOJUIN23!P11+HISTOJUIL23!P11+HISTOAOUT23!P11+HISTOSEPT23!P11+HISTOOCT23!P11+HISTONOV23!P11+HISTODEC23!P11 -> 186000 | ... T11: =HISTOJANV23!T11+HISTOFEV23!T11+HISTOMARS23!T11+HISTOAVRIL23!T11+HISTOMAI23!T11+HISTOJUIN23!T11+HISTOJUIL23!T11+HISTOAOUT23!T11+HISTOSEPT23!T11+HISTOOCT23!T11+HISTONOV23!T11+HISTODEC23!T11 -> #VALUE! | U11: =G11+S11++R11+P11+O11+M11+I11+K11+Q11+V11+W11 -> 4365500 | V11: =HISTOJANV23!V11+HISTOFEV23!V11+HISTOMARS23!V11+HISTOAVRIL23!V11+HISTOMAI23!V11+HISTOJUIN23!V11+HISTOJUIL23!V11+HISTOAOUT23!V11+HISTOSEPT23!V11+HISTOOCT23!V11+HISTONOV23!V11+HISTODEC23!V11 -> 0 | W11: =HISTOJANV23!W11+HISTOFEV23!W11+HISTOMARS23!W11+HISTOAVRIL23!W11+HISTOMAI23!W11+HISTOJUIN23!W11+HISTOJUIL23!W11+HISTOAOUT23!W11+HISTOSEPT23!W11+HISTOOCT23!W11+HISTONOV23!W11+HISTODEC23!W11 -> 0 | X11: =HISTOJANV23!X11+HISTOFEV23!X11+HISTOMARS23!X11+HISTOAVRIL23!X11+HISTOMAI23!X11+HISTOJUIN23!X11+HISTOJUIL23!X11+HISTOAOUT23!X11+HISTOSEPT23!X11+HISTOOCT23!X11+HISTONOV23!X11+HISTODEC23!X11 -> 0 | Y11: =HISTOJANV23!Y11+HISTOFEV23!Y11+HISTOMARS23!Y11+HISTOAVRIL23!Y11+HISTOMAI23!Y11+HISTOJUIN23!Y11+HISTOJUIL23!Y11+HISTOAOUT23!Y11+HISTOSEPT23!Y11+HISTOOCT23!Y11+HISTONOV23!Y11+HISTODEC23!Y11 -> 0 | Z11: =HISTOJANV23!Z11+HISTOFEV23!Z11+HISTOMARS23!Z11+HISTOAVRIL23!Z11+HISTOMAI23!Z11+HISTOJUIN23!Z11+HISTOJUIL23!Z11+HISTOAOUT23!Z11+HISTOSEPT23!Z11+HISTOOCT23!Z11+HISTONOV23!Z11+HISTODEC23!Z11 -> 2000000 | AA11: =HISTOJANV23!AA11+HISTOFEV23!AA11+HISTOMARS23!AA11+HISTOAVRIL23!AA11+HISTOMAI23!AA11+HISTOJUIN23!AA11+HISTOJUIL23!AA11+HISTOAOUT23!AA11+HISTOSEPT23!AA11+HISTOOCT23!AA11+HISTONOV23!AA11+HISTODEC23!AA11 -> #VALUE! | AB11: =HISTOJANV23!AB11+HISTOFEV23!AB11+HISTOMARS23!AB11+HISTOAVRIL23!AB11+HISTOMAI23!AB11+HISTOJUIN23!AB11+HISTOJUIL23!AB11+HISTOAOUT23!AB11+HISTOSEPT23!AB11+HISTOOCT23!AB11+HISTONOV23!AB11+HISTODEC23!AB11 -> 0 | AC11: =HISTOJANV23!AC11+HISTOFEV23!AC11+HISTOMARS23!AC11+HISTOAVRIL23!AC11+HISTOMAI23!AC11+HISTOJUIN23!AC11+HISTOJUIL23!AC11+HISTOAOUT23!AC11+HISTOSEPT23!AC11+HISTOOCT23!AC11+HISTONOV23!AC11+HISTODEC23!AC11 -> 10000 | ... BM11: =HISTOJANV23!BM11+HISTOFEV23!BM11+HISTOMARS23!BM11+HISTOAVRIL23!BM11+HISTOMAI23!BM11+HISTOJUIN23!BM11+HISTOJUIL23!BM11+HISTOAOUT23!BM11+HISTOSEPT23!BM11+HISTOOCT23!BM11+HISTONOV23!BM11+HISTODEC23!BM11 -> 0 | BN11: PRODUCTION RAPPORT | BO11: FONDS DE ROULEMENT | BP11: =HISTOJANV23!BP11+HISTOFEV23!BP11+HISTOMARS23!BP11+HISTOAVRIL23!BP11+HISTOMAI23!BP11+HISTOJUIN23!BP11+HISTOJUIL23!BP11+HISTOAOUT23!BP11+HISTOSEPT23!BP11+HISTOOCT23!BP11+HISTONOV23!BP11+HISTODEC23!BP11 -> 38000
A12: AS201608 | B12: =VLOOKUP(A12,[17]LISTADHERENT!A$5:H$39,3,0) -> DJUOMBESSY ANTOINE | C12: =HISTOJANV23!C12+HISTOFEV23!C12+HISTOMARS23!C12+HISTOAVRIL23!C12+HISTOMAI23!C12+HISTOJUIN23!C12+HISTOJUIL23!C12+HISTOAOUT23!C12+HISTOSEPT23!C12+HISTOOCT23!C12+HISTONOV23!C12+HISTODEC23!C12 -> 0 | D12: =HISTOJANV23!D12+HISTOFEV23!D12+HISTOMARS23!D12+HISTOAVRIL23!D12+HISTOMAI23!D12+HISTOJUIN23!D12+HISTOJUIL23!D12+HISTOAOUT23!D12+HISTOSEPT23!D12+HISTOOCT23!D12+HISTONOV23!D12+HISTODEC23!D12 -> 5374500 | E12: =HISTOJANV23!E12+HISTOFEV23!E12+HISTOMARS23!E12+HISTOAVRIL23!E12+HISTOMAI23!E12+HISTOJUIN23!E12+HISTOJUIL23!E12+HISTOAOUT23!E12+HISTOSEPT23!E12+HISTOOCT23!E12+HISTONOV23!E12+HISTODEC23!E12 -> 257000 | F12: =HISTOJANV23!F12+HISTOFEV23!F12+HISTOMARS23!F12+HISTOAVRIL23!F12+HISTOMAI23!F12+HISTOJUIN23!F12+HISTOJUIL23!F12+HISTOAOUT23!F12+HISTOSEPT23!F12+HISTOOCT23!F12+HISTONOV23!F12+HISTODEC23!F12 -> 1070000 | G12: =HISTOJANV23!G12+HISTOFEV23!G12+HISTOMARS23!G12+HISTOAVRIL23!G12+HISTOMAI23!G12+HISTOJUIN23!G12+HISTOJUIL23!G12+HISTOAOUT23!G12+HISTOSEPT23!G12+HISTOOCT23!G12+HISTONOV23!G12+HISTODEC23!G12 -> 0 | H12: =IF($D12<>0,"BANQUE",IF($E12<>0,"ESPECES","ECHEC")) -> BANQUE | I12: =HISTOJANV23!I12+HISTOFEV23!I12+HISTOMARS23!I12+HISTOAVRIL23!I12+HISTOMAI23!I12+HISTOJUIN23!I12+HISTOJUIL23!I12+HISTOAOUT23!I12+HISTOSEPT23!I12+HISTOOCT23!I12+HISTONOV23!I12+HISTODEC23!I12 -> 199800 | J12: =HISTOJANV23!J12+HISTOFEV23!J12+HISTOMARS23!J12+HISTOAVRIL23!J12+HISTOMAI23!J12+HISTOJUIN23!J12+HISTOJUIL23!J12+HISTOAOUT23!J12+HISTOSEPT23!J12+HISTOOCT23!J12+HISTONOV23!J12+HISTODEC23!J12 -> 12 | K12: =HISTOJANV23!K12+HISTOFEV23!K12+HISTOMARS23!K12+HISTOAVRIL23!K12+HISTOMAI23!K12+HISTOJUIN23!K12+HISTOJUIL23!K12+HISTOAOUT23!K12+HISTOSEPT23!K12+HISTOOCT23!K12+HISTONOV23!K12+HISTODEC23!K12 -> 480000 | L12: =HISTOJANV23!L12+HISTOFEV23!L12+HISTOMARS23!L12+HISTOAVRIL23!L12+HISTOMAI23!L12+HISTOJUIN23!L12+HISTOJUIL23!L12+HISTOAOUT23!L12+HISTOSEPT23!L12+HISTOOCT23!L12+HISTONOV23!L12+HISTODEC23!L12 -> 12 | M12: =HISTOJANV23!M12+HISTOFEV23!M12+HISTOMARS23!M12+HISTOAVRIL23!M12+HISTOMAI23!M12+HISTOJUIN23!M12+HISTOJUIL23!M12+HISTOAOUT23!M12+HISTOSEPT23!M12+HISTOOCT23!M12+HISTONOV23!M12+HISTODEC23!M12 -> 900000 | N12: =HISTOJANV23!N12+HISTOFEV23!N12+HISTOMARS23!N12+HISTOAVRIL23!N12+HISTOMAI23!N12+HISTOJUIN23!N12+HISTOJUIL23!N12+HISTOAOUT23!N12+HISTOSEPT23!N12+HISTOOCT23!N12+HISTONOV23!N12+HISTODEC23!N12 -> 24 | O12: =HISTOJANV23!O12+HISTOFEV23!O12+HISTOMARS23!O12+HISTOAVRIL23!O12+HISTOMAI23!O12+HISTOJUIN23!O12+HISTOJUIL23!O12+HISTOAOUT23!O12+HISTOSEPT23!O12+HISTOOCT23!O12+HISTONOV23!O12+HISTODEC23!O12 -> 2400000 | P12: =HISTOJANV23!P12+HISTOFEV23!P12+HISTOMARS23!P12+HISTOAVRIL23!P12+HISTOMAI23!P12+HISTOJUIN23!P12+HISTOJUIL23!P12+HISTOAOUT23!P12+HISTOSEPT23!P12+HISTOOCT23!P12+HISTONOV23!P12+HISTODEC23!P12 -> 30500 | ... T12: =HISTOJANV23!T12+HISTOFEV23!T12+HISTOMARS23!T12+HISTOAVRIL23!T12+HISTOMAI23!T12+HISTOJUIN23!T12+HISTOJUIL23!T12+HISTOAOUT23!T12+HISTOSEPT23!T12+HISTOOCT23!T12+HISTONOV23!T12+HISTODEC23!T12 -> #VALUE! | U12: =G12+S12++R12+P12+O12+M12+I12+K12+Q12+V12+W12 -> 6631500 | V12: =HISTOJANV23!V12+HISTOFEV23!V12+HISTOMARS23!V12+HISTOAVRIL23!V12+HISTOMAI23!V12+HISTOJUIN23!V12+HISTOJUIL23!V12+HISTOAOUT23!V12+HISTOSEPT23!V12+HISTOOCT23!V12+HISTONOV23!V12+HISTODEC23!V12 -> 0 | W12: =HISTOJANV23!W12+HISTOFEV23!W12+HISTOMARS23!W12+HISTOAVRIL23!W12+HISTOMAI23!W12+HISTOJUIN23!W12+HISTOJUIL23!W12+HISTOAOUT23!W12+HISTOSEPT23!W12+HISTOOCT23!W12+HISTONOV23!W12+HISTODEC23!W12 -> 0 | X12: =HISTOJANV23!X12+HISTOFEV23!X12+HISTOMARS23!X12+HISTOAVRIL23!X12+HISTOMAI23!X12+HISTOJUIN23!X12+HISTOJUIL23!X12+HISTOAOUT23!X12+HISTOSEPT23!X12+HISTOOCT23!X12+HISTONOV23!X12+HISTODEC23!X12 -> 0 | Y12: =HISTOJANV23!Y12+HISTOFEV23!Y12+HISTOMARS23!Y12+HISTOAVRIL23!Y12+HISTOMAI23!Y12+HISTOJUIN23!Y12+HISTOJUIL23!Y12+HISTOAOUT23!Y12+HISTOSEPT23!Y12+HISTOOCT23!Y12+HISTONOV23!Y12+HISTODEC23!Y12 -> 0 | Z12: =HISTOJANV23!Z12+HISTOFEV23!Z12+HISTOMARS23!Z12+HISTOAVRIL23!Z12+HISTOMAI23!Z12+HISTOJUIN23!Z12+HISTOJUIL23!Z12+HISTOAOUT23!Z12+HISTOSEPT23!Z12+HISTOOCT23!Z12+HISTONOV23!Z12+HISTODEC23!Z12 -> 1705000 | AA12: =HISTOJANV23!AA12+HISTOFEV23!AA12+HISTOMARS23!AA12+HISTOAVRIL23!AA12+HISTOMAI23!AA12+HISTOJUIN23!AA12+HISTOJUIL23!AA12+HISTOAOUT23!AA12+HISTOSEPT23!AA12+HISTOOCT23!AA12+HISTONOV23!AA12+HISTODEC23!AA12 -> #VALUE! | AB12: =HISTOJANV23!AB12+HISTOFEV23!AB12+HISTOMARS23!AB12+HISTOAVRIL23!AB12+HISTOMAI23!AB12+HISTOJUIN23!AB12+HISTOJUIL23!AB12+HISTOAOUT23!AB12+HISTOSEPT23!AB12+HISTOOCT23!AB12+HISTONOV23!AB12+HISTODEC23!AB12 -> 0 | AC12: =HISTOJANV23!AC12+HISTOFEV23!AC12+HISTOMARS23!AC12+HISTOAVRIL23!AC12+HISTOMAI23!AC12+HISTOJUIN23!AC12+HISTOJUIL23!AC12+HISTOAOUT23!AC12+HISTOSEPT23!AC12+HISTOOCT23!AC12+HISTONOV23!AC12+HISTODEC23!AC12 -> 5000 | ... BM12: =HISTOJANV23!BM12+HISTOFEV23!BM12+HISTOMARS23!BM12+HISTOAVRIL23!BM12+HISTOMAI23!BM12+HISTOJUIN23!BM12+HISTOJUIL23!BM12+HISTOAOUT23!BM12+HISTOSEPT23!BM12+HISTOOCT23!BM12+HISTONOV23!BM12+HISTODEC23!BM12 -> 0 | BN12: ACHAT SOURIS ET PHOTOCOPIE | BO12: FONDS DE ROULEMENT | BP12: =HISTOJANV23!BP12+HISTOFEV23!BP12+HISTOMARS23!BP12+HISTOAVRIL23!BP12+HISTOMAI23!BP12+HISTOJUIN23!BP12+HISTOJUIL23!BP12+HISTOAOUT23!BP12+HISTOSEPT23!BP12+HISTOOCT23!BP12+HISTONOV23!BP12+HISTODEC23!BP12 -> 0
A13: AS201651 | B13: =VLOOKUP(A13,[17]LISTADHERENT!A$5:H$39,3,0) -> DOMOU FABIEN | C13: =HISTOJANV23!C13+HISTOFEV23!C13+HISTOMARS23!C13+HISTOAVRIL23!C13+HISTOMAI23!C13+HISTOJUIN23!C13+HISTOJUIL23!C13+HISTOAOUT23!C13+HISTOSEPT23!C13+HISTOOCT23!C13+HISTONOV23!C13+HISTODEC23!C13 -> 0 | D13: =HISTOJANV23!D13+HISTOFEV23!D13+HISTOMARS23!D13+HISTOAVRIL23!D13+HISTOMAI23!D13+HISTOJUIN23!D13+HISTOJUIL23!D13+HISTOAOUT23!D13+HISTOSEPT23!D13+HISTOOCT23!D13+HISTONOV23!D13+HISTODEC23!D13 -> 1440000 | E13: =HISTOJANV23!E13+HISTOFEV23!E13+HISTOMARS23!E13+HISTOAVRIL23!E13+HISTOMAI23!E13+HISTOJUIN23!E13+HISTOJUIL23!E13+HISTOAOUT23!E13+HISTOSEPT23!E13+HISTOOCT23!E13+HISTONOV23!E13+HISTODEC23!E13 -> 40000 | F13: =HISTOJANV23!F13+HISTOFEV23!F13+HISTOMARS23!F13+HISTOAVRIL23!F13+HISTOMAI23!F13+HISTOJUIN23!F13+HISTOJUIL23!F13+HISTOAOUT23!F13+HISTOSEPT23!F13+HISTOOCT23!F13+HISTONOV23!F13+HISTODEC23!F13 -> 70000 | G13: =HISTOJANV23!G13+HISTOFEV23!G13+HISTOMARS23!G13+HISTOAVRIL23!G13+HISTOMAI23!G13+HISTOJUIN23!G13+HISTOJUIL23!G13+HISTOAOUT23!G13+HISTOSEPT23!G13+HISTOOCT23!G13+HISTONOV23!G13+HISTODEC23!G13 -> 0 | H13: =IF($D13<>0,"BANQUE",IF($E13<>0,"ESPECES","ECHEC")) -> BANQUE | I13: =HISTOJANV23!I13+HISTOFEV23!I13+HISTOMARS23!I13+HISTOAVRIL23!I13+HISTOMAI23!I13+HISTOJUIN23!I13+HISTOJUIL23!I13+HISTOAOUT23!I13+HISTOSEPT23!I13+HISTOOCT23!I13+HISTONOV23!I13+HISTODEC23!I13 -> 0 | J13: =HISTOJANV23!J13+HISTOFEV23!J13+HISTOMARS23!J13+HISTOAVRIL23!J13+HISTOMAI23!J13+HISTOJUIN23!J13+HISTOJUIL23!J13+HISTOAOUT23!J13+HISTOSEPT23!J13+HISTOOCT23!J13+HISTONOV23!J13+HISTODEC23!J13 -> 12 | K13: =HISTOJANV23!K13+HISTOFEV23!K13+HISTOMARS23!K13+HISTOAVRIL23!K13+HISTOMAI23!K13+HISTOJUIN23!K13+HISTOJUIL23!K13+HISTOAOUT23!K13+HISTOSEPT23!K13+HISTOOCT23!K13+HISTONOV23!K13+HISTODEC23!K13 -> 480000 | L13: =HISTOJANV23!L13+HISTOFEV23!L13+HISTOMARS23!L13+HISTOAVRIL23!L13+HISTOMAI23!L13+HISTOJUIN23!L13+HISTOJUIL23!L13+HISTOAOUT23!L13+HISTOSEPT23!L13+HISTOOCT23!L13+HISTONOV23!L13+HISTODEC23!L13 -> 0 | M13: =HISTOJANV23!M13+HISTOFEV23!M13+HISTOMARS23!M13+HISTOAVRIL23!M13+HISTOMAI23!M13+HISTOJUIN23!M13+HISTOJUIL23!M13+HISTOAOUT23!M13+HISTOSEPT23!M13+HISTOOCT23!M13+HISTONOV23!M13+HISTODEC23!M13 -> 0 | N13: =HISTOJANV23!N13+HISTOFEV23!N13+HISTOMARS23!N13+HISTOAVRIL23!N13+HISTOMAI23!N13+HISTOJUIN23!N13+HISTOJUIL23!N13+HISTOAOUT23!N13+HISTOSEPT23!N13+HISTOOCT23!N13+HISTONOV23!N13+HISTODEC23!N13 -> 0 | O13: =HISTOJANV23!O13+HISTOFEV23!O13+HISTOMARS23!O13+HISTOAVRIL23!O13+HISTOMAI23!O13+HISTOJUIN23!O13+HISTOJUIL23!O13+HISTOAOUT23!O13+HISTOSEPT23!O13+HISTOOCT23!O13+HISTONOV23!O13+HISTODEC23!O13 -> 0 | P13: =HISTOJANV23!P13+HISTOFEV23!P13+HISTOMARS23!P13+HISTOAVRIL23!P13+HISTOMAI23!P13+HISTOJUIN23!P13+HISTOJUIL23!P13+HISTOAOUT23!P13+HISTOSEPT23!P13+HISTOOCT23!P13+HISTONOV23!P13+HISTODEC23!P13 -> 0 | ... T13: =HISTOJANV23!T13+HISTOFEV23!T13+HISTOMARS23!T13+HISTOAVRIL23!T13+HISTOMAI23!T13+HISTOJUIN23!T13+HISTOJUIL23!T13+HISTOAOUT23!T13+HISTOSEPT23!T13+HISTOOCT23!T13+HISTONOV23!T13+HISTODEC23!T13 -> #VALUE! | U13: =G13+S13++R13+P13+O13+M13+I13+K13+Q13+V13+W13 -> 1480000 | V13: =HISTOJANV23!V13+HISTOFEV23!V13+HISTOMARS23!V13+HISTOAVRIL23!V13+HISTOMAI23!V13+HISTOJUIN23!V13+HISTOJUIL23!V13+HISTOAOUT23!V13+HISTOSEPT23!V13+HISTOOCT23!V13+HISTONOV23!V13+HISTODEC23!V13 -> 0 | W13: =HISTOJANV23!W13+HISTOFEV23!W13+HISTOMARS23!W13+HISTOAVRIL23!W13+HISTOMAI23!W13+HISTOJUIN23!W13+HISTOJUIL23!W13+HISTOAOUT23!W13+HISTOSEPT23!W13+HISTOOCT23!W13+HISTONOV23!W13+HISTODEC23!W13 -> 0 | X13: =HISTOJANV23!X13+HISTOFEV23!X13+HISTOMARS23!X13+HISTOAVRIL23!X13+HISTOMAI23!X13+HISTOJUIN23!X13+HISTOJUIL23!X13+HISTOAOUT23!X13+HISTOSEPT23!X13+HISTOOCT23!X13+HISTONOV23!X13+HISTODEC23!X13 -> 0 | Y13: =HISTOJANV23!Y13+HISTOFEV23!Y13+HISTOMARS23!Y13+HISTOAVRIL23!Y13+HISTOMAI23!Y13+HISTOJUIN23!Y13+HISTOJUIL23!Y13+HISTOAOUT23!Y13+HISTOSEPT23!Y13+HISTOOCT23!Y13+HISTONOV23!Y13+HISTODEC23!Y13 -> 0 | Z13: =HISTOJANV23!Z13+HISTOFEV23!Z13+HISTOMARS23!Z13+HISTOAVRIL23!Z13+HISTOMAI23!Z13+HISTOJUIN23!Z13+HISTOJUIL23!Z13+HISTOAOUT23!Z13+HISTOSEPT23!Z13+HISTOOCT23!Z13+HISTONOV23!Z13+HISTODEC23!Z13 -> 1000000 | AA13: =HISTOJANV23!AA13+HISTOFEV23!AA13+HISTOMARS23!AA13+HISTOAVRIL23!AA13+HISTOMAI23!AA13+HISTOJUIN23!AA13+HISTOJUIL23!AA13+HISTOAOUT23!AA13+HISTOSEPT23!AA13+HISTOOCT23!AA13+HISTONOV23!AA13+HISTODEC23!AA13 -> #VALUE! | AB13: =HISTOJANV23!AB13+HISTOFEV23!AB13+HISTOMARS23!AB13+HISTOAVRIL23!AB13+HISTOMAI23!AB13+HISTOJUIN23!AB13+HISTOJUIL23!AB13+HISTOAOUT23!AB13+HISTOSEPT23!AB13+HISTOOCT23!AB13+HISTONOV23!AB13+HISTODEC23!AB13 -> 0 | AC13: =HISTOJANV23!AC13+HISTOFEV23!AC13+HISTOMARS23!AC13+HISTOAVRIL23!AC13+HISTOMAI23!AC13+HISTOJUIN23!AC13+HISTOJUIL23!AC13+HISTOAOUT23!AC13+HISTOSEPT23!AC13+HISTOOCT23!AC13+HISTONOV23!AC13+HISTODEC23!AC13 -> 10000 | ... BM13: =HISTOJANV23!BM13+HISTOFEV23!BM13+HISTOMARS23!BM13+HISTOAVRIL23!BM13+HISTOMAI23!BM13+HISTOJUIN23!BM13+HISTOJUIL23!BM13+HISTOAOUT23!BM13+HISTOSEPT23!BM13+HISTOOCT23!BM13+HISTONOV23!BM13+HISTODEC23!BM13 -> 0 | BN13: TAXI BANQUE | BO13: FONDS DE ROULEMENT | BP13: =HISTOJANV23!BP13+HISTOFEV23!BP13+HISTOMARS23!BP13+HISTOAVRIL23!BP13+HISTOMAI23!BP13+HISTOJUIN23!BP13+HISTOJUIL23!BP13+HISTOAOUT23!BP13+HISTOSEPT23!BP13+HISTOOCT23!BP13+HISTONOV23!BP13+HISTODEC23!BP13 -> 78000
A14: AS201609 | B14: =VLOOKUP(A14,[17]LISTADHERENT!A$5:H$39,3,0) -> DONHOU DAVID | C14: =HISTOJANV23!C14+HISTOFEV23!C14+HISTOMARS23!C14+HISTOAVRIL23!C14+HISTOMAI23!C14+HISTOJUIN23!C14+HISTOJUIL23!C14+HISTOAOUT23!C14+HISTOSEPT23!C14+HISTOOCT23!C14+HISTONOV23!C14+HISTODEC23!C14 -> -70000 | D14: =HISTOJANV23!D14+HISTOFEV23!D14+HISTOMARS23!D14+HISTOAVRIL23!D14+HISTOMAI23!D14+HISTOJUIN23!D14+HISTOJUIL23!D14+HISTOAOUT23!D14+HISTOSEPT23!D14+HISTOOCT23!D14+HISTONOV23!D14+HISTODEC23!D14 -> 480000 | E14: =HISTOJANV23!E14+HISTOFEV23!E14+HISTOMARS23!E14+HISTOAVRIL23!E14+HISTOMAI23!E14+HISTOJUIN23!E14+HISTOJUIL23!E14+HISTOAOUT23!E14+HISTOSEPT23!E14+HISTOOCT23!E14+HISTONOV23!E14+HISTODEC23!E14 -> 0 | F14: =HISTOJANV23!F14+HISTOFEV23!F14+HISTOMARS23!F14+HISTOAVRIL23!F14+HISTOMAI23!F14+HISTOJUIN23!F14+HISTOJUIL23!F14+HISTOAOUT23!F14+HISTOSEPT23!F14+HISTOOCT23!F14+HISTONOV23!F14+HISTODEC23!F14 -> 0 | G14: =HISTOJANV23!G14+HISTOFEV23!G14+HISTOMARS23!G14+HISTOAVRIL23!G14+HISTOMAI23!G14+HISTOJUIN23!G14+HISTOJUIL23!G14+HISTOAOUT23!G14+HISTOSEPT23!G14+HISTOOCT23!G14+HISTONOV23!G14+HISTODEC23!G14 -> 0 | H14: =IF($D14<>0,"BANQUE",IF($E14<>0,"ESPECES","ECHEC")) -> BANQUE | I14: =HISTOJANV23!I14+HISTOFEV23!I14+HISTOMARS23!I14+HISTOAVRIL23!I14+HISTOMAI23!I14+HISTOJUIN23!I14+HISTOJUIL23!I14+HISTOAOUT23!I14+HISTOSEPT23!I14+HISTOOCT23!I14+HISTONOV23!I14+HISTODEC23!I14 -> 0 | J14: =HISTOJANV23!J14+HISTOFEV23!J14+HISTOMARS23!J14+HISTOAVRIL23!J14+HISTOMAI23!J14+HISTOJUIN23!J14+HISTOJUIL23!J14+HISTOAOUT23!J14+HISTOSEPT23!J14+HISTOOCT23!J14+HISTONOV23!J14+HISTODEC23!J14 -> 12 | K14: =HISTOJANV23!K14+HISTOFEV23!K14+HISTOMARS23!K14+HISTOAVRIL23!K14+HISTOMAI23!K14+HISTOJUIN23!K14+HISTOJUIL23!K14+HISTOAOUT23!K14+HISTOSEPT23!K14+HISTOOCT23!K14+HISTONOV23!K14+HISTODEC23!K14 -> 480000 | L14: =HISTOJANV23!L14+HISTOFEV23!L14+HISTOMARS23!L14+HISTOAVRIL23!L14+HISTOMAI23!L14+HISTOJUIN23!L14+HISTOJUIL23!L14+HISTOAOUT23!L14+HISTOSEPT23!L14+HISTOOCT23!L14+HISTONOV23!L14+HISTODEC23!L14 -> 0 | M14: =HISTOJANV23!M14+HISTOFEV23!M14+HISTOMARS23!M14+HISTOAVRIL23!M14+HISTOMAI23!M14+HISTOJUIN23!M14+HISTOJUIL23!M14+HISTOAOUT23!M14+HISTOSEPT23!M14+HISTOOCT23!M14+HISTONOV23!M14+HISTODEC23!M14 -> 0 | N14: =HISTOJANV23!N14+HISTOFEV23!N14+HISTOMARS23!N14+HISTOAVRIL23!N14+HISTOMAI23!N14+HISTOJUIN23!N14+HISTOJUIL23!N14+HISTOAOUT23!N14+HISTOSEPT23!N14+HISTOOCT23!N14+HISTONOV23!N14+HISTODEC23!N14 -> 0 | O14: =HISTOJANV23!O14+HISTOFEV23!O14+HISTOMARS23!O14+HISTOAVRIL23!O14+HISTOMAI23!O14+HISTOJUIN23!O14+HISTOJUIL23!O14+HISTOAOUT23!O14+HISTOSEPT23!O14+HISTOOCT23!O14+HISTONOV23!O14+HISTODEC23!O14 -> 0 | P14: =HISTOJANV23!P14+HISTOFEV23!P14+HISTOMARS23!P14+HISTOAVRIL23!P14+HISTOMAI23!P14+HISTOJUIN23!P14+HISTOJUIL23!P14+HISTOAOUT23!P14+HISTOSEPT23!P14+HISTOOCT23!P14+HISTONOV23!P14+HISTODEC23!P14 -> 0 | ... T14: =HISTOJANV23!T14+HISTOFEV23!T14+HISTOMARS23!T14+HISTOAVRIL23!T14+HISTOMAI23!T14+HISTOJUIN23!T14+HISTOJUIL23!T14+HISTOAOUT23!T14+HISTOSEPT23!T14+HISTOOCT23!T14+HISTONOV23!T14+HISTODEC23!T14 -> 0 | U14: =G14+S14++R14+P14+O14+M14+I14+K14+Q14+V14+W14 -> 480000 | V14: =HISTOJANV23!V14+HISTOFEV23!V14+HISTOMARS23!V14+HISTOAVRIL23!V14+HISTOMAI23!V14+HISTOJUIN23!V14+HISTOJUIL23!V14+HISTOAOUT23!V14+HISTOSEPT23!V14+HISTOOCT23!V14+HISTONOV23!V14+HISTODEC23!V14 -> 0 | W14: =HISTOJANV23!W14+HISTOFEV23!W14+HISTOMARS23!W14+HISTOAVRIL23!W14+HISTOMAI23!W14+HISTOJUIN23!W14+HISTOJUIL23!W14+HISTOAOUT23!W14+HISTOSEPT23!W14+HISTOOCT23!W14+HISTONOV23!W14+HISTODEC23!W14 -> 0 | X14: =HISTOJANV23!X14+HISTOFEV23!X14+HISTOMARS23!X14+HISTOAVRIL23!X14+HISTOMAI23!X14+HISTOJUIN23!X14+HISTOJUIL23!X14+HISTOAOUT23!X14+HISTOSEPT23!X14+HISTOOCT23!X14+HISTONOV23!X14+HISTODEC23!X14 -> 0 | Y14: =HISTOJANV23!Y14+HISTOFEV23!Y14+HISTOMARS23!Y14+HISTOAVRIL23!Y14+HISTOMAI23!Y14+HISTOJUIN23!Y14+HISTOJUIL23!Y14+HISTOAOUT23!Y14+HISTOSEPT23!Y14+HISTOOCT23!Y14+HISTONOV23!Y14+HISTODEC23!Y14 -> 0 | Z14: =HISTOJANV23!Z14+HISTOFEV23!Z14+HISTOMARS23!Z14+HISTOAVRIL23!Z14+HISTOMAI23!Z14+HISTOJUIN23!Z14+HISTOJUIL23!Z14+HISTOAOUT23!Z14+HISTOSEPT23!Z14+HISTOOCT23!Z14+HISTONOV23!Z14+HISTODEC23!Z14 -> 0 | AA14: =HISTOJANV23!AA14+HISTOFEV23!AA14+HISTOMARS23!AA14+HISTOAVRIL23!AA14+HISTOMAI23!AA14+HISTOJUIN23!AA14+HISTOJUIL23!AA14+HISTOAOUT23!AA14+HISTOSEPT23!AA14+HISTOOCT23!AA14+HISTONOV23!AA14+HISTODEC23!AA14 -> 0 | AB14: =HISTOJANV23!AB14+HISTOFEV23!AB14+HISTOMARS23!AB14+HISTOAVRIL23!AB14+HISTOMAI23!AB14+HISTOJUIN23!AB14+HISTOJUIL23!AB14+HISTOAOUT23!AB14+HISTOSEPT23!AB14+HISTOOCT23!AB14+HISTONOV23!AB14+HISTODEC23!AB14 -> 0 | AC14: =HISTOJANV23!AC14+HISTOFEV23!AC14+HISTOMARS23!AC14+HISTOAVRIL23!AC14+HISTOMAI23!AC14+HISTOJUIN23!AC14+HISTOJUIL23!AC14+HISTOAOUT23!AC14+HISTOSEPT23!AC14+HISTOOCT23!AC14+HISTONOV23!AC14+HISTODEC23!AC14 -> 2500 | ... BM14: =HISTOJANV23!BM14+HISTOFEV23!BM14+HISTOMARS23!BM14+HISTOAVRIL23!BM14+HISTOMAI23!BM14+HISTOJUIN23!BM14+HISTOJUIL23!BM14+HISTOAOUT23!BM14+HISTOSEPT23!BM14+HISTOOCT23!BM14+HISTONOV23!BM14+HISTODEC23!BM14 -> 0 | BN14: CONFECTION CACHET | BO14: FONDS DE ROULEMENT | BP14: =HISTOJANV23!BP14+HISTOFEV23!BP14+HISTOMARS23!BP14+HISTOAVRIL23!BP14+HISTOMAI23!BP14+HISTOJUIN23!BP14+HISTOJUIL23!BP14+HISTOAOUT23!BP14+HISTOSEPT23!BP14+HISTOOCT23!BP14+HISTONOV23!BP14+HISTODEC23!BP14 -> 0
A15: AS201611 | B15: =VLOOKUP(A15,[17]LISTADHERENT!A$5:H$39,3,0) -> HENGUE PAUL OMER | C15: =HISTOJANV23!C15+HISTOFEV23!C15+HISTOMARS23!C15+HISTOAVRIL23!C15+HISTOMAI23!C15+HISTOJUIN23!C15+HISTOJUIL23!C15+HISTOAOUT23!C15+HISTOSEPT23!C15+HISTOOCT23!C15+HISTONOV23!C15+HISTODEC23!C15 -> 0 | D15: =HISTOJANV23!D15+HISTOFEV23!D15+HISTOMARS23!D15+HISTOAVRIL23!D15+HISTOMAI23!D15+HISTOJUIN23!D15+HISTOJUIL23!D15+HISTOAOUT23!D15+HISTOSEPT23!D15+HISTOOCT23!D15+HISTONOV23!D15+HISTODEC23!D15 -> 1265000 | E15: =HISTOJANV23!E15+HISTOFEV23!E15+HISTOMARS23!E15+HISTOAVRIL23!E15+HISTOMAI23!E15+HISTOJUIN23!E15+HISTOJUIL23!E15+HISTOAOUT23!E15+HISTOSEPT23!E15+HISTOOCT23!E15+HISTONOV23!E15+HISTODEC23!E15 -> 118000 | F15: =HISTOJANV23!F15+HISTOFEV23!F15+HISTOMARS23!F15+HISTOAVRIL23!F15+HISTOMAI23!F15+HISTOJUIN23!F15+HISTOJUIL23!F15+HISTOAOUT23!F15+HISTOSEPT23!F15+HISTOOCT23!F15+HISTONOV23!F15+HISTODEC23!F15 -> 70000 | G15: =HISTOJANV23!G15+HISTOFEV23!G15+HISTOMARS23!G15+HISTOAVRIL23!G15+HISTOMAI23!G15+HISTOJUIN23!G15+HISTOJUIL23!G15+HISTOAOUT23!G15+HISTOSEPT23!G15+HISTOOCT23!G15+HISTONOV23!G15+HISTODEC23!G15 -> 3000 | H15: =IF($D15<>0,"BANQUE",IF($E15<>0,"ESPECES","ECHEC")) -> BANQUE | I15: =HISTOJANV23!I15+HISTOFEV23!I15+HISTOMARS23!I15+HISTOAVRIL23!I15+HISTOMAI23!I15+HISTOJUIN23!I15+HISTOJUIL23!I15+HISTOAOUT23!I15+HISTOSEPT23!I15+HISTOOCT23!I15+HISTONOV23!I15+HISTODEC23!I15 -> 0 | J15: =HISTOJANV23!J15+HISTOFEV23!J15+HISTOMARS23!J15+HISTOAVRIL23!J15+HISTOMAI23!J15+HISTOJUIN23!J15+HISTOJUIL23!J15+HISTOAOUT23!J15+HISTOSEPT23!J15+HISTOOCT23!J15+HISTONOV23!J15+HISTODEC23!J15 -> 12 | K15: =HISTOJANV23!K15+HISTOFEV23!K15+HISTOMARS23!K15+HISTOAVRIL23!K15+HISTOMAI23!K15+HISTOJUIN23!K15+HISTOJUIL23!K15+HISTOAOUT23!K15+HISTOSEPT23!K15+HISTOOCT23!K15+HISTONOV23!K15+HISTODEC23!K15 -> 480000 | L15: =HISTOJANV23!L15+HISTOFEV23!L15+HISTOMARS23!L15+HISTOAVRIL23!L15+HISTOMAI23!L15+HISTOJUIN23!L15+HISTOJUIL23!L15+HISTOAOUT23!L15+HISTOSEPT23!L15+HISTOOCT23!L15+HISTONOV23!L15+HISTODEC23!L15 -> 12 | M15: =HISTOJANV23!M15+HISTOFEV23!M15+HISTOMARS23!M15+HISTOAVRIL23!M15+HISTOMAI23!M15+HISTOJUIN23!M15+HISTOJUIL23!M15+HISTOAOUT23!M15+HISTOSEPT23!M15+HISTOOCT23!M15+HISTONOV23!M15+HISTODEC23!M15 -> 900000 | N15: =HISTOJANV23!N15+HISTOFEV23!N15+HISTOMARS23!N15+HISTOAVRIL23!N15+HISTOMAI23!N15+HISTOJUIN23!N15+HISTOJUIL23!N15+HISTOAOUT23!N15+HISTOSEPT23!N15+HISTOOCT23!N15+HISTONOV23!N15+HISTODEC23!N15 -> 0 | O15: =HISTOJANV23!O15+HISTOFEV23!O15+HISTOMARS23!O15+HISTOAVRIL23!O15+HISTOMAI23!O15+HISTOJUIN23!O15+HISTOJUIL23!O15+HISTOAOUT23!O15+HISTOSEPT23!O15+HISTOOCT23!O15+HISTONOV23!O15+HISTODEC23!O15 -> 0 | P15: =HISTOJANV23!P15+HISTOFEV23!P15+HISTOMARS23!P15+HISTOAVRIL23!P15+HISTOMAI23!P15+HISTOJUIN23!P15+HISTOJUIL23!P15+HISTOAOUT23!P15+HISTOSEPT23!P15+HISTOOCT23!P15+HISTONOV23!P15+HISTODEC23!P15 -> 0 | ... T15: =HISTOJANV23!T15+HISTOFEV23!T15+HISTOMARS23!T15+HISTOAVRIL23!T15+HISTOMAI23!T15+HISTOJUIN23!T15+HISTOJUIL23!T15+HISTOAOUT23!T15+HISTOSEPT23!T15+HISTOOCT23!T15+HISTONOV23!T15+HISTODEC23!T15 -> 0 | U15: =G15+S15++R15+P15+O15+M15+I15+K15+Q15+V15+W15 -> 1401000 | V15: =HISTOJANV23!V15+HISTOFEV23!V15+HISTOMARS23!V15+HISTOAVRIL23!V15+HISTOMAI23!V15+HISTOJUIN23!V15+HISTOJUIL23!V15+HISTOAOUT23!V15+HISTOSEPT23!V15+HISTOOCT23!V15+HISTONOV23!V15+HISTODEC23!V15 -> 18000 | W15: =HISTOJANV23!W15+HISTOFEV23!W15+HISTOMARS23!W15+HISTOAVRIL23!W15+HISTOMAI23!W15+HISTOJUIN23!W15+HISTOJUIL23!W15+HISTOAOUT23!W15+HISTOSEPT23!W15+HISTOOCT23!W15+HISTONOV23!W15+HISTODEC23!W15 -> 0 | X15: =HISTOJANV23!X15+HISTOFEV23!X15+HISTOMARS23!X15+HISTOAVRIL23!X15+HISTOMAI23!X15+HISTOJUIN23!X15+HISTOJUIL23!X15+HISTOAOUT23!X15+HISTOSEPT23!X15+HISTOOCT23!X15+HISTONOV23!X15+HISTODEC23!X15 -> 0 | Y15: =HISTOJANV23!Y15+HISTOFEV23!Y15+HISTOMARS23!Y15+HISTOAVRIL23!Y15+HISTOMAI23!Y15+HISTOJUIN23!Y15+HISTOJUIL23!Y15+HISTOAOUT23!Y15+HISTOSEPT23!Y15+HISTOOCT23!Y15+HISTONOV23!Y15+HISTODEC23!Y15 -> 0 | Z15: =HISTOJANV23!Z15+HISTOFEV23!Z15+HISTOMARS23!Z15+HISTOAVRIL23!Z15+HISTOMAI23!Z15+HISTOJUIN23!Z15+HISTOJUIL23!Z15+HISTOAOUT23!Z15+HISTOSEPT23!Z15+HISTOOCT23!Z15+HISTONOV23!Z15+HISTODEC23!Z15 -> 0 | AA15: =HISTOJANV23!AA15+HISTOFEV23!AA15+HISTOMARS23!AA15+HISTOAVRIL23!AA15+HISTOMAI23!AA15+HISTOJUIN23!AA15+HISTOJUIL23!AA15+HISTOAOUT23!AA15+HISTOSEPT23!AA15+HISTOOCT23!AA15+HISTONOV23!AA15+HISTODEC23!AA15 -> 0 | AB15: =HISTOJANV23!AB15+HISTOFEV23!AB15+HISTOMARS23!AB15+HISTOAVRIL23!AB15+HISTOMAI23!AB15+HISTOJUIN23!AB15+HISTOJUIL23!AB15+HISTOAOUT23!AB15+HISTOSEPT23!AB15+HISTOOCT23!AB15+HISTONOV23!AB15+HISTODEC23!AB15 -> 0 | AC15: =HISTOJANV23!AC15+HISTOFEV23!AC15+HISTOMARS23!AC15+HISTOAVRIL23!AC15+HISTOMAI23!AC15+HISTOJUIN23!AC15+HISTOJUIL23!AC15+HISTOAOUT23!AC15+HISTOSEPT23!AC15+HISTOOCT23!AC15+HISTONOV23!AC15+HISTODEC23!AC15 -> 2500 | ... BM15: =HISTOJANV23!BM15+HISTOFEV23!BM15+HISTOMARS23!BM15+HISTOAVRIL23!BM15+HISTOMAI23!BM15+HISTOJUIN23!BM15+HISTOJUIL23!BM15+HISTOAOUT23!BM15+HISTOSEPT23!BM15+HISTOOCT23!BM15+HISTONOV23!BM15+HISTODEC23!BM15 -> 0
A16: AS201613 | B16: =VLOOKUP(A16,[17]LISTADHERENT!A$5:H$39,3,0) -> HOTCHO BENJAMIN | C16: =HISTOJANV23!C16+HISTOFEV23!C16+HISTOMARS23!C16+HISTOAVRIL23!C16+HISTOMAI23!C16+HISTOJUIN23!C16+HISTOJUIL23!C16+HISTOAOUT23!C16+HISTOSEPT23!C16+HISTOOCT23!C16+HISTONOV23!C16+HISTODEC23!C16 -> 0 | D16: =HISTOJANV23!D16+HISTOFEV23!D16+HISTOMARS23!D16+HISTOAVRIL23!D16+HISTOMAI23!D16+HISTOJUIN23!D16+HISTOJUIL23!D16+HISTOAOUT23!D16+HISTOSEPT23!D16+HISTOOCT23!D16+HISTONOV23!D16+HISTODEC23!D16 -> 3549000 | E16: =HISTOJANV23!E16+HISTOFEV23!E16+HISTOMARS23!E16+HISTOAVRIL23!E16+HISTOMAI23!E16+HISTOJUIN23!E16+HISTOJUIL23!E16+HISTOAOUT23!E16+HISTOSEPT23!E16+HISTOOCT23!E16+HISTONOV23!E16+HISTODEC23!E16 -> 706000 | F16: =HISTOJANV23!F16+HISTOFEV23!F16+HISTOMARS23!F16+HISTOAVRIL23!F16+HISTOMAI23!F16+HISTOJUIN23!F16+HISTOJUIL23!F16+HISTOAOUT23!F16+HISTOSEPT23!F16+HISTOOCT23!F16+HISTONOV23!F16+HISTODEC23!F16 -> 1070000 | G16: =HISTOJANV23!G16+HISTOFEV23!G16+HISTOMARS23!G16+HISTOAVRIL23!G16+HISTOMAI23!G16+HISTOJUIN23!G16+HISTOJUIL23!G16+HISTOAOUT23!G16+HISTOSEPT23!G16+HISTOOCT23!G16+HISTONOV23!G16+HISTODEC23!G16 -> 0 | H16: =IF($D16<>0,"BANQUE",IF($E16<>0,"ESPECES","ECHEC")) -> BANQUE | I16: =HISTOJANV23!I16+HISTOFEV23!I16+HISTOMARS23!I16+HISTOAVRIL23!I16+HISTOMAI23!I16+HISTOJUIN23!I16+HISTOJUIL23!I16+HISTOAOUT23!I16+HISTOSEPT23!I16+HISTOOCT23!I16+HISTONOV23!I16+HISTODEC23!I16 -> 400000 | J16: =HISTOJANV23!J16+HISTOFEV23!J16+HISTOMARS23!J16+HISTOAVRIL23!J16+HISTOMAI23!J16+HISTOJUIN23!J16+HISTOJUIL23!J16+HISTOAOUT23!J16+HISTOSEPT23!J16+HISTOOCT23!J16+HISTONOV23!J16+HISTODEC23!J16 -> 12 | K16: =HISTOJANV23!K16+HISTOFEV23!K16+HISTOMARS23!K16+HISTOAVRIL23!K16+HISTOMAI23!K16+HISTOJUIN23!K16+HISTOJUIL23!K16+HISTOAOUT23!K16+HISTOSEPT23!K16+HISTOOCT23!K16+HISTONOV23!K16+HISTODEC23!K16 -> 480000 | L16: =HISTOJANV23!L16+HISTOFEV23!L16+HISTOMARS23!L16+HISTOAVRIL23!L16+HISTOMAI23!L16+HISTOJUIN23!L16+HISTOJUIL23!L16+HISTOAOUT23!L16+HISTOSEPT23!L16+HISTOOCT23!L16+HISTONOV23!L16+HISTODEC23!L16 -> 12 | M16: =HISTOJANV23!M16+HISTOFEV23!M16+HISTOMARS23!M16+HISTOAVRIL23!M16+HISTOMAI23!M16+HISTOJUIN23!M16+HISTOJUIL23!M16+HISTOAOUT23!M16+HISTOSEPT23!M16+HISTOOCT23!M16+HISTONOV23!M16+HISTODEC23!M16 -> 900000 | N16: =HISTOJANV23!N16+HISTOFEV23!N16+HISTOMARS23!N16+HISTOAVRIL23!N16+HISTOMAI23!N16+HISTOJUIN23!N16+HISTOJUIL23!N16+HISTOAOUT23!N16+HISTOSEPT23!N16+HISTOOCT23!N16+HISTONOV23!N16+HISTODEC23!N16 -> 12 | O16: =HISTOJANV23!O16+HISTOFEV23!O16+HISTOMARS23!O16+HISTOAVRIL23!O16+HISTOMAI23!O16+HISTOJUIN23!O16+HISTOJUIL23!O16+HISTOAOUT23!O16+HISTOSEPT23!O16+HISTOOCT23!O16+HISTONOV23!O16+HISTODEC23!O16 -> 1200000 | P16: =HISTOJANV23!P16+HISTOFEV23!P16+HISTOMARS23!P16+HISTOAVRIL23!P16+HISTOMAI23!P16+HISTOJUIN23!P16+HISTOJUIL23!P16+HISTOAOUT23!P16+HISTOSEPT23!P16+HISTOOCT23!P16+HISTONOV23!P16+HISTODEC23!P16 -> 0 | ... T16: =HISTOJANV23!T16+HISTOFEV23!T16+HISTOMARS23!T16+HISTOAVRIL23!T16+HISTOMAI23!T16+HISTOJUIN23!T16+HISTOJUIL23!T16+HISTOAOUT23!T16+HISTOSEPT23!T16+HISTOOCT23!T16+HISTONOV23!T16+HISTODEC23!T16 -> #VALUE! | U16: =G16+S16++R16+P16+O16+M16+I16+K16+Q16+V16+W16 -> 5267000 | V16: =HISTOJANV23!V16+HISTOFEV23!V16+HISTOMARS23!V16+HISTOAVRIL23!V16+HISTOMAI23!V16+HISTOJUIN23!V16+HISTOJUIL23!V16+HISTOAOUT23!V16+HISTOSEPT23!V16+HISTOOCT23!V16+HISTONOV23!V16+HISTODEC23!V16 -> 12000 | W16: =HISTOJANV23!W16+HISTOFEV23!W16+HISTOMARS23!W16+HISTOAVRIL23!W16+HISTOMAI23!W16+HISTOJUIN23!W16+HISTOJUIL23!W16+HISTOAOUT23!W16+HISTOSEPT23!W16+HISTOOCT23!W16+HISTONOV23!W16+HISTODEC23!W16 -> 0 | X16: =HISTOJANV23!X16+HISTOFEV23!X16+HISTOMARS23!X16+HISTOAVRIL23!X16+HISTOMAI23!X16+HISTOJUIN23!X16+HISTOJUIL23!X16+HISTOAOUT23!X16+HISTOSEPT23!X16+HISTOOCT23!X16+HISTONOV23!X16+HISTODEC23!X16 -> 0 | Y16: =HISTOJANV23!Y16+HISTOFEV23!Y16+HISTOMARS23!Y16+HISTOAVRIL23!Y16+HISTOMAI23!Y16+HISTOJUIN23!Y16+HISTOJUIL23!Y16+HISTOAOUT23!Y16+HISTOSEPT23!Y16+HISTOOCT23!Y16+HISTONOV23!Y16+HISTODEC23!Y16 -> 0 | Z16: =HISTOJANV23!Z16+HISTOFEV23!Z16+HISTOMARS23!Z16+HISTOAVRIL23!Z16+HISTOMAI23!Z16+HISTOJUIN23!Z16+HISTOJUIL23!Z16+HISTOAOUT23!Z16+HISTOSEPT23!Z16+HISTOOCT23!Z16+HISTONOV23!Z16+HISTODEC23!Z16 -> 500000 | AA16: =HISTOJANV23!AA16+HISTOFEV23!AA16+HISTOMARS23!AA16+HISTOAVRIL23!AA16+HISTOMAI23!AA16+HISTOJUIN23!AA16+HISTOJUIL23!AA16+HISTOAOUT23!AA16+HISTOSEPT23!AA16+HISTOOCT23!AA16+HISTONOV23!AA16+HISTODEC23!AA16 -> #VALUE! | AB16: =HISTOJANV23!AB16+HISTOFEV23!AB16+HISTOMARS23!AB16+HISTOAVRIL23!AB16+HISTOMAI23!AB16+HISTOJUIN23!AB16+HISTOJUIL23!AB16+HISTOAOUT23!AB16+HISTOSEPT23!AB16+HISTOOCT23!AB16+HISTONOV23!AB16+HISTODEC23!AB16 -> 0 | AC16: =HISTOJANV23!AC16+HISTOFEV23!AC16+HISTOMARS23!AC16+HISTOAVRIL23!AC16+HISTOMAI23!AC16+HISTOJUIN23!AC16+HISTOJUIL23!AC16+HISTOAOUT23!AC16+HISTOSEPT23!AC16+HISTOOCT23!AC16+HISTONOV23!AC16+HISTODEC23!AC16 -> 2500 | ... BM16: =HISTOJANV23!BM16+HISTOFEV23!BM16+HISTOMARS23!BM16+HISTOAVRIL23!BM16+HISTOMAI23!BM16+HISTOJUIN23!BM16+HISTOJUIL23!BM16+HISTOAOUT23!BM16+HISTOSEPT23!BM16+HISTOOCT23!BM16+HISTONOV23!BM16+HISTODEC23!BM16 -> 0 | BN16: S/TOTAL | BP16: =SUM(BP6:BP15) -> 199000
A17: AS201617 | B17: =VLOOKUP(A17,[17]LISTADHERENT!A$5:H$39,3,0) -> KOUAMOU MOISE | C17: =HISTOJANV23!C17+HISTOFEV23!C17+HISTOMARS23!C17+HISTOAVRIL23!C17+HISTOMAI23!C17+HISTOJUIN23!C17+HISTOJUIL23!C17+HISTOAOUT23!C17+HISTOSEPT23!C17+HISTOOCT23!C17+HISTONOV23!C17+HISTODEC23!C17 -> -70000 | D17: =HISTOJANV23!D17+HISTOFEV23!D17+HISTOMARS23!D17+HISTOAVRIL23!D17+HISTOMAI23!D17+HISTOJUIN23!D17+HISTOJUIL23!D17+HISTOAOUT23!D17+HISTOSEPT23!D17+HISTOOCT23!D17+HISTONOV23!D17+HISTODEC23!D17 -> 2983000 | E17: =HISTOJANV23!E17+HISTOFEV23!E17+HISTOMARS23!E17+HISTOAVRIL23!E17+HISTOMAI23!E17+HISTOJUIN23!E17+HISTOJUIL23!E17+HISTOAOUT23!E17+HISTOSEPT23!E17+HISTOOCT23!E17+HISTONOV23!E17+HISTODEC23!E17 -> 0 | F17: =HISTOJANV23!F17+HISTOFEV23!F17+HISTOMARS23!F17+HISTOAVRIL23!F17+HISTOMAI23!F17+HISTOJUIN23!F17+HISTOJUIL23!F17+HISTOAOUT23!F17+HISTOSEPT23!F17+HISTOOCT23!F17+HISTONOV23!F17+HISTODEC23!F17 -> 0 | G17: =HISTOJANV23!G17+HISTOFEV23!G17+HISTOMARS23!G17+HISTOAVRIL23!G17+HISTOMAI23!G17+HISTOJUIN23!G17+HISTOJUIL23!G17+HISTOAOUT23!G17+HISTOSEPT23!G17+HISTOOCT23!G17+HISTONOV23!G17+HISTODEC23!G17 -> 0 | H17: =IF($D17<>0,"BANQUE",IF($E17<>0,"ESPECES","ECHEC")) -> BANQUE | I17: =HISTOJANV23!I17+HISTOFEV23!I17+HISTOMARS23!I17+HISTOAVRIL23!I17+HISTOMAI23!I17+HISTOJUIN23!I17+HISTOJUIL23!I17+HISTOAOUT23!I17+HISTOSEPT23!I17+HISTOOCT23!I17+HISTONOV23!I17+HISTODEC23!I17 -> 0 | J17: =HISTOJANV23!J17+HISTOFEV23!J17+HISTOMARS23!J17+HISTOAVRIL23!J17+HISTOMAI23!J17+HISTOJUIN23!J17+HISTOJUIL23!J17+HISTOAOUT23!J17+HISTOSEPT23!J17+HISTOOCT23!J17+HISTONOV23!J17+HISTODEC23!J17 -> 12 | K17: =HISTOJANV23!K17+HISTOFEV23!K17+HISTOMARS23!K17+HISTOAVRIL23!K17+HISTOMAI23!K17+HISTOJUIN23!K17+HISTOJUIL23!K17+HISTOAOUT23!K17+HISTOSEPT23!K17+HISTOOCT23!K17+HISTONOV23!K17+HISTODEC23!K17 -> 480000 | L17: =HISTOJANV23!L17+HISTOFEV23!L17+HISTOMARS23!L17+HISTOAVRIL23!L17+HISTOMAI23!L17+HISTOJUIN23!L17+HISTOJUIL23!L17+HISTOAOUT23!L17+HISTOSEPT23!L17+HISTOOCT23!L17+HISTONOV23!L17+HISTODEC23!L17 -> 0 | M17: =HISTOJANV23!M17+HISTOFEV23!M17+HISTOMARS23!M17+HISTOAVRIL23!M17+HISTOMAI23!M17+HISTOJUIN23!M17+HISTOJUIL23!M17+HISTOAOUT23!M17+HISTOSEPT23!M17+HISTOOCT23!M17+HISTONOV23!M17+HISTODEC23!M17 -> 0 | N17: =HISTOJANV23!N17+HISTOFEV23!N17+HISTOMARS23!N17+HISTOAVRIL23!N17+HISTOMAI23!N17+HISTOJUIN23!N17+HISTOJUIL23!N17+HISTOAOUT23!N17+HISTOSEPT23!N17+HISTOOCT23!N17+HISTONOV23!N17+HISTODEC23!N17 -> 12 | O17: =HISTOJANV23!O17+HISTOFEV23!O17+HISTOMARS23!O17+HISTOAVRIL23!O17+HISTOMAI23!O17+HISTOJUIN23!O17+HISTOJUIL23!O17+HISTOAOUT23!O17+HISTOSEPT23!O17+HISTOOCT23!O17+HISTONOV23!O17+HISTODEC23!O17 -> 1200000 | P17: =HISTOJANV23!P17+HISTOFEV23!P17+HISTOMARS23!P17+HISTOAVRIL23!P17+HISTOMAI23!P17+HISTOJUIN23!P17+HISTOJUIL23!P17+HISTOAOUT23!P17+HISTOSEPT23!P17+HISTOOCT23!P17+HISTONOV23!P17+HISTODEC23!P17 -> 0 | ... T17: =HISTOJANV23!T17+HISTOFEV23!T17+HISTOMARS23!T17+HISTOAVRIL23!T17+HISTOMAI23!T17+HISTOJUIN23!T17+HISTOJUIL23!T17+HISTOAOUT23!T17+HISTOSEPT23!T17+HISTOOCT23!T17+HISTONOV23!T17+HISTODEC23!T17 -> #VALUE! | U17: =G17+S17++R17+P17+O17+M17+I17+K17+Q17+V17+W17 -> 2992000 | V17: =HISTOJANV23!V17+HISTOFEV23!V17+HISTOMARS23!V17+HISTOAVRIL23!V17+HISTOMAI23!V17+HISTOJUIN23!V17+HISTOJUIL23!V17+HISTOAOUT23!V17+HISTOSEPT23!V17+HISTOOCT23!V17+HISTONOV23!V17+HISTODEC23!V17 -> 9000 | W17: =HISTOJANV23!W17+HISTOFEV23!W17+HISTOMARS23!W17+HISTOAVRIL23!W17+HISTOMAI23!W17+HISTOJUIN23!W17+HISTOJUIL23!W17+HISTOAOUT23!W17+HISTOSEPT23!W17+HISTOOCT23!W17+HISTONOV23!W17+HISTODEC23!W17 -> 0 | X17: =HISTOJANV23!X17+HISTOFEV23!X17+HISTOMARS23!X17+HISTOAVRIL23!X17+HISTOMAI23!X17+HISTOJUIN23!X17+HISTOJUIL23!X17+HISTOAOUT23!X17+HISTOSEPT23!X17+HISTOOCT23!X17+HISTONOV23!X17+HISTODEC23!X17 -> 0 | Y17: =HISTOJANV23!Y17+HISTOFEV23!Y17+HISTOMARS23!Y17+HISTOAVRIL23!Y17+HISTOMAI23!Y17+HISTOJUIN23!Y17+HISTOJUIL23!Y17+HISTOAOUT23!Y17+HISTOSEPT23!Y17+HISTOOCT23!Y17+HISTONOV23!Y17+HISTODEC23!Y17 -> 0 | Z17: =HISTOJANV23!Z17+HISTOFEV23!Z17+HISTOMARS23!Z17+HISTOAVRIL23!Z17+HISTOMAI23!Z17+HISTOJUIN23!Z17+HISTOJUIL23!Z17+HISTOAOUT23!Z17+HISTOSEPT23!Z17+HISTOOCT23!Z17+HISTONOV23!Z17+HISTODEC23!Z17 -> 1000000 | AA17: =HISTOJANV23!AA17+HISTOFEV23!AA17+HISTOMARS23!AA17+HISTOAVRIL23!AA17+HISTOMAI23!AA17+HISTOJUIN23!AA17+HISTOJUIL23!AA17+HISTOAOUT23!AA17+HISTOSEPT23!AA17+HISTOOCT23!AA17+HISTONOV23!AA17+HISTODEC23!AA17 -> #VALUE! | AB17: =HISTOJANV23!AB17+HISTOFEV23!AB17+HISTOMARS23!AB17+HISTOAVRIL23!AB17+HISTOMAI23!AB17+HISTOJUIN23!AB17+HISTOJUIL23!AB17+HISTOAOUT23!AB17+HISTOSEPT23!AB17+HISTOOCT23!AB17+HISTONOV23!AB17+HISTODEC23!AB17 -> 0 | AC17: =HISTOJANV23!AC17+HISTOFEV23!AC17+HISTOMARS23!AC17+HISTOAVRIL23!AC17+HISTOMAI23!AC17+HISTOJUIN23!AC17+HISTOJUIL23!AC17+HISTOAOUT23!AC17+HISTOSEPT23!AC17+HISTOOCT23!AC17+HISTONOV23!AC17+HISTODEC23!AC17 -> 6500 | ... BM17: =HISTOJANV23!BM17+HISTOFEV23!BM17+HISTOMARS23!BM17+HISTOAVRIL23!BM17+HISTOMAI23!BM17+HISTOJUIN23!BM17+HISTOJUIL23!BM17+HISTOAOUT23!BM17+HISTOSEPT23!BM17+HISTOOCT23!BM17+HISTONOV23!BM17+HISTODEC23!BM17 -> 0
A18: AS201619 | B18: =VLOOKUP(A18,[17]LISTADHERENT!A$5:H$39,3,0) -> KOUATCHO MESSACK | C18: =HISTOJANV23!C18+HISTOFEV23!C18+HISTOMARS23!C18+HISTOAVRIL23!C18+HISTOMAI23!C18+HISTOJUIN23!C18+HISTOJUIL23!C18+HISTOAOUT23!C18+HISTOSEPT23!C18+HISTOOCT23!C18+HISTONOV23!C18+HISTODEC23!C18 -> 1000 | D18: =HISTOJANV23!D18+HISTOFEV23!D18+HISTOMARS23!D18+HISTOAVRIL23!D18+HISTOMAI23!D18+HISTOJUIN23!D18+HISTOJUIL23!D18+HISTOAOUT23!D18+HISTOSEPT23!D18+HISTOOCT23!D18+HISTONOV23!D18+HISTODEC23!D18 -> 4863000 | E18: =HISTOJANV23!E18+HISTOFEV23!E18+HISTOMARS23!E18+HISTOAVRIL23!E18+HISTOMAI23!E18+HISTOJUIN23!E18+HISTOJUIL23!E18+HISTOAOUT23!E18+HISTOSEPT23!E18+HISTOOCT23!E18+HISTONOV23!E18+HISTODEC23!E18 -> 858500 | F18: =HISTOJANV23!F18+HISTOFEV23!F18+HISTOMARS23!F18+HISTOAVRIL23!F18+HISTOMAI23!F18+HISTOJUIN23!F18+HISTOJUIL23!F18+HISTOAOUT23!F18+HISTOSEPT23!F18+HISTOOCT23!F18+HISTONOV23!F18+HISTODEC23!F18 -> 70000 | G18: =HISTOJANV23!G18+HISTOFEV23!G18+HISTOMARS23!G18+HISTOAVRIL23!G18+HISTOMAI23!G18+HISTOJUIN23!G18+HISTOJUIL23!G18+HISTOAOUT23!G18+HISTOSEPT23!G18+HISTOOCT23!G18+HISTONOV23!G18+HISTODEC23!G18 -> 0 | H18: =IF($D18<>0,"BANQUE",IF($E18<>0,"ESPECES","ECHEC")) -> BANQUE | I18: =HISTOJANV23!I18+HISTOFEV23!I18+HISTOMARS23!I18+HISTOAVRIL23!I18+HISTOMAI23!I18+HISTOJUIN23!I18+HISTOJUIL23!I18+HISTOAOUT23!I18+HISTOSEPT23!I18+HISTOOCT23!I18+HISTONOV23!I18+HISTODEC23!I18 -> 0 | J18: =HISTOJANV23!J18+HISTOFEV23!J18+HISTOMARS23!J18+HISTOAVRIL23!J18+HISTOMAI23!J18+HISTOJUIN23!J18+HISTOJUIL23!J18+HISTOAOUT23!J18+HISTOSEPT23!J18+HISTOOCT23!J18+HISTONOV23!J18+HISTODEC23!J18 -> 12 | K18: =HISTOJANV23!K18+HISTOFEV23!K18+HISTOMARS23!K18+HISTOAVRIL23!K18+HISTOMAI23!K18+HISTOJUIN23!K18+HISTOJUIL23!K18+HISTOAOUT23!K18+HISTOSEPT23!K18+HISTOOCT23!K18+HISTONOV23!K18+HISTODEC23!K18 -> 480000 | L18: =HISTOJANV23!L18+HISTOFEV23!L18+HISTOMARS23!L18+HISTOAVRIL23!L18+HISTOMAI23!L18+HISTOJUIN23!L18+HISTOJUIL23!L18+HISTOAOUT23!L18+HISTOSEPT23!L18+HISTOOCT23!L18+HISTONOV23!L18+HISTODEC23!L18 -> 12 | M18: =HISTOJANV23!M18+HISTOFEV23!M18+HISTOMARS23!M18+HISTOAVRIL23!M18+HISTOMAI23!M18+HISTOJUIN23!M18+HISTOJUIL23!M18+HISTOAOUT23!M18+HISTOSEPT23!M18+HISTOOCT23!M18+HISTONOV23!M18+HISTODEC23!M18 -> 900000 | N18: =HISTOJANV23!N18+HISTOFEV23!N18+HISTOMARS23!N18+HISTOAVRIL23!N18+HISTOMAI23!N18+HISTOJUIN23!N18+HISTOJUIL23!N18+HISTOAOUT23!N18+HISTOSEPT23!N18+HISTOOCT23!N18+HISTONOV23!N18+HISTODEC23!N18 -> 12 | O18: =HISTOJANV23!O18+HISTOFEV23!O18+HISTOMARS23!O18+HISTOAVRIL23!O18+HISTOMAI23!O18+HISTOJUIN23!O18+HISTOJUIL23!O18+HISTOAOUT23!O18+HISTOSEPT23!O18+HISTOOCT23!O18+HISTONOV23!O18+HISTODEC23!O18 -> 1200000 | P18: =HISTOJANV23!P18+HISTOFEV23!P18+HISTOMARS23!P18+HISTOAVRIL23!P18+HISTOMAI23!P18+HISTOJUIN23!P18+HISTOJUIL23!P18+HISTOAOUT23!P18+HISTOSEPT23!P18+HISTOOCT23!P18+HISTONOV23!P18+HISTODEC23!P18 -> 30500 | ... T18: =HISTOJANV23!T18+HISTOFEV23!T18+HISTOMARS23!T18+HISTOAVRIL23!T18+HISTOMAI23!T18+HISTOJUIN23!T18+HISTOJUIL23!T18+HISTOAOUT23!T18+HISTOSEPT23!T18+HISTOOCT23!T18+HISTONOV23!T18+HISTODEC23!T18 -> #VALUE! | U18: =G18+S18++R18+P18+O18+M18+I18+K18+Q18+V18+W18 -> 5723500 | V18: =HISTOJANV23!V18+HISTOFEV23!V18+HISTOMARS23!V18+HISTOAVRIL23!V18+HISTOMAI23!V18+HISTOJUIN23!V18+HISTOJUIL23!V18+HISTOAOUT23!V18+HISTOSEPT23!V18+HISTOOCT23!V18+HISTONOV23!V18+HISTODEC23!V18 -> 3000 | W18: =HISTOJANV23!W18+HISTOFEV23!W18+HISTOMARS23!W18+HISTOAVRIL23!W18+HISTOMAI23!W18+HISTOJUIN23!W18+HISTOJUIL23!W18+HISTOAOUT23!W18+HISTOSEPT23!W18+HISTOOCT23!W18+HISTONOV23!W18+HISTODEC23!W18 -> 0 | X18: =HISTOJANV23!X18+HISTOFEV23!X18+HISTOMARS23!X18+HISTOAVRIL23!X18+HISTOMAI23!X18+HISTOJUIN23!X18+HISTOJUIL23!X18+HISTOAOUT23!X18+HISTOSEPT23!X18+HISTOOCT23!X18+HISTONOV23!X18+HISTODEC23!X18 -> 0 | Y18: =HISTOJANV23!Y18+HISTOFEV23!Y18+HISTOMARS23!Y18+HISTOAVRIL23!Y18+HISTOMAI23!Y18+HISTOJUIN23!Y18+HISTOJUIL23!Y18+HISTOAOUT23!Y18+HISTOSEPT23!Y18+HISTOOCT23!Y18+HISTONOV23!Y18+HISTODEC23!Y18 -> 0 | Z18: =HISTOJANV23!Z18+HISTOFEV23!Z18+HISTOMARS23!Z18+HISTOAVRIL23!Z18+HISTOMAI23!Z18+HISTOJUIN23!Z18+HISTOJUIL23!Z18+HISTOAOUT23!Z18+HISTOSEPT23!Z18+HISTOOCT23!Z18+HISTONOV23!Z18+HISTODEC23!Z18 -> 2250000 | AA18: =HISTOJANV23!AA18+HISTOFEV23!AA18+HISTOMARS23!AA18+HISTOAVRIL23!AA18+HISTOMAI23!AA18+HISTOJUIN23!AA18+HISTOJUIL23!AA18+HISTOAOUT23!AA18+HISTOSEPT23!AA18+HISTOOCT23!AA18+HISTONOV23!AA18+HISTODEC23!AA18 -> #VALUE! | AB18: =HISTOJANV23!AB18+HISTOFEV23!AB18+HISTOMARS23!AB18+HISTOAVRIL23!AB18+HISTOMAI23!AB18+HISTOJUIN23!AB18+HISTOJUIL23!AB18+HISTOAOUT23!AB18+HISTOSEPT23!AB18+HISTOOCT23!AB18+HISTONOV23!AB18+HISTODEC23!AB18 -> 0 | AC18: =HISTOJANV23!AC18+HISTOFEV23!AC18+HISTOMARS23!AC18+HISTOAVRIL23!AC18+HISTOMAI23!AC18+HISTOJUIN23!AC18+HISTOJUIL23!AC18+HISTOAOUT23!AC18+HISTOSEPT23!AC18+HISTOOCT23!AC18+HISTONOV23!AC18+HISTODEC23!AC18 -> 40000 | ... BM18: =HISTOJANV23!BM18+HISTOFEV23!BM18+HISTOMARS23!BM18+HISTOAVRIL23!BM18+HISTOMAI23!BM18+HISTOJUIN23!BM18+HISTOJUIL23!BM18+HISTOAOUT23!BM18+HISTOSEPT23!BM18+HISTOOCT23!BM18+HISTONOV23!BM18+HISTODEC23!BM18 -> 0 | BN18: GRATIFICATION BUREAU 2021 | BO18: PENALITE VERSEMENT ESPECES | BP18: =HISTOJANV23!BP18+HISTOFEV23!BP18+HISTOMARS23!BP18+HISTOAVRIL23!BP18+HISTOMAI23!BP18+HISTOJUIN23!BP18+HISTOJUIL23!BP18+HISTOAOUT23!BP18+HISTOSEPT23!BP18+HISTOOCT23!BP18+HISTONOV23!BP18+HISTODEC23!BP18 -> 200000
A19: AS201620 | B19: =VLOOKUP(A19,[17]LISTADHERENT!A$5:H$39,3,0) -> LOWE JEAN | C19: =HISTOJANV23!C19+HISTOFEV23!C19+HISTOMARS23!C19+HISTOAVRIL23!C19+HISTOMAI23!C19+HISTOJUIN23!C19+HISTOJUIL23!C19+HISTOAOUT23!C19+HISTOSEPT23!C19+HISTOOCT23!C19+HISTONOV23!C19+HISTODEC23!C19 -> -1000000 | D19: =HISTOJANV23!D19+HISTOFEV23!D19+HISTOMARS23!D19+HISTOAVRIL23!D19+HISTOMAI23!D19+HISTOJUIN23!D19+HISTOJUIL23!D19+HISTOAOUT23!D19+HISTOSEPT23!D19+HISTOOCT23!D19+HISTONOV23!D19+HISTODEC23!D19 -> 740000 | E19: =HISTOJANV23!E19+HISTOFEV23!E19+HISTOMARS23!E19+HISTOAVRIL23!E19+HISTOMAI23!E19+HISTOJUIN23!E19+HISTOJUIL23!E19+HISTOAOUT23!E19+HISTOSEPT23!E19+HISTOOCT23!E19+HISTONOV23!E19+HISTODEC23!E19 -> 40000 | F19: =HISTOJANV23!F19+HISTOFEV23!F19+HISTOMARS23!F19+HISTOAVRIL23!F19+HISTOMAI23!F19+HISTOJUIN23!F19+HISTOJUIL23!F19+HISTOAOUT23!F19+HISTOSEPT23!F19+HISTOOCT23!F19+HISTONOV23!F19+HISTODEC23!F19 -> 70000 | G19: =HISTOJANV23!G19+HISTOFEV23!G19+HISTOMARS23!G19+HISTOAVRIL23!G19+HISTOMAI23!G19+HISTOJUIN23!G19+HISTOJUIL23!G19+HISTOAOUT23!G19+HISTOSEPT23!G19+HISTOOCT23!G19+HISTONOV23!G19+HISTODEC23!G19 -> 0 | H19: =IF($D19<>0,"BANQUE",IF($E19<>0,"ESPECES","ECHEC")) -> BANQUE | I19: =HISTOJANV23!I19+HISTOFEV23!I19+HISTOMARS23!I19+HISTOAVRIL23!I19+HISTOMAI23!I19+HISTOJUIN23!I19+HISTOJUIL23!I19+HISTOAOUT23!I19+HISTOSEPT23!I19+HISTOOCT23!I19+HISTONOV23!I19+HISTODEC23!I19 -> 0 | J19: =HISTOJANV23!J19+HISTOFEV23!J19+HISTOMARS23!J19+HISTOAVRIL23!J19+HISTOMAI23!J19+HISTOJUIN23!J19+HISTOJUIL23!J19+HISTOAOUT23!J19+HISTOSEPT23!J19+HISTOOCT23!J19+HISTONOV23!J19+HISTODEC23!J19 -> 12 | K19: =HISTOJANV23!K19+HISTOFEV23!K19+HISTOMARS23!K19+HISTOAVRIL23!K19+HISTOMAI23!K19+HISTOJUIN23!K19+HISTOJUIL23!K19+HISTOAOUT23!K19+HISTOSEPT23!K19+HISTOOCT23!K19+HISTONOV23!K19+HISTODEC23!K19 -> 480000 | L19: =HISTOJANV23!L19+HISTOFEV23!L19+HISTOMARS23!L19+HISTOAVRIL23!L19+HISTOMAI23!L19+HISTOJUIN23!L19+HISTOJUIL23!L19+HISTOAOUT23!L19+HISTOSEPT23!L19+HISTOOCT23!L19+HISTONOV23!L19+HISTODEC23!L19 -> 0 | M19: =HISTOJANV23!M19+HISTOFEV23!M19+HISTOMARS23!M19+HISTOAVRIL23!M19+HISTOMAI23!M19+HISTOJUIN23!M19+HISTOJUIL23!M19+HISTOAOUT23!M19+HISTOSEPT23!M19+HISTOOCT23!M19+HISTONOV23!M19+HISTODEC23!M19 -> 0 | N19: =HISTOJANV23!N19+HISTOFEV23!N19+HISTOMARS23!N19+HISTOAVRIL23!N19+HISTOMAI23!N19+HISTOJUIN23!N19+HISTOJUIL23!N19+HISTOAOUT23!N19+HISTOSEPT23!N19+HISTOOCT23!N19+HISTONOV23!N19+HISTODEC23!N19 -> 0 | O19: =HISTOJANV23!O19+HISTOFEV23!O19+HISTOMARS23!O19+HISTOAVRIL23!O19+HISTOMAI23!O19+HISTOJUIN23!O19+HISTOJUIL23!O19+HISTOAOUT23!O19+HISTOSEPT23!O19+HISTOOCT23!O19+HISTONOV23!O19+HISTODEC23!O19 -> 0 | P19: =HISTOJANV23!P19+HISTOFEV23!P19+HISTOMARS23!P19+HISTOAVRIL23!P19+HISTOMAI23!P19+HISTOJUIN23!P19+HISTOJUIL23!P19+HISTOAOUT23!P19+HISTOSEPT23!P19+HISTOOCT23!P19+HISTONOV23!P19+HISTODEC23!P19 -> 0 | ... T19: =HISTOJANV23!T19+HISTOFEV23!T19+HISTOMARS23!T19+HISTOAVRIL23!T19+HISTOMAI23!T19+HISTOJUIN23!T19+HISTOJUIL23!T19+HISTOAOUT23!T19+HISTOSEPT23!T19+HISTOOCT23!T19+HISTONOV23!T19+HISTODEC23!T19 -> #VALUE! | U19: =G19+S19++R19+P19+O19+M19+I19+K19+Q19+V19+W19 -> 1800000 | V19: =HISTOJANV23!V19+HISTOFEV23!V19+HISTOMARS23!V19+HISTOAVRIL23!V19+HISTOMAI23!V19+HISTOJUIN23!V19+HISTOJUIL23!V19+HISTOAOUT23!V19+HISTOSEPT23!V19+HISTOOCT23!V19+HISTONOV23!V19+HISTODEC23!V19 -> 20000 | W19: =HISTOJANV23!W19+HISTOFEV23!W19+HISTOMARS23!W19+HISTOAVRIL23!W19+HISTOMAI23!W19+HISTOJUIN23!W19+HISTOJUIL23!W19+HISTOAOUT23!W19+HISTOSEPT23!W19+HISTOOCT23!W19+HISTONOV23!W19+HISTODEC23!W19 -> 0 | X19: =HISTOJANV23!X19+HISTOFEV23!X19+HISTOMARS23!X19+HISTOAVRIL23!X19+HISTOMAI23!X19+HISTOJUIN23!X19+HISTOJUIL23!X19+HISTOAOUT23!X19+HISTOSEPT23!X19+HISTOOCT23!X19+HISTONOV23!X19+HISTODEC23!X19 -> 0 | Y19: =HISTOJANV23!Y19+HISTOFEV23!Y19+HISTOMARS23!Y19+HISTOAVRIL23!Y19+HISTOMAI23!Y19+HISTOJUIN23!Y19+HISTOJUIL23!Y19+HISTOAOUT23!Y19+HISTOSEPT23!Y19+HISTOOCT23!Y19+HISTONOV23!Y19+HISTODEC23!Y19 -> 0 | Z19: =HISTOJANV23!Z19+HISTOFEV23!Z19+HISTOMARS23!Z19+HISTOAVRIL23!Z19+HISTOMAI23!Z19+HISTOJUIN23!Z19+HISTOJUIL23!Z19+HISTOAOUT23!Z19+HISTOSEPT23!Z19+HISTOOCT23!Z19+HISTONOV23!Z19+HISTODEC23!Z19 -> 300000 | AA19: =HISTOJANV23!AA19+HISTOFEV23!AA19+HISTOMARS23!AA19+HISTOAVRIL23!AA19+HISTOMAI23!AA19+HISTOJUIN23!AA19+HISTOJUIL23!AA19+HISTOAOUT23!AA19+HISTOSEPT23!AA19+HISTOOCT23!AA19+HISTONOV23!AA19+HISTODEC23!AA19 -> #VALUE! | AB19: =HISTOJANV23!AB19+HISTOFEV23!AB19+HISTOMARS23!AB19+HISTOAVRIL23!AB19+HISTOMAI23!AB19+HISTOJUIN23!AB19+HISTOJUIL23!AB19+HISTOAOUT23!AB19+HISTOSEPT23!AB19+HISTOOCT23!AB19+HISTONOV23!AB19+HISTODEC23!AB19 -> 0 | AC19: =HISTOJANV23!AC19+HISTOFEV23!AC19+HISTOMARS23!AC19+HISTOAVRIL23!AC19+HISTOMAI23!AC19+HISTOJUIN23!AC19+HISTOJUIL23!AC19+HISTOAOUT23!AC19+HISTOSEPT23!AC19+HISTOOCT23!AC19+HISTONOV23!AC19+HISTODEC23!AC19 -> 3000 | ... BM19: =HISTOJANV23!BM19+HISTOFEV23!BM19+HISTOMARS23!BM19+HISTOAVRIL23!BM19+HISTOMAI23!BM19+HISTOJUIN23!BM19+HISTOJUIL23!BM19+HISTOAOUT23!BM19+HISTOSEPT23!BM19+HISTOOCT23!BM19+HISTONOV23!BM19+HISTODEC23!BM19 -> 0 | BN19: ACHAT LAPTOP | BO19: PENALITE VERSEMENT ESPECES | BP19: =HISTOJANV23!BP19+HISTOFEV23!BP19+HISTOMARS23!BP19+HISTOAVRIL23!BP19+HISTOMAI23!BP19+HISTOJUIN23!BP19+HISTOJUIL23!BP19+HISTOAOUT23!BP19+HISTOSEPT23!BP19+HISTOOCT23!BP19+HISTONOV23!BP19+HISTODEC23!BP19 -> 0
A20: AS201649 | B20: =VLOOKUP(A20,[17]LISTADHERENT!A$5:H$39,3,0) -> MBOGNING TUGMA GUY | C20: =HISTOJANV23!C20+HISTOFEV23!C20+HISTOMARS23!C20+HISTOAVRIL23!C20+HISTOMAI23!C20+HISTOJUIN23!C20+HISTOJUIL23!C20+HISTOAOUT23!C20+HISTOSEPT23!C20+HISTOOCT23!C20+HISTONOV23!C20+HISTODEC23!C20 -> 93000 | D20: =HISTOJANV23!D20+HISTOFEV23!D20+HISTOMARS23!D20+HISTOAVRIL23!D20+HISTOMAI23!D20+HISTOJUIN23!D20+HISTOJUIL23!D20+HISTOAOUT23!D20+HISTOSEPT23!D20+HISTOOCT23!D20+HISTONOV23!D20+HISTODEC23!D20 -> 5010500 | E20: =HISTOJANV23!E20+HISTOFEV23!E20+HISTOMARS23!E20+HISTOAVRIL23!E20+HISTOMAI23!E20+HISTOJUIN23!E20+HISTOJUIL23!E20+HISTOAOUT23!E20+HISTOSEPT23!E20+HISTOOCT23!E20+HISTONOV23!E20+HISTODEC23!E20 -> 2044000 | F20: =HISTOJANV23!F20+HISTOFEV23!F20+HISTOMARS23!F20+HISTOAVRIL23!F20+HISTOMAI23!F20+HISTOJUIN23!F20+HISTOJUIL23!F20+HISTOAOUT23!F20+HISTOSEPT23!F20+HISTOOCT23!F20+HISTONOV23!F20+HISTODEC23!F20 -> 0 | G20: =HISTOJANV23!G20+HISTOFEV23!G20+HISTOMARS23!G20+HISTOAVRIL23!G20+HISTOMAI23!G20+HISTOJUIN23!G20+HISTOJUIL23!G20+HISTOAOUT23!G20+HISTOSEPT23!G20+HISTOOCT23!G20+HISTONOV23!G20+HISTODEC23!G20 -> 0 | H20: =IF($D20<>0,"BANQUE",IF($E20<>0,"ESPECES","ECHEC")) -> BANQUE | I20: =HISTOJANV23!I20+HISTOFEV23!I20+HISTOMARS23!I20+HISTOAVRIL23!I20+HISTOMAI23!I20+HISTOJUIN23!I20+HISTOJUIL23!I20+HISTOAOUT23!I20+HISTOSEPT23!I20+HISTOOCT23!I20+HISTONOV23!I20+HISTODEC23!I20 -> 500 | J20: =HISTOJANV23!J20+HISTOFEV23!J20+HISTOMARS23!J20+HISTOAVRIL23!J20+HISTOMAI23!J20+HISTOJUIN23!J20+HISTOJUIL23!J20+HISTOAOUT23!J20+HISTOSEPT23!J20+HISTOOCT23!J20+HISTONOV23!J20+HISTODEC23!J20 -> 12 | K20: =HISTOJANV23!K20+HISTOFEV23!K20+HISTOMARS23!K20+HISTOAVRIL23!K20+HISTOMAI23!K20+HISTOJUIN23!K20+HISTOJUIL23!K20+HISTOAOUT23!K20+HISTOSEPT23!K20+HISTOOCT23!K20+HISTONOV23!K20+HISTODEC23!K20 -> 480000 | L20: =HISTOJANV23!L20+HISTOFEV23!L20+HISTOMARS23!L20+HISTOAVRIL23!L20+HISTOMAI23!L20+HISTOJUIN23!L20+HISTOJUIL23!L20+HISTOAOUT23!L20+HISTOSEPT23!L20+HISTOOCT23!L20+HISTONOV23!L20+HISTODEC23!L20 -> 12 | M20: =HISTOJANV23!M20+HISTOFEV23!M20+HISTOMARS23!M20+HISTOAVRIL23!M20+HISTOMAI23!M20+HISTOJUIN23!M20+HISTOJUIL23!M20+HISTOAOUT23!M20+HISTOSEPT23!M20+HISTOOCT23!M20+HISTONOV23!M20+HISTODEC23!M20 -> 900000 | N20: =HISTOJANV23!N20+HISTOFEV23!N20+HISTOMARS23!N20+HISTOAVRIL23!N20+HISTOMAI23!N20+HISTOJUIN23!N20+HISTOJUIL23!N20+HISTOAOUT23!N20+HISTOSEPT23!N20+HISTOOCT23!N20+HISTONOV23!N20+HISTODEC23!N20 -> 12 | O20: =HISTOJANV23!O20+HISTOFEV23!O20+HISTOMARS23!O20+HISTOAVRIL23!O20+HISTOMAI23!O20+HISTOJUIN23!O20+HISTOJUIL23!O20+HISTOAOUT23!O20+HISTOSEPT23!O20+HISTOOCT23!O20+HISTONOV23!O20+HISTODEC23!O20 -> 1200000 | P20: =HISTOJANV23!P20+HISTOFEV23!P20+HISTOMARS23!P20+HISTOAVRIL23!P20+HISTOMAI23!P20+HISTOJUIN23!P20+HISTOJUIL23!P20+HISTOAOUT23!P20+HISTOSEPT23!P20+HISTOOCT23!P20+HISTONOV23!P20+HISTODEC23!P20 -> 124000 | ... T20: =HISTOJANV23!T20+HISTOFEV23!T20+HISTOMARS23!T20+HISTOAVRIL23!T20+HISTOMAI23!T20+HISTOJUIN23!T20+HISTOJUIL23!T20+HISTOAOUT23!T20+HISTOSEPT23!T20+HISTOOCT23!T20+HISTONOV23!T20+HISTODEC23!T20 -> #VALUE! | U20: =G20+S20++R20+P20+O20+M20+I20+K20+Q20+V20+W20 -> 6108000 | V20: =HISTOJANV23!V20+HISTOFEV23!V20+HISTOMARS23!V20+HISTOAVRIL23!V20+HISTOMAI23!V20+HISTOJUIN23!V20+HISTOJUIL23!V20+HISTOAOUT23!V20+HISTOSEPT23!V20+HISTOOCT23!V20+HISTONOV23!V20+HISTODEC23!V20 -> 0 | W20: =HISTOJANV23!W20+HISTOFEV23!W20+HISTOMARS23!W20+HISTOAVRIL23!W20+HISTOMAI23!W20+HISTOJUIN23!W20+HISTOJUIL23!W20+HISTOAOUT23!W20+HISTOSEPT23!W20+HISTOOCT23!W20+HISTONOV23!W20+HISTODEC23!W20 -> 0 | X20: =HISTOJANV23!X20+HISTOFEV23!X20+HISTOMARS23!X20+HISTOAVRIL23!X20+HISTOMAI23!X20+HISTOJUIN23!X20+HISTOJUIL23!X20+HISTOAOUT23!X20+HISTOSEPT23!X20+HISTOOCT23!X20+HISTONOV23!X20+HISTODEC23!X20 -> 0 | Y20: =HISTOJANV23!Y20+HISTOFEV23!Y20+HISTOMARS23!Y20+HISTOAVRIL23!Y20+HISTOMAI23!Y20+HISTOJUIN23!Y20+HISTOJUIL23!Y20+HISTOAOUT23!Y20+HISTOSEPT23!Y20+HISTOOCT23!Y20+HISTONOV23!Y20+HISTODEC23!Y20 -> 0 | Z20: =HISTOJANV23!Z20+HISTOFEV23!Z20+HISTOMARS23!Z20+HISTOAVRIL23!Z20+HISTOMAI23!Z20+HISTOJUIN23!Z20+HISTOJUIL23!Z20+HISTOAOUT23!Z20+HISTOSEPT23!Z20+HISTOOCT23!Z20+HISTONOV23!Z20+HISTODEC23!Z20 -> 1000000 | AA20: =HISTOJANV23!AA20+HISTOFEV23!AA20+HISTOMARS23!AA20+HISTOAVRIL23!AA20+HISTOMAI23!AA20+HISTOJUIN23!AA20+HISTOJUIL23!AA20+HISTOAOUT23!AA20+HISTOSEPT23!AA20+HISTOOCT23!AA20+HISTONOV23!AA20+HISTODEC23!AA20 -> #VALUE! | AB20: =HISTOJANV23!AB20+HISTOFEV23!AB20+HISTOMARS23!AB20+HISTOAVRIL23!AB20+HISTOMAI23!AB20+HISTOJUIN23!AB20+HISTOJUIL23!AB20+HISTOAOUT23!AB20+HISTOSEPT23!AB20+HISTOOCT23!AB20+HISTONOV23!AB20+HISTODEC23!AB20 -> 0 | AC20: =HISTOJANV23!AC20+HISTOFEV23!AC20+HISTOMARS23!AC20+HISTOAVRIL23!AC20+HISTOMAI23!AC20+HISTOJUIN23!AC20+HISTOJUIL23!AC20+HISTOAOUT23!AC20+HISTOSEPT23!AC20+HISTOOCT23!AC20+HISTONOV23!AC20+HISTODEC23!AC20 -> 11000 | ... BM20: =HISTOJANV23!BM20+HISTOFEV23!BM20+HISTOMARS23!BM20+HISTOAVRIL23!BM20+HISTOMAI23!BM20+HISTOJUIN23!BM20+HISTOJUIL23!BM20+HISTOAOUT23!BM20+HISTOSEPT23!BM20+HISTOOCT23!BM20+HISTONOV23!BM20+HISTODEC23!BM20 -> 0
A21: AS201639 | B21: =VLOOKUP(A21,[17]LISTADHERENT!A$5:H$39,3,0) -> NANGUEN MARTIN | C21: =HISTOJANV23!C21+HISTOFEV23!C21+HISTOMARS23!C21+HISTOAVRIL23!C21+HISTOMAI23!C21+HISTOJUIN23!C21+HISTOJUIL23!C21+HISTOAOUT23!C21+HISTOSEPT23!C21+HISTOOCT23!C21+HISTONOV23!C21+HISTODEC23!C21 -> 0 | D21: =HISTOJANV23!D21+HISTOFEV23!D21+HISTOMARS23!D21+HISTOAVRIL23!D21+HISTOMAI23!D21+HISTOJUIN23!D21+HISTOJUIL23!D21+HISTOAOUT23!D21+HISTOSEPT23!D21+HISTOOCT23!D21+HISTONOV23!D21+HISTODEC23!D21 -> 980000 | E21: =HISTOJANV23!E21+HISTOFEV23!E21+HISTOMARS23!E21+HISTOAVRIL23!E21+HISTOMAI23!E21+HISTOJUIN23!E21+HISTOJUIL23!E21+HISTOAOUT23!E21+HISTOSEPT23!E21+HISTOOCT23!E21+HISTONOV23!E21+HISTODEC23!E21 -> 0 | F21: =HISTOJANV23!F21+HISTOFEV23!F21+HISTOMARS23!F21+HISTOAVRIL23!F21+HISTOMAI23!F21+HISTOJUIN23!F21+HISTOJUIL23!F21+HISTOAOUT23!F21+HISTOSEPT23!F21+HISTOOCT23!F21+HISTONOV23!F21+HISTODEC23!F21 -> 70000 | G21: =HISTOJANV23!G21+HISTOFEV23!G21+HISTOMARS23!G21+HISTOAVRIL23!G21+HISTOMAI23!G21+HISTOJUIN23!G21+HISTOJUIL23!G21+HISTOAOUT23!G21+HISTOSEPT23!G21+HISTOOCT23!G21+HISTONOV23!G21+HISTODEC23!G21 -> 0 | H21: =IF($D21<>0,"BANQUE",IF($E21<>0,"ESPECES","ECHEC")) -> BANQUE | I21: =HISTOJANV23!I21+HISTOFEV23!I21+HISTOMARS23!I21+HISTOAVRIL23!I21+HISTOMAI23!I21+HISTOJUIN23!I21+HISTOJUIL23!I21+HISTOAOUT23!I21+HISTOSEPT23!I21+HISTOOCT23!I21+HISTONOV23!I21+HISTODEC23!I21 -> 0 | J21: =HISTOJANV23!J21+HISTOFEV23!J21+HISTOMARS23!J21+HISTOAVRIL23!J21+HISTOMAI23!J21+HISTOJUIN23!J21+HISTOJUIL23!J21+HISTOAOUT23!J21+HISTOSEPT23!J21+HISTOOCT23!J21+HISTONOV23!J21+HISTODEC23!J21 -> 12 | K21: =HISTOJANV23!K21+HISTOFEV23!K21+HISTOMARS23!K21+HISTOAVRIL23!K21+HISTOMAI23!K21+HISTOJUIN23!K21+HISTOJUIL23!K21+HISTOAOUT23!K21+HISTOSEPT23!K21+HISTOOCT23!K21+HISTONOV23!K21+HISTODEC23!K21 -> 480000 | L21: =HISTOJANV23!L21+HISTOFEV23!L21+HISTOMARS23!L21+HISTOAVRIL23!L21+HISTOMAI23!L21+HISTOJUIN23!L21+HISTOJUIL23!L21+HISTOAOUT23!L21+HISTOSEPT23!L21+HISTOOCT23!L21+HISTONOV23!L21+HISTODEC23!L21 -> 0 | M21: =HISTOJANV23!M21+HISTOFEV23!M21+HISTOMARS23!M21+HISTOAVRIL23!M21+HISTOMAI23!M21+HISTOJUIN23!M21+HISTOJUIL23!M21+HISTOAOUT23!M21+HISTOSEPT23!M21+HISTOOCT23!M21+HISTONOV23!M21+HISTODEC23!M21 -> 0 | N21: =HISTOJANV23!N21+HISTOFEV23!N21+HISTOMARS23!N21+HISTOAVRIL23!N21+HISTOMAI23!N21+HISTOJUIN23!N21+HISTOJUIL23!N21+HISTOAOUT23!N21+HISTOSEPT23!N21+HISTOOCT23!N21+HISTONOV23!N21+HISTODEC23!N21 -> 0 | O21: =HISTOJANV23!O21+HISTOFEV23!O21+HISTOMARS23!O21+HISTOAVRIL23!O21+HISTOMAI23!O21+HISTOJUIN23!O21+HISTOJUIL23!O21+HISTOAOUT23!O21+HISTOSEPT23!O21+HISTOOCT23!O21+HISTONOV23!O21+HISTODEC23!O21 -> 0 | P21: =HISTOJANV23!P21+HISTOFEV23!P21+HISTOMARS23!P21+HISTOAVRIL23!P21+HISTOMAI23!P21+HISTOJUIN23!P21+HISTOJUIL23!P21+HISTOAOUT23!P21+HISTOSEPT23!P21+HISTOOCT23!P21+HISTONOV23!P21+HISTODEC23!P21 -> 0 | ... T21: =HISTOJANV23!T21+HISTOFEV23!T21+HISTOMARS23!T21+HISTOAVRIL23!T21+HISTOMAI23!T21+HISTOJUIN23!T21+HISTOJUIL23!T21+HISTOAOUT23!T21+HISTOSEPT23!T21+HISTOOCT23!T21+HISTONOV23!T21+HISTODEC23!T21 -> #VALUE! | U21: =G21+S21++R21+P21+O21+M21+I21+K21+Q21+V21+W21 -> 980000 | V21: =HISTOJANV23!V21+HISTOFEV23!V21+HISTOMARS23!V21+HISTOAVRIL23!V21+HISTOMAI23!V21+HISTOJUIN23!V21+HISTOJUIL23!V21+HISTOAOUT23!V21+HISTOSEPT23!V21+HISTOOCT23!V21+HISTONOV23!V21+HISTODEC23!V21 -> 0 | W21: =HISTOJANV23!W21+HISTOFEV23!W21+HISTOMARS23!W21+HISTOAVRIL23!W21+HISTOMAI23!W21+HISTOJUIN23!W21+HISTOJUIL23!W21+HISTOAOUT23!W21+HISTOSEPT23!W21+HISTOOCT23!W21+HISTONOV23!W21+HISTODEC23!W21 -> 0 | X21: =HISTOJANV23!X21+HISTOFEV23!X21+HISTOMARS23!X21+HISTOAVRIL23!X21+HISTOMAI23!X21+HISTOJUIN23!X21+HISTOJUIL23!X21+HISTOAOUT23!X21+HISTOSEPT23!X21+HISTOOCT23!X21+HISTONOV23!X21+HISTODEC23!X21 -> 0 | Y21: =HISTOJANV23!Y21+HISTOFEV23!Y21+HISTOMARS23!Y21+HISTOAVRIL23!Y21+HISTOMAI23!Y21+HISTOJUIN23!Y21+HISTOJUIL23!Y21+HISTOAOUT23!Y21+HISTOSEPT23!Y21+HISTOOCT23!Y21+HISTONOV23!Y21+HISTODEC23!Y21 -> 0 | Z21: =HISTOJANV23!Z21+HISTOFEV23!Z21+HISTOMARS23!Z21+HISTOAVRIL23!Z21+HISTOMAI23!Z21+HISTOJUIN23!Z21+HISTOJUIL23!Z21+HISTOAOUT23!Z21+HISTOSEPT23!Z21+HISTOOCT23!Z21+HISTONOV23!Z21+HISTODEC23!Z21 -> 300000 | AA21: =HISTOJANV23!AA21+HISTOFEV23!AA21+HISTOMARS23!AA21+HISTOAVRIL23!AA21+HISTOMAI23!AA21+HISTOJUIN23!AA21+HISTOJUIL23!AA21+HISTOAOUT23!AA21+HISTOSEPT23!AA21+HISTOOCT23!AA21+HISTONOV23!AA21+HISTODEC23!AA21 -> #VALUE! | AB21: =HISTOJANV23!AB21+HISTOFEV23!AB21+HISTOMARS23!AB21+HISTOAVRIL23!AB21+HISTOMAI23!AB21+HISTOJUIN23!AB21+HISTOJUIL23!AB21+HISTOAOUT23!AB21+HISTOSEPT23!AB21+HISTOOCT23!AB21+HISTONOV23!AB21+HISTODEC23!AB21 -> 0 | AC21: =HISTOJANV23!AC21+HISTOFEV23!AC21+HISTOMARS23!AC21+HISTOAVRIL23!AC21+HISTOMAI23!AC21+HISTOJUIN23!AC21+HISTOJUIL23!AC21+HISTOAOUT23!AC21+HISTOSEPT23!AC21+HISTOOCT23!AC21+HISTONOV23!AC21+HISTODEC23!AC21 -> 2500 | ... BM21: =HISTOJANV23!BM21+HISTOFEV23!BM21+HISTOMARS23!BM21+HISTOAVRIL23!BM21+HISTOMAI23!BM21+HISTOJUIN23!BM21+HISTOJUIL23!BM21+HISTOAOUT23!BM21+HISTOSEPT23!BM21+HISTOOCT23!BM21+HISTONOV23!BM21+HISTODEC23!BM21 -> 0
A22: AS201621 | B22: =VLOOKUP(A22,[17]LISTADHERENT!A$5:H$39,3,0) -> NANKAM APPOLINAIRE | C22: =HISTOJANV23!C22+HISTOFEV23!C22+HISTOMARS23!C22+HISTOAVRIL23!C22+HISTOMAI23!C22+HISTOJUIN23!C22+HISTOJUIL23!C22+HISTOAOUT23!C22+HISTOSEPT23!C22+HISTOOCT23!C22+HISTONOV23!C22+HISTODEC23!C22 -> 0 | D22: =HISTOJANV23!D22+HISTOFEV23!D22+HISTOMARS23!D22+HISTOAVRIL23!D22+HISTOMAI23!D22+HISTOJUIN23!D22+HISTOJUIL23!D22+HISTOAOUT23!D22+HISTOSEPT23!D22+HISTOOCT23!D22+HISTONOV23!D22+HISTODEC23!D22 -> 1487500 | E22: =HISTOJANV23!E22+HISTOFEV23!E22+HISTOMARS23!E22+HISTOAVRIL23!E22+HISTOMAI23!E22+HISTOJUIN23!E22+HISTOJUIL23!E22+HISTOAOUT23!E22+HISTOSEPT23!E22+HISTOOCT23!E22+HISTONOV23!E22+HISTODEC23!E22 -> 0 | F22: =HISTOJANV23!F22+HISTOFEV23!F22+HISTOMARS23!F22+HISTOAVRIL23!F22+HISTOMAI23!F22+HISTOJUIN23!F22+HISTOJUIL23!F22+HISTOAOUT23!F22+HISTOSEPT23!F22+HISTOOCT23!F22+HISTONOV23!F22+HISTODEC23!F22 -> 962500 | G22: =HISTOJANV23!G22+HISTOFEV23!G22+HISTOMARS23!G22+HISTOAVRIL23!G22+HISTOMAI23!G22+HISTOJUIN23!G22+HISTOJUIL23!G22+HISTOAOUT23!G22+HISTOSEPT23!G22+HISTOOCT23!G22+HISTONOV23!G22+HISTODEC23!G22 -> 0 | H22: =IF($D22<>0,"BANQUE",IF($E22<>0,"ESPECES","ECHEC")) -> BANQUE | I22: =HISTOJANV23!I22+HISTOFEV23!I22+HISTOMARS23!I22+HISTOAVRIL23!I22+HISTOMAI23!I22+HISTOJUIN23!I22+HISTOJUIL23!I22+HISTOAOUT23!I22+HISTOSEPT23!I22+HISTOOCT23!I22+HISTONOV23!I22+HISTODEC23!I22 -> 0 | J22: =HISTOJANV23!J22+HISTOFEV23!J22+HISTOMARS23!J22+HISTOAVRIL23!J22+HISTOMAI23!J22+HISTOJUIN23!J22+HISTOJUIL23!J22+HISTOAOUT23!J22+HISTOSEPT23!J22+HISTOOCT23!J22+HISTONOV23!J22+HISTODEC23!J22 -> 12 | K22: =HISTOJANV23!K22+HISTOFEV23!K22+HISTOMARS23!K22+HISTOAVRIL23!K22+HISTOMAI23!K22+HISTOJUIN23!K22+HISTOJUIL23!K22+HISTOAOUT23!K22+HISTOSEPT23!K22+HISTOOCT23!K22+HISTONOV23!K22+HISTODEC23!K22 -> 480000 | L22: =HISTOJANV23!L22+HISTOFEV23!L22+HISTOMARS23!L22+HISTOAVRIL23!L22+HISTOMAI23!L22+HISTOJUIN23!L22+HISTOJUIL23!L22+HISTOAOUT23!L22+HISTOSEPT23!L22+HISTOOCT23!L22+HISTONOV23!L22+HISTODEC23!L22 -> 12 | M22: =HISTOJANV23!M22+HISTOFEV23!M22+HISTOMARS23!M22+HISTOAVRIL23!M22+HISTOMAI23!M22+HISTOJUIN23!M22+HISTOJUIL23!M22+HISTOAOUT23!M22+HISTOSEPT23!M22+HISTOOCT23!M22+HISTONOV23!M22+HISTODEC23!M22 -> 900000 | N22: =HISTOJANV23!N22+HISTOFEV23!N22+HISTOMARS23!N22+HISTOAVRIL23!N22+HISTOMAI23!N22+HISTOJUIN23!N22+HISTOJUIL23!N22+HISTOAOUT23!N22+HISTOSEPT23!N22+HISTOOCT23!N22+HISTONOV23!N22+HISTODEC23!N22 -> 0 | O22: =HISTOJANV23!O22+HISTOFEV23!O22+HISTOMARS23!O22+HISTOAVRIL23!O22+HISTOMAI23!O22+HISTOJUIN23!O22+HISTOJUIL23!O22+HISTOAOUT23!O22+HISTOSEPT23!O22+HISTOOCT23!O22+HISTONOV23!O22+HISTODEC23!O22 -> 0 | P22: =HISTOJANV23!P22+HISTOFEV23!P22+HISTOMARS23!P22+HISTOAVRIL23!P22+HISTOMAI23!P22+HISTOJUIN23!P22+HISTOJUIL23!P22+HISTOAOUT23!P22+HISTOSEPT23!P22+HISTOOCT23!P22+HISTONOV23!P22+HISTODEC23!P22 -> 0 | ... T22: =HISTOJANV23!T22+HISTOFEV23!T22+HISTOMARS23!T22+HISTOAVRIL23!T22+HISTOMAI23!T22+HISTOJUIN23!T22+HISTOJUIL23!T22+HISTOAOUT23!T22+HISTOSEPT23!T22+HISTOOCT23!T22+HISTONOV23!T22+HISTODEC23!T22 -> #VALUE! | U22: =G22+S22++R22+P22+O22+M22+I22+K22+Q22+V22+W22 -> 2400000 | V22: =HISTOJANV23!V22+HISTOFEV23!V22+HISTOMARS23!V22+HISTOAVRIL23!V22+HISTOMAI23!V22+HISTOJUIN23!V22+HISTOJUIL23!V22+HISTOAOUT23!V22+HISTOSEPT23!V22+HISTOOCT23!V22+HISTONOV23!V22+HISTODEC23!V22 -> 20000 | W22: =HISTOJANV23!W22+HISTOFEV23!W22+HISTOMARS23!W22+HISTOAVRIL23!W22+HISTOMAI23!W22+HISTOJUIN23!W22+HISTOJUIL23!W22+HISTOAOUT23!W22+HISTOSEPT23!W22+HISTOOCT23!W22+HISTONOV23!W22+HISTODEC23!W22 -> 0 | X22: =HISTOJANV23!X22+HISTOFEV23!X22+HISTOMARS23!X22+HISTOAVRIL23!X22+HISTOMAI23!X22+HISTOJUIN23!X22+HISTOJUIL23!X22+HISTOAOUT23!X22+HISTOSEPT23!X22+HISTOOCT23!X22+HISTONOV23!X22+HISTODEC23!X22 -> 0 | Y22: =HISTOJANV23!Y22+HISTOFEV23!Y22+HISTOMARS23!Y22+HISTOAVRIL23!Y22+HISTOMAI23!Y22+HISTOJUIN23!Y22+HISTOJUIL23!Y22+HISTOAOUT23!Y22+HISTOSEPT23!Y22+HISTOOCT23!Y22+HISTONOV23!Y22+HISTODEC23!Y22 -> 0 | Z22: =HISTOJANV23!Z22+HISTOFEV23!Z22+HISTOMARS23!Z22+HISTOAVRIL23!Z22+HISTOMAI23!Z22+HISTOJUIN23!Z22+HISTOJUIL23!Z22+HISTOAOUT23!Z22+HISTOSEPT23!Z22+HISTOOCT23!Z22+HISTONOV23!Z22+HISTODEC23!Z22 -> 1000000 | AA22: =HISTOJANV23!AA22+HISTOFEV23!AA22+HISTOMARS23!AA22+HISTOAVRIL23!AA22+HISTOMAI23!AA22+HISTOJUIN23!AA22+HISTOJUIL23!AA22+HISTOAOUT23!AA22+HISTOSEPT23!AA22+HISTOOCT23!AA22+HISTONOV23!AA22+HISTODEC23!AA22 -> #VALUE! | AB22: =HISTOJANV23!AB22+HISTOFEV23!AB22+HISTOMARS23!AB22+HISTOAVRIL23!AB22+HISTOMAI23!AB22+HISTOJUIN23!AB22+HISTOJUIL23!AB22+HISTOAOUT23!AB22+HISTOSEPT23!AB22+HISTOOCT23!AB22+HISTONOV23!AB22+HISTODEC23!AB22 -> 0 | AC22: =HISTOJANV23!AC22+HISTOFEV23!AC22+HISTOMARS23!AC22+HISTOAVRIL23!AC22+HISTOMAI23!AC22+HISTOJUIN23!AC22+HISTOJUIL23!AC22+HISTOAOUT23!AC22+HISTOSEPT23!AC22+HISTOOCT23!AC22+HISTONOV23!AC22+HISTODEC23!AC22 -> 4500 | ... BM22: =HISTOJANV23!BM22+HISTOFEV23!BM22+HISTOMARS23!BM22+HISTOAVRIL23!BM22+HISTOMAI23!BM22+HISTOJUIN23!BM22+HISTOJUIL23!BM22+HISTOAOUT23!BM22+HISTOSEPT23!BM22+HISTOOCT23!BM22+HISTONOV23!BM22+HISTODEC23!BM22 -> 0 | BN22: S/TOTAL | BP22: =SUM(BP18:BP21) -> 200000
A23: AS201622 | B23: =VLOOKUP(A23,[17]LISTADHERENT!A$5:H$39,3,0) -> NDJOMO ETIENNE | C23: =HISTOJANV23!C23+HISTOFEV23!C23+HISTOMARS23!C23+HISTOAVRIL23!C23+HISTOMAI23!C23+HISTOJUIN23!C23+HISTOJUIL23!C23+HISTOAOUT23!C23+HISTOSEPT23!C23+HISTOOCT23!C23+HISTONOV23!C23+HISTODEC23!C23 -> -576000 | D23: =HISTOJANV23!D23+HISTOFEV23!D23+HISTOMARS23!D23+HISTOAVRIL23!D23+HISTOMAI23!D23+HISTOJUIN23!D23+HISTOJUIL23!D23+HISTOAOUT23!D23+HISTOSEPT23!D23+HISTOOCT23!D23+HISTONOV23!D23+HISTODEC23!D23 -> 4327000 | E23: =HISTOJANV23!E23+HISTOFEV23!E23+HISTOMARS23!E23+HISTOAVRIL23!E23+HISTOMAI23!E23+HISTOJUIN23!E23+HISTOJUIL23!E23+HISTOAOUT23!E23+HISTOSEPT23!E23+HISTOOCT23!E23+HISTONOV23!E23+HISTODEC23!E23 -> 0 | F23: =HISTOJANV23!F23+HISTOFEV23!F23+HISTOMARS23!F23+HISTOAVRIL23!F23+HISTOMAI23!F23+HISTOJUIN23!F23+HISTOJUIL23!F23+HISTOAOUT23!F23+HISTOSEPT23!F23+HISTOOCT23!F23+HISTONOV23!F23+HISTODEC23!F23 -> 70000 | G23: =HISTOJANV23!G23+HISTOFEV23!G23+HISTOMARS23!G23+HISTOAVRIL23!G23+HISTOMAI23!G23+HISTOJUIN23!G23+HISTOJUIL23!G23+HISTOAOUT23!G23+HISTOSEPT23!G23+HISTOOCT23!G23+HISTONOV23!G23+HISTODEC23!G23 -> 0 | H23: =IF($D23<>0,"BANQUE",IF($E23<>0,"ESPECES","ECHEC")) -> BANQUE | I23: =HISTOJANV23!I23+HISTOFEV23!I23+HISTOMARS23!I23+HISTOAVRIL23!I23+HISTOMAI23!I23+HISTOJUIN23!I23+HISTOJUIL23!I23+HISTOAOUT23!I23+HISTOSEPT23!I23+HISTOOCT23!I23+HISTONOV23!I23+HISTODEC23!I23 -> 116000 | J23: =HISTOJANV23!J23+HISTOFEV23!J23+HISTOMARS23!J23+HISTOAVRIL23!J23+HISTOMAI23!J23+HISTOJUIN23!J23+HISTOJUIL23!J23+HISTOAOUT23!J23+HISTOSEPT23!J23+HISTOOCT23!J23+HISTONOV23!J23+HISTODEC23!J23 -> 12 | K23: =HISTOJANV23!K23+HISTOFEV23!K23+HISTOMARS23!K23+HISTOAVRIL23!K23+HISTOMAI23!K23+HISTOJUIN23!K23+HISTOJUIL23!K23+HISTOAOUT23!K23+HISTOSEPT23!K23+HISTOOCT23!K23+HISTONOV23!K23+HISTODEC23!K23 -> 480000 | L23: =HISTOJANV23!L23+HISTOFEV23!L23+HISTOMARS23!L23+HISTOAVRIL23!L23+HISTOMAI23!L23+HISTOJUIN23!L23+HISTOJUIL23!L23+HISTOAOUT23!L23+HISTOSEPT23!L23+HISTOOCT23!L23+HISTONOV23!L23+HISTODEC23!L23 -> 0 | M23: =HISTOJANV23!M23+HISTOFEV23!M23+HISTOMARS23!M23+HISTOAVRIL23!M23+HISTOMAI23!M23+HISTOJUIN23!M23+HISTOJUIL23!M23+HISTOAOUT23!M23+HISTOSEPT23!M23+HISTOOCT23!M23+HISTONOV23!M23+HISTODEC23!M23 -> 0 | N23: =HISTOJANV23!N23+HISTOFEV23!N23+HISTOMARS23!N23+HISTOAVRIL23!N23+HISTOMAI23!N23+HISTOJUIN23!N23+HISTOJUIL23!N23+HISTOAOUT23!N23+HISTOSEPT23!N23+HISTOOCT23!N23+HISTONOV23!N23+HISTODEC23!N23 -> 24 | O23: =HISTOJANV23!O23+HISTOFEV23!O23+HISTOMARS23!O23+HISTOAVRIL23!O23+HISTOMAI23!O23+HISTOJUIN23!O23+HISTOJUIL23!O23+HISTOAOUT23!O23+HISTOSEPT23!O23+HISTOOCT23!O23+HISTONOV23!O23+HISTODEC23!O23 -> 2400000 | P23: =HISTOJANV23!P23+HISTOFEV23!P23+HISTOMARS23!P23+HISTOAVRIL23!P23+HISTOMAI23!P23+HISTOJUIN23!P23+HISTOJUIL23!P23+HISTOAOUT23!P23+HISTOSEPT23!P23+HISTOOCT23!P23+HISTONOV23!P23+HISTODEC23!P23 -> 0 | ... T23: =HISTOJANV23!T23+HISTOFEV23!T23+HISTOMARS23!T23+HISTOAVRIL23!T23+HISTOMAI23!T23+HISTOJUIN23!T23+HISTOJUIL23!T23+HISTOAOUT23!T23+HISTOSEPT23!T23+HISTOOCT23!T23+HISTONOV23!T23+HISTODEC23!T23 -> #VALUE! | U23: =G23+S23++R23+P23+O23+M23+I23+K23+Q23+V23+W23 -> 4903000 | V23: =HISTOJANV23!V23+HISTOFEV23!V23+HISTOMARS23!V23+HISTOAVRIL23!V23+HISTOMAI23!V23+HISTOJUIN23!V23+HISTOJUIL23!V23+HISTOAOUT23!V23+HISTOSEPT23!V23+HISTOOCT23!V23+HISTONOV23!V23+HISTODEC23!V23 -> 0 | W23: =HISTOJANV23!W23+HISTOFEV23!W23+HISTOMARS23!W23+HISTOAVRIL23!W23+HISTOMAI23!W23+HISTOJUIN23!W23+HISTOJUIL23!W23+HISTOAOUT23!W23+HISTOSEPT23!W23+HISTOOCT23!W23+HISTONOV23!W23+HISTODEC23!W23 -> 0 | X23: =HISTOJANV23!X23+HISTOFEV23!X23+HISTOMARS23!X23+HISTOAVRIL23!X23+HISTOMAI23!X23+HISTOJUIN23!X23+HISTOJUIL23!X23+HISTOAOUT23!X23+HISTOSEPT23!X23+HISTOOCT23!X23+HISTONOV23!X23+HISTODEC23!X23 -> 0 | Y23: =HISTOJANV23!Y23+HISTOFEV23!Y23+HISTOMARS23!Y23+HISTOAVRIL23!Y23+HISTOMAI23!Y23+HISTOJUIN23!Y23+HISTOJUIL23!Y23+HISTOAOUT23!Y23+HISTOSEPT23!Y23+HISTOOCT23!Y23+HISTONOV23!Y23+HISTODEC23!Y23 -> 0 | Z23: =HISTOJANV23!Z23+HISTOFEV23!Z23+HISTOMARS23!Z23+HISTOAVRIL23!Z23+HISTOMAI23!Z23+HISTOJUIN23!Z23+HISTOJUIL23!Z23+HISTOAOUT23!Z23+HISTOSEPT23!Z23+HISTOOCT23!Z23+HISTONOV23!Z23+HISTODEC23!Z23 -> 1100000 | AA23: =HISTOJANV23!AA23+HISTOFEV23!AA23+HISTOMARS23!AA23+HISTOAVRIL23!AA23+HISTOMAI23!AA23+HISTOJUIN23!AA23+HISTOJUIL23!AA23+HISTOAOUT23!AA23+HISTOSEPT23!AA23+HISTOOCT23!AA23+HISTONOV23!AA23+HISTODEC23!AA23 -> #VALUE! | AB23: =HISTOJANV23!AB23+HISTOFEV23!AB23+HISTOMARS23!AB23+HISTOAVRIL23!AB23+HISTOMAI23!AB23+HISTOJUIN23!AB23+HISTOJUIL23!AB23+HISTOAOUT23!AB23+HISTOSEPT23!AB23+HISTOOCT23!AB23+HISTONOV23!AB23+HISTODEC23!AB23 -> 0 | AC23: =HISTOJANV23!AC23+HISTOFEV23!AC23+HISTOMARS23!AC23+HISTOAVRIL23!AC23+HISTOMAI23!AC23+HISTOJUIN23!AC23+HISTOJUIL23!AC23+HISTOAOUT23!AC23+HISTOSEPT23!AC23+HISTOOCT23!AC23+HISTONOV23!AC23+HISTODEC23!AC23 -> 2500 | ... BM23: =HISTOJANV23!BM23+HISTOFEV23!BM23+HISTOMARS23!BM23+HISTOAVRIL23!BM23+HISTOMAI23!BM23+HISTOJUIN23!BM23+HISTOJUIL23!BM23+HISTOAOUT23!BM23+HISTOSEPT23!BM23+HISTOOCT23!BM23+HISTONOV23!BM23+HISTODEC23!BM23 -> 0
A24: AS201624 | B24: =VLOOKUP(A24,[17]LISTADHERENT!A$5:H$39,3,0) -> NGONDIEP CLAUDE | C24: =HISTOJANV23!C24+HISTOFEV23!C24+HISTOMARS23!C24+HISTOAVRIL23!C24+HISTOMAI23!C24+HISTOJUIN23!C24+HISTOJUIL23!C24+HISTOAOUT23!C24+HISTOSEPT23!C24+HISTOOCT23!C24+HISTONOV23!C24+HISTODEC23!C24 -> -526000 | D24: =HISTOJANV23!D24+HISTOFEV23!D24+HISTOMARS23!D24+HISTOAVRIL23!D24+HISTOMAI23!D24+HISTOJUIN23!D24+HISTOJUIL23!D24+HISTOAOUT23!D24+HISTOSEPT23!D24+HISTOOCT23!D24+HISTONOV23!D24+HISTODEC23!D24 -> 4135000 | E24: =HISTOJANV23!E24+HISTOFEV23!E24+HISTOMARS23!E24+HISTOAVRIL23!E24+HISTOMAI23!E24+HISTOJUIN23!E24+HISTOJUIL23!E24+HISTOAOUT23!E24+HISTOSEPT23!E24+HISTOOCT23!E24+HISTONOV23!E24+HISTODEC23!E24 -> 439000 | F24: =HISTOJANV23!F24+HISTOFEV23!F24+HISTOMARS23!F24+HISTOAVRIL23!F24+HISTOMAI23!F24+HISTOJUIN23!F24+HISTOJUIL23!F24+HISTOAOUT23!F24+HISTOSEPT23!F24+HISTOOCT23!F24+HISTONOV23!F24+HISTODEC23!F24 -> 70000 | G24: =HISTOJANV23!G24+HISTOFEV23!G24+HISTOMARS23!G24+HISTOAVRIL23!G24+HISTOMAI23!G24+HISTOJUIN23!G24+HISTOJUIL23!G24+HISTOAOUT23!G24+HISTOSEPT23!G24+HISTOOCT23!G24+HISTONOV23!G24+HISTODEC23!G24 -> 3000 | H24: =IF($D24<>0,"BANQUE",IF($E24<>0,"ESPECES","ECHEC")) -> BANQUE | I24: =HISTOJANV23!I24+HISTOFEV23!I24+HISTOMARS23!I24+HISTOAVRIL23!I24+HISTOMAI23!I24+HISTOJUIN23!I24+HISTOJUIL23!I24+HISTOAOUT23!I24+HISTOSEPT23!I24+HISTOOCT23!I24+HISTONOV23!I24+HISTODEC23!I24 -> 12000 | J24: =HISTOJANV23!J24+HISTOFEV23!J24+HISTOMARS23!J24+HISTOAVRIL23!J24+HISTOMAI23!J24+HISTOJUIN23!J24+HISTOJUIL23!J24+HISTOAOUT23!J24+HISTOSEPT23!J24+HISTOOCT23!J24+HISTONOV23!J24+HISTODEC23!J24 -> 12 | K24: =HISTOJANV23!K24+HISTOFEV23!K24+HISTOMARS23!K24+HISTOAVRIL23!K24+HISTOMAI23!K24+HISTOJUIN23!K24+HISTOJUIL23!K24+HISTOAOUT23!K24+HISTOSEPT23!K24+HISTOOCT23!K24+HISTONOV23!K24+HISTODEC23!K24 -> 480000 | L24: =HISTOJANV23!L24+HISTOFEV23!L24+HISTOMARS23!L24+HISTOAVRIL23!L24+HISTOMAI23!L24+HISTOJUIN23!L24+HISTOJUIL23!L24+HISTOAOUT23!L24+HISTOSEPT23!L24+HISTOOCT23!L24+HISTONOV23!L24+HISTODEC23!L24 -> 12 | M24: =HISTOJANV23!M24+HISTOFEV23!M24+HISTOMARS23!M24+HISTOAVRIL23!M24+HISTOMAI23!M24+HISTOJUIN23!M24+HISTOJUIL23!M24+HISTOAOUT23!M24+HISTOSEPT23!M24+HISTOOCT23!M24+HISTONOV23!M24+HISTODEC23!M24 -> 900000 | N24: =HISTOJANV23!N24+HISTOFEV23!N24+HISTOMARS23!N24+HISTOAVRIL23!N24+HISTOMAI23!N24+HISTOJUIN23!N24+HISTOJUIL23!N24+HISTOAOUT23!N24+HISTOSEPT23!N24+HISTOOCT23!N24+HISTONOV23!N24+HISTODEC23!N24 -> 12 | O24: =HISTOJANV23!O24+HISTOFEV23!O24+HISTOMARS23!O24+HISTOAVRIL23!O24+HISTOMAI23!O24+HISTOJUIN23!O24+HISTOJUIL23!O24+HISTOAOUT23!O24+HISTOSEPT23!O24+HISTOOCT23!O24+HISTONOV23!O24+HISTODEC23!O24 -> 1200000 | P24: =HISTOJANV23!P24+HISTOFEV23!P24+HISTOMARS23!P24+HISTOAVRIL23!P24+HISTOMAI23!P24+HISTOJUIN23!P24+HISTOJUIL23!P24+HISTOAOUT23!P24+HISTOSEPT23!P24+HISTOOCT23!P24+HISTONOV23!P24+HISTODEC23!P24 -> 148000 | ... T24: =HISTOJANV23!T24+HISTOFEV23!T24+HISTOMARS23!T24+HISTOAVRIL23!T24+HISTOMAI23!T24+HISTOJUIN23!T24+HISTOJUIL23!T24+HISTOAOUT23!T24+HISTOSEPT23!T24+HISTOOCT23!T24+HISTONOV23!T24+HISTODEC23!T24 -> #VALUE! | U24: =G24+S24++R24+P24+O24+M24+I24+K24+Q24+V24+W24 -> 5115000 | V24: =HISTOJANV23!V24+HISTOFEV23!V24+HISTOMARS23!V24+HISTOAVRIL23!V24+HISTOMAI23!V24+HISTOJUIN23!V24+HISTOJUIL23!V24+HISTOAOUT23!V24+HISTOSEPT23!V24+HISTOOCT23!V24+HISTONOV23!V24+HISTODEC23!V24 -> 15000 | W24: =HISTOJANV23!W24+HISTOFEV23!W24+HISTOMARS23!W24+HISTOAVRIL23!W24+HISTOMAI23!W24+HISTOJUIN23!W24+HISTOJUIL23!W24+HISTOAOUT23!W24+HISTOSEPT23!W24+HISTOOCT23!W24+HISTONOV23!W24+HISTODEC23!W24 -> 0 | X24: =HISTOJANV23!X24+HISTOFEV23!X24+HISTOMARS23!X24+HISTOAVRIL23!X24+HISTOMAI23!X24+HISTOJUIN23!X24+HISTOJUIL23!X24+HISTOAOUT23!X24+HISTOSEPT23!X24+HISTOOCT23!X24+HISTONOV23!X24+HISTODEC23!X24 -> 0 | Y24: =HISTOJANV23!Y24+HISTOFEV23!Y24+HISTOMARS23!Y24+HISTOAVRIL23!Y24+HISTOMAI23!Y24+HISTOJUIN23!Y24+HISTOJUIL23!Y24+HISTOAOUT23!Y24+HISTOSEPT23!Y24+HISTOOCT23!Y24+HISTONOV23!Y24+HISTODEC23!Y24 -> 0 | Z24: =HISTOJANV23!Z24+HISTOFEV23!Z24+HISTOMARS23!Z24+HISTOAVRIL23!Z24+HISTOMAI23!Z24+HISTOJUIN23!Z24+HISTOJUIL23!Z24+HISTOAOUT23!Z24+HISTOSEPT23!Z24+HISTOOCT23!Z24+HISTONOV23!Z24+HISTODEC23!Z24 -> 1000000 | AA24: =HISTOJANV23!AA24+HISTOFEV23!AA24+HISTOMARS23!AA24+HISTOAVRIL23!AA24+HISTOMAI23!AA24+HISTOJUIN23!AA24+HISTOJUIL23!AA24+HISTOAOUT23!AA24+HISTOSEPT23!AA24+HISTOOCT23!AA24+HISTONOV23!AA24+HISTODEC23!AA24 -> #VALUE! | AB24: =HISTOJANV23!AB24+HISTOFEV23!AB24+HISTOMARS23!AB24+HISTOAVRIL23!AB24+HISTOMAI23!AB24+HISTOJUIN23!AB24+HISTOJUIL23!AB24+HISTOAOUT23!AB24+HISTOSEPT23!AB24+HISTOOCT23!AB24+HISTONOV23!AB24+HISTODEC23!AB24 -> 0 | AC24: =HISTOJANV23!AC24+HISTOFEV23!AC24+HISTOMARS23!AC24+HISTOAVRIL23!AC24+HISTOMAI23!AC24+HISTOJUIN23!AC24+HISTOJUIL23!AC24+HISTOAOUT23!AC24+HISTOSEPT23!AC24+HISTOOCT23!AC24+HISTONOV23!AC24+HISTODEC23!AC24 -> 3000 | ... BM24: =HISTOJANV23!BM24+HISTOFEV23!BM24+HISTOMARS23!BM24+HISTOAVRIL23!BM24+HISTOMAI23!BM24+HISTOJUIN23!BM24+HISTOJUIL23!BM24+HISTOAOUT23!BM24+HISTOSEPT23!BM24+HISTOOCT23!BM24+HISTONOV23!BM24+HISTODEC23!BM24 -> 0 | BN24: GRATIFICATION BUREAU 2021 | BO24: FRAIS EXEPTIONNEL | BP24: =HISTOJANV23!BP24+HISTOFEV23!BP24+HISTOMARS23!BP24+HISTOAVRIL23!BP24+HISTOMAI23!BP24+HISTOJUIN23!BP24+HISTOJUIL23!BP24+HISTOAOUT23!BP24+HISTOSEPT23!BP24+HISTOOCT23!BP24+HISTONOV23!BP24+HISTODEC23!BP24 -> 0
A25: AS201626 | B25: =VLOOKUP(A25,[17]LISTADHERENT!A$5:H$39,3,0) -> NGUIEMEGNI MATHIEU BLAISE | C25: =HISTOJANV23!C25+HISTOFEV23!C25+HISTOMARS23!C25+HISTOAVRIL23!C25+HISTOMAI23!C25+HISTOJUIN23!C25+HISTOJUIL23!C25+HISTOAOUT23!C25+HISTOSEPT23!C25+HISTOOCT23!C25+HISTONOV23!C25+HISTODEC23!C25 -> -10000 | D25: =HISTOJANV23!D25+HISTOFEV23!D25+HISTOMARS23!D25+HISTOAVRIL23!D25+HISTOMAI23!D25+HISTOJUIN23!D25+HISTOJUIL23!D25+HISTOAOUT23!D25+HISTOSEPT23!D25+HISTOOCT23!D25+HISTONOV23!D25+HISTODEC23!D25 -> 4888000 | E25: =HISTOJANV23!E25+HISTOFEV23!E25+HISTOMARS23!E25+HISTOAVRIL23!E25+HISTOMAI23!E25+HISTOJUIN23!E25+HISTOJUIL23!E25+HISTOAOUT23!E25+HISTOSEPT23!E25+HISTOOCT23!E25+HISTONOV23!E25+HISTODEC23!E25 -> 1060000 | F25: =HISTOJANV23!F25+HISTOFEV23!F25+HISTOMARS23!F25+HISTOAVRIL23!F25+HISTOMAI23!F25+HISTOJUIN23!F25+HISTOJUIL23!F25+HISTOAOUT23!F25+HISTOSEPT23!F25+HISTOOCT23!F25+HISTONOV23!F25+HISTODEC23!F25 -> 70000 | G25: =HISTOJANV23!G25+HISTOFEV23!G25+HISTOMARS23!G25+HISTOAVRIL23!G25+HISTOMAI23!G25+HISTOJUIN23!G25+HISTOJUIL23!G25+HISTOAOUT23!G25+HISTOSEPT23!G25+HISTOOCT23!G25+HISTONOV23!G25+HISTODEC23!G25 -> 0 | H25: =IF($D25<>0,"BANQUE",IF($E25<>0,"ESPECES","ECHEC")) -> BANQUE | I25: =HISTOJANV23!I25+HISTOFEV23!I25+HISTOMARS23!I25+HISTOAVRIL23!I25+HISTOMAI23!I25+HISTOJUIN23!I25+HISTOJUIL23!I25+HISTOAOUT23!I25+HISTOSEPT23!I25+HISTOOCT23!I25+HISTONOV23!I25+HISTODEC23!I25 -> 308000 | J25: =HISTOJANV23!J25+HISTOFEV23!J25+HISTOMARS23!J25+HISTOAVRIL23!J25+HISTOMAI23!J25+HISTOJUIN23!J25+HISTOJUIL23!J25+HISTOAOUT23!J25+HISTOSEPT23!J25+HISTOOCT23!J25+HISTONOV23!J25+HISTODEC23!J25 -> 12 | K25: =HISTOJANV23!K25+HISTOFEV23!K25+HISTOMARS23!K25+HISTOAVRIL23!K25+HISTOMAI23!K25+HISTOJUIN23!K25+HISTOJUIL23!K25+HISTOAOUT23!K25+HISTOSEPT23!K25+HISTOOCT23!K25+HISTONOV23!K25+HISTODEC23!K25 -> 480000 | L25: =HISTOJANV23!L25+HISTOFEV23!L25+HISTOMARS23!L25+HISTOAVRIL23!L25+HISTOMAI23!L25+HISTOJUIN23!L25+HISTOJUIL23!L25+HISTOAOUT23!L25+HISTOSEPT23!L25+HISTOOCT23!L25+HISTONOV23!L25+HISTODEC23!L25 -> 24 | M25: =HISTOJANV23!M25+HISTOFEV23!M25+HISTOMARS23!M25+HISTOAVRIL23!M25+HISTOMAI23!M25+HISTOJUIN23!M25+HISTOJUIL23!M25+HISTOAOUT23!M25+HISTOSEPT23!M25+HISTOOCT23!M25+HISTONOV23!M25+HISTODEC23!M25 -> 1800000 | N25: =HISTOJANV23!N25+HISTOFEV23!N25+HISTOMARS23!N25+HISTOAVRIL23!N25+HISTOMAI23!N25+HISTOJUIN23!N25+HISTOJUIL23!N25+HISTOAOUT23!N25+HISTOSEPT23!N25+HISTOOCT23!N25+HISTONOV23!N25+HISTODEC23!N25 -> 12 | O25: =HISTOJANV23!O25+HISTOFEV23!O25+HISTOMARS23!O25+HISTOAVRIL23!O25+HISTOMAI23!O25+HISTOJUIN23!O25+HISTOJUIL23!O25+HISTOAOUT23!O25+HISTOSEPT23!O25+HISTOOCT23!O25+HISTONOV23!O25+HISTODEC23!O25 -> 1200000 | P25: =HISTOJANV23!P25+HISTOFEV23!P25+HISTOMARS23!P25+HISTOAVRIL23!P25+HISTOMAI23!P25+HISTOJUIN23!P25+HISTOJUIL23!P25+HISTOAOUT23!P25+HISTOSEPT23!P25+HISTOOCT23!P25+HISTONOV23!P25+HISTODEC23!P25 -> 31000 | ... T25: =HISTOJANV23!T25+HISTOFEV23!T25+HISTOMARS23!T25+HISTOAVRIL23!T25+HISTOMAI23!T25+HISTOJUIN23!T25+HISTOJUIL23!T25+HISTOAOUT23!T25+HISTOSEPT23!T25+HISTOOCT23!T25+HISTONOV23!T25+HISTODEC23!T25 -> #VALUE! | U25: =G25+S25++R25+P25+O25+M25+I25+K25+Q25+V25+W25 -> 5973000 | V25: =HISTOJANV23!V25+HISTOFEV23!V25+HISTOMARS23!V25+HISTOAVRIL23!V25+HISTOMAI23!V25+HISTOJUIN23!V25+HISTOJUIL23!V25+HISTOAOUT23!V25+HISTOSEPT23!V25+HISTOOCT23!V25+HISTONOV23!V25+HISTODEC23!V25 -> 15000 | W25: =HISTOJANV23!W25+HISTOFEV23!W25+HISTOMARS23!W25+HISTOAVRIL23!W25+HISTOMAI23!W25+HISTOJUIN23!W25+HISTOJUIL23!W25+HISTOAOUT23!W25+HISTOSEPT23!W25+HISTOOCT23!W25+HISTONOV23!W25+HISTODEC23!W25 -> 0 | X25: =HISTOJANV23!X25+HISTOFEV23!X25+HISTOMARS23!X25+HISTOAVRIL23!X25+HISTOMAI23!X25+HISTOJUIN23!X25+HISTOJUIL23!X25+HISTOAOUT23!X25+HISTOSEPT23!X25+HISTOOCT23!X25+HISTONOV23!X25+HISTODEC23!X25 -> 0 | Y25: =HISTOJANV23!Y25+HISTOFEV23!Y25+HISTOMARS23!Y25+HISTOAVRIL23!Y25+HISTOMAI23!Y25+HISTOJUIN23!Y25+HISTOJUIL23!Y25+HISTOAOUT23!Y25+HISTOSEPT23!Y25+HISTOOCT23!Y25+HISTONOV23!Y25+HISTODEC23!Y25 -> 0 | Z25: =HISTOJANV23!Z25+HISTOFEV23!Z25+HISTOMARS23!Z25+HISTOAVRIL23!Z25+HISTOMAI23!Z25+HISTOJUIN23!Z25+HISTOJUIL23!Z25+HISTOAOUT23!Z25+HISTOSEPT23!Z25+HISTOOCT23!Z25+HISTONOV23!Z25+HISTODEC23!Z25 -> 1000000 | AA25: =HISTOJANV23!AA25+HISTOFEV23!AA25+HISTOMARS23!AA25+HISTOAVRIL23!AA25+HISTOMAI23!AA25+HISTOJUIN23!AA25+HISTOJUIL23!AA25+HISTOAOUT23!AA25+HISTOSEPT23!AA25+HISTOOCT23!AA25+HISTONOV23!AA25+HISTODEC23!AA25 -> #VALUE! | AB25: =HISTOJANV23!AB25+HISTOFEV23!AB25+HISTOMARS23!AB25+HISTOAVRIL23!AB25+HISTOMAI23!AB25+HISTOJUIN23!AB25+HISTOJUIL23!AB25+HISTOAOUT23!AB25+HISTOSEPT23!AB25+HISTOOCT23!AB25+HISTONOV23!AB25+HISTODEC23!AB25 -> 0 | AC25: =HISTOJANV23!AC25+HISTOFEV23!AC25+HISTOMARS23!AC25+HISTOAVRIL23!AC25+HISTOMAI23!AC25+HISTOJUIN23!AC25+HISTOJUIL23!AC25+HISTOAOUT23!AC25+HISTOSEPT23!AC25+HISTOOCT23!AC25+HISTONOV23!AC25+HISTODEC23!AC25 -> 7500 | ... BM25: =HISTOJANV23!BM25+HISTOFEV23!BM25+HISTOMARS23!BM25+HISTOAVRIL23!BM25+HISTOMAI23!BM25+HISTOJUIN23!BM25+HISTOJUIL23!BM25+HISTOAOUT23!BM25+HISTOSEPT23!BM25+HISTOOCT23!BM25+HISTONOV23!BM25+HISTODEC23!BM25 -> 0 | BN25: DEVELOPPEMENT LAGWEU | BO25: FRAIS EXEPTIONNEL | BP25: =HISTOJANV23!BP25+HISTOFEV23!BP25+HISTOMARS23!BP25+HISTOAVRIL23!BP25+HISTOMAI23!BP25+HISTOJUIN23!BP25+HISTOJUIL23!BP25+HISTOAOUT23!BP25+HISTOSEPT23!BP25+HISTOOCT23!BP25+HISTONOV23!BP25+HISTODEC23!BP25 -> 600000
A26: AS201628 | B26: =VLOOKUP(A26,[17]LISTADHERENT!A$5:H$39,3,0) -> NKAMGANG JUSTIN DEJOLIE | C26: =HISTOJANV23!C26+HISTOFEV23!C26+HISTOMARS23!C26+HISTOAVRIL23!C26+HISTOMAI23!C26+HISTOJUIN23!C26+HISTOJUIL23!C26+HISTOAOUT23!C26+HISTOSEPT23!C26+HISTOOCT23!C26+HISTONOV23!C26+HISTODEC23!C26 -> -859000 | D26: =HISTOJANV23!D26+HISTOFEV23!D26+HISTOMARS23!D26+HISTOAVRIL23!D26+HISTOMAI23!D26+HISTOJUIN23!D26+HISTOJUIL23!D26+HISTOAOUT23!D26+HISTOSEPT23!D26+HISTOOCT23!D26+HISTONOV23!D26+HISTODEC23!D26 -> 130000 | E26: =HISTOJANV23!E26+HISTOFEV23!E26+HISTOMARS23!E26+HISTOAVRIL23!E26+HISTOMAI23!E26+HISTOJUIN23!E26+HISTOJUIL23!E26+HISTOAOUT23!E26+HISTOSEPT23!E26+HISTOOCT23!E26+HISTONOV23!E26+HISTODEC23!E26 -> 1810500 | F26: =HISTOJANV23!F26+HISTOFEV23!F26+HISTOMARS23!F26+HISTOAVRIL23!F26+HISTOMAI23!F26+HISTOJUIN23!F26+HISTOJUIL23!F26+HISTOAOUT23!F26+HISTOSEPT23!F26+HISTOOCT23!F26+HISTONOV23!F26+HISTODEC23!F26 -> 1070000 | G26: =HISTOJANV23!G26+HISTOFEV23!G26+HISTOMARS23!G26+HISTOAVRIL23!G26+HISTOMAI23!G26+HISTOJUIN23!G26+HISTOJUIL23!G26+HISTOAOUT23!G26+HISTOSEPT23!G26+HISTOOCT23!G26+HISTONOV23!G26+HISTODEC23!G26 -> 18000 | H26: =IF($D26<>0,"BANQUE",IF($E26<>0,"ESPECES","ECHEC")) -> BANQUE | I26: =HISTOJANV23!I26+HISTOFEV23!I26+HISTOMARS23!I26+HISTOAVRIL23!I26+HISTOMAI23!I26+HISTOJUIN23!I26+HISTOJUIL23!I26+HISTOAOUT23!I26+HISTOSEPT23!I26+HISTOOCT23!I26+HISTONOV23!I26+HISTODEC23!I26 -> -2000 | J26: =HISTOJANV23!J26+HISTOFEV23!J26+HISTOMARS23!J26+HISTOAVRIL23!J26+HISTOMAI23!J26+HISTOJUIN23!J26+HISTOJUIL23!J26+HISTOAOUT23!J26+HISTOSEPT23!J26+HISTOOCT23!J26+HISTONOV23!J26+HISTODEC23!J26 -> 12 | K26: =HISTOJANV23!K26+HISTOFEV23!K26+HISTOMARS23!K26+HISTOAVRIL23!K26+HISTOMAI23!K26+HISTOJUIN23!K26+HISTOJUIL23!K26+HISTOAOUT23!K26+HISTOSEPT23!K26+HISTOOCT23!K26+HISTONOV23!K26+HISTODEC23!K26 -> 480000 | L26: =HISTOJANV23!L26+HISTOFEV23!L26+HISTOMARS23!L26+HISTOAVRIL23!L26+HISTOMAI23!L26+HISTOJUIN23!L26+HISTOJUIL23!L26+HISTOAOUT23!L26+HISTOSEPT23!L26+HISTOOCT23!L26+HISTONOV23!L26+HISTODEC23!L26 -> 0 | M26: =HISTOJANV23!M26+HISTOFEV23!M26+HISTOMARS23!M26+HISTOAVRIL23!M26+HISTOMAI23!M26+HISTOJUIN23!M26+HISTOJUIL23!M26+HISTOAOUT23!M26+HISTOSEPT23!M26+HISTOOCT23!M26+HISTONOV23!M26+HISTODEC23!M26 -> 0 | N26: =HISTOJANV23!N26+HISTOFEV23!N26+HISTOMARS23!N26+HISTOAVRIL23!N26+HISTOMAI23!N26+HISTOJUIN23!N26+HISTOJUIL23!N26+HISTOAOUT23!N26+HISTOSEPT23!N26+HISTOOCT23!N26+HISTONOV23!N26+HISTODEC23!N26 -> 0 | O26: =HISTOJANV23!O26+HISTOFEV23!O26+HISTOMARS23!O26+HISTOAVRIL23!O26+HISTOMAI23!O26+HISTOJUIN23!O26+HISTOJUIL23!O26+HISTOAOUT23!O26+HISTOSEPT23!O26+HISTOOCT23!O26+HISTONOV23!O26+HISTODEC23!O26 -> 0 | P26: =HISTOJANV23!P26+HISTOFEV23!P26+HISTOMARS23!P26+HISTOAVRIL23!P26+HISTOMAI23!P26+HISTOJUIN23!P26+HISTOJUIL23!P26+HISTOAOUT23!P26+HISTOSEPT23!P26+HISTOOCT23!P26+HISTONOV23!P26+HISTODEC23!P26 -> 303500 | ... T26: =HISTOJANV23!T26+HISTOFEV23!T26+HISTOMARS23!T26+HISTOAVRIL23!T26+HISTOMAI23!T26+HISTOJUIN23!T26+HISTOJUIL23!T26+HISTOAOUT23!T26+HISTOSEPT23!T26+HISTOOCT23!T26+HISTONOV23!T26+HISTODEC23!T26 -> #VALUE! | U26: =G26+S26++R26+P26+O26+M26+I26+K26+Q26+V26+W26 -> 3799500 | V26: =HISTOJANV23!V26+HISTOFEV23!V26+HISTOMARS23!V26+HISTOAVRIL23!V26+HISTOMAI23!V26+HISTOJUIN23!V26+HISTOJUIL23!V26+HISTOAOUT23!V26+HISTOSEPT23!V26+HISTOOCT23!V26+HISTONOV23!V26+HISTODEC23!V26 -> 0 | W26: =HISTOJANV23!W26+HISTOFEV23!W26+HISTOMARS23!W26+HISTOAVRIL23!W26+HISTOMAI23!W26+HISTOJUIN23!W26+HISTOJUIL23!W26+HISTOAOUT23!W26+HISTOSEPT23!W26+HISTOOCT23!W26+HISTONOV23!W26+HISTODEC23!W26 -> 0 | X26: =HISTOJANV23!X26+HISTOFEV23!X26+HISTOMARS23!X26+HISTOAVRIL23!X26+HISTOMAI23!X26+HISTOJUIN23!X26+HISTOJUIL23!X26+HISTOAOUT23!X26+HISTOSEPT23!X26+HISTOOCT23!X26+HISTONOV23!X26+HISTODEC23!X26 -> 0 | Y26: =HISTOJANV23!Y26+HISTOFEV23!Y26+HISTOMARS23!Y26+HISTOAVRIL23!Y26+HISTOMAI23!Y26+HISTOJUIN23!Y26+HISTOJUIL23!Y26+HISTOAOUT23!Y26+HISTOSEPT23!Y26+HISTOOCT23!Y26+HISTONOV23!Y26+HISTODEC23!Y26 -> 0 | Z26: =HISTOJANV23!Z26+HISTOFEV23!Z26+HISTOMARS23!Z26+HISTOAVRIL23!Z26+HISTOMAI23!Z26+HISTOJUIN23!Z26+HISTOJUIL23!Z26+HISTOAOUT23!Z26+HISTOSEPT23!Z26+HISTOOCT23!Z26+HISTONOV23!Z26+HISTODEC23!Z26 -> 3000000 | AA26: =HISTOJANV23!AA26+HISTOFEV23!AA26+HISTOMARS23!AA26+HISTOAVRIL23!AA26+HISTOMAI23!AA26+HISTOJUIN23!AA26+HISTOJUIL23!AA26+HISTOAOUT23!AA26+HISTOSEPT23!AA26+HISTOOCT23!AA26+HISTONOV23!AA26+HISTODEC23!AA26 -> #VALUE! | AB26: =HISTOJANV23!AB26+HISTOFEV23!AB26+HISTOMARS23!AB26+HISTOAVRIL23!AB26+HISTOMAI23!AB26+HISTOJUIN23!AB26+HISTOJUIL23!AB26+HISTOAOUT23!AB26+HISTOSEPT23!AB26+HISTOOCT23!AB26+HISTONOV23!AB26+HISTODEC23!AB26 -> 0 | AC26: =HISTOJANV23!AC26+HISTOFEV23!AC26+HISTOMARS23!AC26+HISTOAVRIL23!AC26+HISTOMAI23!AC26+HISTOJUIN23!AC26+HISTOJUIL23!AC26+HISTOAOUT23!AC26+HISTOSEPT23!AC26+HISTOOCT23!AC26+HISTONOV23!AC26+HISTODEC23!AC26 -> 3500 | ... BM26: =HISTOJANV23!BM26+HISTOFEV23!BM26+HISTOMARS23!BM26+HISTOAVRIL23!BM26+HISTOMAI23!BM26+HISTOJUIN23!BM26+HISTOJUIL23!BM26+HISTOAOUT23!BM26+HISTOSEPT23!BM26+HISTOOCT23!BM26+HISTONOV23!BM26+HISTODEC23!BM26 -> 0 | BN26: DEUIL TCHEMNOU EMMANUEL | BO26: FRAIS EXEPTIONNEL | BP26: =HISTOJANV23!BP26+HISTOFEV23!BP26+HISTOMARS23!BP26+HISTOAVRIL23!BP26+HISTOMAI23!BP26+HISTOJUIN23!BP26+HISTOJUIL23!BP26+HISTOAOUT23!BP26+HISTOSEPT23!BP26+HISTOOCT23!BP26+HISTONOV23!BP26+HISTODEC23!BP26 -> 225000
A27: AS201656 | B27: =VLOOKUP(A27,[17]LISTADHERENT!A$5:H$39,3,0) -> NOUBE ETIENNE | C27: =HISTOJANV23!C27+HISTOFEV23!C27+HISTOMARS23!C27+HISTOAVRIL23!C27+HISTOMAI23!C27+HISTOJUIN23!C27+HISTOJUIL23!C27+HISTOAOUT23!C27+HISTOSEPT23!C27+HISTOOCT23!C27+HISTONOV23!C27+HISTODEC23!C27 -> -7500 | D27: =HISTOJANV23!D27+HISTOFEV23!D27+HISTOMARS23!D27+HISTOAVRIL23!D27+HISTOMAI23!D27+HISTOJUIN23!D27+HISTOJUIL23!D27+HISTOAOUT23!D27+HISTOSEPT23!D27+HISTOOCT23!D27+HISTONOV23!D27+HISTODEC23!D27 -> 1045000 | E27: =HISTOJANV23!E27+HISTOFEV23!E27+HISTOMARS23!E27+HISTOAVRIL23!E27+HISTOMAI23!E27+HISTOJUIN23!E27+HISTOJUIL23!E27+HISTOAOUT23!E27+HISTOSEPT23!E27+HISTOOCT23!E27+HISTONOV23!E27+HISTODEC23!E27 -> 65000 | F27: =HISTOJANV23!F27+HISTOFEV23!F27+HISTOMARS23!F27+HISTOAVRIL23!F27+HISTOMAI23!F27+HISTOJUIN23!F27+HISTOJUIL23!F27+HISTOAOUT23!F27+HISTOSEPT23!F27+HISTOOCT23!F27+HISTONOV23!F27+HISTODEC23!F27 -> 70000 | G27: =HISTOJANV23!G27+HISTOFEV23!G27+HISTOMARS23!G27+HISTOAVRIL23!G27+HISTOMAI23!G27+HISTOJUIN23!G27+HISTOJUIL23!G27+HISTOAOUT23!G27+HISTOSEPT23!G27+HISTOOCT23!G27+HISTONOV23!G27+HISTODEC23!G27 -> 0 | H27: =IF($D27<>0,"BANQUE",IF($E27<>0,"ESPECES","ECHEC")) -> BANQUE | I27: =HISTOJANV23!I27+HISTOFEV23!I27+HISTOMARS23!I27+HISTOAVRIL23!I27+HISTOMAI23!I27+HISTOJUIN23!I27+HISTOJUIL23!I27+HISTOAOUT23!I27+HISTOSEPT23!I27+HISTOOCT23!I27+HISTONOV23!I27+HISTODEC23!I27 -> 612500 | J27: =HISTOJANV23!J27+HISTOFEV23!J27+HISTOMARS23!J27+HISTOAVRIL23!J27+HISTOMAI23!J27+HISTOJUIN23!J27+HISTOJUIL23!J27+HISTOAOUT23!J27+HISTOSEPT23!J27+HISTOOCT23!J27+HISTONOV23!J27+HISTODEC23!J27 -> 12 | K27: =HISTOJANV23!K27+HISTOFEV23!K27+HISTOMARS23!K27+HISTOAVRIL23!K27+HISTOMAI23!K27+HISTOJUIN23!K27+HISTOJUIL23!K27+HISTOAOUT23!K27+HISTOSEPT23!K27+HISTOOCT23!K27+HISTONOV23!K27+HISTODEC23!K27 -> 480000 | L27: =HISTOJANV23!L27+HISTOFEV23!L27+HISTOMARS23!L27+HISTOAVRIL23!L27+HISTOMAI23!L27+HISTOJUIN23!L27+HISTOJUIL23!L27+HISTOAOUT23!L27+HISTOSEPT23!L27+HISTOOCT23!L27+HISTONOV23!L27+HISTODEC23!L27 -> 0 | M27: =HISTOJANV23!M27+HISTOFEV23!M27+HISTOMARS23!M27+HISTOAVRIL23!M27+HISTOMAI23!M27+HISTOJUIN23!M27+HISTOJUIL23!M27+HISTOAOUT23!M27+HISTOSEPT23!M27+HISTOOCT23!M27+HISTONOV23!M27+HISTODEC23!M27 -> 0 | N27: =HISTOJANV23!N27+HISTOFEV23!N27+HISTOMARS23!N27+HISTOAVRIL23!N27+HISTOMAI23!N27+HISTOJUIN23!N27+HISTOJUIL23!N27+HISTOAOUT23!N27+HISTOSEPT23!N27+HISTOOCT23!N27+HISTONOV23!N27+HISTODEC23!N27 -> 0 | O27: =HISTOJANV23!O27+HISTOFEV23!O27+HISTOMARS23!O27+HISTOAVRIL23!O27+HISTOMAI23!O27+HISTOJUIN23!O27+HISTOJUIL23!O27+HISTOAOUT23!O27+HISTOSEPT23!O27+HISTOOCT23!O27+HISTONOV23!O27+HISTODEC23!O27 -> 0 | P27: =HISTOJANV23!P27+HISTOFEV23!P27+HISTOMARS23!P27+HISTOAVRIL23!P27+HISTOMAI23!P27+HISTOJUIN23!P27+HISTOJUIL23!P27+HISTOAOUT23!P27+HISTOSEPT23!P27+HISTOOCT23!P27+HISTONOV23!P27+HISTODEC23!P27 -> 0 | ... T27: =HISTOJANV23!T27+HISTOFEV23!T27+HISTOMARS23!T27+HISTOAVRIL23!T27+HISTOMAI23!T27+HISTOJUIN23!T27+HISTOJUIL23!T27+HISTOAOUT23!T27+HISTOSEPT23!T27+HISTOOCT23!T27+HISTONOV23!T27+HISTODEC23!T27 -> 0 | U27: =G27+S27++R27+P27+O27+M27+I27+K27+Q27+V27+W27 -> 1117500 | V27: =HISTOJANV23!V27+HISTOFEV23!V27+HISTOMARS23!V27+HISTOAVRIL23!V27+HISTOMAI23!V27+HISTOJUIN23!V27+HISTOJUIL23!V27+HISTOAOUT23!V27+HISTOSEPT23!V27+HISTOOCT23!V27+HISTONOV23!V27+HISTODEC23!V27 -> 0 | W27: =HISTOJANV23!W27+HISTOFEV23!W27+HISTOMARS23!W27+HISTOAVRIL23!W27+HISTOMAI23!W27+HISTOJUIN23!W27+HISTOJUIL23!W27+HISTOAOUT23!W27+HISTOSEPT23!W27+HISTOOCT23!W27+HISTONOV23!W27+HISTODEC23!W27 -> 25000 | X27: =HISTOJANV23!X27+HISTOFEV23!X27+HISTOMARS23!X27+HISTOAVRIL23!X27+HISTOMAI23!X27+HISTOJUIN23!X27+HISTOJUIL23!X27+HISTOAOUT23!X27+HISTOSEPT23!X27+HISTOOCT23!X27+HISTONOV23!X27+HISTODEC23!X27 -> 0 | Y27: =HISTOJANV23!Y27+HISTOFEV23!Y27+HISTOMARS23!Y27+HISTOAVRIL23!Y27+HISTOMAI23!Y27+HISTOJUIN23!Y27+HISTOJUIL23!Y27+HISTOAOUT23!Y27+HISTOSEPT23!Y27+HISTOOCT23!Y27+HISTONOV23!Y27+HISTODEC23!Y27 -> 0 | Z27: =HISTOJANV23!Z27+HISTOFEV23!Z27+HISTOMARS23!Z27+HISTOAVRIL23!Z27+HISTOMAI23!Z27+HISTOJUIN23!Z27+HISTOJUIL23!Z27+HISTOAOUT23!Z27+HISTOSEPT23!Z27+HISTOOCT23!Z27+HISTONOV23!Z27+HISTODEC23!Z27 -> 0 | AA27: =HISTOJANV23!AA27+HISTOFEV23!AA27+HISTOMARS23!AA27+HISTOAVRIL23!AA27+HISTOMAI23!AA27+HISTOJUIN23!AA27+HISTOJUIL23!AA27+HISTOAOUT23!AA27+HISTOSEPT23!AA27+HISTOOCT23!AA27+HISTONOV23!AA27+HISTODEC23!AA27 -> 0 | AB27: =HISTOJANV23!AB27+HISTOFEV23!AB27+HISTOMARS23!AB27+HISTOAVRIL23!AB27+HISTOMAI23!AB27+HISTOJUIN23!AB27+HISTOJUIL23!AB27+HISTOAOUT23!AB27+HISTOSEPT23!AB27+HISTOOCT23!AB27+HISTONOV23!AB27+HISTODEC23!AB27 -> 0 | AC27: =HISTOJANV23!AC27+HISTOFEV23!AC27+HISTOMARS23!AC27+HISTOAVRIL23!AC27+HISTOMAI23!AC27+HISTOJUIN23!AC27+HISTOJUIL23!AC27+HISTOAOUT23!AC27+HISTOSEPT23!AC27+HISTOOCT23!AC27+HISTONOV23!AC27+HISTODEC23!AC27 -> 2500 | ... BM27: =HISTOJANV23!BM27+HISTOFEV23!BM27+HISTOMARS23!BM27+HISTOAVRIL23!BM27+HISTOMAI23!BM27+HISTOJUIN23!BM27+HISTOJUIL23!BM27+HISTOAOUT23!BM27+HISTOSEPT23!BM27+HISTOOCT23!BM27+HISTONOV23!BM27+HISTODEC23!BM27 -> 0
A28: AS201633 | B28: =VLOOKUP(A28,[17]LISTADHERENT!A$5:H$39,3,0) -> PATEGO NJOSSU GUSTAVE | C28: =HISTOJANV23!C28+HISTOFEV23!C28+HISTOMARS23!C28+HISTOAVRIL23!C28+HISTOMAI23!C28+HISTOJUIN23!C28+HISTOJUIL23!C28+HISTOAOUT23!C28+HISTOSEPT23!C28+HISTOOCT23!C28+HISTONOV23!C28+HISTODEC23!C28 -> -70000 | D28: =HISTOJANV23!D28+HISTOFEV23!D28+HISTOMARS23!D28+HISTOAVRIL23!D28+HISTOMAI23!D28+HISTOJUIN23!D28+HISTOJUIL23!D28+HISTOAOUT23!D28+HISTOSEPT23!D28+HISTOOCT23!D28+HISTONOV23!D28+HISTODEC23!D28 -> 1380000 | E28: =HISTOJANV23!E28+HISTOFEV23!E28+HISTOMARS23!E28+HISTOAVRIL23!E28+HISTOMAI23!E28+HISTOJUIN23!E28+HISTOJUIL23!E28+HISTOAOUT23!E28+HISTOSEPT23!E28+HISTOOCT23!E28+HISTONOV23!E28+HISTODEC23!E28 -> 0 | F28: =HISTOJANV23!F28+HISTOFEV23!F28+HISTOMARS23!F28+HISTOAVRIL23!F28+HISTOMAI23!F28+HISTOJUIN23!F28+HISTOJUIL23!F28+HISTOAOUT23!F28+HISTOSEPT23!F28+HISTOOCT23!F28+HISTONOV23!F28+HISTODEC23!F28 -> 0 | G28: =HISTOJANV23!G28+HISTOFEV23!G28+HISTOMARS23!G28+HISTOAVRIL23!G28+HISTOMAI23!G28+HISTOJUIN23!G28+HISTOJUIL23!G28+HISTOAOUT23!G28+HISTOSEPT23!G28+HISTOOCT23!G28+HISTONOV23!G28+HISTODEC23!G28 -> 0 | H28: =IF($D28<>0,"BANQUE",IF($E28<>0,"ESPECES","ECHEC")) -> BANQUE | I28: =HISTOJANV23!I28+HISTOFEV23!I28+HISTOMARS23!I28+HISTOAVRIL23!I28+HISTOMAI23!I28+HISTOJUIN23!I28+HISTOJUIL23!I28+HISTOAOUT23!I28+HISTOSEPT23!I28+HISTOOCT23!I28+HISTONOV23!I28+HISTODEC23!I28 -> 0 | J28: =HISTOJANV23!J28+HISTOFEV23!J28+HISTOMARS23!J28+HISTOAVRIL23!J28+HISTOMAI23!J28+HISTOJUIN23!J28+HISTOJUIL23!J28+HISTOAOUT23!J28+HISTOSEPT23!J28+HISTOOCT23!J28+HISTONOV23!J28+HISTODEC23!J28 -> 12 | K28: =HISTOJANV23!K28+HISTOFEV23!K28+HISTOMARS23!K28+HISTOAVRIL23!K28+HISTOMAI23!K28+HISTOJUIN23!K28+HISTOJUIL23!K28+HISTOAOUT23!K28+HISTOSEPT23!K28+HISTOOCT23!K28+HISTONOV23!K28+HISTODEC23!K28 -> 480000 | L28: =HISTOJANV23!L28+HISTOFEV23!L28+HISTOMARS23!L28+HISTOAVRIL23!L28+HISTOMAI23!L28+HISTOJUIN23!L28+HISTOJUIL23!L28+HISTOAOUT23!L28+HISTOSEPT23!L28+HISTOOCT23!L28+HISTONOV23!L28+HISTODEC23!L28 -> 12 | M28: =HISTOJANV23!M28+HISTOFEV23!M28+HISTOMARS23!M28+HISTOAVRIL23!M28+HISTOMAI23!M28+HISTOJUIN23!M28+HISTOJUIL23!M28+HISTOAOUT23!M28+HISTOSEPT23!M28+HISTOOCT23!M28+HISTONOV23!M28+HISTODEC23!M28 -> 900000 | N28: =HISTOJANV23!N28+HISTOFEV23!N28+HISTOMARS23!N28+HISTOAVRIL23!N28+HISTOMAI23!N28+HISTOJUIN23!N28+HISTOJUIL23!N28+HISTOAOUT23!N28+HISTOSEPT23!N28+HISTOOCT23!N28+HISTONOV23!N28+HISTODEC23!N28 -> 0 | O28: =HISTOJANV23!O28+HISTOFEV23!O28+HISTOMARS23!O28+HISTOAVRIL23!O28+HISTOMAI23!O28+HISTOJUIN23!O28+HISTOJUIL23!O28+HISTOAOUT23!O28+HISTOSEPT23!O28+HISTOOCT23!O28+HISTONOV23!O28+HISTODEC23!O28 -> 0 | P28: =HISTOJANV23!P28+HISTOFEV23!P28+HISTOMARS23!P28+HISTOAVRIL23!P28+HISTOMAI23!P28+HISTOJUIN23!P28+HISTOJUIL23!P28+HISTOAOUT23!P28+HISTOSEPT23!P28+HISTOOCT23!P28+HISTONOV23!P28+HISTODEC23!P28 -> 0 | ... T28: =HISTOJANV23!T28+HISTOFEV23!T28+HISTOMARS23!T28+HISTOAVRIL23!T28+HISTOMAI23!T28+HISTOJUIN23!T28+HISTOJUIL23!T28+HISTOAOUT23!T28+HISTOSEPT23!T28+HISTOOCT23!T28+HISTONOV23!T28+HISTODEC23!T28 -> 0 | U28: =G28+S28++R28+P28+O28+M28+I28+K28+Q28+V28+W28 -> 1380000 | V28: =HISTOJANV23!V28+HISTOFEV23!V28+HISTOMARS23!V28+HISTOAVRIL23!V28+HISTOMAI23!V28+HISTOJUIN23!V28+HISTOJUIL23!V28+HISTOAOUT23!V28+HISTOSEPT23!V28+HISTOOCT23!V28+HISTONOV23!V28+HISTODEC23!V28 -> 0 | W28: =HISTOJANV23!W28+HISTOFEV23!W28+HISTOMARS23!W28+HISTOAVRIL23!W28+HISTOMAI23!W28+HISTOJUIN23!W28+HISTOJUIL23!W28+HISTOAOUT23!W28+HISTOSEPT23!W28+HISTOOCT23!W28+HISTONOV23!W28+HISTODEC23!W28 -> 0 | X28: =HISTOJANV23!X28+HISTOFEV23!X28+HISTOMARS23!X28+HISTOAVRIL23!X28+HISTOMAI23!X28+HISTOJUIN23!X28+HISTOJUIL23!X28+HISTOAOUT23!X28+HISTOSEPT23!X28+HISTOOCT23!X28+HISTONOV23!X28+HISTODEC23!X28 -> 0 | Y28: =HISTOJANV23!Y28+HISTOFEV23!Y28+HISTOMARS23!Y28+HISTOAVRIL23!Y28+HISTOMAI23!Y28+HISTOJUIN23!Y28+HISTOJUIL23!Y28+HISTOAOUT23!Y28+HISTOSEPT23!Y28+HISTOOCT23!Y28+HISTONOV23!Y28+HISTODEC23!Y28 -> 0 | Z28: =HISTOJANV23!Z28+HISTOFEV23!Z28+HISTOMARS23!Z28+HISTOAVRIL23!Z28+HISTOMAI23!Z28+HISTOJUIN23!Z28+HISTOJUIL23!Z28+HISTOAOUT23!Z28+HISTOSEPT23!Z28+HISTOOCT23!Z28+HISTONOV23!Z28+HISTODEC23!Z28 -> 0 | AA28: =HISTOJANV23!AA28+HISTOFEV23!AA28+HISTOMARS23!AA28+HISTOAVRIL23!AA28+HISTOMAI23!AA28+HISTOJUIN23!AA28+HISTOJUIL23!AA28+HISTOAOUT23!AA28+HISTOSEPT23!AA28+HISTOOCT23!AA28+HISTONOV23!AA28+HISTODEC23!AA28 -> 0 | AB28: =HISTOJANV23!AB28+HISTOFEV23!AB28+HISTOMARS23!AB28+HISTOAVRIL23!AB28+HISTOMAI23!AB28+HISTOJUIN23!AB28+HISTOJUIL23!AB28+HISTOAOUT23!AB28+HISTOSEPT23!AB28+HISTOOCT23!AB28+HISTONOV23!AB28+HISTODEC23!AB28 -> 0 | AC28: =HISTOJANV23!AC28+HISTOFEV23!AC28+HISTOMARS23!AC28+HISTOAVRIL23!AC28+HISTOMAI23!AC28+HISTOJUIN23!AC28+HISTOJUIL23!AC28+HISTOAOUT23!AC28+HISTOSEPT23!AC28+HISTOOCT23!AC28+HISTONOV23!AC28+HISTODEC23!AC28 -> 2500 | ... BM28: =HISTOJANV23!BM28+HISTOFEV23!BM28+HISTOMARS23!BM28+HISTOAVRIL23!BM28+HISTOMAI23!BM28+HISTOJUIN23!BM28+HISTOJUIL23!BM28+HISTOAOUT23!BM28+HISTOSEPT23!BM28+HISTOOCT23!BM28+HISTONOV23!BM28+HISTODEC23!BM28 -> 0 | BN28: S/TOTAL | BP28: =SUM(BP24:BP26) -> 825000
A29: AS201657 | B29: =VLOOKUP(A29,[17]LISTADHERENT!A$5:H$39,3,0) -> SEUMO POLYCARPE | C29: =HISTOJANV23!C29+HISTOFEV23!C29+HISTOMARS23!C29+HISTOAVRIL23!C29+HISTOMAI23!C29+HISTOJUIN23!C29+HISTOJUIL23!C29+HISTOAOUT23!C29+HISTOSEPT23!C29+HISTOOCT23!C29+HISTONOV23!C29+HISTODEC23!C29 -> -57500 | D29: =HISTOJANV23!D29+HISTOFEV23!D29+HISTOMARS23!D29+HISTOAVRIL23!D29+HISTOMAI23!D29+HISTOJUIN23!D29+HISTOJUIL23!D29+HISTOAOUT23!D29+HISTOSEPT23!D29+HISTOOCT23!D29+HISTONOV23!D29+HISTODEC23!D29 -> 560000 | E29: =HISTOJANV23!E29+HISTOFEV23!E29+HISTOMARS23!E29+HISTOAVRIL23!E29+HISTOMAI23!E29+HISTOJUIN23!E29+HISTOJUIL23!E29+HISTOAOUT23!E29+HISTOSEPT23!E29+HISTOOCT23!E29+HISTONOV23!E29+HISTODEC23!E29 -> 65000 | F29: =HISTOJANV23!F29+HISTOFEV23!F29+HISTOMARS23!F29+HISTOAVRIL23!F29+HISTOMAI23!F29+HISTOJUIN23!F29+HISTOJUIL23!F29+HISTOAOUT23!F29+HISTOSEPT23!F29+HISTOOCT23!F29+HISTONOV23!F29+HISTODEC23!F29 -> 70000 | G29: =HISTOJANV23!G29+HISTOFEV23!G29+HISTOMARS23!G29+HISTOAVRIL23!G29+HISTOMAI23!G29+HISTOJUIN23!G29+HISTOJUIL23!G29+HISTOAOUT23!G29+HISTOSEPT23!G29+HISTOOCT23!G29+HISTONOV23!G29+HISTODEC23!G29 -> 0 | H29: =IF($D29<>0,"BANQUE",IF($E29<>0,"ESPECES","ECHEC")) -> BANQUE | I29: =HISTOJANV23!I29+HISTOFEV23!I29+HISTOMARS23!I29+HISTOAVRIL23!I29+HISTOMAI23!I29+HISTOJUIN23!I29+HISTOJUIL23!I29+HISTOAOUT23!I29+HISTOSEPT23!I29+HISTOOCT23!I29+HISTONOV23!I29+HISTODEC23!I29 -> 177500 | J29: =HISTOJANV23!J29+HISTOFEV23!J29+HISTOMARS23!J29+HISTOAVRIL23!J29+HISTOMAI23!J29+HISTOJUIN23!J29+HISTOJUIL23!J29+HISTOAOUT23!J29+HISTOSEPT23!J29+HISTOOCT23!J29+HISTONOV23!J29+HISTODEC23!J29 -> 12 | K29: =HISTOJANV23!K29+HISTOFEV23!K29+HISTOMARS23!K29+HISTOAVRIL23!K29+HISTOMAI23!K29+HISTOJUIN23!K29+HISTOJUIL23!K29+HISTOAOUT23!K29+HISTOSEPT23!K29+HISTOOCT23!K29+HISTONOV23!K29+HISTODEC23!K29 -> 480000 | L29: =HISTOJANV23!L29+HISTOFEV23!L29+HISTOMARS23!L29+HISTOAVRIL23!L29+HISTOMAI23!L29+HISTOJUIN23!L29+HISTOJUIL23!L29+HISTOAOUT23!L29+HISTOSEPT23!L29+HISTOOCT23!L29+HISTONOV23!L29+HISTODEC23!L29 -> 0 | M29: =HISTOJANV23!M29+HISTOFEV23!M29+HISTOMARS23!M29+HISTOAVRIL23!M29+HISTOMAI23!M29+HISTOJUIN23!M29+HISTOJUIL23!M29+HISTOAOUT23!M29+HISTOSEPT23!M29+HISTOOCT23!M29+HISTONOV23!M29+HISTODEC23!M29 -> 0 | N29: =HISTOJANV23!N29+HISTOFEV23!N29+HISTOMARS23!N29+HISTOAVRIL23!N29+HISTOMAI23!N29+HISTOJUIN23!N29+HISTOJUIL23!N29+HISTOAOUT23!N29+HISTOSEPT23!N29+HISTOOCT23!N29+HISTONOV23!N29+HISTODEC23!N29 -> 0 | O29: =HISTOJANV23!O29+HISTOFEV23!O29+HISTOMARS23!O29+HISTOAVRIL23!O29+HISTOMAI23!O29+HISTOJUIN23!O29+HISTOJUIL23!O29+HISTOAOUT23!O29+HISTOSEPT23!O29+HISTOOCT23!O29+HISTONOV23!O29+HISTODEC23!O29 -> 0 | P29: =HISTOJANV23!P29+HISTOFEV23!P29+HISTOMARS23!P29+HISTOAVRIL23!P29+HISTOMAI23!P29+HISTOJUIN23!P29+HISTOJUIL23!P29+HISTOAOUT23!P29+HISTOSEPT23!P29+HISTOOCT23!P29+HISTONOV23!P29+HISTODEC23!P29 -> 0 | ... T29: =HISTOJANV23!T29+HISTOFEV23!T29+HISTOMARS23!T29+HISTOAVRIL23!T29+HISTOMAI23!T29+HISTOJUIN23!T29+HISTOJUIL23!T29+HISTOAOUT23!T29+HISTOSEPT23!T29+HISTOOCT23!T29+HISTONOV23!T29+HISTODEC23!T29 -> 0 | U29: =G29+S29++R29+P29+O29+M29+I29+K29+Q29+V29+W29 -> 682500 | V29: =HISTOJANV23!V29+HISTOFEV23!V29+HISTOMARS23!V29+HISTOAVRIL23!V29+HISTOMAI23!V29+HISTOJUIN23!V29+HISTOJUIL23!V29+HISTOAOUT23!V29+HISTOSEPT23!V29+HISTOOCT23!V29+HISTONOV23!V29+HISTODEC23!V29 -> 0 | W29: =HISTOJANV23!W29+HISTOFEV23!W29+HISTOMARS23!W29+HISTOAVRIL23!W29+HISTOMAI23!W29+HISTOJUIN23!W29+HISTOJUIL23!W29+HISTOAOUT23!W29+HISTOSEPT23!W29+HISTOOCT23!W29+HISTONOV23!W29+HISTODEC23!W29 -> 25000 | X29: =HISTOJANV23!X29+HISTOFEV23!X29+HISTOMARS23!X29+HISTOAVRIL23!X29+HISTOMAI23!X29+HISTOJUIN23!X29+HISTOJUIL23!X29+HISTOAOUT23!X29+HISTOSEPT23!X29+HISTOOCT23!X29+HISTONOV23!X29+HISTODEC23!X29 -> 0 | Y29: =HISTOJANV23!Y29+HISTOFEV23!Y29+HISTOMARS23!Y29+HISTOAVRIL23!Y29+HISTOMAI23!Y29+HISTOJUIN23!Y29+HISTOJUIL23!Y29+HISTOAOUT23!Y29+HISTOSEPT23!Y29+HISTOOCT23!Y29+HISTONOV23!Y29+HISTODEC23!Y29 -> 0 | Z29: =HISTOJANV23!Z29+HISTOFEV23!Z29+HISTOMARS23!Z29+HISTOAVRIL23!Z29+HISTOMAI23!Z29+HISTOJUIN23!Z29+HISTOJUIL23!Z29+HISTOAOUT23!Z29+HISTOSEPT23!Z29+HISTOOCT23!Z29+HISTONOV23!Z29+HISTODEC23!Z29 -> 0 | AA29: =HISTOJANV23!AA29+HISTOFEV23!AA29+HISTOMARS23!AA29+HISTOAVRIL23!AA29+HISTOMAI23!AA29+HISTOJUIN23!AA29+HISTOJUIL23!AA29+HISTOAOUT23!AA29+HISTOSEPT23!AA29+HISTOOCT23!AA29+HISTONOV23!AA29+HISTODEC23!AA29 -> 0 | AB29: =HISTOJANV23!AB29+HISTOFEV23!AB29+HISTOMARS23!AB29+HISTOAVRIL23!AB29+HISTOMAI23!AB29+HISTOJUIN23!AB29+HISTOJUIL23!AB29+HISTOAOUT23!AB29+HISTOSEPT23!AB29+HISTOOCT23!AB29+HISTONOV23!AB29+HISTODEC23!AB29 -> 0 | AC29: =HISTOJANV23!AC29+HISTOFEV23!AC29+HISTOMARS23!AC29+HISTOAVRIL23!AC29+HISTOMAI23!AC29+HISTOJUIN23!AC29+HISTOJUIL23!AC29+HISTOAOUT23!AC29+HISTOSEPT23!AC29+HISTOOCT23!AC29+HISTONOV23!AC29+HISTODEC23!AC29 -> 2500 | ... BM29: =HISTOJANV23!BM29+HISTOFEV23!BM29+HISTOMARS23!BM29+HISTOAVRIL23!BM29+HISTOMAI23!BM29+HISTOJUIN23!BM29+HISTOJUIL23!BM29+HISTOAOUT23!BM29+HISTOSEPT23!BM29+HISTOOCT23!BM29+HISTONOV23!BM29+HISTODEC23!BM29 -> 0
A30: AS201653 | B30: =VLOOKUP(A30,[17]LISTADHERENT!A$5:H$39,3,0) -> SIME BRICE | C30: =HISTOJANV23!C30+HISTOFEV23!C30+HISTOMARS23!C30+HISTOAVRIL23!C30+HISTOMAI23!C30+HISTOJUIN23!C30+HISTOJUIL23!C30+HISTOAOUT23!C30+HISTOSEPT23!C30+HISTOOCT23!C30+HISTONOV23!C30+HISTODEC23!C30 -> 0 | D30: =HISTOJANV23!D30+HISTOFEV23!D30+HISTOMARS23!D30+HISTOAVRIL23!D30+HISTOMAI23!D30+HISTOJUIN23!D30+HISTOJUIL23!D30+HISTOAOUT23!D30+HISTOSEPT23!D30+HISTOOCT23!D30+HISTONOV23!D30+HISTODEC23!D30 -> 1265000 | E30: =HISTOJANV23!E30+HISTOFEV23!E30+HISTOMARS23!E30+HISTOAVRIL23!E30+HISTOMAI23!E30+HISTOJUIN23!E30+HISTOJUIL23!E30+HISTOAOUT23!E30+HISTOSEPT23!E30+HISTOOCT23!E30+HISTONOV23!E30+HISTODEC23!E30 -> 115000 | F30: =HISTOJANV23!F30+HISTOFEV23!F30+HISTOMARS23!F30+HISTOAVRIL23!F30+HISTOMAI23!F30+HISTOJUIN23!F30+HISTOJUIL23!F30+HISTOAOUT23!F30+HISTOSEPT23!F30+HISTOOCT23!F30+HISTONOV23!F30+HISTODEC23!F30 -> 70000 | G30: =HISTOJANV23!G30+HISTOFEV23!G30+HISTOMARS23!G30+HISTOAVRIL23!G30+HISTOMAI23!G30+HISTOJUIN23!G30+HISTOJUIL23!G30+HISTOAOUT23!G30+HISTOSEPT23!G30+HISTOOCT23!G30+HISTONOV23!G30+HISTODEC23!G30 -> 0 | H30: =IF($D30<>0,"BANQUE",IF($E30<>0,"ESPECES","ECHEC")) -> BANQUE | I30: =HISTOJANV23!I30+HISTOFEV23!I30+HISTOMARS23!I30+HISTOAVRIL23!I30+HISTOMAI23!I30+HISTOJUIN23!I30+HISTOJUIL23!I30+HISTOAOUT23!I30+HISTOSEPT23!I30+HISTOOCT23!I30+HISTONOV23!I30+HISTODEC23!I30 -> 0 | J30: =HISTOJANV23!J30+HISTOFEV23!J30+HISTOMARS23!J30+HISTOAVRIL23!J30+HISTOMAI23!J30+HISTOJUIN23!J30+HISTOJUIL23!J30+HISTOAOUT23!J30+HISTOSEPT23!J30+HISTOOCT23!J30+HISTONOV23!J30+HISTODEC23!J30 -> 12 | K30: =HISTOJANV23!K30+HISTOFEV23!K30+HISTOMARS23!K30+HISTOAVRIL23!K30+HISTOMAI23!K30+HISTOJUIN23!K30+HISTOJUIL23!K30+HISTOAOUT23!K30+HISTOSEPT23!K30+HISTOOCT23!K30+HISTONOV23!K30+HISTODEC23!K30 -> 480000 | L30: =HISTOJANV23!L30+HISTOFEV23!L30+HISTOMARS23!L30+HISTOAVRIL23!L30+HISTOMAI23!L30+HISTOJUIN23!L30+HISTOJUIL23!L30+HISTOAOUT23!L30+HISTOSEPT23!L30+HISTOOCT23!L30+HISTONOV23!L30+HISTODEC23!L30 -> 12 | M30: =HISTOJANV23!M30+HISTOFEV23!M30+HISTOMARS23!M30+HISTOAVRIL23!M30+HISTOMAI23!M30+HISTOJUIN23!M30+HISTOJUIL23!M30+HISTOAOUT23!M30+HISTOSEPT23!M30+HISTOOCT23!M30+HISTONOV23!M30+HISTODEC23!M30 -> 900000 | N30: =HISTOJANV23!N30+HISTOFEV23!N30+HISTOMARS23!N30+HISTOAVRIL23!N30+HISTOMAI23!N30+HISTOJUIN23!N30+HISTOJUIL23!N30+HISTOAOUT23!N30+HISTOSEPT23!N30+HISTOOCT23!N30+HISTONOV23!N30+HISTODEC23!N30 -> 0 | O30: =HISTOJANV23!O30+HISTOFEV23!O30+HISTOMARS23!O30+HISTOAVRIL23!O30+HISTOMAI23!O30+HISTOJUIN23!O30+HISTOJUIL23!O30+HISTOAOUT23!O30+HISTOSEPT23!O30+HISTOOCT23!O30+HISTONOV23!O30+HISTODEC23!O30 -> 0 | P30: =HISTOJANV23!P30+HISTOFEV23!P30+HISTOMARS23!P30+HISTOAVRIL23!P30+HISTOMAI23!P30+HISTOJUIN23!P30+HISTOJUIL23!P30+HISTOAOUT23!P30+HISTOSEPT23!P30+HISTOOCT23!P30+HISTONOV23!P30+HISTODEC23!P30 -> 0 | ... T30: =HISTOJANV23!T30+HISTOFEV23!T30+HISTOMARS23!T30+HISTOAVRIL23!T30+HISTOMAI23!T30+HISTOJUIN23!T30+HISTOJUIL23!T30+HISTOAOUT23!T30+HISTOSEPT23!T30+HISTOOCT23!T30+HISTONOV23!T30+HISTODEC23!T30 -> 0 | U30: =G30+S30++R30+P30+O30+M30+I30+K30+Q30+V30+W30 -> 1414000 | V30: =HISTOJANV23!V30+HISTOFEV23!V30+HISTOMARS23!V30+HISTOAVRIL23!V30+HISTOMAI23!V30+HISTOJUIN23!V30+HISTOJUIL23!V30+HISTOAOUT23!V30+HISTOSEPT23!V30+HISTOOCT23!V30+HISTONOV23!V30+HISTODEC23!V30 -> 34000 | W30: =HISTOJANV23!W30+HISTOFEV23!W30+HISTOMARS23!W30+HISTOAVRIL23!W30+HISTOMAI23!W30+HISTOJUIN23!W30+HISTOJUIL23!W30+HISTOAOUT23!W30+HISTOSEPT23!W30+HISTOOCT23!W30+HISTONOV23!W30+HISTODEC23!W30 -> 0 | X30: =HISTOJANV23!X30+HISTOFEV23!X30+HISTOMARS23!X30+HISTOAVRIL23!X30+HISTOMAI23!X30+HISTOJUIN23!X30+HISTOJUIL23!X30+HISTOAOUT23!X30+HISTOSEPT23!X30+HISTOOCT23!X30+HISTONOV23!X30+HISTODEC23!X30 -> 0 | Y30: =HISTOJANV23!Y30+HISTOFEV23!Y30+HISTOMARS23!Y30+HISTOAVRIL23!Y30+HISTOMAI23!Y30+HISTOJUIN23!Y30+HISTOJUIL23!Y30+HISTOAOUT23!Y30+HISTOSEPT23!Y30+HISTOOCT23!Y30+HISTONOV23!Y30+HISTODEC23!Y30 -> 0 | Z30: =HISTOJANV23!Z30+HISTOFEV23!Z30+HISTOMARS23!Z30+HISTOAVRIL23!Z30+HISTOMAI23!Z30+HISTOJUIN23!Z30+HISTOJUIL23!Z30+HISTOAOUT23!Z30+HISTOSEPT23!Z30+HISTOOCT23!Z30+HISTONOV23!Z30+HISTODEC23!Z30 -> 1000000 | AA30: =HISTOJANV23!AA30+HISTOFEV23!AA30+HISTOMARS23!AA30+HISTOAVRIL23!AA30+HISTOMAI23!AA30+HISTOJUIN23!AA30+HISTOJUIL23!AA30+HISTOAOUT23!AA30+HISTOSEPT23!AA30+HISTOOCT23!AA30+HISTONOV23!AA30+HISTODEC23!AA30 -> #VALUE! | AB30: =HISTOJANV23!AB30+HISTOFEV23!AB30+HISTOMARS23!AB30+HISTOAVRIL23!AB30+HISTOMAI23!AB30+HISTOJUIN23!AB30+HISTOJUIL23!AB30+HISTOAOUT23!AB30+HISTOSEPT23!AB30+HISTOOCT23!AB30+HISTONOV23!AB30+HISTODEC23!AB30 -> 0 | AC30: =HISTOJANV23!AC30+HISTOFEV23!AC30+HISTOMARS23!AC30+HISTOAVRIL23!AC30+HISTOMAI23!AC30+HISTOJUIN23!AC30+HISTOJUIL23!AC30+HISTOAOUT23!AC30+HISTOSEPT23!AC30+HISTOOCT23!AC30+HISTONOV23!AC30+HISTODEC23!AC30 -> 3000 | ... BM30: =HISTOJANV23!BM30+HISTOFEV23!BM30+HISTOMARS23!BM30+HISTOAVRIL23!BM30+HISTOMAI23!BM30+HISTOJUIN23!BM30+HISTOJUIL23!BM30+HISTOAOUT23!BM30+HISTOSEPT23!BM30+HISTOOCT23!BM30+HISTONOV23!BM30+HISTODEC23!BM30 -> 0 | BN30: DECES | BO30: MUTUELLE | BP30: =HISTOJANV23!BP30+HISTOFEV23!BP30+HISTOMARS23!BP30+HISTOAVRIL23!BP30+HISTOMAI23!BP30+HISTOJUIN23!BP30+HISTOJUIL23!BP30+HISTOAOUT23!BP30+HISTOSEPT23!BP30+HISTOOCT23!BP30+HISTONOV23!BP30+HISTODEC23!BP30 -> 1320000
A31: AS201638 | B31: =VLOOKUP(A31,[17]LISTADHERENT!A$5:H$39,3,0) -> SIMO PIERRE | C31: =HISTOJANV23!C31+HISTOFEV23!C31+HISTOMARS23!C31+HISTOAVRIL23!C31+HISTOMAI23!C31+HISTOJUIN23!C31+HISTOJUIL23!C31+HISTOAOUT23!C31+HISTOSEPT23!C31+HISTOOCT23!C31+HISTONOV23!C31+HISTODEC23!C31 -> -70000 | D31: =HISTOJANV23!D31+HISTOFEV23!D31+HISTOMARS23!D31+HISTOAVRIL23!D31+HISTOMAI23!D31+HISTOJUIN23!D31+HISTOJUIL23!D31+HISTOAOUT23!D31+HISTOSEPT23!D31+HISTOOCT23!D31+HISTONOV23!D31+HISTODEC23!D31 -> 2743000 | E31: =HISTOJANV23!E31+HISTOFEV23!E31+HISTOMARS23!E31+HISTOAVRIL23!E31+HISTOMAI23!E31+HISTOJUIN23!E31+HISTOJUIL23!E31+HISTOAOUT23!E31+HISTOSEPT23!E31+HISTOOCT23!E31+HISTONOV23!E31+HISTODEC23!E31 -> 140000 | F31: =HISTOJANV23!F31+HISTOFEV23!F31+HISTOMARS23!F31+HISTOAVRIL23!F31+HISTOMAI23!F31+HISTOJUIN23!F31+HISTOJUIL23!F31+HISTOAOUT23!F31+HISTOSEPT23!F31+HISTOOCT23!F31+HISTONOV23!F31+HISTODEC23!F31 -> 0 | G31: =HISTOJANV23!G31+HISTOFEV23!G31+HISTOMARS23!G31+HISTOAVRIL23!G31+HISTOMAI23!G31+HISTOJUIN23!G31+HISTOJUIL23!G31+HISTOAOUT23!G31+HISTOSEPT23!G31+HISTOOCT23!G31+HISTONOV23!G31+HISTODEC23!G31 -> 0 | H31: =IF($D31<>0,"BANQUE",IF($E31<>0,"ESPECES","ECHEC")) -> BANQUE | I31: =HISTOJANV23!I31+HISTOFEV23!I31+HISTOMARS23!I31+HISTOAVRIL23!I31+HISTOMAI23!I31+HISTOJUIN23!I31+HISTOJUIL23!I31+HISTOAOUT23!I31+HISTOSEPT23!I31+HISTOOCT23!I31+HISTONOV23!I31+HISTODEC23!I31 -> 110500 | J31: =HISTOJANV23!J31+HISTOFEV23!J31+HISTOMARS23!J31+HISTOAVRIL23!J31+HISTOMAI23!J31+HISTOJUIN23!J31+HISTOJUIL23!J31+HISTOAOUT23!J31+HISTOSEPT23!J31+HISTOOCT23!J31+HISTONOV23!J31+HISTODEC23!J31 -> 12 | K31: =HISTOJANV23!K31+HISTOFEV23!K31+HISTOMARS23!K31+HISTOAVRIL23!K31+HISTOMAI23!K31+HISTOJUIN23!K31+HISTOJUIL23!K31+HISTOAOUT23!K31+HISTOSEPT23!K31+HISTOOCT23!K31+HISTONOV23!K31+HISTODEC23!K31 -> 480000 | L31: =HISTOJANV23!L31+HISTOFEV23!L31+HISTOMARS23!L31+HISTOAVRIL23!L31+HISTOMAI23!L31+HISTOJUIN23!L31+HISTOJUIL23!L31+HISTOAOUT23!L31+HISTOSEPT23!L31+HISTOOCT23!L31+HISTONOV23!L31+HISTODEC23!L31 -> 0 | M31: =HISTOJANV23!M31+HISTOFEV23!M31+HISTOMARS23!M31+HISTOAVRIL23!M31+HISTOMAI23!M31+HISTOJUIN23!M31+HISTOJUIL23!M31+HISTOAOUT23!M31+HISTOSEPT23!M31+HISTOOCT23!M31+HISTONOV23!M31+HISTODEC23!M31 -> 0 | N31: =HISTOJANV23!N31+HISTOFEV23!N31+HISTOMARS23!N31+HISTOAVRIL23!N31+HISTOMAI23!N31+HISTOJUIN23!N31+HISTOJUIL23!N31+HISTOAOUT23!N31+HISTOSEPT23!N31+HISTOOCT23!N31+HISTONOV23!N31+HISTODEC23!N31 -> 12 | O31: =HISTOJANV23!O31+HISTOFEV23!O31+HISTOMARS23!O31+HISTOAVRIL23!O31+HISTOMAI23!O31+HISTOJUIN23!O31+HISTOJUIL23!O31+HISTOAOUT23!O31+HISTOSEPT23!O31+HISTOOCT23!O31+HISTONOV23!O31+HISTODEC23!O31 -> 1200000 | P31: =HISTOJANV23!P31+HISTOFEV23!P31+HISTOMARS23!P31+HISTOAVRIL23!P31+HISTOMAI23!P31+HISTOJUIN23!P31+HISTOJUIL23!P31+HISTOAOUT23!P31+HISTOSEPT23!P31+HISTOOCT23!P31+HISTONOV23!P31+HISTODEC23!P31 -> 30500 | ... T31: =HISTOJANV23!T31+HISTOFEV23!T31+HISTOMARS23!T31+HISTOAVRIL23!T31+HISTOMAI23!T31+HISTOJUIN23!T31+HISTOJUIL23!T31+HISTOAOUT23!T31+HISTOSEPT23!T31+HISTOOCT23!T31+HISTONOV23!T31+HISTODEC23!T31 -> #VALUE! | U31: =G31+S31++R31+P31+O31+M31+I31+K31+Q31+V31+W31 -> 2883000 | V31: =HISTOJANV23!V31+HISTOFEV23!V31+HISTOMARS23!V31+HISTOAVRIL23!V31+HISTOMAI23!V31+HISTOJUIN23!V31+HISTOJUIL23!V31+HISTOAOUT23!V31+HISTOSEPT23!V31+HISTOOCT23!V31+HISTONOV23!V31+HISTODEC23!V31 -> 0 | W31: =HISTOJANV23!W31+HISTOFEV23!W31+HISTOMARS23!W31+HISTOAVRIL23!W31+HISTOMAI23!W31+HISTOJUIN23!W31+HISTOJUIL23!W31+HISTOAOUT23!W31+HISTOSEPT23!W31+HISTOOCT23!W31+HISTONOV23!W31+HISTODEC23!W31 -> 0 | X31: =HISTOJANV23!X31+HISTOFEV23!X31+HISTOMARS23!X31+HISTOAVRIL23!X31+HISTOMAI23!X31+HISTOJUIN23!X31+HISTOJUIL23!X31+HISTOAOUT23!X31+HISTOSEPT23!X31+HISTOOCT23!X31+HISTONOV23!X31+HISTODEC23!X31 -> 0 | Y31: =HISTOJANV23!Y31+HISTOFEV23!Y31+HISTOMARS23!Y31+HISTOAVRIL23!Y31+HISTOMAI23!Y31+HISTOJUIN23!Y31+HISTOJUIL23!Y31+HISTOAOUT23!Y31+HISTOSEPT23!Y31+HISTOOCT23!Y31+HISTONOV23!Y31+HISTODEC23!Y31 -> 0 | Z31: =HISTOJANV23!Z31+HISTOFEV23!Z31+HISTOMARS23!Z31+HISTOAVRIL23!Z31+HISTOMAI23!Z31+HISTOJUIN23!Z31+HISTOJUIL23!Z31+HISTOAOUT23!Z31+HISTOSEPT23!Z31+HISTOOCT23!Z31+HISTONOV23!Z31+HISTODEC23!Z31 -> 250000 | AA31: =HISTOJANV23!AA31+HISTOFEV23!AA31+HISTOMARS23!AA31+HISTOAVRIL23!AA31+HISTOMAI23!AA31+HISTOJUIN23!AA31+HISTOJUIL23!AA31+HISTOAOUT23!AA31+HISTOSEPT23!AA31+HISTOOCT23!AA31+HISTONOV23!AA31+HISTODEC23!AA31 -> #VALUE! | AB31: =HISTOJANV23!AB31+HISTOFEV23!AB31+HISTOMARS23!AB31+HISTOAVRIL23!AB31+HISTOMAI23!AB31+HISTOJUIN23!AB31+HISTOJUIL23!AB31+HISTOAOUT23!AB31+HISTOSEPT23!AB31+HISTOOCT23!AB31+HISTONOV23!AB31+HISTODEC23!AB31 -> 0 | AC31: =HISTOJANV23!AC31+HISTOFEV23!AC31+HISTOMARS23!AC31+HISTOAVRIL23!AC31+HISTOMAI23!AC31+HISTOJUIN23!AC31+HISTOJUIL23!AC31+HISTOAOUT23!AC31+HISTOSEPT23!AC31+HISTOOCT23!AC31+HISTONOV23!AC31+HISTODEC23!AC31 -> 11000 | ... BM31: =HISTOJANV23!BM31+HISTOFEV23!BM31+HISTOMARS23!BM31+HISTOAVRIL23!BM31+HISTOMAI23!BM31+HISTOJUIN23!BM31+HISTOJUIL23!BM31+HISTOAOUT23!BM31+HISTOSEPT23!BM31+HISTOOCT23!BM31+HISTONOV23!BM31+HISTODEC23!BM31 -> 0 | BN31: TRANSPORT DELEGUE | BO31: MUTUELLE | BP31: =HISTOJANV23!BP31+HISTOFEV23!BP31+HISTOMARS23!BP31+HISTOAVRIL23!BP31+HISTOMAI23!BP31+HISTOJUIN23!BP31+HISTOJUIL23!BP31+HISTOAOUT23!BP31+HISTOSEPT23!BP31+HISTOOCT23!BP31+HISTONOV23!BP31+HISTODEC23!BP31 -> 0
A32: AS201641 | B32: =VLOOKUP(A32,[17]LISTADHERENT!A$5:H$39,3,0) -> TCHOUAMOU MATHIEU | C32: =HISTOJANV23!C32+HISTOFEV23!C32+HISTOMARS23!C32+HISTOAVRIL23!C32+HISTOMAI23!C32+HISTOJUIN23!C32+HISTOJUIL23!C32+HISTOAOUT23!C32+HISTOSEPT23!C32+HISTOOCT23!C32+HISTONOV23!C32+HISTODEC23!C32 -> -200000 | D32: =HISTOJANV23!D32+HISTOFEV23!D32+HISTOMARS23!D32+HISTOAVRIL23!D32+HISTOMAI23!D32+HISTOJUIN23!D32+HISTOJUIL23!D32+HISTOAOUT23!D32+HISTOSEPT23!D32+HISTOOCT23!D32+HISTONOV23!D32+HISTODEC23!D32 -> 2575000 | E32: =HISTOJANV23!E32+HISTOFEV23!E32+HISTOMARS23!E32+HISTOAVRIL23!E32+HISTOMAI23!E32+HISTOJUIN23!E32+HISTOJUIL23!E32+HISTOAOUT23!E32+HISTOSEPT23!E32+HISTOOCT23!E32+HISTONOV23!E32+HISTODEC23!E32 -> 102000 | F32: =HISTOJANV23!F32+HISTOFEV23!F32+HISTOMARS23!F32+HISTOAVRIL23!F32+HISTOMAI23!F32+HISTOJUIN23!F32+HISTOJUIL23!F32+HISTOAOUT23!F32+HISTOSEPT23!F32+HISTOOCT23!F32+HISTONOV23!F32+HISTODEC23!F32 -> 70000 | G32: =HISTOJANV23!G32+HISTOFEV23!G32+HISTOMARS23!G32+HISTOAVRIL23!G32+HISTOMAI23!G32+HISTOJUIN23!G32+HISTOJUIL23!G32+HISTOAOUT23!G32+HISTOSEPT23!G32+HISTOOCT23!G32+HISTONOV23!G32+HISTODEC23!G32 -> 0 | H32: =IF($D32<>0,"BANQUE",IF($E32<>0,"ESPECES","ECHEC")) -> BANQUE | I32: =HISTOJANV23!I32+HISTOFEV23!I32+HISTOMARS23!I32+HISTOAVRIL23!I32+HISTOMAI23!I32+HISTOJUIN23!I32+HISTOJUIL23!I32+HISTOAOUT23!I32+HISTOSEPT23!I32+HISTOOCT23!I32+HISTONOV23!I32+HISTODEC23!I32 -> 0 | J32: =HISTOJANV23!J32+HISTOFEV23!J32+HISTOMARS23!J32+HISTOAVRIL23!J32+HISTOMAI23!J32+HISTOJUIN23!J32+HISTOJUIL23!J32+HISTOAOUT23!J32+HISTOSEPT23!J32+HISTOOCT23!J32+HISTONOV23!J32+HISTODEC23!J32 -> 12 | K32: =HISTOJANV23!K32+HISTOFEV23!K32+HISTOMARS23!K32+HISTOAVRIL23!K32+HISTOMAI23!K32+HISTOJUIN23!K32+HISTOJUIL23!K32+HISTOAOUT23!K32+HISTOSEPT23!K32+HISTOOCT23!K32+HISTONOV23!K32+HISTODEC23!K32 -> 480000 | L32: =HISTOJANV23!L32+HISTOFEV23!L32+HISTOMARS23!L32+HISTOAVRIL23!L32+HISTOMAI23!L32+HISTOJUIN23!L32+HISTOJUIL23!L32+HISTOAOUT23!L32+HISTOSEPT23!L32+HISTOOCT23!L32+HISTONOV23!L32+HISTODEC23!L32 -> 12 | M32: =HISTOJANV23!M32+HISTOFEV23!M32+HISTOMARS23!M32+HISTOAVRIL23!M32+HISTOMAI23!M32+HISTOJUIN23!M32+HISTOJUIL23!M32+HISTOAOUT23!M32+HISTOSEPT23!M32+HISTOOCT23!M32+HISTONOV23!M32+HISTODEC23!M32 -> 900000 | N32: =HISTOJANV23!N32+HISTOFEV23!N32+HISTOMARS23!N32+HISTOAVRIL23!N32+HISTOMAI23!N32+HISTOJUIN23!N32+HISTOJUIL23!N32+HISTOAOUT23!N32+HISTOSEPT23!N32+HISTOOCT23!N32+HISTONOV23!N32+HISTODEC23!N32 -> 0 | O32: =HISTOJANV23!O32+HISTOFEV23!O32+HISTOMARS23!O32+HISTOAVRIL23!O32+HISTOMAI23!O32+HISTOJUIN23!O32+HISTOJUIL23!O32+HISTOAOUT23!O32+HISTOSEPT23!O32+HISTOOCT23!O32+HISTONOV23!O32+HISTODEC23!O32 -> 0 | P32: =HISTOJANV23!P32+HISTOFEV23!P32+HISTOMARS23!P32+HISTOAVRIL23!P32+HISTOMAI23!P32+HISTOJUIN23!P32+HISTOJUIL23!P32+HISTOAOUT23!P32+HISTOSEPT23!P32+HISTOOCT23!P32+HISTONOV23!P32+HISTODEC23!P32 -> 0 | ... T32: =HISTOJANV23!T32+HISTOFEV23!T32+HISTOMARS23!T32+HISTOAVRIL23!T32+HISTOMAI23!T32+HISTOJUIN23!T32+HISTOJUIL23!T32+HISTOAOUT23!T32+HISTOSEPT23!T32+HISTOOCT23!T32+HISTONOV23!T32+HISTODEC23!T32 -> #VALUE! | U32: =G32+S32++R32+P32+O32+M32+I32+K32+Q32+V32+W32 -> 2877000 | V32: =HISTOJANV23!V32+HISTOFEV23!V32+HISTOMARS23!V32+HISTOAVRIL23!V32+HISTOMAI23!V32+HISTOJUIN23!V32+HISTOJUIL23!V32+HISTOAOUT23!V32+HISTOSEPT23!V32+HISTOOCT23!V32+HISTONOV23!V32+HISTODEC23!V32 -> 0 | W32: =HISTOJANV23!W32+HISTOFEV23!W32+HISTOMARS23!W32+HISTOAVRIL23!W32+HISTOMAI23!W32+HISTOJUIN23!W32+HISTOJUIL23!W32+HISTOAOUT23!W32+HISTOSEPT23!W32+HISTOOCT23!W32+HISTONOV23!W32+HISTODEC23!W32 -> 0 | X32: =HISTOJANV23!X32+HISTOFEV23!X32+HISTOMARS23!X32+HISTOAVRIL23!X32+HISTOMAI23!X32+HISTOJUIN23!X32+HISTOJUIL23!X32+HISTOAOUT23!X32+HISTOSEPT23!X32+HISTOOCT23!X32+HISTONOV23!X32+HISTODEC23!X32 -> 0 | Y32: =HISTOJANV23!Y32+HISTOFEV23!Y32+HISTOMARS23!Y32+HISTOAVRIL23!Y32+HISTOMAI23!Y32+HISTOJUIN23!Y32+HISTOJUIL23!Y32+HISTOAOUT23!Y32+HISTOSEPT23!Y32+HISTOOCT23!Y32+HISTONOV23!Y32+HISTODEC23!Y32 -> 0 | Z32: =HISTOJANV23!Z32+HISTOFEV23!Z32+HISTOMARS23!Z32+HISTOAVRIL23!Z32+HISTOMAI23!Z32+HISTOJUIN23!Z32+HISTOJUIL23!Z32+HISTOAOUT23!Z32+HISTOSEPT23!Z32+HISTOOCT23!Z32+HISTONOV23!Z32+HISTODEC23!Z32 -> 900000 | AA32: =HISTOJANV23!AA32+HISTOFEV23!AA32+HISTOMARS23!AA32+HISTOAVRIL23!AA32+HISTOMAI23!AA32+HISTOJUIN23!AA32+HISTOJUIL23!AA32+HISTOAOUT23!AA32+HISTOSEPT23!AA32+HISTOOCT23!AA32+HISTONOV23!AA32+HISTODEC23!AA32 -> #VALUE! | AB32: =HISTOJANV23!AB32+HISTOFEV23!AB32+HISTOMARS23!AB32+HISTOAVRIL23!AB32+HISTOMAI23!AB32+HISTOJUIN23!AB32+HISTOJUIL23!AB32+HISTOAOUT23!AB32+HISTOSEPT23!AB32+HISTOOCT23!AB32+HISTONOV23!AB32+HISTODEC23!AB32 -> 0 | AC32: =HISTOJANV23!AC32+HISTOFEV23!AC32+HISTOMARS23!AC32+HISTOAVRIL23!AC32+HISTOMAI23!AC32+HISTOJUIN23!AC32+HISTOJUIL23!AC32+HISTOAOUT23!AC32+HISTOSEPT23!AC32+HISTOOCT23!AC32+HISTONOV23!AC32+HISTODEC23!AC32 -> 2500 | ... BM32: =HISTOJANV23!BM32+HISTOFEV23!BM32+HISTOMARS23!BM32+HISTOAVRIL23!BM32+HISTOMAI23!BM32+HISTOJUIN23!BM32+HISTOJUIL23!BM32+HISTOAOUT23!BM32+HISTOSEPT23!BM32+HISTOOCT23!BM32+HISTONOV23!BM32+HISTODEC23!BM32 -> 0
A33: AS201643 | B33: =VLOOKUP(A33,[17]LISTADHERENT!A$5:H$39,3,0) -> TCHOUTOU NANA CLAUDE | C33: =HISTOJANV23!C33+HISTOFEV23!C33+HISTOMARS23!C33+HISTOAVRIL23!C33+HISTOMAI23!C33+HISTOJUIN23!C33+HISTOJUIL23!C33+HISTOAOUT23!C33+HISTOSEPT23!C33+HISTOOCT23!C33+HISTONOV23!C33+HISTODEC23!C33 -> 117000 | D33: =HISTOJANV23!D33+HISTOFEV23!D33+HISTOMARS23!D33+HISTOAVRIL23!D33+HISTOMAI23!D33+HISTOJUIN23!D33+HISTOJUIL23!D33+HISTOAOUT23!D33+HISTOSEPT23!D33+HISTOOCT23!D33+HISTONOV23!D33+HISTODEC23!D33 -> 450000 | E33: =HISTOJANV23!E33+HISTOFEV23!E33+HISTOMARS23!E33+HISTOAVRIL23!E33+HISTOMAI23!E33+HISTOJUIN23!E33+HISTOJUIL23!E33+HISTOAOUT23!E33+HISTOSEPT23!E33+HISTOOCT23!E33+HISTONOV23!E33+HISTODEC23!E33 -> 163000 | F33: =HISTOJANV23!F33+HISTOFEV23!F33+HISTOMARS23!F33+HISTOAVRIL23!F33+HISTOMAI23!F33+HISTOJUIN23!F33+HISTOJUIL23!F33+HISTOAOUT23!F33+HISTOSEPT23!F33+HISTOOCT23!F33+HISTONOV23!F33+HISTODEC23!F33 -> 0 | G33: =HISTOJANV23!G33+HISTOFEV23!G33+HISTOMARS23!G33+HISTOAVRIL23!G33+HISTOMAI23!G33+HISTOJUIN23!G33+HISTOJUIL23!G33+HISTOAOUT23!G33+HISTOSEPT23!G33+HISTOOCT23!G33+HISTONOV23!G33+HISTODEC23!G33 -> 18000 | H33: =IF($D33<>0,"BANQUE",IF($E33<>0,"ESPECES","ECHEC")) -> BANQUE | I33: =HISTOJANV23!I33+HISTOFEV23!I33+HISTOMARS23!I33+HISTOAVRIL23!I33+HISTOMAI23!I33+HISTOJUIN23!I33+HISTOJUIL23!I33+HISTOAOUT23!I33+HISTOSEPT23!I33+HISTOOCT23!I33+HISTONOV23!I33+HISTODEC23!I33 -> -2000 | J33: =HISTOJANV23!J33+HISTOFEV23!J33+HISTOMARS23!J33+HISTOAVRIL23!J33+HISTOMAI23!J33+HISTOJUIN23!J33+HISTOJUIL23!J33+HISTOAOUT23!J33+HISTOSEPT23!J33+HISTOOCT23!J33+HISTONOV23!J33+HISTODEC23!J33 -> 12 | K33: =HISTOJANV23!K33+HISTOFEV23!K33+HISTOMARS23!K33+HISTOAVRIL23!K33+HISTOMAI23!K33+HISTOJUIN23!K33+HISTOJUIL23!K33+HISTOAOUT23!K33+HISTOSEPT23!K33+HISTOOCT23!K33+HISTONOV23!K33+HISTODEC23!K33 -> 480000 | L33: =HISTOJANV23!L33+HISTOFEV23!L33+HISTOMARS23!L33+HISTOAVRIL23!L33+HISTOMAI23!L33+HISTOJUIN23!L33+HISTOJUIL23!L33+HISTOAOUT23!L33+HISTOSEPT23!L33+HISTOOCT23!L33+HISTONOV23!L33+HISTODEC23!L33 -> 0 | M33: =HISTOJANV23!M33+HISTOFEV23!M33+HISTOMARS23!M33+HISTOAVRIL23!M33+HISTOMAI23!M33+HISTOJUIN23!M33+HISTOJUIL23!M33+HISTOAOUT23!M33+HISTOSEPT23!M33+HISTOOCT23!M33+HISTONOV23!M33+HISTODEC23!M33 -> 0 | N33: =HISTOJANV23!N33+HISTOFEV23!N33+HISTOMARS23!N33+HISTOAVRIL23!N33+HISTOMAI23!N33+HISTOJUIN23!N33+HISTOJUIL23!N33+HISTOAOUT23!N33+HISTOSEPT23!N33+HISTOOCT23!N33+HISTONOV23!N33+HISTODEC23!N33 -> 0 | O33: =HISTOJANV23!O33+HISTOFEV23!O33+HISTOMARS23!O33+HISTOAVRIL23!O33+HISTOMAI23!O33+HISTOJUIN23!O33+HISTOJUIL23!O33+HISTOAOUT23!O33+HISTOSEPT23!O33+HISTOOCT23!O33+HISTONOV23!O33+HISTODEC23!O33 -> 0 | P33: =HISTOJANV23!P33+HISTOFEV23!P33+HISTOMARS23!P33+HISTOAVRIL23!P33+HISTOMAI23!P33+HISTOJUIN23!P33+HISTOJUIL23!P33+HISTOAOUT23!P33+HISTOSEPT23!P33+HISTOOCT23!P33+HISTONOV23!P33+HISTODEC23!P33 -> 0 | ... T33: =HISTOJANV23!T33+HISTOFEV23!T33+HISTOMARS23!T33+HISTOAVRIL23!T33+HISTOMAI23!T33+HISTOJUIN23!T33+HISTOJUIL23!T33+HISTOAOUT23!T33+HISTOSEPT23!T33+HISTOOCT23!T33+HISTONOV23!T33+HISTODEC23!T33 -> 0 | U33: =G33+S33++R33+P33+O33+M33+I33+K33+Q33+V33+W33 -> 496000 | V33: =HISTOJANV23!V33+HISTOFEV23!V33+HISTOMARS23!V33+HISTOAVRIL23!V33+HISTOMAI23!V33+HISTOJUIN23!V33+HISTOJUIL23!V33+HISTOAOUT23!V33+HISTOSEPT23!V33+HISTOOCT23!V33+HISTONOV23!V33+HISTODEC23!V33 -> 0 | W33: =HISTOJANV23!W33+HISTOFEV23!W33+HISTOMARS23!W33+HISTOAVRIL23!W33+HISTOMAI23!W33+HISTOJUIN23!W33+HISTOJUIL23!W33+HISTOAOUT23!W33+HISTOSEPT23!W33+HISTOOCT23!W33+HISTONOV23!W33+HISTODEC23!W33 -> 0 | X33: =HISTOJANV23!X33+HISTOFEV23!X33+HISTOMARS23!X33+HISTOAVRIL23!X33+HISTOMAI23!X33+HISTOJUIN23!X33+HISTOJUIL23!X33+HISTOAOUT23!X33+HISTOSEPT23!X33+HISTOOCT23!X33+HISTONOV23!X33+HISTODEC23!X33 -> 0 | Y33: =HISTOJANV23!Y33+HISTOFEV23!Y33+HISTOMARS23!Y33+HISTOAVRIL23!Y33+HISTOMAI23!Y33+HISTOJUIN23!Y33+HISTOJUIL23!Y33+HISTOAOUT23!Y33+HISTOSEPT23!Y33+HISTOOCT23!Y33+HISTONOV23!Y33+HISTODEC23!Y33 -> 0 | Z33: =HISTOJANV23!Z33+HISTOFEV23!Z33+HISTOMARS23!Z33+HISTOAVRIL23!Z33+HISTOMAI23!Z33+HISTOJUIN23!Z33+HISTOJUIL23!Z33+HISTOAOUT23!Z33+HISTOSEPT23!Z33+HISTOOCT23!Z33+HISTONOV23!Z33+HISTODEC23!Z33 -> 0 | AA33: =HISTOJANV23!AA33+HISTOFEV23!AA33+HISTOMARS23!AA33+HISTOAVRIL23!AA33+HISTOMAI23!AA33+HISTOJUIN23!AA33+HISTOJUIL23!AA33+HISTOAOUT23!AA33+HISTOSEPT23!AA33+HISTOOCT23!AA33+HISTONOV23!AA33+HISTODEC23!AA33 -> 0 | AB33: =HISTOJANV23!AB33+HISTOFEV23!AB33+HISTOMARS23!AB33+HISTOAVRIL23!AB33+HISTOMAI23!AB33+HISTOJUIN23!AB33+HISTOJUIL23!AB33+HISTOAOUT23!AB33+HISTOSEPT23!AB33+HISTOOCT23!AB33+HISTONOV23!AB33+HISTODEC23!AB33 -> 0 | AC33: =HISTOJANV23!AC33+HISTOFEV23!AC33+HISTOMARS23!AC33+HISTOAVRIL23!AC33+HISTOMAI23!AC33+HISTOJUIN23!AC33+HISTOJUIL23!AC33+HISTOAOUT23!AC33+HISTOSEPT23!AC33+HISTOOCT23!AC33+HISTONOV23!AC33+HISTODEC23!AC33 -> 2500 | ... BM33: =HISTOJANV23!BM33+HISTOFEV23!BM33+HISTOMARS23!BM33+HISTOAVRIL23!BM33+HISTOMAI23!BM33+HISTOJUIN23!BM33+HISTOJUIL23!BM33+HISTOAOUT23!BM33+HISTOSEPT23!BM33+HISTOOCT23!BM33+HISTONOV23!BM33+HISTODEC23!BM33 -> 0 | BN33: S/TOTAL | BP33: =SUM(BP30:BP32) -> 1320000
A34: AS201658 | B34: =VLOOKUP(A34,[17]LISTADHERENT!A$5:H$39,3,0) -> YANTCHOU GERVAIS | C34: =HISTOJANV23!C34+HISTOFEV23!C34+HISTOMARS23!C34+HISTOAVRIL23!C34+HISTOMAI23!C34+HISTOJUIN23!C34+HISTOJUIL23!C34+HISTOAOUT23!C34+HISTOSEPT23!C34+HISTOOCT23!C34+HISTONOV23!C34+HISTODEC23!C34 -> -107500 | D34: =HISTOJANV23!D34+HISTOFEV23!D34+HISTOMARS23!D34+HISTOAVRIL23!D34+HISTOMAI23!D34+HISTOJUIN23!D34+HISTOJUIL23!D34+HISTOAOUT23!D34+HISTOSEPT23!D34+HISTOOCT23!D34+HISTONOV23!D34+HISTODEC23!D34 -> 830000 | E34: =HISTOJANV23!E34+HISTOFEV23!E34+HISTOMARS23!E34+HISTOAVRIL23!E34+HISTOMAI23!E34+HISTOJUIN23!E34+HISTOJUIL23!E34+HISTOAOUT23!E34+HISTOSEPT23!E34+HISTOOCT23!E34+HISTONOV23!E34+HISTODEC23!E34 -> 200000 | F34: =HISTOJANV23!F34+HISTOFEV23!F34+HISTOMARS23!F34+HISTOAVRIL23!F34+HISTOMAI23!F34+HISTOJUIN23!F34+HISTOJUIL23!F34+HISTOAOUT23!F34+HISTOSEPT23!F34+HISTOOCT23!F34+HISTONOV23!F34+HISTODEC23!F34 -> 70000 | G34: =HISTOJANV23!G34+HISTOFEV23!G34+HISTOMARS23!G34+HISTOAVRIL23!G34+HISTOMAI23!G34+HISTOJUIN23!G34+HISTOJUIL23!G34+HISTOAOUT23!G34+HISTOSEPT23!G34+HISTOOCT23!G34+HISTONOV23!G34+HISTODEC23!G34 -> 3000 | H34: =IF($D34<>0,"BANQUE",IF($E34<>0,"ESPECES","ECHEC")) -> BANQUE | I34: =HISTOJANV23!I34+HISTOFEV23!I34+HISTOMARS23!I34+HISTOAVRIL23!I34+HISTOMAI23!I34+HISTOJUIN23!I34+HISTOJUIL23!I34+HISTOAOUT23!I34+HISTOSEPT23!I34+HISTOOCT23!I34+HISTONOV23!I34+HISTODEC23!I34 -> 629500 | J34: =HISTOJANV23!J34+HISTOFEV23!J34+HISTOMARS23!J34+HISTOAVRIL23!J34+HISTOMAI23!J34+HISTOJUIN23!J34+HISTOJUIL23!J34+HISTOAOUT23!J34+HISTOSEPT23!J34+HISTOOCT23!J34+HISTONOV23!J34+HISTODEC23!J34 -> 12 | K34: =HISTOJANV23!K34+HISTOFEV23!K34+HISTOMARS23!K34+HISTOAVRIL23!K34+HISTOMAI23!K34+HISTOJUIN23!K34+HISTOJUIL23!K34+HISTOAOUT23!K34+HISTOSEPT23!K34+HISTOOCT23!K34+HISTONOV23!K34+HISTODEC23!K34 -> 480000 | L34: =HISTOJANV23!L34+HISTOFEV23!L34+HISTOMARS23!L34+HISTOAVRIL23!L34+HISTOMAI23!L34+HISTOJUIN23!L34+HISTOJUIL23!L34+HISTOAOUT23!L34+HISTOSEPT23!L34+HISTOOCT23!L34+HISTONOV23!L34+HISTODEC23!L34 -> 0 | M34: =HISTOJANV23!M34+HISTOFEV23!M34+HISTOMARS23!M34+HISTOAVRIL23!M34+HISTOMAI23!M34+HISTOJUIN23!M34+HISTOJUIL23!M34+HISTOAOUT23!M34+HISTOSEPT23!M34+HISTOOCT23!M34+HISTONOV23!M34+HISTODEC23!M34 -> 0 | N34: =HISTOJANV23!N34+HISTOFEV23!N34+HISTOMARS23!N34+HISTOAVRIL23!N34+HISTOMAI23!N34+HISTOJUIN23!N34+HISTOJUIL23!N34+HISTOAOUT23!N34+HISTOSEPT23!N34+HISTOOCT23!N34+HISTONOV23!N34+HISTODEC23!N34 -> 0 | O34: =HISTOJANV23!O34+HISTOFEV23!O34+HISTOMARS23!O34+HISTOAVRIL23!O34+HISTOMAI23!O34+HISTOJUIN23!O34+HISTOJUIL23!O34+HISTOAOUT23!O34+HISTOSEPT23!O34+HISTOOCT23!O34+HISTONOV23!O34+HISTODEC23!O34 -> 0 | P34: =HISTOJANV23!P34+HISTOFEV23!P34+HISTOMARS23!P34+HISTOAVRIL23!P34+HISTOMAI23!P34+HISTOJUIN23!P34+HISTOJUIL23!P34+HISTOAOUT23!P34+HISTOSEPT23!P34+HISTOOCT23!P34+HISTONOV23!P34+HISTODEC23!P34 -> 0 | ... T34: =HISTOJANV23!T34+HISTOFEV23!T34+HISTOMARS23!T34+HISTOAVRIL23!T34+HISTOMAI23!T34+HISTOJUIN23!T34+HISTOJUIL23!T34+HISTOAOUT23!T34+HISTOSEPT23!T34+HISTOOCT23!T34+HISTONOV23!T34+HISTODEC23!T34 -> 0 | U34: =G34+S34++R34+P34+O34+M34+I34+K34+Q34+V34+W34 -> 1137500 | V34: =HISTOJANV23!V34+HISTOFEV23!V34+HISTOMARS23!V34+HISTOAVRIL23!V34+HISTOMAI23!V34+HISTOJUIN23!V34+HISTOJUIL23!V34+HISTOAOUT23!V34+HISTOSEPT23!V34+HISTOOCT23!V34+HISTONOV23!V34+HISTODEC23!V34 -> 0 | W34: =HISTOJANV23!W34+HISTOFEV23!W34+HISTOMARS23!W34+HISTOAVRIL23!W34+HISTOMAI23!W34+HISTOJUIN23!W34+HISTOJUIL23!W34+HISTOAOUT23!W34+HISTOSEPT23!W34+HISTOOCT23!W34+HISTONOV23!W34+HISTODEC23!W34 -> 25000 | X34: =HISTOJANV23!X34+HISTOFEV23!X34+HISTOMARS23!X34+HISTOAVRIL23!X34+HISTOMAI23!X34+HISTOJUIN23!X34+HISTOJUIL23!X34+HISTOAOUT23!X34+HISTOSEPT23!X34+HISTOOCT23!X34+HISTONOV23!X34+HISTODEC23!X34 -> 0 | Y34: =HISTOJANV23!Y34+HISTOFEV23!Y34+HISTOMARS23!Y34+HISTOAVRIL23!Y34+HISTOMAI23!Y34+HISTOJUIN23!Y34+HISTOJUIL23!Y34+HISTOAOUT23!Y34+HISTOSEPT23!Y34+HISTOOCT23!Y34+HISTONOV23!Y34+HISTODEC23!Y34 -> 0 | Z34: =HISTOJANV23!Z34+HISTOFEV23!Z34+HISTOMARS23!Z34+HISTOAVRIL23!Z34+HISTOMAI23!Z34+HISTOJUIN23!Z34+HISTOJUIL23!Z34+HISTOAOUT23!Z34+HISTOSEPT23!Z34+HISTOOCT23!Z34+HISTONOV23!Z34+HISTODEC23!Z34 -> 700000 | AA34: =HISTOJANV23!AA34+HISTOFEV23!AA34+HISTOMARS23!AA34+HISTOAVRIL23!AA34+HISTOMAI23!AA34+HISTOJUIN23!AA34+HISTOJUIL23!AA34+HISTOAOUT23!AA34+HISTOSEPT23!AA34+HISTOOCT23!AA34+HISTONOV23!AA34+HISTODEC23!AA34 -> #VALUE! | AB34: =HISTOJANV23!AB34+HISTOFEV23!AB34+HISTOMARS23!AB34+HISTOAVRIL23!AB34+HISTOMAI23!AB34+HISTOJUIN23!AB34+HISTOJUIL23!AB34+HISTOAOUT23!AB34+HISTOSEPT23!AB34+HISTOOCT23!AB34+HISTONOV23!AB34+HISTODEC23!AB34 -> 0 | AC34: =HISTOJANV23!AC34+HISTOFEV23!AC34+HISTOMARS23!AC34+HISTOAVRIL23!AC34+HISTOMAI23!AC34+HISTOJUIN23!AC34+HISTOJUIL23!AC34+HISTOAOUT23!AC34+HISTOSEPT23!AC34+HISTOOCT23!AC34+HISTONOV23!AC34+HISTODEC23!AC34 -> 2500 | ... BM34: =HISTOJANV23!BM34+HISTOFEV23!BM34+HISTOMARS23!BM34+HISTOAVRIL23!BM34+HISTOMAI23!BM34+HISTOJUIN23!BM34+HISTOJUIL23!BM34+HISTOAOUT23!BM34+HISTOSEPT23!BM34+HISTOOCT23!BM34+HISTONOV23!BM34+HISTODEC23!BM34 -> 0
