Workbook
Name MODEPAID: MODEPAID!$A$1:$A$3
Name MODEPAID: #REF!
Name MODEPAID: #REF!
Name MODEPAID: #REF!
Name MODEPAID: #REF!
Name MODEPAID: #REF!
Name MODEPAID: #REF!
Name MODEPAID: #REF!
Name MODEPAID: #REF!
Name MODEPAID: #REF!
Name MODEPAID: #REF!
Name MODEPAID: #REF!
Name MODEPAID: #REF!
Name MODEPAID: #REF!
Name MODEPAID: #REF!
Name MODEPAID: #REF!
Name MODEPAID: #REF!
Name MODEPAID: #REF!
Name MODEPAID: #REF!
Name VALMODEPAID: MODEPAID!$A$1:$A$3

Sheet MODEPAID
A1: BANQUE
A2: ESPECES
A3: ECHEC

Sheet TONTJUIL
A1: ASSOCIATION | B1: ASELBY
A2: ANNEE | B2: 2019/2020
A3: TONTINE | B3: 75000
C4: 44031
A5: MATRICULE | B5: NOM ET PRENOM | C5: MONTANT TONTINE | D5: PENALITE | E5: MODE VERSEMENT TONTINE | F5: VENTE PETIT LOT | G5: INTERET PETIT LOT | H5: MODE VERSEMENT VENTE PETIT LOT | I5: NUMERO CHEQUE | J5: MONTANT A REMOURSER | K5: MONTANT REMBOURSE | L5: MODE VERSEMENT REMBOURSEMENT | M5: MODE VERSEMENT TONTINE PRINCIPAL | N5: NUMERO CHEQUE | O5: MONTANT TONTINE LOT PRINCIPAL | P5: INTERET LOT PRINCIPAL
A6: AS201602 | B6: =VLOOKUP(A6,[1]LISTADHERENT!A$5:H$60,3,0) -> BOUTCHOUANG WILLIAM | C6: =IF(E6="ECHEC",0,IF(E6="",0,75000)) -> 75000 | D6: =IF(E6="ESPECES",0,0) -> 0 | E6: BANQUE | K6: =J6 -> 0 | O6: =IF(P6=0,0,($C$36-P6)) -> 0
A7: AS201603 | B7: =VLOOKUP(A7,[1]LISTADHERENT!A$5:H$60,3,0) -> CHINGUE FABRICE | C7: =IF(E7="ECHEC",0,IF(E7="",0,75000)) -> 75000 | D7: =IF(E7="ESPECES",0,0) -> 0 | E7: BANQUE | K7: =J7 -> 0 | O7: =IF(P7=0,0,($C$36-P7)) -> 0
A8: AS201604 | B8: =VLOOKUP(A8,[1]LISTADHERENT!A$5:H$60,3,0) -> DJOMO JEAN PAUL | C8: =IF(E8="ECHEC",0,IF(E8="",0,75000)) -> 75000 | D8: =IF(E8="ESPECES",0,0) -> 0 | E8: BANQUE | F8: 100000 | G8: 2000 | K8: =J8 -> 0 | O8: =IF(P8=0,0,($C$36-P8)) -> 1000000 | P8: 200000
A9: AS201605 | B9: =VLOOKUP(A9,[1]LISTADHERENT!A$5:H$60,3,0) -> DJOUKWE NANGUEN GUY BLAISE | C9: =IF(E9="ECHEC",0,IF(E9="",0,75000)) -> 75000 | D9: =IF(E9="ESPECES",0,0) -> 0 | E9: BANQUE | K9: =J9 -> 0 | O9: =IF(P9=0,0,($C$36-P9)) -> 0
A10: AS201613 | B10: =VLOOKUP(A10,[1]LISTADHERENT!A$5:H$60,3,0) -> HOTCHO BENJAMIN | C10: =IF(E10="ECHEC",0,IF(E10="",0,75000)) -> 75000 | D10: =IF(E10="ESPECES",0,0) -> 0 | E10: BANQUE | K10: =J10 -> 0 | O10: =IF(P10=0,0,($C$36-P10)) -> 0
A11: AS201611 | B11: =VLOOKUP(A11,[1]LISTADHERENT!A$5:H$60,3,0) -> HENGUE PAUL OMER | C11: =IF(E11="ECHEC",0,IF(E11="",0,75000)) -> 75000 | D11: =IF(E11="ESPECES",0,0) -> 0 | E11: BANQUE | K11: =J11 -> 0 | O11: =IF(P11=0,0,($C$36-P11)) -> 0
A12: AS201619 | B12: =VLOOKUP(A12,[1]LISTADHERENT!A$5:H$60,3,0) -> KOUATCHO MESSACK | C12: =IF(E12="ECHEC",0,IF(E12="",0,75000)) -> 75000 | D12: =IF(E12="ESPECES",0,0) -> 0 | E12: BANQUE | F12: 100000 | G12: 2000 | K12: =J12 -> 0 | O12: =IF(P12=0,0,($C$36-P12)) -> 0
A13: AS201621 | B13: =VLOOKUP(A13,[1]LISTADHERENT!A$5:H$60,3,0) -> NANKAM APPOLINAIRE | C13: =IF(E13="ECHEC",0,IF(E13="",0,75000)) -> 75000 | D13: =IF(E13="ESPECES",0,0) -> 0 | E13: BANQUE | K13: =J13 -> 0 | O13: =IF(P13=0,0,($C$36-P13)) -> 0
A14: AS201649 | B14: =VLOOKUP(A14,[1]LISTADHERENT!A$5:H$60,3,0) -> MBOGNING TUGMA GUY | C14: =IF(E14="ECHEC",0,IF(E14="",0,75000)) -> 75000 | D14: =IF(E14="ESPECES",0,0) -> 0 | E14: BANQUE | F14: 100000 | G14: 2000 | K14: =J14 -> 0 | O14: =IF(P14=0,0,($C$36-P14)) -> 0
A15: AS201649 | B15: =VLOOKUP(A15,[1]LISTADHERENT!A$5:H$60,3,0) -> MBOGNING TUGMA GUY | C15: =IF(E15="ECHEC",0,IF(E15="",0,75000)) -> 75000 | D15: =IF(E15="ESPECES",0,0) -> 0 | E15: BANQUE | K15: =J15 -> 0 | O15: =IF(P15=0,0,($C$36-P15)) -> 0
A16: AS201649 | B16: =VLOOKUP(A16,[1]LISTADHERENT!A$5:H$60,3,0) -> MBOGNING TUGMA GUY | C16: =IF(E16="ECHEC",0,IF(E16="",0,75000)) -> 75000 | D16: =IF(E16="ESPECES",0,0) -> 0 | E16: BANQUE | K16: =J16 -> 0 | O16: =IF(P16=0,0,($C$36-P16)) -> 0
A17: AS201626 | B17: =VLOOKUP(A17,[1]LISTADHERENT!A$5:H$60,3,0) -> NGUIEMEGNI MATHIEU BLAISE | C17: =IF(E17="ECHEC",0,IF(E17="",0,75000)) -> 75000 | D17: =IF(E17="ESPECES",0,0) -> 0 | E17: BANQUE | K17: =J17 -> 0 | O17: =IF(P17=0,0,($C$36-P17)) -> 0
A18: AS201626 | B18: =VLOOKUP(A18,[1]LISTADHERENT!A$5:H$60,3,0) -> NGUIEMEGNI MATHIEU BLAISE | C18: =IF(E18="ECHEC",0,IF(E18="",0,75000)) -> 75000 | D18: =IF(E18="ESPECES",0,0) -> 0 | E18: BANQUE | K18: =J18 -> 0 | O18: =IF(P18=0,0,($C$36-P18)) -> 0
A19: AS201628 | B19: =VLOOKUP(A19,[1]LISTADHERENT!A$5:H$60,3,0) -> NKAMGANG JUSTIN DEJOLIE | C19: =IF(E19="ECHEC",0,IF(E19="",0,75000)) -> 75000 | D19: =IF(E19="ESPECES",0,0) -> 0 | E19: BANQUE | F19: 50000 | G19: 1000 | K19: =J19 -> 0 | O19: =IF(P19=0,0,($C$36-P19)) -> 0
A20: AS201633 | B20: =VLOOKUP(A20,[1]LISTADHERENT!A$5:H$60,3,0) -> PATEGO NJOSSU GUSTAVE | C20: =IF(E20="ECHEC",0,IF(E20="",0,75000)) -> 75000 | D20: =IF(E20="ESPECES",0,0) -> 0 | E20: BANQUE | K20: =J20 -> 0 | O20: =IF(P20=0,0,($C$36-P20)) -> 0
A21: AS201638 | B21: =VLOOKUP(A21,[1]LISTADHERENT!A$5:H$60,3,0) -> SIMO PIERRE | C21: =IF(E21="ECHEC",0,IF(E21="",0,75000)) -> 75000 | D21: =IF(E21="ESPECES",0,0) -> 0 | E21: BANQUE | K21: =J21 -> 0 | O21: =IF(P21=0,0,($C$36-P21)) -> 0
A22: AS201655 | B22: =VLOOKUP(A22,[1]LISTADHERENT!A$5:H$60,3,0) -> TCHEMHOU EMMANUEL | C22: =IF(E22="ECHEC",0,IF(E22="",0,75000)) -> 0 | D22: =IF(E22="ESPECES",0,0) -> 0 | E22: ECHEC | J22: =K22 -> 0 | K22: =+TONTJUIL!F21+TONTJUIL!G21 -> 0 | O22: =IF(P22=0,0,($C$36-P22)) -> 0
A23: AS201647 | B23: =VLOOKUP(A23,[1]LISTADHERENT!A$5:H$60,3,0) -> YOUMBI EMMANUEL | C23: =IF(E23="ECHEC",0,IF(E23="",0,75000)) -> 75000 | D23: =IF(E23="ESPECES",0,0) -> 0 | E23: BANQUE | K23: =J23 -> 0 | O23: =IF(P23=0,0,($C$36-P23)) -> 0
A24: AS201647 | B24: =VLOOKUP(A24,[1]LISTADHERENT!A$5:H$60,3,0) -> YOUMBI EMMANUEL | C24: =IF(E24="ECHEC",0,IF(E24="",0,75000)) -> 75000 | D24: =IF(E24="ESPECES",0,0) -> 0 | E24: BANQUE | K24: =J24 -> 0 | O24: =IF(P24=0,0,($C$36-P24)) -> 0
A26: TOTAL | C26: =SUM(C6:C24) -> 1350000 | D26: =SUM(D6:D24) -> 0 | F26: =SUM(F6:F24) -> 350000 | G26: =SUM(G6:G24) -> 7000 | I26: =SUM(I6:I24) -> 0 | J26: =SUM(J6:J24) -> 0 | K26: =SUM(K6:K24) -> 0 | M26: =SUM(M6:M24) -> 0 | N26: =SUM(N6:N24) -> 0 | O26: =SUM(O6:O24) -> 1000000 | P26: =SUM(P6:P24) -> 200000
C28: TONTINE | D28: REMBOURSEMENT PETIT LOT | E28: VENTE PETIT LOT | F28: VENTE LOT PRINCIPAL | G28: SOLDE EN CAISSE | I28: TONTINE + REMB + INTERET VENTE | J28: =(C33+D33+P26) -> 1550000
I29: VENTE LOT | J29: =IF(J28>=2000000,120000*2,1200000) -> 1200000
B30: ESPECES | C30: =SUMIFS(C6:C24,E6:E24,"ESPECES") -> 0 | D30: =SUMIFS(J6:J24,L6:L24,"ESPECES") -> 0 | E30: =SUMIFS(F6:F24,H6:H24,"ESPECES") -> 0 | F30: =SUMIFS(M6:M24,L6:L24,"ESPECES") -> 0 | G30: =C30+D30-E30-F30 -> 0
B31: BANQUE | C31: =SUMIFS(C6:C24,E6:E24,"BANQUE") -> 1350000 | D31: =SUMIFS(K6:K24,L6:L24,"BANQUE") -> 0 | E31: =SUMIFS(F6:F24,H6:H24,"BANQUE") -> 0 | F31: =SUMIFS(M6:M24,L6:L24,"BANQUE") -> 0 | G31: =C31+D31-E31-F31 -> 1350000 | I31: PETIT LOT | J31: =IF(J28>0,J28-J29,0) -> 350000
B33: TOTAL | C33: =C30+C31 -> 1350000 | D33: =D30+D31 -> 0 | E33: =E30+E31 -> 0 | F33: =F30+F31 -> 0 | G33: =G30+G31 -> 1350000 | I33: RESTE | J33: =J31-F26 -> 0
B36: MONTANT TONTINE | C36: 1200000

Sheet TONTAOUT
A1: ASSOCIATION | B1: ASELBY
A2: ANNEE | B2: 2019/2020
A3: TONTINE | B3: 75000
C4: 44059
A5: MATRICULE | B5: NOM ET PRENOM | C5: MONTANT TONTINE | D5: PENALITE | E5: MODE VERSEMENT TONTINE | F5: VENTE PETIT LOT | G5: INTERET PETIT LOT | H5: MODE VERSEMENT VENTE PETIT LOT | I5: NUMERO CHEQUE | J5: MONTANT REMBOURSE | K5: MONTANT A REMBOURSER | L5: MODE VERSEMENT REMBOURSEMENT | M5: MODE VERSEMENT TONTINE PRINCIPAL | N5: NUMERO CHEQUE | O5: MONTANT TONTINE LOT PRINCIPAL | P5: INTERET LOT PRINCIPAL
A6: AS201602 | B6: =VLOOKUP(A6,[1]LISTADHERENT!A$5:H$60,3,0) -> BOUTCHOUANG WILLIAM | C6: =IF(E6="ECHEC",0,IF(E6="",0,75000)) -> 75000 | D6: =IF(E6="ESPECES",0,0) -> 0 | E6: BANQUE | J6: =K6 -> 0 | K6: =+TONTJUIL!F6+TONTJUIL!G6 -> 0 | O6: =IF(P6=0,0,($C$36-P6)) -> 0
A7: AS201603 | B7: =VLOOKUP(A7,[1]LISTADHERENT!A$5:H$60,3,0) -> CHINGUE FABRICE | C7: =IF(E7="ECHEC",0,IF(E7="",0,75000)) -> 0 | D7: =IF(E7="ESPECES",0,0) -> 0 | E7: ECHEC | J7: =K7 -> 0 | K7: =+TONTJUIL!F7+TONTJUIL!G7 -> 0 | O7: =IF(P7=0,0,($C$36-P7)) -> 0
A8: AS201604 | B8: =VLOOKUP(A8,[1]LISTADHERENT!A$5:H$60,3,0) -> DJOMO JEAN PAUL | C8: =IF(E8="ECHEC",0,IF(E8="",0,75000)) -> 75000 | D8: =IF(E8="ESPECES",0,0) -> 0 | E8: BANQUE | F8: 100000 | G8: 2000 | J8: =K8 -> 102000 | K8: =+TONTJUIL!F8+TONTJUIL!G8 -> 102000 | L8: ESPECES | O8: =IF(P8=0,0,($C$36-P8)) -> 0
A9: AS201605 | B9: =VLOOKUP(A9,[1]LISTADHERENT!A$5:H$60,3,0) -> DJOUKWE NANGUEN GUY BLAISE | C9: =IF(E9="ECHEC",0,IF(E9="",0,75000)) -> 75000 | D9: =IF(E9="ESPECES",0,0) -> 0 | E9: BANQUE | F9: 100000 | G9: 2000 | J9: =K9 -> 0 | K9: =+TONTJUIL!F9+TONTJUIL!G9 -> 0 | O9: =IF(P9=0,0,($C$36-P9)) -> 0
A10: AS201613 | B10: =VLOOKUP(A10,[1]LISTADHERENT!A$5:H$60,3,0) -> HOTCHO BENJAMIN | C10: =IF(E10="ECHEC",0,IF(E10="",0,75000)) -> 75000 | D10: =IF(E10="ESPECES",0,0) -> 0 | E10: BANQUE | J10: =K10 -> 0 | K10: =+TONTJUIL!F10+TONTJUIL!G10 -> 0 | O10: =IF(P10=0,0,($C$36-P10)) -> 0
A11: AS201611 | B11: =VLOOKUP(A11,[1]LISTADHERENT!A$5:H$60,3,0) -> HENGUE PAUL OMER | C11: =IF(E11="ECHEC",0,IF(E11="",0,75000)) -> 75000 | D11: =IF(E11="ESPECES",0,0) -> 0 | E11: BANQUE | J11: =K11 -> 0 | K11: =+TONTJUIL!F11+TONTJUIL!G11 -> 0 | O11: =IF(P11=0,0,($C$36-P11)) -> 0
A12: AS201619 | B12: =VLOOKUP(A12,[1]LISTADHERENT!A$5:H$60,3,0) -> KOUATCHO MESSACK | C12: =IF(E12="ECHEC",0,IF(E12="",0,75000)) -> 75000 | D12: =IF(E12="ESPECES",0,0) -> 0 | E12: BANQUE | J12: =K12 -> 102000 | K12: =+TONTJUIL!F12+TONTJUIL!G12 -> 102000 | O12: =IF(P12=0,0,($C$36-P12)) -> 0
A13: AS201621 | B13: =VLOOKUP(A13,[1]LISTADHERENT!A$5:H$60,3,0) -> NANKAM APPOLINAIRE | C13: =IF(E13="ECHEC",0,IF(E13="",0,75000)) -> 75000 | D13: =IF(E13="ESPECES",0,0) -> 0 | E13: BANQUE | J13: =K13 -> 0 | K13: =+TONTJUIL!F13+TONTJUIL!G13 -> 0 | O13: =IF(P13=0,0,($C$36-P13)) -> 0
A14: AS201649 | B14: =VLOOKUP(A14,[1]LISTADHERENT!A$5:H$60,3,0) -> MBOGNING TUGMA GUY | C14: =IF(E14="ECHEC",0,IF(E14="",0,75000)) -> 75000 | D14: =IF(E14="ESPECES",0,0) -> 0 | E14: BANQUE | F14: 100000 | G14: 2000 | J14: =K14 -> 102000 | K14: =+TONTJUIL!F14+TONTJUIL!G14 -> 102000 | L14: BANQUE | O14: =IF(P14=0,0,($C$36-P14)) -> 1040000 | P14: 160000
A15: AS201649 | B15: =VLOOKUP(A15,[1]LISTADHERENT!A$5:H$60,3,0) -> MBOGNING TUGMA GUY | C15: =IF(E15="ECHEC",0,IF(E15="",0,75000)) -> 75000 | D15: =IF(E15="ESPECES",0,0) -> 0 | E15: BANQUE | J15: =K15 -> 0 | K15: =+TONTJUIL!F15+TONTJUIL!G15 -> 0 | O15: =IF(P15=0,0,($C$36-P15)) -> 0
A16: AS201649 | B16: =VLOOKUP(A16,[1]LISTADHERENT!A$5:H$60,3,0) -> MBOGNING TUGMA GUY | C16: =IF(E16="ECHEC",0,IF(E16="",0,75000)) -> 75000 | D16: =IF(E16="ESPECES",0,0) -> 0 | E16: BANQUE | J16: =K16 -> 0 | K16: =+TONTJUIL!F16+TONTJUIL!G16 -> 0 | O16: =IF(P16=0,0,($C$36-P16)) -> 0
A17: AS201626 | B17: =VLOOKUP(A17,[1]LISTADHERENT!A$5:H$60,3,0) -> NGUIEMEGNI MATHIEU BLAISE | C17: =IF(E17="ECHEC",0,IF(E17="",0,75000)) -> 75000 | D17: =IF(E17="ESPECES",0,0) -> 0 | E17: BANQUE | F17: 100000 | G17: 2000 | J17: =K17 -> 0 | K17: =+TONTJUIL!F17+TONTJUIL!G17 -> 0 | O17: =IF(P17=0,0,($C$36-P17)) -> 0
A18: AS201626 | B18: =VLOOKUP(A18,[1]LISTADHERENT!A$5:H$60,3,0) -> NGUIEMEGNI MATHIEU BLAISE | C18: =IF(E18="ECHEC",0,IF(E18="",0,75000)) -> 75000 | D18: =IF(E18="ESPECES",0,0) -> 0 | E18: BANQUE | J18: =K18 -> 0 | K18: =+TONTJUIL!F18+TONTJUIL!G18 -> 0 | O18: =IF(P18=0,0,($C$36-P18)) -> 0
A19: AS201628 | B19: =VLOOKUP(A19,[1]LISTADHERENT!A$5:H$60,3,0) -> NKAMGANG JUSTIN DEJOLIE | C19: =IF(E19="ECHEC",0,IF(E19="",0,75000)) -> 75000 | D19: =IF(E19="ESPECES",0,0) -> 0 | E19: ESPECES | F19: 100000 | G19: 2000 | J19: =K19 -> 51000 | K19: =+TONTJUIL!F19+TONTJUIL!G19 -> 51000 | L19: ESPECES | O19: =IF(P19=0,0,($C$36-P19)) -> 0
A20: AS201633 | B20: =VLOOKUP(A20,[1]LISTADHERENT!A$5:H$60,3,0) -> PATEGO NJOSSU GUSTAVE | C20: =IF(E20="ECHEC",0,IF(E20="",0,75000)) -> 75000 | D20: =IF(E20="ESPECES",0,0) -> 0 | E20: BANQUE | J20: =K20 -> 0 | K20: =+TONTJUIL!F20+TONTJUIL!G20 -> 0 | O20: =IF(P20=0,0,($C$36-P20)) -> 0
A21: AS201638 | B21: =VLOOKUP(A21,[1]LISTADHERENT!A$5:H$60,3,0) -> SIMO PIERRE | C21: =IF(E21="ECHEC",0,IF(E21="",0,75000)) -> 75000 | D21: =IF(E21="ESPECES",0,0) -> 0 | E21: BANQUE | J21: =K21 -> 0 | K21: =+TONTJUIL!F21+TONTJUIL!G21 -> 0 | O21: =IF(P21=0,0,($C$36-P21)) -> 0
A22: AS201655 | B22: =VLOOKUP(A22,[1]LISTADHERENT!A$5:H$60,3,0) -> TCHEMHOU EMMANUEL | C22: 161500 | D22: =IF(E22="ESPECES",0,0) -> 0 | E22: ESPECES | J22: =K22 -> 0 | K22: =+TONTJUIL!F21+TONTJUIL!G21 -> 0 | O22: =IF(P22=0,0,($C$36-P22)) -> 0
A23: AS201647 | B23: =VLOOKUP(A23,[1]LISTADHERENT!A$5:H$60,3,0) -> YOUMBI EMMANUEL | C23: =IF(E23="ECHEC",0,IF(E23="",0,75000)) -> 75000 | D23: =IF(E23="ESPECES",0,0) -> 0 | E23: BANQUE | J23: =K23 -> 0 | K23: =+TONTJUIL!F23+TONTJUIL!G23 -> 0 | O23: =IF(P23=0,0,($C$36-P23)) -> 0
A24: AS201647 | B24: =VLOOKUP(A24,[1]LISTADHERENT!A$5:H$60,3,0) -> YOUMBI EMMANUEL | C24: =IF(E24="ECHEC",0,IF(E24="",0,75000)) -> 75000 | D24: =IF(E24="ESPECES",0,0) -> 0 | E24: BANQUE | J24: =K24 -> 0 | K24: =+TONTJUIL!F24+TONTJUIL!G24 -> 0 | O24: =IF(P24=0,0,($C$36-P24)) -> 0
A26: TOTAL | C26: =SUM(C6:C24) -> 1436500 | D26: =SUM(D6:D24) -> 0 | F26: =SUM(F6:F24) -> 500000 | G26: =SUM(G6:G24) -> 10000 | I26: =SUM(I6:I24) -> 0 | J26: =SUM(J6:J24) -> 357000 | K26: =SUM(K6:K24) -> 357000 | M26: =SUM(M6:M24) -> 0 | N26: =SUM(N6:N24) -> 0 | O26: =SUM(O6:O24) -> 1040000 | P26: =SUM(P6:P24) -> 160000
C28: TONTINE | D28: REMBOURSEMENT PETIT LOT | E28: VENTE PETIT LOT | F28: VENTE LOT PRINCIPAL | G28: SOLDE EN CAISSE | I28: TONTINE + REMB + INTERET VENTE | J28: =(C33+D33+P26) -> 1851500
I29: VENTE LOT | J29: =IF(J28>=2000000,1200000*2,1200000) -> 1200000
B30: ESPECES | C30: =SUMIFS(C6:C24,E6:E24,"ESPECES") -> 236500 | D30: =SUMIFS(J6:J24,L6:L24,"ESPECES") -> 153000 | E30: =SUMIFS(F6:F24,H6:H24,"ESPECES") -> 0 | F30: =SUMIFS(M6:M24,L6:L24,"ESPECES") -> 0 | G30: =C30+D30-E30-F30 -> 389500
B31: BANQUE | C31: =SUMIFS(C6:C24,E6:E24,"BANQUE") -> 1200000 | D31: =SUMIFS(J6:J24,L6:L24,"BANQUE") -> 102000 | E31: =SUMIFS(F6:F24,H6:H24,"BANQUE") -> 0 | F31: =SUMIFS(M6:M24,L6:L24,"BANQUE") -> 0 | G31: =C31+D31-E31-F31 -> 1302000 | I31: PETIT LOT | J31: =IF(J28>0,J28-J29,0) -> 651500
B33: TOTAL | C33: =C30+C31 -> 1436500 | D33: =D30+D31 -> 255000 | E33: =E30+E31 -> 0 | F33: =F30+F31 -> 0 | G33: =G30+G31 -> 1691500 | I33: RESTE | J33: =J31-F26+TONTJUIL!J33 -> 151500 | K33: EN CAISSE
B36: MONTANT TONTINE | C36: 1200000

Sheet TONTSEPT
A1: ASSOCIATION | B1: ASELBY
A2: ANNEE | B2: 2019/2020
A3: TONTINE | B3: 75000
C4: 44094
A5: MATRICULE | B5: NOM ET PRENOM | C5: MONTANT TONTINE | D5: PENALITE | E5: MODE VERSEMENT TONTINE | F5: VENTE PETIT LOT | G5: INTERET PETIT LOT | H5: MODE VERSEMENT VENTE PETIT LOT | I5: NUMERO CHEQUE | J5: MONTANT REMBOURSE | K5: MONTANT A REMBOURSER | L5: MODE VERSEMENT REMBOURSEMENT | M5: MODE VERSEMENT TONTINE PRINCIPAL | N5: NUMERO CHEQUE | O5: MONTANT TONTINE LOT PRINCIPAL | P5: INTERET LOT PRINCIPAL
A6: AS201602 | B6: =VLOOKUP(A6,[1]LISTADHERENT!A$5:H$60,3,0) -> BOUTCHOUANG WILLIAM | C6: =IF(E6="ECHEC",0,IF(E6="",0,75000)) -> 75000 | D6: =IF(E6="ESPECES",0,0) -> 0 | E6: BANQUE | J6: =K6 -> 0 | K6: =+TONTAOUT!F6+TONTAOUT!G6 -> 0 | O6: =IF(P6=0,0,($C$36-P6)) -> 0
A7: AS201603 | B7: =VLOOKUP(A7,[1]LISTADHERENT!A$5:H$60,3,0) -> CHINGUE FABRICE | C7: =IF(E7="ECHEC",0,IF(E7="",0,75000)) -> 0 | D7: =IF(E7="ESPECES",0,0) -> 0 | E7: ECHEC | J7: =K7 -> 0 | K7: =+TONTAOUT!F7+TONTAOUT!G7 -> 0 | O7: =IF(P7=0,0,($C$36-P7)) -> 0
A8: AS201604 | B8: =VLOOKUP(A8,[1]LISTADHERENT!A$5:H$60,3,0) -> DJOMO JEAN PAUL | C8: =IF(E8="ECHEC",0,IF(E8="",0,75000)) -> 75000 | D8: =IF(E8="ESPECES",0,0) -> 0 | E8: BANQUE | F8: 50000 | G8: 1000 | J8: =K8 -> 102000 | K8: =+TONTAOUT!F8+TONTAOUT!G8 -> 102000 | L8: BANQUE | O8: =IF(P8=0,0,($C$36-P8)) -> 0
A9: AS201605 | B9: =VLOOKUP(A9,[1]LISTADHERENT!A$5:H$60,3,0) -> DJOUKWE NANGUEN GUY BLAISE | C9: =IF(E9="ECHEC",0,IF(E9="",0,75000)) -> 75000 | D9: =IF(E9="ESPECES",0,0) -> 0 | E9: BANQUE | F9: 150000 | G9: 3000 | J9: =K9 -> 102000 | K9: =+TONTAOUT!F9+TONTAOUT!G9 -> 102000 | L9: BANQUE | O9: =IF(P9=0,0,($C$36-P9)) -> 0
A10: AS201613 | B10: =VLOOKUP(A10,[1]LISTADHERENT!A$5:H$60,3,0) -> HOTCHO BENJAMIN | C10: =IF(E10="ECHEC",0,IF(E10="",0,75000)) -> 75000 | D10: =IF(E10="ESPECES",0,0) -> 0 | E10: BANQUE | J10: =K10 -> 0 | K10: =+TONTAOUT!F10+TONTAOUT!G10 -> 0 | O10: =IF(P10=0,0,($C$36-P10)) -> 0
A11: AS201611 | B11: =VLOOKUP(A11,[1]LISTADHERENT!A$5:H$60,3,0) -> HENGUE PAUL OMER | C11: =IF(E11="ECHEC",0,IF(E11="",0,75000)) -> 75000 | D11: =IF(E11="ESPECES",0,0) -> 0 | E11: BANQUE | J11: =K11 -> 0 | K11: =+TONTAOUT!F11+TONTAOUT!G11 -> 0 | O11: =IF(P11=0,0,($C$36-P11)) -> 0
A12: AS201619 | B12: =VLOOKUP(A12,[1]LISTADHERENT!A$5:H$60,3,0) -> KOUATCHO MESSACK | C12: =IF(E12="ECHEC",0,IF(E12="",0,75000)) -> 75000 | D12: =IF(E12="ESPECES",0,0) -> 0 | E12: BANQUE | F12: 100000 | G12: 2000 | J12: =K12 -> 0 | K12: =+TONTAOUT!F12+TONTAOUT!G12 -> 0 | O12: =IF(P12=0,0,($C$36-P12)) -> 0
A13: AS201621 | B13: =VLOOKUP(A13,[1]LISTADHERENT!A$5:H$60,3,0) -> NANKAM APPOLINAIRE | C13: =IF(E13="ECHEC",0,IF(E13="",0,75000)) -> 75000 | D13: =IF(E13="ESPECES",0,0) -> 0 | E13: BANQUE | J13: =K13 -> 0 | K13: =+TONTAOUT!F13+TONTAOUT!G13 -> 0 | O13: =IF(P13=0,0,($C$36-P13)) -> 0
A14: AS201649 | B14: =VLOOKUP(A14,[1]LISTADHERENT!A$5:H$60,3,0) -> MBOGNING TUGMA GUY | C14: =IF(E14="ECHEC",0,IF(E14="",0,75000)) -> 75000 | D14: =IF(E14="ESPECES",0,0) -> 0 | E14: BANQUE | F14: 100000 | G14: 2000 | J14: =K14 -> 102000 | K14: =+TONTAOUT!F14+TONTAOUT!G14 -> 102000 | L14: BANQUE | O14: =IF(P14=0,0,($C$36-P14)) -> 0
A15: AS201649 | B15: =VLOOKUP(A15,[1]LISTADHERENT!A$5:H$60,3,0) -> MBOGNING TUGMA GUY | C15: =IF(E15="ECHEC",0,IF(E15="",0,75000)) -> 75000 | D15: =IF(E15="ESPECES",0,0) -> 0 | E15: BANQUE | J15: =K15 -> 0 | K15: =+TONTAOUT!F15+TONTAOUT!G15 -> 0 | O15: =IF(P15=0,0,($C$36-P15)) -> 0
A16: AS201649 | B16: =VLOOKUP(A16,[1]LISTADHERENT!A$5:H$60,3,0) -> MBOGNING TUGMA GUY | C16: =IF(E16="ECHEC",0,IF(E16="",0,75000)) -> 75000 | D16: =IF(E16="ESPECES",0,0) -> 0 | E16: BANQUE | J16: =K16 -> 0 | K16: =+TONTAOUT!F16+TONTAOUT!G16 -> 0 | O16: =IF(P16=0,0,($C$36-P16)) -> 0
A17: AS201626 | B17: =VLOOKUP(A17,[1]LISTADHERENT!A$5:H$60,3,0) -> NGUIEMEGNI MATHIEU BLAISE | C17: =IF(E17="ECHEC",0,IF(E17="",0,75000)) -> 75000 | D17: =IF(E17="ESPECES",0,0) -> 0 | E17: BANQUE | F17: 102000 | G17: 4000 | H17: ECHEC | J17: =K17 -> 102000 | K17: =+TONTAOUT!F17+TONTAOUT!G17 -> 102000 | L17: ECHEC | O17: =IF(P17=0,0,($C$36-P17)) -> 0
A18: AS201626 | B18: =VLOOKUP(A18,[1]LISTADHERENT!A$5:H$60,3,0) -> NGUIEMEGNI MATHIEU BLAISE | C18: =IF(E18="ECHEC",0,IF(E18="",0,75000)) -> 75000 | D18: =IF(E18="ESPECES",0,0) -> 0 | E18: BANQUE | J18: =K18 -> 0 | K18: =+TONTAOUT!F18+TONTAOUT!G18 -> 0 | O18: =IF(P18=0,0,($C$36-P18)) -> 0
A19: AS201628 | B19: =VLOOKUP(A19,[1]LISTADHERENT!A$5:H$60,3,0) -> NKAMGANG JUSTIN DEJOLIE | C19: =IF(E19="ECHEC",0,IF(E19="",0,75000)) -> 75000 | D19: =IF(E19="ESPECES",0,0) -> 0 | E19: ESPECES | F19: 100000 | G19: 2000 | J19: =K19 -> 102000 | K19: =+TONTAOUT!F19+TONTAOUT!G19 -> 102000 | L19: ESPECES | O19: =IF(P19=0,0,($C$36-P19)) -> 1115000 | P19: 85000
A20: AS201633 | B20: =VLOOKUP(A20,[1]LISTADHERENT!A$5:H$60,3,0) -> PATEGO NJOSSU GUSTAVE | C20: =IF(E20="ECHEC",0,IF(E20="",0,75000)) -> 75000 | D20: =IF(E20="ESPECES",0,0) -> 0 | E20: BANQUE | J20: =K20 -> 0 | K20: =+TONTAOUT!F20+TONTAOUT!G20 -> 0 | O20: =IF(P20=0,0,($C$36-P20)) -> 0
A21: AS201638 | B21: =VLOOKUP(A21,[1]LISTADHERENT!A$5:H$60,3,0) -> SIMO PIERRE | C21: =IF(E21="ECHEC",0,IF(E21="",0,75000)) -> 75000 | D21: =IF(E21="ESPECES",0,0) -> 0 | E21: BANQUE | J21: =K21 -> 0 | K21: =+TONTAOUT!F21+TONTAOUT!G21 -> 0 | O21: =IF(P21=0,0,($C$36-P21)) -> 0
A22: AS201655 | B22: =VLOOKUP(A22,[1]LISTADHERENT!A$5:H$60,3,0) -> TCHEMHOU EMMANUEL | C22: =IF(E22="ECHEC",0,IF(E22="",0,75000)) -> 75000 | D22: =IF(E22="ESPECES",0,0) -> 0 | E22: BANQUE | J22: =K22 -> 0 | K22: =+TONTAOUT!F22+TONTAOUT!G22 -> 0 | O22: =IF(P22=0,0,($C$36-P22)) -> 0
A23: AS201647 | B23: =VLOOKUP(A23,[1]LISTADHERENT!A$5:H$60,3,0) -> YOUMBI EMMANUEL | C23: =IF(E23="ECHEC",0,IF(E23="",0,75000)) -> 75000 | D23: =IF(E23="ESPECES",0,0) -> 0 | E23: BANQUE | J23: =K23 -> 0 | K23: =+TONTAOUT!F23+TONTAOUT!G23 -> 0 | O23: =IF(P23=0,0,($C$36-P23)) -> 0
A24: AS201647 | B24: =VLOOKUP(A24,[1]LISTADHERENT!A$5:H$60,3,0) -> YOUMBI EMMANUEL | C24: =IF(E24="ECHEC",0,IF(E24="",0,75000)) -> 75000 | D24: =IF(E24="ESPECES",0,0) -> 0 | E24: BANQUE | J24: =K24 -> 0 | K24: =+TONTAOUT!F24+TONTAOUT!G24 -> 0 | O24: =IF(P24=0,0,($C$36-P24)) -> 0
A26: TOTAL | C26: =SUM(C6:C24) -> 1350000 | D26: =SUM(D6:D24) -> 0 | F26: =SUM(F6:F24) -> 602000 | G26: =SUM(G6:G24) -> 14000 | I26: =SUM(I6:I24) -> 0 | J26: =SUM(J6:J24) -> 510000 | K26: =SUM(K6:K24) -> 510000 | M26: =SUM(M6:M24) -> 0 | N26: =SUM(N6:N24) -> 0 | O26: =SUM(O6:O24) -> 1115000 | P26: =SUM(P6:P24) -> 85000
C28: TONTINE | D28: REMBOURSEMENT PETIT LOT | E28: VENTE PETIT LOT | F28: VENTE LOT PRINCIPAL | G28: SOLDE EN CAISSE | I28: TONTINE + REMB + INTERET VENTE | J28: =(C33+D33+P26) -> 1843000
I29: VENTE LOT | J29: =IF(J28>=2000000,1200000*2,1200000) -> 1200000
B30: ESPECES | C30: =SUMIFS(C6:C24,E6:E24,"ESPECES") -> 75000 | D30: =SUMIFS(J6:J24,L6:L24,"ESPECES") -> 102000 | E30: =SUMIFS(F6:F24,H6:H24,"ESPECES") -> 0 | F30: =SUMIFS(M6:M24,L6:L24,"ESPECES") -> 0 | G30: =C30+D30-E30-F30 -> 177000
B31: BANQUE | C31: =SUMIFS(C6:C24,E6:E24,"BANQUE") -> 1275000 | D31: =SUMIFS(J6:J24,L6:L24,"BANQUE") -> 306000 | E31: =SUMIFS(F6:F24,H6:H24,"BANQUE") -> 0 | F31: =SUMIFS(M6:M24,L6:L24,"BANQUE") -> 0 | G31: =C31+D31-E31-F31 -> 1581000 | I31: PETIT LOT | J31: =IF(J28>0,J28-J29,0) -> 643000
B33: TOTAL | C33: =C30+C31 -> 1350000 | D33: =D30+D31 -> 408000 | E33: =E30+E31 -> 0 | F33: =F30+F31 -> 0 | G33: =G30+G31 -> 1758000 | I33: RESTE | J33: =J31-F26+TONTAOUT!J33 -> 192500
I35: ECHEC TONTINE | J35: 0
B36: MONTANT TONTINE | C36: 1200000 | I36: ECHEC REMBOURSEMENT | J36: =106000+53000 -> 159000 | K36: NGUIEMENI/MBONING

Sheet TONTOCT
A1: ASSOCIATION | B1: ASELBY
A2: ANNEE | B2: 2019/2020
A3: TONTINE | B3: 75000
C4: 44122
A5: MATRICULE | B5: NOM ET PRENOM | C5: MONTANT TONTINE | D5: PENALITE | E5: MODE VERSEMENT TONTINE | F5: VENTE PETIT LOT | G5: INTERET PETIT LOT | H5: MODE VERSEMENT VENTE PETIT LOT | I5: NUMERO CHEQUE | J5: MONTANT REMBOURSE | K5: MONTANT A REMBOURSER | L5: MODE VERSEMENT REMBOURSEMENT | M5: MODE VERSEMENT TONTINE PRINCIPAL | N5: NUMERO CHEQUE | O5: MONTANT TONTINE LOT PRINCIPAL | P5: INTERET LOT PRINCIPAL
A6: AS201602 | B6: =VLOOKUP(A6,[1]LISTADHERENT!A$5:H$60,3,0) -> BOUTCHOUANG WILLIAM | C6: =IF(E6="ECHEC",0,IF(E6="",0,75000)) -> 75000 | D6: =IF(E6="ESPECES",0,0) -> 0 | E6: BANQUE | J6: =K6 -> 0 | K6: =TONTSEPT!F6+TONTSEPT!G6 -> 0 | O6: =IF(P6=0,0,($C$36-P6)) -> 0
A7: AS201603 | B7: =VLOOKUP(A7,[1]LISTADHERENT!A$5:H$60,3,0) -> CHINGUE FABRICE | C7: =IF(E7="ECHEC",0,IF(E7="",0,75000)) -> 0 | D7: =IF(E7="ESPECES",0,0) -> 0 | E7: ECHEC | J7: =K7 -> 0 | K7: =TONTSEPT!F7+TONTSEPT!G7 -> 0 | O7: =IF(P7=0,0,($C$36-P7)) -> 0
A8: AS201604 | B8: =VLOOKUP(A8,[1]LISTADHERENT!A$5:H$60,3,0) -> DJOMO JEAN PAUL | C8: =IF(E8="ECHEC",0,IF(E8="",0,75000)) -> 75000 | D8: =IF(E8="ESPECES",0,0) -> 0 | E8: BANQUE | J8: =K8 -> 51000 | K8: =TONTSEPT!F8+TONTSEPT!G8 -> 51000 | L8: BANQUE | O8: =IF(P8=0,0,($C$36-P8)) -> 0
A9: AS201605 | B9: =VLOOKUP(A9,[1]LISTADHERENT!A$5:H$60,3,0) -> DJOUKWE NANGUEN GUY BLAISE | C9: =IF(E9="ECHEC",0,IF(E9="",0,75000)) -> 75000 | D9: =IF(E9="ESPECES",0,0) -> 0 | E9: BANQUE | J9: =K9 -> 153000 | K9: =TONTSEPT!F9+TONTSEPT!G9 -> 153000 | L9: BANQUE | O9: =IF(P9=0,0,($C$36-P9)) -> 0
A10: AS201613 | B10: =VLOOKUP(A10,[1]LISTADHERENT!A$5:H$60,3,0) -> HOTCHO BENJAMIN | C10: =IF(E10="ECHEC",0,IF(E10="",0,75000)) -> 75000 | D10: =IF(E10="ESPECES",0,0) -> 0 | E10: BANQUE | J10: =K10 -> 0 | K10: =TONTSEPT!F10+TONTSEPT!G10 -> 0 | O10: =IF(P10=0,0,($C$36-P10)) -> 1125000 | P10: 75000
A11: AS201611 | B11: =VLOOKUP(A11,[1]LISTADHERENT!A$5:H$60,3,0) -> HENGUE PAUL OMER | C11: =IF(E11="ECHEC",0,IF(E11="",0,75000)) -> 75000 | D11: =IF(E11="ESPECES",0,0) -> 0 | E11: BANQUE | J11: =K11 -> 0 | K11: =TONTSEPT!F11+TONTSEPT!G11 -> 0 | O11: =IF(P11=0,0,($C$36-P11)) -> 0
A12: AS201619 | B12: =VLOOKUP(A12,[1]LISTADHERENT!A$5:H$60,3,0) -> KOUATCHO MESSACK | C12: =IF(E12="ECHEC",0,IF(E12="",0,75000)) -> 75000 | D12: =IF(E12="ESPECES",0,0) -> 0 | E12: BANQUE | J12: =K12 -> 102000 | K12: =TONTSEPT!F12+TONTSEPT!G12 -> 102000 | L12: BANQUE | O12: =IF(P12=0,0,($C$36-P12)) -> 0
A13: AS201621 | B13: =VLOOKUP(A13,[1]LISTADHERENT!A$5:H$60,3,0) -> NANKAM APPOLINAIRE | C13: =IF(E13="ECHEC",0,IF(E13="",0,75000)) -> 75000 | D13: =IF(E13="ESPECES",0,0) -> 0 | E13: BANQUE | J13: =K13 -> 0 | K13: =TONTSEPT!F13+TONTSEPT!G13 -> 0 | O13: =IF(P13=0,0,($C$36-P13)) -> 0
A14: AS201649 | B14: =VLOOKUP(A14,[1]LISTADHERENT!A$5:H$60,3,0) -> MBOGNING TUGMA GUY | C14: =IF(E14="ECHEC",0,IF(E14="",0,75000)) -> 75000 | D14: =IF(E14="ESPECES",0,0) -> 0 | E14: BANQUE | J14: =K14 -> 102000 | K14: =TONTSEPT!F14+TONTSEPT!G14 -> 102000 | L14: BANQUE | O14: =IF(P14=0,0,($C$36-P14)) -> 0
A15: AS201649 | B15: =VLOOKUP(A15,[1]LISTADHERENT!A$5:H$60,3,0) -> MBOGNING TUGMA GUY | C15: =IF(E15="ECHEC",0,IF(E15="",0,75000)) -> 75000 | D15: =IF(E15="ESPECES",0,0) -> 0 | E15: BANQUE | J15: =K15 -> 0 | K15: =TONTSEPT!F15+TONTSEPT!G15 -> 0 | O15: =IF(P15=0,0,($C$36-P15)) -> 0
A16: AS201649 | B16: =VLOOKUP(A16,[1]LISTADHERENT!A$5:H$60,3,0) -> MBOGNING TUGMA GUY | C16: =IF(E16="ECHEC",0,IF(E16="",0,75000)) -> 75000 | D16: =IF(E16="ESPECES",0,0) -> 0 | E16: BANQUE | J16: =K16 -> 0 | K16: =TONTSEPT!F16+TONTSEPT!G16 -> 0 | O16: =IF(P16=0,0,($C$36-P16)) -> 0
A17: AS201626 | B17: =VLOOKUP(A17,[1]LISTADHERENT!A$5:H$60,3,0) -> NGUIEMEGNI MATHIEU BLAISE | C17: =IF(E17="ECHEC",0,IF(E17="",0,75000)) -> 75000 | D17: =IF(E17="ESPECES",0,0) -> 0 | E17: BANQUE | J17: =K17 -> 106000 | K17: =TONTSEPT!F17+TONTSEPT!G17 -> 106000 | L17: BANQUE | O17: =IF(P17=0,0,($C$36-P17)) -> 0
A18: AS201626 | B18: =VLOOKUP(A18,[1]LISTADHERENT!A$5:H$60,3,0) -> NGUIEMEGNI MATHIEU BLAISE | C18: =IF(E18="ECHEC",0,IF(E18="",0,75000)) -> 75000 | D18: =IF(E18="ESPECES",0,0) -> 0 | E18: BANQUE | J18: =K18 -> 0 | K18: =TONTSEPT!F18+TONTSEPT!G18 -> 0 | O18: =IF(P18=0,0,($C$36-P18)) -> 0
A19: AS201628 | B19: =VLOOKUP(A19,[1]LISTADHERENT!A$5:H$60,3,0) -> NKAMGANG JUSTIN DEJOLIE | C19: =IF(E19="ECHEC",0,IF(E19="",0,75000)) -> 75000 | D19: =IF(E19="ESPECES",0,0) -> 0 | E19: ESPECES | J19: =K19 -> 102000 | K19: =TONTSEPT!F19+TONTSEPT!G19 -> 102000 | L19: ESPECES | O19: =IF(P19=0,0,($C$36-P19)) -> 0
A20: AS201633 | B20: =VLOOKUP(A20,[1]LISTADHERENT!A$5:H$60,3,0) -> PATEGO NJOSSU GUSTAVE | C20: =IF(E20="ECHEC",0,IF(E20="",0,75000)) -> 75000 | D20: =IF(E20="ESPECES",0,0) -> 0 | E20: BANQUE | J20: =K20 -> 0 | K20: =TONTSEPT!F20+TONTSEPT!G20 -> 0 | O20: =IF(P20=0,0,($C$36-P20)) -> 0
A21: AS201638 | B21: =VLOOKUP(A21,[1]LISTADHERENT!A$5:H$60,3,0) -> SIMO PIERRE | C21: =IF(E21="ECHEC",0,IF(E21="",0,75000)) -> 75000 | D21: =IF(E21="ESPECES",0,0) -> 0 | E21: BANQUE | J21: =K21 -> 0 | K21: =TONTSEPT!F21+TONTSEPT!G21 -> 0 | O21: =IF(P21=0,0,($C$36-P21)) -> 0
A22: AS201655 | B22: =VLOOKUP(A22,[1]LISTADHERENT!A$5:H$60,3,0) -> TCHEMHOU EMMANUEL | C22: =IF(E22="ECHEC",0,IF(E22="",0,75000)) -> 75000 | D22: =IF(E22="ESPECES",0,0) -> 0 | E22: BANQUE | J22: =K22 -> 0 | K22: =TONTSEPT!F22+TONTSEPT!G22 -> 0 | O22: =IF(P22=0,0,($C$36-P22)) -> 0
A23: AS201647 | B23: =VLOOKUP(A23,[1]LISTADHERENT!A$5:H$60,3,0) -> YOUMBI EMMANUEL | C23: =IF(E23="ECHEC",0,IF(E23="",0,75000)) -> 75000 | D23: =IF(E23="ESPECES",0,0) -> 0 | E23: BANQUE | J23: =K23 -> 0 | K23: =TONTSEPT!F23+TONTSEPT!G23 -> 0 | O23: =IF(P23=0,0,($C$36-P23)) -> 1125000 | P23: 75000
A24: AS201647 | B24: =VLOOKUP(A24,[1]LISTADHERENT!A$5:H$60,3,0) -> YOUMBI EMMANUEL | C24: =IF(E24="ECHEC",0,IF(E24="",0,75000)) -> 75000 | D24: =IF(E24="ESPECES",0,0) -> 0 | E24: BANQUE | J24: =K24 -> 0 | K24: =TONTSEPT!F24+TONTSEPT!G24 -> 0 | O24: =IF(P24=0,0,($C$36-P24)) -> 0
A26: TOTAL | C26: =SUM(C6:C24) -> 1350000 | D26: =SUM(D6:D24) -> 0 | F26: =SUM(F6:F24) -> 0 | G26: =SUM(G6:G24) -> 0 | I26: =SUM(I6:I24) -> 0 | J26: =SUM(J6:J24) -> 616000 | K26: =SUM(K6:K24) -> 616000 | M26: =SUM(M6:M24) -> 0 | N26: =SUM(N6:N24) -> 0 | O26: =SUM(O6:O24) -> 2250000 | P26: =SUM(P6:P24) -> 150000
C28: TONTINE | D28: REMBOURSEMENT PETIT LOT | E28: VENTE PETIT LOT | F28: VENTE LOT PRINCIPAL | G28: SOLDE EN CAISSE | I28: TONTINE + REMB + INTERET VENTE | J28: =(C33+D33+P26) -> 2116000
I29: VENTE LOT | J29: =IF(J28>=2000000,1200000*2,1200000) -> 2400000
B30: ESPECES | C30: =SUMIFS(C6:C24,E6:E24,"ESPECES") -> 75000 | D30: =SUMIFS(K6:K24,L6:L24,"ESPECES") -> 102000 | E30: =SUMIFS(F6:F24,H6:H24,"ESPECES") -> 0 | F30: =SUMIFS(M6:M24,L6:L24,"ESPECES") -> 0 | G30: =C30+D30-E30-F30 -> 177000
B31: BANQUE | C31: =SUMIFS(C6:C24,E6:E24,"BANQUE") -> 1275000 | D31: =SUMIFS(K6:K24,L6:L24,"BANQUE") -> 514000 | E31: =SUMIFS(F6:F24,H6:H24,"BANQUE") -> 0 | F31: =SUMIFS(M6:M24,L6:L24,"BANQUE") -> 0 | G31: =C31+D31-E31-F31 -> 1789000 | I31: PETIT LOT | J31: =IF(J28>0,J28-J29,0) -> -284000
B33: TOTAL | C33: =C30+C31 -> 1350000 | D33: =D30+D31 -> 616000 | E33: =E30+E31 -> 0 | F33: =F30+F31 -> 0 | G33: =G30+G31 -> 1966000 | I33: RESTE | J33: =J31-F26+TONTSEPT!J33 -> -91500
B36: MONTANT TONTINE | C36: 1200000

Sheet TONTNOV
A1: ASSOCIATION | B1: ASELBY
A2: ANNEE | B2: 2019/2020
A3: TONTINE | B3: 75000
C4: 44150
A5: MATRICULE | B5: NOM ET PRENOM | C5: MONTANT TONTINE | D5: PENALITE | E5: MODE VERSEMENT TONTINE | F5: VENTE PETIT LOT | G5: INTERET PETIT LOT | H5: MODE VERSEMENT VENTE PETIT LOT | I5: NUMERO CHEQUE | J5: MONTANT REMBOURSE | K5: MONTANT A REMBOURSER | L5: MODE VERSEMENT REMBOURSEMENT | M5: MODE VERSEMENT TONTINE PRINCIPAL | N5: NUMERO CHEQUE | O5: MONTANT TONTINE LOT PRINCIPAL | P5: INTERET LOT PRINCIPAL
A6: AS201602 | B6: =VLOOKUP(A6,[1]LISTADHERENT!A$5:H$60,3,0) -> BOUTCHOUANG WILLIAM | C6: =IF(E6="ECHEC",0,IF(E6="",0,75000)) -> 0 | D6: =IF(E6="ESPECES",0,0) -> 0 | E6: ECHEC | J6: =K6 -> 0 | K6: =+TONTOCT!F6+TONTOCT!G6 -> 0 | O6: =IF(P6=0,0,($C$36-P6)) -> 0
A7: AS201603 | B7: =VLOOKUP(A7,[1]LISTADHERENT!A$5:H$60,3,0) -> CHINGUE FABRICE | C7: =IF(E7="ECHEC",0,IF(E7="",0,75000)) -> 0 | D7: =IF(E7="ESPECES",0,0) -> 0 | E7: ECHEC | J7: =K7 -> 0 | K7: =+TONTOCT!F7+TONTOCT!G7 -> 0 | O7: =IF(P7=0,0,($C$36-P7)) -> 0
A8: AS201604 | B8: =VLOOKUP(A8,[1]LISTADHERENT!A$5:H$60,3,0) -> DJOMO JEAN PAUL | C8: =IF(E8="ECHEC",0,IF(E8="",0,75000)) -> 0 | D8: =IF(E8="ESPECES",0,0) -> 0 | E8: ECHEC | J8: =K8 -> 0 | K8: =+TONTOCT!F8+TONTOCT!G8 -> 0 | O8: =IF(P8=0,0,($C$36-P8)) -> 0
A9: AS201605 | B9: =VLOOKUP(A9,[1]LISTADHERENT!A$5:H$60,3,0) -> DJOUKWE NANGUEN GUY BLAISE | C9: =IF(E9="ECHEC",0,IF(E9="",0,75000)) -> 0 | D9: =IF(E9="ESPECES",0,0) -> 0 | E9: ECHEC | J9: =K9 -> 0 | K9: =+TONTOCT!F9+TONTOCT!G9 -> 0 | O9: =IF(P9=0,0,($C$36-P9)) -> 0
A10: AS201613 | B10: =VLOOKUP(A10,[1]LISTADHERENT!A$5:H$60,3,0) -> HOTCHO BENJAMIN | C10: =IF(E10="ECHEC",0,IF(E10="",0,75000)) -> 0 | D10: =IF(E10="ESPECES",0,0) -> 0 | E10: ECHEC | J10: =K10 -> 0 | K10: =+TONTOCT!F10+TONTOCT!G10 -> 0 | O10: =IF(P10=0,0,($C$36-P10)) -> 0
A11: AS201611 | B11: =VLOOKUP(A11,[1]LISTADHERENT!A$5:H$60,3,0) -> HENGUE PAUL OMER | C11: =IF(E11="ECHEC",0,IF(E11="",0,75000)) -> 0 | D11: =IF(E11="ESPECES",0,0) -> 0 | E11: ECHEC | J11: =K11 -> 0 | K11: =+TONTOCT!F11+TONTOCT!G11 -> 0 | O11: =IF(P11=0,0,($C$36-P11)) -> 0
A12: AS201619 | B12: =VLOOKUP(A12,[1]LISTADHERENT!A$5:H$60,3,0) -> KOUATCHO MESSACK | C12: =IF(E12="ECHEC",0,IF(E12="",0,75000)) -> 0 | D12: =IF(E12="ESPECES",0,0) -> 0 | E12: ECHEC | J12: =K12 -> 0 | K12: =+TONTOCT!F12+TONTOCT!G12 -> 0 | O12: =IF(P12=0,0,($C$36-P12)) -> 0
A13: AS201621 | B13: =VLOOKUP(A13,[1]LISTADHERENT!A$5:H$60,3,0) -> NANKAM APPOLINAIRE | C13: =IF(E13="ECHEC",0,IF(E13="",0,75000)) -> 0 | D13: =IF(E13="ESPECES",0,0) -> 0 | E13: ECHEC | J13: =K13 -> 0 | K13: =+TONTOCT!F13+TONTOCT!G13 -> 0 | O13: =IF(P13=0,0,($C$36-P13)) -> 0
A14: AS201649 | B14: =VLOOKUP(A14,[1]LISTADHERENT!A$5:H$60,3,0) -> MBOGNING TUGMA GUY | C14: =IF(E14="ECHEC",0,IF(E14="",0,75000)) -> 0 | D14: =IF(E14="ESPECES",0,0) -> 0 | E14: ECHEC | J14: =K14 -> 0 | K14: =+TONTOCT!F14+TONTOCT!G14 -> 0 | O14: =IF(P14=0,0,($C$36-P14)) -> 0
A15: AS201649 | B15: =VLOOKUP(A15,[1]LISTADHERENT!A$5:H$60,3,0) -> MBOGNING TUGMA GUY | C15: =IF(E15="ECHEC",0,IF(E15="",0,75000)) -> 0 | D15: =IF(E15="ESPECES",0,0) -> 0 | E15: ECHEC | J15: =K15 -> 0 | K15: =+TONTOCT!F15+TONTOCT!G15 -> 0 | O15: =IF(P15=0,0,($C$36-P15)) -> 0
A16: AS201649 | B16: =VLOOKUP(A16,[1]LISTADHERENT!A$5:H$60,3,0) -> MBOGNING TUGMA GUY | C16: =IF(E16="ECHEC",0,IF(E16="",0,75000)) -> 0 | D16: =IF(E16="ESPECES",0,0) -> 0 | E16: ECHEC | J16: =K16 -> 0 | K16: =+TONTOCT!F16+TONTOCT!G16 -> 0 | O16: =IF(P16=0,0,($C$36-P16)) -> 0
A17: AS201626 | B17: =VLOOKUP(A17,[1]LISTADHERENT!A$5:H$60,3,0) -> NGUIEMEGNI MATHIEU BLAISE | C17: =IF(E17="ECHEC",0,IF(E17="",0,75000)) -> 0 | D17: =IF(E17="ESPECES",0,0) -> 0 | E17: ECHEC | J17: =K17 -> 0 | K17: =+TONTOCT!F17+TONTOCT!G17 -> 0 | O17: =IF(P17=0,0,($C$36-P17)) -> 0
... A24: AS201647 | B24: =VLOOKUP(A24,[1]LISTADHERENT!A$5:H$60,3,0) -> YOUMBI EMMANUEL | C24: =IF(E24="ECHEC",0,IF(E24="",0,75000)) -> 0 | D24: =IF(E24="ESPECES",0,0) -> 0 | E24: ECHEC | J24: =K24 -> 0 | K24: =+TONTOCT!F24+TONTOCT!G24 -> 0 | O24: =IF(P24=0,0,($C$36-P24)) -> 0
A26: TOTAL | C26: =SUM(C6:C24) -> 0 | D26: =SUM(D6:D24) -> 0 | F26: =SUM(F6:F24) -> 0 | G26: =SUM(G6:G24) -> 0 | I26: =SUM(I6:I24) -> 0 | J26: =SUM(J6:J24) -> 0 | K26: =SUM(K6:K24) -> 0 | M26: =SUM(M6:M24) -> 0 | N26: =SUM(N6:N24) -> 0 | O26: =SUM(O6:O24) -> 0 | P26: =SUM(P6:P24) -> 0
C28: TONTINE | D28: REMBOURSEMENT PETIT LOT | E28: VENTE PETIT LOT | F28: VENTE LOT PRINCIPAL | G28: SOLDE EN CAISSE | I28: TONTINE + REMB + INTERET VENTE | J28: =(C33+D33+P26) -> 0
I29: VENTE LOT | J29: =IF(J28>=2000000,1200000*2,1200000) -> 1200000
B30: ESPECES | C30: =SUMIFS(C6:C24,E6:E24,"ESPECES") -> 0 | D30: =SUMIFS(J6:J24,L6:L24,"ESPECES") -> 0 | E30: =SUMIFS(F6:F24,H6:H24,"ESPECES") -> 0 | F30: =SUMIFS(M6:M24,L6:L24,"ESPECES") -> 0 | G30: =C30+D30-E30-F30 -> 0
B31: BANQUE | C31: =SUMIFS(C6:C24,E6:E24,"BANQUE") -> 0 | D31: =SUMIFS(J6:J24,L6:L24,"BANQUE") -> 0 | E31: =SUMIFS(F6:F24,H6:H24,"BANQUE") -> 0 | F31: =SUMIFS(M6:M24,L6:L24,"BANQUE") -> 0 | G31: =C31+D31-E31-F31 -> 0 | I31: PETIT LOT | J31: =IF(J28>0,J28-J29,0) -> 0
B33: TOTAL | C33: =C30+C31 -> 0 | D33: =D30+D31 -> 0 | E33: =E30+E31 -> 0 | F33: =F30+F31 -> 0 | G33: =G30+G31 -> 0 | I33: RESTE | J33: =J31-F26+TONTOCT!J33 -> -91500
B36: MONTANT TONTINE | C36: 1200000

Sheet TONTDEC
A1: ASSOCIATION | B1: ASELBY
A2: ANNEE | B2: 2019/2020
A3: TONTINE | B3: 75000
C4: 44185
A5: MATRICULE | B5: NOM ET PRENOM | C5: MONTANT TONTINE | D5: PENALITE | E5: MODE VERSEMENT TONTINE | F5: VENTE PETIT LOT | G5: INTERET PETIT LOT | H5: MODE VERSEMENT VENTE PETIT LOT | I5: NUMERO CHEQUE | J5: MONTANT REMBOURSE | K5: MONTANT A REMBOURSER | L5: MODE VERSEMENT REMBOURSEMENT | M5: MODE VERSEMENT TONTINE PRINCIPAL | N5: NUMERO CHEQUE | O5: MONTANT TONTINE LOT PRINCIPAL | P5: INTERET LOT PRINCIPAL
A6: AS201602 | B6: =VLOOKUP(A6,[1]LISTADHERENT!A$5:H$60,3,0) -> BOUTCHOUANG WILLIAM | C6: =IF(E6="ECHEC",0,IF(E6="",0,75000)) -> 0 | D6: =IF(E6="ESPECES",0,0) -> 0 | E6: ECHEC | J6: =K6 -> 0 | K6: =+TONTNOV!F6+TONTNOV!G6 -> 0 | O6: =IF(P6=0,0,($C$36-P6)) -> 0
A7: AS201603 | B7: =VLOOKUP(A7,[1]LISTADHERENT!A$5:H$60,3,0) -> CHINGUE FABRICE | C7: =IF(E7="ECHEC",0,IF(E7="",0,75000)) -> 0 | D7: =IF(E7="ESPECES",0,0) -> 0 | E7: ECHEC | J7: =K7 -> 0 | K7: =+TONTNOV!F7+TONTNOV!G7 -> 0 | O7: =IF(P7=0,0,($C$36-P7)) -> 0
A8: AS201604 | B8: =VLOOKUP(A8,[1]LISTADHERENT!A$5:H$60,3,0) -> DJOMO JEAN PAUL | C8: =IF(E8="ECHEC",0,IF(E8="",0,75000)) -> 0 | D8: =IF(E8="ESPECES",0,0) -> 0 | E8: ECHEC | J8: =K8 -> 0 | K8: =+TONTNOV!F8+TONTNOV!G8 -> 0 | O8: =IF(P8=0,0,($C$36-P8)) -> 0
A9: AS201605 | B9: =VLOOKUP(A9,[1]LISTADHERENT!A$5:H$60,3,0) -> DJOUKWE NANGUEN GUY BLAISE | C9: =IF(E9="ECHEC",0,IF(E9="",0,75000)) -> 0 | D9: =IF(E9="ESPECES",0,0) -> 0 | E9: ECHEC | J9: =K9 -> 0 | K9: =+TONTNOV!F9+TONTNOV!G9 -> 0 | O9: =IF(P9=0,0,($C$36-P9)) -> 0
A10: AS201613 | B10: =VLOOKUP(A10,[1]LISTADHERENT!A$5:H$60,3,0) -> HOTCHO BENJAMIN | C10: =IF(E10="ECHEC",0,IF(E10="",0,75000)) -> 0 | D10: =IF(E10="ESPECES",0,0) -> 0 | E10: ECHEC | J10: =K10 -> 0 | K10: =+TONTNOV!F10+TONTNOV!G10 -> 0 | O10: =IF(P10=0,0,($C$36-P10)) -> 0
A11: AS201611 | B11: =VLOOKUP(A11,[1]LISTADHERENT!A$5:H$60,3,0) -> HENGUE PAUL OMER | C11: =IF(E11="ECHEC",0,IF(E11="",0,75000)) -> 0 | D11: =IF(E11="ESPECES",0,0) -> 0 | E11: ECHEC | J11: =K11 -> 0 | K11: =+TONTNOV!F11+TONTNOV!G11 -> 0 | O11: =IF(P11=0,0,($C$36-P11)) -> 0
A12: AS201619 | B12: =VLOOKUP(A12,[1]LISTADHERENT!A$5:H$60,3,0) -> KOUATCHO MESSACK | C12: =IF(E12="ECHEC",0,IF(E12="",0,75000)) -> 0 | D12: =IF(E12="ESPECES",0,0) -> 0 | E12: ECHEC | J12: =K12 -> 0 | K12: =+TONTNOV!F12+TONTNOV!G12 -> 0 | O12: =IF(P12=0,0,($C$36-P12)) -> 0
A13: AS201621 | B13: =VLOOKUP(A13,[1]LISTADHERENT!A$5:H$60,3,0) -> NANKAM APPOLINAIRE | C13: =IF(E13="ECHEC",0,IF(E13="",0,75000)) -> 0 | D13: =IF(E13="ESPECES",0,0) -> 0 | E13: ECHEC | J13: =K13 -> 0 | K13: =+TONTNOV!F13+TONTNOV!G13 -> 0 | O13: =IF(P13=0,0,($C$36-P13)) -> 0
A14: AS201649 | B14: =VLOOKUP(A14,[1]LISTADHERENT!A$5:H$60,3,0) -> MBOGNING TUGMA GUY | C14: =IF(E14="ECHEC",0,IF(E14="",0,75000)) -> 0 | D14: =IF(E14="ESPECES",0,0) -> 0 | E14: ECHEC | J14: =K14 -> 0 | K14: =+TONTNOV!F14+TONTNOV!G14 -> 0 | O14: =IF(P14=0,0,($C$36-P14)) -> 0
A15: AS201649 | B15: =VLOOKUP(A15,[1]LISTADHERENT!A$5:H$60,3,0) -> MBOGNING TUGMA GUY | C15: =IF(E15="ECHEC",0,IF(E15="",0,75000)) -> 0 | D15: =IF(E15="ESPECES",0,0) -> 0 | E15: ECHEC | J15: =K15 -> 0 | K15: =+TONTNOV!F15+TONTNOV!G15 -> 0 | O15: =IF(P15=0,0,($C$36-P15)) -> 0
A16: AS201649 | B16: =VLOOKUP(A16,[1]LISTADHERENT!A$5:H$60,3,0) -> MBOGNING TUGMA GUY | C16: =IF(E16="ECHEC",0,IF(E16="",0,75000)) -> 0 | D16: =IF(E16="ESPECES",0,0) -> 0 | E16: ECHEC | J16: =K16 -> 0 | K16: =+TONTNOV!F16+TONTNOV!G16 -> 0 | O16: =IF(P16=0,0,($C$36-P16)) -> 0
A17: AS201626 | B17: =VLOOKUP(A17,[1]LISTADHERENT!A$5:H$60,3,0) -> NGUIEMEGNI MATHIEU BLAISE | C17: =IF(E17="ECHEC",0,IF(E17="",0,75000)) -> 0 | D17: =IF(E17="ESPECES",0,0) -> 0 | E17: ECHEC | J17: =K17 -> 0 | K17: =+TONTNOV!F17+TONTNOV!G17 -> 0 | O17: =IF(P17=0,0,($C$36-P17)) -> 0
... A24: AS201647 | B24: =VLOOKUP(A24,[1]LISTADHERENT!A$5:H$60,3,0) -> YOUMBI EMMANUEL | C24: =IF(E24="ECHEC",0,IF(E24="",0,75000)) -> 0 | D24: =IF(E24="ESPECES",0,0) -> 0 | E24: ECHEC | J24: =K24 -> 0 | K24: =+TONTNOV!F24+TONTNOV!G24 -> 0 | O24: =IF(P24=0,0,($C$36-P24)) -> 0
A26: TOTAL | C26: =SUM(C6:C24) -> 0 | D26: =SUM(D6:D24) -> 0 | F26: =SUM(F6:F24) -> 0 | G26: =SUM(G6:G24) -> 0 | I26: =SUM(I6:I24) -> 0 | J26: =SUM(J6:J24) -> 0 | K26: =SUM(K6:K24) -> 0 | M26: =SUM(M6:M24) -> 0 | N26: =SUM(N6:N24) -> 0 | O26: =SUM(O6:O24) -> 0 | P26: =SUM(P6:P24) -> 0
C28: TONTINE | D28: REMBOURSEMENT PETIT LOT | E28: VENTE PETIT LOT | F28: VENTE LOT PRINCIPAL | G28: SOLDE EN CAISSE | I28: TONTINE + REMB + INTERET VENTE | J28: =(C33+D33+P26) -> 0
I29: VENTE LOT | J29: =IF(J28>=2000000,1200000*2,1200000) -> 1200000
B30: ESPECES | C30: =SUMIFS(C6:C24,E6:E24,"ESPECES") -> 0 | D30: =SUMIFS(J6:J24,L6:L24,"ESPECES") -> 0 | E30: =SUMIFS(F6:F24,H6:H24,"ESPECES") -> 0 | F30: =SUMIFS(M6:M24,L6:L24,"ESPECES") -> 0 | G30: =C30+D30-E30-F30 -> 0
B31: BANQUE | C31: =SUMIFS(C6:C24,E6:E24,"BANQUE") -> 0 | D31: =SUMIFS(J6:J24,L6:L24,"BANQUE") -> 0 | E31: =SUMIFS(F6:F24,H6:H24,"BANQUE") -> 0 | F31: =SUMIFS(M6:M24,L6:L24,"BANQUE") -> 0 | G31: =C31+D31-E31-F31 -> 0 | I31: PETIT LOT | J31: =IF(J28>0,J28-J29,0) -> 0
B33: TOTAL | C33: =C30+C31 -> 0 | D33: =D30+D31 -> 0 | E33: =E30+E31 -> 0 | F33: =F30+F31 -> 0 | G33: =G30+G31 -> 0 | I33: RESTE | J33: =J31-F26+TONTNOV!J33 -> -91500
B36: MONTANT TONTINE | C36: 1200000

Sheet TONTJANV
A1: ASSOCIATION | B1: ASELBY
A2: ANNEE | B2: 2019/2020
A3: TONTINE | B3: 75000
C4: 44213
A5: MATRICULE | B5: NOM ET PRENOM | C5: MONTANT TONTINE | D5: PENALITE | E5: MODE VERSEMENT TONTINE | F5: VENTE PETIT LOT | G5: INTERET PETIT LOT | H5: MODE VERSEMENT VENTE PETIT LOT | I5: NUMERO CHEQUE | J5: MONTANT REMBOURSE | K5: MONTANT A REMBOURSER | L5: MODE VERSEMENT REMBOURSEMENT | M5: MODE VERSEMENT TONTINE PRINCIPAL | N5: NUMERO CHEQUE | O5: MONTANT TONTINE LOT PRINCIPAL | P5: INTERET LOT PRINCIPAL
A6: AS201602 | B6: =VLOOKUP(A6,[1]LISTADHERENT!A$5:H$60,3,0) -> BOUTCHOUANG WILLIAM | C6: =IF(E6="ECHEC",0,IF(E6="",0,75000)) -> 0 | D6: =IF(E6="ESPECES",0,0) -> 0 | E6: ECHEC | J6: =K6 -> 0 | K6: =+TONTDEC!F6+TONTDEC!G6 -> 0 | O6: =IF(P6=0,0,($C$36-P6)) -> 0
A7: AS201603 | B7: =VLOOKUP(A7,[1]LISTADHERENT!A$5:H$60,3,0) -> CHINGUE FABRICE | C7: =IF(E7="ECHEC",0,IF(E7="",0,75000)) -> 0 | D7: =IF(E7="ESPECES",0,0) -> 0 | E7: ECHEC | J7: =K7 -> 0 | K7: =+TONTDEC!F7+TONTDEC!G7 -> 0 | O7: =IF(P7=0,0,($C$36-P7)) -> 0
A8: AS201604 | B8: =VLOOKUP(A8,[1]LISTADHERENT!A$5:H$60,3,0) -> DJOMO JEAN PAUL | C8: =IF(E8="ECHEC",0,IF(E8="",0,75000)) -> 0 | D8: =IF(E8="ESPECES",0,0) -> 0 | E8: ECHEC | J8: =K8 -> 0 | K8: =+TONTDEC!F8+TONTDEC!G8 -> 0 | O8: =IF(P8=0,0,($C$36-P8)) -> 0
A9: AS201605 | B9: =VLOOKUP(A9,[1]LISTADHERENT!A$5:H$60,3,0) -> DJOUKWE NANGUEN GUY BLAISE | C9: =IF(E9="ECHEC",0,IF(E9="",0,75000)) -> 0 | D9: =IF(E9="ESPECES",0,0) -> 0 | E9: ECHEC | J9: =K9 -> 0 | K9: =+TONTDEC!F9+TONTDEC!G9 -> 0 | O9: =IF(P9=0,0,($C$36-P9)) -> 0
A10: AS201613 | B10: =VLOOKUP(A10,[1]LISTADHERENT!A$5:H$60,3,0) -> HOTCHO BENJAMIN | C10: =IF(E10="ECHEC",0,IF(E10="",0,75000)) -> 0 | D10: =IF(E10="ESPECES",0,0) -> 0 | E10: ECHEC | J10: =K10 -> 0 | K10: =+TONTDEC!F10+TONTDEC!G10 -> 0 | O10: =IF(P10=0,0,($C$36-P10)) -> 0
A11: AS201611 | B11: =VLOOKUP(A11,[1]LISTADHERENT!A$5:H$60,3,0) -> HENGUE PAUL OMER | C11: =IF(E11="ECHEC",0,IF(E11="",0,75000)) -> 0 | D11: =IF(E11="ESPECES",0,0) -> 0 | E11: ECHEC | J11: =K11 -> 0 | K11: =+TONTDEC!F11+TONTDEC!G11 -> 0 | O11: =IF(P11=0,0,($C$36-P11)) -> 0
A12: AS201619 | B12: =VLOOKUP(A12,[1]LISTADHERENT!A$5:H$60,3,0) -> KOUATCHO MESSACK | C12: =IF(E12="ECHEC",0,IF(E12="",0,75000)) -> 0 | D12: =IF(E12="ESPECES",0,0) -> 0 | E12: ECHEC | J12: =K12 -> 0 | K12: =+TONTDEC!F12+TONTDEC!G12 -> 0 | O12: =IF(P12=0,0,($C$36-P12)) -> 0
A13: AS201621 | B13: =VLOOKUP(A13,[1]LISTADHERENT!A$5:H$60,3,0) -> NANKAM APPOLINAIRE | C13: =IF(E13="ECHEC",0,IF(E13="",0,75000)) -> 0 | D13: =IF(E13="ESPECES",0,0) -> 0 | E13: ECHEC | J13: =K13 -> 0 | K13: =+TONTDEC!F13+TONTDEC!G13 -> 0 | O13: =IF(P13=0,0,($C$36-P13)) -> 0
A14: AS201649 | B14: =VLOOKUP(A14,[1]LISTADHERENT!A$5:H$60,3,0) -> MBOGNING TUGMA GUY | C14: =IF(E14="ECHEC",0,IF(E14="",0,75000)) -> 0 | D14: =IF(E14="ESPECES",0,0) -> 0 | E14: ECHEC | J14: =K14 -> 0 | K14: =+TONTDEC!F14+TONTDEC!G14 -> 0 | O14: =IF(P14=0,0,($C$36-P14)) -> 0
A15: AS201649 | B15: =VLOOKUP(A15,[1]LISTADHERENT!A$5:H$60,3,0) -> MBOGNING TUGMA GUY | C15: =IF(E15="ECHEC",0,IF(E15="",0,75000)) -> 0 | D15: =IF(E15="ESPECES",0,0) -> 0 | E15: ECHEC | J15: =K15 -> 0 | K15: =+TONTDEC!F15+TONTDEC!G15 -> 0 | O15: =IF(P15=0,0,($C$36-P15)) -> 0
A16: AS201649 | B16: =VLOOKUP(A16,[1]LISTADHERENT!A$5:H$60,3,0) -> MBOGNING TUGMA GUY | C16: =IF(E16="ECHEC",0,IF(E16="",0,75000)) -> 0 | D16: =IF(E16="ESPECES",0,0) -> 0 | E16: ECHEC | J16: =K16 -> 0 | K16: =+TONTDEC!F16+TONTDEC!G16 -> 0 | O16: =IF(P16=0,0,($C$36-P16)) -> 0
A17: AS201626 | B17: =VLOOKUP(A17,[1]LISTADHERENT!A$5:H$60,3,0) -> NGUIEMEGNI MATHIEU BLAISE | C17: =IF(E17="ECHEC",0,IF(E17="",0,75000)) -> 0 | D17: =IF(E17="ESPECES",0,0) -> 0 | E17: ECHEC | J17: =K17 -> 0 | K17: =+TONTDEC!F17+TONTDEC!G17 -> 0 | O17: =IF(P17=0,0,($C$36-P17)) -> 0
... A24: AS201647 | B24: =VLOOKUP(A24,[1]LISTADHERENT!A$5:H$60,3,0) -> YOUMBI EMMANUEL | C24: =IF(E24="ECHEC",0,IF(E24="",0,75000)) -> 0 | D24: =IF(E24="ESPECES",0,0) -> 0 | E24: ECHEC | J24: =K24 -> 0 | K24: =+TONTDEC!F24+TONTDEC!G24 -> 0 | O24: =IF(P24=0,0,($C$36-P24)) -> 0
A26: TOTAL | C26: =SUM(C6:C24) -> 0 | D26: =SUM(D6:D24) -> 0 | F26: =SUM(F6:F24) -> 0 | G26: =SUM(G6:G24) -> 0 | I26: =SUM(I6:I24) -> 0 | J26: =SUM(J6:J24) -> 0 | K26: =SUM(K6:K24) -> 0 | M26: =SUM(M6:M24) -> 0 | N26: =SUM(N6:N24) -> 0 | O26: =SUM(O6:O24) -> 0 | P26: =SUM(P6:P24) -> 0
C28: TONTINE | D28: REMBOURSEMENT PETIT LOT | E28: VENTE PETIT LOT | F28: VENTE LOT PRINCIPAL | G28: SOLDE EN CAISSE | I28: TONTINE + REMB + INTERET VENTE | J28: =(C33+D33+P26) -> 0
I29: VENTE LOT | J29: =IF(J28>=2000000,1200000*2,1200000) -> 1200000
B30: ESPECES | C30: =SUMIFS(C6:C24,E6:E24,"ESPECES") -> 0 | D30: =SUMIFS(J6:J24,L6:L24,"ESPECES") -> 0 | E30: =SUMIFS(F6:F24,H6:H24,"ESPECES") -> 0 | F30: =SUMIFS(M6:M24,L6:L24,"ESPECES") -> 0 | G30: =C30+D30-E30-F30 -> 0
B31: BANQUE | C31: =SUMIFS(C6:C24,E6:E24,"BANQUE") -> 0 | D31: =SUMIFS(J6:J24,L6:L24,"BANQUE") -> 0 | E31: =SUMIFS(F6:F24,H6:H24,"BANQUE") -> 0 | F31: =SUMIFS(M6:M24,L6:L24,"BANQUE") -> 0 | G31: =C31+D31-E31-F31 -> 0 | I31: PETIT LOT | J31: =IF(J28>0,J28-J29,0) -> 0
B33: TOTAL | C33: =C30+C31 -> 0 | D33: =D30+D31 -> 0 | E33: =E30+E31 -> 0 | F33: =F30+F31 -> 0 | G33: =G30+G31 -> 0 | I33: RESTE | J33: =J31-F26+TONTDEC!J33 -> -91500
B36: MONTANT TONTINE | C36: 1200000

Sheet TONTFEV
A1: ASSOCIATION | B1: ASELBY
A2: ANNEE | B2: 2019/2020
A3: TONTINE | B3: 75000
C4: 44248
A5: MATRICULE | B5: NOM ET PRENOM | C5: MONTANT TONTINE | D5: PENALITE | E5: MODE VERSEMENT TONTINE | F5: VENTE PETIT LOT | G5: INTERET PETIT LOT | H5: MODE VERSEMENT VENTE PETIT LOT | I5: NUMERO CHEQUE | J5: MONTANT REMBOURSE | K5: MONTANT A REMBOURSER | L5: MODE VERSEMENT REMBOURSEMENT | M5: MODE VERSEMENT TONTINE PRINCIPAL | N5: NUMERO CHEQUE | O5: MONTANT TONTINE LOT PRINCIPAL | P5: INTERET LOT PRINCIPAL
A6: AS201602 | B6: =VLOOKUP(A6,[1]LISTADHERENT!A$5:H$60,3,0) -> BOUTCHOUANG WILLIAM | C6: =IF(E6="ECHEC",0,IF(E6="",0,75000)) -> 0 | D6: =IF(E6="ESPECES",0,0) -> 0 | E6: ECHEC | J6: =K6 -> 0 | K6: =+TONTJANV!F6+TONTJANV!G6 -> 0 | O6: =IF(P6=0,0,($C$36-P6)) -> 0
A7: AS201603 | B7: =VLOOKUP(A7,[1]LISTADHERENT!A$5:H$60,3,0) -> CHINGUE FABRICE | C7: =IF(E7="ECHEC",0,IF(E7="",0,75000)) -> 0 | D7: =IF(E7="ESPECES",0,0) -> 0 | E7: ECHEC | J7: =K7 -> 0 | K7: =+TONTJANV!F7+TONTJANV!G7 -> 0 | O7: =IF(P7=0,0,($C$36-P7)) -> 0
A8: AS201604 | B8: =VLOOKUP(A8,[1]LISTADHERENT!A$5:H$60,3,0) -> DJOMO JEAN PAUL | C8: =IF(E8="ECHEC",0,IF(E8="",0,75000)) -> 0 | D8: =IF(E8="ESPECES",0,0) -> 0 | E8: ECHEC | J8: =K8 -> 0 | K8: =+TONTJANV!F8+TONTJANV!G8 -> 0 | O8: =IF(P8=0,0,($C$36-P8)) -> 0
A9: AS201605 | B9: =VLOOKUP(A9,[1]LISTADHERENT!A$5:H$60,3,0) -> DJOUKWE NANGUEN GUY BLAISE | C9: =IF(E9="ECHEC",0,IF(E9="",0,75000)) -> 0 | D9: =IF(E9="ESPECES",0,0) -> 0 | E9: ECHEC | J9: =K9 -> 0 | K9: =+TONTJANV!F9+TONTJANV!G9 -> 0 | O9: =IF(P9=0,0,($C$36-P9)) -> 0
A10: AS201613 | B10: =VLOOKUP(A10,[1]LISTADHERENT!A$5:H$60,3,0) -> HOTCHO BENJAMIN | C10: =IF(E10="ECHEC",0,IF(E10="",0,75000)) -> 0 | D10: =IF(E10="ESPECES",0,0) -> 0 | E10: ECHEC | J10: =K10 -> 0 | K10: =+TONTJANV!F10+TONTJANV!G10 -> 0 | O10: =IF(P10=0,0,($C$36-P10)) -> 0
A11: AS201611 | B11: =VLOOKUP(A11,[1]LISTADHERENT!A$5:H$60,3,0) -> HENGUE PAUL OMER | C11: =IF(E11="ECHEC",0,IF(E11="",0,75000)) -> 0 | D11: =IF(E11="ESPECES",0,0) -> 0 | E11: ECHEC | J11: =K11 -> 0 | K11: =+TONTJANV!F11+TONTJANV!G11 -> 0 | O11: =IF(P11=0,0,($C$36-P11)) -> 0
A12: AS201619 | B12: =VLOOKUP(A12,[1]LISTADHERENT!A$5:H$60,3,0) -> KOUATCHO MESSACK | C12: =IF(E12="ECHEC",0,IF(E12="",0,75000)) -> 0 | D12: =IF(E12="ESPECES",0,0) -> 0 | E12: ECHEC | J12: =K12 -> 0 | K12: =+TONTJANV!F12+TONTJANV!G12 -> 0 | O12: =IF(P12=0,0,($C$36-P12)) -> 0
A13: AS201621 | B13: =VLOOKUP(A13,[1]LISTADHERENT!A$5:H$60,3,0) -> NANKAM APPOLINAIRE | C13: =IF(E13="ECHEC",0,IF(E13="",0,75000)) -> 0 | D13: =IF(E13="ESPECES",0,0) -> 0 | E13: ECHEC | J13: =K13 -> 0 | K13: =+TONTJANV!F13+TONTJANV!G13 -> 0 | O13: =IF(P13=0,0,($C$36-P13)) -> 0
A14: AS201649 | B14: =VLOOKUP(A14,[1]LISTADHERENT!A$5:H$60,3,0) -> MBOGNING TUGMA GUY | C14: =IF(E14="ECHEC",0,IF(E14="",0,75000)) -> 0 | D14: =IF(E14="ESPECES",0,0) -> 0 | E14: ECHEC | J14: =K14 -> 0 | K14: =+TONTJANV!F14+TONTJANV!G14 -> 0 | O14: =IF(P14=0,0,($C$36-P14)) -> 0
A15: AS201649 | B15: =VLOOKUP(A15,[1]LISTADHERENT!A$5:H$60,3,0) -> MBOGNING TUGMA GUY | C15: =IF(E15="ECHEC",0,IF(E15="",0,75000)) -> 0 | D15: =IF(E15="ESPECES",0,0) -> 0 | E15: ECHEC | J15: =K15 -> 0 | K15: =+TONTJANV!F15+TONTJANV!G15 -> 0 | O15: =IF(P15=0,0,($C$36-P15)) -> 0
A16: AS201649 | B16: =VLOOKUP(A16,[1]LISTADHERENT!A$5:H$60,3,0) -> MBOGNING TUGMA GUY | C16: =IF(E16="ECHEC",0,IF(E16="",0,75000)) -> 0 | D16: =IF(E16="ESPECES",0,0) -> 0 | E16: ECHEC | J16: =K16 -> 0 | K16: =+TONTJANV!F16+TONTJANV!G16 -> 0 | O16: =IF(P16=0,0,($C$36-P16)) -> 0
A17: AS201626 | B17: =VLOOKUP(A17,[1]LISTADHERENT!A$5:H$60,3,0) -> NGUIEMEGNI MATHIEU BLAISE | C17: =IF(E17="ECHEC",0,IF(E17="",0,75000)) -> 0 | D17: =IF(E17="ESPECES",0,0) -> 0 | E17: ECHEC | J17: =K17 -> 0 | K17: =+TONTJANV!F17+TONTJANV!G17 -> 0 | O17: =IF(P17=0,0,($C$36-P17)) -> 0
... A24: AS201647 | B24: =VLOOKUP(A24,[1]LISTADHERENT!A$5:H$60,3,0) -> YOUMBI EMMANUEL | C24: =IF(E24="ECHEC",0,IF(E24="",0,75000)) -> 0 | D24: =IF(E24="ESPECES",0,0) -> 0 | E24: ECHEC | J24: =K24 -> 0 | K24: =+TONTJANV!F24+TONTJANV!G24 -> 0 | O24: =IF(P24=0,0,($C$36-P24)) -> 0
A26: TOTAL | C26: =SUM(C6:C24) -> 0 | D26: =SUM(D6:D24) -> 0 | F26: =SUM(F6:F24) -> 0 | G26: =SUM(G6:G24) -> 0 | I26: =SUM(I6:I24) -> 0 | J26: =SUM(J6:J24) -> 0 | K26: =SUM(K6:K24) -> 0 | M26: =SUM(M6:M24) -> 0 | N26: =SUM(N6:N24) -> 0 | O26: =SUM(O6:O24) -> 0 | P26: =SUM(P6:P24) -> 0
C28: TONTINE | D28: REMBOURSEMENT PETIT LOT | E28: VENTE PETIT LOT | F28: VENTE LOT PRINCIPAL | G28: SOLDE EN CAISSE | I28: TONTINE + REMB + INTERET VENTE | J28: =(C33+D33+P26) -> 0
I29: VENTE LOT | J29: =IF(J28>=2000000,1200000*2,1200000) -> 1200000
B30: ESPECES | C30: =SUMIFS(C6:C24,E6:E24,"ESPECES") -> 0 | D30: =SUMIFS(J6:J24,L6:L24,"ESPECES") -> 0 | E30: =SUMIFS(F6:F24,H6:H24,"ESPECES") -> 0 | F30: =SUMIFS(M6:M24,L6:L24,"ESPECES") -> 0 | G30: =C30+D30-E30-F30 -> 0
B31: BANQUE | C31: =SUMIFS(C6:C24,E6:E24,"BANQUE") -> 0 | D31: =SUMIFS(J6:J24,L6:L24,"BANQUE") -> 0 | E31: =SUMIFS(F6:F24,H6:H24,"BANQUE") -> 0 | F31: =SUMIFS(M6:M24,L6:L24,"BANQUE") -> 0 | G31: =C31+D31-E31-F31 -> 0 | I31: PETIT LOT | J31: =IF(J28>0,J28-J29,0) -> 0
B33: TOTAL | C33: =C30+C31 -> 0 | D33: =D30+D31 -> 0 | E33: =E30+E31 -> 0 | F33: =F30+F31 -> 0 | G33: =G30+G31 -> 0 | I33: RESTE | J33: =J31-F26+TONTJANV!J33 -> -91500
B36: MONTANT TONTINE | C36: 1200000

Sheet TONTMARS
A1: ASSOCIATION | B1: ASELBY
A2: ANNEE | B2: 2019/2020
A3: TONTINE | B3: 75000
C4: 44276
A5: MATRICULE | B5: NOM ET PRENOM | C5: MONTANT TONTINE | D5: PENALITE | E5: MODE VERSEMENT TONTINE | F5: VENTE PETIT LOT | G5: INTERET PETIT LOT | H5: MODE VERSEMENT VENTE PETIT LOT | I5: NUMERO CHEQUE | J5: MONTANT REMBOURSE | K5: MONTANT A REMBOURSER | L5: MODE VERSEMENT REMBOURSEMENT | M5: MODE VERSEMENT TONTINE PRINCIPAL | N5: NUMERO CHEQUE | O5: MONTANT TONTINE LOT PRINCIPAL | P5: INTERET LOT PRINCIPAL
A6: AS201602 | B6: =VLOOKUP(A6,[1]LISTADHERENT!A$5:H$60,3,0) -> BOUTCHOUANG WILLIAM | C6: =IF(E6="ECHEC",0,IF(E6="",0,75000)) -> 0 | D6: =IF(E6="ESPECES",0,0) -> 0 | E6: ECHEC | J6: =K6 -> 0 | K6: =+TONTFEV!F6+TONTFEV!G6 -> 0 | O6: =IF(P6=0,0,($C$36-P6)) -> 0
A7: AS201603 | B7: =VLOOKUP(A7,[1]LISTADHERENT!A$5:H$60,3,0) -> CHINGUE FABRICE | C7: =IF(E7="ECHEC",0,IF(E7="",0,75000)) -> 0 | D7: =IF(E7="ESPECES",0,0) -> 0 | E7: ECHEC | J7: =K7 -> 0 | K7: =+TONTFEV!F7+TONTFEV!G7 -> 0 | O7: =IF(P7=0,0,($C$36-P7)) -> 0
A8: AS201604 | B8: =VLOOKUP(A8,[1]LISTADHERENT!A$5:H$60,3,0) -> DJOMO JEAN PAUL | C8: =IF(E8="ECHEC",0,IF(E8="",0,75000)) -> 0 | D8: =IF(E8="ESPECES",0,0) -> 0 | E8: ECHEC | J8: =K8 -> 0 | K8: =+TONTFEV!F8+TONTFEV!G8 -> 0 | O8: =IF(P8=0,0,($C$36-P8)) -> 0
A9: AS201605 | B9: =VLOOKUP(A9,[1]LISTADHERENT!A$5:H$60,3,0) -> DJOUKWE NANGUEN GUY BLAISE | C9: =IF(E9="ECHEC",0,IF(E9="",0,75000)) -> 0 | D9: =IF(E9="ESPECES",0,0) -> 0 | E9: ECHEC | J9: =K9 -> 0 | K9: =+TONTFEV!F9+TONTFEV!G9 -> 0 | O9: =IF(P9=0,0,($C$36-P9)) -> 0
A10: AS201613 | B10: =VLOOKUP(A10,[1]LISTADHERENT!A$5:H$60,3,0) -> HOTCHO BENJAMIN | C10: =IF(E10="ECHEC",0,IF(E10="",0,75000)) -> 0 | D10: =IF(E10="ESPECES",0,0) -> 0 | E10: ECHEC | J10: =K10 -> 0 | K10: =+TONTFEV!F10+TONTFEV!G10 -> 0 | O10: =IF(P10=0,0,($C$36-P10)) -> 0
A11: AS201611 | B11: =VLOOKUP(A11,[1]LISTADHERENT!A$5:H$60,3,0) -> HENGUE PAUL OMER | C11: =IF(E11="ECHEC",0,IF(E11="",0,75000)) -> 0 | D11: =IF(E11="ESPECES",0,0) -> 0 | E11: ECHEC | J11: =K11 -> 0 | K11: =+TONTFEV!F11+TONTFEV!G11 -> 0 | O11: =IF(P11=0,0,($C$36-P11)) -> 0
A12: AS201619 | B12: =VLOOKUP(A12,[1]LISTADHERENT!A$5:H$60,3,0) -> KOUATCHO MESSACK | C12: =IF(E12="ECHEC",0,IF(E12="",0,75000)) -> 0 | D12: =IF(E12="ESPECES",0,0) -> 0 | E12: ECHEC | J12: =K12 -> 0 | K12: =+TONTFEV!F12+TONTFEV!G12 -> 0 | O12: =IF(P12=0,0,($C$36-P12)) -> 0
A13: AS201621 | B13: =VLOOKUP(A13,[1]LISTADHERENT!A$5:H$60,3,0) -> NANKAM APPOLINAIRE | C13: =IF(E13="ECHEC",0,IF(E13="",0,75000)) -> 0 | D13: =IF(E13="ESPECES",0,0) -> 0 | E13: ECHEC | J13: =K13 -> 0 | K13: =+TONTFEV!F13+TONTFEV!G13 -> 0 | O13: =IF(P13=0,0,($C$36-P13)) -> 0
A14: AS201649 | B14: =VLOOKUP(A14,[1]LISTADHERENT!A$5:H$60,3,0) -> MBOGNING TUGMA GUY | C14: =IF(E14="ECHEC",0,IF(E14="",0,75000)) -> 0 | D14: =IF(E14="ESPECES",0,0) -> 0 | E14: ECHEC | J14: =K14 -> 0 | K14: =+TONTFEV!F14+TONTFEV!G14 -> 0 | O14: =IF(P14=0,0,($C$36-P14)) -> 0
A15: AS201649 | B15: =VLOOKUP(A15,[1]LISTADHERENT!A$5:H$60,3,0) -> MBOGNING TUGMA GUY | C15: =IF(E15="ECHEC",0,IF(E15="",0,75000)) -> 0 | D15: =IF(E15="ESPECES",0,0) -> 0 | E15: ECHEC | J15: =K15 -> 0 | K15: =+TONTFEV!F15+TONTFEV!G15 -> 0 | O15: =IF(P15=0,0,($C$36-P15)) -> 0
A16: AS201649 | B16: =VLOOKUP(A16,[1]LISTADHERENT!A$5:H$60,3,0) -> MBOGNING TUGMA GUY | C16: =IF(E16="ECHEC",0,IF(E16="",0,75000)) -> 0 | D16: =IF(E16="ESPECES",0,0) -> 0 | E16: ECHEC | J16: =K16 -> 0 | K16: =+TONTFEV!F16+TONTFEV!G16 -> 0 | O16: =IF(P16=0,0,($C$36-P16)) -> 0
A17: AS201626 | B17: =VLOOKUP(A17,[1]LISTADHERENT!A$5:H$60,3,0) -> NGUIEMEGNI MATHIEU BLAISE | C17: =IF(E17="ECHEC",0,IF(E17="",0,75000)) -> 0 | D17: =IF(E17="ESPECES",0,0) -> 0 | E17: ECHEC | J17: =K17 -> 0 | K17: =+TONTFEV!F17+TONTFEV!G17 -> 0 | O17: =IF(P17=0,0,($C$36-P17)) -> 0
... A24: AS201647 | B24: =VLOOKUP(A24,[1]LISTADHERENT!A$5:H$60,3,0) -> YOUMBI EMMANUEL | C24: =IF(E24="ECHEC",0,IF(E24="",0,75000)) -> 0 | D24: =IF(E24="ESPECES",0,0) -> 0 | E24: ECHEC | J24: =K24 -> 0 | K24: =+TONTFEV!F24+TONTFEV!G24 -> 0 | O24: =IF(P24=0,0,($C$36-P24)) -> 0
A26: TOTAL | C26: =SUM(C6:C24) -> 0 | D26: =SUM(D6:D24) -> 0 | F26: =SUM(F6:F24) -> 0 | G26: =SUM(G6:G24) -> 0 | I26: =SUM(I6:I24) -> 0 | J26: =SUM(J6:J24) -> 0 | K26: =SUM(K6:K24) -> 0 | M26: =SUM(M6:M24) -> 0 | N26: =SUM(N6:N24) -> 0 | O26: =SUM(O6:O24) -> 0 | P26: =SUM(P6:P24) -> 0
C28: TONTINE | D28: REMBOURSEMENT PETIT LOT | E28: VENTE PETIT LOT | F28: VENTE LOT PRINCIPAL | G28: SOLDE EN CAISSE | I28: TONTINE + REMB + INTERET VENTE | J28: =(C33+D33+P26) -> 0
I29: VENTE LOT | J29: =IF(J28>=2000000,1200000*2,1200000) -> 1200000
B30: ESPECES | C30: =SUMIFS(C6:C24,E6:E24,"ESPECES") -> 0 | D30: =SUMIFS(J6:J24,L6:L24,"ESPECES") -> 0 | E30: =SUMIFS(F6:F24,H6:H24,"ESPECES") -> 0 | F30: =SUMIFS(M6:M24,L6:L24,"ESPECES") -> 0 | G30: =C30+D30-E30-F30 -> 0
B31: BANQUE | C31: =SUMIFS(C6:C24,E6:E24,"BANQUE") -> 0 | D31: =SUMIFS(J6:J24,L6:L24,"BANQUE") -> 0 | E31: =SUMIFS(F6:F24,H6:H24,"BANQUE") -> 0 | F31: =SUMIFS(M6:M24,L6:L24,"BANQUE") -> 0 | G31: =C31+D31-E31-F31 -> 0 | I31: PETIT LOT | J31: =IF(J28>0,J28-J29,0) -> 0
B33: TOTAL | C33: =C30+C31 -> 0 | D33: =D30+D31 -> 0 | E33: =E30+E31 -> 0 | F33: =F30+F31 -> 0 | G33: =G30+G31 -> 0 | I33: RESTE | J33: =J31-F26+TONTFEV!J33 -> -91500
B36: MONTANT TONTINE | C36: 1200000

Sheet TONTAVRIL
A1: ASSOCIATION | B1: ASELBY
A2: ANNEE | B2: 2019/2020
A3: TONTINE | B3: 75000
C4: 44304
A5: MATRICULE | B5: NOM ET PRENOM | C5: MONTANT TONTINE | D5: PENALITE | E5: MODE VERSEMENT TONTINE | F5: VENTE PETIT LOT | G5: INTERET PETIT LOT | H5: MODE VERSEMENT VENTE PETIT LOT | I5: NUMERO CHEQUE | J5: MONTANT REMBOURSE | K5: MONTANT A REMBOURSER | L5: MODE VERSEMENT REMBOURSEMENT | M5: MODE VERSEMENT TONTINE PRINCIPAL | N5: NUMERO CHEQUE | O5: MONTANT TONTINE LOT PRINCIPAL | P5: INTERET LOT PRINCIPAL
A6: AS201602 | B6: =VLOOKUP(A6,[1]LISTADHERENT!A$5:H$60,3,0) -> BOUTCHOUANG WILLIAM | C6: =IF(E6="ECHEC",0,IF(E6="",0,75000)) -> 0 | D6: =IF(E6="ESPECES",0,0) -> 0 | E6: ECHEC | J6: =K6 -> 0 | K6: =+TONTMARS!F6+TONTMARS!G6 -> 0 | O6: =IF(P6=0,0,($C$36-P6)) -> 0
A7: AS201603 | B7: =VLOOKUP(A7,[1]LISTADHERENT!A$5:H$60,3,0) -> CHINGUE FABRICE | C7: =IF(E7="ECHEC",0,IF(E7="",0,75000)) -> 0 | D7: =IF(E7="ESPECES",0,0) -> 0 | E7: ECHEC | J7: =K7 -> 0 | K7: =+TONTMARS!F7+TONTMARS!G7 -> 0 | O7: =IF(P7=0,0,($C$36-P7)) -> 0
A8: AS201604 | B8: =VLOOKUP(A8,[1]LISTADHERENT!A$5:H$60,3,0) -> DJOMO JEAN PAUL | C8: =IF(E8="ECHEC",0,IF(E8="",0,75000)) -> 0 | D8: =IF(E8="ESPECES",0,0) -> 0 | E8: ECHEC | J8: =K8 -> 0 | K8: =+TONTMARS!F8+TONTMARS!G8 -> 0 | O8: =IF(P8=0,0,($C$36-P8)) -> 0
A9: AS201605 | B9: =VLOOKUP(A9,[1]LISTADHERENT!A$5:H$60,3,0) -> DJOUKWE NANGUEN GUY BLAISE | C9: =IF(E9="ECHEC",0,IF(E9="",0,75000)) -> 0 | D9: =IF(E9="ESPECES",0,0) -> 0 | E9: ECHEC | J9: =K9 -> 0 | K9: =+TONTMARS!F9+TONTMARS!G9 -> 0 | O9: =IF(P9=0,0,($C$36-P9)) -> 0
A10: AS201613 | B10: =VLOOKUP(A10,[1]LISTADHERENT!A$5:H$60,3,0) -> HOTCHO BENJAMIN | C10: =IF(E10="ECHEC",0,IF(E10="",0,75000)) -> 0 | D10: =IF(E10="ESPECES",0,0) -> 0 | E10: ECHEC | J10: =K10 -> 0 | K10: =+TONTMARS!F10+TONTMARS!G10 -> 0 | O10: =IF(P10=0,0,($C$36-P10)) -> 0
A11: AS201611 | B11: =VLOOKUP(A11,[1]LISTADHERENT!A$5:H$60,3,0) -> HENGUE PAUL OMER | C11: =IF(E11="ECHEC",0,IF(E11="",0,75000)) -> 0 | D11: =IF(E11="ESPECES",0,0) -> 0 | E11: ECHEC | J11: =K11 -> 0 | K11: =+TONTMARS!F11+TONTMARS!G11 -> 0 | O11: =IF(P11=0,0,($C$36-P11)) -> 0
A12: AS201619 | B12: =VLOOKUP(A12,[1]LISTADHERENT!A$5:H$60,3,0) -> KOUATCHO MESSACK | C12: =IF(E12="ECHEC",0,IF(E12="",0,75000)) -> 0 | D12: =IF(E12="ESPECES",0,0) -> 0 | E12: ECHEC | J12: =K12 -> 0 | K12: =+TONTMARS!F12+TONTMARS!G12 -> 0 | O12: =IF(P12=0,0,($C$36-P12)) -> 0
A13: AS201621 | B13: =VLOOKUP(A13,[1]LISTADHERENT!A$5:H$60,3,0) -> NANKAM APPOLINAIRE | C13: =IF(E13="ECHEC",0,IF(E13="",0,75000)) -> 0 | D13: =IF(E13="ESPECES",0,0) -> 0 | E13: ECHEC | J13: =K13 -> 0 | K13: =+TONTMARS!F13+TONTMARS!G13 -> 0 | O13: =IF(P13=0,0,($C$36-P13)) -> 0
A14: AS201649 | B14: =VLOOKUP(A14,[1]LISTADHERENT!A$5:H$60,3,0) -> MBOGNING TUGMA GUY | C14: =IF(E14="ECHEC",0,IF(E14="",0,75000)) -> 0 | D14: =IF(E14="ESPECES",0,0) -> 0 | E14: ECHEC | J14: =K14 -> 0 | K14: =+TONTMARS!F14+TONTMARS!G14 -> 0 | O14: =IF(P14=0,0,($C$36-P14)) -> 0
A15: AS201649 | B15: =VLOOKUP(A15,[1]LISTADHERENT!A$5:H$60,3,0) -> MBOGNING TUGMA GUY | C15: =IF(E15="ECHEC",0,IF(E15="",0,75000)) -> 0 | D15: =IF(E15="ESPECES",0,0) -> 0 | E15: ECHEC | J15: =K15 -> 0 | K15: =+TONTMARS!F15+TONTMARS!G15 -> 0 | O15: =IF(P15=0,0,($C$36-P15)) -> 0
A16: AS201649 | B16: =VLOOKUP(A16,[1]LISTADHERENT!A$5:H$60,3,0) -> MBOGNING TUGMA GUY | C16: =IF(E16="ECHEC",0,IF(E16="",0,75000)) -> 0 | D16: =IF(E16="ESPECES",0,0) -> 0 | E16: ECHEC | J16: =K16 -> 0 | K16: =+TONTMARS!F16+TONTMARS!G16 -> 0 | O16: =IF(P16=0,0,($C$36-P16)) -> 0
A17: AS201626 | B17: =VLOOKUP(A17,[1]LISTADHERENT!A$5:H$60,3,0) -> NGUIEMEGNI MATHIEU BLAISE | C17: =IF(E17="ECHEC",0,IF(E17="",0,75000)) -> 0 | D17: =IF(E17="ESPECES",0,0) -> 0 | E17: ECHEC | J17: =K17 -> 0 | K17: =+TONTMARS!F17+TONTMARS!G17 -> 0 | O17: =IF(P17=0,0,($C$36-P17)) -> 0
... A24: AS201647 | B24: =VLOOKUP(A24,[1]LISTADHERENT!A$5:H$60,3,0) -> YOUMBI EMMANUEL | C24: =IF(E24="ECHEC",0,IF(E24="",0,75000)) -> 0 | D24: =IF(E24="ESPECES",0,0) -> 0 | E24: ECHEC | J24: =K24 -> 0 | K24: =+TONTMARS!F24+TONTMARS!G24 -> 0 | O24: =IF(P24=0,0,($C$36-P24)) -> 0
A26: TOTAL | C26: =SUM(C6:C24) -> 0 | D26: =SUM(D6:D24) -> 0 | F26: =SUM(F6:F24) -> 0 | G26: =SUM(G6:G24) -> 0 | I26: =SUM(I6:I24) -> 0 | J26: =SUM(J6:J24) -> 0 | K26: =SUM(K6:K24) -> 0 | M26: =SUM(M6:M24) -> 0 | N26: =SUM(N6:N24) -> 0 | O26: =SUM(O6:O24) -> 0 | P26: =SUM(P6:P24) -> 0
C28: TONTINE | D28: REMBOURSEMENT PETIT LOT | E28: VENTE PETIT LOT | F28: VENTE LOT PRINCIPAL | G28: SOLDE EN CAISSE | I28: TONTINE + REMB + INTERET VENTE | J28: =(C33+D33+P26) -> 0
I29: VENTE LOT | J29: =IF(J28>=2000000,1200000*2,1200000) -> 1200000
B30: ESPECES | C30: =SUMIFS(C6:C24,E6:E24,"ESPECES") -> 0 | D30: =SUMIFS(J6:J24,L6:L24,"ESPECES") -> 0 | E30: =SUMIFS(F6:F24,H6:H24,"ESPECES") -> 0 | F30: =SUMIFS(M6:M24,L6:L24,"ESPECES") -> 0 | G30: =C30+D30-E30-F30 -> 0
B31: BANQUE | C31: =SUMIFS(C6:C24,E6:E24,"BANQUE") -> 0 | D31: =SUMIFS(J6:J24,L6:L24,"BANQUE") -> 0 | E31: =SUMIFS(F6:F24,H6:H24,"BANQUE") -> 0 | F31: =SUMIFS(M6:M24,L6:L24,"BANQUE") -> 0 | G31: =C31+D31-E31-F31 -> 0 | I31: PETIT LOT | J31: =IF(J28>0,J28-J29,0) -> 0
B33: TOTAL | C33: =C30+C31 -> 0 | D33: =D30+D31 -> 0 | E33: =E30+E31 -> 0 | F33: =F30+F31 -> 0 | G33: =G30+G31 -> 0 | I33: RESTE | J33: =J31-F26+TONTMARS!J33 -> -91500
B36: MONTANT TONTINE | C36: 1200000

Sheet TONTMAI
A1: ASSOCIATION | B1: ASELBY
A2: ANNEE | B2: 2019/2020
A3: TONTINE | B3: 75000
C4: 44332
A5: MATRICULE | B5: NOM ET PRENOM | C5: MONTANT TONTINE | D5: PENALITE | E5: MODE VERSEMENT TONTINE | F5: VENTE PETIT LOT | G5: INTERET PETIT LOT | H5: MODE VERSEMENT VENTE PETIT LOT | I5: NUMERO CHEQUE | J5: MONTANT REMBOURSE | K5: MONTANT A REMBOURSER | L5: MODE VERSEMENT REMBOURSEMENT | M5: MODE VERSEMENT TONTINE PRINCIPAL | N5: NUMERO CHEQUE | O5: MONTANT TONTINE LOT PRINCIPAL | P5: INTERET LOT PRINCIPAL
A6: AS201602 | B6: =VLOOKUP(A6,[1]LISTADHERENT!A$5:H$60,3,0) -> BOUTCHOUANG WILLIAM | C6: =IF(E6="ECHEC",0,IF(E6="",0,75000)) -> 0 | D6: =IF(E6="ESPECES",0,0) -> 0 | E6: ECHEC | J6: =K6 -> 0 | K6: =+TONTAVRIL!F6+TONTAVRIL!G6 -> 0 | O6: =IF(P6=0,0,($C$36-P6)) -> 0
A7: AS201603 | B7: =VLOOKUP(A7,[1]LISTADHERENT!A$5:H$60,3,0) -> CHINGUE FABRICE | C7: =IF(E7="ECHEC",0,IF(E7="",0,75000)) -> 0 | D7: =IF(E7="ESPECES",0,0) -> 0 | E7: ECHEC | J7: =K7 -> 0 | K7: =+TONTAVRIL!F7+TONTAVRIL!G7 -> 0 | O7: =IF(P7=0,0,($C$36-P7)) -> 0
A8: AS201604 | B8: =VLOOKUP(A8,[1]LISTADHERENT!A$5:H$60,3,0) -> DJOMO JEAN PAUL | C8: =IF(E8="ECHEC",0,IF(E8="",0,75000)) -> 0 | D8: =IF(E8="ESPECES",0,0) -> 0 | E8: ECHEC | J8: =K8 -> 0 | K8: =+TONTAVRIL!F8+TONTAVRIL!G8 -> 0 | O8: =IF(P8=0,0,($C$36-P8)) -> 0
A9: AS201605 | B9: =VLOOKUP(A9,[1]LISTADHERENT!A$5:H$60,3,0) -> DJOUKWE NANGUEN GUY BLAISE | C9: =IF(E9="ECHEC",0,IF(E9="",0,75000)) -> 0 | D9: =IF(E9="ESPECES",0,0) -> 0 | E9: ECHEC | J9: =K9 -> 0 | K9: =+TONTAVRIL!F9+TONTAVRIL!G9 -> 0 | O9: =IF(P9=0,0,($C$36-P9)) -> 0
A10: AS201613 | B10: =VLOOKUP(A10,[1]LISTADHERENT!A$5:H$60,3,0) -> HOTCHO BENJAMIN | C10: =IF(E10="ECHEC",0,IF(E10="",0,75000)) -> 0 | D10: =IF(E10="ESPECES",0,0) -> 0 | E10: ECHEC | J10: =K10 -> 0 | K10: =+TONTAVRIL!F10+TONTAVRIL!G10 -> 0 | O10: =IF(P10=0,0,($C$36-P10)) -> 0
A11: AS201611 | B11: =VLOOKUP(A11,[1]LISTADHERENT!A$5:H$60,3,0) -> HENGUE PAUL OMER | C11: =IF(E11="ECHEC",0,IF(E11="",0,75000)) -> 0 | D11: =IF(E11="ESPECES",0,0) -> 0 | E11: ECHEC | J11: =K11 -> 0 | K11: =+TONTAVRIL!F11+TONTAVRIL!G11 -> 0 | O11: =IF(P11=0,0,($C$36-P11)) -> 0
A12: AS201619 | B12: =VLOOKUP(A12,[1]LISTADHERENT!A$5:H$60,3,0) -> KOUATCHO MESSACK | C12: =IF(E12="ECHEC",0,IF(E12="",0,75000)) -> 0 | D12: =IF(E12="ESPECES",0,0) -> 0 | E12: ECHEC | J12: =K12 -> 0 | K12: =+TONTAVRIL!F12+TONTAVRIL!G12 -> 0 | O12: =IF(P12=0,0,($C$36-P12)) -> 0
A13: AS201621 | B13: =VLOOKUP(A13,[1]LISTADHERENT!A$5:H$60,3,0) -> NANKAM APPOLINAIRE | C13: =IF(E13="ECHEC",0,IF(E13="",0,75000)) -> 0 | D13: =IF(E13="ESPECES",0,0) -> 0 | E13: ECHEC | J13: =K13 -> 0 | K13: =+TONTAVRIL!F13+TONTAVRIL!G13 -> 0 | O13: =IF(P13=0,0,($C$36-P13)) -> 0
A14: AS201649 | B14: =VLOOKUP(A14,[1]LISTADHERENT!A$5:H$60,3,0) -> MBOGNING TUGMA GUY | C14: =IF(E14="ECHEC",0,IF(E14="",0,75000)) -> 0 | D14: =IF(E14="ESPECES",0,0) -> 0 | E14: ECHEC | J14: =K14 -> 0 | K14: =+TONTAVRIL!F14+TONTAVRIL!G14 -> 0 | O14: =IF(P14=0,0,($C$36-P14)) -> 0
A15: AS201649 | B15: =VLOOKUP(A15,[1]LISTADHERENT!A$5:H$60,3,0) -> MBOGNING TUGMA GUY | C15: =IF(E15="ECHEC",0,IF(E15="",0,75000)) -> 0 | D15: =IF(E15="ESPECES",0,0) -> 0 | E15: ECHEC | J15: =K15 -> 0 | K15: =+TONTAVRIL!F15+TONTAVRIL!G15 -> 0 | O15: =IF(P15=0,0,($C$36-P15)) -> 0
A16: AS201649 | B16: =VLOOKUP(A16,[1]LISTADHERENT!A$5:H$60,3,0) -> MBOGNING TUGMA GUY | C16: =IF(E16="ECHEC",0,IF(E16="",0,75000)) -> 0 | D16: =IF(E16="ESPECES",0,0) -> 0 | E16: ECHEC | J16: =K16 -> 0 | K16: =+TONTAVRIL!F16+TONTAVRIL!G16 -> 0 | O16: =IF(P16=0,0,($C$36-P16)) -> 0
A17: AS201626 | B17: =VLOOKUP(A17,[1]LISTADHERENT!A$5:H$60,3,0) -> NGUIEMEGNI MATHIEU BLAISE | C17: =IF(E17="ECHEC",0,IF(E17="",0,75000)) -> 0 | D17: =IF(E17="ESPECES",0,0) -> 0 | E17: ECHEC | J17: =K17 -> 0 | K17: =+TONTAVRIL!F17+TONTAVRIL!G17 -> 0 | O17: =IF(P17=0,0,($C$36-P17)) -> 0
... A24: AS201647 | B24: =VLOOKUP(A24,[1]LISTADHERENT!A$5:H$60,3,0) -> YOUMBI EMMANUEL | C24: =IF(E24="ECHEC",0,IF(E24="",0,75000)) -> 0 | D24: =IF(E24="ESPECES",0,0) -> 0 | E24: ECHEC | J24: =K24 -> 0 | K24: =+TONTAVRIL!F24+TONTAVRIL!G24 -> 0 | O24: =IF(P24=0,0,($C$36-P24)) -> 0
A26: TOTAL | C26: =SUM(C6:C24) -> 0 | D26: =SUM(D6:D24) -> 0 | F26: =SUM(F6:F24) -> 0 | G26: =SUM(G6:G24) -> 0 | I26: =SUM(I6:I24) -> 0 | J26: =SUM(J6:J24) -> 0 | K26: =SUM(K6:K24) -> 0 | M26: =SUM(M6:M24) -> 0 | N26: =SUM(N6:N24) -> 0 | O26: =SUM(O6:O24) -> 0 | P26: =SUM(P6:P24) -> 0
C28: TONTINE | D28: REMBOURSEMENT PETIT LOT | E28: VENTE PETIT LOT | F28: VENTE LOT PRINCIPAL | G28: SOLDE EN CAISSE | I28: TONTINE + REMB + INTERET VENTE | J28: =(C33+D33+P26) -> 0
I29: VENTE LOT | J29: =IF(J28>=2000000,1200000*2,1200000) -> 1200000
B30: ESPECES | C30: =SUMIFS(C6:C24,E6:E24,"ESPECES") -> 0 | D30: =SUMIFS(J6:J24,L6:L24,"ESPECES") -> 0 | E30: =SUMIFS(F6:F24,H6:H24,"ESPECES") -> 0 | F30: =SUMIFS(M6:M24,L6:L24,"ESPECES") -> 0 | G30: =C30+D30-E30-F30 -> 0
B31: BANQUE | C31: =SUMIFS(C6:C24,E6:E24,"BANQUE") -> 0 | D31: =SUMIFS(J6:J24,L6:L24,"BANQUE") -> 0 | E31: =SUMIFS(F6:F24,H6:H24,"BANQUE") -> 0 | F31: =SUMIFS(M6:M24,L6:L24,"BANQUE") -> 0 | G31: =C31+D31-E31-F31 -> 0 | I31: PETIT LOT | J31: =IF(J28>0,J28-J29,0) -> 0
B33: TOTAL | C33: =C30+C31 -> 0 | D33: =D30+D31 -> 0 | E33: =E30+E31 -> 0 | F33: =F30+F31 -> 0 | G33: =G30+G31 -> 0 | I33: RESTE | J33: =J31-F26+TONTAVRIL!J33 -> -91500
B36: MONTANT TONTINE | C36: 1200000

Sheet TONTJUIN
A1: ASSOCIATION | B1: ASELBY
A2: ANNEE | B2: 2019/2020
A3: TONTINE | B3: 75000
C4: 44367
A5: MATRICULE | B5: NOM ET PRENOM | C5: MONTANT TONTINE | D5: PENALITE | E5: MODE VERSEMENT TONTINE | F5: VENTE PETIT LOT | G5: INTERET PETIT LOT | H5: MODE VERSEMENT VENTE PETIT LOT | I5: NUMERO CHEQUE | J5: MONTANT REMBOURSE | K5: MONTANT A REMBOURSER | L5: MODE VERSEMENT REMBOURSEMENT | M5: MODE VERSEMENT TONTINE PRINCIPAL | N5: NUMERO CHEQUE | O5: MONTANT TONTINE LOT PRINCIPAL | P5: INTERET LOT PRINCIPAL
A6: AS201602 | B6: =VLOOKUP(A6,[1]LISTADHERENT!A$5:H$60,3,0) -> BOUTCHOUANG WILLIAM | C6: =IF(E6="ECHEC",0,IF(E6="",0,75000)) -> 0 | D6: =IF(E6="ESPECES",0,0) -> 0 | E6: ECHEC | J6: =K6 -> 0 | K6: =+TONTMAI!F6+TONTMAI!G6 -> 0 | O6: =IF(P6=0,0,($C$36-P6)) -> 0
A7: AS201603 | B7: =VLOOKUP(A7,[1]LISTADHERENT!A$5:H$60,3,0) -> CHINGUE FABRICE | C7: =IF(E7="ECHEC",0,IF(E7="",0,75000)) -> 0 | D7: =IF(E7="ESPECES",0,0) -> 0 | E7: ECHEC | J7: =K7 -> 0 | K7: =+TONTMAI!F7+TONTMAI!G7 -> 0 | O7: =IF(P7=0,0,($C$36-P7)) -> 0
A8: AS201604 | B8: =VLOOKUP(A8,[1]LISTADHERENT!A$5:H$60,3,0) -> DJOMO JEAN PAUL | C8: =IF(E8="ECHEC",0,IF(E8="",0,75000)) -> 0 | D8: =IF(E8="ESPECES",0,0) -> 0 | E8: ECHEC | J8: =K8 -> 0 | K8: =+TONTMAI!F8+TONTMAI!G8 -> 0 | O8: =IF(P8=0,0,($C$36-P8)) -> 0
A9: AS201605 | B9: =VLOOKUP(A9,[1]LISTADHERENT!A$5:H$60,3,0) -> DJOUKWE NANGUEN GUY BLAISE | C9: =IF(E9="ECHEC",0,IF(E9="",0,75000)) -> 0 | D9: =IF(E9="ESPECES",0,0) -> 0 | E9: ECHEC | J9: =K9 -> 0 | K9: =+TONTMAI!F9+TONTMAI!G9 -> 0 | O9: =IF(P9=0,0,($C$36-P9)) -> 0
A10: AS201613 | B10: =VLOOKUP(A10,[1]LISTADHERENT!A$5:H$60,3,0) -> HOTCHO BENJAMIN | C10: =IF(E10="ECHEC",0,IF(E10="",0,75000)) -> 0 | D10: =IF(E10="ESPECES",0,0) -> 0 | E10: ECHEC | J10: =K10 -> 0 | K10: =+TONTMAI!F10+TONTMAI!G10 -> 0 | O10: =IF(P10=0,0,($C$36-P10)) -> 0
A11: AS201611 | B11: =VLOOKUP(A11,[1]LISTADHERENT!A$5:H$60,3,0) -> HENGUE PAUL OMER | C11: =IF(E11="ECHEC",0,IF(E11="",0,75000)) -> 0 | D11: =IF(E11="ESPECES",0,0) -> 0 | E11: ECHEC | J11: =K11 -> 0 | K11: =+TONTMAI!F11+TONTMAI!G11 -> 0 | O11: =IF(P11=0,0,($C$36-P11)) -> 0
A12: AS201619 | B12: =VLOOKUP(A12,[1]LISTADHERENT!A$5:H$60,3,0) -> KOUATCHO MESSACK | C12: =IF(E12="ECHEC",0,IF(E12="",0,75000)) -> 0 | D12: =IF(E12="ESPECES",0,0) -> 0 | E12: ECHEC | J12: =K12 -> 0 | K12: =+TONTMAI!F12+TONTMAI!G12 -> 0 | O12: =IF(P12=0,0,($C$36-P12)) -> 0
A13: AS201621 | B13: =VLOOKUP(A13,[1]LISTADHERENT!A$5:H$60,3,0) -> NANKAM APPOLINAIRE | C13: =IF(E13="ECHEC",0,IF(E13="",0,75000)) -> 0 | D13: =IF(E13="ESPECES",0,0) -> 0 | E13: ECHEC | J13: =K13 -> 0 | K13: =+TONTMAI!F13+TONTMAI!G13 -> 0 | O13: =IF(P13=0,0,($C$36-P13)) -> 0
A14: AS201649 | B14: =VLOOKUP(A14,[1]LISTADHERENT!A$5:H$60,3,0) -> MBOGNING TUGMA GUY | C14: =IF(E14="ECHEC",0,IF(E14="",0,75000)) -> 0 | D14: =IF(E14="ESPECES",0,0) -> 0 | E14: ECHEC | J14: =K14 -> 0 | K14: =+TONTMAI!F14+TONTMAI!G14 -> 0 | O14: =IF(P14=0,0,($C$36-P14)) -> 0
A15: AS201649 | B15: =VLOOKUP(A15,[1]LISTADHERENT!A$5:H$60,3,0) -> MBOGNING TUGMA GUY | C15: =IF(E15="ECHEC",0,IF(E15="",0,75000)) -> 0 | D15: =IF(E15="ESPECES",0,0) -> 0 | E15: ECHEC | J15: =K15 -> 0 | K15: =+TONTMAI!F15+TONTMAI!G15 -> 0 | O15: =IF(P15=0,0,($C$36-P15)) -> 0
A16: AS201649 | B16: =VLOOKUP(A16,[1]LISTADHERENT!A$5:H$60,3,0) -> MBOGNING TUGMA GUY | C16: =IF(E16="ECHEC",0,IF(E16="",0,75000)) -> 0 | D16: =IF(E16="ESPECES",0,0) -> 0 | E16: ECHEC | J16: =K16 -> 0 | K16: =+TONTMAI!F16+TONTMAI!G16 -> 0 | O16: =IF(P16=0,0,($C$36-P16)) -> 0
A17: AS201626 | B17: =VLOOKUP(A17,[1]LISTADHERENT!A$5:H$60,3,0) -> NGUIEMEGNI MATHIEU BLAISE | C17: =IF(E17="ECHEC",0,IF(E17="",0,75000)) -> 0 | D17: =IF(E17="ESPECES",0,0) -> 0 | E17: ECHEC | J17: =K17 -> 0 | K17: =+TONTMAI!F17+TONTMAI!G17 -> 0 | O17: =IF(P17=0,0,($C$36-P17)) -> 0
... A24: AS201647 | B24: =VLOOKUP(A24,[1]LISTADHERENT!A$5:H$60,3,0) -> YOUMBI EMMANUEL | C24: =IF(E24="ECHEC",0,IF(E24="",0,75000)) -> 0 | D24: =IF(E24="ESPECES",0,0) -> 0 | E24: ECHEC | J24: =K24 -> 0 | K24: =+TONTMAI!F24+TONTMAI!G24 -> 0 | O24: =IF(P24=0,0,($C$36-P24)) -> 0
A26: TOTAL | C26: =SUM(C6:C24) -> 0 | D26: =SUM(D6:D24) -> 0 | F26: =SUM(F6:F24) -> 0 | G26: =SUM(G6:G24) -> 0 | I26: =SUM(I6:I24) -> 0 | J26: =SUM(J6:J24) -> 0 | K26: =SUM(K6:K24) -> 0 | M26: =SUM(M6:M24) -> 0 | N26: =SUM(N6:N24) -> 0 | O26: =SUM(O6:O24) -> 0 | P26: =SUM(P6:P24) -> 0
C28: TONTINE | D28: REMBOURSEMENT PETIT LOT | E28: VENTE PETIT LOT | F28: VENTE LOT PRINCIPAL | G28: SOLDE EN CAISSE | I28: TONTINE + REMB + INTERET VENTE | J28: =(C33+D33+P26) -> 0
I29: VENTE LOT | J29: =IF(J28>=2000000,1200000*2,1200000) -> 1200000
B30: ESPECES | C30: =SUMIFS(C6:C24,E6:E24,"ESPECES") -> 0 | D30: =SUMIFS(J6:J24,L6:L24,"ESPECES") -> 0 | E30: =SUMIFS(F6:F24,H6:H24,"ESPECES") -> 0 | F30: =SUMIFS(M6:M24,L6:L24,"ESPECES") -> 0 | G30: =C30+D30-E30-F30 -> 0
B31: BANQUE | C31: =SUMIFS(C6:C24,E6:E24,"BANQUE") -> 0 | D31: =SUMIFS(J6:J24,L6:L24,"BANQUE") -> 0 | E31: =SUMIFS(F6:F24,H6:H24,"BANQUE") -> 0 | F31: =SUMIFS(M6:M24,L6:L24,"BANQUE") -> 0 | G31: =C31+D31-E31-F31 -> 0 | I31: PETIT LOT | J31: =IF(J28>0,J28-J29,0) -> 0
B33: TOTAL | C33: =C30+C31 -> 0 | D33: =D30+D31 -> 0 | E33: =E30+E31 -> 0 | F33: =F30+F31 -> 0 | G33: =G30+G31 -> 0 | I33: RESTE | J33: =J31-F26+TONTMAI!J33 -> -91500
B36: MONTANT TONTINE | C36: 1200000

Sheet TONTJUIL2021
A1: ASSOCIATION | B1: ASELBY
A2: ANNEE | B2: 2019/2020
A3: TONTINE | B3: 75000
C4: 44395
A5: MATRICULE | B5: NOM ET PRENOM | C5: MONTANT TONTINE | D5: PENALITE | E5: MODE VERSEMENT TONTINE | F5: VENTE PETIT LOT | G5: INTERET PETIT LOT | H5: MODE VERSEMENT VENTE PETIT LOT | I5: NUMERO CHEQUE | J5: MONTANT REMBOURSE | K5: MONTANT A REMBOURSER | L5: MODE VERSEMENT REMBOURSEMENT | M5: MODE VERSEMENT TONTINE PRINCIPAL | N5: NUMERO CHEQUE | O5: MONTANT TONTINE LOT PRINCIPAL | P5: INTERET LOT PRINCIPAL
A6: AS201602 | B6: =VLOOKUP(A6,[1]LISTADHERENT!A$5:H$60,3,0) -> BOUTCHOUANG WILLIAM | C6: =IF(E6="ECHEC",0,IF(E6="",0,75000)) -> 0 | D6: =IF(E6="ESPECES",0,0) -> 0 | E6: ECHEC | J6: =K6 -> 0 | K6: =+TONTJUIN!F6+TONTJUIN!G6 -> 0 | O6: =IF(P6=0,0,($C$36-P6)) -> 0
A7: AS201603 | B7: =VLOOKUP(A7,[1]LISTADHERENT!A$5:H$60,3,0) -> CHINGUE FABRICE | C7: =IF(E7="ECHEC",0,IF(E7="",0,75000)) -> 0 | D7: =IF(E7="ESPECES",0,0) -> 0 | E7: ECHEC | J7: =K7 -> 0 | K7: =+TONTJUIN!F7+TONTJUIN!G7 -> 0 | O7: =IF(P7=0,0,($C$36-P7)) -> 0
A8: AS201604 | B8: =VLOOKUP(A8,[1]LISTADHERENT!A$5:H$60,3,0) -> DJOMO JEAN PAUL | C8: =IF(E8="ECHEC",0,IF(E8="",0,75000)) -> 0 | D8: =IF(E8="ESPECES",0,0) -> 0 | E8: ECHEC | J8: =K8 -> 0 | K8: =+TONTJUIN!F8+TONTJUIN!G8 -> 0 | O8: =IF(P8=0,0,($C$36-P8)) -> 0
A9: AS201605 | B9: =VLOOKUP(A9,[1]LISTADHERENT!A$5:H$60,3,0) -> DJOUKWE NANGUEN GUY BLAISE | C9: =IF(E9="ECHEC",0,IF(E9="",0,75000)) -> 0 | D9: =IF(E9="ESPECES",0,0) -> 0 | E9: ECHEC | J9: =K9 -> 0 | K9: =+TONTJUIN!F9+TONTJUIN!G9 -> 0 | O9: =IF(P9=0,0,($C$36-P9)) -> 0
A10: AS201613 | B10: =VLOOKUP(A10,[1]LISTADHERENT!A$5:H$60,3,0) -> HOTCHO BENJAMIN | C10: =IF(E10="ECHEC",0,IF(E10="",0,75000)) -> 0 | D10: =IF(E10="ESPECES",0,0) -> 0 | E10: ECHEC | J10: =K10 -> 0 | K10: =+TONTJUIN!F10+TONTJUIN!G10 -> 0 | O10: =IF(P10=0,0,($C$36-P10)) -> 0
A11: AS201611 | B11: =VLOOKUP(A11,[1]LISTADHERENT!A$5:H$60,3,0) -> HENGUE PAUL OMER | C11: =IF(E11="ECHEC",0,IF(E11="",0,75000)) -> 0 | D11: =IF(E11="ESPECES",0,0) -> 0 | E11: ECHEC | J11: =K11 -> 0 | K11: =+TONTJUIN!F11+TONTJUIN!G11 -> 0 | O11: =IF(P11=0,0,($C$36-P11)) -> 0
A12: AS201619 | B12: =VLOOKUP(A12,[1]LISTADHERENT!A$5:H$60,3,0) -> KOUATCHO MESSACK | C12: =IF(E12="ECHEC",0,IF(E12="",0,75000)) -> 0 | D12: =IF(E12="ESPECES",0,0) -> 0 | E12: ECHEC | J12: =K12 -> 0 | K12: =+TONTJUIN!F12+TONTJUIN!G12 -> 0 | O12: =IF(P12=0,0,($C$36-P12)) -> 0
A13: AS201621 | B13: =VLOOKUP(A13,[1]LISTADHERENT!A$5:H$60,3,0) -> NANKAM APPOLINAIRE | C13: =IF(E13="ECHEC",0,IF(E13="",0,75000)) -> 0 | D13: =IF(E13="ESPECES",0,0) -> 0 | E13: ECHEC | J13: =K13 -> 0 | K13: =+TONTJUIN!F13+TONTJUIN!G13 -> 0 | O13: =IF(P13=0,0,($C$36-P13)) -> 0
A14: AS201649 | B14: =VLOOKUP(A14,[1]LISTADHERENT!A$5:H$60,3,0) -> MBOGNING TUGMA GUY | C14: =IF(E14="ECHEC",0,IF(E14="",0,75000)) -> 0 | D14: =IF(E14="ESPECES",0,0) -> 0 | E14: ECHEC | J14: =K14 -> 0 | K14: =+TONTJUIN!F14+TONTJUIN!G14 -> 0 | O14: =IF(P14=0,0,($C$36-P14)) -> 0
A15: AS201649 | B15: =VLOOKUP(A15,[1]LISTADHERENT!A$5:H$60,3,0) -> MBOGNING TUGMA GUY | C15: =IF(E15="ECHEC",0,IF(E15="",0,75000)) -> 0 | D15: =IF(E15="ESPECES",0,0) -> 0 | E15: ECHEC | J15: =K15 -> 0 | K15: =+TONTJUIN!F15+TONTJUIN!G15 -> 0 | O15: =IF(P15=0,0,($C$36-P15)) -> 0
A16: AS201649 | B16: =VLOOKUP(A16,[1]LISTADHERENT!A$5:H$60,3,0) -> MBOGNING TUGMA GUY | C16: =IF(E16="ECHEC",0,IF(E16="",0,75000)) -> 0 | D16: =IF(E16="ESPECES",0,0) -> 0 | E16: ECHEC | J16: =K16 -> 0 | K16: =+TONTJUIN!F16+TONTJUIN!G16 -> 0 | O16: =IF(P16=0,0,($C$36-P16)) -> 0
A17: AS201626 | B17: =VLOOKUP(A17,[1]LISTADHERENT!A$5:H$60,3,0) -> NGUIEMEGNI MATHIEU BLAISE | C17: =IF(E17="ECHEC",0,IF(E17="",0,75000)) -> 0 | D17: =IF(E17="ESPECES",0,0) -> 0 | E17: ECHEC | J17: =K17 -> 0 | K17: =+TONTJUIN!F17+TONTJUIN!G17 -> 0 | O17: =IF(P17=0,0,($C$36-P17)) -> 0
... A24: AS201647 | B24: =VLOOKUP(A24,[1]LISTADHERENT!A$5:H$60,3,0) -> YOUMBI EMMANUEL | C24: =IF(E24="ECHEC",0,IF(E24="",0,75000)) -> 0 | D24: =IF(E24="ESPECES",0,0) -> 0 | E24: ECHEC | J24: =K24 -> 0 | K24: =+TONTJUIN!F24+TONTJUIN!G24 -> 0 | O24: =IF(P24=0,0,($C$36-P24)) -> 0
A26: TOTAL | C26: =SUM(C6:C24) -> 0 | D26: =SUM(D6:D24) -> 0 | F26: =SUM(F6:F24) -> 0 | G26: =SUM(G6:G24) -> 0 | I26: =SUM(I6:I24) -> 0 | J26: =SUM(J6:J24) -> 0 | K26: =SUM(K6:K24) -> 0 | M26: =SUM(M6:M24) -> 0 | N26: =SUM(N6:N24) -> 0 | O26: =SUM(O6:O24) -> 0 | P26: =SUM(P6:P24) -> 0
C28: TONTINE | D28: REMBOURSEMENT PETIT LOT | E28: VENTE PETIT LOT | F28: VENTE LOT PRINCIPAL | G28: SOLDE EN CAISSE | I28: TONTINE + REMB + INTERET VENTE | J28: =(C33+D33+P26) -> 0
I29: VENTE LOT | J29: =IF(J28>=2000000,1200000*2,1200000) -> 1200000
B30: ESPECES | C30: =SUMIFS(C6:C24,E6:E24,"ESPECES") -> 0 | D30: =SUMIFS(J6:J24,L6:L24,"ESPECES") -> 0 | E30: =SUMIFS(F6:F24,H6:H24,"ESPECES") -> 0 | F30: =SUMIFS(M6:M24,L6:L24,"ESPECES") -> 0 | G30: =C30+D30-E30-F30 -> 0
B31: BANQUE | C31: =SUMIFS(C6:C24,E6:E24,"BANQUE") -> 0 | D31: =SUMIFS(J6:J24,L6:L24,"BANQUE") -> 0 | E31: =SUMIFS(F6:F24,H6:H24,"BANQUE") -> 0 | F31: =SUMIFS(M6:M24,L6:L24,"BANQUE") -> 0 | G31: =C31+D31-E31-F31 -> 0 | I31: PETIT LOT | J31: =IF(J28>0,J28-J29,0) -> 0
B33: TOTAL | C33: =C30+C31 -> 0 | D33: =D30+D31 -> 0 | E33: =E30+E31 -> 0 | F33: =F30+F31 -> 0 | G33: =G30+G31 -> 0 | I33: RESTE | J33: =J31-F26+TONTJUIN!J33 -> -91500
B36: MONTANT TONTINE | C36: 1200000

Sheet TONTAOUT2021
A1: ASSOCIATION | B1: ASELBY
A2: ANNEE | B2: 2019/2020
A3: TONTINE | B3: 75000
C4: 44430
A5: MATRICULE | B5: NOM ET PRENOM | C5: MONTANT TONTINE | D5: PENALITE | E5: MODE VERSEMENT TONTINE | F5: VENTE PETIT LOT | G5: INTERET PETIT LOT | H5: MODE VERSEMENT VENTE PETIT LOT | I5: NUMERO CHEQUE | J5: MONTANT REMBOURSE | K5: MONTANT A REMBOURSER | L5: MODE VERSEMENT REMBOURSEMENT | M5: MODE VERSEMENT TONTINE PRINCIPAL | N5: NUMERO CHEQUE | O5: MONTANT TONTINE LOT PRINCIPAL | P5: INTERET LOT PRINCIPAL
A6: AS201602 | B6: =VLOOKUP(A6,[1]LISTADHERENT!A$5:H$60,3,0) -> BOUTCHOUANG WILLIAM | C6: =IF(E6="ECHEC",0,IF(E6="",0,75000)) -> 0 | D6: =IF(E6="ESPECES",0,0) -> 0 | E6: ECHEC | J6: =K6 -> 0 | K6: =+TONTJUIL2021!F6+TONTJUIL2021!G6 -> 0 | O6: =IF(P6=0,0,($C$36-P6)) -> 0
A7: AS201603 | B7: =VLOOKUP(A7,[1]LISTADHERENT!A$5:H$60,3,0) -> CHINGUE FABRICE | C7: =IF(E7="ECHEC",0,IF(E7="",0,75000)) -> 0 | D7: =IF(E7="ESPECES",0,0) -> 0 | E7: ECHEC | J7: =K7 -> 0 | K7: =+TONTJUIL2021!F7+TONTJUIL2021!G7 -> 0 | O7: =IF(P7=0,0,($C$36-P7)) -> 0
A8: AS201604 | B8: =VLOOKUP(A8,[1]LISTADHERENT!A$5:H$60,3,0) -> DJOMO JEAN PAUL | C8: =IF(E8="ECHEC",0,IF(E8="",0,75000)) -> 0 | D8: =IF(E8="ESPECES",0,0) -> 0 | E8: ECHEC | J8: =K8 -> 0 | K8: =+TONTJUIL2021!F8+TONTJUIL2021!G8 -> 0 | O8: =IF(P8=0,0,($C$36-P8)) -> 0
A9: AS201605 | B9: =VLOOKUP(A9,[1]LISTADHERENT!A$5:H$60,3,0) -> DJOUKWE NANGUEN GUY BLAISE | C9: =IF(E9="ECHEC",0,IF(E9="",0,75000)) -> 0 | D9: =IF(E9="ESPECES",0,0) -> 0 | E9: ECHEC | J9: =K9 -> 0 | K9: =+TONTJUIL2021!F9+TONTJUIL2021!G9 -> 0 | O9: =IF(P9=0,0,($C$36-P9)) -> 0
A10: AS201613 | B10: =VLOOKUP(A10,[1]LISTADHERENT!A$5:H$60,3,0) -> HOTCHO BENJAMIN | C10: =IF(E10="ECHEC",0,IF(E10="",0,75000)) -> 0 | D10: =IF(E10="ESPECES",0,0) -> 0 | E10: ECHEC | J10: =K10 -> 0 | K10: =+TONTJUIL2021!F10+TONTJUIL2021!G10 -> 0 | O10: =IF(P10=0,0,($C$36-P10)) -> 0
A11: AS201611 | B11: =VLOOKUP(A11,[1]LISTADHERENT!A$5:H$60,3,0) -> HENGUE PAUL OMER | C11: =IF(E11="ECHEC",0,IF(E11="",0,75000)) -> 0 | D11: =IF(E11="ESPECES",0,0) -> 0 | E11: ECHEC | J11: =K11 -> 0 | K11: =+TONTJUIL2021!F11+TONTJUIL2021!G11 -> 0 | O11: =IF(P11=0,0,($C$36-P11)) -> 0
A12: AS201619 | B12: =VLOOKUP(A12,[1]LISTADHERENT!A$5:H$60,3,0) -> KOUATCHO MESSACK | C12: =IF(E12="ECHEC",0,IF(E12="",0,75000)) -> 0 | D12: =IF(E12="ESPECES",0,0) -> 0 | E12: ECHEC | J12: =K12 -> 0 | K12: =+TONTJUIL2021!F12+TONTJUIL2021!G12 -> 0 | O12: =IF(P12=0,0,($C$36-P12)) -> 0
A13: AS201621 | B13: =VLOOKUP(A13,[1]LISTADHERENT!A$5:H$60,3,0) -> NANKAM APPOLINAIRE | C13: =IF(E13="ECHEC",0,IF(E13="",0,75000)) -> 0 | D13: =IF(E13="ESPECES",0,0) -> 0 | E13: ECHEC | J13: =K13 -> 0 | K13: =+TONTJUIL2021!F13+TONTJUIL2021!G13 -> 0 | O13: =IF(P13=0,0,($C$36-P13)) -> 0
A14: AS201649 | B14: =VLOOKUP(A14,[1]LISTADHERENT!A$5:H$60,3,0) -> MBOGNING TUGMA GUY | C14: =IF(E14="ECHEC",0,IF(E14="",0,75000)) -> 0 | D14: =IF(E14="ESPECES",0,0) -> 0 | E14: ECHEC | J14: =K14 -> 0 | K14: =+TONTJUIL2021!F14+TONTJUIL2021!G14 -> 0 | O14: =IF(P14=0,0,($C$36-P14)) -> 0
A15: AS201649 | B15: =VLOOKUP(A15,[1]LISTADHERENT!A$5:H$60,3,0) -> MBOGNING TUGMA GUY | C15: =IF(E15="ECHEC",0,IF(E15="",0,75000)) -> 0 | D15: =IF(E15="ESPECES",0,0) -> 0 | E15: ECHEC | J15: =K15 -> 0 | K15: =+TONTJUIL2021!F15+TONTJUIL2021!G15 -> 0 | O15: =IF(P15=0,0,($C$36-P15)) -> 0
A16: AS201649 | B16: =VLOOKUP(A16,[1]LISTADHERENT!A$5:H$60,3,0) -> MBOGNING TUGMA GUY | C16: =IF(E16="ECHEC",0,IF(E16="",0,75000)) -> 0 | D16: =IF(E16="ESPECES",0,0) -> 0 | E16: ECHEC | J16: =K16 -> 0 | K16: =+TONTJUIL2021!F16+TONTJUIL2021!G16 -> 0 | O16: =IF(P16=0,0,($C$36-P16)) -> 0
A17: AS201626 | B17: =VLOOKUP(A17,[1]LISTADHERENT!A$5:H$60,3,0) -> NGUIEMEGNI MATHIEU BLAISE | C17: =IF(E17="ECHEC",0,IF(E17="",0,75000)) -> 0 | D17: =IF(E17="ESPECES",0,0) -> 0 | E17: ECHEC | J17: =K17 -> 0 | K17: =+TONTJUIL2021!F17+TONTJUIL2021!G17 -> 0 | O17: =IF(P17=0,0,($C$36-P17)) -> 0
... A24: AS201647 | B24: =VLOOKUP(A24,[1]LISTADHERENT!A$5:H$60,3,0) -> YOUMBI EMMANUEL | C24: =IF(E24="ECHEC",0,IF(E24="",0,75000)) -> 0 | D24: =IF(E24="ESPECES",0,0) -> 0 | E24: ECHEC | J24: =K24 -> 0 | K24: =+TONTJUIL2021!F24+TONTJUIL2021!G24 -> 0 | O24: =IF(P24=0,0,($C$36-P24)) -> 0
A26: TOTAL | C26: =SUM(C6:C24) -> 0 | D26: =SUM(D6:D24) -> 0 | F26: =SUM(F6:F24) -> 0 | G26: =SUM(G6:G24) -> 0 | I26: =SUM(I6:I24) -> 0 | J26: =SUM(J6:J24) -> 0 | K26: =SUM(K6:K24) -> 0 | M26: =SUM(M6:M24) -> 0 | N26: =SUM(N6:N24) -> 0 | O26: =SUM(O6:O24) -> 0 | P26: =SUM(P6:P24) -> 0
C28: TONTINE | D28: REMBOURSEMENT PETIT LOT | E28: VENTE PETIT LOT | F28: VENTE LOT PRINCIPAL | G28: SOLDE EN CAISSE | I28: TONTINE + REMB + INTERET VENTE | J28: =(C33+D33+P26) -> 0
I29: VENTE LOT | J29: =IF(J28>=2000000,1200000*2,1200000) -> 1200000
B30: ESPECES | C30: =SUMIFS(C6:C24,E6:E24,"ESPECES") -> 0 | D30: =SUMIFS(J6:J24,L6:L24,"ESPECES") -> 0 | E30: =SUMIFS(F6:F24,H6:H24,"ESPECES") -> 0 | F30: =SUMIFS(M6:M24,L6:L24,"ESPECES") -> 0 | G30: =C30+D30-E30-F30 -> 0
B31: BANQUE | C31: =SUMIFS(C6:C24,E6:E24,"BANQUE") -> 0 | D31: =SUMIFS(J6:J24,L6:L24,"BANQUE") -> 0 | E31: =SUMIFS(F6:F24,H6:H24,"BANQUE") -> 0 | F31: =SUMIFS(M6:M24,L6:L24,"BANQUE") -> 0 | G31: =C31+D31-E31-F31 -> 0 | I31: PETIT LOT | J31: =IF(J28>0,J28-J29,0) -> 0
B33: TOTAL | C33: =C30+C31 -> 0 | D33: =D30+D31 -> 0 | E33: =E30+E31 -> 0 | F33: =F30+F31 -> 0 | G33: =G30+G31 -> 0 | I33: RESTE | J33: =J31-F26+TONTJUIL2021!J33 -> -91500
B36: MONTANT TONTINE | C36: 1200000

Sheet TONTSEPT2021
A1: ASSOCIATION | B1: ASELBY
A2: ANNEE | B2: 2019/2020 | G2: =1200000/75000 -> 16
A3: TONTINE | B3: 75000
C4: 44458
A5: MATRICULE | B5: NOM ET PRENOM | C5: MONTANT TONTINE | D5: PENALITE | E5: MODE VERSEMENT TONTINE | F5: VENTE PETIT LOT | G5: INTERET PETIT LOT | H5: MODE VERSEMENT VENTE PETIT LOT | I5: NUMERO CHEQUE | J5: MONTANT REMBOURSE | K5: MONTANT A REMBOURSER | L5: MODE VERSEMENT REMBOURSEMENT | M5: MODE VERSEMENT TONTINE PRINCIPAL | N5: NUMERO CHEQUE | O5: MONTANT TONTINE LOT PRINCIPAL | P5: INTERET LOT PRINCIPAL
A6: AS201602 | B6: =VLOOKUP(A6,[1]LISTADHERENT!A$5:H$60,3,0) -> BOUTCHOUANG WILLIAM | C6: =IF(E6="ECHEC",0,IF(E6="",0,75000)) -> 0 | D6: =IF(E6="ESPECES",0,0) -> 0 | E6: ECHEC | J6: =K6 -> 0 | K6: =+TONTAOUT2021!F6+TONTAOUT2021!G6 -> 0 | O6: =IF(P6=0,0,($C$36-P6)) -> 0
A7: AS201603 | B7: =VLOOKUP(A7,[1]LISTADHERENT!A$5:H$60,3,0) -> CHINGUE FABRICE | C7: =IF(E7="ECHEC",0,IF(E7="",0,75000)) -> 0 | D7: =IF(E7="ESPECES",0,0) -> 0 | E7: ECHEC | J7: =K7 -> 0 | K7: =+TONTAOUT2021!F7+TONTAOUT2021!G7 -> 0 | O7: =IF(P7=0,0,($C$36-P7)) -> 0
A8: AS201604 | B8: =VLOOKUP(A8,[1]LISTADHERENT!A$5:H$60,3,0) -> DJOMO JEAN PAUL | C8: =IF(E8="ECHEC",0,IF(E8="",0,75000)) -> 0 | D8: =IF(E8="ESPECES",0,0) -> 0 | E8: ECHEC | J8: =K8 -> 0 | K8: =+TONTAOUT2021!F8+TONTAOUT2021!G8 -> 0 | O8: =IF(P8=0,0,($C$36-P8)) -> 0
A9: AS201605 | B9: =VLOOKUP(A9,[1]LISTADHERENT!A$5:H$60,3,0) -> DJOUKWE NANGUEN GUY BLAISE | C9: =IF(E9="ECHEC",0,IF(E9="",0,75000)) -> 0 | D9: =IF(E9="ESPECES",0,0) -> 0 | E9: ECHEC | J9: =K9 -> 0 | K9: =+TONTAOUT2021!F9+TONTAOUT2021!G9 -> 0 | O9: =IF(P9=0,0,($C$36-P9)) -> 0
A10: AS201613 | B10: =VLOOKUP(A10,[1]LISTADHERENT!A$5:H$60,3,0) -> HOTCHO BENJAMIN | C10: =IF(E10="ECHEC",0,IF(E10="",0,75000)) -> 0 | D10: =IF(E10="ESPECES",0,0) -> 0 | E10: ECHEC | J10: =K10 -> 0 | K10: =+TONTAOUT2021!F10+TONTAOUT2021!G10 -> 0 | O10: =IF(P10=0,0,($C$36-P10)) -> 0
A11: AS201611 | B11: =VLOOKUP(A11,[1]LISTADHERENT!A$5:H$60,3,0) -> HENGUE PAUL OMER | C11: =IF(E11="ECHEC",0,IF(E11="",0,75000)) -> 0 | D11: =IF(E11="ESPECES",0,0) -> 0 | E11: ECHEC | J11: =K11 -> 0 | K11: =+TONTAOUT2021!F11+TONTAOUT2021!G11 -> 0 | O11: =IF(P11=0,0,($C$36-P11)) -> 0
A12: AS201619 | B12: =VLOOKUP(A12,[1]LISTADHERENT!A$5:H$60,3,0) -> KOUATCHO MESSACK | C12: =IF(E12="ECHEC",0,IF(E12="",0,75000)) -> 0 | D12: =IF(E12="ESPECES",0,0) -> 0 | E12: ECHEC | J12: =K12 -> 0 | K12: =+TONTAOUT2021!F12+TONTAOUT2021!G12 -> 0 | O12: =IF(P12=0,0,($C$36-P12)) -> 0
A13: AS201621 | B13: =VLOOKUP(A13,[1]LISTADHERENT!A$5:H$60,3,0) -> NANKAM APPOLINAIRE | C13: =IF(E13="ECHEC",0,IF(E13="",0,75000)) -> 0 | D13: =IF(E13="ESPECES",0,0) -> 0 | E13: ECHEC | J13: =K13 -> 0 | K13: =+TONTAOUT2021!F13+TONTAOUT2021!G13 -> 0 | O13: =IF(P13=0,0,($C$36-P13)) -> 0
A14: AS201649 | B14: =VLOOKUP(A14,[1]LISTADHERENT!A$5:H$60,3,0) -> MBOGNING TUGMA GUY | C14: =IF(E14="ECHEC",0,IF(E14="",0,75000)) -> 0 | D14: =IF(E14="ESPECES",0,0) -> 0 | E14: ECHEC | J14: =K14 -> 0 | K14: =+TONTAOUT2021!F14+TONTAOUT2021!G14 -> 0 | O14: =IF(P14=0,0,($C$36-P14)) -> 0
A15: AS201649 | B15: =VLOOKUP(A15,[1]LISTADHERENT!A$5:H$60,3,0) -> MBOGNING TUGMA GUY | C15: =IF(E15="ECHEC",0,IF(E15="",0,75000)) -> 0 | D15: =IF(E15="ESPECES",0,0) -> 0 | E15: ECHEC | J15: =K15 -> 0 | K15: =+TONTAOUT2021!F15+TONTAOUT2021!G15 -> 0 | O15: =IF(P15=0,0,($C$36-P15)) -> 0
A16: AS201649 | B16: =VLOOKUP(A16,[1]LISTADHERENT!A$5:H$60,3,0) -> MBOGNING TUGMA GUY | C16: =IF(E16="ECHEC",0,IF(E16="",0,75000)) -> 0 | D16: =IF(E16="ESPECES",0,0) -> 0 | E16: ECHEC | J16: =K16 -> 0 | K16: =+TONTAOUT2021!F16+TONTAOUT2021!G16 -> 0 | O16: =IF(P16=0,0,($C$36-P16)) -> 0
A17: AS201626 | B17: =VLOOKUP(A17,[1]LISTADHERENT!A$5:H$60,3,0) -> NGUIEMEGNI MATHIEU BLAISE | C17: =IF(E17="ECHEC",0,IF(E17="",0,75000)) -> 0 | D17: =IF(E17="ESPECES",0,0) -> 0 | E17: ECHEC | J17: =K17 -> 0 | K17: =+TONTAOUT2021!F17+TONTAOUT2021!G17 -> 0 | O17: =IF(P17=0,0,($C$36-P17)) -> 0
... A24: AS201647 | B24: =VLOOKUP(A24,[1]LISTADHERENT!A$5:H$60,3,0) -> YOUMBI EMMANUEL | C24: =IF(E24="ECHEC",0,IF(E24="",0,75000)) -> 0 | D24: =IF(E24="ESPECES",0,0) -> 0 | E24: ECHEC | J24: =K24 -> 0 | K24: =+TONTAOUT2021!F24+TONTAOUT2021!G24 -> 0 | O24: =IF(P24=0,0,($C$36-P24)) -> 0
A26: TOTAL | C26: =SUM(C6:C24) -> 0 | D26: =SUM(D6:D24) -> 0 | F26: =SUM(F6:F24) -> 0 | G26: =SUM(G6:G24) -> 0 | I26: =SUM(I6:I24) -> 0 | J26: =SUM(J6:J24) -> 0 | K26: =SUM(K6:K24) -> 0 | M26: =SUM(M6:M24) -> 0 | N26: =SUM(N6:N24) -> 0 | O26: =SUM(O6:O24) -> 0 | P26: =SUM(P6:P24) -> 0
C28: TONTINE | D28: REMBOURSEMENT PETIT LOT | E28: VENTE PETIT LOT | F28: VENTE LOT PRINCIPAL | G28: SOLDE EN CAISSE | I28: TONTINE + REMB + INTERET VENTE | J28: =(C33+D33+P26) -> 0
I29: VENTE LOT | J29: =IF(J28>=2000000,1200000*2,1200000) -> 1200000
B30: ESPECES | C30: =SUMIFS(C6:C24,E6:E24,"ESPECES") -> 0 | D30: =SUMIFS(J6:J24,L6:L24,"ESPECES") -> 0 | E30: =SUMIFS(F6:F24,H6:H24,"ESPECES") -> 0 | F30: =SUMIFS(M6:M24,L6:L24,"ESPECES") -> 0 | G30: =C30+D30-E30-F30 -> 0
B31: BANQUE | C31: =SUMIFS(C6:C24,E6:E24,"BANQUE") -> 0 | D31: =SUMIFS(J6:J24,L6:L24,"BANQUE") -> 0 | E31: =SUMIFS(F6:F24,H6:H24,"BANQUE") -> 0 | F31: =SUMIFS(M6:M24,L6:L24,"BANQUE") -> 0 | G31: =C31+D31-E31-F31 -> 0 | I31: PETIT LOT | J31: =IF(J28>0,J28-J29,0) -> 0
B33: TOTAL | C33: =C30+C31 -> 0 | D33: =D30+D31 -> 0 | E33: =E30+E31 -> 0 | F33: =F30+F31 -> 0 | G33: =G30+G31 -> 0 | I33: RESTE | J33: =J31-F26+TONTAOUT2021!J33 -> -91500
B36: MONTANT TONTINE | C36: 1200000

Sheet TONTRESUME
A1: ASSOCIATION | B1: ASELBY
A2: ANNEE | B2: 2019/2020
A3: TONTINE | B3: 75000
C4: 44460
A5: MATRICULE | B5: NOM ET PRENOM | C5: MONTANT TONTINE | D5: PENALITE | E5: VENTE PETIT LOT | F5: INTERET PETIT LOT | G5: MONTANT REMBOURSE | H5: MONTANT A REMBOURSER | I5: MONTANT TONTINE LOT PRINCIPAL | J5: INTERET LOT PRINCIPAL | K5: DATE ACHAT | L5: BONUS
A6: AS201602 | B6: =VLOOKUP(A6,[1]LISTADHERENT!A$5:H$60,3,0) -> BOUTCHOUANG WILLIAM | C6: =TONTJUIL!C6+TONTAOUT!C6+TONTSEPT!C6+TONTOCT!C6+TONTNOV!C6+TONTDEC!C6+TONTFEV!C6+TONTMARS!C6+TONTAVRIL!C6+TONTMAI!C6+TONTJUIN!C6+TONTJUIL2021!C6+TONTAOUT2021!C6+TONTSEPT2021!C6 -> 300000 | D6: =TONTJUIL!D6+TONTAOUT!D6+TONTSEPT!D6+TONTOCT!D6+TONTNOV!D6+TONTDEC!D6+TONTFEV!D6+TONTMARS!D6+TONTAVRIL!D6+TONTMAI!D6+TONTJUIN!D6+TONTJUIL2021!D6+TONTAOUT2021!D6+TONTSEPT2021!D6 -> 0 | E6: =TONTJUIL!F6+TONTAOUT!F6+TONTSEPT!F6+TONTOCT!F6+TONTNOV!F6+TONTDEC!F6+TONTFEV!F6+TONTMARS!F6+TONTAVRIL!F6+TONTMAI!F6+TONTJUIN!F6+TONTJUIL2021!F6+TONTAOUT2021!F6+TONTSEPT2021!F6 -> 0 | F6: =TONTJUIL!G6+TONTAOUT!G6+TONTSEPT!G6+TONTOCT!G6+TONTNOV!G6+TONTDEC!G6+TONTFEV!G6+TONTMARS!G6+TONTAVRIL!G6+TONTMAI!G6+TONTJUIN!G6+TONTJUIL2021!G6+TONTAOUT2021!G6+TONTSEPT2021!G6 -> 0 | G6: =TONTJUIL!J6+TONTAOUT!J6+TONTSEPT!J6+TONTOCT!J6+TONTNOV!J6+TONTDEC!J6+TONTFEV!J6+TONTMARS!J6+TONTAVRIL!J6+TONTMAI!J6+TONTJUIN!J6+TONTJUIL2021!J6+TONTAOUT2021!J6+TONTSEPT2021!J6 -> 0 | H6: =TONTJUIL!K6+TONTAOUT!K6+TONTSEPT!K6+TONTOCT!K6+TONTNOV!K6+TONTDEC!K6+TONTFEV!K6+TONTMARS!K6+TONTAVRIL!K6+TONTMAI!K6+TONTJUIN!K6+TONTJUIL2021!K6+TONTAOUT2021!K6+TONTSEPT2021!K6 -> 0 | I6: =TONTJUIL!O6+TONTAOUT!O6+TONTSEPT!O6+TONTOCT!O6+TONTNOV!O6+TONTDEC!O6+TONTFEV!O6+TONTMARS!O6+TONTAVRIL!O6+TONTMAI!O6+TONTJUIN!O6+TONTJUIL2021!O6+TONTAOUT2021!O6+TONTSEPT2021!O6 -> 0 | J6: =TONTJUIL!P6+TONTAOUT!P6+TONTSEPT!P6+TONTOCT!P6+TONTNOV!P6+TONTDEC!P6+TONTFEV!P6+TONTMARS!P6+TONTAVRIL!P6+TONTMAI!P6+TONTJUIN!P6+TONTJUIL2021!P6+TONTAOUT2021!P6+TONTSEPT2021!P6 -> 0 | L6: =IF(I6=0,0,(J6-75000)) -> 0
A7: AS201603 | B7: =VLOOKUP(A7,[1]LISTADHERENT!A$5:H$60,3,0) -> CHINGUE FABRICE | C7: =TONTJUIL!C7+TONTAOUT!C7+TONTSEPT!C7+TONTOCT!C7+TONTNOV!C7+TONTDEC!C7+TONTFEV!C7+TONTMARS!C7+TONTAVRIL!C7+TONTMAI!C7+TONTJUIN!C7+TONTJUIL2021!C7+TONTAOUT2021!C7+TONTSEPT2021!C7 -> 75000 | D7: =TONTJUIL!D7+TONTAOUT!D7+TONTSEPT!D7+TONTOCT!D7+TONTNOV!D7+TONTDEC!D7+TONTFEV!D7+TONTMARS!D7+TONTAVRIL!D7+TONTMAI!D7+TONTJUIN!D7+TONTJUIL2021!D7+TONTAOUT2021!D7+TONTSEPT2021!D7 -> 0 | E7: =TONTJUIL!F7+TONTAOUT!F7+TONTSEPT!F7+TONTOCT!F7+TONTNOV!F7+TONTDEC!F7+TONTFEV!F7+TONTMARS!F7+TONTAVRIL!F7+TONTMAI!F7+TONTJUIN!F7+TONTJUIL2021!F7+TONTAOUT2021!F7+TONTSEPT2021!F7 -> 0 | F7: =TONTJUIL!G7+TONTAOUT!G7+TONTSEPT!G7+TONTOCT!G7+TONTNOV!G7+TONTDEC!G7+TONTFEV!G7+TONTMARS!G7+TONTAVRIL!G7+TONTMAI!G7+TONTJUIN!G7+TONTJUIL2021!G7+TONTAOUT2021!G7+TONTSEPT2021!G7 -> 0 | G7: =TONTJUIL!J7+TONTAOUT!J7+TONTSEPT!J7+TONTOCT!J7+TONTNOV!J7+TONTDEC!J7+TONTFEV!J7+TONTMARS!J7+TONTAVRIL!J7+TONTMAI!J7+TONTJUIN!J7+TONTJUIL2021!J7+TONTAOUT2021!J7+TONTSEPT2021!J7 -> 0 | H7: =TONTJUIL!K7+TONTAOUT!K7+TONTSEPT!K7+TONTOCT!K7+TONTNOV!K7+TONTDEC!K7+TONTFEV!K7+TONTMARS!K7+TONTAVRIL!K7+TONTMAI!K7+TONTJUIN!K7+TONTJUIL2021!K7+TONTAOUT2021!K7+TONTSEPT2021!K7 -> 0 | I7: =TONTJUIL!O7+TONTAOUT!O7+TONTSEPT!O7+TONTOCT!O7+TONTNOV!O7+TONTDEC!O7+TONTFEV!O7+TONTMARS!O7+TONTAVRIL!O7+TONTMAI!O7+TONTJUIN!O7+TONTJUIL2021!O7+TONTAOUT2021!O7+TONTSEPT2021!O7 -> 0 | J7: =TONTJUIL!P7+TONTAOUT!P7+TONTSEPT!P7+TONTOCT!P7+TONTNOV!P7+TONTDEC!P7+TONTFEV!P7+TONTMARS!P7+TONTAVRIL!P7+TONTMAI!P7+TONTJUIN!P7+TONTJUIL2021!P7+TONTAOUT2021!P7+TONTSEPT2021!P7 -> 0 | L7: =IF(I7=0,0,(J7-75000)) -> 0
A8: AS201604 | B8: =VLOOKUP(A8,[1]LISTADHERENT!A$5:H$60,3,0) -> DJOMO JEAN PAUL | C8: =TONTJUIL!C8+TONTAOUT!C8+TONTSEPT!C8+TONTOCT!C8+TONTNOV!C8+TONTDEC!C8+TONTFEV!C8+TONTMARS!C8+TONTAVRIL!C8+TONTMAI!C8+TONTJUIN!C8+TONTJUIL2021!C8+TONTAOUT2021!C8+TONTSEPT2021!C8 -> 300000 | D8: =TONTJUIL!D8+TONTAOUT!D8+TONTSEPT!D8+TONTOCT!D8+TONTNOV!D8+TONTDEC!D8+TONTFEV!D8+TONTMARS!D8+TONTAVRIL!D8+TONTMAI!D8+TONTJUIN!D8+TONTJUIL2021!D8+TONTAOUT2021!D8+TONTSEPT2021!D8 -> 0 | E8: =TONTJUIL!F8+TONTAOUT!F8+TONTSEPT!F8+TONTOCT!F8+TONTNOV!F8+TONTDEC!F8+TONTFEV!F8+TONTMARS!F8+TONTAVRIL!F8+TONTMAI!F8+TONTJUIN!F8+TONTJUIL2021!F8+TONTAOUT2021!F8+TONTSEPT2021!F8 -> 250000 | F8: =TONTJUIL!G8+TONTAOUT!G8+TONTSEPT!G8+TONTOCT!G8+TONTNOV!G8+TONTDEC!G8+TONTFEV!G8+TONTMARS!G8+TONTAVRIL!G8+TONTMAI!G8+TONTJUIN!G8+TONTJUIL2021!G8+TONTAOUT2021!G8+TONTSEPT2021!G8 -> 5000 | G8: =TONTJUIL!J8+TONTAOUT!J8+TONTSEPT!J8+TONTOCT!J8+TONTNOV!J8+TONTDEC!J8+TONTFEV!J8+TONTMARS!J8+TONTAVRIL!J8+TONTMAI!J8+TONTJUIN!J8+TONTJUIL2021!J8+TONTAOUT2021!J8+TONTSEPT2021!J8 -> 255000 | H8: =TONTJUIL!K8+TONTAOUT!K8+TONTSEPT!K8+TONTOCT!K8+TONTNOV!K8+TONTDEC!K8+TONTFEV!K8+TONTMARS!K8+TONTAVRIL!K8+TONTMAI!K8+TONTJUIN!K8+TONTJUIL2021!K8+TONTAOUT2021!K8+TONTSEPT2021!K8 -> 255000 | I8: =TONTJUIL!O8+TONTAOUT!O8+TONTSEPT!O8+TONTOCT!O8+TONTNOV!O8+TONTDEC!O8+TONTFEV!O8+TONTMARS!O8+TONTAVRIL!O8+TONTMAI!O8+TONTJUIN!O8+TONTJUIL2021!O8+TONTAOUT2021!O8+TONTSEPT2021!O8 -> 1000000 | J8: =TONTJUIL!P8+TONTAOUT!P8+TONTSEPT!P8+TONTOCT!P8+TONTNOV!P8+TONTDEC!P8+TONTFEV!P8+TONTMARS!P8+TONTAVRIL!P8+TONTMAI!P8+TONTJUIN!P8+TONTJUIL2021!P8+TONTAOUT2021!P8+TONTSEPT2021!P8 -> 200000 | K8: 44031 | L8: =IF(I8=0,0,(J8-75000)) -> 125000
A9: AS201605 | B9: =VLOOKUP(A9,[1]LISTADHERENT!A$5:H$60,3,0) -> DJOUKWE NANGUEN GUY BLAISE | C9: =TONTJUIL!C9+TONTAOUT!C9+TONTSEPT!C9+TONTOCT!C9+TONTNOV!C9+TONTDEC!C9+TONTFEV!C9+TONTMARS!C9+TONTAVRIL!C9+TONTMAI!C9+TONTJUIN!C9+TONTJUIL2021!C9+TONTAOUT2021!C9+TONTSEPT2021!C9 -> 300000 | D9: =TONTJUIL!D9+TONTAOUT!D9+TONTSEPT!D9+TONTOCT!D9+TONTNOV!D9+TONTDEC!D9+TONTFEV!D9+TONTMARS!D9+TONTAVRIL!D9+TONTMAI!D9+TONTJUIN!D9+TONTJUIL2021!D9+TONTAOUT2021!D9+TONTSEPT2021!D9 -> 0 | E9: =TONTJUIL!F9+TONTAOUT!F9+TONTSEPT!F9+TONTOCT!F9+TONTNOV!F9+TONTDEC!F9+TONTFEV!F9+TONTMARS!F9+TONTAVRIL!F9+TONTMAI!F9+TONTJUIN!F9+TONTJUIL2021!F9+TONTAOUT2021!F9+TONTSEPT2021!F9 -> 250000 | F9: =TONTJUIL!G9+TONTAOUT!G9+TONTSEPT!G9+TONTOCT!G9+TONTNOV!G9+TONTDEC!G9+TONTFEV!G9+TONTMARS!G9+TONTAVRIL!G9+TONTMAI!G9+TONTJUIN!G9+TONTJUIL2021!G9+TONTAOUT2021!G9+TONTSEPT2021!G9 -> 5000 | G9: =TONTJUIL!J9+TONTAOUT!J9+TONTSEPT!J9+TONTOCT!J9+TONTNOV!J9+TONTDEC!J9+TONTFEV!J9+TONTMARS!J9+TONTAVRIL!J9+TONTMAI!J9+TONTJUIN!J9+TONTJUIL2021!J9+TONTAOUT2021!J9+TONTSEPT2021!J9 -> 255000 | H9: =TONTJUIL!K9+TONTAOUT!K9+TONTSEPT!K9+TONTOCT!K9+TONTNOV!K9+TONTDEC!K9+TONTFEV!K9+TONTMARS!K9+TONTAVRIL!K9+TONTMAI!K9+TONTJUIN!K9+TONTJUIL2021!K9+TONTAOUT2021!K9+TONTSEPT2021!K9 -> 255000 | I9: =TONTJUIL!O9+TONTAOUT!O9+TONTSEPT!O9+TONTOCT!O9+TONTNOV!O9+TONTDEC!O9+TONTFEV!O9+TONTMARS!O9+TONTAVRIL!O9+TONTMAI!O9+TONTJUIN!O9+TONTJUIL2021!O9+TONTAOUT2021!O9+TONTSEPT2021!O9 -> 0 | J9: =TONTJUIL!P9+TONTAOUT!P9+TONTSEPT!P9+TONTOCT!P9+TONTNOV!P9+TONTDEC!P9+TONTFEV!P9+TONTMARS!P9+TONTAVRIL!P9+TONTMAI!P9+TONTJUIN!P9+TONTJUIL2021!P9+TONTAOUT2021!P9+TONTSEPT2021!P9 -> 0 | L9: =IF(I9=0,0,(J9-75000)) -> 0
A10: AS201613 | B10: =VLOOKUP(A10,[1]LISTADHERENT!A$5:H$60,3,0) -> HOTCHO BENJAMIN | C10: =TONTJUIL!C10+TONTAOUT!C10+TONTSEPT!C10+TONTOCT!C10+TONTNOV!C10+TONTDEC!C10+TONTFEV!C10+TONTMARS!C10+TONTAVRIL!C10+TONTMAI!C10+TONTJUIN!C10+TONTJUIL2021!C10+TONTAOUT2021!C10+TONTSEPT2021!C10 -> 300000 | D10: =TONTJUIL!D10+TONTAOUT!D10+TONTSEPT!D10+TONTOCT!D10+TONTNOV!D10+TONTDEC!D10+TONTFEV!D10+TONTMARS!D10+TONTAVRIL!D10+TONTMAI!D10+TONTJUIN!D10+TONTJUIL2021!D10+TONTAOUT2021!D10+TONTSEPT2021!D10 -> 0 | E10: =TONTJUIL!F10+TONTAOUT!F10+TONTSEPT!F10+TONTOCT!F10+TONTNOV!F10+TONTDEC!F10+TONTFEV!F10+TONTMARS!F10+TONTAVRIL!F10+TONTMAI!F10+TONTJUIN!F10+TONTJUIL2021!F10+TONTAOUT2021!F10+TONTSEPT2021!F10 -> 0 | F10: =TONTJUIL!G10+TONTAOUT!G10+TONTSEPT!G10+TONTOCT!G10+TONTNOV!G10+TONTDEC!G10+TONTFEV!G10+TONTMARS!G10+TONTAVRIL!G10+TONTMAI!G10+TONTJUIN!G10+TONTJUIL2021!G10+TONTAOUT2021!G10+TONTSEPT2021!G10 -> 0 | G10: =TONTJUIL!J10+TONTAOUT!J10+TONTSEPT!J10+TONTOCT!J10+TONTNOV!J10+TONTDEC!J10+TONTFEV!J10+TONTMARS!J10+TONTAVRIL!J10+TONTMAI!J10+TONTJUIN!J10+TONTJUIL2021!J10+TONTAOUT2021!J10+TONTSEPT2021!J10 -> 0 | H10: =TONTJUIL!K10+TONTAOUT!K10+TONTSEPT!K10+TONTOCT!K10+TONTNOV!K10+TONTDEC!K10+TONTFEV!K10+TONTMARS!K10+TONTAVRIL!K10+TONTMAI!K10+TONTJUIN!K10+TONTJUIL2021!K10+TONTAOUT2021!K10+TONTSEPT2021!K10 -> 0 | I10: =TONTJUIL!O10+TONTAOUT!O10+TONTSEPT!O10+TONTOCT!O10+TONTNOV!O10+TONTDEC!O10+TONTFEV!O10+TONTMARS!O10+TONTAVRIL!O10+TONTMAI!O10+TONTJUIN!O10+TONTJUIL2021!O10+TONTAOUT2021!O10+TONTSEPT2021!O10 -> 1125000 | J10: =TONTJUIL!P10+TONTAOUT!P10+TONTSEPT!P10+TONTOCT!P10+TONTNOV!P10+TONTDEC!P10+TONTFEV!P10+TONTMARS!P10+TONTAVRIL!P10+TONTMAI!P10+TONTJUIN!P10+TONTJUIL2021!P10+TONTAOUT2021!P10+TONTSEPT2021!P10 -> 75000 | K10: 44122 | L10: =IF(I10=0,0,(J10-75000)) -> 0
A11: AS201611 | B11: =VLOOKUP(A11,[1]LISTADHERENT!A$5:H$60,3,0) -> HENGUE PAUL OMER | C11: =TONTJUIL!C11+TONTAOUT!C11+TONTSEPT!C11+TONTOCT!C11+TONTNOV!C11+TONTDEC!C11+TONTFEV!C11+TONTMARS!C11+TONTAVRIL!C11+TONTMAI!C11+TONTJUIN!C11+TONTJUIL2021!C11+TONTAOUT2021!C11+TONTSEPT2021!C11 -> 300000 | D11: =TONTJUIL!D11+TONTAOUT!D11+TONTSEPT!D11+TONTOCT!D11+TONTNOV!D11+TONTDEC!D11+TONTFEV!D11+TONTMARS!D11+TONTAVRIL!D11+TONTMAI!D11+TONTJUIN!D11+TONTJUIL2021!D11+TONTAOUT2021!D11+TONTSEPT2021!D11 -> 0 | E11: =TONTJUIL!F11+TONTAOUT!F11+TONTSEPT!F11+TONTOCT!F11+TONTNOV!F11+TONTDEC!F11+TONTFEV!F11+TONTMARS!F11+TONTAVRIL!F11+TONTMAI!F11+TONTJUIN!F11+TONTJUIL2021!F11+TONTAOUT2021!F11+TONTSEPT2021!F11 -> 0 | F11: =TONTJUIL!G11+TONTAOUT!G11+TONTSEPT!G11+TONTOCT!G11+TONTNOV!G11+TONTDEC!G11+TONTFEV!G11+TONTMARS!G11+TONTAVRIL!G11+TONTMAI!G11+TONTJUIN!G11+TONTJUIL2021!G11+TONTAOUT2021!G11+TONTSEPT2021!G11 -> 0 | G11: =TONTJUIL!J11+TONTAOUT!J11+TONTSEPT!J11+TONTOCT!J11+TONTNOV!J11+TONTDEC!J11+TONTFEV!J11+TONTMARS!J11+TONTAVRIL!J11+TONTMAI!J11+TONTJUIN!J11+TONTJUIL2021!J11+TONTAOUT2021!J11+TONTSEPT2021!J11 -> 0 | H11: =TONTJUIL!K11+TONTAOUT!K11+TONTSEPT!K11+TONTOCT!K11+TONTNOV!K11+TONTDEC!K11+TONTFEV!K11+TONTMARS!K11+TONTAVRIL!K11+TONTMAI!K11+TONTJUIN!K11+TONTJUIL2021!K11+TONTAOUT2021!K11+TONTSEPT2021!K11 -> 0 | I11: =TONTJUIL!O11+TONTAOUT!O11+TONTSEPT!O11+TONTOCT!O11+TONTNOV!O11+TONTDEC!O11+TONTFEV!O11+TONTMARS!O11+TONTAVRIL!O11+TONTMAI!O11+TONTJUIN!O11+TONTJUIL2021!O11+TONTAOUT2021!O11+TONTSEPT2021!O11 -> 0 | J11: =TONTJUIL!P11+TONTAOUT!P11+TONTSEPT!P11+TONTOCT!P11+TONTNOV!P11+TONTDEC!P11+TONTFEV!P11+TONTMARS!P11+TONTAVRIL!P11+TONTMAI!P11+TONTJUIN!P11+TONTJUIL2021!P11+TONTAOUT2021!P11+TONTSEPT2021!P11 -> 0 | L11: =IF(I11=0,0,(J11-75000)) -> 0
A12: AS201619 | B12: =VLOOKUP(A12,[1]LISTADHERENT!A$5:H$60,3,0) -> KOUATCHO MESSACK | C12: =TONTJUIL!C12+TONTAOUT!C12+TONTSEPT!C12+TONTOCT!C12+TONTNOV!C12+TONTDEC!C12+TONTFEV!C12+TONTMARS!C12+TONTAVRIL!C12+TONTMAI!C12+TONTJUIN!C12+TONTJUIL2021!C12+TONTAOUT2021!C12+TONTSEPT2021!C12 -> 300000 | D12: =TONTJUIL!D12+TONTAOUT!D12+TONTSEPT!D12+TONTOCT!D12+TONTNOV!D12+TONTDEC!D12+TONTFEV!D12+TONTMARS!D12+TONTAVRIL!D12+TONTMAI!D12+TONTJUIN!D12+TONTJUIL2021!D12+TONTAOUT2021!D12+TONTSEPT2021!D12 -> 0 | E12: =TONTJUIL!F12+TONTAOUT!F12+TONTSEPT!F12+TONTOCT!F12+TONTNOV!F12+TONTDEC!F12+TONTFEV!F12+TONTMARS!F12+TONTAVRIL!F12+TONTMAI!F12+TONTJUIN!F12+TONTJUIL2021!F12+TONTAOUT2021!F12+TONTSEPT2021!F12 -> 200000 | F12: =TONTJUIL!G12+TONTAOUT!G12+TONTSEPT!G12+TONTOCT!G12+TONTNOV!G12+TONTDEC!G12+TONTFEV!G12+TONTMARS!G12+TONTAVRIL!G12+TONTMAI!G12+TONTJUIN!G12+TONTJUIL2021!G12+TONTAOUT2021!G12+TONTSEPT2021!G12 -> 4000 | G12: =TONTJUIL!J12+TONTAOUT!J12+TONTSEPT!J12+TONTOCT!J12+TONTNOV!J12+TONTDEC!J12+TONTFEV!J12+TONTMARS!J12+TONTAVRIL!J12+TONTMAI!J12+TONTJUIN!J12+TONTJUIL2021!J12+TONTAOUT2021!J12+TONTSEPT2021!J12 -> 204000 | H12: =TONTJUIL!K12+TONTAOUT!K12+TONTSEPT!K12+TONTOCT!K12+TONTNOV!K12+TONTDEC!K12+TONTFEV!K12+TONTMARS!K12+TONTAVRIL!K12+TONTMAI!K12+TONTJUIN!K12+TONTJUIL2021!K12+TONTAOUT2021!K12+TONTSEPT2021!K12 -> 204000 | I12: =TONTJUIL!O12+TONTAOUT!O12+TONTSEPT!O12+TONTOCT!O12+TONTNOV!O12+TONTDEC!O12+TONTFEV!O12+TONTMARS!O12+TONTAVRIL!O12+TONTMAI!O12+TONTJUIN!O12+TONTJUIL2021!O12+TONTAOUT2021!O12+TONTSEPT2021!O12 -> 0 | J12: =TONTJUIL!P12+TONTAOUT!P12+TONTSEPT!P12+TONTOCT!P12+TONTNOV!P12+TONTDEC!P12+TONTFEV!P12+TONTMARS!P12+TONTAVRIL!P12+TONTMAI!P12+TONTJUIN!P12+TONTJUIL2021!P12+TONTAOUT2021!P12+TONTSEPT2021!P12 -> 0 | L12: =IF(I12=0,0,(J12-75000)) -> 0
A13: AS201621 | B13: =VLOOKUP(A13,[1]LISTADHERENT!A$5:H$60,3,0) -> NANKAM APPOLINAIRE | C13: =TONTJUIL!C13+TONTAOUT!C13+TONTSEPT!C13+TONTOCT!C13+TONTNOV!C13+TONTDEC!C13+TONTFEV!C13+TONTMARS!C13+TONTAVRIL!C13+TONTMAI!C13+TONTJUIN!C13+TONTJUIL2021!C13+TONTAOUT2021!C13+TONTSEPT2021!C13 -> 300000 | D13: =TONTJUIL!D13+TONTAOUT!D13+TONTSEPT!D13+TONTOCT!D13+TONTNOV!D13+TONTDEC!D13+TONTFEV!D13+TONTMARS!D13+TONTAVRIL!D13+TONTMAI!D13+TONTJUIN!D13+TONTJUIL2021!D13+TONTAOUT2021!D13+TONTSEPT2021!D13 -> 0 | E13: =TONTJUIL!F13+TONTAOUT!F13+TONTSEPT!F13+TONTOCT!F13+TONTNOV!F13+TONTDEC!F13+TONTFEV!F13+TONTMARS!F13+TONTAVRIL!F13+TONTMAI!F13+TONTJUIN!F13+TONTJUIL2021!F13+TONTAOUT2021!F13+TONTSEPT2021!F13 -> 0 | F13: =TONTJUIL!G13+TONTAOUT!G13+TONTSEPT!G13+TONTOCT!G13+TONTNOV!G13+TONTDEC!G13+TONTFEV!G13+TONTMARS!G13+TONTAVRIL!G13+TONTMAI!G13+TONTJUIN!G13+TONTJUIL2021!G13+TONTAOUT2021!G13+TONTSEPT2021!G13 -> 0 | G13: =TONTJUIL!J13+TONTAOUT!J13+TONTSEPT!J13+TONTOCT!J13+TONTNOV!J13+TONTDEC!J13+TONTFEV!J13+TONTMARS!J13+TONTAVRIL!J13+TONTMAI!J13+TONTJUIN!J13+TONTJUIL2021!J13+TONTAOUT2021!J13+TONTSEPT2021!J13 -> 0 | H13: =TONTJUIL!K13+TONTAOUT!K13+TONTSEPT!K13+TONTOCT!K13+TONTNOV!K13+TONTDEC!K13+TONTFEV!K13+TONTMARS!K13+TONTAVRIL!K13+TONTMAI!K13+TONTJUIN!K13+TONTJUIL2021!K13+TONTAOUT2021!K13+TONTSEPT2021!K13 -> 0 | I13: =TONTJUIL!O13+TONTAOUT!O13+TONTSEPT!O13+TONTOCT!O13+TONTNOV!O13+TONTDEC!O13+TONTFEV!O13+TONTMARS!O13+TONTAVRIL!O13+TONTMAI!O13+TONTJUIN!O13+TONTJUIL2021!O13+TONTAOUT2021!O13+TONTSEPT2021!O13 -> 0 | J13: =TONTJUIL!P13+TONTAOUT!P13+TONTSEPT!P13+TONTOCT!P13+TONTNOV!P13+TONTDEC!P13+TONTFEV!P13+TONTMARS!P13+TONTAVRIL!P13+TONTMAI!P13+TONTJUIN!P13+TONTJUIL2021!P13+TONTAOUT2021!P13+TONTSEPT2021!P13 -> 0 | L13: =IF(I13=0,0,(J13-75000)) -> 0
A14: AS201649 | B14: =VLOOKUP(A14,[1]LISTADHERENT!A$5:H$60,3,0) -> MBOGNING TUGMA GUY | C14: =TONTJUIL!C14+TONTAOUT!C14+TONTSEPT!C14+TONTOCT!C14+TONTNOV!C14+TONTDEC!C14+TONTFEV!C14+TONTMARS!C14+TONTAVRIL!C14+TONTMAI!C14+TONTJUIN!C14+TONTJUIL2021!C14+TONTAOUT2021!C14+TONTSEPT2021!C14 -> 300000 | D14: =TONTJUIL!D14+TONTAOUT!D14+TONTSEPT!D14+TONTOCT!D14+TONTNOV!D14+TONTDEC!D14+TONTFEV!D14+TONTMARS!D14+TONTAVRIL!D14+TONTMAI!D14+TONTJUIN!D14+TONTJUIL2021!D14+TONTAOUT2021!D14+TONTSEPT2021!D14 -> 0 | E14: =TONTJUIL!F14+TONTAOUT!F14+TONTSEPT!F14+TONTOCT!F14+TONTNOV!F14+TONTDEC!F14+TONTFEV!F14+TONTMARS!F14+TONTAVRIL!F14+TONTMAI!F14+TONTJUIN!F14+TONTJUIL2021!F14+TONTAOUT2021!F14+TONTSEPT2021!F14 -> 300000 | F14: =TONTJUIL!G14+TONTAOUT!G14+TONTSEPT!G14+TONTOCT!G14+TONTNOV!G14+TONTDEC!G14+TONTFEV!G14+TONTMARS!G14+TONTAVRIL!G14+TONTMAI!G14+TONTJUIN!G14+TONTJUIL2021!G14+TONTAOUT2021!G14+TONTSEPT2021!G14 -> 6000 | G14: =TONTJUIL!J14+TONTAOUT!J14+TONTSEPT!J14+TONTOCT!J14+TONTNOV!J14+TONTDEC!J14+TONTFEV!J14+TONTMARS!J14+TONTAVRIL!J14+TONTMAI!J14+TONTJUIN!J14+TONTJUIL2021!J14+TONTAOUT2021!J14+TONTSEPT2021!J14 -> 306000 | H14: =TONTJUIL!K14+TONTAOUT!K14+TONTSEPT!K14+TONTOCT!K14+TONTNOV!K14+TONTDEC!K14+TONTFEV!K14+TONTMARS!K14+TONTAVRIL!K14+TONTMAI!K14+TONTJUIN!K14+TONTJUIL2021!K14+TONTAOUT2021!K14+TONTSEPT2021!K14 -> 306000 | I14: =TONTJUIL!O14+TONTAOUT!O14+TONTSEPT!O14+TONTOCT!O14+TONTNOV!O14+TONTDEC!O14+TONTFEV!O14+TONTMARS!O14+TONTAVRIL!O14+TONTMAI!O14+TONTJUIN!O14+TONTJUIL2021!O14+TONTAOUT2021!O14+TONTSEPT2021!O14 -> 1040000 | J14: =TONTJUIL!P14+TONTAOUT!P14+TONTSEPT!P14+TONTOCT!P14+TONTNOV!P14+TONTDEC!P14+TONTFEV!P14+TONTMARS!P14+TONTAVRIL!P14+TONTMAI!P14+TONTJUIN!P14+TONTJUIL2021!P14+TONTAOUT2021!P14+TONTSEPT2021!P14 -> 160000 | K14: 44061 | L14: =IF(I14=0,0,(J14-75000)) -> 85000
A15: AS201649 | B15: =VLOOKUP(A15,[1]LISTADHERENT!A$5:H$60,3,0) -> MBOGNING TUGMA GUY | C15: =TONTJUIL!C15+TONTAOUT!C15+TONTSEPT!C15+TONTOCT!C15+TONTNOV!C15+TONTDEC!C15+TONTFEV!C15+TONTMARS!C15+TONTAVRIL!C15+TONTMAI!C15+TONTJUIN!C15+TONTJUIL2021!C15+TONTAOUT2021!C15+TONTSEPT2021!C15 -> 300000 | D15: =TONTJUIL!D15+TONTAOUT!D15+TONTSEPT!D15+TONTOCT!D15+TONTNOV!D15+TONTDEC!D15+TONTFEV!D15+TONTMARS!D15+TONTAVRIL!D15+TONTMAI!D15+TONTJUIN!D15+TONTJUIL2021!D15+TONTAOUT2021!D15+TONTSEPT2021!D15 -> 0 | E15: =TONTJUIL!F15+TONTAOUT!F15+TONTSEPT!F15+TONTOCT!F15+TONTNOV!F15+TONTDEC!F15+TONTFEV!F15+TONTMARS!F15+TONTAVRIL!F15+TONTMAI!F15+TONTJUIN!F15+TONTJUIL2021!F15+TONTAOUT2021!F15+TONTSEPT2021!F15 -> 0 | F15: =TONTJUIL!G15+TONTAOUT!G15+TONTSEPT!G15+TONTOCT!G15+TONTNOV!G15+TONTDEC!G15+TONTFEV!G15+TONTMARS!G15+TONTAVRIL!G15+TONTMAI!G15+TONTJUIN!G15+TONTJUIL2021!G15+TONTAOUT2021!G15+TONTSEPT2021!G15 -> 0 | G15: =TONTJUIL!J15+TONTAOUT!J15+TONTSEPT!J15+TONTOCT!J15+TONTNOV!J15+TONTDEC!J15+TONTFEV!J15+TONTMARS!J15+TONTAVRIL!J15+TONTMAI!J15+TONTJUIN!J15+TONTJUIL2021!J15+TONTAOUT2021!J15+TONTSEPT2021!J15 -> 0 | H15: =TONTJUIL!K15+TONTAOUT!K15+TONTSEPT!K15+TONTOCT!K15+TONTNOV!K15+TONTDEC!K15+TONTFEV!K15+TONTMARS!K15+TONTAVRIL!K15+TONTMAI!K15+TONTJUIN!K15+TONTJUIL2021!K15+TONTAOUT2021!K15+TONTSEPT2021!K15 -> 0 | I15: =TONTJUIL!O15+TONTAOUT!O15+TONTSEPT!O15+TONTOCT!O15+TONTNOV!O15+TONTDEC!O15+TONTFEV!O15+TONTMARS!O15+TONTAVRIL!O15+TONTMAI!O15+TONTJUIN!O15+TONTJUIL2021!O15+TONTAOUT2021!O15+TONTSEPT2021!O15 -> 0 | J15: =TONTJUIL!P15+TONTAOUT!P15+TONTSEPT!P15+TONTOCT!P15+TONTNOV!P15+TONTDEC!P15+TONTFEV!P15+TONTMARS!P15+TONTAVRIL!P15+TONTMAI!P15+TONTJUIN!P15+TONTJUIL2021!P15+TONTAOUT2021!P15+TONTSEPT2021!P15 -> 0 | L15: =IF(I15=0,0,(J15-75000)) -> 0
A16: AS201649 | B16: =VLOOKUP(A16,[1]LISTADHERENT!A$5:H$60,3,0) -> MBOGNING TUGMA GUY | C16: =TONTJUIL!C16+TONTAOUT!C16+TONTSEPT!C16+TONTOCT!C16+TONTNOV!C16+TONTDEC!C16+TONTFEV!C16+TONTMARS!C16+TONTAVRIL!C16+TONTMAI!C16+TONTJUIN!C16+TONTJUIL2021!C16+TONTAOUT2021!C16+TONTSEPT2021!C16 -> 300000 | D16: =TONTJUIL!D16+TONTAOUT!D16+TONTSEPT!D16+TONTOCT!D16+TONTNOV!D16+TONTDEC!D16+TONTFEV!D16+TONTMARS!D16+TONTAVRIL!D16+TONTMAI!D16+TONTJUIN!D16+TONTJUIL2021!D16+TONTAOUT2021!D16+TONTSEPT2021!D16 -> 0 | E16: =TONTJUIL!F16+TONTAOUT!F16+TONTSEPT!F16+TONTOCT!F16+TONTNOV!F16+TONTDEC!F16+TONTFEV!F16+TONTMARS!F16+TONTAVRIL!F16+TONTMAI!F16+TONTJUIN!F16+TONTJUIL2021!F16+TONTAOUT2021!F16+TONTSEPT2021!F16 -> 0 | F16: =TONTJUIL!G16+TONTAOUT!G16+TONTSEPT!G16+TONTOCT!G16+TONTNOV!G16+TONTDEC!G16+TONTFEV!G16+TONTMARS!G16+TONTAVRIL!G16+TONTMAI!G16+TONTJUIN!G16+TONTJUIL2021!G16+TONTAOUT2021!G16+TONTSEPT2021!G16 -> 0 | G16: =TONTJUIL!J16+TONTAOUT!J16+TONTSEPT!J16+TONTOCT!J16+TONTNOV!J16+TONTDEC!J16+TONTFEV!J16+TONTMARS!J16+TONTAVRIL!J16+TONTMAI!J16+TONTJUIN!J16+TONTJUIL2021!J16+TONTAOUT2021!J16+TONTSEPT2021!J16 -> 0 | H16: =TONTJUIL!K16+TONTAOUT!K16+TONTSEPT!K16+TONTOCT!K16+TONTNOV!K16+TONTDEC!K16+TONTFEV!K16+TONTMARS!K16+TONTAVRIL!K16+TONTMAI!K16+TONTJUIN!K16+TONTJUIL2021!K16+TONTAOUT2021!K16+TONTSEPT2021!K16 -> 0 | I16: =TONTJUIL!O16+TONTAOUT!O16+TONTSEPT!O16+TONTOCT!O16+TONTNOV!O16+TONTDEC!O16+TONTFEV!O16+TONTMARS!O16+TONTAVRIL!O16+TONTMAI!O16+TONTJUIN!O16+TONTJUIL2021!O16+TONTAOUT2021!O16+TONTSEPT2021!O16 -> 0 | J16: =TONTJUIL!P16+TONTAOUT!P16+TONTSEPT!P16+TONTOCT!P16+TONTNOV!P16+TONTDEC!P16+TONTFEV!P16+TONTMARS!P16+TONTAVRIL!P16+TONTMAI!P16+TONTJUIN!P16+TONTJUIL2021!P16+TONTAOUT2021!P16+TONTSEPT2021!P16 -> 0 | L16: =IF(I16=0,0,(J16-75000)) -> 0
A17: AS201626 | B17: =VLOOKUP(A17,[1]LISTADHERENT!A$5:H$60,3,0) -> NGUIEMEGNI MATHIEU BLAISE | C17: =TONTJUIL!C17+TONTAOUT!C17+TONTSEPT!C17+TONTOCT!C17+TONTNOV!C17+TONTDEC!C17+TONTFEV!C17+TONTMARS!C17+TONTAVRIL!C17+TONTMAI!C17+TONTJUIN!C17+TONTJUIL2021!C17+TONTAOUT2021!C17+TONTSEPT2021!C17 -> 300000 | D17: =TONTJUIL!D17+TONTAOUT!D17+TONTSEPT!D17+TONTOCT!D17+TONTNOV!D17+TONTDEC!D17+TONTFEV!D17+TONTMARS!D17+TONTAVRIL!D17+TONTMAI!D17+TONTJUIN!D17+TONTJUIL2021!D17+TONTAOUT2021!D17+TONTSEPT2021!D17 -> 0 | E17: =TONTJUIL!F17+TONTAOUT!F17+TONTSEPT!F17+TONTOCT!F17+TONTNOV!F17+TONTDEC!F17+TONTFEV!F17+TONTMARS!F17+TONTAVRIL!F17+TONTMAI!F17+TONTJUIN!F17+TONTJUIL2021!F17+TONTAOUT2021!F17+TONTSEPT2021!F17 -> 202000 | F17: =TONTJUIL!G17+TONTAOUT!G17+TONTSEPT!G17+TONTOCT!G17+TONTNOV!G17+TONTDEC!G17+TONTFEV!G17+TONTMARS!G17+TONTAVRIL!G17+TONTMAI!G17+TONTJUIN!G17+TONTJUIL2021!G17+TONTAOUT2021!G17+TONTSEPT2021!G17 -> 6000 | G17: =TONTJUIL!J17+TONTAOUT!J17+TONTSEPT!J17+TONTOCT!J17+TONTNOV!J17+TONTDEC!J17+TONTFEV!J17+TONTMARS!J17+TONTAVRIL!J17+TONTMAI!J17+TONTJUIN!J17+TONTJUIL2021!J17+TONTAOUT2021!J17+TONTSEPT2021!J17 -> 208000 | H17: =TONTJUIL!K17+TONTAOUT!K17+TONTSEPT!K17+TONTOCT!K17+TONTNOV!K17+TONTDEC!K17+TONTFEV!K17+TONTMARS!K17+TONTAVRIL!K17+TONTMAI!K17+TONTJUIN!K17+TONTJUIL2021!K17+TONTAOUT2021!K17+TONTSEPT2021!K17 -> 208000 | I17: =TONTJUIL!O17+TONTAOUT!O17+TONTSEPT!O17+TONTOCT!O17+TONTNOV!O17+TONTDEC!O17+TONTFEV!O17+TONTMARS!O17+TONTAVRIL!O17+TONTMAI!O17+TONTJUIN!O17+TONTJUIL2021!O17+TONTAOUT2021!O17+TONTSEPT2021!O17 -> 0 | J17: =TONTJUIL!P17+TONTAOUT!P17+TONTSEPT!P17+TONTOCT!P17+TONTNOV!P17+TONTDEC!P17+TONTFEV!P17+TONTMARS!P17+TONTAVRIL!P17+TONTMAI!P17+TONTJUIN!P17+TONTJUIL2021!P17+TONTAOUT2021!P17+TONTSEPT2021!P17 -> 0 | L17: =IF(I17=0,0,(J17-75000)) -> 0
A18: AS201626 | B18: =VLOOKUP(A18,[1]LISTADHERENT!A$5:H$60,3,0) -> NGUIEMEGNI MATHIEU BLAISE | C18: =TONTJUIL!C18+TONTAOUT!C18+TONTSEPT!C18+TONTOCT!C18+TONTNOV!C18+TONTDEC!C18+TONTFEV!C18+TONTMARS!C18+TONTAVRIL!C18+TONTMAI!C18+TONTJUIN!C18+TONTJUIL2021!C18+TONTAOUT2021!C18+TONTSEPT2021!C18 -> 300000 | D18: =TONTJUIL!D18+TONTAOUT!D18+TONTSEPT!D18+TONTOCT!D18+TONTNOV!D18+TONTDEC!D18+TONTFEV!D18+TONTMARS!D18+TONTAVRIL!D18+TONTMAI!D18+TONTJUIN!D18+TONTJUIL2021!D18+TONTAOUT2021!D18+TONTSEPT2021!D18 -> 0 | E18: =TONTJUIL!F18+TONTAOUT!F18+TONTSEPT!F18+TONTOCT!F18+TONTNOV!F18+TONTDEC!F18+TONTFEV!F18+TONTMARS!F18+TONTAVRIL!F18+TONTMAI!F18+TONTJUIN!F18+TONTJUIL2021!F18+TONTAOUT2021!F18+TONTSEPT2021!F18 -> 0 | F18: =TONTJUIL!G18+TONTAOUT!G18+TONTSEPT!G18+TONTOCT!G18+TONTNOV!G18+TONTDEC!G18+TONTFEV!G18+TONTMARS!G18+TONTAVRIL!G18+TONTMAI!G18+TONTJUIN!G18+TONTJUIL2021!G18+TONTAOUT2021!G18+TONTSEPT2021!G18 -> 0 | G18: =TONTJUIL!J18+TONTAOUT!J18+TONTSEPT!J18+TONTOCT!J18+TONTNOV!J18+TONTDEC!J18+TONTFEV!J18+TONTMARS!J18+TONTAVRIL!J18+TONTMAI!J18+TONTJUIN!J18+TONTJUIL2021!J18+TONTAOUT2021!J18+TONTSEPT2021!J18 -> 0 | H18: =TONTJUIL!K18+TONTAOUT!K18+TONTSEPT!K18+TONTOCT!K18+TONTNOV!K18+TONTDEC!K18+TONTFEV!K18+TONTMARS!K18+TONTAVRIL!K18+TONTMAI!K18+TONTJUIN!K18+TONTJUIL2021!K18+TONTAOUT2021!K18+TONTSEPT2021!K18 -> 0 | I18: =TONTJUIL!O18+TONTAOUT!O18+TONTSEPT!O18+TONTOCT!O18+TONTNOV!O18+TONTDEC!O18+TONTFEV!O18+TONTMARS!O18+TONTAVRIL!O18+TONTMAI!O18+TONTJUIN!O18+TONTJUIL2021!O18+TONTAOUT2021!O18+TONTSEPT2021!O18 -> 0 | J18: =TONTJUIL!P18+TONTAOUT!P18+TONTSEPT!P18+TONTOCT!P18+TONTNOV!P18+TONTDEC!P18+TONTFEV!P18+TONTMARS!P18+TONTAVRIL!P18+TONTMAI!P18+TONTJUIN!P18+TONTJUIL2021!P18+TONTAOUT2021!P18+TONTSEPT2021!P18 -> 0 | L18: =IF(I18=0,0,(J18-75000)) -> 0
A19: AS201628 | B19: =VLOOKUP(A19,[1]LISTADHERENT!A$5:H$60,3,0) -> NKAMGANG JUSTIN DEJOLIE | C19: =TONTJUIL!C19+TONTAOUT!C19+TONTSEPT!C19+TONTOCT!C19+TONTNOV!C19+TONTDEC!C19+TONTFEV!C19+TONTMARS!C19+TONTAVRIL!C19+TONTMAI!C19+TONTJUIN!C19+TONTJUIL2021!C19+TONTAOUT2021!C19+TONTSEPT2021!C19 -> 300000 | D19: =TONTJUIL!D19+TONTAOUT!D19+TONTSEPT!D19+TONTOCT!D19+TONTNOV!D19+TONTDEC!D19+TONTFEV!D19+TONTMARS!D19+TONTAVRIL!D19+TONTMAI!D19+TONTJUIN!D19+TONTJUIL2021!D19+TONTAOUT2021!D19+TONTSEPT2021!D19 -> 0 | E19: =TONTJUIL!F19+TONTAOUT!F19+TONTSEPT!F19+TONTOCT!F19+TONTNOV!F19+TONTDEC!F19+TONTFEV!F19+TONTMARS!F19+TONTAVRIL!F19+TONTMAI!F19+TONTJUIN!F19+TONTJUIL2021!F19+TONTAOUT2021!F19+TONTSEPT2021!F19 -> 250000 | F19: =TONTJUIL!G19+TONTAOUT!G19+TONTSEPT!G19+TONTOCT!G19+TONTNOV!G19+TONTDEC!G19+TONTFEV!G19+TONTMARS!G19+TONTAVRIL!G19+TONTMAI!G19+TONTJUIN!G19+TONTJUIL2021!G19+TONTAOUT2021!G19+TONTSEPT2021!G19 -> 5000 | G19: =TONTJUIL!J19+TONTAOUT!J19+TONTSEPT!J19+TONTOCT!J19+TONTNOV!J19+TONTDEC!J19+TONTFEV!J19+TONTMARS!J19+TONTAVRIL!J19+TONTMAI!J19+TONTJUIN!J19+TONTJUIL2021!J19+TONTAOUT2021!J19+TONTSEPT2021!J19 -> 255000 | H19: =TONTJUIL!K19+TONTAOUT!K19+TONTSEPT!K19+TONTOCT!K19+TONTNOV!K19+TONTDEC!K19+TONTFEV!K19+TONTMARS!K19+TONTAVRIL!K19+TONTMAI!K19+TONTJUIN!K19+TONTJUIL2021!K19+TONTAOUT2021!K19+TONTSEPT2021!K19 -> 255000 | I19: =TONTJUIL!O19+TONTAOUT!O19+TONTSEPT!O19+TONTOCT!O19+TONTNOV!O19+TONTDEC!O19+TONTFEV!O19+TONTMARS!O19+TONTAVRIL!O19+TONTMAI!O19+TONTJUIN!O19+TONTJUIL2021!O19+TONTAOUT2021!O19+TONTSEPT2021!O19 -> 1115000 | J19: =TONTJUIL!P19+TONTAOUT!P19+TONTSEPT!P19+TONTOCT!P19+TONTNOV!P19+TONTDEC!P19+TONTFEV!P19+TONTMARS!P19+TONTAVRIL!P19+TONTMAI!P19+TONTJUIN!P19+TONTJUIL2021!P19+TONTAOUT2021!P19+TONTSEPT2021!P19 -> 85000 | K19: 44090 | L19: =IF(I19=0,0,(J19-75000)) -> 10000
A20: AS201633 | B20: =VLOOKUP(A20,[1]LISTADHERENT!A$5:H$60,3,0) -> PATEGO NJOSSU GUSTAVE | C20: =TONTJUIL!C20+TONTAOUT!C20+TONTSEPT!C20+TONTOCT!C20+TONTNOV!C20+TONTDEC!C20+TONTFEV!C20+TONTMARS!C20+TONTAVRIL!C20+TONTMAI!C20+TONTJUIN!C20+TONTJUIL2021!C20+TONTAOUT2021!C20+TONTSEPT2021!C20 -> 300000 | D20: =TONTJUIL!D20+TONTAOUT!D20+TONTSEPT!D20+TONTOCT!D20+TONTNOV!D20+TONTDEC!D20+TONTFEV!D20+TONTMARS!D20+TONTAVRIL!D20+TONTMAI!D20+TONTJUIN!D20+TONTJUIL2021!D20+TONTAOUT2021!D20+TONTSEPT2021!D20 -> 0 | E20: =TONTJUIL!F20+TONTAOUT!F20+TONTSEPT!F20+TONTOCT!F20+TONTNOV!F20+TONTDEC!F20+TONTFEV!F20+TONTMARS!F20+TONTAVRIL!F20+TONTMAI!F20+TONTJUIN!F20+TONTJUIL2021!F20+TONTAOUT2021!F20+TONTSEPT2021!F20 -> 0 | F20: =TONTJUIL!G20+TONTAOUT!G20+TONTSEPT!G20+TONTOCT!G20+TONTNOV!G20+TONTDEC!G20+TONTFEV!G20+TONTMARS!G20+TONTAVRIL!G20+TONTMAI!G20+TONTJUIN!G20+TONTJUIL2021!G20+TONTAOUT2021!G20+TONTSEPT2021!G20 -> 0 | G20: =TONTJUIL!J20+TONTAOUT!J20+TONTSEPT!J20+TONTOCT!J20+TONTNOV!J20+TONTDEC!J20+TONTFEV!J20+TONTMARS!J20+TONTAVRIL!J20+TONTMAI!J20+TONTJUIN!J20+TONTJUIL2021!J20+TONTAOUT2021!J20+TONTSEPT2021!J20 -> 0 | H20: =TONTJUIL!K20+TONTAOUT!K20+TONTSEPT!K20+TONTOCT!K20+TONTNOV!K20+TONTDEC!K20+TONTFEV!K20+TONTMARS!K20+TONTAVRIL!K20+TONTMAI!K20+TONTJUIN!K20+TONTJUIL2021!K20+TONTAOUT2021!K20+TONTSEPT2021!K20 -> 0 | I20: =TONTJUIL!O20+TONTAOUT!O20+TONTSEPT!O20+TONTOCT!O20+TONTNOV!O20+TONTDEC!O20+TONTFEV!O20+TONTMARS!O20+TONTAVRIL!O20+TONTMAI!O20+TONTJUIN!O20+TONTJUIL2021!O20+TONTAOUT2021!O20+TONTSEPT2021!O20 -> 0 | J20: =TONTJUIL!P20+TONTAOUT!P20+TONTSEPT!P20+TONTOCT!P20+TONTNOV!P20+TONTDEC!P20+TONTFEV!P20+TONTMARS!P20+TONTAVRIL!P20+TONTMAI!P20+TONTJUIN!P20+TONTJUIL2021!P20+TONTAOUT2021!P20+TONTSEPT2021!P20 -> 0 | L20: =IF(I20=0,0,(J20-75000)) -> 0
A21: AS201638 | B21: =VLOOKUP(A21,[1]LISTADHERENT!A$5:H$60,3,0) -> SIMO PIERRE | C21: =TONTJUIL!C21+TONTAOUT!C21+TONTSEPT!C21+TONTOCT!C21+TONTNOV!C21+TONTDEC!C21+TONTFEV!C21+TONTMARS!C21+TONTAVRIL!C21+TONTMAI!C21+TONTJUIN!C21+TONTJUIL2021!C21+TONTAOUT2021!C21+TONTSEPT2021!C21 -> 300000 | D21: =TONTJUIL!D21+TONTAOUT!D21+TONTSEPT!D21+TONTOCT!D21+TONTNOV!D21+TONTDEC!D21+TONTFEV!D21+TONTMARS!D21+TONTAVRIL!D21+TONTMAI!D21+TONTJUIN!D21+TONTJUIL2021!D21+TONTAOUT2021!D21+TONTSEPT2021!D21 -> 0 | E21: =TONTJUIL!F21+TONTAOUT!F21+TONTSEPT!F21+TONTOCT!F21+TONTNOV!F21+TONTDEC!F21+TONTFEV!F21+TONTMARS!F21+TONTAVRIL!F21+TONTMAI!F21+TONTJUIN!F21+TONTJUIL2021!F21+TONTAOUT2021!F21+TONTSEPT2021!F21 -> 0 | F21: =TONTJUIL!G21+TONTAOUT!G21+TONTSEPT!G21+TONTOCT!G21+TONTNOV!G21+TONTDEC!G21+TONTFEV!G21+TONTMARS!G21+TONTAVRIL!G21+TONTMAI!G21+TONTJUIN!G21+TONTJUIL2021!G21+TONTAOUT2021!G21+TONTSEPT2021!G21 -> 0 | G21: =TONTJUIL!J21+TONTAOUT!J21+TONTSEPT!J21+TONTOCT!J21+TONTNOV!J21+TONTDEC!J21+TONTFEV!J21+TONTMARS!J21+TONTAVRIL!J21+TONTMAI!J21+TONTJUIN!J21+TONTJUIL2021!J21+TONTAOUT2021!J21+TONTSEPT2021!J21 -> 0 | H21: =TONTJUIL!K21+TONTAOUT!K21+TONTSEPT!K21+TONTOCT!K21+TONTNOV!K21+TONTDEC!K21+TONTFEV!K21+TONTMARS!K21+TONTAVRIL!K21+TONTMAI!K21+TONTJUIN!K21+TONTJUIL2021!K21+TONTAOUT2021!K21+TONTSEPT2021!K21 -> 0 | I21: =TONTJUIL!O21+TONTAOUT!O21+TONTSEPT!O21+TONTOCT!O21+TONTNOV!O21+TONTDEC!O21+TONTFEV!O21+TONTMARS!O21+TONTAVRIL!O21+TONTMAI!O21+TONTJUIN!O21+TONTJUIL2021!O21+TONTAOUT2021!O21+TONTSEPT2021!O21 -> 0 | J21: =TONTJUIL!P21+TONTAOUT!P21+TONTSEPT!P21+TONTOCT!P21+TONTNOV!P21+TONTDEC!P21+TONTFEV!P21+TONTMARS!P21+TONTAVRIL!P21+TONTMAI!P21+TONTJUIN!P21+TONTJUIL2021!P21+TONTAOUT2021!P21+TONTSEPT2021!P21 -> 0 | L21: =IF(I21=0,0,(J21-75000)) -> 0
A22: AS201655 | B22: =VLOOKUP(A22,[1]LISTADHERENT!A$5:H$60,3,0) -> TCHEMHOU EMMANUEL | C22: =TONTJUIL!C22+TONTAOUT!C22+TONTSEPT!C22+TONTOCT!C22+TONTNOV!C22+TONTDEC!C22+TONTFEV!C22+TONTMARS!C22+TONTAVRIL!C22+TONTMAI!C22+TONTJUIN!C22+TONTJUIL2021!C22+TONTAOUT2021!C22+TONTSEPT2021!C22 -> 311500 | D22: =TONTJUIL!D22+TONTAOUT!D22+TONTSEPT!D22+TONTOCT!D22+TONTNOV!D22+TONTDEC!D22+TONTFEV!D22+TONTMARS!D22+TONTAVRIL!D22+TONTMAI!D22+TONTJUIN!D22+TONTJUIL2021!D22+TONTAOUT2021!D22+TONTSEPT2021!D22 -> 0 | E22: =TONTJUIL!F22+TONTAOUT!F22+TONTSEPT!F22+TONTOCT!F22+TONTNOV!F22+TONTDEC!F22+TONTFEV!F22+TONTMARS!F22+TONTAVRIL!F22+TONTMAI!F22+TONTJUIN!F22+TONTJUIL2021!F22+TONTAOUT2021!F22+TONTSEPT2021!F22 -> 0 | F22: =TONTJUIL!G22+TONTAOUT!G22+TONTSEPT!G22+TONTOCT!G22+TONTNOV!G22+TONTDEC!G22+TONTFEV!G22+TONTMARS!G22+TONTAVRIL!G22+TONTMAI!G22+TONTJUIN!G22+TONTJUIL2021!G22+TONTAOUT2021!G22+TONTSEPT2021!G22 -> 0 | G22: =TONTJUIL!J22+TONTAOUT!J22+TONTSEPT!J22+TONTOCT!J22+TONTNOV!J22+TONTDEC!J22+TONTFEV!J22+TONTMARS!J22+TONTAVRIL!J22+TONTMAI!J22+TONTJUIN!J22+TONTJUIL2021!J22+TONTAOUT2021!J22+TONTSEPT2021!J22 -> 0 | H22: =TONTJUIL!K22+TONTAOUT!K22+TONTSEPT!K22+TONTOCT!K22+TONTNOV!K22+TONTDEC!K22+TONTFEV!K22+TONTMARS!K22+TONTAVRIL!K22+TONTMAI!K22+TONTJUIN!K22+TONTJUIL2021!K22+TONTAOUT2021!K22+TONTSEPT2021!K22 -> 0 | I22: =TONTJUIL!O22+TONTAOUT!O22+TONTSEPT!O22+TONTOCT!O22+TONTNOV!O22+TONTDEC!O22+TONTFEV!O22+TONTMARS!O22+TONTAVRIL!O22+TONTMAI!O22+TONTJUIN!O22+TONTJUIL2021!O22+TONTAOUT2021!O22+TONTSEPT2021!O22 -> 0 | J22: =TONTJUIL!P22+TONTAOUT!P22+TONTSEPT!P22+TONTOCT!P22+TONTNOV!P22+TONTDEC!P22+TONTFEV!P22+TONTMARS!P22+TONTAVRIL!P22+TONTMAI!P22+TONTJUIN!P22+TONTJUIL2021!P22+TONTAOUT2021!P22+TONTSEPT2021!P22 -> 0 | L22: =IF(I22=0,0,(J22-75000)) -> 0
A23: AS201647 | B23: =VLOOKUP(A23,[1]LISTADHERENT!A$5:H$60,3,0) -> YOUMBI EMMANUEL | C23: =TONTJUIL!C23+TONTAOUT!C23+TONTSEPT!C23+TONTOCT!C23+TONTNOV!C23+TONTDEC!C23+TONTFEV!C23+TONTMARS!C23+TONTAVRIL!C23+TONTMAI!C23+TONTJUIN!C23+TONTJUIL2021!C23+TONTAOUT2021!C23+TONTSEPT2021!C23 -> 300000 | D23: =TONTJUIL!D23+TONTAOUT!D23+TONTSEPT!D23+TONTOCT!D23+TONTNOV!D23+TONTDEC!D23+TONTFEV!D23+TONTMARS!D23+TONTAVRIL!D23+TONTMAI!D23+TONTJUIN!D23+TONTJUIL2021!D23+TONTAOUT2021!D23+TONTSEPT2021!D23 -> 0 | E23: =TONTJUIL!F23+TONTAOUT!F23+TONTSEPT!F23+TONTOCT!F23+TONTNOV!F23+TONTDEC!F23+TONTFEV!F23+TONTMARS!F23+TONTAVRIL!F23+TONTMAI!F23+TONTJUIN!F23+TONTJUIL2021!F23+TONTAOUT2021!F23+TONTSEPT2021!F23 -> 0 | F23: =TONTJUIL!G23+TONTAOUT!G23+TONTSEPT!G23+TONTOCT!G23+TONTNOV!G23+TONTDEC!G23+TONTFEV!G23+TONTMARS!G23+TONTAVRIL!G23+TONTMAI!G23+TONTJUIN!G23+TONTJUIL2021!G23+TONTAOUT2021!G23+TONTSEPT2021!G23 -> 0 | G23: =TONTJUIL!J23+TONTAOUT!J23+TONTSEPT!J23+TONTOCT!J23+TONTNOV!J23+TONTDEC!J23+TONTFEV!J23+TONTMARS!J23+TONTAVRIL!J23+TONTMAI!J23+TONTJUIN!J23+TONTJUIL2021!J23+TONTAOUT2021!J23+TONTSEPT2021!J23 -> 0 | H23: =TONTJUIL!K23+TONTAOUT!K23+TONTSEPT!K23+TONTOCT!K23+TONTNOV!K23+TONTDEC!K23+TONTFEV!K23+TONTMARS!K23+TONTAVRIL!K23+TONTMAI!K23+TONTJUIN!K23+TONTJUIL2021!K23+TONTAOUT2021!K23+TONTSEPT2021!K23 -> 0 | I23: =TONTJUIL!O23+TONTAOUT!O23+TONTSEPT!O23+TONTOCT!O23+TONTNOV!O23+TONTDEC!O23+TONTFEV!O23+TONTMARS!O23+TONTAVRIL!O23+TONTMAI!O23+TONTJUIN!O23+TONTJUIL2021!O23+TONTAOUT2021!O23+TONTSEPT2021!O23 -> 1125000 | J23: =TONTJUIL!P23+TONTAOUT!P23+TONTSEPT!P23+TONTOCT!P23+TONTNOV!P23+TONTDEC!P23+TONTFEV!P23+TONTMARS!P23+TONTAVRIL!P23+TONTMAI!P23+TONTJUIN!P23+TONTJUIL2021!P23+TONTAOUT2021!P23+TONTSEPT2021!P23 -> 75000 | K23: 44122 | L23: =IF(I23=0,0,(J23-75000)) -> 0
A24: AS201647 | B24: =VLOOKUP(A24,[1]LISTADHERENT!A$5:H$60,3,0) -> YOUMBI EMMANUEL | C24: =TONTJUIL!C24+TONTAOUT!C24+TONTSEPT!C24+TONTOCT!C24+TONTNOV!C24+TONTDEC!C24+TONTFEV!C24+TONTMARS!C24+TONTAVRIL!C24+TONTMAI!C24+TONTJUIN!C24+TONTJUIL2021!C24+TONTAOUT2021!C24+TONTSEPT2021!C24 -> 300000 | D24: =TONTJUIL!D24+TONTAOUT!D24+TONTSEPT!D24+TONTOCT!D24+TONTNOV!D24+TONTDEC!D24+TONTFEV!D24+TONTMARS!D24+TONTAVRIL!D24+TONTMAI!D24+TONTJUIN!D24+TONTJUIL2021!D24+TONTAOUT2021!D24+TONTSEPT2021!D24 -> 0 | E24: =TONTJUIL!F24+TONTAOUT!F24+TONTSEPT!F24+TONTOCT!F24+TONTNOV!F24+TONTDEC!F24+TONTFEV!F24+TONTMARS!F24+TONTAVRIL!F24+TONTMAI!F24+TONTJUIN!F24+TONTJUIL2021!F24+TONTAOUT2021!F24+TONTSEPT2021!F24 -> 0 | F24: =TONTJUIL!G24+TONTAOUT!G24+TONTSEPT!G24+TONTOCT!G24+TONTNOV!G24+TONTDEC!G24+TONTFEV!G24+TONTMARS!G24+TONTAVRIL!G24+TONTMAI!G24+TONTJUIN!G24+TONTJUIL2021!G24+TONTAOUT2021!G24+TONTSEPT2021!G24 -> 0 | G24: =TONTJUIL!J24+TONTAOUT!J24+TONTSEPT!J24+TONTOCT!J24+TONTNOV!J24+TONTDEC!J24+TONTFEV!J24+TONTMARS!J24+TONTAVRIL!J24+TONTMAI!J24+TONTJUIN!J24+TONTJUIL2021!J24+TONTAOUT2021!J24+TONTSEPT2021!J24 -> 0 | H24: =TONTJUIL!K24+TONTAOUT!K24+TONTSEPT!K24+TONTOCT!K24+TONTNOV!K24+TONTDEC!K24+TONTFEV!K24+TONTMARS!K24+TONTAVRIL!K24+TONTMAI!K24+TONTJUIN!K24+TONTJUIL2021!K24+TONTAOUT2021!K24+TONTSEPT2021!K24 -> 0 | I24: =TONTJUIL!O24+TONTAOUT!O24+TONTSEPT!O24+TONTOCT!O24+TONTNOV!O24+TONTDEC!O24+TONTFEV!O24+TONTMARS!O24+TONTAVRIL!O24+TONTMAI!O24+TONTJUIN!O24+TONTJUIL2021!O24+TONTAOUT2021!O24+TONTSEPT2021!O24 -> 0 | J24: =TONTJUIL!P24+TONTAOUT!P24+TONTSEPT!P24+TONTOCT!P24+TONTNOV!P24+TONTDEC!P24+TONTFEV!P24+TONTMARS!P24+TONTAVRIL!P24+TONTMAI!P24+TONTJUIN!P24+TONTJUIL2021!P24+TONTAOUT2021!P24+TONTSEPT2021!P24 -> 0 | L24: =IF(I24=0,0,(J24-75000)) -> 0
A26: TOTAL | C26: =SUM(C6:C24) -> 5486500 | D26: =SUM(D6:D24) -> 0 | E26: =SUM(E6:E24) -> 1452000 | F26: =SUM(F6:F24) -> 31000 | G26: =SUM(G6:G24) -> 1483000 | H26: =SUM(H6:H24) -> 1483000 | I26: =SUM(I6:I24) -> 5405000 | J26: =SUM(J6:J24) -> 595000 | L26: =SUM(L6:L24) -> 220000
J29: =J26-(75000*L26) -> -16499405000
J31: =J29-O25 -> -16499405000

Sheet TONTRESUME (2)
A1: ASSOCIATION | B1: ASELBY
A2: ANNEE | B2: 2019/2020
A3: TONTINE | B3: 75000
C4: 44003
A5: MATRICULE | B5: NOM ET PRENOM | C5: MONTANT TONTINE | D5: PENALITE | E5: VENTE PETIT LOT | F5: INTERET PETIT LOT | G5: MONTANT REMBOURSE | H5: MONTANT A REMBOURSER | I5: MONTANT TONTINE LOT PRINCIPAL | J5: INTERET LOT PRINCIPAL | K5: AVALISTE | L5: MISE A PRIX INTERET LOT PRINCIPAL
A6: AS201602 | B6: =VLOOKUP(A6,[1]LISTADHERENT!A$5:H$60,3,0) -> BOUTCHOUANG WILLIAM | C6: =TONTJUIL!C6+TONTAOUT!C6+#REF!+TONTOCT!C6+#REF!+#REF!+#REF!+#REF!+#REF!+#REF!+#REF!+#REF! -> #REF! | D6: =TONTJUIL!D6+TONTAOUT!D6+#REF!+TONTOCT!D6+#REF!+#REF!+#REF!+#REF!+#REF!+#REF!+#REF!+#REF! -> #REF! | E6: =TONTJUIL!F6+TONTAOUT!F6+#REF!+TONTOCT!F6+#REF!+#REF!+#REF!+#REF!+#REF!+#REF!+#REF!+#REF! -> #REF! | F6: =TONTJUIL!G6+TONTAOUT!G6+#REF!+TONTOCT!G6+#REF!+#REF!+#REF!+#REF!+#REF!+#REF!+#REF!+#REF! -> #REF! | G6: =TONTJUIL!J6+TONTAOUT!J6+#REF!+TONTOCT!J6+#REF!+#REF!+#REF!+#REF!+#REF!+#REF!+#REF!+#REF! -> #REF! | H6: =TONTJUIL!K6+TONTAOUT!K6+#REF!+TONTOCT!K6+#REF!+#REF!+#REF!+#REF!+#REF!+#REF!+#REF!+#REF! -> #REF! | I6: =TONTJUIL!O6+TONTAOUT!O6+#REF!+TONTOCT!O6+#REF!+#REF!+#REF!+#REF!+#REF!+#REF!+#REF!+#REF! -> #REF! | J6: =TONTJUIL!P6+TONTAOUT!P6+#REF!+TONTOCT!P6+#REF!+#REF!+#REF!+#REF!+#REF!+#REF!+#REF!+#REF! -> #REF! | K6: 43968 | L6: 75000 | M6: =J6-L6 -> #REF!
A7: AS201604 | B7: =VLOOKUP(A7,[1]LISTADHERENT!A$5:H$60,3,0) -> DJOMO JEAN PAUL | C7: =TONTJUIL!C8+TONTAOUT!C8+#REF!+TONTOCT!C8+#REF!+#REF!+#REF!+#REF!+#REF!+#REF!+#REF!+#REF! -> #REF! | D7: =TONTJUIL!D8+TONTAOUT!D8+#REF!+TONTOCT!D8+#REF!+#REF!+#REF!+#REF!+#REF!+#REF!+#REF!+#REF! -> #REF! | E7: =TONTJUIL!F8+TONTAOUT!F8+#REF!+TONTOCT!F8+#REF!+#REF!+#REF!+#REF!+#REF!+#REF!+#REF!+#REF! -> #REF! | F7: =TONTJUIL!G8+TONTAOUT!G8+#REF!+TONTOCT!G8+#REF!+#REF!+#REF!+#REF!+#REF!+#REF!+#REF!+#REF! -> #REF! | G7: =TONTJUIL!J8+TONTAOUT!J8+#REF!+TONTOCT!J8+#REF!+#REF!+#REF!+#REF!+#REF!+#REF!+#REF!+#REF! -> #REF! | H7: =TONTJUIL!K8+TONTAOUT!K8+#REF!+TONTOCT!K8+#REF!+#REF!+#REF!+#REF!+#REF!+#REF!+#REF!+#REF! -> #REF! | I7: =TONTJUIL!O8+TONTAOUT!O8+#REF!+TONTOCT!O8+#REF!+#REF!+#REF!+#REF!+#REF!+#REF!+#REF!+#REF! -> #REF! | J7: =TONTJUIL!P8+TONTAOUT!P8+#REF!+TONTOCT!P8+#REF!+#REF!+#REF!+#REF!+#REF!+#REF!+#REF!+#REF! -> #REF! | K7: 43758 | L7: 75000 | M7: =J7-L7 -> #REF!
A8: AS201605 | B8: =VLOOKUP(A8,[1]LISTADHERENT!A$5:H$60,3,0) -> DJOUKWE NANGUEN GUY BLAISE | C8: =TONTJUIL!C9+TONTAOUT!C9+#REF!+TONTOCT!C9+#REF!+#REF!+#REF!+#REF!+#REF!+#REF!+#REF!+#REF! -> #REF! | D8: =TONTJUIL!D9+TONTAOUT!D9+#REF!+TONTOCT!D9+#REF!+#REF!+#REF!+#REF!+#REF!+#REF!+#REF!+#REF! -> #REF! | E8: =TONTJUIL!F9+TONTAOUT!F9+#REF!+TONTOCT!F9+#REF!+#REF!+#REF!+#REF!+#REF!+#REF!+#REF!+#REF! -> #REF! | F8: =TONTJUIL!G9+TONTAOUT!G9+#REF!+TONTOCT!G9+#REF!+#REF!+#REF!+#REF!+#REF!+#REF!+#REF!+#REF! -> #REF! | G8: =TONTJUIL!J9+TONTAOUT!J9+#REF!+TONTOCT!J9+#REF!+#REF!+#REF!+#REF!+#REF!+#REF!+#REF!+#REF! -> #REF! | H8: =TONTJUIL!K9+TONTAOUT!K9+#REF!+TONTOCT!K9+#REF!+#REF!+#REF!+#REF!+#REF!+#REF!+#REF!+#REF! -> #REF! | I8: =TONTJUIL!O9+TONTAOUT!O9+#REF!+TONTOCT!O9+#REF!+#REF!+#REF!+#REF!+#REF!+#REF!+#REF!+#REF! -> #REF! | J8: =TONTJUIL!P9+TONTAOUT!P9+#REF!+TONTOCT!P9+#REF!+#REF!+#REF!+#REF!+#REF!+#REF!+#REF!+#REF! -> #REF! | K8: 43912 | L8: 75000 | M8: =J8-L8 -> #REF!
A9: AS201610 | B9: =VLOOKUP(A9,[1]LISTADHERENT!A$5:H$60,3,0) -> FOTSO THOMAS | C9: =TONTJUIL!#REF!+TONTAOUT!#REF!+#REF!+TONTOCT!#REF!+#REF!+#REF!+#REF!+#REF!+#REF!+#REF!+#REF!+#REF! -> #REF! | D9: =TONTJUIL!#REF!+TONTAOUT!#REF!+#REF!+TONTOCT!#REF!+#REF!+#REF!+#REF!+#REF!+#REF!+#REF!+#REF!+#REF! -> #REF! | E9: =TONTJUIL!#REF!+TONTAOUT!#REF!+#REF!+TONTOCT!#REF!+#REF!+#REF!+#REF!+#REF!+#REF!+#REF!+#REF!+#REF! -> #REF! | F9: =TONTJUIL!#REF!+TONTAOUT!#REF!+#REF!+TONTOCT!#REF!+#REF!+#REF!+#REF!+#REF!+#REF!+#REF!+#REF!+#REF! -> #REF! | G9: =TONTJUIL!#REF!+TONTAOUT!#REF!+#REF!+TONTOCT!#REF!+#REF!+#REF!+#REF!+#REF!+#REF!+#REF!+#REF!+#REF! -> #REF! | H9: =TONTJUIL!#REF!+TONTAOUT!#REF!+#REF!+TONTOCT!#REF!+#REF!+#REF!+#REF!+#REF!+#REF!+#REF!+#REF!+#REF! -> #REF! | I9: =TONTJUIL!#REF!+TONTAOUT!#REF!+#REF!+TONTOCT!#REF!+#REF!+#REF!+#REF!+#REF!+#REF!+#REF!+#REF!+#REF! -> #REF! | J9: =TONTJUIL!#REF!+TONTAOUT!#REF!+#REF!+TONTOCT!#REF!+#REF!+#REF!+#REF!+#REF!+#REF!+#REF!+#REF!+#REF! -> #REF! | K9: 43358 | L9: 75000 | M9: =J9-L9 -> #REF!
A10: AS201613 | B10: =VLOOKUP(A10,[1]LISTADHERENT!A$5:H$60,3,0) -> HOTCHO BENJAMIN | C10: =TONTJUIL!C10+TONTAOUT!C10+#REF!+TONTOCT!C10+#REF!+#REF!+#REF!+#REF!+#REF!+#REF!+#REF!+#REF! -> #REF! | D10: =TONTJUIL!D10+TONTAOUT!D10+#REF!+TONTOCT!D10+#REF!+#REF!+#REF!+#REF!+#REF!+#REF!+#REF!+#REF! -> #REF! | E10: =TONTJUIL!F10+TONTAOUT!F10+#REF!+TONTOCT!F10+#REF!+#REF!+#REF!+#REF!+#REF!+#REF!+#REF!+#REF! -> #REF! | F10: =TONTJUIL!G10+TONTAOUT!G10+#REF!+TONTOCT!G10+#REF!+#REF!+#REF!+#REF!+#REF!+#REF!+#REF!+#REF! -> #REF! | G10: =TONTJUIL!J10+TONTAOUT!J10+#REF!+TONTOCT!J10+#REF!+#REF!+#REF!+#REF!+#REF!+#REF!+#REF!+#REF! -> #REF! | H10: =TONTJUIL!K10+TONTAOUT!K10+#REF!+TONTOCT!K10+#REF!+#REF!+#REF!+#REF!+#REF!+#REF!+#REF!+#REF! -> #REF! | I10: =TONTJUIL!O10+TONTAOUT!O10+#REF!+TONTOCT!O10+#REF!+#REF!+#REF!+#REF!+#REF!+#REF!+#REF!+#REF! -> #REF! | J10: =TONTJUIL!P10+TONTAOUT!P10+#REF!+TONTOCT!P10+#REF!+#REF!+#REF!+#REF!+#REF!+#REF!+#REF!+#REF! -> #REF! | K10: 43849 | L10: 75000 | M10: =J10-L10 -> #REF!
A11: AS201611 | B11: =VLOOKUP(A11,[1]LISTADHERENT!A$5:H$60,3,0) -> HENGUE PAUL OMER | C11: =TONTJUIL!C11+TONTAOUT!C11+#REF!+TONTOCT!C11+#REF!+#REF!+#REF!+#REF!+#REF!+#REF!+#REF!+#REF! -> #REF! | D11: =TONTJUIL!D11+TONTAOUT!D11+#REF!+TONTOCT!D11+#REF!+#REF!+#REF!+#REF!+#REF!+#REF!+#REF!+#REF! -> #REF! | E11: =TONTJUIL!F11+TONTAOUT!F11+#REF!+TONTOCT!F11+#REF!+#REF!+#REF!+#REF!+#REF!+#REF!+#REF!+#REF! -> #REF! | F11: =TONTJUIL!G11+TONTAOUT!G11+#REF!+TONTOCT!G11+#REF!+#REF!+#REF!+#REF!+#REF!+#REF!+#REF!+#REF! -> #REF! | G11: =TONTJUIL!J11+TONTAOUT!J11+#REF!+TONTOCT!J11+#REF!+#REF!+#REF!+#REF!+#REF!+#REF!+#REF!+#REF! -> #REF! | H11: =TONTJUIL!K11+TONTAOUT!K11+#REF!+TONTOCT!K11+#REF!+#REF!+#REF!+#REF!+#REF!+#REF!+#REF!+#REF! -> #REF! | I11: =TONTJUIL!O11+TONTAOUT!O11+#REF!+TONTOCT!O11+#REF!+#REF!+#REF!+#REF!+#REF!+#REF!+#REF!+#REF! -> #REF! | J11: =TONTJUIL!P11+TONTAOUT!P11+#REF!+TONTOCT!P11+#REF!+#REF!+#REF!+#REF!+#REF!+#REF!+#REF!+#REF! -> #REF! | K11: 43877 | L11: 75000 | M11: =J11-L11 -> #REF!
A12: AS201618 | B12: =VLOOKUP(A12,[1]LISTADHERENT!A$5:H$60,3,0) -> KOUAMO VICTOR PEGUY | C12: =TONTJUIL!#REF!+TONTAOUT!#REF!+#REF!+TONTOCT!#REF!+#REF!+#REF!+#REF!+#REF!+#REF!+#REF!+#REF!+#REF! -> #REF! | D12: =TONTJUIL!#REF!+TONTAOUT!#REF!+#REF!+TONTOCT!#REF!+#REF!+#REF!+#REF!+#REF!+#REF!+#REF!+#REF!+#REF! -> #REF! | E12: =TONTJUIL!#REF!+TONTAOUT!#REF!+#REF!+TONTOCT!#REF!+#REF!+#REF!+#REF!+#REF!+#REF!+#REF!+#REF!+#REF! -> #REF! | F12: =TONTJUIL!#REF!+TONTAOUT!#REF!+#REF!+TONTOCT!#REF!+#REF!+#REF!+#REF!+#REF!+#REF!+#REF!+#REF!+#REF! -> #REF! | G12: =TONTJUIL!#REF!+TONTAOUT!#REF!+#REF!+TONTOCT!#REF!+#REF!+#REF!+#REF!+#REF!+#REF!+#REF!+#REF!+#REF! -> #REF! | H12: =TONTJUIL!#REF!+TONTAOUT!#REF!+#REF!+TONTOCT!#REF!+#REF!+#REF!+#REF!+#REF!+#REF!+#REF!+#REF!+#REF! -> #REF! | I12: =TONTJUIL!#REF!+TONTAOUT!#REF!+#REF!+TONTOCT!#REF!+#REF!+#REF!+#REF!+#REF!+#REF!+#REF!+#REF!+#REF! -> #REF! | J12: =TONTJUIL!#REF!+TONTAOUT!#REF!+#REF!+TONTOCT!#REF!+#REF!+#REF!+#REF!+#REF!+#REF!+#REF!+#REF!+#REF! -> #REF! | K12: 43667 | L12: 75000 | M12: =J12-L12 -> #REF!
A13: AS201618 | B13: =VLOOKUP(A13,[1]LISTADHERENT!A$5:H$60,3,0) -> KOUAMO VICTOR PEGUY | C13: =TONTJUIL!#REF!+TONTAOUT!#REF!+#REF!+TONTOCT!#REF!+#REF!+#REF!+#REF!+#REF!+#REF!+#REF!+#REF!+#REF! -> #REF! | D13: =TONTJUIL!#REF!+TONTAOUT!#REF!+#REF!+TONTOCT!#REF!+#REF!+#REF!+#REF!+#REF!+#REF!+#REF!+#REF!+#REF! -> #REF! | E13: =TONTJUIL!#REF!+TONTAOUT!#REF!+#REF!+TONTOCT!#REF!+#REF!+#REF!+#REF!+#REF!+#REF!+#REF!+#REF!+#REF! -> #REF! | F13: =TONTJUIL!#REF!+TONTAOUT!#REF!+#REF!+TONTOCT!#REF!+#REF!+#REF!+#REF!+#REF!+#REF!+#REF!+#REF!+#REF! -> #REF! | G13: =TONTJUIL!#REF!+TONTAOUT!#REF!+#REF!+TONTOCT!#REF!+#REF!+#REF!+#REF!+#REF!+#REF!+#REF!+#REF!+#REF! -> #REF! | H13: =TONTJUIL!#REF!+TONTAOUT!#REF!+#REF!+TONTOCT!#REF!+#REF!+#REF!+#REF!+#REF!+#REF!+#REF!+#REF!+#REF! -> #REF! | I13: =TONTJUIL!#REF!+TONTAOUT!#REF!+#REF!+TONTOCT!#REF!+#REF!+#REF!+#REF!+#REF!+#REF!+#REF!+#REF!+#REF! -> #REF! | J13: =TONTJUIL!#REF!+TONTAOUT!#REF!+#REF!+TONTOCT!#REF!+#REF!+#REF!+#REF!+#REF!+#REF!+#REF!+#REF!+#REF! -> #REF! | L13: 75000 | M13: 0
A14: AS201619 | B14: =VLOOKUP(A14,[1]LISTADHERENT!A$5:H$60,3,0) -> KOUATCHO MESSACK | C14: =TONTJUIL!C12+TONTAOUT!C12+#REF!+TONTOCT!C12+#REF!+#REF!+#REF!+#REF!+#REF!+#REF!+#REF!+#REF! -> #REF! | D14: =TONTJUIL!D12+TONTAOUT!D12+#REF!+TONTOCT!D12+#REF!+#REF!+#REF!+#REF!+#REF!+#REF!+#REF!+#REF! -> #REF! | E14: =TONTJUIL!F12+TONTAOUT!F12+#REF!+TONTOCT!F12+#REF!+#REF!+#REF!+#REF!+#REF!+#REF!+#REF!+#REF! -> #REF! | F14: =TONTJUIL!G12+TONTAOUT!G12+#REF!+TONTOCT!G12+#REF!+#REF!+#REF!+#REF!+#REF!+#REF!+#REF!+#REF! -> #REF! | G14: =TONTJUIL!J12+TONTAOUT!J12+#REF!+TONTOCT!J12+#REF!+#REF!+#REF!+#REF!+#REF!+#REF!+#REF!+#REF! -> #REF! | H14: =TONTJUIL!K12+TONTAOUT!K12+#REF!+TONTOCT!K12+#REF!+#REF!+#REF!+#REF!+#REF!+#REF!+#REF!+#REF! -> #REF! | I14: =TONTJUIL!O12+TONTAOUT!O12+#REF!+TONTOCT!O12+#REF!+#REF!+#REF!+#REF!+#REF!+#REF!+#REF!+#REF! -> #REF! | J14: =TONTJUIL!P12+TONTAOUT!P12+#REF!+TONTOCT!P12+#REF!+#REF!+#REF!+#REF!+#REF!+#REF!+#REF!+#REF! -> #REF! | K14: 43358 | L14: 75000 | M14: =J14-L14 -> #REF!
A15: AS201621 | B15: =VLOOKUP(A15,[1]LISTADHERENT!A$5:H$60,3,0) -> NANKAM APPOLINAIRE | C15: =TONTJUIL!C13+TONTAOUT!C13+#REF!+TONTOCT!C13+#REF!+#REF!+#REF!+#REF!+#REF!+#REF!+#REF!+#REF! -> #REF! | D15: =TONTJUIL!D13+TONTAOUT!D13+#REF!+TONTOCT!D13+#REF!+#REF!+#REF!+#REF!+#REF!+#REF!+#REF!+#REF! -> #REF! | E15: =TONTJUIL!F13+TONTAOUT!F13+#REF!+TONTOCT!F13+#REF!+#REF!+#REF!+#REF!+#REF!+#REF!+#REF!+#REF! -> #REF! | F15: =TONTJUIL!G13+TONTAOUT!G13+#REF!+TONTOCT!G13+#REF!+#REF!+#REF!+#REF!+#REF!+#REF!+#REF!+#REF! -> #REF! | G15: =TONTJUIL!J13+TONTAOUT!J13+#REF!+TONTOCT!J13+#REF!+#REF!+#REF!+#REF!+#REF!+#REF!+#REF!+#REF! -> #REF! | H15: =TONTJUIL!K13+TONTAOUT!K13+#REF!+TONTOCT!K13+#REF!+#REF!+#REF!+#REF!+#REF!+#REF!+#REF!+#REF! -> #REF! | I15: =TONTJUIL!O13+TONTAOUT!O13+#REF!+TONTOCT!O13+#REF!+#REF!+#REF!+#REF!+#REF!+#REF!+#REF!+#REF! -> #REF! | J15: =TONTJUIL!P13+TONTAOUT!P13+#REF!+TONTOCT!P13+#REF!+#REF!+#REF!+#REF!+#REF!+#REF!+#REF!+#REF! -> #REF! | K15: 44003 | L15: 75000 | M15: =J15-L15 -> #REF!
A16: AS201649 | B16: =VLOOKUP(A16,[1]LISTADHERENT!A$5:H$60,3,0) -> MBOGNING TUGMA GUY | C16: =TONTJUIL!C14+TONTAOUT!C14+#REF!+TONTOCT!C14+#REF!+#REF!+#REF!+#REF!+#REF!+#REF!+#REF!+#REF! -> #REF! | D16: =TONTJUIL!D14+TONTAOUT!D14+#REF!+TONTOCT!D14+#REF!+#REF!+#REF!+#REF!+#REF!+#REF!+#REF!+#REF! -> #REF! | E16: =TONTJUIL!F14+TONTAOUT!F14+#REF!+TONTOCT!F14+#REF!+#REF!+#REF!+#REF!+#REF!+#REF!+#REF!+#REF! -> #REF! | F16: =TONTJUIL!G14+TONTAOUT!G14+#REF!+TONTOCT!G14+#REF!+#REF!+#REF!+#REF!+#REF!+#REF!+#REF!+#REF! -> #REF! | G16: =TONTJUIL!J14+TONTAOUT!J14+#REF!+TONTOCT!J14+#REF!+#REF!+#REF!+#REF!+#REF!+#REF!+#REF!+#REF! -> #REF! | H16: =TONTJUIL!K14+TONTAOUT!K14+#REF!+TONTOCT!K14+#REF!+#REF!+#REF!+#REF!+#REF!+#REF!+#REF!+#REF! -> #REF! | I16: =TONTJUIL!O14+TONTAOUT!O14+#REF!+TONTOCT!O14+#REF!+#REF!+#REF!+#REF!+#REF!+#REF!+#REF!+#REF! -> #REF! | J16: =TONTJUIL!P14+TONTAOUT!P14+#REF!+TONTOCT!P14+#REF!+#REF!+#REF!+#REF!+#REF!+#REF!+#REF!+#REF! -> #REF! | K16: 43695 | L16: 75000 | M16: =J16-L16 -> #REF!
A17: AS201649 | B17: =VLOOKUP(A17,[1]LISTADHERENT!A$5:H$60,3,0) -> MBOGNING TUGMA GUY | C17: =TONTJUIL!C15+TONTAOUT!C15+#REF!+TONTOCT!C15+#REF!+#REF!+#REF!+#REF!+#REF!+#REF!+#REF!+#REF! -> #REF! | D17: =TONTJUIL!D15+TONTAOUT!D15+#REF!+TONTOCT!D15+#REF!+#REF!+#REF!+#REF!+#REF!+#REF!+#REF!+#REF! -> #REF! | E17: =TONTJUIL!F15+TONTAOUT!F15+#REF!+TONTOCT!F15+#REF!+#REF!+#REF!+#REF!+#REF!+#REF!+#REF!+#REF! -> #REF! | F17: =TONTJUIL!G15+TONTAOUT!G15+#REF!+TONTOCT!G15+#REF!+#REF!+#REF!+#REF!+#REF!+#REF!+#REF!+#REF! -> #REF! | G17: =TONTJUIL!J15+TONTAOUT!J15+#REF!+TONTOCT!J15+#REF!+#REF!+#REF!+#REF!+#REF!+#REF!+#REF!+#REF! -> #REF! | H17: =TONTJUIL!K15+TONTAOUT!K15+#REF!+TONTOCT!K15+#REF!+#REF!+#REF!+#REF!+#REF!+#REF!+#REF!+#REF! -> #REF! | I17: =TONTJUIL!O15+TONTAOUT!O15+#REF!+TONTOCT!O15+#REF!+#REF!+#REF!+#REF!+#REF!+#REF!+#REF!+#REF! -> #REF! | J17: =TONTJUIL!P15+TONTAOUT!P15+#REF!+TONTOCT!P15+#REF!+#REF!+#REF!+#REF!+#REF!+#REF!+#REF!+#REF! -> #REF! | K17: 43814 | L17: 75000 | M17: =J17-L17 -> #REF!
A18: AS201649 | B18: =VLOOKUP(A18,[1]LISTADHERENT!A$5:H$60,3,0) -> MBOGNING TUGMA GUY | C18: =TONTJUIL!C16+TONTAOUT!C16+#REF!+TONTOCT!C16+#REF!+#REF!+#REF!+#REF!+#REF!+#REF!+#REF!+#REF! -> #REF! | D18: =TONTJUIL!D16+TONTAOUT!D16+#REF!+TONTOCT!D16+#REF!+#REF!+#REF!+#REF!+#REF!+#REF!+#REF!+#REF! -> #REF! | E18: =TONTJUIL!F16+TONTAOUT!F16+#REF!+TONTOCT!F16+#REF!+#REF!+#REF!+#REF!+#REF!+#REF!+#REF!+#REF! -> #REF! | F18: =TONTJUIL!G16+TONTAOUT!G16+#REF!+TONTOCT!G16+#REF!+#REF!+#REF!+#REF!+#REF!+#REF!+#REF!+#REF! -> #REF! | G18: =TONTJUIL!J16+TONTAOUT!J16+#REF!+TONTOCT!J16+#REF!+#REF!+#REF!+#REF!+#REF!+#REF!+#REF!+#REF! -> #REF! | H18: =TONTJUIL!K16+TONTAOUT!K16+#REF!+TONTOCT!K16+#REF!+#REF!+#REF!+#REF!+#REF!+#REF!+#REF!+#REF! -> #REF! | I18: =TONTJUIL!O16+TONTAOUT!O16+#REF!+TONTOCT!O16+#REF!+#REF!+#REF!+#REF!+#REF!+#REF!+#REF!+#REF! -> #REF! | J18: =TONTJUIL!P16+TONTAOUT!P16+#REF!+TONTOCT!P16+#REF!+#REF!+#REF!+#REF!+#REF!+#REF!+#REF!+#REF! -> #REF! | K18: 43940 | L18: 75000 | M18: =J18-L18 -> #REF!
A19: AS201626 | B19: =VLOOKUP(A19,[1]LISTADHERENT!A$5:H$60,3,0) -> NGUIEMEGNI MATHIEU BLAISE | C19: =TONTJUIL!C17+TONTAOUT!C17+#REF!+TONTOCT!C17+#REF!+#REF!+#REF!+#REF!+#REF!+#REF!+#REF!+#REF! -> #REF! | D19: =TONTJUIL!D17+TONTAOUT!D17+#REF!+TONTOCT!D17+#REF!+#REF!+#REF!+#REF!+#REF!+#REF!+#REF!+#REF! -> #REF! | E19: =TONTJUIL!F17+TONTAOUT!F17+#REF!+TONTOCT!F17+#REF!+#REF!+#REF!+#REF!+#REF!+#REF!+#REF!+#REF! -> #REF! | F19: =TONTJUIL!G17+TONTAOUT!G17+#REF!+TONTOCT!G17+#REF!+#REF!+#REF!+#REF!+#REF!+#REF!+#REF!+#REF! -> #REF! | G19: =TONTJUIL!J17+TONTAOUT!J17+#REF!+TONTOCT!J17+#REF!+#REF!+#REF!+#REF!+#REF!+#REF!+#REF!+#REF! -> #REF! | H19: =TONTJUIL!K17+TONTAOUT!K17+#REF!+TONTOCT!K17+#REF!+#REF!+#REF!+#REF!+#REF!+#REF!+#REF!+#REF! -> #REF! | I19: =TONTJUIL!O17+TONTAOUT!O17+#REF!+TONTOCT!O17+#REF!+#REF!+#REF!+#REF!+#REF!+#REF!+#REF!+#REF! -> #REF! | J19: =TONTJUIL!P17+TONTAOUT!P17+#REF!+TONTOCT!P17+#REF!+#REF!+#REF!+#REF!+#REF!+#REF!+#REF!+#REF! -> #REF! | K19: 43758 | L19: 75000 | M19: =J19-L19 -> #REF!
A20: AS201626 | B20: =VLOOKUP(A20,[1]LISTADHERENT!A$5:H$60,3,0) -> NGUIEMEGNI MATHIEU BLAISE | C20: =TONTJUIL!C18+TONTAOUT!C18+#REF!+TONTOCT!C18+#REF!+#REF!+#REF!+#REF!+#REF!+#REF!+#REF!+#REF! -> #REF! | D20: =TONTJUIL!D18+TONTAOUT!D18+#REF!+TONTOCT!D18+#REF!+#REF!+#REF!+#REF!+#REF!+#REF!+#REF!+#REF! -> #REF! | E20: =TONTJUIL!F18+TONTAOUT!F18+#REF!+TONTOCT!F18+#REF!+#REF!+#REF!+#REF!+#REF!+#REF!+#REF!+#REF! -> #REF! | F20: =TONTJUIL!G18+TONTAOUT!G18+#REF!+TONTOCT!G18+#REF!+#REF!+#REF!+#REF!+#REF!+#REF!+#REF!+#REF! -> #REF! | G20: =TONTJUIL!J18+TONTAOUT!J18+#REF!+TONTOCT!J18+#REF!+#REF!+#REF!+#REF!+#REF!+#REF!+#REF!+#REF! -> #REF! | H20: =TONTJUIL!K18+TONTAOUT!K18+#REF!+TONTOCT!K18+#REF!+#REF!+#REF!+#REF!+#REF!+#REF!+#REF!+#REF! -> #REF! | I20: =TONTJUIL!O18+TONTAOUT!O18+#REF!+TONTOCT!O18+#REF!+#REF!+#REF!+#REF!+#REF!+#REF!+#REF!+#REF! -> #REF! | J20: =TONTJUIL!P18+TONTAOUT!P18+#REF!+TONTOCT!P18+#REF!+#REF!+#REF!+#REF!+#REF!+#REF!+#REF!+#REF! -> #REF! | K20: 43849 | L20: 75000 | M20: =J20-L20 -> #REF!
A21: AS201628 | B21: =VLOOKUP(A21,[1]LISTADHERENT!A$5:H$60,3,0) -> NKAMGANG JUSTIN DEJOLIE | C21: =TONTJUIL!C19+TONTAOUT!C19+#REF!+TONTOCT!C19+#REF!+#REF!+#REF!+#REF!+#REF!+#REF!+#REF!+#REF! -> #REF! | D21: =TONTJUIL!D19+TONTAOUT!D19+#REF!+TONTOCT!D19+#REF!+#REF!+#REF!+#REF!+#REF!+#REF!+#REF!+#REF! -> #REF! | E21: =TONTJUIL!F19+TONTAOUT!F19+#REF!+TONTOCT!F19+#REF!+#REF!+#REF!+#REF!+#REF!+#REF!+#REF!+#REF! -> #REF! | F21: =TONTJUIL!G19+TONTAOUT!G19+#REF!+TONTOCT!G19+#REF!+#REF!+#REF!+#REF!+#REF!+#REF!+#REF!+#REF! -> #REF! | G21: =TONTJUIL!J19+TONTAOUT!J19+#REF!+TONTOCT!J19+#REF!+#REF!+#REF!+#REF!+#REF!+#REF!+#REF!+#REF! -> #REF! | H21: =TONTJUIL!K19+TONTAOUT!K19+#REF!+TONTOCT!K19+#REF!+#REF!+#REF!+#REF!+#REF!+#REF!+#REF!+#REF! -> #REF! | I21: =TONTJUIL!O19+TONTAOUT!O19+#REF!+TONTOCT!O19+#REF!+#REF!+#REF!+#REF!+#REF!+#REF!+#REF!+#REF! -> #REF! | J21: =TONTJUIL!P19+TONTAOUT!P19+#REF!+TONTOCT!P19+#REF!+#REF!+#REF!+#REF!+#REF!+#REF!+#REF!+#REF! -> #REF! | K21: 43695 | L21: 75000 | M21: =J21-L21 -> #REF!
A22: AS201633 | B22: =VLOOKUP(A22,[1]LISTADHERENT!A$5:H$60,3,0) -> PATEGO NJOSSU GUSTAVE | C22: =TONTJUIL!C20+TONTAOUT!C20+#REF!+TONTOCT!C20+#REF!+#REF!+#REF!+#REF!+#REF!+#REF!+#REF!+#REF! -> #REF! | D22: =TONTJUIL!D20+TONTAOUT!D20+#REF!+TONTOCT!D20+#REF!+#REF!+#REF!+#REF!+#REF!+#REF!+#REF!+#REF! -> #REF! | E22: =TONTJUIL!F20+TONTAOUT!F20+#REF!+TONTOCT!F20+#REF!+#REF!+#REF!+#REF!+#REF!+#REF!+#REF!+#REF! -> #REF! | F22: =TONTJUIL!G20+TONTAOUT!G20+#REF!+TONTOCT!G20+#REF!+#REF!+#REF!+#REF!+#REF!+#REF!+#REF!+#REF! -> #REF! | G22: =TONTJUIL!J20+TONTAOUT!J20+#REF!+TONTOCT!J20+#REF!+#REF!+#REF!+#REF!+#REF!+#REF!+#REF!+#REF! -> #REF! | H22: =TONTJUIL!K20+TONTAOUT!K20+#REF!+TONTOCT!K20+#REF!+#REF!+#REF!+#REF!+#REF!+#REF!+#REF!+#REF! -> #REF! | I22: =TONTJUIL!O20+TONTAOUT!O20+#REF!+TONTOCT!O20+#REF!+#REF!+#REF!+#REF!+#REF!+#REF!+#REF!+#REF! -> #REF! | J22: =TONTJUIL!P20+TONTAOUT!P20+#REF!+TONTOCT!P20+#REF!+#REF!+#REF!+#REF!+#REF!+#REF!+#REF!+#REF! -> #REF! | K22: 43940 | L22: 75000 | M22: =J22-L22 -> #REF!
A23: AS201638 | B23: =VLOOKUP(A23,[1]LISTADHERENT!A$5:H$60,3,0) -> SIMO PIERRE | C23: =TONTJUIL!C21+TONTAOUT!C21+#REF!+TONTOCT!C21+#REF!+#REF!+#REF!+#REF!+#REF!+#REF!+#REF!+#REF! -> #REF! | D23: =TONTJUIL!D21+TONTAOUT!D21+#REF!+TONTOCT!D21+#REF!+#REF!+#REF!+#REF!+#REF!+#REF!+#REF!+#REF! -> #REF! | E23: =TONTJUIL!F21+TONTAOUT!F21+#REF!+TONTOCT!F21+#REF!+#REF!+#REF!+#REF!+#REF!+#REF!+#REF!+#REF! -> #REF! | F23: =TONTJUIL!G21+TONTAOUT!G21+#REF!+TONTOCT!G21+#REF!+#REF!+#REF!+#REF!+#REF!+#REF!+#REF!+#REF! -> #REF! | G23: =TONTJUIL!J21+TONTAOUT!J21+#REF!+TONTOCT!J21+#REF!+#REF!+#REF!+#REF!+#REF!+#REF!+#REF!+#REF! -> #REF! | H23: =TONTJUIL!K21+TONTAOUT!K21+#REF!+TONTOCT!K21+#REF!+#REF!+#REF!+#REF!+#REF!+#REF!+#REF!+#REF! -> #REF! | I23: =TONTJUIL!O21+TONTAOUT!O21+#REF!+TONTOCT!O21+#REF!+#REF!+#REF!+#REF!+#REF!+#REF!+#REF!+#REF! -> #REF! | J23: =TONTJUIL!P21+TONTAOUT!P21+#REF!+TONTOCT!P21+#REF!+#REF!+#REF!+#REF!+#REF!+#REF!+#REF!+#REF! -> #REF! | K23: 43793 | L23: 75000 | M23: =J23-L23 -> #REF!
A24: AS201647 | B24: =VLOOKUP(A24,[1]LISTADHERENT!A$5:H$60,3,0) -> YOUMBI EMMANUEL | C24: =TONTJUIL!C23+TONTAOUT!C23+#REF!+TONTOCT!C23+#REF!+#REF!+#REF!+#REF!+#REF!+#REF!+#REF!+#REF! -> #REF! | D24: =TONTJUIL!D23+TONTAOUT!D23+#REF!+TONTOCT!D23+#REF!+#REF!+#REF!+#REF!+#REF!+#REF!+#REF!+#REF! -> #REF! | E24: =TONTJUIL!F23+TONTAOUT!F23+#REF!+TONTOCT!F23+#REF!+#REF!+#REF!+#REF!+#REF!+#REF!+#REF!+#REF! -> #REF! | F24: =TONTJUIL!G23+TONTAOUT!G23+#REF!+TONTOCT!G23+#REF!+#REF!+#REF!+#REF!+#REF!+#REF!+#REF!+#REF! -> #REF! | G24: =TONTJUIL!J23+TONTAOUT!J23+#REF!+TONTOCT!J23+#REF!+#REF!+#REF!+#REF!+#REF!+#REF!+#REF!+#REF! -> #REF! | H24: =TONTJUIL!K23+TONTAOUT!K23+#REF!+TONTOCT!K23+#REF!+#REF!+#REF!+#REF!+#REF!+#REF!+#REF!+#REF! -> #REF! | I24: =TONTJUIL!O23+TONTAOUT!O23+#REF!+TONTOCT!O23+#REF!+#REF!+#REF!+#REF!+#REF!+#REF!+#REF!+#REF! -> #REF! | J24: =TONTJUIL!P23+TONTAOUT!P23+#REF!+TONTOCT!P23+#REF!+#REF!+#REF!+#REF!+#REF!+#REF!+#REF!+#REF! -> #REF! | K24: 43877 | L24: 75000 | M24: =J24-L24 -> #REF!
A25: AS201647 | B25: =VLOOKUP(A25,[1]LISTADHERENT!A$5:H$60,3,0) -> YOUMBI EMMANUEL | C25: =TONTJUIL!C24+TONTAOUT!C24+#REF!+TONTOCT!C24+#REF!+#REF!+#REF!+#REF!+#REF!+#REF!+#REF!+#REF! -> #REF! | D25: =TONTJUIL!D24+TONTAOUT!D24+#REF!+TONTOCT!D24+#REF!+#REF!+#REF!+#REF!+#REF!+#REF!+#REF!+#REF! -> #REF! | E25: =TONTJUIL!F24+TONTAOUT!F24+#REF!+TONTOCT!F24+#REF!+#REF!+#REF!+#REF!+#REF!+#REF!+#REF!+#REF! -> #REF! | F25: =TONTJUIL!G24+TONTAOUT!G24+#REF!+TONTOCT!G24+#REF!+#REF!+#REF!+#REF!+#REF!+#REF!+#REF!+#REF! -> #REF! | G25: =TONTJUIL!J24+TONTAOUT!J24+#REF!+TONTOCT!J24+#REF!+#REF!+#REF!+#REF!+#REF!+#REF!+#REF!+#REF! -> #REF! | H25: =TONTJUIL!K24+TONTAOUT!K24+#REF!+TONTOCT!K24+#REF!+#REF!+#REF!+#REF!+#REF!+#REF!+#REF!+#REF! -> #REF! | I25: =TONTJUIL!O24+TONTAOUT!O24+#REF!+TONTOCT!O24+#REF!+#REF!+#REF!+#REF!+#REF!+#REF!+#REF!+#REF! -> #REF! | J25: =TONTJUIL!P24+TONTAOUT!P24+#REF!+TONTOCT!P24+#REF!+#REF!+#REF!+#REF!+#REF!+#REF!+#REF!+#REF! -> #REF! | K25: 44003 | L25: 75000 | M25: =J25-L25 -> #REF! | O25: 1000000
M26: =SUM(M6:M25) -> #REF! | O26: =75000*13 -> 975000 | P26: =(O25-O26)*12 -> 300000
A27: TOTAL | C27: =SUM(C6:C25) -> #REF! | D27: =SUM(D6:D25) -> #REF! | E27: =SUM(E6:E25) -> #REF! | F27: =SUM(F6:F25) -> #REF! | G27: =SUM(G6:G25) -> #REF! | H27: =SUM(H6:H25) -> #REF! | I27: =SUM(I6:I25) -> #REF! | J27: =SUM(J6:J25) -> #REF! | L27: =COUNTIFS(J6:J25,"<>0") -> 20 | M27: CRITERE
O28: 656441329
J30: =J27-(75000*L27) -> #REF!
J32: =J30-P26 -> #REF!
