Workbook
Name BANQUE: #REF!
Name BANQUE: #REF!
Name BANQUE: #REF!
Name BANQUE: #REF!
Name BANQUE: #REF!
Name BANQUE: #REF!
Name BANQUE: #REF!
Name BANQUE: #REF!
Name BANQUE: #REF!
Name BANQUE: #REF!
Name BANQUE: #REF!
Name BANQUE: #REF!
Name BANQUE: #REF!
Name BANQUE: #REF!
Name BANQUE: #REF!
Name MODEPAID: [1]Feuil2!$A$1:$A$3
Name MODEVERSEMENT: #REF!
Name MODEVERSEMENT: #REF!
Name MODEVERSEMENT: #REF!
Name MODEVERSEMENT: #REF!
Name MODEVERSEMENT: #REF!
Name MODEVERSEMENT: #REF!
Name MODEVERSEMENT: #REF!
Name MODEVERSEMENT: #REF!
Name MODEVERSEMENT: #REF!
Name MODEVERSEMENT: #REF!
Name MODEVERSEMENT: #REF!
Name MODEVERSEMENT: #REF!
Name MODEVERSEMENT: #REF!
Name MODEVERSEMENT: #REF!
Name MODEVERSEMENT: #REF!
Name MODEVERSEMENTS: MODEVERSEMENT!$A$1:$A$3
Name MODPAID: TONT20000ANNUELLE!$H$5
Name MODPAID: TONT20000ANNUELLEBACKUP!$H$5
Name MODPAID: TONT20000AOUT2017!$H$5
Name MODPAID: TONT20000AVRIL2017!$H$5
Name MODPAID: TONT20000FEV2017!$H$5
Name MODPAID: TONT20000JANV2017!$H$5
Name MODPAID: TONT20000JUIL2017!$H$5
Name MODPAID: TONT20000JUIN2017!$H$5
Name MODPAID: TONT20000MAI2017!$H$5
Name MODPAID: TONT20000MARS2017!$H$5
Name MODPAID: TONT20000NOV2017!$H$5
Name MODPAID: TONT20000OCT2017!$H$5
Name MODPAID: TONT20000SEPT2017!$H$5
Name MODPAID: TONTINVENTFINAOUT2017!#REF!
Name MODPAID: TONT20000DEC2016!$J$5

Sheet LISTADHERENT
A1: ASELBY
A2: LISTE DES ADHERENTS 19 JUN 2016
A4: MLE | B4: NOM ET PRENOM | C4: FONCTION | D4: DATE ADHESION | E4: CONTACT | F4: CONTACT 2 | G4: RESIDENCE | H4: DATE RECEPTION
A5: AS201601 | B5: BAKOP ACHILLE | C5: FONCTIONNAIRE DE POLICE | E5: 677841881 | G5: NKOLBISSON | H5: 42887
A6: AS201602 | B6: BOUTCHOUANG WILLIAM | C6: OPERATEUR ECONOMIQUE | E6: 677704694 | G6: EMANA | H6: 43191
A7: AS201603 | B7: CHINGUE FABRICE | C7: OPERATEUR ECONOMIQUE | E7: 677881912 | G7: SANTA BARBARA | H7: 43466
A8: AS201604 | B8: DJOMO JEAN PAUL | C8: RETRAITE | E8: 677986676 | G8: RUE MANGUIERS | H8: 43132
A9: AS201605 | B9: DJOUKWE NANGUEN GUY BLAISE | C9: PROFESSEUR DES LYCEES TECHNIQUE | E9: 675250451 | G9: RUE MANGUIERS | H9: 43313
A10: AS201606 | B10: DJOSSEU JOSUE | C10: PROFESSEUR DES LYCEES TECHNIQUE | E10: 675250451 | G10: RUE MANGUIERS | H10: 43313
A11: AS201607 | B11: DJOUNKEP SAMUEL | C11: COMPTABLE RETRAITE | E11: 697103557 | G11: BIYEM ASSI LYCEE | H11: 42401
A12: AS201608 | B12: DJUOMBESSY ANTOINE | C12: ANALYSTE CONCEPTEUR SI | E12: 677501239 | F12: 699324095 | G12: MESSASSI | H12: 43647
A13: AS201609 | B13: DONHOU DAVID | C13: MAGISTRAT | E13: 699908065 | G13: TONGOLO | H13: 42979
A14: AS201610 | B14: FOTSO THOMAS | C14: CADRE BANQUE | E14: 677910278 | G14: OYOMABANG | H14: 43344
A15: AS201611 | B15: HENGUE PAUL OMER | C15: SOCIOLOGUE | E15: 694468080 | G15: MESSASSI | H15: 42583
A16: AS201612 | B16: HODIEP JULES | C16: CADRE CNPS | E16: 675291170 | G16: NYOM 2 | H16: 43009
A17: AS201613 | B17: HOTCHO BENJAMIN | C17: COMPTABLE | E17: 699956355 | G17: DAMAS | H17: 42614
A18: AS201614 | B18: KEPHE DAVID | C18: OPERATEUR ECONOMIQUE | E18: 677053815 | G18: MESSASSI | H18: 43374
A19: AS201615 | B19: KEPSEU FRANCIS | C19: OFFICIER DE POLICE RETRAITE | E19: 699528700 | G19: SIMBOCK | H19: 43405
A20: AS201616 | B20: KOUAMOU EMMANUEL | C20: OPERATEUR ECONOMIQUE | E20: 699335584 | G20: MONTEE JOUVENCE | H20: 42795
A21: AS201617 | B21: KOUAMOU MOISE | C21: INGENIEUR E-F | E21: 675836725 | G21: DAMAS | H21: 42370
A22: AS201618 | B22: KOUAMO VICTOR PEGUY | C22: S/OFFICIER SUPERIEUR | E22: 696564847 | G22: MESSASSI | H22: 43617
A23: AS201619 | B23: KOUATCHO MESSACK | C23: INSPECTEUR DE TRAVAIL | E23: 677735778 | G23: SANTA BARBARA | H23: 42644
A24: AS201620 | B24: LOWE JEAN | C24: PROFESSEUR DE LYCEE
A25: AS201621 | B25: NANKAM APPOLINAIRE | C25: ENSEIGNANT | E25: 693055118 | G25: DAMAS | H25: 43678
A26: AS201622 | B26: NDJOMO ETIENNE | C26: COMPTABLE | E26: 677553702 | G26: MONTEE JOUVENCE | H26: 42705
A27: AS201623 | B27: NDOMBOU JEAN CLAUDE | C27: ING AGRONOME RETRAITE | E27: 699358350 | G27: ETOUG EBE | H27: 42767
A28: AS201624 | B28: NGONDIEP CLAUDE | C28: DAS(DIRECTEUR ADMINISTRATEUR SOCIETE) | E28: 675249207 | G28: CITE VERTE | H28: 43070
A29: AS201625 | B29: NGONGANG JEAN THEODORE | C29: CHEF ENTREPRISE | E29: 677766503 | G29: RUE MANGUIERS | H29: 42491
A30: AS201626 | B30: NGUIEMEGNI MATHIEU BLAISE | C30: CADRE CADASTRE | E30: 677068360 | G30: MONATELE | H30: 43101
A31: AS201627 | B31: NJEPDJIO MBOUKAM DELUXE | C31: OPERATEUR ECONOMIQUE | E31: 670909070 | G31: MENDONG | H31: 43586
A32: AS201628 | B32: NKAMGANG JUSTIN DEJOLIE | C32: DELEGUE COMMERCIAL | E32: 676659191 | G32: MENDONG | H32: 43497
A33: AS201629 | B33: NKEPSEU DIEUDONNE | C33: OPERATEUR ECONOMIQUE | E33: 677575366 | G33: ESSOS | H33: 42917
A34: AS201630 | B34: NKEPSEU HENANG RENE | C34: CADRE SONEL RETRAITE | E34: 699843118 | G34: BIYEM ASSI LYCEE | H34: 42522
A35: AS201631 | B35: NTEPDIE TUEMAC MZ | C35: OPERATEUR ECONOMIQUE | E35: 677377251 | G35: MONTEE JOUVENCE | H35: 43282
A36: AS201632 | B36: NTOMBOU ADOLPHE | C36: INGENIEUR | E36: 677867173 | G36: BIYEM ASSI LYCEE | H36: 42461
... A51: AS201647 | B51: YOUMBI EMMANUEL | C51: PROFESSEUR DES UNIVERSITES | E51: 677547311 | G51: MENDONG (GUINNESS) | H51: 42675
A52: AS201648 | B52: ASELBY | C52: ASSOCIATION DES ELITES BANGOU DE YAOUNDE

Sheet TRAVAUXINVENTAIRE
A1: ASSOCIATION | B1: ASELBY
A2: ANNEE | B2: 2016/2017
A3: TONTINE | B3: 20 000
A4: MATRICULE | B4: NOM ET PRENOM | C4: FONDS DE CAISSE | D4: RELIQUAT 2015 | E4: RELIQUAT 2016 | F4: CAPITAL DEPART | G4: REPARTITION INTERET | H4: CAPITAL COMPOSE FIN | I4: CAPITAL TOTAL A PERCEVOIR | J4: RETENUE | K4: CAPITAL A DISTRIBUER | L4: MONTANT EFFECTIVEMENT VERSE | M4: COMPLEMENT FONDS | N4: SANCTION | O4: RETOUR EN CAISSE MUTUELLE | P4: FRAIS FIXE A PRELEVER | Q4: MONTANT VERSE | R4: EPARGNE | S4: FONDS DE ROULEMENT | T4: FRAIS EXCEPTIONNEL | U4: COLLATION | V4: MUTUELLE | W4: TONTINE | X4: EMPRUNT | Y4: INTERET EMPRUNT | Z4: REMBOURSEMENT | AA4: PENALITE EMPRUNT | AB4: PENALITE FONDS | AC4: INTERET ACHAT | AD4: DATE ACHAT
A5: AS201648 | B5: =VLOOKUP(A5,[2]LISTADHERENT!A$5:H$52,2,0) -> ASELBY | C5: 0 | D5: 318145 | E5: 355097 | F5: 318145 | G5: 36952 | H5: 355097.52 | I5: 355097 | J5: 0 | K5: 355097 | L5: 0 | M5: 0 | N5: 0 | O5: 0 | P5: 0 | Q5: 0 | R5: 0 | S5: 0 | T5: 0 | U5: 0 | V5: 0 | W5: 0 | X5: 0 | Y5: 0 | Z5: 0 | AA5: 0 | AB5: 0 | AC5: 0
A6: AS201601 | B6: =VLOOKUP(A6,[2]LISTADHERENT!A$5:H$52,2,0) -> BAKOP ACHILLE | C6: 390000 | D6: 33536 | E6: 51993 | F6: 453536 | G6: 51457 | H6: 504993.98 | I6: 114993 | J6: 63000 | K6: 51993 | L6: 0 | M6: 30000 | O6: =25000+25000 -> 50000 | P6: 8000 | Q6: 225000 | R6: 30000 | S6: 5000 | T6: 10000 | U6: 25000 | V6: 25000 | W6: 130000 | X6: 500000 | Y6: 15000 | Z6: 0 | AA6: 0 | AB6: 0 | AC6: 0
A7: AS201602 | B7: =VLOOKUP(A7,[2]LISTADHERENT!A$5:H$52,2,0) -> BOUTCHOUANG WILLIAM | C7: 390000 | D7: 1704 | E7: 2720 | F7: 427704 | G7: 48016 | H7: 475720.56 | I7: 85720 | J7: 80000 | K7: 5720 | L7: 3000 | M7: 30000 | O7: 50000 | P7: 0 | Q7: 240000 | R7: 36000 | S7: 6000 | T7: 12000 | U7: 30000 | V7: 0 | W7: 156000 | X7: 1700000 | Y7: 124000 | Z7: 1000000 | AA7: 0 | AB7: 0 | AC7: 0
A8: AS201603 | B8: =VLOOKUP(A8,[2]LISTADHERENT!A$5:H$52,2,0) -> CHINGUE FABRICE | C8: 390000 | D8: 1842 | E8: 5874 | F8: 427842 | G8: 48032 | H8: 475874.59 | I8: 85874 | J8: 80000 | K8: 5874 | L8: 0 | M8: 30000 | O8: 50000 | P8: 0 | Q8: 240000 | R8: 36000 | S8: 6000 | T8: 12000 | U8: 30000 | V8: 0 | W8: 156000 | X8: 2000000 | Y8: 180000 | Z8: 1000000 | AA8: 0 | AB8: 0 | AC8: 0
A9: AS201604 | B9: =VLOOKUP(A9,[2]LISTADHERENT!A$5:H$52,2,0) -> DJOMO JEAN PAUL | C9: 390000 | D9: 8156 | E9: 2570 | F9: 441156 | G9: 48914 | H9: 490070.36 | I9: 100070 | J9: 80000 | K9: 20070 | L9: 17500 | M9: 30000 | O9: 50000 | P9: 0 | Q9: 247000 | R9: 43000 | S9: 6000 | T9: 12000 | U9: 30000 | V9: 0 | W9: 156000 | X9: 200000 | Y9: 6000 | Z9: 0 | AA9: 0 | AB9: 0 | AC9: 0
A10: AS201605 | B10: =VLOOKUP(A10,[2]LISTADHERENT!A$5:H$52,2,0) -> DJOUKWE GUY | C10: 390000 | D10: 5905 | E10: 2697 | F10: 471905 | G10: 51792 | H10: 523697.05 | I10: 133697 | J10: 80000 | K10: 53697 | L10: 51000 | M10: 30000 | O10: 50000 | P10: 0 | Q10: 280000 | R10: 76000 | S10: 6000 | T10: 12000 | U10: 30000 | V10: 0 | W10: 156000 | X10: 250000 | Y10: 7500 | Z10: 0 | AA10: 0 | AB10: 0 | AC10: 0
A11: AS201606 | B11: =VLOOKUP(A11,[2]LISTADHERENT!A$5:H$52,2,0) -> DJOSSEU JOSUE | E11: 0
A12: AS201607 | B12: =VLOOKUP(A12,[2]LISTADHERENT!A$5:H$52,2,0) -> DJOUNKEP SAMUEL | C12: 390000 | D12: 1055294 | E12: 635540 | F12: 2001294 | G12: 204246 | H12: 2135835.7 | I12: 1815540 | J12: 80000 | K12: 1735540 | L12: 1100000 | M12: 30000 | O12: 50000 | P12: 0 | Q12: 760000 | R12: 556000 | S12: 6000 | T12: 12000 | U12: 30000 | V12: 0 | W12: 156000 | X12: 0 | Y12: 0 | Z12: 0 | AA12: 0 | AB12: 0 | AC12: 0
A13: AS201608 | B13: =VLOOKUP(A13,[2]LISTADHERENT!A$5:H$52,2,0) -> DJUOMBESSY ANTOINE | C13: 390000 | D13: 0 | E13: 2746 | F13: 457560 | G13: 43186 | H13: 500746.25 | I13: 110746 | J13: 80000 | K13: 30746 | L13: 28000 | M13: 30000 | O13: 50000 | P13: 0 | Q13: 271560 | R13: 67560 | S13: 6000 | T13: 12000 | U13: 30000 | V13: 0 | W13: 156000 | X13: 700000 | Y13: 84000 | Z13: 0 | AA13: 0 | AB13: 48440 | AC13: 0
A14: AS201609 | B14: =VLOOKUP(A14,[2]LISTADHERENT!A$5:H$52,2,0) -> DONHOU DAVID | C14: 390000 | D14: 44734 | E14: 53748 | F14: 470734 | G14: 53014 | H14: 523748.49 | I14: 133748 | J14: 80000 | K14: 53748 | L14: 0 | M14: 30000 | O14: 50000 | P14: 0 | Q14: 240000 | R14: 36000 | S14: 6000 | T14: 12000 | U14: 30000 | V14: 0 | W14: 156000 | X14: 0 | Y14: 0 | Z14: 0 | AA14: 0 | AB14: 0 | AC14: 0
A15: AS201610 | B15: =VLOOKUP(A15,[2]LISTADHERENT!A$5:H$52,2,0) -> FOTSO THOMAS | C15: 390000 | D15: 3318 | E15: 2522 | F15: 429318 | G15: 48204 | H15: 477522.03 | I15: 87522 | J15: 80000 | K15: 7522 | L15: 5000 | M15: 30000 | O15: 50000 | P15: 0 | Q15: 240000 | R15: 36000 | S15: 6000 | T15: 12000 | U15: 30000 | V15: 0 | W15: 156000 | X15: 1000000 | Y15: 120000 | Z15: 0 | AA15: 0 | AB15: 0 | AC15: 0
A16: AS201611 | B16: =VLOOKUP(A16,[2]LISTADHERENT!A$5:H$52,2,0) -> HENGUE PAUL OMER | C16: 390000 | E16: -10298 | F16: 420000 | G16: 47702 | H16: 467702.04 | I16: 77702 | J16: 88000 | K16: -10298 | L16: 0 | M16: 30000 | O16: 50000 | P16: 8000 | Q16: 200000 | R16: 30000 | S16: 5000 | T16: 10000 | U16: 25000 | V16: 0 | W16: 130000 | X16: 0 | Y16: 0 | Z16: 0 | AA16: 0 | AB16: 0 | AC16: 0
A17: AS201612 | B17: =VLOOKUP(A17,[2]LISTADHERENT!A$5:H$52,2,0) -> HODIEP JULES | C17: 50000 | D17: 0 | E17: 260 | F17: 58100 | G17: 6252 | H17: 92252.382 | I17: 14352 | J17: 14092 | K17: 260 | L17: 0 | O17: 14092 | P17: 0 | Q17: 240000 | R17: 8100 | S17: 6000 | T17: 12000 | U17: 30000 | V17: 0 | W17: 156000 | X17: 0 | Y17: 0 | Z17: 0 | AA17: 0 | AB17: 0 | AC17: 0
A18: AS201613 | B18: =VLOOKUP(A18,[2]LISTADHERENT!A$5:H$52,2,0) -> HOTCHO BENJAMIN | C18: 390000 | D18: 8723 | E18: 112685 | F18: 482723 | G18: 49962 | H18: 532685.38 | I18: 142685 | J18: 30000 | K18: 112685 | L18: 0 | M18: 30000 | O18: 50000 | P18: 0 | Q18: 338000 | R18: 84000 | S18: 6000 | T18: 12000 | U18: 30000 | V18: 50000 | W18: 156000 | X18: 0 | Y18: 0 | Z18: 0 | AA18: 0 | AB18: 0 | AC18: 0
A19: AS201614 | B19: =VLOOKUP(A19,[2]LISTADHERENT!A$5:H$52,2,0) -> KEPHE DAVID | C19: 0 | D19: 12795 | E19: 177 | F19: 18000 | G19: 4006 | H19: 52801.313 | I19: 22006 | J19: 21829 | K19: 177 | L19: 0 | O19: 21829 | P19: 0 | Q19: 240000 | R19: 5205 | S19: 6000 | T19: 12000 | U19: 30000 | V19: 0 | W19: 156000 | X19: 0 | Y19: 0 | Z19: 0 | AA19: 0 | AB19: 0 | AC19: 0
A20: AS201615 | B20: =VLOOKUP(A20,[2]LISTADHERENT!A$5:H$52,2,0) -> KEPSEU FRANCIS | C20: 390000 | D20: 186997 | E20: 705425 | F20: 1128997 | G20: 117428 | H20: 1246425.8 | I20: 856425 | J20: 80000 | K20: 776425 | L20: 71000 | M20: 30000 | O20: 50000 | P20: 0 | Q20: 756000 | R20: 552000 | S20: 6000 | T20: 12000 | U20: 30000 | V20: 0 | W20: 156000 | X20: 0 | Y20: 0 | Z20: 0 | AA20: 0 | AB20: 0 | AC20: 0
A21: AS201616 | B21: =VLOOKUP(A21,[2]LISTADHERENT!A$5:H$52,2,0) -> KOUAMOU EMMANUEL | C21: 390000 | D21: 2723 | E21: 2357 | F21: 428723 | G21: 48134 | H21: 476857.92 | I21: 86857 | J21: 80000 | K21: 6857 | L21: 4500 | M21: 30000 | O21: 50000 | P21: 0 | Q21: 240000 | R21: 36000 | S21: 6000 | T21: 12000 | U21: 30000 | V21: 0 | W21: 156000 | X21: 1000000 | Y21: 120000 | Z21: 0 | AA21: 0 | AB21: 0 | AC21: 0
A22: AS201617 | B22: =VLOOKUP(A22,[2]LISTADHERENT!A$5:H$52,2,0) -> KOUAMOU MOISE | C22: 390000 | D22: 2099 | E22: 3048 | F22: 428099 | G22: 44949 | H22: 473048.51 | I22: 83048 | J22: 80000 | K22: 3048 | L22: 0 | M22: 30000 | O22: 50000 | P22: 0 | Q22: 240000 | R22: 36000 | S22: 6000 | T22: 12000 | U22: 30000 | V22: 0 | W22: 156000 | X22: 860000 | Y22: 97800 | Z22: 0 | AA22: 0 | AB22: 0 | AC22: 0
A23: AS201618 | B23: =VLOOKUP(A23,[2]LISTADHERENT!A$5:H$52,2,0) -> KOUAMOU VICTOR PEGUY | C23: 390000 | D23: 36629 | E23: 2686 | F23: 461629 | G23: 52057 | H23: 513686.78 | I23: 123686 | J23: 80000 | K23: 43686 | L23: 41000 | M23: 30000 | O23: 50000 | P23: 0 | Q23: 239000 | R23: 35000 | S23: 6000 | T23: 12000 | U23: 30000 | V23: 0 | W23: 156000 | X23: 1800000 | Y23: 128000 | Z23: 1000000 | AA23: 0 | AB23: 0 | AC23: 0
A24: AS201619 | B24: =VLOOKUP(A24,[2]LISTADHERENT!A$5:H$52,2,0) -> KOUATCHO MESSACK | C24: 390000 | D24: 0 | E24: 3818 | F24: 426000 | G24: 47818 | H24: 473818.64 | I24: 83818 | J24: 80000 | K24: 3818 | L24: 0 | M24: 30000 | O24: 50000 | P24: 0 | Q24: 240000 | R24: 36000 | S24: 6000 | T24: 12000 | U24: 30000 | V24: 0 | W24: 156000 | X24: 1600000 | Y24: 192000 | Z24: 0 | AA24: 0 | AB24: 0 | AC24: 0
A25: AS201620 | B25: =VLOOKUP(A25,[2]LISTADHERENT!A$5:H$52,2,0) -> LOWE JEAN | C25: 390000 | D25: 4331 | E25: 2652 | F25: 430331 | G25: 48321 | H25: 478652.69 | I25: 88652 | J25: 80000 | K25: 8652 | L25: 6000 | M25: 30000 | O25: 50000 | P25: 0 | Q25: 240000 | R25: 36000 | S25: 6000 | T25: 12000 | U25: 30000 | V25: 0 | W25: 156000 | X25: 240000 | Y25: 7200 | Z25: 160000 | AA25: 0 | AB25: 0 | AC25: 0
A26: AS201621 | B26: =VLOOKUP(A26,[2]LISTADHERENT!A$5:H$52,2,0) -> NANKAM APPOLINAIRE | C26: 390000 | D26: 4411 | E26: 2741 | F26: 430411 | G26: 48330 | H26: 478741.98 | I26: 88741 | J26: 80000 | K26: 8741 | L26: 6000 | M26: 30000 | O26: 50000 | P26: 0 | Q26: 240000 | R26: 36000 | S26: 6000 | T26: 12000 | U26: 30000 | V26: 0 | W26: 156000 | X26: 1000000 | Y26: 120000 | Z26: 0 | AA26: 0 | AB26: 0 | AC26: 0
A27: AS201622 | B27: =VLOOKUP(A27,[2]LISTADHERENT!A$5:H$52,2,0) -> NDJOMO ETIENNE | C27: 390000 | D27: 2060 | E27: 2818 | F27: 488060 | G27: 52258 | H27: 540318.2 | I27: 150318 | J27: 80000 | K27: 70318 | L27: 67500 | M27: 30000 | O27: 50000 | P27: 0 | Q27: 300000 | R27: 96000 | S27: 6000 | T27: 12000 | U27: 30000 | V27: 0 | W27: 156000 | X27: 1600000 | Y27: 48000 | Z27: 1200000 | AA27: 0 | AB27: 0 | AC27: 0
A28: AS201623 | B28: =VLOOKUP(A28,[2]LISTADHERENT!A$5:H$52,2,0) -> NDOMBOU JEAN CLAUDE | C28: 0 | D28: 0 | E28: 0 | F28: 0 | G28: 0 | H28: 0 | I28: 0 | J28: 0 | K28: 0 | Q28: 0 | R28: 0 | S28: 0 | T28: 0 | U28: 0 | V28: 0 | W28: 0 | X28: 0 | Y28: 0 | Z28: 0 | AA28: 0 | AB28: 0 | AC28: 0
A29: AS201624 | B29: =VLOOKUP(A29,[2]LISTADHERENT!A$5:H$52,2,0) -> NGONDIEP CLAUDE | C29: 390000 | D29: 179574 | E29: 3250 | F29: 605574 | G29: 68676 | H29: 674250.15 | I29: 284250 | J29: 80000 | K29: 204250 | L29: 201000 | M29: 30000 | O29: 50000 | P29: 0 | Q29: 240000 | R29: 36000 | S29: 6000 | T29: 12000 | U29: 30000 | V29: 0 | W29: 156000 | X29: 0 | Y29: 0 | Z29: 0 | AA29: 0 | AB29: 0 | AC29: 0
A30: AS201625 | B30: =VLOOKUP(A30,[2]LISTADHERENT!A$5:H$52,2,0) -> NGONGANG JEAN THEODORE | C30: 0 | D30: 0 | E30: 106 | F30: 17782 | G30: 2520 | H30: 38520.175 | I30: 20302 | J30: 20196 | K30: 106 | L30: 0 | O30: 20196 | P30: 0 | Q30: 240000 | R30: 17782 | S30: 6000 | T30: 12000 | U30: 30000 | V30: 0 | W30: 156000 | X30: 0 | Y30: 0 | Z30: 0 | AA30: 0 | AB30: 0 | AC30: 0
A31: AS201626 | B31: =VLOOKUP(A31,[2]LISTADHERENT!A$5:H$52,2,0) -> NGUIEMEGNI MATHIEU BLAISE | C31: 390000 | D31: 0 | E31: 565188 | F31: 945945 | G31: 39243 | H31: 985188.09 | I31: 595188 | J31: 30000 | K31: 565188 | L31: 0 | M31: 30000 | O31: 50000 | P31: 0 | Q31: 860000 | R31: 555945 | S31: 6000 | T31: 12000 | U31: 30000 | V31: 50000 | W31: 156000 | X31: 0 | Y31: 0 | Z31: 0 | AA31: 0 | AB31: 50055 | AC31: 0
A32: AS201627 | B32: =VLOOKUP(A32,[2]LISTADHERENT!A$5:H$52,2,0) -> NJEPDJIO MBOUKAM DELUXE | C32: 390000 | D32: 1734 | E32: 2773 | F32: 443734 | G32: 49539 | H32: 493273.71 | I32: 103273 | J32: 80000 | K32: 23273 | L32: 20500 | M32: 30000 | O32: 50000 | P32: 0 | Q32: 256000 | R32: 52000 | S32: 6000 | T32: 12000 | U32: 30000 | V32: 0 | W32: 156000 | X32: 2000000 | Y32: 150000 | Z32: 1000000 | AA32: 0 | AB32: 0 | AC32: 0
A33: AS201628 | B33: =VLOOKUP(A33,[2]LISTADHERENT!A$5:H$52,2,0) -> NKAMGANG JUSTIN DEJOLIE | C33: 372800 | D33: 0 | E33: 14208 | F33: 444800 | G33: 22208 | H33: 539008.02 | I33: 94208 | J33: 80000 | K33: 14208 | L33: 0 | M33: 30000 | O33: 50000 | P33: 0 | Q33: 648800 | R33: 72000 | S33: 6000 | T33: 12000 | U33: 30000 | V33: 0 | W33: 156000 | X33: 1000000 | Y33: 120000 | Z33: 0 | AA33: 0 | AB33: 0 | AC33: 0
A34: AS201629 | B34: =VLOOKUP(A34,[2]LISTADHERENT!A$5:H$52,2,0) -> NKEPSEU DIEUDONNE | C34: 390000 | D34: 8739 | E34: 2772 | F34: 494739 | G34: 53033 | H34: 547772.97 | I34: 157772 | J34: 30000 | K34: 127772 | L34: 125000 | M34: 30000 | O34: =25000+25000 -> 50000 | P34: 0 | Q34: 350000 | R34: 96000 | S34: 6000 | T34: 12000 | U34: 30000 | V34: 50000 | W34: 156000 | X34: 600000 | Y34: 72000 | Z34: 0 | AA34: 0 | AB34: 0 | AC34: 0
A35: AS201630 | B35: =VLOOKUP(A35,[2]LISTADHERENT!A$5:H$52,2,0) -> NKEPSEU HENANG RENE | E35: 0
A36: AS201631 | B36: =VLOOKUP(A36,[2]LISTADHERENT!A$5:H$52,2,0) -> NTEPDIE TUEMAC MZ | C36: 0 | D36: 0 | E36: -12105 | F36: 15000 | G36: 895 | H36: 15895.449 | I36: 15895 | J36: 28000 | K36: -12105 | L36: 0 | P36: 28000 | Q36: 100000 | R36: 15000 | S36: 2500 | T36: 5000 | U36: 12500 | V36: 0 | W36: 65000 | X36: 0 | Y36: 0 | Z36: 0 | AA36: 0 | AB36: 0 | AC36: 0
A37: AS201632 | B37: =VLOOKUP(A37,[2]LISTADHERENT!A$5:H$52,2,0) -> NTOMBOU ADOLPHE | E37: 0
A38: AS201633 | B38: =VLOOKUP(A38,[2]LISTADHERENT!A$5:H$52,2,0) -> PATEGO NJOSSU GUSTAVE | C38: 390000 | D38: 140 | E38: 2474 | F38: 426140 | G38: 47834 | H38: 473974.9 | I38: 83974 | J38: 80000 | K38: 3974 | L38: 1500 | M38: 30000 | O38: 50000 | P38: 0 | Q38: 240000 | R38: 36000 | S38: 6000 | T38: 12000 | U38: 30000 | V38: 0 | W38: 156000 | X38: 0 | Y38: 0 | Z38: 0 | AA38: 0 | AB38: 0 | AC38: 0
A39: AS201634 | B39: =VLOOKUP(A39,[2]LISTADHERENT!A$5:H$52,2,0) -> SEUNOU RICHELOT | C39: 390000 | D39: 2632 | E39: 6756 | F39: 428632 | G39: 48124 | H39: 476756.35 | I39: 86756 | J39: 80000 | K39: 6756 | L39: 0 | M39: 30000 | O39: 50000 | P39: 0 | Q39: 240000 | R39: 36000 | S39: 6000 | T39: 12000 | U39: 30000 | V39: 0 | W39: 156000 | X39: 1000000 | Y39: 120000 | Z39: 0 | AA39: 0 | AB39: 0 | AC39: 0
A40: AS201635 | B40: =VLOOKUP(A40,[2]LISTADHERENT!A$5:H$52,2,0) -> SIME ABEL | C40: 390000 | D40: 0 | E40: 488 | F40: 398873 | G40: 15621 | H40: 441621.35 | I40: 24494 | J40: 24006 | K40: 488 | L40: 0 | O40: 24006 | P40: 0 | Q40: 240000 | R40: 8873 | S40: 6000 | T40: 12000 | U40: 30000 | V40: 0 | W40: 156000 | X40: 0 | Y40: 0 | Z40: 0 | AA40: 0 | AB40: 0 | AC40: 0
A41: AS201636 | B41: =VLOOKUP(A41,[2]LISTADHERENT!A$5:H$52,2,0) -> SIME FONGANG ERIC | C41: 390000 | D41: 982 | E41: 4914 | F41: 426982 | G41: 47932 | H41: 474914.7 | I41: 84914 | J41: 80000 | K41: 4914 | L41: 0 | M41: 30000 | O41: 50000 | P41: 0 | Q41: 240000 | R41: 36000 | S41: 6000 | T41: 12000 | U41: 30000 | V41: 0 | W41: 156000 | X41: 1000000 | Y41: 120000 | Z41: 0 | AA41: 0 | AB41: 0 | AC41: 0
A42: AS201637 | B42: =VLOOKUP(A42,[2]LISTADHERENT!A$5:H$52,2,0) -> SIME MATHIEU | C42: 390000 | D42: 636 | E42: 4528 | F42: 426636 | G42: 47892 | H42: 474528.51 | I42: 84528 | J42: 80000 | K42: 4528 | L42: 0 | M42: 30000 | O42: 50000 | P42: 0 | Q42: 240000 | R42: 36000 | S42: 6000 | T42: 12000 | U42: 30000 | V42: 0 | W42: 156000 | X42: 800000 | Y42: 96000 | Z42: 0 | AA42: 0 | AB42: 0 | AC42: 0
A43: AS201638 | B43: =VLOOKUP(A43,[2]LISTADHERENT!A$5:H$52,2,0) -> SIME PIERRE | C43: 390000 | D43: 146079 | E43: 105975 | F43: 1147306 | G43: 121669 | H43: 1268975.9 | I43: 878975 | J43: 80000 | K43: 798975 | L43: 693000 | M43: 30000 | O43: 50000 | P43: 0 | Q43: 1130000 | R43: 611227 | S43: 6000 | T43: 12000 | U43: 30000 | V43: 10000 | W43: 156000 | X43: 1110000 | Y43: 84600 | Z43: 540000 | AA43: 0 | AB43: 0 | AC43: 0
A44: AS201639 | B44: =VLOOKUP(A44,[2]LISTADHERENT!A$5:H$52,2,0) -> TAGNE NANGUEN MARTIN | C44: 390000 | D44: 0 | E44: 1621 | F44: 426000 | G44: 15621 | H44: 441621.35 | I44: 51621 | J44: 50000 | K44: 1621 | L44: 0 | O44: 50000 | P44: 0 | Q44: 240000 | R44: 36000 | S44: 6000 | T44: 12000 | U44: 30000 | V44: 0 | W44: 156000 | X44: 0 | Y44: 0 | Z44: 0 | AA44: 0 | AB44: 0 | AC44: 0
A45: AS201640 | B45: =VLOOKUP(A45,[2]LISTADHERENT!A$5:H$52,2,0) -> TCHOUAMOU JEAN PAUL | C45: 0 | D45: 0 | E45: 106 | F45: 12323 | G45: 2520 | H45: 38520.175 | I45: 14843 | J45: 14737 | K45: 106 | L45: 0 | O45: 50000 | P45: 0 | Q45: 290000 | R45: 12323 | S45: 6000 | T45: 12000 | U45: 30000 | V45: 50000 | W45: 156000 | X45: 0 | Y45: 0 | Z45: 0 | AA45: 0 | AB45: 0 | AC45: 0
A46: AS201641 | B46: =VLOOKUP(A46,[2]LISTADHERENT!A$5:H$52,2,0) -> TCHOUAMOU MATHIEU | C46: 390000 | D46: 3437 | E46: 2654 | F46: 429437 | G46: 48217 | H46: 477654.85 | I46: 87654 | J46: 80000 | K46: 7654 | L46: 5000 | M46: 30000 | O46: 50000 | P46: 0 | Q46: 240000 | R46: 36000 | S46: 6000 | T46: 12000 | U46: 30000 | V46: 0 | W46: 156000 | X46: 1500000 | Y46: 45000 | Z46: 1000000 | AA46: 94825 | AB46: 0 | AC46: 0
A47: AS201642 | B47: =VLOOKUP(A47,[2]LISTADHERENT!A$5:H$52,2,0) -> TCHOUANTE FRANCOIS | C47: 325719 | D47: 4925 | E47: 25832 | F47: 393644 | G47: 37907 | H47: 431551.07 | I47: 105832 | J47: 80000 | K47: 25832 | L47: 0 | M47: 30000 | O47: 50000 | P47: 0 | Q47: 267000 | R47: 63000 | S47: 6000 | T47: 12000 | U47: 30000 | V47: 0 | W47: 156000 | X47: 1250000 | Y47: 105000 | Z47: 0 | AA47: 0 | AB47: 0 | AC47: 0
A48: AS201643 | B48: =VLOOKUP(A48,[2]LISTADHERENT!A$5:H$52,2,0) -> TCHOUTOU NANA CLAUDE | C48: 0 | D48: 0 | E48: -437 | F48: 14126 | G48: 1437 | H48: 25437.043 | I48: 15563 | J48: 16000 | K48: -437 | L48: 0 | P48: 16000 | Q48: 160000 | R48: 14126 | S48: 4000 | T48: 8000 | U48: 20000 | V48: 0 | W48: 104000 | X48: 0 | Y48: 0 | Z48: 0 | AA48: 0 | AB48: 0 | AC48: 0
A49: AS201644 | B49: =VLOOKUP(A49,[2]LISTADHERENT!A$5:H$52,2,0) -> TIEYAM ERNEST | C49: 390000 | D49: 804 | E49: 2593 | F49: 426804 | G49: 47789 | H49: 474593.29 | I49: 84593 | J49: 80000 | K49: 4593 | L49: 2000 | M49: 30000 | O49: 50000 | P49: 0 | Q49: 240000 | R49: 36000 | S49: 6000 | T49: 12000 | U49: 30000 | V49: 0 | W49: 156000 | X49: 1000000 | Y49: 120000 | Z49: 0 | AA49: 0 | AB49: 0 | AC49: 0
A50: AS201645 | B50: =VLOOKUP(A50,[2]LISTADHERENT!A$5:H$52,2,0) -> TUGMA PIERRE LOTI | C50: 390000 | D50: 17636 | E50: 2503 | F50: 443636 | G50: 49867 | H50: 493503.06 | I50: 103503 | J50: 80000 | K50: 23503 | L50: 21000 | M50: 30000 | O50: 50000 | P50: 0 | Q50: 240000 | R50: 36000 | S50: 6000 | T50: 12000 | U50: 30000 | V50: 0 | W50: 156000 | X50: 0 | Y50: 0 | Z50: 0 | AA50: 0 | AB50: 0 | AC50: 0
A51: AS201646 | B51: =VLOOKUP(A51,[2]LISTADHERENT!A$5:H$52,2,0) -> YEPMOU JEAN JACQUES | C51: 390000 | D51: 421237 | E51: 393982 | F51: 847237 | G51: 96745 | H51: 943982.29 | I51: 553982 | J51: 80000 | K51: 473982 | L51: 80000 | M51: 30000 | O51: 50000 | P51: 0 | Q51: 240000 | R51: 36000 | S51: 6000 | T51: 12000 | U51: 30000 | V51: 0 | W51: 156000 | X51: 0 | Y51: 0 | Z51: 0 | AA51: 0 | AB51: 0 | AC51: 0
A52: AS201647 | B52: =VLOOKUP(A52,[2]LISTADHERENT!A$5:H$52,2,0) -> YOUMBI EMMANUEL | C52: 390000 | D52: 1003279 | E52: 883628 | F52: 1429279 | G52: 164349 | H52: 1593628.4 | I52: 1203628 | J52: 80000 | K52: 1123628 | L52: 240000 | M52: 30000 | O52: 50000 | P52: 0 | Q52: 240000 | R52: 36000 | S52: 6000 | T52: 12000 | U52: 30000 | V52: 0 | W52: 156000 | X52: 0 | Y52: 0 | Z52: 0 | AA52: 0 | AB52: 0 | AC52: 0
A54: TOTAL | C54: =SUM(C5:C53) -> 14398519 | D54: =SUM(D5:D53) -> 3525236 | E54: =SUM(E5:E53) -> 3957685 | F54: =SUM(F5:F53) -> 21744896 | G54: =SUM(G5:G53) -> 2230668 | H54: =SUM(H5:H53) -> 24115470 | I54: =SUM(I5:I53) -> 9577045 | J54: =SUM(J5:J53) -> 2829860 | ... AC54: =SUM(AC5:AC53) -> 0
A55: TOTAL A DISTRIBUER | K55: =K5+K6+K7+K8+K9+K10+K12+K13+K14+K15+K17+K18+K19+K20+K21+K22+K23+K24+K25+K26+K27+K29+K30+K31+K32+K33+K34+K38+K39+K40+K41+K42+K43+K44+K45+K46+K47+K49+K50+K51+K52 -> 6770025
K56: =K16+K36+K48 -> -22840
B57: CAPITAL A DISTRIBUER | H57: =F58+F59+F60 -> 9577045
D58: RELIQUAT 2015 | F58: =D54 -> 3525236 | K58: SORTIE | L58: 8000000
D59: INTERET 2016 | F59: =+G54 -> 2230668 | K59: FONDS DISTRIBUE | L59: =L54 -> 2789500
D60: EPARGNE 2016 | F60: =R54 -> 3821141 | K60: TONTINE | L60: 914500
K61: FRAIS DE TAXI | L61: 9000
B62: CAPITAL A DISTRIBUER | G62: =K55 -> 6770025
B63: CAPITAL EFFECTIVEMENT DISTRIBUE | G63: =L54 -> 2789500 | K63: RETOUR BANQUE | L63: =L58-L59-L60-L61 -> 4287000
B64: RETOUR MUTUELLE | G64: =O54 -> 1930123 | L64: =L63-3934000 -> 353000
B65: COMPLEMENT FONDS | G65: =M54 -> 1050000
B66: FRAIS FIXE A COMPLETER | G66: =P54 -> 60000
B67: SANCTION | G67: =N54 -> 0
B69: TOTAL | H69: =G62+G64+G65+G66+G67 -> 9810148
B71: RELIQUAT | H71: =H57-H69 -> -233103

Sheet FONDSDECAISSE
A1: ASSOCIATION | B1: ASELBY
A2: ANNEE | B2: 2016/2017
A3: TONTINE | B3: 20 000
A4: MATRICULE | B4: NOM ET PRENOM | C4: DECEMBRE | D4: JANVIER | E4: FÉVRIER | F4: MARS | G4: AVRIL | H4: MAI | I4: JUIN | J4: JUILLET | K4: AOÛT | L4: SEPTEMBRE | M4: OCTOBRE | N4: NOVEMBRE | O4: TOTAL
A5: AS201648 | B5: =VLOOKUP(A5,LISTADHERENT!A$5:H$52,2,0) -> ASELBY | C5: 0 | O5: =SUM(C5:N5) -> 0
A6: AS201601 | B6: =VLOOKUP(A6,LISTADHERENT!A$5:H$52,2,0) -> BAKOP ACHILLE | C6: 420000 | O6: =SUM(C6:N6) -> 420000
A7: AS201602 | B7: =VLOOKUP(A7,LISTADHERENT!A$5:H$52,2,0) -> BOUTCHOUANG WILLIAM | C7: 420000 | O7: =SUM(C7:N7) -> 420000
A8: AS201603 | B8: =VLOOKUP(A8,LISTADHERENT!A$5:H$52,2,0) -> CHINGUE FABRICE | C8: 420000 | O8: =SUM(C8:N8) -> 420000
A9: AS201604 | B9: =VLOOKUP(A9,LISTADHERENT!A$5:H$52,2,0) -> DJOMO JEAN PAUL | C9: 420000 | O9: =SUM(C9:N9) -> 420000
A10: AS201605 | B10: =VLOOKUP(A10,LISTADHERENT!A$5:H$52,2,0) -> DJOUKWE NANGUEN GUY BLAISE | C10: 420000 | O10: =SUM(C10:N10) -> 420000
A11: AS201606 | B11: =VLOOKUP(A11,LISTADHERENT!A$5:H$52,2,0) -> DJOSSEU JOSUE | C11: 0 | O11: =SUM(C11:N11) -> 0
A12: AS201607 | B12: =VLOOKUP(A12,LISTADHERENT!A$5:H$52,2,0) -> DJOUNKEP SAMUEL | C12: 420000 | O12: =SUM(C12:N12) -> 420000
A13: AS201608 | B13: =VLOOKUP(A13,LISTADHERENT!A$5:H$52,2,0) -> DJUOMBESSY ANTOINE | C13: 420000 | O13: =SUM(C13:N13) -> 420000
A14: AS201609 | B14: =VLOOKUP(A14,LISTADHERENT!A$5:H$52,2,0) -> DONHOU DAVID | C14: 420000 | O14: =SUM(C14:N14) -> 420000
A15: AS201610 | B15: =VLOOKUP(A15,LISTADHERENT!A$5:H$52,2,0) -> FOTSO THOMAS | C15: 420000 | O15: =SUM(C15:N15) -> 420000
A16: AS201611 | B16: =VLOOKUP(A16,LISTADHERENT!A$5:H$52,2,0) -> HENGUE PAUL OMER | C16: 420000 | O16: =SUM(C16:N16) -> 420000
... A18: AS201613 | B18: =VLOOKUP(A18,LISTADHERENT!A$5:H$52,2,0) -> HOTCHO BENJAMIN | C18: 420000 | O18: =SUM(C18:N18) -> 420000
A19: AS201614 | B19: =VLOOKUP(A19,LISTADHERENT!A$5:H$52,2,0) -> KEPHE DAVID | C19: 0 | K19: 100000 | O19: =SUM(C19:N19) -> 100000
A20: AS201615 | B20: =VLOOKUP(A20,LISTADHERENT!A$5:H$52,2,0) -> KEPSEU FRANCIS | C20: 420000 | O20: =SUM(C20:N20) -> 420000
A21: AS201616 | B21: =VLOOKUP(A21,LISTADHERENT!A$5:H$52,2,0) -> KOUAMOU EMMANUEL | C21: 420000 | O21: =SUM(C21:N21) -> 420000
A22: AS201617 | B22: =VLOOKUP(A22,LISTADHERENT!A$5:H$52,2,0) -> KOUAMOU MOISE | C22: 420000 | O22: =SUM(C22:N22) -> 420000
A23: AS201618 | B23: =VLOOKUP(A23,LISTADHERENT!A$5:H$52,2,0) -> KOUAMO VICTOR PEGUY | C23: 420000 | O23: =SUM(C23:N23) -> 420000
A24: AS201619 | B24: =VLOOKUP(A24,LISTADHERENT!A$5:H$52,2,0) -> KOUATCHO MESSACK | C24: 420000 | O24: =SUM(C24:N24) -> 420000
A25: AS201620 | B25: =VLOOKUP(A25,LISTADHERENT!A$5:H$52,2,0) -> LOWE JEAN | C25: 420000 | O25: =SUM(C25:N25) -> 420000
A26: AS201621 | B26: =VLOOKUP(A26,LISTADHERENT!A$5:H$52,2,0) -> NANKAM APPOLINAIRE | C26: 420000 | O26: =SUM(C26:N26) -> 420000
A27: AS201622 | B27: =VLOOKUP(A27,LISTADHERENT!A$5:H$52,2,0) -> NDJOMO ETIENNE | C27: 420000 | O27: =SUM(C27:N27) -> 420000
A28: AS201623 | B28: =VLOOKUP(A28,LISTADHERENT!A$5:H$52,2,0) -> NDOMBOU JEAN CLAUDE | C28: 0 | F28: 420000 | O28: =SUM(C28:N28) -> 420000
A29: AS201624 | B29: =VLOOKUP(A29,LISTADHERENT!A$5:H$52,2,0) -> NGONDIEP CLAUDE | C29: 420000 | O29: =SUM(C29:N29) -> 420000
A30: AS201625 | B30: =VLOOKUP(A30,LISTADHERENT!A$5:H$52,2,0) -> NGONGANG JEAN THEODORE | C30: 0 | O30: =SUM(C30:N30) -> 0
A31: AS201626 | B31: =VLOOKUP(A31,LISTADHERENT!A$5:H$52,2,0) -> NGUIEMEGNI MATHIEU BLAISE | C31: 420000 | O31: =SUM(C31:N31) -> 420000
A32: AS201627 | B32: =VLOOKUP(A32,LISTADHERENT!A$5:H$52,2,0) -> NJEPDJIO MBOUKAM DELUXE | C32: 420000 | O32: =SUM(C32:N32) -> 420000
A33: AS201628 | B33: =VLOOKUP(A33,LISTADHERENT!A$5:H$52,2,0) -> NKAMGANG JUSTIN DEJOLIE | C33: 102800 | K33: =372800-55600 -> 317200 | O33: =SUM(C33:N33) -> 420000
A34: AS201629 | B34: =VLOOKUP(A34,LISTADHERENT!A$5:H$52,2,0) -> NKEPSEU DIEUDONNE | C34: 420000 | O34: =SUM(C34:N34) -> 420000
A35: AS201630 | B35: =VLOOKUP(A35,LISTADHERENT!A$5:H$52,2,0) -> NKEPSEU HENANG RENE | O35: =SUM(C35:N35) -> 0
A36: AS201631 | B36: =VLOOKUP(A36,LISTADHERENT!A$5:H$52,2,0) -> NTEPDIE TUEMAC MZ | C36: 0 | O36: =SUM(C36:N36) -> 0
A37: AS201632 | B37: =VLOOKUP(A37,LISTADHERENT!A$5:H$52,2,0) -> NTOMBOU ADOLPHE | C37: 0 | O37: =SUM(C37:N37) -> 0
A38: AS201633 | B38: =VLOOKUP(A38,LISTADHERENT!A$5:H$52,2,0) -> PATEGO NJOSSU GUSTAVE | C38: 420000 | O38: =SUM(C38:N38) -> 420000
A39: AS201634 | B39: =VLOOKUP(A39,LISTADHERENT!A$5:H$52,2,0) -> SEUNOU RICHELOT | C39: 420000 | O39: =SUM(C39:N39) -> 420000
A40: AS201635 | B40: =VLOOKUP(A40,LISTADHERENT!A$5:H$52,2,0) -> SIME ABEL | C40: 390000 | O40: =SUM(C40:N40) -> 390000
A41: AS201636 | B41: =VLOOKUP(A41,LISTADHERENT!A$5:H$52,2,0) -> SIME FONGANG ERIC | C41: 420000 | O41: =SUM(C41:N41) -> 420000
A42: AS201637 | B42: =VLOOKUP(A42,LISTADHERENT!A$5:H$52,2,0) -> SIME MATHIEU | C42: 420000 | O42: =SUM(C42:N42) -> 420000
A43: AS201638 | B43: =VLOOKUP(A43,LISTADHERENT!A$5:H$52,2,0) -> SIME PIERRE | C43: 420000 | O43: =SUM(C43:N43) -> 420000
A44: AS201639 | B44: =VLOOKUP(A44,LISTADHERENT!A$5:H$52,2,0) -> TAGNE NANGUEN MARTIN | C44: 390000 | O44: =SUM(C44:N44) -> 390000
A45: AS201640 | B45: =VLOOKUP(A45,LISTADHERENT!A$5:H$52,2,0) -> TCHOUAMOU JEAN PAUL | C45: 0 | O45: =SUM(C45:N45) -> 0
A46: AS201641 | B46: =VLOOKUP(A46,LISTADHERENT!A$5:H$52,2,0) -> TCHOUAMOU MATHIEU | C46: 420000 | O46: =SUM(C46:N46) -> 420000
A47: AS201642 | B47: =VLOOKUP(A47,LISTADHERENT!A$5:H$52,2,0) -> TCHOUANTE FRANCOIS | C47: =355719+48100 -> 403819 | O47: =SUM(C47:N47) -> 403819
A48: AS201643 | B48: =VLOOKUP(A48,LISTADHERENT!A$5:H$52,2,0) -> TCHOUTOU NANA CLAUDE | C48: 0 | O48: =SUM(C48:N48) -> 0
A49: AS201644 | B49: =VLOOKUP(A49,LISTADHERENT!A$5:H$52,2,0) -> TIEYAM ERNEST | C49: 420000 | O49: =SUM(C49:N49) -> 420000
A50: AS201645 | B50: =VLOOKUP(A50,LISTADHERENT!A$5:H$52,2,0) -> TUGMA PIERRE LOTI | C50: 420000 | O50: =SUM(C50:N50) -> 420000
A51: AS201646 | B51: =VLOOKUP(A51,LISTADHERENT!A$5:H$52,2,0) -> YEPMOU JEAN JACQUES | C51: 420000 | O51: =SUM(C51:N51) -> 420000
A52: AS201647 | B52: =VLOOKUP(A52,LISTADHERENT!A$5:H$52,2,0) -> YOUMBI EMMANUEL | C52: 420000 | O52: =SUM(C52:N52) -> 420000
A54: TOTAL | C54: 15538519 | D54: =SUM(D6:D52) -> 0 | E54: =SUM(E6:E52) -> 0 | F54: =SUM(F6:F52) -> 420000 | G54: =SUM(G6:G52) -> 0 | H54: =SUM(H6:H52) -> 0 | I54: =SUM(I6:I52) -> 0 | J54: =SUM(J6:J52) -> 0 | K54: =SUM(K6:K52) -> 417200 | ... O54: =SUM(O6:O52) -> 16033819

Sheet TONT20000DEC2016
A1: ASSOCIATION | B1: ASELBY
A2: ANNEE | B2: 2016/2017
A3: TONTINE | B3: 20 000
A4: MATRICULE | B4: NOM ET PRENOM | C4: FONDS DE CAISSE | D4: RELIQUAT 2016 | E4: REPARTITION INTERET | F4: CAPITAL COMPOSE | G4: SANCTION | H4: MONTANT TONTINE | I4: PENALITE | J4: MODE VERSEMENT | K4: MONTANT VERSE | L4: EPARGNE | M4: FONDS DE ROULEMENT | N4: FRAIS EXCEPTIONNEL | O4: COLLATION | P4: MUTUELLE | Q4: EMPRUNT | R4: INTERET EMPRUNT | S4: REMBOURSEMENT | T4: PENALITE EMPRUNT | U4: PENALITE FONDS | V4: INTERET ACHAT | W4: DATE ACHAT | X4: AVALISTE
A5: AS201648 | B5: =VLOOKUP(A5,LISTADHERENT!A$5:H$52,2,0) -> ASELBY | C5: =VLOOKUP(A5,FONDSDECAISSE!A$5:O$52,15,0) -> 0 | D5: 355097 | E5: =$R$56/$F$56*F5 -> 204.20954 | F5: =C5+D5+L5 -> 355097
A6: AS201601 | B6: =VLOOKUP(A6,LISTADHERENT!A$5:H$52,2,0) -> BAKOP ACHILLE | C6: =VLOOKUP(A6,FONDSDECAISSE!A$5:O$52,15,0) -> 420000 | D6: 51993 | E6: =$R$56/$F$56*F6 -> 271.4342 | F6: =C6+D6+L6 -> 471993 | H6: =IF(J6="ECHEC",0,13000) -> 0 | I6: =IF(J6="ESPECES",1000,0) -> 0 | J6: ECHEC | K6: =IF(H6=0,0,L6+M6+N6+O6+P6+#REF!) -> 0 | R6: =IF(Q6<=500000,(Q6*1*3/100),(Q6*12/100)) -> 0 | S6: =Q6+R6 -> 0
A7: AS201602 | B7: =VLOOKUP(A7,LISTADHERENT!A$5:H$51,2) -> BOUTCHOUANG WILLIAM | C7: =VLOOKUP(A7,FONDSDECAISSE!A$5:O$52,15,0) -> 420000 | D7: 2720 | E7: =$R$56/$F$56*F7 -> 244.82348 | F7: =C7+D7+L7 -> 425720 | H7: =IF(J7="ECHEC",0,13000) -> 13000 | I7: =IF(J7="ESPECES",1000,0) -> 1000 | J7: ESPECES | K7: =IF(H7=0,0,H7+L7+M7+N7+O7+P7) -> 20000 | L7: 3000 | M7: 500 | N7: 1000 | O7: 2500 | R7: =IF(Q7<=500000,(Q7*1*3/100),(Q7*12/100)) -> 0 | S7: =Q7+R7 -> 0
A8: AS201603 | B8: =VLOOKUP(A8,LISTADHERENT!A$5:H$51,2) -> CHINGUE FABRICE | C8: =VLOOKUP(A8,FONDSDECAISSE!A$5:O$52,15,0) -> 420000 | D8: 5874 | E8: =$R$56/$F$56*F8 -> 246.63729 | F8: =C8+D8+L8 -> 428874 | H8: =IF(J8="ECHEC",0,13000) -> 13000 | I8: =IF(J8="ESPECES",1000,0) -> 1000 | J8: ESPECES | K8: =IF(H8=0,0,H8+L8+M8+N8+O8+P8) -> 20000 | L8: 3000 | M8: 500 | N8: 1000 | O8: 2500 | R8: =IF(Q8<=500000,(Q8*1*3/100),(Q8*12/100)) -> 0 | S8: =Q8+R8 -> 0
A9: AS201604 | B9: =VLOOKUP(A9,LISTADHERENT!A$5:H$51,2) -> DJOMO JEAN PAUL | C9: =VLOOKUP(A9,FONDSDECAISSE!A$5:O$52,15,0) -> 420000 | D9: 2570 | E9: =$R$56/$F$56*F9 -> 244.73722 | F9: =C9+D9+L9 -> 425570 | H9: =IF(J9="ECHEC",0,13000) -> 13000 | I9: =IF(J9="ESPECES",1000,0) -> 0 | J9: BANQUE | K9: =IF(H9=0,0,H9+L9+M9+N9+O9+P9) -> 20000 | L9: 3000 | M9: 500 | N9: 1000 | O9: 2500 | R9: =IF(Q9<=500000,(Q9*1*3/100),(Q9*12/100)) -> 0 | S9: =Q9+R9 -> 0 | V9: 11000 | W9: 42723 | X9: KOUAMOU VICTOR PEGUY
A10: AS201605 | B10: =VLOOKUP(A10,LISTADHERENT!A$5:H$51,2) -> DJOUKWE NANGUEN GUY BLAISE | C10: =VLOOKUP(A10,FONDSDECAISSE!A$5:O$52,15,0) -> 420000 | D10: 2697 | E10: =$R$56/$F$56*F10 -> 244.81025 | F10: =C10+D10+L10 -> 425697 | H10: =IF(J10="ECHEC",0,13000) -> 13000 | I10: =IF(J10="ESPECES",1000,0) -> 0 | J10: BANQUE | K10: =IF(H10=0,0,H10+L10+M10+N10+O10+P10) -> 20000 | L10: 3000 | M10: 500 | N10: 1000 | O10: 2500 | R10: =IF(Q10<=500000,(Q10*1*3/100),(Q10*12/100)) -> 0 | S10: =Q10+R10 -> 0
D11: 0 | F11: =C11+D11+L11 -> 0 | R11: =IF(Q11<=500000,(Q11*1*3/100),(Q11*12/100)) -> 0 | S11: =Q11+R11 -> 0
A12: AS201607 | B12: =VLOOKUP(A12,LISTADHERENT!A$5:H$51,2) -> DJOUNKEP SAMUEL | C12: =VLOOKUP(A12,FONDSDECAISSE!A$5:O$52,15,0) -> 420000 | D12: 635540 | E12: =$R$56/$F$56*F12 -> 608.74623 | F12: =C12+D12+L12 -> 1058540 | H12: =IF(J12="ECHEC",0,13000) -> 13000 | I12: =IF(J12="ESPECES",1000,0) -> 0 | J12: BANQUE | K12: =IF(H12=0,0,H12+L12+M12+N12+O12+P12) -> 20000 | L12: 3000 | M12: 500 | N12: 1000 | O12: 2500 | R12: =IF(Q12<=500000,(Q12*1*3/100),(Q12*12/100)) -> 0 | S12: =Q12+R12 -> 0
A13: AS201608 | B13: =VLOOKUP(A13,LISTADHERENT!A$5:H$51,2) -> DJUOMBESSY ANTOINE | C13: =VLOOKUP(A13,FONDSDECAISSE!A$5:O$52,15,0) -> 420000 | D13: 2746 | E13: =$R$56/$F$56*F13 -> 244.83843 | F13: =C13+D13+L13 -> 425746 | H13: =IF(J13="ECHEC",0,13000) -> 13000 | I13: =IF(J13="ESPECES",1000,0) -> 0 | J13: BANQUE | K13: =IF(H13=0,0,H13+L13+M13+N13+O13+P13) -> 20000 | L13: 3000 | M13: 500 | N13: 1000 | O13: 2500 | R13: =IF(Q13<=500000,(Q13*1*3/100),(Q13*12/100)) -> 0 | S13: =Q13+R13 -> 0
A14: AS201609 | B14: =VLOOKUP(A14,LISTADHERENT!A$5:H$51,2) -> DONHOU DAVID | C14: =VLOOKUP(A14,FONDSDECAISSE!A$5:O$52,15,0) -> 420000 | D14: 53748 | E14: =$R$56/$F$56*F14 -> 274.16871 | F14: =C14+D14+L14 -> 476748 | H14: =IF(J14="ECHEC",0,13000) -> 13000 | I14: =IF(J14="ESPECES",1000,0) -> 1000 | J14: ESPECES | K14: =IF(H14=0,0,H14+L14+M14+N14+O14+P14) -> 20000 | L14: 3000 | M14: 500 | N14: 1000 | O14: 2500 | R14: =IF(Q14<=500000,(Q14*1*3/100),(Q14*12/100)) -> 0 | S14: =Q14+R14 -> 0
A15: AS201610 | B15: =VLOOKUP(A15,LISTADHERENT!A$5:H$51,2) -> FOTSO THOMAS | C15: =VLOOKUP(A15,FONDSDECAISSE!A$5:O$52,15,0) -> 420000 | D15: 2522 | E15: =$R$56/$F$56*F15 -> 244.70961 | F15: =C15+D15+L15 -> 425522 | H15: =IF(J15="ECHEC",0,13000) -> 13000 | I15: =IF(J15="ESPECES",1000,0) -> 1000 | J15: ESPECES | K15: =IF(H15=0,0,H15+L15+M15+N15+O15+P15) -> 20000 | L15: 3000 | M15: 500 | N15: 1000 | O15: 2500 | R15: =IF(Q15<=500000,(Q15*1*3/100),(Q15*12/100)) -> 0 | S15: =Q15+R15 -> 0
A16: AS201611 | B16: =VLOOKUP(A16,LISTADHERENT!A$5:H$51,2) -> HENGUE PAUL OMER | C16: =VLOOKUP(A16,FONDSDECAISSE!A$5:O$52,15,0) -> 420000 | E16: =$R$56/$F$56*F16 -> 281.21461 | F16: =C16+D16+L16 -> 489000 | H16: 39000 | I16: =IF(J16="ESPECES",1000,0) -> 0 | J16: BANQUE | K16: =IF(H16=0,0,H16+L16+M16+N16+O16+P16) -> 120000 | L16: 69000 | M16: 1500 | N16: 3000 | O16: 7500 | R16: =IF(Q16<=500000,(Q16*1*3/100),(Q16*12/100)) -> 0 | S16: =Q16+R16 -> 0
A17: AS201612 | B17: =VLOOKUP(A17,LISTADHERENT!A$5:H$51,2) -> HODIEP JULES | C17: =VLOOKUP(A17,FONDSDECAISSE!A$5:O$52,15,0) -> 50000 | D17: 260 | E17: =$R$56/$F$56*F17 -> 28.903571 | F17: =C17+D17+L17 -> 50260 | H17: =IF(J17="ECHEC",0,13000) -> 0 | I17: =IF(J17="ESPECES",1000,0) -> 0 | J17: ECHEC | K17: =IF(H17=0,0,H17+L17+M17+N17+O17+P17) -> 0 | R17: =IF(Q17<=500000,(Q17*1*3/100),(Q17*12/100)) -> 0 | S17: =Q17+R17 -> 0
A18: AS201613 | B18: =VLOOKUP(A18,LISTADHERENT!A$5:H$51,2) -> HOTCHO BENJAMIN | C18: =VLOOKUP(A18,FONDSDECAISSE!A$5:O$52,15,0) -> 420000 | D18: 112685 | E18: =$R$56/$F$56*F18 -> 308.06226 | F18: =C18+D18+L18 -> 535685 | H18: =IF(J18="ECHEC",0,13000) -> 13000 | I18: =IF(J18="ESPECES",1000,0) -> 0 | J18: BANQUE | K18: =IF(H18=0,0,H18+L18+M18+N18+O18+P18) -> 20000 | L18: 3000 | M18: 500 | N18: 1000 | O18: 2500 | R18: =IF(Q18<=500000,(Q18*1*3/100),(Q18*12/100)) -> 0 | S18: =Q18+R18 -> 0
A19: AS201614 | B19: =VLOOKUP(A19,LISTADHERENT!A$5:H$51,2) -> KEPHE DAVID | C19: =VLOOKUP(A19,FONDSDECAISSE!A$5:O$52,15,0) -> 100000 | D19: 177 | E19: =$R$56/$F$56*F19 -> 59.335132 | F19: =C19+D19+L19 -> 103177 | H19: =IF(J19="ECHEC",0,13000) -> 13000 | I19: =IF(J19="ESPECES",1000,0) -> 0 | J19: BANQUE | K19: =IF(H19=0,0,H19+L19+M19+N19+O19+P19) -> 20000 | L19: 3000 | M19: 500 | N19: 1000 | O19: 2500 | R19: =IF(Q19<=500000,(Q19*1*3/100),(Q19*12/100)) -> 0 | S19: =Q19+R19 -> 0
A20: AS201615 | B20: =VLOOKUP(A20,LISTADHERENT!A$5:H$51,2) -> KEPSEU FRANCIS | C20: =VLOOKUP(A20,FONDSDECAISSE!A$5:O$52,15,0) -> 420000 | D20: 705425 | E20: =$R$56/$F$56*F20 -> 1225.742 | F20: =C20+D20+L20 -> 2131425 | H20: =IF(J20="ECHEC",0,13000) -> 13000 | I20: =IF(J20="ESPECES",1000,0) -> 0 | J20: BANQUE | K20: =IF(H20=0,0,H20+L20+M20+N20+O20+P20) -> 1023000 | L20: 1006000 | M20: 500 | N20: 1000 | O20: 2500 | R20: =IF(Q20<=500000,(Q20*1*3/100),(Q20*12/100)) -> 0 | S20: =Q20+R20 -> 0
A21: AS201616 | B21: =VLOOKUP(A21,LISTADHERENT!A$5:H$51,2) -> KOUAMOU EMMANUEL | C21: =VLOOKUP(A21,FONDSDECAISSE!A$5:O$52,15,0) -> 420000 | D21: 2357 | E21: =$R$56/$F$56*F21 -> 244.61473 | F21: =C21+D21+L21 -> 425357 | H21: =IF(J21="ECHEC",0,13000) -> 13000 | I21: =IF(J21="ESPECES",1000,0) -> 0 | J21: BANQUE | K21: =IF(H21=0,0,H21+L21+M21+N21+O21+P21) -> 20000 | L21: 3000 | M21: 500 | N21: 1000 | O21: 2500 | R21: =IF(Q21<=500000,(Q21*1*3/100),(Q21*12/100)) -> 0 | S21: =Q21+R21 -> 0
A22: AS201617 | B22: =VLOOKUP(A22,LISTADHERENT!A$5:H$51,2) -> KOUAMOU MOISE | C22: =VLOOKUP(A22,FONDSDECAISSE!A$5:O$52,15,0) -> 420000 | D22: 3048 | E22: =$R$56/$F$56*F22 -> 245.01211 | F22: =C22+D22+L22 -> 426048 | H22: =IF(J22="ECHEC",0,13000) -> 13000 | I22: =IF(J22="ESPECES",1000,0) -> 1000 | J22: ESPECES | K22: =IF(H22=0,0,H22+L22+M22+N22+O22+P22) -> 20000 | L22: 3000 | M22: 500 | N22: 1000 | O22: 2500 | R22: =IF(Q22<=500000,(Q22*1*3/100),(Q22*12/100)) -> 0 | S22: =Q22+R22 -> 0 | V22: 12000 | W22: 42723 | X22: TIEYAM ERNEST
A23: AS201618 | B23: =VLOOKUP(A23,LISTADHERENT!A$5:H$51,2) -> KOUAMO VICTOR PEGUY | C23: =VLOOKUP(A23,FONDSDECAISSE!A$5:O$52,15,0) -> 420000 | D23: 2686 | E23: =$R$56/$F$56*F23 -> 244.80393 | F23: =C23+D23+L23 -> 425686 | H23: =IF(J23="ECHEC",0,13000) -> 13000 | I23: =IF(J23="ESPECES",1000,0) -> 1000 | J23: ESPECES | K23: =IF(H23=0,0,H23+L23+M23+N23+O23+P23) -> 20000 | L23: 3000 | M23: 500 | N23: 1000 | O23: 2500 | R23: =IF(Q23<=500000,(Q23*1*3/100),(Q23*12/100)) -> 0 | S23: =Q23+R23 -> 0 | V23: 12000 | W23: 42723 | X23: NANKAM APPOLINAIRE
A24: AS201619 | B24: =VLOOKUP(A24,LISTADHERENT!A$5:H$51,2) -> KOUATCHO MESSACK | C24: =VLOOKUP(A24,FONDSDECAISSE!A$5:O$52,15,0) -> 420000 | D24: 3818 | E24: =$R$56/$F$56*F24 -> 245.45492 | F24: =C24+D24+L24 -> 426818 | H24: =IF(J24="ECHEC",0,13000) -> 13000 | I24: =IF(J24="ESPECES",1000,0) -> 1000 | J24: ESPECES | K24: =IF(H24=0,0,H24+L24+M24+N24+O24+P24) -> 20000 | L24: 3000 | M24: 500 | N24: 1000 | O24: 2500 | R24: =IF(Q24<=500000,(Q24*1*3/100),(Q24*12/100)) -> 0 | S24: =Q24+R24 -> 0
A25: AS201620 | B25: =VLOOKUP(A25,LISTADHERENT!A$5:H$51,2) -> LOWE JEAN | C25: =VLOOKUP(A25,FONDSDECAISSE!A$5:O$52,15,0) -> 420000 | D25: 2652 | E25: =$R$56/$F$56*F25 -> 244.78437 | F25: =C25+D25+L25 -> 425652 | H25: =IF(J25="ECHEC",0,13000) -> 13000 | I25: =IF(J25="ESPECES",1000,0) -> 0 | J25: BANQUE | K25: =IF(H25=0,0,H25+L25+M25+N25+O25+P25) -> 20000 | L25: 3000 | M25: 500 | N25: 1000 | O25: 2500 | R25: =IF(Q25<=500000,(Q25*1*3/100),(Q25*12/100)) -> 0 | S25: 82400
A26: AS201621 | B26: =VLOOKUP(A26,LISTADHERENT!A$5:H$51,2) -> NANKAM APPOLINAIRE | C26: =VLOOKUP(A26,FONDSDECAISSE!A$5:O$52,15,0) -> 420000 | D26: 2741 | E26: =$R$56/$F$56*F26 -> 244.83556 | F26: =C26+D26+L26 -> 425741 | H26: =IF(J26="ECHEC",0,13000) -> 13000 | I26: =IF(J26="ESPECES",1000,0) -> 0 | J26: BANQUE | K26: =IF(H26=0,0,H26+L26+M26+N26+O26+P26) -> 20000 | L26: 3000 | M26: 500 | N26: 1000 | O26: 2500 | R26: =IF(Q26<=500000,(Q26*1*3/100),(Q26*12/100)) -> 0 | S26: =Q26+R26 -> 0
A27: AS201622 | B27: =VLOOKUP(A27,LISTADHERENT!A$5:H$51,2) -> NDJOMO ETIENNE | C27: =VLOOKUP(A27,FONDSDECAISSE!A$5:O$52,15,0) -> 420000 | D27: 2818 | E27: =$R$56/$F$56*F27 -> 247.75524 | F27: =C27+D27+L27 -> 430818 | H27: =IF(J27="ECHEC",0,13000) -> 13000 | I27: =IF(J27="ESPECES",1000,0) -> 0 | J27: BANQUE | K27: =IF(H27=0,0,H27+L27+M27+N27+O27+P27) -> 25000 | L27: 8000 | M27: 500 | N27: 1000 | O27: 2500 | Q27: 400000 | R27: =IF(Q27<=500000,(Q27*1*3/100),(Q27*12/100)) -> 12000 | S27: 412000
A28: AS201623 | B28: =VLOOKUP(A28,LISTADHERENT!A$5:H$51,2) -> NDOMBOU JEAN CLAUDE | C28: =VLOOKUP(A28,FONDSDECAISSE!A$5:O$52,15,0) -> 420000 | D28: 0 | E28: =$R$56/$F$56*F28 -> 241.53402 | F28: =C28+D28+L28 -> 420000 | R28: =IF(Q28<=500000,(Q28*1*3/100),(Q28*12/100)) -> 0 | S28: =Q28+R28 -> 0
A29: AS201624 | B29: =VLOOKUP(A29,LISTADHERENT!A$5:H$51,2) -> NGONDIEP CLAUDE | C29: =VLOOKUP(A29,FONDSDECAISSE!A$5:O$52,15,0) -> 420000 | D29: 3250 | E29: =$R$56/$F$56*F29 -> 245.12827 | F29: =C29+D29+L29 -> 426250 | H29: =IF(J29="ECHEC",0,13000) -> 13000 | I29: =IF(J29="ESPECES",1000,0) -> 0 | J29: BANQUE | K29: =IF(H29=0,0,H29+L29+M29+N29+O29+P29) -> 20000 | L29: 3000 | M29: 500 | N29: 1000 | O29: 2500 | R29: =IF(Q29<=500000,(Q29*1*3/100),(Q29*12/100)) -> 0 | S29: =Q29+R29 -> 0
A30: AS201625 | B30: =VLOOKUP(A30,LISTADHERENT!A$5:H$51,2) -> NGONGANG JEAN THEODORE | C30: =VLOOKUP(A30,FONDSDECAISSE!A$5:O$52,15,0) -> 0 | D30: 106 | E30: =$R$56/$F$56*F30 -> 1.7862016 | F30: =C30+D30+L30 -> 3106 | H30: =IF(J30="ECHEC",0,13000) -> 13000 | I30: =IF(J30="ESPECES",1000,0) -> 0 | J30: BANQUE | K30: =IF(H30=0,0,H30+L30+M30+N30+O30+P30) -> 20000 | L30: 3000 | M30: 500 | N30: 1000 | O30: 2500 | R30: =IF(Q30<=500000,(Q30*1*3/100),(Q30*12/100)) -> 0 | S30: =Q30+R30 -> 0
A31: AS201626 | B31: =VLOOKUP(A31,LISTADHERENT!A$5:H$51,2) -> NGUIEMEGNI MATHIEU BLAISE | C31: =VLOOKUP(A31,FONDSDECAISSE!A$5:O$52,15,0) -> 420000 | D31: =565188-420000-50000-55055 -> 40133 | E31: =$R$56/$F$56*F31 -> 266.33899 | F31: =C31+D31+L31 -> 463133 | H31: =IF(J31="ECHEC",0,13000) -> 13000 | I31: =IF(J31="ESPECES",1000,0) -> 0 | J31: BANQUE | K31: =IF(H31=0,0,H31+L31+M31+N31+O31+P31) -> 20000 | L31: 3000 | M31: 500 | N31: 1000 | O31: 2500 | R31: =IF(Q31<=500000,(Q31*1*3/100),(Q31*12/100)) -> 0 | S31: =Q31+R31 -> 0
A32: AS201627 | B32: =VLOOKUP(A32,LISTADHERENT!A$5:H$51,2) -> NJEPDJIO MBOUKAM DELUXE | C32: =VLOOKUP(A32,FONDSDECAISSE!A$5:O$52,15,0) -> 420000 | D32: 2773 | E32: =$R$56/$F$56*F32 -> 244.85396 | F32: =C32+D32+L32 -> 425773 | H32: =IF(J32="ECHEC",0,13000) -> 13000 | I32: =IF(J32="ESPECES",1000,0) -> 0 | J32: BANQUE | K32: =IF(H32=0,0,H32+L32+M32+N32+O32+P32) -> 20000 | L32: 3000 | M32: 500 | N32: 1000 | O32: 2500 | R32: =IF(Q32<=500000,(Q32*1*3/100),(Q32*12/100)) -> 0 | S32: =Q32+R32 -> 0
A33: AS201628 | B33: =VLOOKUP(A33,LISTADHERENT!A$5:H$51,2) -> NKAMGANG JUSTIN DEJOLIE | C33: =VLOOKUP(A33,FONDSDECAISSE!A$5:O$52,15,0) -> 420000 | D33: =14208+55600 -> 69808 | E33: =$R$56/$F$56*F33 -> 285.12976 | F33: =C33+D33+L33 -> 495808 | H33: =IF(J33="ECHEC",0,13000) -> 13000 | I33: =IF(J33="ESPECES",1000,0) -> 1000 | J33: ESPECES | K33: =IF(H33=0,0,H33+L33+M33+N33+O33+P33) -> 23000 | L33: =6000 -> 6000 | M33: 500 | N33: 1000 | O33: 2500 | R33: =IF(Q33<=500000,(Q33*1*3/100),(Q33*12/100)) -> 0 | S33: =Q33+R33 -> 0
A34: AS201629 | B34: =VLOOKUP(A34,LISTADHERENT!A$5:H$51,2) -> NKEPSEU DIEUDONNE | C34: =VLOOKUP(A34,FONDSDECAISSE!A$5:O$52,15,0) -> 420000 | D34: 2772 | E34: =$R$56/$F$56*F34 -> 305.23689 | F34: =C34+D34+L34 -> 530772 | H34: =IF(J34="ECHEC",0,13000) -> 13000 | I34: =IF(J34="ESPECES",1000,0) -> 1000 | J34: ESPECES | K34: =IF(H34=0,0,H34+L34+M34+N34+O34+P34) -> 125000 | L34: 108000 | M34: 500 | N34: 1000 | O34: 2500 | R34: =IF(Q34<=500000,(Q34*1*3/100),(Q34*12/100)) -> 0 | S34: =Q34+R34 -> 0
D35: 0 | E35: =$R$56/$F$56*F35 -> 0 | F35: =C35+D35+L35 -> 0 | R35: =IF(Q35<=500000,(Q35*1*3/100),(Q35*12/100)) -> 0 | S35: =Q35+R35 -> 0
A36: AS201631 | B36: =VLOOKUP(A36,LISTADHERENT!A$5:H$51,2) -> NTEPDIE TUEMAC MZ | C36: =VLOOKUP(A36,FONDSDECAISSE!A$5:O$52,15,0) -> 0 | E36: =$R$56/$F$56*F36 -> 0 | F36: =C36+D36+L36 -> 0 | H36: =IF(J36="ECHEC",0,13000) -> 0 | I36: =IF(J36="ESPECES",1000,0) -> 0 | J36: ECHEC | K36: =IF(H36=0,0,H36+L36+M36+N36+O36+P36) -> 0 | R36: =IF(Q36<=500000,(Q36*1*3/100),(Q36*12/100)) -> 0 | S36: =Q36+R36 -> 0
D37: 0 | E37: =$R$56/$F$56*F37 -> 0 | F37: =C37+D37+L37 -> 0 | R37: =IF(Q37<=500000,(Q37*1*3/100),(Q37*12/100)) -> 0 | S37: =Q37+R37 -> 0
A38: AS201633 | B38: =VLOOKUP(A38,LISTADHERENT!A$5:H$51,2) -> PATEGO NJOSSU GUSTAVE | C38: =VLOOKUP(A38,FONDSDECAISSE!A$5:O$52,15,0) -> 420000 | D38: 2474 | E38: =$R$56/$F$56*F38 -> 244.68201 | F38: =C38+D38+L38 -> 425474 | H38: =IF(J38="ECHEC",0,13000) -> 13000 | I38: =IF(J38="ESPECES",1000,0) -> 0 | J38: BANQUE | K38: =IF(H38=0,0,H38+L38+M38+N38+O38+P38) -> 20000 | L38: 3000 | M38: 500 | N38: 1000 | O38: 2500 | R38: =IF(Q38<=500000,(Q38*1*3/100),(Q38*12/100)) -> 0 | S38: =Q38+R38 -> 0
A39: AS201634 | B39: =VLOOKUP(A39,LISTADHERENT!A$5:H$51,2) -> SEUNOU RICHELOT | C39: =VLOOKUP(A39,FONDSDECAISSE!A$5:O$52,15,0) -> 420000 | D39: 6756 | E39: =$R$56/$F$56*F39 -> 247.14451 | F39: =C39+D39+L39 -> 429756 | H39: =IF(J39="ECHEC",0,13000) -> 13000 | I39: =IF(J39="ESPECES",1000,0) -> 1000 | J39: ESPECES | K39: =IF(H39=0,0,H39+L39+M39+N39+O39+P39) -> 20000 | L39: 3000 | M39: 500 | N39: 1000 | O39: 2500 | R39: =IF(Q39<=500000,(Q39*1*3/100),(Q39*12/100)) -> 0 | S39: =Q39+R39 -> 0 | V39: 12000 | W39: 42723 | X39: NDJOMO ETIENNE
A40: AS201635 | B40: =VLOOKUP(A40,LISTADHERENT!A$5:H$51,2) -> SIME ABEL | C40: =VLOOKUP(A40,FONDSDECAISSE!A$5:O$52,15,0) -> 390000 | D40: 488 | E40: =$R$56/$F$56*F40 -> 226.28747 | F40: =C40+D40+L40 -> 393488 | H40: =IF(J40="ECHEC",0,13000) -> 13000 | I40: =IF(J40="ESPECES",1000,0) -> 1000 | J40: ESPECES | K40: =IF(H40=0,0,H40+L40+M40+N40+O40+P40) -> 20000 | L40: 3000 | M40: 500 | N40: 1000 | O40: 2500 | R40: =IF(Q40<=500000,(Q40*1*3/100),(Q40*12/100)) -> 0 | S40: =Q40+R40 -> 0
A41: AS201636 | B41: =VLOOKUP(A41,LISTADHERENT!A$5:H$51,2) -> SIME FONGANG ERIC | C41: =VLOOKUP(A41,FONDSDECAISSE!A$5:O$52,15,0) -> 420000 | D41: 4914 | E41: =$R$56/$F$56*F41 -> 246.08521 | F41: =C41+D41+L41 -> 427914 | H41: =IF(J41="ECHEC",0,13000) -> 13000 | I41: =IF(J41="ESPECES",1000,0) -> 0 | J41: BANQUE | K41: =IF(H41=0,0,H41+L41+M41+N41+O41+P41) -> 20000 | L41: 3000 | M41: 500 | N41: 1000 | O41: 2500 | R41: =IF(Q41<=500000,(Q41*1*3/100),(Q41*12/100)) -> 0 | S41: =Q41+R41 -> 0
A42: AS201637 | B42: =VLOOKUP(A42,LISTADHERENT!A$5:H$51,2) -> SIME MATHIEU | C42: =VLOOKUP(A42,FONDSDECAISSE!A$5:O$52,15,0) -> 420000 | D42: 4528 | E42: =$R$56/$F$56*F42 -> 245.86323 | F42: =C42+D42+L42 -> 427528 | H42: =IF(J42="ECHEC",0,13000) -> 13000 | I42: =IF(J42="ESPECES",1000,0) -> 1000 | J42: ESPECES | K42: =IF(H42=0,0,H42+L42+M42+N42+O42+P42) -> 20000 | L42: 3000 | M42: 500 | N42: 1000 | O42: 2500 | R42: =IF(Q42<=500000,(Q42*1*3/100),(Q42*12/100)) -> 0 | S42: =Q42+R42 -> 0
A43: AS201638 | B43: =VLOOKUP(A43,LISTADHERENT!A$5:H$51,2) -> SIME PIERRE | C43: =VLOOKUP(A43,FONDSDECAISSE!A$5:O$52,15,0) -> 420000 | D43: 105975 | E43: =$R$56/$F$56*F43 -> 307.07887 | F43: =C43+D43+L43 -> 533975 | H43: =IF(J43="ECHEC",0,13000) -> 13000 | I43: =IF(J43="ESPECES",1000,0) -> 0 | J43: BANQUE | K43: =IF(H43=0,0,H43+L43+M43+N43+O43+P43) -> 25000 | L43: 8000 | M43: 500 | N43: 1000 | O43: 2500 | R43: =IF(Q43<=500000,(Q43*1*3/100),(Q43*12/100)) -> 0 | S43: =Q43+R43 -> 0
A44: AS201639 | B44: =VLOOKUP(A44,LISTADHERENT!A$5:H$51,2) -> TAGNE NANGUEN MARTIN | C44: =VLOOKUP(A44,FONDSDECAISSE!A$5:O$52,15,0) -> 390000 | D44: 1621 | E44: =$R$56/$F$56*F44 -> 226.93904 | F44: =C44+D44+L44 -> 394621 | H44: =IF(J44="ECHEC",0,13000) -> 13000 | I44: =IF(J44="ESPECES",1000,0) -> 0 | J44: BANQUE | K44: =IF(H44=0,0,H44+L44+M44+N44+O44+P44) -> 20000 | L44: 3000 | M44: 500 | N44: 1000 | O44: 2500 | R44: =IF(Q44<=500000,(Q44*1*3/100),(Q44*12/100)) -> 0 | S44: =Q44+R44 -> 0
A45: AS201640 | B45: =VLOOKUP(A45,LISTADHERENT!A$5:H$51,2) -> TCHOUAMOU JEAN PAUL | C45: =VLOOKUP(A45,FONDSDECAISSE!A$5:O$52,15,0) -> 0 | D45: =106+14737 -> 14843 | E45: =$R$56/$F$56*F45 -> 10.26117 | F45: =C45+D45+L45 -> 17843 | H45: =IF(J45="ECHEC",0,13000) -> 13000 | I45: =IF(J45="ESPECES",1000,0) -> 0 | J45: BANQUE | K45: =IF(H45=0,0,H45+L45+M45+N45+O45+P45) -> 20000 | L45: 3000 | M45: 500 | N45: 1000 | O45: 2500 | R45: =IF(Q45<=500000,(Q45*1*3/100),(Q45*12/100)) -> 0 | S45: =Q45+R45 -> 0
A46: AS201641 | B46: =VLOOKUP(A46,LISTADHERENT!A$5:H$51,2) -> TCHOUAMOU MATHIEU | C46: =VLOOKUP(A46,FONDSDECAISSE!A$5:O$52,15,0) -> 420000 | D46: 2654 | E46: =$R$56/$F$56*F46 -> 244.78552 | F46: =C46+D46+L46 -> 425654 | H46: =IF(J46="ECHEC",0,13000) -> 13000 | I46: =IF(J46="ESPECES",1000,0) -> 0 | J46: BANQUE | K46: =IF(H46=0,0,H46+L46+M46+N46+O46+P46) -> 20000 | L46: 3000 | M46: 500 | N46: 1000 | O46: 2500 | R46: =IF(Q46<=500000,(Q46*1*3/100),(Q46*12/100)) -> 0 | S46: =Q46+R46 -> 0
A47: AS201642 | B47: =VLOOKUP(A47,LISTADHERENT!A$5:H$51,2) -> TCHOUANTE FRANCOIS | C47: =VLOOKUP(A47,FONDSDECAISSE!A$5:O$52,15,0) -> 403819 | D47: 25832 | E47: =$R$56/$F$56*F47 -> 248.80937 | F47: =C47+D47+L47 -> 432651 | H47: =IF(J47="ECHEC",0,13000) -> 13000 | I47: =IF(J47="ESPECES",1000,0) -> 1000 | J47: ESPECES | K47: =IF(H47=0,0,H47+L47+M47+N47+O47+P47) -> 20000 | L47: 3000 | M47: 500 | N47: 1000 | O47: 2500 | R47: =IF(Q47<=500000,(Q47*1*3/100),(Q47*12/100)) -> 0 | S47: =Q47+R47 -> 0
A48: AS201643 | B48: =VLOOKUP(A48,LISTADHERENT!A$5:H$51,2) -> TCHOUTOU NANA CLAUDE | C48: =VLOOKUP(A48,FONDSDECAISSE!A$5:O$52,15,0) -> 0 | E48: =$R$56/$F$56*F48 -> 1.725243 | F48: =C48+D48+L48 -> 3000 | H48: =IF(J48="ECHEC",0,13000) -> 13000 | I48: =IF(J48="ESPECES",1000,0) -> 1000 | J48: ESPECES | K48: =IF(H48=0,0,H48+L48+M48+N48+O48+P48) -> 20000 | L48: 3000 | M48: 500 | N48: 1000 | O48: 2500 | R48: =IF(Q48<=500000,(Q48*1*3/100),(Q48*12/100)) -> 0 | S48: =Q48+R48 -> 0
A49: AS201644 | B49: =VLOOKUP(A49,LISTADHERENT!A$5:H$51,2) -> TIEYAM ERNEST | C49: =VLOOKUP(A49,FONDSDECAISSE!A$5:O$52,15,0) -> 420000 | D49: 2593 | E49: =$R$56/$F$56*F49 -> 244.75045 | F49: =C49+D49+L49 -> 425593 | H49: =IF(J49="ECHEC",0,13000) -> 13000 | I49: =IF(J49="ESPECES",1000,0) -> 0 | J49: BANQUE | K49: =IF(H49=0,0,H49+L49+M49+N49+O49+P49) -> 20000 | L49: 3000 | M49: 500 | N49: 1000 | O49: 2500 | R49: =IF(Q49<=500000,(Q49*1*3/100),(Q49*12/100)) -> 0 | S49: =Q49+R49 -> 0
A50: AS201645 | B50: =VLOOKUP(A50,LISTADHERENT!A$5:H$51,2) -> TUGMA PIERRE LOTI | C50: =VLOOKUP(A50,FONDSDECAISSE!A$5:O$52,15,0) -> 420000 | D50: 2503 | E50: =$R$56/$F$56*F50 -> 244.69869 | F50: =C50+D50+L50 -> 425503 | H50: =IF(J50="ECHEC",0,13000) -> 13000 | I50: =IF(J50="ESPECES",1000,0) -> 0 | J50: BANQUE | K50: =IF(H50=0,0,H50+L50+M50+N50+O50+P50) -> 20000 | L50: 3000 | M50: 500 | N50: 1000 | O50: 2500 | R50: =IF(Q50<=500000,(Q50*1*3/100),(Q50*12/100)) -> 0 | S50: =Q50+R50 -> 0
A51: AS201646 | B51: =VLOOKUP(A51,LISTADHERENT!A$5:H$51,2) -> YEPMOU JEAN JACQUES | C51: =VLOOKUP(A51,FONDSDECAISSE!A$5:O$52,15,0) -> 420000 | D51: 393982 | E51: =$R$56/$F$56*F51 -> 469.83082 | F51: =C51+D51+L51 -> 816982 | H51: =IF(J51="ECHEC",0,13000) -> 13000 | I51: =IF(J51="ESPECES",1000,0) -> 1000 | J51: ESPECES | K51: =IF(H51=0,0,H51+L51+M51+N51+O51+P51) -> 20000 | L51: 3000 | M51: 500 | N51: 1000 | O51: 2500 | R51: =IF(Q51<=500000,(Q51*1*3/100),(Q51*12/100)) -> 0 | S51: =Q51+R51 -> 0
A52: AS201647 | B52: =VLOOKUP(A52,LISTADHERENT!A$5:H$51,2) -> YOUMBI EMMANUEL | C52: =VLOOKUP(A52,FONDSDECAISSE!A$5:O$52,15,0) -> 420000 | D52: 883628 | E52: =$R$56/$F$56*F52 -> 751.41693 | F52: =C52+D52+L52 -> 1306628 | H52: =IF(J52="ECHEC",0,13000) -> 13000 | I52: =IF(J52="ESPECES",1000,0) -> 1000 | J52: ESPECES | K52: =IF(H52=0,0,H52+L52+M52+N52+O52+P52) -> 20000 | L52: 3000 | M52: 500 | N52: 1000 | O52: 2500 | R52: =IF(Q52<=500000,(Q52*1*3/100),(Q52*12/100)) -> 0 | S52: =Q52+R52 -> 0
A56: TOTAL | C56: =SUM(C5:C52) -> 16033819 | D56: =SUM(D5:D52) -> 3525807 | E56: =SUM(E5:E52) -> 12000 | F56: =SUM(F5:F52) -> 20866626 | G56: =SUM(G5:G52) -> 0 | H56: =SUM(H5:H52) -> 546000 | I56: =SUM(I5:I52) -> 16000 | K56: =SUM(K5:K52) -> 2021000 | L56: =SUM(L5:L52) -> 1307000 | M56: =SUM(M5:M52) -> 21000 | N56: =SUM(N5:N52) -> 42000 | O56: =SUM(O5:O52) -> 105000 | P56: =SUM(P5:P52) -> 0 | Q56: =SUM(Q5:Q52) -> 400000 | R56: =SUM(R5:R52) -> 12000 | ... T56: =SUM(T5:T52) -> 0

Sheet TONT20000JANV2017
A1: ASSOCIATION | B1: ASELBY
A2: ANNEE | B2: 2016/2017
A3: TONTINE | B3: 20 000
A4: MATRICULE | B4: NOM ET PRENOM | C4: REPARTITION INTERET | D4: CAPITAL COMPOSE | E4: SANCTION | F4: MONTANT TONTINE | G4: PENALITE | H4: MODE VERSEMENT | I4: MONTANT VERSE | J4: EPARGNE | K4: FONDS DE ROULEMENT | L4: FRAIS EXCEPTIONNEL | M4: COLLATION | N4: MUTUELLE | O4: EMPRUNT | P4: INTERET EMPRUNT | Q4: REMBOURSEMENT | R4: PENALITE EMPRUNT | S4: PENALITE FONDS | T4: INTERET ACHAT | U4: DATE ACHAT | V4: AVALISTE
A5: AS201648 | B5: =VLOOKUP(A5,LISTADHERENT!A$5:H$52,2,0) -> ASELBY | C5: =$P$56/$D$56*D5 -> 0 | D5: =TONT20000DEC2016!F5+TONT20000DEC2016!E5+TONT20000JANV2017!J5 -> 355301.21
A6: AS201601 | B6: =VLOOKUP(A6,LISTADHERENT!A$5:H$52,2,0) -> BAKOP ACHILLE | C6: =$P$56/$D$56*D6 -> 0 | D6: =TONT20000DEC2016!F6+TONT20000DEC2016!E6+TONT20000JANV2017!J6 -> 472264.43 | F6: =IF(H6="ECHEC",0,13000) -> 0 | G6: =IF(H6="ESPECES",1000,0) -> 0 | H6: ECHEC | I6: =IF(F6=0,0,J6+K6+L6+M6+N6+#REF!) -> 0 | P6: =IF(O6<=500000,(O6*1*3/100),(O6*12/100)) -> 0
A7: AS201602 | B7: =VLOOKUP(A7,LISTADHERENT!A$5:H$51,2) -> BOUTCHOUANG WILLIAM | C7: =$P$56/$D$56*D7 -> 0 | D7: =TONT20000DEC2016!F7+TONT20000DEC2016!E7+TONT20000JANV2017!J7 -> 428964.82 | F7: =IF(H7="ECHEC",0,13000) -> 13000 | G7: =IF(H7="ESPECES",1000,0) -> 1000 | H7: ESPECES | I7: =IF(F7=0,0,F7+J7+K7+L7+M7+N7) -> 20000 | J7: 3000 | K7: 500 | L7: 1000 | M7: 2500 | P7: =IF(O7<=500000,(O7*1*3/100),(O7*12/100)) -> 0
A8: AS201603 | B8: =VLOOKUP(A8,LISTADHERENT!A$5:H$51,2) -> CHINGUE FABRICE | C8: =$P$56/$D$56*D8 -> 0 | D8: =TONT20000DEC2016!F8+TONT20000DEC2016!E8+TONT20000JANV2017!J8 -> 432120.64 | F8: =IF(H8="ECHEC",0,13000) -> 13000 | G8: =IF(H8="ESPECES",1000,0) -> 1000 | H8: ESPECES | I8: =IF(F8=0,0,F8+J8+K8+L8+M8+N8) -> 20000 | J8: 3000 | K8: 500 | L8: 1000 | M8: 2500 | P8: =IF(O8<=500000,(O8*1*3/100),(O8*12/100)) -> 0
A9: AS201604 | B9: =VLOOKUP(A9,LISTADHERENT!A$5:H$51,2) -> DJOMO JEAN PAUL | C9: =$P$56/$D$56*D9 -> 0 | D9: =TONT20000DEC2016!F9+TONT20000DEC2016!E9+TONT20000JANV2017!J9 -> 428814.74 | F9: =IF(H9="ECHEC",0,13000) -> 13000 | G9: =IF(H9="ESPECES",1000,0) -> 0 | H9: BANQUE | I9: =IF(F9=0,0,F9+J9+K9+L9+M9+N9) -> 20000 | J9: 3000 | K9: 500 | L9: 1000 | M9: 2500 | P9: =IF(O9<=500000,(O9*1*3/100),(O9*12/100)) -> 0
A10: AS201605 | B10: =VLOOKUP(A10,LISTADHERENT!A$5:H$51,2) -> DJOUKWE NANGUEN GUY BLAISE | C10: =$P$56/$D$56*D10 -> 0 | D10: =TONT20000DEC2016!F10+TONT20000DEC2016!E10+TONT20000JANV2017!J10 -> 428941.81 | F10: =IF(H10="ECHEC",0,13000) -> 13000 | G10: =IF(H10="ESPECES",1000,0) -> 1000 | H10: ESPECES | I10: =IF(F10=0,0,F10+J10+K10+L10+M10+N10) -> 20000 | J10: 3000 | K10: 500 | L10: 1000 | M10: 2500 | P10: =IF(O10<=500000,(O10*1*3/100),(O10*12/100)) -> 0
D11: =TONT20000DEC2016!F11+TONT20000DEC2016!E11+TONT20000JANV2017!J11 -> 0
A12: AS201607 | B12: =VLOOKUP(A12,LISTADHERENT!A$5:H$51,2) -> DJOUNKEP SAMUEL | C12: =$P$56/$D$56*D12 -> 0 | D12: =TONT20000DEC2016!F12+TONT20000DEC2016!E12+TONT20000JANV2017!J12 -> 1062148.7 | F12: =IF(H12="ECHEC",0,13000) -> 13000 | G12: =IF(H12="ESPECES",1000,0) -> 0 | H12: BANQUE | I12: =IF(F12=0,0,F12+J12+K12+L12+M12+N12) -> 20000 | J12: 3000 | K12: 500 | L12: 1000 | M12: 2500 | P12: =IF(O12<=500000,(O12*1*3/100),(O12*12/100)) -> 0
A13: AS201608 | B13: =VLOOKUP(A13,LISTADHERENT!A$5:H$51,2) -> DJUOMBESSY ANTOINE | C13: =$P$56/$D$56*D13 -> 0 | D13: =TONT20000DEC2016!F13+TONT20000DEC2016!E13+TONT20000JANV2017!J13 -> 428990.84 | F13: =IF(H13="ECHEC",0,13000) -> 13000 | G13: =IF(H13="ESPECES",1000,0) -> 0 | H13: BANQUE | I13: =IF(F13=0,0,F13+J13+K13+L13+M13+N13) -> 20000 | J13: 3000 | K13: 500 | L13: 1000 | M13: 2500 | P13: =IF(O13<=500000,(O13*1*3/100),(O13*12/100)) -> 0
A14: AS201609 | B14: =VLOOKUP(A14,LISTADHERENT!A$5:H$51,2) -> DONHOU DAVID | C14: =$P$56/$D$56*D14 -> 0 | D14: =TONT20000DEC2016!F14+TONT20000DEC2016!E14+TONT20000JANV2017!J14 -> 480022.17 | F14: =IF(H14="ECHEC",0,13000) -> 13000 | G14: =IF(H14="ESPECES",1000,0) -> 1000 | H14: ESPECES | I14: =IF(F14=0,0,F14+J14+K14+L14+M14+N14) -> 20000 | J14: 3000 | K14: 500 | L14: 1000 | M14: 2500 | P14: =IF(O14<=500000,(O14*1*3/100),(O14*12/100)) -> 0
A15: AS201610 | B15: =VLOOKUP(A15,LISTADHERENT!A$5:H$51,2) -> FOTSO THOMAS | C15: =$P$56/$D$56*D15 -> 0 | D15: =TONT20000DEC2016!F15+TONT20000DEC2016!E15+TONT20000JANV2017!J15 -> 428766.71 | F15: =IF(H15="ECHEC",0,13000) -> 13000 | G15: =IF(H15="ESPECES",1000,0) -> 1000 | H15: ESPECES | I15: =IF(F15=0,0,F15+J15+K15+L15+M15+N15) -> 20000 | J15: 3000 | K15: 500 | L15: 1000 | M15: 2500 | P15: =IF(O15<=500000,(O15*1*3/100),(O15*12/100)) -> 0
A16: AS201611 | B16: =VLOOKUP(A16,LISTADHERENT!A$5:H$51,2) -> HENGUE PAUL OMER | C16: =$P$56/$D$56*D16 -> 0 | D16: =TONT20000DEC2016!F16+TONT20000DEC2016!E16+TONT20000JANV2017!J16 -> 492281.21 | F16: 13000 | G16: =IF(H16="ESPECES",1000,0) -> 1000 | H16: ESPECES | I16: =IF(F16=0,0,F16+J16+K16+L16+M16+N16) -> 20000 | J16: 3000 | K16: 500 | L16: 1000 | M16: 2500 | P16: =IF(O16<=500000,(O16*1*3/100),(O16*12/100)) -> 0
A17: AS201612 | B17: =VLOOKUP(A17,LISTADHERENT!A$5:H$51,2) -> HODIEP JULES | C17: =$P$56/$D$56*D17 -> 0 | D17: =TONT20000DEC2016!F17+TONT20000DEC2016!E17+TONT20000JANV2017!J17 -> 50288.904 | F17: =IF(H17="ECHEC",0,13000) -> 0 | G17: =IF(H17="ESPECES",1000,0) -> 0 | H17: ECHEC | I17: =IF(F17=0,0,F17+J17+K17+L17+M17+N17) -> 0 | P17: =IF(O17<=500000,(O17*1*3/100),(O17*12/100)) -> 0
A18: AS201613 | B18: =VLOOKUP(A18,LISTADHERENT!A$5:H$51,2) -> HOTCHO BENJAMIN | C18: =$P$56/$D$56*D18 -> 0 | D18: =TONT20000DEC2016!F18+TONT20000DEC2016!E18+TONT20000JANV2017!J18 -> 538993.06 | F18: =IF(H18="ECHEC",0,13000) -> 13000 | G18: =IF(H18="ESPECES",1000,0) -> 0 | H18: BANQUE | I18: =IF(F18=0,0,F18+J18+K18+L18+M18+N18) -> 20000 | J18: 3000 | K18: 500 | L18: 1000 | M18: 2500 | P18: =IF(O18<=500000,(O18*1*3/100),(O18*12/100)) -> 0
A19: AS201614 | B19: =VLOOKUP(A19,LISTADHERENT!A$5:H$51,2) -> KEPHE DAVID | C19: =$P$56/$D$56*D19 -> 0 | D19: =TONT20000DEC2016!F19+TONT20000DEC2016!E19+TONT20000JANV2017!J19 -> 106236.34 | F19: =IF(H19="ECHEC",0,13000) -> 13000 | G19: =IF(H19="ESPECES",1000,0) -> 0 | H19: BANQUE | I19: =IF(F19=0,0,F19+J19+K19+L19+M19+N19) -> 20000 | J19: 3000 | K19: 500 | L19: 1000 | M19: 2500 | P19: =IF(O19<=500000,(O19*1*3/100),(O19*12/100)) -> 0
A20: AS201615 | B20: =VLOOKUP(A20,LISTADHERENT!A$5:H$51,2) -> KEPSEU FRANCIS | C20: =$P$56/$D$56*D20 -> 0 | D20: =TONT20000DEC2016!F20+TONT20000DEC2016!E20+TONT20000JANV2017!J20 -> 2138650.7 | F20: =IF(H20="ECHEC",0,13000) -> 13000 | G20: =IF(H20="ESPECES",1000,0) -> 0 | H20: BANQUE | I20: =IF(F20=0,0,F20+J20+K20+L20+M20+N20) -> 23000 | J20: 6000 | K20: 500 | L20: 1000 | M20: 2500 | P20: =IF(O20<=500000,(O20*1*3/100),(O20*12/100)) -> 0
A21: AS201616 | B21: =VLOOKUP(A21,LISTADHERENT!A$5:H$51,2) -> KOUAMOU EMMANUEL | C21: =$P$56/$D$56*D21 -> 0 | D21: =TONT20000DEC2016!F21+TONT20000DEC2016!E21+TONT20000JANV2017!J21 -> 428601.61 | F21: =IF(H21="ECHEC",0,13000) -> 13000 | G21: =IF(H21="ESPECES",1000,0) -> 0 | H21: BANQUE | I21: =IF(F21=0,0,F21+J21+K21+L21+M21+N21) -> 20000 | J21: 3000 | K21: 500 | L21: 1000 | M21: 2500 | P21: =IF(O21<=500000,(O21*1*3/100),(O21*12/100)) -> 0
A22: AS201617 | B22: =VLOOKUP(A22,LISTADHERENT!A$5:H$51,2) -> KOUAMOU MOISE | C22: =$P$56/$D$56*D22 -> 0 | D22: =TONT20000DEC2016!F22+TONT20000DEC2016!E22+TONT20000JANV2017!J22 -> 429293.01 | F22: =IF(H22="ECHEC",0,13000) -> 13000 | G22: =IF(H22="ESPECES",1000,0) -> 0 | H22: BANQUE | I22: =IF(F22=0,0,F22+J22+K22+L22+M22+N22) -> 20000 | J22: 3000 | K22: 500 | L22: 1000 | M22: 2500 | P22: =IF(O22<=500000,(O22*1*3/100),(O22*12/100)) -> 0
A23: AS201618 | B23: =VLOOKUP(A23,LISTADHERENT!A$5:H$51,2) -> KOUAMO VICTOR PEGUY | C23: =$P$56/$D$56*D23 -> 0 | D23: =TONT20000DEC2016!F23+TONT20000DEC2016!E23+TONT20000JANV2017!J23 -> 428930.8 | F23: =IF(H23="ECHEC",0,13000) -> 13000 | G23: =IF(H23="ESPECES",1000,0) -> 1000 | H23: ESPECES | I23: =IF(F23=0,0,F23+J23+K23+L23+M23+N23) -> 20000 | J23: 3000 | K23: 500 | L23: 1000 | M23: 2500 | P23: =IF(O23<=500000,(O23*1*3/100),(O23*12/100)) -> 0
A24: AS201619 | B24: =VLOOKUP(A24,LISTADHERENT!A$5:H$51,2) -> KOUATCHO MESSACK | C24: =$P$56/$D$56*D24 -> 0 | D24: =TONT20000DEC2016!F24+TONT20000DEC2016!E24+TONT20000JANV2017!J24 -> 430063.45 | F24: =IF(H24="ECHEC",0,13000) -> 13000 | G24: =IF(H24="ESPECES",1000,0) -> 1000 | H24: ESPECES | I24: =IF(F24=0,0,F24+J24+K24+L24+M24+N24) -> 20000 | J24: 3000 | K24: 500 | L24: 1000 | M24: 2500 | P24: =IF(O24<=500000,(O24*1*3/100),(O24*12/100)) -> 0
A25: AS201620 | B25: =VLOOKUP(A25,LISTADHERENT!A$5:H$51,2) -> LOWE JEAN | C25: =$P$56/$D$56*D25 -> 0 | D25: =TONT20000DEC2016!F25+TONT20000DEC2016!E25+TONT20000JANV2017!J25 -> 428896.78 | F25: =IF(H25="ECHEC",0,13000) -> 13000 | G25: =IF(H25="ESPECES",1000,0) -> 0 | H25: BANQUE | I25: =IF(F25=0,0,F25+J25+K25+L25+M25+N25) -> 20000 | J25: 3000 | K25: 500 | L25: 1000 | M25: 2500 | P25: =IF(O25<=500000,(O25*1*3/100),(O25*12/100)) -> 0
A26: AS201621 | B26: =VLOOKUP(A26,LISTADHERENT!A$5:H$51,2) -> NANKAM APPOLINAIRE | C26: =$P$56/$D$56*D26 -> 0 | D26: =TONT20000DEC2016!F26+TONT20000DEC2016!E26+TONT20000JANV2017!J26 -> 428985.84 | F26: =IF(H26="ECHEC",0,13000) -> 13000 | G26: =IF(H26="ESPECES",1000,0) -> 0 | H26: BANQUE | I26: =IF(F26=0,0,F26+J26+K26+L26+M26+N26) -> 20000 | J26: 3000 | K26: 500 | L26: 1000 | M26: 2500 | P26: =IF(O26<=500000,(O26*1*3/100),(O26*12/100)) -> 0
A27: AS201622 | B27: =VLOOKUP(A27,LISTADHERENT!A$5:H$51,2) -> NDJOMO ETIENNE | C27: =$P$56/$D$56*D27 -> 0 | D27: =TONT20000DEC2016!F27+TONT20000DEC2016!E27+TONT20000JANV2017!J27 -> 439065.76 | F27: =IF(H27="ECHEC",0,13000) -> 13000 | G27: =IF(H27="ESPECES",1000,0) -> 0 | H27: BANQUE | I27: =IF(F27=0,0,F27+J27+K27+L27+M27+N27) -> 25000 | J27: 8000 | K27: 500 | L27: 1000 | M27: 2500 | P27: =IF(O27<=500000,(O27*1*3/100),(O27*12/100)) -> 0
A28: AS201623 | B28: =VLOOKUP(A28,LISTADHERENT!A$5:H$51,2) -> NDOMBOU JEAN CLAUDE | C28: =$P$56/$D$56*D28 -> 0 | D28: =TONT20000DEC2016!F28+TONT20000DEC2016!E28+TONT20000JANV2017!J28 -> 420241.53
A29: AS201624 | B29: =VLOOKUP(A29,LISTADHERENT!A$5:H$51,2) -> NGONDIEP CLAUDE | C29: =$P$56/$D$56*D29 -> 0 | D29: =TONT20000DEC2016!F29+TONT20000DEC2016!E29+TONT20000JANV2017!J29 -> 438495.13 | F29: =IF(H29="ECHEC",0,13000) -> 13000 | G29: =IF(H29="ESPECES",1000,0) -> 0 | H29: BANQUE | I29: =IF(F29=0,0,F29+J29+K29+L29+M29+N29) -> 29000 | J29: 12000 | K29: 500 | L29: 1000 | M29: 2500 | P29: =IF(O29<=500000,(O29*1*3/100),(O29*12/100)) -> 0
A30: AS201625 | B30: =VLOOKUP(A30,LISTADHERENT!A$5:H$51,2) -> NGONGANG JEAN THEODORE | C30: =$P$56/$D$56*D30 -> 0 | D30: =TONT20000DEC2016!F30+TONT20000DEC2016!E30+TONT20000JANV2017!J30 -> 3107.7862 | F30: =IF(H30="ECHEC",0,13000) -> 0 | G30: =IF(H30="ESPECES",1000,0) -> 0 | H30: ECHEC | I30: =IF(F30=0,0,F30+J30+K30+L30+M30+N30) -> 0 | P30: =IF(O30<=500000,(O30*1*3/100),(O30*12/100)) -> 0
A31: AS201626 | B31: =VLOOKUP(A31,LISTADHERENT!A$5:H$51,2) -> NGUIEMEGNI MATHIEU BLAISE | C31: =$P$56/$D$56*D31 -> 0 | D31: =TONT20000DEC2016!F31+TONT20000DEC2016!E31+TONT20000JANV2017!J31 -> 466399.34 | F31: =IF(H31="ECHEC",0,13000) -> 13000 | G31: =IF(H31="ESPECES",1000,0) -> 0 | H31: BANQUE | I31: =IF(F31=0,0,F31+J31+K31+L31+M31+N31) -> 20000 | J31: 3000 | K31: 500 | L31: 1000 | M31: 2500 | P31: =IF(O31<=500000,(O31*1*3/100),(O31*12/100)) -> 0
A32: AS201627 | B32: =VLOOKUP(A32,LISTADHERENT!A$5:H$51,2) -> NJEPDJIO MBOUKAM DELUXE | C32: =$P$56/$D$56*D32 -> 0 | D32: =TONT20000DEC2016!F32+TONT20000DEC2016!E32+TONT20000JANV2017!J32 -> 434017.85 | F32: =IF(H32="ECHEC",0,13000) -> 13000 | G32: =IF(H32="ESPECES",1000,0) -> 1000 | H32: ESPECES | I32: =IF(F32=0,0,F32+J32+K32+L32+M32+N32) -> 25000 | J32: 8000 | K32: 500 | L32: 1000 | M32: 2500 | P32: =IF(O32<=500000,(O32*1*3/100),(O32*12/100)) -> 0
A33: AS201628 | B33: =VLOOKUP(A33,LISTADHERENT!A$5:H$51,2) -> NKAMGANG JUSTIN DEJOLIE | C33: =$P$56/$D$56*D33 -> 0 | D33: =TONT20000DEC2016!F33+TONT20000DEC2016!E33+TONT20000JANV2017!J33 -> 504093.13 | F33: =IF(H33="ECHEC",0,13000) -> 13000 | G33: =IF(H33="ESPECES",1000,0) -> 1000 | H33: ESPECES | I33: =IF(F33=0,0,F33+J33+K33+L33+M33+N33) -> 25000 | J33: 8000 | K33: 500 | L33: 1000 | M33: 2500 | P33: =IF(O33<=500000,(O33*1*3/100),(O33*12/100)) -> 0
A34: AS201629 | B34: =VLOOKUP(A34,LISTADHERENT!A$5:H$51,2) -> NKEPSEU DIEUDONNE | C34: =$P$56/$D$56*D34 -> 0 | D34: =TONT20000DEC2016!F34+TONT20000DEC2016!E34+TONT20000JANV2017!J34 -> 539077.24 | F34: =IF(H34="ECHEC",0,13000) -> 13000 | G34: =IF(H34="ESPECES",1000,0) -> 1000 | H34: ESPECES | I34: =IF(F34=0,0,F34+J34+K34+L34+M34+N34) -> 25000 | J34: 8000 | K34: 500 | L34: 1000 | M34: 2500 | P34: =IF(O34<=500000,(O34*1*3/100),(O34*12/100)) -> 0
D35: =TONT20000DEC2016!F35+TONT20000DEC2016!E35+TONT20000JANV2017!J35 -> 0
A36: AS201631 | B36: =VLOOKUP(A36,LISTADHERENT!A$5:H$51,2) -> NTEPDIE TUEMAC MZ | C36: =$P$56/$D$56*D36 -> 0 | D36: =TONT20000DEC2016!F36+TONT20000DEC2016!E36+TONT20000JANV2017!J36 -> 0 | F36: =IF(H36="ECHEC",0,13000) -> 0 | G36: =IF(H36="ESPECES",1000,0) -> 0 | H36: ECHEC | I36: =IF(F36=0,0,F36+J36+K36+L36+M36+N36) -> 0 | P36: =IF(O36<=500000,(O36*1*3/100),(O36*12/100)) -> 0
D37: =TONT20000DEC2016!F37+TONT20000DEC2016!E37+TONT20000JANV2017!J37 -> 0
A38: AS201633 | B38: =VLOOKUP(A38,LISTADHERENT!A$5:H$51,2) -> PATEGO NJOSSU GUSTAVE | C38: =$P$56/$D$56*D38 -> 0 | D38: =TONT20000DEC2016!F38+TONT20000DEC2016!E38+TONT20000JANV2017!J38 -> 428718.68 | F38: =IF(H38="ECHEC",0,13000) -> 13000 | G38: =IF(H38="ESPECES",1000,0) -> 0 | H38: BANQUE | I38: =IF(F38=0,0,F38+J38+K38+L38+M38+N38) -> 20000 | J38: 3000 | K38: 500 | L38: 1000 | M38: 2500 | P38: =IF(O38<=500000,(O38*1*3/100),(O38*12/100)) -> 0
A39: AS201634 | B39: =VLOOKUP(A39,LISTADHERENT!A$5:H$51,2) -> SEUNOU RICHELOT | C39: =$P$56/$D$56*D39 -> 0 | D39: =TONT20000DEC2016!F39+TONT20000DEC2016!E39+TONT20000JANV2017!J39 -> 433003.14 | F39: =IF(H39="ECHEC",0,13000) -> 13000 | G39: =IF(H39="ESPECES",1000,0) -> 1000 | H39: ESPECES | I39: =IF(F39=0,0,F39+J39+K39+L39+M39+N39) -> 20000 | J39: 3000 | K39: 500 | L39: 1000 | M39: 2500 | P39: =IF(O39<=500000,(O39*1*3/100),(O39*12/100)) -> 0
A40: AS201635 | B40: =VLOOKUP(A40,LISTADHERENT!A$5:H$51,2) -> SIME ABEL | C40: =$P$56/$D$56*D40 -> 0 | D40: =TONT20000DEC2016!F40+TONT20000DEC2016!E40+TONT20000JANV2017!J40 -> 396714.29 | F40: =IF(H40="ECHEC",0,13000) -> 13000 | G40: =IF(H40="ESPECES",1000,0) -> 1000 | H40: ESPECES | I40: =IF(F40=0,0,F40+J40+K40+L40+M40+N40) -> 20000 | J40: 3000 | K40: 500 | L40: 1000 | M40: 2500 | P40: =IF(O40<=500000,(O40*1*3/100),(O40*12/100)) -> 0
A41: AS201636 | B41: =VLOOKUP(A41,LISTADHERENT!A$5:H$51,2) -> SIME FONGANG ERIC | C41: =$P$56/$D$56*D41 -> 0 | D41: =TONT20000DEC2016!F41+TONT20000DEC2016!E41+TONT20000JANV2017!J41 -> 431160.09 | F41: =IF(H41="ECHEC",0,13000) -> 13000 | G41: =IF(H41="ESPECES",1000,0) -> 0 | H41: BANQUE | I41: =IF(F41=0,0,F41+J41+K41+L41+M41+N41) -> 20000 | J41: 3000 | K41: 500 | L41: 1000 | M41: 2500 | P41: =IF(O41<=500000,(O41*1*3/100),(O41*12/100)) -> 0
A42: AS201637 | B42: =VLOOKUP(A42,LISTADHERENT!A$5:H$51,2) -> SIME MATHIEU | C42: =$P$56/$D$56*D42 -> 0 | D42: =TONT20000DEC2016!F42+TONT20000DEC2016!E42+TONT20000JANV2017!J42 -> 430773.86 | F42: =IF(H42="ECHEC",0,13000) -> 13000 | G42: =IF(H42="ESPECES",1000,0) -> 0 | H42: BANQUE | I42: =IF(F42=0,0,F42+J42+K42+L42+M42+N42) -> 20000 | J42: 3000 | K42: 500 | L42: 1000 | M42: 2500 | P42: =IF(O42<=500000,(O42*1*3/100),(O42*12/100)) -> 0
A43: AS201638 | B43: =VLOOKUP(A43,LISTADHERENT!A$5:H$51,2) -> SIME PIERRE | C43: =$P$56/$D$56*D43 -> 0 | D43: =TONT20000DEC2016!F43+TONT20000DEC2016!E43+TONT20000JANV2017!J43 -> 547282.08 | F43: =IF(H43="ECHEC",0,13000) -> 13000 | G43: =IF(H43="ESPECES",1000,0) -> 0 | H43: BANQUE | I43: =IF(F43=0,0,F43+J43+K43+L43+M43+N43) -> 30000 | J43: 13000 | K43: 500 | L43: 1000 | M43: 2500 | P43: =IF(O43<=500000,(O43*1*3/100),(O43*12/100)) -> 0
A44: AS201639 | B44: =VLOOKUP(A44,LISTADHERENT!A$5:H$51,2) -> TAGNE NANGUEN MARTIN | C44: =$P$56/$D$56*D44 -> 0 | D44: =TONT20000DEC2016!F44+TONT20000DEC2016!E44+TONT20000JANV2017!J44 -> 397847.94 | F44: =IF(H44="ECHEC",0,13000) -> 13000 | G44: =IF(H44="ESPECES",1000,0) -> 0 | H44: BANQUE | I44: =IF(F44=0,0,F44+J44+K44+L44+M44+N44) -> 20000 | J44: 3000 | K44: 500 | L44: 1000 | M44: 2500 | P44: =IF(O44<=500000,(O44*1*3/100),(O44*12/100)) -> 0
A45: AS201640 | B45: =VLOOKUP(A45,LISTADHERENT!A$5:H$51,2) -> TCHOUAMOU JEAN PAUL | C45: =$P$56/$D$56*D45 -> 0 | D45: =TONT20000DEC2016!F45+TONT20000DEC2016!E45+TONT20000JANV2017!J45 -> 17853.261 | F45: =IF(H45="ECHEC",0,13000) -> 0 | G45: =IF(H45="ESPECES",1000,0) -> 0 | H45: ECHEC | I45: =IF(F45=0,0,F45+J45+K45+L45+M45+N45) -> 0 | P45: =IF(O45<=500000,(O45*1*3/100),(O45*12/100)) -> 0
A46: AS201641 | B46: =VLOOKUP(A46,LISTADHERENT!A$5:H$51,2) -> TCHOUAMOU MATHIEU | C46: =$P$56/$D$56*D46 -> 0 | D46: =TONT20000DEC2016!F46+TONT20000DEC2016!E46+TONT20000JANV2017!J46 -> 428898.79 | F46: =IF(H46="ECHEC",0,13000) -> 13000 | G46: =IF(H46="ESPECES",1000,0) -> 0 | H46: BANQUE | I46: =IF(F46=0,0,F46+J46+K46+L46+M46+N46) -> 20000 | J46: 3000 | K46: 500 | L46: 1000 | M46: 2500 | P46: =IF(O46<=500000,(O46*1*3/100),(O46*12/100)) -> 0
A47: AS201642 | B47: =VLOOKUP(A47,LISTADHERENT!A$5:H$51,2) -> TCHOUANTE FRANCOIS | C47: =$P$56/$D$56*D47 -> 0 | D47: =TONT20000DEC2016!F47+TONT20000DEC2016!E47+TONT20000JANV2017!J47 -> 475899.81 | F47: =IF(H47="ECHEC",0,13000) -> 13000 | G47: =IF(H47="ESPECES",1000,0) -> 1000 | H47: ESPECES | I47: =IF(F47=0,0,F47+J47+K47+L47+M47+N47) -> 60000 | J47: 43000 | K47: 500 | L47: 1000 | M47: 2500 | P47: =IF(O47<=500000,(O47*1*3/100),(O47*12/100)) -> 0 | Q47: 229000
A48: AS201643 | B48: =VLOOKUP(A48,LISTADHERENT!A$5:H$51,2) -> TCHOUTOU NANA CLAUDE | C48: =$P$56/$D$56*D48 -> 0 | D48: =TONT20000DEC2016!F48+TONT20000DEC2016!E48+TONT20000JANV2017!J48 -> 6001.7252 | F48: =IF(H48="ECHEC",0,13000) -> 13000 | G48: =IF(H48="ESPECES",1000,0) -> 0 | H48: BANQUE | I48: =IF(F48=0,0,F48+J48+K48+L48+M48+N48) -> 20000 | J48: 3000 | K48: 500 | L48: 1000 | M48: 2500 | P48: =IF(O48<=500000,(O48*1*3/100),(O48*12/100)) -> 0
A49: AS201644 | B49: =VLOOKUP(A49,LISTADHERENT!A$5:H$51,2) -> TIEYAM ERNEST | C49: =$P$56/$D$56*D49 -> 0 | D49: =TONT20000DEC2016!F49+TONT20000DEC2016!E49+TONT20000JANV2017!J49 -> 428837.75 | F49: =IF(H49="ECHEC",0,13000) -> 13000 | G49: =IF(H49="ESPECES",1000,0) -> 0 | H49: BANQUE | I49: =IF(F49=0,0,F49+J49+K49+L49+M49+N49) -> 20000 | J49: 3000 | K49: 500 | L49: 1000 | M49: 2500 | P49: =IF(O49<=500000,(O49*1*3/100),(O49*12/100)) -> 0
A50: AS201645 | B50: =VLOOKUP(A50,LISTADHERENT!A$5:H$51,2) -> TUGMA PIERRE LOTI | C50: =$P$56/$D$56*D50 -> 0 | D50: =TONT20000DEC2016!F50+TONT20000DEC2016!E50+TONT20000JANV2017!J50 -> 428747.7 | F50: =IF(H50="ECHEC",0,13000) -> 13000 | G50: =IF(H50="ESPECES",1000,0) -> 0 | H50: BANQUE | I50: =IF(F50=0,0,F50+J50+K50+L50+M50+N50) -> 20000 | J50: 3000 | K50: 500 | L50: 1000 | M50: 2500 | P50: =IF(O50<=500000,(O50*1*3/100),(O50*12/100)) -> 0
A51: AS201646 | B51: =VLOOKUP(A51,LISTADHERENT!A$5:H$51,2) -> YEPMOU JEAN JACQUES | C51: =$P$56/$D$56*D51 -> 0 | D51: =TONT20000DEC2016!F51+TONT20000DEC2016!E51+TONT20000JANV2017!J51 -> 820451.83 | F51: =IF(H51="ECHEC",0,13000) -> 13000 | G51: =IF(H51="ESPECES",1000,0) -> 1000 | H51: ESPECES | I51: =IF(F51=0,0,F51+J51+K51+L51+M51+N51) -> 20000 | J51: 3000 | K51: 500 | L51: 1000 | M51: 2500 | P51: =IF(O51<=500000,(O51*1*3/100),(O51*12/100)) -> 0
A52: AS201647 | B52: =VLOOKUP(A52,LISTADHERENT!A$5:H$51,2) -> YOUMBI EMMANUEL | C52: =$P$56/$D$56*D52 -> 0 | D52: =TONT20000DEC2016!F52+TONT20000DEC2016!E52+TONT20000JANV2017!J52 -> 1510379.4 | F52: =IF(H52="ECHEC",0,13000) -> 13000 | G52: =IF(H52="ESPECES",1000,0) -> 1000 | H52: ESPECES | I52: =IF(F52=0,0,F52+J52+K52+L52+M52+N52) -> 220000 | J52: 203000 | K52: 500 | L52: 1000 | M52: 2500 | P52: =IF(O52<=500000,(O52*1*3/100),(O52*12/100)) -> 0
A56: TOTAL | C56: =SUM(C5:C52) -> 0 | D56: =SUM(D5:D52) -> 21274626 | E56: =SUM(E5:E52) -> 0 | F56: =SUM(F5:F52) -> 494000 | G56: =SUM(G5:G52) -> 16000 | I56: =SUM(I5:I52) -> 1042000 | J56: =SUM(J5:J52) -> 396000 | K56: =SUM(K5:K52) -> 19000 | L56: =SUM(L5:L52) -> 38000 | M56: =SUM(M5:M52) -> 95000 | N56: =SUM(N5:N52) -> 0 | O56: =SUM(O5:O52) -> 0 | P56: =SUM(P5:P52) -> 0 | ... T56: =SUM(T5:T52) -> 0
D60: FONDS DE ROULEMENT | E60: =+K56 -> 19000
D61: EPARGNE | E61: =+J56 -> 396000
D62: MUTUELLE | E62: 0
D63: FRAIS EXCEPTIONNELS | E63: =+L56 -> 38000
D64: COLLATION | E64: =+M56 -> 95000
D65: TONTINE | E65: =+F56 -> 494000
D66: PENALITE | E66: =+G56 -> 16000
D67: REMBOURSEMENT | E67: 12500
D69: TOTAL | E69: =SUM(E60:E67) -> 1070500
D71: DETAIL
E72: ESPECES | F72: 587500
E73: BANQUE | F73: 467000

Sheet TONT20000FEV2017
A1: ASSOCIATION | B1: ASELBY
A2: ANNEE | B2: 2016/2017
A3: TONTINE | B3: 20 000
A4: MATRICULE | B4: NOM ET PRENOM | C4: REPARTITION INTERET | D4: CAPITAL COMPOSE | E4: SANCTION | F4: MONTANT TONTINE | G4: PENALITE | H4: MODE VERSEMENT | I4: MONTANT VERSE | J4: EPARGNE | K4: FONDS DE ROULEMENT | L4: FRAIS EXCEPTIONNEL | M4: COLLATION | N4: MUTUELLE | O4: EMPRUNT | P4: INTERET EMPRUNT | Q4: REMBOURSEMENT | R4: PENALITE EMPRUNT | S4: PENALITE FONDS | T4: INTERET ACHAT | U4: DATE ACHAT | V4: AVALISTE
A5: AS201648 | B5: =VLOOKUP(A5,LISTADHERENT!A$5:H$52,2,0) -> ASELBY | C5: =$P$56/$D$56*D5 -> 3977.6928 | D5: =TONT20000JANV2017!C5+TONT20000JANV2017!D5+TONT20000FEV2017!J5 -> 355301.21
A6: AS201601 | B6: =VLOOKUP(A6,LISTADHERENT!A$5:H$52,2,0) -> BAKOP ACHILLE | C6: =$P$56/$D$56*D6 -> 5287.1276 | D6: =TONT20000JANV2017!C6+TONT20000JANV2017!D6+TONT20000FEV2017!J6 -> 472264.43 | F6: =IF(H6="ECHEC",0,13000) -> 0 | G6: =IF(H6="ESPECES",1000,0) -> 0 | H6: ECHEC | I6: =IF(F6=0,0,J6+K6+L6+M6+N6) -> 0 | J6: =IF($F6>=13000,3000,0) -> 0 | K6: =IF($F6>=13000,500,0) -> 0 | L6: =IF($F6>=13000,1000,0) -> 0 | M6: =IF($F6>=13000,2500,0) -> 0 | P6: =IF(O6<=500000,(O6*1*3/100),(O6*12/100)) -> 0
A7: AS201602 | B7: =VLOOKUP(A7,LISTADHERENT!A$5:H$51,2) -> BOUTCHOUANG WILLIAM | C7: =$P$56/$D$56*D7 -> 4835.9626 | D7: =TONT20000JANV2017!C7+TONT20000JANV2017!D7+TONT20000FEV2017!J7 -> 431964.82 | F7: =IF(H7="ECHEC",0,13000) -> 13000 | G7: =IF(H7="ESPECES",1000,0) -> 1000 | H7: ESPECES | I7: =IF(F7=0,0,F7+J7+K7+L7+M7+N7) -> 20000 | J7: =IF($F7>=13000,3000,0) -> 3000 | K7: =IF($F7>=13000,500,0) -> 500 | L7: =IF($F7>=13000,1000,0) -> 1000 | M7: =IF($F7>=13000,2500,0) -> 2500 | P7: =IF(O7<=500000,(O7*1*3/100),(O7*12/100)) -> 0
A8: AS201603 | B8: =VLOOKUP(A8,LISTADHERENT!A$5:H$51,2) -> CHINGUE FABRICE | C8: =$P$56/$D$56*D8 -> 4871.2928 | D8: =TONT20000JANV2017!C8+TONT20000JANV2017!D8+TONT20000FEV2017!J8 -> 435120.64 | F8: =IF(H8="ECHEC",0,13000) -> 13000 | G8: =IF(H8="ESPECES",1000,0) -> 1000 | H8: ESPECES | I8: =IF(F8=0,0,F8+J8+K8+L8+M8+N8) -> 20000 | J8: =IF($F8>=13000,3000,0) -> 3000 | K8: =IF($F8>=13000,500,0) -> 500 | L8: =IF($F8>=13000,1000,0) -> 1000 | M8: =IF($F8>=13000,2500,0) -> 2500 | P8: =IF(O8<=500000,(O8*1*3/100),(O8*12/100)) -> 0
A9: AS201604 | B9: =VLOOKUP(A9,LISTADHERENT!A$5:H$51,2) -> DJOMO JEAN PAUL | C9: =$P$56/$D$56*D9 -> 4912.6492 | D9: =TONT20000JANV2017!C9+TONT20000JANV2017!D9+TONT20000FEV2017!J9 -> 438814.74 | F9: =IF(H9="ECHEC",0,13000) -> 13000 | G9: =IF(H9="ESPECES",1000,0) -> 0 | H9: BANQUE | I9: =IF(F9=0,0,F9+J9+K9+L9+M9+N9) -> 27000 | J9: 10000 | K9: =IF($F9>=13000,500,0) -> 500 | L9: =IF($F9>=13000,1000,0) -> 1000 | M9: =IF($F9>=13000,2500,0) -> 2500 | O9: 1000000 | P9: =IF(O9<=500000,(O9*1*3/100),(O9*12/100)) -> 120000 | Q9: 103000
A10: AS201605 | B10: =VLOOKUP(A10,LISTADHERENT!A$5:H$51,2) -> DJOUKWE NANGUEN GUY BLAISE | C10: =$P$56/$D$56*D10 -> 4880.486 | D10: =TONT20000JANV2017!C10+TONT20000JANV2017!D10+TONT20000FEV2017!J10 -> 435941.81 | F10: =IF(H10="ECHEC",0,13000) -> 13000 | G10: =IF(H10="ESPECES",1000,0) -> 1000 | H10: ESPECES | I10: =IF(F10=0,0,F10+J10+K10+L10+M10+N10) -> 24000 | J10: 7000 | K10: =IF($F10>=13000,500,0) -> 500 | L10: =IF($F10>=13000,1000,0) -> 1000 | M10: =IF($F10>=13000,2500,0) -> 2500 | P10: =IF(O10<=500000,(O10*1*3/100),(O10*12/100)) -> 0
D11: =TONT20000JANV2017!C11+TONT20000JANV2017!D11+TONT20000FEV2017!J11 -> 0 | P11: =IF(O11<=500000,(O11*1*3/100),(O11*12/100)) -> 0
A12: AS201607 | B12: =VLOOKUP(A12,LISTADHERENT!A$5:H$51,2) -> DJOUNKEP SAMUEL | C12: =$P$56/$D$56*D12 -> 11924.627 | D12: =TONT20000JANV2017!C12+TONT20000JANV2017!D12+TONT20000FEV2017!J12 -> 1065148.7 | F12: =IF(H12="ECHEC",0,13000) -> 13000 | G12: =IF(H12="ESPECES",1000,0) -> 0 | H12: BANQUE | I12: =IF(F12=0,0,F12+J12+K12+L12+M12+N12) -> 20000 | J12: 3000 | K12: =IF($F12>=13000,500,0) -> 500 | L12: =IF($F12>=13000,1000,0) -> 1000 | M12: =IF($F12>=13000,2500,0) -> 2500 | P12: =IF(O12<=500000,(O12*1*3/100),(O12*12/100)) -> 0
A13: AS201608 | B13: =VLOOKUP(A13,LISTADHERENT!A$5:H$51,2) -> DJUOMBESSY ANTOINE | C13: =$P$56/$D$56*D13 -> 4836.2538 | D13: =TONT20000JANV2017!C13+TONT20000JANV2017!D13+TONT20000FEV2017!J13 -> 431990.84 | F13: =IF(H13="ECHEC",0,13000) -> 13000 | G13: =IF(H13="ESPECES",1000,0) -> 1000 | H13: ESPECES | I13: =IF(F13=0,0,F13+J13+K13+L13+M13+N13) -> 20000 | J13: =IF($F13>=13000,3000,0) -> 3000 | K13: =IF($F13>=13000,500,0) -> 500 | L13: =IF($F13>=13000,1000,0) -> 1000 | M13: =IF($F13>=13000,2500,0) -> 2500 | P13: =IF(O13<=500000,(O13*1*3/100),(O13*12/100)) -> 0 | Q13: 70000 | T13: 11000 | U13: 42785 | V13: HOTCHO
A14: AS201609 | B14: =VLOOKUP(A14,LISTADHERENT!A$5:H$51,2) -> DONHOU DAVID | C14: =$P$56/$D$56*D14 -> 5407.5633 | D14: =TONT20000JANV2017!C14+TONT20000JANV2017!D14+TONT20000FEV2017!J14 -> 483022.17 | F14: =IF(H14="ECHEC",0,13000) -> 13000 | G14: =IF(H14="ESPECES",1000,0) -> 0 | H14: BANQUE | I14: =IF(F14=0,0,F14+J14+K14+L14+M14+N14) -> 20000 | J14: =IF($F14>=13000,3000,0) -> 3000 | K14: =IF($F14>=13000,500,0) -> 500 | L14: =IF($F14>=13000,1000,0) -> 1000 | M14: =IF($F14>=13000,2500,0) -> 2500 | P14: =IF(O14<=500000,(O14*1*3/100),(O14*12/100)) -> 0
A15: AS201610 | B15: =VLOOKUP(A15,LISTADHERENT!A$5:H$51,2) -> FOTSO THOMAS | C15: =$P$56/$D$56*D15 -> 4833.7447 | D15: =TONT20000JANV2017!C15+TONT20000JANV2017!D15+TONT20000FEV2017!J15 -> 431766.71 | F15: =IF(H15="ECHEC",0,13000) -> 13000 | G15: =IF(H15="ESPECES",1000,0) -> 1000 | H15: ESPECES | I15: =IF(F15=0,0,F15+J15+K15+L15+M15+N15) -> 20000 | J15: =IF($F15>=13000,3000,0) -> 3000 | K15: =IF($F15>=13000,500,0) -> 500 | L15: =IF($F15>=13000,1000,0) -> 1000 | M15: =IF($F15>=13000,2500,0) -> 2500 | P15: =IF(O15<=500000,(O15*1*3/100),(O15*12/100)) -> 0
A16: AS201611 | B16: =VLOOKUP(A16,LISTADHERENT!A$5:H$51,2) -> HENGUE PAUL OMER | C16: =$P$56/$D$56*D16 -> 5544.8067 | D16: =TONT20000JANV2017!C16+TONT20000JANV2017!D16+TONT20000FEV2017!J16 -> 495281.21 | F16: 13000 | G16: =IF(H16="ESPECES",1000,0) -> 0 | H16: BANQUE | I16: =IF(F16=0,0,F16+J16+K16+L16+M16+N16) -> 20000 | J16: =IF($F16>=13000,3000,0) -> 3000 | K16: =IF($F16>=13000,500,0) -> 500 | L16: =IF($F16>=13000,1000,0) -> 1000 | M16: =IF($F16>=13000,2500,0) -> 2500 | P16: =IF(O16<=500000,(O16*1*3/100),(O16*12/100)) -> 0
A17: AS201612 | B17: =VLOOKUP(A17,LISTADHERENT!A$5:H$51,2) -> HODIEP JULES | C17: =$P$56/$D$56*D17 -> 562.99783 | D17: =TONT20000JANV2017!C17+TONT20000JANV2017!D17+TONT20000FEV2017!J17 -> 50288.904 | F17: =IF(H17="ECHEC",0,13000) -> 0 | G17: =IF(H17="ESPECES",1000,0) -> 0 | H17: ECHEC | I17: =IF(F17=0,0,F17+J17+K17+L17+M17+N17) -> 0 | J17: =IF($F17>=13000,3000,0) -> 0 | K17: =IF($F17>=13000,500,0) -> 0 | L17: =IF($F17>=13000,1000,0) -> 0 | M17: =IF($F17>=13000,2500,0) -> 0 | P17: =IF(O17<=500000,(O17*1*3/100),(O17*12/100)) -> 0
A18: AS201613 | B18: =VLOOKUP(A18,LISTADHERENT!A$5:H$51,2) -> HOTCHO BENJAMIN | C18: =$P$56/$D$56*D18 -> 6067.7584 | D18: =TONT20000JANV2017!C18+TONT20000JANV2017!D18+TONT20000FEV2017!J18 -> 541993.06 | F18: =IF(H18="ECHEC",0,13000) -> 13000 | G18: =IF(H18="ESPECES",1000,0) -> 0 | H18: BANQUE | I18: =IF(F18=0,0,F18+J18+K18+L18+M18+N18) -> 20000 | J18: =IF($F18>=13000,3000,0) -> 3000 | K18: =IF($F18>=13000,500,0) -> 500 | L18: =IF($F18>=13000,1000,0) -> 1000 | M18: =IF($F18>=13000,2500,0) -> 2500 | P18: =IF(O18<=500000,(O18*1*3/100),(O18*12/100)) -> 0
A19: AS201614 | B19: =VLOOKUP(A19,LISTADHERENT!A$5:H$51,2) -> KEPHE DAVID | C19: =$P$56/$D$56*D19 -> 1222.9302 | D19: =TONT20000JANV2017!C19+TONT20000JANV2017!D19+TONT20000FEV2017!J19 -> 109236.34 | F19: =IF(H19="ECHEC",0,13000) -> 13000 | G19: =IF(H19="ESPECES",1000,0) -> 0 | H19: BANQUE | I19: =IF(F19=0,0,F19+J19+K19+L19+M19+N19) -> 20000 | J19: =IF($F19>=13000,3000,0) -> 3000 | K19: =IF($F19>=13000,500,0) -> 500 | L19: =IF($F19>=13000,1000,0) -> 1000 | M19: =IF($F19>=13000,2500,0) -> 2500 | P19: =IF(O19<=500000,(O19*1*3/100),(O19*12/100)) -> 0
A20: AS201615 | B20: =VLOOKUP(A20,LISTADHERENT!A$5:H$51,2) -> KEPSEU FRANCIS | C20: =$P$56/$D$56*D20 -> 24009.943 | D20: =TONT20000JANV2017!C20+TONT20000JANV2017!D20+TONT20000FEV2017!J20 -> 2144650.7 | F20: =IF(H20="ECHEC",0,13000) -> 13000 | G20: =IF(H20="ESPECES",1000,0) -> 0 | H20: BANQUE | I20: =IF(F20=0,0,F20+J20+K20+L20+M20+N20) -> 23000 | J20: 6000 | K20: =IF($F20>=13000,500,0) -> 500 | L20: =IF($F20>=13000,1000,0) -> 1000 | M20: =IF($F20>=13000,2500,0) -> 2500 | P20: =IF(O20<=500000,(O20*1*3/100),(O20*12/100)) -> 0
A21: AS201616 | B21: =VLOOKUP(A21,LISTADHERENT!A$5:H$51,2) -> KOUAMOU EMMANUEL | C21: =$P$56/$D$56*D21 -> 4831.8964 | D21: =TONT20000JANV2017!C21+TONT20000JANV2017!D21+TONT20000FEV2017!J21 -> 431601.61 | F21: =IF(H21="ECHEC",0,13000) -> 13000 | G21: =IF(H21="ESPECES",1000,0) -> 1000 | H21: ESPECES | I21: =IF(F21=0,0,F21+J21+K21+L21+M21+N21) -> 20000 | J21: =IF($F21>=13000,3000,0) -> 3000 | K21: =IF($F21>=13000,500,0) -> 500 | L21: =IF($F21>=13000,1000,0) -> 1000 | M21: =IF($F21>=13000,2500,0) -> 2500 | P21: =IF(O21<=500000,(O21*1*3/100),(O21*12/100)) -> 0
A22: AS201617 | B22: =VLOOKUP(A22,LISTADHERENT!A$5:H$51,2) -> KOUAMOU MOISE | C22: =$P$56/$D$56*D22 -> 4839.6368 | D22: =TONT20000JANV2017!C22+TONT20000JANV2017!D22+TONT20000FEV2017!J22 -> 432293.01 | F22: =IF(H22="ECHEC",0,13000) -> 13000 | G22: =IF(H22="ESPECES",1000,0) -> 0 | H22: BANQUE | I22: =IF(F22=0,0,F22+J22+K22+L22+M22+N22) -> 20000 | J22: =IF($F22>=13000,3000,0) -> 3000 | K22: =IF($F22>=13000,500,0) -> 500 | L22: =IF($F22>=13000,1000,0) -> 1000 | M22: =IF($F22>=13000,2500,0) -> 2500 | P22: =IF(O22<=500000,(O22*1*3/100),(O22*12/100)) -> 0 | V22: TIEYAM ERNEST
A23: AS201618 | B23: =VLOOKUP(A23,LISTADHERENT!A$5:H$51,2) -> KOUAMO VICTOR PEGUY | C23: =$P$56/$D$56*D23 -> 4835.5817 | D23: =TONT20000JANV2017!C23+TONT20000JANV2017!D23+TONT20000FEV2017!J23 -> 431930.8 | F23: =IF(H23="ECHEC",0,13000) -> 13000 | G23: =IF(H23="ESPECES",1000,0) -> 0 | H23: BANQUE | I23: =IF(F23=0,0,F23+J23+K23+L23+M23+N23) -> 20000 | J23: =IF($F23>=13000,3000,0) -> 3000 | K23: =IF($F23>=13000,500,0) -> 500 | L23: =IF($F23>=13000,1000,0) -> 1000 | M23: =IF($F23>=13000,2500,0) -> 2500 | P23: =IF(O23<=500000,(O23*1*3/100),(O23*12/100)) -> 0 | V23: NANKAM APPOLINAIRE
A24: AS201619 | B24: =VLOOKUP(A24,LISTADHERENT!A$5:H$51,2) -> KOUATCHO MESSACK | C24: =$P$56/$D$56*D24 -> 4848.2621 | D24: =TONT20000JANV2017!C24+TONT20000JANV2017!D24+TONT20000FEV2017!J24 -> 433063.45 | F24: =IF(H24="ECHEC",0,13000) -> 13000 | G24: =IF(H24="ESPECES",1000,0) -> 0 | H24: BANQUE | I24: =IF(F24=0,0,F24+J24+K24+L24+M24+N24) -> 20000 | J24: =IF($F24>=13000,3000,0) -> 3000 | K24: =IF($F24>=13000,500,0) -> 500 | L24: =IF($F24>=13000,1000,0) -> 1000 | M24: =IF($F24>=13000,2500,0) -> 2500 | P24: =IF(O24<=500000,(O24*1*3/100),(O24*12/100)) -> 0
A25: AS201620 | B25: =VLOOKUP(A25,LISTADHERENT!A$5:H$51,2) -> LOWE JEAN | C25: =$P$56/$D$56*D25 -> 4835.2009 | D25: =TONT20000JANV2017!C25+TONT20000JANV2017!D25+TONT20000FEV2017!J25 -> 431896.78 | F25: =IF(H25="ECHEC",0,13000) -> 13000 | G25: =IF(H25="ESPECES",1000,0) -> 0 | H25: BANQUE | I25: =IF(F25=0,0,F25+J25+K25+L25+M25+N25) -> 20000 | J25: =IF($F25>=13000,3000,0) -> 3000 | K25: =IF($F25>=13000,500,0) -> 500 | L25: =IF($F25>=13000,1000,0) -> 1000 | M25: =IF($F25>=13000,2500,0) -> 2500 | P25: =IF(O25<=500000,(O25*1*3/100),(O25*12/100)) -> 0
A26: AS201621 | B26: =VLOOKUP(A26,LISTADHERENT!A$5:H$51,2) -> NANKAM APPOLINAIRE | C26: =$P$56/$D$56*D26 -> 4836.1978 | D26: =TONT20000JANV2017!C26+TONT20000JANV2017!D26+TONT20000FEV2017!J26 -> 431985.84 | F26: =IF(H26="ECHEC",0,13000) -> 13000 | G26: =IF(H26="ESPECES",1000,0) -> 0 | H26: BANQUE | I26: =IF(F26=0,0,F26+J26+K26+L26+M26+N26) -> 20000 | J26: =IF($F26>=13000,3000,0) -> 3000 | K26: =IF($F26>=13000,500,0) -> 500 | L26: =IF($F26>=13000,1000,0) -> 1000 | M26: =IF($F26>=13000,2500,0) -> 2500 | P26: =IF(O26<=500000,(O26*1*3/100),(O26*12/100)) -> 0 | Q26: 100000
A27: AS201622 | B27: =VLOOKUP(A27,LISTADHERENT!A$5:H$51,2) -> NDJOMO ETIENNE | C27: =$P$56/$D$56*D27 -> 5005.0216 | D27: =TONT20000JANV2017!C27+TONT20000JANV2017!D27+TONT20000FEV2017!J27 -> 447065.76 | F27: =IF(H27="ECHEC",0,13000) -> 13000 | G27: =IF(H27="ESPECES",1000,0) -> 0 | H27: BANQUE | I27: =IF(F27=0,0,F27+J27+K27+L27+M27+N27) -> 25000 | J27: 8000 | K27: =IF($F27>=13000,500,0) -> 500 | L27: =IF($F27>=13000,1000,0) -> 1000 | M27: =IF($F27>=13000,2500,0) -> 2500 | P27: =IF(O27<=500000,(O27*1*3/100),(O27*12/100)) -> 0
A28: AS201623 | B28: =VLOOKUP(A28,LISTADHERENT!A$5:H$51,2) -> NDOMBOU JEAN CLAUDE | C28: =$P$56/$D$56*D28 -> 4704.7172 | D28: =TONT20000JANV2017!C28+TONT20000JANV2017!D28+TONT20000FEV2017!J28 -> 420241.53 | P28: =IF(O28<=500000,(O28*1*3/100),(O28*12/100)) -> 0
A29: AS201624 | B29: =VLOOKUP(A29,LISTADHERENT!A$5:H$51,2) -> NGONDIEP CLAUDE | C29: =$P$56/$D$56*D29 -> 4942.6569 | D29: =TONT20000JANV2017!C29+TONT20000JANV2017!D29+TONT20000FEV2017!J29 -> 441495.13 | F29: =IF(H29="ECHEC",0,13000) -> 13000 | G29: =IF(H29="ESPECES",1000,0) -> 0 | H29: BANQUE | I29: =IF(F29=0,0,F29+J29+K29+L29+M29+N29) -> 20000 | J29: =IF($F29>=13000,3000,0) -> 3000 | K29: =IF($F29>=13000,500,0) -> 500 | L29: =IF($F29>=13000,1000,0) -> 1000 | M29: =IF($F29>=13000,2500,0) -> 2500 | P29: =IF(O29<=500000,(O29*1*3/100),(O29*12/100)) -> 0
A30: AS201625 | B30: =VLOOKUP(A30,LISTADHERENT!A$5:H$51,2) -> NGONGANG JEAN THEODORE | C30: =$P$56/$D$56*D30 -> 101.96412 | D30: =TONT20000JANV2017!C30+TONT20000JANV2017!D30+TONT20000FEV2017!J30 -> 9107.7862 | F30: 26000 | G30: =IF(H30="ESPECES",1000,0) -> 1000 | H30: ESPECES | I30: =IF(F30=0,0,F30+J30+K30+L30+M30+N30) -> 40000 | J30: 6000 | K30: 1000 | L30: 2000 | M30: 5000 | P30: =IF(O30<=500000,(O30*1*3/100),(O30*12/100)) -> 0
A31: AS201626 | B31: =VLOOKUP(A31,LISTADHERENT!A$5:H$51,2) -> NGUIEMEGNI MATHIEU BLAISE | C31: =$P$56/$D$56*D31 -> 5255.0521 | D31: =TONT20000JANV2017!C31+TONT20000JANV2017!D31+TONT20000FEV2017!J31 -> 469399.34 | F31: =IF(H31="ECHEC",0,13000) -> 13000 | G31: =IF(H31="ESPECES",1000,0) -> 0 | H31: BANQUE | I31: =IF(F31=0,0,F31+J31+K31+L31+M31+N31) -> 20000 | J31: =IF($F31>=13000,3000,0) -> 3000 | K31: =IF($F31>=13000,500,0) -> 500 | L31: =IF($F31>=13000,1000,0) -> 1000 | M31: =IF($F31>=13000,2500,0) -> 2500 | P31: =IF(O31<=500000,(O31*1*3/100),(O31*12/100)) -> 0
A32: AS201627 | B32: =VLOOKUP(A32,LISTADHERENT!A$5:H$51,2) -> NJEPDJIO MBOUKAM DELUXE | C32: =$P$56/$D$56*D32 -> 4892.5326 | D32: =TONT20000JANV2017!C32+TONT20000JANV2017!D32+TONT20000FEV2017!J32 -> 437017.85 | F32: =IF(H32="ECHEC",0,13000) -> 13000 | G32: =IF(H32="ESPECES",1000,0) -> 1000 | H32: ESPECES | I32: =IF(F32=0,0,F32+J32+K32+L32+M32+N32) -> 20000 | J32: =IF($F32>=13000,3000,0) -> 3000 | K32: =IF($F32>=13000,500,0) -> 500 | L32: =IF($F32>=13000,1000,0) -> 1000 | M32: =IF($F32>=13000,2500,0) -> 2500 | P32: =IF(O32<=500000,(O32*1*3/100),(O32*12/100)) -> 0
A33: AS201628 | B33: =VLOOKUP(A33,LISTADHERENT!A$5:H$51,2) -> NKAMGANG JUSTIN DEJOLIE | C33: =$P$56/$D$56*D33 -> 5710.63 | D33: =TONT20000JANV2017!C33+TONT20000JANV2017!D33+TONT20000FEV2017!J33 -> 510093.13 | F33: =IF(H33="ECHEC",0,13000) -> 13000 | G33: =IF(H33="ESPECES",1000,0) -> 1000 | H33: ESPECES | I33: =IF(F33=0,0,F33+J33+K33+L33+M33+N33) -> 23000 | J33: 6000 | K33: =IF($F33>=13000,500,0) -> 500 | L33: =IF($F33>=13000,1000,0) -> 1000 | M33: =IF($F33>=13000,2500,0) -> 2500 | P33: =IF(O33<=500000,(O33*1*3/100),(O33*12/100)) -> 0
A34: AS201629 | B34: =VLOOKUP(A34,LISTADHERENT!A$5:H$51,2) -> NKEPSEU DIEUDONNE | C34: =$P$56/$D$56*D34 -> 6124.6771 | D34: =TONT20000JANV2017!C34+TONT20000JANV2017!D34+TONT20000FEV2017!J34 -> 547077.24 | F34: =IF(H34="ECHEC",0,13000) -> 13000 | G34: =IF(H34="ESPECES",1000,0) -> 1000 | H34: ESPECES | I34: =IF(F34=0,0,F34+J34+K34+L34+M34+N34) -> 25000 | J34: 8000 | K34: =IF($F34>=13000,500,0) -> 500 | L34: =IF($F34>=13000,1000,0) -> 1000 | M34: =IF($F34>=13000,2500,0) -> 2500 | P34: =IF(O34<=500000,(O34*1*3/100),(O34*12/100)) -> 0
D35: =TONT20000JANV2017!C35+TONT20000JANV2017!D35+TONT20000FEV2017!J35 -> 0 | P35: =IF(O35<=500000,(O35*1*3/100),(O35*12/100)) -> 0
A36: AS201631 | B36: =VLOOKUP(A36,LISTADHERENT!A$5:H$51,2) -> NTEPDIE TUEMAC MZ | C36: =$P$56/$D$56*D36 -> 0 | D36: =TONT20000JANV2017!C36+TONT20000JANV2017!D36+TONT20000FEV2017!J36 -> 0 | F36: =IF(H36="ECHEC",0,13000) -> 0 | G36: =IF(H36="ESPECES",1000,0) -> 0 | H36: ECHEC | I36: =IF(F36=0,0,F36+J36+K36+L36+M36+N36) -> 0 | J36: =IF($F36>=13000,3000,0) -> 0 | K36: =IF($F36>=13000,500,0) -> 0 | L36: =IF($F36>=13000,1000,0) -> 0 | M36: =IF($F36>=13000,2500,0) -> 0 | P36: =IF(O36<=500000,(O36*1*3/100),(O36*12/100)) -> 0
D37: =TONT20000JANV2017!C37+TONT20000JANV2017!D37+TONT20000FEV2017!J37 -> 0 | P37: =IF(O37<=500000,(O37*1*3/100),(O37*12/100)) -> 0
A38: AS201633 | B38: =VLOOKUP(A38,LISTADHERENT!A$5:H$51,2) -> PATEGO NJOSSU GUSTAVE | C38: =$P$56/$D$56*D38 -> 4833.207 | D38: =TONT20000JANV2017!C38+TONT20000JANV2017!D38+TONT20000FEV2017!J38 -> 431718.68 | F38: =IF(H38="ECHEC",0,13000) -> 13000 | G38: =IF(H38="ESPECES",1000,0) -> 0 | H38: BANQUE | I38: =IF(F38=0,0,F38+J38+K38+L38+M38+N38) -> 20000 | J38: =IF($F38>=13000,3000,0) -> 3000 | K38: =IF($F38>=13000,500,0) -> 500 | L38: =IF($F38>=13000,1000,0) -> 1000 | M38: =IF($F38>=13000,2500,0) -> 2500 | P38: =IF(O38<=500000,(O38*1*3/100),(O38*12/100)) -> 0
A39: AS201634 | B39: =VLOOKUP(A39,LISTADHERENT!A$5:H$51,2) -> SEUNOU RICHELOT | C39: =$P$56/$D$56*D39 -> 4881.1727 | D39: =TONT20000JANV2017!C39+TONT20000JANV2017!D39+TONT20000FEV2017!J39 -> 436003.14 | F39: =IF(H39="ECHEC",0,13000) -> 13000 | G39: =IF(H39="ESPECES",1000,0) -> 1000 | H39: ESPECES | I39: =IF(F39=0,0,F39+J39+K39+L39+M39+N39) -> 20000 | J39: =IF($F39>=13000,3000,0) -> 3000 | K39: =IF($F39>=13000,500,0) -> 500 | L39: =IF($F39>=13000,1000,0) -> 1000 | M39: =IF($F39>=13000,2500,0) -> 2500 | P39: =IF(O39<=500000,(O39*1*3/100),(O39*12/100)) -> 0
A40: AS201635 | B40: =VLOOKUP(A40,LISTADHERENT!A$5:H$51,2) -> SIME ABEL | C40: =$P$56/$D$56*D40 -> 4474.9092 | D40: =TONT20000JANV2017!C40+TONT20000JANV2017!D40+TONT20000FEV2017!J40 -> 399714.29 | F40: =IF(H40="ECHEC",0,13000) -> 13000 | G40: =IF(H40="ESPECES",1000,0) -> 1000 | H40: ESPECES | I40: =IF(F40=0,0,F40+J40+K40+L40+M40+N40) -> 20000 | J40: =IF($F40>=13000,3000,0) -> 3000 | K40: =IF($F40>=13000,500,0) -> 500 | L40: =IF($F40>=13000,1000,0) -> 1000 | M40: =IF($F40>=13000,2500,0) -> 2500 | P40: =IF(O40<=500000,(O40*1*3/100),(O40*12/100)) -> 0
A41: AS201636 | B41: =VLOOKUP(A41,LISTADHERENT!A$5:H$51,2) -> SIME FONGANG ERIC | C41: =$P$56/$D$56*D41 -> 4860.5391 | D41: =TONT20000JANV2017!C41+TONT20000JANV2017!D41+TONT20000FEV2017!J41 -> 434160.09 | F41: =IF(H41="ECHEC",0,13000) -> 13000 | G41: =IF(H41="ESPECES",1000,0) -> 0 | H41: BANQUE | I41: =IF(F41=0,0,F41+J41+K41+L41+M41+N41) -> 20000 | J41: =IF($F41>=13000,3000,0) -> 3000 | K41: =IF($F41>=13000,500,0) -> 500 | L41: =IF($F41>=13000,1000,0) -> 1000 | M41: =IF($F41>=13000,2500,0) -> 2500 | P41: =IF(O41<=500000,(O41*1*3/100),(O41*12/100)) -> 0
A42: AS201637 | B42: =VLOOKUP(A42,LISTADHERENT!A$5:H$51,2) -> SIME MATHIEU | C42: =$P$56/$D$56*D42 -> 4856.2153 | D42: =TONT20000JANV2017!C42+TONT20000JANV2017!D42+TONT20000FEV2017!J42 -> 433773.86 | F42: =IF(H42="ECHEC",0,13000) -> 13000 | G42: =IF(H42="ESPECES",1000,0) -> 0 | H42: BANQUE | I42: =IF(F42=0,0,F42+J42+K42+L42+M42+N42) -> 20000 | J42: =IF($F42>=13000,3000,0) -> 3000 | K42: =IF($F42>=13000,500,0) -> 500 | L42: =IF($F42>=13000,1000,0) -> 1000 | M42: =IF($F42>=13000,2500,0) -> 2500 | P42: =IF(O42<=500000,(O42*1*3/100),(O42*12/100)) -> 0
A43: AS201638 | B43: =VLOOKUP(A43,LISTADHERENT!A$5:H$51,2) -> SIME PIERRE | C43: =$P$56/$D$56*D43 -> 6272.5089 | D43: =TONT20000JANV2017!C43+TONT20000JANV2017!D43+TONT20000FEV2017!J43 -> 560282.08 | F43: =IF(H43="ECHEC",0,13000) -> 13000 | G43: =IF(H43="ESPECES",1000,0) -> 0 | H43: BANQUE | I43: =IF(F43=0,0,F43+J43+K43+L43+M43+N43) -> 30000 | J43: 13000 | K43: =IF($F43>=13000,500,0) -> 500 | L43: =IF($F43>=13000,1000,0) -> 1000 | M43: =IF($F43>=13000,2500,0) -> 2500 | P43: =IF(O43<=500000,(O43*1*3/100),(O43*12/100)) -> 0
A44: AS201639 | B44: =VLOOKUP(A44,LISTADHERENT!A$5:H$51,2) -> TAGNE NANGUEN MARTIN | C44: =$P$56/$D$56*D44 -> 4487.6007 | D44: =TONT20000JANV2017!C44+TONT20000JANV2017!D44+TONT20000FEV2017!J44 -> 400847.94 | F44: =IF(H44="ECHEC",0,13000) -> 13000 | G44: =IF(H44="ESPECES",1000,0) -> 0 | H44: BANQUE | I44: =IF(F44=0,0,F44+J44+K44+L44+M44+N44) -> 20000 | J44: =IF($F44>=13000,3000,0) -> 3000 | K44: =IF($F44>=13000,500,0) -> 500 | L44: =IF($F44>=13000,1000,0) -> 1000 | M44: =IF($F44>=13000,2500,0) -> 2500 | P44: =IF(O44<=500000,(O44*1*3/100),(O44*12/100)) -> 0
A45: AS201640 | B45: =VLOOKUP(A45,LISTADHERENT!A$5:H$51,2) -> TCHOUAMOU JEAN PAUL | C45: =$P$56/$D$56*D45 -> 267.04369 | D45: =TONT20000JANV2017!C45+TONT20000JANV2017!D45+TONT20000FEV2017!J45 -> 23853.261 | F45: 26000 | G45: =IF(H45="ESPECES",1000,0) -> 0 | H45: BANQUE | I45: =IF(F45=0,0,F45+J45+K45+L45+M45+N45) -> 40000 | J45: 6000 | K45: 1000 | L45: 2000 | M45: 5000 | P45: =IF(O45<=500000,(O45*1*3/100),(O45*12/100)) -> 0
A46: AS201641 | B46: =VLOOKUP(A46,LISTADHERENT!A$5:H$51,2) -> TCHOUAMOU MATHIEU | C46: =$P$56/$D$56*D46 -> 4835.2233 | D46: =TONT20000JANV2017!C46+TONT20000JANV2017!D46+TONT20000FEV2017!J46 -> 431898.79 | F46: =IF(H46="ECHEC",0,13000) -> 13000 | G46: =IF(H46="ESPECES",1000,0) -> 0 | H46: BANQUE | I46: =IF(F46=0,0,F46+J46+K46+L46+M46+N46) -> 20000 | J46: =IF($F46>=13000,3000,0) -> 3000 | K46: =IF($F46>=13000,500,0) -> 500 | L46: =IF($F46>=13000,1000,0) -> 1000 | M46: =IF($F46>=13000,2500,0) -> 2500 | P46: =IF(O46<=500000,(O46*1*3/100),(O46*12/100)) -> 0
A47: AS201642 | B47: =VLOOKUP(A47,LISTADHERENT!A$5:H$51,2) -> TCHOUANTE FRANCOIS | C47: =$P$56/$D$56*D47 -> 5361.4124 | D47: =TONT20000JANV2017!C47+TONT20000JANV2017!D47+TONT20000FEV2017!J47 -> 478899.81 | F47: =IF(H47="ECHEC",0,13000) -> 13000 | G47: =IF(H47="ESPECES",1000,0) -> 1000 | H47: ESPECES | I47: =IF(F47=0,0,F47+J47+K47+L47+M47+N47) -> 20000 | J47: =IF($F47>=13000,3000,0) -> 3000 | K47: =IF($F47>=13000,500,0) -> 500 | L47: =IF($F47>=13000,1000,0) -> 1000 | M47: =IF($F47>=13000,2500,0) -> 2500 | P47: =IF(O47<=500000,(O47*1*3/100),(O47*12/100)) -> 0
A48: AS201643 | B48: =VLOOKUP(A48,LISTADHERENT!A$5:H$51,2) -> TCHOUTOU NANA CLAUDE | C48: =$P$56/$D$56*D48 -> 100.77674 | D48: =TONT20000JANV2017!C48+TONT20000JANV2017!D48+TONT20000FEV2017!J48 -> 9001.7252 | F48: =IF(H48="ECHEC",0,13000) -> 13000 | G48: =IF(H48="ESPECES",1000,0) -> 0 | H48: BANQUE | I48: =IF(F48=0,0,F48+J48+K48+L48+M48+N48) -> 20000 | J48: =IF($F48>=13000,3000,0) -> 3000 | K48: =IF($F48>=13000,500,0) -> 500 | L48: =IF($F48>=13000,1000,0) -> 1000 | M48: =IF($F48>=13000,2500,0) -> 2500 | P48: =IF(O48<=500000,(O48*1*3/100),(O48*12/100)) -> 0
A49: AS201644 | B49: =VLOOKUP(A49,LISTADHERENT!A$5:H$51,2) -> TIEYAM ERNEST | C49: =$P$56/$D$56*D49 -> 4834.54 | D49: =TONT20000JANV2017!C49+TONT20000JANV2017!D49+TONT20000FEV2017!J49 -> 431837.75 | F49: =IF(H49="ECHEC",0,13000) -> 13000 | G49: =IF(H49="ESPECES",1000,0) -> 0 | H49: BANQUE | I49: =IF(F49=0,0,F49+J49+K49+L49+M49+N49) -> 20000 | J49: =IF($F49>=13000,3000,0) -> 3000 | K49: =IF($F49>=13000,500,0) -> 500 | L49: =IF($F49>=13000,1000,0) -> 1000 | M49: =IF($F49>=13000,2500,0) -> 2500 | O49: 1000000 | P49: =IF(O49<=500000,(O49*1*3/100),(O49*12/100)) -> 120000 | Q49: 1176000
A50: AS201645 | B50: =VLOOKUP(A50,LISTADHERENT!A$5:H$51,2) -> TUGMA PIERRE LOTI | C50: =$P$56/$D$56*D50 -> 4833.5318 | D50: =TONT20000JANV2017!C50+TONT20000JANV2017!D50+TONT20000FEV2017!J50 -> 431747.7 | F50: =IF(H50="ECHEC",0,13000) -> 13000 | G50: =IF(H50="ESPECES",1000,0) -> 0 | H50: BANQUE | I50: =IF(F50=0,0,F50+J50+K50+L50+M50+N50) -> 20000 | J50: =IF($F50>=13000,3000,0) -> 3000 | K50: =IF($F50>=13000,500,0) -> 500 | L50: =IF($F50>=13000,1000,0) -> 1000 | M50: =IF($F50>=13000,2500,0) -> 2500 | P50: =IF(O50<=500000,(O50*1*3/100),(O50*12/100)) -> 0
A51: AS201646 | B51: =VLOOKUP(A51,LISTADHERENT!A$5:H$51,2) -> YEPMOU JEAN JACQUES | C51: =$P$56/$D$56*D51 -> 9218.7651 | D51: =TONT20000JANV2017!C51+TONT20000JANV2017!D51+TONT20000FEV2017!J51 -> 823451.83 | F51: =IF(H51="ECHEC",0,13000) -> 13000 | G51: =IF(H51="ESPECES",1000,0) -> 1000 | H51: ESPECES | I51: =IF(F51=0,0,F51+J51+K51+L51+M51+N51) -> 20000 | J51: =IF($F51>=13000,3000,0) -> 3000 | K51: =IF($F51>=13000,500,0) -> 500 | L51: =IF($F51>=13000,1000,0) -> 1000 | M51: =IF($F51>=13000,2500,0) -> 2500 | P51: =IF(O51<=500000,(O51*1*3/100),(O51*12/100)) -> 0
A52: AS201647 | B52: =VLOOKUP(A52,LISTADHERENT!A$5:H$51,2) -> YOUMBI EMMANUEL | C52: =$P$56/$D$56*D52 -> 16942.69 | D52: =TONT20000JANV2017!C52+TONT20000JANV2017!D52+TONT20000FEV2017!J52 -> 1513379.4 | F52: =IF(H52="ECHEC",0,13000) -> 13000 | G52: =IF(H52="ESPECES",1000,0) -> 0 | H52: BANQUE | I52: =IF(F52=0,0,F52+J52+K52+L52+M52+N52) -> 20000 | J52: =IF($F52>=13000,3000,0) -> 3000 | K52: =IF($F52>=13000,500,0) -> 500 | L52: =IF($F52>=13000,1000,0) -> 1000 | M52: =IF($F52>=13000,2500,0) -> 2500 | P52: =IF(O52<=500000,(O52*1*3/100),(O52*12/100)) -> 0
A56: TOTAL | C56: =SUM(C5:C52) -> 240000 | D56: =SUM(D5:D52) -> 21437626 | E56: =SUM(E5:E52) -> 0 | F56: =SUM(F5:F52) -> 546000 | G56: =SUM(G5:G52) -> 14000 | I56: =SUM(I5:I52) -> 877000 | J56: =SUM(J5:J52) -> 163000 | K56: =SUM(K5:K52) -> 21000 | L56: =SUM(L5:L52) -> 42000 | M56: =SUM(M5:M52) -> 105000 | N56: =SUM(N5:N52) -> 0 | O56: =SUM(O5:O52) -> 2000000 | P56: =SUM(P5:P52) -> 240000 | ... T56: =SUM(T5:T52) -> 11000
D60: FONDS DE ROULEMENT | E60: =+K56 -> 21000
D61: EPARGNE | E61: =+J56 -> 163000
D62: MUTUELLE | E62: 0
D63: FRAIS EXCEPTIONNELS | E63: =+L56 -> 42000
D64: COLLATION | E64: =+M56 -> 105000
D65: TONTINE | E65: =+F56+73000 -> 619000
D66: PENALITE | E66: =G56 -> 14000
D67: REMBOURSEMENT | E67: =Q56 -> 1449000
D69: TOTAL | E69: =SUM(E60:E67) -> 2413000
D71: DETAIL
E72: ESPECES | F72: 169000
E73: BANQUE | F73: =F56-F72 -> 377000

Sheet TONT20000MARS2017
A1: ASSOCIATION | B1: ASELBY
A2: ANNEE | B2: 2016/2017
A3: TONTINE | B3: 20 000
A4: MATRICULE | B4: NOM ET PRENOM | C4: REPARTITION INTERET | D4: CAPITAL COMPOSE | E4: SANCTION | F4: MONTANT TONTINE | G4: PENALITE | H4: MODE VERSEMENT | I4: MONTANT VERSE | J4: EPARGNE | K4: FONDS DE ROULEMENT | L4: FRAIS EXCEPTIONNEL | M4: COLLATION | N4: MUTUELLE | O4: EMPRUNT | P4: INTERET EMPRUNT | Q4: REMBOURSEMENT | R4: PENALITE EMPRUNT | S4: PENALITE FONDS | T4: INTERET ACHAT | U4: DATE ACHAT | V4: AVALISTE
A5: AS201648 | B5: =VLOOKUP(A5,LISTADHERENT!A$5:H$52,2,0) -> ASELBY | C5: =$P$56/$D$56*D5 -> 3155.3714 | D5: =TONT20000FEV2017!C5+TONT20000FEV2017!D5+TONT20000MARS2017!J5 -> 359278.9
A6: AS201601 | B6: =VLOOKUP(A6,LISTADHERENT!A$5:H$52,2,0) -> BAKOP ACHILLE | C6: =$P$56/$D$56*D6 -> 4194.1025 | D6: =TONT20000FEV2017!C6+TONT20000FEV2017!D6+TONT20000MARS2017!J6 -> 477551.56 | F6: =IF(H6="ECHEC",0,13000) -> 0 | G6: =IF(H6="ESPECES",1000,0) -> 0 | H6: ECHEC | I6: =IF(F6=0,0,J6+K6+L6+M6+N6+#REF!) -> 0 | J6: =IF(F6=0,0,3000) -> 0 | K6: =IF(F6=0,0,500) -> 0 | L6: =IF(F6=0,0,1000) -> 0 | M6: =IF(F6=0,0,2500) -> 0 | P6: =IF(O6<=500000,(O6*1*3/100),(O6*12/100)) -> 0
A7: AS201602 | B7: =VLOOKUP(A7,LISTADHERENT!A$5:H$51,2) -> BOUTCHOUANG WILLIAM | C7: =$P$56/$D$56*D7 -> 3862.5558 | D7: =TONT20000FEV2017!C7+TONT20000FEV2017!D7+TONT20000MARS2017!J7 -> 439800.79 | F7: =IF(H7="ECHEC",0,13000) -> 13000 | G7: =IF(H7="ESPECES",1000,0) -> 1000 | H7: ESPECES | I7: =IF(F7=0,0,F7+J7+K7+L7+M7+N7) -> 20000 | J7: =IF(F7=0,0,3000) -> 3000 | K7: =IF(F7=0,0,500) -> 500 | L7: =IF(F7=0,0,1000) -> 1000 | M7: =IF(F7=0,0,2500) -> 2500 | P7: =IF(O7<=500000,(O7*1*3/100),(O7*12/100)) -> 0
A8: AS201603 | B8: =VLOOKUP(A8,LISTADHERENT!A$5:H$51,2) -> CHINGUE FABRICE | C8: =$P$56/$D$56*D8 -> 3890.5821 | D8: =TONT20000FEV2017!C8+TONT20000FEV2017!D8+TONT20000MARS2017!J8 -> 442991.93 | F8: =IF(H8="ECHEC",0,13000) -> 13000 | G8: =IF(H8="ESPECES",1000,0) -> 1000 | H8: ESPECES | I8: =IF(F8=0,0,F8+J8+K8+L8+M8+N8) -> 20000 | J8: =IF(F8=0,0,3000) -> 3000 | K8: =IF(F8=0,0,500) -> 500 | L8: =IF(F8=0,0,1000) -> 1000 | M8: =IF(F8=0,0,2500) -> 2500 | P8: =IF(O8<=500000,(O8*1*3/100),(O8*12/100)) -> 0
A9: AS201604 | B9: =VLOOKUP(A9,LISTADHERENT!A$5:H$51,2) -> DJOMO JEAN PAUL | C9: =$P$56/$D$56*D9 -> 3923.3888 | D9: =TONT20000FEV2017!C9+TONT20000FEV2017!D9+TONT20000MARS2017!J9 -> 446727.39 | F9: =IF(H9="ECHEC",0,13000) -> 13000 | G9: =IF(H9="ESPECES",1000,0) -> 0 | H9: BANQUE | I9: =IF(F9=0,0,F9+J9+K9+L9+M9+N9) -> 20000 | J9: =IF(F9=0,0,3000) -> 3000 | K9: =IF(F9=0,0,500) -> 500 | L9: =IF(F9=0,0,1000) -> 1000 | M9: =IF(F9=0,0,2500) -> 2500 | P9: =IF(O9<=500000,(O9*1*3/100),(O9*12/100)) -> 0
A10: AS201605 | B10: =VLOOKUP(A10,LISTADHERENT!A$5:H$51,2) -> DJOUKWE NANGUEN GUY BLAISE | C10: =$P$56/$D$56*D10 -> 3897.8748 | D10: =TONT20000FEV2017!C10+TONT20000FEV2017!D10+TONT20000MARS2017!J10 -> 443822.3 | F10: =IF(H10="ECHEC",0,13000) -> 13000 | G10: =IF(H10="ESPECES",1000,0) -> 1000 | H10: ESPECES | I10: =IF(F10=0,0,F10+J10+K10+L10+M10+N10) -> 20000 | J10: =IF(F10=0,0,3000) -> 3000 | K10: =IF(F10=0,0,500) -> 500 | L10: =IF(F10=0,0,1000) -> 1000 | M10: =IF(F10=0,0,2500) -> 2500 | P10: =IF(O10<=500000,(O10*1*3/100),(O10*12/100)) -> 0
D11: =TONT20000FEV2017!C11+TONT20000FEV2017!D11+TONT20000MARS2017!J11 -> 0 | J11: =IF(F11=0,0,3000) -> 0 | K11: =IF(F11=0,0,500) -> 0 | L11: =IF(F11=0,0,1000) -> 0 | M11: =IF(F11=0,0,2500) -> 0 | P11: =IF(O11<=500000,(O11*1*3/100),(O11*12/100)) -> 0
A12: AS201607 | B12: =VLOOKUP(A12,LISTADHERENT!A$5:H$51,2) -> DJOUNKEP SAMUEL | C12: =$P$56/$D$56*D12 -> 9485.7577 | D12: =TONT20000FEV2017!C12+TONT20000FEV2017!D12+TONT20000MARS2017!J12 -> 1080073.4 | F12: =IF(H12="ECHEC",0,13000) -> 13000 | G12: =IF(H12="ESPECES",1000,0) -> 0 | H12: BANQUE | I12: =IF(F12=0,0,F12+J12+K12+L12+M12+N12) -> 20000 | J12: =IF(F12=0,0,3000) -> 3000 | K12: =IF(F12=0,0,500) -> 500 | L12: =IF(F12=0,0,1000) -> 1000 | M12: =IF(F12=0,0,2500) -> 2500 | P12: =IF(O12<=500000,(O12*1*3/100),(O12*12/100)) -> 0 | T12: 10000 | U12: 42813 | V12: TUEGMA P LOTTI
A13: AS201608 | B13: =VLOOKUP(A13,LISTADHERENT!A$5:H$51,2) -> DJUOMBESSY ANTOINE | C13: =$P$56/$D$56*D13 -> 3862.7869 | D13: =TONT20000FEV2017!C13+TONT20000FEV2017!D13+TONT20000MARS2017!J13 -> 439827.09 | F13: =IF(H13="ECHEC",0,13000) -> 13000 | G13: =IF(H13="ESPECES",1000,0) -> 0 | H13: BANQUE | I13: =IF(F13=0,0,F13+J13+K13+L13+M13+N13) -> 20000 | J13: =IF(F13=0,0,3000) -> 3000 | K13: =IF(F13=0,0,500) -> 500 | L13: =IF(F13=0,0,1000) -> 1000 | M13: =IF(F13=0,0,2500) -> 2500 | P13: =IF(O13<=500000,(O13*1*3/100),(O13*12/100)) -> 0
A14: AS201609 | B14: =VLOOKUP(A14,LISTADHERENT!A$5:H$51,2) -> DONHOU DAVID | C14: =$P$56/$D$56*D14 -> 4315.9877 | D14: =TONT20000FEV2017!C14+TONT20000FEV2017!D14+TONT20000MARS2017!J14 -> 491429.73 | F14: =IF(H14="ECHEC",0,13000) -> 13000 | G14: =IF(H14="ESPECES",1000,0) -> 0 | H14: BANQUE | I14: =IF(F14=0,0,F14+J14+K14+L14+M14+N14) -> 20000 | J14: =IF(F14=0,0,3000) -> 3000 | K14: =IF(F14=0,0,500) -> 500 | L14: =IF(F14=0,0,1000) -> 1000 | M14: =IF(F14=0,0,2500) -> 2500 | P14: =IF(O14<=500000,(O14*1*3/100),(O14*12/100)) -> 0 | T14: 10000 | U14: 42813 | V14: KOUADJO
A15: AS201610 | B15: =VLOOKUP(A15,LISTADHERENT!A$5:H$51,2) -> FOTSO THOMAS | C15: =$P$56/$D$56*D15 -> 3860.7964 | D15: =TONT20000FEV2017!C15+TONT20000FEV2017!D15+TONT20000MARS2017!J15 -> 439600.45 | F15: =IF(H15="ECHEC",0,13000) -> 13000 | G15: =IF(H15="ESPECES",1000,0) -> 1000 | H15: ESPECES | I15: =IF(F15=0,0,F15+J15+K15+L15+M15+N15) -> 20000 | J15: =IF(F15=0,0,3000) -> 3000 | K15: =IF(F15=0,0,500) -> 500 | L15: =IF(F15=0,0,1000) -> 1000 | M15: =IF(F15=0,0,2500) -> 2500 | P15: =IF(O15<=500000,(O15*1*3/100),(O15*12/100)) -> 0
A16: AS201611 | B16: =VLOOKUP(A16,LISTADHERENT!A$5:H$51,2) -> HENGUE PAUL OMER | C16: =$P$56/$D$56*D16 -> 4424.8582 | D16: =TONT20000FEV2017!C16+TONT20000FEV2017!D16+TONT20000MARS2017!J16 -> 503826.02 | F16: 13000 | G16: =IF(H16="ESPECES",1000,0) -> 0 | H16: BANQUE | I16: =IF(F16=0,0,F16+J16+K16+L16+M16+N16) -> 20000 | J16: =IF(F16=0,0,3000) -> 3000 | K16: =IF(F16=0,0,500) -> 500 | L16: =IF(F16=0,0,1000) -> 1000 | M16: =IF(F16=0,0,2500) -> 2500 | P16: =IF(O16<=500000,(O16*1*3/100),(O16*12/100)) -> 0
A17: AS201612 | B17: =VLOOKUP(A17,LISTADHERENT!A$5:H$51,2) -> HODIEP JULES | C17: =$P$56/$D$56*D17 -> 446.60745 | D17: =TONT20000FEV2017!C17+TONT20000FEV2017!D17+TONT20000MARS2017!J17 -> 50851.901 | F17: =IF(H17="ECHEC",0,13000) -> 0 | G17: =IF(H17="ESPECES",1000,0) -> 0 | H17: ECHEC | I17: =IF(F17=0,0,F17+J17+K17+L17+M17+N17) -> 0 | J17: =IF(F17=0,0,3000) -> 0 | K17: =IF(F17=0,0,500) -> 0 | L17: =IF(F17=0,0,1000) -> 0 | M17: =IF(F17=0,0,2500) -> 0 | P17: =IF(O17<=500000,(O17*1*3/100),(O17*12/100)) -> 0
A18: AS201613 | B18: =VLOOKUP(A18,LISTADHERENT!A$5:H$51,2) -> HOTCHO BENJAMIN | C18: =$P$56/$D$56*D18 -> 4839.6985 | D18: =TONT20000FEV2017!C18+TONT20000FEV2017!D18+TONT20000MARS2017!J18 -> 551060.82 | F18: =IF(H18="ECHEC",0,13000) -> 13000 | G18: =IF(H18="ESPECES",1000,0) -> 0 | H18: BANQUE | I18: =IF(F18=0,0,F18+J18+K18+L18+M18+N18) -> 20000 | J18: =IF(F18=0,0,3000) -> 3000 | K18: =IF(F18=0,0,500) -> 500 | L18: =IF(F18=0,0,1000) -> 1000 | M18: =IF(F18=0,0,2500) -> 2500 | P18: =IF(O18<=500000,(O18*1*3/100),(O18*12/100)) -> 0
A19: AS201614 | B19: =VLOOKUP(A19,LISTADHERENT!A$5:H$51,2) -> KEPHE DAVID | C19: =$P$56/$D$56*D19 -> 996.4574 | D19: =TONT20000FEV2017!C19+TONT20000FEV2017!D19+TONT20000MARS2017!J19 -> 113459.27 | F19: =IF(H19="ECHEC",0,13000) -> 13000 | G19: =IF(H19="ESPECES",1000,0) -> 0 | H19: BANQUE | I19: =IF(F19=0,0,F19+J19+K19+L19+M19+N19) -> 20000 | J19: =IF(F19=0,0,3000) -> 3000 | K19: =IF(F19=0,0,500) -> 500 | L19: =IF(F19=0,0,1000) -> 1000 | M19: =IF(F19=0,0,2500) -> 2500 | P19: =IF(O19<=500000,(O19*1*3/100),(O19*12/100)) -> 0
A20: AS201615 | B20: =VLOOKUP(A20,LISTADHERENT!A$5:H$51,2) -> KEPSEU FRANCIS | C20: =$P$56/$D$56*D20 -> 19098.984 | D20: =TONT20000FEV2017!C20+TONT20000FEV2017!D20+TONT20000MARS2017!J20 -> 2174660.7 | F20: =IF(H20="ECHEC",0,13000) -> 13000 | G20: =IF(H20="ESPECES",1000,0) -> 0 | H20: BANQUE | I20: =IF(F20=0,0,F20+J20+K20+L20+M20+N20) -> 23000 | J20: 6000 | K20: =IF(F20=0,0,500) -> 500 | L20: =IF(F20=0,0,1000) -> 1000 | M20: =IF(F20=0,0,2500) -> 2500 | P20: =IF(O20<=500000,(O20*1*3/100),(O20*12/100)) -> 0
A21: AS201616 | B21: =VLOOKUP(A21,LISTADHERENT!A$5:H$51,2) -> KOUAMOU EMMANUEL | C21: =$P$56/$D$56*D21 -> 3859.3302 | D21: =TONT20000FEV2017!C21+TONT20000FEV2017!D21+TONT20000MARS2017!J21 -> 439433.51 | F21: =IF(H21="ECHEC",0,13000) -> 13000 | G21: =IF(H21="ESPECES",1000,0) -> 1000 | H21: ESPECES | I21: =IF(F21=0,0,F21+J21+K21+L21+M21+N21) -> 20000 | J21: =IF(F21=0,0,3000) -> 3000 | K21: =IF(F21=0,0,500) -> 500 | L21: =IF(F21=0,0,1000) -> 1000 | M21: =IF(F21=0,0,2500) -> 2500 | P21: =IF(O21<=500000,(O21*1*3/100),(O21*12/100)) -> 0
A22: AS201617 | B22: =VLOOKUP(A22,LISTADHERENT!A$5:H$51,2) -> KOUAMOU MOISE | C22: =$P$56/$D$56*D22 -> 3865.4704 | D22: =TONT20000FEV2017!C22+TONT20000FEV2017!D22+TONT20000MARS2017!J22 -> 440132.65 | F22: =IF(H22="ECHEC",0,13000) -> 13000 | G22: =IF(H22="ESPECES",1000,0) -> 0 | H22: BANQUE | I22: =IF(F22=0,0,F22+J22+K22+L22+M22+N22) -> 20000 | J22: =IF(F22=0,0,3000) -> 3000 | K22: =IF(F22=0,0,500) -> 500 | L22: =IF(F22=0,0,1000) -> 1000 | M22: =IF(F22=0,0,2500) -> 2500 | P22: =IF(O22<=500000,(O22*1*3/100),(O22*12/100)) -> 0 | Q22: 864000
A23: AS201618 | B23: =VLOOKUP(A23,LISTADHERENT!A$5:H$51,2) -> KOUAMO VICTOR PEGUY | C23: =$P$56/$D$56*D23 -> 3862.2537 | D23: =TONT20000FEV2017!C23+TONT20000FEV2017!D23+TONT20000MARS2017!J23 -> 439766.39 | F23: =IF(H23="ECHEC",0,13000) -> 13000 | G23: =IF(H23="ESPECES",1000,0) -> 1000 | H23: ESPECES | I23: =IF(F23=0,0,F23+J23+K23+L23+M23+N23) -> 20000 | J23: =IF(F23=0,0,3000) -> 3000 | K23: =IF(F23=0,0,500) -> 500 | L23: =IF(F23=0,0,1000) -> 1000 | M23: =IF(F23=0,0,2500) -> 2500 | P23: =IF(O23<=500000,(O23*1*3/100),(O23*12/100)) -> 0
A24: AS201619 | B24: =VLOOKUP(A24,LISTADHERENT!A$5:H$51,2) -> KOUATCHO MESSACK | C24: =$P$56/$D$56*D24 -> 3872.3126 | D24: =TONT20000FEV2017!C24+TONT20000FEV2017!D24+TONT20000MARS2017!J24 -> 440911.72 | F24: =IF(H24="ECHEC",0,13000) -> 13000 | G24: =IF(H24="ESPECES",1000,0) -> 0 | H24: BANQUE | I24: =IF(F24=0,0,F24+J24+K24+L24+M24+N24) -> 20000 | J24: =IF(F24=0,0,3000) -> 3000 | K24: =IF(F24=0,0,500) -> 500 | L24: =IF(F24=0,0,1000) -> 1000 | M24: =IF(F24=0,0,2500) -> 2500 | P24: =IF(O24<=500000,(O24*1*3/100),(O24*12/100)) -> 0
A25: AS201620 | B25: =VLOOKUP(A25,LISTADHERENT!A$5:H$51,2) -> LOWE JEAN | C25: =$P$56/$D$56*D25 -> 3861.9516 | D25: =TONT20000FEV2017!C25+TONT20000FEV2017!D25+TONT20000MARS2017!J25 -> 439731.99 | F25: =IF(H25="ECHEC",0,13000) -> 13000 | G25: =IF(H25="ESPECES",1000,0) -> 0 | H25: BANQUE | I25: =IF(F25=0,0,F25+J25+K25+L25+M25+N25) -> 20000 | J25: =IF(F25=0,0,3000) -> 3000 | K25: =IF(F25=0,0,500) -> 500 | L25: =IF(F25=0,0,1000) -> 1000 | M25: =IF(F25=0,0,2500) -> 2500 | P25: =IF(O25<=500000,(O25*1*3/100),(O25*12/100)) -> 0
A26: AS201621 | B26: =VLOOKUP(A26,LISTADHERENT!A$5:H$51,2) -> NANKAM APPOLINAIRE | C26: =$P$56/$D$56*D26 -> 3862.7424 | D26: =TONT20000FEV2017!C26+TONT20000FEV2017!D26+TONT20000MARS2017!J26 -> 439822.03 | F26: =IF(H26="ECHEC",0,13000) -> 13000 | G26: =IF(H26="ESPECES",1000,0) -> 1000 | H26: ESPECES | I26: =IF(F26=0,0,F26+J26+K26+L26+M26+N26) -> 20000 | J26: =IF(F26=0,0,3000) -> 3000 | K26: =IF(F26=0,0,500) -> 500 | L26: =IF(F26=0,0,1000) -> 1000 | M26: =IF(F26=0,0,2500) -> 2500 | P26: =IF(O26<=500000,(O26*1*3/100),(O26*12/100)) -> 0
A27: AS201622 | B27: =VLOOKUP(A27,LISTADHERENT!A$5:H$51,2) -> NDJOMO ETIENNE | C27: =$P$56/$D$56*D27 -> 4040.5773 | D27: =TONT20000FEV2017!C27+TONT20000FEV2017!D27+TONT20000MARS2017!J27 -> 460070.78 | F27: =IF(H27="ECHEC",0,13000) -> 13000 | G27: =IF(H27="ESPECES",1000,0) -> 1000 | H27: ESPECES | I27: =IF(F27=0,0,F27+J27+K27+L27+M27+N27) -> 25000 | J27: 8000 | K27: =IF(F27=0,0,500) -> 500 | L27: =IF(F27=0,0,1000) -> 1000 | M27: =IF(F27=0,0,2500) -> 2500 | O27: 600000 | P27: =IF(O27<=500000,(O27*1*3/100),(O27*12/100)) -> 72000 | Q27: 412000
A28: AS201623 | B28: =VLOOKUP(A28,LISTADHERENT!A$5:H$51,2) -> NDOMBOU JEAN CLAUDE | C28: =$P$56/$D$56*D28 -> 3732.0957 | D28: =TONT20000FEV2017!C28+TONT20000FEV2017!D28+TONT20000MARS2017!J28 -> 424946.25 | F28: =IF(H28="ECHEC",0,13000) -> 0 | G28: =IF(H28="ESPECES",1000,0) -> 0 | H28: ECHEC | I28: =IF(F28=0,0,F28+J28+K28+L28+M28+N28) -> 0 | J28: 0 | K28: =IF(F28=0,0,500) -> 0 | L28: =IF(F28=0,0,1000) -> 0 | M28: =IF(F28=0,0,2500) -> 0 | N28: 50000 | P28: =IF(O28<=500000,(O28*1*3/100),(O28*12/100)) -> 0
A29: AS201624 | B29: =VLOOKUP(A29,LISTADHERENT!A$5:H$51,2) -> NGONDIEP CLAUDE | C29: =$P$56/$D$56*D29 -> 3947.1929 | D29: =TONT20000FEV2017!C29+TONT20000FEV2017!D29+TONT20000MARS2017!J29 -> 449437.79 | F29: =IF(H29="ECHEC",0,13000) -> 13000 | G29: =IF(H29="ESPECES",1000,0) -> 1000 | H29: ESPECES | I29: =IF(F29=0,0,F29+J29+K29+L29+M29+N29) -> 20000 | J29: =IF(F29=0,0,3000) -> 3000 | K29: =IF(F29=0,0,500) -> 500 | L29: =IF(F29=0,0,1000) -> 1000 | M29: =IF(F29=0,0,2500) -> 2500 | P29: =IF(O29<=500000,(O29*1*3/100),(O29*12/100)) -> 0
A30: AS201625 | B30: =VLOOKUP(A30,LISTADHERENT!A$5:H$51,2) -> NGONGANG JEAN THEODORE | C30: =$P$56/$D$56*D30 -> 195.05741 | D30: =TONT20000FEV2017!C30+TONT20000FEV2017!D30+TONT20000MARS2017!J30 -> 22209.75 | F30: =IF(H30="ECHEC",0,13000) -> 13000 | G30: =IF(H30="ESPECES",1000,0) -> 0 | H30: BANQUE | I30: =IF(F30=0,0,F30+J30+K30+L30+M30+N30) -> 30000 | J30: 13000 | K30: =IF(F30=0,0,500) -> 500 | L30: =IF(F30=0,0,1000) -> 1000 | M30: =IF(F30=0,0,2500) -> 2500 | P30: =IF(O30<=500000,(O30*1*3/100),(O30*12/100)) -> 0
A31: AS201626 | B31: =VLOOKUP(A31,LISTADHERENT!A$5:H$51,2) -> NGUIEMEGNI MATHIEU BLAISE | C31: =$P$56/$D$56*D31 -> 4195.0056 | D31: =TONT20000FEV2017!C31+TONT20000FEV2017!D31+TONT20000MARS2017!J31 -> 477654.39 | F31: =IF(H31="ECHEC",0,13000) -> 13000 | G31: =IF(H31="ESPECES",1000,0) -> 0 | H31: BANQUE | I31: =IF(F31=0,0,F31+J31+K31+L31+M31+N31) -> 20000 | J31: =IF(F31=0,0,3000) -> 3000 | K31: =IF(F31=0,0,500) -> 500 | L31: =IF(F31=0,0,1000) -> 1000 | M31: =IF(F31=0,0,2500) -> 2500 | P31: =IF(O31<=500000,(O31*1*3/100),(O31*12/100)) -> 0
A32: AS201627 | B32: =VLOOKUP(A32,LISTADHERENT!A$5:H$51,2) -> NJEPDJIO MBOUKAM DELUXE | C32: =$P$56/$D$56*D32 -> 3907.431 | D32: =TONT20000FEV2017!C32+TONT20000FEV2017!D32+TONT20000MARS2017!J32 -> 444910.39 | F32: =IF(H32="ECHEC",0,13000) -> 13000 | G32: =IF(H32="ESPECES",1000,0) -> 1000 | H32: ESPECES | I32: =IF(F32=0,0,F32+J32+K32+L32+M32+N32) -> 20000 | J32: =IF(F32=0,0,3000) -> 3000 | K32: =IF(F32=0,0,500) -> 500 | L32: =IF(F32=0,0,1000) -> 1000 | M32: =IF(F32=0,0,2500) -> 2500 | P32: =IF(O32<=500000,(O32*1*3/100),(O32*12/100)) -> 0
A33: AS201628 | B33: =VLOOKUP(A33,LISTADHERENT!A$5:H$51,2) -> NKAMGANG JUSTIN DEJOLIE | C33: =$P$56/$D$56*D33 -> 4582.748 | D33: =TONT20000FEV2017!C33+TONT20000FEV2017!D33+TONT20000MARS2017!J33 -> 521803.76 | F33: =IF(H33="ECHEC",0,13000) -> 13000 | G33: =IF(H33="ESPECES",1000,0) -> 1000 | H33: ESPECES | I33: =IF(F33=0,0,F33+J33+K33+L33+M33+N33) -> 23000 | J33: 6000 | K33: =IF(F33=0,0,500) -> 500 | L33: =IF(F33=0,0,1000) -> 1000 | M33: =IF(F33=0,0,2500) -> 2500 | P33: =IF(O33<=500000,(O33*1*3/100),(O33*12/100)) -> 0
A34: AS201629 | B34: =VLOOKUP(A34,LISTADHERENT!A$5:H$51,2) -> NKEPSEU DIEUDONNE | C34: =$P$56/$D$56*D34 -> 4928.7627 | D34: =TONT20000FEV2017!C34+TONT20000FEV2017!D34+TONT20000MARS2017!J34 -> 561201.91 | F34: =IF(H34="ECHEC",0,13000) -> 13000 | G34: =IF(H34="ESPECES",1000,0) -> 1000 | H34: ESPECES | I34: =IF(F34=0,0,F34+J34+K34+L34+M34+N34) -> 25000 | J34: 8000 | K34: =IF(F34=0,0,500) -> 500 | L34: =IF(F34=0,0,1000) -> 1000 | M34: =IF(F34=0,0,2500) -> 2500 | P34: =IF(O34<=500000,(O34*1*3/100),(O34*12/100)) -> 0
D35: =TONT20000FEV2017!C35+TONT20000FEV2017!D35+TONT20000MARS2017!J35 -> 0 | J35: =IF(F35=0,0,3000) -> 0 | K35: =IF(F35=0,0,500) -> 0 | L35: =IF(F35=0,0,1000) -> 0 | M35: =IF(F35=0,0,2500) -> 0 | P35: =IF(O35<=500000,(O35*1*3/100),(O35*12/100)) -> 0
A36: AS201631 | B36: =VLOOKUP(A36,LISTADHERENT!A$5:H$51,2) -> NTEPDIE TUEMAC MZ | C36: =$P$56/$D$56*D36 -> 0 | D36: =TONT20000FEV2017!C36+TONT20000FEV2017!D36+TONT20000MARS2017!J36 -> 0 | F36: =IF(H36="ECHEC",0,13000) -> 0 | G36: =IF(H36="ESPECES",1000,0) -> 0 | H36: ECHEC | I36: =IF(F36=0,0,F36+J36+K36+L36+M36+N36) -> 0 | J36: =IF(F36=0,0,3000) -> 0 | K36: =IF(F36=0,0,500) -> 0 | L36: =IF(F36=0,0,1000) -> 0 | M36: =IF(F36=0,0,2500) -> 0 | P36: =IF(O36<=500000,(O36*1*3/100),(O36*12/100)) -> 0
D37: =TONT20000FEV2017!C37+TONT20000FEV2017!D37+TONT20000MARS2017!J37 -> 0 | J37: =IF(F37=0,0,3000) -> 0 | K37: =IF(F37=0,0,500) -> 0 | L37: =IF(F37=0,0,1000) -> 0 | M37: =IF(F37=0,0,2500) -> 0 | P37: =IF(O37<=500000,(O37*1*3/100),(O37*12/100)) -> 0
A38: AS201633 | B38: =VLOOKUP(A38,LISTADHERENT!A$5:H$51,2) -> PATEGO NJOSSU GUSTAVE | C38: =$P$56/$D$56*D38 -> 3860.3699 | D38: =TONT20000FEV2017!C38+TONT20000FEV2017!D38+TONT20000MARS2017!J38 -> 439551.89 | F38: =IF(H38="ECHEC",0,13000) -> 13000 | G38: =IF(H38="ESPECES",1000,0) -> 0 | H38: BANQUE | I38: =IF(F38=0,0,F38+J38+K38+L38+M38+N38) -> 20000 | J38: =IF(F38=0,0,3000) -> 3000 | K38: =IF(F38=0,0,500) -> 500 | L38: =IF(F38=0,0,1000) -> 1000 | M38: =IF(F38=0,0,2500) -> 2500 | P38: =IF(O38<=500000,(O38*1*3/100),(O38*12/100)) -> 0 | T38: 10000 | U38: 42813 | V38: YEPMOU J JACQUES
A39: AS201634 | B39: =VLOOKUP(A39,LISTADHERENT!A$5:H$51,2) -> SEUNOU RICHELOT | C39: =$P$56/$D$56*D39 -> 3898.4195 | D39: =TONT20000FEV2017!C39+TONT20000FEV2017!D39+TONT20000MARS2017!J39 -> 443884.32 | F39: =IF(H39="ECHEC",0,13000) -> 13000 | G39: =IF(H39="ESPECES",1000,0) -> 1000 | H39: ESPECES | I39: =IF(F39=0,0,F39+J39+K39+L39+M39+N39) -> 20000 | J39: =IF(F39=0,0,3000) -> 3000 | K39: =IF(F39=0,0,500) -> 500 | L39: =IF(F39=0,0,1000) -> 1000 | M39: =IF(F39=0,0,2500) -> 2500 | P39: =IF(O39<=500000,(O39*1*3/100),(O39*12/100)) -> 0
A40: AS201635 | B40: =VLOOKUP(A40,LISTADHERENT!A$5:H$51,2) -> SIME ABEL | C40: =$P$56/$D$56*D40 -> 3576.1441 | D40: =TONT20000FEV2017!C40+TONT20000FEV2017!D40+TONT20000MARS2017!J40 -> 407189.2 | F40: =IF(H40="ECHEC",0,13000) -> 13000 | G40: =IF(H40="ESPECES",1000,0) -> 1000 | H40: ESPECES | I40: =IF(F40=0,0,F40+J40+K40+L40+M40+N40) -> 20000 | J40: =IF(F40=0,0,3000) -> 3000 | K40: =IF(F40=0,0,500) -> 500 | L40: =IF(F40=0,0,1000) -> 1000 | M40: =IF(F40=0,0,2500) -> 2500 | P40: =IF(O40<=500000,(O40*1*3/100),(O40*12/100)) -> 0
A41: AS201636 | B41: =VLOOKUP(A41,LISTADHERENT!A$5:H$51,2) -> SIME FONGANG ERIC | C41: =$P$56/$D$56*D41 -> 3882.0516 | D41: =TONT20000FEV2017!C41+TONT20000FEV2017!D41+TONT20000MARS2017!J41 -> 442020.62 | F41: =IF(H41="ECHEC",0,13000) -> 13000 | G41: =IF(H41="ESPECES",1000,0) -> 1000 | H41: ESPECES | I41: =IF(F41=0,0,F41+J41+K41+L41+M41+N41) -> 20000 | J41: =IF(F41=0,0,3000) -> 3000 | K41: =IF(F41=0,0,500) -> 500 | L41: =IF(F41=0,0,1000) -> 1000 | M41: =IF(F41=0,0,2500) -> 2500 | P41: =IF(O41<=500000,(O41*1*3/100),(O41*12/100)) -> 0
A42: AS201637 | B42: =VLOOKUP(A42,LISTADHERENT!A$5:H$51,2) -> SIME MATHIEU | C42: =$P$56/$D$56*D42 -> 3878.6216 | D42: =TONT20000FEV2017!C42+TONT20000FEV2017!D42+TONT20000MARS2017!J42 -> 441630.08 | F42: =IF(H42="ECHEC",0,13000) -> 13000 | G42: =IF(H42="ESPECES",1000,0) -> 0 | H42: BANQUE | I42: =IF(F42=0,0,F42+J42+K42+L42+M42+N42) -> 20000 | J42: =IF(F42=0,0,3000) -> 3000 | K42: =IF(F42=0,0,500) -> 500 | L42: =IF(F42=0,0,1000) -> 1000 | M42: =IF(F42=0,0,2500) -> 2500 | O42: 1000000 | P42: =IF(O42<=500000,(O42*1*3/100),(O42*12/100)) -> 120000 | Q42: 563000
A43: AS201638 | B43: =VLOOKUP(A43,LISTADHERENT!A$5:H$51,2) -> SIME PIERRE | C43: =$P$56/$D$56*D43 -> 5089.9453 | D43: =TONT20000FEV2017!C43+TONT20000FEV2017!D43+TONT20000MARS2017!J43 -> 579554.59 | F43: =IF(H43="ECHEC",0,13000) -> 13000 | G43: =IF(H43="ESPECES",1000,0) -> 0 | H43: BANQUE | I43: =IF(F43=0,0,F43+J43+K43+L43+M43+N43) -> 30000 | J43: 13000 | K43: =IF(F43=0,0,500) -> 500 | L43: =IF(F43=0,0,1000) -> 1000 | M43: =IF(F43=0,0,2500) -> 2500 | P43: =IF(O43<=500000,(O43*1*3/100),(O43*12/100)) -> 0
A44: AS201639 | B44: =VLOOKUP(A44,LISTADHERENT!A$5:H$51,2) -> TAGNE NANGUEN MARTIN | C44: =$P$56/$D$56*D44 -> 3586.2119 | D44: =TONT20000FEV2017!C44+TONT20000FEV2017!D44+TONT20000MARS2017!J44 -> 408335.54 | F44: =IF(H44="ECHEC",0,13000) -> 13000 | G44: =IF(H44="ESPECES",1000,0) -> 0 | H44: BANQUE | I44: =IF(F44=0,0,F44+J44+K44+L44+M44+N44) -> 20000 | J44: =IF(F44=0,0,3000) -> 3000 | K44: =IF(F44=0,0,500) -> 500 | L44: =IF(F44=0,0,1000) -> 1000 | M44: =IF(F44=0,0,2500) -> 2500 | P44: =IF(O44<=500000,(O44*1*3/100),(O44*12/100)) -> 0 | T44: 10000 | U44: 42813 | V44: DJOMO JEAN JACQUES
A45: AS201640 | B45: =VLOOKUP(A45,LISTADHERENT!A$5:H$51,2) -> TCHOUAMOU JEAN PAUL | C45: =$P$56/$D$56*D45 -> 238.18441 | D45: =TONT20000FEV2017!C45+TONT20000FEV2017!D45+TONT20000MARS2017!J45 -> 27120.305 | F45: =IF(H45="ECHEC",0,13000) -> 13000 | G45: =IF(H45="ESPECES",1000,0) -> 0 | H45: BANQUE | I45: =IF(F45=0,0,F45+J45+K45+L45+M45+N45) -> 20000 | J45: =IF(F45=0,0,3000) -> 3000 | K45: =IF(F45=0,0,500) -> 500 | L45: =IF(F45=0,0,1000) -> 1000 | M45: =IF(F45=0,0,2500) -> 2500 | P45: =IF(O45<=500000,(O45*1*3/100),(O45*12/100)) -> 0
A46: AS201641 | B46: =VLOOKUP(A46,LISTADHERENT!A$5:H$51,2) -> TCHOUAMOU MATHIEU | C46: =$P$56/$D$56*D46 -> 3861.9694 | D46: =TONT20000FEV2017!C46+TONT20000FEV2017!D46+TONT20000MARS2017!J46 -> 439734.01 | F46: =IF(H46="ECHEC",0,13000) -> 13000 | G46: =IF(H46="ESPECES",1000,0) -> 1000 | H46: ESPECES | I46: =IF(F46=0,0,F46+J46+K46+L46+M46+N46) -> 20000 | J46: =IF(F46=0,0,3000) -> 3000 | K46: =IF(F46=0,0,500) -> 500 | L46: =IF(F46=0,0,1000) -> 1000 | M46: =IF(F46=0,0,2500) -> 2500 | P46: =IF(O46<=500000,(O46*1*3/100),(O46*12/100)) -> 0
A47: AS201642 | B47: =VLOOKUP(A47,LISTADHERENT!A$5:H$51,2) -> TCHOUANTE FRANCOIS | C47: =$P$56/$D$56*D47 -> 4279.3777 | D47: =TONT20000FEV2017!C47+TONT20000FEV2017!D47+TONT20000MARS2017!J47 -> 487261.22 | F47: =IF(H47="ECHEC",0,13000) -> 13000 | G47: =IF(H47="ESPECES",1000,0) -> 1000 | H47: ESPECES | I47: =IF(F47=0,0,F47+J47+K47+L47+M47+N47) -> 20000 | J47: =IF(F47=0,0,3000) -> 3000 | K47: =IF(F47=0,0,500) -> 500 | L47: =IF(F47=0,0,1000) -> 1000 | M47: =IF(F47=0,0,2500) -> 2500 | P47: =IF(O47<=500000,(O47*1*3/100),(O47*12/100)) -> 0
A48: AS201643 | B48: =VLOOKUP(A48,LISTADHERENT!A$5:H$51,2) -> TCHOUTOU NANA CLAUDE | C48: =$P$56/$D$56*D48 -> 106.29037 | D48: =TONT20000FEV2017!C48+TONT20000FEV2017!D48+TONT20000MARS2017!J48 -> 12102.502 | F48: =IF(H48="ECHEC",0,13000) -> 13000 | G48: =IF(H48="ESPECES",1000,0) -> 0 | H48: BANQUE | I48: =IF(F48=0,0,F48+J48+K48+L48+M48+N48) -> 20000 | J48: =IF(F48=0,0,3000) -> 3000 | K48: =IF(F48=0,0,500) -> 500 | L48: =IF(F48=0,0,1000) -> 1000 | M48: =IF(F48=0,0,2500) -> 2500 | P48: =IF(O48<=500000,(O48*1*3/100),(O48*12/100)) -> 0
A49: AS201644 | B49: =VLOOKUP(A49,LISTADHERENT!A$5:H$51,2) -> TIEYAM ERNEST | C49: =$P$56/$D$56*D49 -> 4107.3377 | D49: =TONT20000FEV2017!C49+TONT20000FEV2017!D49+TONT20000MARS2017!J49 -> 467672.29 | F49: =IF(H49="ECHEC",0,13000) -> 13000 | G49: =IF(H49="ESPECES",1000,0) -> 0 | H49: BANQUE | I49: =IF(F49=0,0,F49+J49+K49+L49+M49+N49) -> 48000 | J49: 31000 | K49: =IF(F49=0,0,500) -> 500 | L49: =IF(F49=0,0,1000) -> 1000 | M49: =IF(F49=0,0,2500) -> 2500 | P49: =IF(O49<=500000,(O49*1*3/100),(O49*12/100)) -> 0
A50: AS201645 | B50: =VLOOKUP(A50,LISTADHERENT!A$5:H$51,2) -> TUGMA PIERRE LOTI | C50: =$P$56/$D$56*D50 -> 3860.6276 | D50: =TONT20000FEV2017!C50+TONT20000FEV2017!D50+TONT20000MARS2017!J50 -> 439581.23 | F50: =IF(H50="ECHEC",0,13000) -> 13000 | G50: =IF(H50="ESPECES",1000,0) -> 0 | H50: BANQUE | I50: =IF(F50=0,0,F50+J50+K50+L50+M50+N50) -> 20000 | J50: =IF(F50=0,0,3000) -> 3000 | K50: =IF(F50=0,0,500) -> 500 | L50: =IF(F50=0,0,1000) -> 1000 | M50: =IF(F50=0,0,2500) -> 2500 | P50: =IF(O50<=500000,(O50*1*3/100),(O50*12/100)) -> 0
A51: AS201646 | B51: =VLOOKUP(A51,LISTADHERENT!A$5:H$51,2) -> YEPMOU JEAN JACQUES | C51: =$P$56/$D$56*D51 -> 7339.2873 | D51: =TONT20000FEV2017!C51+TONT20000FEV2017!D51+TONT20000MARS2017!J51 -> 835670.6 | F51: =IF(H51="ECHEC",0,13000) -> 13000 | G51: =IF(H51="ESPECES",1000,0) -> 1000 | H51: ESPECES | I51: =IF(F51=0,0,F51+J51+K51+L51+M51+N51) -> 20000 | J51: =IF(F51=0,0,3000) -> 3000 | K51: =IF(F51=0,0,500) -> 500 | L51: =IF(F51=0,0,1000) -> 1000 | M51: =IF(F51=0,0,2500) -> 2500 | P51: =IF(O51<=500000,(O51*1*3/100),(O51*12/100)) -> 0
A52: AS201647 | B52: =VLOOKUP(A52,LISTADHERENT!A$5:H$51,2) -> YOUMBI EMMANUEL | C52: =$P$56/$D$56*D52 -> 13466.42 | D52: =TONT20000FEV2017!C52+TONT20000FEV2017!D52+TONT20000MARS2017!J52 -> 1533322.1 | F52: =IF(H52="ECHEC",0,13000) -> 13000 | G52: =IF(H52="ESPECES",1000,0) -> 0 | H52: BANQUE | I52: =IF(F52=0,0,F52+J52+K52+L52+M52+N52) -> 20000 | J52: =IF(F52=0,0,3000) -> 3000 | K52: =IF(F52=0,0,500) -> 500 | L52: =IF(F52=0,0,1000) -> 1000 | M52: =IF(F52=0,0,2500) -> 2500 | P52: =IF(O52<=500000,(O52*1*3/100),(O52*12/100)) -> 0
A56: TOTAL | C56: =SUM(C5:C52) -> 192000 | D56: =SUM(D5:D52) -> 21861626 | E56: =SUM(E5:E52) -> 0 | F56: =SUM(F5:F52) -> 520000 | G56: =SUM(G5:G52) -> 18000 | I56: =SUM(I5:I52) -> 864000 | J56: =SUM(J5:J52) -> 184000 | K56: =SUM(K5:K52) -> 20000 | L56: =SUM(L5:L52) -> 40000 | M56: =SUM(M5:M52) -> 100000 | N56: =SUM(N5:N52) -> 50000 | O56: =SUM(O5:O52) -> 1600000 | P56: =SUM(P5:P52) -> 192000 | ... T56: =SUM(T5:T52) -> 40000
D59: PENALITE | E59: =+G56 -> 18000
D60: FONDS DE ROULEMENT | E60: =+K56 -> 20000
D61: EPARGNE | E61: =+J56 -> 184000
D62: MUTUELLE | E62: 0
D63: FRAIS EXCEPTIONNELS | E63: =+L56 -> 40000
D64: COLLATION | E64: =+M56 -> 100000
D65: TONTINE | E65: =+F56 -> 520000
D66: REMBOURSEMENT | E66: 12500
D68: TOTAL | E68: =SUM(E59:E66) -> 894500
D70: DETAIL
E71: ESPECES | F71: 373000
E72: BANQUE | F72: =+I56-F71 -> 491000

Sheet TONT20000AVRIL2017
A1: ASSOCIATION | B1: ASELBY
A2: ANNEE | B2: 2016/2017
A3: TONTINE | B3: 20 000
A4: MATRICULE | B4: NOM ET PRENOM | C4: REPARTITION INTERET | D4: CAPITAL COMPOSE | E4: SANCTION | F4: MONTANT TONTINE | G4: PENALITE | H4: MODE VERSEMENT | I4: MONTANT VERSE | J4: EPARGNE | K4: FONDS DE ROULEMENT | L4: FRAIS EXCEPTIONNEL | M4: COLLATION | N4: MUTUELLE | O4: EMPRUNT | P4: INTERET EMPRUNT | Q4: REMBOURSEMENT | R4: PENALITE EMPRUNT | S4: PENALITE FONDS | T4: INTERET ACHAT | U4: DATE ACHAT | V4: AVALISTE
A5: AS201648 | B5: =VLOOKUP(A5,LISTADHERENT!A$5:H$52,2,0) -> ASELBY | C5: =$P$56/$D$56*D5 -> 2203.3346 | D5: =TONT20000MARS2017!C5+TONT20000MARS2017!D5+TONT20000AVRIL2017!J5 -> 362434.27
A6: AS201601 | B6: =VLOOKUP(A6,LISTADHERENT!A$5:H$52,2,0) -> BAKOP ACHILLE | C6: =$P$56/$D$56*D6 -> 2928.6603 | D6: =TONT20000MARS2017!C6+TONT20000MARS2017!D6+TONT20000AVRIL2017!J6 -> 481745.66 | F6: =IF(H6="ECHEC",0,13000) -> 0 | G6: =IF(H6="ESPECES",1000,0) -> 0 | H6: ECHEC | I6: =IF(F6=0,0,J6+K6+L6+M6+N6+#REF!) -> 0 | J6: =IF(F6=0,0,3000) -> 0 | K6: =IF(F6=0,0,500) -> 0 | L6: =IF(F6=0,0,1000) -> 0 | M6: =IF(F6=0,0,2500) -> 0 | P6: =IF(O6<=500000,(O6*1*3/100),(O6*12/100)) -> 0
A7: AS201602 | B7: =VLOOKUP(A7,LISTADHERENT!A$5:H$51,2) -> BOUTCHOUANG WILLIAM | C7: =$P$56/$D$56*D7 -> 2715.3855 | D7: =TONT20000MARS2017!C7+TONT20000MARS2017!D7+TONT20000AVRIL2017!J7 -> 446663.34 | F7: =IF(H7="ECHEC",0,13000) -> 13000 | G7: =IF(H7="ESPECES",1000,0) -> 1000 | H7: ESPECES | I7: =IF(F7=0,0,F7+J7+K7+L7+M7+N7) -> 20000 | J7: =IF(F7=0,0,3000) -> 3000 | K7: =IF(F7=0,0,500) -> 500 | L7: =IF(F7=0,0,1000) -> 1000 | M7: =IF(F7=0,0,2500) -> 2500 | P7: =IF(O7<=500000,(O7*1*3/100),(O7*12/100)) -> 0 | T7: 10000 | U7: 42841
A8: AS201603 | B8: =VLOOKUP(A8,LISTADHERENT!A$5:H$51,2) -> CHINGUE FABRICE | C8: =$P$56/$D$56*D8 -> 2734.9557 | D8: =TONT20000MARS2017!C8+TONT20000MARS2017!D8+TONT20000AVRIL2017!J8 -> 449882.51 | F8: =IF(H8="ECHEC",0,13000) -> 13000 | G8: =IF(H8="ESPECES",1000,0) -> 1000 | H8: ESPECES | I8: =IF(F8=0,0,F8+J8+K8+L8+M8+N8) -> 20000 | J8: =IF(F8=0,0,3000) -> 3000 | K8: =IF(F8=0,0,500) -> 500 | L8: =IF(F8=0,0,1000) -> 1000 | M8: =IF(F8=0,0,2500) -> 2500 | P8: =IF(O8<=500000,(O8*1*3/100),(O8*12/100)) -> 0
A9: AS201604 | B9: =VLOOKUP(A9,LISTADHERENT!A$5:H$51,2) -> DJOMO JEAN PAUL | C9: =$P$56/$D$56*D9 -> 2757.864 | D9: =TONT20000MARS2017!C9+TONT20000MARS2017!D9+TONT20000AVRIL2017!J9 -> 453650.78 | F9: =IF(H9="ECHEC",0,13000) -> 13000 | G9: =IF(H9="ESPECES",1000,0) -> 1000 | H9: ESPECES | I9: =IF(F9=0,0,F9+J9+K9+L9+M9+N9) -> 20000 | J9: =IF(F9=0,0,3000) -> 3000 | K9: =IF(F9=0,0,500) -> 500 | L9: =IF(F9=0,0,1000) -> 1000 | M9: =IF(F9=0,0,2500) -> 2500 | P9: =IF(O9<=500000,(O9*1*3/100),(O9*12/100)) -> 0
A10: AS201605 | B10: =VLOOKUP(A10,LISTADHERENT!A$5:H$51,2) -> DJOUKWE NANGUEN GUY BLAISE | C10: =$P$56/$D$56*D10 -> 2740.0481 | D10: =TONT20000MARS2017!C10+TONT20000MARS2017!D10+TONT20000AVRIL2017!J10 -> 450720.17 | F10: =IF(H10="ECHEC",0,13000) -> 13000 | G10: =IF(H10="ESPECES",1000,0) -> 1000 | H10: ESPECES | I10: =IF(F10=0,0,F10+J10+K10+L10+M10+N10) -> 20000 | J10: =IF(F10=0,0,3000) -> 3000 | K10: =IF(F10=0,0,500) -> 500 | L10: =IF(F10=0,0,1000) -> 1000 | M10: =IF(F10=0,0,2500) -> 2500 | P10: =IF(O10<=500000,(O10*1*3/100),(O10*12/100)) -> 0
D11: =TONT20000MARS2017!C11+TONT20000MARS2017!D11+TONT20000AVRIL2017!J11 -> 0 | J11: =IF(F11=0,0,3000) -> 0 | K11: =IF(F11=0,0,500) -> 0 | L11: =IF(F11=0,0,1000) -> 0 | M11: =IF(F11=0,0,2500) -> 0 | P11: =IF(O11<=500000,(O11*1*3/100),(O11*12/100)) -> 0
A12: AS201607 | B12: =VLOOKUP(A12,LISTADHERENT!A$5:H$51,2) -> DJOUNKEP SAMUEL | C12: =$P$56/$D$56*D12 -> 6641.9582 | D12: =TONT20000MARS2017!C12+TONT20000MARS2017!D12+TONT20000AVRIL2017!J12 -> 1092559.1 | F12: =IF(H12="ECHEC",0,13000) -> 13000 | G12: =IF(H12="ESPECES",1000,0) -> 0 | H12: BANQUE | I12: =IF(F12=0,0,F12+J12+K12+L12+M12+N12) -> 20000 | J12: =IF(F12=0,0,3000) -> 3000 | K12: =IF(F12=0,0,500) -> 500 | L12: =IF(F12=0,0,1000) -> 1000 | M12: =IF(F12=0,0,2500) -> 2500 | P12: =IF(O12<=500000,(O12*1*3/100),(O12*12/100)) -> 0
A13: AS201608 | B13: =VLOOKUP(A13,LISTADHERENT!A$5:H$51,2) -> DJUOMBESSY ANTOINE | C13: =$P$56/$D$56*D13 -> 2715.5469 | D13: =TONT20000MARS2017!C13+TONT20000MARS2017!D13+TONT20000AVRIL2017!J13 -> 446689.88 | F13: =IF(H13="ECHEC",0,13000) -> 13000 | G13: =IF(H13="ESPECES",1000,0) -> 0 | H13: BANQUE | I13: =IF(F13=0,0,F13+J13+K13+L13+M13+N13) -> 20000 | J13: =IF(F13=0,0,3000) -> 3000 | K13: =IF(F13=0,0,500) -> 500 | L13: =IF(F13=0,0,1000) -> 1000 | M13: =IF(F13=0,0,2500) -> 2500 | P13: =IF(O13<=500000,(O13*1*3/100),(O13*12/100)) -> 0
A14: AS201609 | B14: =VLOOKUP(A14,LISTADHERENT!A$5:H$51,2) -> DONHOU DAVID | C14: =$P$56/$D$56*D14 -> 3032.0082 | D14: =TONT20000MARS2017!C14+TONT20000MARS2017!D14+TONT20000AVRIL2017!J14 -> 498745.72 | F14: =IF(H14="ECHEC",0,13000) -> 13000 | G14: =IF(H14="ESPECES",1000,0) -> 1000 | H14: ESPECES | I14: =IF(F14=0,0,F14+J14+K14+L14+M14+N14) -> 20000 | J14: =IF(F14=0,0,3000) -> 3000 | K14: =IF(F14=0,0,500) -> 500 | L14: =IF(F14=0,0,1000) -> 1000 | M14: =IF(F14=0,0,2500) -> 2500 | P14: =IF(O14<=500000,(O14*1*3/100),(O14*12/100)) -> 0
A15: AS201610 | B15: =VLOOKUP(A15,LISTADHERENT!A$5:H$51,2) -> FOTSO THOMAS | C15: =$P$56/$D$56*D15 -> 2714.157 | D15: =TONT20000MARS2017!C15+TONT20000MARS2017!D15+TONT20000AVRIL2017!J15 -> 446461.25 | F15: =IF(H15="ECHEC",0,13000) -> 13000 | G15: =IF(H15="ESPECES",1000,0) -> 1000 | H15: ESPECES | I15: =IF(F15=0,0,F15+J15+K15+L15+M15+N15) -> 20000 | J15: =IF(F15=0,0,3000) -> 3000 | K15: =IF(F15=0,0,500) -> 500 | L15: =IF(F15=0,0,1000) -> 1000 | M15: =IF(F15=0,0,2500) -> 2500 | P15: =IF(O15<=500000,(O15*1*3/100),(O15*12/100)) -> 0
A16: AS201611 | B16: =VLOOKUP(A16,LISTADHERENT!A$5:H$51,2) -> HENGUE PAUL OMER | C16: =$P$56/$D$56*D16 -> 3108.0304 | D16: =TONT20000MARS2017!C16+TONT20000MARS2017!D16+TONT20000AVRIL2017!J16 -> 511250.88 | F16: =IF(H16="ECHEC",0,13000) -> 13000 | G16: =IF(H16="ESPECES",1000,0) -> 0 | H16: BANQUE | I16: =IF(F16=0,0,F16+J16+K16+L16+M16+N16) -> 20000 | J16: =IF(F16=0,0,3000) -> 3000 | K16: =IF(F16=0,0,500) -> 500 | L16: =IF(F16=0,0,1000) -> 1000 | M16: =IF(F16=0,0,2500) -> 2500 | P16: =IF(O16<=500000,(O16*1*3/100),(O16*12/100)) -> 0
A17: AS201612 | B17: =VLOOKUP(A17,LISTADHERENT!A$5:H$51,2) -> HODIEP JULES | C17: =$P$56/$D$56*D17 -> 311.85731 | D17: =TONT20000MARS2017!C17+TONT20000MARS2017!D17+TONT20000AVRIL2017!J17 -> 51298.509 | F17: =IF(H17="ECHEC",0,13000) -> 0 | G17: =IF(H17="ESPECES",1000,0) -> 0 | H17: ECHEC | I17: =IF(F17=0,0,F17+J17+K17+L17+M17+N17) -> 0 | J17: =IF(F17=0,0,3000) -> 0 | K17: =IF(F17=0,0,500) -> 0 | L17: =IF(F17=0,0,1000) -> 0 | M17: =IF(F17=0,0,2500) -> 0 | P17: =IF(O17<=500000,(O17*1*3/100),(O17*12/100)) -> 0
A18: AS201613 | B18: =VLOOKUP(A18,LISTADHERENT!A$5:H$51,2) -> HOTCHO BENJAMIN | C18: =$P$56/$D$56*D18 -> 3397.7053 | D18: =TONT20000MARS2017!C18+TONT20000MARS2017!D18+TONT20000AVRIL2017!J18 -> 558900.52 | F18: =IF(H18="ECHEC",0,13000) -> 13000 | G18: =IF(H18="ESPECES",1000,0) -> 0 | H18: BANQUE | I18: =IF(F18=0,0,F18+J18+K18+L18+M18+N18) -> 20000 | J18: =IF(F18=0,0,3000) -> 3000 | K18: =IF(F18=0,0,500) -> 500 | L18: =IF(F18=0,0,1000) -> 1000 | M18: =IF(F18=0,0,2500) -> 2500 | P18: =IF(O18<=500000,(O18*1*3/100),(O18*12/100)) -> 0
A19: AS201614 | B19: =VLOOKUP(A19,LISTADHERENT!A$5:H$51,2) -> KEPHE DAVID | C19: =$P$56/$D$56*D19 -> 714.04465 | D19: =TONT20000MARS2017!C19+TONT20000MARS2017!D19+TONT20000AVRIL2017!J19 -> 117455.72 | F19: =IF(H19="ECHEC",0,13000) -> 13000 | G19: =IF(H19="ESPECES",1000,0) -> 0 | H19: BANQUE | I19: =IF(F19=0,0,F19+J19+K19+L19+M19+N19) -> 20000 | J19: =IF(F19=0,0,3000) -> 3000 | K19: =IF(F19=0,0,500) -> 500 | L19: =IF(F19=0,0,1000) -> 1000 | M19: =IF(F19=0,0,2500) -> 2500 | P19: =IF(O19<=500000,(O19*1*3/100),(O19*12/100)) -> 0
A20: AS201615 | B20: =VLOOKUP(A20,LISTADHERENT!A$5:H$51,2) -> KEPSEU FRANCIS | C20: =$P$56/$D$56*D20 -> 13372.926 | D20: =TONT20000MARS2017!C20+TONT20000MARS2017!D20+TONT20000AVRIL2017!J20 -> 2199759.7 | F20: =IF(H20="ECHEC",0,13000) -> 13000 | G20: =IF(H20="ESPECES",1000,0) -> 0 | H20: BANQUE | I20: =IF(F20=0,0,F20+J20+K20+L20+M20+N20) -> 23000 | J20: =IF(F20=0,0,6000) -> 6000 | K20: =IF(F20=0,0,500) -> 500 | L20: =IF(F20=0,0,1000) -> 1000 | M20: =IF(F20=0,0,2500) -> 2500 | P20: =IF(O20<=500000,(O20*1*3/100),(O20*12/100)) -> 0
A21: AS201616 | B21: =VLOOKUP(A21,LISTADHERENT!A$5:H$51,2) -> KOUAMOU EMMANUEL | C21: =$P$56/$D$56*D21 -> 2713.1332 | D21: =TONT20000MARS2017!C21+TONT20000MARS2017!D21+TONT20000AVRIL2017!J21 -> 446292.84 | F21: =IF(H21="ECHEC",0,13000) -> 13000 | G21: =IF(H21="ESPECES",1000,0) -> 1000 | H21: ESPECES | I21: =IF(F21=0,0,F21+J21+K21+L21+M21+N21) -> 20000 | J21: =IF(F21=0,0,3000) -> 3000 | K21: =IF(F21=0,0,500) -> 500 | L21: =IF(F21=0,0,1000) -> 1000 | M21: =IF(F21=0,0,2500) -> 2500 | P21: =IF(O21<=500000,(O21*1*3/100),(O21*12/100)) -> 0
A22: AS201617 | B22: =VLOOKUP(A22,LISTADHERENT!A$5:H$51,2) -> KOUAMOU MOISE | C22: =$P$56/$D$56*D22 -> 2717.4207 | D22: =TONT20000MARS2017!C22+TONT20000MARS2017!D22+TONT20000AVRIL2017!J22 -> 446998.12 | F22: =IF(H22="ECHEC",0,13000) -> 13000 | G22: =IF(H22="ESPECES",1000,0) -> 0 | H22: BANQUE | I22: =IF(F22=0,0,F22+J22+K22+L22+M22+N22) -> 20000 | J22: =IF(F22=0,0,3000) -> 3000 | K22: =IF(F22=0,0,500) -> 500 | L22: =IF(F22=0,0,1000) -> 1000 | M22: =IF(F22=0,0,2500) -> 2500 | O22: 500000 | P22: =IF(O22<=500000,(O22*1*3/100),(O22*12/100)) -> 15000
A23: AS201618 | B23: =VLOOKUP(A23,LISTADHERENT!A$5:H$51,2) -> KOUAMO VICTOR PEGUY | C23: =$P$56/$D$56*D23 -> 2715.1746 | D23: =TONT20000MARS2017!C23+TONT20000MARS2017!D23+TONT20000AVRIL2017!J23 -> 446628.64 | F23: =IF(H23="ECHEC",0,13000) -> 13000 | G23: =IF(H23="ESPECES",1000,0) -> 1000 | H23: ESPECES | I23: =IF(F23=0,0,F23+J23+K23+L23+M23+N23) -> 20000 | J23: =IF(F23=0,0,3000) -> 3000 | K23: =IF(F23=0,0,500) -> 500 | L23: =IF(F23=0,0,1000) -> 1000 | M23: =IF(F23=0,0,2500) -> 2500 | P23: =IF(O23<=500000,(O23*1*3/100),(O23*12/100)) -> 0
A24: AS201619 | B24: =VLOOKUP(A24,LISTADHERENT!A$5:H$51,2) -> KOUATCHO MESSACK | C24: =$P$56/$D$56*D24 -> 2722.1985 | D24: =TONT20000MARS2017!C24+TONT20000MARS2017!D24+TONT20000AVRIL2017!J24 -> 447784.03 | F24: =IF(H24="ECHEC",0,13000) -> 13000 | G24: =IF(H24="ESPECES",1000,0) -> 1000 | H24: ESPECES | I24: =IF(F24=0,0,F24+J24+K24+L24+M24+N24) -> 20000 | J24: =IF(F24=0,0,3000) -> 3000 | K24: =IF(F24=0,0,500) -> 500 | L24: =IF(F24=0,0,1000) -> 1000 | M24: =IF(F24=0,0,2500) -> 2500 | O24: 1000000 | P24: =IF(O24<=500000,(O24*1*3/100),(O24*12/100)) -> 120000 | Q24: 1120000
A25: AS201620 | B25: =VLOOKUP(A25,LISTADHERENT!A$5:H$51,2) -> LOWE JEAN | C25: =$P$56/$D$56*D25 -> 2714.9636 | D25: =TONT20000MARS2017!C25+TONT20000MARS2017!D25+TONT20000AVRIL2017!J25 -> 446593.94 | F25: =IF(H25="ECHEC",0,13000) -> 13000 | G25: =IF(H25="ESPECES",1000,0) -> 0 | H25: BANQUE | I25: =IF(F25=0,0,F25+J25+K25+L25+M25+N25) -> 20000 | J25: =IF(F25=0,0,3000) -> 3000 | K25: =IF(F25=0,0,500) -> 500 | L25: =IF(F25=0,0,1000) -> 1000 | M25: =IF(F25=0,0,2500) -> 2500 | P25: =IF(O25<=500000,(O25*1*3/100),(O25*12/100)) -> 0
A26: AS201621 | B26: =VLOOKUP(A26,LISTADHERENT!A$5:H$51,2) -> NANKAM APPOLINAIRE | C26: =$P$56/$D$56*D26 -> 2715.5158 | D26: =TONT20000MARS2017!C26+TONT20000MARS2017!D26+TONT20000AVRIL2017!J26 -> 446684.78 | F26: =IF(H26="ECHEC",0,13000) -> 13000 | G26: =IF(H26="ESPECES",1000,0) -> 0 | H26: BANQUE | I26: =IF(F26=0,0,F26+J26+K26+L26+M26+N26) -> 20000 | J26: =IF(F26=0,0,3000) -> 3000 | K26: =IF(F26=0,0,500) -> 500 | L26: =IF(F26=0,0,1000) -> 1000 | M26: =IF(F26=0,0,2500) -> 2500 | P26: =IF(O26<=500000,(O26*1*3/100),(O26*12/100)) -> 0
A27: AS201622 | B27: =VLOOKUP(A27,LISTADHERENT!A$5:H$51,2) -> NDJOMO ETIENNE | C27: =$P$56/$D$56*D27 -> 2870.0908 | D27: =TONT20000MARS2017!C27+TONT20000MARS2017!D27+TONT20000AVRIL2017!J27 -> 472111.35 | F27: =IF(H27="ECHEC",0,13000) -> 13000 | G27: =IF(H27="ESPECES",1000,0) -> 0 | H27: BANQUE | I27: =IF(F27=0,0,F27+J27+K27+L27+M27+N27) -> 25000 | J27: =IF(F27=0,0,8000) -> 8000 | K27: =IF(F27=0,0,500) -> 500 | L27: =IF(F27=0,0,1000) -> 1000 | M27: =IF(F27=0,0,2500) -> 2500 | P27: =IF(O27<=500000,(O27*1*3/100),(O27*12/100)) -> 0
A28: AS201623 | B28: =VLOOKUP(A28,LISTADHERENT!A$5:H$51,2) -> NDOMBOU JEAN CLAUDE | C28: =$P$56/$D$56*D28 -> 2606.05 | D28: =TONT20000MARS2017!C28+TONT20000MARS2017!D28+TONT20000AVRIL2017!J28 -> 428678.35 | J28: =IF(F28=0,0,3000) -> 0 | K28: =IF(F28=0,0,500) -> 0 | L28: =IF(F28=0,0,1000) -> 0 | M28: =IF(F28=0,0,2500) -> 0 | P28: =IF(O28<=500000,(O28*1*3/100),(O28*12/100)) -> 0
A29: AS201624 | B29: =VLOOKUP(A29,LISTADHERENT!A$5:H$51,2) -> NGONDIEP CLAUDE | C29: =$P$56/$D$56*D29 -> 2774.486 | D29: =TONT20000MARS2017!C29+TONT20000MARS2017!D29+TONT20000AVRIL2017!J29 -> 456384.98 | F29: =IF(H29="ECHEC",0,13000) -> 13000 | G29: =IF(H29="ESPECES",1000,0) -> 0 | H29: BANQUE | I29: =IF(F29=0,0,F29+J29+K29+L29+M29+N29) -> 20000 | J29: =IF(F29=0,0,3000) -> 3000 | K29: =IF(F29=0,0,500) -> 500 | L29: =IF(F29=0,0,1000) -> 1000 | M29: =IF(F29=0,0,2500) -> 2500 | P29: =IF(O29<=500000,(O29*1*3/100),(O29*12/100)) -> 0
A30: AS201625 | B30: =VLOOKUP(A30,LISTADHERENT!A$5:H$51,2) -> NGONGANG JEAN THEODORE | C30: =$P$56/$D$56*D30 -> 215.23527 | D30: =TONT20000MARS2017!C30+TONT20000MARS2017!D30+TONT20000AVRIL2017!J30 -> 35404.808 | F30: =IF(H30="ECHEC",0,13000) -> 13000 | G30: =IF(H30="ESPECES",1000,0) -> 0 | H30: BANQUE | I30: =IF(F30=0,0,F30+J30+K30+L30+M30+N30) -> 30000 | J30: =IF(F30=0,0,13000) -> 13000 | K30: =IF(F30=0,0,500) -> 500 | L30: =IF(F30=0,0,1000) -> 1000 | M30: =IF(F30=0,0,2500) -> 2500 | P30: =IF(O30<=500000,(O30*1*3/100),(O30*12/100)) -> 0
A31: AS201626 | B31: =VLOOKUP(A31,LISTADHERENT!A$5:H$51,2) -> NGUIEMEGNI MATHIEU BLAISE | C31: =$P$56/$D$56*D31 -> 2947.5287 | D31: =TONT20000MARS2017!C31+TONT20000MARS2017!D31+TONT20000AVRIL2017!J31 -> 484849.4 | F31: =IF(H31="ECHEC",0,13000) -> 13000 | G31: =IF(H31="ESPECES",1000,0) -> 1000 | H31: ESPECES | I31: =IF(F31=0,0,F31+J31+K31+L31+M31+N31) -> 20000 | J31: =IF(F31=0,0,3000) -> 3000 | K31: =IF(F31=0,0,500) -> 500 | L31: =IF(F31=0,0,1000) -> 1000 | M31: =IF(F31=0,0,2500) -> 2500 | P31: =IF(O31<=500000,(O31*1*3/100),(O31*12/100)) -> 0
A32: AS201627 | B32: =VLOOKUP(A32,LISTADHERENT!A$5:H$51,2) -> NJEPDJIO MBOUKAM DELUXE | C32: =$P$56/$D$56*D32 -> 2746.721 | D32: =TONT20000MARS2017!C32+TONT20000MARS2017!D32+TONT20000AVRIL2017!J32 -> 451817.82 | F32: =IF(H32="ECHEC",0,13000) -> 13000 | G32: =IF(H32="ESPECES",1000,0) -> 1000 | H32: ESPECES | I32: =IF(F32=0,0,F32+J32+K32+L32+M32+N32) -> 20000 | J32: =IF(F32=0,0,3000) -> 3000 | K32: =IF(F32=0,0,500) -> 500 | L32: =IF(F32=0,0,1000) -> 1000 | M32: =IF(F32=0,0,2500) -> 2500 | P32: =IF(O32<=500000,(O32*1*3/100),(O32*12/100)) -> 0
A33: AS201628 | B33: =VLOOKUP(A33,LISTADHERENT!A$5:H$51,2) -> NKAMGANG JUSTIN DEJOLIE | C33: =$P$56/$D$56*D33 -> 3236.5195 | D33: =TONT20000MARS2017!C33+TONT20000MARS2017!D33+TONT20000AVRIL2017!J33 -> 532386.51 | F33: =IF(H33="ECHEC",0,13000) -> 13000 | G33: =IF(H33="ESPECES",1000,0) -> 1000 | H33: ESPECES | I33: =IF(F33=0,0,F33+J33+K33+L33+M33+N33) -> 23000 | J33: =IF(F33=0,0,6000) -> 6000 | K33: =IF(F33=0,0,500) -> 500 | L33: =IF(F33=0,0,1000) -> 1000 | M33: =IF(F33=0,0,2500) -> 2500 | P33: =IF(O33<=500000,(O33*1*3/100),(O33*12/100)) -> 0
A34: AS201629 | B34: =VLOOKUP(A34,LISTADHERENT!A$5:H$51,2) -> NKEPSEU DIEUDONNE | C34: =$P$56/$D$56*D34 -> 3490.2935 | D34: =TONT20000MARS2017!C34+TONT20000MARS2017!D34+TONT20000AVRIL2017!J34 -> 574130.68 | F34: =IF(H34="ECHEC",0,13000) -> 13000 | G34: =IF(H34="ESPECES",1000,0) -> 1000 | H34: ESPECES | I34: =IF(F34=0,0,F34+J34+K34+L34+M34+N34) -> 25000 | J34: =IF(F34=0,0,8000) -> 8000 | K34: =IF(F34=0,0,500) -> 500 | L34: =IF(F34=0,0,1000) -> 1000 | M34: =IF(F34=0,0,2500) -> 2500 | P34: =IF(O34<=500000,(O34*1*3/100),(O34*12/100)) -> 0
D35: =TONT20000MARS2017!C35+TONT20000MARS2017!D35+TONT20000AVRIL2017!J35 -> 0 | J35: =IF(F35=0,0,3000) -> 0 | K35: =IF(F35=0,0,500) -> 0 | L35: =IF(F35=0,0,1000) -> 0 | M35: =IF(F35=0,0,2500) -> 0 | P35: =IF(O35<=500000,(O35*1*3/100),(O35*12/100)) -> 0
A36: AS201631 | B36: =VLOOKUP(A36,LISTADHERENT!A$5:H$51,2) -> NTEPDIE TUEMAC MZ | C36: =$P$56/$D$56*D36 -> 0 | D36: =TONT20000MARS2017!C36+TONT20000MARS2017!D36+TONT20000AVRIL2017!J36 -> 0 | F36: =IF(H36="ECHEC",0,13000) -> 0 | G36: =IF(H36="ESPECES",1000,0) -> 0 | H36: ECHEC | I36: =IF(F36=0,0,F36+J36+K36+L36+M36+N36) -> 0 | J36: =IF(F36=0,0,3000) -> 0 | K36: =IF(F36=0,0,500) -> 0 | L36: =IF(F36=0,0,1000) -> 0 | M36: =IF(F36=0,0,2500) -> 0 | P36: =IF(O36<=500000,(O36*1*3/100),(O36*12/100)) -> 0
D37: =TONT20000MARS2017!C37+TONT20000MARS2017!D37+TONT20000AVRIL2017!J37 -> 0 | J37: =IF(F37=0,0,3000) -> 0 | K37: =IF(F37=0,0,500) -> 0 | L37: =IF(F37=0,0,1000) -> 0 | M37: =IF(F37=0,0,2500) -> 0 | P37: =IF(O37<=500000,(O37*1*3/100),(O37*12/100)) -> 0
A38: AS201633 | B38: =VLOOKUP(A38,LISTADHERENT!A$5:H$51,2) -> PATEGO NJOSSU GUSTAVE | C38: =$P$56/$D$56*D38 -> 2713.8591 | D38: =TONT20000MARS2017!C38+TONT20000MARS2017!D38+TONT20000AVRIL2017!J38 -> 446412.26 | F38: =IF(H38="ECHEC",0,13000) -> 13000 | G38: =IF(H38="ESPECES",1000,0) -> 0 | H38: BANQUE | I38: =IF(F38=0,0,F38+J38+K38+L38+M38+N38) -> 20000 | J38: =IF(F38=0,0,3000) -> 3000 | K38: =IF(F38=0,0,500) -> 500 | L38: =IF(F38=0,0,1000) -> 1000 | M38: =IF(F38=0,0,2500) -> 2500 | P38: =IF(O38<=500000,(O38*1*3/100),(O38*12/100)) -> 0
A39: AS201634 | B39: =VLOOKUP(A39,LISTADHERENT!A$5:H$51,2) -> SEUNOU RICHELOT | C39: =$P$56/$D$56*D39 -> 2740.4284 | D39: =TONT20000MARS2017!C39+TONT20000MARS2017!D39+TONT20000AVRIL2017!J39 -> 450782.74 | F39: =IF(H39="ECHEC",0,13000) -> 13000 | G39: =IF(H39="ESPECES",1000,0) -> 1000 | H39: ESPECES | I39: =IF(F39=0,0,F39+J39+K39+L39+M39+N39) -> 20000 | J39: =IF(F39=0,0,3000) -> 3000 | K39: =IF(F39=0,0,500) -> 500 | L39: =IF(F39=0,0,1000) -> 1000 | M39: =IF(F39=0,0,2500) -> 2500 | P39: =IF(O39<=500000,(O39*1*3/100),(O39*12/100)) -> 0
A40: AS201635 | B40: =VLOOKUP(A40,LISTADHERENT!A$5:H$51,2) -> SIME ABEL | C40: =$P$56/$D$56*D40 -> 2497.152 | D40: =TONT20000MARS2017!C40+TONT20000MARS2017!D40+TONT20000AVRIL2017!J40 -> 410765.34 | F40: =IF(H40="ECHEC",0,13000) -> 0 | G40: =IF(H40="ESPECES",1000,0) -> 0 | H40: ECHEC | I40: =IF(F40=0,0,F40+J40+K40+L40+M40+N40) -> 0 | J40: =IF(F40=0,0,3000) -> 0 | K40: =IF(F40=0,0,500) -> 0 | L40: =IF(F40=0,0,1000) -> 0 | M40: =IF(F40=0,0,2500) -> 0 | P40: =IF(O40<=500000,(O40*1*3/100),(O40*12/100)) -> 0
A41: AS201636 | B41: =VLOOKUP(A41,LISTADHERENT!A$5:H$51,2) -> SIME FONGANG ERIC | C41: =$P$56/$D$56*D41 -> 2728.999 | D41: =TONT20000MARS2017!C41+TONT20000MARS2017!D41+TONT20000AVRIL2017!J41 -> 448902.68 | F41: =IF(H41="ECHEC",0,13000) -> 13000 | G41: =IF(H41="ESPECES",1000,0) -> 0 | H41: BANQUE | I41: =IF(F41=0,0,F41+J41+K41+L41+M41+N41) -> 20000 | J41: =IF(F41=0,0,3000) -> 3000 | K41: =IF(F41=0,0,500) -> 500 | L41: =IF(F41=0,0,1000) -> 1000 | M41: =IF(F41=0,0,2500) -> 2500 | P41: =IF(O41<=500000,(O41*1*3/100),(O41*12/100)) -> 0 | T41: 10000 | U41: 42841
A42: AS201637 | B42: =VLOOKUP(A42,LISTADHERENT!A$5:H$51,2) -> SIME MATHIEU | C42: =$P$56/$D$56*D42 -> 2726.604 | D42: =TONT20000MARS2017!C42+TONT20000MARS2017!D42+TONT20000AVRIL2017!J42 -> 448508.7 | F42: =IF(H42="ECHEC",0,13000) -> 13000 | G42: =IF(H42="ESPECES",1000,0) -> 0 | H42: BANQUE | I42: =IF(F42=0,0,F42+J42+K42+L42+M42+N42) -> 20000 | J42: =IF(F42=0,0,3000) -> 3000 | K42: =IF(F42=0,0,500) -> 500 | L42: =IF(F42=0,0,1000) -> 1000 | M42: =IF(F42=0,0,2500) -> 2500 | P42: =IF(O42<=500000,(O42*1*3/100),(O42*12/100)) -> 0
A43: AS201638 | B43: =VLOOKUP(A43,LISTADHERENT!A$5:H$51,2) -> SIME PIERRE | C43: =$P$56/$D$56*D43 -> 3633.2405 | D43: =TONT20000MARS2017!C43+TONT20000MARS2017!D43+TONT20000AVRIL2017!J43 -> 597644.53 | F43: =IF(H43="ECHEC",0,13000) -> 13000 | G43: =IF(H43="ESPECES",1000,0) -> 0 | H43: BANQUE | I43: =IF(F43=0,0,F43+J43+K43+L43+M43+N43) -> 30000 | J43: =IF(F43=0,0,13000) -> 13000 | K43: =IF(F43=0,0,500) -> 500 | L43: =IF(F43=0,0,1000) -> 1000 | M43: =IF(F43=0,0,2500) -> 2500 | P43: =IF(O43<=500000,(O43*1*3/100),(O43*12/100)) -> 0
A44: AS201639 | B44: =VLOOKUP(A44,LISTADHERENT!A$5:H$51,2) -> TAGNE NANGUEN MARTIN | C44: =$P$56/$D$56*D44 -> 2522.42 | D44: =TONT20000MARS2017!C44+TONT20000MARS2017!D44+TONT20000AVRIL2017!J44 -> 414921.75 | F44: =IF(H44="ECHEC",0,13000) -> 13000 | G44: =IF(H44="ESPECES",1000,0) -> 0 | H44: BANQUE | I44: =IF(F44=0,0,F44+J44+K44+L44+M44+N44) -> 20000 | J44: =IF(F44=0,0,3000) -> 3000 | K44: =IF(F44=0,0,500) -> 500 | L44: =IF(F44=0,0,1000) -> 1000 | M44: =IF(F44=0,0,2500) -> 2500 | P44: =IF(O44<=500000,(O44*1*3/100),(O44*12/100)) -> 0
A45: AS201640 | B45: =VLOOKUP(A45,LISTADHERENT!A$5:H$51,2) -> TCHOUAMOU JEAN PAUL | C45: =$P$56/$D$56*D45 -> 184.55735 | D45: =TONT20000MARS2017!C45+TONT20000MARS2017!D45+TONT20000AVRIL2017!J45 -> 30358.489 | F45: =IF(H45="ECHEC",0,13000) -> 13000 | G45: =IF(H45="ESPECES",1000,0) -> 0 | H45: BANQUE | I45: =IF(F45=0,0,F45+J45+K45+L45+M45+N45) -> 20000 | J45: =IF(F45=0,0,3000) -> 3000 | K45: =IF(F45=0,0,500) -> 500 | L45: =IF(F45=0,0,1000) -> 1000 | M45: =IF(F45=0,0,2500) -> 2500 | P45: =IF(O45<=500000,(O45*1*3/100),(O45*12/100)) -> 0
A46: AS201641 | B46: =VLOOKUP(A46,LISTADHERENT!A$5:H$51,2) -> TCHOUAMOU MATHIEU | C46: =$P$56/$D$56*D46 -> 2714.976 | D46: =TONT20000MARS2017!C46+TONT20000MARS2017!D46+TONT20000AVRIL2017!J46 -> 446595.98 | F46: =IF(H46="ECHEC",0,13000) -> 13000 | G46: =IF(H46="ESPECES",1000,0) -> 0 | H46: BANQUE | I46: =IF(F46=0,0,F46+J46+K46+L46+M46+N46) -> 20000 | J46: =IF(F46=0,0,3000) -> 3000 | K46: =IF(F46=0,0,500) -> 500 | L46: =IF(F46=0,0,1000) -> 1000 | M46: =IF(F46=0,0,2500) -> 2500 | P46: =IF(O46<=500000,(O46*1*3/100),(O46*12/100)) -> 0
A47: AS201642 | B47: =VLOOKUP(A47,LISTADHERENT!A$5:H$51,2) -> TCHOUANTE FRANCOIS | C47: =$P$56/$D$56*D47 -> 3006.4442 | D47: =TONT20000MARS2017!C47+TONT20000MARS2017!D47+TONT20000AVRIL2017!J47 -> 494540.6 | F47: =IF(H47="ECHEC",0,13000) -> 13000 | G47: =IF(H47="ESPECES",1000,0) -> 1000 | H47: ESPECES | I47: =IF(F47=0,0,F47+J47+K47+L47+M47+N47) -> 20000 | J47: =IF(F47=0,0,3000) -> 3000 | K47: =IF(F47=0,0,500) -> 500 | L47: =IF(F47=0,0,1000) -> 1000 | M47: =IF(F47=0,0,2500) -> 2500 | P47: =IF(O47<=500000,(O47*1*3/100),(O47*12/100)) -> 0
A48: AS201643 | B48: =VLOOKUP(A48,LISTADHERENT!A$5:H$51,2) -> TCHOUTOU NANA CLAUDE | C48: =$P$56/$D$56*D48 -> 92.458304 | D48: =TONT20000MARS2017!C48+TONT20000MARS2017!D48+TONT20000AVRIL2017!J48 -> 15208.792 | F48: =IF(H48="ECHEC",0,13000) -> 13000 | G48: =IF(H48="ESPECES",1000,0) -> 0 | H48: BANQUE | I48: =IF(F48=0,0,F48+J48+K48+L48+M48+N48) -> 20000 | J48: =IF(F48=0,0,3000) -> 3000 | K48: =IF(F48=0,0,500) -> 500 | L48: =IF(F48=0,0,1000) -> 1000 | M48: =IF(F48=0,0,2500) -> 2500 | P48: =IF(O48<=500000,(O48*1*3/100),(O48*12/100)) -> 0
A49: AS201644 | B49: =VLOOKUP(A49,LISTADHERENT!A$5:H$51,2) -> TIEYAM ERNEST | C49: =$P$56/$D$56*D49 -> 2886.3119 | D49: =TONT20000MARS2017!C49+TONT20000MARS2017!D49+TONT20000AVRIL2017!J49 -> 474779.63 | F49: =IF(H49="ECHEC",0,13000) -> 13000 | G49: =IF(H49="ESPECES",1000,0) -> 1000 | H49: ESPECES | I49: =IF(F49=0,0,F49+J49+K49+L49+M49+N49) -> 20000 | J49: =IF(F49=0,0,3000) -> 3000 | K49: =IF(F49=0,0,500) -> 500 | L49: =IF(F49=0,0,1000) -> 1000 | M49: =IF(F49=0,0,2500) -> 2500 | P49: =IF(O49<=500000,(O49*1*3/100),(O49*12/100)) -> 0
A50: AS201645 | B50: =VLOOKUP(A50,LISTADHERENT!A$5:H$51,2) -> TUGMA PIERRE LOTI | C50: =$P$56/$D$56*D50 -> 2714.0391 | D50: =TONT20000MARS2017!C50+TONT20000MARS2017!D50+TONT20000AVRIL2017!J50 -> 446441.86 | F50: =IF(H50="ECHEC",0,13000) -> 13000 | G50: =IF(H50="ESPECES",1000,0) -> 0 | H50: BANQUE | I50: =IF(F50=0,0,F50+J50+K50+L50+M50+N50) -> 20000 | J50: =IF(F50=0,0,3000) -> 3000 | K50: =IF(F50=0,0,500) -> 500 | L50: =IF(F50=0,0,1000) -> 1000 | M50: =IF(F50=0,0,2500) -> 2500 | P50: =IF(O50<=500000,(O50*1*3/100),(O50*12/100)) -> 0
A51: AS201646 | B51: =VLOOKUP(A51,LISTADHERENT!A$5:H$51,2) -> YEPMOU JEAN JACQUES | C51: =$P$56/$D$56*D51 -> 5143.1196 | D51: =TONT20000MARS2017!C51+TONT20000MARS2017!D51+TONT20000AVRIL2017!J51 -> 846009.88 | F51: =IF(H51="ECHEC",0,13000) -> 13000 | G51: =IF(H51="ESPECES",1000,0) -> 1000 | H51: ESPECES | I51: =IF(F51=0,0,F51+J51+K51+L51+M51+N51) -> 20000 | J51: =IF(F51=0,0,3000) -> 3000 | K51: =IF(F51=0,0,500) -> 500 | L51: =IF(F51=0,0,1000) -> 1000 | M51: =IF(F51=0,0,2500) -> 2500 | P51: =IF(O51<=500000,(O51*1*3/100),(O51*12/100)) -> 0 | T51: 10000 | U51: 42841
A52: AS201647 | B52: =VLOOKUP(A52,LISTADHERENT!A$5:H$51,2) -> YOUMBI EMMANUEL | C52: =$P$56/$D$56*D52 -> 9421.5777 | D52: =TONT20000MARS2017!C52+TONT20000MARS2017!D52+TONT20000AVRIL2017!J52 -> 1549788.5 | F52: =IF(H52="ECHEC",0,13000) -> 13000 | G52: =IF(H52="ESPECES",1000,0) -> 0 | H52: BANQUE | I52: =IF(F52=0,0,F52+J52+K52+L52+M52+N52) -> 20000 | J52: =IF(F52=0,0,3000) -> 3000 | K52: =IF(F52=0,0,500) -> 500 | L52: =IF(F52=0,0,1000) -> 1000 | M52: =IF(F52=0,0,2500) -> 2500 | P52: =IF(O52<=500000,(O52*1*3/100),(O52*12/100)) -> 0
A56: TOTAL | C56: =SUM(C5:C52) -> 135000 | D56: =SUM(D5:D52) -> 22206626 | E56: =SUM(E5:E52) -> 0 | F56: =SUM(F5:F52) -> 507000 | G56: =SUM(G5:G52) -> 17000 | I56: =SUM(I5:I52) -> 816000 | J56: =SUM(J5:J52) -> 153000 | K56: =SUM(K5:K52) -> 19500 | L56: =SUM(L5:L52) -> 39000 | M56: =SUM(M5:M52) -> 97500 | N56: =SUM(N5:N52) -> 0 | O56: =SUM(O5:O52) -> 1500000 | P56: =SUM(P5:P52) -> 135000 | ... T56: =SUM(T5:T52) -> 30000
D60: FONDS DE ROULEMENT | E60: =+K56 -> 19500
D61: EPARGNE | E61: =+J56 -> 153000
D62: MUTUELLE | E62: 0
D63: FRAIS EXCEPTIONNELS | E63: =+L56 -> 39000
D64: COLLATION | E64: =+M56 -> 97500
D65: TONTINE | E65: =+F56 -> 507000
D66: REMBOURSEMENT | E66: 0
D68: TOTAL | E68: =SUM(E60:E66) -> 816000
D70: DETAIL
E71: ESPECES | F71: =SUMIFS(I6:I52,H6:H52,"ESPECES") -> 348000 | G71: =SUMIFS(F6:F52,H6:H52,"ESPECES") -> 221000
E72: BANQUE | F72: =SUMIFS(I6:I52,H6:H52,"BANQUE") -> 468000 | G72: =SUMIFS(F6:F52,H6:H52,"BANQUE") -> 286000

Sheet TONT20000MAI2017
A1: ASSOCIATION | B1: ASELBY
A2: ANNEE | B2: 2016/2017
A3: TONTINE | B3: 20 000
A4: MATRICULE | B4: NOM ET PRENOM | C4: REPARTITION INTERET | D4: CAPITAL COMPOSE | E4: SANCTION | F4: MONTANT TONTINE | G4: PENALITE | H4: MODE VERSEMENT | I4: MONTANT VERSE | J4: EPARGNE | K4: FONDS DE ROULEMENT | L4: FRAIS EXCEPTIONNEL | M4: COLLATION | N4: MUTUELLE | O4: EMPRUNT | P4: INTERET EMPRUNT | Q4: REMBOURSEMENT | R4: PENALITE EMPRUNT | S4: PENALITE FONDS | T4: INTERET ACHAT | U4: DATE ACHAT | V4: AVALISTE
A5: AS201648 | B5: =VLOOKUP(A5,LISTADHERENT!A$5:H$52,2,0) -> ASELBY | C5: =$P$56/$D$56*D5 -> 8162.1439 | D5: =TONT20000AVRIL2017!C5+TONT20000AVRIL2017!D5+TONT20000MAI2017!J5 -> 364637.61
A6: AS201601 | B6: =VLOOKUP(A6,LISTADHERENT!A$5:H$52,2,0) -> BAKOP ACHILLE | C6: =$P$56/$D$56*D6 -> 10849.077 | D6: =TONT20000AVRIL2017!C6+TONT20000AVRIL2017!D6+TONT20000MAI2017!J6 -> 484674.32 | F6: =IF(H6="ECHEC",0,13000) -> 0 | G6: =IF(H6="ESPECES",1000,0) -> 0 | H6: ECHEC | I6: =IF(F6=0,0,J6+K6+L6+M6+N6+#REF!) -> 0 | J6: =IF(F6=0,0,3000) -> 0 | K6: =IF(F6=0,0,500) -> 0 | L6: =IF(F6=0,0,1000) -> 0 | M6: =IF(F6=0,0,2500) -> 0 | P6: =IF(O6<=500000,(O6*1*3/100),(O6*12/100)) -> 0
A7: AS201602 | B7: =VLOOKUP(A7,LISTADHERENT!A$5:H$51,2) -> BOUTCHOUANG WILLIAM | C7: =$P$56/$D$56*D7 -> 10126.164 | D7: =TONT20000AVRIL2017!C7+TONT20000AVRIL2017!D7+TONT20000MAI2017!J7 -> 452378.73 | F7: =IF(H7="ECHEC",0,13000) -> 13000 | G7: =IF(H7="ESPECES",1000,0) -> 1000 | H7: ESPECES | I7: =IF(F7=0,0,F7+J7+K7+L7+M7+N7) -> 20000 | J7: =IF(F7=0,0,3000) -> 3000 | K7: =IF(F7=0,0,500) -> 500 | L7: =IF(F7=0,0,1000) -> 1000 | M7: =IF(F7=0,0,2500) -> 2500 | P7: =IF(O7<=500000,(O7*1*3/100),(O7*12/100)) -> 0
A8: AS201603 | B8: =VLOOKUP(A8,LISTADHERENT!A$5:H$51,2) -> CHINGUE FABRICE | C8: =$P$56/$D$56*D8 -> 10198.661 | D8: =TONT20000AVRIL2017!C8+TONT20000AVRIL2017!D8+TONT20000MAI2017!J8 -> 455617.47 | F8: =IF(H8="ECHEC",0,13000) -> 13000 | G8: =IF(H8="ESPECES",1000,0) -> 1000 | H8: ESPECES | I8: =IF(F8=0,0,F8+J8+K8+L8+M8+N8) -> 20000 | J8: =IF(F8=0,0,3000) -> 3000 | K8: =IF(F8=0,0,500) -> 500 | L8: =IF(F8=0,0,1000) -> 1000 | M8: =IF(F8=0,0,2500) -> 2500 | P8: =IF(O8<=500000,(O8*1*3/100),(O8*12/100)) -> 0
A9: AS201604 | B9: =VLOOKUP(A9,LISTADHERENT!A$5:H$51,2) -> DJOMO JEAN PAUL | C9: =$P$56/$D$56*D9 -> 10283.524 | D9: =TONT20000AVRIL2017!C9+TONT20000AVRIL2017!D9+TONT20000MAI2017!J9 -> 459408.64 | F9: =IF(H9="ECHEC",0,13000) -> 13000 | G9: =IF(H9="ESPECES",1000,0) -> 0 | H9: BANQUE | I9: =IF(F9=0,0,F9+J9+K9+L9+M9+N9) -> 20000 | J9: =IF(F9=0,0,3000) -> 3000 | K9: =IF(F9=0,0,500) -> 500 | L9: =IF(F9=0,0,1000) -> 1000 | M9: =IF(F9=0,0,2500) -> 2500 | P9: =IF(O9<=500000,(O9*1*3/100),(O9*12/100)) -> 0
A10: AS201605 | B10: =VLOOKUP(A10,LISTADHERENT!A$5:H$51,2) -> DJOUKWE NANGUEN GUY BLAISE | C10: =$P$56/$D$56*D10 -> 10307.062 | D10: =TONT20000AVRIL2017!C10+TONT20000AVRIL2017!D10+TONT20000MAI2017!J10 -> 460460.22 | F10: =IF(H10="ECHEC",0,13000) -> 13000 | G10: =IF(H10="ESPECES",1000,0) -> 1000 | H10: ESPECES | I10: =IF(F10=0,0,F10+J10+K10+L10+M10+N10) -> 24000 | J10: =IF(F10=0,0,3000)+4000 -> 7000 | K10: =IF(F10=0,0,500) -> 500 | L10: =IF(F10=0,0,1000) -> 1000 | M10: =IF(F10=0,0,2500) -> 2500 | P10: =IF(O10<=500000,(O10*1*3/100),(O10*12/100)) -> 0 | Q10: 140000 | T10: 10000 | U10: 42876
D11: =TONT20000AVRIL2017!C11+TONT20000AVRIL2017!D11+TONT20000MAI2017!J11 -> 0 | J11: =IF(F11=0,0,3000) -> 0 | K11: =IF(F11=0,0,500) -> 0 | L11: =IF(F11=0,0,1000) -> 0 | M11: =IF(F11=0,0,2500) -> 0 | P11: =IF(O11<=500000,(O11*1*3/100),(O11*12/100)) -> 0
A12: AS201607 | B12: =VLOOKUP(A12,LISTADHERENT!A$5:H$51,2) -> DJOUNKEP SAMUEL | C12: =$P$56/$D$56*D12 -> 24671.958 | D12: =TONT20000AVRIL2017!C12+TONT20000AVRIL2017!D12+TONT20000MAI2017!J12 -> 1102201.1 | F12: =IF(H12="ECHEC",0,13000) -> 13000 | G12: =IF(H12="ESPECES",1000,0) -> 0 | H12: BANQUE | I12: =IF(F12=0,0,F12+J12+K12+L12+M12+N12) -> 20000 | J12: =IF(F12=0,0,3000) -> 3000 | K12: =IF(F12=0,0,500) -> 500 | L12: =IF(F12=0,0,1000) -> 1000 | M12: =IF(F12=0,0,2500) -> 2500 | P12: =IF(O12<=500000,(O12*1*3/100),(O12*12/100)) -> 0
A13: AS201608 | B13: =VLOOKUP(A13,LISTADHERENT!A$5:H$51,2) -> DJUOMBESSY ANTOINE | C13: =$P$56/$D$56*D13 -> 10126.762 | D13: =TONT20000AVRIL2017!C13+TONT20000AVRIL2017!D13+TONT20000MAI2017!J13 -> 452405.43 | F13: =IF(H13="ECHEC",0,13000) -> 13000 | G13: =IF(H13="ESPECES",1000,0) -> 1000 | H13: ESPECES | I13: =IF(F13=0,0,F13+J13+K13+L13+M13+N13) -> 20000 | J13: =IF(F13=0,0,3000) -> 3000 | K13: =IF(F13=0,0,500) -> 500 | L13: =IF(F13=0,0,1000) -> 1000 | M13: =IF(F13=0,0,2500) -> 2500 | P13: =IF(O13<=500000,(O13*1*3/100),(O13*12/100)) -> 0
A14: AS201609 | B14: =VLOOKUP(A14,LISTADHERENT!A$5:H$51,2) -> DONHOU DAVID | C14: =$P$56/$D$56*D14 -> 11299.077 | D14: =TONT20000AVRIL2017!C14+TONT20000AVRIL2017!D14+TONT20000MAI2017!J14 -> 504777.73 | F14: =IF(H14="ECHEC",0,13000) -> 13000 | G14: =IF(H14="ESPECES",1000,0) -> 0 | H14: BANQUE | I14: =IF(F14=0,0,F14+J14+K14+L14+M14+N14) -> 20000 | J14: =IF(F14=0,0,3000) -> 3000 | K14: =IF(F14=0,0,500) -> 500 | L14: =IF(F14=0,0,1000) -> 1000 | M14: =IF(F14=0,0,2500) -> 2500 | P14: =IF(O14<=500000,(O14*1*3/100),(O14*12/100)) -> 0
A15: AS201610 | B15: =VLOOKUP(A15,LISTADHERENT!A$5:H$51,2) -> FOTSO THOMAS | C15: =$P$56/$D$56*D15 -> 10121.613 | D15: =TONT20000AVRIL2017!C15+TONT20000AVRIL2017!D15+TONT20000MAI2017!J15 -> 452175.41 | F15: =IF(H15="ECHEC",0,13000) -> 13000 | G15: =IF(H15="ESPECES",1000,0) -> 1000 | H15: ESPECES | I15: =IF(F15=0,0,F15+J15+K15+L15+M15+N15) -> 20000 | J15: =IF(F15=0,0,3000) -> 3000 | K15: =IF(F15=0,0,500) -> 500 | L15: =IF(F15=0,0,1000) -> 1000 | M15: =IF(F15=0,0,2500) -> 2500 | P15: =IF(O15<=500000,(O15*1*3/100),(O15*12/100)) -> 0
A16: AS201611 | B16: =VLOOKUP(A16,LISTADHERENT!A$5:H$51,2) -> HENGUE PAUL OMER | C16: =$P$56/$D$56*D16 -> 11580.698 | D16: =TONT20000AVRIL2017!C16+TONT20000AVRIL2017!D16+TONT20000MAI2017!J16 -> 517358.91 | F16: =IF(H16="ECHEC",0,13000) -> 13000 | G16: =IF(H16="ESPECES",1000,0) -> 0 | H16: BANQUE | I16: =IF(F16=0,0,F16+J16+K16+L16+M16+N16) -> 20000 | J16: =IF(F16=0,0,3000) -> 3000 | K16: =IF(F16=0,0,500) -> 500 | L16: =IF(F16=0,0,1000) -> 1000 | M16: =IF(F16=0,0,2500) -> 2500 | P16: =IF(O16<=500000,(O16*1*3/100),(O16*12/100)) -> 0
A17: AS201612 | B17: =VLOOKUP(A17,LISTADHERENT!A$5:H$51,2) -> HODIEP JULES | C17: =$P$56/$D$56*D17 -> 1155.26 | D17: =TONT20000AVRIL2017!C17+TONT20000AVRIL2017!D17+TONT20000MAI2017!J17 -> 51610.366 | F17: =IF(H17="ECHEC",0,13000) -> 0 | G17: =IF(H17="ESPECES",1000,0) -> 0 | H17: ECHEC | I17: =IF(F17=0,0,F17+J17+K17+L17+M17+N17) -> 0 | J17: =IF(F17=0,0,3000) -> 0 | K17: =IF(F17=0,0,500) -> 0 | L17: =IF(F17=0,0,1000) -> 0 | M17: =IF(F17=0,0,2500) -> 0 | P17: =IF(O17<=500000,(O17*1*3/100),(O17*12/100)) -> 0
A18: AS201613 | B18: =VLOOKUP(A18,LISTADHERENT!A$5:H$51,2) -> HOTCHO BENJAMIN | C18: =$P$56/$D$56*D18 -> 12653.784 | D18: =TONT20000AVRIL2017!C18+TONT20000AVRIL2017!D18+TONT20000MAI2017!J18 -> 565298.22 | F18: =IF(H18="ECHEC",0,13000) -> 13000 | G18: =IF(H18="ESPECES",1000,0) -> 0 | H18: BANQUE | I18: =IF(F18=0,0,F18+J18+K18+L18+M18+N18) -> 20000 | J18: =IF(F18=0,0,3000) -> 3000 | K18: =IF(F18=0,0,500) -> 500 | L18: =IF(F18=0,0,1000) -> 1000 | M18: =IF(F18=0,0,2500) -> 2500 | P18: =IF(O18<=500000,(O18*1*3/100),(O18*12/100)) -> 0
A19: AS201614 | B19: =VLOOKUP(A19,LISTADHERENT!A$5:H$51,2) -> KEPHE DAVID | C19: =$P$56/$D$56*D19 -> 2712.2959 | D19: =TONT20000AVRIL2017!C19+TONT20000AVRIL2017!D19+TONT20000MAI2017!J19 -> 121169.77 | F19: =IF(H19="ECHEC",0,13000) -> 13000 | G19: =IF(H19="ESPECES",1000,0) -> 1000 | H19: ESPECES | I19: =IF(F19=0,0,F19+J19+K19+L19+M19+N19) -> 20000 | J19: =IF(F19=0,0,3000) -> 3000 | K19: =IF(F19=0,0,500) -> 500 | L19: =IF(F19=0,0,1000) -> 1000 | M19: =IF(F19=0,0,2500) -> 2500 | P19: =IF(O19<=500000,(O19*1*3/100),(O19*12/100)) -> 0
A20: AS201615 | B20: =VLOOKUP(A20,LISTADHERENT!A$5:H$51,2) -> KEPSEU FRANCIS | C20: =$P$56/$D$56*D20 -> 49673.646 | D20: =TONT20000AVRIL2017!C20+TONT20000AVRIL2017!D20+TONT20000MAI2017!J20 -> 2219132.6 | F20: =IF(H20="ECHEC",0,13000) -> 13000 | G20: =IF(H20="ESPECES",1000,0) -> 0 | H20: BANQUE | I20: =IF(F20=0,0,F20+J20+K20+L20+M20+N20) -> 23000 | J20: =IF(F20=0,0,6000) -> 6000 | K20: =IF(F20=0,0,500) -> 500 | L20: =IF(F20=0,0,1000) -> 1000 | M20: =IF(F20=0,0,2500) -> 2500 | P20: =IF(O20<=500000,(O20*1*3/100),(O20*12/100)) -> 0
A21: AS201616 | B21: =VLOOKUP(A21,LISTADHERENT!A$5:H$51,2) -> KOUAMOU EMMANUEL | C21: =$P$56/$D$56*D21 -> 10117.82 | D21: =TONT20000AVRIL2017!C21+TONT20000AVRIL2017!D21+TONT20000MAI2017!J21 -> 452005.97 | F21: =IF(H21="ECHEC",0,13000) -> 13000 | G21: =IF(H21="ESPECES",1000,0) -> 1000 | H21: ESPECES | I21: =IF(F21=0,0,F21+J21+K21+L21+M21+N21) -> 20000 | J21: =IF(F21=0,0,3000) -> 3000 | K21: =IF(F21=0,0,500) -> 500 | L21: =IF(F21=0,0,1000) -> 1000 | M21: =IF(F21=0,0,2500) -> 2500 | P21: =IF(O21<=500000,(O21*1*3/100),(O21*12/100)) -> 0
A22: AS201617 | B22: =VLOOKUP(A22,LISTADHERENT!A$5:H$51,2) -> KOUAMOU MOISE | C22: =$P$56/$D$56*D22 -> 10066.551 | D22: =TONT20000AVRIL2017!C22+TONT20000AVRIL2017!D22+TONT20000MAI2017!J22 -> 449715.54 | F22: =IF(H22="ECHEC",0,13000) -> 0 | G22: =IF(H22="ESPECES",1000,0) -> 0 | H22: ECHEC | I22: =IF(F22=0,0,F22+J22+K22+L22+M22+N22) -> 0 | J22: =IF(F22=0,0,3000) -> 0 | K22: =IF(F22=0,0,500) -> 0 | L22: =IF(F22=0,0,1000) -> 0 | M22: =IF(F22=0,0,2500) -> 0 | P22: =IF(O22<=500000,(O22*1*3/100),(O22*12/100)) -> 0
A23: AS201618 | B23: =VLOOKUP(A23,LISTADHERENT!A$5:H$51,2) -> KOUAMO VICTOR PEGUY | C23: =$P$56/$D$56*D23 -> 10125.383 | D23: =TONT20000AVRIL2017!C23+TONT20000AVRIL2017!D23+TONT20000MAI2017!J23 -> 452343.81 | F23: =IF(H23="ECHEC",0,13000) -> 13000 | G23: =IF(H23="ESPECES",1000,0) -> 1000 | H23: ESPECES | I23: =IF(F23=0,0,F23+J23+K23+L23+M23+N23) -> 20000 | J23: =IF(F23=0,0,3000) -> 3000 | K23: =IF(F23=0,0,500) -> 500 | L23: =IF(F23=0,0,1000) -> 1000 | M23: =IF(F23=0,0,2500) -> 2500 | P23: =IF(O23<=500000,(O23*1*3/100),(O23*12/100)) -> 0
A24: AS201619 | B24: =VLOOKUP(A24,LISTADHERENT!A$5:H$51,2) -> KOUATCHO MESSACK | C24: =$P$56/$D$56*D24 -> 10151.402 | D24: =TONT20000AVRIL2017!C24+TONT20000AVRIL2017!D24+TONT20000MAI2017!J24 -> 453506.23 | F24: =IF(H24="ECHEC",0,13000) -> 13000 | G24: =IF(H24="ESPECES",1000,0) -> 0 | H24: BANQUE | I24: =IF(F24=0,0,F24+J24+K24+L24+M24+N24) -> 20000 | J24: =IF(F24=0,0,3000) -> 3000 | K24: =IF(F24=0,0,500) -> 500 | L24: =IF(F24=0,0,1000) -> 1000 | M24: =IF(F24=0,0,2500) -> 2500 | P24: =IF(O24<=500000,(O24*1*3/100),(O24*12/100)) -> 0
A25: AS201620 | B25: =VLOOKUP(A25,LISTADHERENT!A$5:H$51,2) -> LOWE JEAN | C25: =$P$56/$D$56*D25 -> 10124.601 | D25: =TONT20000AVRIL2017!C25+TONT20000AVRIL2017!D25+TONT20000MAI2017!J25 -> 452308.9 | F25: =IF(H25="ECHEC",0,13000) -> 13000 | G25: =IF(H25="ESPECES",1000,0) -> 0 | H25: BANQUE | I25: =IF(F25=0,0,F25+J25+K25+L25+M25+N25) -> 20000 | J25: =IF(F25=0,0,3000) -> 3000 | K25: =IF(F25=0,0,500) -> 500 | L25: =IF(F25=0,0,1000) -> 1000 | M25: =IF(F25=0,0,2500) -> 2500 | P25: =IF(O25<=500000,(O25*1*3/100),(O25*12/100)) -> 0
A26: AS201621 | B26: =VLOOKUP(A26,LISTADHERENT!A$5:H$51,2) -> NANKAM APPOLINAIRE | C26: =$P$56/$D$56*D26 -> 10126.647 | D26: =TONT20000AVRIL2017!C26+TONT20000AVRIL2017!D26+TONT20000MAI2017!J26 -> 452400.29 | F26: =IF(H26="ECHEC",0,13000) -> 13000 | G26: =IF(H26="ESPECES",1000,0) -> 0 | H26: BANQUE | I26: =IF(F26=0,0,F26+J26+K26+L26+M26+N26) -> 20000 | J26: =IF(F26=0,0,3000) -> 3000 | K26: =IF(F26=0,0,500) -> 500 | L26: =IF(F26=0,0,1000) -> 1000 | M26: =IF(F26=0,0,2500) -> 2500 | P26: =IF(O26<=500000,(O26*1*3/100),(O26*12/100)) -> 0
A27: AS201622 | B27: =VLOOKUP(A27,LISTADHERENT!A$5:H$51,2) -> NDJOMO ETIENNE | C27: =$P$56/$D$56*D27 -> 10811.183 | D27: =TONT20000AVRIL2017!C27+TONT20000AVRIL2017!D27+TONT20000MAI2017!J27 -> 482981.44 | F27: =IF(H27="ECHEC",0,13000) -> 13000 | G27: =IF(H27="ESPECES",1000,0) -> 0 | H27: BANQUE | I27: =IF(F27=0,0,F27+J27+K27+L27+M27+N27) -> 25000 | J27: =IF(F27=0,0,8000) -> 8000 | K27: =IF(F27=0,0,500) -> 500 | L27: =IF(F27=0,0,1000) -> 1000 | M27: =IF(F27=0,0,2500) -> 2500 | P27: =IF(O27<=500000,(O27*1*3/100),(O27*12/100)) -> 0
A28: AS201623 | B28: =VLOOKUP(A28,LISTADHERENT!A$5:H$51,2) -> NDOMBOU JEAN CLAUDE | C28: =$P$56/$D$56*D28 -> 9653.9831 | D28: =TONT20000AVRIL2017!C28+TONT20000AVRIL2017!D28+TONT20000MAI2017!J28 -> 431284.4 | J28: =IF(F28=0,0,3000) -> 0 | K28: =IF(F28=0,0,500) -> 0 | L28: =IF(F28=0,0,1000) -> 0 | M28: =IF(F28=0,0,2500) -> 0 | P28: =IF(O28<=500000,(O28*1*3/100),(O28*12/100)) -> 0
A29: AS201624 | B29: =VLOOKUP(A29,LISTADHERENT!A$5:H$51,2) -> NGONDIEP CLAUDE | C29: =$P$56/$D$56*D29 -> 10345.099 | D29: =TONT20000AVRIL2017!C29+TONT20000AVRIL2017!D29+TONT20000MAI2017!J29 -> 462159.46 | F29: =IF(H29="ECHEC",0,13000) -> 13000 | G29: =IF(H29="ESPECES",1000,0) -> 0 | H29: BANQUE | I29: =IF(F29=0,0,F29+J29+K29+L29+M29+N29) -> 20000 | J29: =IF(F29=0,0,3000) -> 3000 | K29: =IF(F29=0,0,500) -> 500 | L29: =IF(F29=0,0,1000) -> 1000 | M29: =IF(F29=0,0,2500) -> 2500 | P29: =IF(O29<=500000,(O29*1*3/100),(O29*12/100)) -> 0
A30: AS201625 | B30: =VLOOKUP(A30,LISTADHERENT!A$5:H$51,2) -> NGONGANG JEAN THEODORE | C30: =$P$56/$D$56*D30 -> 1316.4866 | D30: =TONT20000AVRIL2017!C30+TONT20000AVRIL2017!D30+TONT20000MAI2017!J30 -> 58813.043 | F30: =IF(H30="ECHEC",0,13000) -> 13000 | G30: =IF(H30="ESPECES",1000,0) -> 0 | H30: BANQUE | I30: =IF(F30=0,0,F30+J30+K30+L30+M30+N30) -> 69997 | J30: =13000+10193 -> 23193 | K30: =IF(F30=0,0,500) -> 500 | L30: =IF(F30=0,0,1000) -> 1000 | M30: =IF(F30=0,0,2500) -> 2500 | N30: 29804 | P30: =IF(O30<=500000,(O30*1*3/100),(O30*12/100)) -> 0 | T30: 10000 | U30: 42876
A31: AS201626 | B31: =VLOOKUP(A31,LISTADHERENT!A$5:H$51,2) -> NGUIEMEGNI MATHIEU BLAISE | C31: =$P$56/$D$56*D31 -> 10986.127 | D31: =TONT20000AVRIL2017!C31+TONT20000AVRIL2017!D31+TONT20000MAI2017!J31 -> 490796.93 | F31: =IF(H31="ECHEC",0,13000) -> 13000 | G31: =IF(H31="ESPECES",1000,0) -> 0 | H31: BANQUE | I31: =IF(F31=0,0,F31+J31+K31+L31+M31+N31) -> 20000 | J31: =IF(F31=0,0,3000) -> 3000 | K31: =IF(F31=0,0,500) -> 500 | L31: =IF(F31=0,0,1000) -> 1000 | M31: =IF(F31=0,0,2500) -> 2500 | P31: =IF(O31<=500000,(O31*1*3/100),(O31*12/100)) -> 0
A32: AS201627 | B32: =VLOOKUP(A32,LISTADHERENT!A$5:H$51,2) -> NJEPDJIO MBOUKAM DELUXE | C32: =$P$56/$D$56*D32 -> 10242.245 | D32: =TONT20000AVRIL2017!C32+TONT20000AVRIL2017!D32+TONT20000MAI2017!J32 -> 457564.54 | F32: =IF(H32="ECHEC",0,13000) -> 13000 | G32: =IF(H32="ESPECES",1000,0) -> 1000 | H32: ESPECES | I32: =IF(F32=0,0,F32+J32+K32+L32+M32+N32) -> 20000 | J32: =IF(F32=0,0,3000) -> 3000 | K32: =IF(F32=0,0,500) -> 500 | L32: =IF(F32=0,0,1000) -> 1000 | M32: =IF(F32=0,0,2500) -> 2500 | O32: 800000 | P32: =IF(O32<=500000,(O32*1*3/100),(O32*12/100)) -> 96000 | Q32: 1110000
A33: AS201628 | B33: =VLOOKUP(A33,LISTADHERENT!A$5:H$51,2) -> NKAMGANG JUSTIN DEJOLIE | C33: =$P$56/$D$56*D33 -> 12123.832 | D33: =TONT20000AVRIL2017!C33+TONT20000AVRIL2017!D33+TONT20000MAI2017!J33 -> 541623.03 | F33: =IF(H33="ECHEC",0,13000) -> 13000 | G33: =IF(H33="ESPECES",1000,0) -> 1000 | H33: ESPECES | I33: =IF(F33=0,0,F33+J33+K33+L33+M33+N33) -> 23000 | J33: =IF(F33=0,0,3000)+3000 -> 6000 | K33: =IF(F33=0,0,500) -> 500 | L33: =IF(F33=0,0,1000) -> 1000 | M33: =IF(F33=0,0,2500) -> 2500 | P33: =IF(O33<=500000,(O33*1*3/100),(O33*12/100)) -> 0
A34: AS201629 | B34: =VLOOKUP(A34,LISTADHERENT!A$5:H$51,2) -> NKEPSEU DIEUDONNE | C34: =$P$56/$D$56*D34 -> 13108.693 | D34: =TONT20000AVRIL2017!C34+TONT20000AVRIL2017!D34+TONT20000MAI2017!J34 -> 585620.97 | F34: =IF(H34="ECHEC",0,13000) -> 13000 | G34: =IF(H34="ESPECES",1000,0) -> 1000 | H34: ESPECES | I34: =IF(F34=0,0,F34+J34+K34+L34+M34+N34) -> 25000 | J34: 8000 | K34: =IF(F34=0,0,500) -> 500 | L34: =IF(F34=0,0,1000) -> 1000 | M34: =IF(F34=0,0,2500) -> 2500 | P34: =IF(O34<=500000,(O34*1*3/100),(O34*12/100)) -> 0
D35: =TONT20000AVRIL2017!C35+TONT20000AVRIL2017!D35+TONT20000MAI2017!J35 -> 0 | J35: =IF(F35=0,0,3000) -> 0 | K35: =IF(F35=0,0,500) -> 0 | L35: =IF(F35=0,0,1000) -> 0 | M35: =IF(F35=0,0,2500) -> 0 | P35: =IF(O35<=500000,(O35*1*3/100),(O35*12/100)) -> 0
A36: AS201631 | B36: =VLOOKUP(A36,LISTADHERENT!A$5:H$51,2) -> NTEPDIE TUEMAC MZ | C36: =$P$56/$D$56*D36 -> 0 | D36: =TONT20000AVRIL2017!C36+TONT20000AVRIL2017!D36+TONT20000MAI2017!J36 -> 0 | F36: =IF(H36="ECHEC",0,13000) -> 0 | G36: =IF(H36="ESPECES",1000,0) -> 0 | H36: ECHEC | I36: =IF(F36=0,0,F36+J36+K36+L36+M36+N36) -> 0 | J36: =IF(F36=0,0,3000) -> 0 | K36: =IF(F36=0,0,500) -> 0 | L36: =IF(F36=0,0,1000) -> 0 | M36: =IF(F36=0,0,2500) -> 0 | P36: =IF(O36<=500000,(O36*1*3/100),(O36*12/100)) -> 0
D37: =TONT20000AVRIL2017!C37+TONT20000AVRIL2017!D37+TONT20000MAI2017!J37 -> 0 | J37: =IF(F37=0,0,3000) -> 0 | K37: =IF(F37=0,0,500) -> 0 | L37: =IF(F37=0,0,1000) -> 0 | M37: =IF(F37=0,0,2500) -> 0 | P37: =IF(O37<=500000,(O37*1*3/100),(O37*12/100)) -> 0
A38: AS201633 | B38: =VLOOKUP(A38,LISTADHERENT!A$5:H$51,2) -> PATEGO NJOSSU GUSTAVE | C38: =$P$56/$D$56*D38 -> 10120.51 | D38: =TONT20000AVRIL2017!C38+TONT20000AVRIL2017!D38+TONT20000MAI2017!J38 -> 452126.12 | F38: =IF(H38="ECHEC",0,13000) -> 13000 | G38: =IF(H38="ESPECES",1000,0) -> 0 | H38: BANQUE | I38: =IF(F38=0,0,F38+J38+K38+L38+M38+N38) -> 20000 | J38: =IF(F38=0,0,3000) -> 3000 | K38: =IF(F38=0,0,500) -> 500 | L38: =IF(F38=0,0,1000) -> 1000 | M38: =IF(F38=0,0,2500) -> 2500 | P38: =IF(O38<=500000,(O38*1*3/100),(O38*12/100)) -> 0
A39: AS201634 | B39: =VLOOKUP(A39,LISTADHERENT!A$5:H$51,2) -> SEUNOU RICHELOT | C39: =$P$56/$D$56*D39 -> 10218.934 | D39: =TONT20000AVRIL2017!C39+TONT20000AVRIL2017!D39+TONT20000MAI2017!J39 -> 456523.17 | F39: =IF(H39="ECHEC",0,13000) -> 13000 | G39: =IF(H39="ESPECES",1000,0) -> 1000 | H39: ESPECES | I39: =IF(F39=0,0,F39+J39+K39+L39+M39+N39) -> 20000 | J39: =IF(F39=0,0,3000) -> 3000 | K39: =IF(F39=0,0,500) -> 500 | L39: =IF(F39=0,0,1000) -> 1000 | M39: =IF(F39=0,0,2500) -> 2500 | P39: =IF(O39<=500000,(O39*1*3/100),(O39*12/100)) -> 0
A40: AS201635 | B40: =VLOOKUP(A40,LISTADHERENT!A$5:H$51,2) -> SIME ABEL | C40: =$P$56/$D$56*D40 -> 9317.7289 | D40: =TONT20000AVRIL2017!C40+TONT20000AVRIL2017!D40+TONT20000MAI2017!J40 -> 416262.49 | F40: =IF(H40="ECHEC",0,13000) -> 13000 | G40: =IF(H40="ESPECES",1000,0) -> 1000 | H40: ESPECES | I40: =IF(F40=0,0,F40+J40+K40+L40+M40+N40) -> 20000 | J40: =IF(F40=0,0,3000) -> 3000 | K40: =IF(F40=0,0,500) -> 500 | L40: =IF(F40=0,0,1000) -> 1000 | M40: =IF(F40=0,0,2500) -> 2500 | O40: 700000 | P40: =IF(O40<=500000,(O40*1*3/100),(O40*12/100)) -> 84000
A41: AS201636 | B41: =VLOOKUP(A41,LISTADHERENT!A$5:H$51,2) -> SIME FONGANG ERIC | C41: =$P$56/$D$56*D41 -> 10176.595 | D41: =TONT20000AVRIL2017!C41+TONT20000AVRIL2017!D41+TONT20000MAI2017!J41 -> 454631.67 | F41: =IF(H41="ECHEC",0,13000) -> 13000 | G41: =IF(H41="ESPECES",1000,0) -> 1000 | H41: ESPECES | I41: =IF(F41=0,0,F41+J41+K41+L41+M41+N41) -> 20000 | J41: =IF(F41=0,0,3000) -> 3000 | K41: =IF(F41=0,0,500) -> 500 | L41: =IF(F41=0,0,1000) -> 1000 | M41: =IF(F41=0,0,2500) -> 2500 | O41: 1000000 | P41: =IF(O41<=500000,(O41*1*3/100),(O41*12/100)) -> 120000 | Q41: 1080000
A42: AS201637 | B42: =VLOOKUP(A42,LISTADHERENT!A$5:H$51,2) -> SIME MATHIEU | C42: =$P$56/$D$56*D42 -> 10167.722 | D42: =TONT20000AVRIL2017!C42+TONT20000AVRIL2017!D42+TONT20000MAI2017!J42 -> 454235.3 | F42: =IF(H42="ECHEC",0,13000) -> 13000 | G42: =IF(H42="ESPECES",1000,0) -> 0 | H42: BANQUE | I42: =IF(F42=0,0,F42+J42+K42+L42+M42+N42) -> 20000 | J42: =IF(F42=0,0,3000) -> 3000 | K42: =IF(F42=0,0,500) -> 500 | L42: =IF(F42=0,0,1000) -> 1000 | M42: =IF(F42=0,0,2500) -> 2500 | P42: =IF(O42<=500000,(O42*1*3/100),(O42*12/100)) -> 0 | Q42: 100000
A43: AS201638 | B43: =VLOOKUP(A43,LISTADHERENT!A$5:H$51,2) -> SIME PIERRE | C43: =$P$56/$D$56*D43 -> 13526.312 | D43: =TONT20000AVRIL2017!C43+TONT20000AVRIL2017!D43+TONT20000MAI2017!J43 -> 604277.77 | F43: =IF(H43="ECHEC",0,13000) -> 13000 | G43: =IF(H43="ESPECES",1000,0) -> 0 | H43: BANQUE | I43: =IF(F43=0,0,F43+J43+K43+L43+M43+N43) -> 20000 | J43: 3000 | K43: =IF(F43=0,0,500) -> 500 | L43: =IF(F43=0,0,1000) -> 1000 | M43: =IF(F43=0,0,2500) -> 2500 | P43: =IF(O43<=500000,(O43*1*3/100),(O43*12/100)) -> 0 | Q43: 604200
A44: AS201639 | B44: =VLOOKUP(A44,LISTADHERENT!A$5:H$51,2) -> TAGNE NANGUEN MARTIN | C44: =$P$56/$D$56*D44 -> 9411.3326 | D44: =TONT20000AVRIL2017!C44+TONT20000AVRIL2017!D44+TONT20000MAI2017!J44 -> 420444.17 | F44: =IF(H44="ECHEC",0,13000) -> 13000 | G44: =IF(H44="ESPECES",1000,0) -> 0 | H44: BANQUE | I44: =IF(F44=0,0,F44+J44+K44+L44+M44+N44) -> 20000 | J44: =IF(F44=0,0,3000) -> 3000 | K44: =IF(F44=0,0,500) -> 500 | L44: =IF(F44=0,0,1000) -> 1000 | M44: =IF(F44=0,0,2500) -> 2500 | P44: =IF(O44<=500000,(O44*1*3/100),(O44*12/100)) -> 0
A45: AS201640 | B45: =VLOOKUP(A45,LISTADHERENT!A$5:H$51,2) -> TCHOUAMOU JEAN PAUL | C45: =$P$56/$D$56*D45 -> 750.83636 | D45: =TONT20000AVRIL2017!C45+TONT20000AVRIL2017!D45+TONT20000MAI2017!J45 -> 33543.047 | F45: =IF(H45="ECHEC",0,13000) -> 13000 | G45: =IF(H45="ESPECES",1000,0) -> 0 | H45: BANQUE | I45: =IF(F45=0,0,F45+J45+K45+L45+M45+N45) -> 20000 | J45: =IF(F45=0,0,3000) -> 3000 | K45: =IF(F45=0,0,500) -> 500 | L45: =IF(F45=0,0,1000) -> 1000 | M45: =IF(F45=0,0,2500) -> 2500 | P45: =IF(O45<=500000,(O45*1*3/100),(O45*12/100)) -> 0
A46: AS201641 | B46: =VLOOKUP(A46,LISTADHERENT!A$5:H$51,2) -> TCHOUAMOU MATHIEU | C46: =$P$56/$D$56*D46 -> 10124.647 | D46: =TONT20000AVRIL2017!C46+TONT20000AVRIL2017!D46+TONT20000MAI2017!J46 -> 452310.95 | F46: =IF(H46="ECHEC",0,13000) -> 13000 | G46: =IF(H46="ESPECES",1000,0) -> 0 | H46: BANQUE | I46: =IF(F46=0,0,F46+J46+K46+L46+M46+N46) -> 20000 | J46: =IF(F46=0,0,3000) -> 3000 | K46: =IF(F46=0,0,500) -> 500 | L46: =IF(F46=0,0,1000) -> 1000 | M46: =IF(F46=0,0,2500) -> 2500 | P46: =IF(O46<=500000,(O46*1*3/100),(O46*12/100)) -> 0 | Q46: 554100
A47: AS201642 | B47: =VLOOKUP(A47,LISTADHERENT!A$5:H$51,2) -> TCHOUANTE FRANCOIS | C47: =$P$56/$D$56*D47 -> 11584.909 | D47: =TONT20000AVRIL2017!C47+TONT20000AVRIL2017!D47+TONT20000MAI2017!J47 -> 517547.04 | F47: =IF(H47="ECHEC",0,13000) -> 13000 | G47: =IF(H47="ESPECES",1000,0) -> 1000 | H47: ESPECES | I47: =IF(F47=0,0,F47+J47+K47+L47+M47+N47) -> 37000 | J47: =IF(F47=0,0,3000)+17000 -> 20000 | K47: =IF(F47=0,0,500) -> 500 | L47: =IF(F47=0,0,1000) -> 1000 | M47: =IF(F47=0,0,2500) -> 2500 | O47: 700000 | P47: =IF(O47<=500000,(O47*1*3/100),(O47*12/100)) -> 84000 | Q47: 543500
A48: AS201643 | B48: =VLOOKUP(A48,LISTADHERENT!A$5:H$51,2) -> TCHOUTOU NANA CLAUDE | C48: =$P$56/$D$56*D48 -> 409.66 | D48: =TONT20000AVRIL2017!C48+TONT20000AVRIL2017!D48+TONT20000MAI2017!J48 -> 18301.251 | F48: =IF(H48="ECHEC",0,13000) -> 13000 | G48: =IF(H48="ESPECES",1000,0) -> 0 | H48: BANQUE | I48: =IF(F48=0,0,F48+J48+K48+L48+M48+N48) -> 20000 | J48: =IF(F48=0,0,3000) -> 3000 | K48: =IF(F48=0,0,500) -> 500 | L48: =IF(F48=0,0,1000) -> 1000 | M48: =IF(F48=0,0,2500) -> 2500 | P48: =IF(O48<=500000,(O48*1*3/100),(O48*12/100)) -> 0 | T48: 10000 | U48: 42876
A49: AS201644 | B49: =VLOOKUP(A49,LISTADHERENT!A$5:H$51,2) -> TIEYAM ERNEST | C49: =$P$56/$D$56*D49 -> 10759.353 | D49: =TONT20000AVRIL2017!C49+TONT20000AVRIL2017!D49+TONT20000MAI2017!J49 -> 480665.94 | F49: =IF(H49="ECHEC",0,13000) -> 13000 | G49: =IF(H49="ESPECES",1000,0) -> 0 | H49: BANQUE | I49: =IF(F49=0,0,F49+J49+K49+L49+M49+N49) -> 20000 | J49: =IF(F49=0,0,3000) -> 3000 | K49: =IF(F49=0,0,500) -> 500 | L49: =IF(F49=0,0,1000) -> 1000 | M49: =IF(F49=0,0,2500) -> 2500 | P49: =IF(O49<=500000,(O49*1*3/100),(O49*12/100)) -> 0
A50: AS201645 | B50: =VLOOKUP(A50,LISTADHERENT!A$5:H$51,2) -> TUGMA PIERRE LOTI | C50: =$P$56/$D$56*D50 -> 10121.176 | D50: =TONT20000AVRIL2017!C50+TONT20000AVRIL2017!D50+TONT20000MAI2017!J50 -> 452155.9 | F50: =IF(H50="ECHEC",0,13000) -> 13000 | G50: =IF(H50="ESPECES",1000,0) -> 0 | H50: BANQUE | I50: =IF(F50=0,0,F50+J50+K50+L50+M50+N50) -> 20000 | J50: =IF(F50=0,0,3000) -> 3000 | K50: =IF(F50=0,0,500) -> 500 | L50: =IF(F50=0,0,1000) -> 1000 | M50: =IF(F50=0,0,2500) -> 2500 | O50: 1000000 | P50: =IF(O50<=500000,(O50*1*3/100),(O50*12/100)) -> 120000 | V50: DJOUOKEP SAMUEL
A51: AS201646 | B51: =VLOOKUP(A51,LISTADHERENT!A$5:H$51,2) -> YEPMOU JEAN JACQUES | C51: =$P$56/$D$56*D51 -> 19119.585 | D51: =TONT20000AVRIL2017!C51+TONT20000AVRIL2017!D51+TONT20000MAI2017!J51 -> 854153 | F51: =IF(H51="ECHEC",0,13000) -> 13000 | G51: =IF(H51="ESPECES",1000,0) -> 0 | H51: BANQUE | I51: =IF(F51=0,0,F51+J51+K51+L51+M51+N51) -> 20000 | J51: =IF(F51=0,0,3000) -> 3000 | K51: =IF(F51=0,0,500) -> 500 | L51: =IF(F51=0,0,1000) -> 1000 | M51: =IF(F51=0,0,2500) -> 2500 | P51: =IF(O51<=500000,(O51*1*3/100),(O51*12/100)) -> 0
A52: AS201647 | B52: =VLOOKUP(A52,LISTADHERENT!A$5:H$51,2) -> YOUMBI EMMANUEL | C52: =$P$56/$D$56*D52 -> 34968.921 | D52: =TONT20000AVRIL2017!C52+TONT20000AVRIL2017!D52+TONT20000MAI2017!J52 -> 1562210.1 | F52: =IF(H52="ECHEC",0,13000) -> 13000 | G52: =IF(H52="ESPECES",1000,0) -> 0 | H52: BANQUE | I52: =IF(F52=0,0,F52+J52+K52+L52+M52+N52) -> 20000 | J52: =IF(F52=0,0,3000) -> 3000 | K52: =IF(F52=0,0,500) -> 500 | L52: =IF(F52=0,0,1000) -> 1000 | M52: =IF(F52=0,0,2500) -> 2500 | P52: =IF(O52<=500000,(O52*1*3/100),(O52*12/100)) -> 0 | T52: 10000 | U52: 42876
A56: TOTAL | C56: =SUM(C5:C52) -> 504000 | D56: =SUM(D5:D52) -> 22515819 | E56: =SUM(E5:E52) -> 0 | F56: =SUM(F5:F52) -> 507000 | G56: =SUM(G5:G52) -> 15000 | I56: =SUM(I5:I52) -> 866997 | J56: =SUM(J5:J52) -> 174193 | K56: =SUM(K5:K52) -> 19500 | L56: =SUM(L5:L52) -> 39000 | M56: =SUM(M5:M52) -> 97500 | N56: =SUM(N5:N52) -> 29804 | O56: =SUM(O5:O52) -> 4200000 | P56: =SUM(P5:P52) -> 504000 | ... T56: =SUM(T5:T52) -> 40000
D60: FONDS DE ROULEMENT | E60: =+K56 -> 19500
D61: EPARGNE | E61: =+J56 -> 174193
D62: MUTUELLE | E62: 0
D63: FRAIS EXCEPTIONNELS | E63: =+L56 -> 39000
D64: COLLATION | E64: =+M56 -> 97500
D65: TONTINE | E65: =+F56 -> 507000
D66: REMBOURSEMENT | E66: 0
D68: TOTAL | E68: =SUM(E60:E66) -> 837193
D70: DETAIL
E71: ESPECES | F71: =SUMIFS(I6:I52,H6:H52,"ESPECES") -> 329000 | G71: =SUMIFS(F6:F52,H6:H52,"ESPECES") -> 195000
E72: BANQUE | F72: =SUMIFS(I6:I52,H6:H52,"BANQUE") -> 537997 | G72: =SUMIFS(F6:F52,H6:H52,"BANQUE") -> 312000

Sheet TONT20000JUIN2017
A1: ASSOCIATION | B1: ASELBY
A2: ANNEE | B2: 2016/2017
A3: TONTINE | B3: 20 000
A4: MATRICULE | B4: NOM ET PRENOM | C4: REPARTITION INTERET | D4: CAPITAL COMPOSE | E4: SANCTION | F4: MONTANT TONTINE | G4: PENALITE | H4: MODE VERSEMENT | I4: MONTANT VERSE | J4: EPARGNE | K4: FONDS DE ROULEMENT | L4: FRAIS EXCEPTIONNEL | M4: COLLATION | N4: MUTUELLE | O4: EMPRUNT | P4: INTERET EMPRUNT | Q4: REMBOURSEMENT | R4: PENALITE EMPRUNT | S4: PENALITE FONDS | T4: INTERET ACHAT | U4: DATE ACHAT | V4: AVALISTE
A5: AS201648 | B5: =VLOOKUP(A5,LISTADHERENT!A$5:H$52,2,0) -> ASELBY | C5: =$P$56/$D$56*D5 -> 6471.4638 | D5: =TONT20000MAI2017!C5+TONT20000MAI2017!D5+TONT20000JUIN2017!J5 -> 372799.75
A6: AS201601 | B6: =VLOOKUP(A6,LISTADHERENT!A$5:H$52,2,0) -> BAKOP ACHILLE | C6: =$P$56/$D$56*D6 -> 8601.8345 | D6: =TONT20000MAI2017!C6+TONT20000MAI2017!D6+TONT20000JUIN2017!J6 -> 495523.4 | F6: =IF(H6="ECHEC",0,13000) -> 0 | G6: =IF(H6="ESPECES",1000,0) -> 0 | H6: ECHEC | I6: =IF(F6=0,0,J6+K6+L6+M6+N6+#REF!) -> 0 | J6: =IF(F6=0,0,3000) -> 0 | K6: =IF(F6=0,0,500) -> 0 | L6: =IF(F6=0,0,1000) -> 0 | M6: =IF(F6=0,0,2500) -> 0 | P6: =IF(O6<=500000,(O6*1*3/100),(O6*12/100)) -> 0
A7: AS201602 | B7: =VLOOKUP(A7,LISTADHERENT!A$5:H$51,2) -> BOUTCHOUANG WILLIAM | C7: =$P$56/$D$56*D7 -> 8080.7405 | D7: =TONT20000MAI2017!C7+TONT20000MAI2017!D7+TONT20000JUIN2017!J7 -> 465504.89 | F7: =IF(H7="ECHEC",0,13000) -> 13000 | G7: =IF(H7="ESPECES",1000,0) -> 1000 | H7: ESPECES | I7: =IF(F7=0,0,F7+J7+K7+L7+M7+N7) -> 20000 | J7: =IF(F7=0,0,3000) -> 3000 | K7: =IF(F7=0,0,500) -> 500 | L7: =IF(F7=0,0,1000) -> 1000 | M7: =IF(F7=0,0,2500) -> 2500 | P7: =IF(O7<=500000,(O7*1*3/100),(O7*12/100)) -> 0
A8: AS201603 | B8: =VLOOKUP(A8,LISTADHERENT!A$5:H$51,2) -> CHINGUE FABRICE | C8: =$P$56/$D$56*D8 -> 8138.2206 | D8: =TONT20000MAI2017!C8+TONT20000MAI2017!D8+TONT20000JUIN2017!J8 -> 468816.13 | F8: =IF(H8="ECHEC",0,13000) -> 13000 | G8: =IF(H8="ESPECES",1000,0) -> 1000 | H8: ESPECES | I8: =IF(F8=0,0,F8+J8+K8+L8+M8+N8) -> 20000 | J8: =IF(F8=0,0,3000) -> 3000 | K8: =IF(F8=0,0,500) -> 500 | L8: =IF(F8=0,0,1000) -> 1000 | M8: =IF(F8=0,0,2500) -> 2500 | P8: =IF(O8<=500000,(O8*1*3/100),(O8*12/100)) -> 0
A9: AS201604 | B9: =VLOOKUP(A9,LISTADHERENT!A$5:H$51,2) -> DJOMO JEAN PAUL | C9: =$P$56/$D$56*D9 -> 8205.505 | D9: =TONT20000MAI2017!C9+TONT20000MAI2017!D9+TONT20000JUIN2017!J9 -> 472692.16 | F9: =IF(H9="ECHEC",0,13000) -> 13000 | G9: =IF(H9="ESPECES",1000,0) -> 0 | H9: BANQUE | I9: =IF(F9=0,0,F9+J9+K9+L9+M9+N9) -> 20000 | J9: =IF(F9=0,0,3000) -> 3000 | K9: =IF(F9=0,0,500) -> 500 | L9: =IF(F9=0,0,1000) -> 1000 | M9: =IF(F9=0,0,2500) -> 2500 | P9: =IF(O9<=500000,(O9*1*3/100),(O9*12/100)) -> 0
A10: AS201605 | B10: =VLOOKUP(A10,LISTADHERENT!A$5:H$51,2) -> DJOUKWE NANGUEN GUY BLAISE | C10: =$P$56/$D$56*D10 -> 8380.3999 | D10: =TONT20000MAI2017!C10+TONT20000MAI2017!D10+TONT20000JUIN2017!J10 -> 482767.28 | F10: =IF(H10="ECHEC",0,13000) -> 13000 | G10: =IF(H10="ESPECES",1000,0) -> 1000 | H10: ESPECES | I10: =IF(F10=0,0,F10+J10+K10+L10+M10+N10) -> 29000 | J10: =IF(F10=0,0,3000)+9000 -> 12000 | K10: =IF(F10=0,0,500) -> 500 | L10: =IF(F10=0,0,1000) -> 1000 | M10: =IF(F10=0,0,2500) -> 2500 | P10: =IF(O10<=500000,(O10*1*3/100),(O10*12/100)) -> 0
D11: =TONT20000MAI2017!C11+TONT20000MAI2017!D11+TONT20000JUIN2017!J11 -> 0 | J11: =IF(F11=0,0,3000) -> 0 | K11: =IF(F11=0,0,500) -> 0 | L11: =IF(F11=0,0,1000) -> 0 | M11: =IF(F11=0,0,2500) -> 0 | P11: =IF(O11<=500000,(O11*1*3/100),(O11*12/100)) -> 0
A12: AS201607 | B12: =VLOOKUP(A12,LISTADHERENT!A$5:H$51,2) -> DJOUNKEP SAMUEL | C12: =$P$56/$D$56*D12 -> 19613.566 | D12: =TONT20000MAI2017!C12+TONT20000MAI2017!D12+TONT20000JUIN2017!J12 -> 1129873 | F12: =IF(H12="ECHEC",0,13000) -> 13000 | G12: =IF(H12="ESPECES",1000,0) -> 0 | H12: BANQUE | I12: =IF(F12=0,0,F12+J12+K12+L12+M12+N12) -> 20000 | J12: =IF(F12=0,0,3000) -> 3000 | K12: =IF(F12=0,0,500) -> 500 | L12: =IF(F12=0,0,1000) -> 1000 | M12: =IF(F12=0,0,2500) -> 2500 | O12: 1000000 | P12: =IF(O12<=500000,(O12*1*3/100),(O12*12/100)) -> 120000
A13: AS201608 | B13: =VLOOKUP(A13,LISTADHERENT!A$5:H$51,2) -> DJUOMBESSY ANTOINE | C13: =$P$56/$D$56*D13 -> 8081.2144 | D13: =TONT20000MAI2017!C13+TONT20000MAI2017!D13+TONT20000JUIN2017!J13 -> 465532.19 | F13: =IF(H13="ECHEC",0,13000) -> 13000 | G13: =IF(H13="ESPECES",1000,0) -> 0 | H13: BANQUE | I13: =IF(F13=0,0,F13+J13+K13+L13+M13+N13) -> 20000 | J13: =IF(F13=0,0,3000) -> 3000 | K13: =IF(F13=0,0,500) -> 500 | L13: =IF(F13=0,0,1000) -> 1000 | M13: =IF(F13=0,0,2500) -> 2500 | O13: 700000 | P13: =IF(O13<=500000,(O13*1*3/100),(O13*12/100)) -> 84000 | Q13: =215000+499000 -> 714000
A14: AS201609 | B14: =VLOOKUP(A14,LISTADHERENT!A$5:H$51,2) -> DONHOU DAVID | C14: =$P$56/$D$56*D14 -> 9010.7001 | D14: =TONT20000MAI2017!C14+TONT20000MAI2017!D14+TONT20000JUIN2017!J14 -> 519076.81 | F14: =IF(H14="ECHEC",0,13000) -> 13000 | G14: =IF(H14="ESPECES",1000,0) -> 0 | H14: BANQUE | I14: =IF(F14=0,0,F14+J14+K14+L14+M14+N14) -> 20000 | J14: =IF(F14=0,0,3000) -> 3000 | K14: =IF(F14=0,0,500) -> 500 | L14: =IF(F14=0,0,1000) -> 1000 | M14: =IF(F14=0,0,2500) -> 2500 | P14: =IF(O14<=500000,(O14*1*3/100),(O14*12/100)) -> 0
A15: AS201610 | B15: =VLOOKUP(A15,LISTADHERENT!A$5:H$51,2) -> FOTSO THOMAS | C15: =$P$56/$D$56*D15 -> 8077.1321 | D15: =TONT20000MAI2017!C15+TONT20000MAI2017!D15+TONT20000JUIN2017!J15 -> 465297.02 | F15: =IF(H15="ECHEC",0,13000) -> 13000 | G15: =IF(H15="ESPECES",1000,0) -> 1000 | H15: ESPECES | I15: =IF(F15=0,0,F15+J15+K15+L15+M15+N15) -> 20000 | J15: =IF(F15=0,0,3000) -> 3000 | K15: =IF(F15=0,0,500) -> 500 | L15: =IF(F15=0,0,1000) -> 1000 | M15: =IF(F15=0,0,2500) -> 2500 | P15: =IF(O15<=500000,(O15*1*3/100),(O15*12/100)) -> 0
A16: AS201611 | B16: =VLOOKUP(A16,LISTADHERENT!A$5:H$51,2) -> HENGUE PAUL OMER | C16: =$P$56/$D$56*D16 -> 9233.9866 | D16: =TONT20000MAI2017!C16+TONT20000MAI2017!D16+TONT20000JUIN2017!J16 -> 531939.61 | F16: =IF(H16="ECHEC",0,13000) -> 13000 | G16: =IF(H16="ESPECES",1000,0) -> 0 | H16: BANQUE | I16: =IF(F16=0,0,F16+J16+K16+L16+M16+N16) -> 20000 | J16: =IF(F16=0,0,3000) -> 3000 | K16: =IF(F16=0,0,500) -> 500 | L16: =IF(F16=0,0,1000) -> 1000 | M16: =IF(F16=0,0,2500) -> 2500 | P16: =IF(O16<=500000,(O16*1*3/100),(O16*12/100)) -> 0
A17: AS201612 | B17: =VLOOKUP(A17,LISTADHERENT!A$5:H$51,2) -> HODIEP JULES | C17: =$P$56/$D$56*D17 -> 915.96316 | D17: =TONT20000MAI2017!C17+TONT20000MAI2017!D17+TONT20000JUIN2017!J17 -> 52765.626 | F17: =IF(H17="ECHEC",0,13000) -> 0 | G17: =IF(H17="ESPECES",1000,0) -> 0 | H17: ECHEC | I17: =IF(F17=0,0,F17+J17+K17+L17+M17+N17) -> 0 | J17: =IF(F17=0,0,3000) -> 0 | K17: =IF(F17=0,0,500) -> 0 | L17: =IF(F17=0,0,1000) -> 0 | M17: =IF(F17=0,0,2500) -> 0 | P17: =IF(O17<=500000,(O17*1*3/100),(O17*12/100)) -> 0
A18: AS201613 | B18: =VLOOKUP(A18,LISTADHERENT!A$5:H$51,2) -> HOTCHO BENJAMIN | C18: =$P$56/$D$56*D18 -> 10084.797 | D18: =TONT20000MAI2017!C18+TONT20000MAI2017!D18+TONT20000JUIN2017!J18 -> 580952.01 | F18: =IF(H18="ECHEC",0,13000) -> 13000 | G18: =IF(H18="ESPECES",1000,0) -> 0 | H18: BANQUE | I18: =IF(F18=0,0,F18+J18+K18+L18+M18+N18) -> 20000 | J18: =IF(F18=0,0,3000) -> 3000 | K18: =IF(F18=0,0,500) -> 500 | L18: =IF(F18=0,0,1000) -> 1000 | M18: =IF(F18=0,0,2500) -> 2500 | O18: 700000 | P18: =IF(O18<=500000,(O18*1*3/100),(O18*12/100)) -> 84000
A19: AS201614 | B19: =VLOOKUP(A19,LISTADHERENT!A$5:H$51,2) -> KEPHE DAVID | C19: =$P$56/$D$56*D19 -> 2202.5569 | D19: =TONT20000MAI2017!C19+TONT20000MAI2017!D19+TONT20000JUIN2017!J19 -> 126882.06 | F19: =IF(H19="ECHEC",0,13000) -> 13000 | G19: =IF(H19="ESPECES",1000,0) -> 1000 | H19: ESPECES | I19: =IF(F19=0,0,F19+J19+K19+L19+M19+N19) -> 20000 | J19: =IF(F19=0,0,3000) -> 3000 | K19: =IF(F19=0,0,500) -> 500 | L19: =IF(F19=0,0,1000) -> 1000 | M19: =IF(F19=0,0,2500) -> 2500 | P19: =IF(O19<=500000,(O19*1*3/100),(O19*12/100)) -> 0
A20: AS201615 | B20: =VLOOKUP(A20,LISTADHERENT!A$5:H$51,2) -> KEPSEU FRANCIS | C20: =$P$56/$D$56*D20 -> 56847.651 | D20: =TONT20000MAI2017!C20+TONT20000MAI2017!D20+TONT20000JUIN2017!J20 -> 3274806.2 | F20: =IF(H20="ECHEC",0,13000) -> 13000 | G20: =IF(H20="ESPECES",1000,0) -> 0 | H20: BANQUE | I20: =IF(F20=0,0,F20+J20+K20+L20+M20+N20) -> 1023000 | J20: =IF(F20=0,0,6000)+1000000 -> 1006000 | K20: =IF(F20=0,0,500) -> 500 | L20: =IF(F20=0,0,1000) -> 1000 | M20: =IF(F20=0,0,2500) -> 2500 | P20: =IF(O20<=500000,(O20*1*3/100),(O20*12/100)) -> 0
A21: AS201616 | B21: =VLOOKUP(A21,LISTADHERENT!A$5:H$51,2) -> KOUAMOU EMMANUEL | C21: =$P$56/$D$56*D21 -> 8074.125 | D21: =TONT20000MAI2017!C21+TONT20000MAI2017!D21+TONT20000JUIN2017!J21 -> 465123.79 | F21: =IF(H21="ECHEC",0,13000) -> 13000 | G21: =IF(H21="ESPECES",1000,0) -> 1000 | H21: ESPECES | I21: =IF(F21=0,0,F21+J21+K21+L21+M21+N21) -> 20000 | J21: =IF(F21=0,0,3000) -> 3000 | K21: =IF(F21=0,0,500) -> 500 | L21: =IF(F21=0,0,1000) -> 1000 | M21: =IF(F21=0,0,2500) -> 2500 | P21: =IF(O21<=500000,(O21*1*3/100),(O21*12/100)) -> 0
A22: AS201617 | B22: =VLOOKUP(A22,LISTADHERENT!A$5:H$51,2) -> KOUAMOU MOISE | C22: =$P$56/$D$56*D22 -> 8415.3751 | D22: =TONT20000MAI2017!C22+TONT20000MAI2017!D22+TONT20000JUIN2017!J22 -> 484782.09 | F22: =IF(H22="ECHEC",0,13000) -> 13000 | G22: =IF(H22="ESPECES",1000,0) -> 0 | H22: BANQUE | I22: =IF(F22=0,0,F22+J22+K22+L22+M22+N22) -> 42000 | J22: =IF(F22=0,0,3000)+22000 -> 25000 | K22: =IF(F22=0,0,500) -> 500 | L22: =IF(F22=0,0,1000) -> 1000 | M22: =IF(F22=0,0,2500) -> 2500 | P22: =IF(O22<=500000,(O22*1*3/100),(O22*12/100)) -> 0
A23: AS201618 | B23: =VLOOKUP(A23,LISTADHERENT!A$5:H$51,2) -> KOUAMO VICTOR PEGUY | C23: =$P$56/$D$56*D23 -> 8080.1209 | D23: =TONT20000MAI2017!C23+TONT20000MAI2017!D23+TONT20000JUIN2017!J23 -> 465469.2 | F23: =IF(H23="ECHEC",0,13000) -> 13000 | G23: =IF(H23="ESPECES",1000,0) -> 0 | H23: BANQUE | I23: =IF(F23=0,0,F23+J23+K23+L23+M23+N23) -> 20000 | J23: =IF(F23=0,0,3000) -> 3000 | K23: =IF(F23=0,0,500) -> 500 | L23: =IF(F23=0,0,1000) -> 1000 | M23: =IF(F23=0,0,2500) -> 2500 | P23: =IF(O23<=500000,(O23*1*3/100),(O23*12/100)) -> 0
A24: AS201619 | B24: =VLOOKUP(A24,LISTADHERENT!A$5:H$51,2) -> KOUATCHO MESSACK | C24: =$P$56/$D$56*D24 -> 8100.751 | D24: =TONT20000MAI2017!C24+TONT20000MAI2017!D24+TONT20000JUIN2017!J24 -> 466657.63 | F24: =IF(H24="ECHEC",0,13000) -> 13000 | G24: =IF(H24="ESPECES",1000,0) -> 0 | H24: BANQUE | I24: =IF(F24=0,0,F24+J24+K24+L24+M24+N24) -> 20000 | J24: =IF(F24=0,0,3000) -> 3000 | K24: =IF(F24=0,0,500) -> 500 | L24: =IF(F24=0,0,1000) -> 1000 | M24: =IF(F24=0,0,2500) -> 2500 | P24: =IF(O24<=500000,(O24*1*3/100),(O24*12/100)) -> 0
A25: AS201620 | B25: =VLOOKUP(A25,LISTADHERENT!A$5:H$51,2) -> LOWE JEAN | C25: =$P$56/$D$56*D25 -> 8027.424 | D25: =TONT20000MAI2017!C25+TONT20000MAI2017!D25+TONT20000JUIN2017!J25 -> 462433.5 | F25: =IF(H25="ECHEC",0,13000) -> 0 | G25: =IF(H25="ESPECES",1000,0) -> 0 | H25: ECHEC | I25: =IF(F25=0,0,F25+J25+K25+L25+M25+N25) -> 0 | J25: =IF(F25=0,0,3000) -> 0 | K25: =IF(F25=0,0,500) -> 0 | L25: =IF(F25=0,0,1000) -> 0 | M25: =IF(F25=0,0,2500) -> 0 | P25: =IF(O25<=500000,(O25*1*3/100),(O25*12/100)) -> 0
A26: AS201621 | B26: =VLOOKUP(A26,LISTADHERENT!A$5:H$51,2) -> NANKAM APPOLINAIRE | C26: =$P$56/$D$56*D26 -> 8081.1232 | D26: =TONT20000MAI2017!C26+TONT20000MAI2017!D26+TONT20000JUIN2017!J26 -> 465526.94 | F26: =IF(H26="ECHEC",0,13000) -> 13000 | G26: =IF(H26="ESPECES",1000,0) -> 0 | H26: BANQUE | I26: =IF(F26=0,0,F26+J26+K26+L26+M26+N26) -> 20000 | J26: =IF(F26=0,0,3000) -> 3000 | K26: =IF(F26=0,0,500) -> 500 | L26: =IF(F26=0,0,1000) -> 1000 | M26: =IF(F26=0,0,2500) -> 2500 | P26: =IF(O26<=500000,(O26*1*3/100),(O26*12/100)) -> 0
A27: AS201622 | B27: =VLOOKUP(A27,LISTADHERENT!A$5:H$51,2) -> NDJOMO ETIENNE | C27: =$P$56/$D$56*D27 -> 8710.6626 | D27: =TONT20000MAI2017!C27+TONT20000MAI2017!D27+TONT20000JUIN2017!J27 -> 501792.63 | F27: =IF(H27="ECHEC",0,13000) -> 13000 | G27: =IF(H27="ESPECES",1000,0) -> 0 | H27: BANQUE | I27: =IF(F27=0,0,F27+J27+K27+L27+M27+N27) -> 25000 | J27: =IF(F27=0,0,8000) -> 8000 | K27: =IF(F27=0,0,500) -> 500 | L27: =IF(F27=0,0,1000) -> 1000 | M27: =IF(F27=0,0,2500) -> 2500 | P27: =IF(O27<=500000,(O27*1*3/100),(O27*12/100)) -> 0
A28: AS201623 | B28: =VLOOKUP(A28,LISTADHERENT!A$5:H$51,2) -> NDOMBOU JEAN CLAUDE | C28: =$P$56/$D$56*D28 -> 7654.2883 | D28: =TONT20000MAI2017!C28+TONT20000MAI2017!D28+TONT20000JUIN2017!J28 -> 440938.38 | J28: =IF(F28=0,0,3000) -> 0 | K28: =IF(F28=0,0,500) -> 0 | L28: =IF(F28=0,0,1000) -> 0 | M28: =IF(F28=0,0,2500) -> 0 | P28: =IF(O28<=500000,(O28*1*3/100),(O28*12/100)) -> 0
A29: AS201624 | B29: =VLOOKUP(A29,LISTADHERENT!A$5:H$51,2) -> NGONDIEP CLAUDE | C29: =$P$56/$D$56*D29 -> 8254.3257 | D29: =TONT20000MAI2017!C29+TONT20000MAI2017!D29+TONT20000JUIN2017!J29 -> 475504.56 | F29: =IF(H29="ECHEC",0,13000) -> 13000 | G29: =IF(H29="ESPECES",1000,0) -> 0 | H29: BANQUE | I29: =IF(F29=0,0,F29+J29+K29+L29+M29+N29) -> 20000 | J29: =IF(F29=0,0,3000) -> 3000 | K29: =IF(F29=0,0,500) -> 500 | L29: =IF(F29=0,0,1000) -> 1000 | M29: =IF(F29=0,0,2500) -> 2500 | O29: 1000000 | P29: =IF(O29<=500000,(O29*1*3/100),(O29*12/100)) -> 120000 | T29: 10000
A30: AS201625 | B30: =VLOOKUP(A30,LISTADHERENT!A$5:H$51,2) -> NGONGANG JEAN THEODORE | C30: =$P$56/$D$56*D30 -> 1095.8711 | D30: =TONT20000MAI2017!C30+TONT20000MAI2017!D30+TONT20000JUIN2017!J30 -> 63129.53 | F30: =IF(H30="ECHEC",0,13000) -> 13000 | G30: =IF(H30="ESPECES",1000,0) -> 1000 | H30: ESPECES | I30: =IF(F30=0,0,F30+J30+K30+L30+M30+N30) -> 20000 | J30: =IF(F30=0,0,3000) -> 3000 | K30: =IF(F30=0,0,500) -> 500 | L30: =IF(F30=0,0,1000) -> 1000 | M30: =IF(F30=0,0,2500) -> 2500 | P30: =IF(O30<=500000,(O30*1*3/100),(O30*12/100)) -> 0
A31: AS201626 | B31: =VLOOKUP(A31,LISTADHERENT!A$5:H$51,2) -> NGUIEMEGNI MATHIEU BLAISE | C31: =$P$56/$D$56*D31 -> 8762.5736 | D31: =TONT20000MAI2017!C31+TONT20000MAI2017!D31+TONT20000JUIN2017!J31 -> 504783.05 | F31: =IF(H31="ECHEC",0,13000) -> 13000 | G31: =IF(H31="ESPECES",1000,0) -> 1000 | H31: ESPECES | I31: =IF(F31=0,0,F31+J31+K31+L31+M31+N31) -> 20000 | J31: =IF(F31=0,0,3000) -> 3000 | K31: =IF(F31=0,0,500) -> 500 | L31: =IF(F31=0,0,1000) -> 1000 | M31: =IF(F31=0,0,2500) -> 2500 | P31: =IF(O31<=500000,(O31*1*3/100),(O31*12/100)) -> 0
A32: AS201627 | B32: =VLOOKUP(A32,LISTADHERENT!A$5:H$51,2) -> NJEPDJIO MBOUKAM DELUXE | C32: =$P$56/$D$56*D32 -> 8172.7765 | D32: =TONT20000MAI2017!C32+TONT20000MAI2017!D32+TONT20000JUIN2017!J32 -> 470806.78 | F32: =IF(H32="ECHEC",0,13000) -> 13000 | G32: =IF(H32="ESPECES",1000,0) -> 1000 | H32: ESPECES | I32: =IF(F32=0,0,F32+J32+K32+L32+M32+N32) -> 20000 | J32: =IF(F32=0,0,3000) -> 3000 | K32: =IF(F32=0,0,500) -> 500 | L32: =IF(F32=0,0,1000) -> 1000 | M32: =IF(F32=0,0,2500) -> 2500 | P32: =IF(O32<=500000,(O32*1*3/100),(O32*12/100)) -> 0
A33: AS201628 | B33: =VLOOKUP(A33,LISTADHERENT!A$5:H$51,2) -> NKAMGANG JUSTIN DEJOLIE | C33: =$P$56/$D$56*D33 -> 9716.6952 | D33: =TONT20000MAI2017!C33+TONT20000MAI2017!D33+TONT20000JUIN2017!J33 -> 559746.86 | F33: =IF(H33="ECHEC",0,13000) -> 13000 | G33: =IF(H33="ESPECES",1000,0) -> 0 | H33: BANQUE | I33: =IF(F33=0,0,F33+J33+K33+L33+M33+N33) -> 23000 | J33: =IF(F33=0,0,3000)+3000 -> 6000 | K33: =IF(F33=0,0,500) -> 500 | L33: =IF(F33=0,0,1000) -> 1000 | M33: =IF(F33=0,0,2500) -> 2500 | P33: =IF(O33<=500000,(O33*1*3/100),(O33*12/100)) -> 0
A34: AS201629 | B34: =VLOOKUP(A34,LISTADHERENT!A$5:H$51,2) -> NKEPSEU DIEUDONNE | C34: =$P$56/$D$56*D34 -> 10532.274 | D34: =TONT20000MAI2017!C34+TONT20000MAI2017!D34+TONT20000JUIN2017!J34 -> 606729.66 | F34: =IF(H34="ECHEC",0,13000) -> 13000 | G34: =IF(H34="ESPECES",1000,0) -> 1000 | H34: ESPECES | I34: =IF(F34=0,0,F34+J34+K34+L34+M34+N34) -> 25000 | J34: =IF(F34=0,0,3000)+5000 -> 8000 | K34: =IF(F34=0,0,500) -> 500 | L34: =IF(F34=0,0,1000) -> 1000 | M34: =IF(F34=0,0,2500) -> 2500 | P34: =IF(O34<=500000,(O34*1*3/100),(O34*12/100)) -> 0
D35: =TONT20000MAI2017!C35+TONT20000MAI2017!D35+TONT20000JUIN2017!J35 -> 0 | J35: =IF(F35=0,0,3000) -> 0 | K35: =IF(F35=0,0,500) -> 0 | L35: =IF(F35=0,0,1000) -> 0 | M35: =IF(F35=0,0,2500) -> 0 | P35: =IF(O35<=500000,(O35*1*3/100),(O35*12/100)) -> 0
A36: AS201631 | B36: =VLOOKUP(A36,LISTADHERENT!A$5:H$51,2) -> NTEPDIE TUEMAC MZ | C36: =$P$56/$D$56*D36 -> 0 | D36: =TONT20000MAI2017!C36+TONT20000MAI2017!D36+TONT20000JUIN2017!J36 -> 0 | F36: =IF(H36="ECHEC",0,13000) -> 0 | G36: =IF(H36="ESPECES",1000,0) -> 0 | H36: ECHEC | I36: =IF(F36=0,0,F36+J36+K36+L36+M36+N36) -> 0 | J36: =IF(F36=0,0,3000) -> 0 | K36: =IF(F36=0,0,500) -> 0 | L36: =IF(F36=0,0,1000) -> 0 | M36: =IF(F36=0,0,2500) -> 0 | P36: =IF(O36<=500000,(O36*1*3/100),(O36*12/100)) -> 0
D37: =TONT20000MAI2017!C37+TONT20000MAI2017!D37+TONT20000JUIN2017!J37 -> 0 | J37: =IF(F37=0,0,3000) -> 0 | K37: =IF(F37=0,0,500) -> 0 | L37: =IF(F37=0,0,1000) -> 0 | M37: =IF(F37=0,0,2500) -> 0 | P37: =IF(O37<=500000,(O37*1*3/100),(O37*12/100)) -> 0
A38: AS201633 | B38: =VLOOKUP(A38,LISTADHERENT!A$5:H$51,2) -> PATEGO NJOSSU GUSTAVE | C38: =$P$56/$D$56*D38 -> 8076.2573 | D38: =TONT20000MAI2017!C38+TONT20000MAI2017!D38+TONT20000JUIN2017!J38 -> 465246.63 | F38: =IF(H38="ECHEC",0,13000) -> 13000 | G38: =IF(H38="ESPECES",1000,0) -> 0 | H38: BANQUE | I38: =IF(F38=0,0,F38+J38+K38+L38+M38+N38) -> 20000 | J38: =IF(F38=0,0,3000) -> 3000 | K38: =IF(F38=0,0,500) -> 500 | L38: =IF(F38=0,0,1000) -> 1000 | M38: =IF(F38=0,0,2500) -> 2500 | P38: =IF(O38<=500000,(O38*1*3/100),(O38*12/100)) -> 0
A39: AS201634 | B39: =VLOOKUP(A39,LISTADHERENT!A$5:H$51,2) -> SEUNOU RICHELOT | C39: =$P$56/$D$56*D39 -> 8154.2946 | D39: =TONT20000MAI2017!C39+TONT20000MAI2017!D39+TONT20000JUIN2017!J39 -> 469742.1 | F39: =IF(H39="ECHEC",0,13000) -> 13000 | G39: =IF(H39="ESPECES",1000,0) -> 1000 | H39: ESPECES | I39: =IF(F39=0,0,F39+J39+K39+L39+M39+N39) -> 20000 | J39: =IF(F39=0,0,3000) -> 3000 | K39: =IF(F39=0,0,500) -> 500 | L39: =IF(F39=0,0,1000) -> 1000 | M39: =IF(F39=0,0,2500) -> 2500 | P39: =IF(O39<=500000,(O39*1*3/100),(O39*12/100)) -> 0
A40: AS201635 | B40: =VLOOKUP(A40,LISTADHERENT!A$5:H$51,2) -> SIME ABEL | C40: =$P$56/$D$56*D40 -> 7439.7619 | D40: =TONT20000MAI2017!C40+TONT20000MAI2017!D40+TONT20000JUIN2017!J40 -> 428580.22 | F40: =IF(H40="ECHEC",0,13000) -> 13000 | G40: =IF(H40="ESPECES",1000,0) -> 1000 | H40: ESPECES | I40: =IF(F40=0,0,F40+J40+K40+L40+M40+N40) -> 20000 | J40: =IF(F40=0,0,3000) -> 3000 | K40: =IF(F40=0,0,500) -> 500 | L40: =IF(F40=0,0,1000) -> 1000 | M40: =IF(F40=0,0,2500) -> 2500 | P40: =IF(O40<=500000,(O40*1*3/100),(O40*12/100)) -> 0
A41: AS201636 | B41: =VLOOKUP(A41,LISTADHERENT!A$5:H$51,2) -> SIME FONGANG ERIC | C41: =$P$56/$D$56*D41 -> 8120.7251 | D41: =TONT20000MAI2017!C41+TONT20000MAI2017!D41+TONT20000JUIN2017!J41 -> 467808.27 | F41: =IF(H41="ECHEC",0,13000) -> 13000 | G41: =IF(H41="ESPECES",1000,0) -> 0 | H41: BANQUE | I41: =IF(F41=0,0,F41+J41+K41+L41+M41+N41) -> 20000 | J41: =IF(F41=0,0,3000) -> 3000 | K41: =IF(F41=0,0,500) -> 500 | L41: =IF(F41=0,0,1000) -> 1000 | M41: =IF(F41=0,0,2500) -> 2500 | P41: =IF(O41<=500000,(O41*1*3/100),(O41*12/100)) -> 0
A42: AS201637 | B42: =VLOOKUP(A42,LISTADHERENT!A$5:H$51,2) -> SIME MATHIEU | C42: =$P$56/$D$56*D42 -> 8113.6904 | D42: =TONT20000MAI2017!C42+TONT20000MAI2017!D42+TONT20000JUIN2017!J42 -> 467403.03 | F42: =IF(H42="ECHEC",0,13000) -> 13000 | G42: =IF(H42="ESPECES",1000,0) -> 0 | H42: BANQUE | I42: =IF(F42=0,0,F42+J42+K42+L42+M42+N42) -> 20000 | J42: =IF(F42=0,0,3000) -> 3000 | K42: =IF(F42=0,0,500) -> 500 | L42: =IF(F42=0,0,1000) -> 1000 | M42: =IF(F42=0,0,2500) -> 2500 | P42: =IF(O42<=500000,(O42*1*3/100),(O42*12/100)) -> 0 | Q42: 100000
A43: AS201638 | B43: =VLOOKUP(A43,LISTADHERENT!A$5:H$51,2) -> SIME PIERRE | C43: =$P$56/$D$56*D43 -> 10863.388 | D43: =TONT20000MAI2017!C43+TONT20000MAI2017!D43+TONT20000JUIN2017!J43 -> 625804.09 | F43: =IF(H43="ECHEC",0,13000) -> 13000 | G43: =IF(H43="ESPECES",1000,0) -> 0 | H43: BANQUE | I43: =IF(F43=0,0,F43+J43+K43+L43+M43+N43) -> 25000 | J43: =IF(F43=0,0,3000)+5000 -> 8000 | K43: =IF(F43=0,0,500) -> 500 | L43: =IF(F43=0,0,1000) -> 1000 | M43: =IF(F43=0,0,2500) -> 2500 | O43: 400000 | P43: =IF(O43<=500000,(O43*1*3/100),(O43*12/100)) -> 12000
A44: AS201639 | B44: =VLOOKUP(A44,LISTADHERENT!A$5:H$51,2) -> TAGNE NANGUEN MARTIN | C44: =$P$56/$D$56*D44 -> 7513.9769 | D44: =TONT20000MAI2017!C44+TONT20000MAI2017!D44+TONT20000JUIN2017!J44 -> 432855.5 | F44: =IF(H44="ECHEC",0,13000) -> 13000 | G44: =IF(H44="ESPECES",1000,0) -> 0 | H44: BANQUE | I44: =IF(F44=0,0,F44+J44+K44+L44+M44+N44) -> 20000 | J44: =IF(F44=0,0,3000) -> 3000 | K44: =IF(F44=0,0,500) -> 500 | L44: =IF(F44=0,0,1000) -> 1000 | M44: =IF(F44=0,0,2500) -> 2500 | P44: =IF(O44<=500000,(O44*1*3/100),(O44*12/100)) -> 0
A45: AS201640 | B45: =VLOOKUP(A45,LISTADHERENT!A$5:H$51,2) -> TCHOUAMOU JEAN PAUL | C45: =$P$56/$D$56*D45 -> 647.38781 | D45: =TONT20000MAI2017!C45+TONT20000MAI2017!D45+TONT20000JUIN2017!J45 -> 37293.883 | F45: =IF(H45="ECHEC",0,13000) -> 13000 | G45: =IF(H45="ESPECES",1000,0) -> 0 | H45: BANQUE | I45: =IF(F45=0,0,F45+J45+K45+L45+M45+N45) -> 20000 | J45: =IF(F45=0,0,3000) -> 3000 | K45: =IF(F45=0,0,500) -> 500 | L45: =IF(F45=0,0,1000) -> 1000 | M45: =IF(F45=0,0,2500) -> 2500 | P45: =IF(O45<=500000,(O45*1*3/100),(O45*12/100)) -> 0
