Workbook
Name BANQUE: #REF!
Name BANQUE: #REF!
Name BANQUE: #REF!
Name BANQUE: #REF!
Name BANQUE: #REF!
Name BANQUE: #REF!
Name BANQUE: #REF!
Name BANQUE: #REF!
Name BANQUE: #REF!
Name BANQUE: #REF!
Name BANQUE: #REF!
Name BANQUE: #REF!
Name BANQUE: #REF!
Name BANQUE: #REF!
Name BANQUE: #REF!
Name BANQUE: #REF!
Name BANQUE: #REF!
Name BANQUE: #REF!
Name BANQUE: #REF!
Name BANQUE: #REF!
Name BANQUE: #REF!
Name BANQUE: #REF!
Name BANQUE: #REF!
Name BANQUE: #REF!
Name BANQUE: #REF!
Name BANQUE: #REF!
Name BANQUE: #REF!
Name BANQUE: #REF!
Name BANQUE: #REF!
Name BANQUE: #REF!
Name BANQUE: #REF!
Name BANQUE: #REF!
Name BANQUE: #REF!
Name GG: #REF!
Name GG: #REF!
Name MODEPAID: [1]Feuil2!$A$1:$A$3
Name MODET25000: [2]MODEVERSEMENT!$A$1:$A$3
Name MODEVERSEMENT: #REF!
Name MODEVERSEMENT: #REF!
Name MODEVERSEMENT: #REF!
Name MODEVERSEMENT: #REF!
Name MODEVERSEMENT: #REF!
Name MODEVERSEMENT: #REF!
Name MODEVERSEMENT: #REF!
Name MODEVERSEMENT: #REF!
Name MODEVERSEMENT: #REF!
Name MODEVERSEMENT: #REF!
Name MODEVERSEMENT: #REF!
Name MODEVERSEMENT: #REF!
Name MODEVERSEMENT: #REF!
Name MODEVERSEMENT: #REF!
Name MODEVERSEMENT: #REF!
Name MODEVERSEMENT: #REF!
Name MODEVERSEMENT: #REF!
Name MODEVERSEMENT: #REF!
Name MODEVERSEMENT: #REF!
Name MODEVERSEMENT: #REF!
Name MODEVERSEMENT: #REF!
Name MODEVERSEMENT: #REF!
Name MODEVERSEMENT: #REF!

Sheet MODEVERSEMENT
A1: BANQUE
A2: ESPECES

Sheet HISTOMVTDEPENSE
A1: ASSOCIATION | B1: ASELBY
A2: ANNEE | B2: 2022
A3: 1 | B3: 2 | D3: 3 | E3: 4 | F3: 5 | G3: 6 | H3: 7 | I3: 8 | J3: 9 | K3: 10 | L3: 11 | M3: 12 | N3: 13 | O3: 14 | P3: 15 | Q3: 16 | R3: 17 | S3: 18
B4: TABLEAU DE BORD SAISIE DES DEPENSES
A5: MATRICULE | B5: NOM ET PRENOM | D5: FONDS DE ROULEMENT | M5: FRAIS EXCEPTIONNEL | P5: COLLATION | R5: MUTUELLE | T5: TOTAUX
C6: FRAIS BANCAIRE | D6: ACHAT FOURNITURE | E6: COMMUNICATION | F6: COMMISSION | G6: AUTRES AIDES | H6: CREDIT TELEPHONE | I6: PRODUCTION RAPPORT | J6: ACHAT SOURIS ET PHOTOCOPIE | K6: FRAIS DE BANQUE | L6: CONFECTION CACHET | M6: GRATIFICATION BUREAU | N6: DEVELOPPEMENT LAGWEU | O6: DEUIL | P6: COLLATION | Q6: BOISSON | R6: DECES | S6: TRANSPORT DELEGUE
A7: AS201648 | B7: =VLOOKUP(A7,[5]LISTADHERENT!A$5:H$60,3,0) -> ASELBY | T7: =SUM(D7:S7) -> 0
A8: AS201602 | B8: =VLOOKUP(A8,[5]LISTADHERENT!A$5:H$60,3,0) -> BOUTCHOUANG WILLIAM | T8: =SUM(D8:S8) -> 0
A9: AS201604 | B9: =VLOOKUP(A9,[5]LISTADHERENT!A$5:H$60,3,0) -> DJOMO JEAN PAUL | T9: =SUM(D9:S9) -> 0
A10: AS201654 | B10: =VLOOKUP(A10,[5]LISTADHERENT!A$5:H$60,3,0) -> DJOMOU TCHANDA | T10: =SUM(D10:S10) -> 0
A11: AS201605 | B11: =VLOOKUP(A11,[5]LISTADHERENT!A$5:H$60,3,0) -> DJOUKWE NANGUEN GUY BLAISE | T11: =SUM(D11:S11) -> 0
A12: AS201608 | B12: =VLOOKUP(A12,[5]LISTADHERENT!A$5:H$60,3,0) -> DJUOMBESSY ANTOINE | T12: =SUM(D12:S12) -> 0
A13: AS201651 | B13: =VLOOKUP(A13,[5]LISTADHERENT!A$5:H$60,3,0) -> DOMOU FABIEN | T13: =SUM(D13:S13) -> 0
A14: AS201609 | B14: =VLOOKUP(A14,[5]LISTADHERENT!A$5:H$60,3,0) -> DONHOU DAVID | T14: =SUM(D14:S14) -> 0
A15: AS201610 | B15: =VLOOKUP(A15,[5]LISTADHERENT!A$5:H$60,3,0) -> FOTSO THOMAS | T15: =SUM(D15:S15) -> 0
A16: AS201611 | B16: =VLOOKUP(A16,[5]LISTADHERENT!A$5:H$60,3,0) -> HENGUE PAUL OMER | T16: =SUM(D16:S16) -> 0
A17: AS201613 | B17: =VLOOKUP(A17,[5]LISTADHERENT!A$5:H$60,3,0) -> HOTCHO BENJAMIN | T17: =SUM(D17:S17) -> 0
A18: AS201617 | B18: =VLOOKUP(A18,[5]LISTADHERENT!A$5:H$60,3,0) -> KOUAMOU MOISE | T18: =SUM(D18:S18) -> 0
... A37: AS201647 | B37: =VLOOKUP(A37,[5]LISTADHERENT!A$5:H$60,3,0) -> YOUMBI EMMANUEL | T37: =SUM(D37:S37) -> 0
B39: TOTAUX | C39: =SUM(C8:C38) -> 0 | D39: =SUM(D8:D38) -> 0 | E39: =SUM(E8:E38) -> 0 | F39: =SUM(F8:F38) -> 0 | G39: =SUM(G8:G38) -> 0 | H39: =SUM(H8:H38) -> 0 | J39: =SUM(J8:J38) -> 0 | K39: =SUM(K8:K38) -> 0 | L39: =SUM(L8:L38) -> 0 | M39: =SUM(M8:M38) -> 0 | N39: =SUM(N8:N38) -> 0 | O39: =SUM(O8:O38) -> 0 | P39: =SUM(P8:P38) -> 0 | Q39: =SUM(Q8:Q38) -> 0 | ... T39: =SUM(T8:T38) -> 0

Sheet COMPTE BANQUE
C1: COMPTE BANQUE | H1: COMPTE CAISSE
A2: ANNEE | C2: 2022 | H2: 2022
A4: MOIS | B4: NUMERO CHEQUE | C4: SORTIE | D4: ENTREE | E4: SOLDE | G4: NUMERO PIECE | H4: ENTREE | I4: SORTIE | J4: SOLDE
A5: REPORT A NOUVEAU | E5: =14283661-6017000 -> 8266661
A6: JANVIER | C6: =#REF!+HISTOMVTDEPENSE!T39 -> #REF! | D6: =#REF! -> #REF! | E6: =IF(D6=0,0,E5+D6-C6) -> #REF!
A7: FÉVRIER | C7: =#REF! -> #REF! | D7: =#REF! -> #REF! | E7: =IF(D7=0,0,E6+D7-C7) -> #REF!
A8: MARS | C8: =#REF! -> #REF! | D8: =#REF! -> #REF! | E8: =IF(D8=0,0,E7+D8-C8) -> #REF!
A9: AVRIL | C9: =#REF! -> #REF! | D9: =#REF! -> #REF! | E9: =IF(D9=0,0,E8+D9-C9) -> #REF!
A10: MAI | C10: =#REF! -> #REF! | D10: =#REF! -> #REF! | E10: =IF(D10=0,0,E9+D10-C10) -> #REF!
A11: JUIN | C11: =#REF! -> #REF! | D11: =#REF! -> #REF! | E11: =IF(D11=0,0,E10+D11-C11) -> #REF!
A12: JUILLET | C12: =#REF! -> #REF! | D12: =#REF! -> #REF! | E12: =IF(D12=0,0,E11+D12-C12) -> #REF!
A13: AOÛT | C13: =#REF! -> #REF! | D13: =#REF! -> #REF! | E13: =IF(D13=0,0,E12+D13-C13) -> #REF!
A14: SEPTEMBRE | C14: =#REF! -> #REF! | D14: =#REF! -> #REF! | E14: =IF(D14=0,0,E13+D14-C14) -> #REF!
A15: OCTOBRE | C15: =#REF! -> #REF! | D15: =#REF! -> #REF! | E15: =IF(D15=0,0,E14+D15-C15) -> #REF!
A16: NOVEMBRE | C16: =#REF! -> #REF! | D16: =#REF! -> #REF! | E16: =IF(D16=0,0,E15+D16-C16) -> #REF!
A17: DÉCEMBRE | C17: =#REF! -> #REF! | D17: =#REF! -> #REF! | E17: =IF(D17=0,0,E16+D17-C17) -> #REF!
A19: TOTAL

Sheet HISTODEC22
A1: ASSOCIATION | B1: ASELBY
A2: ANNEE | B2: 2022
A3: 1 | B3: 2 | C3: 3 | D3: 4 | E3: 5 | F3: 6 | G3: 7 | H3: 8 | I3: 9 | J3: 10 | K3: 11 | L3: 12 | M3: 13 | N3: 14 | O3: 15 | P3: 16 | Q3: 17 | R3: 18 | S3: 19 | T3: 20 | U3: 21 | V3: 22 | W3: 23 | X3: 24 | Y3: 25 | Z3: 26 | AA3: 27 | AB3: 28 | AC3: 29 | AD3: 30 | AE3: 31 | AF3: 32 | AG3: 33 | AH3: 34 | AI3: 35 | AJ3: 36 | AK3: 37 | AL3: 38 | AM3: 39 | AN3: 40 | AO3: 41 | AP3: 42 | AQ3: 43 | AR3: 44 | AS3: 45 | AT3: 46 | AU3: 47 | AV3: 48 | AW3: 49 | AX3: 50 | AY3: 51 | AZ3: 52 | BA3: 53 | BB3: 54 | BC3: 55 | BD3: 56 | BE3: 57 | BF3: 58 | BG3: 59 | BH3: 60 | BI3: 61 | BJ3: 62 | BK3: 63 | BL3: 64 | BM3: 65 | BN3: 66
B4: TABLEAU DE BORD SAISIE DES DONNEES
A5: MATRICULE | B5: NOM ET PRENOM | C5: BONUS MALUS | D5: HISTORIQUE BANQUE | E5: HITORIQUE ESPECES | F5: HITORIQUE TONTINE | G5: PENALITE VERSEMENT ESPECES | H5: MODE PAIEMENT TONTINE | I5: NBRE DE LOT | J5: TONTINE 35 000 | K5: COMPLEMENT EPARGNE | L5: NBRE DE LOT | M5: TONTINE 75 000 | N5: NBRE DE LOT | O5: TONTINE 100 000 | P5: REMBOURSEMENT PETIT LOT T35 | Q5: REMBOURSEMENT PETIT LOT T75 | R5: REMBOURSEMENT PETIT LOT T100 | S5: REMBOURSEMENT PRÊT FONDS | T5: MODE PAIEMENT REMBOURSEMENT PRÊT FONDS | U5: MONTANT ENGAGEMENT | V5: SANCTION | W5: INSCRIPTION | X5: EPARGNE ASSURANCE | Y5: RECONSTITUTION FONDS | Z5: PRÊT FONDS | AA5: MODE PAIEMENT PRÊT | AB5: NUM CHEQUE | AC5: ACHAT LOT PRINCIPAL T30 | AD5: ACHAT LOT PRINCIPAL T75 | AE5: ACHAT LOT PRINCIPAL T100 | AF5: MODE PAIEMENT LOT PRINCIPAL | AG5: NUM CHEQUE | AH5: PENALITE VERSEMENT ESPECES | AI5: VENTE PETIT LOT T30 | AJ5: VENTE PETIT LOT T75 | AK5: VENTE PETIT LOT T100 | AL5: INTERET PETIT LOT T30 | AM5: INTERET PETIT LOT T75 | AN5: INTERET PETIT LOT T100 | AO5: NUM CHEQUE | AP5: MODE PAIEMENT PETEIT LOT | AQ5: PENELAITE RETARD TONTINE | AR5: PENELAITE ECHEC TONTINE | AS5: RESTE | AT5: MUTUELLE | AU5: REMBOURSEMENT TRANSPORT | AV5: RETRAIT PARTIEL FONDS | AW5: MONTANT T30 | AX5: MONTANT T75 | AY5: MONTANT T100 | AZ5: MONTANT CHEQUE | BA5: MONTANT ESPECES | BB5: CONTRIBUTION FOYER | BC5: AUTRES SOTIES | BD5: MONTANT CHEQUE EFFECTIF | BE5: NUMERO CHEQUE | BF5: INTERET PRÊT | BG5: NBRE MOIS | BH5: DEPENSE FONDS DE ROULEMENT | BI5: DEPENSE FRAIS EXCEPTIONNEL | BJ5: DEPENSE FONDS MUTUEL | BK5: DEPENSE COLLATION RECEPTION | BL5: PENALITE PRET FONDS | BM5: DEPENSE PENALITE VERSEMENT BANQUE | BN5: LIBELLE | BO5: COMPTE | BP5: MONTANT
A6: AS201648 | B6: =VLOOKUP(A6,[6]LISTADHERENT!A$5:H$60,3,0) -> ASELBY | C6: =D6+E6+F6-U6-BB6 -> 0 | D6: =VLOOKUP(A6,[7]HISTOBQUEDEC22!$A$6:$G$36,3,0) -> 100000 | E6: =VLOOKUP(A6,[7]HISTOBQUEDEC22!$A$6:$G$36,4,0) -> 0 | F6: =VLOOKUP(A6,[7]HISTOBQUEDEC22!$A$6:$G$36,5,0) -> 0 | G6: =IF(H6="ESPECES",3000,0) -> 0 | H6: =IF($D6<>0,"BANQUE",IF($E6<>0,"ESPECES","ECHEC")) -> BANQUE | J6: =IF($D6<>0,I6*30000,IF($E6<>0,I6*30000,0)) -> 0 | M6: =IF($D6<>0,L6*75000,IF($E6<>0,L6*75000,0)) -> 0 | N6: 1 | O6: =IF($D6<>0,N6*100000,IF($E6<>0,N6*100000,0)) -> 100000 | R6: =VLOOKUP(A6,[8]TONTDEC22!$A$6:$P$21,10,0) -> 0 | U6: =G6+S6++R6+P6+O6+M6+K6+J6+Q6+V6+W6 -> 100000 | AE6: 100000 | AF6: BANQUE | AQ6: =IF(H6="ECHEC",((J6+M6+O6)*20/100),0) -> 0 | AR6: =IF(H6="ECHEC",((J6+M6+O6)*20/100),0) -> 0 | AW6: =IF(AC6=0,AI6,(1*23000*13)+(1000+AI6)-AC6) -> 0 | AX6: =IF(AD6=0,AJ6,(1*75000*16)+(AJ6)-AD6) -> 0 | AY6: =IF(AE6=0,AK6,(1*100000*13)+(AK6)-AE6) -> 1200000 | AZ6: =SUM(AV6:AY6)-BF6+Z6-F6+BH6+BI6+BJ6+BK6 -> 1206000 | BD6: =IF(AZ6=0,(AZ6-BA6-BC6),(AZ6-BA6-BB6-BC6)) -> 1206000 | BF6: =Z6*1/100*BG6 -> 0 | BG6: 0 | BH6: =BP16 -> 6000 | BI6: =BP28 -> 0 | BJ6: =BP33 -> 0 | BM6: =BP22 -> 0 | BN6: ACHAT FOURNITURE | BO6: FONDS DE ROULEMENT
A7: AS201602 | B7: =VLOOKUP(A7,[6]LISTADHERENT!A$5:H$60,3,0) -> BOUTCHOUANG WILLIAM | C7: =D7+E7+F7-U7-BB7 -> 0 | D7: =VLOOKUP(A7,[7]HISTOBQUEDEC22!$A$6:$G$36,3,0) -> 105000 | E7: =VLOOKUP(A7,[7]HISTOBQUEDEC22!$A$6:$G$36,4,0) -> 0 | F7: =VLOOKUP(A7,[7]HISTOBQUEDEC22!$A$6:$G$36,5,0) -> 0 | G7: =IF(H7="ESPECES",3000,0) -> 0 | H7: =IF($D7<>0,"BANQUE",IF($E7<>0,"ESPECES","ECHEC")) -> BANQUE | I7: 1 | J7: =IF($D7<>0,I7*30000,IF($E7<>0,I7*30000,0)) -> 30000 | L7: 1 | M7: =IF($D7<>0,L7*75000,IF($E7<>0,L7*75000,0)) -> 75000 | O7: =IF($D7<>0,N7*100000,IF($E7<>0,N7*100000,0)) -> 0 | P7: =VLOOKUP(A7,[9]TONTDEC22!$A$6:$R$31,12,0) -> 0 | U7: =G7+S7++R7+P7+O7+M7+K7+J7+Q7+V7+W7 -> 105000 | Z7: 500000 | AA7: BANQUE | AQ7: =IF(H7="ECHEC",((J7+M7+O7)*20/100),0) -> 0 | AR7: =IF(H7="ECHEC",((J7+M7+O7)*20/100),0) -> 0 | AS7: =IF(H7="ECHEC",0,(J7+K7-23000)) -> 7000 | AT7: 20000 | AW7: =IF(AC7=0,AI7,(1*23000*13)+(1000+AI7)-AC7) -> 0 | AX7: =IF(AD7=0,AJ7,(1*75000*16)+(AJ7)-AD7) -> 0 | AY7: =IF(AE7=0,AK7,(1*100000*13)+(AK7)-AE7) -> 0 | AZ7: =SUM(AV7:AY7)-BF7+Z7-F7+BH7+BI7+BJ7+BK7 -> 490000 | BD7: =IF(AZ7=0,(AZ7-BA7-BC7),(AZ7-BA7-BB7-BC7)) -> 490000 | BF7: =Z7*1/100*BG7 -> 10000 | BG7: 2 | BN7: COMMUNICATION | BO7: FONDS DE ROULEMENT
A8: AS201604 | B8: =VLOOKUP(A8,[6]LISTADHERENT!A$5:H$60,3,0) -> DJOMO JEAN PAUL | C8: =D8+E8+F8-U8-BB8 -> 0 | D8: =VLOOKUP(A8,[7]HISTOBQUEDEC22!$A$6:$G$36,3,0) -> 1105000 | E8: =VLOOKUP(A8,[7]HISTOBQUEDEC22!$A$6:$G$36,4,0) -> 0 | F8: =VLOOKUP(A8,[7]HISTOBQUEDEC22!$A$6:$G$36,5,0) -> 0 | G8: =IF(H8="ESPECES",3000,0) -> 0 | H8: =IF($D8<>0,"BANQUE",IF($E8<>0,"ESPECES","ECHEC")) -> BANQUE | I8: 1 | J8: =IF($D8<>0,I8*30000,IF($E8<>0,I8*30000,0)) -> 30000 | L8: 1 | M8: =IF($D8<>0,L8*75000,IF($E8<>0,L8*75000,0)) -> 75000 | O8: =IF($D8<>0,N8*100000,IF($E8<>0,N8*100000,0)) -> 0 | P8: =VLOOKUP(A8,[9]TONTDEC22!$A$6:$R$31,12,0) -> 0 | Q8: =VLOOKUP(A8,[10]TONTDEC22!$A$6:$P$21,10,0) -> 0 | S8: =775000+130000+95000 -> 1000000 | T8: BANQUE | U8: =G8+S8++R8+P8+O8+M8+K8+J8+Q8+V8+W8 -> 1105000 | Z8: 1000000 | AA8: BANQUE | AQ8: =IF(H8="ECHEC",((J8+M8+O8)*20/100),0) -> 0 | AR8: =IF(H8="ECHEC",((J8+M8+O8)*20/100),0) -> 0 | AS8: =IF(H8="ECHEC",0,(J8+K8-23000)) -> 7000 | AT8: 20000 | AW8: =IF(AC8=0,AI8,(1*23000*13)+(1000+AI8)-AC8) -> 0 | AX8: =IF(AD8=0,AJ8,(1*75000*16)+(AJ8)-AD8) -> 0 | AY8: =IF(AE8=0,AK8,(1*100000*13)+(AK8)-AE8) -> 0 | AZ8: =SUM(AV8:AY8)-BF8+Z8-F8+BH8+BI8+BJ8+BK8 -> 880000 | BD8: =IF(AZ8=0,(AZ8-BA8-BC8),(AZ8-BA8-BB8-BC8)) -> 880000 | BF8: =Z8*1/100*BG8 -> 120000 | BG8: 12 | BN8: COMMISSION | BO8: FONDS DE ROULEMENT
A9: AS201654 | B9: =VLOOKUP(A9,[6]LISTADHERENT!A$5:H$60,3,0) -> DJOMOU TCHANDA | C9: =D9+E9+F9-U9-BB9 -> 0 | D9: =VLOOKUP(A9,[7]HISTOBQUEDEC22!$A$6:$G$36,3,0) -> 30000 | E9: =VLOOKUP(A9,[7]HISTOBQUEDEC22!$A$6:$G$36,4,0) -> 0 | F9: =VLOOKUP(A9,[7]HISTOBQUEDEC22!$A$6:$G$36,5,0) -> 0 | G9: =IF(H9="ESPECES",3000,0) -> 0 | H9: =IF($D9<>0,"BANQUE",IF($E9<>0,"ESPECES","ECHEC")) -> BANQUE | I9: 1 | J9: =IF($D9<>0,I9*30000,IF($E9<>0,I9*30000,0)) -> 30000 | M9: =IF($D9<>0,L9*75000,IF($E9<>0,L9*75000,0)) -> 0 | O9: =IF($D9<>0,N9*100000,IF($E9<>0,N9*100000,0)) -> 0 | P9: =VLOOKUP(A9,[9]TONTDEC22!$A$6:$R$31,12,0) -> 0 | U9: =G9+S9++R9+P9+O9+M9+K9+J9+Q9+V9+W9 -> 30000 | AQ9: =IF(H9="ECHEC",((J9+M9+O9)*20/100),0) -> 0 | AR9: =IF(H9="ECHEC",((J9+M9+O9)*20/100),0) -> 0 | AS9: =IF(H9="ECHEC",0,(J9+K9-23000)) -> 7000 | AT9: 20000 | AW9: =IF(AC9=0,AI9,(1*23000*13)+(1000+AI9)-AC9) -> 0 | AX9: =IF(AD9=0,AJ9,(1*75000*16)+(AJ9)-AD9) -> 0 | AY9: =IF(AE9=0,AK9,(1*100000*13)+(AK9)-AE9) -> 0 | AZ9: =SUM(AV9:AY9)-BF9+Z9-F9+BH9+BI9+BJ9+BK9 -> 0 | BD9: =IF(AZ9=0,(AZ9-BA9-BC9),(AZ9-BA9-BB9-BC9)) -> 0 | BF9: =Z9*1/100*BG9 -> 0 | BG9: 0 | BN9: AIDE UEEB ET CONT FEMME | BO9: FONDS DE ROULEMENT
A10: AS201605 | B10: =VLOOKUP(A10,[6]LISTADHERENT!A$5:H$60,3,0) -> DJOUKWE NANGUEN GUY BLAISE | C10: =D10+E10+F10-U10-BB10 -> 0 | D10: =VLOOKUP(A10,[7]HISTOBQUEDEC22!$A$6:$G$36,3,0) -> 1105000 | E10: =VLOOKUP(A10,[7]HISTOBQUEDEC22!$A$6:$G$36,4,0) -> 0 | F10: =VLOOKUP(A10,[7]HISTOBQUEDEC22!$A$6:$G$36,5,0) -> 0 | G10: =IF(H10="ESPECES",3000,0) -> 0 | H10: =IF($D10<>0,"BANQUE",IF($E10<>0,"ESPECES","ECHEC")) -> BANQUE | I10: 1 | J10: =IF($D10<>0,I10*30000,IF($E10<>0,I10*30000,0)) -> 30000 | L10: 1 | M10: =IF($D10<>0,L10*75000,IF($E10<>0,L10*75000,0)) -> 75000 | O10: =IF($D10<>0,N10*100000,IF($E10<>0,N10*100000,0)) -> 0 | P10: =VLOOKUP(A10,[9]TONTDEC22!$A$6:$R$31,12,0) -> 0 | Q10: =VLOOKUP(A10,[10]TONTDEC22!$A$6:$P$21,10,0) -> 0 | S10: =900000+100000 -> 1000000 | T10: BANQUE | U10: =G10+S10++R10+P10+O10+M10+K10+J10+Q10+V10+W10 -> 1105000 | Z10: 1000000 | AA10: BANQUE | AQ10: =IF(H10="ECHEC",((J10+M10+O10)*20/100),0) -> 0 | AR10: =IF(H10="ECHEC",((J10+M10+O10)*20/100),0) -> 0 | AS10: =IF(H10="ECHEC",0,(J10+K10-23000)) -> 7000 | AT10: 20000 | AW10: =IF(AC10=0,AI10,(1*23000*13)+(1000+AI10)-AC10) -> 0 | AX10: =IF(AD10=0,AJ10,(1*75000*16)+(AJ10)-AD10) -> 0 | AY10: =IF(AE10=0,AK10,(1*100000*13)+(AK10)-AE10) -> 0 | AZ10: =SUM(AV10:AY10)-BF10+Z10-F10+BH10+BI10+BJ10+BK10 -> 980000 | BD10: =IF(AZ10=0,(AZ10-BA10-BC10),(AZ10-BA10-BB10-BC10)) -> 980000 | BF10: =Z10*1/100*BG10 -> 20000 | BG10: 2 | BN10: CREDIT TELEPHONE | BO10: FONDS DE ROULEMENT
A11: AS201608 | B11: =VLOOKUP(A11,[6]LISTADHERENT!A$5:H$60,3,0) -> DJUOMBESSY ANTOINE | C11: =D11+E11+F11-U11-BB11 -> 0 | D11: =VLOOKUP(A11,[7]HISTOBQUEDEC22!$A$6:$G$36,3,0) -> 215000 | E11: =VLOOKUP(A11,[7]HISTOBQUEDEC22!$A$6:$G$36,4,0) -> 0 | F11: =VLOOKUP(A11,[7]HISTOBQUEDEC22!$A$6:$G$36,5,0) -> 0 | G11: =IF(H11="ESPECES",3000,0) -> 0 | H11: =IF($D11<>0,"BANQUE",IF($E11<>0,"ESPECES","ECHEC")) -> BANQUE | I11: 1 | J11: =IF($D11<>0,I11*30000,IF($E11<>0,I11*30000,0)) -> 30000 | K11: 1000 | L11: 1 | M11: =IF($D11<>0,L11*75000,IF($E11<>0,L11*75000,0)) -> 75000 | N11: 1 | O11: =IF($D11<>0,N11*100000,IF($E11<>0,N11*100000,0)) -> 100000 | P11: =VLOOKUP(A11,[9]TONTDEC22!$A$6:$R$31,12,0) -> 0 | Q11: =VLOOKUP(A11,[10]TONTDEC22!$A$6:$P$21,10,0) -> 0 | R11: =VLOOKUP(A11,[8]TONTDEC22!$A$6:$P$21,10,0) -> 0 | U11: =G11+S11++R11+P11+O11+M11+K11+J11+Q11+V11+W11 -> 206000 | Z11: 1000000 | AA11: BANQUE | AQ11: =IF(H11="ECHEC",((J11+M11+O11)*20/100),0) -> 0 | AR11: =IF(H11="ECHEC",((J11+M11+O11)*20/100),0) -> 0 | AS11: =IF(H11="ECHEC",0,(J11+K11-23000)) -> 8000 | AT11: 20000 | AW11: =IF(AC11=0,AI11,(1*23000*13)+(1000+AI11)-AC11) -> 0 | AX11: =IF(AD11=0,AJ11,(1*75000*16)+(AJ11)-AD11) -> 0 | AY11: =IF(AE11=0,AK11,(1*100000*13)+(AK11)-AE11) -> 0 | AZ11: =SUM(AV11:AY11)-BF11+Z11-F11+BH11+BI11+BJ11+BK11 -> 940000 | BB11: 9000 | BD11: =IF(AZ11=0,(AZ11-BA11-BC11),(AZ11-BA11-BB11-BC11)) -> 931000 | BF11: =Z11*1/100*BG11 -> 60000 | BG11: 6 | BN11: PRODUCTION RAPPORT | BO11: FONDS DE ROULEMENT
A12: AS201651 | B12: =VLOOKUP(A12,[6]LISTADHERENT!A$5:H$60,3,0) -> DOMOU FABIEN | C12: =D12+E12+F12-U12-BB12 -> 0 | D12: =VLOOKUP(A12,[7]HISTOBQUEDEC22!$A$6:$G$36,3,0) -> 1035000 | E12: =VLOOKUP(A12,[7]HISTOBQUEDEC22!$A$6:$G$36,4,0) -> 0 | F12: =VLOOKUP(A12,[7]HISTOBQUEDEC22!$A$6:$G$36,5,0) -> 0 | G12: =IF(H12="ESPECES",3000,0) -> 0 | H12: =IF($D12<>0,"BANQUE",IF($E12<>0,"ESPECES","ECHEC")) -> BANQUE | I12: 1 | J12: =IF($D12<>0,I12*30000,IF($E12<>0,I12*30000,0)) -> 30000 | K12: 5000 | M12: =IF($D12<>0,L12*75000,IF($E12<>0,L12*75000,0)) -> 0 | O12: =IF($D12<>0,N12*100000,IF($E12<>0,N12*100000,0)) -> 0 | P12: =VLOOKUP(A12,[9]TONTDEC22!$A$6:$R$31,12,0) -> 0 | S12: 1000000 | T12: BANQUE | U12: =G12+S12++R12+P12+O12+M12+K12+J12+Q12+V12+W12 -> 1035000 | Z12: 1000000 | AA12: BANQUE | AQ12: =IF(H12="ECHEC",((J12+M12+O12)*20/100),0) -> 0 | AR12: =IF(H12="ECHEC",((J12+M12+O12)*20/100),0) -> 0 | AS12: =IF(H12="ECHEC",0,(J12+K12-23000)) -> 12000 | AT12: 20000 | AW12: =IF(AC12=0,AI12,(1*23000*13)+(1000+AI12)-AC12) -> 0 | AX12: =IF(AD12=0,AJ12,(1*75000*16)+(AJ12)-AD12) -> 0 | AY12: =IF(AE12=0,AK12,(1*100000*13)+(AK12)-AE12) -> 0 | AZ12: =SUM(AV12:AY12)-BF12+Z12-F12+BH12+BI12+BJ12+BK12 -> 880000 | BD12: =IF(AZ12=0,(AZ12-BA12-BC12),(AZ12-BA12-BB12-BC12)) -> 880000 | BF12: =Z12*1/100*BG12 -> 120000 | BG12: 12 | BN12: ACHAT SOURIS ET PHOTOCOPIE | BO12: FONDS DE ROULEMENT
A13: AS201609 | B13: =VLOOKUP(A13,[6]LISTADHERENT!A$5:H$60,3,0) -> DONHOU DAVID | C13: =D13+E13+F13-U13-BB13 -> 0 | D13: =VLOOKUP(A13,[7]HISTOBQUEDEC22!$A$6:$G$36,3,0) -> 35000 | E13: =VLOOKUP(A13,[7]HISTOBQUEDEC22!$A$6:$G$36,4,0) -> 0 | F13: =VLOOKUP(A13,[7]HISTOBQUEDEC22!$A$6:$G$36,5,0) -> 0 | G13: =IF(H13="ESPECES",3000,0) -> 0 | H13: =IF($D13<>0,"BANQUE",IF($E13<>0,"ESPECES","ECHEC")) -> BANQUE | I13: 1 | J13: =IF($D13<>0,I13*30000,IF($E13<>0,I13*30000,0)) -> 30000 | K13: 5000 | M13: =IF($D13<>0,L13*75000,IF($E13<>0,L13*75000,0)) -> 0 | O13: =IF($D13<>0,N13*100000,IF($E13<>0,N13*100000,0)) -> 0 | P13: =VLOOKUP(A13,[9]TONTDEC22!$A$6:$R$31,12,0) -> 0 | U13: =G13+S13++R13+P13+O13+M13+K13+J13+Q13+V13+W13 -> 35000 | AC13: 23000 | AF13: BANQUE | AQ13: =IF(H13="ECHEC",((J13+M13+O13)*20/100),0) -> 0 | AR13: =IF(H13="ECHEC",((J13+M13+O13)*20/100),0) -> 0 | AS13: =IF(H13="ECHEC",0,(J13+K13-23000)) -> 12000 | AT13: 20000 | AW13: =IF(AC13=0,AI13,(1*23000*13)+(1000+AI13)-AC13) -> 277000 | AX13: =IF(AD13=0,AJ13,(1*75000*16)+(AJ13)-AD13) -> 0 | AY13: =IF(AE13=0,AK13,(1*100000*13)+(AK13)-AE13) -> 0 | AZ13: =SUM(AV13:AY13)-BF13+Z13-F13+BH13+BI13+BJ13+BK13 -> 277000 | BD13: =IF(AZ13=0,(AZ13-BA13-BC13),(AZ13-BA13-BB13-BC13)) -> 277000 | BF13: =Z13*1/100*BG13 -> 0 | BG13: 0 | BN13: TAXI BANQUE | BO13: FONDS DE ROULEMENT | BP13: 6000
A14: AS201610 | B14: =VLOOKUP(A14,[6]LISTADHERENT!A$5:H$60,3,0) -> FOTSO THOMAS | C14: =D14+E14+F14-U14-BB14 -> 0 | D14: =VLOOKUP(A14,[7]HISTOBQUEDEC22!$A$6:$G$36,3,0) -> 0 | E14: =VLOOKUP(A14,[7]HISTOBQUEDEC22!$A$6:$G$36,4,0) -> 0 | F14: =VLOOKUP(A14,[7]HISTOBQUEDEC22!$A$6:$G$36,5,0) -> 0 | G14: =IF(H14="ESPECES",3000,0) -> 0 | H14: =IF($D14<>0,"BANQUE",IF($E14<>0,"ESPECES","ECHEC")) -> ECHEC | J14: =IF($D14<>0,I14*30000,IF($E14<>0,I14*30000,0)) -> 0 | M14: =IF($D14<>0,L14*75000,IF($E14<>0,L14*75000,0)) -> 0 | O14: =IF($D14<>0,N14*100000,IF($E14<>0,N14*100000,0)) -> 0 | U14: =G14+S14++R14+P14+O14+M14+K14+J14+Q14+V14+W14 -> 0 | AQ14: =IF(H14="ECHEC",((J14+M14+O14)*20/100),0) -> 0 | AR14: =IF(H14="ECHEC",((J14+M14+O14)*20/100),0) -> 0 | AS14: =IF(H14="ECHEC",0,(J14+K14-23000)) -> 0 | AW14: =IF(AC14=0,AI14,(1*23000*13)+(1000+AI14)-AC14) -> 0 | AX14: =IF(AD14=0,AJ14,(1*75000*16)+(AJ14)-AD14) -> 0 | AY14: =IF(AE14=0,AK14,(1*100000*13)+(AK14)-AE14) -> 0 | AZ14: =SUM(AV14:AY14)-BF14+Z14-F14+BH14+BI14+BJ14+BK14 -> 0 | BD14: =IF(AZ14=0,(AZ14-BA14-BC14),(AZ14-BA14-BB14-BC14)) -> 0 | BF14: =Z14*1/100*BG14 -> 0 | BG14: 0 | BN14: CONFECTION CACHET | BO14: FONDS DE ROULEMENT
A15: AS201611 | B15: =VLOOKUP(A15,[6]LISTADHERENT!A$5:H$60,3,0) -> HENGUE PAUL OMER | C15: =D15+E15+F15-U15-BB15 -> 0 | D15: =VLOOKUP(A15,[7]HISTOBQUEDEC22!$A$6:$G$36,3,0) -> 105000 | E15: =VLOOKUP(A15,[7]HISTOBQUEDEC22!$A$6:$G$36,4,0) -> 0 | F15: =VLOOKUP(A15,[7]HISTOBQUEDEC22!$A$6:$G$36,5,0) -> 0 | G15: =IF(H15="ESPECES",3000,0) -> 0 | H15: =IF($D15<>0,"BANQUE",IF($E15<>0,"ESPECES","ECHEC")) -> BANQUE | I15: 1 | J15: =IF($D15<>0,I15*30000,IF($E15<>0,I15*30000,0)) -> 30000 | L15: 1 | M15: =IF($D15<>0,L15*75000,IF($E15<>0,L15*75000,0)) -> 75000 | O15: =IF($D15<>0,N15*100000,IF($E15<>0,N15*100000,0)) -> 0 | P15: =VLOOKUP(A15,[9]TONTDEC22!$A$6:$R$31,12,0) -> 0 | Q15: =VLOOKUP(A15,[10]TONTDEC22!$A$6:$P$21,10,0) -> 0 | U15: =G15+S15++R15+P15+O15+M15+K15+J15+Q15+V15+W15 -> 105000 | AD15: 75000 | AF15: BANQUE | AQ15: =IF(H15="ECHEC",((J15+M15+O15)*20/100),0) -> 0 | AR15: =IF(H15="ECHEC",((J15+M15+O15)*20/100),0) -> 0 | AS15: =IF(H15="ECHEC",0,(J15+K15-23000)) -> 7000 | AT15: 20000 | AW15: =IF(AC15=0,AI15,(1*23000*13)+(1000+AI15)-AC15) -> 0 | AX15: =IF(AD15=0,AJ15,(1*75000*16)+(AJ15)-AD15) -> 1125000 | AY15: =IF(AE15=0,AK15,(1*100000*13)+(AK15)-AE15) -> 0 | AZ15: =SUM(AV15:AY15)-BF15+Z15-F15+BH15+BI15+BJ15+BK15 -> 1125000 | BD15: =IF(AZ15=0,(AZ15-BA15-BC15),(AZ15-BA15-BB15-BC15)) -> 1125000 | BF15: =Z15*1/100*BG15 -> 0 | BG15: 0
A16: AS201613 | B16: =VLOOKUP(A16,[6]LISTADHERENT!A$5:H$60,3,0) -> HOTCHO BENJAMIN | C16: =D16+E16+F16-U16-BB16 -> 0 | D16: =VLOOKUP(A16,[7]HISTOBQUEDEC22!$A$6:$G$36,3,0) -> 1150000 | E16: =VLOOKUP(A16,[7]HISTOBQUEDEC22!$A$6:$G$36,4,0) -> 0 | F16: =VLOOKUP(A16,[7]HISTOBQUEDEC22!$A$6:$G$36,5,0) -> 0 | G16: =IF(H16="ESPECES",3000,0) -> 0 | H16: =IF($D16<>0,"BANQUE",IF($E16<>0,"ESPECES","ECHEC")) -> BANQUE | I16: 1 | J16: =IF($D16<>0,I16*30000,IF($E16<>0,I16*30000,0)) -> 30000 | K16: 45000 | L16: 1 | M16: =IF($D16<>0,L16*75000,IF($E16<>0,L16*75000,0)) -> 75000 | O16: =IF($D16<>0,N16*100000,IF($E16<>0,N16*100000,0)) -> 0 | P16: =VLOOKUP(A16,[9]TONTDEC22!$A$6:$R$31,12,0) -> 0 | Q16: =VLOOKUP(A16,[10]TONTDEC22!$A$6:$P$21,10,0) -> 0 | S16: 1000000 | T16: BANQUE | U16: =G16+S16++R16+P16+O16+M16+K16+J16+Q16+V16+W16 -> 1150000 | Z16: 1000000 | AA16: BANQUE | AQ16: =IF(H16="ECHEC",((J16+M16+O16)*20/100),0) -> 0 | AR16: =IF(H16="ECHEC",((J16+M16+O16)*20/100),0) -> 0 | AS16: =IF(H16="ECHEC",0,(J16+K16-23000)) -> 52000 | AT16: 20000 | AW16: =IF(AC16=0,AI16,(1*23000*13)+(1000+AI16)-AC16) -> 0 | AX16: =IF(AD16=0,AJ16,(1*75000*16)+(AJ16)-AD16) -> 0 | AY16: =IF(AE16=0,AK16,(1*100000*13)+(AK16)-AE16) -> 0 | AZ16: =SUM(AV16:AY16)-BF16+Z16-F16+BH16+BI16+BJ16+BK16 -> 880000 | BD16: =IF(AZ16=0,(AZ16-BA16-BC16),(AZ16-BA16-BB16-BC16)) -> 880000 | BF16: =Z16*1/100*BG16 -> 120000 | BG16: 12 | BN16: S/TOTAL | BP16: =SUM(BP6:BP15) -> 6000
A17: AS201617 | B17: =VLOOKUP(A17,[6]LISTADHERENT!A$5:H$60,3,0) -> KOUAMOU MOISE | C17: =D17+E17+F17-U17-BB17 -> 0 | D17: =VLOOKUP(A17,[7]HISTOBQUEDEC22!$A$6:$G$36,3,0) -> 1030000 | E17: =VLOOKUP(A17,[7]HISTOBQUEDEC22!$A$6:$G$36,4,0) -> 0 | F17: =VLOOKUP(A17,[7]HISTOBQUEDEC22!$A$6:$G$36,5,0) -> 0 | G17: =IF(H17="ESPECES",3000,0) -> 0 | H17: =IF($D17<>0,"BANQUE",IF($E17<>0,"ESPECES","ECHEC")) -> BANQUE | I17: 1 | J17: =IF($D17<>0,I17*30000,IF($E17<>0,I17*30000,0)) -> 30000 | M17: =IF($D17<>0,L17*75000,IF($E17<>0,L17*75000,0)) -> 0 | N17: 3 | O17: =IF($D17<>0,N17*100000,IF($E17<>0,N17*100000,0)) -> 300000 | P17: =VLOOKUP(A17,[9]TONTDEC22!$A$6:$R$31,12,0) -> 0 | R17: =VLOOKUP(A17,[8]TONTDEC22!$A$6:$P$21,10,0) -> 0 | S17: 700000 | T17: BANQUE | U17: =G17+S17++R17+P17+O17+M17+K17+J17+Q17+V17+W17 -> 1030000 | AQ17: =IF(H17="ECHEC",((J17+M17+O17)*20/100),0) -> 0 | AR17: =IF(H17="ECHEC",((J17+M17+O17)*20/100),0) -> 0 | AS17: =IF(H17="ECHEC",0,(J17+K17-23000)) -> 7000 | AT17: 20000 | AW17: =IF(AC17=0,AI17,(1*23000*13)+(1000+AI17)-AC17) -> 0 | AX17: =IF(AD17=0,AJ17,(1*75000*16)+(AJ17)-AD17) -> 0 | AY17: =IF(AE17=0,AK17,(1*100000*13)+(AK17)-AE17) -> 0 | AZ17: =SUM(AV17:AY17)-BF17+Z17-F17+BH17+BI17+BJ17+BK17 -> 0 | BD17: =IF(AZ17=0,(AZ17-BA17-BC17),(AZ17-BA17-BB17-BC17)) -> 0 | BF17: =Z17*1/100*BG17 -> 0 | BG17: 0
A18: AS201619 | B18: =VLOOKUP(A18,[6]LISTADHERENT!A$5:H$60,3,0) -> KOUATCHO MESSACK | C18: =D18+E18+F18-U18-BB18 -> 0 | D18: =VLOOKUP(A18,[7]HISTOBQUEDEC22!$A$6:$G$36,3,0) -> 1205000 | E18: =VLOOKUP(A18,[7]HISTOBQUEDEC22!$A$6:$G$36,4,0) -> 0 | F18: =VLOOKUP(A18,[7]HISTOBQUEDEC22!$A$6:$G$36,5,0) -> 0 | G18: =IF(H18="ESPECES",3000,0) -> 0 | H18: =IF($D18<>0,"BANQUE",IF($E18<>0,"ESPECES","ECHEC")) -> BANQUE | I18: 1 | J18: =IF($D18<>0,I18*30000,IF($E18<>0,I18*30000,0)) -> 30000 | L18: 1 | M18: =IF($D18<>0,L18*75000,IF($E18<>0,L18*75000,0)) -> 75000 | N18: 1 | O18: =IF($D18<>0,N18*100000,IF($E18<>0,N18*100000,0)) -> 100000 | P18: =VLOOKUP(A18,[9]TONTDEC22!$A$6:$R$31,12,0) -> 0 | Q18: =VLOOKUP(A18,[10]TONTDEC22!$A$6:$P$21,10,0) -> 0 | R18: =VLOOKUP(A18,[8]TONTDEC22!$A$6:$P$21,10,0) -> 0 | S18: 1000000 | T18: BANQUE | U18: =G18+S18++R18+P18+O18+M18+K18+J18+Q18+V18+W18 -> 1205000 | Z18: 1000000 | AA18: BANQUE | AQ18: =IF(H18="ECHEC",((J18+M18+O18)*20/100),0) -> 0 | AR18: =IF(H18="ECHEC",((J18+M18+O18)*20/100),0) -> 0 | AS18: =IF(H18="ECHEC",0,(J18+K18-23000)) -> 7000 | AT18: 20000 | AW18: =IF(AC18=0,AI18,(1*23000*13)+(1000+AI18)-AC18) -> 0 | AX18: =IF(AD18=0,AJ18,(1*75000*16)+(AJ18)-AD18) -> 0 | AY18: =IF(AE18=0,AK18,(1*100000*13)+(AK18)-AE18) -> 0 | AZ18: =SUM(AV18:AY18)-BF18+Z18-F18+BH18+BI18+BJ18+BK18 -> 940000 | BD18: =IF(AZ18=0,(AZ18-BA18-BC18),(AZ18-BA18-BB18-BC18)) -> 940000 | BF18: =Z18*1/100*BG18 -> 60000 | BG18: 6 | BN18: GRATIFICATION BUREAU 2021 | BO18: PENALITE VERSEMENT ESPECES
A19: AS201620 | B19: =VLOOKUP(A19,[6]LISTADHERENT!A$5:H$60,3,0) -> LOWE JEAN | C19: =D19+E19+F19-U19-BB19 -> 0 | D19: =VLOOKUP(A19,[7]HISTOBQUEDEC22!$A$6:$G$36,3,0) -> 1030000 | E19: =VLOOKUP(A19,[7]HISTOBQUEDEC22!$A$6:$G$36,4,0) -> 0 | F19: =VLOOKUP(A19,[7]HISTOBQUEDEC22!$A$6:$G$36,5,0) -> 0 | G19: =IF(H19="ESPECES",3000,0) -> 0 | H19: =IF($D19<>0,"BANQUE",IF($E19<>0,"ESPECES","ECHEC")) -> BANQUE | I19: 1 | J19: =IF($D19<>0,I19*30000,IF($E19<>0,I19*30000,0)) -> 30000 | M19: =IF($D19<>0,L19*75000,IF($E19<>0,L19*75000,0)) -> 0 | O19: =IF($D19<>0,N19*100000,IF($E19<>0,N19*100000,0)) -> 0 | P19: =VLOOKUP(A19,[9]TONTDEC22!$A$6:$R$31,12,0) -> 0 | S19: 1000000 | T19: BANQUE | U19: =G19+S19++R19+P19+O19+M19+K19+J19+Q19+V19+W19 -> 1030000 | Z19: 1000000 | AA19: BANQUE | AQ19: =IF(H19="ECHEC",((J19+M19+O19)*20/100),0) -> 0 | AR19: =IF(H19="ECHEC",((J19+M19+O19)*20/100),0) -> 0 | AS19: =IF(H19="ECHEC",0,(J19+K19-23000)) -> 7000 | AT19: 20000 | AW19: =IF(AC19=0,AI19,(1*23000*13)+(1000+AI19)-AC19) -> 0 | AX19: =IF(AD19=0,AJ19,(1*75000*16)+(AJ19)-AD19) -> 0 | AY19: =IF(AE19=0,AK19,(1*100000*13)+(AK19)-AE19) -> 0 | AZ19: =SUM(AV19:AY19)-BF19+Z19-F19+BH19+BI19+BJ19+BK19 -> 960000 | BD19: =IF(AZ19=0,(AZ19-BA19-BC19),(AZ19-BA19-BB19-BC19)) -> 960000 | BF19: =Z19*1/100*BG19 -> 40000 | BG19: 4 | BN19: ACHAT LAPTOP | BO19: PENALITE VERSEMENT ESPECES
A20: AS201649 | B20: =VLOOKUP(A20,[6]LISTADHERENT!A$5:H$60,3,0) -> MBOGNING TUGMA GUY | C20: =D20+E20+F20-U20-BB20 -> 0 | D20: =VLOOKUP(A20,[7]HISTOBQUEDEC22!$A$6:$G$36,3,0) -> 1627500 | E20: =VLOOKUP(A20,[7]HISTOBQUEDEC22!$A$6:$G$36,4,0) -> 0 | F20: =VLOOKUP(A20,[7]HISTOBQUEDEC22!$A$6:$G$36,5,0) -> 0 | G20: =IF(H20="ESPECES",3000,0) -> 0 | H20: =IF($D20<>0,"BANQUE",IF($E20<>0,"ESPECES","ECHEC")) -> BANQUE | I20: 1 | J20: =IF($D20<>0,I20*30000,IF($E20<>0,I20*30000,0)) -> 30000 | L20: 3 | M20: =IF($D20<>0,L20*75000,IF($E20<>0,L20*75000,0)) -> 225000 | N20: 2 | O20: =IF($D20<>0,N20*100000,IF($E20<>0,N20*100000,0)) -> 200000 | P20: =VLOOKUP(A20,[9]TONTDEC22!$A$6:$R$31,12,0) -> 0 | Q20: =VLOOKUP(A20,[10]TONTDEC22!$A$6:$P$21,10,0) -> 0 | R20: =VLOOKUP(A20,[8]TONTDEC22!$A$6:$P$21,10,0) -> 172500 | S20: 1000000 | T20: BANQUE | U20: =G20+S20++R20+P20+O20+M20+K20+J20+Q20+V20+W20 -> 1627500 | Z20: 1000000 | AA20: BANQUE | AP20: BANQUE | AQ20: =IF(H20="ECHEC",((J20+M20+O20)*20/100),0) -> 0 | AR20: =IF(H20="ECHEC",((J20+M20+O20)*20/100),0) -> 0 | AS20: =IF(H20="ECHEC",0,(J20+K20-23000)) -> 7000 | AT20: 20000 | AW20: =IF(AC20=0,AI20,(1*23000*13)+(1000+AI20)-AC20) -> 0 | AX20: =IF(AD20=0,AJ20,(1*75000*16)+(AJ20)-AD20) -> 0 | AY20: =IF(AE20=0,AK20,(1*100000*13)+(AK20)-AE20) -> 0 | AZ20: =SUM(AV20:AY20)-BF20+Z20-F20+BH20+BI20+BJ20+BK20 -> 940000 | BD20: =IF(AZ20=0,(AZ20-BA20-BC20),(AZ20-BA20-BB20-BC20)) -> 940000 | BF20: =Z20*1/100*BG20 -> 60000 | BG20: 6
A21: AS201639 | B21: =VLOOKUP(A21,[6]LISTADHERENT!A$5:H$60,3,0) -> NANGUEN MARTIN | C21: =D21+E21+F21-U21-BB21 -> 0 | D21: =VLOOKUP(A21,[7]HISTOBQUEDEC22!$A$6:$G$36,3,0) -> 30000 | E21: =VLOOKUP(A21,[7]HISTOBQUEDEC22!$A$6:$G$36,4,0) -> 0 | F21: =VLOOKUP(A21,[7]HISTOBQUEDEC22!$A$6:$G$36,5,0) -> 0 | G21: =IF(H21="ESPECES",3000,0) -> 0 | H21: =IF($D21<>0,"BANQUE",IF($E21<>0,"ESPECES","ECHEC")) -> BANQUE | I21: 1 | J21: =IF($D21<>0,I21*30000,IF($E21<>0,I21*30000,0)) -> 30000 | M21: =IF($D21<>0,L21*75000,IF($E21<>0,L21*75000,0)) -> 0 | O21: =IF($D21<>0,N21*100000,IF($E21<>0,N21*100000,0)) -> 0 | P21: =VLOOKUP(A21,[9]TONTDEC22!$A$6:$R$31,12,0) -> 0 | U21: =G21+S21++R21+P21+O21+M21+K21+J21+Q21+V21+W21 -> 30000 | Z21: 500000 | AA21: BANQUE | AQ21: =IF(H21="ECHEC",((J21+M21+O21)*20/100),0) -> 0 | AR21: =IF(H21="ECHEC",((J21+M21+O21)*20/100),0) -> 0 | AS21: =IF(H21="ECHEC",0,(J21+K21-23000)) -> 7000 | AT21: 20000 | AW21: =IF(AC21=0,AI21,(1*23000*13)+(1000+AI21)-AC21) -> 0 | AX21: =IF(AD21=0,AJ21,(1*75000*16)+(AJ21)-AD21) -> 0 | AY21: =IF(AE21=0,AK21,(1*100000*13)+(AK21)-AE21) -> 0 | AZ21: =SUM(AV21:AY21)-BF21+Z21-F21+BH21+BI21+BJ21+BK21 -> 510000 | BD21: =IF(AZ21=0,(AZ21-BA21-BC21),(AZ21-BA21-BB21-BC21)) -> 510000 | BF21: =Z21*1/100*BG21 -> 60000 | BG21: 12 | BK21: 70000
A22: AS201621 | B22: =VLOOKUP(A22,[6]LISTADHERENT!A$5:H$60,3,0) -> NANKAM APPOLINAIRE | C22: =D22+E22+F22-U22-BB22 -> 0 | D22: =VLOOKUP(A22,[7]HISTOBQUEDEC22!$A$6:$G$36,3,0) -> 1105000 | E22: =VLOOKUP(A22,[7]HISTOBQUEDEC22!$A$6:$G$36,4,0) -> 0 | F22: =VLOOKUP(A22,[7]HISTOBQUEDEC22!$A$6:$G$36,5,0) -> 0 | G22: =IF(H22="ESPECES",3000,0) -> 0 | H22: =IF($D22<>0,"BANQUE",IF($E22<>0,"ESPECES","ECHEC")) -> BANQUE | I22: 1 | J22: =IF($D22<>0,I22*30000,IF($E22<>0,I22*30000,0)) -> 30000 | L22: 1 | M22: =IF($D22<>0,L22*75000,IF($E22<>0,L22*75000,0)) -> 75000 | O22: =IF($D22<>0,N22*100000,IF($E22<>0,N22*100000,0)) -> 0 | P22: =VLOOKUP(A22,[9]TONTDEC22!$A$6:$R$31,12,0) -> 0 | Q22: =VLOOKUP(A22,[10]TONTDEC22!$A$6:$P$21,10,0) -> 0 | S22: 1000000 | T22: BANQUE | U22: =G22+S22++R22+P22+O22+M22+K22+J22+Q22+V22+W22 -> 1105000 | Z22: 1000000 | AA22: BANQUE | AQ22: =IF(H22="ECHEC",((J22+M22+O22)*20/100),0) -> 0 | AR22: =IF(H22="ECHEC",((J22+M22+O22)*20/100),0) -> 0 | AS22: =IF(H22="ECHEC",0,(J22+K22-23000)) -> 7000 | AT22: 20000 | AW22: =IF(AC22=0,AI22,(1*23000*13)+(1000+AI22)-AC22) -> 0 | AX22: =IF(AD22=0,AJ22,(1*75000*16)+(AJ22)-AD22) -> 0 | AY22: =IF(AE22=0,AK22,(1*100000*13)+(AK22)-AE22) -> 0 | AZ22: =SUM(AV22:AY22)-BF22+Z22-F22+BH22+BI22+BJ22+BK22 -> 880000 | BD22: =IF(AZ22=0,(AZ22-BA22-BC22),(AZ22-BA22-BB22-BC22))+71000 -> 951000 | BF22: =Z22*1/100*BG22 -> 120000 | BG22: 12 | BN22: S/TOTAL | BP22: =SUM(BP18:BP21) -> 0
A23: AS201622 | B23: =VLOOKUP(A23,[6]LISTADHERENT!A$5:H$60,3,0) -> NDJOMO ETIENNE | C23: =D23+E23+F23-U23-BB23 -> 0 | D23: =VLOOKUP(A23,[7]HISTOBQUEDEC22!$A$6:$G$36,3,0) -> 680000 | E23: =VLOOKUP(A23,[7]HISTOBQUEDEC22!$A$6:$G$36,4,0) -> 101000 | F23: =VLOOKUP(A23,[7]HISTOBQUEDEC22!$A$6:$G$36,5,0) -> 0 | G23: =IF(H23="ESPECES",3000,0) -> 0 | H23: =IF($D23<>0,"BANQUE",IF($E23<>0,"ESPECES","ECHEC")) -> BANQUE | I23: 1 | J23: =IF($D23<>0,I23*30000,IF($E23<>0,I23*30000,0)) -> 30000 | K23: 20000 | M23: =IF($D23<>0,L23*75000,IF($E23<>0,L23*75000,0)) -> 0 | N23: 1 | O23: =IF($D23<>0,N23*100000,IF($E23<>0,N23*100000,0)) -> 100000 | P23: =VLOOKUP(A23,[9]TONTDEC22!$A$6:$R$31,12,0) -> 0 | R23: =VLOOKUP(A23,[8]TONTDEC22!$A$6:$P$21,10,0) -> 101000 | S23: =449000+81000 -> 530000 | T23: BANQUE | U23: =G23+S23++R23+P23+O23+M23+K23+J23+Q23+V23+W23 -> 781000 | Z23: 600000 | AA23: BANQUE | AP23: BANQUE | AQ23: =IF(H23="ECHEC",((J23+M23+O23)*20/100),0) -> 0 | AR23: =IF(H23="ECHEC",((J23+M23+O23)*20/100),0) -> 0 | AS23: =IF(H23="ECHEC",0,(J23+K23-23000)) -> 27000 | AT23: 20000 | AW23: =IF(AC23=0,AI23,(1*23000*13)+(1000+AI23)-AC23) -> 0 | AX23: =IF(AD23=0,AJ23,(1*75000*16)+(AJ23)-AD23) -> 0 | AY23: =IF(AE23=0,AK23,(1*100000*13)+(AK23)-AE23) -> 0 | AZ23: =SUM(AV23:AY23)-BF23+Z23-F23+BH23+BI23+BJ23+BK23 -> 552000 | BD23: =IF(AZ23=0,(AZ23-BA23-BC23),(AZ23-BA23-BB23-BC23)) -> 552000 | BF23: =Z23*1/100*BG23 -> 48000 | BG23: 8
A24: AS201624 | B24: =VLOOKUP(A24,[6]LISTADHERENT!A$5:H$60,3,0) -> NGONDIEP CLAUDE | C24: =D24+E24+F24-U24-BB24 -> 0 | D24: =VLOOKUP(A24,[7]HISTOBQUEDEC22!$A$6:$G$36,3,0) -> 1240000 | E24: =VLOOKUP(A24,[7]HISTOBQUEDEC22!$A$6:$G$36,4,0) -> 0 | F24: =VLOOKUP(A24,[7]HISTOBQUEDEC22!$A$6:$G$36,5,0) -> 0 | G24: =IF(H24="ESPECES",3000,0) -> 0 | H24: =IF($D24<>0,"BANQUE",IF($E24<>0,"ESPECES","ECHEC")) -> BANQUE | I24: 1 | J24: =IF($D24<>0,I24*30000,IF($E24<>0,I24*30000,0)) -> 30000 | K24: 35000 | L24: 1 | M24: =IF($D24<>0,L24*75000,IF($E24<>0,L24*75000,0)) -> 75000 | N24: 1 | O24: =IF($D24<>0,N24*100000,IF($E24<>0,N24*100000,0)) -> 100000 | P24: =VLOOKUP(A24,[9]TONTDEC22!$A$6:$R$31,12,0) -> 0 | Q24: =VLOOKUP(A24,[10]TONTDEC22!$A$6:$P$21,10,0) -> 0 | R24: =VLOOKUP(A24,[8]TONTDEC22!$A$6:$P$21,10,0) -> 0 | S24: 1000000 | T24: BANQUE | U24: =G24+S24++R24+P24+O24+M24+K24+J24+Q24+V24+W24 -> 1240000 | Z24: 1000000 | AA24: BANQUE | AQ24: =IF(H24="ECHEC",((J24+M24+O24)*20/100),0) -> 0 | AR24: =IF(H24="ECHEC",((J24+M24+O24)*20/100),0) -> 0 | AS24: =IF(H24="ECHEC",0,(J24+K24-23000)) -> 42000 | AT24: 20000 | AW24: =IF(AC24=0,AI24,(1*23000*13)+(1000+AI24)-AC24) -> 0 | AX24: =IF(AD24=0,AJ24,(1*75000*16)+(AJ24)-AD24) -> 0 | AY24: =IF(AE24=0,AK24,(1*100000*13)+(AK24)-AE24) -> 0 | AZ24: =SUM(AV24:AY24)-BF24+Z24-F24+BH24+BI24+BJ24+BK24 -> 880000 | BD24: =IF(AZ24=0,(AZ24-BA24-BC24),(AZ24-BA24-BB24-BC24)) -> 880000 | BF24: =Z24*1/100*BG24 -> 120000 | BG24: 12 | BN24: GRATIFICATION BUREAU 2021 | BO24: FRAIS EXEPTIONNEL
A25: AS201626 | B25: =VLOOKUP(A25,[6]LISTADHERENT!A$5:H$60,3,0) -> NGUIEMEGNI MATHIEU BLAISE | C25: =D25+E25+F25-U25-BB25 -> 0 | D25: =VLOOKUP(A25,[7]HISTOBQUEDEC22!$A$6:$G$36,3,0) -> 1280000 | E25: =VLOOKUP(A25,[7]HISTOBQUEDEC22!$A$6:$G$36,4,0) -> 0 | F25: =VLOOKUP(A25,[7]HISTOBQUEDEC22!$A$6:$G$36,5,0) -> 0 | G25: =IF(H25="ESPECES",3000,0) -> 0 | H25: =IF($D25<>0,"BANQUE",IF($E25<>0,"ESPECES","ECHEC")) -> BANQUE | I25: 1 | J25: =IF($D25<>0,I25*30000,IF($E25<>0,I25*30000,0)) -> 30000 | L25: 2 | M25: =IF($D25<>0,L25*75000,IF($E25<>0,L25*75000,0)) -> 150000 | N25: 1 | O25: =IF($D25<>0,N25*100000,IF($E25<>0,N25*100000,0)) -> 100000 | P25: =VLOOKUP(A25,[9]TONTDEC22!$A$6:$R$31,12,0) -> 0 | Q25: =VLOOKUP(A25,[10]TONTDEC22!$A$6:$P$21,10,0) -> 0 | R25: =VLOOKUP(A25,[8]TONTDEC22!$A$6:$P$21,10,0) -> 0 | S25: 1000000 | T25: BANQUE | U25: =G25+S25++R25+P25+O25+M25+K25+J25+Q25+V25+W25 -> 1280000 | Z25: 1000000 | AA25: BANQUE | AQ25: =IF(H25="ECHEC",((J25+M25+O25)*20/100),0) -> 0 | AR25: =IF(H25="ECHEC",((J25+M25+O25)*20/100),0) -> 0 | AS25: =IF(H25="ECHEC",0,(J25+K25-23000)) -> 7000 | AT25: 20000 | AW25: =IF(AC25=0,AI25,(1*23000*13)+(1000+AI25)-AC25) -> 0 | AX25: =IF(AD25=0,AJ25,(1*75000*16)+(AJ25)-AD25) -> 0 | AY25: =IF(AE25=0,AK25,(1*100000*13)+(AK25)-AE25) -> 0 | AZ25: =SUM(AV25:AY25)-BF25+Z25-F25+BH25+BI25+BJ25+BK25 -> 880000 | BD25: =IF(AZ25=0,(AZ25-BA25-BC25),(AZ25-BA25-BB25-BC25)) -> 880000 | BF25: =Z25*1/100*BG25 -> 120000 | BG25: 12 | BN25: DEVELOPPEMENT LAGWEU | BO25: FRAIS EXEPTIONNEL
A26: AS201628 | B26: =VLOOKUP(A26,[6]LISTADHERENT!A$5:H$60,3,0) -> NKAMGANG JUSTIN DEJOLIE | C26: =D26+E26+F26-U26-BB26 -> 0 | D26: =VLOOKUP(A26,[7]HISTOBQUEDEC22!$A$6:$G$36,3,0) -> 1105000 | E26: =VLOOKUP(A26,[7]HISTOBQUEDEC22!$A$6:$G$36,4,0) -> 79500 | F26: =VLOOKUP(A26,[7]HISTOBQUEDEC22!$A$6:$G$36,5,0) -> 0 | G26: =IF(H26="ESPECES",3000,0) -> 0 | H26: =IF($D26<>0,"BANQUE",IF($E26<>0,"ESPECES","ECHEC")) -> BANQUE | I26: 1 | J26: =IF($D26<>0,I26*30000,IF($E26<>0,I26*30000,0)) -> 30000 | L26: 1 | M26: =IF($D26<>0,L26*75000,IF($E26<>0,L26*75000,0)) -> 75000 | O26: =IF($D26<>0,N26*100000,IF($E26<>0,N26*100000,0)) -> 0 | P26: =VLOOKUP(A26,[9]TONTDEC22!$A$6:$R$31,12,0) -> 41000 | Q26: =VLOOKUP(A26,[10]TONTDEC22!$A$6:$P$21,10,0) -> 38500 | S26: 1000000 | T26: BANQUE | U26: =G26+S26++R26+P26+O26+M26+K26+J26+Q26+V26+W26 -> 1184500 | Z26: 1000000 | AA26: BANQUE | AP26: BANQUE | AQ26: =IF(H26="ECHEC",((J26+M26+O26)*20/100),0) -> 0 | AR26: =IF(H26="ECHEC",((J26+M26+O26)*20/100),0) -> 0 | AS26: =IF(H26="ECHEC",0,(J26+K26-23000)) -> 7000 | AT26: 20000 | AW26: =IF(AC26=0,AI26,(1*23000*13)+(1000+AI26)-AC26) -> 0 | AX26: =IF(AD26=0,AJ26,(1*75000*16)+(AJ26)-AD26) -> 0 | AY26: =IF(AE26=0,AK26,(1*100000*13)+(AK26)-AE26) -> 0 | AZ26: =SUM(AV26:AY26)-BF26+Z26-F26+BH26+BI26+BJ26+BK26 -> 980000 | BD26: =IF(AZ26=0,(AZ26-BA26-BC26),(AZ26-BA26-BB26-BC26)) -> 980000 | BF26: =Z26*1/100*BG26 -> 20000 | BG26: 2 | BN26: DEUIL TCHEMNOU EMMANUEL | BO26: FRAIS EXEPTIONNEL
A27: AS201614 | B27: =VLOOKUP(A27,[6]LISTADHERENT!A$5:H$60,3,0) -> NKEHE DAVID | C27: =D27+E27+F27-U27-BB27 -> 520000 | D27: =VLOOKUP(A27,[7]HISTOBQUEDEC22!$A$6:$G$36,3,0) -> 520000 | E27: =VLOOKUP(A27,[7]HISTOBQUEDEC22!$A$6:$G$36,4,0) -> 0 | F27: =VLOOKUP(A27,[7]HISTOBQUEDEC22!$A$6:$G$36,5,0) -> 0 | G27: =IF(H27="ESPECES",3000,0) -> 0 | H27: =IF($D27<>0,"BANQUE",IF($E27<>0,"ESPECES","ECHEC")) -> BANQUE | I27: 0 | J27: =IF($D27<>0,I27*30000,IF($E27<>0,I27*30000,0)) -> 0 | M27: =IF($D27<>0,L27*75000,IF($E27<>0,L27*75000,0)) -> 0 | N27: 0 | O27: =IF($D27<>0,N27*100000,IF($E27<>0,N27*100000,0)) -> 0 | U27: =G27+S27++R27+P27+O27+M27+K27+J27+Q27+V27+W27 -> 0 | AQ27: =IF(H27="ECHEC",((J27+M27+O27)*20/100),0) -> 0 | AR27: =IF(H27="ECHEC",((J27+M27+O27)*20/100),0) -> 0 | AS27: =IF(H27="ECHEC",0,(J27+K27)) -> 0 | AW27: =IF(AC27=0,AI27,(1*23000*13)+(1000+AI27)-AC27) -> 0 | AX27: =IF(AD27=0,AJ27,(1*75000*16)+(AJ27)-AD27) -> 0 | AY27: =IF(AE27=0,AK27,(1*100000*13)+(AK27)-AE27) -> 0 | AZ27: =SUM(AV27:AY27)-BF27+Z27-F27+BH27+BI27+BJ27+BK27 -> 0 | BD27: =IF(AZ27=0,(AZ27-BA27-BC27),(AZ27-BA27-BB27-BC27)) -> 0 | BF27: =Z27*1/100*BG27 -> 0 | BG27: 0
A28: AS201629 | B28: =VLOOKUP(A28,[6]LISTADHERENT!A$5:H$60,3,0) -> NKEPSEU DIEUDONNE | C28: =D28+E28+F28-U28-BB28 -> 0 | D28: =VLOOKUP(A28,[7]HISTOBQUEDEC22!$A$6:$G$36,3,0) -> 1130000 | E28: =VLOOKUP(A28,[7]HISTOBQUEDEC22!$A$6:$G$36,4,0) -> 0 | F28: =VLOOKUP(A28,[7]HISTOBQUEDEC22!$A$6:$G$36,5,0) -> 0 | G28: =IF(H28="ESPECES",3000,0) -> 0 | H28: =IF($D28<>0,"BANQUE",IF($E28<>0,"ESPECES","ECHEC")) -> BANQUE | I28: 1 | J28: =IF($D28<>0,I28*30000,IF($E28<>0,I28*30000,0)) -> 30000 | M28: =IF($D28<>0,L28*75000,IF($E28<>0,L28*75000,0)) -> 0 | N28: 1 | O28: =IF($D28<>0,N28*100000,IF($E28<>0,N28*100000,0)) -> 100000 | P28: =VLOOKUP(A28,[9]TONTDEC22!$A$6:$R$31,12,0) -> 0 | R28: =VLOOKUP(A28,[8]TONTDEC22!$A$6:$P$21,10,0) -> 0 | S28: =600000+400000 -> 1000000 | T28: BANQUE | U28: =G28+S28++R28+P28+O28+M28+K28+J28+Q28+V28+W28 -> 1130000 | AQ28: =IF(H28="ECHEC",((J28+M28+O28)*20/100),0) -> 0 | AR28: =IF(H28="ECHEC",((J28+M28+O28)*20/100),0) -> 0 | AS28: =IF(H28="ECHEC",0,(J28+K28-23000)) -> 7000 | AT28: 20000 | AW28: =IF(AC28=0,AI28,(1*23000*13)+(1000+AI28)-AC28) -> 0 | AX28: =IF(AD28=0,AJ28,(1*75000*16)+(AJ28)-AD28) -> 0 | AY28: =IF(AE28=0,AK28,(1*100000*13)+(AK28)-AE28) -> 0 | AZ28: =SUM(AV28:AY28)-BF28+Z28-F28+BH28+BI28+BJ28+BK28 -> 0 | BD28: =IF(AZ28=0,(AZ28-BA28-BC28),(AZ28-BA28-BB28-BC28)) -> 0 | BF28: =Z28*1/100*BG28 -> 0 | BG28: 0 | BN28: S/TOTAL | BP28: =SUM(BP24:BP26) -> 0
A29: AS201633 | B29: =VLOOKUP(A29,[6]LISTADHERENT!A$5:H$60,3,0) -> PATEGO NJOSSU GUSTAVE | C29: =D29+E29+F29-U29-BB29 -> 0 | D29: =VLOOKUP(A29,[7]HISTOBQUEDEC22!$A$6:$G$36,3,0) -> 105000 | E29: =VLOOKUP(A29,[7]HISTOBQUEDEC22!$A$6:$G$36,4,0) -> 0 | F29: =VLOOKUP(A29,[7]HISTOBQUEDEC22!$A$6:$G$36,5,0) -> 0 | G29: =IF(H29="ESPECES",3000,0) -> 0 | H29: =IF($D29<>0,"BANQUE",IF($E29<>0,"ESPECES","ECHEC")) -> BANQUE | I29: 1 | J29: =IF($D29<>0,I29*30000,IF($E29<>0,I29*30000,0)) -> 30000 | L29: 1 | M29: =IF($D29<>0,L29*75000,IF($E29<>0,L29*75000,0)) -> 75000 | O29: =IF($D29<>0,N29*100000,IF($E29<>0,N29*100000,0)) -> 0 | P29: =VLOOKUP(A29,[9]TONTDEC22!$A$6:$R$31,12,0) -> 0 | Q29: =VLOOKUP(A29,[10]TONTDEC22!$A$6:$P$21,10,0) -> 0 | U29: =G29+S29++R29+P29+O29+M29+K29+J29+Q29+V29+W29 -> 105000 | AQ29: =IF(H29="ECHEC",((J29+M29+O29)*20/100),0) -> 0 | AR29: =IF(H29="ECHEC",((J29+M29+O29)*20/100),0) -> 0 | AS29: =IF(H29="ECHEC",0,(J29+K29-23000)) -> 7000 | AT29: 20000 | AW29: =IF(AC29=0,AI29,(1*23000*13)+(1000+AI29)-AC29) -> 0 | AX29: =IF(AD29=0,AJ29,(1*75000*16)+(AJ29)-AD29) -> 0 | AY29: =IF(AE29=0,AK29,(1*100000*13)+(AK29)-AE29) -> 0 | AZ29: =SUM(AV29:AY29)-BF29+Z29-F29+BH29+BI29+BJ29+BK29 -> 0 | BD29: =IF(AZ29=0,(AZ29-BA29-BC29),(AZ29-BA29-BB29-BC29)) -> 0 | BF29: =Z29*1/100*BG29 -> 0 | BG29: 0
A30: AS201653 | B30: =VLOOKUP(A30,[6]LISTADHERENT!A$5:H$60,3,0) -> SIME BRICE | C30: =D30+E30+F30-U30-BB30 -> -100000 | D30: =VLOOKUP(A30,[7]HISTOBQUEDEC22!$A$6:$G$36,3,0) -> 105000 | E30: =VLOOKUP(A30,[7]HISTOBQUEDEC22!$A$6:$G$36,4,0) -> 0 | F30: =VLOOKUP(A30,[7]HISTOBQUEDEC22!$A$6:$G$36,5,0) -> 0 | G30: =IF(H30="ESPECES",3000,0) -> 0 | H30: =IF($D30<>0,"BANQUE",IF($E30<>0,"ESPECES","ECHEC")) -> BANQUE | I30: 1 | J30: =IF($D30<>0,I30*30000,IF($E30<>0,I30*30000,0)) -> 30000 | L30: 1 | M30: =IF($D30<>0,L30*75000,IF($E30<>0,L30*75000,0)) -> 75000 | O30: =IF($D30<>0,N30*100000,IF($E30<>0,N30*100000,0)) -> 0 | P30: =VLOOKUP(A30,[9]TONTDEC22!$A$6:$R$31,12,0) -> 0 | Q30: =VLOOKUP(A30,[10]TONTDEC22!$A$6:$P$21,10,0) -> 0 | U30: =G30+S30++R30+P30+O30+M30+K30+J30+Q30+V30+W30 -> 105000 | AC30: 23000 | AF30: BANQUE | AQ30: =IF(H30="ECHEC",((J30+M30+O30)*20/100),0) -> 0 | AR30: =IF(H30="ECHEC",((J30+M30+O30)*20/100),0) -> 0 | AS30: =IF(H30="ECHEC",0,(J30+K30-23000)) -> 7000 | AT30: 20000 | AW30: =IF(AC30=0,AI30,(1*23000*13)+(1000+AI30)-AC30) -> 277000 | AX30: =IF(AD30=0,AJ30,(1*75000*16)+(AJ30)-AD30) -> 0 | AY30: =IF(AE30=0,AK30,(1*100000*13)+(AK30)-AE30) -> 0 | AZ30: =SUM(AV30:AY30)-BF30+Z30-F30+BH30+BI30+BJ30+BK30 -> 277000 | BB30: 100000 | BD30: =IF(AZ30=0,(AZ30-BA30-BC30),(AZ30-BA30-BB30-BC30)) -> 177000 | BF30: =Z30*1/100*BG30 -> 0 | BG30: 0 | BN30: DECES | BO30: MUTUELLE
A31: AS201636 | B31: =VLOOKUP(A31,[6]LISTADHERENT!A$5:H$60,3,0) -> SIMO FONGANG ERIC | C31: =D31+E31+F31-U31-BB31 -> 0 | D31: =VLOOKUP(A31,[7]HISTOBQUEDEC22!$A$6:$G$36,3,0) -> 0 | E31: =VLOOKUP(A31,[7]HISTOBQUEDEC22!$A$6:$G$36,4,0) -> 0 | F31: =VLOOKUP(A31,[7]HISTOBQUEDEC22!$A$6:$G$36,5,0) -> 0 | G31: =IF(H31="ESPECES",3000,0) -> 0 | H31: =IF($D31<>0,"BANQUE",IF($E31<>0,"ESPECES","ECHEC")) -> ECHEC | J31: =IF($D31<>0,I31*30000,IF($E31<>0,I31*30000,0)) -> 0 | M31: =IF($D31<>0,L31*75000,IF($E31<>0,L31*75000,0)) -> 0 | O31: =IF($D31<>0,N31*100000,IF($E31<>0,N31*100000,0)) -> 0 | U31: =G31+S31++R31+P31+O31+M31+K31+J31+Q31+V31+W31 -> 0 | AQ31: =IF(H31="ECHEC",((J31+M31+O31)*20/100),0) -> 0 | AR31: =IF(H31="ECHEC",((J31+M31+O31)*20/100),0) -> 0 | AS31: =IF(H31="ECHEC",0,(J31+K31-23000)) -> 0 | AT31: 20000 | AW31: =IF(AC31=0,AI31,(1*23000*13)+(1000+AI31)-AC31) -> 0 | AX31: =IF(AD31=0,AJ31,(1*75000*16)+(AJ31)-AD31) -> 0 | AY31: =IF(AE31=0,AK31,(1*100000*13)+(AK31)-AE31) -> 0 | AZ31: =SUM(AV31:AY31)-BF31+Z31-F31+BH31+BI31+BJ31+BK31 -> 0 | BD31: =IF(AZ31=0,(AZ31-BA31-BC31),(AZ31-BA31-BB31-BC31)) -> 0 | BF31: =Z31*1/100*BG31 -> 0 | BG31: 0 | BN31: TRANSPORT DELEGUE | BO31: MUTUELLE
A32: AS201638 | B32: =VLOOKUP(A32,[6]LISTADHERENT!A$5:H$60,3,0) -> SIMO PIERRE | C32: =D32+E32+F32-U32-BB32 -> 0 | D32: =VLOOKUP(A32,[7]HISTOBQUEDEC22!$A$6:$G$36,3,0) -> 905000 | E32: =VLOOKUP(A32,[7]HISTOBQUEDEC22!$A$6:$G$36,4,0) -> 0 | F32: =VLOOKUP(A32,[7]HISTOBQUEDEC22!$A$6:$G$36,5,0) -> 0 | G32: =IF(H32="ESPECES",3000,0) -> 0 | H32: =IF($D32<>0,"BANQUE",IF($E32<>0,"ESPECES","ECHEC")) -> BANQUE | I32: 1 | J32: =IF($D32<>0,I32*30000,IF($E32<>0,I32*30000,0)) -> 30000 | L32: 1 | M32: =IF($D32<>0,L32*75000,IF($E32<>0,L32*75000,0)) -> 75000 | O32: =IF($D32<>0,N32*100000,IF($E32<>0,N32*100000,0)) -> 0 | P32: =VLOOKUP(A32,[9]TONTDEC22!$A$6:$R$31,12,0) -> 0 | Q32: =VLOOKUP(A32,[10]TONTDEC22!$A$6:$P$21,10,0) -> 0 | S32: =395000+378000+27000 -> 800000 | T32: BANQUE | U32: =G32+S32++R32+P32+O32+M32+K32+J32+Q32+V32+W32 -> 905000 | Z32: 1000000 | AA32: BANQUE | AQ32: =IF(H32="ECHEC",((J32+M32+O32)*20/100),0) -> 0 | AR32: =IF(H32="ECHEC",((J32+M32+O32)*20/100),0) -> 0 | AS32: =IF(H32="ECHEC",0,(J32+K32-23000)) -> 7000 | AT32: 20000 | AW32: =IF(AC32=0,AI32,(1*23000*13)+(1000+AI32)-AC32) -> 0 | AX32: =IF(AD32=0,AJ32,(1*75000*16)+(AJ32)-AD32) -> 0 | AY32: =IF(AE32=0,AK32,(1*100000*13)+(AK32)-AE32) -> 0 | AZ32: =SUM(AV32:AY32)-BF32+Z32-F32+BH32+BI32+BJ32+BK32 -> 880000 | BD32: =IF(AZ32=0,(AZ32-BA32-BC32),(AZ32-BA32-BB32-BC32)) -> 880000 | BF32: =Z32*1/100*BG32 -> 120000 | BG32: 12
A33: AS201641 | B33: =VLOOKUP(A33,[6]LISTADHERENT!A$5:H$60,3,0) -> TCHOUAMOU MATHIEU | C33: =D33+E33+F33-U33-BB33 -> 0 | D33: =VLOOKUP(A33,[7]HISTOBQUEDEC22!$A$6:$G$36,3,0) -> 1030000 | E33: =VLOOKUP(A33,[7]HISTOBQUEDEC22!$A$6:$G$36,4,0) -> 0 | F33: =VLOOKUP(A33,[7]HISTOBQUEDEC22!$A$6:$G$36,5,0) -> 0 | G33: =IF(H33="ESPECES",3000,0) -> 0 | H33: =IF($D33<>0,"BANQUE",IF($E33<>0,"ESPECES","ECHEC")) -> BANQUE | I33: 1 | J33: =IF($D33<>0,I33*30000,IF($E33<>0,I33*30000,0)) -> 30000 | M33: =IF($D33<>0,L33*75000,IF($E33<>0,L33*75000,0)) -> 0 | O33: =IF($D33<>0,N33*100000,IF($E33<>0,N33*100000,0)) -> 0 | P33: =VLOOKUP(A33,[9]TONTDEC22!$A$6:$R$31,12,0) -> 0 | S33: 1000000 | T33: BANQUE | U33: =G33+S33++R33+P33+O33+M33+K33+J33+Q33+V33+W33 -> 1030000 | Z33: 1000000 | AA33: BANQUE | AQ33: =IF(H33="ECHEC",((J33+M33+O33)*20/100),0) -> 0 | AR33: =IF(H33="ECHEC",((J33+M33+O33)*20/100),0) -> 0 | AS33: =IF(H33="ECHEC",0,(J33+K33-23000)) -> 7000 | AT33: 20000 | AW33: =IF(AC33=0,AI33,(1*23000*13)+(1000+AI33)-AC33) -> 0 | AX33: =IF(AD33=0,AJ33,(1*75000*16)+(AJ33)-AD33) -> 0 | AY33: =IF(AE33=0,AK33,(1*100000*13)+(AK33)-AE33) -> 0 | AZ33: =SUM(AV33:AY33)-BF33+Z33-F33+BH33+BI33+BJ33+BK33 -> 970000 | BD33: =IF(AZ33=0,(AZ33-BA33-BC33),(AZ33-BA33-BB33-BC33)) -> 970000 | BF33: =Z33*1/100*BG33 -> 30000 | BG33: 3 | BN33: S/TOTAL | BP33: =SUM(BP30:BP32) -> 0
A34: AS201644 | B34: =VLOOKUP(A34,[6]LISTADHERENT!A$5:H$60,3,0) -> TIEYAM ERNEST | C34: =D34+E34+F34-U34-BB34 -> 0 | D34: =VLOOKUP(A34,[7]HISTOBQUEDEC22!$A$6:$G$36,3,0) -> 0 | E34: =VLOOKUP(A34,[7]HISTOBQUEDEC22!$A$6:$G$36,4,0) -> 0 | F34: =VLOOKUP(A34,[7]HISTOBQUEDEC22!$A$6:$G$36,5,0) -> 0 | G34: =IF(H34="ESPECES",3000,0) -> 0 | H34: =IF($D34<>0,"BANQUE",IF($E34<>0,"ESPECES","ECHEC")) -> ECHEC | I34: 0 | J34: =IF($D34<>0,I34*30000,IF($E34<>0,I34*30000,0)) -> 0 | M34: =IF($D34<>0,L34*75000,IF($E34<>0,L34*75000,0)) -> 0 | N34: 0 | O34: =IF($D34<>0,N34*100000,IF($E34<>0,N34*100000,0)) -> 0 | U34: =G34+S34++R34+P34+O34+M34+K34+J34+Q34+V34+W34 -> 0 | AQ34: =IF(H34="ECHEC",((J34+M34+O34)*20/100),0) -> 0 | AR34: =IF(H34="ECHEC",((J34+M34+O34)*20/100),0) -> 0 | AS34: =IF(H34="ECHEC",0,(J34+K34)) -> 0 | AW34: =IF(AC34=0,AI34,(1*23000*13)+(1000+AI34)-AC34) -> 0 | AX34: =IF(AD34=0,AJ34,(1*75000*16)+(AJ34)-AD34) -> 0 | AY34: =IF(AE34=0,AK34,(1*100000*13)+(AK34)-AE34) -> 0 | AZ34: =SUM(AV34:AY34)-BF34+Z34-F34+BH34+BI34+BJ34+BK34 -> 0 | BD34: =IF(AZ34=0,(AZ34-BA34-BC34),(AZ34-BA34-BB34-BC34)) -> 0 | BF34: =Z34*1/100*BG34 -> 0 | BG34: 0
A35: AS201646 | B35: =VLOOKUP(A35,[6]LISTADHERENT!A$5:H$60,3,0) -> YEPMOU JEAN JACQUES | C35: =D35+E35+F35-U35-BB35 -> 0 | D35: =VLOOKUP(A35,[7]HISTOBQUEDEC22!$A$6:$G$36,3,0) -> 1041250 | E35: =VLOOKUP(A35,[7]HISTOBQUEDEC22!$A$6:$G$36,4,0) -> 0 | F35: =VLOOKUP(A35,[7]HISTOBQUEDEC22!$A$6:$G$36,5,0) -> 0 | G35: =IF(H35="ESPECES",3000,0) -> 0 | H35: =IF($D35<>0,"BANQUE",IF($E35<>0,"ESPECES","ECHEC")) -> BANQUE | I35: 1 | J35: =IF($D35<>0,I35*30000,IF($E35<>0,I35*30000,0)) -> 30000 | M35: =IF($D35<>0,L35*75000,IF($E35<>0,L35*75000,0)) -> 0 | O35: =IF($D35<>0,N35*100000,IF($E35<>0,N35*100000,0)) -> 0 | P35: =VLOOKUP(A35,[9]TONTDEC22!$A$6:$R$31,12,0) -> 0 | S35: 1011250 | T35: BANQUE | U35: =G35+S35++R35+P35+O35+M35+K35+J35+Q35+V35+W35 -> 1041250 | AQ35: =IF(H35="ECHEC",((J35+M35+O35)*20/100),0) -> 0 | AR35: =IF(H35="ECHEC",((J35+M35+O35)*20/100),0) -> 0 | AS35: =IF(H35="ECHEC",0,(J35+K35-23000)) -> 7000 | AT35: 20000 | AW35: =IF(AC35=0,AI35,(1*23000*13)+(1000+AI35)-AC35) -> 0 | AX35: =IF(AD35=0,AJ35,(1*75000*16)+(AJ35)-AD35) -> 0 | AY35: =IF(AE35=0,AK35,(1*100000*13)+(AK35)-AE35) -> 0 | AZ35: =SUM(AV35:AY35)-BF35+Z35-F35+BH35+BI35+BJ35+BK35 -> 0 | BD35: =IF(AZ35=0,(AZ35-BA35-BC35),(AZ35-BA35-BB35-BC35)) -> 0 | BF35: =Z35*1/100*BG35 -> 0 | BG35: 0 | BN35: COLLATION | BO35: COLLATION
A36: AS201647 | B36: =VLOOKUP(A36,[6]LISTADHERENT!A$5:H$60,3,0) -> YOUMBI EMMANUEL | C36: =D36+E36+F36-U36-BB36 -> 0 | D36: =VLOOKUP(A36,[7]HISTOBQUEDEC22!$A$6:$G$36,3,0) -> 280000 | E36: =VLOOKUP(A36,[7]HISTOBQUEDEC22!$A$6:$G$36,4,0) -> 0 | F36: =VLOOKUP(A36,[7]HISTOBQUEDEC22!$A$6:$G$36,5,0) -> 0 | G36: =IF(H36="ESPECES",3000,0) -> 0 | H36: =IF($D36<>0,"BANQUE",IF($E36<>0,"ESPECES","ECHEC")) -> BANQUE | I36: 1 | J36: =IF($D36<>0,I36*30000,IF($E36<>0,I36*30000,0)) -> 30000 | L36: 2 | M36: =IF($D36<>0,L36*75000,IF($E36<>0,L36*75000,0)) -> 150000 | N36: 1 | O36: =IF($D36<>0,N36*100000,IF($E36<>0,N36*100000,0)) -> 100000 | P36: =VLOOKUP(A36,[9]TONTDEC22!$A$6:$R$31,12,0) -> 0 | Q36: =VLOOKUP(A36,[10]TONTDEC22!$A$6:$P$21,10,0) -> 0 | R36: =VLOOKUP(A36,[8]TONTDEC22!$A$6:$P$21,10,0) -> 0 | U36: =G36+S36++R36+P36+O36+M36+K36+J36+Q36+V36+W36 -> 280000 | AQ36: =IF(H36="ECHEC",((J36+M36+O36)*20/100),0) -> 0 | AR36: =IF(H36="ECHEC",((J36+M36+O36)*20/100),0) -> 0 | AS36: =IF(H36="ECHEC",0,(J36+K36-23000)) -> 7000 | AT36: 20000 | AW36: =IF(AC36=0,AI36,(1*23000*13)+(1000+AI36)-AC36) -> 0 | AX36: =IF(AD36=0,AJ36,(1*75000*16)+(AJ36)-AD36) -> 0 | AY36: =IF(AE36=0,AK36,(1*100000*13)+(AK36)-AE36) -> 0 | AZ36: =SUM(AV36:AY36)-BF36+Z36-F36+BH36+BI36+BJ36+BK36 -> 0 | BD36: =IF(AZ36=0,(AZ36-BA36-BC36),(AZ36-BA36-BB36-BC36)) -> 0 | BF36: =Z36*1/100*BG36 -> 0 | BG36: 0 | BN36: BOISSON | BO36: COLLATION
B38: TOTAUX | C38: =SUM(C6:C37) -> 420000 | D38: =SUM(D6:D37) -> 20433750 | E38: =SUM(E6:E37) -> 180500 | F38: =SUM(F6:F37) -> 0 | G38: =SUM(G6:G37) -> 0 | H38: =SUM(H6:H37) -> 0 | I38: =SUM(I6:I37) -> 26 | J38: =SUM(J6:J37) -> 780000 | ... BD38: =SUM(BD6:BD37) -> 17269000 | BF38: =SUM(BF6:BF37) -> 1248000 | BH38: =SUM(BH6:BH37) -> 6000 | BI38: =SUM(BI6:BI37) -> 0 | BJ38: =SUM(BJ6:BJ37) -> 0 | BK38: =SUM(BK6:BK37) -> 70000 | BL38: =SUM(BL6:BL37) -> 0 | BM38: =SUM(BM6:BM37) -> 0 | BN38: S/TOTAL | BP38: =SUM(BP35:BP37) -> 0
C42: BANQUE | F42: ESPECES
B43: LIBELLE | C43: SORTIE | D43: ENTREE | E43: SOLDE | F43: ENTREE | G43: SORTIE | H43: SOLDE
B44: REPORT
B45: TONTINE | C45: =AZ38 -> 17307000 | D45: =SUMIFS(D7:D38,H7:H38,"BANQUE") -> 20333750 | F45: =E38 -> 180500
AZ83: =SUM(AZ7:AZ82) -> 33408000

Sheet HISTOJANV25
A1: ASSOCIATION | B1: ASELBY
A2: ANNEE | B2: 2025
A3: 1 | B3: 2 | C3: 3 | D3: 4 | E3: 5 | G3: 6 | H3: 7 | I3: 8 | J3: 9 | K3: 10 | L3: 11 | M3: 12 | N3: 13 | O3: 14 | P3: 15 | Q3: 16 | R3: 17 | S3: 18 | T3: 19 | U3: 20 | V3: 21 | W3: 22 | X3: 23 | Y3: 24 | Z3: 25 | AA3: 26 | AB3: 27 | AC3: 28 | AD3: 29 | AE3: 30 | AF3: 31 | AG3: 32 | AH3: 33 | AI3: 34 | AJ3: 35 | AK3: 36 | AL3: 37 | AM3: 38 | AN3: 39 | AO3: 40 | AP3: 41 | AQ3: 42 | AR3: 43 | AS3: 44 | AT3: 45 | AU3: 46 | AV3: 47 | AW3: 48 | AX3: 49 | AY3: 50 | AZ3: 51 | BA3: 52 | BB3: 53 | BC3: 54 | BD3: 55 | BE3: 56 | BF3: 57 | BG3: 58 | BH3: 59 | BI3: 60 | BJ3: 61 | BK3: 62 | BL3: 63 | BM3: 64 | BN3: 65 | BP3: 66 | BQ3: 67 | BR3: 68
B4: TABLEAU DE BORD SAISIE DES DONNEES
A5: MATRICULE | B5: NOM ET PRENOM | C5: BONUS MALUS | D5: VERSEMENT BANQUE | E5: VERSEMENT ESPECES | F5: AUTRE VERSEMENTS | G5: HITORIQUE TONTINE | H5: PENALITE VERSEMENT ESPECES | I5: MODE PAIEMENT TONTINE | J5: COMPLEMENT EPARGNE | K5: NBRE DE LOT | L5: TONTINE 50 000 | M5: NBRE DE LOT | N5: TONTINE 75 000 | O5: NBRE DE LOT | P5: TONTINE 100 000 | Q5: REMBOURSEMENT PETIT LOT T50 | R5: REMBOURSEMENT PETIT LOT T75 | S5: REMBOURSEMENT PETIT LOT T100 | T5: REMBOURSEMENT PRÊT FONDS | U5: MODE PAIEMENT REMBOURSEMENT PRÊT FONDS | V5: MONTANT ENGAGEMENT | W5: SANCTION | X5: INSCRIPTION | Y5: EPARGNE ASSURANCE | Z5: RECONSTITUTION FONDS | AA5: PRÊT FONDS | AB5: MODE PAIEMENT PRÊT | AC5: NUM CHEQUE | AD5: ACHAT LOT PRINCIPAL T40 | AE5: ACHAT LOT PRINCIPAL T75 | AF5: ACHAT LOT PRINCIPAL T100 | AG5: MODE PAIEMENT LOT PRINCIPAL | AH5: NUM CHEQUE | AI5: PENALITE VERSEMENT ESPECES | AJ5: VENTE PETIT LOT T50 | AK5: VENTE PETIT LOT T75 | AL5: VENTE PETIT LOT T100 | AM5: INTERET PETIT LOT T50 | AN5: INTERET PETIT LOT T75 | AO5: INTERET PETIT LOT T100 | AP5: NUM CHEQUE | AQ5: MODE PAIEMENT PETEIT LOT | AR5: PENELAITE RETARD TONTINE | AS5: PENELAITE ECHEC TONTINE | AT5: RESTE | AU5: MUTUELLE | AV5: REMBOURSEMENT TRANSPORT | AW5: RETRAIT PARTIEL FONDS | AX5: MONTANT T40 | AY5: MONTANT T75 | AZ5: MONTANT T100 | BA5: MONTANT CHEQUE | BB5: MONTANT ESPECES | BC5: CONTRIBUTION FOYER | BD5: AUTRES SOTIES | BE5: MONTANT CHEQUE EFFECTIF | BF5: NUMERO CHEQUE | BG5: INTERET PRÊT | BH5: NBRE MOIS | BI5: DEPENSE FONDS DE ROULEMENT | BJ5: DEPENSE FRAIS EXCEPTIONNEL | BK5: DEPENSE FONDS MUTUEL | BL5: DEPENSE COLLATION RECEPTION | BM5: PENALITE PRET FONDS | BN5: DEPENSE PENALITE VERSEMENT BANQUE | BO5: AUTRES DEPENSES | BP5: LIBELLE | BQ5: COMPTE | BR5: MONTANT
A6: AS201648 | B6: =VLOOKUP(A6,[11]LISTADHERENT!A$5:H$50,3,0) -> ASELBY | C6: =D6+E6+F6+G6-V6-BC6 -> 0 | D6: =VLOOKUP(A6,[21]HISTOBQUEJANV25!$A$6:$H$46,5,0) -> 250000 | E6: =VLOOKUP(A6,[21]HISTOBQUEJANV25!$A$6:$H$41,4,0) -> 0 | F6: =VLOOKUP(A6,[21]HISTOBQUEJANV25!$A$6:$H$41,6,0) -> 0 | H6: =IF(I6="ESPECES",3000,0) -> 0 | I6: =IF($D6<>0,"BANQUE",IF($E6<>0,"ESPECES","ECHEC")) -> BANQUE | L6: =IF($D6<>0,K6*50000,IF($E6<>0,K6*50000,0)) -> 0 | M6: 2 | N6: =IF($D6<>0,M6*75000,IF($E6<>0,M6*75000,0)) -> 150000 | O6: 1 | P6: =IF($D6<>0,O6*100000,IF($E6<>0,O6*100000,0)) -> 100000 | Q6: =IFERROR(CHERCHEV(A6,[13]TONTJANV24!$A$6:$R$39,12,0),0) -> 0 | R6: =IFERROR(VLOOKUP(A6,[14]TONTJANV24!$A$7:$P$23,10,0),0) -> 0 | S6: =IFERROR(VLOOKUP(A6,[15]TONTJANV24!$A$7:$P$20,10,0),0) -> 0 | V6: =H6+T6++S6+Q6+P6+N6+J6+L6+R6+W6+X6 -> 250000 | AR6: =IF(I6="ECHEC",((L6+N6+P6)*20/100),0) -> 0 | AS6: =IF(I6="ECHEC",((L6+N6+P6)*20/100),0) -> 0 | AX6: =IF(AD6=0,AJ6,(1*25000*12)+AJ6-AD6) -> 0 | AY6: =IF(AE6=0,AK6,(1*75000*12)+(AK6)-AE6) -> 0 | AZ6: =IF(AF6=0,AL6,(1*100000*12)+(AL6)-AF6) -> 0 | BA6: =SUM(AW6:AZ6)-BG6+AA6-G6+BI6+BJ6+BK6+BL6+BM6+BN6 -> 227000 | BE6: =IF(BA6=0,(BA6-BB6-BD6),(BA6-BB6-BC6-BD6)) -> 227000 | BG6: =AA6*1/100*BH6 -> 0 | BH6: 11 | BI6: =BR16 -> 27000 | BJ6: =BR28 -> 200000 | BK6: =BR34 -> 0 | BO6: =+BR22 -> 300000 | BP6: ACHAT FOURNITURE | BQ6: FONDS DE ROULEMENT | BR6: 8500
A7: AS201601 | B7: =VLOOKUP(A7,[11]LISTADHERENT!A$5:H$50,3,0) -> BAKOP ACHILLE | C7: =D7+E7+F7+G7-V7-BC7 -> 0 | D7: =VLOOKUP(A7,[21]HISTOBQUEJANV25!$A$6:$H$46,5,0) -> 0 | E7: =VLOOKUP(A7,[21]HISTOBQUEJANV25!$A$6:$H$41,4,0) -> 50000 | F7: =VLOOKUP(A7,[21]HISTOBQUEJANV25!$A$6:$H$41,6,0) -> 0 | H7: 0 | I7: =IF($D7<>0,"BANQUE",IF($E7<>0,"ESPECES","ECHEC")) -> ESPECES | K7: 1 | L7: =IF($D7<>0,K7*50000,IF($E7<>0,K7*50000,0)) -> 50000 | N7: =IF($D7<>0,M7*75000,IF($E7<>0,M7*75000,0)) -> 0 | P7: =IF($D7<>0,O7*100000,IF($E7<>0,O7*100000,0)) -> 0 | Q7: =VLOOKUP(A7,[13]TONTJANV24!$A$6:$R$39,12,0) -> 0 | R7: =IFERROR(VLOOKUP(A7,[14]TONTJANV24!$A$7:$P$23,10,0),0) -> 0 | S7: =IFERROR(VLOOKUP(A7,[15]TONTJANV24!$A$7:$P$20,10,0),0) -> 0 | V7: =H7+T7++S7+Q7+P7+N7+J7+L7+R7+W7+X7 -> 50000 | AR7: =IF(I7="ECHEC",((L7+N7+P7)*20/100),0) -> 0 | AS7: =IF(I7="ECHEC",((L7+N7+P7)*20/100),0) -> 0 | AT7: =IF(I7="ECHEC",0,(L7+J7-25000)) -> 25000 | AX7: =IF(AD7=0,AJ7,(1*25000*12)+AJ7-AD7) -> 0 | AY7: =IF(AE7=0,AK7,(1*75000*12)+(AK7)-AE7) -> 0 | AZ7: =IF(AF7=0,AL7,(1*100000*12)+(AL7)-AF7) -> 0 | BA7: =SUM(AW7:AZ7)-BG7+AA7-G7+BI7+BJ7+BK7+BL7+BM7+BN7+6000+600000 -> 600000 | BE7: =IF(BA7=0,(BA7-BB7-BD7),(BA7-BB7-BC7-BD7))+G7-600000 -> 0 | BG7: =AA7*1/100*BH7+6000 -> 6000 | BH7: 11 | BP7: COMMUNICATION | BQ7: FONDS DE ROULEMENT
A8: AS201602 | B8: =VLOOKUP(A8,[11]LISTADHERENT!A$5:H$50,3,0) -> BOUTCHOUANG WILLIAM | C8: =D8+E8+F8+G8-V8-BC8 -> 0 | D8: =VLOOKUP(A8,[21]HISTOBQUEJANV25!$A$6:$H$46,5,0) -> 125000 | E8: =VLOOKUP(A8,[21]HISTOBQUEJANV25!$A$6:$H$41,4,0) -> 0 | F8: =VLOOKUP(A8,[21]HISTOBQUEJANV25!$A$6:$H$41,6,0) -> 0 | H8: =IF(I8="ESPECES",3000,0) -> 0 | I8: =IF($D8<>0,"BANQUE",IF($E8<>0,"ESPECES","ECHEC")) -> BANQUE | K8: 1 | L8: =IF($D8<>0,K8*50000,IF($E8<>0,K8*50000,0)) -> 50000 | M8: 1 | N8: =IF($D8<>0,M8*75000,IF($E8<>0,M8*75000,0)) -> 75000 | P8: =IF($D8<>0,O8*100000,IF($E8<>0,O8*100000,0)) -> 0 | Q8: =VLOOKUP(A8,[13]TONTJANV24!$A$6:$R$39,12,0) -> 0 | R8: =IFERROR(VLOOKUP(A8,[14]TONTJANV24!$A$7:$P$23,10,0),0) -> 0 | S8: =IFERROR(VLOOKUP(A8,[15]TONTJANV24!$A$7:$P$20,10,0),0) -> 0 | V8: =H8+T8++S8+Q8+P8+N8+J8+L8+R8+W8+X8 -> 125000 | AR8: =IF(I8="ECHEC",((L8+N8+P8)*20/100),0) -> 0 | AS8: =IF(I8="ECHEC",((L8+N8+P8)*20/100),0) -> 0 | AT8: =IF(I8="ECHEC",0,(L8+J8-25000)) -> 25000 | AX8: =IF(AD8=0,AJ8,(1*25000*12)+AJ8-AD8) -> 0 | AY8: =IF(AE8=0,AK8,(1*75000*12)+(AK8)-AE8) -> 0 | AZ8: =IF(AF8=0,AL8,(1*100000*12)+(AL8)-AF8) -> 0 | BA8: =SUM(AW8:AZ8)-BG8+AA8-G8+BI8+BJ8+BK8+BL8+BM8+BN8 -> 0 | BE8: =IF(BA8=0,(BA8-BB8-BD8),(BA8-BB8-BC8-BD8))+G8 -> 0 | BG8: =AA8*1/100*BH8 -> 0 | BH8: 11 | BP8: COMMISSION | BQ8: FONDS DE ROULEMENT
A9: AS201604 | B9: =VLOOKUP(A9,[11]LISTADHERENT!A$5:H$50,3,0) -> DJOMO JEAN PAUL | C9: =D9+E9+F9+G9-V9-BC9 -> 0 | D9: =VLOOKUP(A9,[21]HISTOBQUEJANV25!$A$6:$H$46,5,0) -> 250000 | E9: =VLOOKUP(A9,[21]HISTOBQUEJANV25!$A$6:$H$41,4,0) -> 0 | F9: =VLOOKUP(A9,[21]HISTOBQUEJANV25!$A$6:$H$41,6,0) -> 0 | H9: =IF(I9="ESPECES",3000,0) -> 0 | I9: =IF($D9<>0,"BANQUE",IF($E9<>0,"ESPECES","ECHEC")) -> BANQUE | K9: 1 | L9: =IF($D9<>0,K9*50000,IF($E9<>0,K9*50000,0)) -> 50000 | N9: =IF($D9<>0,M9*75000,IF($E9<>0,M9*75000,0)) -> 0 | O9: 2 | P9: =IF($D9<>0,O9*100000,IF($E9<>0,O9*100000,0)) -> 200000 | Q9: =VLOOKUP(A9,[13]TONTJANV24!$A$6:$R$39,12,0) -> 0 | R9: =IFERROR(VLOOKUP(A9,[14]TONTJANV24!$A$7:$P$23,10,0),0) -> 0 | S9: =IFERROR(VLOOKUP(A9,[15]TONTJANV24!$A$7:$P$20,10,0),0) -> 0 | V9: =H9+T9++S9+Q9+P9+N9+J9+L9+R9+W9+X9 -> 250000 | AR9: =IF(I9="ECHEC",((L9+N9+P9)*20/100),0) -> 0 | AS9: =IF(I9="ECHEC",((L9+N9+P9)*20/100),0) -> 0 | AT9: =IF(I9="ECHEC",0,(L9+J9-25000)) -> 25000 | AX9: =IF(AD9=0,AJ9,(1*25000*12)+AJ9-AD9) -> 0 | AY9: =IF(AE9=0,AK9,(1*75000*12)+(AK9)-AE9) -> 0 | AZ9: =IF(AF9=0,AL9,(1*100000*12)+(AL9)-AF9) -> 0 | BA9: =SUM(AW9:AZ9)-BG9+AA9-G9+BI9+BJ9+BK9+BL9+BM9+BN9 -> 0 | BE9: =IF(BA9=0,(BA9-BB9-BD9),(BA9-BB9-BC9-BD9))+G9 -> 0 | BG9: =AA9*1/100*BH9 -> 0 | BH9: 11 | BP9: OUVERTURE COMPTE | BQ9: FONDS DE ROULEMENT | BR9: 18500
A10: AS201654 | B10: =VLOOKUP(A10,[11]LISTADHERENT!A$5:H$50,3,0) -> DJOMOU TCHAPDA | C10: =D10+E10+F10+G10-V10-BC10 -> 0 | D10: =VLOOKUP(A10,[21]HISTOBQUEJANV25!$A$6:$H$46,5,0) -> 0 | E10: =VLOOKUP(A10,[21]HISTOBQUEJANV25!$A$6:$H$41,4,0) -> 50000 | F10: =VLOOKUP(A10,[21]HISTOBQUEJANV25!$A$6:$H$41,6,0) -> 0 | H10: 0 | I10: =IF($D10<>0,"BANQUE",IF($E10<>0,"ESPECES","ECHEC")) -> ESPECES | K10: 1 | L10: =IF($D10<>0,K10*50000,IF($E10<>0,K10*50000,0)) -> 50000 | N10: =IF($D10<>0,M10*75000,IF($E10<>0,M10*75000,0)) -> 0 | P10: =IF($D10<>0,O10*100000,IF($E10<>0,O10*100000,0)) -> 0 | Q10: =VLOOKUP(A10,[13]TONTJANV24!$A$6:$R$39,12,0) -> 0 | R10: =IFERROR(VLOOKUP(A10,[14]TONTJANV24!$A$7:$P$23,10,0),0) -> 0 | S10: =IFERROR(VLOOKUP(A10,[15]TONTJANV24!$A$7:$P$20,10,0),0) -> 0 | V10: =H10+T10++S10+Q10+P10+N10+J10+L10+R10+W10+X10 -> 50000 | AR10: =IF(I10="ECHEC",((L10+N10+P10)*20/100),0) -> 0 | AS10: =IF(I10="ECHEC",((L10+N10+P10)*20/100),0) -> 0 | AT10: =IF(I10="ECHEC",0,(L10+J10-25000)) -> 25000 | AX10: =IF(AD10=0,AJ10,(1*25000*12)+AJ10-AD10) -> 0 | AY10: =IF(AE10=0,AK10,(1*75000*12)+(AK10)-AE10) -> 0 | AZ10: =IF(AF10=0,AL10,(1*100000*12)+(AL10)-AF10) -> 0 | BA10: =SUM(AW10:AZ10)-BG10+AA10-G10+BI10+BJ10+BK10+BL10+BM10+BN10 -> 0 | BE10: =IF(BA10=0,(BA10-BB10-BD10),(BA10-BB10-BC10-BD10))+G10 -> 0 | BG10: =AA10*1/100*BH10 -> 0 | BH10: 11 | BP10: CREDIT TELEPHONE | BQ10: FONDS DE ROULEMENT
A11: AS201605 | B11: =VLOOKUP(A11,[11]LISTADHERENT!A$5:H$50,3,0) -> DJOUKWE NANGUEN GUY BLAISE | C11: =D11+E11+F11+G11-V11-BC11 -> 0 | D11: =VLOOKUP(A11,[21]HISTOBQUEJANV25!$A$6:$H$46,5,0) -> 150000 | E11: =VLOOKUP(A11,[21]HISTOBQUEJANV25!$A$6:$H$41,4,0) -> 0 | F11: =VLOOKUP(A11,[21]HISTOBQUEJANV25!$A$6:$H$41,6,0) -> 0 | H11: =IF(I11="ESPECES",3000,0) -> 0 | I11: =IF($D11<>0,"BANQUE",IF($E11<>0,"ESPECES","ECHEC")) -> BANQUE | K11: 1 | L11: =IF($D11<>0,K11*50000,IF($E11<>0,K11*50000,0)) -> 50000 | N11: =IF($D11<>0,M11*75000,IF($E11<>0,M11*75000,0)) -> 0 | O11: 1 | P11: =IF($D11<>0,O11*100000,IF($E11<>0,O11*100000,0)) -> 100000 | Q11: =VLOOKUP(A11,[13]TONTJANV24!$A$6:$R$39,12,0) -> 0 | R11: =IFERROR(VLOOKUP(A11,[14]TONTJANV24!$A$7:$P$23,10,0),0) -> 0 | S11: =IFERROR(VLOOKUP(A11,[15]TONTJANV24!$A$7:$P$20,10,0),0) -> 0 | V11: =H11+T11++S11+Q11+P11+N11+J11+L11+R11+W11+X11 -> 150000 | AR11: =IF(I11="ECHEC",((L11+N11+P11)*20/100),0) -> 0 | AS11: =IF(I11="ECHEC",((L11+N11+P11)*20/100),0) -> 0 | AT11: =IF(I11="ECHEC",0,(L11+J11-25000)) -> 25000 | AX11: =IF(AD11=0,AJ11,(1*25000*12)+AJ11-AD11) -> 0 | AY11: =IF(AE11=0,AK11,(1*75000*12)+(AK11)-AE11) -> 0 | AZ11: =IF(AF11=0,AL11,(1*100000*12)+(AL11)-AF11) -> 0 | BA11: =SUM(AW11:AZ11)-BG11+AA11-G11+BI11+BJ11+BK11+BL11+BM11+BN11 -> 0 | BE11: =IF(BA11=0,(BA11-BB11-BD11),(BA11-BB11-BC11-BD11))+G11 -> 0 | BG11: =AA11*1/100*BH11 -> 0 | BH11: 11 | BP11: PRODUCTION RAPPORT | BQ11: FONDS DE ROULEMENT
A12: AS201608 | B12: =VLOOKUP(A12,[11]LISTADHERENT!A$5:H$50,3,0) -> DJUOMBESSY ANTOINE | C12: =D12+E12+F12+G12-V12-BC12 -> 0 | D12: =VLOOKUP(A12,[21]HISTOBQUEJANV25!$A$6:$H$46,5,0) -> 260000 | E12: =VLOOKUP(A12,[21]HISTOBQUEJANV25!$A$6:$H$41,4,0) -> 0 | F12: =VLOOKUP(A12,[21]HISTOBQUEJANV25!$A$6:$H$41,6,0) -> 0 | H12: =IF(I12="ESPECES",3000,0) -> 0 | I12: =IF($D12<>0,"BANQUE",IF($E12<>0,"ESPECES","ECHEC")) -> BANQUE | J12: 10000 | K12: 1 | L12: =IF($D12<>0,K12*50000,IF($E12<>0,K12*50000,0)) -> 50000 | N12: =IF($D12<>0,M12*75000,IF($E12<>0,M12*75000,0)) -> 0 | O12: 2 | P12: =IF($D12<>0,O12*100000,IF($E12<>0,O12*100000,0)) -> 200000 | Q12: =VLOOKUP(A12,[13]TONTJANV24!$A$6:$R$39,12,0) -> 0 | R12: =IFERROR(VLOOKUP(A12,[14]TONTJANV24!$A$7:$P$23,10,0),0) -> 0 | S12: =IFERROR(VLOOKUP(A12,[15]TONTJANV24!$A$7:$P$20,10,0),0) -> 0 | V12: =H12+T12++S12+Q12+P12+N12+J12+L12+R12+W12+X12 -> 260000 | AR12: =IF(I12="ECHEC",((L12+N12+P12)*20/100),0) -> 0 | AS12: =IF(I12="ECHEC",((L12+N12+P12)*20/100),0) -> 0 | AT12: =IF(I12="ECHEC",0,(L12+J12-25000)) -> 35000 | AX12: =IF(AD12=0,AJ12,(1*25000*12)+AJ12-AD12) -> 0 | AY12: =IF(AE12=0,AK12,(1*75000*12)+(AK12)-AE12) -> 0 | AZ12: =IF(AF12=0,AL12,(1*100000*12)+(AL12)-AF12) -> 0 | BA12: =SUM(AW12:AZ12)-BG12+AA12-G12+BI12+BJ12+BK12+BL12+BM12+BN12 -> 0 | BE12: =IF(BA12=0,(BA12-BB12-BD12),(BA12-BB12-BC12-BD12))+G12 -> 0 | BG12: =AA12*1/100*BH12 -> 0 | BH12: 11 | BP12: ACHAT SOURIS ET PHOTOCOPIE | BQ12: FONDS DE ROULEMENT
A13: AS201651 | B13: =VLOOKUP(A13,[11]LISTADHERENT!A$5:H$50,3,0) -> DOMOU FABIEN | C13: =D13+E13+F13+G13-V13-BC13 -> 0 | D13: =VLOOKUP(A13,[21]HISTOBQUEJANV25!$A$6:$H$46,5,0) -> 50000 | E13: =VLOOKUP(A13,[21]HISTOBQUEJANV25!$A$6:$H$41,4,0) -> 0 | F13: =VLOOKUP(A13,[21]HISTOBQUEJANV25!$A$6:$H$41,6,0) -> 0 | H13: =IF(I13="ESPECES",3000,0) -> 0 | I13: =IF($D13<>0,"BANQUE",IF($E13<>0,"ESPECES","ECHEC")) -> BANQUE | K13: 1 | L13: =IF($D13<>0,K13*50000,IF($E13<>0,K13*50000,0)) -> 50000 | N13: =IF($D13<>0,M13*75000,IF($E13<>0,M13*75000,0)) -> 0 | P13: =IF($D13<>0,O13*100000,IF($E13<>0,O13*100000,0)) -> 0 | Q13: =VLOOKUP(A13,[13]TONTJANV24!$A$6:$R$39,12,0) -> 0 | R13: =IFERROR(VLOOKUP(A13,[14]TONTJANV24!$A$7:$P$23,10,0),0) -> 0 | S13: =IFERROR(VLOOKUP(A13,[15]TONTJANV24!$A$7:$P$20,10,0),0) -> 0 | V13: =H13+T13++S13+Q13+P13+N13+J13+L13+R13+W13+X13 -> 50000 | AR13: =IF(I13="ECHEC",((L13+N13+P13)*20/100),0) -> 0 | AS13: =IF(I13="ECHEC",((L13+N13+P13)*20/100),0) -> 0 | AT13: =IF(I13="ECHEC",0,(L13+J13-25000)) -> 25000 | AX13: =IF(AD13=0,AJ13,(1*25000*12)+AJ13-AD13) -> 0 | AY13: =IF(AE13=0,AK13,(1*75000*12)+(AK13)-AE13) -> 0 | AZ13: =IF(AF13=0,AL13,(1*100000*12)+(AL13)-AF13) -> 0 | BA13: =SUM(AW13:AZ13)-BG13+AA13-G13+BI13+BJ13+BK13+BL13+BM13+BN13 -> 0 | BE13: =IF(BA13=0,(BA13-BB13-BD13),(BA13-BB13-BC13-BD13))+G13 -> 0 | BG13: =AA13*1/100*BH13 -> 0 | BH13: 11 | BP13: TAXI BANQUE | BQ13: FONDS DE ROULEMENT
A14: AS201609 | B14: =VLOOKUP(A14,[11]LISTADHERENT!A$5:H$50,3,0) -> DONHOU DAVID | C14: =D14+E14+F14+G14-V14-BC14 -> 0 | D14: =VLOOKUP(A14,[21]HISTOBQUEJANV25!$A$6:$H$46,5,0) -> 50000 | E14: =VLOOKUP(A14,[21]HISTOBQUEJANV25!$A$6:$H$41,4,0) -> 0 | F14: =VLOOKUP(A14,[21]HISTOBQUEJANV25!$A$6:$H$41,6,0) -> 0 | H14: 0 | I14: =IF($D14<>0,"BANQUE",IF($E14<>0,"ESPECES","ECHEC")) -> BANQUE | K14: 1 | L14: =IF($D14<>0,K14*50000,IF($E14<>0,K14*50000,0)) -> 50000 | N14: =IF($D14<>0,M14*75000,IF($E14<>0,M14*75000,0)) -> 0 | P14: =IF($D14<>0,O14*100000,IF($E14<>0,O14*100000,0)) -> 0 | Q14: =VLOOKUP(A14,[13]TONTJANV24!$A$6:$R$39,12,0) -> 0 | R14: =IFERROR(VLOOKUP(A14,[14]TONTJANV24!$A$7:$P$23,10,0),0) -> 0 | S14: =IFERROR(VLOOKUP(A14,[15]TONTJANV24!$A$7:$P$20,10,0),0) -> 0 | V14: =H14+T14++S14+Q14+P14+N14+J14+L14+R14+W14+X14 -> 50000 | AR14: =IF(I14="ECHEC",((L14+N14+P14)*20/100),0) -> 0 | AS14: =IF(I14="ECHEC",((L14+N14+P14)*20/100),0) -> 0 | AT14: =IF(I14="ECHEC",0,(L14+J14-25000)) -> 25000 | AX14: =IF(AD14=0,AJ14,(1*25000*12)+AJ14-AD14) -> 0 | AY14: =IF(AE14=0,AK14,(1*75000*12)+(AK14)-AE14) -> 0 | AZ14: =IF(AF14=0,AL14,(1*100000*12)+(AL14)-AF14) -> 0 | BA14: =SUM(AW14:AZ14)-BG14+AA14-G14+BI14+BJ14+BK14+BL14+BM14+BN14 -> 0 | BE14: =IF(BA14=0,(BA14-BB14-BD14),(BA14-BB14-BC14-BD14))+G14 -> 0 | BG14: =AA14*1/100*BH14 -> 0 | BH14: 11 | BP14: ACHAT TERRAIN | BQ14: FONDS DE ROULEMENT
A15: AS201611 | B15: =VLOOKUP(A15,[11]LISTADHERENT!A$5:H$50,3,0) -> HENGUE PAUL OMER | C15: =D15+E15+F15+G15-V15-BC15 -> 0 | D15: =VLOOKUP(A15,[21]HISTOBQUEJANV25!$A$6:$H$46,5,0) -> 125000 | E15: =VLOOKUP(A15,[21]HISTOBQUEJANV25!$A$6:$H$41,4,0) -> 0 | F15: =VLOOKUP(A15,[21]HISTOBQUEJANV25!$A$6:$H$41,6,0) -> 0 | H15: =IF(I15="ESPECES",3000,0) -> 0 | I15: =IF($D15<>0,"BANQUE",IF($E15<>0,"ESPECES","ECHEC")) -> BANQUE | K15: 1 | L15: =IF($D15<>0,K15*50000,IF($E15<>0,K15*50000,0)) -> 50000 | M15: 1 | N15: =IF($D15<>0,M15*75000,IF($E15<>0,M15*75000,0)) -> 75000 | P15: =IF($D15<>0,O15*100000,IF($E15<>0,O15*100000,0)) -> 0 | Q15: =VLOOKUP(A15,[13]TONTJANV24!$A$6:$R$39,12,0) -> 0 | R15: =IFERROR(VLOOKUP(A15,[14]TONTJANV24!$A$7:$P$23,10,0),0) -> 0 | S15: =IFERROR(VLOOKUP(A15,[15]TONTJANV24!$A$7:$P$20,10,0),0) -> 0 | V15: =H15+T15++S15+Q15+P15+N15+J15+L15+R15+W15+X15 -> 125000 | AR15: =IF(I15="ECHEC",((L15+N15+P15)*20/100),0) -> 0 | AS15: =IF(I15="ECHEC",((L15+N15+P15)*20/100),0) -> 0 | AT15: =IF(I15="ECHEC",0,(L15+J15-25000)) -> 25000 | AX15: =IF(AD15=0,AJ15,(1*25000*12)+AJ15-AD15) -> 0 | AY15: =IF(AE15=0,AK15,(1*75000*12)+(AK15)-AE15) -> 0 | AZ15: =IF(AF15=0,AL15,(1*100000*12)+(AL15)-AF15) -> 0 | BA15: =SUM(AW15:AZ15)-BG15+AA15-G15+BI15+BJ15+BK15+BL15+BM15+BN15 -> 0 | BE15: =IF(BA15=0,(BA15-BB15-BD15),(BA15-BB15-BC15-BD15))+G15 -> 0 | BG15: =AA15*1/100*BH15 -> 0 | BH15: 11
A16: AS201613 | B16: =VLOOKUP(A16,[11]LISTADHERENT!A$5:H$50,3,0) -> HOTCHO BENJAMIN | C16: =D16+E16+F16+G16-V16-BC16 -> 0 | D16: =VLOOKUP(A16,[21]HISTOBQUEJANV25!$A$6:$H$46,5,0) -> 250000 | E16: =VLOOKUP(A16,[21]HISTOBQUEJANV25!$A$6:$H$41,4,0) -> 25000 | F16: =VLOOKUP(A16,[21]HISTOBQUEJANV25!$A$6:$H$41,6,0) -> 0 | H16: =IF(I16="ESPECES",3000,0) -> 0 | I16: =IF($D16<>0,"BANQUE",IF($E16<>0,"ESPECES","ECHEC")) -> BANQUE | J16: 50000 | K16: 1 | L16: =IF($D16<>0,K16*50000,IF($E16<>0,K16*50000,0)) -> 50000 | M16: 1 | N16: =IF($D16<>0,M16*75000,IF($E16<>0,M16*75000,0)) -> 75000 | O16: 1 | P16: =IF($D16<>0,O16*100000,IF($E16<>0,O16*100000,0)) -> 100000 | Q16: =VLOOKUP(A16,[13]TONTJANV24!$A$6:$R$39,12,0) -> 0 | R16: =IFERROR(VLOOKUP(A16,[14]TONTJANV24!$A$7:$P$23,10,0),0) -> 0 | S16: =IFERROR(VLOOKUP(A16,[15]TONTJANV24!$A$7:$P$20,10,0),0) -> 0 | V16: =H16+T16++S16+Q16+P16+N16+J16+L16+R16+W16+X16 -> 275000 | AR16: =IF(I16="ECHEC",((L16+N16+P16)*20/100),0) -> 0 | AS16: =IF(I16="ECHEC",((L16+N16+P16)*20/100),0) -> 0 | AT16: =IF(I16="ECHEC",0,(L16+J16-25000)) -> 75000 | AX16: =IF(AD16=0,AJ16,(1*25000*12)+AJ16-AD16) -> 0 | AY16: =IF(AE16=0,AK16,(1*75000*12)+(AK16)-AE16) -> 0 | AZ16: =IF(AF16=0,AL16,(1*100000*12)+(AL16)-AF16) -> 0 | BA16: =SUM(AW16:AZ16)-BG16+AA16-G16+BI16+BJ16+BK16+BL16+BM16+BN16 -> 0 | BE16: =IF(BA16=0,(BA16-BB16-BD16),(BA16-BB16-BC16-BD16))+G16 -> 0 | BG16: =AA16*1/100*BH16 -> 0 | BH16: 11 | BP16: S/TOTAL | BR16: =SUM(BR6:BR15) -> 27000
A17: AS201617 | B17: =VLOOKUP(A17,[11]LISTADHERENT!A$5:H$50,3,0) -> KOUAMOU MOISE | C17: =D17+E17+F17+G17-V17-BC17 -> 0 | D17: =VLOOKUP(A17,[21]HISTOBQUEJANV25!$A$6:$H$46,5,0) -> 150000 | E17: =VLOOKUP(A17,[21]HISTOBQUEJANV25!$A$6:$H$41,4,0) -> 0 | F17: =VLOOKUP(A17,[21]HISTOBQUEJANV25!$A$6:$H$41,6,0) -> 0 | H17: =IF(I17="ESPECES",3000,0) -> 0 | I17: =IF($D17<>0,"BANQUE",IF($E17<>0,"ESPECES","ECHEC")) -> BANQUE | K17: 1 | L17: =IF($D17<>0,K17*50000,IF($E17<>0,K17*50000,0)) -> 50000 | N17: =IF($D17<>0,M17*75000,IF($E17<>0,M17*75000,0)) -> 0 | O17: 1 | P17: =IF($D17<>0,O17*100000,IF($E17<>0,O17*100000,0)) -> 100000 | Q17: =VLOOKUP(A17,[13]TONTJANV24!$A$6:$R$39,12,0) -> 0 | R17: =IFERROR(VLOOKUP(A17,[14]TONTJANV24!$A$7:$P$23,10,0),0) -> 0 | S17: =IFERROR(VLOOKUP(A17,[15]TONTJANV24!$A$7:$P$20,10,0),0) -> 0 | V17: =H17+T17++S17+Q17+P17+N17+J17+L17+R17+W17+X17 -> 150000 | AR17: =IF(I17="ECHEC",((L17+N17+P17)*20/100),0) -> 0 | AS17: =IF(I17="ECHEC",((L17+N17+P17)*20/100),0) -> 0 | AT17: =IF(I17="ECHEC",0,(L17+J17-25000)) -> 25000 | AX17: =IF(AD17=0,AJ17,(1*25000*12)+AJ17-AD17) -> 0 | AY17: =IF(AE17=0,AK17,(1*75000*12)+(AK17)-AE17) -> 0 | AZ17: =IF(AF17=0,AL17,(1*100000*12)+(AL17)-AF17) -> 0 | BA17: =SUM(AW17:AZ17)-BG17+AA17-G17+BI17+BJ17+BK17+BL17+BM17+BN17+60000 -> 160000 | BE17: =IF(BA17=0,(BA17-BB17-BD17),(BA17-BB17-BC17-BD17))+G17 -> 160000 | BG17: =AA17*1/100*BH17 -> 0 | BH17: 11 | BL17: 100000
A18: AS201619 | B18: =VLOOKUP(A18,[11]LISTADHERENT!A$5:H$50,3,0) -> KOUATCHO MESSACK | C18: =D18+E18+F18+G18-V18-BC18 -> 0 | D18: =VLOOKUP(A18,[21]HISTOBQUEJANV25!$A$6:$H$46,5,0) -> 160000 | E18: =VLOOKUP(A18,[21]HISTOBQUEJANV25!$A$6:$H$41,4,0) -> 0 | F18: =VLOOKUP(A18,[21]HISTOBQUEJANV25!$A$6:$H$41,6,0) -> 0 | H18: =IF(I18="ESPECES",3000,0) -> 0 | I18: =IF($D18<>0,"BANQUE",IF($E18<>0,"ESPECES","ECHEC")) -> BANQUE | J18: 10000 | K18: 1 | L18: =IF($D18<>0,K18*50000,IF($E18<>0,K18*50000,0)) -> 50000 | N18: =IF($D18<>0,M18*75000,IF($E18<>0,M18*75000,0)) -> 0 | O18: 1 | P18: =IF($D18<>0,O18*100000,IF($E18<>0,O18*100000,0)) -> 100000 | Q18: =VLOOKUP(A18,[13]TONTJANV24!$A$6:$R$39,12,0) -> 0 | R18: =IFERROR(VLOOKUP(A18,[14]TONTJANV24!$A$7:$P$23,10,0),0) -> 0 | S18: =IFERROR(VLOOKUP(A18,[15]TONTJANV24!$A$7:$P$20,10,0),0) -> 0 | V18: =H18+T18++S18+Q18+P18+N18+J18+L18+R18+W18+X18 -> 160000 | AR18: =IF(I18="ECHEC",((L18+N18+P18)*20/100),0) -> 0 | AS18: =IF(I18="ECHEC",((L18+N18+P18)*20/100),0) -> 0 | AT18: =IF(I18="ECHEC",0,(L18+J18-25000)) -> 35000 | AX18: =IF(AD18=0,AJ18,(1*25000*12)+AJ18-AD18) -> 0 | AY18: =IF(AE18=0,AK18,(1*75000*12)+(AK18)-AE18) -> 0 | AZ18: =IF(AF18=0,AL18,(1*100000*12)+(AL18)-AF18) -> 0 | BA18: =SUM(AW18:AZ18)-BG18+AA18-G18+BI18+BJ18+BK18+BL18+BM18+BN18 -> 0 | BE18: =IF(BA18=0,(BA18-BB18-BD18),(BA18-BB18-BC18-BD18))+G18 -> 0 | BG18: =AA18*1/100*BH18 -> 0 | BH18: 11 | BP18: TERRAIN NYOM | BQ18: AUTRES DEPENSES | BR18: 300000
A19: AS201661 | B19: =VLOOKUP(A19,[11]LISTADHERENT!A$5:H$50,3,0) -> MASSEUNGOUE DAGOBERT | C19: =D19+E19+F19+G19-V19-BC19 -> 0 | D19: =VLOOKUP(A19,[21]HISTOBQUEJANV25!$A$6:$H$46,5,0) -> 650000 | E19: =VLOOKUP(A19,[21]HISTOBQUEJANV25!$A$6:$H$41,4,0) -> 0 | F19: =VLOOKUP(A19,[21]HISTOBQUEJANV25!$A$6:$H$41,6,0) -> 0 | H19: =IF(I19="ESPECES",3000,0) -> 0 | I19: =IF($D19<>0,"BANQUE",IF($E19<>0,"ESPECES","ECHEC")) -> BANQUE | J19: 600000 | K19: 1 | L19: =IF($D19<>0,K19*50000,IF($E19<>0,K19*50000,0)) -> 50000 | N19: =IF($D19<>0,M19*75000,IF($E19<>0,M19*75000,0)) -> 0 | P19: =IF($D19<>0,O19*100000,IF($E19<>0,O19*100000,0)) -> 0 | Q19: =VLOOKUP(A19,[13]TONTJANV24!$A$6:$R$39,12,0) -> 0 | R19: =IFERROR(VLOOKUP(A19,[14]TONTJANV24!$A$7:$P$23,10,0),0) -> 0 | S19: =IFERROR(VLOOKUP(A19,[15]TONTJANV24!$A$7:$P$20,10,0),0) -> 0 | V19: =H19+T19++S19+Q19+P19+N19+J19+L19+R19+W19+X19 -> 650000 | AR19: =IF(I19="ECHEC",((L19+N19+P19)*20/100),0) -> 0 | AS19: =IF(I19="ECHEC",((L19+N19+P19)*20/100),0) -> 0 | AT19: =IF(I19="ECHEC",0,(L19+J19-25000)) -> 625000 | AX19: =IF(AD19=0,AJ19,(1*25000*12)+AJ19-AD19) -> 0 | AY19: =IF(AE19=0,AK19,(1*75000*12)+(AK19)-AE19) -> 0 | AZ19: =IF(AF19=0,AL19,(1*100000*12)+(AL19)-AF19) -> 0 | BA19: =SUM(AW19:AZ19)-BG19+AA19-G19+BI19+BJ19+BK19+BL19+BM19+BN19 -> 0 | BE19: =IF(BA19=0,(BA19-BB19-BD19),(BA19-BB19-BC19-BD19))+G19 -> 0 | BG19: =AA19*1/100*BH19 -> 0 | BH19: 11
A20: AS201649 | B20: =VLOOKUP(A20,[11]LISTADHERENT!A$5:H$50,3,0) -> MBOGNING TUGMA GUY | C20: =D20+E20+F20+G20-V20-BC20 -> 0 | D20: =VLOOKUP(A20,[21]HISTOBQUEJANV25!$A$6:$H$46,5,0) -> 325000 | E20: =VLOOKUP(A20,[21]HISTOBQUEJANV25!$A$6:$H$41,4,0) -> 0 | F20: =VLOOKUP(A20,[21]HISTOBQUEJANV25!$A$6:$H$41,6,0) -> 0 | H20: =IF(I20="ESPECES",3000,0) -> 0 | I20: =IF($D20<>0,"BANQUE",IF($E20<>0,"ESPECES","ECHEC")) -> BANQUE | K20: 1 | L20: =IF($D20<>0,K20*50000,IF($E20<>0,K20*50000,0)) -> 50000 | M20: 1 | N20: =IF($D20<>0,M20*75000,IF($E20<>0,M20*75000,0)) -> 75000 | O20: 2 | P20: =IF($D20<>0,O20*100000,IF($E20<>0,O20*100000,0)) -> 200000 | Q20: =VLOOKUP(A20,[13]TONTJANV24!$A$6:$R$39,12,0) -> 0 | R20: =IFERROR(VLOOKUP(A20,[14]TONTJANV24!$A$7:$P$23,10,0),0) -> 0 | S20: =IFERROR(VLOOKUP(A20,[15]TONTJANV24!$A$7:$P$20,10,0),0) -> 0 | V20: =H20+T20++S20+Q20+P20+N20+J20+L20+R20+W20+X20 -> 325000 | AR20: =IF(I20="ECHEC",((L20+N20+P20)*20/100),0) -> 0 | AS20: =IF(I20="ECHEC",((L20+N20+P20)*20/100),0) -> 0 | AT20: =IF(I20="ECHEC",0,(L20+J20-25000)) -> 25000 | AX20: =IF(AD20=0,AJ20,(1*25000*12)+AJ20-AD20) -> 0 | AY20: =IF(AE20=0,AK20,(1*75000*12)+(AK20)-AE20) -> 0 | AZ20: =IF(AF20=0,AL20,(1*100000*12)+(AL20)-AF20) -> 0 | BA20: =SUM(AW20:AZ20)-BG20+AA20-G20+BI20+BJ20+BK20+BL20+BM20+BN20 -> 0 | BE20: =IF(BA20=0,(BA20-BB20-BD20),(BA20-BB20-BC20-BD20))+G20 -> 0 | BG20: =AA20*1/100*BH20 -> 0 | BH20: 11
A21: AS201639 | B21: =VLOOKUP(A21,[11]LISTADHERENT!A$5:H$50,3,0) -> NANGUEN MARTIN | C21: =D21+E21+F21+G21-V21-BC21 -> 0 | D21: =VLOOKUP(A21,[21]HISTOBQUEJANV25!$A$6:$H$46,5,0) -> 50000 | E21: =VLOOKUP(A21,[21]HISTOBQUEJANV25!$A$6:$H$41,4,0) -> 0 | F21: =VLOOKUP(A21,[21]HISTOBQUEJANV25!$A$6:$H$41,6,0) -> 0 | H21: =IF(I21="ESPECES",3000,0) -> 0 | I21: =IF($D21<>0,"BANQUE",IF($E21<>0,"ESPECES","ECHEC")) -> BANQUE | K21: 1 | L21: =IF($D21<>0,K21*50000,IF($E21<>0,K21*50000,0)) -> 50000 | N21: =IF($D21<>0,M21*75000,IF($E21<>0,M21*75000,0)) -> 0 | P21: =IF($D21<>0,O21*100000,IF($E21<>0,O21*100000,0)) -> 0 | Q21: =VLOOKUP(A21,[13]TONTJANV24!$A$6:$R$39,12,0) -> 0 | R21: =IFERROR(VLOOKUP(A21,[14]TONTJANV24!$A$7:$P$23,10,0),0) -> 0 | S21: =IFERROR(VLOOKUP(A21,[15]TONTJANV24!$A$7:$P$20,10,0),0) -> 0 | V21: =H21+T21++S21+Q21+P21+N21+J21+L21+R21+W21+X21 -> 50000 | AR21: =IF(I21="ECHEC",((L21+N21+P21)*20/100),0) -> 0 | AS21: =IF(I21="ECHEC",((L21+N21+P21)*20/100),0) -> 0 | AT21: =IF(I21="ECHEC",0,(L21+J21-25000)) -> 25000 | AX21: =IF(AD21=0,AJ21,(1*25000*12)+AJ21-AD21) -> 0 | AY21: =IF(AE21=0,AK21,(1*75000*12)+(AK21)-AE21) -> 0 | AZ21: =IF(AF21=0,AL21,(1*100000*12)+(AL21)-AF21) -> 0 | BA21: =SUM(AW21:AZ21)-BG21+AA21-G21+BI21+BJ21+BK21+BL21+BM21+BN21 -> 0 | BE21: =IF(BA21=0,(BA21-BB21-BD21),(BA21-BB21-BC21-BD21))+G21 -> 0 | BG21: =AA21*1/100*BH21 -> 0 | BH21: 11
A22: AS201621 | B22: =VLOOKUP(A22,[11]LISTADHERENT!A$5:H$50,3,0) -> NANKAM APPOLINAIRE | C22: =D22+E22+F22+G22-V22-BC22 -> 0 | D22: =VLOOKUP(A22,[21]HISTOBQUEJANV25!$A$6:$H$46,5,0) -> 125000 | E22: =VLOOKUP(A22,[21]HISTOBQUEJANV25!$A$6:$H$41,4,0) -> 0 | F22: =VLOOKUP(A22,[21]HISTOBQUEJANV25!$A$6:$H$41,6,0) -> 0 | H22: =IF(I22="ESPECES",3000,0) -> 0 | I22: =IF($D22<>0,"BANQUE",IF($E22<>0,"ESPECES","ECHEC")) -> BANQUE | K22: 1 | L22: =IF($D22<>0,K22*50000,IF($E22<>0,K22*50000,0)) -> 50000 | M22: 1 | N22: =IF($D22<>0,M22*75000,IF($E22<>0,M22*75000,0)) -> 75000 | P22: =IF($D22<>0,O22*100000,IF($E22<>0,O22*100000,0)) -> 0 | Q22: =VLOOKUP(A22,[13]TONTJANV24!$A$6:$R$39,12,0) -> 0 | R22: =IFERROR(VLOOKUP(A22,[14]TONTJANV24!$A$7:$P$23,10,0),0) -> 0 | S22: =IFERROR(VLOOKUP(A22,[15]TONTJANV24!$A$7:$P$20,10,0),0) -> 0 | V22: =H22+T22++S22+Q22+P22+N22+J22+L22+R22+W22+X22 -> 125000 | AR22: =IF(I22="ECHEC",((L22+N22+P22)*20/100),0) -> 0 | AS22: =IF(I22="ECHEC",((L22+N22+P22)*20/100),0) -> 0 | AT22: =IF(I22="ECHEC",0,(L22+J22-25000)) -> 25000 | AX22: =IF(AD22=0,AJ22,(1*25000*12)+AJ22-AD22) -> 0 | AY22: =IF(AE22=0,AK22,(1*75000*12)+(AK22)-AE22) -> 0 | AZ22: =IF(AF22=0,AL22,(1*100000*12)+(AL22)-AF22) -> 0 | BA22: =SUM(AW22:AZ22)-BG22+AA22-G22+BI22+BJ22+BK22+BL22+BM22+BN22 -> 0 | BE22: =IF(BA22=0,(BA22-BB22-BD22),(BA22-BB22-BC22-BD22))+G22 -> 0 | BG22: =AA22*1/100*BH22 -> 0 | BH22: 11 | BP22: S/TOTAL | BR22: =SUM(BR18:BR21) -> 300000
A23: AS201622 | B23: =VLOOKUP(A23,[11]LISTADHERENT!A$5:H$50,3,0) -> NDJOMO ETIENNE | C23: =D23+E23+F23+G23-V23-BC23 -> 0 | D23: =VLOOKUP(A23,[21]HISTOBQUEJANV25!$A$6:$H$46,5,0) -> 260000 | E23: =VLOOKUP(A23,[21]HISTOBQUEJANV25!$A$6:$H$41,4,0) -> 0 | F23: =VLOOKUP(A23,[21]HISTOBQUEJANV25!$A$6:$H$41,6,0) -> 0 | H23: =IF(I23="ESPECES",3000,0) -> 0 | I23: =IF($D23<>0,"BANQUE",IF($E23<>0,"ESPECES","ECHEC")) -> BANQUE | J23: 10000 | K23: 1 | L23: =IF($D23<>0,K23*50000,IF($E23<>0,K23*50000,0)) -> 50000 | N23: =IF($D23<>0,M23*75000,IF($E23<>0,M23*75000,0)) -> 0 | O23: 2 | P23: =IF($D23<>0,O23*100000,IF($E23<>0,O23*100000,0)) -> 200000 | Q23: =VLOOKUP(A23,[13]TONTJANV24!$A$6:$R$39,12,0) -> 0 | R23: =IFERROR(VLOOKUP(A23,[14]TONTJANV24!$A$7:$P$23,10,0),0) -> 0 | S23: =IFERROR(VLOOKUP(A23,[15]TONTJANV24!$A$7:$P$20,10,0),0) -> 0 | V23: =H23+T23++S23+Q23+P23+N23+J23+L23+R23+W23+X23 -> 260000 | AR23: =IF(I23="ECHEC",((L23+N23+P23)*20/100),0) -> 0 | AS23: =IF(I23="ECHEC",((L23+N23+P23)*20/100),0) -> 0 | AT23: =IF(I23="ECHEC",0,(L23+J23-25000)) -> 35000 | AX23: =IF(AD23=0,AJ23,(1*25000*12)+AJ23-AD23) -> 0 | AY23: =IF(AE23=0,AK23,(1*75000*12)+(AK23)-AE23) -> 0 | AZ23: =IF(AF23=0,AL23,(1*100000*12)+(AL23)-AF23) -> 0 | BA23: =SUM(AW23:AZ23)-BG23+AA23-G23+BI23+BJ23+BK23+BL23+BM23+BN23 -> 0 | BE23: =IF(BA23=0,(BA23-BB23-BD23),(BA23-BB23-BC23-BD23))+G23+56000 -> 56000 | BG23: =AA23*1/100*BH23 -> 0 | BH23: 11
A24: AS201624 | B24: =VLOOKUP(A24,[11]LISTADHERENT!A$5:H$50,3,0) -> NGONDIEP CLAUDE | C24: =D24+E24+F24+G24-V24-BC24 -> 0 | D24: =VLOOKUP(A24,[21]HISTOBQUEJANV25!$A$6:$H$46,5,0) -> 240000 | E24: =VLOOKUP(A24,[21]HISTOBQUEJANV25!$A$6:$H$41,4,0) -> 0 | F24: =VLOOKUP(A24,[21]HISTOBQUEJANV25!$A$6:$H$41,6,0) -> 0 | H24: =IF(I24="ESPECES",3000,0) -> 0 | I24: =IF($D24<>0,"BANQUE",IF($E24<>0,"ESPECES","ECHEC")) -> BANQUE | J24: 15000 | K24: 1 | L24: =IF($D24<>0,K24*50000,IF($E24<>0,K24*50000,0)) -> 50000 | M24: 1 | N24: =IF($D24<>0,M24*75000,IF($E24<>0,M24*75000,0)) -> 75000 | O24: 1 | P24: =IF($D24<>0,O24*100000,IF($E24<>0,O24*100000,0)) -> 100000 | Q24: =VLOOKUP(A24,[13]TONTJANV24!$A$6:$R$39,12,0) -> 0 | R24: =IFERROR(VLOOKUP(A24,[14]TONTJANV24!$A$7:$P$23,10,0),0) -> 0 | S24: =IFERROR(VLOOKUP(A24,[15]TONTJANV24!$A$7:$P$20,10,0),0) -> 0 | V24: =H24+T24++S24+Q24+P24+N24+J24+L24+R24+W24+X24 -> 240000 | AR24: =IF(I24="ECHEC",((L24+N24+P24)*20/100),0) -> 0 | AS24: =IF(I24="ECHEC",((L24+N24+P24)*20/100),0) -> 0 | AT24: =IF(I24="ECHEC",0,(L24+J24-25000)) -> 40000 | AX24: =IF(AD24=0,AJ24,(1*25000*12)+AJ24-AD24) -> 0 | AY24: =IF(AE24=0,AK24,(1*75000*12)+(AK24)-AE24) -> 0 | AZ24: =IF(AF24=0,AL24,(1*100000*12)+(AL24)-AF24) -> 0 | BA24: =SUM(AW24:AZ24)-BG24+AA24-G24+BI24+BJ24+BK24+BL24+BM24+BN24 -> 0 | BE24: =IF(BA24=0,(BA24-BB24-BD24),(BA24-BB24-BC24-BD24))+G24 -> 0 | BG24: =AA24*1/100*BH24 -> 0 | BH24: 11 | BP24: GRATIFICATION BUREAU 2023 | BQ24: FRAIS EXEPTIONNEL | BR24: 200000
A25: AS201626 | B25: =VLOOKUP(A25,[11]LISTADHERENT!A$5:H$50,3,0) -> NGUIEMEGNI MATHIEU BLAISE | C25: =D25+E25+F25+G25-V25-BC25 -> 0 | D25: =VLOOKUP(A25,[21]HISTOBQUEJANV25!$A$6:$H$46,5,0) -> 225000 | E25: =VLOOKUP(A25,[21]HISTOBQUEJANV25!$A$6:$H$41,4,0) -> 25000 | F25: =VLOOKUP(A25,[21]HISTOBQUEJANV25!$A$6:$H$41,6,0) -> 0 | H25: =IF(I25="ESPECES",3000,0) -> 0 | I25: =IF($D25<>0,"BANQUE",IF($E25<>0,"ESPECES","ECHEC")) -> BANQUE | K25: 1 | L25: =IF($D25<>0,K25*50000,IF($E25<>0,K25*50000,0)) -> 50000 | N25: =IF($D25<>0,M25*75000,IF($E25<>0,M25*75000,0)) -> 0 | O25: 2 | P25: =IF($D25<>0,O25*100000,IF($E25<>0,O25*100000,0)) -> 200000 | Q25: =VLOOKUP(A25,[13]TONTJANV24!$A$6:$R$39,12,0) -> 0 | R25: =IFERROR(VLOOKUP(A25,[14]TONTJANV24!$A$7:$P$23,10,0),0) -> 0 | S25: =IFERROR(VLOOKUP(A25,[15]TONTJANV24!$A$7:$P$20,10,0),0) -> 0 | V25: =H25+T25++S25+Q25+P25+N25+J25+L25+R25+W25+X25 -> 250000 | AR25: =IF(I25="ECHEC",((L25+N25+P25)*20/100),0) -> 0 | AS25: =IF(I25="ECHEC",((L25+N25+P25)*20/100),0) -> 0 | AT25: =IF(I25="ECHEC",0,(L25+J25-25000)) -> 25000 | AX25: =IF(AD25=0,AJ25,(1*25000*12)+AJ25-AD25) -> 0 | AY25: =IF(AE25=0,AK25,(1*75000*12)+(AK25)-AE25) -> 0 | AZ25: =IF(AF25=0,AL25,(1*100000*12)+(AL25)-AF25) -> 0 | BA25: =SUM(AW25:AZ25)-BG25+AA25-G25+BI25+BJ25+BK25+BL25+BM25+BN25 -> 0 | BE25: =IF(BA25=0,(BA25-BB25-BD25),(BA25-BB25-BC25-BD25))+G25 -> 0 | BG25: =AA25*1/100*BH25 -> 0 | BH25: 11 | BP25: DOSSIER TECHNIQUE NGIEMENI | BQ25: FRAIS EXEPTIONNEL
A26: AS201628 | B26: =VLOOKUP(A26,[11]LISTADHERENT!A$5:H$50,3,0) -> NKAMGANG JUSTIN DEJOLIE | C26: =D26+E26+F26+G26-V26-BC26 -> 0 | D26: =VLOOKUP(A26,[21]HISTOBQUEJANV25!$A$6:$H$46,5,0) -> 50000 | E26: =VLOOKUP(A26,[21]HISTOBQUEJANV25!$A$6:$H$41,4,0) -> 0 | F26: =VLOOKUP(A26,[21]HISTOBQUEJANV25!$A$6:$H$41,6,0) -> 0 | H26: =IF(I26="ESPECES",3000,0) -> 0 | I26: =IF($D26<>0,"BANQUE",IF($E26<>0,"ESPECES","ECHEC")) -> BANQUE | K26: 1 | L26: =IF($D26<>0,K26*50000,IF($E26<>0,K26*50000,0)) -> 50000 | N26: =IF($D26<>0,M26*75000,IF($E26<>0,M26*75000,0)) -> 0 | P26: =IF($D26<>0,O26*100000,IF($E26<>0,O26*100000,0)) -> 0 | Q26: =VLOOKUP(A26,[13]TONTJANV24!$A$6:$R$39,12,0) -> 0 | R26: =IFERROR(VLOOKUP(A26,[14]TONTJANV24!$A$7:$P$23,10,0),0) -> 0 | S26: =IFERROR(VLOOKUP(A26,[15]TONTJANV24!$A$7:$P$20,10,0),0) -> 0 | V26: =H26+T26++S26+Q26+P26+N26+J26+L26+R26+W26+X26 -> 50000 | AR26: =IF(I26="ECHEC",((L26+N26+P26)*20/100),0) -> 0 | AS26: =IF(I26="ECHEC",((L26+N26+P26)*20/100),0) -> 0 | AT26: =IF(I26="ECHEC",0,(L26+J26-25000)) -> 25000 | AX26: =IF(AD26=0,AJ26,(1*25000*12)+AJ26-AD26) -> 0 | AY26: =IF(AE26=0,AK26,(1*75000*12)+(AK26)-AE26) -> 0 | AZ26: =IF(AF26=0,AL26,(1*100000*12)+(AL26)-AF26) -> 0 | BA26: =SUM(AW26:AZ26)-BG26+AA26-G26+BI26+BJ26+BK26+BL26+BM26+BN26 -> 0 | BE26: =IF(BA26=0,(BA26-BB26-BD26),(BA26-BB26-BC26-BD26))+G26 -> 0 | BG26: =AA26*1/100*BH26 -> 0 | BH26: 11 | BP26: DEUIL TCHEMNOU EMMANUEL | BQ26: FRAIS EXEPTIONNEL
A27: AS201656 | B27: =VLOOKUP(A27,[11]LISTADHERENT!A$5:H$50,3,0) -> NOUBE ETIENNE | C27: =D27+E27+F27+G27-V27-BC27 -> 0 | D27: =VLOOKUP(A27,[21]HISTOBQUEJANV25!$A$6:$H$46,5,0) -> 50000 | E27: =VLOOKUP(A27,[21]HISTOBQUEJANV25!$A$6:$H$41,4,0) -> 0 | F27: =VLOOKUP(A27,[21]HISTOBQUEJANV25!$A$6:$H$41,6,0) -> 0 | H27: =IF(I27="ESPECES",3000,0) -> 0 | I27: =IF($D27<>0,"BANQUE",IF($E27<>0,"ESPECES","ECHEC")) -> BANQUE | K27: 1 | L27: =IF($D27<>0,K27*50000,IF($E27<>0,K27*50000,0)) -> 50000 | N27: =IF($D27<>0,M27*75000,IF($E27<>0,M27*75000,0)) -> 0 | P27: =IF($D27<>0,O27*100000,IF($E27<>0,O27*100000,0)) -> 0 | Q27: =VLOOKUP(A27,[13]TONTJANV24!$A$6:$R$39,12,0) -> 0 | R27: =IFERROR(VLOOKUP(A27,[14]TONTJANV24!$A$7:$P$23,10,0),0) -> 0 | S27: =IFERROR(VLOOKUP(A27,[15]TONTJANV24!$A$7:$P$20,10,0),0) -> 0 | V27: =H27+T27++S27+Q27+P27+N27+J27+L27+R27+W27+X27 -> 50000 | AR27: =IF(I27="ECHEC",((L27+N27+P27)*20/100),0) -> 0 | AS27: =IF(I27="ECHEC",((L27+N27+P27)*20/100),0) -> 0 | AT27: =IF(I27="ECHEC",0,(L27+J27-25000)) -> 25000 | AX27: =IF(AD27=0,AJ27,(1*25000*12)+AJ27-AD27) -> 0 | AY27: =IF(AE27=0,AK27,(1*75000*12)+(AK27)-AE27) -> 0 | AZ27: =IF(AF27=0,AL27,(1*100000*12)+(AL27)-AF27) -> 0 | BA27: =SUM(AW27:AZ27)-BG27+AA27-G27+BI27+BJ27+BK27+BL27+BM27+BN27 -> 0 | BE27: =IF(BA27=0,(BA27-BB27-BD27),(BA27-BB27-BC27-BD27))+G27 -> 0 | BG27: =AA27*1/100*BH27 -> 0 | BH27: 11
A28: AS201633 | B28: =VLOOKUP(A28,[11]LISTADHERENT!A$5:H$50,3,0) -> PATEGO NJOSSU GUSTAVE | C28: =D28+E28+F28+G28-V28-BC28 -> 0 | D28: =VLOOKUP(A28,[21]HISTOBQUEJANV25!$A$6:$H$46,5,0) -> 125000 | E28: =VLOOKUP(A28,[21]HISTOBQUEJANV25!$A$6:$H$41,4,0) -> 0 | F28: =VLOOKUP(A28,[21]HISTOBQUEJANV25!$A$6:$H$41,6,0) -> 0 | H28: =IF(I28="ESPECES",3000,0) -> 0 | I28: =IF($D28<>0,"BANQUE",IF($E28<>0,"ESPECES","ECHEC")) -> BANQUE | K28: 1 | L28: =IF($D28<>0,K28*50000,IF($E28<>0,K28*50000,0)) -> 50000 | M28: 1 | N28: =IF($D28<>0,M28*75000,IF($E28<>0,M28*75000,0)) -> 75000 | P28: =IF($D28<>0,O28*100000,IF($E28<>0,O28*100000,0)) -> 0 | Q28: =VLOOKUP(A28,[13]TONTJANV24!$A$6:$R$39,12,0) -> 0 | R28: =IFERROR(VLOOKUP(A28,[14]TONTJANV24!$A$7:$P$23,10,0),0) -> 0 | S28: =IFERROR(VLOOKUP(A28,[15]TONTJANV24!$A$7:$P$20,10,0),0) -> 0 | V28: =H28+T28++S28+Q28+P28+N28+J28+L28+R28+W28+X28 -> 125000 | AR28: =IF(I28="ECHEC",((L28+N28+P28)*20/100),0) -> 0 | AS28: =IF(I28="ECHEC",((L28+N28+P28)*20/100),0) -> 0 | AT28: =IF(I28="ECHEC",0,(L28+J28-25000)) -> 25000 | AX28: =IF(AD28=0,AJ28,(1*25000*12)+AJ28-AD28) -> 0 | AY28: =IF(AE28=0,AK28,(1*75000*12)+(AK28)-AE28) -> 0 | AZ28: =IF(AF28=0,AL28,(1*100000*12)+(AL28)-AF28) -> 0 | BA28: =SUM(AW28:AZ28)-BG28+AA28-G28+BI28+BJ28+BK28+BL28+BM28+BN28 -> 0 | BE28: =IF(BA28=0,(BA28-BB28-BD28),(BA28-BB28-BC28-BD28))+G28 -> 0 | BG28: =AA28*1/100*BH28 -> 0 | BH28: 11 | BP28: S/TOTAL | BR28: =SUM(BR24:BR26) -> 200000
A29: AS201657 | B29: =VLOOKUP(A29,[11]LISTADHERENT!A$5:H$50,3,0) -> SEUMO POLYCARPE | C29: =D29+E29+F29+G29-V29-BC29 -> 0 | D29: =VLOOKUP(A29,[21]HISTOBQUEJANV25!$A$6:$H$46,5,0) -> 50000 | E29: =VLOOKUP(A29,[21]HISTOBQUEJANV25!$A$6:$H$41,4,0) -> 0 | F29: =VLOOKUP(A29,[21]HISTOBQUEJANV25!$A$6:$H$41,6,0) -> 0 | H29: =IF(I29="ESPECES",3000,0) -> 0 | I29: =IF($D29<>0,"BANQUE",IF($E29<>0,"ESPECES","ECHEC")) -> BANQUE | K29: 1 | L29: =IF($D29<>0,K29*50000,IF($E29<>0,K29*50000,0)) -> 50000 | N29: =IF($D29<>0,M29*75000,IF($E29<>0,M29*75000,0)) -> 0 | P29: =IF($D29<>0,O29*100000,IF($E29<>0,O29*100000,0)) -> 0 | Q29: =VLOOKUP(A29,[13]TONTJANV24!$A$6:$R$39,12,0) -> 0 | R29: =IFERROR(VLOOKUP(A29,[14]TONTJANV24!$A$7:$P$23,10,0),0) -> 0 | S29: =IFERROR(VLOOKUP(A29,[15]TONTJANV24!$A$7:$P$20,10,0),0) -> 0 | V29: =H29+T29++S29+Q29+P29+N29+J29+L29+R29+W29+X29 -> 50000 | AR29: =IF(I29="ECHEC",((L29+N29+P29)*20/100),0) -> 0 | AS29: =IF(I29="ECHEC",((L29+N29+P29)*20/100),0) -> 0 | AT29: =IF(I29="ECHEC",0,(L29+J29-25000)) -> 25000 | AX29: =IF(AD29=0,AJ29,(1*25000*12)+AJ29-AD29) -> 0 | AY29: =IF(AE29=0,AK29,(1*75000*12)+(AK29)-AE29) -> 0 | AZ29: =IF(AF29=0,AL29,(1*100000*12)+(AL29)-AF29) -> 0 | BA29: =SUM(AW29:AZ29)-BG29+AA29-G29+BI29+BJ29+BK29+BL29+BM29+BN29 -> 0 | BE29: =IF(BA29=0,(BA29-BB29-BD29),(BA29-BB29-BC29-BD29))+G29 -> 0 | BG29: =AA29*1/100*BH29 -> 0 | BH29: 11
A30: AS201653 | B30: =VLOOKUP(A30,[11]LISTADHERENT!A$5:H$50,3,0) -> SIME BRICE | C30: =D30+E30+F30+G30-V30-BC30 -> 0 | D30: =VLOOKUP(A30,[21]HISTOBQUEJANV25!$A$6:$H$46,5,0) -> 250000 | E30: =VLOOKUP(A30,[21]HISTOBQUEJANV25!$A$6:$H$41,4,0) -> 0 | F30: =VLOOKUP(A30,[21]HISTOBQUEJANV25!$A$6:$H$41,6,0) -> 0 | H30: =IF(I30="ESPECES",3000,0) -> 0 | I30: =IF($D30<>0,"BANQUE",IF($E30<>0,"ESPECES","ECHEC")) -> BANQUE | K30: 1 | L30: =IF($D30<>0,K30*50000,IF($E30<>0,K30*50000,0)) -> 50000 | N30: =IF($D30<>0,M30*75000,IF($E30<>0,M30*75000,0)) -> 0 | O30: 2 | P30: =IF($D30<>0,O30*100000,IF($E30<>0,O30*100000,0)) -> 200000 | Q30: =VLOOKUP(A30,[13]TONTJANV24!$A$6:$R$39,12,0) -> 0 | R30: =IFERROR(VLOOKUP(A30,[14]TONTJANV24!$A$7:$P$23,10,0),0) -> 0 | S30: =IFERROR(VLOOKUP(A30,[15]TONTJANV24!$A$7:$P$20,10,0),0) -> 0 | V30: =H30+T30++S30+Q30+P30+N30+J30+L30+R30+W30+X30 -> 250000 | AR30: =IF(I30="ECHEC",((L30+N30+P30)*20/100),0) -> 0 | AS30: =IF(I30="ECHEC",((L30+N30+P30)*20/100),0) -> 0 | AT30: =IF(I30="ECHEC",0,(L30+J30-25000)) -> 25000 | AX30: =IF(AD30=0,AJ30,(1*25000*12)+AJ30-AD30) -> 0 | AY30: =IF(AE30=0,AK30,(1*75000*12)+(AK30)-AE30) -> 0 | AZ30: =IF(AF30=0,AL30,(1*100000*12)+(AL30)-AF30) -> 0 | BA30: =SUM(AW30:AZ30)-BG30+AA30-G30+BI30+BJ30+BK30+BL30+BM30+BN30 -> 0 | BE30: =IF(BA30=0,(BA30-BB30-BD30),(BA30-BB30-BC30-BD30))+G30 -> 0 | BG30: =AA30*1/100*BH30 -> 0 | BH30: 11 | BP30: DECES | BQ30: MUTUELLE
A31: AS201629 | B31: =VLOOKUP(A31,[11]LISTADHERENT!A$5:H$50,3,0) -> SIMO FONGANG ERIC | C31: =D31+E31+F31+G31-V31-BC31 -> #N/A | D31: =VLOOKUP(A31,[21]HISTOBQUEJANV25!$A$6:$H$46,5,0) -> 50000 | E31: =VLOOKUP(A31,[21]HISTOBQUEJANV25!$A$6:$H$41,4,0) -> 0 | F31: =VLOOKUP(A31,[21]HISTOBQUEJANV25!$A$6:$H$41,6,0) -> 0 | H31: =IF(I31="ESPECES",3000,0) -> 0 | I31: =IF($D31<>0,"BANQUE",IF($E31<>0,"ESPECES","ECHEC")) -> BANQUE | K31: 1 | L31: =IF($D31<>0,K31*50000,IF($E31<>0,K31*50000,0)) -> 50000 | Q31: =VLOOKUP(A31,[13]TONTJANV24!$A$6:$R$39,12,0) -> #N/A | R31: =IFERROR(VLOOKUP(A31,[14]TONTJANV24!$A$7:$P$23,10,0),0) -> 0 | S31: =IFERROR(VLOOKUP(A31,[15]TONTJANV24!$A$7:$P$20,10,0),0) -> 0 | V31: =H31+T31++S31+Q31+P31+N31+J31+L31+R31+W31+X31 -> #N/A
A32: AS201638 | B32: =VLOOKUP(A32,[11]LISTADHERENT!A$5:H$50,3,0) -> SIMO PIERRE | C32: =D32+E32+F32+G32-V32-BC32 -> 0 | D32: =VLOOKUP(A32,[21]HISTOBQUEJANV25!$A$6:$H$46,5,0) -> 150000 | E32: =VLOOKUP(A32,[21]HISTOBQUEJANV25!$A$6:$H$41,4,0) -> 0 | F32: =VLOOKUP(A32,[21]HISTOBQUEJANV25!$A$6:$H$41,6,0) -> 0 | H32: =IF(I32="ESPECES",3000,0) -> 0 | I32: =IF($D32<>0,"BANQUE",IF($E32<>0,"ESPECES","ECHEC")) -> BANQUE | K32: 1 | L32: =IF($D32<>0,K32*50000,IF($E32<>0,K32*50000,0)) -> 50000 | N32: =IF($D32<>0,M32*75000,IF($E32<>0,M32*75000,0)) -> 0 | O32: 1 | P32: =IF($D32<>0,O32*100000,IF($E32<>0,O32*100000,0)) -> 100000 | Q32: =VLOOKUP(A32,[13]TONTJANV24!$A$6:$R$39,12,0) -> 0 | R32: =IFERROR(VLOOKUP(A32,[14]TONTJANV24!$A$7:$P$23,10,0),0) -> 0 | S32: =IFERROR(VLOOKUP(A32,[15]TONTJANV24!$A$7:$P$20,10,0),0) -> 0 | V32: =H32+T32++S32+Q32+P32+N32+J32+L32+R32+W32+X32 -> 150000 | AR32: =IF(I32="ECHEC",((L32+N32+P32)*20/100),0) -> 0 | AS32: =IF(I32="ECHEC",((L32+N32+P32)*20/100),0) -> 0 | AT32: =IF(I32="ECHEC",0,(L32+J32-25000)) -> 25000 | AX32: =IF(AD32=0,AJ32,(1*25000*12)+AJ32-AD32) -> 0 | AY32: =IF(AE32=0,AK32,(1*75000*12)+(AK32)-AE32) -> 0 | AZ32: =IF(AF32=0,AL32,(1*100000*12)+(AL32)-AF32) -> 0 | BA32: =SUM(AW32:AZ32)-BG32+AA32-G32+BI32+BJ32+BK32+BL32+BM32+BN32 -> 0 | BE32: =IF(BA32=0,(BA32-BB32-BD32),(BA32-BB32-BC32-BD32))+G32 -> 0 | BG32: =AA32*1/100*BH32 -> 0 | BH32: 11 | BP32: TRANSPORT DELEGUE | BQ32: MUTUELLE
A33: AS201641 | B33: =VLOOKUP(A33,[11]LISTADHERENT!A$5:H$50,3,0) -> TCHOUAMOU MATHIEU | C33: =D33+E33+F33+G33-V33-BC33 -> 0 | D33: =VLOOKUP(A33,[21]HISTOBQUEJANV25!$A$6:$H$46,5,0) -> 125000 | E33: =VLOOKUP(A33,[21]HISTOBQUEJANV25!$A$6:$H$41,4,0) -> 0 | F33: =VLOOKUP(A33,[21]HISTOBQUEJANV25!$A$6:$H$41,6,0) -> 0 | H33: =IF(I33="ESPECES",3000,0) -> 0 | I33: =IF($D33<>0,"BANQUE",IF($E33<>0,"ESPECES","ECHEC")) -> BANQUE | K33: 1 | L33: =IF($D33<>0,K33*50000,IF($E33<>0,K33*50000,0)) -> 50000 | M33: 1 | N33: =IF($D33<>0,M33*75000,IF($E33<>0,M33*75000,0)) -> 75000 | P33: =IF($D33<>0,O33*100000,IF($E33<>0,O33*100000,0)) -> 0 | Q33: =VLOOKUP(A33,[13]TONTJANV24!$A$6:$R$39,12,0) -> 0 | R33: =IFERROR(VLOOKUP(A33,[14]TONTJANV24!$A$7:$P$23,10,0),0) -> 0 | S33: =IFERROR(VLOOKUP(A33,[15]TONTJANV24!$A$7:$P$20,10,0),0) -> 0 | V33: =H33+T33++S33+Q33+P33+N33+J33+L33+R33+W33+X33 -> 125000 | AR33: =IF(I33="ECHEC",((L33+N33+P33)*20/100),0) -> 0 | AS33: =IF(I33="ECHEC",((L33+N33+P33)*20/100),0) -> 0 | AT33: =IF(I33="ECHEC",0,(L33+J33-25000)) -> 25000 | AX33: =IF(AD33=0,AJ33,(1*25000*12)+AJ33-AD33) -> 0 | AY33: =IF(AE33=0,AK33,(1*75000*12)+(AK33)-AE33) -> 0 | AZ33: =IF(AF33=0,AL33,(1*100000*12)+(AL33)-AF33) -> 0 | BA33: =SUM(AW33:AZ33)-BG33+AA33-G33+BI33+BJ33+BK33+BL33+BM33+BN33 -> 0 | BE33: =IF(BA33=0,(BA33-BB33-BD33),(BA33-BB33-BC33-BD33))+G33 -> 0 | BG33: =AA33*1/100*BH33 -> 0 | BH33: 6
A34: AS201660 | B34: =VLOOKUP(A34,[11]LISTADHERENT!A$5:H$50,3,0) -> TCHOUATEU AUGUSTIN | C34: =D34+E34+F34+G34-V34-BC34 -> 0 | D34: =VLOOKUP(A34,[21]HISTOBQUEJANV25!$A$6:$H$46,5,0) -> 150000 | E34: =VLOOKUP(A34,[21]HISTOBQUEJANV25!$A$6:$H$41,4,0) -> 0 | F34: =VLOOKUP(A34,[21]HISTOBQUEJANV25!$A$6:$H$41,6,0) -> 0 | H34: =IF(I34="ESPECES",3000,0) -> 0 | I34: =IF($D34<>0,"BANQUE",IF($E34<>0,"ESPECES","ECHEC")) -> BANQUE | K34: 1 | L34: =IF($D34<>0,K34*50000,IF($E34<>0,K34*50000,0)) -> 50000 | N34: =IF($D34<>0,M34*75000,IF($E34<>0,M34*75000,0)) -> 0 | O34: 1 | P34: =IF($D34<>0,O34*100000,IF($E34<>0,O34*100000,0)) -> 100000 | Q34: =VLOOKUP(A34,[13]TONTJANV24!$A$6:$R$39,12,0) -> 0 | R34: =IFERROR(VLOOKUP(A34,[14]TONTJANV24!$A$7:$P$23,10,0),0) -> 0 | S34: =IFERROR(VLOOKUP(A34,[15]TONTJANV24!$A$7:$P$20,10,0),0) -> 0 | V34: =H34+T34++S34+Q34+P34+N34+J34+L34+R34+W34+X34 -> 150000 | AR34: =IF(I34="ECHEC",((L34+N34+P34)*20/100),0) -> 0 | AS34: =IF(I34="ECHEC",((L34+N34+P34)*20/100),0) -> 0 | AT34: =IF(I34="ECHEC",0,(L34+J34-25000)) -> 25000 | AX34: =IF(AD34=0,AJ34,(1*25000*12)+AJ34-AD34) -> 0 | AY34: =IF(AE34=0,AK34,(1*75000*12)+(AK34)-AE34) -> 0 | AZ34: =IF(AF34=0,AL34,(1*100000*12)+(AL34)-AF34) -> 0 | BA34: =SUM(AW34:AZ34)-BG34+AA34-G34+BI34+BJ34+BK34+BL34+BM34+BN34 -> 0 | BE34: =IF(BA34=0,(BA34-BB34-BD34),(BA34-BB34-BC34-BD34))+G34 -> 0 | BG34: =AA34*1/100*BH34 -> 0 | BH34: 11 | BP34: S/TOTAL | BR34: =SUM(BR30:BR33) -> 0
A35: AS201643 | B35: =VLOOKUP(A35,[11]LISTADHERENT!A$5:H$50,3,0) -> TCHOUTOU NANA CLAUDE | C35: =D35+E35+F35+G35-V35-BC35 -> 0 | D35: =VLOOKUP(A35,[21]HISTOBQUEJANV25!$A$6:$H$46,5,0) -> 50000 | E35: =VLOOKUP(A35,[21]HISTOBQUEJANV25!$A$6:$H$41,4,0) -> 0 | F35: =VLOOKUP(A35,[21]HISTOBQUEJANV25!$A$6:$H$41,6,0) -> 0 | H35: =IF(I35="ESPECES",3000,0) -> 0 | I35: =IF($D35<>0,"BANQUE",IF($E35<>0,"ESPECES","ECHEC")) -> BANQUE | K35: 1 | L35: =IF($D35<>0,K35*50000,IF($E35<>0,K35*50000,0)) -> 50000 | N35: =IF($D35<>0,M35*75000,IF($E35<>0,M35*75000,0)) -> 0 | P35: =IF($D35<>0,O35*100000,IF($E35<>0,O35*100000,0)) -> 0 | Q35: =VLOOKUP(A35,[13]TONTJANV24!$A$6:$R$39,12,0) -> 0 | R35: =IFERROR(VLOOKUP(A35,[14]TONTJANV24!$A$7:$P$23,10,0),0) -> 0 | S35: =IFERROR(VLOOKUP(A35,[15]TONTJANV24!$A$7:$P$20,10,0),0) -> 0 | V35: =H35+T35++S35+Q35+P35+N35+J35+L35+R35+W35+X35 -> 50000 | AR35: =IF(I35="ECHEC",((L35+N35+P35)*20/100),0) -> 0 | AS35: =IF(I35="ECHEC",((L35+N35+P35)*20/100),0) -> 0 | AT35: =IF(I35="ECHEC",0,(L35+J35-25000)) -> 25000 | AX35: =IF(AD35=0,AJ35,(1*25000*12)+AJ35-AD35) -> 0 | AY35: =IF(AE35=0,AK35,(1*75000*12)+(AK35)-AE35) -> 0 | AZ35: =IF(AF35=0,AL35,(1*100000*12)+(AL35)-AF35) -> 0 | BA35: =SUM(AW35:AZ35)-BG35+AA35-G35+BI35+BJ35+BK35+BL35+BM35+BN35 -> 0 | BE35: =IF(BA35=0,(BA35-BB35-BD35),(BA35-BB35-BC35-BD35))+G35 -> 0 | BG35: =AA35*1/100*BH35 -> 0 | BH35: 11 | BP35: S/TOTAL | BR35: =SUM(BR32:BR34) -> 0
A36: AS201662 | B36: =VLOOKUP(A36,[11]LISTADHERENT!A$5:H$50,3,0) -> TIEYAM ERNEST | C36: =D36+E36+F36+G36-V36-BC36 -> #N/A | D36: =VLOOKUP(A36,[21]HISTOBQUEJANV25!$A$6:$H$46,5,0) -> 0 | E36: =VLOOKUP(A36,[21]HISTOBQUEJANV25!$A$6:$H$41,4,0) -> 50000 | F36: =VLOOKUP(A36,[21]HISTOBQUEJANV25!$A$6:$H$41,6,0) -> 0 | H36: 0 | I36: =IF($D36<>0,"BANQUE",IF($E36<>0,"ESPECES","ECHEC")) -> ESPECES | K36: 1 | L36: =IF($D36<>0,K36*50000,IF($E36<>0,K36*50000,0)) -> 50000 | N36: =IF($D36<>0,M36*75000,IF($E36<>0,M36*75000,0)) -> 0 | P36: =IF($D36<>0,O36*100000,IF($E36<>0,O36*100000,0)) -> 0 | Q36: =VLOOKUP(A36,[13]TONTJANV24!$A$6:$R$39,12,0) -> #N/A | R36: =IFERROR(VLOOKUP(A36,[14]TONTJANV24!$A$7:$P$23,10,0),0) -> 0 | S36: =IFERROR(VLOOKUP(A36,[15]TONTJANV24!$A$7:$P$20,10,0),0) -> 0 | V36: =H36+T36++S36+Q36+P36+N36+J36+L36+R36+W36+X36 -> #N/A | AR36: =IF(I36="ECHEC",((L36+N36+P36)*20/100),0) -> 0 | AS36: =IF(I36="ECHEC",((L36+N36+P36)*20/100),0) -> 0 | AT36: =IF(I36="ECHEC",0,(L36+J36-25000)) -> 25000 | AX36: =IF(AD36=0,AJ36,(1*25000*12)+AJ36-AD36) -> 0 | AY36: =IF(AE36=0,AK36,(1*75000*12)+(AK36)-AE36) -> 0 | AZ36: =IF(AF36=0,AL36,(1*100000*12)+(AL36)-AF36) -> 0 | BA36: =SUM(AW36:AZ36)-BG36+AA36-G36+BI36+BJ36+BK36+BL36+BM36+BN36 -> 0
A37: AS201658 | B37: =VLOOKUP(A37,[11]LISTADHERENT!A$5:H$50,3,0) -> YANTCHOU GERVAIS | C37: =D37+E37+F37+G37-V37-BC37 -> 0 | D37: =VLOOKUP(A37,[21]HISTOBQUEJANV25!$A$6:$H$46,5,0) -> 100000 | E37: =VLOOKUP(A37,[21]HISTOBQUEJANV25!$A$6:$H$41,4,0) -> 25000 | F37: =VLOOKUP(A37,[21]HISTOBQUEJANV25!$A$6:$H$41,6,0) -> 0 | H37: =IF(I37="ESPECES",3000,0) -> 0 | I37: =IF($D37<>0,"BANQUE",IF($E37<>0,"ESPECES","ECHEC")) -> BANQUE | K37: 1 | L37: =IF($D37<>0,K37*50000,IF($E37<>0,K37*50000,0)) -> 50000 | M37: 1 | N37: =IF($D37<>0,M37*75000,IF($E37<>0,M37*75000,0)) -> 75000 | P37: =IF($D37<>0,O37*100000,IF($E37<>0,O37*100000,0)) -> 0 | Q37: =VLOOKUP(A37,[13]TONTJANV24!$A$6:$R$39,12,0) -> 0 | R37: =IFERROR(VLOOKUP(A37,[14]TONTJANV24!$A$7:$P$23,10,0),0) -> 0 | S37: =IFERROR(VLOOKUP(A37,[15]TONTJANV24!$A$7:$P$20,10,0),0) -> 0 | V37: =H37+T37++S37+Q37+P37+N37+J37+L37+R37+W37+X37 -> 125000 | AR37: =IF(I37="ECHEC",((L37+N37+P37)*20/100),0) -> 0 | AS37: =IF(I37="ECHEC",((L37+N37+P37)*20/100),0) -> 0 | AT37: =IF(I37="ECHEC",0,(L37+J37-25000)) -> 25000 | AX37: =IF(AD37=0,AJ37,(1*25000*12)+AJ37-AD37) -> 0 | AY37: =IF(AE37=0,AK37,(1*75000*12)+(AK37)-AE37) -> 0 | AZ37: =IF(AF37=0,AL37,(1*100000*12)+(AL37)-AF37) -> 0 | BA37: =SUM(AW37:AZ37)-BG37+AA37-G37+BI37+BJ37+BK37+BL37+BM37+BN37 -> 0 | BE37: =IF(BA37=0,(BA37-BB37-BD37),(BA37-BB37-BC37-BD37))+G37 -> 0 | BG37: =AA37*1/100*BH37 -> 0 | BH37: 11
A38: AS201646 | B38: =VLOOKUP(A38,[11]LISTADHERENT!A$5:H$50,3,0) -> YEPMOU JEAN JACQUES | C38: =D38+E38+F38+G38-V38-BC38 -> 0 | D38: =VLOOKUP(A38,[21]HISTOBQUEJANV25!$A$6:$H$46,5,0) -> 0 | E38: =VLOOKUP(A38,[21]HISTOBQUEJANV25!$A$6:$H$41,4,0) -> 50000 | F38: =VLOOKUP(A38,[21]HISTOBQUEJANV25!$A$6:$H$41,6,0) -> 0 | H38: =IF(I38="ESPECES",3000,0)-3000 -> 0 | I38: =IF($D38<>0,"BANQUE",IF($E38<>0,"ESPECES","ECHEC")) -> ESPECES | K38: 1 | L38: =IF($D38<>0,K38*50000,IF($E38<>0,K38*50000,0)) -> 50000 | N38: =IF($D38<>0,M38*75000,IF($E38<>0,M38*75000,0)) -> 0 | P38: =IF($D38<>0,O38*100000,IF($E38<>0,O38*100000,0)) -> 0 | Q38: =VLOOKUP(A38,[13]TONTJANV24!$A$6:$R$39,12,0) -> 0 | R38: =IFERROR(VLOOKUP(A38,[14]TONTJANV24!$A$7:$P$23,10,0),0) -> 0 | S38: =IFERROR(VLOOKUP(A38,[15]TONTJANV24!$A$7:$P$20,10,0),0) -> 0 | V38: =H38+T38++S38+Q38+P38+N38+J38+L38+R38+W38+X38 -> 50000 | AR38: =IF(I38="ECHEC",((L38+N38+P38)*20/100),0) -> 0 | AS38: =IF(I38="ECHEC",((L38+N38+P38)*20/100),0) -> 0 | AT38: =IF(I38="ECHEC",0,(L38+J38-25000)) -> 25000 | AX38: =IF(AD38=0,AJ38,(1*25000*12)+AJ38-AD38) -> 0 | AY38: =IF(AE38=0,AK38,(1*75000*12)+(AK38)-AE38) -> 0 | AZ38: =IF(AF38=0,AL38,(1*100000*12)+(AL38)-AF38) -> 0 | BA38: =SUM(AW38:AZ38)-BG38+AA38-G38+BI38+BJ38+BK38+BL38+BM38+BN38 -> 0 | BE38: =IF(BA38=0,(BA38-BB38-BD38),(BA38-BB38-BC38-BD38))+G38 -> 0 | BG38: =AA38*1/100*BH38 -> 0 | BH38: 11 | BP38: COLLATION | BQ38: COLLATION | BR38: 100000
A39: AS201659 | B39: =VLOOKUP(A39,[11]LISTADHERENT!A$5:H$50,3,0) -> YIALA ALAIN OSCAR | C39: =D39+E39+F39+G39-V39-BC39 -> 0 | D39: =VLOOKUP(A39,[21]HISTOBQUEJANV25!$A$6:$H$46,5,0) -> 250000 | E39: =VLOOKUP(A39,[21]HISTOBQUEJANV25!$A$6:$H$41,4,0) -> 0 | F39: =VLOOKUP(A39,[21]HISTOBQUEJANV25!$A$6:$H$41,6,0) -> 0 | H39: =IF(I39="ESPECES",3000,0) -> 0 | I39: =IF($D39<>0,"BANQUE",IF($E39<>0,"ESPECES","ECHEC")) -> BANQUE | K39: 1 | L39: =IF($D39<>0,K39*50000,IF($E39<>0,K39*50000,0)) -> 50000 | N39: =IF($D39<>0,M39*75000,IF($E39<>0,M39*75000,0)) -> 0 | O39: 2 | P39: =IF($D39<>0,O39*100000,IF($E39<>0,O39*100000,0)) -> 200000 | Q39: =VLOOKUP(A39,[13]TONTJANV24!$A$6:$R$39,12,0) -> 0 | R39: =IFERROR(VLOOKUP(A39,[14]TONTJANV24!$A$7:$P$23,10,0),0) -> 0 | S39: =IFERROR(VLOOKUP(A39,[15]TONTJANV24!$A$7:$P$20,10,0),0) -> 0 | V39: =H39+T39++S39+Q39+P39+N39+J39+L39+R39+W39+X39 -> 250000 | AR39: =IF(I39="ECHEC",((L39+N39+P39)*20/100),0) -> 0 | AS39: =IF(I39="ECHEC",((L39+N39+P39)*20/100),0) -> 0 | AT39: =IF(I39="ECHEC",0,(L39+J39-25000)) -> 25000 | AX39: =IF(AD39=0,AJ39,(1*25000*12)+AJ39-AD39) -> 0 | AY39: =IF(AE39=0,AK39,(1*75000*12)+(AK39)-AE39) -> 0 | AZ39: =IF(AF39=0,AL39,(1*100000*12)+(AL39)-AF39) -> 0 | BA39: =SUM(AW39:AZ39)-BG39+AA39-G39+BI39+BJ39+BK39+BL39+BM39+BN39 -> 0 | BE39: =IF(BA39=0,(BA39-BB39-BD39),(BA39-BB39-BC39-BD39))+G39 -> 0 | BG39: =AA39*1/100*BH39 -> 0 | BH39: 11 | BP39: BOISSON | BQ39: COLLATION
A40: AS201647 | B40: =VLOOKUP(A40,[11]LISTADHERENT!A$5:H$50,3,0) -> YOUMBI EMMANUEL | C40: =D40+E40+F40+G40-V40-BC40 -> 0 | D40: =VLOOKUP(A40,[21]HISTOBQUEJANV25!$A$6:$H$46,5,0) -> 225000 | E40: =VLOOKUP(A40,[21]HISTOBQUEJANV25!$A$6:$H$41,4,0) -> 0 | F40: =VLOOKUP(A40,[21]HISTOBQUEJANV25!$A$6:$H$41,6,0) -> 0 | H40: =IF(I40="ESPECES",3000,0) -> 0 | I40: =IF($D40<>0,"BANQUE",IF($E40<>0,"ESPECES","ECHEC")) -> BANQUE | K40: 1 | L40: =IF($D40<>0,K40*50000,IF($E40<>0,K40*50000,0)) -> 50000 | M40: 1 | N40: =IF($D40<>0,M40*75000,IF($E40<>0,M40*75000,0)) -> 75000 | O40: 1 | P40: =IF($D40<>0,O40*100000,IF($E40<>0,O40*100000,0)) -> 100000 | Q40: =VLOOKUP(A40,[13]TONTJANV24!$A$6:$R$39,12,0) -> 0 | R40: =IFERROR(VLOOKUP(A40,[14]TONTJANV24!$A$7:$P$23,10,0),0) -> 0 | S40: =IFERROR(VLOOKUP(A40,[15]TONTJANV24!$A$7:$P$20,10,0),0) -> 0 | V40: =H40+T40++S40+Q40+P40+N40+J40+L40+R40+W40+X40 -> 225000 | AR40: =IF(I40="ECHEC",((L40+N40+P40)*20/100),0) -> 0 | AS40: =IF(I40="ECHEC",((L40+N40+P40)*20/100),0) -> 0 | AT40: =IF(I40="ECHEC",0,(L40+J40-25000)) -> 25000 | AX40: =IF(AD40=0,AJ40,(1*25000*12)+AJ40-AD40) -> 0 | AY40: =IF(AE40=0,AK40,(1*75000*12)+(AK40)-AE40) -> 0 | AZ40: =IF(AF40=0,AL40,(1*100000*12)+(AL40)-AF40) -> 0 | BA40: =SUM(AW40:AZ40)-BG40+AA40-G40+BI40+BJ40+BK40+BL40+BM40+BN40 -> 0 | BE40: =IF(BA40=0,(BA40-BB40-BD40),(BA40-BB40-BC40-BD40))+G40 -> 0 | BG40: =AA40*1/100*BH40 -> 0 | BH40: 11 | BP40: BOISSON | BQ40: COLLATION
B42: TOTAUX | C42: =SUM(C6:C41) -> #N/A | D42: =SUM(D6:D41) -> 5320000 | E42: =SUM(E6:E41) -> 275000 | G42: =SUM(G6:G41) -> 0 | H42: =SUM(H6:H41) -> 0 | I42: =SUM(I6:I41) -> 0 | J42: =SUM(J6:J41) -> 695000 | K42: =SUM(K6:K41) -> 34 | L42: =SUM(L6:L41) -> 1700000 | M42: =SUM(M6:M41) -> 12 | N42: =SUM(N6:N41) -> 900000 | ... T42: =SUM(T6:T41) -> 0 | V42: =SUM(V6:V41) -> #N/A | W42: =SUM(W6:W41) -> 0 | X42: =SUM(X6:X41) -> 0 | Y42: =SUM(Y6:Y41) -> 0 | Z42: =SUM(Z6:Z41) -> 0 | AA42: =SUM(AA6:AA41) -> 0 | AB42: =SUM(AB6:AB41) -> 0 | AD42: =SUM(AD6:AD41) -> 0 | AE42: =SUM(AE6:AE41) -> 0 | AF42: =SUM(AF6:AF41) -> 0 | AG42: =SUM(AG6:AG41) -> 0 | AH42: =SUM(AH6:AH41) -> 0 | AJ42: =SUM(AJ6:AJ41) -> 0 | AK42: =SUM(AK6:AK41) -> 0 | AL42: =SUM(AL6:AL41) -> 0 | AM42: =SUM(AM6:AM41) -> 0 | AN42: =SUM(AN6:AN41) -> 0 | AO42: =SUM(AO6:AO41) -> 0 | AP42: =SUM(AP6:AP41) -> 0 | AQ42: =SUM(AQ6:AQ41) -> 0 | ... BG42: =SUM(BG6:BG41) -> 6000 | BI42: =SUM(BI6:BI41) -> 27000 | BJ42: =SUM(BJ6:BJ41) -> 200000 | BK42: =SUM(BK6:BK41) -> 0 | BL42: =SUM(BL6:BL41) -> 100000 | BM42: =SUM(BM6:BM41) -> 0 | BN42: =SUM(BN6:BN41) -> 0 | BP42: S/TOTAL | BR42: =SUM(BR38:BR40) -> 100000
B45: AS201643 | BP45: TRANSPORT DELEGUE | BQ45: MUTUELLE
C46: BANQUE | G46: ESPECES
B47: LIBELLE | C47: SORTIE | D47: ENTREE | E47: EN COMPTE | G47: ENTREE | H47: SORTIE | I47: SOLDE | BP47: S/TOTAL | BR47: =SUM(BR44:BR46) -> 0
B48: REPORT
B49: OPERATIONS DU JOUR | C49: =BE42 -> 443000 | D49: =+D42 -> 5320000 | E49: =+C49-D49 -> -4877000 | G49: =E42 -> 275000 | H49: =+BB42 -> 0 | I49: =+G49-H49 -> 275000
C52: NGIEMENI | K52: 120000
C53: KOUAMOU MOISE | K53: 115000
C54: KOUATCHO | K54: 105000
C55: NANKAM | L55: 7500
C56: DJOHOU JEAN PAUL | M56: 31000
C57: SEUMOU POLYCARPE | M57: 30000
C58: DJOMO TCHAPDA | M58: 30000
C59: NKAMGANG | N59: 41000
BA87: =SUM(BA8:BA86) -> 1147000

Sheet HISTOJANV24
A1: ASSOCIATION | B1: ASELBY
A2: ANNEE | B2: 2024
A3: 1 | B3: 2 | C3: 3 | D3: 4 | E3: 5 | F3: 6 | G3: 7 | H3: 8 | I3: 9 | J3: 10 | K3: 11 | L3: 12 | M3: 13 | N3: 14 | O3: 15 | P3: 16 | Q3: 17 | R3: 18 | S3: 19 | T3: 20 | U3: 21 | V3: 22 | W3: 23 | X3: 24 | Y3: 25 | Z3: 26 | AA3: 27 | AB3: 28 | AC3: 29 | AD3: 30 | AE3: 31 | AF3: 32 | AG3: 33 | AH3: 34 | AI3: 35 | AJ3: 36 | AK3: 37 | AL3: 38 | AM3: 39 | AN3: 40 | AO3: 41 | AP3: 42 | AQ3: 43 | AR3: 44 | AS3: 45 | AT3: 46 | AU3: 47 | AV3: 48 | AW3: 49 | AX3: 50 | AY3: 51 | AZ3: 52 | BA3: 53 | BB3: 54 | BC3: 55 | BD3: 56 | BE3: 57 | BF3: 58 | BG3: 59 | BH3: 60 | BI3: 61 | BJ3: 62 | BK3: 63 | BL3: 64 | BM3: 65 | BO3: 66 | BP3: 67 | BQ3: 68
B4: TABLEAU DE BORD SAISIE DES DONNEES
A5: MATRICULE | B5: NOM ET PRENOM | C5: BONUS MALUS | D5: HISTORIQUE BANQUE | E5: HITORIQUE ESPECES | F5: HITORIQUE TONTINE | G5: PENALITE VERSEMENT ESPECES | H5: MODE PAIEMENT TONTINE | I5: COMPLEMENT EPARGNE | J5: NBRE DE LOT | K5: TONTINE 40 000 | L5: NBRE DE LOT | M5: TONTINE 75 000 | N5: NBRE DE LOT | O5: TONTINE 100 000 | P5: REMBOURSEMENT PETIT LOT T50 | Q5: REMBOURSEMENT PETIT LOT T75 | R5: REMBOURSEMENT PETIT LOT T100 | S5: REMBOURSEMENT PRÊT FONDS | T5: MODE PAIEMENT REMBOURSEMENT PRÊT FONDS | U5: MONTANT ENGAGEMENT | V5: SANCTION | W5: INSCRIPTION | X5: EPARGNE ASSURANCE | Y5: RECONSTITUTION FONDS | Z5: PRÊT FONDS | AA5: MODE PAIEMENT PRÊT | AB5: NUM CHEQUE | AC5: ACHAT LOT PRINCIPAL T40 | AD5: ACHAT LOT PRINCIPAL T75 | AE5: ACHAT LOT PRINCIPAL T100 | AF5: MODE PAIEMENT LOT PRINCIPAL | AG5: NUM CHEQUE | AH5: PENALITE VERSEMENT ESPECES | AI5: VENTE PETIT LOT T50 | AJ5: VENTE PETIT LOT T75 | AK5: VENTE PETIT LOT T100 | AL5: INTERET PETIT LOT T50 | AM5: INTERET PETIT LOT T75 | AN5: INTERET PETIT LOT T100 | AO5: NUM CHEQUE | AP5: MODE PAIEMENT PETEIT LOT | AQ5: PENELAITE RETARD TONTINE | AR5: PENELAITE ECHEC TONTINE | AS5: RESTE | AT5: MUTUELLE | AU5: REMBOURSEMENT TRANSPORT | AV5: RETRAIT PARTIEL FONDS | AW5: MONTANT T40 | AX5: MONTANT T75 | AY5: MONTANT T100 | AZ5: MONTANT CHEQUE | BA5: MONTANT ESPECES | BB5: CONTRIBUTION FOYER | BC5: AUTRES SOTIES | BD5: MONTANT CHEQUE EFFECTIF | BE5: NUMERO CHEQUE | BF5: INTERET PRÊT | BG5: NBRE MOIS | BH5: DEPENSE FONDS DE ROULEMENT | BI5: DEPENSE FRAIS EXCEPTIONNEL | BJ5: DEPENSE FONDS MUTUEL | BK5: DEPENSE COLLATION RECEPTION | BL5: PENALITE PRET FONDS | BM5: DEPENSE PENALITE VERSEMENT BANQUE | BN5: AUTRES DEPENSES | BO5: LIBELLE | BP5: COMPTE | BQ5: MONTANT
A6: AS201648 | B6: =VLOOKUP(A6,[11]LISTADHERENT!A$5:H$50,3,0) -> ASELBY | C6: =D6+E6+F6-U6-BB6 -> 0 | D6: =VLOOKUP(A6,[12]HISTOBQUEJANV24!$A$6:$G$46,3,0) -> 175000 | E6: =VLOOKUP(A6,[12]HISTOBQUEJANV24!$A$6:$G$41,4,0) -> 0 | F6: =VLOOKUP(A6,[12]HISTOBQUEJANV24!$A$6:$G$41,5,0) -> 0 | G6: =IF(H6="ESPECES",3000,0) -> 0 | H6: =IF($D6<>0,"BANQUE",IF($E6<>0,"ESPECES","ECHEC")) -> BANQUE | K6: =IF($D6<>0,J6*50000,IF($E6<>0,J6*50000,0)) -> 0 | L6: 1 | M6: =IF($D6<>0,L6*75000,IF($E6<>0,L6*75000,0)) -> 75000 | N6: 1 | O6: =IF($D6<>0,N6*100000,IF($E6<>0,N6*100000,0)) -> 100000 | P6: =IFERROR(CHERCHEV(A6,[13]TONTJANV24!$A$6:$R$39,12,0),0) -> 0 | Q6: =IFERROR(VLOOKUP(A6,[14]TONTJANV24!$A$7:$P$23,10,0),0) -> 0 | R6: =IFERROR(VLOOKUP(A6,[15]TONTJANV24!$A$7:$P$20,10,0),0) -> 0 | U6: =G6+S6++R6+P6+O6+M6+I6+K6+Q6+V6+W6 -> 175000 | AQ6: =IF(H6="ECHEC",((K6+M6+O6)*20/100),0) -> 0 | AR6: =IF(H6="ECHEC",((K6+M6+O6)*20/100),0) -> 0 | AW6: =IF(AC6=0,AI6,(1*25000*12)+AI6-AC6) -> 0 | AX6: =IF(AD6=0,AJ6,(1*75000*12)+(AJ6)-AD6) -> 0 | AY6: =IF(AE6=0,AK6,(1*100000*12)+(AK6)-AE6) -> 0 | AZ6: =SUM(AV6:AY6)-BF6+Z6-F6+BH6+BI6+BJ6+BK6+BL6+BM6 -> 227000 | BA6: 27000 | BD6: =IF(AZ6=0,(AZ6-BA6-BC6),(AZ6-BA6-BB6-BC6)) -> 200000 | BE6: OK | BF6: =Z6*1/100*BG6 -> 0 | BG6: 11 | BH6: =BQ16 -> 27000 | BI6: =BQ28 -> 200000 | BJ6: =BQ33 -> 0 | BN6: =+BQ22 -> 300000 | BO6: ACHAT FOURNITURE | BP6: FONDS DE ROULEMENT | BQ6: 8500
A7: AS201601 | B7: =VLOOKUP(A7,[11]LISTADHERENT!A$5:H$50,3,0) -> BAKOP ACHILLE | C7: =D7+E7+F7-U7-BB7 -> 6000 | D7: =VLOOKUP(A7,[12]HISTOBQUEJANV24!$A$6:$G$46,3,0) -> 56000 | E7: =VLOOKUP(A7,[12]HISTOBQUEJANV24!$A$6:$G$41,4,0) -> 0 | F7: =VLOOKUP(A7,[12]HISTOBQUEJANV24!$A$6:$G$41,5,0) -> 0 | G7: =IF(H7="ESPECES",3000,0) -> 0 | H7: =IF($D7<>0,"BANQUE",IF($E7<>0,"ESPECES","ECHEC")) -> BANQUE | J7: 1 | K7: =IF($D7<>0,J7*50000,IF($E7<>0,J7*50000,0)) -> 50000 | M7: =IF($D7<>0,L7*75000,IF($E7<>0,L7*75000,0)) -> 0 | O7: =IF($D7<>0,N7*100000,IF($E7<>0,N7*100000,0)) -> 0 | P7: =VLOOKUP(A7,[13]TONTJANV24!$A$6:$R$39,12,0) -> 0 | Q7: =IFERROR(VLOOKUP(A7,[14]TONTJANV24!$A$7:$P$23,10,0),0) -> 0 | R7: =IFERROR(VLOOKUP(A7,[15]TONTJANV24!$A$7:$P$20,10,0),0) -> 0 | U7: =G7+S7++R7+P7+O7+M7+I7+K7+Q7+V7+W7 -> 50000 | AQ7: =IF(H7="ECHEC",((K7+M7+O7)*20/100),0) -> 0 | AR7: =IF(H7="ECHEC",((K7+M7+O7)*20/100),0) -> 0 | AS7: =IF(H7="ECHEC",0,(K7+I7-25000)) -> 25000 | AW7: =IF(AC7=0,AI7,(1*25000*12)+AI7-AC7) -> 0 | AX7: =IF(AD7=0,AJ7,(1*75000*12)+(AJ7)-AD7) -> 0 | AY7: =IF(AE7=0,AK7,(1*100000*12)+(AK7)-AE7) -> 0 | AZ7: =SUM(AV7:AY7)-BF7+Z7-F7+BH7+BI7+BJ7+BK7+BL7+BM7+6000+600000 -> 600000 | BD7: =IF(AZ7=0,(AZ7-BA7-BC7),(AZ7-BA7-BB7-BC7))+F7-600000 -> 0 | BF7: =Z7*1/100*BG7+6000 -> 6000 | BG7: 11 | BO7: COMMUNICATION | BP7: FONDS DE ROULEMENT
A8: AS201602 | B8: =VLOOKUP(A8,[11]LISTADHERENT!A$5:H$50,3,0) -> BOUTCHOUANG WILLIAM | C8: =D8+E8+F8-U8-BB8 -> 0 | D8: =VLOOKUP(A8,[12]HISTOBQUEJANV24!$A$6:$G$46,3,0) -> 125000 | E8: =VLOOKUP(A8,[12]HISTOBQUEJANV24!$A$6:$G$41,4,0) -> 0 | F8: =VLOOKUP(A8,[12]HISTOBQUEJANV24!$A$6:$G$41,5,0) -> 0 | G8: =IF(H8="ESPECES",3000,0) -> 0 | H8: =IF($D8<>0,"BANQUE",IF($E8<>0,"ESPECES","ECHEC")) -> BANQUE | J8: 1 | K8: =IF($D8<>0,J8*50000,IF($E8<>0,J8*50000,0)) -> 50000 | L8: 1 | M8: =IF($D8<>0,L8*75000,IF($E8<>0,L8*75000,0)) -> 75000 | O8: =IF($D8<>0,N8*100000,IF($E8<>0,N8*100000,0)) -> 0 | P8: =VLOOKUP(A8,[13]TONTJANV24!$A$6:$R$39,12,0) -> 0 | Q8: =IFERROR(VLOOKUP(A8,[14]TONTJANV24!$A$7:$P$23,10,0),0) -> 0 | R8: =IFERROR(VLOOKUP(A8,[15]TONTJANV24!$A$7:$P$20,10,0),0) -> 0 | U8: =G8+S8++R8+P8+O8+M8+I8+K8+Q8+V8+W8 -> 125000 | AQ8: =IF(H8="ECHEC",((K8+M8+O8)*20/100),0) -> 0 | AR8: =IF(H8="ECHEC",((K8+M8+O8)*20/100),0) -> 0 | AS8: =IF(H8="ECHEC",0,(K8+I8-25000)) -> 25000 | AW8: =IF(AC8=0,AI8,(1*25000*12)+AI8-AC8) -> 0 | AX8: =IF(AD8=0,AJ8,(1*75000*12)+(AJ8)-AD8) -> 0 | AY8: =IF(AE8=0,AK8,(1*100000*12)+(AK8)-AE8) -> 0 | AZ8: =SUM(AV8:AY8)-BF8+Z8-F8+BH8+BI8+BJ8+BK8+BL8+BM8 -> 0 | BD8: =IF(AZ8=0,(AZ8-BA8-BC8),(AZ8-BA8-BB8-BC8))+F8 -> 0 | BF8: =Z8*1/100*BG8 -> 0 | BG8: 11 | BO8: COMMISSION | BP8: FONDS DE ROULEMENT
A9: AS201604 | B9: =VLOOKUP(A9,[11]LISTADHERENT!A$5:H$50,3,0) -> DJOMO JEAN PAUL | C9: =D9+E9+F9-U9-BB9 -> 0 | D9: =VLOOKUP(A9,[12]HISTOBQUEJANV24!$A$6:$G$46,3,0) -> 250000 | E9: =VLOOKUP(A9,[12]HISTOBQUEJANV24!$A$6:$G$41,4,0) -> 0 | F9: =VLOOKUP(A9,[12]HISTOBQUEJANV24!$A$6:$G$41,5,0) -> 0 | G9: =IF(H9="ESPECES",3000,0) -> 0 | H9: =IF($D9<>0,"BANQUE",IF($E9<>0,"ESPECES","ECHEC")) -> BANQUE | J9: 1 | K9: =IF($D9<>0,J9*50000,IF($E9<>0,J9*50000,0)) -> 50000 | M9: =IF($D9<>0,L9*75000,IF($E9<>0,L9*75000,0)) -> 0 | N9: 2 | O9: =IF($D9<>0,N9*100000,IF($E9<>0,N9*100000,0)) -> 200000 | P9: =VLOOKUP(A9,[13]TONTJANV24!$A$6:$R$39,12,0) -> 0 | Q9: =IFERROR(VLOOKUP(A9,[14]TONTJANV24!$A$7:$P$23,10,0),0) -> 0 | R9: =IFERROR(VLOOKUP(A9,[15]TONTJANV24!$A$7:$P$20,10,0),0) -> 0 | U9: =G9+S9++R9+P9+O9+M9+I9+K9+Q9+V9+W9 -> 250000 | AE9: 115000 | AF9: BANQUE | AQ9: =IF(H9="ECHEC",((K9+M9+O9)*20/100),0) -> 0 | AR9: =IF(H9="ECHEC",((K9+M9+O9)*20/100),0) -> 0 | AS9: =IF(H9="ECHEC",0,(K9+I9-25000)) -> 25000 | AW9: =IF(AC9=0,AI9,(1*25000*12)+AI9-AC9) -> 0 | AX9: =IF(AD9=0,AJ9,(1*75000*12)+(AJ9)-AD9) -> 0 | AY9: =IF(AE9=0,AK9,(1*100000*12)+(AK9)-AE9) -> 1085000 | AZ9: =SUM(AV9:AY9)-BF9+Z9-F9+BH9+BI9+BJ9+BK9+BL9+BM9 -> 1085000 | BA9: 500000 | BD9: =IF(AZ9=0,(AZ9-BA9-BC9),(AZ9-BA9-BB9-BC9))+F9 -> 585000 | BE9: OK | BF9: =Z9*1/100*BG9 -> 0 | BG9: 11 | BO9: OUVERTURE COMPTE | BP9: FONDS DE ROULEMENT | BQ9: 18500
A10: AS201654 | B10: =VLOOKUP(A10,[11]LISTADHERENT!A$5:H$50,3,0) -> DJOMOU TCHAPDA | C10: =D10+E10+F10-U10-BB10 -> 0 | D10: =VLOOKUP(A10,[12]HISTOBQUEJANV24!$A$6:$G$46,3,0) -> 125000 | E10: =VLOOKUP(A10,[12]HISTOBQUEJANV24!$A$6:$G$41,4,0) -> 0 | F10: =VLOOKUP(A10,[12]HISTOBQUEJANV24!$A$6:$G$41,5,0) -> 0 | G10: =IF(H10="ESPECES",3000,0) -> 0 | H10: =IF($D10<>0,"BANQUE",IF($E10<>0,"ESPECES","ECHEC")) -> BANQUE | J10: 1 | K10: =IF($D10<>0,J10*50000,IF($E10<>0,J10*50000,0)) -> 50000 | L10: 1 | M10: =IF($D10<>0,L10*75000,IF($E10<>0,L10*75000,0)) -> 75000 | O10: =IF($D10<>0,N10*100000,IF($E10<>0,N10*100000,0)) -> 0 | P10: =VLOOKUP(A10,[13]TONTJANV24!$A$6:$R$39,12,0) -> 0 | Q10: =IFERROR(VLOOKUP(A10,[14]TONTJANV24!$A$7:$P$23,10,0),0) -> 0 | R10: =IFERROR(VLOOKUP(A10,[15]TONTJANV24!$A$7:$P$20,10,0),0) -> 0 | U10: =G10+S10++R10+P10+O10+M10+I10+K10+Q10+V10+W10 -> 125000 | AJ10: =50000+50000 -> 100000 | AM10: 2000 | AQ10: =IF(H10="ECHEC",((K10+M10+O10)*20/100),0) -> 0 | AR10: =IF(H10="ECHEC",((K10+M10+O10)*20/100),0) -> 0 | AS10: =IF(H10="ECHEC",0,(K10+I10-25000)) -> 25000 | AW10: =IF(AC10=0,AI10,(1*25000*12)+AI10-AC10) -> 0 | AX10: =IF(AD10=0,AJ10,(1*75000*12)+(AJ10)-AD10) -> 100000 | AY10: =IF(AE10=0,AK10,(1*100000*12)+(AK10)-AE10) -> 0 | AZ10: =SUM(AV10:AY10)-BF10+Z10-F10+BH10+BI10+BJ10+BK10+BL10+BM10 -> 100000 | BD10: =IF(AZ10=0,(AZ10-BA10-BC10),(AZ10-BA10-BB10-BC10))+F10 -> 100000 | BE10: OK | BF10: =Z10*1/100*BG10 -> 0 | BG10: 11 | BO10: CREDIT TELEPHONE | BP10: FONDS DE ROULEMENT
A11: AS201605 | B11: =VLOOKUP(A11,[11]LISTADHERENT!A$5:H$50,3,0) -> DJOUKWE NANGUEN GUY BLAISE | C11: =D11+E11+F11-U11-BB11 -> 0 | D11: =VLOOKUP(A11,[12]HISTOBQUEJANV24!$A$6:$G$46,3,0) -> 125000 | E11: =VLOOKUP(A11,[12]HISTOBQUEJANV24!$A$6:$G$41,4,0) -> 0 | F11: =VLOOKUP(A11,[12]HISTOBQUEJANV24!$A$6:$G$41,5,0) -> 0 | G11: =IF(H11="ESPECES",3000,0) -> 0 | H11: =IF($D11<>0,"BANQUE",IF($E11<>0,"ESPECES","ECHEC")) -> BANQUE | J11: 1 | K11: =IF($D11<>0,J11*50000,IF($E11<>0,J11*50000,0)) -> 50000 | L11: 1 | M11: =IF($D11<>0,L11*75000,IF($E11<>0,L11*75000,0)) -> 75000 | O11: =IF($D11<>0,N11*100000,IF($E11<>0,N11*100000,0)) -> 0 | P11: =VLOOKUP(A11,[13]TONTJANV24!$A$6:$R$39,12,0) -> 0 | Q11: =IFERROR(VLOOKUP(A11,[14]TONTJANV24!$A$7:$P$23,10,0),0) -> 0 | R11: =IFERROR(VLOOKUP(A11,[15]TONTJANV24!$A$7:$P$20,10,0),0) -> 0 | U11: =G11+S11++R11+P11+O11+M11+I11+K11+Q11+V11+W11 -> 125000 | AJ11: =50000+50000 -> 100000 | AM11: 2000 | AQ11: =IF(H11="ECHEC",((K11+M11+O11)*20/100),0) -> 0 | AR11: =IF(H11="ECHEC",((K11+M11+O11)*20/100),0) -> 0 | AS11: =IF(H11="ECHEC",0,(K11+I11-25000)) -> 25000 | AW11: =IF(AC11=0,AI11,(1*25000*12)+AI11-AC11) -> 0 | AX11: =IF(AD11=0,AJ11,(1*75000*12)+(AJ11)-AD11) -> 100000 | AY11: =IF(AE11=0,AK11,(1*100000*12)+(AK11)-AE11) -> 0 | AZ11: =SUM(AV11:AY11)-BF11+Z11-F11+BH11+BI11+BJ11+BK11+BL11+BM11 -> 100000 | BA11: 100000 | BD11: =IF(AZ11=0,(AZ11-BA11-BC11),(AZ11-BA11-BB11-BC11))+F11 -> 0 | BF11: =Z11*1/100*BG11 -> 0 | BG11: 11 | BO11: PRODUCTION RAPPORT | BP11: FONDS DE ROULEMENT
A12: AS201608 | B12: =VLOOKUP(A12,[11]LISTADHERENT!A$5:H$50,3,0) -> DJUOMBESSY ANTOINE | C12: =D12+E12+F12-U12-BB12 -> 0 | D12: =VLOOKUP(A12,[12]HISTOBQUEJANV24!$A$6:$G$46,3,0) -> 330000 | E12: =VLOOKUP(A12,[12]HISTOBQUEJANV24!$A$6:$G$41,4,0) -> 0 | F12: =VLOOKUP(A12,[12]HISTOBQUEJANV24!$A$6:$G$41,5,0) -> 0 | G12: =IF(H12="ESPECES",3000,0) -> 0 | H12: =IF($D12<>0,"BANQUE",IF($E12<>0,"ESPECES","ECHEC")) -> BANQUE | I12: 5000 | J12: 1 | K12: =IF($D12<>0,J12*50000,IF($E12<>0,J12*50000,0)) -> 50000 | L12: 1 | M12: =IF($D12<>0,L12*75000,IF($E12<>0,L12*75000,0)) -> 75000 | N12: 2 | O12: =IF($D12<>0,N12*100000,IF($E12<>0,N12*100000,0)) -> 200000 | P12: =VLOOKUP(A12,[13]TONTJANV24!$A$6:$R$39,12,0) -> 0 | Q12: =IFERROR(VLOOKUP(A12,[14]TONTJANV24!$A$7:$P$23,10,0),0) -> 0 | R12: =IFERROR(VLOOKUP(A12,[15]TONTJANV24!$A$7:$P$20,10,0),0) -> 0 | U12: =G12+S12++R12+P12+O12+M12+I12+K12+Q12+V12+W12 -> 330000 | AD12: 60000 | AF12: BANQUE | AQ12: =IF(H12="ECHEC",((K12+M12+O12)*20/100),0) -> 0 | AR12: =IF(H12="ECHEC",((K12+M12+O12)*20/100),0) -> 0 | AS12: =IF(H12="ECHEC",0,(K12+I12-25000)) -> 30000 | AW12: =IF(AC12=0,AI12,(1*25000*12)+AI12-AC12) -> 0 | AX12: =IF(AD12=0,AJ12,(1*75000*12)+(AJ12)-AD12) -> 840000 | AY12: =IF(AE12=0,AK12,(1*100000*12)+(AK12)-AE12) -> 0 | AZ12: =SUM(AV12:AY12)-BF12+Z12-F12+BH12+BI12+BJ12+BK12+BL12+BM12 -> 840000 | BD12: =IF(AZ12=0,(AZ12-BA12-BC12),(AZ12-BA12-BB12-BC12))+F12 -> 840000 | BE12: OK | BF12: =Z12*1/100*BG12 -> 0 | BG12: 11 | BO12: ACHAT SOURIS ET PHOTOCOPIE | BP12: FONDS DE ROULEMENT
A13: AS201651 | B13: =VLOOKUP(A13,[11]LISTADHERENT!A$5:H$50,3,0) -> DOMOU FABIEN | C13: =D13+E13+F13-U13-BB13 -> 0 | D13: =VLOOKUP(A13,[12]HISTOBQUEJANV24!$A$6:$G$46,3,0) -> 50000 | E13: =VLOOKUP(A13,[12]HISTOBQUEJANV24!$A$6:$G$41,4,0) -> 0 | F13: =VLOOKUP(A13,[12]HISTOBQUEJANV24!$A$6:$G$41,5,0) -> 0 | G13: =IF(H13="ESPECES",3000,0) -> 0 | H13: =IF($D13<>0,"BANQUE",IF($E13<>0,"ESPECES","ECHEC")) -> BANQUE | J13: 1 | K13: =IF($D13<>0,J13*50000,IF($E13<>0,J13*50000,0)) -> 50000 | M13: =IF($D13<>0,L13*75000,IF($E13<>0,L13*75000,0)) -> 0 | O13: =IF($D13<>0,N13*100000,IF($E13<>0,N13*100000,0)) -> 0 | P13: =VLOOKUP(A13,[13]TONTJANV24!$A$6:$R$39,12,0) -> 0 | Q13: =IFERROR(VLOOKUP(A13,[14]TONTJANV24!$A$7:$P$23,10,0),0) -> 0 | R13: =IFERROR(VLOOKUP(A13,[15]TONTJANV24!$A$7:$P$20,10,0),0) -> 0 | U13: =G13+S13++R13+P13+O13+M13+I13+K13+Q13+V13+W13 -> 50000 | AQ13: =IF(H13="ECHEC",((K13+M13+O13)*20/100),0) -> 0 | AR13: =IF(H13="ECHEC",((K13+M13+O13)*20/100),0) -> 0 | AS13: =IF(H13="ECHEC",0,(K13+I13-25000)) -> 25000 | AW13: =IF(AC13=0,AI13,(1*25000*12)+AI13-AC13) -> 0 | AX13: =IF(AD13=0,AJ13,(1*75000*12)+(AJ13)-AD13) -> 0 | AY13: =IF(AE13=0,AK13,(1*100000*12)+(AK13)-AE13) -> 0 | AZ13: =SUM(AV13:AY13)-BF13+Z13-F13+BH13+BI13+BJ13+BK13+BL13+BM13 -> 0 | BD13: =IF(AZ13=0,(AZ13-BA13-BC13),(AZ13-BA13-BB13-BC13))+F13 -> 0 | BF13: =Z13*1/100*BG13 -> 0 | BG13: 11 | BO13: TAXI BANQUE | BP13: FONDS DE ROULEMENT
A14: AS201609 | B14: =VLOOKUP(A14,[11]LISTADHERENT!A$5:H$50,3,0) -> DONHOU DAVID | C14: =D14+E14+F14-U14-BB14 -> 0 | D14: =VLOOKUP(A14,[12]HISTOBQUEJANV24!$A$6:$G$46,3,0) -> 0 | E14: =VLOOKUP(A14,[12]HISTOBQUEJANV24!$A$6:$G$41,4,0) -> 50000 | F14: =VLOOKUP(A14,[12]HISTOBQUEJANV24!$A$6:$G$41,5,0) -> 0 | G14: =IF(H14="ESPECES",3000,0)-3000 -> 0 | H14: =IF($D14<>0,"BANQUE",IF($E14<>0,"ESPECES","ECHEC")) -> ESPECES | J14: 1 | K14: =IF($D14<>0,J14*50000,IF($E14<>0,J14*50000,0)) -> 50000 | M14: =IF($D14<>0,L14*75000,IF($E14<>0,L14*75000,0)) -> 0 | O14: =IF($D14<>0,N14*100000,IF($E14<>0,N14*100000,0)) -> 0 | P14: =VLOOKUP(A14,[13]TONTJANV24!$A$6:$R$39,12,0) -> 0 | Q14: =IFERROR(VLOOKUP(A14,[14]TONTJANV24!$A$7:$P$23,10,0),0) -> 0 | R14: =IFERROR(VLOOKUP(A14,[15]TONTJANV24!$A$7:$P$20,10,0),0) -> 0 | U14: =G14+S14++R14+P14+O14+M14+I14+K14+Q14+V14+W14 -> 50000 | AQ14: =IF(H14="ECHEC",((K14+M14+O14)*20/100),0) -> 0 | AR14: =IF(H14="ECHEC",((K14+M14+O14)*20/100),0) -> 0 | AS14: =IF(H14="ECHEC",0,(K14+I14-25000)) -> 25000 | AW14: =IF(AC14=0,AI14,(1*25000*12)+AI14-AC14) -> 0 | AX14: =IF(AD14=0,AJ14,(1*75000*12)+(AJ14)-AD14) -> 0 | AY14: =IF(AE14=0,AK14,(1*100000*12)+(AK14)-AE14) -> 0 | AZ14: =SUM(AV14:AY14)-BF14+Z14-F14+BH14+BI14+BJ14+BK14+BL14+BM14 -> 0 | BD14: =IF(AZ14=0,(AZ14-BA14-BC14),(AZ14-BA14-BB14-BC14))+F14 -> 0 | BF14: =Z14*1/100*BG14 -> 0 | BG14: 11 | BO14: ACHAT TERRAIN | BP14: FONDS DE ROULEMENT
A15: AS201611 | B15: =VLOOKUP(A15,[11]LISTADHERENT!A$5:H$50,3,0) -> HENGUE PAUL OMER | C15: =D15+E15+F15-U15-BB15 -> 0 | D15: =VLOOKUP(A15,[12]HISTOBQUEJANV24!$A$6:$G$46,3,0) -> 125000 | E15: =VLOOKUP(A15,[12]HISTOBQUEJANV24!$A$6:$G$41,4,0) -> 0 | F15: =VLOOKUP(A15,[12]HISTOBQUEJANV24!$A$6:$G$41,5,0) -> 0 | G15: =IF(H15="ESPECES",3000,0) -> 0 | H15: =IF($D15<>0,"BANQUE",IF($E15<>0,"ESPECES","ECHEC")) -> BANQUE | J15: 1 | K15: =IF($D15<>0,J15*50000,IF($E15<>0,J15*50000,0)) -> 50000 | L15: 1 | M15: =IF($D15<>0,L15*75000,IF($E15<>0,L15*75000,0)) -> 75000 | O15: =IF($D15<>0,N15*100000,IF($E15<>0,N15*100000,0)) -> 0 | P15: =VLOOKUP(A15,[13]TONTJANV24!$A$6:$R$39,12,0) -> 0 | Q15: =IFERROR(VLOOKUP(A15,[14]TONTJANV24!$A$7:$P$23,10,0),0) -> 0 | R15: =IFERROR(VLOOKUP(A15,[15]TONTJANV24!$A$7:$P$20,10,0),0) -> 0 | U15: =G15+S15++R15+P15+O15+M15+I15+K15+Q15+V15+W15 -> 125000 | AQ15: =IF(H15="ECHEC",((K15+M15+O15)*20/100),0) -> 0 | AR15: =IF(H15="ECHEC",((K15+M15+O15)*20/100),0) -> 0 | AS15: =IF(H15="ECHEC",0,(K15+I15-25000)) -> 25000 | AW15: =IF(AC15=0,AI15,(1*25000*12)+AI15-AC15) -> 0 | AX15: =IF(AD15=0,AJ15,(1*75000*12)+(AJ15)-AD15) -> 0 | AY15: =IF(AE15=0,AK15,(1*100000*12)+(AK15)-AE15) -> 0 | AZ15: =SUM(AV15:AY15)-BF15+Z15-F15+BH15+BI15+BJ15+BK15+BL15+BM15 -> 0 | BD15: =IF(AZ15=0,(AZ15-BA15-BC15),(AZ15-BA15-BB15-BC15))+F15 -> 0 | BF15: =Z15*1/100*BG15 -> 0 | BG15: 11
A16: AS201613 | B16: =VLOOKUP(A16,[11]LISTADHERENT!A$5:H$50,3,0) -> HOTCHO BENJAMIN | C16: =D16+E16+F16-U16-BB16 -> 0 | D16: =VLOOKUP(A16,[12]HISTOBQUEJANV24!$A$6:$G$46,3,0) -> 260000 | E16: =VLOOKUP(A16,[12]HISTOBQUEJANV24!$A$6:$G$41,4,0) -> 0 | F16: =VLOOKUP(A16,[12]HISTOBQUEJANV24!$A$6:$G$41,5,0) -> 0 | G16: =IF(H16="ESPECES",3000,0) -> 0 | H16: =IF($D16<>0,"BANQUE",IF($E16<>0,"ESPECES","ECHEC")) -> BANQUE | I16: 35000 | J16: 1 | K16: =IF($D16<>0,J16*50000,IF($E16<>0,J16*50000,0)) -> 50000 | L16: 1 | M16: =IF($D16<>0,L16*75000,IF($E16<>0,L16*75000,0)) -> 75000 | N16: 1 | O16: =IF($D16<>0,N16*100000,IF($E16<>0,N16*100000,0)) -> 100000 | P16: =VLOOKUP(A16,[13]TONTJANV24!$A$6:$R$39,12,0) -> 0 | Q16: =IFERROR(VLOOKUP(A16,[14]TONTJANV24!$A$7:$P$23,10,0),0) -> 0 | R16: =IFERROR(VLOOKUP(A16,[15]TONTJANV24!$A$7:$P$20,10,0),0) -> 0 | U16: =G16+S16++R16+P16+O16+M16+I16+K16+Q16+V16+W16 -> 260000 | AC16: 12000 | AF16: BANQUE | AQ16: =IF(H16="ECHEC",((K16+M16+O16)*20/100),0) -> 0 | AR16: =IF(H16="ECHEC",((K16+M16+O16)*20/100),0) -> 0 | AS16: =IF(H16="ECHEC",0,(K16+I16-25000)) -> 60000 | AW16: =IF(AC16=0,AI16,(1*25000*12)+AI16-AC16) -> 288000 | AX16: =IF(AD16=0,AJ16,(1*75000*12)+(AJ16)-AD16) -> 0 | AY16: =IF(AE16=0,AK16,(1*100000*12)+(AK16)-AE16) -> 0 | AZ16: =SUM(AV16:AY16)-BF16+Z16-F16+BH16+BI16+BJ16+BK16+BL16+BM16 -> 288000 | BD16: =IF(AZ16=0,(AZ16-BA16-BC16),(AZ16-BA16-BB16-BC16))+F16 -> 288000 | BE16: OK | BF16: =Z16*1/100*BG16 -> 0 | BG16: 11 | BO16: S/TOTAL | BQ16: =SUM(BQ6:BQ15) -> 27000
A17: AS201617 | B17: =VLOOKUP(A17,[11]LISTADHERENT!A$5:H$50,3,0) -> KOUAMOU MOISE | C17: =D17+E17+F17-U17-BB17 -> 0 | D17: =VLOOKUP(A17,[12]HISTOBQUEJANV24!$A$6:$G$46,3,0) -> 150000 | E17: =VLOOKUP(A17,[12]HISTOBQUEJANV24!$A$6:$G$41,4,0) -> 0 | F17: =VLOOKUP(A17,[12]HISTOBQUEJANV24!$A$6:$G$41,5,0) -> 0 | G17: =IF(H17="ESPECES",3000,0) -> 0 | H17: =IF($D17<>0,"BANQUE",IF($E17<>0,"ESPECES","ECHEC")) -> BANQUE | J17: 1 | K17: =IF($D17<>0,J17*50000,IF($E17<>0,J17*50000,0)) -> 50000 | M17: =IF($D17<>0,L17*75000,IF($E17<>0,L17*75000,0)) -> 0 | N17: 1 | O17: =IF($D17<>0,N17*100000,IF($E17<>0,N17*100000,0)) -> 100000 | P17: =VLOOKUP(A17,[13]TONTJANV24!$A$6:$R$39,12,0) -> 0 | Q17: =IFERROR(VLOOKUP(A17,[14]TONTJANV24!$A$7:$P$23,10,0),0) -> 0 | R17: =IFERROR(VLOOKUP(A17,[15]TONTJANV24!$A$7:$P$20,10,0),0) -> 0 | U17: =G17+S17++R17+P17+O17+M17+I17+K17+Q17+V17+W17 -> 150000 | Z17: 1000000 | AK17: 100000 | AN17: 1000 | AQ17: =IF(H17="ECHEC",((K17+M17+O17)*20/100),0) -> 0 | AR17: =IF(H17="ECHEC",((K17+M17+O17)*20/100),0) -> 0 | AS17: =IF(H17="ECHEC",0,(K17+I17-25000)) -> 25000 | AW17: =IF(AC17=0,AI17,(1*25000*12)+AI17-AC17) -> 0 | AX17: =IF(AD17=0,AJ17,(1*75000*12)+(AJ17)-AD17) -> 0 | AY17: =IF(AE17=0,AK17,(1*100000*12)+(AK17)-AE17) -> 100000 | AZ17: =SUM(AV17:AY17)-BF17+Z17-F17+BH17+BI17+BJ17+BK17+BL17+BM17+60000 -> 1150000 | BA17: 100000 | BD17: =IF(AZ17=0,(AZ17-BA17-BC17),(AZ17-BA17-BB17-BC17))+F17 -> 1050000 | BE17: OK | BF17: =Z17*1/100*BG17 -> 110000 | BG17: 11 | BK17: 100000
A18: AS201619 | B18: =VLOOKUP(A18,[11]LISTADHERENT!A$5:H$50,3,0) -> KOUATCHO MESSACK | C18: =D18+E18+F18-U18-BB18 -> 0 | D18: =VLOOKUP(A18,[12]HISTOBQUEJANV24!$A$6:$G$46,3,0) -> 150000 | E18: =VLOOKUP(A18,[12]HISTOBQUEJANV24!$A$6:$G$41,4,0) -> 0 | F18: =VLOOKUP(A18,[12]HISTOBQUEJANV24!$A$6:$G$41,5,0) -> 0 | G18: =IF(H18="ESPECES",3000,0) -> 0 | H18: =IF($D18<>0,"BANQUE",IF($E18<>0,"ESPECES","ECHEC")) -> BANQUE | J18: 1 | K18: =IF($D18<>0,J18*50000,IF($E18<>0,J18*50000,0)) -> 50000 | M18: =IF($D18<>0,L18*75000,IF($E18<>0,L18*75000,0)) -> 0 | N18: 1 | O18: =IF($D18<>0,N18*100000,IF($E18<>0,N18*100000,0)) -> 100000 | P18: =VLOOKUP(A18,[13]TONTJANV24!$A$6:$R$39,12,0) -> 0 | Q18: =IFERROR(VLOOKUP(A18,[14]TONTJANV24!$A$7:$P$23,10,0),0) -> 0 | R18: =IFERROR(VLOOKUP(A18,[15]TONTJANV24!$A$7:$P$20,10,0),0) -> 0 | U18: =G18+S18++R18+P18+O18+M18+I18+K18+Q18+V18+W18 -> 150000 | AC18: 13000 | AF18: BANQUE | AQ18: =IF(H18="ECHEC",((K18+M18+O18)*20/100),0) -> 0 | AR18: =IF(H18="ECHEC",((K18+M18+O18)*20/100),0) -> 0 | AS18: =IF(H18="ECHEC",0,(K18+I18-25000)) -> 25000 | AW18: =IF(AC18=0,AI18,(1*25000*12)+AI18-AC18) -> 287000 | AX18: =IF(AD18=0,AJ18,(1*75000*12)+(AJ18)-AD18) -> 0 | AY18: =IF(AE18=0,AK18,(1*100000*12)+(AK18)-AE18) -> 0 | AZ18: =SUM(AV18:AY18)-BF18+Z18-F18+BH18+BI18+BJ18+BK18+BL18+BM18 -> 287000 | BD18: =IF(AZ18=0,(AZ18-BA18-BC18),(AZ18-BA18-BB18-BC18))+F18 -> 287000 | BE18: OK | BF18: =Z18*1/100*BG18 -> 0 | BG18: 11 | BO18: TERRAIN NYOM | BP18: AUTRES DEPENSES | BQ18: 300000
A19: AS201661 | B19: =VLOOKUP(A19,[11]LISTADHERENT!A$5:H$50,3,0) -> MASSEUNGOUE DAGOBERT | C19: =D19+E19+F19-U19-BB19 -> 0 | D19: =VLOOKUP(A19,[12]HISTOBQUEJANV24!$A$6:$G$46,3,0) -> 50000 | E19: =VLOOKUP(A19,[12]HISTOBQUEJANV24!$A$6:$G$41,4,0) -> 25000 | F19: =VLOOKUP(A19,[12]HISTOBQUEJANV24!$A$6:$G$41,5,0) -> 0 | G19: =IF(H19="ESPECES",3000,0) -> 0 | H19: =IF($D19<>0,"BANQUE",IF($E19<>0,"ESPECES","ECHEC")) -> BANQUE | J19: 1 | K19: =IF($D19<>0,J19*50000,IF($E19<>0,J19*50000,0)) -> 50000 | M19: =IF($D19<>0,L19*75000,IF($E19<>0,L19*75000,0)) -> 0 | O19: =IF($D19<>0,N19*100000,IF($E19<>0,N19*100000,0)) -> 0 | P19: =VLOOKUP(A19,[13]TONTJANV24!$A$6:$R$39,12,0) -> 0 | Q19: =IFERROR(VLOOKUP(A19,[14]TONTJANV24!$A$7:$P$23,10,0),0) -> 0 | R19: =IFERROR(VLOOKUP(A19,[15]TONTJANV24!$A$7:$P$20,10,0),0) -> 0 | U19: =G19+S19++R19+P19+O19+M19+I19+K19+Q19+V19+W19 -> 75000 | W19: 25000 | AQ19: =IF(H19="ECHEC",((K19+M19+O19)*20/100),0) -> 0 | AR19: =IF(H19="ECHEC",((K19+M19+O19)*20/100),0) -> 0 | AS19: =IF(H19="ECHEC",0,(K19+I19-25000)) -> 25000 | AW19: =IF(AC19=0,AI19,(1*25000*12)+AI19-AC19) -> 0 | AX19: =IF(AD19=0,AJ19,(1*75000*12)+(AJ19)-AD19) -> 0 | AY19: =IF(AE19=0,AK19,(1*100000*12)+(AK19)-AE19) -> 0 | AZ19: =SUM(AV19:AY19)-BF19+Z19-F19+BH19+BI19+BJ19+BK19+BL19+BM19 -> 0 | BD19: =IF(AZ19=0,(AZ19-BA19-BC19),(AZ19-BA19-BB19-BC19))+F19 -> 0 | BF19: =Z19*1/100*BG19 -> 0 | BG19: 11
A20: AS201649 | B20: =VLOOKUP(A20,[11]LISTADHERENT!A$5:H$50,3,0) -> MBOGNING TUGMA GUY | C20: =D20+E20+F20-U20-BB20 -> 0 | D20: =VLOOKUP(A20,[12]HISTOBQUEJANV24!$A$6:$G$46,3,0) -> 225000 | E20: =VLOOKUP(A20,[12]HISTOBQUEJANV24!$A$6:$G$41,4,0) -> 0 | F20: =VLOOKUP(A20,[12]HISTOBQUEJANV24!$A$6:$G$41,5,0) -> 0 | G20: =IF(H20="ESPECES",3000,0) -> 0 | H20: =IF($D20<>0,"BANQUE",IF($E20<>0,"ESPECES","ECHEC")) -> BANQUE | J20: 1 | K20: =IF($D20<>0,J20*50000,IF($E20<>0,J20*50000,0)) -> 50000 | L20: 1 | M20: =IF($D20<>0,L20*75000,IF($E20<>0,L20*75000,0)) -> 75000 | N20: 1 | O20: =IF($D20<>0,N20*100000,IF($E20<>0,N20*100000,0)) -> 100000 | P20: =VLOOKUP(A20,[13]TONTJANV24!$A$6:$R$39,12,0) -> 0 | Q20: =IFERROR(VLOOKUP(A20,[14]TONTJANV24!$A$7:$P$23,10,0),0) -> 0 | R20: =IFERROR(VLOOKUP(A20,[15]TONTJANV24!$A$7:$P$20,10,0),0) -> 0 | U20: =G20+S20++R20+P20+O20+M20+I20+K20+Q20+V20+W20 -> 225000 | AE20: 115000 | AF20: BANQUE | AQ20: =IF(H20="ECHEC",((K20+M20+O20)*20/100),0) -> 0 | AR20: =IF(H20="ECHEC",((K20+M20+O20)*20/100),0) -> 0 | AS20: =IF(H20="ECHEC",0,(K20+I20-25000)) -> 25000 | AW20: =IF(AC20=0,AI20,(1*25000*12)+AI20-AC20) -> 0 | AX20: =IF(AD20=0,AJ20,(1*75000*12)+(AJ20)-AD20) -> 0 | AY20: =IF(AE20=0,AK20,(1*100000*12)+(AK20)-AE20) -> 1085000 | AZ20: =SUM(AV20:AY20)-BF20+Z20-F20+BH20+BI20+BJ20+BK20+BL20+BM20 -> 1085000 | BD20: =IF(AZ20=0,(AZ20-BA20-BC20),(AZ20-BA20-BB20-BC20))+F20 -> 1085000 | BE20: OK | BF20: =Z20*1/100*BG20 -> 0 | BG20: 11
A21: AS201639 | B21: =VLOOKUP(A21,[11]LISTADHERENT!A$5:H$50,3,0) -> NANGUEN MARTIN | C21: =D21+E21+F21-U21-BB21 -> 0 | D21: =VLOOKUP(A21,[12]HISTOBQUEJANV24!$A$6:$G$46,3,0) -> 50000 | E21: =VLOOKUP(A21,[12]HISTOBQUEJANV24!$A$6:$G$41,4,0) -> 0 | F21: =VLOOKUP(A21,[12]HISTOBQUEJANV24!$A$6:$G$41,5,0) -> 0 | G21: =IF(H21="ESPECES",3000,0) -> 0 | H21: =IF($D21<>0,"BANQUE",IF($E21<>0,"ESPECES","ECHEC")) -> BANQUE | J21: 1 | K21: =IF($D21<>0,J21*50000,IF($E21<>0,J21*50000,0)) -> 50000 | M21: =IF($D21<>0,L21*75000,IF($E21<>0,L21*75000,0)) -> 0 | O21: =IF($D21<>0,N21*100000,IF($E21<>0,N21*100000,0)) -> 0 | P21: =VLOOKUP(A21,[13]TONTJANV24!$A$6:$R$39,12,0) -> 0 | Q21: =IFERROR(VLOOKUP(A21,[14]TONTJANV24!$A$7:$P$23,10,0),0) -> 0 | R21: =IFERROR(VLOOKUP(A21,[15]TONTJANV24!$A$7:$P$20,10,0),0) -> 0 | U21: =G21+S21++R21+P21+O21+M21+I21+K21+Q21+V21+W21 -> 50000 | AQ21: =IF(H21="ECHEC",((K21+M21+O21)*20/100),0) -> 0 | AR21: =IF(H21="ECHEC",((K21+M21+O21)*20/100),0) -> 0 | AS21: =IF(H21="ECHEC",0,(K21+I21-25000)) -> 25000 | AW21: =IF(AC21=0,AI21,(1*25000*12)+AI21-AC21) -> 0 | AX21: =IF(AD21=0,AJ21,(1*75000*12)+(AJ21)-AD21) -> 0 | AY21: =IF(AE21=0,AK21,(1*100000*12)+(AK21)-AE21) -> 0 | AZ21: =SUM(AV21:AY21)-BF21+Z21-F21+BH21+BI21+BJ21+BK21+BL21+BM21 -> 0 | BD21: =IF(AZ21=0,(AZ21-BA21-BC21),(AZ21-BA21-BB21-BC21))+F21 -> 0 | BF21: =Z21*1/100*BG21 -> 0 | BG21: 11
A22: AS201621 | B22: =VLOOKUP(A22,[11]LISTADHERENT!A$5:H$50,3,0) -> NANKAM APPOLINAIRE | C22: =D22+E22+F22-U22-BB22 -> 0 | D22: =VLOOKUP(A22,[12]HISTOBQUEJANV24!$A$6:$G$46,3,0) -> 125000 | E22: =VLOOKUP(A22,[12]HISTOBQUEJANV24!$A$6:$G$41,4,0) -> 0 | F22: =VLOOKUP(A22,[12]HISTOBQUEJANV24!$A$6:$G$41,5,0) -> 0 | G22: =IF(H22="ESPECES",3000,0) -> 0 | H22: =IF($D22<>0,"BANQUE",IF($E22<>0,"ESPECES","ECHEC")) -> BANQUE | J22: 1 | K22: =IF($D22<>0,J22*50000,IF($E22<>0,J22*50000,0)) -> 50000 | L22: 1 | M22: =IF($D22<>0,L22*75000,IF($E22<>0,L22*75000,0)) -> 75000 | O22: =IF($D22<>0,N22*100000,IF($E22<>0,N22*100000,0)) -> 0 | P22: =VLOOKUP(A22,[13]TONTJANV24!$A$6:$R$39,12,0) -> 0 | Q22: =IFERROR(VLOOKUP(A22,[14]TONTJANV24!$A$7:$P$23,10,0),0) -> 0 | R22: =IFERROR(VLOOKUP(A22,[15]TONTJANV24!$A$7:$P$20,10,0),0) -> 0 | U22: =G22+S22++R22+P22+O22+M22+I22+K22+Q22+V22+W22 -> 125000 | AQ22: =IF(H22="ECHEC",((K22+M22+O22)*20/100),0) -> 0 | AR22: =IF(H22="ECHEC",((K22+M22+O22)*20/100),0) -> 0 | AS22: =IF(H22="ECHEC",0,(K22+I22-25000)) -> 25000 | AW22: =IF(AC22=0,AI22,(1*25000*12)+AI22-AC22) -> 0 | AX22: =IF(AD22=0,AJ22,(1*75000*12)+(AJ22)-AD22) -> 0 | AY22: =IF(AE22=0,AK22,(1*100000*12)+(AK22)-AE22) -> 0 | AZ22: =SUM(AV22:AY22)-BF22+Z22-F22+BH22+BI22+BJ22+BK22+BL22+BM22 -> 0 | BD22: =IF(AZ22=0,(AZ22-BA22-BC22),(AZ22-BA22-BB22-BC22))+F22 -> 0 | BF22: =Z22*1/100*BG22 -> 0 | BG22: 11 | BO22: S/TOTAL | BQ22: =SUM(BQ18:BQ21) -> 300000
A23: AS201622 | B23: =VLOOKUP(A23,[11]LISTADHERENT!A$5:H$50,3,0) -> NDJOMO ETIENNE | C23: =D23+E23+F23-U23-BB23 -> 0 | D23: =VLOOKUP(A23,[12]HISTOBQUEJANV24!$A$6:$G$46,3,0) -> 260000 | E23: =VLOOKUP(A23,[12]HISTOBQUEJANV24!$A$6:$G$41,4,0) -> 0 | F23: =VLOOKUP(A23,[12]HISTOBQUEJANV24!$A$6:$G$41,5,0) -> 0 | G23: =IF(H23="ESPECES",3000,0) -> 0 | H23: =IF($D23<>0,"BANQUE",IF($E23<>0,"ESPECES","ECHEC")) -> BANQUE | I23: 10000 | J23: 1 | K23: =IF($D23<>0,J23*50000,IF($E23<>0,J23*50000,0)) -> 50000 | M23: =IF($D23<>0,L23*75000,IF($E23<>0,L23*75000,0)) -> 0 | N23: 2 | O23: =IF($D23<>0,N23*100000,IF($E23<>0,N23*100000,0)) -> 200000 | P23: =VLOOKUP(A23,[13]TONTJANV24!$A$6:$R$39,12,0) -> 0 | Q23: =IFERROR(VLOOKUP(A23,[14]TONTJANV24!$A$7:$P$23,10,0),0) -> 0 | R23: =IFERROR(VLOOKUP(A23,[15]TONTJANV24!$A$7:$P$20,10,0),0) -> 0 | U23: =G23+S23++R23+P23+O23+M23+I23+K23+Q23+V23+W23 -> 260000 | AQ23: =IF(H23="ECHEC",((K23+M23+O23)*20/100),0) -> 0 | AR23: =IF(H23="ECHEC",((K23+M23+O23)*20/100),0) -> 0 | AS23: =IF(H23="ECHEC",0,(K23+I23-25000)) -> 35000 | AW23: =IF(AC23=0,AI23,(1*25000*12)+AI23-AC23) -> 0 | AX23: =IF(AD23=0,AJ23,(1*75000*12)+(AJ23)-AD23) -> 0 | AY23: =IF(AE23=0,AK23,(1*100000*12)+(AK23)-AE23) -> 0 | AZ23: =SUM(AV23:AY23)-BF23+Z23-F23+BH23+BI23+BJ23+BK23+BL23+BM23 -> 0 | BA23: 56000 | BD23: =IF(AZ23=0,(AZ23-BA23-BC23),(AZ23-BA23-BB23-BC23))+F23+56000 -> 0 | BF23: =Z23*1/100*BG23 -> 0 | BG23: 11
A24: AS201624 | B24: =VLOOKUP(A24,[11]LISTADHERENT!A$5:H$50,3,0) -> NGONDIEP CLAUDE | C24: =D24+E24+F24-U24-BB24 -> 0 | D24: =VLOOKUP(A24,[12]HISTOBQUEJANV24!$A$6:$G$46,3,0) -> 225000 | E24: =VLOOKUP(A24,[12]HISTOBQUEJANV24!$A$6:$G$41,4,0) -> 0 | F24: =VLOOKUP(A24,[12]HISTOBQUEJANV24!$A$6:$G$41,5,0) -> 0 | G24: =IF(H24="ESPECES",3000,0) -> 0 | H24: =IF($D24<>0,"BANQUE",IF($E24<>0,"ESPECES","ECHEC")) -> BANQUE | J24: 1 | K24: =IF($D24<>0,J24*50000,IF($E24<>0,J24*50000,0)) -> 50000 | L24: 1 | M24: =IF($D24<>0,L24*75000,IF($E24<>0,L24*75000,0)) -> 75000 | N24: 1 | O24: =IF($D24<>0,N24*100000,IF($E24<>0,N24*100000,0)) -> 100000 | P24: =VLOOKUP(A24,[13]TONTJANV24!$A$6:$R$39,12,0) -> 0 | Q24: =IFERROR(VLOOKUP(A24,[14]TONTJANV24!$A$7:$P$23,10,0),0) -> 0 | R24: =IFERROR(VLOOKUP(A24,[15]TONTJANV24!$A$7:$P$20,10,0),0) -> 0 | U24: =G24+S24++R24+P24+O24+M24+I24+K24+Q24+V24+W24 -> 225000 | AQ24: =IF(H24="ECHEC",((K24+M24+O24)*20/100),0) -> 0 | AR24: =IF(H24="ECHEC",((K24+M24+O24)*20/100),0) -> 0 | AS24: =IF(H24="ECHEC",0,(K24+I24-25000)) -> 25000 | AW24: =IF(AC24=0,AI24,(1*25000*12)+AI24-AC24) -> 0 | AX24: =IF(AD24=0,AJ24,(1*75000*12)+(AJ24)-AD24) -> 0 | AY24: =IF(AE24=0,AK24,(1*100000*12)+(AK24)-AE24) -> 0 | AZ24: =SUM(AV24:AY24)-BF24+Z24-F24+BH24+BI24+BJ24+BK24+BL24+BM24 -> 0 | BD24: =IF(AZ24=0,(AZ24-BA24-BC24),(AZ24-BA24-BB24-BC24))+F24 -> 0 | BF24: =Z24*1/100*BG24 -> 0 | BG24: 11 | BO24: GRATIFICATION BUREAU 2023 | BP24: FRAIS EXEPTIONNEL | BQ24: 200000
A25: AS201626 | B25: =VLOOKUP(A25,[11]LISTADHERENT!A$5:H$50,3,0) -> NGUIEMEGNI MATHIEU BLAISE | C25: =D25+E25+F25-U25-BB25 -> 0 | D25: =VLOOKUP(A25,[12]HISTOBQUEJANV24!$A$6:$G$46,3,0) -> 375000 | E25: =VLOOKUP(A25,[12]HISTOBQUEJANV24!$A$6:$G$41,4,0) -> 0 | F25: =VLOOKUP(A25,[12]HISTOBQUEJANV24!$A$6:$G$41,5,0) -> 0 | G25: =IF(H25="ESPECES",3000,0) -> 0 | H25: =IF($D25<>0,"BANQUE",IF($E25<>0,"ESPECES","ECHEC")) -> BANQUE | J25: 1 | K25: =IF($D25<>0,J25*50000,IF($E25<>0,J25*50000,0)) -> 50000 | L25: 3 | M25: =IF($D25<>0,L25*75000,IF($E25<>0,L25*75000,0)) -> 225000 | N25: 1 | O25: =IF($D25<>0,N25*100000,IF($E25<>0,N25*100000,0)) -> 100000 | P25: =VLOOKUP(A25,[13]TONTJANV24!$A$6:$R$39,12,0) -> 0 | Q25: =IFERROR(VLOOKUP(A25,[14]TONTJANV24!$A$7:$P$23,10,0),0) -> 0 | R25: =IFERROR(VLOOKUP(A25,[15]TONTJANV24!$A$7:$P$20,10,0),0) -> 0 | U25: =G25+S25++R25+P25+O25+M25+I25+K25+Q25+V25+W25 -> 375000 | AD25: 65000 | AE25: 125000 | AF25: BANQUE | AQ25: =IF(H25="ECHEC",((K25+M25+O25)*20/100),0) -> 0 | AR25: =IF(H25="ECHEC",((K25+M25+O25)*20/100),0) -> 0 | AS25: =IF(H25="ECHEC",0,(K25+I25-25000)) -> 25000 | AW25: =IF(AC25=0,AI25,(1*25000*12)+AI25-AC25) -> 0 | AX25: =IF(AD25=0,AJ25,(1*75000*12)+(AJ25)-AD25) -> 835000 | AY25: =IF(AE25=0,AK25,(1*100000*12)+(AK25)-AE25) -> 1075000 | AZ25: =SUM(AV25:AY25)-BF25+Z25-F25+BH25+BI25+BJ25+BK25+BL25+BM25 -> 1910000 | BD25: =IF(AZ25=0,(AZ25-BA25-BC25),(AZ25-BA25-BB25-BC25))+F25 -> 1910000 | BE25: OK | BF25: =Z25*1/100*BG25 -> 0 | BG25: 11 | BO25: DOSSIER TECHNIQUE NGIEMENI | BP25: FRAIS EXEPTIONNEL
A26: AS201628 | B26: =VLOOKUP(A26,[11]LISTADHERENT!A$5:H$50,3,0) -> NKAMGANG JUSTIN DEJOLIE | C26: =D26+E26+F26-U26-BB26 -> 50000 | D26: =VLOOKUP(A26,[12]HISTOBQUEJANV24!$A$6:$G$46,3,0) -> 50000 | E26: =VLOOKUP(A26,[12]HISTOBQUEJANV24!$A$6:$G$41,4,0) -> 50000 | F26: =VLOOKUP(A26,[12]HISTOBQUEJANV24!$A$6:$G$41,5,0) -> 0 | G26: =IF(H26="ESPECES",3000,0) -> 0 | H26: =IF($D26<>0,"BANQUE",IF($E26<>0,"ESPECES","ECHEC")) -> BANQUE | J26: 1 | K26: =IF($D26<>0,J26*50000,IF($E26<>0,J26*50000,0)) -> 50000 | M26: =IF($D26<>0,L26*75000,IF($E26<>0,L26*75000,0)) -> 0 | O26: =IF($D26<>0,N26*100000,IF($E26<>0,N26*100000,0)) -> 0 | P26: =VLOOKUP(A26,[13]TONTJANV24!$A$6:$R$39,12,0) -> 0 | Q26: =IFERROR(VLOOKUP(A26,[14]TONTJANV24!$A$7:$P$23,10,0),0) -> 0 | R26: =IFERROR(VLOOKUP(A26,[15]TONTJANV24!$A$7:$P$20,10,0),0) -> 0 | U26: =G26+S26++R26+P26+O26+M26+I26+K26+Q26+V26+W26 -> 50000 | AC26: 13000 | AF26: BANQUE | AQ26: =IF(H26="ECHEC",((K26+M26+O26)*20/100),0) -> 0 | AR26: =IF(H26="ECHEC",((K26+M26+O26)*20/100),0) -> 0 | AS26: =IF(H26="ECHEC",0,(K26+I26-25000)) -> 25000 | AW26: =IF(AC26=0,AI26,(1*25000*12)+AI26-AC26) -> 287000 | AX26: =IF(AD26=0,AJ26,(1*75000*12)+(AJ26)-AD26) -> 0 | AY26: =IF(AE26=0,AK26,(1*100000*12)+(AK26)-AE26) -> 0 | AZ26: =SUM(AV26:AY26)-BF26+Z26-F26+BH26+BI26+BJ26+BK26+BL26+BM26 -> 287000 | BA26: 7000 | BD26: =IF(AZ26=0,(AZ26-BA26-BC26),(AZ26-BA26-BB26-BC26))+F26 -> 280000 | BE26: OK | BF26: =Z26*1/100*BG26 -> 0 | BG26: 11 | BO26: DEUIL TCHEMNOU EMMANUEL | BP26: FRAIS EXEPTIONNEL
A27: AS201656 | B27: =VLOOKUP(A27,[11]LISTADHERENT!A$5:H$50,3,0) -> NOUBE ETIENNE | C27: =D27+E27+F27-U27-BB27 -> 0 | D27: =VLOOKUP(A27,[12]HISTOBQUEJANV24!$A$6:$G$46,3,0) -> 50000 | E27: =VLOOKUP(A27,[12]HISTOBQUEJANV24!$A$6:$G$41,4,0) -> 0 | F27: =VLOOKUP(A27,[12]HISTOBQUEJANV24!$A$6:$G$41,5,0) -> 0 | G27: =IF(H27="ESPECES",3000,0) -> 0 | H27: =IF($D27<>0,"BANQUE",IF($E27<>0,"ESPECES","ECHEC")) -> BANQUE | J27: 1 | K27: =IF($D27<>0,J27*50000,IF($E27<>0,J27*50000,0)) -> 50000 | M27: =IF($D27<>0,L27*75000,IF($E27<>0,L27*75000,0)) -> 0 | O27: =IF($D27<>0,N27*100000,IF($E27<>0,N27*100000,0)) -> 0 | P27: =VLOOKUP(A27,[13]TONTJANV24!$A$6:$R$39,12,0) -> 0 | Q27: =IFERROR(VLOOKUP(A27,[14]TONTJANV24!$A$7:$P$23,10,0),0) -> 0 | R27: =IFERROR(VLOOKUP(A27,[15]TONTJANV24!$A$7:$P$20,10,0),0) -> 0 | U27: =G27+S27++R27+P27+O27+M27+I27+K27+Q27+V27+W27 -> 50000 | AQ27: =IF(H27="ECHEC",((K27+M27+O27)*20/100),0) -> 0 | AR27: =IF(H27="ECHEC",((K27+M27+O27)*20/100),0) -> 0 | AS27: =IF(H27="ECHEC",0,(K27+I27-25000)) -> 25000 | AW27: =IF(AC27=0,AI27,(1*25000*12)+AI27-AC27) -> 0 | AX27: =IF(AD27=0,AJ27,(1*75000*12)+(AJ27)-AD27) -> 0 | AY27: =IF(AE27=0,AK27,(1*100000*12)+(AK27)-AE27) -> 0 | AZ27: =SUM(AV27:AY27)-BF27+Z27-F27+BH27+BI27+BJ27+BK27+BL27+BM27 -> 0 | BD27: =IF(AZ27=0,(AZ27-BA27-BC27),(AZ27-BA27-BB27-BC27))+F27 -> 0 | BF27: =Z27*1/100*BG27 -> 0 | BG27: 11
A28: AS201633 | B28: =VLOOKUP(A28,[11]LISTADHERENT!A$5:H$50,3,0) -> PATEGO NJOSSU GUSTAVE | C28: =D28+E28+F28-U28-BB28 -> 0 | D28: =VLOOKUP(A28,[12]HISTOBQUEJANV24!$A$6:$G$46,3,0) -> 125000 | E28: =VLOOKUP(A28,[12]HISTOBQUEJANV24!$A$6:$G$41,4,0) -> 0 | F28: =VLOOKUP(A28,[12]HISTOBQUEJANV24!$A$6:$G$41,5,0) -> 0 | G28: =IF(H28="ESPECES",3000,0) -> 0 | H28: =IF($D28<>0,"BANQUE",IF($E28<>0,"ESPECES","ECHEC")) -> BANQUE | J28: 1 | K28: =IF($D28<>0,J28*50000,IF($E28<>0,J28*50000,0)) -> 50000 | L28: 1 | M28: =IF($D28<>0,L28*75000,IF($E28<>0,L28*75000,0)) -> 75000 | O28: =IF($D28<>0,N28*100000,IF($E28<>0,N28*100000,0)) -> 0 | P28: =VLOOKUP(A28,[13]TONTJANV24!$A$6:$R$39,12,0) -> 0 | Q28: =IFERROR(VLOOKUP(A28,[14]TONTJANV24!$A$7:$P$23,10,0),0) -> 0 | R28: =IFERROR(VLOOKUP(A28,[15]TONTJANV24!$A$7:$P$20,10,0),0) -> 0 | U28: =G28+S28++R28+P28+O28+M28+I28+K28+Q28+V28+W28 -> 125000 | AQ28: =IF(H28="ECHEC",((K28+M28+O28)*20/100),0) -> 0 | AR28: =IF(H28="ECHEC",((K28+M28+O28)*20/100),0) -> 0 | AS28: =IF(H28="ECHEC",0,(K28+I28-25000)) -> 25000 | AW28: =IF(AC28=0,AI28,(1*25000*12)+AI28-AC28) -> 0 | AX28: =IF(AD28=0,AJ28,(1*75000*12)+(AJ28)-AD28) -> 0 | AY28: =IF(AE28=0,AK28,(1*100000*12)+(AK28)-AE28) -> 0 | AZ28: =SUM(AV28:AY28)-BF28+Z28-F28+BH28+BI28+BJ28+BK28+BL28+BM28 -> 0 | BD28: =IF(AZ28=0,(AZ28-BA28-BC28),(AZ28-BA28-BB28-BC28))+F28 -> 0 | BF28: =Z28*1/100*BG28 -> 0 | BG28: 11 | BO28: S/TOTAL | BQ28: =SUM(BQ24:BQ26) -> 200000
A29: AS201657 | B29: =VLOOKUP(A29,[11]LISTADHERENT!A$5:H$50,3,0) -> SEUMO POLYCARPE | C29: =D29+E29+F29-U29-BB29 -> 0 | D29: =VLOOKUP(A29,[12]HISTOBQUEJANV24!$A$6:$G$46,3,0) -> 500000 | E29: =VLOOKUP(A29,[12]HISTOBQUEJANV24!$A$6:$G$41,4,0) -> 0 | F29: =VLOOKUP(A29,[12]HISTOBQUEJANV24!$A$6:$G$41,5,0) -> 0 | G29: =IF(H29="ESPECES",3000,0) -> 0 | H29: =IF($D29<>0,"BANQUE",IF($E29<>0,"ESPECES","ECHEC")) -> BANQUE | I29: 450000 | J29: 1 | K29: =IF($D29<>0,J29*50000,IF($E29<>0,J29*50000,0)) -> 50000 | M29: =IF($D29<>0,L29*75000,IF($E29<>0,L29*75000,0)) -> 0 | O29: =IF($D29<>0,N29*100000,IF($E29<>0,N29*100000,0)) -> 0 | P29: =VLOOKUP(A29,[13]TONTJANV24!$A$6:$R$39,12,0) -> 0 | Q29: =IFERROR(VLOOKUP(A29,[14]TONTJANV24!$A$7:$P$23,10,0),0) -> 0 | R29: =IFERROR(VLOOKUP(A29,[15]TONTJANV24!$A$7:$P$20,10,0),0) -> 0 | U29: =G29+S29++R29+P29+O29+M29+I29+K29+Q29+V29+W29 -> 500000 | AQ29: =IF(H29="ECHEC",((K29+M29+O29)*20/100),0) -> 0 | AR29: =IF(H29="ECHEC",((K29+M29+O29)*20/100),0) -> 0 | AS29: =IF(H29="ECHEC",0,(K29+I29-25000)) -> 475000 | AW29: =IF(AC29=0,AI29,(1*25000*12)+AI29-AC29) -> 0 | AX29: =IF(AD29=0,AJ29,(1*75000*12)+(AJ29)-AD29) -> 0 | AY29: =IF(AE29=0,AK29,(1*100000*12)+(AK29)-AE29) -> 0 | AZ29: =SUM(AV29:AY29)-BF29+Z29-F29+BH29+BI29+BJ29+BK29+BL29+BM29 -> 0 | BD29: =IF(AZ29=0,(AZ29-BA29-BC29),(AZ29-BA29-BB29-BC29))+F29 -> 0 | BF29: =Z29*1/100*BG29 -> 0 | BG29: 11
A30: AS201653 | B30: =VLOOKUP(A30,[11]LISTADHERENT!A$5:H$50,3,0) -> SIME BRICE | C30: =D30+E30+F30-U30-BB30 -> 0 | D30: =VLOOKUP(A30,[12]HISTOBQUEJANV24!$A$6:$G$46,3,0) -> 250000 | E30: =VLOOKUP(A30,[12]HISTOBQUEJANV24!$A$6:$G$41,4,0) -> 0 | F30: =VLOOKUP(A30,[12]HISTOBQUEJANV24!$A$6:$G$41,5,0) -> 0 | G30: =IF(H30="ESPECES",3000,0) -> 0 | H30: =IF($D30<>0,"BANQUE",IF($E30<>0,"ESPECES","ECHEC")) -> BANQUE | J30: 1 | K30: =IF($D30<>0,J30*50000,IF($E30<>0,J30*50000,0)) -> 50000 | M30: =IF($D30<>0,L30*75000,IF($E30<>0,L30*75000,0)) -> 0 | N30: 2 | O30: =IF($D30<>0,N30*100000,IF($E30<>0,N30*100000,0)) -> 200000 | P30: =VLOOKUP(A30,[13]TONTJANV24!$A$6:$R$39,12,0) -> 0 | Q30: =IFERROR(VLOOKUP(A30,[14]TONTJANV24!$A$7:$P$23,10,0),0) -> 0 | R30: =IFERROR(VLOOKUP(A30,[15]TONTJANV24!$A$7:$P$20,10,0),0) -> 0 | U30: =G30+S30++R30+P30+O30+M30+I30+K30+Q30+V30+W30 -> 250000 | AQ30: =IF(H30="ECHEC",((K30+M30+O30)*20/100),0) -> 0 | AR30: =IF(H30="ECHEC",((K30+M30+O30)*20/100),0) -> 0 | AS30: =IF(H30="ECHEC",0,(K30+I30-25000)) -> 25000 | AW30: =IF(AC30=0,AI30,(1*25000*12)+AI30-AC30) -> 0 | AX30: =IF(AD30=0,AJ30,(1*75000*12)+(AJ30)-AD30) -> 0 | AY30: =IF(AE30=0,AK30,(1*100000*12)+(AK30)-AE30) -> 0 | AZ30: =SUM(AV30:AY30)-BF30+Z30-F30+BH30+BI30+BJ30+BK30+BL30+BM30 -> 0 | BD30: =IF(AZ30=0,(AZ30-BA30-BC30),(AZ30-BA30-BB30-BC30))+F30 -> 0 | BF30: =Z30*1/100*BG30 -> 0 | BG30: 11 | BO30: DECES | BP30: MUTUELLE
A31: AS201638 | B31: =VLOOKUP(A31,[11]LISTADHERENT!A$5:H$50,3,0) -> SIMO PIERRE | C31: =D31+E31+F31-U31-BB31 -> 0 | D31: =VLOOKUP(A31,[12]HISTOBQUEJANV24!$A$6:$G$46,3,0) -> 150000 | E31: =VLOOKUP(A31,[12]HISTOBQUEJANV24!$A$6:$G$41,4,0) -> 0 | F31: =VLOOKUP(A31,[12]HISTOBQUEJANV24!$A$6:$G$41,5,0) -> 0 | G31: =IF(H31="ESPECES",3000,0) -> 0 | H31: =IF($D31<>0,"BANQUE",IF($E31<>0,"ESPECES","ECHEC")) -> BANQUE | J31: 1 | K31: =IF($D31<>0,J31*50000,IF($E31<>0,J31*50000,0)) -> 50000 | M31: =IF($D31<>0,L31*75000,IF($E31<>0,L31*75000,0)) -> 0 | N31: 1 | O31: =IF($D31<>0,N31*100000,IF($E31<>0,N31*100000,0)) -> 100000 | P31: =VLOOKUP(A31,[13]TONTJANV24!$A$6:$R$39,12,0) -> 0 | Q31: =IFERROR(VLOOKUP(A31,[14]TONTJANV24!$A$7:$P$23,10,0),0) -> 0 | R31: =IFERROR(VLOOKUP(A31,[15]TONTJANV24!$A$7:$P$20,10,0),0) -> 0 | U31: =G31+S31++R31+P31+O31+M31+I31+K31+Q31+V31+W31 -> 150000 | AQ31: =IF(H31="ECHEC",((K31+M31+O31)*20/100),0) -> 0 | AR31: =IF(H31="ECHEC",((K31+M31+O31)*20/100),0) -> 0 | AS31: =IF(H31="ECHEC",0,(K31+I31-25000)) -> 25000 | AW31: =IF(AC31=0,AI31,(1*25000*12)+AI31-AC31) -> 0 | AX31: =IF(AD31=0,AJ31,(1*75000*12)+(AJ31)-AD31) -> 0 | AY31: =IF(AE31=0,AK31,(1*100000*12)+(AK31)-AE31) -> 0 | AZ31: =SUM(AV31:AY31)-BF31+Z31-F31+BH31+BI31+BJ31+BK31+BL31+BM31 -> 0 | BD31: =IF(AZ31=0,(AZ31-BA31-BC31),(AZ31-BA31-BB31-BC31))+F31 -> 0 | BF31: =Z31*1/100*BG31 -> 0 | BG31: 11 | BO31: TRANSPORT DELEGUE | BP31: MUTUELLE
A32: AS201641 | B32: =VLOOKUP(A32,[11]LISTADHERENT!A$5:H$50,3,0) -> TCHOUAMOU MATHIEU | C32: =D32+E32+F32-U32-BB32 -> 0 | D32: =VLOOKUP(A32,[12]HISTOBQUEJANV24!$A$6:$G$46,3,0) -> 125000 | E32: =VLOOKUP(A32,[12]HISTOBQUEJANV24!$A$6:$G$41,4,0) -> 0 | F32: =VLOOKUP(A32,[12]HISTOBQUEJANV24!$A$6:$G$41,5,0) -> 0 | G32: =IF(H32="ESPECES",3000,0) -> 0 | H32: =IF($D32<>0,"BANQUE",IF($E32<>0,"ESPECES","ECHEC")) -> BANQUE | J32: 1 | K32: =IF($D32<>0,J32*50000,IF($E32<>0,J32*50000,0)) -> 50000 | L32: 1 | M32: =IF($D32<>0,L32*75000,IF($E32<>0,L32*75000,0)) -> 75000 | O32: =IF($D32<>0,N32*100000,IF($E32<>0,N32*100000,0)) -> 0 | P32: =VLOOKUP(A32,[13]TONTJANV24!$A$6:$R$39,12,0) -> 0 | Q32: =IFERROR(VLOOKUP(A32,[14]TONTJANV24!$A$7:$P$23,10,0),0) -> 0 | R32: =IFERROR(VLOOKUP(A32,[15]TONTJANV24!$A$7:$P$20,10,0),0) -> 0 | U32: =G32+S32++R32+P32+O32+M32+I32+K32+Q32+V32+W32 -> 125000 | Z32: 1000000 | AQ32: =IF(H32="ECHEC",((K32+M32+O32)*20/100),0) -> 0 | AR32: =IF(H32="ECHEC",((K32+M32+O32)*20/100),0) -> 0 | AS32: =IF(H32="ECHEC",0,(K32+I32-25000)) -> 25000 | AW32: =IF(AC32=0,AI32,(1*25000*12)+AI32-AC32) -> 0 | AX32: =IF(AD32=0,AJ32,(1*75000*12)+(AJ32)-AD32) -> 0 | AY32: =IF(AE32=0,AK32,(1*100000*12)+(AK32)-AE32) -> 0 | AZ32: =SUM(AV32:AY32)-BF32+Z32-F32+BH32+BI32+BJ32+BK32+BL32+BM32 -> 940000 | BD32: =IF(AZ32=0,(AZ32-BA32-BC32),(AZ32-BA32-BB32-BC32))+F32 -> 940000 | BE32: OK | BF32: =Z32*1/100*BG32 -> 60000 | BG32: 6
A33: AS201660 | B33: =VLOOKUP(A33,[11]LISTADHERENT!A$5:H$50,3,0) -> TCHOUATEU AUGUSTIN | C33: =D33+E33+F33-U33-BB33 -> 120000 | D33: =VLOOKUP(A33,[12]HISTOBQUEJANV24!$A$6:$G$46,3,0) -> 540000 | E33: =VLOOKUP(A33,[12]HISTOBQUEJANV24!$A$6:$G$41,4,0) -> 0 | F33: =VLOOKUP(A33,[12]HISTOBQUEJANV24!$A$6:$G$41,5,0) -> 0 | G33: =IF(H33="ESPECES",3000,0) -> 0 | H33: =IF($D33<>0,"BANQUE",IF($E33<>0,"ESPECES","ECHEC")) -> BANQUE | I33: 245000 | J33: 1 | K33: =IF($D33<>0,J33*50000,IF($E33<>0,J33*50000,0)) -> 50000 | M33: =IF($D33<>0,L33*75000,IF($E33<>0,L33*75000,0)) -> 0 | N33: 1 | O33: =IF($D33<>0,N33*100000,IF($E33<>0,N33*100000,0)) -> 100000 | P33: =VLOOKUP(A33,[13]TONTJANV24!$A$6:$R$39,12,0) -> 0 | Q33: =IFERROR(VLOOKUP(A33,[14]TONTJANV24!$A$7:$P$23,10,0),0) -> 0 | R33: =IFERROR(VLOOKUP(A33,[15]TONTJANV24!$A$7:$P$20,10,0),0) -> 0 | U33: =G33+S33++R33+P33+O33+M33+I33+K33+Q33+V33+W33 -> 420000 | W33: 25000 | AQ33: =IF(H33="ECHEC",((K33+M33+O33)*20/100),0) -> 0 | AR33: =IF(H33="ECHEC",((K33+M33+O33)*20/100),0) -> 0 | AS33: =IF(H33="ECHEC",0,(K33+I33-25000)) -> 270000 | AT33: 120000 | AW33: =IF(AC33=0,AI33,(1*25000*12)+AI33-AC33) -> 0 | AX33: =IF(AD33=0,AJ33,(1*75000*12)+(AJ33)-AD33) -> 0 | AY33: =IF(AE33=0,AK33,(1*100000*12)+(AK33)-AE33) -> 0 | AZ33: =SUM(AV33:AY33)-BF33+Z33-F33+BH33+BI33+BJ33+BK33+BL33+BM33 -> 0 | BD33: =IF(AZ33=0,(AZ33-BA33-BC33),(AZ33-BA33-BB33-BC33))+F33 -> 0 | BF33: =Z33*1/100*BG33 -> 0 | BG33: 11 | BO33: S/TOTAL | BQ33: =SUM(BQ30:BQ32) -> 0
A34: AS201643 | B34: =VLOOKUP(A34,[11]LISTADHERENT!A$5:H$50,3,0) -> TCHOUTOU NANA CLAUDE | C34: =D34+E34+F34-U34-BB34 -> 0 | D34: =VLOOKUP(A34,[12]HISTOBQUEJANV24!$A$6:$G$46,3,0) -> 50000 | E34: =VLOOKUP(A34,[12]HISTOBQUEJANV24!$A$6:$G$41,4,0) -> 0 | F34: =VLOOKUP(A34,[12]HISTOBQUEJANV24!$A$6:$G$41,5,0) -> 0 | G34: =IF(H34="ESPECES",3000,0) -> 0 | H34: =IF($D34<>0,"BANQUE",IF($E34<>0,"ESPECES","ECHEC")) -> BANQUE | J34: 1 | K34: =IF($D34<>0,J34*50000,IF($E34<>0,J34*50000,0)) -> 50000 | M34: =IF($D34<>0,L34*75000,IF($E34<>0,L34*75000,0)) -> 0 | O34: =IF($D34<>0,N34*100000,IF($E34<>0,N34*100000,0)) -> 0 | P34: =VLOOKUP(A34,[13]TONTJANV24!$A$6:$R$39,12,0) -> 0 | Q34: =IFERROR(VLOOKUP(A34,[14]TONTJANV24!$A$7:$P$23,10,0),0) -> 0 | R34: =IFERROR(VLOOKUP(A34,[15]TONTJANV24!$A$7:$P$20,10,0),0) -> 0 | U34: =G34+S34++R34+P34+O34+M34+I34+K34+Q34+V34+W34 -> 50000 | AQ34: =IF(H34="ECHEC",((K34+M34+O34)*20/100),0) -> 0 | AR34: =IF(H34="ECHEC",((K34+M34+O34)*20/100),0) -> 0 | AS34: =IF(H34="ECHEC",0,(K34+I34-25000)) -> 25000 | AW34: =IF(AC34=0,AI34,(1*25000*12)+AI34-AC34) -> 0 | AX34: =IF(AD34=0,AJ34,(1*75000*12)+(AJ34)-AD34) -> 0 | AY34: =IF(AE34=0,AK34,(1*100000*12)+(AK34)-AE34) -> 0 | AZ34: =SUM(AV34:AY34)-BF34+Z34-F34+BH34+BI34+BJ34+BK34+BL34+BM34 -> 0 | BD34: =IF(AZ34=0,(AZ34-BA34-BC34),(AZ34-BA34-BB34-BC34))+F34 -> 0 | BF34: =Z34*1/100*BG34 -> 0 | BG34: 11 | BO34: S/TOTAL | BQ34: =SUM(BQ31:BQ33) -> 0
A35: AS201658 | B35: =VLOOKUP(A35,[11]LISTADHERENT!A$5:H$50,3,0) -> YANTCHOU GERVAIS | C35: =D35+E35+F35-U35-BB35 -> 0 | D35: =VLOOKUP(A35,[12]HISTOBQUEJANV24!$A$6:$G$46,3,0) -> 60000 | E35: =VLOOKUP(A35,[12]HISTOBQUEJANV24!$A$6:$G$41,4,0) -> 0 | F35: =VLOOKUP(A35,[12]HISTOBQUEJANV24!$A$6:$G$41,5,0) -> 0 | G35: =IF(H35="ESPECES",3000,0) -> 0 | H35: =IF($D35<>0,"BANQUE",IF($E35<>0,"ESPECES","ECHEC")) -> BANQUE | I35: 10000 | J35: 1 | K35: =IF($D35<>0,J35*50000,IF($E35<>0,J35*50000,0)) -> 50000 | M35: =IF($D35<>0,L35*75000,IF($E35<>0,L35*75000,0)) -> 0 | O35: =IF($D35<>0,N35*100000,IF($E35<>0,N35*100000,0)) -> 0 | P35: =VLOOKUP(A35,[13]TONTJANV24!$A$6:$R$39,12,0) -> 0 | Q35: =IFERROR(VLOOKUP(A35,[14]TONTJANV24!$A$7:$P$23,10,0),0) -> 0 | R35: =IFERROR(VLOOKUP(A35,[15]TONTJANV24!$A$7:$P$20,10,0),0) -> 0 | U35: =G35+S35++R35+P35+O35+M35+I35+K35+Q35+V35+W35 -> 60000 | AQ35: =IF(H35="ECHEC",((K35+M35+O35)*20/100),0) -> 0 | AR35: =IF(H35="ECHEC",((K35+M35+O35)*20/100),0) -> 0 | AS35: =IF(H35="ECHEC",0,(K35+I35-25000)) -> 35000 | AW35: =IF(AC35=0,AI35,(1*25000*12)+AI35-AC35) -> 0 | AX35: =IF(AD35=0,AJ35,(1*75000*12)+(AJ35)-AD35) -> 0 | AY35: =IF(AE35=0,AK35,(1*100000*12)+(AK35)-AE35) -> 0 | AZ35: =SUM(AV35:AY35)-BF35+Z35-F35+BH35+BI35+BJ35+BK35+BL35+BM35 -> 0 | BD35: =IF(AZ35=0,(AZ35-BA35-BC35),(AZ35-BA35-BB35-BC35))+F35 -> 0 | BF35: =Z35*1/100*BG35 -> 0 | BG35: 11
A36: AS201646 | B36: =VLOOKUP(A36,[11]LISTADHERENT!A$5:H$50,3,0) -> YEPMOU JEAN JACQUES | C36: =D36+E36+F36-U36-BB36 -> 53000 | D36: =VLOOKUP(A36,[12]HISTOBQUEJANV24!$A$6:$G$46,3,0) -> 50000 | E36: =VLOOKUP(A36,[12]HISTOBQUEJANV24!$A$6:$G$41,4,0) -> 50000 | F36: =VLOOKUP(A36,[12]HISTOBQUEJANV24!$A$6:$G$41,5,0) -> 0 | G36: =IF(H36="ESPECES",3000,0)-3000 -> -3000 | H36: =IF($D36<>0,"BANQUE",IF($E36<>0,"ESPECES","ECHEC")) -> BANQUE | J36: 1 | K36: =IF($D36<>0,J36*50000,IF($E36<>0,J36*50000,0)) -> 50000 | M36: =IF($D36<>0,L36*75000,IF($E36<>0,L36*75000,0)) -> 0 | O36: =IF($D36<>0,N36*100000,IF($E36<>0,N36*100000,0)) -> 0 | P36: =VLOOKUP(A36,[13]TONTJANV24!$A$6:$R$39,12,0) -> 0 | Q36: =IFERROR(VLOOKUP(A36,[14]TONTJANV24!$A$7:$P$23,10,0),0) -> 0 | R36: =IFERROR(VLOOKUP(A36,[15]TONTJANV24!$A$7:$P$20,10,0),0) -> 0 | U36: =G36+S36++R36+P36+O36+M36+I36+K36+Q36+V36+W36 -> 47000 | AQ36: =IF(H36="ECHEC",((K36+M36+O36)*20/100),0) -> 0 | AR36: =IF(H36="ECHEC",((K36+M36+O36)*20/100),0) -> 0 | AS36: =IF(H36="ECHEC",0,(K36+I36-25000)) -> 25000 | AW36: =IF(AC36=0,AI36,(1*25000*12)+AI36-AC36) -> 0 | AX36: =IF(AD36=0,AJ36,(1*75000*12)+(AJ36)-AD36) -> 0 | AY36: =IF(AE36=0,AK36,(1*100000*12)+(AK36)-AE36) -> 0 | AZ36: =SUM(AV36:AY36)-BF36+Z36-F36+BH36+BI36+BJ36+BK36+BL36+BM36 -> 0 | BD36: =IF(AZ36=0,(AZ36-BA36-BC36),(AZ36-BA36-BB36-BC36))+F36 -> 0 | BF36: =Z36*1/100*BG36 -> 0 | BG36: 11 | BO36: COLLATION | BP36: COLLATION | BQ36: 100000
A37: AS201659 | B37: =VLOOKUP(A37,[11]LISTADHERENT!A$5:H$50,3,0) -> YIALA ALAIN OSCAR | C37: =D37+E37+F37-U37-BB37 -> 0 | D37: =VLOOKUP(A37,[12]HISTOBQUEJANV24!$A$6:$G$46,3,0) -> 150000 | E37: =VLOOKUP(A37,[12]HISTOBQUEJANV24!$A$6:$G$41,4,0) -> 25000 | F37: =VLOOKUP(A37,[12]HISTOBQUEJANV24!$A$6:$G$41,5,0) -> 0 | G37: =IF(H37="ESPECES",3000,0) -> 0 | H37: =IF($D37<>0,"BANQUE",IF($E37<>0,"ESPECES","ECHEC")) -> BANQUE | J37: 1 | K37: =IF($D37<>0,J37*50000,IF($E37<>0,J37*50000,0)) -> 50000 | M37: =IF($D37<>0,L37*75000,IF($E37<>0,L37*75000,0)) -> 0 | N37: 1 | O37: =IF($D37<>0,N37*100000,IF($E37<>0,N37*100000,0)) -> 100000 | P37: =VLOOKUP(A37,[13]TONTJANV24!$A$6:$R$39,12,0) -> 0 | Q37: =IFERROR(VLOOKUP(A37,[14]TONTJANV24!$A$7:$P$23,10,0),0) -> 0 | R37: =IFERROR(VLOOKUP(A37,[15]TONTJANV24!$A$7:$P$20,10,0),0) -> 0 | U37: =G37+S37++R37+P37+O37+M37+I37+K37+Q37+V37+W37 -> 175000 | W37: 25000 | AQ37: =IF(H37="ECHEC",((K37+M37+O37)*20/100),0) -> 0 | AR37: =IF(H37="ECHEC",((K37+M37+O37)*20/100),0) -> 0 | AS37: =IF(H37="ECHEC",0,(K37+I37-25000)) -> 25000 | AW37: =IF(AC37=0,AI37,(1*25000*12)+AI37-AC37) -> 0 | AX37: =IF(AD37=0,AJ37,(1*75000*12)+(AJ37)-AD37) -> 0 | AY37: =IF(AE37=0,AK37,(1*100000*12)+(AK37)-AE37) -> 0 | AZ37: =SUM(AV37:AY37)-BF37+Z37-F37+BH37+BI37+BJ37+BK37+BL37+BM37 -> 0 | BD37: =IF(AZ37=0,(AZ37-BA37-BC37),(AZ37-BA37-BB37-BC37))+F37 -> 0 | BF37: =Z37*1/100*BG37 -> 0 | BG37: 11 | BO37: BOISSON | BP37: COLLATION
A38: AS201647 | B38: =VLOOKUP(A38,[11]LISTADHERENT!A$5:H$50,3,0) -> YOUMBI EMMANUEL | C38: =D38+E38+F38-U38-BB38 -> 0 | D38: =VLOOKUP(A38,[12]HISTOBQUEJANV24!$A$6:$G$46,3,0) -> 125000 | E38: =VLOOKUP(A38,[12]HISTOBQUEJANV24!$A$6:$G$41,4,0) -> 0 | F38: =VLOOKUP(A38,[12]HISTOBQUEJANV24!$A$6:$G$41,5,0) -> 0 | G38: =IF(H38="ESPECES",3000,0) -> 0 | H38: =IF($D38<>0,"BANQUE",IF($E38<>0,"ESPECES","ECHEC")) -> BANQUE | J38: 1 | K38: =IF($D38<>0,J38*50000,IF($E38<>0,J38*50000,0)) -> 50000 | L38: 1 | M38: =IF($D38<>0,L38*75000,IF($E38<>0,L38*75000,0)) -> 75000 | O38: =IF($D38<>0,N38*100000,IF($E38<>0,N38*100000,0)) -> 0 | P38: =VLOOKUP(A38,[13]TONTJANV24!$A$6:$R$39,12,0) -> 0 | Q38: =IFERROR(VLOOKUP(A38,[14]TONTJANV24!$A$7:$P$23,10,0),0) -> 0 | R38: =IFERROR(VLOOKUP(A38,[15]TONTJANV24!$A$7:$P$20,10,0),0) -> 0 | U38: =G38+S38++R38+P38+O38+M38+I38+K38+Q38+V38+W38 -> 125000 | AQ38: =IF(H38="ECHEC",((K38+M38+O38)*20/100),0) -> 0 | AR38: =IF(H38="ECHEC",((K38+M38+O38)*20/100),0) -> 0 | AS38: =IF(H38="ECHEC",0,(K38+I38-25000)) -> 25000 | AW38: =IF(AC38=0,AI38,(1*25000*12)+AI38-AC38) -> 0 | AX38: =IF(AD38=0,AJ38,(1*75000*12)+(AJ38)-AD38) -> 0 | AY38: =IF(AE38=0,AK38,(1*100000*12)+(AK38)-AE38) -> 0 | AZ38: =SUM(AV38:AY38)-BF38+Z38-F38+BH38+BI38+BJ38+BK38+BL38+BM38 -> 0 | BD38: =IF(AZ38=0,(AZ38-BA38-BC38),(AZ38-BA38-BB38-BC38))+F38 -> 0 | BF38: =Z38*1/100*BG38 -> 0 | BG38: 11 | BO38: BOISSON | BP38: COLLATION
B40: TOTAUX | C40: =SUM(C6:C39) -> 229000 | D40: =SUM(D6:D39) -> 5456000 | E40: =SUM(E6:E39) -> 200000 | F40: =SUM(F6:F39) -> 0 | G40: =SUM(G6:G39) -> -3000 | H40: =SUM(H6:H39) -> 0 | I40: =SUM(I6:I39) -> 755000 | J40: =SUM(J6:J39) -> 32 | ... S40: =SUM(S6:S39) -> 0 | U40: =SUM(U6:U39) -> 5427000 | V40: =SUM(V6:V39) -> 0 | W40: =SUM(W6:W39) -> 75000 | X40: =SUM(X6:X39) -> 0 | Y40: =SUM(Y6:Y39) -> 0 | Z40: =SUM(Z6:Z39) -> 2000000 | AA40: =SUM(AA6:AA39) -> 0 | AC40: =SUM(AC6:AC39) -> 38000 | AD40: =SUM(AD6:AD39) -> 125000 | AE40: =SUM(AE6:AE39) -> 355000 | AF40: =SUM(AF6:AF39) -> 0 | AG40: =SUM(AG6:AG39) -> 0 | AI40: =SUM(AI6:AI39) -> 0 | AJ40: =SUM(AJ6:AJ39) -> 200000 | AK40: =SUM(AK6:AK39) -> 100000 | AL40: =SUM(AL6:AL39) -> 0 | AM40: =SUM(AM6:AM39) -> 4000 | AN40: =SUM(AN6:AN39) -> 1000 | AO40: =SUM(AO6:AO39) -> 0 | AP40: =SUM(AP6:AP39) -> 0 | ... BF40: =SUM(BF6:BF39) -> 176000 | BH40: =SUM(BH6:BH39) -> 27000 | BI40: =SUM(BI6:BI39) -> 200000 | BJ40: =SUM(BJ6:BJ39) -> 0 | BK40: =SUM(BK6:BK39) -> 100000 | BL40: =SUM(BL6:BL39) -> 0 | BM40: =SUM(BM6:BM39) -> 0 | BO40: S/TOTAL | BQ40: =SUM(BQ36:BQ38) -> 100000
B43: AS201643 | BO43: TRANSPORT DELEGUE | BP43: MUTUELLE
C44: BANQUE | F44: ESPECES
B45: LIBELLE | C45: SORTIE | D45: ENTREE | E45: EN COMPTE | F45: ENTREE | G45: SORTIE | H45: SOLDE | BO45: S/TOTAL | BQ45: =SUM(BQ42:BQ44) -> 0
B46: REPORT
B47: OPERATIONS DU JOUR | C47: =BD40 -> 7565000 | D47: =+D40 -> 5456000 | E47: =+C47-D47 -> 2109000 | F47: =E40 -> 200000 | G47: =+BA40 -> 790000 | H47: =+F47-G47 -> -590000
AZ85: =SUM(AZ8:AZ84) -> 16971000

Sheet HISTOFEV24
A1: ASSOCIATION | B1: ASELBY
A2: ANNEE | B2: 2024
A3: 1 | B3: 2 | C3: 3 | D3: 4 | E3: 5 | F3: 6 | G3: 7 | H3: 8 | I3: 9 | J3: 10 | K3: 11 | L3: 12 | M3: 13 | N3: 14 | O3: 15 | P3: 16 | Q3: 17 | R3: 18 | S3: 19 | T3: 20 | U3: 21 | V3: 22 | W3: 23 | X3: 24 | Y3: 25 | Z3: 26 | AA3: 27 | AB3: 28 | AC3: 29 | AD3: 30 | AE3: 31 | AF3: 32 | AG3: 33 | AH3: 34 | AI3: 35 | AJ3: 36 | AK3: 37 | AL3: 38 | AM3: 39 | AN3: 40 | AO3: 41 | AP3: 42 | AQ3: 43 | AR3: 44 | AS3: 45 | AT3: 46 | AU3: 47 | AV3: 48 | AW3: 49 | AX3: 50 | AY3: 51 | AZ3: 52 | BA3: 53 | BB3: 54 | BC3: 55 | BD3: 56 | BE3: 57 | BF3: 58 | BG3: 59 | BH3: 60 | BI3: 61 | BJ3: 62 | BK3: 63 | BL3: 64 | BM3: 65 | BO3: 66 | BP3: 67 | BQ3: 68
B4: TABLEAU DE BORD SAISIE DES DONNEES
A5: MATRICULE | B5: NOM ET PRENOM | C5: BONUS MALUS | D5: HISTORIQUE BANQUE | E5: HITORIQUE ESPECES | F5: HITORIQUE TONTINE | G5: PENALITE VERSEMENT ESPECES | H5: MODE PAIEMENT TONTINE | I5: COMPLEMENT EPARGNE | J5: NBRE DE LOT | K5: TONTINE 40 000 | L5: NBRE DE LOT | M5: TONTINE 75 000 | N5: NBRE DE LOT | O5: TONTINE 100 000 | P5: REMBOURSEMENT PETIT LOT T50 | Q5: REMBOURSEMENT PETIT LOT T75 | R5: REMBOURSEMENT PETIT LOT T100 | S5: REMBOURSEMENT PRÊT FONDS | T5: MODE PAIEMENT REMBOURSEMENT PRÊT FONDS | U5: MONTANT ENGAGEMENT | V5: SANCTION | W5: INSCRIPTION | X5: EPARGNE ASSURANCE | Y5: RECONSTITUTION FONDS | Z5: PRÊT FONDS | AA5: MODE PAIEMENT PRÊT | AB5: NUM CHEQUE | AC5: ACHAT LOT PRINCIPAL T50 | AD5: ACHAT LOT PRINCIPAL T75 | AE5: ACHAT LOT PRINCIPAL T100 | AF5: MODE PAIEMENT LOT PRINCIPAL | AG5: NUM CHEQUE | AH5: PENALITE VERSEMENT ESPECES | AI5: VENTE PETIT LOT T50 | AJ5: VENTE PETIT LOT T75 | AK5: VENTE PETIT LOT T100 | AL5: INTERET PETIT LOT T50 | AM5: INTERET PETIT LOT T75 | AN5: INTERET PETIT LOT T100 | AO5: NUM CHEQUE | AP5: MODE PAIEMENT PETEIT LOT | AQ5: PENELAITE RETARD TONTINE | AR5: PENELAITE ECHEC TONTINE | AS5: RESTE | AT5: MUTUELLE | AU5: REMBOURSEMENT TRANSPORT | AV5: RETRAIT PARTIEL FONDS | AW5: MONTANT T50 | AX5: MONTANT T75 | AY5: MONTANT T100 | AZ5: MONTANT CHEQUE | BA5: MONTANT ESPECES | BB5: CONTRIBUTION FOYER | BC5: AUTRES SOTIES | BD5: MONTANT CHEQUE EFFECTIF | BE5: NUMERO CHEQUE | BF5: INTERET PRÊT | BG5: NBRE MOIS | BH5: DEPENSE FONDS DE ROULEMENT | BI5: DEPENSE FRAIS EXCEPTIONNEL | BJ5: DEPENSE FONDS MUTUEL | BK5: DEPENSE COLLATION RECEPTION | BL5: PENALITE PRET FONDS | BM5: DEPENSE PENALITE VERSEMENT BANQUE | BN5: AUTRES DEPENSES | BO5: LIBELLE | BP5: COMPTE | BQ5: MONTANT
A6: AS201648 | B6: =VLOOKUP(A6,[11]LISTADHERENT!A$5:H$50,3,0) -> ASELBY | C6: =D6+E6+F6-U6-BB6 -> 0 | D6: =VLOOKUP(A6,[12]HISTOBQUEFEV24!$A$6:$G$46,3,0) -> 175000 | E6: =VLOOKUP(A6,[12]HISTOBQUEFEV24!$A$6:$G$41,4,0) -> 0 | F6: =VLOOKUP(A6,[12]HISTOBQUEFEV24!$A$6:$G$41,5,0) -> 0 | G6: =IF(H6="ESPECES",3000,0) -> 0 | H6: =IF($D6<>0,"BANQUE",IF($E6<>0,"ESPECES","ECHEC")) -> BANQUE | K6: =IF($D6<>0,J6*50000,IF($E6<>0,J6*50000,0)) -> 0 | L6: 1 | M6: =IF($D6<>0,L6*75000,IF($E6<>0,L6*75000,0)) -> 75000 | N6: 1 | O6: =IF($D6<>0,N6*100000,IF($E6<>0,N6*100000,0)) -> 100000 | P6: =IFERROR(CHERCHEV(A6,[13]TONTFEV24!$A$6:$R$39,12,0),0) -> 0 | Q6: =IFERROR(VLOOKUP(A6,[14]TONTFEV24!$A$7:$P$23,10,0),0) -> 0 | R6: =IFERROR(VLOOKUP(A6,[15]TONTFEV24!$A$7:$P$20,10,0),0) -> 0 | U6: =G6+S6++R6+P6+O6+M6+I6+K6+Q6+V6+W6 -> 175000 | AQ6: =IF(H6="ECHEC",((K6+M6+O6)*20/100),0) -> 0 | AR6: =IF(H6="ECHEC",((K6+M6+O6)*20/100),0) -> 0 | AW6: =IF(AC6=0,AI6,(1*25000*12)+AI6-AC6) -> 0 | AX6: =IF(AD6=0,AJ6,(1*75000*12)+(AJ6)-AD6) -> 0 | AY6: =IF(AE6=0,AK6,(1*100000*12)+(AK6)-AE6) -> 0 | AZ6: =SUM(AV6:AY6)-BF6+Z6-F6+BH6+BI6+BJ6+BK6+BL6+BM6 -> 127000 | BD6: =IF(AZ6=0,(AZ6-BA6-BC6),(AZ6-BA6-BB6-BC6)) -> 127000 | BE6: OK | BF6: =Z6*1/100*BG6 -> 0 | BG6: 10 | BH6: =BQ16 -> 27000 | BI6: =BQ28 -> 0 | BJ6: =BQ33 -> 100000 | BN6: =+BQ22 -> 0 | BO6: ACHAT FOURNITURE | BP6: FONDS DE ROULEMENT | BQ6: 3000
A7: AS201601 | B7: =VLOOKUP(A7,[11]LISTADHERENT!A$5:H$50,3,0) -> BAKOP ACHILLE | C7: =D7+E7+F7-U7-BB7 -> 6000 | D7: =VLOOKUP(A7,[12]HISTOBQUEFEV24!$A$6:$G$46,3,0) -> 56000 | E7: =VLOOKUP(A7,[12]HISTOBQUEFEV24!$A$6:$G$41,4,0) -> 0 | F7: =VLOOKUP(A7,[12]HISTOBQUEFEV24!$A$6:$G$41,5,0) -> 0 | G7: =IF(H7="ESPECES",3000,0) -> 0 | H7: =IF($D7<>0,"BANQUE",IF($E7<>0,"ESPECES","ECHEC")) -> BANQUE | J7: 1 | K7: =IF($D7<>0,J7*50000,IF($E7<>0,J7*50000,0)) -> 50000 | M7: =IF($D7<>0,L7*75000,IF($E7<>0,L7*75000,0)) -> 0 | O7: =IF($D7<>0,N7*100000,IF($E7<>0,N7*100000,0)) -> 0 | P7: =VLOOKUP(A7,[13]TONTFEV24!$A$6:$R$39,12,0) -> 0 | Q7: =IFERROR(VLOOKUP(A7,[14]TONTFEV24!$A$7:$P$23,10,0),0) -> 0 | R7: =IFERROR(VLOOKUP(A7,[15]TONTFEV24!$A$7:$P$20,10,0),0) -> 0 | U7: =G7+S7++R7+P7+O7+M7+I7+K7+Q7+V7+W7 -> 50000 | AI7: 60000 | AL7: 1000 | AQ7: =IF(H7="ECHEC",((K7+M7+O7)*20/100),0) -> 0 | AR7: =IF(H7="ECHEC",((K7+M7+O7)*20/100),0) -> 0 | AS7: =IF(H7="ECHEC",0,(K7+I7-25000)) -> 25000 | AW7: =IF(AC7=0,AI7,(1*25000*12)+AI7-AC7) -> 60000 | AX7: =IF(AD7=0,AJ7,(1*75000*12)+(AJ7)-AD7) -> 0 | AY7: =IF(AE7=0,AK7,(1*100000*12)+(AK7)-AE7) -> 0 | AZ7: =SUM(AV7:AY7)-BF7+Z7-F7+BH7+BI7+BJ7+BK7+BL7+BM7+6000 -> 60000 | BD7: =IF(AZ7=0,(AZ7-BA7-BC7),(AZ7-BA7-BB7-BC7)) -> 60000 | BE7: OK | BF7: =Z7*1/100*BG7+6000 -> 6000 | BG7: 10 | BO7: COMMUNICATION | BP7: FONDS DE ROULEMENT
A8: AS201602 | B8: =VLOOKUP(A8,[11]LISTADHERENT!A$5:H$50,3,0) -> BOUTCHOUANG WILLIAM | C8: =D8+E8+F8-U8-BB8 -> 0 | D8: =VLOOKUP(A8,[12]HISTOBQUEFEV24!$A$6:$G$46,3,0) -> 100000 | E8: =VLOOKUP(A8,[12]HISTOBQUEFEV24!$A$6:$G$41,4,0) -> 25000 | F8: =VLOOKUP(A8,[12]HISTOBQUEFEV24!$A$6:$G$41,5,0) -> 0 | G8: =IF(H8="ESPECES",3000,0)+3000 -> 3000 | H8: =IF($D8<>0,"BANQUE",IF($E8<>0,"ESPECES","ECHEC")) -> BANQUE | I8: -3000 | J8: 1 | K8: =IF($D8<>0,J8*50000,IF($E8<>0,J8*50000,0)) -> 50000 | L8: 1 | M8: =IF($D8<>0,L8*75000,IF($E8<>0,L8*75000,0)) -> 75000 | O8: =IF($D8<>0,N8*100000,IF($E8<>0,N8*100000,0)) -> 0 | P8: =VLOOKUP(A8,[13]TONTFEV24!$A$6:$R$39,12,0) -> 0 | Q8: =IFERROR(VLOOKUP(A8,[14]TONTFEV24!$A$7:$P$23,10,0),0) -> 0 | R8: =IFERROR(VLOOKUP(A8,[15]TONTFEV24!$A$7:$P$20,10,0),0) -> 0 | U8: =G8+S8++R8+P8+O8+M8+I8+K8+Q8+V8+W8 -> 125000 | AQ8: =IF(H8="ECHEC",((K8+M8+O8)*20/100),0) -> 0 | AR8: =IF(H8="ECHEC",((K8+M8+O8)*20/100),0) -> 0 | AS8: =IF(H8="ECHEC",0,(K8+I8-25000)) -> 22000 | AW8: =IF(AC8=0,AI8,(1*25000*12)+AI8-AC8) -> 0 | AX8: =IF(AD8=0,AJ8,(1*75000*12)+(AJ8)-AD8) -> 0 | AY8: =IF(AE8=0,AK8,(1*100000*12)+(AK8)-AE8) -> 0 | AZ8: =SUM(AV8:AY8)-BF8+Z8-F8+BH8+BI8+BJ8+BK8+BL8+BM8 -> 0 | BD8: =IF(AZ8=0,(AZ8-BA8-BC8),(AZ8-BA8-BB8-BC8)) -> 0 | BF8: =Z8*1/100*BG8 -> 0 | BG8: 10 | BO8: COMMISSION | BP8: FONDS DE ROULEMENT | BQ8: 12000
A9: AS201604 | B9: =VLOOKUP(A9,[11]LISTADHERENT!A$5:H$50,3,0) -> DJOMO JEAN PAUL | C9: =D9+E9+F9-U9-BB9 -> 0 | D9: =VLOOKUP(A9,[12]HISTOBQUEFEV24!$A$6:$G$46,3,0) -> 250000 | E9: =VLOOKUP(A9,[12]HISTOBQUEFEV24!$A$6:$G$41,4,0) -> 0 | F9: =VLOOKUP(A9,[12]HISTOBQUEFEV24!$A$6:$G$41,5,0) -> 0 | G9: =IF(H9="ESPECES",3000,0) -> 0 | H9: =IF($D9<>0,"BANQUE",IF($E9<>0,"ESPECES","ECHEC")) -> BANQUE | J9: 1 | K9: =IF($D9<>0,J9*50000,IF($E9<>0,J9*50000,0)) -> 50000 | M9: =IF($D9<>0,L9*75000,IF($E9<>0,L9*75000,0)) -> 0 | N9: 2 | O9: =IF($D9<>0,N9*100000,IF($E9<>0,N9*100000,0)) -> 200000 | P9: =VLOOKUP(A9,[13]TONTFEV24!$A$6:$R$39,12,0) -> 0 | Q9: =IFERROR(VLOOKUP(A9,[14]TONTFEV24!$A$7:$P$23,10,0),0) -> 0 | R9: =IFERROR(VLOOKUP(A9,[15]TONTFEV24!$A$7:$P$20,10,0),0) -> 0 | U9: =G9+S9++R9+P9+O9+M9+I9+K9+Q9+V9+W9 -> 250000 | AQ9: =IF(H9="ECHEC",((K9+M9+O9)*20/100),0) -> 0 | AR9: =IF(H9="ECHEC",((K9+M9+O9)*20/100),0) -> 0 | AS9: =IF(H9="ECHEC",0,(K9+I9-25000)) -> 25000 | AW9: =IF(AC9=0,AI9,(1*25000*12)+AI9-AC9) -> 0 | AX9: =IF(AD9=0,AJ9,(1*75000*12)+(AJ9)-AD9) -> 0 | AY9: =IF(AE9=0,AK9,(1*100000*12)+(AK9)-AE9) -> 0 | AZ9: =SUM(AV9:AY9)-BF9+Z9-F9+BH9+BI9+BJ9+BK9+BL9+BM9 -> 0 | BD9: =IF(AZ9=0,(AZ9-BA9-BC9),(AZ9-BA9-BB9-BC9)) -> 0 | BF9: =Z9*1/100*BG9 -> 0 | BG9: 10 | BO9: OUVERTURE COMPTE | BP9: FONDS DE ROULEMENT
A10: AS201654 | B10: =VLOOKUP(A10,[11]LISTADHERENT!A$5:H$50,3,0) -> DJOMOU TCHAPDA | C10: =D10+E10+F10-U10-BB10 -> 0 | D10: =VLOOKUP(A10,[12]HISTOBQUEFEV24!$A$6:$G$46,3,0) -> 125000 | E10: =VLOOKUP(A10,[12]HISTOBQUEFEV24!$A$6:$G$41,4,0) -> 105000 | F10: =VLOOKUP(A10,[12]HISTOBQUEFEV24!$A$6:$G$41,5,0) -> 0 | G10: =IF(H10="ESPECES",3000,0)+3000 -> 3000 | H10: =IF($D10<>0,"BANQUE",IF($E10<>0,"ESPECES","ECHEC")) -> BANQUE | J10: 1 | K10: =IF($D10<>0,J10*50000,IF($E10<>0,J10*50000,0)) -> 50000 | L10: 1 | M10: =IF($D10<>0,L10*75000,IF($E10<>0,L10*75000,0)) -> 75000 | O10: =IF($D10<>0,N10*100000,IF($E10<>0,N10*100000,0)) -> 0 | P10: =VLOOKUP(A10,[13]TONTFEV24!$A$6:$R$39,12,0) -> 0 | Q10: =IFERROR(VLOOKUP(A10,[14]TONTFEV24!$A$7:$P$23,10,0),0) -> 102000 | R10: =IFERROR(VLOOKUP(A10,[15]TONTFEV24!$A$7:$P$20,10,0),0) -> 0 | U10: =G10+S10++R10+P10+O10+M10+I10+K10+Q10+V10+W10 -> 230000 | AI10: 60000 | AL10: 1000 | AP10: BANQUE | AQ10: =IF(H10="ECHEC",((K10+M10+O10)*20/100),0) -> 0 | AR10: =IF(H10="ECHEC",((K10+M10+O10)*20/100),0) -> 0 | AS10: =IF(H10="ECHEC",0,(K10+I10-25000)) -> 25000 | AW10: =IF(AC10=0,AI10,(1*25000*12)+AI10-AC10) -> 60000 | AX10: =IF(AD10=0,AJ10,(1*75000*12)+(AJ10)-AD10) -> 0 | AY10: =IF(AE10=0,AK10,(1*100000*12)+(AK10)-AE10) -> 0 | AZ10: =SUM(AV10:AY10)-BF10+Z10-F10+BH10+BI10+BJ10+BK10+BL10+BM10 -> 60000 | BA10: 60000 | BD10: =IF(AZ10=0,(AZ10-BA10-BC10),(AZ10-BA10-BB10-BC10)) -> 0 | BF10: =Z10*1/100*BG10 -> 0 | BG10: 10 | BO10: CREDIT TELEPHONE | BP10: FONDS DE ROULEMENT
A11: AS201605 | B11: =VLOOKUP(A11,[11]LISTADHERENT!A$5:H$50,3,0) -> DJOUKWE NANGUEN GUY BLAISE | C11: =D11+E11+F11-U11-BB11 -> 0 | D11: =VLOOKUP(A11,[12]HISTOBQUEFEV24!$A$6:$G$46,3,0) -> 227000 | E11: =VLOOKUP(A11,[12]HISTOBQUEFEV24!$A$6:$G$41,4,0) -> 0 | F11: =VLOOKUP(A11,[12]HISTOBQUEFEV24!$A$6:$G$41,5,0)+1000000 -> 1000000 | G11: =IF(H11="ESPECES",3000,0) -> 0 | H11: =IF($D11<>0,"BANQUE",IF($E11<>0,"ESPECES","ECHEC")) -> BANQUE | J11: 1 | K11: =IF($D11<>0,J11*50000,IF($E11<>0,J11*50000,0)) -> 50000 | L11: 1 | M11: =IF($D11<>0,L11*75000,IF($E11<>0,L11*75000,0)) -> 75000 | O11: =IF($D11<>0,N11*100000,IF($E11<>0,N11*100000,0)) -> 0 | P11: =VLOOKUP(A11,[13]TONTFEV24!$A$6:$R$39,12,0) -> 0 | Q11: =IFERROR(VLOOKUP(A11,[14]TONTFEV24!$A$7:$P$23,10,0),0) -> 102000 | R11: =IFERROR(VLOOKUP(A11,[15]TONTFEV24!$A$7:$P$20,10,0),0) -> 0 | S11: 1000000 | U11: =G11+S11++R11+P11+O11+M11+I11+K11+Q11+V11+W11 -> 1227000 | Z11: 1000000 | AC11: 16000 | AD11: 16000 | AF11: BANQUE | AP11: BANQUE | AQ11: =IF(H11="ECHEC",((K11+M11+O11)*20/100),0) -> 0 | AR11: =IF(H11="ECHEC",((K11+M11+O11)*20/100),0) -> 0 | AS11: =IF(H11="ECHEC",0,(K11+I11-25000)) -> 25000 | AW11: =IF(AC11=0,AI11,(1*25000*12)+AI11-AC11) -> 284000 | AX11: =IF(AD11=0,AJ11,(1*75000*12)+(AJ11)-AD11) -> 884000 | AY11: =IF(AE11=0,AK11,(1*100000*12)+(AK11)-AE11) -> 0 | AZ11: =SUM(AV11:AY11)-BF11+Z11-F11+BH11+BI11+BJ11+BK11+BL11+BM11 -> 1148000 | BA11: 168000 | BD11: =IF(AZ11=0,(AZ11-BA11-BC11),(AZ11-BA11-BB11-BC11))-102000 -> 878000 | BE11: OK | BF11: =Z11*1/100*BG11 -> 20000 | BG11: 2 | BO11: PRODUCTION RAPPORT | BP11: FONDS DE ROULEMENT
A12: AS201608 | B12: =VLOOKUP(A12,[11]LISTADHERENT!A$5:H$50,3,0) -> DJUOMBESSY ANTOINE | C12: =D12+E12+F12-U12-BB12 -> 0 | D12: =VLOOKUP(A12,[12]HISTOBQUEFEV24!$A$6:$G$46,3,0) -> 330000 | E12: =VLOOKUP(A12,[12]HISTOBQUEFEV24!$A$6:$G$41,4,0) -> 0 | F12: =VLOOKUP(A12,[12]HISTOBQUEFEV24!$A$6:$G$41,5,0) -> 0 | G12: =IF(H12="ESPECES",3000,0) -> 0 | H12: =IF($D12<>0,"BANQUE",IF($E12<>0,"ESPECES","ECHEC")) -> BANQUE | I12: 5000 | J12: 1 | K12: =IF($D12<>0,J12*50000,IF($E12<>0,J12*50000,0)) -> 50000 | L12: 1 | M12: =IF($D12<>0,L12*75000,IF($E12<>0,L12*75000,0)) -> 75000 | N12: 2 | O12: =IF($D12<>0,N12*100000,IF($E12<>0,N12*100000,0)) -> 200000 | P12: =VLOOKUP(A12,[13]TONTFEV24!$A$6:$R$39,12,0) -> 0 | Q12: =IFERROR(VLOOKUP(A12,[14]TONTFEV24!$A$7:$P$23,10,0),0) -> 0 | R12: =IFERROR(VLOOKUP(A12,[15]TONTFEV24!$A$7:$P$20,10,0),0) -> 0 | U12: =G12+S12++R12+P12+O12+M12+I12+K12+Q12+V12+W12 -> 330000 | AK12: 131000 | AN12: 1000 | AP12: BANQUE | AQ12: =IF(H12="ECHEC",((K12+M12+O12)*20/100),0) -> 0 | AR12: =IF(H12="ECHEC",((K12+M12+O12)*20/100),0) -> 0 | AS12: =IF(H12="ECHEC",0,(K12+I12-25000)) -> 30000 | AW12: =IF(AC12=0,AI12,(1*25000*12)+AI12-AC12) -> 0 | AX12: =IF(AD12=0,AJ12,(1*75000*12)+(AJ12)-AD12) -> 0 | AY12: =IF(AE12=0,AK12,(1*100000*12)+(AK12)-AE12) -> 131000 | AZ12: =SUM(AV12:AY12)-BF12+Z12-F12+BH12+BI12+BJ12+BK12+BL12+BM12 -> 131000 | BA12: 66700 | BD12: =IF(AZ12=0,(AZ12-BA12-BC12),(AZ12-BA12-BB12-BC12))+5000 -> 69300 | BE12: OK | BF12: =Z12*1/100*BG12 -> 0 | BG12: 10 | BO12: ACHAT SOURIS ET PHOTOCOPIE | BP12: FONDS DE ROULEMENT
A13: AS201651 | B13: =VLOOKUP(A13,[11]LISTADHERENT!A$5:H$50,3,0) -> DOMOU FABIEN | C13: =D13+E13+F13-U13-BB13 -> 0 | D13: =VLOOKUP(A13,[12]HISTOBQUEFEV24!$A$6:$G$46,3,0) -> 50000 | E13: =VLOOKUP(A13,[12]HISTOBQUEFEV24!$A$6:$G$41,4,0) -> 0 | F13: =VLOOKUP(A13,[12]HISTOBQUEFEV24!$A$6:$G$41,5,0) -> 0 | G13: =IF(H13="ESPECES",3000,0) -> 0 | H13: =IF($D13<>0,"BANQUE",IF($E13<>0,"ESPECES","ECHEC")) -> BANQUE | J13: 1 | K13: =IF($D13<>0,J13*50000,IF($E13<>0,J13*50000,0)) -> 50000 | M13: =IF($D13<>0,L13*75000,IF($E13<>0,L13*75000,0)) -> 0 | O13: =IF($D13<>0,N13*100000,IF($E13<>0,N13*100000,0)) -> 0 | P13: =VLOOKUP(A13,[13]TONTFEV24!$A$6:$R$39,12,0) -> 0 | Q13: =IFERROR(VLOOKUP(A13,[14]TONTFEV24!$A$7:$P$23,10,0),0) -> 0 | R13: =IFERROR(VLOOKUP(A13,[15]TONTFEV24!$A$7:$P$20,10,0),0) -> 0 | U13: =G13+S13++R13+P13+O13+M13+I13+K13+Q13+V13+W13 -> 50000 | AQ13: =IF(H13="ECHEC",((K13+M13+O13)*20/100),0) -> 0 | AR13: =IF(H13="ECHEC",((K13+M13+O13)*20/100),0) -> 0 | AS13: =IF(H13="ECHEC",0,(K13+I13-25000)) -> 25000 | AW13: =IF(AC13=0,AI13,(1*25000*12)+AI13-AC13) -> 0 | AX13: =IF(AD13=0,AJ13,(1*75000*12)+(AJ13)-AD13) -> 0 | AY13: =IF(AE13=0,AK13,(1*100000*12)+(AK13)-AE13) -> 0 | AZ13: =SUM(AV13:AY13)-BF13+Z13-F13+BH13+BI13+BJ13+BK13+BL13+BM13 -> 0 | BD13: =IF(AZ13=0,(AZ13-BA13-BC13),(AZ13-BA13-BB13-BC13)) -> 0 | BF13: =Z13*1/100*BG13 -> 0 | BG13: 10 | BO13: TAXI BANQUE | BP13: FONDS DE ROULEMENT | BQ13: 12000
A14: AS201609 | B14: =VLOOKUP(A14,[11]LISTADHERENT!A$5:H$50,3,0) -> DONHOU DAVID | C14: =D14+E14+F14-U14-BB14 -> 0 | D14: =VLOOKUP(A14,[12]HISTOBQUEFEV24!$A$6:$G$46,3,0) -> 50000 | E14: =VLOOKUP(A14,[12]HISTOBQUEFEV24!$A$6:$G$41,4,0) -> 0 | F14: =VLOOKUP(A14,[12]HISTOBQUEFEV24!$A$6:$G$41,5,0) -> 0 | G14: =IF(H14="ESPECES",3000,0) -> 0 | H14: =IF($D14<>0,"BANQUE",IF($E14<>0,"ESPECES","ECHEC")) -> BANQUE | J14: 1 | K14: =IF($D14<>0,J14*50000,IF($E14<>0,J14*50000,0)) -> 50000 | M14: =IF($D14<>0,L14*75000,IF($E14<>0,L14*75000,0)) -> 0 | O14: =IF($D14<>0,N14*100000,IF($E14<>0,N14*100000,0)) -> 0 | P14: =VLOOKUP(A14,[13]TONTFEV24!$A$6:$R$39,12,0) -> 0 | Q14: =IFERROR(VLOOKUP(A14,[14]TONTFEV24!$A$7:$P$23,10,0),0) -> 0 | R14: =IFERROR(VLOOKUP(A14,[15]TONTFEV24!$A$7:$P$20,10,0),0) -> 0 | U14: =G14+S14++R14+P14+O14+M14+I14+K14+Q14+V14+W14 -> 50000 | AQ14: =IF(H14="ECHEC",((K14+M14+O14)*20/100),0) -> 0 | AR14: =IF(H14="ECHEC",((K14+M14+O14)*20/100),0) -> 0 | AS14: =IF(H14="ECHEC",0,(K14+I14-25000)) -> 25000 | AW14: =IF(AC14=0,AI14,(1*25000*12)+AI14-AC14) -> 0 | AX14: =IF(AD14=0,AJ14,(1*75000*12)+(AJ14)-AD14) -> 0 | AY14: =IF(AE14=0,AK14,(1*100000*12)+(AK14)-AE14) -> 0 | AZ14: =SUM(AV14:AY14)-BF14+Z14-F14+BH14+BI14+BJ14+BK14+BL14+BM14 -> 0 | BD14: =IF(AZ14=0,(AZ14-BA14-BC14),(AZ14-BA14-BB14-BC14)) -> 0 | BF14: =Z14*1/100*BG14 -> 0 | BG14: 10 | BO14: ACHAT TERRAIN | BP14: FONDS DE ROULEMENT
A15: AS201611 | B15: =VLOOKUP(A15,[11]LISTADHERENT!A$5:H$50,3,0) -> HENGUE PAUL OMER | C15: =D15+E15+F15-U15-BB15 -> 0 | D15: =VLOOKUP(A15,[12]HISTOBQUEFEV24!$A$6:$G$46,3,0) -> 125000 | E15: =VLOOKUP(A15,[12]HISTOBQUEFEV24!$A$6:$G$41,4,0) -> 0 | F15: =VLOOKUP(A15,[12]HISTOBQUEFEV24!$A$6:$G$41,5,0) -> 0 | G15: =IF(H15="ESPECES",3000,0) -> 0 | H15: =IF($D15<>0,"BANQUE",IF($E15<>0,"ESPECES","ECHEC")) -> BANQUE | J15: 1 | K15: =IF($D15<>0,J15*50000,IF($E15<>0,J15*50000,0)) -> 50000 | L15: 1 | M15: =IF($D15<>0,L15*75000,IF($E15<>0,L15*75000,0)) -> 75000 | O15: =IF($D15<>0,N15*100000,IF($E15<>0,N15*100000,0)) -> 0 | P15: =VLOOKUP(A15,[13]TONTFEV24!$A$6:$R$39,12,0) -> 0 | Q15: =IFERROR(VLOOKUP(A15,[14]TONTFEV24!$A$7:$P$23,10,0),0) -> 0 | R15: =IFERROR(VLOOKUP(A15,[15]TONTFEV24!$A$7:$P$20,10,0),0) -> 0 | U15: =G15+S15++R15+P15+O15+M15+I15+K15+Q15+V15+W15 -> 125000 | AQ15: =IF(H15="ECHEC",((K15+M15+O15)*20/100),0) -> 0 | AR15: =IF(H15="ECHEC",((K15+M15+O15)*20/100),0) -> 0 | AS15: =IF(H15="ECHEC",0,(K15+I15-25000)) -> 25000 | AW15: =IF(AC15=0,AI15,(1*25000*12)+AI15-AC15) -> 0 | AX15: =IF(AD15=0,AJ15,(1*75000*12)+(AJ15)-AD15) -> 0 | AY15: =IF(AE15=0,AK15,(1*100000*12)+(AK15)-AE15) -> 0 | AZ15: =SUM(AV15:AY15)-BF15+Z15-F15+BH15+BI15+BJ15+BK15+BL15+BM15 -> 0 | BD15: =IF(AZ15=0,(AZ15-BA15-BC15),(AZ15-BA15-BB15-BC15)) -> 0 | BF15: =Z15*1/100*BG15 -> 0 | BG15: 10
A16: AS201613 | B16: =VLOOKUP(A16,[11]LISTADHERENT!A$5:H$50,3,0) -> HOTCHO BENJAMIN | C16: =D16+E16+F16-U16-BB16 -> 0 | D16: =VLOOKUP(A16,[12]HISTOBQUEFEV24!$A$6:$G$46,3,0) -> 260000 | E16: =VLOOKUP(A16,[12]HISTOBQUEFEV24!$A$6:$G$41,4,0) -> 0 | F16: =VLOOKUP(A16,[12]HISTOBQUEFEV24!$A$6:$G$41,5,0) -> 0 | G16: =IF(H16="ESPECES",3000,0) -> 0 | H16: =IF($D16<>0,"BANQUE",IF($E16<>0,"ESPECES","ECHEC")) -> BANQUE | I16: 35000 | J16: 1 | K16: =IF($D16<>0,J16*50000,IF($E16<>0,J16*50000,0)) -> 50000 | L16: 1 | M16: =IF($D16<>0,L16*75000,IF($E16<>0,L16*75000,0)) -> 75000 | N16: 1 | O16: =IF($D16<>0,N16*100000,IF($E16<>0,N16*100000,0)) -> 100000 | P16: =VLOOKUP(A16,[13]TONTFEV24!$A$6:$R$39,12,0) -> 0 | Q16: =IFERROR(VLOOKUP(A16,[14]TONTFEV24!$A$7:$P$23,10,0),0) -> 0 | R16: =IFERROR(VLOOKUP(A16,[15]TONTFEV24!$A$7:$P$20,10,0),0) -> 0 | U16: =G16+S16++R16+P16+O16+M16+I16+K16+Q16+V16+W16 -> 260000 | AQ16: =IF(H16="ECHEC",((K16+M16+O16)*20/100),0) -> 0 | AR16: =IF(H16="ECHEC",((K16+M16+O16)*20/100),0) -> 0 | AS16: =IF(H16="ECHEC",0,(K16+I16-25000)) -> 60000 | AW16: =IF(AC16=0,AI16,(1*25000*12)+AI16-AC16) -> 0 | AX16: =IF(AD16=0,AJ16,(1*75000*12)+(AJ16)-AD16) -> 0 | AY16: =IF(AE16=0,AK16,(1*100000*12)+(AK16)-AE16) -> 0 | AZ16: =SUM(AV16:AY16)-BF16+Z16-F16+BH16+BI16+BJ16+BK16+BL16+BM16 -> 0 | BD16: =IF(AZ16=0,(AZ16-BA16-BC16),(AZ16-BA16-BB16-BC16)) -> 0 | BF16: =Z16*1/100*BG16 -> 0 | BG16: 10 | BO16: S/TOTAL | BQ16: =SUM(BQ6:BQ15) -> 27000
A17: AS201617 | B17: =VLOOKUP(A17,[11]LISTADHERENT!A$5:H$50,3,0) -> KOUAMOU MOISE | C17: =D17+E17+F17-U17-BB17 -> 0 | D17: =VLOOKUP(A17,[12]HISTOBQUEFEV24!$A$6:$G$46,3,0) -> 251000 | E17: =VLOOKUP(A17,[12]HISTOBQUEFEV24!$A$6:$G$41,4,0) -> 0 | F17: =VLOOKUP(A17,[12]HISTOBQUEFEV24!$A$6:$G$41,5,0) -> 0 | G17: =IF(H17="ESPECES",3000,0) -> 0 | H17: =IF($D17<>0,"BANQUE",IF($E17<>0,"ESPECES","ECHEC")) -> BANQUE | J17: 1 | K17: =IF($D17<>0,J17*50000,IF($E17<>0,J17*50000,0)) -> 50000 | M17: =IF($D17<>0,L17*75000,IF($E17<>0,L17*75000,0)) -> 0 | N17: 1 | O17: =IF($D17<>0,N17*100000,IF($E17<>0,N17*100000,0)) -> 100000 | P17: =VLOOKUP(A17,[13]TONTFEV24!$A$6:$R$39,12,0) -> 0 | Q17: =IFERROR(VLOOKUP(A17,[14]TONTFEV24!$A$7:$P$23,10,0),0) -> 0 | R17: =IFERROR(VLOOKUP(A17,[15]TONTFEV24!$A$7:$P$20,10,0),0) -> 101000 | U17: =G17+S17++R17+P17+O17+M17+I17+K17+Q17+V17+W17 -> 251000 | AC17: 17000 | AF17: BANQUE | AP17: BANQUE | AQ17: =IF(H17="ECHEC",((K17+M17+O17)*20/100),0) -> 0 | AR17: =IF(H17="ECHEC",((K17+M17+O17)*20/100),0) -> 0 | AS17: =IF(H17="ECHEC",0,(K17+I17-25000)) -> 25000 | AW17: =IF(AC17=0,AI17,(1*25000*12)+AI17-AC17) -> 283000 | AX17: =IF(AD17=0,AJ17,(1*75000*12)+(AJ17)-AD17) -> 0 | AY17: =IF(AE17=0,AK17,(1*100000*12)+(AK17)-AE17) -> 0 | AZ17: =SUM(AV17:AY17)-BF17+Z17-F17+BH17+BI17+BJ17+BK17+BL17+BM17 -> 283000 | BD17: =IF(AZ17=0,(AZ17-BA17-BC17),(AZ17-BA17-BB17-BC17)) -> 283000 | BE17: OK | BF17: =Z17*1/100*BG17 -> 0 | BG17: 10
A18: AS201619 | B18: =VLOOKUP(A18,[11]LISTADHERENT!A$5:H$50,3,0) -> KOUATCHO MESSACK | C18: =D18+E18+F18-U18-BB18 -> 0 | D18: =VLOOKUP(A18,[12]HISTOBQUEFEV24!$A$6:$G$46,3,0) -> 160000 | E18: =VLOOKUP(A18,[12]HISTOBQUEFEV24!$A$6:$G$41,4,0) -> 0 | F18: =VLOOKUP(A18,[12]HISTOBQUEFEV24!$A$6:$G$41,5,0) -> 0 | G18: =IF(H18="ESPECES",3000,0) -> 0 | H18: =IF($D18<>0,"BANQUE",IF($E18<>0,"ESPECES","ECHEC")) -> BANQUE | I18: 10000 | J18: 1 | K18: =IF($D18<>0,J18*50000,IF($E18<>0,J18*50000,0)) -> 50000 | M18: =IF($D18<>0,L18*75000,IF($E18<>0,L18*75000,0)) -> 0 | N18: 1 | O18: =IF($D18<>0,N18*100000,IF($E18<>0,N18*100000,0)) -> 100000 | P18: =VLOOKUP(A18,[13]TONTFEV24!$A$6:$R$39,12,0) -> 0 | Q18: =IFERROR(VLOOKUP(A18,[14]TONTFEV24!$A$7:$P$23,10,0),0) -> 0 | R18: =IFERROR(VLOOKUP(A18,[15]TONTFEV24!$A$7:$P$20,10,0),0) -> 0 | U18: =G18+S18++R18+P18+O18+M18+I18+K18+Q18+V18+W18 -> 160000 | AE18: 40000 | AF18: BANQUE | AQ18: =IF(H18="ECHEC",((K18+M18+O18)*20/100),0) -> 0 | AR18: =IF(H18="ECHEC",((K18+M18+O18)*20/100),0) -> 0 | AS18: =IF(H18="ECHEC",0,(K18+I18-25000)) -> 35000 | AW18: =IF(AC18=0,AI18,(1*25000*12)+AI18-AC18) -> 0 | AX18: =IF(AD18=0,AJ18,(1*75000*12)+(AJ18)-AD18) -> 0 | AY18: =IF(AE18=0,AK18,(1*100000*12)+(AK18)-AE18) -> 1160000 | AZ18: =SUM(AV18:AY18)-BF18+Z18-F18+BH18+BI18+BJ18+BK18+BL18+BM18 -> 1160000 | BD18: =IF(AZ18=0,(AZ18-BA18-BC18),(AZ18-BA18-BB18-BC18)) -> 1160000 | BE18: OK | BF18: =Z18*1/100*BG18 -> 0 | BG18: 10 | BO18: TERRAIN NYOM | BP18: AUTRES DEPENSES
A19: AS201661 | B19: =VLOOKUP(A19,[11]LISTADHERENT!A$5:H$50,3,0) -> MASSEUNGOUE DAGOBERT | C19: =D19+E19+F19-U19-BB19 -> 0 | D19: =VLOOKUP(A19,[12]HISTOBQUEFEV24!$A$6:$G$46,3,0) -> 50000 | E19: =VLOOKUP(A19,[12]HISTOBQUEFEV24!$A$6:$G$41,4,0) -> 0 | F19: =VLOOKUP(A19,[12]HISTOBQUEFEV24!$A$6:$G$41,5,0) -> 0 | G19: =IF(H19="ESPECES",3000,0) -> 0 | H19: =IF($D19<>0,"BANQUE",IF($E19<>0,"ESPECES","ECHEC")) -> BANQUE | J19: 1 | K19: =IF($D19<>0,J19*50000,IF($E19<>0,J19*50000,0)) -> 50000 | M19: =IF($D19<>0,L19*75000,IF($E19<>0,L19*75000,0)) -> 0 | O19: =IF($D19<>0,N19*100000,IF($E19<>0,N19*100000,0)) -> 0 | P19: =VLOOKUP(A19,[13]TONTFEV24!$A$6:$R$39,12,0) -> 0 | Q19: =IFERROR(VLOOKUP(A19,[14]TONTFEV24!$A$7:$P$23,10,0),0) -> 0 | R19: =IFERROR(VLOOKUP(A19,[15]TONTFEV24!$A$7:$P$20,10,0),0) -> 0 | U19: =G19+S19++R19+P19+O19+M19+I19+K19+Q19+V19+W19 -> 50000 | AQ19: =IF(H19="ECHEC",((K19+M19+O19)*20/100),0) -> 0 | AR19: =IF(H19="ECHEC",((K19+M19+O19)*20/100),0) -> 0 | AS19: =IF(H19="ECHEC",0,(K19+I19-25000)) -> 25000 | AW19: =IF(AC19=0,AI19,(1*25000*12)+AI19-AC19) -> 0 | AX19: =IF(AD19=0,AJ19,(1*75000*12)+(AJ19)-AD19) -> 0 | AY19: =IF(AE19=0,AK19,(1*100000*12)+(AK19)-AE19) -> 0 | AZ19: =SUM(AV19:AY19)-BF19+Z19-F19+BH19+BI19+BJ19+BK19+BL19+BM19 -> 0 | BD19: =IF(AZ19=0,(AZ19-BA19-BC19),(AZ19-BA19-BB19-BC19)) -> 0 | BF19: =Z19*1/100*BG19 -> 0 | BG19: 10
A20: AS201649 | B20: =VLOOKUP(A20,[11]LISTADHERENT!A$5:H$50,3,0) -> MBOGNING TUGMA GUY | C20: =D20+E20+F20-U20-BB20 -> 0 | D20: =VLOOKUP(A20,[12]HISTOBQUEFEV24!$A$6:$G$46,3,0) -> 225000 | E20: =VLOOKUP(A20,[12]HISTOBQUEFEV24!$A$6:$G$41,4,0) -> 0 | F20: =VLOOKUP(A20,[12]HISTOBQUEFEV24!$A$6:$G$41,5,0) -> 0 | G20: =IF(H20="ESPECES",3000,0) -> 0 | H20: =IF($D20<>0,"BANQUE",IF($E20<>0,"ESPECES","ECHEC")) -> BANQUE | J20: 1 | K20: =IF($D20<>0,J20*50000,IF($E20<>0,J20*50000,0)) -> 50000 | L20: 1 | M20: =IF($D20<>0,L20*75000,IF($E20<>0,L20*75000,0)) -> 75000 | N20: 1 | O20: =IF($D20<>0,N20*100000,IF($E20<>0,N20*100000,0)) -> 100000 | P20: =VLOOKUP(A20,[13]TONTFEV24!$A$6:$R$39,12,0) -> 0 | Q20: =IFERROR(VLOOKUP(A20,[14]TONTFEV24!$A$7:$P$23,10,0),0) -> 0 | R20: =IFERROR(VLOOKUP(A20,[15]TONTFEV24!$A$7:$P$20,10,0),0) -> 0 | U20: =G20+S20++R20+P20+O20+M20+I20+K20+Q20+V20+W20 -> 225000 | AD20: 16000 | AF20: BANQUE | AK20: =100000+100000 -> 200000 | AN20: =1000+1000 -> 2000 | AP20: BANQUE | AQ20: =IF(H20="ECHEC",((K20+M20+O20)*20/100),0) -> 0 | AR20: =IF(H20="ECHEC",((K20+M20+O20)*20/100),0) -> 0 | AS20: =IF(H20="ECHEC",0,(K20+I20-25000)) -> 25000 | AW20: =IF(AC20=0,AI20,(1*25000*12)+AI20-AC20) -> 0 | AX20: =IF(AD20=0,AJ20,(1*75000*12)+(AJ20)-AD20) -> 884000 | AY20: =IF(AE20=0,AK20,(1*100000*12)+(AK20)-AE20) -> 200000 | AZ20: =SUM(AV20:AY20)-BF20+Z20-F20+BH20+BI20+BJ20+BK20+BL20+BM20 -> 1084000 | BA20: 140000 | BD20: =IF(AZ20=0,(AZ20-BA20-BC20),(AZ20-BA20-BB20-BC20)) -> 944000 | BE20: OK | BF20: =Z20*1/100*BG20 -> 0 | BG20: 10
A21: AS201639 | B21: =VLOOKUP(A21,[11]LISTADHERENT!A$5:H$50,3,0) -> NANGUEN MARTIN | C21: =D21+E21+F21-U21-BB21 -> 0 | D21: =VLOOKUP(A21,[12]HISTOBQUEFEV24!$A$6:$G$46,3,0) -> 50000 | E21: =VLOOKUP(A21,[12]HISTOBQUEFEV24!$A$6:$G$41,4,0) -> 0 | F21: =VLOOKUP(A21,[12]HISTOBQUEFEV24!$A$6:$G$41,5,0) -> 0 | G21: =IF(H21="ESPECES",3000,0) -> 0 | H21: =IF($D21<>0,"BANQUE",IF($E21<>0,"ESPECES","ECHEC")) -> BANQUE | J21: 1 | K21: =IF($D21<>0,J21*50000,IF($E21<>0,J21*50000,0)) -> 50000 | M21: =IF($D21<>0,L21*75000,IF($E21<>0,L21*75000,0)) -> 0 | O21: =IF($D21<>0,N21*100000,IF($E21<>0,N21*100000,0)) -> 0 | P21: =VLOOKUP(A21,[13]TONTFEV24!$A$6:$R$39,12,0) -> 0 | Q21: =IFERROR(VLOOKUP(A21,[14]TONTFEV24!$A$7:$P$23,10,0),0) -> 0 | R21: =IFERROR(VLOOKUP(A21,[15]TONTFEV24!$A$7:$P$20,10,0),0) -> 0 | U21: =G21+S21++R21+P21+O21+M21+I21+K21+Q21+V21+W21 -> 50000 | AQ21: =IF(H21="ECHEC",((K21+M21+O21)*20/100),0) -> 0 | AR21: =IF(H21="ECHEC",((K21+M21+O21)*20/100),0) -> 0 | AS21: =IF(H21="ECHEC",0,(K21+I21-25000)) -> 25000 | AW21: =IF(AC21=0,AI21,(1*25000*12)+AI21-AC21) -> 0 | AX21: =IF(AD21=0,AJ21,(1*75000*12)+(AJ21)-AD21) -> 0 | AY21: =IF(AE21=0,AK21,(1*100000*12)+(AK21)-AE21) -> 0 | AZ21: =SUM(AV21:AY21)-BF21+Z21-F21+BH21+BI21+BJ21+BK21+BL21+BM21 -> 0 | BD21: =IF(AZ21=0,(AZ21-BA21-BC21),(AZ21-BA21-BB21-BC21)) -> 0 | BF21: =Z21*1/100*BG21 -> 0 | BG21: 10
A22: AS201621 | B22: =VLOOKUP(A22,[11]LISTADHERENT!A$5:H$50,3,0) -> NANKAM APPOLINAIRE | C22: =D22+E22+F22-U22-BB22 -> 0 | D22: =VLOOKUP(A22,[12]HISTOBQUEFEV24!$A$6:$G$46,3,0) -> 125000 | E22: =VLOOKUP(A22,[12]HISTOBQUEFEV24!$A$6:$G$41,4,0) -> 0 | F22: =VLOOKUP(A22,[12]HISTOBQUEFEV24!$A$6:$G$41,5,0) -> 0 | G22: =IF(H22="ESPECES",3000,0) -> 0 | H22: =IF($D22<>0,"BANQUE",IF($E22<>0,"ESPECES","ECHEC")) -> BANQUE | J22: 1 | K22: =IF($D22<>0,J22*50000,IF($E22<>0,J22*50000,0)) -> 50000 | L22: 1 | M22: =IF($D22<>0,L22*75000,IF($E22<>0,L22*75000,0)) -> 75000 | O22: =IF($D22<>0,N22*100000,IF($E22<>0,N22*100000,0)) -> 0 | P22: =VLOOKUP(A22,[13]TONTFEV24!$A$6:$R$39,12,0) -> 0 | Q22: =IFERROR(VLOOKUP(A22,[14]TONTFEV24!$A$7:$P$23,10,0),0) -> 0 | R22: =IFERROR(VLOOKUP(A22,[15]TONTFEV24!$A$7:$P$20,10,0),0) -> 0 | U22: =G22+S22++R22+P22+O22+M22+I22+K22+Q22+V22+W22 -> 125000 | AQ22: =IF(H22="ECHEC",((K22+M22+O22)*20/100),0) -> 0 | AR22: =IF(H22="ECHEC",((K22+M22+O22)*20/100),0) -> 0 | AS22: =IF(H22="ECHEC",0,(K22+I22-25000)) -> 25000 | AW22: =IF(AC22=0,AI22,(1*25000*12)+AI22-AC22) -> 0 | AX22: =IF(AD22=0,AJ22,(1*75000*12)+(AJ22)-AD22) -> 0 | AY22: =IF(AE22=0,AK22,(1*100000*12)+(AK22)-AE22) -> 0 | AZ22: =SUM(AV22:AY22)-BF22+Z22-F22+BH22+BI22+BJ22+BK22+BL22+BM22 -> 0 | BD22: =IF(AZ22=0,(AZ22-BA22-BC22),(AZ22-BA22-BB22-BC22)) -> 0 | BF22: =Z22*1/100*BG22 -> 0 | BG22: 10 | BO22: S/TOTAL | BQ22: =SUM(BQ18:BQ21) -> 0
A23: AS201622 | B23: =VLOOKUP(A23,[11]LISTADHERENT!A$5:H$50,3,0) -> NDJOMO ETIENNE | C23: =D23+E23+F23-U23-BB23 -> 0 | D23: =VLOOKUP(A23,[12]HISTOBQUEFEV24!$A$6:$G$46,3,0) -> 260000 | E23: =VLOOKUP(A23,[12]HISTOBQUEFEV24!$A$6:$G$41,4,0) -> 0 | F23: =VLOOKUP(A23,[12]HISTOBQUEFEV24!$A$6:$G$41,5,0) -> 0 | G23: =IF(H23="ESPECES",3000,0) -> 0 | H23: =IF($D23<>0,"BANQUE",IF($E23<>0,"ESPECES","ECHEC")) -> BANQUE | I23: 10000 | J23: 1 | K23: =IF($D23<>0,J23*50000,IF($E23<>0,J23*50000,0)) -> 50000 | M23: =IF($D23<>0,L23*75000,IF($E23<>0,L23*75000,0)) -> 0 | N23: 2 | O23: =IF($D23<>0,N23*100000,IF($E23<>0,N23*100000,0)) -> 200000 | P23: =VLOOKUP(A23,[13]TONTFEV24!$A$6:$R$39,12,0) -> 0 | Q23: =IFERROR(VLOOKUP(A23,[14]TONTFEV24!$A$7:$P$23,10,0),0) -> 0 | R23: =IFERROR(VLOOKUP(A23,[15]TONTFEV24!$A$7:$P$20,10,0),0) -> 0 | U23: =G23+S23++R23+P23+O23+M23+I23+K23+Q23+V23+W23 -> 260000 | AQ23: =IF(H23="ECHEC",((K23+M23+O23)*20/100),0) -> 0 | AR23: =IF(H23="ECHEC",((K23+M23+O23)*20/100),0) -> 0 | AS23: =IF(H23="ECHEC",0,(K23+I23-25000)) -> 35000 | AW23: =IF(AC23=0,AI23,(1*25000*12)+AI23-AC23) -> 0 | AX23: =IF(AD23=0,AJ23,(1*75000*12)+(AJ23)-AD23) -> 0 | AY23: =IF(AE23=0,AK23,(1*100000*12)+(AK23)-AE23) -> 0 | AZ23: =SUM(AV23:AY23)-BF23+Z23-F23+BH23+BI23+BJ23+BK23+BL23+BM23 -> 0 | BD23: =IF(AZ23=0,(AZ23-BA23-BC23),(AZ23-BA23-BB23-BC23)) -> 0 | BF23: =Z23*1/100*BG23 -> 0 | BG23: 10
A24: AS201624 | B24: =VLOOKUP(A24,[11]LISTADHERENT!A$5:H$50,3,0) -> NGONDIEP CLAUDE | C24: =D24+E24+F24-U24-BB24 -> 0 | D24: =VLOOKUP(A24,[12]HISTOBQUEFEV24!$A$6:$G$46,3,0) -> 240000 | E24: =VLOOKUP(A24,[12]HISTOBQUEFEV24!$A$6:$G$41,4,0) -> 0 | F24: =VLOOKUP(A24,[12]HISTOBQUEFEV24!$A$6:$G$41,5,0) -> 0 | G24: =IF(H24="ESPECES",3000,0) -> 0 | H24: =IF($D24<>0,"BANQUE",IF($E24<>0,"ESPECES","ECHEC")) -> BANQUE | I24: 15000 | J24: 1 | K24: =IF($D24<>0,J24*50000,IF($E24<>0,J24*50000,0)) -> 50000 | L24: 1 | M24: =IF($D24<>0,L24*75000,IF($E24<>0,L24*75000,0)) -> 75000 | N24: 1 | O24: =IF($D24<>0,N24*100000,IF($E24<>0,N24*100000,0)) -> 100000 | P24: =VLOOKUP(A24,[13]TONTFEV24!$A$6:$R$39,12,0) -> 0 | Q24: =IFERROR(VLOOKUP(A24,[14]TONTFEV24!$A$7:$P$23,10,0),0) -> 0 | R24: =IFERROR(VLOOKUP(A24,[15]TONTFEV24!$A$7:$P$20,10,0),0) -> 0 | U24: =G24+S24++R24+P24+O24+M24+I24+K24+Q24+V24+W24 -> 240000 | AQ24: =IF(H24="ECHEC",((K24+M24+O24)*20/100),0) -> 0 | AR24: =IF(H24="ECHEC",((K24+M24+O24)*20/100),0) -> 0 | AS24: =IF(H24="ECHEC",0,(K24+I24-25000)) -> 40000 | AW24: =IF(AC24=0,AI24,(1*25000*12)+AI24-AC24) -> 0 | AX24: =IF(AD24=0,AJ24,(1*75000*12)+(AJ24)-AD24) -> 0 | AY24: =IF(AE24=0,AK24,(1*100000*12)+(AK24)-AE24) -> 0 | AZ24: =SUM(AV24:AY24)-BF24+Z24-F24+BH24+BI24+BJ24+BK24+BL24+BM24 -> 100000 | BD24: =IF(AZ24=0,(AZ24-BA24-BC24),(AZ24-BA24-BB24-BC24)) -> 100000 | BE24: OK | BF24: =Z24*1/100*BG24 -> 0 | BG24: 10 | BK24: 100000 | BO24: GRATIFICATION BUREAU 2021 | BP24: FRAIS EXEPTIONNEL
A25: AS201626 | B25: =VLOOKUP(A25,[11]LISTADHERENT!A$5:H$50,3,0) -> NGUIEMEGNI MATHIEU BLAISE | C25: =D25+E25+F25-U25-BB25 -> 0 | D25: =VLOOKUP(A25,[12]HISTOBQUEFEV24!$A$6:$G$46,3,0) -> 375000 | E25: =VLOOKUP(A25,[12]HISTOBQUEFEV24!$A$6:$G$41,4,0) -> 0 | F25: =VLOOKUP(A25,[12]HISTOBQUEFEV24!$A$6:$G$41,5,0) -> 0 | G25: =IF(H25="ESPECES",3000,0) -> 0 | H25: =IF($D25<>0,"BANQUE",IF($E25<>0,"ESPECES","ECHEC")) -> BANQUE | J25: 1 | K25: =IF($D25<>0,J25*50000,IF($E25<>0,J25*50000,0)) -> 50000 | L25: 3 | M25: =IF($D25<>0,L25*75000,IF($E25<>0,L25*75000,0)) -> 225000 | N25: 1 | O25: =IF($D25<>0,N25*100000,IF($E25<>0,N25*100000,0)) -> 100000 | P25: =VLOOKUP(A25,[13]TONTFEV24!$A$6:$R$39,12,0) -> 0 | Q25: =IFERROR(VLOOKUP(A25,[14]TONTFEV24!$A$7:$P$23,10,0),0) -> 0 | R25: =IFERROR(VLOOKUP(A25,[15]TONTFEV24!$A$7:$P$20,10,0),0) -> 0 | U25: =G25+S25++R25+P25+O25+M25+I25+K25+Q25+V25+W25 -> 375000 | AK25: 100000 | AN25: 1500 | AQ25: =IF(H25="ECHEC",((K25+M25+O25)*20/100),0) -> 0 | AR25: =IF(H25="ECHEC",((K25+M25+O25)*20/100),0) -> 0 | AS25: =IF(H25="ECHEC",0,(K25+I25-25000)) -> 25000 | AW25: =IF(AC25=0,AI25,(1*25000*12)+AI25-AC25) -> 0 | AX25: =IF(AD25=0,AJ25,(1*75000*12)+(AJ25)-AD25) -> 0 | AY25: =IF(AE25=0,AK25,(1*100000*12)+(AK25)-AE25) -> 100000 | AZ25: =SUM(AV25:AY25)-BF25+Z25-F25+BH25+BI25+BJ25+BK25+BL25+BM25 -> 100000 | BA25: 100000 | BD25: =IF(AZ25=0,(AZ25-BA25-BC25),(AZ25-BA25-BB25-BC25)) -> 0 | BF25: =Z25*1/100*BG25 -> 0 | BG25: 10 | BO25: DEVELOPPEMENT LAGWEU | BP25: FRAIS EXEPTIONNEL
A26: AS201628 | B26: =VLOOKUP(A26,[11]LISTADHERENT!A$5:H$50,3,0) -> NKAMGANG JUSTIN DEJOLIE | C26: =D26+E26+F26-U26-BB26 -> 0 | D26: =VLOOKUP(A26,[12]HISTOBQUEFEV24!$A$6:$G$46,3,0) -> 50000 | E26: =VLOOKUP(A26,[12]HISTOBQUEFEV24!$A$6:$G$41,4,0) -> 0 | F26: =VLOOKUP(A26,[12]HISTOBQUEFEV24!$A$6:$G$41,5,0) -> 0 | G26: =IF(H26="ESPECES",3000,0) -> 0 | H26: =IF($D26<>0,"BANQUE",IF($E26<>0,"ESPECES","ECHEC")) -> BANQUE | J26: 1 | K26: =IF($D26<>0,J26*50000,IF($E26<>0,J26*50000,0)) -> 50000 | M26: =IF($D26<>0,L26*75000,IF($E26<>0,L26*75000,0)) -> 0 | O26: =IF($D26<>0,N26*100000,IF($E26<>0,N26*100000,0)) -> 0 | P26: =VLOOKUP(A26,[13]TONTFEV24!$A$6:$R$39,12,0) -> 0 | Q26: =IFERROR(VLOOKUP(A26,[14]TONTFEV24!$A$7:$P$23,10,0),0) -> 0 | R26: =IFERROR(VLOOKUP(A26,[15]TONTFEV24!$A$7:$P$20,10,0),0) -> 0 | U26: =G26+S26++R26+P26+O26+M26+I26+K26+Q26+V26+W26 -> 50000 | AQ26: =IF(H26="ECHEC",((K26+M26+O26)*20/100),0) -> 0 | AR26: =IF(H26="ECHEC",((K26+M26+O26)*20/100),0) -> 0 | AS26: =IF(H26="ECHEC",0,(K26+I26-25000)) -> 25000 | AW26: =IF(AC26=0,AI26,(1*25000*12)+AI26-AC26) -> 0 | AX26: =IF(AD26=0,AJ26,(1*75000*12)+(AJ26)-AD26) -> 0 | AY26: =IF(AE26=0,AK26,(1*100000*12)+(AK26)-AE26) -> 0 | AZ26: =SUM(AV26:AY26)-BF26+Z26-F26+BH26+BI26+BJ26+BK26+BL26+BM26 -> 0 | BD26: =IF(AZ26=0,(AZ26-BA26-BC26),(AZ26-BA26-BB26-BC26)) -> 0 | BF26: =Z26*1/100*BG26 -> 0 | BG26: 10 | BO26: DEUIL TCHEMNOU EMMANUEL | BP26: FRAIS EXEPTIONNEL
A27: AS201656 | B27: =VLOOKUP(A27,[11]LISTADHERENT!A$5:H$50,3,0) -> NOUBE ETIENNE | C27: =D27+E27+F27-U27-BB27 -> 0 | D27: =VLOOKUP(A27,[12]HISTOBQUEFEV24!$A$6:$G$46,3,0) -> 50000 | E27: =VLOOKUP(A27,[12]HISTOBQUEFEV24!$A$6:$G$41,4,0) -> 0 | F27: =VLOOKUP(A27,[12]HISTOBQUEFEV24!$A$6:$G$41,5,0) -> 0 | G27: =IF(H27="ESPECES",3000,0) -> 0 | H27: =IF($D27<>0,"BANQUE",IF($E27<>0,"ESPECES","ECHEC")) -> BANQUE | J27: 1 | K27: =IF($D27<>0,J27*50000,IF($E27<>0,J27*50000,0)) -> 50000 | M27: =IF($D27<>0,L27*75000,IF($E27<>0,L27*75000,0)) -> 0 | O27: =IF($D27<>0,N27*100000,IF($E27<>0,N27*100000,0)) -> 0 | P27: =VLOOKUP(A27,[13]TONTFEV24!$A$6:$R$39,12,0) -> 0 | Q27: =IFERROR(VLOOKUP(A27,[14]TONTFEV24!$A$7:$P$23,10,0),0) -> 0 | R27: =IFERROR(VLOOKUP(A27,[15]TONTFEV24!$A$7:$P$20,10,0),0) -> 0 | U27: =G27+S27++R27+P27+O27+M27+I27+K27+Q27+V27+W27 -> 50000 | AQ27: =IF(H27="ECHEC",((K27+M27+O27)*20/100),0) -> 0 | AR27: =IF(H27="ECHEC",((K27+M27+O27)*20/100),0) -> 0 | AS27: =IF(H27="ECHEC",0,(K27+I27-25000)) -> 25000 | AW27: =IF(AC27=0,AI27,(1*25000*12)+AI27-AC27) -> 0 | AX27: =IF(AD27=0,AJ27,(1*75000*12)+(AJ27)-AD27) -> 0 | AY27: =IF(AE27=0,AK27,(1*100000*12)+(AK27)-AE27) -> 0 | AZ27: =SUM(AV27:AY27)-BF27+Z27-F27+BH27+BI27+BJ27+BK27+BL27+BM27 -> 0 | BD27: =IF(AZ27=0,(AZ27-BA27-BC27),(AZ27-BA27-BB27-BC27)) -> 0 | BF27: =Z27*1/100*BG27 -> 0 | BG27: 10
A28: AS201633 | B28: =VLOOKUP(A28,[11]LISTADHERENT!A$5:H$50,3,0) -> PATEGO NJOSSU GUSTAVE | C28: =D28+E28+F28-U28-BB28 -> 0 | D28: =VLOOKUP(A28,[12]HISTOBQUEFEV24!$A$6:$G$46,3,0) -> 125000 | E28: =VLOOKUP(A28,[12]HISTOBQUEFEV24!$A$6:$G$41,4,0) -> 0 | F28: =VLOOKUP(A28,[12]HISTOBQUEFEV24!$A$6:$G$41,5,0) -> 0 | G28: =IF(H28="ESPECES",3000,0) -> 0 | H28: =IF($D28<>0,"BANQUE",IF($E28<>0,"ESPECES","ECHEC")) -> BANQUE | J28: 1 | K28: =IF($D28<>0,J28*50000,IF($E28<>0,J28*50000,0)) -> 50000 | L28: 1 | M28: =IF($D28<>0,L28*75000,IF($E28<>0,L28*75000,0)) -> 75000 | O28: =IF($D28<>0,N28*100000,IF($E28<>0,N28*100000,0)) -> 0 | P28: =VLOOKUP(A28,[13]TONTFEV24!$A$6:$R$39,12,0) -> 0 | Q28: =IFERROR(VLOOKUP(A28,[14]TONTFEV24!$A$7:$P$23,10,0),0) -> 0 | R28: =IFERROR(VLOOKUP(A28,[15]TONTFEV24!$A$7:$P$20,10,0),0) -> 0 | U28: =G28+S28++R28+P28+O28+M28+I28+K28+Q28+V28+W28 -> 125000 | AQ28: =IF(H28="ECHEC",((K28+M28+O28)*20/100),0) -> 0 | AR28: =IF(H28="ECHEC",((K28+M28+O28)*20/100),0) -> 0 | AS28: =IF(H28="ECHEC",0,(K28+I28-25000)) -> 25000 | AW28: =IF(AC28=0,AI28,(1*25000*12)+AI28-AC28) -> 0 | AX28: =IF(AD28=0,AJ28,(1*75000*12)+(AJ28)-AD28) -> 0 | AY28: =IF(AE28=0,AK28,(1*100000*12)+(AK28)-AE28) -> 0 | AZ28: =SUM(AV28:AY28)-BF28+Z28-F28+BH28+BI28+BJ28+BK28+BL28+BM28 -> 0 | BD28: =IF(AZ28=0,(AZ28-BA28-BC28),(AZ28-BA28-BB28-BC28)) -> 0 | BF28: =Z28*1/100*BG28 -> 0 | BG28: 10 | BO28: S/TOTAL | BQ28: =SUM(BQ24:BQ26) -> 0
A29: AS201657 | B29: =VLOOKUP(A29,[11]LISTADHERENT!A$5:H$50,3,0) -> SEUMO POLYCARPE | C29: =D29+E29+F29-U29-BB29 -> 0 | D29: =VLOOKUP(A29,[12]HISTOBQUEFEV24!$A$6:$G$46,3,0) -> 50000 | E29: =VLOOKUP(A29,[12]HISTOBQUEFEV24!$A$6:$G$41,4,0) -> 0 | F29: =VLOOKUP(A29,[12]HISTOBQUEFEV24!$A$6:$G$41,5,0) -> 0 | G29: =IF(H29="ESPECES",3000,0) -> 0 | H29: =IF($D29<>0,"BANQUE",IF($E29<>0,"ESPECES","ECHEC")) -> BANQUE | J29: 1 | K29: =IF($D29<>0,J29*50000,IF($E29<>0,J29*50000,0)) -> 50000 | M29: =IF($D29<>0,L29*75000,IF($E29<>0,L29*75000,0)) -> 0 | O29: =IF($D29<>0,N29*100000,IF($E29<>0,N29*100000,0)) -> 0 | P29: =VLOOKUP(A29,[13]TONTFEV24!$A$6:$R$39,12,0) -> 0 | Q29: =IFERROR(VLOOKUP(A29,[14]TONTFEV24!$A$7:$P$23,10,0),0) -> 0 | R29: =IFERROR(VLOOKUP(A29,[15]TONTFEV24!$A$7:$P$20,10,0),0) -> 0 | U29: =G29+S29++R29+P29+O29+M29+I29+K29+Q29+V29+W29 -> 50000 | AI29: 51000 | AL29: 1000 | AQ29: =IF(H29="ECHEC",((K29+M29+O29)*20/100),0) -> 0 | AR29: =IF(H29="ECHEC",((K29+M29+O29)*20/100),0) -> 0 | AS29: =IF(H29="ECHEC",0,(K29+I29-25000)) -> 25000 | AW29: =IF(AC29=0,AI29,(1*25000*12)+AI29-AC29) -> 51000 | AX29: =IF(AD29=0,AJ29,(1*75000*12)+(AJ29)-AD29) -> 0 | AY29: =IF(AE29=0,AK29,(1*100000*12)+(AK29)-AE29) -> 0 | AZ29: =SUM(AV29:AY29)-BF29+Z29-F29+BH29+BI29+BJ29+BK29+BL29+BM29 -> 51000 | BD29: =IF(AZ29=0,(AZ29-BA29-BC29),(AZ29-BA29-BB29-BC29)) -> 51000 | BE29: OK | BF29: =Z29*1/100*BG29 -> 0 | BG29: 10
A30: AS201653 | B30: =VLOOKUP(A30,[11]LISTADHERENT!A$5:H$50,3,0) -> SIME BRICE | C30: =D30+E30+F30-U30-BB30 -> 0 | D30: =VLOOKUP(A30,[12]HISTOBQUEFEV24!$A$6:$G$46,3,0) -> 250000 | E30: =VLOOKUP(A30,[12]HISTOBQUEFEV24!$A$6:$G$41,4,0) -> 0 | F30: =VLOOKUP(A30,[12]HISTOBQUEFEV24!$A$6:$G$41,5,0) -> 0 | G30: =IF(H30="ESPECES",3000,0) -> 0 | H30: =IF($D30<>0,"BANQUE",IF($E30<>0,"ESPECES","ECHEC")) -> BANQUE | J30: 1 | K30: =IF($D30<>0,J30*50000,IF($E30<>0,J30*50000,0)) -> 50000 | M30: =IF($D30<>0,L30*75000,IF($E30<>0,L30*75000,0)) -> 0 | N30: 2 | O30: =IF($D30<>0,N30*100000,IF($E30<>0,N30*100000,0)) -> 200000 | P30: =VLOOKUP(A30,[13]TONTFEV24!$A$6:$R$39,12,0) -> 0 | Q30: =IFERROR(VLOOKUP(A30,[14]TONTFEV24!$A$7:$P$23,10,0),0) -> 0 | R30: =IFERROR(VLOOKUP(A30,[15]TONTFEV24!$A$7:$P$20,10,0),0) -> 0 | U30: =G30+S30++R30+P30+O30+M30+I30+K30+Q30+V30+W30 -> 250000 | AE30: 35000 | AF30: BANQUE | AQ30: =IF(H30="ECHEC",((K30+M30+O30)*20/100),0) -> 0 | AR30: =IF(H30="ECHEC",((K30+M30+O30)*20/100),0) -> 0 | AS30: =IF(H30="ECHEC",0,(K30+I30-25000)) -> 25000 | AW30: =IF(AC30=0,AI30,(1*25000*12)+AI30-AC30) -> 0 | AX30: =IF(AD30=0,AJ30,(1*75000*12)+(AJ30)-AD30) -> 0 | AY30: =IF(AE30=0,AK30,(1*100000*12)+(AK30)-AE30) -> 1165000 | AZ30: =SUM(AV30:AY30)-BF30+Z30-F30+BH30+BI30+BJ30+BK30+BL30+BM30 -> 1165000 | BD30: =IF(AZ30=0,(AZ30-BA30-BC30),(AZ30-BA30-BB30-BC30)) -> 1165000 | BE30: OK | BF30: =Z30*1/100*BG30 -> 0 | BG30: 10 | BO30: DECES | BP30: MUTUELLE
A31: AS201638 | B31: =VLOOKUP(A31,[11]LISTADHERENT!A$5:H$50,3,0) -> SIMO PIERRE | C31: =D31+E31+F31-U31-BB31 -> 0 | D31: =VLOOKUP(A31,[12]HISTOBQUEFEV24!$A$6:$G$46,3,0) -> 150000 | E31: =VLOOKUP(A31,[12]HISTOBQUEFEV24!$A$6:$G$41,4,0) -> 0 | F31: =VLOOKUP(A31,[12]HISTOBQUEFEV24!$A$6:$G$41,5,0) -> 0 | G31: =IF(H31="ESPECES",3000,0) -> 0 | H31: =IF($D31<>0,"BANQUE",IF($E31<>0,"ESPECES","ECHEC")) -> BANQUE | J31: 1 | K31: =IF($D31<>0,J31*50000,IF($E31<>0,J31*50000,0)) -> 50000 | M31: =IF($D31<>0,L31*75000,IF($E31<>0,L31*75000,0)) -> 0 | N31: 1 | O31: =IF($D31<>0,N31*100000,IF($E31<>0,N31*100000,0)) -> 100000 | P31: =VLOOKUP(A31,[13]TONTFEV24!$A$6:$R$39,12,0) -> 0 | Q31: =IFERROR(VLOOKUP(A31,[14]TONTFEV24!$A$7:$P$23,10,0),0) -> 0 | R31: =IFERROR(VLOOKUP(A31,[15]TONTFEV24!$A$7:$P$20,10,0),0) -> 0 | U31: =G31+S31++R31+P31+O31+M31+I31+K31+Q31+V31+W31 -> 150000 | AQ31: =IF(H31="ECHEC",((K31+M31+O31)*20/100),0) -> 0 | AR31: =IF(H31="ECHEC",((K31+M31+O31)*20/100),0) -> 0 | AS31: =IF(H31="ECHEC",0,(K31+I31-25000)) -> 25000 | AW31: =IF(AC31=0,AI31,(1*25000*12)+AI31-AC31) -> 0 | AX31: =IF(AD31=0,AJ31,(1*75000*12)+(AJ31)-AD31) -> 0 | AY31: =IF(AE31=0,AK31,(1*100000*12)+(AK31)-AE31) -> 0 | AZ31: =SUM(AV31:AY31)-BF31+Z31-F31+BH31+BI31+BJ31+BK31+BL31+BM31 -> 0 | BD31: =IF(AZ31=0,(AZ31-BA31-BC31),(AZ31-BA31-BB31-BC31)) -> 0 | BF31: =Z31*1/100*BG31 -> 0 | BG31: 10 | BO31: TRANSPORT DELEGUE | BP31: MUTUELLE
A32: AS201641 | B32: =VLOOKUP(A32,[11]LISTADHERENT!A$5:H$50,3,0) -> TCHOUAMOU MATHIEU | C32: =D32+E32+F32-U32-BB32 -> 0 | D32: =VLOOKUP(A32,[12]HISTOBQUEFEV24!$A$6:$G$46,3,0) -> 125000 | E32: =VLOOKUP(A32,[12]HISTOBQUEFEV24!$A$6:$G$41,4,0) -> 0 | F32: =VLOOKUP(A32,[12]HISTOBQUEFEV24!$A$6:$G$41,5,0) -> 0 | G32: =IF(H32="ESPECES",3000,0) -> 0 | H32: =IF($D32<>0,"BANQUE",IF($E32<>0,"ESPECES","ECHEC")) -> BANQUE | J32: 1 | K32: =IF($D32<>0,J32*50000,IF($E32<>0,J32*50000,0)) -> 50000 | L32: 1 | M32: =IF($D32<>0,L32*75000,IF($E32<>0,L32*75000,0)) -> 75000 | O32: =IF($D32<>0,N32*100000,IF($E32<>0,N32*100000,0)) -> 0 | P32: =VLOOKUP(A32,[13]TONTFEV24!$A$6:$R$39,12,0) -> 0 | Q32: =IFERROR(VLOOKUP(A32,[14]TONTFEV24!$A$7:$P$23,10,0),0) -> 0 | R32: =IFERROR(VLOOKUP(A32,[15]TONTFEV24!$A$7:$P$20,10,0),0) -> 0 | U32: =G32+S32++R32+P32+O32+M32+I32+K32+Q32+V32+W32 -> 125000 | AQ32: =IF(H32="ECHEC",((K32+M32+O32)*20/100),0) -> 0 | AR32: =IF(H32="ECHEC",((K32+M32+O32)*20/100),0) -> 0 | AS32: =IF(H32="ECHEC",0,(K32+I32-25000)) -> 25000 | AW32: =IF(AC32=0,AI32,(1*25000*12)+AI32-AC32) -> 0 | AX32: =IF(AD32=0,AJ32,(1*75000*12)+(AJ32)-AD32) -> 0 | AY32: =IF(AE32=0,AK32,(1*100000*12)+(AK32)-AE32) -> 0 | AZ32: =SUM(AV32:AY32)-BF32+Z32-F32+BH32+BI32+BJ32+BK32+BL32+BM32 -> 0 | BD32: =IF(AZ32=0,(AZ32-BA32-BC32),(AZ32-BA32-BB32-BC32)) -> 0 | BF32: =Z32*1/100*BG32 -> 0 | BG32: 10 | BO32: FUNERAILLE JOSUE DJOSSE | BQ32: 100000
A33: AS201660 | B33: =VLOOKUP(A33,[11]LISTADHERENT!A$5:H$50,3,0) -> TCHOUATEU AUGUSTIN | C33: =D33+E33+F33-U33-BB33 -> 0 | D33: =VLOOKUP(A33,[12]HISTOBQUEFEV24!$A$6:$G$46,3,0) -> 180000 | E33: =VLOOKUP(A33,[12]HISTOBQUEFEV24!$A$6:$G$41,4,0) -> 0 | F33: =VLOOKUP(A33,[12]HISTOBQUEFEV24!$A$6:$G$41,5,0) -> 0 | G33: =IF(H33="ESPECES",3000,0) -> 0 | H33: =IF($D33<>0,"BANQUE",IF($E33<>0,"ESPECES","ECHEC")) -> BANQUE | I33: 30000 | J33: 1 | K33: =IF($D33<>0,J33*50000,IF($E33<>0,J33*50000,0)) -> 50000 | M33: =IF($D33<>0,L33*75000,IF($E33<>0,L33*75000,0)) -> 0 | N33: 1 | O33: =IF($D33<>0,N33*100000,IF($E33<>0,N33*100000,0)) -> 100000 | P33: =VLOOKUP(A33,[13]TONTFEV24!$A$6:$R$39,12,0) -> 0 | Q33: =IFERROR(VLOOKUP(A33,[14]TONTFEV24!$A$7:$P$23,10,0),0) -> 0 | R33: =IFERROR(VLOOKUP(A33,[15]TONTFEV24!$A$7:$P$20,10,0),0) -> 0 | U33: =G33+S33++R33+P33+O33+M33+I33+K33+Q33+V33+W33 -> 180000 | AQ33: =IF(H33="ECHEC",((K33+M33+O33)*20/100),0) -> 0 | AR33: =IF(H33="ECHEC",((K33+M33+O33)*20/100),0) -> 0 | AS33: =IF(H33="ECHEC",0,(K33+I33-25000)) -> 55000 | AW33: =IF(AC33=0,AI33,(1*25000*12)+AI33-AC33) -> 0 | AX33: =IF(AD33=0,AJ33,(1*75000*12)+(AJ33)-AD33) -> 0 | AY33: =IF(AE33=0,AK33,(1*100000*12)+(AK33)-AE33) -> 0 | AZ33: =SUM(AV33:AY33)-BF33+Z33-F33+BH33+BI33+BJ33+BK33+BL33+BM33 -> 0 | BD33: =IF(AZ33=0,(AZ33-BA33-BC33),(AZ33-BA33-BB33-BC33)) -> 0 | BF33: =Z33*1/100*BG33 -> 0 | BG33: 10 | BO33: S/TOTAL | BQ33: =SUM(BQ30:BQ32) -> 100000
A34: AS201643 | B34: =VLOOKUP(A34,[11]LISTADHERENT!A$5:H$50,3,0) -> TCHOUTOU NANA CLAUDE | C34: =D34+E34+F34-U34-BB34 -> 0 | D34: =VLOOKUP(A34,[12]HISTOBQUEFEV24!$A$6:$G$46,3,0) -> 50000 | E34: =VLOOKUP(A34,[12]HISTOBQUEFEV24!$A$6:$G$41,4,0) -> 0 | F34: =VLOOKUP(A34,[12]HISTOBQUEFEV24!$A$6:$G$41,5,0) -> 0 | G34: =IF(H34="ESPECES",3000,0) -> 0 | H34: =IF($D34<>0,"BANQUE",IF($E34<>0,"ESPECES","ECHEC")) -> BANQUE | J34: 1 | K34: =IF($D34<>0,J34*50000,IF($E34<>0,J34*50000,0)) -> 50000 | M34: =IF($D34<>0,L34*75000,IF($E34<>0,L34*75000,0)) -> 0 | O34: =IF($D34<>0,N34*100000,IF($E34<>0,N34*100000,0)) -> 0 | P34: =VLOOKUP(A34,[13]TONTFEV24!$A$6:$R$39,12,0) -> 0 | Q34: =IFERROR(VLOOKUP(A34,[14]TONTFEV24!$A$7:$P$23,10,0),0) -> 0 | R34: =IFERROR(VLOOKUP(A34,[15]TONTFEV24!$A$7:$P$20,10,0),0) -> 0 | U34: =G34+S34++R34+P34+O34+M34+I34+K34+Q34+V34+W34 -> 50000 | AQ34: =IF(H34="ECHEC",((K34+M34+O34)*20/100),0) -> 0 | AR34: =IF(H34="ECHEC",((K34+M34+O34)*20/100),0) -> 0 | AS34: =IF(H34="ECHEC",0,(K34+I34-25000)) -> 25000 | AW34: =IF(AC34=0,AI34,(1*25000*12)+AI34-AC34) -> 0 | AX34: =IF(AD34=0,AJ34,(1*75000*12)+(AJ34)-AD34) -> 0 | AY34: =IF(AE34=0,AK34,(1*100000*12)+(AK34)-AE34) -> 0 | AZ34: =SUM(AV34:AY34)-BF34+Z34-F34+BH34+BI34+BJ34+BK34+BL34+BM34 -> 0 | BD34: =IF(AZ34=0,(AZ34-BA34-BC34),(AZ34-BA34-BB34-BC34)) -> 0 | BF34: =Z34*1/100*BG34 -> 0 | BG34: 10 | BO34: S/TOTAL | BQ34: =SUM(BQ31:BQ33) -> 200000
A35: AS201658 | B35: =VLOOKUP(A35,[11]LISTADHERENT!A$5:H$50,3,0) -> YANTCHOU GERVAIS | C35: =D35+E35+F35-U35-BB35 -> 0 | D35: =VLOOKUP(A35,[12]HISTOBQUEFEV24!$A$6:$G$46,3,0) -> 60000 | E35: =VLOOKUP(A35,[12]HISTOBQUEFEV24!$A$6:$G$41,4,0) -> 0 | F35: =VLOOKUP(A35,[12]HISTOBQUEFEV24!$A$6:$G$41,5,0) -> 0 | G35: =IF(H35="ESPECES",3000,0) -> 0 | H35: =IF($D35<>0,"BANQUE",IF($E35<>0,"ESPECES","ECHEC")) -> BANQUE | I35: 10000 | J35: 1 | K35: =IF($D35<>0,J35*50000,IF($E35<>0,J35*50000,0)) -> 50000 | M35: =IF($D35<>0,L35*75000,IF($E35<>0,L35*75000,0)) -> 0 | O35: =IF($D35<>0,N35*100000,IF($E35<>0,N35*100000,0)) -> 0 | P35: =VLOOKUP(A35,[13]TONTFEV24!$A$6:$R$39,12,0) -> 0 | Q35: =IFERROR(VLOOKUP(A35,[14]TONTFEV24!$A$7:$P$23,10,0),0) -> 0 | R35: =IFERROR(VLOOKUP(A35,[15]TONTFEV24!$A$7:$P$20,10,0),0) -> 0 | U35: =G35+S35++R35+P35+O35+M35+I35+K35+Q35+V35+W35 -> 60000 | AQ35: =IF(H35="ECHEC",((K35+M35+O35)*20/100),0) -> 0 | AR35: =IF(H35="ECHEC",((K35+M35+O35)*20/100),0) -> 0 | AS35: =IF(H35="ECHEC",0,(K35+I35-25000)) -> 35000 | AW35: =IF(AC35=0,AI35,(1*25000*12)+AI35-AC35) -> 0 | AX35: =IF(AD35=0,AJ35,(1*75000*12)+(AJ35)-AD35) -> 0 | AY35: =IF(AE35=0,AK35,(1*100000*12)+(AK35)-AE35) -> 0 | AZ35: =SUM(AV35:AY35)-BF35+Z35-F35+BH35+BI35+BJ35+BK35+BL35+BM35 -> 0 | BD35: =IF(AZ35=0,(AZ35-BA35-BC35),(AZ35-BA35-BB35-BC35)) -> 0 | BF35: =Z35*1/100*BG35 -> 0 | BG35: 10
