Workbook
Name BANQUE: #REF!
Name BANQUE: #REF!
Name BANQUE: #REF!
Name BANQUE: #REF!
Name BANQUE: #REF!
Name BANQUE: #REF!
Name BANQUE: #REF!
Name BANQUE: #REF!
Name BANQUE: #REF!
Name BANQUE: #REF!
Name BANQUE: #REF!
Name BANQUE: #REF!
Name BANQUE: #REF!
Name BANQUE: #REF!
Name BANQUE: #REF!
Name BANQUE: #REF!
Name BANQUE: #REF!
Name BANQUE: #REF!
Name BANQUE: #REF!
Name BANQUE: #REF!
Name BANQUE: #REF!
Name BANQUE: #REF!
Name BANQUE: #REF!
Name BANQUE: #REF!
Name BANQUE: #REF!
Name BANQUE: #REF!
Name BANQUE: #REF!
Name BANQUE: #REF!
Name BANQUE: #REF!
Name BANQUE: #REF!
Name BANQUE: #REF!
Name BANQUE: #REF!
Name BANQUE: #REF!
Name BANQUE: #REF!
Name BANQUE: #REF!
Name BANQUE: #REF!
Name BANQUE: #REF!
Name BANQUE: #REF!
Name BANQUE: #REF!
Name BANQUE: #REF!
Name BANQUE: #REF!
Name BANQUE: #REF!
Name BANQUE: #REF!
Name BANQUE: #REF!
Name BANQUE: #REF!
Name BANQUE: #REF!
Name BANQUE: #REF!
Name GG: #REF!
Name GG: #REF!
Name GG: #REF!
Name GG: #REF!
Name GG: #REF!
Name GG: #REF!
Name GG: #REF!
Name GG: #REF!
Name GG: #REF!
Name GG: #REF!
Name GG: #REF!
Name GG: #REF!
Name GG: #REF!

Sheet MODETABORD
A1: BANQUE
A2: ESPECES

Sheet HISTOMVTDEPENSE
A1: ASSOCIATION | B1: ASELBY
A2: ANNEE | B2: 2022
A3: 1 | B3: 2 | D3: 3 | E3: 4 | F3: 5 | G3: 6 | H3: 7 | I3: 8 | J3: 9 | K3: 10 | L3: 11 | M3: 12 | N3: 13 | O3: 14 | P3: 15 | Q3: 16 | R3: 17 | S3: 18
B4: TABLEAU DE BORD SAISIE DES DEPENSES
A5: MATRICULE | B5: NOM ET PRENOM | D5: FONDS DE ROULEMENT | M5: FRAIS EXCEPTIONNEL | P5: COLLATION | R5: MUTUELLE | T5: TOTAUX
C6: FRAIS BANCAIRE | D6: ACHAT FOURNITURE | E6: COMMUNICATION | F6: COMMISSION | G6: AUTRES AIDES | H6: CREDIT TELEPHONE | I6: PRODUCTION RAPPORT | J6: ACHAT SOURIS ET PHOTOCOPIE | K6: FRAIS DE BANQUE | L6: CONFECTION CACHET | M6: GRATIFICATION BUREAU | N6: DEVELOPPEMENT LAGWEU | O6: DEUIL | P6: COLLATION | Q6: BOISSON | R6: DECES | S6: TRANSPORT DELEGUE
A7: AS201648 | B7: ASELBY | T7: =SUM(D7:S7) -> 0
A8: AS201602 | B8: BOUTCHOUANG WILLIAM | T8: =SUM(D8:S8) -> 0
A9: AS201604 | B9: DJOMO JEAN PAUL | T9: =SUM(D9:S9) -> 0
A10: AS201654 | B10: DJOMOU TCHANDA | T10: =SUM(D10:S10) -> 0
A11: AS201605 | B11: DJOUKWE NANGUEN GUY BLAISE | T11: =SUM(D11:S11) -> 0
A12: AS201608 | B12: DJUOMBESSY ANTOINE | T12: =SUM(D12:S12) -> 0
A13: AS201651 | B13: DOMOU FABIEN | T13: =SUM(D13:S13) -> 0
A14: AS201609 | B14: DONHOU DAVID | T14: =SUM(D14:S14) -> 0
A15: AS201610 | B15: FOTSO THOMAS | T15: =SUM(D15:S15) -> 0
A16: AS201611 | B16: HENGUE PAUL OMER | T16: =SUM(D16:S16) -> 0
A17: AS201613 | B17: HOTCHO BENJAMIN | T17: =SUM(D17:S17) -> 0
A18: AS201617 | B18: KOUAMOU MOISE | T18: =SUM(D18:S18) -> 0
... A37: AS201647 | B37: YOUMBI EMMANUEL | T37: =SUM(D37:S37) -> 0
B39: TOTAUX | C39: =SUM(C8:C38) -> 0 | D39: =SUM(D8:D38) -> 0 | E39: =SUM(E8:E38) -> 0 | F39: =SUM(F8:F38) -> 0 | G39: =SUM(G8:G38) -> 0 | H39: =SUM(H8:H38) -> 0 | J39: =SUM(J8:J38) -> 0 | K39: =SUM(K8:K38) -> 0 | L39: =SUM(L8:L38) -> 0 | M39: =SUM(M8:M38) -> 0 | N39: =SUM(N8:N38) -> 0 | O39: =SUM(O8:O38) -> 0 | P39: =SUM(P8:P38) -> 0 | Q39: =SUM(Q8:Q38) -> 0 | ... T39: =SUM(T8:T38) -> 0

Sheet COMPTE BANQUE
C1: COMPTE BANQUE | H1: COMPTE CAISSE
A2: ANNEE | C2: 2022 | H2: 2022
A4: MOIS | B4: NUMERO CHEQUE | C4: SORTIE | D4: ENTREE | E4: SOLDE | G4: NUMERO PIECE | H4: ENTREE | I4: SORTIE | J4: SOLDE
A5: REPORT A NOUVEAU | E5: =14283661-6017000 -> 8266661
A6: JANVIER | C6: =#REF!+HISTOMVTDEPENSE!T39 -> #REF! | D6: =#REF! -> #REF! | E6: =IF(D6=0,0,E5+D6-C6) -> #REF!
A7: FÉVRIER | C7: =#REF! -> #REF! | D7: =#REF! -> #REF! | E7: =IF(D7=0,0,E6+D7-C7) -> #REF!
A8: MARS | C8: =#REF! -> #REF! | D8: =#REF! -> #REF! | E8: =IF(D8=0,0,E7+D8-C8) -> #REF!
A9: AVRIL | C9: =#REF! -> #REF! | D9: =#REF! -> #REF! | E9: =IF(D9=0,0,E8+D9-C9) -> #REF!
A10: MAI | C10: =#REF! -> #REF! | D10: =#REF! -> #REF! | E10: =IF(D10=0,0,E9+D10-C10) -> #REF!
A11: JUIN | C11: =#REF! -> #REF! | D11: =#REF! -> #REF! | E11: =IF(D11=0,0,E10+D11-C11) -> #REF!
A12: JUILLET | C12: =#REF! -> #REF! | D12: =#REF! -> #REF! | E12: =IF(D12=0,0,E11+D12-C12) -> #REF!
A13: AOÛT | C13: =#REF! -> #REF! | D13: =#REF! -> #REF! | E13: =IF(D13=0,0,E12+D13-C13) -> #REF!
A14: SEPTEMBRE | C14: =#REF! -> #REF! | D14: =#REF! -> #REF! | E14: =IF(D14=0,0,E13+D14-C14) -> #REF!
A15: OCTOBRE | C15: =#REF! -> #REF! | D15: =#REF! -> #REF! | E15: =IF(D15=0,0,E14+D15-C15) -> #REF!
A16: NOVEMBRE | C16: =#REF! -> #REF! | D16: =#REF! -> #REF! | E16: =IF(D16=0,0,E15+D16-C16) -> #REF!
A17: DÉCEMBRE | C17: =#REF! -> #REF! | D17: =#REF! -> #REF! | E17: =IF(D17=0,0,E16+D17-C17) -> #REF!
A19: TOTAL

Sheet HISTODEC22
A1: ASSOCIATION | B1: ASELBY
A2: ANNEE | B2: 2022
A3: 1 | B3: 2 | C3: 3 | D3: 4 | E3: 5 | F3: 6 | G3: 7 | H3: 8 | I3: 9 | J3: 10 | K3: 11 | L3: 12 | M3: 13 | N3: 14 | O3: 15 | P3: 16 | Q3: 17 | R3: 18 | S3: 19 | T3: 20 | U3: 21 | V3: 22 | W3: 23 | X3: 24 | Y3: 25 | Z3: 26 | AA3: 27 | AB3: 28 | AC3: 29 | AD3: 30 | AE3: 31 | AF3: 32 | AG3: 33 | AH3: 34 | AI3: 35 | AJ3: 36 | AK3: 37 | AL3: 38 | AM3: 39 | AN3: 40 | AO3: 41 | AP3: 42 | AQ3: 43 | AR3: 44 | AS3: 45 | AT3: 46 | AU3: 47 | AV3: 48 | AW3: 49 | AX3: 50 | AY3: 51 | AZ3: 52 | BA3: 53 | BB3: 54 | BC3: 55 | BD3: 56 | BE3: 57 | BF3: 58 | BG3: 59 | BH3: 60 | BI3: 61 | BJ3: 62 | BK3: 63 | BL3: 64 | BM3: 65 | BN3: 66
B4: TABLEAU DE BORD SAISIE DES DONNEES
A5: MATRICULE | B5: NOM ET PRENOM | C5: BONUS MALUS | D5: HISTORIQUE BANQUE | E5: HITORIQUE ESPECES | F5: HITORIQUE TONTINE | G5: PENALITE VERSEMENT ESPECES | H5: MODE PAIEMENT TONTINE | I5: NBRE DE LOT | J5: TONTINE 35 000 | K5: COMPLEMENT EPARGNE | L5: NBRE DE LOT | M5: TONTINE 75 000 | N5: NBRE DE LOT | O5: TONTINE 100 000 | P5: REMBOURSEMENT PETIT LOT T35 | Q5: REMBOURSEMENT PETIT LOT T75 | R5: REMBOURSEMENT PETIT LOT T100 | S5: REMBOURSEMENT PRÊT FONDS | T5: MODE PAIEMENT REMBOURSEMENT PRÊT FONDS | U5: MONTANT ENGAGEMENT | V5: SANCTION | W5: INSCRIPTION | X5: EPARGNE ASSURANCE | Y5: RECONSTITUTION FONDS | Z5: PRÊT FONDS | AA5: MODE PAIEMENT PRÊT | AB5: NUM CHEQUE | AC5: ACHAT LOT PRINCIPAL T30 | AD5: ACHAT LOT PRINCIPAL T75 | AE5: ACHAT LOT PRINCIPAL T100 | AF5: MODE PAIEMENT LOT PRINCIPAL | AG5: NUM CHEQUE | AH5: PENALITE VERSEMENT ESPECES | AI5: VENTE PETIT LOT T30 | AJ5: VENTE PETIT LOT T75 | AK5: VENTE PETIT LOT T100 | AL5: INTERET PETIT LOT T30 | AM5: INTERET PETIT LOT T75 | AN5: INTERET PETIT LOT T100 | AO5: NUM CHEQUE | AP5: MODE PAIEMENT PETEIT LOT | AQ5: PENELAITE RETARD TONTINE | AR5: PENELAITE ECHEC TONTINE | AS5: RESTE | AT5: MUTUELLE | AU5: REMBOURSEMENT TRANSPORT | AV5: RETRAIT PARTIEL FONDS | AW5: MONTANT T30 | AX5: MONTANT T75 | AY5: MONTANT T100 | AZ5: MONTANT CHEQUE | BA5: MONTANT ESPECES | BB5: CONTRIBUTION FOYER | BC5: AUTRES SOTIES | BD5: MONTANT CHEQUE EFFECTIF | BE5: NUMERO CHEQUE | BF5: INTERET PRÊT | BG5: NBRE MOIS | BH5: DEPENSE FONDS DE ROULEMENT | BI5: DEPENSE FRAIS EXCEPTIONNEL | BJ5: DEPENSE FONDS MUTUEL | BK5: DEPENSE COLLATION RECEPTION | BL5: PENALITE PRET FONDS | BM5: DEPENSE PENALITE VERSEMENT BANQUE | BN5: LIBELLE | BO5: COMPTE | BP5: MONTANT
A6: AS201648 | B6: ASELBY | C6: =D6+E6+F6-U6-BB6 -> 0 | D6: 100000 | E6: 0 | F6: 0 | G6: =IF(H6="ESPECES",3000,0) -> 0 | H6: =IF($D6<>0,"BANQUE",IF($E6<>0,"ESPECES","ECHEC")) -> BANQUE | J6: =IF($D6<>0,I6*30000,IF($E6<>0,I6*30000,0)) -> 0 | M6: =IF($D6<>0,L6*75000,IF($E6<>0,L6*75000,0)) -> 0 | N6: 1 | O6: =IF($D6<>0,N6*100000,IF($E6<>0,N6*100000,0)) -> 100000 | R6: 0 | U6: =G6+S6++R6+P6+O6+M6+K6+J6+Q6+V6+W6 -> 100000 | AE6: 100000 | AF6: BANQUE | AQ6: =IF(H6="ECHEC",((J6+M6+O6)*20/100),0) -> 0 | AR6: =IF(H6="ECHEC",((J6+M6+O6)*20/100),0) -> 0 | AW6: =IF(AC6=0,AI6,(1*23000*13)+(1000+AI6)-AC6) -> 0 | AX6: =IF(AD6=0,AJ6,(1*75000*16)+(AJ6)-AD6) -> 0 | AY6: =IF(AE6=0,AK6,(1*100000*13)+(AK6)-AE6) -> 1200000 | AZ6: =SUM(AV6:AY6)-BF6+Z6-F6+BH6+BI6+BJ6+BK6 -> 1206000 | BD6: =IF(AZ6=0,(AZ6-BA6-BC6),(AZ6-BA6-BB6-BC6)) -> 1206000 | BF6: =Z6*1/100*BG6 -> 0 | BG6: 0 | BH6: =BP16 -> 6000 | BI6: =BP28 -> 0 | BJ6: =BP33 -> 0 | BM6: =BP22 -> 0 | BN6: ACHAT FOURNITURE | BO6: FONDS DE ROULEMENT
A7: AS201602 | B7: BOUTCHOUANG WILLIAM | C7: =D7+E7+F7-U7-BB7 -> 0 | D7: 105000 | E7: 0 | F7: 0 | G7: =IF(H7="ESPECES",3000,0) -> 0 | H7: =IF($D7<>0,"BANQUE",IF($E7<>0,"ESPECES","ECHEC")) -> BANQUE | I7: 1 | J7: =IF($D7<>0,I7*30000,IF($E7<>0,I7*30000,0)) -> 30000 | L7: 1 | M7: =IF($D7<>0,L7*75000,IF($E7<>0,L7*75000,0)) -> 75000 | O7: =IF($D7<>0,N7*100000,IF($E7<>0,N7*100000,0)) -> 0 | P7: 0 | U7: =G7+S7++R7+P7+O7+M7+K7+J7+Q7+V7+W7 -> 105000 | Z7: 500000 | AA7: BANQUE | AQ7: =IF(H7="ECHEC",((J7+M7+O7)*20/100),0) -> 0 | AR7: =IF(H7="ECHEC",((J7+M7+O7)*20/100),0) -> 0 | AS7: =IF(H7="ECHEC",0,(J7+K7-23000)) -> 7000 | AT7: 20000 | AW7: =IF(AC7=0,AI7,(1*23000*13)+(1000+AI7)-AC7) -> 0 | AX7: =IF(AD7=0,AJ7,(1*75000*16)+(AJ7)-AD7) -> 0 | AY7: =IF(AE7=0,AK7,(1*100000*13)+(AK7)-AE7) -> 0 | AZ7: =SUM(AV7:AY7)-BF7+Z7-F7+BH7+BI7+BJ7+BK7 -> 490000 | BD7: =IF(AZ7=0,(AZ7-BA7-BC7),(AZ7-BA7-BB7-BC7)) -> 490000 | BF7: =Z7*1/100*BG7 -> 10000 | BG7: 2 | BN7: COMMUNICATION | BO7: FONDS DE ROULEMENT
A8: AS201604 | B8: DJOMO JEAN PAUL | C8: =D8+E8+F8-U8-BB8 -> 0 | D8: 1105000 | E8: 0 | F8: 0 | G8: =IF(H8="ESPECES",3000,0) -> 0 | H8: =IF($D8<>0,"BANQUE",IF($E8<>0,"ESPECES","ECHEC")) -> BANQUE | I8: 1 | J8: =IF($D8<>0,I8*30000,IF($E8<>0,I8*30000,0)) -> 30000 | L8: 1 | M8: =IF($D8<>0,L8*75000,IF($E8<>0,L8*75000,0)) -> 75000 | O8: =IF($D8<>0,N8*100000,IF($E8<>0,N8*100000,0)) -> 0 | P8: 0 | Q8: 0 | S8: =775000+130000+95000 -> 1000000 | T8: BANQUE | U8: =G8+S8++R8+P8+O8+M8+K8+J8+Q8+V8+W8 -> 1105000 | Z8: 1000000 | AA8: BANQUE | AQ8: =IF(H8="ECHEC",((J8+M8+O8)*20/100),0) -> 0 | AR8: =IF(H8="ECHEC",((J8+M8+O8)*20/100),0) -> 0 | AS8: =IF(H8="ECHEC",0,(J8+K8-23000)) -> 7000 | AT8: 20000 | AW8: =IF(AC8=0,AI8,(1*23000*13)+(1000+AI8)-AC8) -> 0 | AX8: =IF(AD8=0,AJ8,(1*75000*16)+(AJ8)-AD8) -> 0 | AY8: =IF(AE8=0,AK8,(1*100000*13)+(AK8)-AE8) -> 0 | AZ8: =SUM(AV8:AY8)-BF8+Z8-F8+BH8+BI8+BJ8+BK8 -> 880000 | BD8: =IF(AZ8=0,(AZ8-BA8-BC8),(AZ8-BA8-BB8-BC8)) -> 880000 | BF8: =Z8*1/100*BG8 -> 120000 | BG8: 12 | BN8: COMMISSION | BO8: FONDS DE ROULEMENT
A9: AS201654 | B9: DJOMOU TCHANDA | C9: =D9+E9+F9-U9-BB9 -> 0 | D9: 30000 | E9: 0 | F9: 0 | G9: =IF(H9="ESPECES",3000,0) -> 0 | H9: =IF($D9<>0,"BANQUE",IF($E9<>0,"ESPECES","ECHEC")) -> BANQUE | I9: 1 | J9: =IF($D9<>0,I9*30000,IF($E9<>0,I9*30000,0)) -> 30000 | M9: =IF($D9<>0,L9*75000,IF($E9<>0,L9*75000,0)) -> 0 | O9: =IF($D9<>0,N9*100000,IF($E9<>0,N9*100000,0)) -> 0 | P9: 0 | U9: =G9+S9++R9+P9+O9+M9+K9+J9+Q9+V9+W9 -> 30000 | AQ9: =IF(H9="ECHEC",((J9+M9+O9)*20/100),0) -> 0 | AR9: =IF(H9="ECHEC",((J9+M9+O9)*20/100),0) -> 0 | AS9: =IF(H9="ECHEC",0,(J9+K9-23000)) -> 7000 | AT9: 20000 | AW9: =IF(AC9=0,AI9,(1*23000*13)+(1000+AI9)-AC9) -> 0 | AX9: =IF(AD9=0,AJ9,(1*75000*16)+(AJ9)-AD9) -> 0 | AY9: =IF(AE9=0,AK9,(1*100000*13)+(AK9)-AE9) -> 0 | AZ9: =SUM(AV9:AY9)-BF9+Z9-F9+BH9+BI9+BJ9+BK9 -> 0 | BD9: =IF(AZ9=0,(AZ9-BA9-BC9),(AZ9-BA9-BB9-BC9)) -> 0 | BF9: =Z9*1/100*BG9 -> 0 | BG9: 0 | BN9: AIDE UEEB ET CONT FEMME | BO9: FONDS DE ROULEMENT
A10: AS201605 | B10: DJOUKWE NANGUEN GUY BLAISE | C10: =D10+E10+F10-U10-BB10 -> 0 | D10: 1105000 | E10: 0 | F10: 0 | G10: =IF(H10="ESPECES",3000,0) -> 0 | H10: =IF($D10<>0,"BANQUE",IF($E10<>0,"ESPECES","ECHEC")) -> BANQUE | I10: 1 | J10: =IF($D10<>0,I10*30000,IF($E10<>0,I10*30000,0)) -> 30000 | L10: 1 | M10: =IF($D10<>0,L10*75000,IF($E10<>0,L10*75000,0)) -> 75000 | O10: =IF($D10<>0,N10*100000,IF($E10<>0,N10*100000,0)) -> 0 | P10: 0 | Q10: 0 | S10: =900000+100000 -> 1000000 | T10: BANQUE | U10: =G10+S10++R10+P10+O10+M10+K10+J10+Q10+V10+W10 -> 1105000 | Z10: 1000000 | AA10: BANQUE | AQ10: =IF(H10="ECHEC",((J10+M10+O10)*20/100),0) -> 0 | AR10: =IF(H10="ECHEC",((J10+M10+O10)*20/100),0) -> 0 | AS10: =IF(H10="ECHEC",0,(J10+K10-23000)) -> 7000 | AT10: 20000 | AW10: =IF(AC10=0,AI10,(1*23000*13)+(1000+AI10)-AC10) -> 0 | AX10: =IF(AD10=0,AJ10,(1*75000*16)+(AJ10)-AD10) -> 0 | AY10: =IF(AE10=0,AK10,(1*100000*13)+(AK10)-AE10) -> 0 | AZ10: =SUM(AV10:AY10)-BF10+Z10-F10+BH10+BI10+BJ10+BK10 -> 980000 | BD10: =IF(AZ10=0,(AZ10-BA10-BC10),(AZ10-BA10-BB10-BC10)) -> 980000 | BF10: =Z10*1/100*BG10 -> 20000 | BG10: 2 | BN10: CREDIT TELEPHONE | BO10: FONDS DE ROULEMENT
A11: AS201608 | B11: DJUOMBESSY ANTOINE | C11: =D11+E11+F11-U11-BB11 -> 0 | D11: 215000 | E11: 0 | F11: 0 | G11: =IF(H11="ESPECES",3000,0) -> 0 | H11: =IF($D11<>0,"BANQUE",IF($E11<>0,"ESPECES","ECHEC")) -> BANQUE | I11: 1 | J11: =IF($D11<>0,I11*30000,IF($E11<>0,I11*30000,0)) -> 30000 | K11: 1000 | L11: 1 | M11: =IF($D11<>0,L11*75000,IF($E11<>0,L11*75000,0)) -> 75000 | N11: 1 | O11: =IF($D11<>0,N11*100000,IF($E11<>0,N11*100000,0)) -> 100000 | P11: 0 | Q11: 0 | R11: 0 | U11: =G11+S11++R11+P11+O11+M11+K11+J11+Q11+V11+W11 -> 206000 | Z11: 1000000 | AA11: BANQUE | AQ11: =IF(H11="ECHEC",((J11+M11+O11)*20/100),0) -> 0 | AR11: =IF(H11="ECHEC",((J11+M11+O11)*20/100),0) -> 0 | AS11: =IF(H11="ECHEC",0,(J11+K11-23000)) -> 8000 | AT11: 20000 | AW11: =IF(AC11=0,AI11,(1*23000*13)+(1000+AI11)-AC11) -> 0 | AX11: =IF(AD11=0,AJ11,(1*75000*16)+(AJ11)-AD11) -> 0 | AY11: =IF(AE11=0,AK11,(1*100000*13)+(AK11)-AE11) -> 0 | AZ11: =SUM(AV11:AY11)-BF11+Z11-F11+BH11+BI11+BJ11+BK11 -> 940000 | BB11: 9000 | BD11: =IF(AZ11=0,(AZ11-BA11-BC11),(AZ11-BA11-BB11-BC11)) -> 931000 | BF11: =Z11*1/100*BG11 -> 60000 | BG11: 6 | BN11: PRODUCTION RAPPORT | BO11: FONDS DE ROULEMENT
A12: AS201651 | B12: DOMOU FABIEN | C12: =D12+E12+F12-U12-BB12 -> 0 | D12: 1035000 | E12: 0 | F12: 0 | G12: =IF(H12="ESPECES",3000,0) -> 0 | H12: =IF($D12<>0,"BANQUE",IF($E12<>0,"ESPECES","ECHEC")) -> BANQUE | I12: 1 | J12: =IF($D12<>0,I12*30000,IF($E12<>0,I12*30000,0)) -> 30000 | K12: 5000 | M12: =IF($D12<>0,L12*75000,IF($E12<>0,L12*75000,0)) -> 0 | O12: =IF($D12<>0,N12*100000,IF($E12<>0,N12*100000,0)) -> 0 | P12: 0 | S12: 1000000 | T12: BANQUE | U12: =G12+S12++R12+P12+O12+M12+K12+J12+Q12+V12+W12 -> 1035000 | Z12: 1000000 | AA12: BANQUE | AQ12: =IF(H12="ECHEC",((J12+M12+O12)*20/100),0) -> 0 | AR12: =IF(H12="ECHEC",((J12+M12+O12)*20/100),0) -> 0 | AS12: =IF(H12="ECHEC",0,(J12+K12-23000)) -> 12000 | AT12: 20000 | AW12: =IF(AC12=0,AI12,(1*23000*13)+(1000+AI12)-AC12) -> 0 | AX12: =IF(AD12=0,AJ12,(1*75000*16)+(AJ12)-AD12) -> 0 | AY12: =IF(AE12=0,AK12,(1*100000*13)+(AK12)-AE12) -> 0 | AZ12: =SUM(AV12:AY12)-BF12+Z12-F12+BH12+BI12+BJ12+BK12 -> 880000 | BD12: =IF(AZ12=0,(AZ12-BA12-BC12),(AZ12-BA12-BB12-BC12)) -> 880000 | BF12: =Z12*1/100*BG12 -> 120000 | BG12: 12 | BN12: ACHAT SOURIS ET PHOTOCOPIE | BO12: FONDS DE ROULEMENT
A13: AS201609 | B13: DONHOU DAVID | C13: =D13+E13+F13-U13-BB13 -> 0 | D13: 35000 | E13: 0 | F13: 0 | G13: =IF(H13="ESPECES",3000,0) -> 0 | H13: =IF($D13<>0,"BANQUE",IF($E13<>0,"ESPECES","ECHEC")) -> BANQUE | I13: 1 | J13: =IF($D13<>0,I13*30000,IF($E13<>0,I13*30000,0)) -> 30000 | K13: 5000 | M13: =IF($D13<>0,L13*75000,IF($E13<>0,L13*75000,0)) -> 0 | O13: =IF($D13<>0,N13*100000,IF($E13<>0,N13*100000,0)) -> 0 | P13: 0 | U13: =G13+S13++R13+P13+O13+M13+K13+J13+Q13+V13+W13 -> 35000 | AC13: 23000 | AF13: BANQUE | AQ13: =IF(H13="ECHEC",((J13+M13+O13)*20/100),0) -> 0 | AR13: =IF(H13="ECHEC",((J13+M13+O13)*20/100),0) -> 0 | AS13: =IF(H13="ECHEC",0,(J13+K13-23000)) -> 12000 | AT13: 20000 | AW13: =IF(AC13=0,AI13,(1*23000*13)+(1000+AI13)-AC13) -> 277000 | AX13: =IF(AD13=0,AJ13,(1*75000*16)+(AJ13)-AD13) -> 0 | AY13: =IF(AE13=0,AK13,(1*100000*13)+(AK13)-AE13) -> 0 | AZ13: =SUM(AV13:AY13)-BF13+Z13-F13+BH13+BI13+BJ13+BK13 -> 277000 | BD13: =IF(AZ13=0,(AZ13-BA13-BC13),(AZ13-BA13-BB13-BC13)) -> 277000 | BF13: =Z13*1/100*BG13 -> 0 | BG13: 0 | BN13: TAXI BANQUE | BO13: FONDS DE ROULEMENT | BP13: 6000
A14: AS201610 | B14: FOTSO THOMAS | C14: =D14+E14+F14-U14-BB14 -> 0 | D14: 0 | E14: 0 | F14: 0 | G14: =IF(H14="ESPECES",3000,0) -> 0 | H14: =IF($D14<>0,"BANQUE",IF($E14<>0,"ESPECES","ECHEC")) -> ECHEC | J14: =IF($D14<>0,I14*30000,IF($E14<>0,I14*30000,0)) -> 0 | M14: =IF($D14<>0,L14*75000,IF($E14<>0,L14*75000,0)) -> 0 | O14: =IF($D14<>0,N14*100000,IF($E14<>0,N14*100000,0)) -> 0 | U14: =G14+S14++R14+P14+O14+M14+K14+J14+Q14+V14+W14 -> 0 | AQ14: =IF(H14="ECHEC",((J14+M14+O14)*20/100),0) -> 0 | AR14: =IF(H14="ECHEC",((J14+M14+O14)*20/100),0) -> 0 | AS14: =IF(H14="ECHEC",0,(J14+K14-23000)) -> 0 | AW14: =IF(AC14=0,AI14,(1*23000*13)+(1000+AI14)-AC14) -> 0 | AX14: =IF(AD14=0,AJ14,(1*75000*16)+(AJ14)-AD14) -> 0 | AY14: =IF(AE14=0,AK14,(1*100000*13)+(AK14)-AE14) -> 0 | AZ14: =SUM(AV14:AY14)-BF14+Z14-F14+BH14+BI14+BJ14+BK14 -> 0 | BD14: =IF(AZ14=0,(AZ14-BA14-BC14),(AZ14-BA14-BB14-BC14)) -> 0 | BF14: =Z14*1/100*BG14 -> 0 | BG14: 0 | BN14: CONFECTION CACHET | BO14: FONDS DE ROULEMENT
A15: AS201611 | B15: HENGUE PAUL OMER | C15: =D15+E15+F15-U15-BB15 -> 0 | D15: 105000 | E15: 0 | F15: 0 | G15: =IF(H15="ESPECES",3000,0) -> 0 | H15: =IF($D15<>0,"BANQUE",IF($E15<>0,"ESPECES","ECHEC")) -> BANQUE | I15: 1 | J15: =IF($D15<>0,I15*30000,IF($E15<>0,I15*30000,0)) -> 30000 | L15: 1 | M15: =IF($D15<>0,L15*75000,IF($E15<>0,L15*75000,0)) -> 75000 | O15: =IF($D15<>0,N15*100000,IF($E15<>0,N15*100000,0)) -> 0 | P15: 0 | Q15: 0 | U15: =G15+S15++R15+P15+O15+M15+K15+J15+Q15+V15+W15 -> 105000 | AD15: 75000 | AF15: BANQUE | AQ15: =IF(H15="ECHEC",((J15+M15+O15)*20/100),0) -> 0 | AR15: =IF(H15="ECHEC",((J15+M15+O15)*20/100),0) -> 0 | AS15: =IF(H15="ECHEC",0,(J15+K15-23000)) -> 7000 | AT15: 20000 | AW15: =IF(AC15=0,AI15,(1*23000*13)+(1000+AI15)-AC15) -> 0 | AX15: =IF(AD15=0,AJ15,(1*75000*16)+(AJ15)-AD15) -> 1125000 | AY15: =IF(AE15=0,AK15,(1*100000*13)+(AK15)-AE15) -> 0 | AZ15: =SUM(AV15:AY15)-BF15+Z15-F15+BH15+BI15+BJ15+BK15 -> 1125000 | BD15: =IF(AZ15=0,(AZ15-BA15-BC15),(AZ15-BA15-BB15-BC15)) -> 1125000 | BF15: =Z15*1/100*BG15 -> 0 | BG15: 0
A16: AS201613 | B16: HOTCHO BENJAMIN | C16: =D16+E16+F16-U16-BB16 -> 0 | D16: 1150000 | E16: 0 | F16: 0 | G16: =IF(H16="ESPECES",3000,0) -> 0 | H16: =IF($D16<>0,"BANQUE",IF($E16<>0,"ESPECES","ECHEC")) -> BANQUE | I16: 1 | J16: =IF($D16<>0,I16*30000,IF($E16<>0,I16*30000,0)) -> 30000 | K16: 45000 | L16: 1 | M16: =IF($D16<>0,L16*75000,IF($E16<>0,L16*75000,0)) -> 75000 | O16: =IF($D16<>0,N16*100000,IF($E16<>0,N16*100000,0)) -> 0 | P16: 0 | Q16: 0 | S16: 1000000 | T16: BANQUE | U16: =G16+S16++R16+P16+O16+M16+K16+J16+Q16+V16+W16 -> 1150000 | Z16: 1000000 | AA16: BANQUE | AQ16: =IF(H16="ECHEC",((J16+M16+O16)*20/100),0) -> 0 | AR16: =IF(H16="ECHEC",((J16+M16+O16)*20/100),0) -> 0 | AS16: =IF(H16="ECHEC",0,(J16+K16-23000)) -> 52000 | AT16: 20000 | AW16: =IF(AC16=0,AI16,(1*23000*13)+(1000+AI16)-AC16) -> 0 | AX16: =IF(AD16=0,AJ16,(1*75000*16)+(AJ16)-AD16) -> 0 | AY16: =IF(AE16=0,AK16,(1*100000*13)+(AK16)-AE16) -> 0 | AZ16: =SUM(AV16:AY16)-BF16+Z16-F16+BH16+BI16+BJ16+BK16 -> 880000 | BD16: =IF(AZ16=0,(AZ16-BA16-BC16),(AZ16-BA16-BB16-BC16)) -> 880000 | BF16: =Z16*1/100*BG16 -> 120000 | BG16: 12 | BN16: S/TOTAL | BP16: =SUM(BP6:BP15) -> 6000
A17: AS201617 | B17: KOUAMOU MOISE | C17: =D17+E17+F17-U17-BB17 -> 0 | D17: 1030000 | E17: 0 | F17: 0 | G17: =IF(H17="ESPECES",3000,0) -> 0 | H17: =IF($D17<>0,"BANQUE",IF($E17<>0,"ESPECES","ECHEC")) -> BANQUE | I17: 1 | J17: =IF($D17<>0,I17*30000,IF($E17<>0,I17*30000,0)) -> 30000 | M17: =IF($D17<>0,L17*75000,IF($E17<>0,L17*75000,0)) -> 0 | N17: 3 | O17: =IF($D17<>0,N17*100000,IF($E17<>0,N17*100000,0)) -> 300000 | P17: 0 | R17: 0 | S17: 700000 | T17: BANQUE | U17: =G17+S17++R17+P17+O17+M17+K17+J17+Q17+V17+W17 -> 1030000 | AQ17: =IF(H17="ECHEC",((J17+M17+O17)*20/100),0) -> 0 | AR17: =IF(H17="ECHEC",((J17+M17+O17)*20/100),0) -> 0 | AS17: =IF(H17="ECHEC",0,(J17+K17-23000)) -> 7000 | AT17: 20000 | AW17: =IF(AC17=0,AI17,(1*23000*13)+(1000+AI17)-AC17) -> 0 | AX17: =IF(AD17=0,AJ17,(1*75000*16)+(AJ17)-AD17) -> 0 | AY17: =IF(AE17=0,AK17,(1*100000*13)+(AK17)-AE17) -> 0 | AZ17: =SUM(AV17:AY17)-BF17+Z17-F17+BH17+BI17+BJ17+BK17 -> 0 | BD17: =IF(AZ17=0,(AZ17-BA17-BC17),(AZ17-BA17-BB17-BC17)) -> 0 | BF17: =Z17*1/100*BG17 -> 0 | BG17: 0
A18: AS201619 | B18: KOUATCHO MESSACK | C18: =D18+E18+F18-U18-BB18 -> 0 | D18: 1205000 | E18: 0 | F18: 0 | G18: =IF(H18="ESPECES",3000,0) -> 0 | H18: =IF($D18<>0,"BANQUE",IF($E18<>0,"ESPECES","ECHEC")) -> BANQUE | I18: 1 | J18: =IF($D18<>0,I18*30000,IF($E18<>0,I18*30000,0)) -> 30000 | L18: 1 | M18: =IF($D18<>0,L18*75000,IF($E18<>0,L18*75000,0)) -> 75000 | N18: 1 | O18: =IF($D18<>0,N18*100000,IF($E18<>0,N18*100000,0)) -> 100000 | P18: 0 | Q18: 0 | R18: 0 | S18: 1000000 | T18: BANQUE | U18: =G18+S18++R18+P18+O18+M18+K18+J18+Q18+V18+W18 -> 1205000 | Z18: 1000000 | AA18: BANQUE | AQ18: =IF(H18="ECHEC",((J18+M18+O18)*20/100),0) -> 0 | AR18: =IF(H18="ECHEC",((J18+M18+O18)*20/100),0) -> 0 | AS18: =IF(H18="ECHEC",0,(J18+K18-23000)) -> 7000 | AT18: 20000 | AW18: =IF(AC18=0,AI18,(1*23000*13)+(1000+AI18)-AC18) -> 0 | AX18: =IF(AD18=0,AJ18,(1*75000*16)+(AJ18)-AD18) -> 0 | AY18: =IF(AE18=0,AK18,(1*100000*13)+(AK18)-AE18) -> 0 | AZ18: =SUM(AV18:AY18)-BF18+Z18-F18+BH18+BI18+BJ18+BK18 -> 940000 | BD18: =IF(AZ18=0,(AZ18-BA18-BC18),(AZ18-BA18-BB18-BC18)) -> 940000 | BF18: =Z18*1/100*BG18 -> 60000 | BG18: 6 | BN18: GRATIFICATION BUREAU 2021 | BO18: PENALITE VERSEMENT ESPECES
A19: AS201620 | B19: LOWE JEAN | C19: =D19+E19+F19-U19-BB19 -> 0 | D19: 1030000 | E19: 0 | F19: 0 | G19: =IF(H19="ESPECES",3000,0) -> 0 | H19: =IF($D19<>0,"BANQUE",IF($E19<>0,"ESPECES","ECHEC")) -> BANQUE | I19: 1 | J19: =IF($D19<>0,I19*30000,IF($E19<>0,I19*30000,0)) -> 30000 | M19: =IF($D19<>0,L19*75000,IF($E19<>0,L19*75000,0)) -> 0 | O19: =IF($D19<>0,N19*100000,IF($E19<>0,N19*100000,0)) -> 0 | P19: 0 | S19: 1000000 | T19: BANQUE | U19: =G19+S19++R19+P19+O19+M19+K19+J19+Q19+V19+W19 -> 1030000 | Z19: 1000000 | AA19: BANQUE | AQ19: =IF(H19="ECHEC",((J19+M19+O19)*20/100),0) -> 0 | AR19: =IF(H19="ECHEC",((J19+M19+O19)*20/100),0) -> 0 | AS19: =IF(H19="ECHEC",0,(J19+K19-23000)) -> 7000 | AT19: 20000 | AW19: =IF(AC19=0,AI19,(1*23000*13)+(1000+AI19)-AC19) -> 0 | AX19: =IF(AD19=0,AJ19,(1*75000*16)+(AJ19)-AD19) -> 0 | AY19: =IF(AE19=0,AK19,(1*100000*13)+(AK19)-AE19) -> 0 | AZ19: =SUM(AV19:AY19)-BF19+Z19-F19+BH19+BI19+BJ19+BK19 -> 960000 | BD19: =IF(AZ19=0,(AZ19-BA19-BC19),(AZ19-BA19-BB19-BC19)) -> 960000 | BF19: =Z19*1/100*BG19 -> 40000 | BG19: 4 | BN19: ACHAT LAPTOP | BO19: PENALITE VERSEMENT ESPECES
A20: AS201649 | B20: MBOGNING TUGMA GUY | C20: =D20+E20+F20-U20-BB20 -> 0 | D20: 1627500 | E20: 0 | F20: 0 | G20: =IF(H20="ESPECES",3000,0) -> 0 | H20: =IF($D20<>0,"BANQUE",IF($E20<>0,"ESPECES","ECHEC")) -> BANQUE | I20: 1 | J20: =IF($D20<>0,I20*30000,IF($E20<>0,I20*30000,0)) -> 30000 | L20: 3 | M20: =IF($D20<>0,L20*75000,IF($E20<>0,L20*75000,0)) -> 225000 | N20: 2 | O20: =IF($D20<>0,N20*100000,IF($E20<>0,N20*100000,0)) -> 200000 | P20: 0 | Q20: 0 | R20: 172500 | S20: 1000000 | T20: BANQUE | U20: =G20+S20++R20+P20+O20+M20+K20+J20+Q20+V20+W20 -> 1627500 | Z20: 1000000 | AA20: BANQUE | AP20: BANQUE | AQ20: =IF(H20="ECHEC",((J20+M20+O20)*20/100),0) -> 0 | AR20: =IF(H20="ECHEC",((J20+M20+O20)*20/100),0) -> 0 | AS20: =IF(H20="ECHEC",0,(J20+K20-23000)) -> 7000 | AT20: 20000 | AW20: =IF(AC20=0,AI20,(1*23000*13)+(1000+AI20)-AC20) -> 0 | AX20: =IF(AD20=0,AJ20,(1*75000*16)+(AJ20)-AD20) -> 0 | AY20: =IF(AE20=0,AK20,(1*100000*13)+(AK20)-AE20) -> 0 | AZ20: =SUM(AV20:AY20)-BF20+Z20-F20+BH20+BI20+BJ20+BK20 -> 940000 | BD20: =IF(AZ20=0,(AZ20-BA20-BC20),(AZ20-BA20-BB20-BC20)) -> 940000 | BF20: =Z20*1/100*BG20 -> 60000 | BG20: 6
A21: AS201639 | B21: NANGUEN MARTIN | C21: =D21+E21+F21-U21-BB21 -> 0 | D21: 30000 | E21: 0 | F21: 0 | G21: =IF(H21="ESPECES",3000,0) -> 0 | H21: =IF($D21<>0,"BANQUE",IF($E21<>0,"ESPECES","ECHEC")) -> BANQUE | I21: 1 | J21: =IF($D21<>0,I21*30000,IF($E21<>0,I21*30000,0)) -> 30000 | M21: =IF($D21<>0,L21*75000,IF($E21<>0,L21*75000,0)) -> 0 | O21: =IF($D21<>0,N21*100000,IF($E21<>0,N21*100000,0)) -> 0 | P21: 0 | U21: =G21+S21++R21+P21+O21+M21+K21+J21+Q21+V21+W21 -> 30000 | Z21: 500000 | AA21: BANQUE | AQ21: =IF(H21="ECHEC",((J21+M21+O21)*20/100),0) -> 0 | AR21: =IF(H21="ECHEC",((J21+M21+O21)*20/100),0) -> 0 | AS21: =IF(H21="ECHEC",0,(J21+K21-23000)) -> 7000 | AT21: 20000 | AW21: =IF(AC21=0,AI21,(1*23000*13)+(1000+AI21)-AC21) -> 0 | AX21: =IF(AD21=0,AJ21,(1*75000*16)+(AJ21)-AD21) -> 0 | AY21: =IF(AE21=0,AK21,(1*100000*13)+(AK21)-AE21) -> 0 | AZ21: =SUM(AV21:AY21)-BF21+Z21-F21+BH21+BI21+BJ21+BK21 -> 510000 | BD21: =IF(AZ21=0,(AZ21-BA21-BC21),(AZ21-BA21-BB21-BC21)) -> 510000 | BF21: =Z21*1/100*BG21 -> 60000 | BG21: 12 | BK21: 70000
A22: AS201621 | B22: NANKAM APPOLINAIRE | C22: =D22+E22+F22-U22-BB22 -> 0 | D22: 1105000 | E22: 0 | F22: 0 | G22: =IF(H22="ESPECES",3000,0) -> 0 | H22: =IF($D22<>0,"BANQUE",IF($E22<>0,"ESPECES","ECHEC")) -> BANQUE | I22: 1 | J22: =IF($D22<>0,I22*30000,IF($E22<>0,I22*30000,0)) -> 30000 | L22: 1 | M22: =IF($D22<>0,L22*75000,IF($E22<>0,L22*75000,0)) -> 75000 | O22: =IF($D22<>0,N22*100000,IF($E22<>0,N22*100000,0)) -> 0 | P22: 0 | Q22: 0 | S22: 1000000 | T22: BANQUE | U22: =G22+S22++R22+P22+O22+M22+K22+J22+Q22+V22+W22 -> 1105000 | Z22: 1000000 | AA22: BANQUE | AQ22: =IF(H22="ECHEC",((J22+M22+O22)*20/100),0) -> 0 | AR22: =IF(H22="ECHEC",((J22+M22+O22)*20/100),0) -> 0 | AS22: =IF(H22="ECHEC",0,(J22+K22-23000)) -> 7000 | AT22: 20000 | AW22: =IF(AC22=0,AI22,(1*23000*13)+(1000+AI22)-AC22) -> 0 | AX22: =IF(AD22=0,AJ22,(1*75000*16)+(AJ22)-AD22) -> 0 | AY22: =IF(AE22=0,AK22,(1*100000*13)+(AK22)-AE22) -> 0 | AZ22: =SUM(AV22:AY22)-BF22+Z22-F22+BH22+BI22+BJ22+BK22 -> 880000 | BD22: =IF(AZ22=0,(AZ22-BA22-BC22),(AZ22-BA22-BB22-BC22))+71000 -> 951000 | BF22: =Z22*1/100*BG22 -> 120000 | BG22: 12 | BN22: S/TOTAL | BP22: =SUM(BP18:BP21) -> 0
A23: AS201622 | B23: NDJOMO ETIENNE | C23: =D23+E23+F23-U23-BB23 -> 0 | D23: 680000 | E23: 101000 | F23: 0 | G23: =IF(H23="ESPECES",3000,0) -> 0 | H23: =IF($D23<>0,"BANQUE",IF($E23<>0,"ESPECES","ECHEC")) -> BANQUE | I23: 1 | J23: =IF($D23<>0,I23*30000,IF($E23<>0,I23*30000,0)) -> 30000 | K23: 20000 | M23: =IF($D23<>0,L23*75000,IF($E23<>0,L23*75000,0)) -> 0 | N23: 1 | O23: =IF($D23<>0,N23*100000,IF($E23<>0,N23*100000,0)) -> 100000 | P23: 0 | R23: 101000 | S23: =449000+81000 -> 530000 | T23: BANQUE | U23: =G23+S23++R23+P23+O23+M23+K23+J23+Q23+V23+W23 -> 781000 | Z23: 600000 | AA23: BANQUE | AP23: BANQUE | AQ23: =IF(H23="ECHEC",((J23+M23+O23)*20/100),0) -> 0 | AR23: =IF(H23="ECHEC",((J23+M23+O23)*20/100),0) -> 0 | AS23: =IF(H23="ECHEC",0,(J23+K23-23000)) -> 27000 | AT23: 20000 | AW23: =IF(AC23=0,AI23,(1*23000*13)+(1000+AI23)-AC23) -> 0 | AX23: =IF(AD23=0,AJ23,(1*75000*16)+(AJ23)-AD23) -> 0 | AY23: =IF(AE23=0,AK23,(1*100000*13)+(AK23)-AE23) -> 0 | AZ23: =SUM(AV23:AY23)-BF23+Z23-F23+BH23+BI23+BJ23+BK23 -> 552000 | BD23: =IF(AZ23=0,(AZ23-BA23-BC23),(AZ23-BA23-BB23-BC23)) -> 552000 | BF23: =Z23*1/100*BG23 -> 48000 | BG23: 8
A24: AS201624 | B24: NGONDIEP CLAUDE | C24: =D24+E24+F24-U24-BB24 -> 0 | D24: 1240000 | E24: 0 | F24: 0 | G24: =IF(H24="ESPECES",3000,0) -> 0 | H24: =IF($D24<>0,"BANQUE",IF($E24<>0,"ESPECES","ECHEC")) -> BANQUE | I24: 1 | J24: =IF($D24<>0,I24*30000,IF($E24<>0,I24*30000,0)) -> 30000 | K24: 35000 | L24: 1 | M24: =IF($D24<>0,L24*75000,IF($E24<>0,L24*75000,0)) -> 75000 | N24: 1 | O24: =IF($D24<>0,N24*100000,IF($E24<>0,N24*100000,0)) -> 100000 | P24: 0 | Q24: 0 | R24: 0 | S24: 1000000 | T24: BANQUE | U24: =G24+S24++R24+P24+O24+M24+K24+J24+Q24+V24+W24 -> 1240000 | Z24: 1000000 | AA24: BANQUE | AQ24: =IF(H24="ECHEC",((J24+M24+O24)*20/100),0) -> 0 | AR24: =IF(H24="ECHEC",((J24+M24+O24)*20/100),0) -> 0 | AS24: =IF(H24="ECHEC",0,(J24+K24-23000)) -> 42000 | AT24: 20000 | AW24: =IF(AC24=0,AI24,(1*23000*13)+(1000+AI24)-AC24) -> 0 | AX24: =IF(AD24=0,AJ24,(1*75000*16)+(AJ24)-AD24) -> 0 | AY24: =IF(AE24=0,AK24,(1*100000*13)+(AK24)-AE24) -> 0 | AZ24: =SUM(AV24:AY24)-BF24+Z24-F24+BH24+BI24+BJ24+BK24 -> 880000 | BD24: =IF(AZ24=0,(AZ24-BA24-BC24),(AZ24-BA24-BB24-BC24)) -> 880000 | BF24: =Z24*1/100*BG24 -> 120000 | BG24: 12 | BN24: GRATIFICATION BUREAU 2021 | BO24: FRAIS EXEPTIONNEL
A25: AS201626 | B25: NGUIEMEGNI MATHIEU BLAISE | C25: =D25+E25+F25-U25-BB25 -> 0 | D25: 1280000 | E25: 0 | F25: 0 | G25: =IF(H25="ESPECES",3000,0) -> 0 | H25: =IF($D25<>0,"BANQUE",IF($E25<>0,"ESPECES","ECHEC")) -> BANQUE | I25: 1 | J25: =IF($D25<>0,I25*30000,IF($E25<>0,I25*30000,0)) -> 30000 | L25: 2 | M25: =IF($D25<>0,L25*75000,IF($E25<>0,L25*75000,0)) -> 150000 | N25: 1 | O25: =IF($D25<>0,N25*100000,IF($E25<>0,N25*100000,0)) -> 100000 | P25: 0 | Q25: 0 | R25: 0 | S25: 1000000 | T25: BANQUE | U25: =G25+S25++R25+P25+O25+M25+K25+J25+Q25+V25+W25 -> 1280000 | Z25: 1000000 | AA25: BANQUE | AQ25: =IF(H25="ECHEC",((J25+M25+O25)*20/100),0) -> 0 | AR25: =IF(H25="ECHEC",((J25+M25+O25)*20/100),0) -> 0 | AS25: =IF(H25="ECHEC",0,(J25+K25-23000)) -> 7000 | AT25: 20000 | AW25: =IF(AC25=0,AI25,(1*23000*13)+(1000+AI25)-AC25) -> 0 | AX25: =IF(AD25=0,AJ25,(1*75000*16)+(AJ25)-AD25) -> 0 | AY25: =IF(AE25=0,AK25,(1*100000*13)+(AK25)-AE25) -> 0 | AZ25: =SUM(AV25:AY25)-BF25+Z25-F25+BH25+BI25+BJ25+BK25 -> 880000 | BD25: =IF(AZ25=0,(AZ25-BA25-BC25),(AZ25-BA25-BB25-BC25)) -> 880000 | BF25: =Z25*1/100*BG25 -> 120000 | BG25: 12 | BN25: DEVELOPPEMENT LAGWEU | BO25: FRAIS EXEPTIONNEL
A26: AS201628 | B26: NKAMGANG JUSTIN DEJOLIE | C26: =D26+E26+F26-U26-BB26 -> 0 | D26: 1105000 | E26: 79500 | F26: 0 | G26: =IF(H26="ESPECES",3000,0) -> 0 | H26: =IF($D26<>0,"BANQUE",IF($E26<>0,"ESPECES","ECHEC")) -> BANQUE | I26: 1 | J26: =IF($D26<>0,I26*30000,IF($E26<>0,I26*30000,0)) -> 30000 | L26: 1 | M26: =IF($D26<>0,L26*75000,IF($E26<>0,L26*75000,0)) -> 75000 | O26: =IF($D26<>0,N26*100000,IF($E26<>0,N26*100000,0)) -> 0 | P26: 41000 | Q26: 38500 | S26: 1000000 | T26: BANQUE | U26: =G26+S26++R26+P26+O26+M26+K26+J26+Q26+V26+W26 -> 1184500 | Z26: 1000000 | AA26: BANQUE | AP26: BANQUE | AQ26: =IF(H26="ECHEC",((J26+M26+O26)*20/100),0) -> 0 | AR26: =IF(H26="ECHEC",((J26+M26+O26)*20/100),0) -> 0 | AS26: =IF(H26="ECHEC",0,(J26+K26-23000)) -> 7000 | AT26: 20000 | AW26: =IF(AC26=0,AI26,(1*23000*13)+(1000+AI26)-AC26) -> 0 | AX26: =IF(AD26=0,AJ26,(1*75000*16)+(AJ26)-AD26) -> 0 | AY26: =IF(AE26=0,AK26,(1*100000*13)+(AK26)-AE26) -> 0 | AZ26: =SUM(AV26:AY26)-BF26+Z26-F26+BH26+BI26+BJ26+BK26 -> 980000 | BD26: =IF(AZ26=0,(AZ26-BA26-BC26),(AZ26-BA26-BB26-BC26)) -> 980000 | BF26: =Z26*1/100*BG26 -> 20000 | BG26: 2 | BN26: DEUIL TCHEMNOU EMMANUEL | BO26: FRAIS EXEPTIONNEL
A27: AS201614 | B27: NKEHE DAVID | C27: =D27+E27+F27-U27-BB27 -> 520000 | D27: 520000 | E27: 0 | F27: 0 | G27: =IF(H27="ESPECES",3000,0) -> 0 | H27: =IF($D27<>0,"BANQUE",IF($E27<>0,"ESPECES","ECHEC")) -> BANQUE | I27: 0 | J27: =IF($D27<>0,I27*30000,IF($E27<>0,I27*30000,0)) -> 0 | M27: =IF($D27<>0,L27*75000,IF($E27<>0,L27*75000,0)) -> 0 | N27: 0 | O27: =IF($D27<>0,N27*100000,IF($E27<>0,N27*100000,0)) -> 0 | U27: =G27+S27++R27+P27+O27+M27+K27+J27+Q27+V27+W27 -> 0 | AQ27: =IF(H27="ECHEC",((J27+M27+O27)*20/100),0) -> 0 | AR27: =IF(H27="ECHEC",((J27+M27+O27)*20/100),0) -> 0 | AS27: =IF(H27="ECHEC",0,(J27+K27)) -> 0 | AW27: =IF(AC27=0,AI27,(1*23000*13)+(1000+AI27)-AC27) -> 0 | AX27: =IF(AD27=0,AJ27,(1*75000*16)+(AJ27)-AD27) -> 0 | AY27: =IF(AE27=0,AK27,(1*100000*13)+(AK27)-AE27) -> 0 | AZ27: =SUM(AV27:AY27)-BF27+Z27-F27+BH27+BI27+BJ27+BK27 -> 0 | BD27: =IF(AZ27=0,(AZ27-BA27-BC27),(AZ27-BA27-BB27-BC27)) -> 0 | BF27: =Z27*1/100*BG27 -> 0 | BG27: 0
A28: AS201629 | B28: NKEPSEU DIEUDONNE | C28: =D28+E28+F28-U28-BB28 -> 0 | D28: 1130000 | E28: 0 | F28: 0 | G28: =IF(H28="ESPECES",3000,0) -> 0 | H28: =IF($D28<>0,"BANQUE",IF($E28<>0,"ESPECES","ECHEC")) -> BANQUE | I28: 1 | J28: =IF($D28<>0,I28*30000,IF($E28<>0,I28*30000,0)) -> 30000 | M28: =IF($D28<>0,L28*75000,IF($E28<>0,L28*75000,0)) -> 0 | N28: 1 | O28: =IF($D28<>0,N28*100000,IF($E28<>0,N28*100000,0)) -> 100000 | P28: 0 | R28: 0 | S28: =600000+400000 -> 1000000 | T28: BANQUE | U28: =G28+S28++R28+P28+O28+M28+K28+J28+Q28+V28+W28 -> 1130000 | AQ28: =IF(H28="ECHEC",((J28+M28+O28)*20/100),0) -> 0 | AR28: =IF(H28="ECHEC",((J28+M28+O28)*20/100),0) -> 0 | AS28: =IF(H28="ECHEC",0,(J28+K28-23000)) -> 7000 | AT28: 20000 | AW28: =IF(AC28=0,AI28,(1*23000*13)+(1000+AI28)-AC28) -> 0 | AX28: =IF(AD28=0,AJ28,(1*75000*16)+(AJ28)-AD28) -> 0 | AY28: =IF(AE28=0,AK28,(1*100000*13)+(AK28)-AE28) -> 0 | AZ28: =SUM(AV28:AY28)-BF28+Z28-F28+BH28+BI28+BJ28+BK28 -> 0 | BD28: =IF(AZ28=0,(AZ28-BA28-BC28),(AZ28-BA28-BB28-BC28)) -> 0 | BF28: =Z28*1/100*BG28 -> 0 | BG28: 0 | BN28: S/TOTAL | BP28: =SUM(BP24:BP26) -> 0
A29: AS201633 | B29: PATEGO NJOSSU GUSTAVE | C29: =D29+E29+F29-U29-BB29 -> 0 | D29: 105000 | E29: 0 | F29: 0 | G29: =IF(H29="ESPECES",3000,0) -> 0 | H29: =IF($D29<>0,"BANQUE",IF($E29<>0,"ESPECES","ECHEC")) -> BANQUE | I29: 1 | J29: =IF($D29<>0,I29*30000,IF($E29<>0,I29*30000,0)) -> 30000 | L29: 1 | M29: =IF($D29<>0,L29*75000,IF($E29<>0,L29*75000,0)) -> 75000 | O29: =IF($D29<>0,N29*100000,IF($E29<>0,N29*100000,0)) -> 0 | P29: 0 | Q29: 0 | U29: =G29+S29++R29+P29+O29+M29+K29+J29+Q29+V29+W29 -> 105000 | AQ29: =IF(H29="ECHEC",((J29+M29+O29)*20/100),0) -> 0 | AR29: =IF(H29="ECHEC",((J29+M29+O29)*20/100),0) -> 0 | AS29: =IF(H29="ECHEC",0,(J29+K29-23000)) -> 7000 | AT29: 20000 | AW29: =IF(AC29=0,AI29,(1*23000*13)+(1000+AI29)-AC29) -> 0 | AX29: =IF(AD29=0,AJ29,(1*75000*16)+(AJ29)-AD29) -> 0 | AY29: =IF(AE29=0,AK29,(1*100000*13)+(AK29)-AE29) -> 0 | AZ29: =SUM(AV29:AY29)-BF29+Z29-F29+BH29+BI29+BJ29+BK29 -> 0 | BD29: =IF(AZ29=0,(AZ29-BA29-BC29),(AZ29-BA29-BB29-BC29)) -> 0 | BF29: =Z29*1/100*BG29 -> 0 | BG29: 0
A30: AS201653 | B30: SIME BRICE | C30: =D30+E30+F30-U30-BB30 -> -100000 | D30: 105000 | E30: 0 | F30: 0 | G30: =IF(H30="ESPECES",3000,0) -> 0 | H30: =IF($D30<>0,"BANQUE",IF($E30<>0,"ESPECES","ECHEC")) -> BANQUE | I30: 1 | J30: =IF($D30<>0,I30*30000,IF($E30<>0,I30*30000,0)) -> 30000 | L30: 1 | M30: =IF($D30<>0,L30*75000,IF($E30<>0,L30*75000,0)) -> 75000 | O30: =IF($D30<>0,N30*100000,IF($E30<>0,N30*100000,0)) -> 0 | P30: 0 | Q30: 0 | U30: =G30+S30++R30+P30+O30+M30+K30+J30+Q30+V30+W30 -> 105000 | AC30: 23000 | AF30: BANQUE | AQ30: =IF(H30="ECHEC",((J30+M30+O30)*20/100),0) -> 0 | AR30: =IF(H30="ECHEC",((J30+M30+O30)*20/100),0) -> 0 | AS30: =IF(H30="ECHEC",0,(J30+K30-23000)) -> 7000 | AT30: 20000 | AW30: =IF(AC30=0,AI30,(1*23000*13)+(1000+AI30)-AC30) -> 277000 | AX30: =IF(AD30=0,AJ30,(1*75000*16)+(AJ30)-AD30) -> 0 | AY30: =IF(AE30=0,AK30,(1*100000*13)+(AK30)-AE30) -> 0 | AZ30: =SUM(AV30:AY30)-BF30+Z30-F30+BH30+BI30+BJ30+BK30 -> 277000 | BB30: 100000 | BD30: =IF(AZ30=0,(AZ30-BA30-BC30),(AZ30-BA30-BB30-BC30)) -> 177000 | BF30: =Z30*1/100*BG30 -> 0 | BG30: 0 | BN30: DECES | BO30: MUTUELLE
A31: AS201636 | B31: SIMO FONGANG ERIC | C31: =D31+E31+F31-U31-BB31 -> 0 | D31: 0 | E31: 0 | F31: 0 | G31: =IF(H31="ESPECES",3000,0) -> 0 | H31: =IF($D31<>0,"BANQUE",IF($E31<>0,"ESPECES","ECHEC")) -> ECHEC | J31: =IF($D31<>0,I31*30000,IF($E31<>0,I31*30000,0)) -> 0 | M31: =IF($D31<>0,L31*75000,IF($E31<>0,L31*75000,0)) -> 0 | O31: =IF($D31<>0,N31*100000,IF($E31<>0,N31*100000,0)) -> 0 | U31: =G31+S31++R31+P31+O31+M31+K31+J31+Q31+V31+W31 -> 0 | AQ31: =IF(H31="ECHEC",((J31+M31+O31)*20/100),0) -> 0 | AR31: =IF(H31="ECHEC",((J31+M31+O31)*20/100),0) -> 0 | AS31: =IF(H31="ECHEC",0,(J31+K31-23000)) -> 0 | AT31: 20000 | AW31: =IF(AC31=0,AI31,(1*23000*13)+(1000+AI31)-AC31) -> 0 | AX31: =IF(AD31=0,AJ31,(1*75000*16)+(AJ31)-AD31) -> 0 | AY31: =IF(AE31=0,AK31,(1*100000*13)+(AK31)-AE31) -> 0 | AZ31: =SUM(AV31:AY31)-BF31+Z31-F31+BH31+BI31+BJ31+BK31 -> 0 | BD31: =IF(AZ31=0,(AZ31-BA31-BC31),(AZ31-BA31-BB31-BC31)) -> 0 | BF31: =Z31*1/100*BG31 -> 0 | BG31: 0 | BN31: TRANSPORT DELEGUE | BO31: MUTUELLE
A32: AS201638 | B32: SIMO PIERRE | C32: =D32+E32+F32-U32-BB32 -> 0 | D32: 905000 | E32: 0 | F32: 0 | G32: =IF(H32="ESPECES",3000,0) -> 0 | H32: =IF($D32<>0,"BANQUE",IF($E32<>0,"ESPECES","ECHEC")) -> BANQUE | I32: 1 | J32: =IF($D32<>0,I32*30000,IF($E32<>0,I32*30000,0)) -> 30000 | L32: 1 | M32: =IF($D32<>0,L32*75000,IF($E32<>0,L32*75000,0)) -> 75000 | O32: =IF($D32<>0,N32*100000,IF($E32<>0,N32*100000,0)) -> 0 | P32: 0 | Q32: 0 | S32: =395000+378000+27000 -> 800000 | T32: BANQUE | U32: =G32+S32++R32+P32+O32+M32+K32+J32+Q32+V32+W32 -> 905000 | Z32: 1000000 | AA32: BANQUE | AQ32: =IF(H32="ECHEC",((J32+M32+O32)*20/100),0) -> 0 | AR32: =IF(H32="ECHEC",((J32+M32+O32)*20/100),0) -> 0 | AS32: =IF(H32="ECHEC",0,(J32+K32-23000)) -> 7000 | AT32: 20000 | AW32: =IF(AC32=0,AI32,(1*23000*13)+(1000+AI32)-AC32) -> 0 | AX32: =IF(AD32=0,AJ32,(1*75000*16)+(AJ32)-AD32) -> 0 | AY32: =IF(AE32=0,AK32,(1*100000*13)+(AK32)-AE32) -> 0 | AZ32: =SUM(AV32:AY32)-BF32+Z32-F32+BH32+BI32+BJ32+BK32 -> 880000 | BD32: =IF(AZ32=0,(AZ32-BA32-BC32),(AZ32-BA32-BB32-BC32)) -> 880000 | BF32: =Z32*1/100*BG32 -> 120000 | BG32: 12
A33: AS201641 | B33: TCHOUAMOU MATHIEU | C33: =D33+E33+F33-U33-BB33 -> 0 | D33: 1030000 | E33: 0 | F33: 0 | G33: =IF(H33="ESPECES",3000,0) -> 0 | H33: =IF($D33<>0,"BANQUE",IF($E33<>0,"ESPECES","ECHEC")) -> BANQUE | I33: 1 | J33: =IF($D33<>0,I33*30000,IF($E33<>0,I33*30000,0)) -> 30000 | M33: =IF($D33<>0,L33*75000,IF($E33<>0,L33*75000,0)) -> 0 | O33: =IF($D33<>0,N33*100000,IF($E33<>0,N33*100000,0)) -> 0 | P33: 0 | S33: 1000000 | T33: BANQUE | U33: =G33+S33++R33+P33+O33+M33+K33+J33+Q33+V33+W33 -> 1030000 | Z33: 1000000 | AA33: BANQUE | AQ33: =IF(H33="ECHEC",((J33+M33+O33)*20/100),0) -> 0 | AR33: =IF(H33="ECHEC",((J33+M33+O33)*20/100),0) -> 0 | AS33: =IF(H33="ECHEC",0,(J33+K33-23000)) -> 7000 | AT33: 20000 | AW33: =IF(AC33=0,AI33,(1*23000*13)+(1000+AI33)-AC33) -> 0 | AX33: =IF(AD33=0,AJ33,(1*75000*16)+(AJ33)-AD33) -> 0 | AY33: =IF(AE33=0,AK33,(1*100000*13)+(AK33)-AE33) -> 0 | AZ33: =SUM(AV33:AY33)-BF33+Z33-F33+BH33+BI33+BJ33+BK33 -> 970000 | BD33: =IF(AZ33=0,(AZ33-BA33-BC33),(AZ33-BA33-BB33-BC33)) -> 970000 | BF33: =Z33*1/100*BG33 -> 30000 | BG33: 3 | BN33: S/TOTAL | BP33: =SUM(BP30:BP32) -> 0
A34: AS201644 | B34: TIEYAM ERNEST | C34: =D34+E34+F34-U34-BB34 -> 0 | D34: 0 | E34: 0 | F34: 0 | G34: =IF(H34="ESPECES",3000,0) -> 0 | H34: =IF($D34<>0,"BANQUE",IF($E34<>0,"ESPECES","ECHEC")) -> ECHEC | I34: 0 | J34: =IF($D34<>0,I34*30000,IF($E34<>0,I34*30000,0)) -> 0 | M34: =IF($D34<>0,L34*75000,IF($E34<>0,L34*75000,0)) -> 0 | N34: 0 | O34: =IF($D34<>0,N34*100000,IF($E34<>0,N34*100000,0)) -> 0 | U34: =G34+S34++R34+P34+O34+M34+K34+J34+Q34+V34+W34 -> 0 | AQ34: =IF(H34="ECHEC",((J34+M34+O34)*20/100),0) -> 0 | AR34: =IF(H34="ECHEC",((J34+M34+O34)*20/100),0) -> 0 | AS34: =IF(H34="ECHEC",0,(J34+K34)) -> 0 | AW34: =IF(AC34=0,AI34,(1*23000*13)+(1000+AI34)-AC34) -> 0 | AX34: =IF(AD34=0,AJ34,(1*75000*16)+(AJ34)-AD34) -> 0 | AY34: =IF(AE34=0,AK34,(1*100000*13)+(AK34)-AE34) -> 0 | AZ34: =SUM(AV34:AY34)-BF34+Z34-F34+BH34+BI34+BJ34+BK34 -> 0 | BD34: =IF(AZ34=0,(AZ34-BA34-BC34),(AZ34-BA34-BB34-BC34)) -> 0 | BF34: =Z34*1/100*BG34 -> 0 | BG34: 0
A35: AS201646 | B35: YEPMOU JEAN JACQUES | C35: =D35+E35+F35-U35-BB35 -> 0 | D35: 1041250 | E35: 0 | F35: 0 | G35: =IF(H35="ESPECES",3000,0) -> 0 | H35: =IF($D35<>0,"BANQUE",IF($E35<>0,"ESPECES","ECHEC")) -> BANQUE | I35: 1 | J35: =IF($D35<>0,I35*30000,IF($E35<>0,I35*30000,0)) -> 30000 | M35: =IF($D35<>0,L35*75000,IF($E35<>0,L35*75000,0)) -> 0 | O35: =IF($D35<>0,N35*100000,IF($E35<>0,N35*100000,0)) -> 0 | P35: 0 | S35: 1011250 | T35: BANQUE | U35: =G35+S35++R35+P35+O35+M35+K35+J35+Q35+V35+W35 -> 1041250 | AQ35: =IF(H35="ECHEC",((J35+M35+O35)*20/100),0) -> 0 | AR35: =IF(H35="ECHEC",((J35+M35+O35)*20/100),0) -> 0 | AS35: =IF(H35="ECHEC",0,(J35+K35-23000)) -> 7000 | AT35: 20000 | AW35: =IF(AC35=0,AI35,(1*23000*13)+(1000+AI35)-AC35) -> 0 | AX35: =IF(AD35=0,AJ35,(1*75000*16)+(AJ35)-AD35) -> 0 | AY35: =IF(AE35=0,AK35,(1*100000*13)+(AK35)-AE35) -> 0 | AZ35: =SUM(AV35:AY35)-BF35+Z35-F35+BH35+BI35+BJ35+BK35 -> 0 | BD35: =IF(AZ35=0,(AZ35-BA35-BC35),(AZ35-BA35-BB35-BC35)) -> 0 | BF35: =Z35*1/100*BG35 -> 0 | BG35: 0 | BN35: COLLATION | BO35: COLLATION
A36: AS201647 | B36: YOUMBI EMMANUEL | C36: =D36+E36+F36-U36-BB36 -> 0 | D36: 280000 | E36: 0 | F36: 0 | G36: =IF(H36="ESPECES",3000,0) -> 0 | H36: =IF($D36<>0,"BANQUE",IF($E36<>0,"ESPECES","ECHEC")) -> BANQUE | I36: 1 | J36: =IF($D36<>0,I36*30000,IF($E36<>0,I36*30000,0)) -> 30000 | L36: 2 | M36: =IF($D36<>0,L36*75000,IF($E36<>0,L36*75000,0)) -> 150000 | N36: 1 | O36: =IF($D36<>0,N36*100000,IF($E36<>0,N36*100000,0)) -> 100000 | P36: 0 | Q36: 0 | R36: 0 | U36: =G36+S36++R36+P36+O36+M36+K36+J36+Q36+V36+W36 -> 280000 | AQ36: =IF(H36="ECHEC",((J36+M36+O36)*20/100),0) -> 0 | AR36: =IF(H36="ECHEC",((J36+M36+O36)*20/100),0) -> 0 | AS36: =IF(H36="ECHEC",0,(J36+K36-23000)) -> 7000 | AT36: 20000 | AW36: =IF(AC36=0,AI36,(1*23000*13)+(1000+AI36)-AC36) -> 0 | AX36: =IF(AD36=0,AJ36,(1*75000*16)+(AJ36)-AD36) -> 0 | AY36: =IF(AE36=0,AK36,(1*100000*13)+(AK36)-AE36) -> 0 | AZ36: =SUM(AV36:AY36)-BF36+Z36-F36+BH36+BI36+BJ36+BK36 -> 0 | BD36: =IF(AZ36=0,(AZ36-BA36-BC36),(AZ36-BA36-BB36-BC36)) -> 0 | BF36: =Z36*1/100*BG36 -> 0 | BG36: 0 | BN36: BOISSON | BO36: COLLATION
B38: TOTAUX | C38: =SUM(C6:C37) -> 420000 | D38: =SUM(D6:D37) -> 20433750 | E38: =SUM(E6:E37) -> 180500 | F38: =SUM(F6:F37) -> 0 | G38: =SUM(G6:G37) -> 0 | H38: =SUM(H6:H37) -> 0 | I38: =SUM(I6:I37) -> 26 | J38: =SUM(J6:J37) -> 780000 | ... BD38: =SUM(BD6:BD37) -> 17269000 | BF38: =SUM(BF6:BF37) -> 1248000 | BH38: =SUM(BH6:BH37) -> 6000 | BI38: =SUM(BI6:BI37) -> 0 | BJ38: =SUM(BJ6:BJ37) -> 0 | BK38: =SUM(BK6:BK37) -> 70000 | BL38: =SUM(BL6:BL37) -> 0 | BM38: =SUM(BM6:BM37) -> 0 | BN38: S/TOTAL | BP38: =SUM(BP35:BP37) -> 0
C42: BANQUE | F42: ESPECES
B43: LIBELLE | C43: SORTIE | D43: ENTREE | E43: SOLDE | F43: ENTREE | G43: SORTIE | H43: SOLDE
B44: REPORT
B45: TONTINE | C45: =AZ38 -> 17307000 | D45: =SUMIFS(D7:D38,H7:H38,"BANQUE") -> 20333750 | F45: =E38 -> 180500
AZ83: =SUM(AZ7:AZ82) -> 33408000

Sheet HISTODEC24
A1: ASSOCIATION | B1: ASELBY
A2: ANNEE | B2: 2024
A3: 1 | B3: 2 | C3: 3 | D3: 4 | E3: 5 | F3: 6 | G3: 7 | H3: 8 | I3: 9 | J3: 10 | K3: 11 | L3: 12 | M3: 13 | N3: 14 | O3: 15 | P3: 16 | Q3: 17 | R3: 18 | S3: 19 | T3: 20 | U3: 21 | V3: 22 | W3: 23 | X3: 24 | Y3: 25 | Z3: 26 | AA3: 27 | AB3: 28 | AC3: 29 | AD3: 30 | AE3: 31 | AF3: 32 | AG3: 33 | AH3: 34 | AI3: 35 | AJ3: 36 | AK3: 37 | AL3: 38 | AM3: 39 | AN3: 40 | AO3: 41 | AP3: 42 | AQ3: 43 | AR3: 44 | AS3: 45 | AT3: 46 | AU3: 47 | AV3: 48 | AW3: 49 | AX3: 50 | AY3: 51 | AZ3: 52 | BA3: 53 | BB3: 54 | BC3: 55 | BD3: 56 | BE3: 57 | BF3: 58 | BG3: 59 | BH3: 60 | BI3: 61 | BJ3: 62 | BK3: 63 | BL3: 64 | BM3: 65 | BO3: 66 | BP3: 67 | BQ3: 68
B4: TABLEAU DE BORD SAISIE DES DONNEES
A5: MATRICULE | B5: NOM ET PRENOM | C5: BONUS MALUS | D5: HISTORIQUE BANQUE | E5: HITORIQUE ESPECES | F5: HITORIQUE TONTINE | G5: PENALITE VERSEMENT ESPECES | H5: MODE PAIEMENT TONTINE | I5: COMPLEMENT EPARGNE | J5: NBRE DE LOT | K5: TONTINE 40 000 | L5: NBRE DE LOT | M5: TONTINE 75 000 | N5: NBRE DE LOT | O5: TONTINE 100 000 | P5: REMBOURSEMENT PETIT LOT T50 | Q5: REMBOURSEMENT PETIT LOT T75 | R5: REMBOURSEMENT PETIT LOT T100 | S5: REMBOURSEMENT PRÊT FONDS | T5: MODE PAIEMENT REMBOURSEMENT PRÊT FONDS | U5: MONTANT ENGAGEMENT | V5: SANCTION | W5: INSCRIPTION | X5: EPARGNE ASSURANCE | Y5: RECONSTITUTION FONDS | Z5: PRÊT FONDS | AA5: MODE PAIEMENT PRÊT | AB5: NUM CHEQUE | AC5: ACHAT LOT PRINCIPAL T50 | AD5: ACHAT LOT PRINCIPAL T75 | AE5: ACHAT LOT PRINCIPAL T100 | AF5: MODE PAIEMENT LOT PRINCIPAL | AG5: NUM CHEQUE | AH5: PENALITE VERSEMENT ESPECES | AI5: VENTE PETIT LOT T50 | AJ5: VENTE PETIT LOT T75 | AK5: VENTE PETIT LOT T100 | AL5: INTERET PETIT LOT T50 | AM5: INTERET PETIT LOT T75 | AN5: INTERET PETIT LOT T100 | AO5: NUM CHEQUE | AP5: MODE PAIEMENT PETIT LOT | AQ5: PENELAITE RETARD TONTINE | AR5: PENELAITE ECHEC TONTINE | AS5: RESTE | AT5: MUTUELLE | AU5: REMBOURSEMENT TRANSPORT | AV5: RETRAIT PARTIEL FONDS | AW5: MONTANT T50 | AX5: MONTANT T75 | AY5: MONTANT T100 | AZ5: MONTANT CHEQUE | BA5: MONTANT ESPECES | BB5: CONTRIBUTION FOYER | BC5: AUTRES SOTIES | BD5: MONTANT CHEQUE EFFECTIF | BE5: NUMERO CHEQUE | BF5: INTERET PRÊT | BG5: NBRE MOIS | BH5: DEPENSE FONDS DE ROULEMENT | BI5: DEPENSE FRAIS EXCEPTIONNEL | BJ5: DEPENSE FONDS MUTUEL | BK5: DEPENSE COLLATION RECEPTION | BL5: PENALITE PRET FONDS | BM5: DEPENSE PENALITE VERSEMENT BANQUE | BN5: AUTRES DEPENSES | BO5: LIBELLE | BP5: COMPTE | BQ5: MONTANT | BR5: COMPLEMENT TONTINE | BS5: PLUS VALUE
A6: AS201648 | B6: =VLOOKUP(A6,[5]LISTADHERENT!A$5:H$50,3,0) -> ASELBY | C6: =D6+E6+F6-U6-BB6 -> -61000 | D6: 175000 | E6: 0 | F6: 0 | G6: 0 | H6: =IF($D6<>0,"BANQUE",IF($E6<>0,"ESPECES","ECHEC")) -> BANQUE | I6: 61000 | K6: =IF($D6<>0,J6*50000,IF($E6<>0,J6*50000,0)) -> 0 | L6: 1 | M6: =IF($D6<>0,L6*75000,IF($E6<>0,L6*75000,0)) -> 75000 | N6: 1 | O6: =IF($D6<>0,N6*100000,IF($E6<>0,N6*100000,0)) -> 100000 | P6: 0 | Q6: 0 | R6: 0 | U6: =G6+S6++R6+P6+O6+M6+I6+K6+Q6+V6+W6 -> 236000 | AD6: 7500 | AE6: 10000 | AQ6: =IF(H6="ECHEC",((K6+M6+O6)*20/100),0) -> 0 | AR6: =IF(H6="ECHEC",((K6+M6+O6)*20/100),0) -> 0 | AW6: =IF(AC6=0,AI6,(1*25000*12)+AI6-AC6) -> 0 | AX6: =IF(AD6=0,AJ6,(1*75000*12)+(AJ6)-AD6) -> 892500 | AY6: =IF(AE6=0,AK6,(1*100000*12)+(AK6)-AE6) -> 1190000 | AZ6: =SUM(AV6:AY6)-BF6+Z6-F6+BH6+BI6+BJ6+BK6+BL6+BM6-2082500 -> 4031000 | BA6: 31000 | BD6: =IF(AZ6=0,(AZ6-BA6-BC6),(AZ6-BA6-BB6-BC6))+BN6 -> 5026618 | BF6: =Z6*1/100*BG6 -> 0 | BG6: 12 | BH6: =BQ17 -> 4031000 | BI6: =BQ30 -> 0 | BJ6: =BQ36 -> 0 | BN6: =+BQ24 -> 1026618 | BO6: ACHAT FOURNITURE | BP6: FONDS DE ROULEMENT | BR6: -175000 | BS6: =IF(BR6>0,BR6,0) -> 0
A7: AS201601 | B7: =VLOOKUP(A7,[5]LISTADHERENT!A$5:H$50,3,0) -> BAKOP ACHILLE | C7: =D7+E7+F7-U7-BB7 -> 0 | D7: 0 | E7: 50000 | F7: 0 | G7: 0 | H7: =IF($D7<>0,"BANQUE",IF($E7<>0,"ESPECES","ECHEC")) -> ESPECES | J7: 1 | K7: =IF($D7<>0,J7*50000,IF($E7<>0,J7*50000,0)) -> 50000 | M7: =IF($D7<>0,L7*75000,IF($E7<>0,L7*75000,0)) -> 0 | O7: =IF($D7<>0,N7*100000,IF($E7<>0,N7*100000,0)) -> 0 | P7: 0 | Q7: 0 | R7: 0 | U7: =G7+S7++R7+P7+O7+M7+I7+K7+Q7+V7+W7 -> 50000 | AQ7: =IF(H7="ECHEC",((K7+M7+O7)*20/100),0) -> 0 | AR7: =IF(H7="ECHEC",((K7+M7+O7)*20/100),0) -> 0 | AS7: =IF(H7="ECHEC",0,(K7+I7-25000)) -> 25000 | AW7: =IF(AC7=0,AI7,(1*25000*12)+AI7-AC7) -> 0 | AX7: =IF(AD7=0,AJ7,(1*75000*12)+(AJ7)-AD7) -> 0 | AY7: =IF(AE7=0,AK7,(1*100000*12)+(AK7)-AE7) -> 0 | AZ7: =SUM(AV7:AY7)-BF7+Z7-F7+BH7+BI7+BJ7+BK7+BL7+BM7+93000 -> 93000 | BD7: =IF(AZ7=0,(AZ7-BA7-BC7),(AZ7-BA7-BB7-BC7)) -> 93000 | BF7: =Z7*1/100*BG7+93000-93000 -> 0 | BG7: 12 | BO7: COMMUNICATION | BP7: FONDS DE ROULEMENT | BR7: 0 | BS7: =IF(BR7>0,BR7,0) -> 0
A8: AS201602 | B8: =VLOOKUP(A8,[5]LISTADHERENT!A$5:H$50,3,0) -> BOUTCHOUANG WILLIAM | C8: =D8+E8+F8-U8-BB8 -> 0 | D8: 125000 | E8: 500000 | F8: 0 | G8: 0 | H8: =IF($D8<>0,"BANQUE",IF($E8<>0,"ESPECES","ECHEC")) -> BANQUE | J8: 1 | K8: =IF($D8<>0,J8*50000,IF($E8<>0,J8*50000,0)) -> 50000 | L8: 1 | M8: =IF($D8<>0,L8*75000,IF($E8<>0,L8*75000,0)) -> 75000 | O8: =IF($D8<>0,N8*100000,IF($E8<>0,N8*100000,0)) -> 0 | P8: 0 | Q8: 0 | R8: 0 | S8: 500000 | U8: =G8+S8++R8+P8+O8+M8+I8+K8+Q8+V8+W8 -> 625000 | Z8: 500000 | AQ8: =IF(H8="ECHEC",((K8+M8+O8)*20/100),0) -> 0 | AR8: =IF(H8="ECHEC",((K8+M8+O8)*20/100),0) -> 0 | AS8: =IF(H8="ECHEC",0,(K8+I8-25000)) -> 25000 | AW8: =IF(AC8=0,AI8,(1*25000*12)+AI8-AC8) -> 0 | AX8: =IF(AD8=0,AJ8,(1*75000*12)+(AJ8)-AD8) -> 0 | AY8: =IF(AE8=0,AK8,(1*100000*12)+(AK8)-AE8) -> 0 | AZ8: =SUM(AV8:AY8)-BF8+Z8-F8+BH8+BI8+BJ8+BK8+BL8+BM8 -> 485000 | BA8: 440000 | BD8: =IF(AZ8=0,(AZ8-BA8-BC8),(AZ8-BA8-BB8-BC8)) -> 45000 | BF8: =Z8*1/100*BG8 -> 15000 | BG8: 3 | BO8: COMMISSION | BP8: FONDS DE ROULEMENT | BQ8: 25000 | BR8: 0 | BS8: =IF(BR8>0,BR8,0) -> 0
A9: AS201604 | B9: =VLOOKUP(A9,[5]LISTADHERENT!A$5:H$50,3,0) -> DJOMO JEAN PAUL | C9: =D9+E9+F9-U9-BB9+1000 -> 500000 | D9: 250000 | E9: 1600000 | F9: 0 | G9: 0 | H9: =IF($D9<>0,"BANQUE",IF($E9<>0,"ESPECES","ECHEC")) -> BANQUE | J9: 1 | K9: =IF($D9<>0,J9*50000,IF($E9<>0,J9*50000,0)) -> 50000 | M9: =IF($D9<>0,L9*75000,IF($E9<>0,L9*75000,0)) -> 0 | N9: 2 | O9: =IF($D9<>0,N9*100000,IF($E9<>0,N9*100000,0)) -> 200000 | P9: 0 | Q9: 0 | R9: 101000 | S9: 1000000 | U9: =G9+S9++R9+P9+O9+M9+I9+K9+Q9+V9+W9 -> 1351000 | Z9: 1000000 | AQ9: =IF(H9="ECHEC",((K9+M9+O9)*20/100),0) -> 0 | AR9: =IF(H9="ECHEC",((K9+M9+O9)*20/100),0) -> 0 | AS9: =IF(H9="ECHEC",0,(K9+I9-25000)) -> 25000 | AW9: =IF(AC9=0,AI9,(1*25000*12)+AI9-AC9) -> 0 | AX9: =IF(AD9=0,AJ9,(1*75000*12)+(AJ9)-AD9) -> 0 | AY9: =IF(AE9=0,AK9,(1*100000*12)+(AK9)-AE9) -> 0 | AZ9: =SUM(AV9:AY9)-BF9+Z9-F9+BH9+BI9+BJ9+BK9+BL9+BM9 -> 880000 | BA9: 880000 | BD9: =IF(AZ9=0,(AZ9-BA9-BC9),(AZ9-BA9-BB9-BC9)) -> 0 | BF9: =Z9*1/100*BG9 -> 120000 | BG9: 12 | BO9: OUVERTURE COMPTE | BP9: FONDS DE ROULEMENT | BR9: 0 | BS9: =IF(BR9>0,BR9,0) -> 0
A10: AS201654 | B10: =VLOOKUP(A10,[5]LISTADHERENT!A$5:H$50,3,0) -> DJOMOU TCHAPDA | C10: =D10+E10+F10-U10-BB10 -> -11000 | D10: 0 | E10: 1307000 | F10: 0 | G10: 0 | H10: =IF($D10<>0,"BANQUE",IF($E10<>0,"ESPECES","ECHEC")) -> ESPECES | J10: 1 | K10: =IF($D10<>0,J10*50000,IF($E10<>0,J10*50000,0)) -> 50000 | L10: 1 | M10: =IF($D10<>0,L10*75000,IF($E10<>0,L10*75000,0)) -> 75000 | O10: =IF($D10<>0,N10*100000,IF($E10<>0,N10*100000,0)) -> 0 | P10: 61000 | Q10: 132000 | R10: 0 | S10: 1000000 | U10: =G10+S10++R10+P10+O10+M10+I10+K10+Q10+V10+W10 -> 1318000 | Z10: 1000000 | AQ10: =IF(H10="ECHEC",((K10+M10+O10)*20/100),0) -> 0 | AR10: =IF(H10="ECHEC",((K10+M10+O10)*20/100),0) -> 0 | AS10: =IF(H10="ECHEC",0,(K10+I10-25000)) -> 25000 | AW10: =IF(AC10=0,AI10,(1*25000*12)+AI10-AC10) -> 0 | AX10: =IF(AD10=0,AJ10,(1*75000*12)+(AJ10)-AD10) -> 0 | AY10: =IF(AE10=0,AK10,(1*100000*12)+(AK10)-AE10) -> 0 | AZ10: =SUM(AV10:AY10)-BF10+Z10-F10+BH10+BI10+BJ10+BK10+BL10+BM10 -> 880000 | BD10: =IF(AZ10=0,(AZ10-BA10-BC10),(AZ10-BA10-BB10-BC10)) -> 880000 | BE10: OK | BF10: =Z10*1/100*BG10 -> 120000 | BG10: 12 | BO10: CREDIT TELEPHONE | BP10: FONDS DE ROULEMENT | BR10: 0 | BS10: =IF(BR10>0,BR10,0) -> 0
A11: AS201605 | B11: =VLOOKUP(A11,[5]LISTADHERENT!A$5:H$50,3,0) -> DJOUKWE NANGUEN GUY BLAISE | C11: =D11+E11+F11-U11-BB11 -> 0 | D11: 0 | E11: 228000 | F11: 0 | G11: 0 | H11: =IF($D11<>0,"BANQUE",IF($E11<>0,"ESPECES","ECHEC")) -> ESPECES | J11: 1 | K11: =IF($D11<>0,J11*50000,IF($E11<>0,J11*50000,0)) -> 50000 | L11: 1 | M11: =IF($D11<>0,L11*75000,IF($E11<>0,L11*75000,0)) -> 75000 | O11: =IF($D11<>0,N11*100000,IF($E11<>0,N11*100000,0)) -> 0 | P11: 0 | Q11: 103000 | R11: 0 | U11: =G11+S11++R11+P11+O11+M11+I11+K11+Q11+V11+W11 -> 228000 | Z11: 1135000 | AQ11: =IF(H11="ECHEC",((K11+M11+O11)*20/100),0) -> 0 | AR11: =IF(H11="ECHEC",((K11+M11+O11)*20/100),0) -> 0 | AS11: =IF(H11="ECHEC",0,(K11+I11-25000)) -> 25000 | AW11: =IF(AC11=0,AI11,(1*25000*12)+AI11-AC11) -> 0 | AX11: =IF(AD11=0,AJ11,(1*75000*12)+(AJ11)-AD11) -> 0 | AY11: =IF(AE11=0,AK11,(1*100000*12)+(AK11)-AE11) -> 0 | AZ11: =SUM(AV11:AY11)-BF11+Z11-F11+BH11+BI11+BJ11+BK11+BL11+BM11 -> 1135000 | BD11: =IF(AZ11=0,(AZ11-BA11-BC11),(AZ11-BA11-BB11-BC11)) -> 1135000 | BF11: =Z11*1/100*BG11 -> 0 | BG11: 0 | BO11: PRODUCTION RAPPORT | BP11: FONDS DE ROULEMENT | BR11: 0 | BS11: =IF(BR11>0,BR11,0) -> 0
A12: AS201608 | B12: =VLOOKUP(A12,[5]LISTADHERENT!A$5:H$50,3,0) -> DJUOMBESSY ANTOINE | C12: =D12+E12+F12-U12-BB12 -> 0 | D12: 400000 | E12: 637500 | F12: 0 | G12: 0 | H12: =IF($D12<>0,"BANQUE",IF($E12<>0,"ESPECES","ECHEC")) -> BANQUE | I12: 5000 | J12: 1 | K12: =IF($D12<>0,J12*50000,IF($E12<>0,J12*50000,0)) -> 50000 | L12: 1 | M12: =IF($D12<>0,L12*75000,IF($E12<>0,L12*75000,0)) -> 75000 | N12: 2 | O12: =IF($D12<>0,N12*100000,IF($E12<>0,N12*100000,0)) -> 200000 | P12: 61000 | Q12: 101500 | R12: 505000 | S12: 40000 | U12: =G12+S12++R12+P12+O12+M12+I12+K12+Q12+V12+W12 -> 1037500 | Z12: 1000000 | AQ12: =IF(H12="ECHEC",((K12+M12+O12)*20/100),0) -> 0 | AR12: =IF(H12="ECHEC",((K12+M12+O12)*20/100),0) -> 0 | AS12: =IF(H12="ECHEC",0,(K12+I12-25000)) -> 30000 | AW12: =IF(AC12=0,AI12,(1*25000*12)+AI12-AC12) -> 0 | AX12: =IF(AD12=0,AJ12,(1*75000*12)+(AJ12)-AD12) -> 0 | AY12: =IF(AE12=0,AK12,(1*100000*12)+(AK12)-AE12) -> 0 | AZ12: =SUM(AV12:AY12)-BF12+Z12-F12+BH12+BI12+BJ12+BK12+BL12+BM12 -> 940000 | BA12: 940000 | BD12: =IF(AZ12=0,(AZ12-BA12-BC12),(AZ12-BA12-BB12-BC12)) -> 0 | BF12: =Z12*1/100*BG12 -> 60000 | BG12: 6 | BO12: ACHAT SOURIS ET PHOTOCOPIE | BP12: FONDS DE ROULEMENT | BR12: 0 | BS12: =IF(BR12>0,BR12,0) -> 0
A13: AS201651 | B13: =VLOOKUP(A13,[5]LISTADHERENT!A$5:H$50,3,0) -> DOMOU FABIEN | C13: =D13+E13+F13-U13-BB13 -> 0 | D13: 1050000 | E13: 0 | F13: 0 | G13: 0 | H13: =IF($D13<>0,"BANQUE",IF($E13<>0,"ESPECES","ECHEC")) -> BANQUE | J13: 1 | K13: =IF($D13<>0,J13*50000,IF($E13<>0,J13*50000,0)) -> 50000 | M13: =IF($D13<>0,L13*75000,IF($E13<>0,L13*75000,0)) -> 0 | O13: =IF($D13<>0,N13*100000,IF($E13<>0,N13*100000,0)) -> 0 | P13: 0 | Q13: 0 | R13: 0 | S13: 1000000 | U13: =G13+S13++R13+P13+O13+M13+I13+K13+Q13+V13+W13 -> 1050000 | AQ13: =IF(H13="ECHEC",((K13+M13+O13)*20/100),0) -> 0 | AR13: =IF(H13="ECHEC",((K13+M13+O13)*20/100),0) -> 0 | AS13: =IF(H13="ECHEC",0,(K13+I13-25000)) -> 25000 | AW13: =IF(AC13=0,AI13,(1*25000*12)+AI13-AC13) -> 0 | AX13: =IF(AD13=0,AJ13,(1*75000*12)+(AJ13)-AD13) -> 0 | AY13: =IF(AE13=0,AK13,(1*100000*12)+(AK13)-AE13) -> 0 | AZ13: =SUM(AV13:AY13)-BF13+Z13-F13+BH13+BI13+BJ13+BK13+BL13+BM13 -> 0 | BD13: =IF(AZ13=0,(AZ13-BA13-BC13),(AZ13-BA13-BB13-BC13)) -> 0 | BF13: =Z13*1/100*BG13 -> 0 | BG13: 12 | BO13: TAXI BANQUE | BP13: FONDS DE ROULEMENT | BQ13: 6000 | BR13: 1000000 | BS13: =IF(BR13>0,BR13,0) -> 1000000
A14: AS201609 | B14: =VLOOKUP(A14,[5]LISTADHERENT!A$5:H$50,3,0) -> DONHOU DAVID | C14: =D14+E14+F14-U14-BB14 -> 0 | D14: 50000 | E14: 0 | F14: 0 | G14: 0 | H14: =IF($D14<>0,"BANQUE",IF($E14<>0,"ESPECES","ECHEC")) -> BANQUE | J14: 1 | K14: =IF($D14<>0,J14*50000,IF($E14<>0,J14*50000,0)) -> 50000 | M14: =IF($D14<>0,L14*75000,IF($E14<>0,L14*75000,0)) -> 0 | O14: =IF($D14<>0,N14*100000,IF($E14<>0,N14*100000,0)) -> 0 | P14: 0 | Q14: 0 | R14: 0 | U14: =G14+S14++R14+P14+O14+M14+I14+K14+Q14+V14+W14 -> 50000 | AQ14: =IF(H14="ECHEC",((K14+M14+O14)*20/100),0) -> 0 | AR14: =IF(H14="ECHEC",((K14+M14+O14)*20/100),0) -> 0 | AS14: =IF(H14="ECHEC",0,(K14+I14-25000)) -> 25000 | AW14: =IF(AC14=0,AI14,(1*25000*12)+AI14-AC14) -> 0 | AX14: =IF(AD14=0,AJ14,(1*75000*12)+(AJ14)-AD14) -> 0 | AY14: =IF(AE14=0,AK14,(1*100000*12)+(AK14)-AE14) -> 0 | AZ14: =SUM(AV14:AY14)-BF14+Z14-F14+BH14+BI14+BJ14+BK14+BL14+BM14 -> 0 | BD14: =IF(AZ14=0,(AZ14-BA14-BC14),(AZ14-BA14-BB14-BC14)) -> 0 | BF14: =Z14*1/100*BG14 -> 0 | BG14: 12 | BO14: ACHAT TERRAIN | BP14: FONDS DE ROULEMENT | BQ14: 4000000 | BR14: 0 | BS14: =IF(BR14>0,BR14,0) -> 0
A15: AS201663 | B15: =VLOOKUP(A15,[5]LISTADHERENT!A$5:H$50,3,0) -> FAMPOU PAUL | BF15: =Z15*1/100*BG15 -> 0
A16: AS201611 | B16: =VLOOKUP(A16,[5]LISTADHERENT!A$5:H$50,3,0) -> HENGUE PAUL OMER | C16: =D16+E16+F16-U16-BB16 -> 0 | D16: 0 | E16: 125000 | F16: 0 | G16: 0 | H16: =IF($D16<>0,"BANQUE",IF($E16<>0,"ESPECES","ECHEC")) -> ESPECES | J16: 1 | K16: =IF($D16<>0,J16*50000,IF($E16<>0,J16*50000,0)) -> 50000 | L16: 1 | M16: =IF($D16<>0,L16*75000,IF($E16<>0,L16*75000,0)) -> 75000 | O16: =IF($D16<>0,N16*100000,IF($E16<>0,N16*100000,0)) -> 0 | P16: 0 | Q16: 0 | R16: 0 | U16: =G16+S16++R16+P16+O16+M16+I16+K16+Q16+V16+W16 -> 125000 | Z16: 1050000 | AQ16: =IF(H16="ECHEC",((K16+M16+O16)*20/100),0) -> 0 | AR16: =IF(H16="ECHEC",((K16+M16+O16)*20/100),0) -> 0 | AS16: =IF(H16="ECHEC",0,(K16+I16-25000)) -> 25000 | AW16: =IF(AC16=0,AI16,(1*25000*12)+AI16-AC16) -> 0 | AX16: =IF(AD16=0,AJ16,(1*75000*12)+(AJ16)-AD16) -> 0 | AY16: =IF(AE16=0,AK16,(1*100000*12)+(AK16)-AE16) -> 0 | AZ16: =SUM(AV16:AY16)-BF16+Z16-F16+BH16+BI16+BJ16+BK16+BL16+BM16 -> 1050000 | BD16: =IF(AZ16=0,(AZ16-BA16-BC16),(AZ16-BA16-BB16-BC16)) -> 1050000 | BF16: =Z16*1/100*BG16 -> 0 | BG16: 0 | BR16: 0 | BS16: =IF(BR16>0,BR16,0) -> 0
A17: AS201613 | B17: =VLOOKUP(A17,[5]LISTADHERENT!A$5:H$50,3,0) -> HOTCHO BENJAMIN | C17: =D17+E17+F17-U17-BB17 -> -530000 | D17: 952000 | E17: 202000 | F17: 0 | G17: 0 | H17: =IF($D17<>0,"BANQUE",IF($E17<>0,"ESPECES","ECHEC")) -> BANQUE | I17: =15000+40000 -> 55000 | J17: 1 | K17: =IF($D17<>0,J17*50000,IF($E17<>0,J17*50000,0)) -> 50000 | L17: 1 | M17: =IF($D17<>0,L17*75000,IF($E17<>0,L17*75000,0)) -> 75000 | N17: 1 | O17: =IF($D17<>0,N17*100000,IF($E17<>0,N17*100000,0)) -> 100000 | P17: 0 | Q17: 202000 | R17: 202000 | S17: 1000000 | U17: =G17+S17++R17+P17+O17+M17+I17+K17+Q17+V17+W17 -> 1684000 | AQ17: =IF(H17="ECHEC",((K17+M17+O17)*20/100),0) -> 0 | AR17: =IF(H17="ECHEC",((K17+M17+O17)*20/100),0) -> 0 | AS17: =IF(H17="ECHEC",0,(K17+I17-25000)) -> 80000 | AW17: =IF(AC17=0,AI17,(1*25000*12)+AI17-AC17) -> 0 | AX17: =IF(AD17=0,AJ17,(1*75000*12)+(AJ17)-AD17) -> 0 | AY17: =IF(AE17=0,AK17,(1*100000*12)+(AK17)-AE17) -> 0 | AZ17: =SUM(AV17:AY17)-BF17+Z17-F17+BH17+BI17+BJ17+BK17+BL17+BM17 -> 0 | BD17: =IF(AZ17=0,(AZ17-BA17-BC17),(AZ17-BA17-BB17-BC17)) -> 0 | BF17: =Z17*1/100*BG17 -> 0 | BG17: 12 | BO17: S/TOTAL | BQ17: =SUM(BQ6:BQ16) -> 4031000 | BR17: 0 | BS17: =IF(BR17>0,BR17,0) -> 0
A18: AS201617 | B18: =VLOOKUP(A18,[5]LISTADHERENT!A$5:H$50,3,0) -> KOUAMOU MOISE | C18: =D18+E18+F18-U18-BB18 -> -170000 | D18: 260000 | E18: 0 | F18: 0 | G18: 0 | H18: =IF($D18<>0,"BANQUE",IF($E18<>0,"ESPECES","ECHEC")) -> BANQUE | I18: 5500 | J18: 1 | K18: =IF($D18<>0,J18*50000,IF($E18<>0,J18*50000,0)) -> 50000 | M18: =IF($D18<>0,L18*75000,IF($E18<>0,L18*75000,0)) -> 0 | N18: 1 | O18: =IF($D18<>0,N18*100000,IF($E18<>0,N18*100000,0)) -> 100000 | P18: 0 | Q18: 0 | R18: 104500 | S18: 170000 | U18: =G18+S18++R18+P18+O18+M18+I18+K18+Q18+V18+W18 -> 430000 | Z18: 346500 | AQ18: =IF(H18="ECHEC",((K18+M18+O18)*20/100),0) -> 0 | AR18: =IF(H18="ECHEC",((K18+M18+O18)*20/100),0) -> 0 | AS18: =IF(H18="ECHEC",0,(K18+I18-25000)) -> 30500 | AW18: =IF(AC18=0,AI18,(1*25000*12)+AI18-AC18) -> 0 | AX18: =IF(AD18=0,AJ18,(1*75000*12)+(AJ18)-AD18) -> 0 | AY18: =IF(AE18=0,AK18,(1*100000*12)+(AK18)-AE18) -> 0 | AZ18: =SUM(AV18:AY18)-BF18+Z18-F18+BH18+BI18+BJ18+BK18+BL18+BM18 -> 346500 | BD18: =IF(AZ18=0,(AZ18-BA18-BC18),(AZ18-BA18-BB18-BC18)) -> 346500 | BF18: =Z18*1/100*BG18 -> 0 | BG18: 0 | BR18: 110000 | BS18: =IF(BR18>0,BR18,0) -> 110000
A19: AS201619 | B19: =VLOOKUP(A19,[5]LISTADHERENT!A$5:H$50,3,0) -> KOUATCHO MESSACK | C19: =D19+E19+F19-U19-BB19 -> 0 | D19: 611000 | E19: 0 | F19: 0 | G19: 0 | H19: =IF($D19<>0,"BANQUE",IF($E19<>0,"ESPECES","ECHEC")) -> BANQUE | I19: 10000 | J19: 1 | K19: =IF($D19<>0,J19*50000,IF($E19<>0,J19*50000,0)) -> 50000 | M19: =IF($D19<>0,L19*75000,IF($E19<>0,L19*75000,0)) -> 0 | N19: 1 | O19: =IF($D19<>0,N19*100000,IF($E19<>0,N19*100000,0)) -> 100000 | P19: 0 | Q19: 0 | R19: 101000 | S19: 350000 | U19: =G19+S19++R19+P19+O19+M19+I19+K19+Q19+V19+W19 -> 611000 | Z19: 1000000 | AQ19: =IF(H19="ECHEC",((K19+M19+O19)*20/100),0) -> 0 | AR19: =IF(H19="ECHEC",((K19+M19+O19)*20/100),0) -> 0 | AS19: =IF(H19="ECHEC",0,(K19+I19-25000)) -> 35000 | AW19: =IF(AC19=0,AI19,(1*25000*12)+AI19-AC19) -> 0 | AX19: =IF(AD19=0,AJ19,(1*75000*12)+(AJ19)-AD19) -> 0 | AY19: =IF(AE19=0,AK19,(1*100000*12)+(AK19)-AE19) -> 0 | AZ19: =SUM(AV19:AY19)-BF19+Z19-F19+BH19+BI19+BJ19+BK19+BL19+BM19 -> 880000 | BD19: =IF(AZ19=0,(AZ19-BA19-BC19),(AZ19-BA19-BB19-BC19)) -> 880000 | BE19: OK | BF19: =Z19*1/100*BG19 -> 120000 | BG19: 12 | BO19: TERRAIN NYOM | BP19: AUTRES DEPENSES | BQ19: 1026618 | BR19: 461000 | BS19: =IF(BR19>0,BR19,0) -> 461000
A20: AS201620 | B20: =VLOOKUP(A20,[5]LISTADHERENT!A$5:H$50,3,0) -> LOWE JEAN
A21: AS201661 | B21: =VLOOKUP(A21,[5]LISTADHERENT!A$5:H$50,3,0) -> MASSEUNGOUE DAGOBERT | C21: =D21+E21+F21-U21-BB21 -> -487500 | D21: 50000 | E21: 0 | F21: 0 | G21: 0 | H21: =IF($D21<>0,"BANQUE",IF($E21<>0,"ESPECES","ECHEC")) -> BANQUE | I21: 297500 | J21: 1 | K21: =IF($D21<>0,J21*50000,IF($E21<>0,J21*50000,0)) -> 50000 | M21: =IF($D21<>0,L21*75000,IF($E21<>0,L21*75000,0)) -> 0 | O21: =IF($D21<>0,N21*100000,IF($E21<>0,N21*100000,0)) -> 0 | P21: 0 | Q21: 0 | R21: 0 | U21: =G21+S21++R21+P21+O21+M21+I21+K21+Q21+V21+W21 -> 347500 | AC21: 2500 | AQ21: =IF(H21="ECHEC",((K21+M21+O21)*20/100),0) -> 0 | AR21: =IF(H21="ECHEC",((K21+M21+O21)*20/100),0) -> 0 | AS21: =IF(H21="ECHEC",0,(K21+I21-25000)) -> 322500 | AW21: =IF(AC21=0,AI21,(1*25000*12)+AI21-AC21) -> 297500 | AX21: =IF(AD21=0,AJ21,(1*75000*12)+(AJ21)-AD21) -> 0 | AY21: =IF(AE21=0,AK21,(1*100000*12)+(AK21)-AE21) -> 0 | AZ21: =SUM(AV21:AY21)-BF21+Z21-F21+BH21+BI21+BJ21+BK21+BL21+BM21 -> 297500 | BA21: 297500 | BB21: 190000 | BF21: =Z21*1/100*BG21 -> 0 | BG21: 12 | BR21: 0 | BS21: =IF(BR21>0,BR21,0) -> 0
A22: AS201649 | B22: =VLOOKUP(A22,[5]LISTADHERENT!A$5:H$50,3,0) -> MBOGNING TUGMA GUY | C22: =D22+E22+F22-U22-BB22 -> -66700 | D22: 225000 | E22: 1536000 | F22: 0 | G22: 0 | H22: =IF($D22<>0,"BANQUE",IF($E22<>0,"ESPECES","ECHEC")) -> BANQUE | J22: 1 | K22: =IF($D22<>0,J22*50000,IF($E22<>0,J22*50000,0)) -> 50000 | L22: 1 | M22: =IF($D22<>0,L22*75000,IF($E22<>0,L22*75000,0)) -> 75000 | N22: 1 | O22: =IF($D22<>0,N22*100000,IF($E22<>0,N22*100000,0)) -> 100000 | P22: 132000 | Q22: 202000 | R22: 202000 | S22: 1000000 | U22: =G22+S22++R22+P22+O22+M22+I22+K22+Q22+V22+W22 -> 1761000 | Z22: 1000000 | AQ22: =IF(H22="ECHEC",((K22+M22+O22)*20/100),0) -> 0 | AR22: =IF(H22="ECHEC",((K22+M22+O22)*20/100),0) -> 0 | AS22: =IF(H22="ECHEC",0,(K22+I22-25000)) -> 25000 | AW22: =IF(AC22=0,AI22,(1*25000*12)+AI22-AC22) -> 0 | AX22: =IF(AD22=0,AJ22,(1*75000*12)+(AJ22)-AD22) -> 0 | AY22: =IF(AE22=0,AK22,(1*100000*12)+(AK22)-AE22) -> 0 | AZ22: =SUM(AV22:AY22)-BF22+Z22-F22+BH22+BI22+BJ22+BK22+BL22+BM22 -> 970000 | BA22: 970000 | BB22: 66700 | BF22: =Z22*1/100*BG22 -> 30000 | BG22: 3 | BR22: 0 | BS22: =IF(BR22>0,BR22,0) -> 0
A23: AS201639 | B23: =VLOOKUP(A23,[5]LISTADHERENT!A$5:H$50,3,0) -> NANGUEN MARTIN | C23: =D23+E23+F23-U23-BB23 -> -283500 | D23: 0 | E23: 66500 | F23: 0 | G23: 0 | H23: =IF($D23<>0,"BANQUE",IF($E23<>0,"ESPECES","ECHEC")) -> ESPECES | J23: 1 | K23: =IF($D23<>0,J23*50000,IF($E23<>0,J23*50000,0)) -> 50000 | M23: =IF($D23<>0,L23*75000,IF($E23<>0,L23*75000,0)) -> 0 | O23: =IF($D23<>0,N23*100000,IF($E23<>0,N23*100000,0)) -> 0 | P23: 0 | Q23: 0 | R23: 0 | S23: =296500+3500 -> 300000 | U23: =G23+S23++R23+P23+O23+M23+I23+K23+Q23+V23+W23 -> 350000 | AQ23: =IF(H23="ECHEC",((K23+M23+O23)*20/100),0) -> 0 | AR23: =IF(H23="ECHEC",((K23+M23+O23)*20/100),0) -> 0 | AS23: =IF(H23="ECHEC",0,(K23+I23-25000)) -> 25000 | AW23: =IF(AC23=0,AI23,(1*25000*12)+AI23-AC23) -> 0 | AX23: =IF(AD23=0,AJ23,(1*75000*12)+(AJ23)-AD23) -> 0 | AY23: =IF(AE23=0,AK23,(1*100000*12)+(AK23)-AE23) -> 0 | AZ23: =SUM(AV23:AY23)-BF23+Z23-F23+BH23+BI23+BJ23+BK23+BL23+BM23+46500 -> 46500 | BD23: =IF(AZ23=0,(AZ23-BA23-BC23),(AZ23-BA23-BB23-BC23)) -> 46500 | BF23: =Z23*1/100*BG23+46500-46500 -> 0 | BG23: 12 | BR23: 0 | BS23: =IF(BR23>0,BR23,0) -> 0
A24: AS201621 | B24: =VLOOKUP(A24,[5]LISTADHERENT!A$5:H$50,3,0) -> NANKAM APPOLINAIRE | C24: =D24+E24+F24-U24-BB24 -> -107500 | D24: 125000 | E24: 0 | F24: 0 | G24: 0 | H24: =IF($D24<>0,"BANQUE",IF($E24<>0,"ESPECES","ECHEC")) -> BANQUE | J24: 1 | K24: =IF($D24<>0,J24*50000,IF($E24<>0,J24*50000,0)) -> 50000 | L24: 1 | M24: =IF($D24<>0,L24*75000,IF($E24<>0,L24*75000,0)) -> 75000 | O24: =IF($D24<>0,N24*100000,IF($E24<>0,N24*100000,0)) -> 0 | P24: 0 | Q24: 0 | R24: 0 | S24: 107500 | U24: =G24+S24++R24+P24+O24+M24+I24+K24+Q24+V24+W24 -> 232500 | Z24: 900000 | AQ24: =IF(H24="ECHEC",((K24+M24+O24)*20/100),0) -> 0 | AR24: =IF(H24="ECHEC",((K24+M24+O24)*20/100),0) -> 0 | AS24: =IF(H24="ECHEC",0,(K24+I24-25000)) -> 25000 | AW24: =IF(AC24=0,AI24,(1*25000*12)+AI24-AC24) -> 0 | AX24: =IF(AD24=0,AJ24,(1*75000*12)+(AJ24)-AD24) -> 0 | AY24: =IF(AE24=0,AK24,(1*100000*12)+(AK24)-AE24) -> 0 | AZ24: =SUM(AV24:AY24)-BF24+Z24-F24+BH24+BI24+BJ24+BK24+BL24+BM24 -> 792000 | BD24: =IF(AZ24=0,(AZ24-BA24-BC24),(AZ24-BA24-BB24-BC24)) -> 792000 | BE24: OK | BF24: =Z24*1/100*BG24 -> 108000 | BG24: 12 | BO24: S/TOTAL | BQ24: =SUM(BQ19:BQ23) -> 1026618 | BR24: 0 | BS24: =IF(BR24>0,BR24,0) -> 0
A25: AS201622 | B25: =VLOOKUP(A25,[5]LISTADHERENT!A$5:H$50,3,0) -> NDJOMO ETIENNE | C25: =D25+E25+F25-U25-BB25 -> 0 | D25: 1164000 | E25: 0 | F25: 0 | G25: 0 | H25: =IF($D25<>0,"BANQUE",IF($E25<>0,"ESPECES","ECHEC")) -> BANQUE | I25: 10000 | J25: 1 | K25: =IF($D25<>0,J25*50000,IF($E25<>0,J25*50000,0)) -> 50000 | M25: =IF($D25<>0,L25*75000,IF($E25<>0,L25*75000,0)) -> 0 | N25: 2 | O25: =IF($D25<>0,N25*100000,IF($E25<>0,N25*100000,0)) -> 200000 | P25: 0 | Q25: 0 | R25: 404000 | S25: 500000 | U25: =G25+S25++R25+P25+O25+M25+I25+K25+Q25+V25+W25 -> 1164000 | Z25: 500000 | AQ25: =IF(H25="ECHEC",((K25+M25+O25)*20/100),0) -> 0 | AR25: =IF(H25="ECHEC",((K25+M25+O25)*20/100),0) -> 0 | AS25: =IF(H25="ECHEC",0,(K25+I25-25000)) -> 35000 | AW25: =IF(AC25=0,AI25,(1*25000*12)+AI25-AC25) -> 0 | AX25: =IF(AD25=0,AJ25,(1*75000*12)+(AJ25)-AD25) -> 0 | AY25: =IF(AE25=0,AK25,(1*100000*12)+(AK25)-AE25) -> 0 | AZ25: =SUM(AV25:AY25)-BF25+Z25-F25+BH25+BI25+BJ25+BK25+BL25+BM25 -> 470000 | BD25: =IF(AZ25=0,(AZ25-BA25-BC25),(AZ25-BA25-BB25-BC25)) -> 470000 | BE25: OK | BF25: =Z25*1/100*BG25 -> 30000 | BG25: 6 | BR25: 904000 | BS25: =IF(BR25>0,BR25,0) -> 904000
A26: AS201624 | B26: =VLOOKUP(A26,[5]LISTADHERENT!A$5:H$50,3,0) -> NGONDIEP CLAUDE | C26: =D26+E26+F26-U26-BB26 -> 0 | D26: 442000 | E26: 500000 | F26: 0 | G26: 0 | H26: =IF($D26<>0,"BANQUE",IF($E26<>0,"ESPECES","ECHEC")) -> BANQUE | I26: 13000 | J26: 1 | K26: =IF($D26<>0,J26*50000,IF($E26<>0,J26*50000,0)) -> 50000 | L26: 1 | M26: =IF($D26<>0,L26*75000,IF($E26<>0,L26*75000,0)) -> 75000 | N26: 1 | O26: =IF($D26<>0,N26*100000,IF($E26<>0,N26*100000,0)) -> 100000 | P26: 0 | Q26: 0 | R26: 204000 | S26: 500000 | U26: =G26+S26++R26+P26+O26+M26+I26+K26+Q26+V26+W26 -> 942000 | AQ26: =IF(H26="ECHEC",((K26+M26+O26)*20/100),0) -> 0 | AR26: =IF(H26="ECHEC",((K26+M26+O26)*20/100),0) -> 0 | AS26: =IF(H26="ECHEC",0,(K26+I26-25000)) -> 38000 | AW26: =IF(AC26=0,AI26,(1*25000*12)+AI26-AC26) -> 0 | AX26: =IF(AD26=0,AJ26,(1*75000*12)+(AJ26)-AD26) -> 0 | AY26: =IF(AE26=0,AK26,(1*100000*12)+(AK26)-AE26) -> 0 | AZ26: =SUM(AV26:AY26)-BF26+Z26-F26+BH26+BI26+BJ26+BK26+BL26+BM26 -> 0 | BD26: =IF(AZ26=0,(AZ26-BA26-BC26),(AZ26-BA26-BB26-BC26)) -> 0 | BF26: =Z26*1/100*BG26 -> 0 | BG26: 12 | BO26: GRATIFICATION BUREAU 2021 | BP26: FRAIS EXEPTIONNEL | BR26: 0 | BS26: =IF(BR26>0,BR26,0) -> 0
A27: AS201626 | B27: =VLOOKUP(A27,[5]LISTADHERENT!A$5:H$50,3,0) -> NGUIEMEGNI MATHIEU BLAISE | C27: =D27+E27+F27-U27-BB27 -> -1000000 | D27: 375000 | E27: 0 | F27: 0 | G27: 0 | H27: =IF($D27<>0,"BANQUE",IF($E27<>0,"ESPECES","ECHEC")) -> BANQUE | J27: 1 | K27: =IF($D27<>0,J27*50000,IF($E27<>0,J27*50000,0)) -> 50000 | L27: 3 | M27: =IF($D27<>0,L27*75000,IF($E27<>0,L27*75000,0)) -> 225000 | N27: 1 | O27: =IF($D27<>0,N27*100000,IF($E27<>0,N27*100000,0)) -> 100000 | P27: 0 | Q27: 0 | R27: 0 | S27: 1000000 | U27: =G27+S27++R27+P27+O27+M27+I27+K27+Q27+V27+W27 -> 1375000 | Z27: 1000000 | AQ27: =IF(H27="ECHEC",((K27+M27+O27)*20/100),0) -> 0 | AR27: =IF(H27="ECHEC",((K27+M27+O27)*20/100),0) -> 0 | AS27: =IF(H27="ECHEC",0,(K27+I27-25000)) -> 25000 | AW27: =IF(AC27=0,AI27,(1*25000*12)+AI27-AC27) -> 0 | AX27: =IF(AD27=0,AJ27,(1*75000*12)+(AJ27)-AD27) -> 0 | AY27: =IF(AE27=0,AK27,(1*100000*12)+(AK27)-AE27) -> 0 | AZ27: =SUM(AV27:AY27)-BF27+Z27-F27+BH27+BI27+BJ27+BK27+BL27+BM27 -> 880000 | BD27: =IF(AZ27=0,(AZ27-BA27-BC27),(AZ27-BA27-BB27-BC27)) -> 880000 | BE27: OK | BF27: =Z27*1/100*BG27 -> 120000 | BG27: 12 | BO27: DEVELOPPEMENT LAGWEU | BP27: FRAIS EXEPTIONNEL | BR27: 0 | BS27: =IF(BR27>0,BR27,0) -> 0
A28: AS201628 | B28: =VLOOKUP(A28,[5]LISTADHERENT!A$5:H$50,3,0) -> NKAMGANG JUSTIN DEJOLIE | C28: =D28+E28+F28-U28-BB28 -> 0 | D28: 0 | E28: 1050000 | F28: 0 | G28: 0 | H28: =IF($D28<>0,"BANQUE",IF($E28<>0,"ESPECES","ECHEC")) -> ESPECES | J28: 1 | K28: =IF($D28<>0,J28*50000,IF($E28<>0,J28*50000,0)) -> 50000 | M28: =IF($D28<>0,L28*75000,IF($E28<>0,L28*75000,0)) -> 0 | O28: =IF($D28<>0,N28*100000,IF($E28<>0,N28*100000,0)) -> 0 | P28: 0 | Q28: 0 | R28: 0 | S28: 1000000 | U28: =G28+S28++R28+P28+O28+M28+I28+K28+Q28+V28+W28 -> 1050000 | Z28: 1000000 | AQ28: =IF(H28="ECHEC",((K28+M28+O28)*20/100),0) -> 0 | AR28: =IF(H28="ECHEC",((K28+M28+O28)*20/100),0) -> 0 | AS28: =IF(H28="ECHEC",0,(K28+I28-25000)) -> 25000 | AW28: =IF(AC28=0,AI28,(1*25000*12)+AI28-AC28) -> 0 | AX28: =IF(AD28=0,AJ28,(1*75000*12)+(AJ28)-AD28) -> 0 | AY28: =IF(AE28=0,AK28,(1*100000*12)+(AK28)-AE28) -> 0 | AZ28: =SUM(AV28:AY28)-BF28+Z28-F28+BH28+BI28+BJ28+BK28+BL28+BM28 -> 970000 | BA28: 144500 | BD28: =IF(AZ28=0,(AZ28-BA28-BC28),(AZ28-BA28-BB28-BC28)) -> 825500 | BE28: OK | BF28: =Z28*1/100*BG28 -> 30000 | BG28: 3 | BO28: DEUIL TCHEMNOU EMMANUEL | BP28: FRAIS EXEPTIONNEL | BR28: 0 | BS28: =IF(BR28>0,BR28,0) -> 0
A29: AS201656 | B29: =VLOOKUP(A29,[5]LISTADHERENT!A$5:H$50,3,0) -> NOUBE ETIENNE | C29: =D29+E29+F29-U29-BB29 -> -50000 | D29: 50000 | E29: 0 | F29: 0 | G29: 0 | H29: =IF($D29<>0,"BANQUE",IF($E29<>0,"ESPECES","ECHEC")) -> BANQUE | J29: 1 | K29: =IF($D29<>0,J29*50000,IF($E29<>0,J29*50000,0)) -> 50000 | M29: =IF($D29<>0,L29*75000,IF($E29<>0,L29*75000,0)) -> 0 | O29: =IF($D29<>0,N29*100000,IF($E29<>0,N29*100000,0)) -> 0 | P29: 0 | Q29: 0 | R29: 0 | S29: 50000 | U29: =G29+S29++R29+P29+O29+M29+I29+K29+Q29+V29+W29 -> 100000 | AQ29: =IF(H29="ECHEC",((K29+M29+O29)*20/100),0) -> 0 | AR29: =IF(H29="ECHEC",((K29+M29+O29)*20/100),0) -> 0 | AS29: =IF(H29="ECHEC",0,(K29+I29-25000)) -> 25000 | AW29: =IF(AC29=0,AI29,(1*25000*12)+AI29-AC29) -> 0 | AX29: =IF(AD29=0,AJ29,(1*75000*12)+(AJ29)-AD29) -> 0 | AY29: =IF(AE29=0,AK29,(1*100000*12)+(AK29)-AE29) -> 0 | AZ29: =SUM(AV29:AY29)-BF29+Z29-F29+BH29+BI29+BJ29+BK29+BL29+BM29+7750 -> 7750 | BD29: =IF(AZ29=0,(AZ29-BA29-BC29),(AZ29-BA29-BB29-BC29)) -> 7750 | BF29: =Z29*1/100*BG29+7750-7750 -> 0 | BG29: 3 | BR29: 0 | BS29: =IF(BR29>0,BR29,0) -> 0
A30: AS201633 | B30: =VLOOKUP(A30,[5]LISTADHERENT!A$5:H$50,3,0) -> PATEGO NJOSSU GUSTAVE | C30: =D30+E30+F30-U30-BB30 -> -27000 | D30: 125000 | E30: 0 | F30: 0 | G30: 0 | H30: =IF($D30<>0,"BANQUE",IF($E30<>0,"ESPECES","ECHEC")) -> BANQUE | I30: 27000 | J30: 1 | K30: =IF($D30<>0,J30*50000,IF($E30<>0,J30*50000,0)) -> 50000 | L30: 1 | M30: =IF($D30<>0,L30*75000,IF($E30<>0,L30*75000,0)) -> 75000 | O30: =IF($D30<>0,N30*100000,IF($E30<>0,N30*100000,0)) -> 0 | P30: 0 | Q30: 0 | R30: 0 | U30: =G30+S30++R30+P30+O30+M30+I30+K30+Q30+V30+W30 -> 152000 | AQ30: =IF(H30="ECHEC",((K30+M30+O30)*20/100),0) -> 0 | AR30: =IF(H30="ECHEC",((K30+M30+O30)*20/100),0) -> 0 | AS30: =IF(H30="ECHEC",0,(K30+I30-25000)) -> 52000 | AW30: =IF(AC30=0,AI30,(1*25000*12)+AI30-AC30) -> 0 | AX30: =IF(AD30=0,AJ30,(1*75000*12)+(AJ30)-AD30) -> 0 | AY30: =IF(AE30=0,AK30,(1*100000*12)+(AK30)-AE30) -> 0 | AZ30: =SUM(AV30:AY30)-BF30+Z30-F30+BH30+BI30+BJ30+BK30+BL30+BM30 -> 0 | BD30: =IF(AZ30=0,(AZ30-BA30-BC30),(AZ30-BA30-BB30-BC30)) -> 0 | BF30: =Z30*1/100*BG30 -> 0 | BG30: 12 | BO30: S/TOTAL | BQ30: =SUM(BQ26:BQ28) -> 0 | BR30: 0 | BS30: =IF(BR30>0,BR30,0) -> 0
A31: AS201657 | B31: =VLOOKUP(A31,[5]LISTADHERENT!A$5:H$50,3,0) -> SEUMO POLYCARPE | C31: =D31+E31+F31-U31-BB31 -> -115000 | D31: 110000 | E31: 0 | F31: 0 | G31: 0 | H31: =IF($D31<>0,"BANQUE",IF($E31<>0,"ESPECES","ECHEC")) -> BANQUE | I31: -1000 | J31: 1 | K31: =IF($D31<>0,J31*50000,IF($E31<>0,J31*50000,0)) -> 50000 | M31: =IF($D31<>0,L31*75000,IF($E31<>0,L31*75000,0)) -> 0 | O31: =IF($D31<>0,N31*100000,IF($E31<>0,N31*100000,0)) -> 0 | P31: 61000 | Q31: 0 | R31: 0 | U31: =G31+S31++R31+P31+O31+M31+I31+K31+Q31+V31+W31 -> 110000 | Z31: 1000000 | AQ31: =IF(H31="ECHEC",((K31+M31+O31)*20/100),0) -> 0 | AR31: =IF(H31="ECHEC",((K31+M31+O31)*20/100),0) -> 0 | AS31: =IF(H31="ECHEC",0,(K31+I31-25000)) -> 24000 | AW31: =IF(AC31=0,AI31,(1*25000*12)+AI31-AC31) -> 0 | AX31: =IF(AD31=0,AJ31,(1*75000*12)+(AJ31)-AD31) -> 0 | AY31: =IF(AE31=0,AK31,(1*100000*12)+(AK31)-AE31) -> 0 | AZ31: =SUM(AV31:AY31)-BF31+Z31-F31+BH31+BI31+BJ31+BK31+BL31+BM31 -> 980000 | BA31: 980000 | BB31: 115000 | BF31: =Z31*1/100*BG31 -> 120000 | BG31: 12 | BK31: 100000 | BR31: 60000 | BS31: =IF(BR31>0,BR31,0) -> 60000
A32: AS201653 | B32: =VLOOKUP(A32,[5]LISTADHERENT!A$5:H$50,3,0) -> SIME BRICE | C32: =D32+E32+F32-U32-BB32 -> 0 | D32: 452000 | E32: 1000000 | F32: 0 | G32: 0 | H32: =IF($D32<>0,"BANQUE",IF($E32<>0,"ESPECES","ECHEC")) -> BANQUE | J32: 1 | K32: =IF($D32<>0,J32*50000,IF($E32<>0,J32*50000,0)) -> 50000 | M32: =IF($D32<>0,L32*75000,IF($E32<>0,L32*75000,0)) -> 0 | N32: 2 | O32: =IF($D32<>0,N32*100000,IF($E32<>0,N32*100000,0)) -> 200000 | P32: 0 | Q32: 0 | R32: 202000 | S32: 1000000 | U32: =G32+S32++R32+P32+O32+M32+I32+K32+Q32+V32+W32 -> 1452000 | Z32: 1000000 | AQ32: =IF(H32="ECHEC",((K32+M32+O32)*20/100),0) -> 0 | AR32: =IF(H32="ECHEC",((K32+M32+O32)*20/100),0) -> 0 | AS32: =IF(H32="ECHEC",0,(K32+I32-25000)) -> 25000 | AW32: =IF(AC32=0,AI32,(1*25000*12)+AI32-AC32) -> 0 | AX32: =IF(AD32=0,AJ32,(1*75000*12)+(AJ32)-AD32) -> 0 | AY32: =IF(AE32=0,AK32,(1*100000*12)+(AK32)-AE32) -> 0 | AZ32: =SUM(AV32:AY32)-BF32+Z32-F32+BH32+BI32+BJ32+BK32+BL32+BM32 -> 970000 | BA32: 880000 | BD32: =IF(AZ32=0,(AZ32-BA32-BC32),(AZ32-BA32-BB32-BC32)) -> 90000 | BF32: =Z32*1/100*BG32 -> 30000 | BG32: 3 | BO32: DECES | BP32: MUTUELLE | BR32: 0 | BS32: =IF(BR32>0,BR32,0) -> 0
A33: AS201629 | B33: =VLOOKUP(A33,[5]LISTADHERENT!A$5:H$50,3,0) -> SIMO FONGANG ERIC
A34: AS201638 | B34: =VLOOKUP(A34,[5]LISTADHERENT!A$5:H$50,3,0) -> SIMO PIERRE | C34: =D34+E34+F34-U34-BB34 -> 0 | D34: 1150000 | E34: 0 | F34: 0 | G34: 0 | H34: =IF($D34<>0,"BANQUE",IF($E34<>0,"ESPECES","ECHEC")) -> BANQUE | J34: 1 | K34: =IF($D34<>0,J34*50000,IF($E34<>0,J34*50000,0)) -> 50000 | M34: =IF($D34<>0,L34*75000,IF($E34<>0,L34*75000,0)) -> 0 | N34: 1 | O34: =IF($D34<>0,N34*100000,IF($E34<>0,N34*100000,0)) -> 100000 | P34: 0 | Q34: 0 | R34: 0 | S34: 1000000 | U34: =G34+S34++R34+P34+O34+M34+I34+K34+Q34+V34+W34 -> 1150000 | Z34: 1000000 | AQ34: =IF(H34="ECHEC",((K34+M34+O34)*20/100),0) -> 0 | AR34: =IF(H34="ECHEC",((K34+M34+O34)*20/100),0) -> 0 | AS34: =IF(H34="ECHEC",0,(K34+I34-25000)) -> 25000 | AW34: =IF(AC34=0,AI34,(1*25000*12)+AI34-AC34) -> 0 | AX34: =IF(AD34=0,AJ34,(1*75000*12)+(AJ34)-AD34) -> 0 | AY34: =IF(AE34=0,AK34,(1*100000*12)+(AK34)-AE34) -> 0 | AZ34: =SUM(AV34:AY34)-BF34+Z34-F34+BH34+BI34+BJ34+BK34+BL34+BM34 -> 880000 | BD34: =IF(AZ34=0,(AZ34-BA34-BC34),(AZ34-BA34-BB34-BC34)) -> 880000 | BE34: OK | BF34: =Z34*1/100*BG34 -> 120000 | BG34: 12 | BO34: TRANSPORT DELEGUE | BP34: MUTUELLE | BR34: 1000000 | BS34: =IF(BR34>0,BR34,0) -> 1000000
A35: AS201641 | B35: =VLOOKUP(A35,[5]LISTADHERENT!A$5:H$50,3,0) -> TCHOUAMOU MATHIEU | C35: =D35+E35+F35-U35-BB35 -> 0 | D35: 327000 | E35: 0 | F35: 0 | G35: 0 | H35: =IF($D35<>0,"BANQUE",IF($E35<>0,"ESPECES","ECHEC")) -> BANQUE | J35: 1 | K35: =IF($D35<>0,J35*50000,IF($E35<>0,J35*50000,0)) -> 50000 | L35: 1 | M35: =IF($D35<>0,L35*75000,IF($E35<>0,L35*75000,0)) -> 75000 | O35: =IF($D35<>0,N35*100000,IF($E35<>0,N35*100000,0)) -> 0 | P35: 0 | Q35: 202000 | R35: 0 | U35: =G35+S35++R35+P35+O35+M35+I35+K35+Q35+V35+W35 -> 327000 | Z35: 1000000 | AQ35: =IF(H35="ECHEC",((K35+M35+O35)*20/100),0) -> 0 | AR35: =IF(H35="ECHEC",((K35+M35+O35)*20/100),0) -> 0 | AS35: =IF(H35="ECHEC",0,(K35+I35-25000)) -> 25000 | AW35: =IF(AC35=0,AI35,(1*25000*12)+AI35-AC35) -> 0 | AX35: =IF(AD35=0,AJ35,(1*75000*12)+(AJ35)-AD35) -> 0 | AY35: =IF(AE35=0,AK35,(1*100000*12)+(AK35)-AE35) -> 0 | AZ35: =SUM(AV35:AY35)-BF35+Z35-F35+BH35+BI35+BJ35+BK35+BL35+BM35 -> 880000 | BD35: =IF(AZ35=0,(AZ35-BA35-BC35),(AZ35-BA35-BB35-BC35)) -> 880000 | BE35: OK | BF35: =Z35*1/100*BG35 -> 120000 | BG35: 12 | BO35: FUNERAILLE JOSUE DJOSSE | BR35: 0 | BS35: =IF(BR35>0,BR35,0) -> 0
A36: AS201660 | B36: =VLOOKUP(A36,[5]LISTADHERENT!A$5:H$50,3,0) -> TCHOUATEU AUGUSTIN | C36: =D36+E36+F36-U36-BB36 -> 0 | D36: 160000 | E36: 0 | F36: 0 | G36: 0 | H36: =IF($D36<>0,"BANQUE",IF($E36<>0,"ESPECES","ECHEC")) -> BANQUE | I36: 10000 | J36: 1 | K36: =IF($D36<>0,J36*50000,IF($E36<>0,J36*50000,0)) -> 50000 | M36: =IF($D36<>0,L36*75000,IF($E36<>0,L36*75000,0)) -> 0 | N36: 1 | O36: =IF($D36<>0,N36*100000,IF($E36<>0,N36*100000,0)) -> 100000 | P36: 0 | Q36: 0 | R36: 0 | U36: =G36+S36++R36+P36+O36+M36+I36+K36+Q36+V36+W36 -> 160000 | Z36: 1000000 | AQ36: =IF(H36="ECHEC",((K36+M36+O36)*20/100),0) -> 0 | AR36: =IF(H36="ECHEC",((K36+M36+O36)*20/100),0) -> 0 | AS36: =IF(H36="ECHEC",0,(K36+I36-25000)) -> 35000 | AW36: =IF(AC36=0,AI36,(1*25000*12)+AI36-AC36) -> 0 | AX36: =IF(AD36=0,AJ36,(1*75000*12)+(AJ36)-AD36) -> 0 | AY36: =IF(AE36=0,AK36,(1*100000*12)+(AK36)-AE36) -> 0 | AZ36: =SUM(AV36:AY36)-BF36+Z36-F36+BH36+BI36+BJ36+BK36+BL36+BM36 -> 880000 | BA36: 880000 | BD36: =IF(AZ36=0,(AZ36-BA36-BC36),(AZ36-BA36-BB36-BC36)) -> 0 | BF36: =Z36*1/100*BG36 -> 120000 | BG36: 12 | BO36: S/TOTAL | BQ36: =SUM(BQ32:BQ35) -> 0 | BR36: 10000 | BS36: =IF(BR36>0,BR36,0) -> 10000
A37: AS201643 | B37: =VLOOKUP(A37,[5]LISTADHERENT!A$5:H$50,3,0) -> TCHOUTOU NANA CLAUDE | C37: =D37+E37+F37-U37-BB37 -> -297500 | D37: 0 | E37: 50000 | F37: 0 | G37: 0 | H37: =IF($D37<>0,"BANQUE",IF($E37<>0,"ESPECES","ECHEC")) -> ESPECES | I37: 297500 | J37: 1 | K37: =IF($D37<>0,J37*50000,IF($E37<>0,J37*50000,0)) -> 50000 | M37: =IF($D37<>0,L37*75000,IF($E37<>0,L37*75000,0)) -> 0 | O37: =IF($D37<>0,N37*100000,IF($E37<>0,N37*100000,0)) -> 0 | P37: 0 | Q37: 0 | R37: 0 | U37: =G37+S37++R37+P37+O37+M37+I37+K37+Q37+V37+W37 -> 347500 | AC37: 2500 | AQ37: =IF(H37="ECHEC",((K37+M37+O37)*20/100),0) -> 0 | AR37: =IF(H37="ECHEC",((K37+M37+O37)*20/100),0) -> 0 | AS37: =IF(H37="ECHEC",0,(K37+I37-25000)) -> 322500 | AW37: =IF(AC37=0,AI37,(1*25000*12)+AI37-AC37) -> 297500 | AX37: =IF(AD37=0,AJ37,(1*75000*12)+(AJ37)-AD37) -> 0 | AY37: =IF(AE37=0,AK37,(1*100000*12)+(AK37)-AE37) -> 0 | AZ37: =SUM(AV37:AY37)-BF37+Z37-F37+BH37+BI37+BJ37+BK37+BL37+BM37 -> 297500 | BA37: 297500 | BD37: =IF(AZ37=0,(AZ37-BA37-BC37),(AZ37-BA37-BB37-BC37)) -> 0 | BF37: =Z37*1/100*BG37 -> 0 | BG37: 12 | BO37: S/TOTAL | BQ37: =SUM(BQ34:BQ36) -> 0 | BR37: 0 | BS37: =IF(BR37>0,BR37,0) -> 0
A38: AS201662 | B38: =VLOOKUP(A38,[5]LISTADHERENT!A$5:H$50,3,0) -> TIEYAM ERNEST
A39: AS201658 | B39: =VLOOKUP(A39,[5]LISTADHERENT!A$5:H$50,3,0) -> YANTCHOU GERVAIS | C39: =D39+E39+F39-U39-BB39 -> 0 | D39: 350000 | E39: 0 | F39: 0 | G39: 0 | H39: =IF($D39<>0,"BANQUE",IF($E39<>0,"ESPECES","ECHEC")) -> BANQUE | J39: 1 | K39: =IF($D39<>0,J39*50000,IF($E39<>0,J39*50000,0)) -> 50000 | M39: =IF($D39<>0,L39*75000,IF($E39<>0,L39*75000,0)) -> 0 | O39: =IF($D39<>0,N39*100000,IF($E39<>0,N39*100000,0)) -> 0 | P39: 0 | Q39: 0 | R39: 0 | S39: 300000 | U39: =G39+S39++R39+P39+O39+M39+I39+K39+Q39+V39+W39 -> 350000 | Z39: 1000000 | AQ39: =IF(H39="ECHEC",((K39+M39+O39)*20/100),0) -> 0 | AR39: =IF(H39="ECHEC",((K39+M39+O39)*20/100),0) -> 0 | AS39: =IF(H39="ECHEC",0,(K39+I39-25000)) -> 25000 | AW39: =IF(AC39=0,AI39,(1*25000*12)+AI39-AC39) -> 0 | AX39: =IF(AD39=0,AJ39,(1*75000*12)+(AJ39)-AD39) -> 0 | AY39: =IF(AE39=0,AK39,(1*100000*12)+(AK39)-AE39) -> 0 | AZ39: =SUM(AV39:AY39)-BF39+Z39-F39+BH39+BI39+BJ39+BK39+BL39+BM39 -> 880000 | BD39: =IF(AZ39=0,(AZ39-BA39-BC39),(AZ39-BA39-BB39-BC39)) -> 880000 | BE39: OK | BF39: =Z39*1/100*BG39 -> 120000 | BG39: 12 | BR39: 290000 | BS39: =IF(BR39>0,BR39,0) -> 290000
A40: AS201646 | B40: =VLOOKUP(A40,[5]LISTADHERENT!A$5:H$50,3,0) -> YEPMOU JEAN JACQUES | C40: =D40+E40+F40-U40-BB40 -> 0 | D40: 0 | E40: 50000 | F40: 0 | G40: 0 | H40: =IF($D40<>0,"BANQUE",IF($E40<>0,"ESPECES","ECHEC")) -> ESPECES | J40: 1 | K40: =IF($D40<>0,J40*50000,IF($E40<>0,J40*50000,0)) -> 50000 | M40: =IF($D40<>0,L40*75000,IF($E40<>0,L40*75000,0)) -> 0 | O40: =IF($D40<>0,N40*100000,IF($E40<>0,N40*100000,0)) -> 0 | P40: 0 | Q40: 0 | R40: 0 | U40: =G40+S40++R40+P40+O40+M40+I40+K40+Q40+V40+W40 -> 50000 | AC40: 2500 | AQ40: =IF(H40="ECHEC",((K40+M40+O40)*20/100),0) -> 0 | AR40: =IF(H40="ECHEC",((K40+M40+O40)*20/100),0) -> 0 | AS40: =IF(H40="ECHEC",0,(K40+I40-25000)) -> 25000 | AW40: =IF(AC40=0,AI40,(1*25000*12)+AI40-AC40) -> 297500 | AX40: =IF(AD40=0,AJ40,(1*75000*12)+(AJ40)-AD40) -> 0 | AY40: =IF(AE40=0,AK40,(1*100000*12)+(AK40)-AE40) -> 0 | AZ40: =SUM(AV40:AY40)-BF40+Z40-F40+BH40+BI40+BJ40+BK40+BL40+BM40 -> 297500 | BA40: 297500 | BD40: =IF(AZ40=0,(AZ40-BA40-BC40),(AZ40-BA40-BB40-BC40)) -> 0 | BF40: =Z40*1/100*BG40 -> 0 | BG40: 12 | BO40: COLLATION | BP40: COLLATION | BR40: 0 | BS40: =IF(BR40>0,BR40,0) -> 0
A41: AS201659 | B41: =VLOOKUP(A41,[5]LISTADHERENT!A$5:H$50,3,0) -> YIALA ALAIN OSCAR | C41: =D41+E41+F41-U41-BB41 -> 0 | D41: 0 | E41: 150000 | F41: 0 | G41: 0 | H41: =IF($D41<>0,"BANQUE",IF($E41<>0,"ESPECES","ECHEC")) -> ESPECES | J41: 1 | K41: =IF($D41<>0,J41*50000,IF($E41<>0,J41*50000,0)) -> 50000 | M41: =IF($D41<>0,L41*75000,IF($E41<>0,L41*75000,0)) -> 0 | N41: 1 | O41: =IF($D41<>0,N41*100000,IF($E41<>0,N41*100000,0)) -> 100000 | P41: 0 | Q41: 0 | R41: 0 | U41: =G41+S41++R41+P41+O41+M41+I41+K41+Q41+V41+W41 -> 150000 | AQ41: =IF(H41="ECHEC",((K41+M41+O41)*20/100),0) -> 0 | AR41: =IF(H41="ECHEC",((K41+M41+O41)*20/100),0) -> 0 | AS41: =IF(H41="ECHEC",0,(K41+I41-25000)) -> 25000 | AW41: =IF(AC41=0,AI41,(1*25000*12)+AI41-AC41) -> 0 | AX41: =IF(AD41=0,AJ41,(1*75000*12)+(AJ41)-AD41) -> 0 | AY41: =IF(AE41=0,AK41,(1*100000*12)+(AK41)-AE41) -> 0 | AZ41: =SUM(AV41:AY41)-BF41+Z41-F41+BH41+BI41+BJ41+BK41+BL41+BM41 -> 0 | BD41: =IF(AZ41=0,(AZ41-BA41-BC41),(AZ41-BA41-BB41-BC41)) -> 0 | BF41: =Z41*1/100*BG41 -> 0 | BG41: 12 | BO41: BOISSON | BP41: COLLATION | BR41: 0 | BS41: =IF(BR41>0,BR41,0) -> 0
A42: AS201647 | B42: =VLOOKUP(A42,[5]LISTADHERENT!A$5:H$50,3,0) -> YOUMBI EMMANUEL | C42: =D42+E42+F42-U42-BB42 -> 0 | D42: 125000 | E42: 0 | F42: 0 | G42: 0 | H42: =IF($D42<>0,"BANQUE",IF($E42<>0,"ESPECES","ECHEC")) -> BANQUE | J42: 1 | K42: =IF($D42<>0,J42*50000,IF($E42<>0,J42*50000,0)) -> 50000 | L42: 1 | M42: =IF($D42<>0,L42*75000,IF($E42<>0,L42*75000,0)) -> 75000 | O42: =IF($D42<>0,N42*100000,IF($E42<>0,N42*100000,0)) -> 0 | P42: 0 | Q42: 0 | R42: 0 | U42: =G42+S42++R42+P42+O42+M42+I42+K42+Q42+V42+W42 -> 125000 | Z42: 500000 | AQ42: =IF(H42="ECHEC",((K42+M42+O42)*20/100),0) -> 0 | AR42: =IF(H42="ECHEC",((K42+M42+O42)*20/100),0) -> 0 | AS42: =IF(H42="ECHEC",0,(K42+I42-25000)) -> 25000 | AW42: =IF(AC42=0,AI42,(1*25000*12)+AI42-AC42) -> 0 | AX42: =IF(AD42=0,AJ42,(1*75000*12)+(AJ42)-AD42) -> 0 | AY42: =IF(AE42=0,AK42,(1*100000*12)+(AK42)-AE42) -> 0 | AZ42: =SUM(AV42:AY42)-BF42+Z42-F42+BH42+BI42+BJ42+BK42+BL42+BM42 -> 485000 | BA42: 485000 | BD42: =IF(AZ42=0,(AZ42-BA42-BC42),(AZ42-BA42-BB42-BC42)) -> 0 | BF42: =Z42*1/100*BG42 -> 15000 | BG42: 3 | BO42: BOISSON | BP42: COLLATION | BR42: 0 | BS42: =IF(BR42>0,BR42,0) -> 0
B44: TOTAUX | C44: =SUM(C6:C43) -> -2706700 | D44: =SUM(D6:D43) -> 9103000 | E44: =SUM(E6:E43) -> 9052000 | F44: =SUM(F6:F43) -> 0 | G44: =SUM(G6:G43) -> 0 | H44: =SUM(H6:H43) -> 0 | I44: =SUM(I6:I43) -> 790500 | J44: =SUM(J6:J43) -> 32 | ... S44: =SUM(S6:S43) -> 11817500 | U44: =SUM(U6:U43) -> 20491000 | V44: =SUM(V6:V43) -> 0 | W44: =SUM(W6:W43) -> 0 | X44: =SUM(X6:X43) -> 0 | Y44: =SUM(Y6:Y43) -> 0 | Z44: =SUM(Z6:Z43) -> 17931500 | AA44: =SUM(AA6:AA43) -> 0 | AC44: =SUM(AC6:AC43) -> 7500 | AD44: =SUM(AD6:AD43) -> 7500 | AE44: =SUM(AE6:AE43) -> 10000 | AF44: =SUM(AF6:AF43) -> 0 | AG44: =SUM(AG6:AG43) -> 0 | AI44: =SUM(AI6:AI43) -> 0 | AJ44: =SUM(AJ6:AJ43) -> 0 | AK44: =SUM(AK6:AK43) -> 0 | AL44: =SUM(AL6:AL43) -> 0 | AM44: =SUM(AM6:AM43) -> 0 | AN44: =SUM(AN6:AN43) -> 0 | AO44: =SUM(AO6:AO43) -> 0 | AP44: =SUM(AP6:AP43) -> 0 | ... BF44: =SUM(BF6:BF43) -> 1398000 | BH44: =SUM(BH6:BH43) -> 4031000 | BI44: =SUM(BI6:BI43) -> 0 | BJ44: =SUM(BJ6:BJ43) -> 0 | BK44: =SUM(BK6:BK43) -> 100000 | BL44: =SUM(BL6:BL43) -> 0 | BM44: =SUM(BM6:BM43) -> 0 | BO44: S/TOTAL | BQ44: =SUM(BQ40:BQ42) -> 0
B47: AS201643 | BO47: TRANSPORT DELEGUE | BP47: MUTUELLE
C48: BANQUE | F48: ESPECES
B49: LIBELLE | C49: SORTIE | D49: ENTREE | E49: SOLDE | F49: ENTREE | G49: SORTIE | H49: SOLDE | BO49: S/TOTAL | BQ49: =SUM(BQ46:BQ48) -> 0
B50: REPORT
B51: TONTINE | C51: =AZ44 -> 21704250 | D51: =SUMIFS(D8:D44,H8:H44,"BANQUE") -> 8928000 | F51: =E44 -> 9052000
AZ89: =SUM(AZ8:AZ88) -> 39284500

Sheet HISTOJANV25
A1: ASSOCIATION | B1: ASELBY
A2: ANNEE | B2: 2025
A3: 1 | B3: 2 | C3: 3 | D3: 4 | E3: 5 | F3: 6 | G3: 7 | H3: 8 | I3: 9 | J3: 10 | K3: 11 | L3: 12 | M3: 13 | N3: 14 | O3: 15 | P3: 16 | Q3: 17 | R3: 18 | S3: 19 | T3: 20 | U3: 21 | V3: 22 | W3: 23 | X3: 24 | Y3: 25 | Z3: 26 | AA3: 27 | AB3: 28 | AC3: 29 | AD3: 30 | AE3: 31 | AF3: 32 | AG3: 33 | AH3: 34 | AI3: 35 | AJ3: 36 | AK3: 37 | AL3: 38 | AM3: 39 | AN3: 40 | AO3: 41 | AP3: 42 | AQ3: 43 | AR3: 44 | AS3: 45 | AT3: 46 | AU3: 47 | AV3: 48 | AW3: 49 | AX3: 50 | AY3: 51 | AZ3: 52 | BA3: 53 | BB3: 54 | BC3: 55 | BD3: 56 | BE3: 57 | BF3: 58 | BG3: 59 | BH3: 60 | BI3: 61 | BJ3: 62 | BK3: 63 | BL3: 64 | BM3: 65 | BN3: 66 | BO3: 67 | BP3: 68 | BQ3: 69
B4: TABLEAU DE BORD SAISIE DES DONNEES
A5: MATRICULE | B5: NOM ET PRENOM | C5: BONUS MALUS | D5: VERSEMENT BANQUE | E5: VERSEMENT ESPECES | F5: AUTRE VERSEMENTS | G5: COMPLEMENT EPARGNE | H5: PENALITE VERSEMENT ESPECES | I5: MODE PAIEMENT TONTINE | J5: NBRE DE LOT | K5: TONTINE 25 000 | L5: NBRE DE LOT | M5: TONTINE 75 000 | N5: NBRE DE LOT | O5: TONTINE 100 000 | P5: REMBOURSEMENT PETIT LOT T25 | Q5: REMBOURSEMENT PETIT LOT T75 | R5: REMBOURSEMENT PETIT LOT T100 | S5: REMBOURSEMENT PRÊT FONDS | T5: MODE PAIEMENT REMBOURSEMENT PRÊT FONDS | U5: MONTANT ENGAGEMENT | V5: SANCTION | W5: INSCRIPTION | X5: EPARGNE ASSURANCE | Y5: TONTINE MOIS | Z5: PRÊT FONDS | AA5: MODE PAIEMENT PRÊT | AB5: NUM CHEQUE | AC5: ACHAT LOT PRINCIPAL T25 | AD5: ACHAT LOT PRINCIPAL T75 | AE5: ACHAT LOT PRINCIPAL T100 | AF5: MODE PAIEMENT LOT PRINCIPAL | AG5: NUM CHEQUE | AH5: PENALITE VERSEMENT ESPECES | AI5: VENTE PETIT LOT T25 | AJ5: VENTE PETIT LOT T75 | AK5: VENTE PETIT LOT T100 | AL5: INTERET PETIT LOT T25 | AM5: INTERET PETIT LOT T75 | AN5: INTERET PETIT LOT T100 | AO5: NUM CHEQUE | AP5: MODE REMBOURSEMENT PAIEMENT PETIT LOT | AQ5: PENELAITE RETARD TONTINE | AR5: PENELAITE ECHEC TONTINE | AS5: RESTE | AT5: MUTUELLE | AU5: REMBOURSEMENT TRANSPORT | AV5: RETRAIT PARTIEL FONDS | AW5: MONTANT T25 | AX5: MONTANT T75 | AY5: MONTANT T100 | AZ5: MONTANT CHEQUE | BA5: MONTANT ESPECES | BB5: CONTRIBUTION FOYER | BC5: AUTRES MODE DE VERST | BD5: MONTANT CHEQUE EFFECTIF | BE5: NUMERO CHEQUE | BF5: INTERET PRÊT | BG5: NBRE MOIS | BH5: DEPENSE FONDS DE ROULEMENT | BI5: DEPENSE FRAIS EXCEPTIONNEL | BJ5: DEPENSE FONDS MUTUEL | BK5: DEPENSE COLLATION RECEPTION | BL5: PENALITE PRET FONDS | BM5: DEPENSE PENALITE VERSEMENT BANQUE | BN5: AUTRES DEPENSES | BO5: LIBELLE | BP5: COMPTE | BQ5: MONTANT
A6: AS201648 | B6: =VLOOKUP(A6,[5]LISTADHERENT!A$5:H$50,3,0) -> ASELBY | C6: =IF(I6<>"ECHEC",D6+E6+F6-U6,0) -> 0 | D6: =VLOOKUP(A6,[6]HISTOBQUEJANV25!$A$6:$H$48,5,0) -> 250000 | E6: =VLOOKUP(A6,[6]HISTOBQUEJANV25!$A$6:$H$43,4,0) -> 0 | F6: =VLOOKUP(A6,[6]HISTOBQUEJANV25!$A$6:$H$43,6,0) -> 0 | H6: =IF(I6="ESPECES",3000,0) -> 0 | I6: =IF($D6<>0,"BANQUE",IF($E6<>0,"ESPECES","ECHEC")) -> BANQUE | K6: =IF($D6<>0,J6*50000,IF($E6<>0,J6*50000,0)) -> 0 | L6: 2 | M6: =IF($D6<>0,L6*75000,IF($E6<>0,L6*75000,0)) -> 150000 | N6: 1 | O6: =IF($D6<>0,N6*100000,IF($E6<>0,N6*100000,0)) -> 100000 | U6: =G6+H6+S6+R6+P6+O6+M6+K6+Q6+V6+W6 -> 250000 | Y6: =K6+M6+O6 -> 250000 | AQ6: =IF(I6="ECHEC",((K6+M6+O6)*20/100),0) -> 0 | AR6: =IF(I6="ECHEC",((K6+M6+O6)*20/100),0) -> 0 | AW6: =IF(AC6=0,AI6,(1*25000*12)+AI6-AC6) -> 0 | AX6: =IF(AD6=0,AJ6,(1*75000*12)+(AJ6)-AD6) -> 0 | AY6: =IF(AE6=0,AK6,(1*100000*12)+(AK6)-AE6) -> 0 | AZ6: =SUM(AV6:AY6)-BF6+Z6+BH6+BI6+BJ6+BK6+BL6+BM6+BN6 -> 673000 | BA6: =30000+15000+15000+15000+15000+6000+6000 -> 102000 | BC6: =F6 -> 0 | BD6: =IF(AZ6=0,(AZ6-BA6-BC6),(AZ6-BA6-BB6-BC6)) -> 571000 | BF6: =Z6*1/100*BG6 -> 0 | BG6: 11 | BH6: =BQ17 -> 72000 | BI6: =BQ30 -> 200000 | BJ6: =BQ36 -> 0 | BN6: =+BQ24 -> 401000 | BO6: ACHAT FOURNITURE | BP6: FONDS DE ROULEMENT
A7: AS201601 | B7: =VLOOKUP(A7,[5]LISTADHERENT!A$5:H$50,3,0) -> BAKOP ACHILLE | C7: =IF(I7<>"ECHEC",D7+E7+F7-U7,0) -> 0 | D7: =VLOOKUP(A7,[6]HISTOBQUEJANV25!$A$6:$H$48,5,0) -> 0 | E7: =VLOOKUP(A7,[6]HISTOBQUEJANV25!$A$6:$H$43,4,0) -> 50000 | F7: =VLOOKUP(A7,[6]HISTOBQUEJANV25!$A$6:$H$43,6,0) -> 0 | H7: 0 | I7: =IF($D7<>0,"BANQUE",IF($E7<>0,"ESPECES","ECHEC")) -> ESPECES | J7: 1 | K7: =IF($D7<>0,J7*50000,IF($E7<>0,J7*50000,0)) -> 50000 | M7: =IF($D7<>0,L7*75000,IF($E7<>0,L7*75000,0)) -> 0 | O7: =IF($D7<>0,N7*100000,IF($E7<>0,N7*100000,0)) -> 0 | U7: =G7+H7+S7+R7+P7+O7+M7+K7+Q7+V7+W7 -> 50000 | Y7: =K7+M7+O7 -> 50000 | Z7: 1000000 | AA7: BANQUE | AQ7: =IF(I7="ECHEC",((K7+M7+O7)*20/100),0) -> 0 | AR7: =IF(I7="ECHEC",((K7+M7+O7)*20/100),0) -> 0 | AS7: =IF(I7="ECHEC",0,(K7+G7-25000)) -> 25000 | AW7: =IF(AC7=0,AI7,(1*25000*12)+AI7-AC7) -> 0 | AX7: =IF(AD7=0,AJ7,(1*75000*12)+(AJ7)-AD7) -> 0 | AY7: =IF(AE7=0,AK7,(1*100000*12)+(AK7)-AE7) -> 0 | AZ7: =SUM(AV7:AY7)-BF7+Z7+BH7+BI7+BJ7+BK7+BL7+BM7 -> 890000 | BC7: =F7 -> 0 | BD7: =IF(AZ7=0,(AZ7-BA7-BC7),(AZ7-BA7-BB7-BC7)) -> 890000 | BE7: OK | BF7: =Z7*1/100*BG7 -> 110000 | BG7: 11 | BO7: COMMUNICATION | BP7: FONDS DE ROULEMENT
A8: AS201602 | B8: =VLOOKUP(A8,[5]LISTADHERENT!A$5:H$50,3,0) -> BOUTCHOUANG WILLIAM | C8: =IF(I8<>"ECHEC",D8+E8+F8-U8,0) -> 0 | D8: =VLOOKUP(A8,[6]HISTOBQUEJANV25!$A$6:$H$48,5,0) -> 125000 | E8: =VLOOKUP(A8,[6]HISTOBQUEJANV25!$A$6:$H$43,4,0) -> 0 | F8: =VLOOKUP(A8,[6]HISTOBQUEJANV25!$A$6:$H$43,6,0) -> 0 | H8: =IF(I8="ESPECES",3000,0) -> 0 | I8: =IF($D8<>0,"BANQUE",IF($E8<>0,"ESPECES","ECHEC")) -> BANQUE | J8: 1 | K8: =IF($D8<>0,J8*50000,IF($E8<>0,J8*50000,0)) -> 50000 | L8: 1 | M8: =IF($D8<>0,L8*75000,IF($E8<>0,L8*75000,0)) -> 75000 | O8: =IF($D8<>0,N8*100000,IF($E8<>0,N8*100000,0)) -> 0 | U8: =G8+H8+S8+R8+P8+O8+M8+K8+Q8+V8+W8 -> 125000 | Y8: =K8+M8+O8 -> 125000 | AQ8: =IF(I8="ECHEC",((K8+M8+O8)*20/100),0) -> 0 | AR8: =IF(I8="ECHEC",((K8+M8+O8)*20/100),0) -> 0 | AS8: =IF(I8="ECHEC",0,(K8+G8-25000)) -> 25000 | AW8: =IF(AC8=0,AI8,(1*25000*12)+AI8-AC8) -> 0 | AX8: =IF(AD8=0,AJ8,(1*75000*12)+(AJ8)-AD8) -> 0 | AY8: =IF(AE8=0,AK8,(1*100000*12)+(AK8)-AE8) -> 0 | AZ8: =SUM(AV8:AY8)-BF8+Z8+BH8+BI8+BJ8+BK8+BL8+BM8 -> 0 | BC8: =F8 -> 0 | BD8: =IF(AZ8=0,(AZ8-BA8-BC8),(AZ8-BA8-BB8-BC8)) -> 0 | BF8: =Z8*1/100*BG8 -> 0 | BG8: 11 | BO8: COMMISSION | BP8: FONDS DE ROULEMENT | BQ8: 66000
A9: AS201604 | B9: =VLOOKUP(A9,[5]LISTADHERENT!A$5:H$50,3,0) -> DJOMO JEAN PAUL | C9: =IF(I9<>"ECHEC",D9+E9+F9-U9,0) -> 0 | D9: =VLOOKUP(A9,[6]HISTOBQUEJANV25!$A$6:$H$48,5,0) -> 250000 | E9: =VLOOKUP(A9,[6]HISTOBQUEJANV25!$A$6:$H$43,4,0) -> 0 | F9: =VLOOKUP(A9,[6]HISTOBQUEJANV25!$A$6:$H$43,6,0) -> 0 | H9: =IF(I9="ESPECES",3000,0) -> 0 | I9: =IF($D9<>0,"BANQUE",IF($E9<>0,"ESPECES","ECHEC")) -> BANQUE | J9: 1 | K9: =IF($D9<>0,J9*50000,IF($E9<>0,J9*50000,0)) -> 50000 | M9: =IF($D9<>0,L9*75000,IF($E9<>0,L9*75000,0)) -> 0 | N9: 2 | O9: =IF($D9<>0,N9*100000,IF($E9<>0,N9*100000,0)) -> 200000 | U9: =G9+H9+S9+R9+P9+O9+M9+K9+Q9+V9+W9 -> 250000 | Y9: =K9+M9+O9 -> 250000 | AC9: 31000 | AF9: BANQUE | AQ9: =IF(I9="ECHEC",((K9+M9+O9)*20/100),0) -> 0 | AR9: =IF(I9="ECHEC",((K9+M9+O9)*20/100),0) -> 0 | AS9: =IF(I9="ECHEC",0,(K9+G9-25000)) -> 25000 | AW9: =IF(AC9=0,AI9,(1*25000*12)+AI9-AC9) -> 269000 | AX9: =IF(AD9=0,AJ9,(1*75000*12)+(AJ9)-AD9) -> 0 | AY9: =IF(AE9=0,AK9,(1*100000*12)+(AK9)-AE9) -> 0 | AZ9: =SUM(AV9:AY9)-BF9+Z9+BH9+BI9+BJ9+BK9+BL9+BM9 -> 269000 | BC9: =F9 -> 0 | BD9: =IF(AZ9=0,(AZ9-BA9-BC9),(AZ9-BA9-BB9-BC9)) -> 269000 | BE9: OK | BF9: =Z9*1/100*BG9 -> 0 | BG9: 11 | BO9: OUVERTURE COMPTE | BP9: FONDS DE ROULEMENT
A10: AS201654 | B10: =VLOOKUP(A10,[5]LISTADHERENT!A$5:H$50,3,0) -> DJOMOU TCHAPDA | C10: =IF(I10<>"ECHEC",D10+E10+F10-U10,0) -> 0 | D10: =VLOOKUP(A10,[6]HISTOBQUEJANV25!$A$6:$H$48,5,0) -> 0 | E10: =VLOOKUP(A10,[6]HISTOBQUEJANV25!$A$6:$H$43,4,0) -> 50000 | F10: =VLOOKUP(A10,[6]HISTOBQUEJANV25!$A$6:$H$43,6,0) -> 0 | H10: 0 | I10: =IF($D10<>0,"BANQUE",IF($E10<>0,"ESPECES","ECHEC")) -> ESPECES | J10: 1 | K10: =IF($D10<>0,J10*50000,IF($E10<>0,J10*50000,0)) -> 50000 | M10: =IF($D10<>0,L10*75000,IF($E10<>0,L10*75000,0)) -> 0 | O10: =IF($D10<>0,N10*100000,IF($E10<>0,N10*100000,0)) -> 0 | U10: =G10+H10+S10+R10+P10+O10+M10+K10+Q10+V10+W10 -> 50000 | Y10: =K10+M10+O10 -> 50000 | AC10: 30000 | AF10: BANQUE | AQ10: =IF(I10="ECHEC",((K10+M10+O10)*20/100),0) -> 0 | AR10: =IF(I10="ECHEC",((K10+M10+O10)*20/100),0) -> 0 | AS10: =IF(I10="ECHEC",0,(K10+G10-25000)) -> 25000 | AW10: =IF(AC10=0,AI10,(1*25000*12)+AI10-AC10) -> 270000 | AX10: =IF(AD10=0,AJ10,(1*75000*12)+(AJ10)-AD10) -> 0 | AY10: =IF(AE10=0,AK10,(1*100000*12)+(AK10)-AE10) -> 0 | AZ10: =SUM(AV10:AY10)-BF10+Z10+BH10+BI10+BJ10+BK10+BL10+BM10 -> 270000 | BC10: =F10 -> 0 | BD10: =IF(AZ10=0,(AZ10-BA10-BC10),(AZ10-BA10-BB10-BC10)) -> 270000 | BE10: OK | BF10: =Z10*1/100*BG10 -> 0 | BG10: 11 | BO10: CREDIT TELEPHONE | BP10: FONDS DE ROULEMENT
A11: AS201605 | B11: =VLOOKUP(A11,[5]LISTADHERENT!A$5:H$50,3,0) -> DJOUKWE NANGUEN GUY BLAISE | C11: =IF(I11<>"ECHEC",D11+E11+F11-U11,0) -> 0 | D11: =VLOOKUP(A11,[6]HISTOBQUEJANV25!$A$6:$H$48,5,0) -> 150000 | E11: =VLOOKUP(A11,[6]HISTOBQUEJANV25!$A$6:$H$43,4,0) -> 0 | F11: =VLOOKUP(A11,[6]HISTOBQUEJANV25!$A$6:$H$43,6,0) -> 0 | H11: =IF(I11="ESPECES",3000,0) -> 0 | I11: =IF($D11<>0,"BANQUE",IF($E11<>0,"ESPECES","ECHEC")) -> BANQUE | J11: 1 | K11: =IF($D11<>0,J11*50000,IF($E11<>0,J11*50000,0)) -> 50000 | M11: =IF($D11<>0,L11*75000,IF($E11<>0,L11*75000,0)) -> 0 | N11: 1 | O11: =IF($D11<>0,N11*100000,IF($E11<>0,N11*100000,0)) -> 100000 | U11: =G11+H11+S11+R11+P11+O11+M11+K11+Q11+V11+W11 -> 150000 | Y11: =K11+M11+O11 -> 150000 | AQ11: =IF(I11="ECHEC",((K11+M11+O11)*20/100),0) -> 0 | AR11: =IF(I11="ECHEC",((K11+M11+O11)*20/100),0) -> 0 | AS11: =IF(I11="ECHEC",0,(K11+G11-25000)) -> 25000 | AW11: =IF(AC11=0,AI11,(1*25000*12)+AI11-AC11) -> 0 | AX11: =IF(AD11=0,AJ11,(1*75000*12)+(AJ11)-AD11) -> 0 | AY11: =IF(AE11=0,AK11,(1*100000*12)+(AK11)-AE11) -> 0 | AZ11: =SUM(AV11:AY11)-BF11+Z11+BH11+BI11+BJ11+BK11+BL11+BM11 -> 0 | BC11: =F11 -> 0 | BD11: =IF(AZ11=0,(AZ11-BA11-BC11),(AZ11-BA11-BB11-BC11)) -> 0 | BF11: =Z11*1/100*BG11 -> 0 | BG11: 11 | BO11: PRODUCTION RAPPORT | BP11: FONDS DE ROULEMENT
A12: AS201608 | B12: =VLOOKUP(A12,[5]LISTADHERENT!A$5:H$50,3,0) -> DJUOMBESSY ANTOINE | C12: =IF(I12<>"ECHEC",D12+E12+F12-U12,0) -> 0 | D12: =VLOOKUP(A12,[6]HISTOBQUEJANV25!$A$6:$H$48,5,0) -> 260000 | E12: =VLOOKUP(A12,[6]HISTOBQUEJANV25!$A$6:$H$43,4,0) -> 0 | F12: =VLOOKUP(A12,[6]HISTOBQUEJANV25!$A$6:$H$43,6,0) -> 0 | G12: 10000 | H12: =IF(I12="ESPECES",3000,0) -> 0 | I12: =IF($D12<>0,"BANQUE",IF($E12<>0,"ESPECES","ECHEC")) -> BANQUE | J12: 1 | K12: =IF($D12<>0,J12*50000,IF($E12<>0,J12*50000,0)) -> 50000 | M12: =IF($D12<>0,L12*75000,IF($E12<>0,L12*75000,0)) -> 0 | N12: 2 | O12: =IF($D12<>0,N12*100000,IF($E12<>0,N12*100000,0)) -> 200000 | U12: =G12+H12+S12+R12+P12+O12+M12+K12+Q12+V12+W12 -> 260000 | Y12: =K12+M12+O12 -> 250000 | AQ12: =IF(I12="ECHEC",((K12+M12+O12)*20/100),0) -> 0 | AR12: =IF(I12="ECHEC",((K12+M12+O12)*20/100),0) -> 0 | AS12: =IF(I12="ECHEC",0,(K12+G12-25000)) -> 35000 | AW12: =IF(AC12=0,AI12,(1*25000*12)+AI12-AC12) -> 0 | AX12: =IF(AD12=0,AJ12,(1*75000*12)+(AJ12)-AD12) -> 0 | AY12: =IF(AE12=0,AK12,(1*100000*12)+(AK12)-AE12) -> 0 | AZ12: =SUM(AV12:AY12)-BF12+Z12+BH12+BI12+BJ12+BK12+BL12+BM12 -> 0 | BC12: =F12 -> 0 | BD12: =IF(AZ12=0,(AZ12-BA12-BC12),(AZ12-BA12-BB12-BC12)) -> 0 | BF12: =Z12*1/100*BG12 -> 0 | BG12: 11 | BO12: ACHAT SOURIS ET PHOTOCOPIE | BP12: FONDS DE ROULEMENT
A13: AS201651 | B13: =VLOOKUP(A13,[5]LISTADHERENT!A$5:H$50,3,0) -> DOMOU FABIEN | C13: =IF(I13<>"ECHEC",D13+E13+F13-U13,0) -> 0 | D13: =VLOOKUP(A13,[6]HISTOBQUEJANV25!$A$6:$H$48,5,0) -> 50000 | E13: =VLOOKUP(A13,[6]HISTOBQUEJANV25!$A$6:$H$43,4,0) -> 0 | F13: =VLOOKUP(A13,[6]HISTOBQUEJANV25!$A$6:$H$43,6,0) -> 0 | H13: =IF(I13="ESPECES",3000,0) -> 0 | I13: =IF($D13<>0,"BANQUE",IF($E13<>0,"ESPECES","ECHEC")) -> BANQUE | J13: 1 | K13: =IF($D13<>0,J13*50000,IF($E13<>0,J13*50000,0)) -> 50000 | M13: =IF($D13<>0,L13*75000,IF($E13<>0,L13*75000,0)) -> 0 | O13: =IF($D13<>0,N13*100000,IF($E13<>0,N13*100000,0)) -> 0 | U13: =G13+H13+S13+R13+P13+O13+M13+K13+Q13+V13+W13 -> 50000 | Y13: =K13+M13+O13 -> 50000 | AQ13: =IF(I13="ECHEC",((K13+M13+O13)*20/100),0) -> 0 | AR13: =IF(I13="ECHEC",((K13+M13+O13)*20/100),0) -> 0 | AS13: =IF(I13="ECHEC",0,(K13+G13-25000)) -> 25000 | AW13: =IF(AC13=0,AI13,(1*25000*12)+AI13-AC13) -> 0 | AX13: =IF(AD13=0,AJ13,(1*75000*12)+(AJ13)-AD13) -> 0 | AY13: =IF(AE13=0,AK13,(1*100000*12)+(AK13)-AE13) -> 0 | AZ13: =SUM(AV13:AY13)-BF13+Z13+BH13+BI13+BJ13+BK13+BL13+BM13 -> 0 | BC13: =F13 -> 0 | BD13: =IF(AZ13=0,(AZ13-BA13-BC13),(AZ13-BA13-BB13-BC13)) -> 0 | BF13: =Z13*1/100*BG13 -> 0 | BG13: 11 | BO13: TAXI BANQUE | BP13: FONDS DE ROULEMENT | BQ13: 6000
A14: AS201609 | B14: =VLOOKUP(A14,[5]LISTADHERENT!A$5:H$50,3,0) -> DONHOU DAVID | C14: =IF(I14<>"ECHEC",D14+E14+F14-U14,0) -> 0 | D14: =VLOOKUP(A14,[6]HISTOBQUEJANV25!$A$6:$H$48,5,0) -> 50000 | E14: =VLOOKUP(A14,[6]HISTOBQUEJANV25!$A$6:$H$43,4,0) -> 0 | F14: =VLOOKUP(A14,[6]HISTOBQUEJANV25!$A$6:$H$43,6,0) -> 0 | H14: 0 | I14: =IF($D14<>0,"BANQUE",IF($E14<>0,"ESPECES","ECHEC")) -> BANQUE | J14: 1 | K14: =IF($D14<>0,J14*50000,IF($E14<>0,J14*50000,0)) -> 50000 | M14: =IF($D14<>0,L14*75000,IF($E14<>0,L14*75000,0)) -> 0 | O14: =IF($D14<>0,N14*100000,IF($E14<>0,N14*100000,0)) -> 0 | U14: =G14+H14+S14+R14+P14+O14+M14+K14+Q14+V14+W14 -> 50000 | Y14: =K14+M14+O14 -> 50000 | AQ14: =IF(I14="ECHEC",((K14+M14+O14)*20/100),0) -> 0 | AR14: =IF(I14="ECHEC",((K14+M14+O14)*20/100),0) -> 0 | AS14: =IF(I14="ECHEC",0,(K14+G14-25000)) -> 25000 | AW14: =IF(AC14=0,AI14,(1*25000*12)+AI14-AC14) -> 0 | AX14: =IF(AD14=0,AJ14,(1*75000*12)+(AJ14)-AD14) -> 0 | AY14: =IF(AE14=0,AK14,(1*100000*12)+(AK14)-AE14) -> 0 | AZ14: =SUM(AV14:AY14)-BF14+Z14+BH14+BI14+BJ14+BK14+BL14+BM14 -> 0 | BC14: =F14 -> 0 | BD14: =IF(AZ14=0,(AZ14-BA14-BC14),(AZ14-BA14-BB14-BC14)) -> 0 | BF14: =Z14*1/100*BG14 -> 0 | BG14: 11 | BO14: ACHAT TERRAIN | BP14: FONDS DE ROULEMENT
A15: AS201663 | B15: =VLOOKUP(A15,[5]LISTADHERENT!A$5:H$50,3,0) -> FAMPOU PAUL | C15: =IF(I15<>"ECHEC",D15+E15+F15-U15,0) -> 0 | D15: =VLOOKUP(A15,[6]HISTOBQUEJANV25!$A$6:$H$48,5,0) -> 0 | E15: =VLOOKUP(A15,[6]HISTOBQUEJANV25!$A$6:$H$43,4,0) -> 0 | F15: =VLOOKUP(A15,[6]HISTOBQUEJANV25!$A$6:$H$43,6,0) -> 0 | H15: 0 | I15: ECHEC | J15: 1 | K15: =IF($D15<>0,J15*50000,IF($E15<>0,J15*50000,0)) -> 0 | M15: =IF($D15<>0,L15*75000,IF($E15<>0,L15*75000,0)) -> 0 | N15: 1 | O15: =IF($D15<>0,N15*100000,IF($E15<>0,N15*100000,0)) -> 0 | U15: =G15+H15+S15+R15+P15+O15+M15+K15+Q15+V15+W15 -> 0 | Y15: =K15+M15+O15 -> 0 | AQ15: =IF(I15="ECHEC",((K15+M15+O15)*20/100),0) -> 0 | AR15: =IF(I15="ECHEC",((K15+M15+O15)*20/100),0) -> 0 | AS15: =IF(I15="ECHEC",0,(K15+G15-25000)) -> 0 | AW15: =IF(AC15=0,AI15,(1*25000*12)+AI15-AC15) -> 0 | AX15: =IF(AD15=0,AJ15,(1*75000*12)+(AJ15)-AD15) -> 0 | AY15: =IF(AE15=0,AK15,(1*100000*12)+(AK15)-AE15) -> 0 | AZ15: =SUM(AV15:AY15)-BF15+Z15+BH15+BI15+BJ15+BK15+BL15+BM15 -> 0 | BC15: =F15 -> 0 | BD15: =IF(AZ15=0,(AZ15-BA15-BC15),(AZ15-BA15-BB15-BC15)) -> 0 | BF15: =Z15*1/100*BG15 -> 0 | BG15: 11 | BO15: ACHAT TERRAIN | BP15: FONDS DE ROULEMENT
A16: AS201611 | B16: =VLOOKUP(A16,[5]LISTADHERENT!A$5:H$50,3,0) -> HENGUE PAUL OMER | C16: =IF(I16<>"ECHEC",D16+E16+F16-U16,0) -> 0 | D16: =VLOOKUP(A16,[6]HISTOBQUEJANV25!$A$6:$H$48,5,0) -> 125000 | E16: =VLOOKUP(A16,[6]HISTOBQUEJANV25!$A$6:$H$43,4,0) -> 0 | F16: =VLOOKUP(A16,[6]HISTOBQUEJANV25!$A$6:$H$43,6,0) -> 0 | H16: =IF(I16="ESPECES",3000,0) -> 0 | I16: =IF($D16<>0,"BANQUE",IF($E16<>0,"ESPECES","ECHEC")) -> BANQUE | J16: 1 | K16: =IF($D16<>0,J16*50000,IF($E16<>0,J16*50000,0)) -> 50000 | L16: 1 | M16: =IF($D16<>0,L16*75000,IF($E16<>0,L16*75000,0)) -> 75000 | O16: =IF($D16<>0,N16*100000,IF($E16<>0,N16*100000,0)) -> 0 | U16: =G16+H16+S16+R16+P16+O16+M16+K16+Q16+V16+W16 -> 125000 | Y16: =K16+M16+O16 -> 125000 | AQ16: =IF(I16="ECHEC",((K16+M16+O16)*20/100),0) -> 0 | AR16: =IF(I16="ECHEC",((K16+M16+O16)*20/100),0) -> 0 | AS16: =IF(I16="ECHEC",0,(K16+G16-25000)) -> 25000 | AW16: =IF(AC16=0,AI16,(1*25000*12)+AI16-AC16) -> 0 | AX16: =IF(AD16=0,AJ16,(1*75000*12)+(AJ16)-AD16) -> 0 | AY16: =IF(AE16=0,AK16,(1*100000*12)+(AK16)-AE16) -> 0 | AZ16: =SUM(AV16:AY16)-BF16+Z16+BH16+BI16+BJ16+BK16+BL16+BM16 -> 0 | BC16: =F16 -> 0 | BD16: =IF(AZ16=0,(AZ16-BA16-BC16),(AZ16-BA16-BB16-BC16)) -> 0 | BF16: =Z16*1/100*BG16 -> 0 | BG16: 11
A17: AS201613 | B17: =VLOOKUP(A17,[5]LISTADHERENT!A$5:H$50,3,0) -> HOTCHO BENJAMIN | C17: =IF(I17<>"ECHEC",D17+E17+F17-U17,0) -> 0 | D17: =VLOOKUP(A17,[6]HISTOBQUEJANV25!$A$6:$H$48,5,0) -> 250000 | E17: =VLOOKUP(A17,[6]HISTOBQUEJANV25!$A$6:$H$43,4,0) -> 25000 | F17: =VLOOKUP(A17,[6]HISTOBQUEJANV25!$A$6:$H$43,6,0) -> 0 | G17: 50000 | H17: =IF(I17="ESPECES",3000,0) -> 0 | I17: =IF($D17<>0,"BANQUE",IF($E17<>0,"ESPECES","ECHEC")) -> BANQUE | J17: 1 | K17: =IF($D17<>0,J17*50000,IF($E17<>0,J17*50000,0)) -> 50000 | L17: 1 | M17: =IF($D17<>0,L17*75000,IF($E17<>0,L17*75000,0)) -> 75000 | N17: 1 | O17: =IF($D17<>0,N17*100000,IF($E17<>0,N17*100000,0)) -> 100000 | U17: =G17+H17+S17+R17+P17+O17+M17+K17+Q17+V17+W17 -> 275000 | Y17: =K17+M17+O17 -> 225000 | AQ17: =IF(I17="ECHEC",((K17+M17+O17)*20/100),0) -> 0 | AR17: =IF(I17="ECHEC",((K17+M17+O17)*20/100),0) -> 0 | AS17: =IF(I17="ECHEC",0,(K17+G17-25000)) -> 75000 | AW17: =IF(AC17=0,AI17,(1*25000*12)+AI17-AC17) -> 0 | AX17: =IF(AD17=0,AJ17,(1*75000*12)+(AJ17)-AD17) -> 0 | AY17: =IF(AE17=0,AK17,(1*100000*12)+(AK17)-AE17) -> 0 | AZ17: =SUM(AV17:AY17)-BF17+Z17+BH17+BI17+BJ17+BK17+BL17+BM17 -> 0 | BC17: =F17 -> 0 | BD17: =IF(AZ17=0,(AZ17-BA17-BC17),(AZ17-BA17-BB17-BC17)) -> 0 | BF17: =Z17*1/100*BG17 -> 0 | BG17: 11 | BO17: S/TOTAL | BQ17: =SUM(BQ6:BQ16) -> 72000
A18: AS201617 | B18: =VLOOKUP(A18,[5]LISTADHERENT!A$5:H$50,3,0) -> KOUAMOU MOISE | C18: =IF(I18<>"ECHEC",D18+E18+F18-U18,0) -> 0 | D18: =VLOOKUP(A18,[6]HISTOBQUEJANV25!$A$6:$H$48,5,0) -> 150000 | E18: =VLOOKUP(A18,[6]HISTOBQUEJANV25!$A$6:$H$43,4,0) -> 0 | F18: =VLOOKUP(A18,[6]HISTOBQUEJANV25!$A$6:$H$43,6,0) -> 346500 | H18: =IF(I18="ESPECES",3000,0) -> 0 | I18: =IF($D18<>0,"BANQUE",IF($E18<>0,"ESPECES","ECHEC")) -> BANQUE | J18: 1 | K18: =IF($D18<>0,J18*50000,IF($E18<>0,J18*50000,0)) -> 50000 | M18: =IF($D18<>0,L18*75000,IF($E18<>0,L18*75000,0)) -> 0 | N18: 1 | O18: =IF($D18<>0,N18*100000,IF($E18<>0,N18*100000,0)) -> 100000 | S18: 346500 | T18: BANQUE | U18: =G18+H18+S18+R18+P18+O18+M18+K18+Q18+V18+W18 -> 496500 | Y18: =K18+M18+O18 -> 150000 | AE18: 115000 | AF18: BANQUE | AQ18: =IF(I18="ECHEC",((K18+M18+O18)*20/100),0) -> 0 | AR18: =IF(I18="ECHEC",((K18+M18+O18)*20/100),0) -> 0 | AS18: =IF(I18="ECHEC",0,(K18+G18-25000)) -> 25000 | AW18: =IF(AC18=0,AI18,(1*25000*12)+AI18-AC18) -> 0 | AX18: =IF(AD18=0,AJ18,(1*75000*12)+(AJ18)-AD18) -> 0 | AY18: =IF(AE18=0,AK18,(1*100000*12)+(AK18)-AE18) -> 1085000 | AZ18: =SUM(AV18:AY18)-BF18+Z18+BH18+BI18+BJ18+BK18+BL18+BM18 -> 1085000 | BC18: =F18 -> 346500 | BD18: =IF(AZ18=0,(AZ18-BA18-BC18),(AZ18-BA18-BB18-BC18)) -> 738500 | BE18: OK | BF18: =Z18*1/100*BG18 -> 0 | BG18: 11
A19: AS201619 | B19: =VLOOKUP(A19,[5]LISTADHERENT!A$5:H$50,3,0) -> KOUATCHO MESSACK | C19: =IF(I19<>"ECHEC",D19+E19+F19-U19,0) -> 0 | D19: =VLOOKUP(A19,[6]HISTOBQUEJANV25!$A$6:$H$48,5,0)+75000 -> 235000 | E19: =VLOOKUP(A19,[6]HISTOBQUEJANV25!$A$6:$H$43,4,0) -> 0 | F19: =VLOOKUP(A19,[6]HISTOBQUEJANV25!$A$6:$H$43,6,0) -> 0 | G19: 10000 | H19: =IF(I19="ESPECES",3000,0) -> 0 | I19: =IF($D19<>0,"BANQUE",IF($E19<>0,"ESPECES","ECHEC")) -> BANQUE | J19: 1 | K19: =IF($D19<>0,J19*50000,IF($E19<>0,J19*50000,0)) -> 50000 | L19: 1 | M19: =IF($D19<>0,L19*75000,IF($E19<>0,L19*75000,0)) -> 75000 | N19: 1 | O19: =IF($D19<>0,N19*100000,IF($E19<>0,N19*100000,0)) -> 100000 | U19: =G19+H19+S19+R19+P19+O19+M19+K19+Q19+V19+W19 -> 235000 | Y19: =K19+M19+O19 -> 225000 | AE19: 105000 | AF19: BANQUE | AQ19: =IF(I19="ECHEC",((K19+M19+O19)*20/100),0) -> 0 | AR19: =IF(I19="ECHEC",((K19+M19+O19)*20/100),0) -> 0 | AS19: =IF(I19="ECHEC",0,(K19+G19-25000)) -> 35000 | AW19: =IF(AC19=0,AI19,(1*25000*12)+AI19-AC19) -> 0 | AX19: =IF(AD19=0,AJ19,(1*75000*12)+(AJ19)-AD19) -> 0 | AY19: =IF(AE19=0,AK19,(1*100000*12)+(AK19)-AE19) -> 1095000 | AZ19: =SUM(AV19:AY19)-BF19+Z19+BH19+BI19+BJ19+BK19+BL19+BM19 -> 1095000 | BC19: =F19 -> 0 | BD19: =IF(AZ19=0,(AZ19-BA19-BC19),(AZ19-BA19-BB19-BC19)) -> 1095000 | BE19: OK | BF19: =Z19*1/100*BG19 -> 0 | BG19: 11 | BO19: TERRAIN NYOM | BP19: AUTRES DEPENSES
A20: AS201620 | B20: =VLOOKUP(A20,[5]LISTADHERENT!A$5:H$50,3,0) -> LOWE JEAN
A21: AS201661 | B21: =VLOOKUP(A21,[5]LISTADHERENT!A$5:H$50,3,0) -> MASSEUNGOUE DAGOBERT | C21: =IF(I21<>"ECHEC",D21+E21+F21-U21,0) -> 0 | D21: =VLOOKUP(A21,[6]HISTOBQUEJANV25!$A$6:$H$48,5,0) -> 650000 | E21: =VLOOKUP(A21,[6]HISTOBQUEJANV25!$A$6:$H$43,4,0) -> 0 | F21: =VLOOKUP(A21,[6]HISTOBQUEJANV25!$A$6:$H$43,6,0) -> 0 | G21: 600000 | H21: =IF(I21="ESPECES",3000,0) -> 0 | I21: =IF($D21<>0,"BANQUE",IF($E21<>0,"ESPECES","ECHEC")) -> BANQUE | J21: 1 | K21: =IF($D21<>0,J21*50000,IF($E21<>0,J21*50000,0)) -> 50000 | M21: =IF($D21<>0,L21*75000,IF($E21<>0,L21*75000,0)) -> 0 | O21: =IF($D21<>0,N21*100000,IF($E21<>0,N21*100000,0)) -> 0 | U21: =G21+H21+S21+R21+P21+O21+M21+K21+Q21+V21+W21 -> 650000 | Y21: =K21+M21+O21 -> 50000 | AQ21: =IF(I21="ECHEC",((K21+M21+O21)*20/100),0) -> 0 | AR21: =IF(I21="ECHEC",((K21+M21+O21)*20/100),0) -> 0 | AS21: =IF(I21="ECHEC",0,(K21+G21-25000)) -> 625000 | AW21: =IF(AC21=0,AI21,(1*25000*12)+AI21-AC21) -> 0 | AX21: =IF(AD21=0,AJ21,(1*75000*12)+(AJ21)-AD21) -> 0 | AY21: =IF(AE21=0,AK21,(1*100000*12)+(AK21)-AE21) -> 0 | AZ21: =SUM(AV21:AY21)-BF21+Z21+BH21+BI21+BJ21+BK21+BL21+BM21 -> 0 | BC21: =F21 -> 0 | BD21: =IF(AZ21=0,(AZ21-BA21-BC21),(AZ21-BA21-BB21-BC21)) -> 0 | BF21: =Z21*1/100*BG21 -> 0 | BG21: 11 | BO21: RETRAIT COMPTE FOYER | BQ21: =371000 -> 371000
A22: AS201649 | B22: =VLOOKUP(A22,[5]LISTADHERENT!A$5:H$50,3,0) -> MBOGNING TUGMA GUY | C22: =IF(I22<>"ECHEC",D22+E22+F22-U22,0) -> 0 | D22: =VLOOKUP(A22,[6]HISTOBQUEJANV25!$A$6:$H$48,5,0) -> 325000 | E22: =VLOOKUP(A22,[6]HISTOBQUEJANV25!$A$6:$H$43,4,0) -> 0 | F22: =VLOOKUP(A22,[6]HISTOBQUEJANV25!$A$6:$H$43,6,0) -> 0 | H22: =IF(I22="ESPECES",3000,0) -> 0 | I22: =IF($D22<>0,"BANQUE",IF($E22<>0,"ESPECES","ECHEC")) -> BANQUE | J22: 1 | K22: =IF($D22<>0,J22*50000,IF($E22<>0,J22*50000,0)) -> 50000 | L22: 1 | M22: =IF($D22<>0,L22*75000,IF($E22<>0,L22*75000,0)) -> 75000 | N22: 2 | O22: =IF($D22<>0,N22*100000,IF($E22<>0,N22*100000,0)) -> 200000 | U22: =G22+H22+S22+R22+P22+O22+M22+K22+Q22+V22+W22 -> 325000 | Y22: =K22+M22+O22 -> 325000 | AQ22: =IF(I22="ECHEC",((K22+M22+O22)*20/100),0) -> 0 | AR22: =IF(I22="ECHEC",((K22+M22+O22)*20/100),0) -> 0 | AS22: =IF(I22="ECHEC",0,(K22+G22-25000)) -> 25000 | AW22: =IF(AC22=0,AI22,(1*25000*12)+AI22-AC22) -> 0 | AX22: =IF(AD22=0,AJ22,(1*75000*12)+(AJ22)-AD22) -> 0 | AY22: =IF(AE22=0,AK22,(1*100000*12)+(AK22)-AE22) -> 0 | AZ22: =SUM(AV22:AY22)-BF22+Z22+BH22+BI22+BJ22+BK22+BL22+BM22 -> 0 | BC22: =F22 -> 0 | BD22: =IF(AZ22=0,(AZ22-BA22-BC22),(AZ22-BA22-BB22-BC22)) -> 0 | BF22: =Z22*1/100*BG22 -> 0 | BG22: 11 | BO22: RETRAIT AIDE | BQ22: 30000
A23: AS201639 | B23: =VLOOKUP(A23,[5]LISTADHERENT!A$5:H$50,3,0) -> NANGUEN MARTIN | C23: =IF(I23<>"ECHEC",D23+E23+F23-U23,0) -> 0 | D23: =VLOOKUP(A23,[6]HISTOBQUEJANV25!$A$6:$H$48,5,0) -> 50000 | E23: =VLOOKUP(A23,[6]HISTOBQUEJANV25!$A$6:$H$43,4,0) -> 0 | F23: =VLOOKUP(A23,[6]HISTOBQUEJANV25!$A$6:$H$43,6,0) -> 0 | H23: =IF(I23="ESPECES",3000,0) -> 0 | I23: =IF($D23<>0,"BANQUE",IF($E23<>0,"ESPECES","ECHEC")) -> BANQUE | J23: 1 | K23: =IF($D23<>0,J23*50000,IF($E23<>0,J23*50000,0)) -> 50000 | M23: =IF($D23<>0,L23*75000,IF($E23<>0,L23*75000,0)) -> 0 | O23: =IF($D23<>0,N23*100000,IF($E23<>0,N23*100000,0)) -> 0 | U23: =G23+H23+S23+R23+P23+O23+M23+K23+Q23+V23+W23 -> 50000 | Y23: =K23+M23+O23 -> 50000 | AQ23: =IF(I23="ECHEC",((K23+M23+O23)*20/100),0) -> 0 | AR23: =IF(I23="ECHEC",((K23+M23+O23)*20/100),0) -> 0 | AS23: =IF(I23="ECHEC",0,(K23+G23-25000)) -> 25000 | AW23: =IF(AC23=0,AI23,(1*25000*12)+AI23-AC23) -> 0 | AX23: =IF(AD23=0,AJ23,(1*75000*12)+(AJ23)-AD23) -> 0 | AY23: =IF(AE23=0,AK23,(1*100000*12)+(AK23)-AE23) -> 0 | AZ23: =SUM(AV23:AY23)-BF23+Z23+BH23+BI23+BJ23+BK23+BL23+BM23 -> 0 | BC23: =F23 -> 0 | BD23: =IF(AZ23=0,(AZ23-BA23-BC23),(AZ23-BA23-BB23-BC23)) -> 0 | BF23: =Z23*1/100*BG23 -> 0 | BG23: 11
A24: AS201621 | B24: =VLOOKUP(A24,[5]LISTADHERENT!A$5:H$50,3,0) -> NANKAM APPOLINAIRE | C24: =IF(I24<>"ECHEC",D24+E24+F24-U24,0) -> 0 | D24: =VLOOKUP(A24,[6]HISTOBQUEJANV25!$A$6:$H$48,5,0) -> 125000 | E24: =VLOOKUP(A24,[6]HISTOBQUEJANV25!$A$6:$H$43,4,0) -> 0 | F24: =VLOOKUP(A24,[6]HISTOBQUEJANV25!$A$6:$H$43,6,0) -> 0 | H24: =IF(I24="ESPECES",3000,0) -> 0 | I24: =IF($D24<>0,"BANQUE",IF($E24<>0,"ESPECES","ECHEC")) -> BANQUE | J24: 1 | K24: =IF($D24<>0,J24*50000,IF($E24<>0,J24*50000,0)) -> 50000 | L24: 1 | M24: =IF($D24<>0,L24*75000,IF($E24<>0,L24*75000,0)) -> 75000 | O24: =IF($D24<>0,N24*100000,IF($E24<>0,N24*100000,0)) -> 0 | U24: =G24+H24+S24+R24+P24+O24+M24+K24+Q24+V24+W24 -> 125000 | Y24: =K24+M24+O24 -> 125000 | AD24: 7500 | AF24: BANQUE | AQ24: =IF(I24="ECHEC",((K24+M24+O24)*20/100),0) -> 0 | AR24: =IF(I24="ECHEC",((K24+M24+O24)*20/100),0) -> 0 | AS24: =IF(I24="ECHEC",0,(K24+G24-25000)) -> 25000 | AW24: =IF(AC24=0,AI24,(1*25000*12)+AI24-AC24) -> 0 | AX24: =IF(AD24=0,AJ24,(1*75000*12)+(AJ24)-AD24) -> 892500 | AY24: =IF(AE24=0,AK24,(1*100000*12)+(AK24)-AE24) -> 0 | AZ24: =SUM(AV24:AY24)-BF24+Z24+BH24+BI24+BJ24+BK24+BL24+BM24 -> 892500 | BA24: 32000 | BC24: =F24 -> 0 | BD24: =IF(AZ24=0,(AZ24-BA24-BC24),(AZ24-BA24-BB24-BC24)) -> 860500 | BE24: OK | BF24: =Z24*1/100*BG24 -> 0 | BG24: 11 | BO24: S/TOTAL | BQ24: =SUM(BQ19:BQ23) -> 401000
A25: AS201622 | B25: =VLOOKUP(A25,[5]LISTADHERENT!A$5:H$50,3,0) -> NDJOMO ETIENNE | C25: =IF(I25<>"ECHEC",D25+E25+F25-U25,0) -> 0 | D25: =VLOOKUP(A25,[6]HISTOBQUEJANV25!$A$6:$H$48,5,0) -> 260000 | E25: =VLOOKUP(A25,[6]HISTOBQUEJANV25!$A$6:$H$43,4,0) -> 0 | F25: =VLOOKUP(A25,[6]HISTOBQUEJANV25!$A$6:$H$43,6,0) -> 0 | G25: 10000 | H25: =IF(I25="ESPECES",3000,0) -> 0 | I25: =IF($D25<>0,"BANQUE",IF($E25<>0,"ESPECES","ECHEC")) -> BANQUE | J25: 1 | K25: =IF($D25<>0,J25*50000,IF($E25<>0,J25*50000,0)) -> 50000 | M25: =IF($D25<>0,L25*75000,IF($E25<>0,L25*75000,0)) -> 0 | N25: 2 | O25: =IF($D25<>0,N25*100000,IF($E25<>0,N25*100000,0)) -> 200000 | U25: =G25+H25+S25+R25+P25+O25+M25+K25+Q25+V25+W25 -> 260000 | Y25: =K25+M25+O25 -> 250000 | AQ25: =IF(I25="ECHEC",((K25+M25+O25)*20/100),0) -> 0 | AR25: =IF(I25="ECHEC",((K25+M25+O25)*20/100),0) -> 0 | AS25: =IF(I25="ECHEC",0,(K25+G25-25000)) -> 35000 | AW25: =IF(AC25=0,AI25,(1*25000*12)+AI25-AC25) -> 0 | AX25: =IF(AD25=0,AJ25,(1*75000*12)+(AJ25)-AD25) -> 0 | AY25: =IF(AE25=0,AK25,(1*100000*12)+(AK25)-AE25) -> 0 | AZ25: =SUM(AV25:AY25)-BF25+Z25+BH25+BI25+BJ25+BK25+BL25+BM25 -> 0 | BC25: =F25 -> 0 | BD25: =IF(AZ25=0,(AZ25-BA25-BC25),(AZ25-BA25-BB25-BC25)) -> 0 | BF25: =Z25*1/100*BG25 -> 0 | BG25: 11
A26: AS201624 | B26: =VLOOKUP(A26,[5]LISTADHERENT!A$5:H$50,3,0) -> NGONDIEP CLAUDE | C26: =IF(I26<>"ECHEC",D26+E26+F26-U26,0) -> 0 | D26: =VLOOKUP(A26,[6]HISTOBQUEJANV25!$A$6:$H$48,5,0) -> 240000 | E26: =VLOOKUP(A26,[6]HISTOBQUEJANV25!$A$6:$H$43,4,0) -> 0 | F26: =VLOOKUP(A26,[6]HISTOBQUEJANV25!$A$6:$H$43,6,0) -> 0 | G26: 15000 | H26: =IF(I26="ESPECES",3000,0) -> 0 | I26: =IF($D26<>0,"BANQUE",IF($E26<>0,"ESPECES","ECHEC")) -> BANQUE | J26: 1 | K26: =IF($D26<>0,J26*50000,IF($E26<>0,J26*50000,0)) -> 50000 | L26: 1 | M26: =IF($D26<>0,L26*75000,IF($E26<>0,L26*75000,0)) -> 75000 | N26: 1 | O26: =IF($D26<>0,N26*100000,IF($E26<>0,N26*100000,0)) -> 100000 | U26: =G26+H26+S26+R26+P26+O26+M26+K26+Q26+V26+W26 -> 240000 | Y26: =K26+M26+O26 -> 225000 | Z26: 1000000 | AA26: BANQUE | AQ26: =IF(I26="ECHEC",((K26+M26+O26)*20/100),0) -> 0 | AR26: =IF(I26="ECHEC",((K26+M26+O26)*20/100),0) -> 0 | AS26: =IF(I26="ECHEC",0,(K26+G26-25000)) -> 40000 | AW26: =IF(AC26=0,AI26,(1*25000*12)+AI26-AC26) -> 0 | AX26: =IF(AD26=0,AJ26,(1*75000*12)+(AJ26)-AD26) -> 0 | AY26: =IF(AE26=0,AK26,(1*100000*12)+(AK26)-AE26) -> 0 | AZ26: =SUM(AV26:AY26)-BF26+Z26+BH26+BI26+BJ26+BK26+BL26+BM26 -> 890000 | BC26: =F26 -> 0 | BD26: =IF(AZ26=0,(AZ26-BA26-BC26),(AZ26-BA26-BB26-BC26)) -> 890000 | BE26: OK | BF26: =Z26*1/100*BG26 -> 110000 | BG26: 11 | BO26: GRATIFICATION BUREAU 2023 | BP26: FRAIS EXEPTIONNEL | BQ26: 200000
A27: AS201626 | B27: =VLOOKUP(A27,[5]LISTADHERENT!A$5:H$50,3,0) -> NGUIEMEGNI MATHIEU BLAISE | C27: =IF(I27<>"ECHEC",D27+E27+F27-U27,0) -> 0 | D27: =VLOOKUP(A27,[6]HISTOBQUEJANV25!$A$6:$H$48,5,0) -> 225000 | E27: =VLOOKUP(A27,[6]HISTOBQUEJANV25!$A$6:$H$43,4,0) -> 25000 | F27: =VLOOKUP(A27,[6]HISTOBQUEJANV25!$A$6:$H$43,6,0) -> 0 | H27: =IF(I27="ESPECES",3000,0) -> 0 | I27: =IF($D27<>0,"BANQUE",IF($E27<>0,"ESPECES","ECHEC")) -> BANQUE | J27: 1 | K27: =IF($D27<>0,J27*50000,IF($E27<>0,J27*50000,0)) -> 50000 | M27: =IF($D27<>0,L27*75000,IF($E27<>0,L27*75000,0)) -> 0 | N27: 2 | O27: =IF($D27<>0,N27*100000,IF($E27<>0,N27*100000,0)) -> 200000 | U27: =G27+H27+S27+R27+P27+O27+M27+K27+Q27+V27+W27 -> 250000 | Y27: =K27+M27+O27 -> 250000 | AE27: 120000 | AF27: BANQUE | AQ27: =IF(I27="ECHEC",((K27+M27+O27)*20/100),0) -> 0 | AR27: =IF(I27="ECHEC",((K27+M27+O27)*20/100),0) -> 0 | AS27: =IF(I27="ECHEC",0,(K27+G27-25000)) -> 25000 | AW27: =IF(AC27=0,AI27,(1*25000*12)+AI27-AC27) -> 0 | AX27: =IF(AD27=0,AJ27,(1*75000*12)+(AJ27)-AD27) -> 0 | AY27: =IF(AE27=0,AK27,(1*100000*12)+(AK27)-AE27) -> 1080000 | AZ27: =SUM(AV27:AY27)-BF27+Z27+BH27+BI27+BJ27+BK27+BL27+BM27 -> 1080000 | BC27: =F27 -> 0 | BD27: =IF(AZ27=0,(AZ27-BA27-BC27),(AZ27-BA27-BB27-BC27)) -> 1080000 | BE27: OK | BF27: =Z27*1/100*BG27 -> 0 | BG27: 11 | BO27: DOSSIER TECHNIQUE NGIEMENI | BP27: FRAIS EXEPTIONNEL
A28: AS201628 | B28: =VLOOKUP(A28,[5]LISTADHERENT!A$5:H$50,3,0) -> NKAMGANG JUSTIN DEJOLIE | C28: =IF(I28<>"ECHEC",D28+E28+F28-U28,0) -> 0 | D28: =VLOOKUP(A28,[6]HISTOBQUEJANV25!$A$6:$H$48,5,0) -> 50000 | E28: =VLOOKUP(A28,[6]HISTOBQUEJANV25!$A$6:$H$43,4,0) -> 0 | F28: =VLOOKUP(A28,[6]HISTOBQUEJANV25!$A$6:$H$43,6,0) -> 0 | H28: =IF(I28="ESPECES",3000,0) -> 0 | I28: =IF($D28<>0,"BANQUE",IF($E28<>0,"ESPECES","ECHEC")) -> BANQUE | J28: 1 | K28: =IF($D28<>0,J28*50000,IF($E28<>0,J28*50000,0)) -> 50000 | M28: =IF($D28<>0,L28*75000,IF($E28<>0,L28*75000,0)) -> 0 | O28: =IF($D28<>0,N28*100000,IF($E28<>0,N28*100000,0)) -> 0 | U28: =G28+H28+S28+R28+P28+O28+M28+K28+Q28+V28+W28 -> 50000 | Y28: =K28+M28+O28 -> 50000 | AI28: 41000 | AL28: 1000 | AP28: BANQUE | AQ28: =IF(I28="ECHEC",((K28+M28+O28)*20/100),0) -> 0 | AR28: =IF(I28="ECHEC",((K28+M28+O28)*20/100),0) -> 0 | AS28: =IF(I28="ECHEC",0,(K28+G28-25000)) -> 25000 | AW28: =IF(AC28=0,AI28,(1*25000*12)+AI28-AC28) -> 41000 | AX28: =IF(AD28=0,AJ28,(1*75000*12)+(AJ28)-AD28) -> 0 | AY28: =IF(AE28=0,AK28,(1*100000*12)+(AK28)-AE28) -> 0 | AZ28: =SUM(AV28:AY28)-BF28+Z28+BH28+BI28+BJ28+BK28+BL28+BM28 -> 41000 | BA28: 41000 | BC28: =F28 -> 0 | BD28: =IF(AZ28=0,(AZ28-BA28-BC28),(AZ28-BA28-BB28-BC28)) -> 0 | BF28: =Z28*1/100*BG28 -> 0 | BG28: 11
A29: AS201656 | B29: =VLOOKUP(A29,[5]LISTADHERENT!A$5:H$50,3,0) -> NOUBE ETIENNE | C29: =IF(I29<>"ECHEC",D29+E29+F29-U29,0) -> 0 | D29: =VLOOKUP(A29,[6]HISTOBQUEJANV25!$A$6:$H$48,5,0) -> 50000 | E29: =VLOOKUP(A29,[6]HISTOBQUEJANV25!$A$6:$H$43,4,0) -> 0 | F29: =VLOOKUP(A29,[6]HISTOBQUEJANV25!$A$6:$H$43,6,0) -> 0 | H29: =IF(I29="ESPECES",3000,0) -> 0 | I29: =IF($D29<>0,"BANQUE",IF($E29<>0,"ESPECES","ECHEC")) -> BANQUE | J29: 1 | K29: =IF($D29<>0,J29*50000,IF($E29<>0,J29*50000,0)) -> 50000 | M29: =IF($D29<>0,L29*75000,IF($E29<>0,L29*75000,0)) -> 0 | O29: =IF($D29<>0,N29*100000,IF($E29<>0,N29*100000,0)) -> 0 | U29: =G29+H29+S29+R29+P29+O29+M29+K29+Q29+V29+W29 -> 50000 | Y29: =K29+M29+O29 -> 50000 | AQ29: =IF(I29="ECHEC",((K29+M29+O29)*20/100),0) -> 0 | AR29: =IF(I29="ECHEC",((K29+M29+O29)*20/100),0) -> 0 | AS29: =IF(I29="ECHEC",0,(K29+G29-25000)) -> 25000 | AW29: =IF(AC29=0,AI29,(1*25000*12)+AI29-AC29) -> 0 | AX29: =IF(AD29=0,AJ29,(1*75000*12)+(AJ29)-AD29) -> 0 | AY29: =IF(AE29=0,AK29,(1*100000*12)+(AK29)-AE29) -> 0 | AZ29: =SUM(AV29:AY29)-BF29+Z29+BH29+BI29+BJ29+BK29+BL29+BM29 -> 0 | BC29: =F29 -> 0 | BD29: =IF(AZ29=0,(AZ29-BA29-BC29),(AZ29-BA29-BB29-BC29)) -> 0 | BF29: =Z29*1/100*BG29 -> 0 | BG29: 11
A30: AS201633 | B30: =VLOOKUP(A30,[5]LISTADHERENT!A$5:H$50,3,0) -> PATEGO NJOSSU GUSTAVE | C30: =IF(I30<>"ECHEC",D30+E30+F30-U30,0) -> 0 | D30: =VLOOKUP(A30,[6]HISTOBQUEJANV25!$A$6:$H$48,5,0) -> 125000 | E30: =VLOOKUP(A30,[6]HISTOBQUEJANV25!$A$6:$H$43,4,0) -> 0 | F30: =VLOOKUP(A30,[6]HISTOBQUEJANV25!$A$6:$H$43,6,0) -> 0 | H30: =IF(I30="ESPECES",3000,0) -> 0 | I30: =IF($D30<>0,"BANQUE",IF($E30<>0,"ESPECES","ECHEC")) -> BANQUE | J30: 1 | K30: =IF($D30<>0,J30*50000,IF($E30<>0,J30*50000,0)) -> 50000 | L30: 1 | M30: =IF($D30<>0,L30*75000,IF($E30<>0,L30*75000,0)) -> 75000 | O30: =IF($D30<>0,N30*100000,IF($E30<>0,N30*100000,0)) -> 0 | U30: =G30+H30+S30+R30+P30+O30+M30+K30+Q30+V30+W30 -> 125000 | Y30: =K30+M30+O30 -> 125000 | AQ30: =IF(I30="ECHEC",((K30+M30+O30)*20/100),0) -> 0 | AR30: =IF(I30="ECHEC",((K30+M30+O30)*20/100),0) -> 0 | AS30: =IF(I30="ECHEC",0,(K30+G30-25000)) -> 25000 | AW30: =IF(AC30=0,AI30,(1*25000*12)+AI30-AC30) -> 0 | AX30: =IF(AD30=0,AJ30,(1*75000*12)+(AJ30)-AD30) -> 0 | AY30: =IF(AE30=0,AK30,(1*100000*12)+(AK30)-AE30) -> 0 | AZ30: =SUM(AV30:AY30)-BF30+Z30+BH30+BI30+BJ30+BK30+BL30+BM30+100000 -> 100000 | BA30: 100000 | BC30: =F30 -> 0 | BD30: =IF(AZ30=0,(AZ30-BA30-BC30),(AZ30-BA30-BB30-BC30)) -> 0 | BF30: =Z30*1/100*BG30 -> 0 | BG30: 11 | BO30: S/TOTAL | BQ30: =SUM(BQ26:BQ28) -> 200000
A31: AS201657 | B31: =VLOOKUP(A31,[5]LISTADHERENT!A$5:H$50,3,0) -> SEUMO POLYCARPE | C31: =IF(I31<>"ECHEC",D31+E31+F31-U31,0) -> 0 | D31: =VLOOKUP(A31,[6]HISTOBQUEJANV25!$A$6:$H$48,5,0) -> 50000 | E31: =VLOOKUP(A31,[6]HISTOBQUEJANV25!$A$6:$H$43,4,0) -> 0 | F31: =VLOOKUP(A31,[6]HISTOBQUEJANV25!$A$6:$H$43,6,0) -> 0 | H31: =IF(I31="ESPECES",3000,0) -> 0 | I31: =IF($D31<>0,"BANQUE",IF($E31<>0,"ESPECES","ECHEC")) -> BANQUE | J31: 1 | K31: =IF($D31<>0,J31*50000,IF($E31<>0,J31*50000,0)) -> 50000 | M31: =IF($D31<>0,L31*75000,IF($E31<>0,L31*75000,0)) -> 0 | O31: =IF($D31<>0,N31*100000,IF($E31<>0,N31*100000,0)) -> 0 | U31: =G31+H31+S31+R31+P31+O31+M31+K31+Q31+V31+W31 -> 50000 | Y31: =K31+M31+O31 -> 50000 | AC31: 30000 | AF31: BANQUE | AQ31: =IF(I31="ECHEC",((K31+M31+O31)*20/100),0) -> 0 | AR31: =IF(I31="ECHEC",((K31+M31+O31)*20/100),0) -> 0 | AS31: =IF(I31="ECHEC",0,(K31+G31-25000)) -> 25000 | AW31: =IF(AC31=0,AI31,(1*25000*12)+AI31-AC31) -> 270000 | AX31: =IF(AD31=0,AJ31,(1*75000*12)+(AJ31)-AD31) -> 0 | AY31: =IF(AE31=0,AK31,(1*100000*12)+(AK31)-AE31) -> 0 | AZ31: =SUM(AV31:AY31)-BF31+Z31+BH31+BI31+BJ31+BK31+BL31+BM31 -> 270000 | BC31: =F31 -> 0 | BD31: =IF(AZ31=0,(AZ31-BA31-BC31),(AZ31-BA31-BB31-BC31)) -> 270000 | BE31: OK | BF31: =Z31*1/100*BG31 -> 0 | BG31: 11
A32: AS201653 | B32: =VLOOKUP(A32,[5]LISTADHERENT!A$5:H$50,3,0) -> SIME BRICE | C32: =IF(I32<>"ECHEC",D32+E32+F32-U32,0) -> 0 | D32: =VLOOKUP(A32,[6]HISTOBQUEJANV25!$A$6:$H$48,5,0) -> 250000 | E32: =VLOOKUP(A32,[6]HISTOBQUEJANV25!$A$6:$H$43,4,0) -> 0 | F32: =VLOOKUP(A32,[6]HISTOBQUEJANV25!$A$6:$H$43,6,0) -> 0 | H32: =IF(I32="ESPECES",3000,0) -> 0 | I32: =IF($D32<>0,"BANQUE",IF($E32<>0,"ESPECES","ECHEC")) -> BANQUE | J32: 1 | K32: =IF($D32<>0,J32*50000,IF($E32<>0,J32*50000,0)) -> 50000 | M32: =IF($D32<>0,L32*75000,IF($E32<>0,L32*75000,0)) -> 0 | N32: 2 | O32: =IF($D32<>0,N32*100000,IF($E32<>0,N32*100000,0)) -> 200000 | U32: =G32+H32+S32+R32+P32+O32+M32+K32+Q32+V32+W32 -> 250000 | Y32: =K32+M32+O32 -> 250000 | AQ32: =IF(I32="ECHEC",((K32+M32+O32)*20/100),0) -> 0 | AR32: =IF(I32="ECHEC",((K32+M32+O32)*20/100),0) -> 0 | AS32: =IF(I32="ECHEC",0,(K32+G32-25000)) -> 25000 | AW32: =IF(AC32=0,AI32,(1*25000*12)+AI32-AC32) -> 0 | AX32: =IF(AD32=0,AJ32,(1*75000*12)+(AJ32)-AD32) -> 0 | AY32: =IF(AE32=0,AK32,(1*100000*12)+(AK32)-AE32) -> 0 | AZ32: =SUM(AV32:AY32)-BF32+Z32+BH32+BI32+BJ32+BK32+BL32+BM32 -> 0 | BC32: =F32 -> 0 | BD32: =IF(AZ32=0,(AZ32-BA32-BC32),(AZ32-BA32-BB32-BC32)) -> 0 | BF32: =Z32*1/100*BG32 -> 0 | BG32: 11 | BO32: DECES | BP32: MUTUELLE
A33: AS201629 | B33: =VLOOKUP(A33,[5]LISTADHERENT!A$5:H$50,3,0) -> SIMO FONGANG ERIC | C33: =IF(I33<>"ECHEC",D33+E33+F33-U33,0) -> 0 | D33: =VLOOKUP(A33,[6]HISTOBQUEJANV25!$A$6:$H$48,5,0) -> 50000 | E33: =VLOOKUP(A33,[6]HISTOBQUEJANV25!$A$6:$H$43,4,0) -> 0 | F33: =VLOOKUP(A33,[6]HISTOBQUEJANV25!$A$6:$H$43,6,0) -> 0 | H33: =IF(I33="ESPECES",3000,0) -> 0 | I33: =IF($D33<>0,"BANQUE",IF($E33<>0,"ESPECES","ECHEC")) -> BANQUE | J33: 1 | K33: =IF($D33<>0,J33*50000,IF($E33<>0,J33*50000,0)) -> 50000 | U33: =G33+H33+S33+R33+P33+O33+M33+K33+Q33+V33+W33 -> 50000 | Y33: =K33+M33+O33 -> 50000 | AQ33: =IF(I33="ECHEC",((K33+M33+O33)*20/100),0) -> 0 | AR33: =IF(I33="ECHEC",((K33+M33+O33)*20/100),0) -> 0 | AS33: =IF(I33="ECHEC",0,(K33+G33-25000)) -> 25000 | AW33: =IF(AC33=0,AI33,(1*25000*12)+AI33-AC33) -> 0 | AX33: =IF(AD33=0,AJ33,(1*75000*12)+(AJ33)-AD33) -> 0 | AY33: =IF(AE33=0,AK33,(1*100000*12)+(AK33)-AE33) -> 0 | AZ33: =SUM(AV33:AY33)-BF33+Z33+BH33+BI33+BJ33+BK33+BL33+BM33 -> 0 | BC33: =F33 -> 0 | BD33: =IF(AZ33=0,(AZ33-BA33-BC33),(AZ33-BA33-BB33-BC33)) -> 0 | BF33: =Z33*1/100*BG33 -> 0 | BG33: 11
A34: AS201638 | B34: =VLOOKUP(A34,[5]LISTADHERENT!A$5:H$50,3,0) -> SIMO PIERRE | C34: =IF(I34<>"ECHEC",D34+E34+F34-U34,0) -> 0 | D34: =VLOOKUP(A34,[6]HISTOBQUEJANV25!$A$6:$H$48,5,0) -> 150000 | E34: =VLOOKUP(A34,[6]HISTOBQUEJANV25!$A$6:$H$43,4,0) -> 0 | F34: =VLOOKUP(A34,[6]HISTOBQUEJANV25!$A$6:$H$43,6,0) -> 0 | H34: =IF(I34="ESPECES",3000,0) -> 0 | I34: =IF($D34<>0,"BANQUE",IF($E34<>0,"ESPECES","ECHEC")) -> BANQUE | J34: 1 | K34: =IF($D34<>0,J34*50000,IF($E34<>0,J34*50000,0)) -> 50000 | M34: =IF($D34<>0,L34*75000,IF($E34<>0,L34*75000,0)) -> 0 | N34: 1 | O34: =IF($D34<>0,N34*100000,IF($E34<>0,N34*100000,0)) -> 100000 | U34: =G34+H34+S34+R34+P34+O34+M34+K34+Q34+V34+W34 -> 150000 | Y34: =K34+M34+O34 -> 150000 | AQ34: =IF(I34="ECHEC",((K34+M34+O34)*20/100),0) -> 0 | AR34: =IF(I34="ECHEC",((K34+M34+O34)*20/100),0) -> 0 | AS34: =IF(I34="ECHEC",0,(K34+G34-25000)) -> 25000 | AW34: =IF(AC34=0,AI34,(1*25000*12)+AI34-AC34) -> 0 | AX34: =IF(AD34=0,AJ34,(1*75000*12)+(AJ34)-AD34) -> 0 | AY34: =IF(AE34=0,AK34,(1*100000*12)+(AK34)-AE34) -> 0 | AZ34: =SUM(AV34:AY34)-BF34+Z34+BH34+BI34+BJ34+BK34+BL34+BM34+100000 -> 100000 | BC34: =F34 -> 0 | BD34: =IF(AZ34=0,(AZ34-BA34-BC34),(AZ34-BA34-BB34-BC34)) -> 100000 | BE34: OK | BF34: =Z34*1/100*BG34 -> 0 | BG34: 11
A35: AS201641 | B35: =VLOOKUP(A35,[5]LISTADHERENT!A$5:H$50,3,0) -> TCHOUAMOU MATHIEU | C35: =IF(I35<>"ECHEC",D35+E35+F35-U35,0) -> 0 | D35: =VLOOKUP(A35,[6]HISTOBQUEJANV25!$A$6:$H$48,5,0) -> 125000 | E35: =VLOOKUP(A35,[6]HISTOBQUEJANV25!$A$6:$H$43,4,0) -> 0 | F35: =VLOOKUP(A35,[6]HISTOBQUEJANV25!$A$6:$H$43,6,0) -> 0 | H35: =IF(I35="ESPECES",3000,0) -> 0 | I35: =IF($D35<>0,"BANQUE",IF($E35<>0,"ESPECES","ECHEC")) -> BANQUE | J35: 1 | K35: =IF($D35<>0,J35*50000,IF($E35<>0,J35*50000,0)) -> 50000 | L35: 1 | M35: =IF($D35<>0,L35*75000,IF($E35<>0,L35*75000,0)) -> 75000 | O35: =IF($D35<>0,N35*100000,IF($E35<>0,N35*100000,0)) -> 0 | U35: =G35+H35+S35+R35+P35+O35+M35+K35+Q35+V35+W35 -> 125000 | Y35: =K35+M35+O35 -> 125000 | AQ35: =IF(I35="ECHEC",((K35+M35+O35)*20/100),0) -> 0 | AR35: =IF(I35="ECHEC",((K35+M35+O35)*20/100),0) -> 0 | AS35: =IF(I35="ECHEC",0,(K35+G35-25000)) -> 25000 | AW35: =IF(AC35=0,AI35,(1*25000*12)+AI35-AC35) -> 0 | AX35: =IF(AD35=0,AJ35,(1*75000*12)+(AJ35)-AD35) -> 0 | AY35: =IF(AE35=0,AK35,(1*100000*12)+(AK35)-AE35) -> 0 | AZ35: =SUM(AV35:AY35)-BF35+Z35+BH35+BI35+BJ35+BK35+BL35+BM35 -> 0 | BC35: =F35 -> 0 | BD35: =IF(AZ35=0,(AZ35-BA35-BC35),(AZ35-BA35-BB35-BC35)) -> 0 | BF35: =Z35*1/100*BG35 -> 0 | BG35: 11
A36: AS201660 | B36: =VLOOKUP(A36,[5]LISTADHERENT!A$5:H$50,3,0) -> TCHOUATEU AUGUSTIN | C36: =IF(I36<>"ECHEC",D36+E36+F36-U36,0) -> 0 | D36: =VLOOKUP(A36,[6]HISTOBQUEJANV25!$A$6:$H$48,5,0) -> 150000 | E36: =VLOOKUP(A36,[6]HISTOBQUEJANV25!$A$6:$H$43,4,0) -> 0 | F36: =VLOOKUP(A36,[6]HISTOBQUEJANV25!$A$6:$H$43,6,0) -> 0 | H36: =IF(I36="ESPECES",3000,0) -> 0 | I36: =IF($D36<>0,"BANQUE",IF($E36<>0,"ESPECES","ECHEC")) -> BANQUE | J36: 1 | K36: =IF($D36<>0,J36*50000,IF($E36<>0,J36*50000,0)) -> 50000 | M36: =IF($D36<>0,L36*75000,IF($E36<>0,L36*75000,0)) -> 0 | N36: 1 | O36: =IF($D36<>0,N36*100000,IF($E36<>0,N36*100000,0)) -> 100000 | U36: =G36+H36+S36+R36+P36+O36+M36+K36+Q36+V36+W36 -> 150000 | Y36: =K36+M36+O36 -> 150000 | AQ36: =IF(I36="ECHEC",((K36+M36+O36)*20/100),0) -> 0 | AR36: =IF(I36="ECHEC",((K36+M36+O36)*20/100),0) -> 0 | AS36: =IF(I36="ECHEC",0,(K36+G36-25000)) -> 25000 | AW36: =IF(AC36=0,AI36,(1*25000*12)+AI36-AC36) -> 0 | AX36: =IF(AD36=0,AJ36,(1*75000*12)+(AJ36)-AD36) -> 0 | AY36: =IF(AE36=0,AK36,(1*100000*12)+(AK36)-AE36) -> 0 | AZ36: =SUM(AV36:AY36)-BF36+Z36+BH36+BI36+BJ36+BK36+BL36+BM36 -> 0 | BC36: =F36 -> 0 | BD36: =IF(AZ36=0,(AZ36-BA36-BC36),(AZ36-BA36-BB36-BC36)) -> 0 | BF36: =Z36*1/100*BG36 -> 0 | BG36: 11 | BO36: S/TOTAL | BQ36: =SUM(BQ32:BQ35) -> 0
A37: AS201643 | B37: =VLOOKUP(A37,[5]LISTADHERENT!A$5:H$50,3,0) -> TCHOUTOU NANA CLAUDE | C37: =IF(I37<>"ECHEC",D37+E37+F37-U37,0) -> 0 | D37: =VLOOKUP(A37,[6]HISTOBQUEJANV25!$A$6:$H$48,5,0) -> 50000 | E37: =VLOOKUP(A37,[6]HISTOBQUEJANV25!$A$6:$H$43,4,0) -> 0 | F37: =VLOOKUP(A37,[6]HISTOBQUEJANV25!$A$6:$H$43,6,0) -> 0 | H37: =IF(I37="ESPECES",3000,0) -> 0 | I37: =IF($D37<>0,"BANQUE",IF($E37<>0,"ESPECES","ECHEC")) -> BANQUE | J37: 1 | K37: =IF($D37<>0,J37*50000,IF($E37<>0,J37*50000,0)) -> 50000 | M37: =IF($D37<>0,L37*75000,IF($E37<>0,L37*75000,0)) -> 0 | O37: =IF($D37<>0,N37*100000,IF($E37<>0,N37*100000,0)) -> 0 | U37: =G37+H37+S37+R37+P37+O37+M37+K37+Q37+V37+W37 -> 50000 | Y37: =K37+M37+O37 -> 50000 | AQ37: =IF(I37="ECHEC",((K37+M37+O37)*20/100),0) -> 0 | AR37: =IF(I37="ECHEC",((K37+M37+O37)*20/100),0) -> 0 | AS37: =IF(I37="ECHEC",0,(K37+G37-25000)) -> 25000 | AW37: =IF(AC37=0,AI37,(1*25000*12)+AI37-AC37) -> 0 | AX37: =IF(AD37=0,AJ37,(1*75000*12)+(AJ37)-AD37) -> 0 | AY37: =IF(AE37=0,AK37,(1*100000*12)+(AK37)-AE37) -> 0 | AZ37: =SUM(AV37:AY37)-BF37+Z37+BH37+BI37+BJ37+BK37+BL37+BM37 -> 0 | BC37: =F37 -> 0 | BD37: =IF(AZ37=0,(AZ37-BA37-BC37),(AZ37-BA37-BB37-BC37)) -> 0 | BF37: =Z37*1/100*BG37 -> 0 | BG37: 11 | BO37: S/TOTAL | BQ37: =SUM(BQ34:BQ36) -> 0
A38: AS201662 | B38: =VLOOKUP(A38,[5]LISTADHERENT!A$5:H$50,3,0) -> TIEYAM ERNEST | C38: =IF(I38<>"ECHEC",D38+E38+F38-U38,0) -> 0 | D38: =VLOOKUP(A38,[6]HISTOBQUEJANV25!$A$6:$H$48,5,0) -> 0 | E38: =VLOOKUP(A38,[6]HISTOBQUEJANV25!$A$6:$H$43,4,0) -> 50000 | F38: =VLOOKUP(A38,[6]HISTOBQUEJANV25!$A$6:$H$43,6,0) -> 0 | H38: 0 | I38: =IF($D38<>0,"BANQUE",IF($E38<>0,"ESPECES","ECHEC")) -> ESPECES | J38: 1 | K38: =IF($D38<>0,J38*50000,IF($E38<>0,J38*50000,0)) -> 50000 | M38: =IF($D38<>0,L38*75000,IF($E38<>0,L38*75000,0)) -> 0 | O38: =IF($D38<>0,N38*100000,IF($E38<>0,N38*100000,0)) -> 0 | U38: =G38+H38+S38+R38+P38+O38+M38+K38+Q38+V38+W38 -> 50000 | Y38: =K38+M38+O38 -> 50000 | AQ38: =IF(I38="ECHEC",((K38+M38+O38)*20/100),0) -> 0 | AR38: =IF(I38="ECHEC",((K38+M38+O38)*20/100),0) -> 0 | AS38: =IF(I38="ECHEC",0,(K38+G38-25000)) -> 25000 | AW38: =IF(AC38=0,AI38,(1*25000*12)+AI38-AC38) -> 0 | AX38: =IF(AD38=0,AJ38,(1*75000*12)+(AJ38)-AD38) -> 0 | AY38: =IF(AE38=0,AK38,(1*100000*12)+(AK38)-AE38) -> 0 | AZ38: =SUM(AV38:AY38)-BF38+Z38+BH38+BI38+BJ38+BK38+BL38+BM38 -> 0 | BC38: =F38 -> 0 | BD38: =IF(AZ38=0,(AZ38-BA38-BC38),(AZ38-BA38-BB38-BC38)) -> 0 | BF38: =Z38*1/100*BG38 -> 0 | BG38: 11
A39: AS201658 | B39: =VLOOKUP(A39,[5]LISTADHERENT!A$5:H$50,3,0) -> YANTCHOU GERVAIS | C39: =IF(I39<>"ECHEC",D39+E39+F39-U39,0) -> 0 | D39: =VLOOKUP(A39,[6]HISTOBQUEJANV25!$A$6:$H$48,5,0) -> 100000 | E39: =VLOOKUP(A39,[6]HISTOBQUEJANV25!$A$6:$H$43,4,0) -> 25000 | F39: =VLOOKUP(A39,[6]HISTOBQUEJANV25!$A$6:$H$43,6,0) -> 0 | H39: =IF(I39="ESPECES",3000,0) -> 0 | I39: =IF($D39<>0,"BANQUE",IF($E39<>0,"ESPECES","ECHEC")) -> BANQUE | J39: 1 | K39: =IF($D39<>0,J39*50000,IF($E39<>0,J39*50000,0)) -> 50000 | L39: 1 | M39: =IF($D39<>0,L39*75000,IF($E39<>0,L39*75000,0)) -> 75000 | O39: =IF($D39<>0,N39*100000,IF($E39<>0,N39*100000,0)) -> 0 | U39: =G39+H39+S39+R39+P39+O39+M39+K39+Q39+V39+W39 -> 125000 | Y39: =K39+M39+O39 -> 125000 | AQ39: =IF(I39="ECHEC",((K39+M39+O39)*20/100),0) -> 0 | AR39: =IF(I39="ECHEC",((K39+M39+O39)*20/100),0) -> 0 | AS39: =IF(I39="ECHEC",0,(K39+G39-25000)) -> 25000 | AW39: =IF(AC39=0,AI39,(1*25000*12)+AI39-AC39) -> 0 | AX39: =IF(AD39=0,AJ39,(1*75000*12)+(AJ39)-AD39) -> 0 | AY39: =IF(AE39=0,AK39,(1*100000*12)+(AK39)-AE39) -> 0 | AZ39: =SUM(AV39:AY39)-BF39+Z39+BH39+BI39+BJ39+BK39+BL39+BM39 -> 0 | BC39: =F39 -> 0 | BD39: =IF(AZ39=0,(AZ39-BA39-BC39),(AZ39-BA39-BB39-BC39)) -> 0 | BF39: =Z39*1/100*BG39 -> 0 | BG39: 11
A40: AS201646 | B40: =VLOOKUP(A40,[5]LISTADHERENT!A$5:H$50,3,0) -> YEPMOU JEAN JACQUES | C40: =IF(I40<>"ECHEC",D40+E40+F40-U40,0) -> 0 | D40: =VLOOKUP(A40,[6]HISTOBQUEJANV25!$A$6:$H$48,5,0) -> 0 | E40: =VLOOKUP(A40,[6]HISTOBQUEJANV25!$A$6:$H$43,4,0) -> 50000 | F40: =VLOOKUP(A40,[6]HISTOBQUEJANV25!$A$6:$H$43,6,0) -> 0 | H40: =IF(I40="ESPECES",3000,0)-3000 -> 0 | I40: =IF($D40<>0,"BANQUE",IF($E40<>0,"ESPECES","ECHEC")) -> ESPECES | J40: 1 | K40: =IF($D40<>0,J40*50000,IF($E40<>0,J40*50000,0)) -> 50000 | M40: =IF($D40<>0,L40*75000,IF($E40<>0,L40*75000,0)) -> 0 | O40: =IF($D40<>0,N40*100000,IF($E40<>0,N40*100000,0)) -> 0 | U40: =G40+H40+S40+R40+P40+O40+M40+K40+Q40+V40+W40 -> 50000 | Y40: =K40+M40+O40 -> 50000 | AQ40: =IF(I40="ECHEC",((K40+M40+O40)*20/100),0) -> 0 | AR40: =IF(I40="ECHEC",((K40+M40+O40)*20/100),0) -> 0 | AS40: =IF(I40="ECHEC",0,(K40+G40-25000)) -> 25000 | AW40: =IF(AC40=0,AI40,(1*25000*12)+AI40-AC40) -> 0 | AX40: =IF(AD40=0,AJ40,(1*75000*12)+(AJ40)-AD40) -> 0 | AY40: =IF(AE40=0,AK40,(1*100000*12)+(AK40)-AE40) -> 0 | AZ40: =SUM(AV40:AY40)-BF40+Z40+BH40+BI40+BJ40+BK40+BL40+BM40 -> 0 | BC40: =F40 -> 0 | BD40: =IF(AZ40=0,(AZ40-BA40-BC40),(AZ40-BA40-BB40-BC40)) -> 0 | BF40: =Z40*1/100*BG40 -> 0 | BG40: 11 | BO40: COLLATION | BP40: COLLATION
A41: AS201659 | B41: =VLOOKUP(A41,[5]LISTADHERENT!A$5:H$50,3,0) -> YIALA ALAIN OSCAR | C41: =IF(I41<>"ECHEC",D41+E41+F41-U41,0) -> 0 | D41: =VLOOKUP(A41,[6]HISTOBQUEJANV25!$A$6:$H$48,5,0) -> 250000 | E41: =VLOOKUP(A41,[6]HISTOBQUEJANV25!$A$6:$H$43,4,0) -> 0 | F41: =VLOOKUP(A41,[6]HISTOBQUEJANV25!$A$6:$H$43,6,0) -> 0 | H41: =IF(I41="ESPECES",3000,0) -> 0 | I41: =IF($D41<>0,"BANQUE",IF($E41<>0,"ESPECES","ECHEC")) -> BANQUE | J41: 1 | K41: =IF($D41<>0,J41*50000,IF($E41<>0,J41*50000,0)) -> 50000 | M41: =IF($D41<>0,L41*75000,IF($E41<>0,L41*75000,0)) -> 0 | N41: 2 | O41: =IF($D41<>0,N41*100000,IF($E41<>0,N41*100000,0)) -> 200000 | U41: =G41+H41+S41+R41+P41+O41+M41+K41+Q41+V41+W41 -> 250000 | Y41: =K41+M41+O41 -> 250000 | AQ41: =IF(I41="ECHEC",((K41+M41+O41)*20/100),0) -> 0 | AR41: =IF(I41="ECHEC",((K41+M41+O41)*20/100),0) -> 0 | AS41: =IF(I41="ECHEC",0,(K41+G41-25000)) -> 25000 | AW41: =IF(AC41=0,AI41,(1*25000*12)+AI41-AC41) -> 0 | AX41: =IF(AD41=0,AJ41,(1*75000*12)+(AJ41)-AD41) -> 0 | AY41: =IF(AE41=0,AK41,(1*100000*12)+(AK41)-AE41) -> 0 | AZ41: =SUM(AV41:AY41)-BF41+Z41+BH41+BI41+BJ41+BK41+BL41+BM41 -> 100000 | BC41: =F41 -> 0 | BD41: =IF(AZ41=0,(AZ41-BA41-BC41),(AZ41-BA41-BB41-BC41)) -> 100000 | BE41: OK | BF41: =Z41*1/100*BG41 -> 0 | BG41: 11 | BK41: 100000 | BO41: BOISSON | BP41: COLLATION
A42: AS201647 | B42: =VLOOKUP(A42,[5]LISTADHERENT!A$5:H$50,3,0) -> YOUMBI EMMANUEL | C42: =IF(I42<>"ECHEC",D42+E42+F42-U42,0) -> 0 | D42: =VLOOKUP(A42,[6]HISTOBQUEJANV25!$A$6:$H$48,5,0) -> 225000 | E42: =VLOOKUP(A42,[6]HISTOBQUEJANV25!$A$6:$H$43,4,0) -> 0 | F42: =VLOOKUP(A42,[6]HISTOBQUEJANV25!$A$6:$H$43,6,0) -> 0 | H42: =IF(I42="ESPECES",3000,0) -> 0 | I42: =IF($D42<>0,"BANQUE",IF($E42<>0,"ESPECES","ECHEC")) -> BANQUE | J42: 1 | K42: =IF($D42<>0,J42*50000,IF($E42<>0,J42*50000,0)) -> 50000 | L42: 1 | M42: =IF($D42<>0,L42*75000,IF($E42<>0,L42*75000,0)) -> 75000 | N42: 1 | O42: =IF($D42<>0,N42*100000,IF($E42<>0,N42*100000,0)) -> 100000 | U42: =G42+H42+S42+R42+P42+O42+M42+K42+Q42+V42+W42 -> 225000 | Y42: =K42+M42+O42 -> 225000 | AQ42: =IF(I42="ECHEC",((K42+M42+O42)*20/100),0) -> 0 | AR42: =IF(I42="ECHEC",((K42+M42+O42)*20/100),0) -> 0 | AS42: =IF(I42="ECHEC",0,(K42+G42-25000)) -> 25000 | AW42: =IF(AC42=0,AI42,(1*25000*12)+AI42-AC42) -> 0 | AX42: =IF(AD42=0,AJ42,(1*75000*12)+(AJ42)-AD42) -> 0 | AY42: =IF(AE42=0,AK42,(1*100000*12)+(AK42)-AE42) -> 0 | AZ42: =SUM(AV42:AY42)-BF42+Z42+BH42+BI42+BJ42+BK42+BL42+BM42 -> 0 | BC42: =F42 -> 0 | BD42: =IF(AZ42=0,(AZ42-BA42-BC42),(AZ42-BA42-BB42-BC42)) -> 0 | BF42: =Z42*1/100*BG42 -> 0 | BG42: 11
B44: TOTAUX | C44: =SUM(C6:C43) -> 0 | D44: =SUM(D6:D43) -> 5395000 | E44: =SUM(E6:E43) -> 275000 | F44: =SUM(F6:F43) -> 346500 | G44: =SUM(G6:G43) -> 695000 | H44: =SUM(H6:H43) -> 0 | I44: =SUM(I6:I43) -> 0 | J44: =SUM(J6:J43) -> 35 | ... S44: =SUM(S6:S43) -> 346500 | U44: =SUM(U6:U43) -> 6016500 | V44: =SUM(V6:V43) -> 0 | W44: =SUM(W6:W43) -> 0 | X44: =SUM(X6:X43) -> 0 | Y44: =SUM(Y6:Y43) -> 4975000 | Z44: =SUM(Z6:Z43) -> 2000000 | AA44: =SUM(AA6:AA43) -> 0 | AC44: =SUM(AC6:AC43) -> 91000 | AD44: =SUM(AD6:AD43) -> 7500 | AE44: =SUM(AE6:AE43) -> 340000 | AG44: =SUM(AG6:AG43) -> 0 | AI44: =SUM(AI6:AI43) -> 41000 | AJ44: =SUM(AJ6:AJ43) -> 0 | AK44: =SUM(AK6:AK43) -> 0 | AL44: =SUM(AL6:AL43) -> 1000 | AM44: =SUM(AM6:AM43) -> 0 | AN44: =SUM(AN6:AN43) -> 0 | AO44: =SUM(AO6:AO43) -> 0 | AP44: =SUM(AP6:AP43) -> 0 | ... BF44: =SUM(BF6:BF43) -> 220000 | BH44: =SUM(BH6:BH43) -> 72000 | BI44: =SUM(BI6:BI43) -> 200000 | BJ44: =SUM(BJ6:BJ43) -> 0 | BK44: =SUM(BK6:BK43) -> 100000 | BL44: =SUM(BL6:BL43) -> 0 | BM44: =SUM(BM6:BM43) -> 0 | BO44: S/TOTAL | BQ44: =SUM(BQ40:BQ42) -> 0
BA46: =E44 -> 275000 | BB46: ESPECES EN CAISSE | BD46: 7134000 | BE46: CHEQUE TIRE
C47: BANQUE | G47: ESPECES | BA47: =+BA46-BA44 -> 0 | BD47: =+BD46-BD44 -> 0
B48: LIBELLE | C48: SORTIE | D48: ENTREE | E48: EN COMPTE | G48: ENTREE | H48: SORTIE | I48: SOLDE | BO48: S/TOTAL | BQ48: =SUM(BQ46:BQ47) -> 0
B49: REPORT
B50: OPERATIONS DU JOUR | C50: =BD44 -> 7134000 | D50: =+D44 -> 5395000 | E50: =+C50-D50 -> 1739000 | G50: =E44 -> 275000 | H50: =+BA44 -> 275000 | I50: =+G50-H50 -> 0 | BO50: FOYER | BQ50: 371000
AZ88: =SUM(AZ8:AZ87) -> 13948000

Sheet HISTOFEV25
A1: ASSOCIATION | B1: ASELBY
A2: ANNEE | B2: 2025
A3: 1 | B3: 2 | C3: 3 | D3: 4 | E3: 5 | F3: 6 | G3: 7 | H3: 8 | I3: 9 | J3: 10 | K3: 11 | L3: 12 | M3: 13 | N3: 14 | O3: 15 | P3: 16 | Q3: 17 | R3: 18 | S3: 19 | T3: 20 | U3: 21 | V3: 22 | W3: 23 | X3: 24 | Y3: 25 | Z3: 26 | AA3: 27 | AB3: 28 | AC3: 29 | AD3: 30 | AE3: 31 | AF3: 32 | AG3: 33 | AH3: 34 | AI3: 35 | AJ3: 36 | AK3: 37 | AL3: 38 | AM3: 39 | AN3: 40 | AO3: 41 | AP3: 42 | AQ3: 43 | AR3: 44 | AS3: 45 | AT3: 46 | AU3: 47 | AV3: 48 | AW3: 49 | AX3: 50 | AY3: 51 | AZ3: 52 | BA3: 53 | BB3: 54 | BC3: 55 | BD3: 56 | BE3: 57 | BF3: 58 | BG3: 59 | BH3: 60 | BI3: 61 | BJ3: 62 | BK3: 63 | BL3: 64 | BM3: 65 | BN3: 66 | BO3: 67 | BP3: 68 | BQ3: 69
B4: TABLEAU DE BORD SAISIE DES DONNEES
A5: MATRICULE | B5: NOM ET PRENOM | C5: BONUS MALUS | D5: VERSEMENT BANQUE | E5: VERSEMENT ESPECES | F5: AUTRE VERSEMENTS | G5: COMPLEMENT EPARGNE | H5: PENALITE VERSEMENT ESPECES | I5: MODE PAIEMENT TONTINE | J5: NBRE DE LOT | K5: TONTINE 25 000 | L5: NBRE DE LOT | M5: TONTINE 75 000 | N5: NBRE DE LOT | O5: TONTINE 100 000 | P5: REMBOURSEMENT PETIT LOT T25 | Q5: REMBOURSEMENT PETIT LOT T75 | R5: REMBOURSEMENT PETIT LOT T100 | S5: REMBOURSEMENT PRÊT FONDS | T5: MODE PAIEMENT REMBOURSEMENT PRÊT FONDS | U5: MONTANT ENGAGEMENT | V5: SANCTION | W5: INSCRIPTION | X5: EPARGNE ASSURANCE | Y5: TONTINE MOIS | Z5: PRÊT FONDS | AA5: MODE PAIEMENT PRÊT | AB5: NUM CHEQUE | AC5: ACHAT LOT PRINCIPAL T25 | AD5: ACHAT LOT PRINCIPAL T75 | AE5: ACHAT LOT PRINCIPAL T100 | AF5: MODE PAIEMENT LOT PRINCIPAL | AG5: NUM CHEQUE | AH5: PENALITE VERSEMENT ESPECES | AI5: VENTE PETIT LOT T25 | AJ5: VENTE PETIT LOT T75 | AK5: VENTE PETIT LOT T100 | AL5: INTERET PETIT LOT T25 | AM5: INTERET PETIT LOT T75 | AN5: INTERET PETIT LOT T100 | AO5: NUM CHEQUE | AP5: MODE REMBOURSEMENT PAIEMENT PETIT LOT | AQ5: PENELAITE RETARD TONTINE | AR5: PENELAITE ECHEC TONTINE | AS5: RESTE | AT5: MUTUELLE | AU5: REMBOURSEMENT TRANSPORT | AV5: RETRAIT PARTIEL FONDS | AW5: MONTANT T25 | AX5: MONTANT T75 | AY5: MONTANT T100 | AZ5: MONTANT CHEQUE | BA5: MONTANT ESPECES | BB5: CONTRIBUTION FOYER | BC5: AUTRES MODE DE VERST | BD5: MONTANT CHEQUE EFFECTIF | BE5: NUMERO CHEQUE | BF5: INTERET PRÊT | BG5: NBRE MOIS | BH5: DEPENSE FONDS DE ROULEMENT | BI5: DEPENSE FRAIS EXCEPTIONNEL | BJ5: DEPENSE FONDS MUTUEL | BK5: DEPENSE COLLATION RECEPTION | BL5: PENALITE PRET FONDS | BM5: DEPENSE PENALITE VERSEMENT BANQUE | BN5: AUTRES DEPENSES | BO5: LIBELLE | BP5: COMPTE | BQ5: MONTANT
A6: AS201648 | B6: =VLOOKUP(A6,[5]LISTADHERENT!A$5:H$50,3,0) -> ASELBY | C6: =IF(I6<>"ECHEC",D6+E6+F6-U6,0) -> 0 | D6: =VLOOKUP(A6,[6]HISTOBQUEFEV25!$A$6:$H$48,5,0) -> 250000 | E6: =VLOOKUP(A6,[6]HISTOBQUEFEV25!$A$6:$H$43,4,0) -> 0 | F6: =VLOOKUP(A6,[6]HISTOBQUEFEV25!$A$6:$H$43,6,0) -> 0 | H6: =IF(I6="ESPECES",3000,0) -> 0 | I6: =IF($D6<>0,"BANQUE",IF($E6<>0,"ESPECES","ECHEC")) -> BANQUE | K6: =IF($D6<>0,J6*50000,IF($E6<>0,J6*50000,0)) -> 0 | L6: 2 | M6: =IF($D6<>0,L6*75000,IF($E6<>0,L6*75000,0)) -> 150000 | N6: 1 | O6: =IF($D6<>0,N6*100000,IF($E6<>0,N6*100000,0)) -> 100000 | P6: =IFERROR(VLOOKUP(A6,[7]TONTFEV25!$A$6:$R$41,12,0),0) -> 0 | Q6: =IFERROR(VLOOKUP(A6,[8]TONTFEV25!$A$6:$R$38,10,0),0) -> 0 | R6: =IFERROR(VLOOKUP(A6,[9]TONTFEV25!$A$6:$R$42,10,0),0) -> 0 | U6: =G6+H6+S6+R6+P6+O6+M6+K6+Q6+V6+W6 -> 250000 | Y6: =K6+M6+O6 -> 250000 | AP6: BANQUE | AQ6: =IF(I6="ECHEC",((K6+M6+O6)*20/100),0) -> 0 | AR6: =IF(I6="ECHEC",((K6+M6+O6)*20/100),0) -> 0 | AW6: =IF(AC6=0,AI6,(1*25000*12)+AI6-AC6) -> 0 | AX6: =IF(AD6=0,AJ6,(1*75000*12)+(AJ6)-AD6) -> 0 | AY6: =IF(AE6=0,AK6,(1*100000*12)+(AK6)-AE6) -> 0 | AZ6: =SUM(AV6:AY6)-BF6+Z6+BH6+BI6+BJ6+BK6+BL6+BM6+BN6 -> 36000 | BA6: 30000 | BC6: =F6 -> 0 | BD6: =IF(AZ6=0,(AZ6-BA6-BC6),(AZ6-BA6-BB6-BC6)) -> 6000 | BE6: OK | BF6: =Z6*1/100*BG6 -> 0 | BG6: 10 | BH6: =BQ17 -> 36000 | BI6: =BQ30 -> 0 | BJ6: =BQ36 -> 0 | BN6: =+BQ24 -> 0 | BO6: ACHAT FOURNITURE | BP6: FONDS DE ROULEMENT
A7: AS201601 | B7: =VLOOKUP(A7,[5]LISTADHERENT!A$5:H$50,3,0) -> BAKOP ACHILLE | C7: =IF(I7<>"ECHEC",D7+E7+F7-U7,0) -> 0 | D7: =VLOOKUP(A7,[6]HISTOBQUEFEV25!$A$6:$H$48,5,0) -> 0 | E7: =VLOOKUP(A7,[6]HISTOBQUEFEV25!$A$6:$H$43,4,0) -> 50000 | F7: =VLOOKUP(A7,[6]HISTOBQUEFEV25!$A$6:$H$43,6,0) -> 0 | H7: =IF(I7="ESPECES",3000,0)-3000 -> 0 | I7: =IF($D7<>0,"BANQUE",IF($E7<>0,"ESPECES","ECHEC")) -> ESPECES | J7: 1 | K7: =IF($D7<>0,J7*50000,IF($E7<>0,J7*50000,0)) -> 50000 | M7: =IF($D7<>0,L7*75000,IF($E7<>0,L7*75000,0)) -> 0 | O7: =IF($D7<>0,N7*100000,IF($E7<>0,N7*100000,0)) -> 0 | P7: =IFERROR(VLOOKUP(A7,[7]TONTFEV25!$A$6:$R$41,12,0),0) -> 0 | Q7: =IFERROR(VLOOKUP(A7,[8]TONTFEV25!$A$6:$R$38,10,0),0) -> 0 | R7: =IFERROR(VLOOKUP(A7,[9]TONTFEV25!$A$6:$R$42,10,0),0) -> 0 | U7: =G7+H7+S7+R7+P7+O7+M7+K7+Q7+V7+W7 -> 50000 | Y7: =K7+M7+O7 -> 50000 | AM7: 2000 | AQ7: =IF(I7="ECHEC",((K7+M7+O7)*20/100),0) -> 0 | AR7: =IF(I7="ECHEC",((K7+M7+O7)*20/100),0) -> 0 | AS7: =IF(I7="ECHEC",0,(K7+G7-25000)) -> 25000 | AW7: =IF(AC7=0,AI7,(1*25000*12)+AI7-AC7) -> 0 | AX7: =IF(AD7=0,AJ7,(1*75000*12)+(AJ7)-AD7) -> 0 | AY7: =IF(AE7=0,AK7,(1*100000*12)+(AK7)-AE7) -> 0 | AZ7: =SUM(AV7:AY7)-BF7+Z7+BH7+BI7+BJ7+BK7+BL7+BM7+BN7 -> 0 | BC7: =F7 -> 0 | BD7: =IF(AZ7=0,(AZ7-BA7-BC7),(AZ7-BA7-BB7-BC7)) -> 0 | BF7: =Z7*1/100*BG7 -> 0 | BG7: 10 | BO7: COMMUNICATION | BP7: FONDS DE ROULEMENT
A8: AS201602 | B8: =VLOOKUP(A8,[5]LISTADHERENT!A$5:H$50,3,0) -> BOUTCHOUANG WILLIAM | C8: =IF(I8<>"ECHEC",D8+E8+F8-U8,0) -> 0 | D8: =VLOOKUP(A8,[6]HISTOBQUEFEV25!$A$6:$H$48,5,0) -> 125000 | E8: =VLOOKUP(A8,[6]HISTOBQUEFEV25!$A$6:$H$43,4,0) -> 0 | F8: =VLOOKUP(A8,[6]HISTOBQUEFEV25!$A$6:$H$43,6,0) -> 0 | H8: =IF(I8="ESPECES",3000,0) -> 0 | I8: =IF($D8<>0,"BANQUE",IF($E8<>0,"ESPECES","ECHEC")) -> BANQUE | J8: 1 | K8: =IF($D8<>0,J8*50000,IF($E8<>0,J8*50000,0)) -> 50000 | L8: 1 | M8: =IF($D8<>0,L8*75000,IF($E8<>0,L8*75000,0)) -> 75000 | O8: =IF($D8<>0,N8*100000,IF($E8<>0,N8*100000,0)) -> 0 | P8: =IFERROR(VLOOKUP(A8,[7]TONTFEV25!$A$6:$R$41,12,0),0) -> 0 | Q8: =IFERROR(VLOOKUP(A8,[8]TONTFEV25!$A$6:$R$38,10,0),0) -> 0 | R8: =IFERROR(VLOOKUP(A8,[9]TONTFEV25!$A$6:$R$42,10,0),0) -> 0 | U8: =G8+H8+S8+R8+P8+O8+M8+K8+Q8+V8+W8 -> 125000 | Y8: =K8+M8+O8 -> 125000 | AJ8: 100000 | AM8: 3000 | AP8: BANQUE | AQ8: =IF(I8="ECHEC",((K8+M8+O8)*20/100),0) -> 0 | AR8: =IF(I8="ECHEC",((K8+M8+O8)*20/100),0) -> 0 | AS8: =IF(I8="ECHEC",0,(K8+G8-25000)) -> 25000 | AW8: =IF(AC8=0,AI8,(1*25000*12)+AI8-AC8) -> 0 | AX8: =IF(AD8=0,AJ8,(1*75000*12)+(AJ8)-AD8) -> 100000 | AY8: =IF(AE8=0,AK8,(1*100000*12)+(AK8)-AE8) -> 0 | AZ8: =SUM(AV8:AY8)-BF8+Z8+BH8+BI8+BJ8+BK8+BL8+BM8+BN8 -> 100000 | BC8: =F8 -> 0 | BD8: =IF(AZ8=0,(AZ8-BA8-BC8),(AZ8-BA8-BB8-BC8)) -> 100000 | BE8: OK | BF8: =Z8*1/100*BG8 -> 0 | BG8: 10 | BO8: COMMISSION | BP8: FONDS DE ROULEMENT | BQ8: 30000
A9: AS201604 | B9: =VLOOKUP(A9,[5]LISTADHERENT!A$5:H$50,3,0) -> DJOMO JEAN PAUL | C9: =IF(I9<>"ECHEC",D9+E9+F9-U9,0) -> 0 | D9: =VLOOKUP(A9,[6]HISTOBQUEFEV25!$A$6:$H$48,5,0) -> 250000 | E9: =VLOOKUP(A9,[6]HISTOBQUEFEV25!$A$6:$H$43,4,0) -> 0 | F9: =VLOOKUP(A9,[6]HISTOBQUEFEV25!$A$6:$H$43,6,0) -> 0 | H9: =IF(I9="ESPECES",3000,0) -> 0 | I9: =IF($D9<>0,"BANQUE",IF($E9<>0,"ESPECES","ECHEC")) -> BANQUE | J9: 1 | K9: =IF($D9<>0,J9*50000,IF($E9<>0,J9*50000,0)) -> 50000 | M9: =IF($D9<>0,L9*75000,IF($E9<>0,L9*75000,0)) -> 0 | N9: 2 | O9: =IF($D9<>0,N9*100000,IF($E9<>0,N9*100000,0)) -> 200000 | P9: =IFERROR(VLOOKUP(A9,[7]TONTFEV25!$A$6:$R$41,12,0),0) -> 0 | Q9: =IFERROR(VLOOKUP(A9,[8]TONTFEV25!$A$6:$R$38,10,0),0) -> 0 | R9: =IFERROR(VLOOKUP(A9,[9]TONTFEV25!$A$6:$R$42,10,0),0) -> 0 | U9: =G9+H9+S9+R9+P9+O9+M9+K9+Q9+V9+W9 -> 250000 | Y9: =K9+M9+O9 -> 250000 | AE9: 80000 | AF9: BANQUE | AK9: 200000 | AN9: =3500+4000 -> 7500 | AP9: BANQUE | AQ9: =IF(I9="ECHEC",((K9+M9+O9)*20/100),0) -> 0 | AR9: =IF(I9="ECHEC",((K9+M9+O9)*20/100),0) -> 0 | AS9: =IF(I9="ECHEC",0,(K9+G9-25000)) -> 25000 | AW9: =IF(AC9=0,AI9,(1*25000*12)+AI9-AC9) -> 0 | AX9: =IF(AD9=0,AJ9,(1*75000*12)+(AJ9)-AD9) -> 0 | AY9: =IF(AE9=0,AK9,(1*100000*12)+(AK9)-AE9) -> 1320000 | AZ9: =SUM(AV9:AY9)-BF9+Z9+BH9+BI9+BJ9+BK9+BL9+BM9+BN9 -> 1320000 | BC9: =F9 -> 0 | BD9: =IF(AZ9=0,(AZ9-BA9-BC9),(AZ9-BA9-BB9-BC9)) -> 1320000 | BE9: OK | BF9: =Z9*1/100*BG9 -> 0 | BG9: 10 | BO9: OUVERTURE COMPTE | BP9: FONDS DE ROULEMENT
A10: AS201654 | B10: =VLOOKUP(A10,[5]LISTADHERENT!A$5:H$50,3,0) -> DJOMOU TCHAPDA | C10: =IF(I10<>"ECHEC",D10+E10+F10-U10,0) -> 0 | D10: =VLOOKUP(A10,[6]HISTOBQUEFEV25!$A$6:$H$48,5,0) -> 50000 | E10: =VLOOKUP(A10,[6]HISTOBQUEFEV25!$A$6:$H$43,4,0) -> 0 | F10: =VLOOKUP(A10,[6]HISTOBQUEFEV25!$A$6:$H$43,6,0) -> 0 | H10: =IF(I10="ESPECES",3000,0) -> 0 | I10: =IF($D10<>0,"BANQUE",IF($E10<>0,"ESPECES","ECHEC")) -> BANQUE | J10: 1 | K10: =IF($D10<>0,J10*50000,IF($E10<>0,J10*50000,0)) -> 50000 | M10: =IF($D10<>0,L10*75000,IF($E10<>0,L10*75000,0)) -> 0 | O10: =IF($D10<>0,N10*100000,IF($E10<>0,N10*100000,0)) -> 0 | P10: =IFERROR(VLOOKUP(A10,[7]TONTFEV25!$A$6:$R$41,12,0),0) -> 0 | Q10: =IFERROR(VLOOKUP(A10,[8]TONTFEV25!$A$6:$R$38,10,0),0) -> 0 | R10: =IFERROR(VLOOKUP(A10,[9]TONTFEV25!$A$6:$R$42,10,0),0) -> 0 | U10: =G10+H10+S10+R10+P10+O10+M10+K10+Q10+V10+W10 -> 50000 | Y10: =K10+M10+O10 -> 50000 | AI10: 40000 | AL10: 1000 | AP10: BANQUE | AQ10: =IF(I10="ECHEC",((K10+M10+O10)*20/100),0) -> 0 | AR10: =IF(I10="ECHEC",((K10+M10+O10)*20/100),0) -> 0 | AS10: =IF(I10="ECHEC",0,(K10+G10-25000)) -> 25000 | AW10: =IF(AC10=0,AI10,(1*25000*12)+AI10-AC10) -> 40000 | AX10: =IF(AD10=0,AJ10,(1*75000*12)+(AJ10)-AD10) -> 0 | AY10: =IF(AE10=0,AK10,(1*100000*12)+(AK10)-AE10) -> 0 | AZ10: =SUM(AV10:AY10)-BF10+Z10+BH10+BI10+BJ10+BK10+BL10+BM10+BN10 -> 40000 | BA10: 40000 | BC10: =F10 -> 0 | BD10: =IF(AZ10=0,(AZ10-BA10-BC10),(AZ10-BA10-BB10-BC10)) -> 0 | BF10: =Z10*1/100*BG10 -> 0 | BG10: 10 | BO10: CREDIT TELEPHONE | BP10: FONDS DE ROULEMENT
A11: AS201605 | B11: =VLOOKUP(A11,[5]LISTADHERENT!A$5:H$50,3,0) -> DJOUKWE NANGUEN GUY BLAISE | C11: =IF(I11<>"ECHEC",D11+E11+F11-U11,0) -> 0 | D11: =VLOOKUP(A11,[6]HISTOBQUEFEV25!$A$6:$H$48,5,0) -> 150375 | E11: =VLOOKUP(A11,[6]HISTOBQUEFEV25!$A$6:$H$43,4,0) -> 0 | F11: =VLOOKUP(A11,[6]HISTOBQUEFEV25!$A$6:$H$43,6,0) -> 0 | G11: 375 | H11: =IF(I11="ESPECES",3000,0) -> 0 | I11: =IF($D11<>0,"BANQUE",IF($E11<>0,"ESPECES","ECHEC")) -> BANQUE | J11: 1 | K11: =IF($D11<>0,J11*50000,IF($E11<>0,J11*50000,0)) -> 50000 | M11: =IF($D11<>0,L11*75000,IF($E11<>0,L11*75000,0)) -> 0 | N11: 1 | O11: =IF($D11<>0,N11*100000,IF($E11<>0,N11*100000,0)) -> 100000 | P11: =IFERROR(VLOOKUP(A11,[7]TONTFEV25!$A$6:$R$41,12,0),0) -> 0 | Q11: =IFERROR(VLOOKUP(A11,[8]TONTFEV25!$A$6:$R$38,10,0),0) -> 0 | R11: =IFERROR(VLOOKUP(A11,[9]TONTFEV25!$A$6:$R$42,10,0),0) -> 0 | U11: =G11+H11+S11+R11+P11+O11+M11+K11+Q11+V11+W11 -> 150375 | Y11: =K11+M11+O11 -> 150000 | AK11: =100000+100000 -> 200000 | AN11: =3500+1000 -> 4500 | AP11: BANQUE | AQ11: =IF(I11="ECHEC",((K11+M11+O11)*20/100),0) -> 0 | AR11: =IF(I11="ECHEC",((K11+M11+O11)*20/100),0) -> 0 | AS11: =IF(I11="ECHEC",0,(K11+G11-25000)) -> 25375 | AW11: =IF(AC11=0,AI11,(1*25000*12)+AI11-AC11) -> 0 | AX11: =IF(AD11=0,AJ11,(1*75000*12)+(AJ11)-AD11) -> 0 | AY11: =IF(AE11=0,AK11,(1*100000*12)+(AK11)-AE11) -> 200000 | AZ11: =SUM(AV11:AY11)-BF11+Z11+BH11+BI11+BJ11+BK11+BL11+BM11+BN11 -> 200000 | BA11: 149000 | BC11: =F11 -> 0 | BD11: =IF(AZ11=0,(AZ11-BA11-BC11),(AZ11-BA11-BB11-BC11)) -> 51000 | BE11: OK | BF11: =Z11*1/100*BG11 -> 0 | BG11: 10 | BO11: PRODUCTION RAPPORT | BP11: FONDS DE ROULEMENT
A12: AS201608 | B12: =VLOOKUP(A12,[5]LISTADHERENT!A$5:H$50,3,0) -> DJUOMBESSY ANTOINE | C12: =IF(I12<>"ECHEC",D12+E12+F12-U12,0) -> 0 | D12: =VLOOKUP(A12,[6]HISTOBQUEFEV25!$A$6:$H$48,5,0) -> 910000 | E12: =VLOOKUP(A12,[6]HISTOBQUEFEV25!$A$6:$H$43,4,0) -> 0 | F12: =VLOOKUP(A12,[6]HISTOBQUEFEV25!$A$6:$H$43,6,0) -> 0 | G12: 660000 | H12: =IF(I12="ESPECES",3000,0) -> 0 | I12: =IF($D12<>0,"BANQUE",IF($E12<>0,"ESPECES","ECHEC")) -> BANQUE | J12: 1 | K12: =IF($D12<>0,J12*50000,IF($E12<>0,J12*50000,0)) -> 50000 | M12: =IF($D12<>0,L12*75000,IF($E12<>0,L12*75000,0)) -> 0 | N12: 2 | O12: =IF($D12<>0,N12*100000,IF($E12<>0,N12*100000,0)) -> 200000 | P12: =IFERROR(VLOOKUP(A12,[7]TONTFEV25!$A$6:$R$41,12,0),0) -> 0 | Q12: =IFERROR(VLOOKUP(A12,[8]TONTFEV25!$A$6:$R$38,10,0),0) -> 0 | R12: =IFERROR(VLOOKUP(A12,[9]TONTFEV25!$A$6:$R$42,10,0),0) -> 0 | U12: =G12+H12+S12+R12+P12+O12+M12+K12+Q12+V12+W12 -> 910000 | Y12: =K12+M12+O12 -> 250000 | AQ12: =IF(I12="ECHEC",((K12+M12+O12)*20/100),0) -> 0 | AR12: =IF(I12="ECHEC",((K12+M12+O12)*20/100),0) -> 0 | AS12: =IF(I12="ECHEC",0,(K12+G12-25000)) -> 685000 | AW12: =IF(AC12=0,AI12,(1*25000*12)+AI12-AC12) -> 0 | AX12: =IF(AD12=0,AJ12,(1*75000*12)+(AJ12)-AD12) -> 0 | AY12: =IF(AE12=0,AK12,(1*100000*12)+(AK12)-AE12) -> 0 | AZ12: =SUM(AV12:AY12)-BF12+Z12+BH12+BI12+BJ12+BK12+BL12+BM12+BN12 -> 0 | BC12: =F12 -> 0 | BD12: =IF(AZ12=0,(AZ12-BA12-BC12),(AZ12-BA12-BB12-BC12)) -> 0 | BF12: =Z12*1/100*BG12 -> 0 | BG12: 10 | BO12: ACHAT SOURIS ET PHOTOCOPIE | BP12: FONDS DE ROULEMENT
A13: AS201651 | B13: =VLOOKUP(A13,[5]LISTADHERENT!A$5:H$50,3,0) -> DOMOU FABIEN | C13: =IF(I13<>"ECHEC",D13+E13+F13-U13,0) -> 0 | D13: =VLOOKUP(A13,[6]HISTOBQUEFEV25!$A$6:$H$48,5,0) -> 50000 | E13: =VLOOKUP(A13,[6]HISTOBQUEFEV25!$A$6:$H$43,4,0) -> 0 | F13: =VLOOKUP(A13,[6]HISTOBQUEFEV25!$A$6:$H$43,6,0) -> 0 | H13: =IF(I13="ESPECES",3000,0) -> 0 | I13: =IF($D13<>0,"BANQUE",IF($E13<>0,"ESPECES","ECHEC")) -> BANQUE | J13: 1 | K13: =IF($D13<>0,J13*50000,IF($E13<>0,J13*50000,0)) -> 50000 | M13: =IF($D13<>0,L13*75000,IF($E13<>0,L13*75000,0)) -> 0 | O13: =IF($D13<>0,N13*100000,IF($E13<>0,N13*100000,0)) -> 0 | P13: =IFERROR(VLOOKUP(A13,[7]TONTFEV25!$A$6:$R$41,12,0),0) -> 0 | Q13: =IFERROR(VLOOKUP(A13,[8]TONTFEV25!$A$6:$R$38,10,0),0) -> 0 | R13: =IFERROR(VLOOKUP(A13,[9]TONTFEV25!$A$6:$R$42,10,0),0) -> 0 | U13: =G13+H13+S13+R13+P13+O13+M13+K13+Q13+V13+W13 -> 50000 | Y13: =K13+M13+O13 -> 50000 | AQ13: =IF(I13="ECHEC",((K13+M13+O13)*20/100),0) -> 0 | AR13: =IF(I13="ECHEC",((K13+M13+O13)*20/100),0) -> 0 | AS13: =IF(I13="ECHEC",0,(K13+G13-25000)) -> 25000 | AW13: =IF(AC13=0,AI13,(1*25000*12)+AI13-AC13) -> 0 | AX13: =IF(AD13=0,AJ13,(1*75000*12)+(AJ13)-AD13) -> 0 | AY13: =IF(AE13=0,AK13,(1*100000*12)+(AK13)-AE13) -> 0 | AZ13: =SUM(AV13:AY13)-BF13+Z13+BH13+BI13+BJ13+BK13+BL13+BM13+BN13 -> 0 | BC13: =F13 -> 0 | BD13: =IF(AZ13=0,(AZ13-BA13-BC13),(AZ13-BA13-BB13-BC13)) -> 0 | BF13: =Z13*1/100*BG13 -> 0 | BG13: 10 | BO13: TAXI BANQUE | BP13: FONDS DE ROULEMENT | BQ13: 6000
A14: AS201609 | B14: =VLOOKUP(A14,[5]LISTADHERENT!A$5:H$50,3,0) -> DONHOU DAVID | C14: =IF(I14<>"ECHEC",D14+E14+F14-U14,0) -> 0 | D14: =VLOOKUP(A14,[6]HISTOBQUEFEV25!$A$6:$H$48,5,0) -> 50000 | E14: =VLOOKUP(A14,[6]HISTOBQUEFEV25!$A$6:$H$43,4,0) -> 0 | F14: =VLOOKUP(A14,[6]HISTOBQUEFEV25!$A$6:$H$43,6,0) -> 0 | H14: =IF(I14="ESPECES",3000,0) -> 0 | I14: =IF($D14<>0,"BANQUE",IF($E14<>0,"ESPECES","ECHEC")) -> BANQUE | J14: 1 | K14: =IF($D14<>0,J14*50000,IF($E14<>0,J14*50000,0)) -> 50000 | M14: =IF($D14<>0,L14*75000,IF($E14<>0,L14*75000,0)) -> 0 | O14: =IF($D14<>0,N14*100000,IF($E14<>0,N14*100000,0)) -> 0 | P14: =IFERROR(VLOOKUP(A14,[7]TONTFEV25!$A$6:$R$41,12,0),0) -> 0 | Q14: =IFERROR(VLOOKUP(A14,[8]TONTFEV25!$A$6:$R$38,10,0),0) -> 0 | R14: =IFERROR(VLOOKUP(A14,[9]TONTFEV25!$A$6:$R$42,10,0),0) -> 0 | U14: =G14+H14+S14+R14+P14+O14+M14+K14+Q14+V14+W14 -> 50000 | Y14: =K14+M14+O14 -> 50000 | AQ14: =IF(I14="ECHEC",((K14+M14+O14)*20/100),0) -> 0 | AR14: =IF(I14="ECHEC",((K14+M14+O14)*20/100),0) -> 0 | AS14: =IF(I14="ECHEC",0,(K14+G14-25000)) -> 25000 | AW14: =IF(AC14=0,AI14,(1*25000*12)+AI14-AC14) -> 0 | AX14: =IF(AD14=0,AJ14,(1*75000*12)+(AJ14)-AD14) -> 0 | AY14: =IF(AE14=0,AK14,(1*100000*12)+(AK14)-AE14) -> 0 | AZ14: =SUM(AV14:AY14)-BF14+Z14+BH14+BI14+BJ14+BK14+BL14+BM14+BN14 -> 0 | BC14: =F14 -> 0 | BD14: =IF(AZ14=0,(AZ14-BA14-BC14),(AZ14-BA14-BB14-BC14)) -> 0 | BF14: =Z14*1/100*BG14 -> 0 | BG14: 10 | BO14: ACHAT TERRAIN | BP14: FONDS DE ROULEMENT
A15: AS201663 | B15: =VLOOKUP(A15,[5]LISTADHERENT!A$5:H$50,3,0) -> FAMPOU PAUL | C15: =IF(I15<>"ECHEC",D15+E15+F15-U15,0) -> -50000 | D15: =VLOOKUP(A15,[6]HISTOBQUEFEV25!$A$6:$H$48,5,0) -> 0 | E15: =VLOOKUP(A15,[6]HISTOBQUEFEV25!$A$6:$H$43,4,0) -> 125000 | F15: =VLOOKUP(A15,[6]HISTOBQUEFEV25!$A$6:$H$43,6,0) -> 0 | H15: =IF(I15="ESPECES",3000,0)-3000 -> 0 | I15: =IF($D15<>0,"BANQUE",IF($E15<>0,"ESPECES","ECHEC")) -> ESPECES | J15: 1 | K15: =IF($D15<>0,J15*50000,IF($E15<>0,J15*50000,0)) -> 50000 | M15: =IF($D15<>0,L15*75000,IF($E15<>0,L15*75000,0)) -> 0 | N15: 1 | O15: =IF($D15<>0,N15*100000,IF($E15<>0,N15*100000,0)) -> 100000 | P15: =IFERROR(VLOOKUP(A15,[7]TONTFEV25!$A$6:$R$41,12,0),0) -> 0 | Q15: =IFERROR(VLOOKUP(A15,[8]TONTFEV25!$A$6:$R$38,10,0),0) -> 0 | R15: =IFERROR(VLOOKUP(A15,[9]TONTFEV25!$A$6:$R$42,10,0),0) -> 0 | U15: =G15+H15+S15+R15+P15+O15+M15+K15+Q15+V15+W15 -> 175000 | W15: 25000 | Y15: =K15+M15+O15 -> 150000 | AQ15: =IF(I15="ECHEC",((K15+M15+O15)*20/100),0) -> 0 | AR15: =IF(I15="ECHEC",((K15+M15+O15)*20/100),0) -> 0 | AS15: =IF(I15="ECHEC",0,(K15+G15-25000))+25000 -> 50000 | AW15: =IF(AC15=0,AI15,(1*25000*12)+AI15-AC15) -> 0 | AX15: =IF(AD15=0,AJ15,(1*75000*12)+(AJ15)-AD15) -> 0 | AY15: =IF(AE15=0,AK15,(1*100000*12)+(AK15)-AE15) -> 0 | AZ15: =SUM(AV15:AY15)-BF15+Z15+BH15+BI15+BJ15+BK15+BL15+BM15+BN15 -> 0 | BC15: =F15 -> 0 | BD15: =IF(AZ15=0,(AZ15-BA15-BC15),(AZ15-BA15-BB15-BC15)) -> 0 | BF15: =Z15*1/100*BG15 -> 0 | BG15: 10 | BO15: ACHAT TERRAIN | BP15: FONDS DE ROULEMENT
A16: AS201611 | B16: =VLOOKUP(A16,[5]LISTADHERENT!A$5:H$50,3,0) -> HENGUE PAUL OMER | C16: =IF(I16<>"ECHEC",D16+E16+F16-U16,0) -> 0 | D16: =VLOOKUP(A16,[6]HISTOBQUEFEV25!$A$6:$H$48,5,0) -> 125000 | E16: =VLOOKUP(A16,[6]HISTOBQUEFEV25!$A$6:$H$43,4,0) -> 0 | F16: =VLOOKUP(A16,[6]HISTOBQUEFEV25!$A$6:$H$43,6,0) -> 0 | H16: =IF(I16="ESPECES",3000,0) -> 0 | I16: =IF($D16<>0,"BANQUE",IF($E16<>0,"ESPECES","ECHEC")) -> BANQUE | J16: 1 | K16: =IF($D16<>0,J16*50000,IF($E16<>0,J16*50000,0)) -> 50000 | L16: 1 | M16: =IF($D16<>0,L16*75000,IF($E16<>0,L16*75000,0)) -> 75000 | O16: =IF($D16<>0,N16*100000,IF($E16<>0,N16*100000,0)) -> 0 | P16: =IFERROR(VLOOKUP(A16,[7]TONTFEV25!$A$6:$R$41,12,0),0) -> 0 | Q16: =IFERROR(VLOOKUP(A16,[8]TONTFEV25!$A$6:$R$38,10,0),0) -> 0 | R16: =IFERROR(VLOOKUP(A16,[9]TONTFEV25!$A$6:$R$42,10,0),0) -> 0 | U16: =G16+H16+S16+R16+P16+O16+M16+K16+Q16+V16+W16 -> 125000 | Y16: =K16+M16+O16 -> 125000 | AQ16: =IF(I16="ECHEC",((K16+M16+O16)*20/100),0) -> 0 | AR16: =IF(I16="ECHEC",((K16+M16+O16)*20/100),0) -> 0 | AS16: =IF(I16="ECHEC",0,(K16+G16-25000)) -> 25000 | AW16: =IF(AC16=0,AI16,(1*25000*12)+AI16-AC16) -> 0 | AX16: =IF(AD16=0,AJ16,(1*75000*12)+(AJ16)-AD16) -> 0 | AY16: =IF(AE16=0,AK16,(1*100000*12)+(AK16)-AE16) -> 0 | AZ16: =SUM(AV16:AY16)-BF16+Z16+BH16+BI16+BJ16+BK16+BL16+BM16+BN16 -> 0 | BC16: =F16 -> 0 | BD16: =IF(AZ16=0,(AZ16-BA16-BC16),(AZ16-BA16-BB16-BC16)) -> 0 | BF16: =Z16*1/100*BG16 -> 0 | BG16: 10
A17: AS201613 | B17: =VLOOKUP(A17,[5]LISTADHERENT!A$5:H$50,3,0) -> HOTCHO BENJAMIN | C17: =IF(I17<>"ECHEC",D17+E17+F17-U17,0) -> 0 | D17: =VLOOKUP(A17,[6]HISTOBQUEFEV25!$A$6:$H$48,5,0) -> 260000 | E17: =VLOOKUP(A17,[6]HISTOBQUEFEV25!$A$6:$H$43,4,0) -> 0 | F17: =VLOOKUP(A17,[6]HISTOBQUEFEV25!$A$6:$H$43,6,0) -> 0 | G17: 35000 | H17: =IF(I17="ESPECES",3000,0) -> 0 | I17: =IF($D17<>0,"BANQUE",IF($E17<>0,"ESPECES","ECHEC")) -> BANQUE | J17: 1 | K17: =IF($D17<>0,J17*50000,IF($E17<>0,J17*50000,0)) -> 50000 | L17: 1 | M17: =IF($D17<>0,L17*75000,IF($E17<>0,L17*75000,0)) -> 75000 | N17: 1 | O17: =IF($D17<>0,N17*100000,IF($E17<>0,N17*100000,0)) -> 100000 | P17: =IFERROR(VLOOKUP(A17,[7]TONTFEV25!$A$6:$R$41,12,0),0) -> 0 | Q17: =IFERROR(VLOOKUP(A17,[8]TONTFEV25!$A$6:$R$38,10,0),0) -> 0 | R17: =IFERROR(VLOOKUP(A17,[9]TONTFEV25!$A$6:$R$42,10,0),0) -> 0 | U17: =G17+H17+S17+R17+P17+O17+M17+K17+Q17+V17+W17 -> 260000 | Y17: =K17+M17+O17 -> 225000 | AQ17: =IF(I17="ECHEC",((K17+M17+O17)*20/100),0) -> 0 | AR17: =IF(I17="ECHEC",((K17+M17+O17)*20/100),0) -> 0 | AS17: =IF(I17="ECHEC",0,(K17+G17-25000)) -> 60000 | AW17: =IF(AC17=0,AI17,(1*25000*12)+AI17-AC17) -> 0 | AX17: =IF(AD17=0,AJ17,(1*75000*12)+(AJ17)-AD17) -> 0 | AY17: =IF(AE17=0,AK17,(1*100000*12)+(AK17)-AE17) -> 0 | AZ17: =SUM(AV17:AY17)-BF17+Z17+BH17+BI17+BJ17+BK17+BL17+BM17+BN17 -> 0 | BC17: =F17 -> 0 | BD17: =IF(AZ17=0,(AZ17-BA17-BC17),(AZ17-BA17-BB17-BC17)) -> 0 | BF17: =Z17*1/100*BG17 -> 0 | BG17: 10 | BO17: S/TOTAL | BQ17: =SUM(BQ6:BQ16) -> 36000
A18: AS201617 | B18: =VLOOKUP(A18,[5]LISTADHERENT!A$5:H$50,3,0) -> KOUAMOU MOISE | C18: =IF(I18<>"ECHEC",D18+E18+F18-U18,0) -> 0 | D18: =VLOOKUP(A18,[6]HISTOBQUEFEV25!$A$6:$H$48,5,0) -> 150000 | E18: =VLOOKUP(A18,[6]HISTOBQUEFEV25!$A$6:$H$43,4,0) -> 0 | F18: =VLOOKUP(A18,[6]HISTOBQUEFEV25!$A$6:$H$43,6,0) -> 0 | H18: =IF(I18="ESPECES",3000,0) -> 0 | I18: =IF($D18<>0,"BANQUE",IF($E18<>0,"ESPECES","ECHEC")) -> BANQUE | J18: 1 | K18: =IF($D18<>0,J18*50000,IF($E18<>0,J18*50000,0)) -> 50000 | M18: =IF($D18<>0,L18*75000,IF($E18<>0,L18*75000,0)) -> 0 | N18: 1 | O18: =IF($D18<>0,N18*100000,IF($E18<>0,N18*100000,0)) -> 100000 | P18: =IFERROR(VLOOKUP(A18,[7]TONTFEV25!$A$6:$R$41,12,0),0) -> 0 | Q18: =IFERROR(VLOOKUP(A18,[8]TONTFEV25!$A$6:$R$38,10,0),0) -> 0 | R18: =IFERROR(VLOOKUP(A18,[9]TONTFEV25!$A$6:$R$42,10,0),0) -> 0 | U18: =G18+H18+S18+R18+P18+O18+M18+K18+Q18+V18+W18 -> 150000 | Y18: =K18+M18+O18 -> 150000 | Z18: 500000 | AA18: BANQUE | AQ18: =IF(I18="ECHEC",((K18+M18+O18)*20/100),0) -> 0 | AR18: =IF(I18="ECHEC",((K18+M18+O18)*20/100),0) -> 0 | AS18: =IF(I18="ECHEC",0,(K18+G18-25000)) -> 25000 | AW18: =IF(AC18=0,AI18,(1*25000*12)+AI18-AC18) -> 0 | AX18: =IF(AD18=0,AJ18,(1*75000*12)+(AJ18)-AD18) -> 0 | AY18: =IF(AE18=0,AK18,(1*100000*12)+(AK18)-AE18) -> 0 | AZ18: =SUM(AV18:AY18)-BF18+Z18+BH18+BI18+BJ18+BK18+BL18+BM18+BN18 -> 470000 | BC18: =F18 -> 0 | BD18: =IF(AZ18=0,(AZ18-BA18-BC18),(AZ18-BA18-BB18-BC18)) -> 470000 | BE18: OK | BF18: =Z18*1/100*BG18 -> 30000 | BG18: 6
A19: AS201619 | B19: =VLOOKUP(A19,[5]LISTADHERENT!A$5:H$50,3,0) -> KOUATCHO MESSACK | C19: =IF(I19<>"ECHEC",D19+E19+F19-U19,0) -> 75000 | D19: =VLOOKUP(A19,[6]HISTOBQUEFEV25!$A$6:$H$48,5,0) -> 310000 | E19: =VLOOKUP(A19,[6]HISTOBQUEFEV25!$A$6:$H$43,4,0) -> 0 | F19: =VLOOKUP(A19,[6]HISTOBQUEFEV25!$A$6:$H$43,6,0) -> 0 | G19: 10000 | H19: =IF(I19="ESPECES",3000,0) -> 0 | I19: =IF($D19<>0,"BANQUE",IF($E19<>0,"ESPECES","ECHEC")) -> BANQUE | J19: 1 | K19: =IF($D19<>0,J19*50000,IF($E19<>0,J19*50000,0)) -> 50000 | L19: 1 | M19: =IF($D19<>0,L19*75000,IF($E19<>0,L19*75000,0)) -> 75000 | N19: 1 | O19: =IF($D19<>0,N19*100000,IF($E19<>0,N19*100000,0)) -> 100000 | P19: =IFERROR(VLOOKUP(A19,[7]TONTFEV25!$A$6:$R$41,12,0),0) -> 0 | Q19: =IFERROR(VLOOKUP(A19,[8]TONTFEV25!$A$6:$R$38,10,0),0) -> 0 | R19: =IFERROR(VLOOKUP(A19,[9]TONTFEV25!$A$6:$R$42,10,0),0) -> 0 | U19: =G19+H19+S19+R19+P19+O19+M19+K19+Q19+V19+W19 -> 235000 | Y19: =K19+M19+O19 -> 225000 | AC19: 26000 | AF19: BANQUE | AJ19: 53000 | AM19: 1500 | AP19: BANQUE | AQ19: =IF(I19="ECHEC",((K19+M19+O19)*20/100),0) -> 0 | AR19: =IF(I19="ECHEC",((K19+M19+O19)*20/100),0) -> 0 | AS19: =IF(I19="ECHEC",0,(K19+G19-25000)) -> 35000 | AW19: =IF(AC19=0,AI19,(1*25000*12)+AI19-AC19) -> 274000 | AX19: =IF(AD19=0,AJ19,(1*75000*12)+(AJ19)-AD19) -> 53000 | AY19: =IF(AE19=0,AK19,(1*100000*12)+(AK19)-AE19) -> 0 | AZ19: =SUM(AV19:AY19)-BF19+Z19+BH19+BI19+BJ19+BK19+BL19+BM19+BN19 -> 327000 | BC19: =F19 -> 0 | BD19: =IF(AZ19=0,(AZ19-BA19-BC19),(AZ19-BA19-BB19-BC19)) -> 327000 | BE19: OK | BF19: =Z19*1/100*BG19 -> 0 | BG19: 10 | BO19: TERRAIN NYOM | BP19: AUTRES DEPENSES
A20: AS201620 | B20: =VLOOKUP(A20,[5]LISTADHERENT!A$5:H$50,3,0) -> LOWE JEAN
A21: AS201661 | B21: =VLOOKUP(A21,[5]LISTADHERENT!A$5:H$50,3,0) -> MASSEUNGOUE DAGOBERT | C21: =IF(I21<>"ECHEC",D21+E21+F21-U21,0) -> 0 | D21: =VLOOKUP(A21,[6]HISTOBQUEFEV25!$A$6:$H$48,5,0) -> 50000 | E21: =VLOOKUP(A21,[6]HISTOBQUEFEV25!$A$6:$H$43,4,0) -> 0 | F21: =VLOOKUP(A21,[6]HISTOBQUEFEV25!$A$6:$H$43,6,0) -> 0 | H21: =IF(I21="ESPECES",3000,0) -> 0 | I21: =IF($D21<>0,"BANQUE",IF($E21<>0,"ESPECES","ECHEC")) -> BANQUE | J21: 1 | K21: =IF($D21<>0,J21*50000,IF($E21<>0,J21*50000,0)) -> 50000 | M21: =IF($D21<>0,L21*75000,IF($E21<>0,L21*75000,0)) -> 0 | O21: =IF($D21<>0,N21*100000,IF($E21<>0,N21*100000,0)) -> 0 | P21: =IFERROR(VLOOKUP(A21,[7]TONTFEV25!$A$6:$R$41,12,0),0) -> 0 | Q21: =IFERROR(VLOOKUP(A21,[8]TONTFEV25!$A$6:$R$38,10,0),0) -> 0 | R21: =IFERROR(VLOOKUP(A21,[9]TONTFEV25!$A$6:$R$42,10,0),0) -> 0 | U21: =G21+H21+S21+R21+P21+O21+M21+K21+Q21+V21+W21 -> 50000 | Y21: =K21+M21+O21 -> 50000 | AQ21: =IF(I21="ECHEC",((K21+M21+O21)*20/100),0) -> 0 | AR21: =IF(I21="ECHEC",((K21+M21+O21)*20/100),0) -> 0 | AS21: =IF(I21="ECHEC",0,(K21+G21-25000)) -> 25000 | AW21: =IF(AC21=0,AI21,(1*25000*12)+AI21-AC21) -> 0 | AX21: =IF(AD21=0,AJ21,(1*75000*12)+(AJ21)-AD21) -> 0 | AY21: =IF(AE21=0,AK21,(1*100000*12)+(AK21)-AE21) -> 0 | AZ21: =SUM(AV21:AY21)-BF21+Z21+BH21+BI21+BJ21+BK21+BL21+BM21+BN21 -> 0 | BC21: =F21 -> 0 | BD21: =IF(AZ21=0,(AZ21-BA21-BC21),(AZ21-BA21-BB21-BC21)) -> 0 | BF21: =Z21*1/100*BG21 -> 0 | BG21: 10 | BO21: RETRAIT COMPTE FOYER
A22: AS201649 | B22: =VLOOKUP(A22,[5]LISTADHERENT!A$5:H$50,3,0) -> MBOGNING TUGMA GUY | C22: =IF(I22<>"ECHEC",D22+E22+F22-U22,0) -> 0 | D22: =VLOOKUP(A22,[6]HISTOBQUEFEV25!$A$6:$H$48,5,0) -> 325000 | E22: =VLOOKUP(A22,[6]HISTOBQUEFEV25!$A$6:$H$43,4,0) -> 0 | F22: =VLOOKUP(A22,[6]HISTOBQUEFEV25!$A$6:$H$43,6,0) -> 0 | H22: =IF(I22="ESPECES",3000,0) -> 0 | I22: =IF($D22<>0,"BANQUE",IF($E22<>0,"ESPECES","ECHEC")) -> BANQUE | J22: 1 | K22: =IF($D22<>0,J22*50000,IF($E22<>0,J22*50000,0)) -> 50000 | L22: 1 | M22: =IF($D22<>0,L22*75000,IF($E22<>0,L22*75000,0)) -> 75000 | N22: 2 | O22: =IF($D22<>0,N22*100000,IF($E22<>0,N22*100000,0)) -> 200000 | P22: =IFERROR(VLOOKUP(A22,[7]TONTFEV25!$A$6:$R$41,12,0),0) -> 0 | Q22: =IFERROR(VLOOKUP(A22,[8]TONTFEV25!$A$6:$R$38,10,0),0) -> 0 | R22: =IFERROR(VLOOKUP(A22,[9]TONTFEV25!$A$6:$R$42,10,0),0) -> 0 | U22: =G22+H22+S22+R22+P22+O22+M22+K22+Q22+V22+W22 -> 325000 | Y22: =K22+M22+O22 -> 325000 | AD22: 45000 | AE22: 85000 | AF22: BANQUE | AJ22: 50000 | AM22: 1000 | AP22: BANQUE | AQ22: =IF(I22="ECHEC",((K22+M22+O22)*20/100),0) -> 0 | AR22: =IF(I22="ECHEC",((K22+M22+O22)*20/100),0) -> 0 | AS22: =IF(I22="ECHEC",0,(K22+G22-25000)) -> 25000 | AW22: =IF(AC22=0,AI22,(1*25000*12)+AI22-AC22) -> 0 | AX22: =IF(AD22=0,AJ22,(1*75000*12)+(AJ22)-AD22) -> 905000 | AY22: =IF(AE22=0,AK22,(1*100000*12)+(AK22)-AE22) -> 1115000 | AZ22: =SUM(AV22:AY22)-BF22+Z22+BH22+BI22+BJ22+BK22+BL22+BM22+BN22 -> 2020000 | BC22: =F22 -> 0 | BD22: =IF(AZ22=0,(AZ22-BA22-BC22),(AZ22-BA22-BB22-BC22))-892500 -> 1127500 | BE22: OK | BF22: =Z22*1/100*BG22 -> 0 | BG22: 10
A23: AS201639 | B23: =VLOOKUP(A23,[5]LISTADHERENT!A$5:H$50,3,0) -> NANGUEN MARTIN | C23: =IF(I23<>"ECHEC",D23+E23+F23-U23,0) -> 0 | D23: =VLOOKUP(A23,[6]HISTOBQUEFEV25!$A$6:$H$48,5,0) -> 50000 | E23: =VLOOKUP(A23,[6]HISTOBQUEFEV25!$A$6:$H$43,4,0) -> 0 | F23: =VLOOKUP(A23,[6]HISTOBQUEFEV25!$A$6:$H$43,6,0) -> 0 | H23: =IF(I23="ESPECES",3000,0) -> 0 | I23: =IF($D23<>0,"BANQUE",IF($E23<>0,"ESPECES","ECHEC")) -> BANQUE | J23: 1 | K23: =IF($D23<>0,J23*50000,IF($E23<>0,J23*50000,0)) -> 50000 | M23: =IF($D23<>0,L23*75000,IF($E23<>0,L23*75000,0)) -> 0 | O23: =IF($D23<>0,N23*100000,IF($E23<>0,N23*100000,0)) -> 0 | P23: =IFERROR(VLOOKUP(A23,[7]TONTFEV25!$A$6:$R$41,12,0),0) -> 0 | Q23: =IFERROR(VLOOKUP(A23,[8]TONTFEV25!$A$6:$R$38,10,0),0) -> 0 | R23: =IFERROR(VLOOKUP(A23,[9]TONTFEV25!$A$6:$R$42,10,0),0) -> 0 | U23: =G23+H23+S23+R23+P23+O23+M23+K23+Q23+V23+W23 -> 50000 | Y23: =K23+M23+O23 -> 50000 | AQ23: =IF(I23="ECHEC",((K23+M23+O23)*20/100),0) -> 0 | AR23: =IF(I23="ECHEC",((K23+M23+O23)*20/100),0) -> 0 | AS23: =IF(I23="ECHEC",0,(K23+G23-25000)) -> 25000 | AW23: =IF(AC23=0,AI23,(1*25000*12)+AI23-AC23) -> 0 | AX23: =IF(AD23=0,AJ23,(1*75000*12)+(AJ23)-AD23) -> 0 | AY23: =IF(AE23=0,AK23,(1*100000*12)+(AK23)-AE23) -> 0 | AZ23: =SUM(AV23:AY23)-BF23+Z23+BH23+BI23+BJ23+BK23+BL23+BM23+BN23 -> 0 | BC23: =F23 -> 0 | BD23: =IF(AZ23=0,(AZ23-BA23-BC23),(AZ23-BA23-BB23-BC23)) -> 0 | BF23: =Z23*1/100*BG23 -> 0 | BG23: 10
A24: AS201621 | B24: =VLOOKUP(A24,[5]LISTADHERENT!A$5:H$50,3,0) -> NANKAM APPOLINAIRE | C24: =IF(I24<>"ECHEC",D24+E24+F24-U24,0) -> 0 | D24: =VLOOKUP(A24,[6]HISTOBQUEFEV25!$A$6:$H$48,5,0) -> 125000 | E24: =VLOOKUP(A24,[6]HISTOBQUEFEV25!$A$6:$H$43,4,0) -> 0 | F24: =VLOOKUP(A24,[6]HISTOBQUEFEV25!$A$6:$H$43,6,0) -> 892500 | G24: 892500 | H24: =IF(I24="ESPECES",3000,0) -> 0 | I24: =IF($D24<>0,"BANQUE",IF($E24<>0,"ESPECES","ECHEC")) -> BANQUE | J24: 1 | K24: =IF($D24<>0,J24*50000,IF($E24<>0,J24*50000,0)) -> 50000 | L24: 1 | M24: =IF($D24<>0,L24*75000,IF($E24<>0,L24*75000,0)) -> 75000 | O24: =IF($D24<>0,N24*100000,IF($E24<>0,N24*100000,0)) -> 0 | P24: =IFERROR(VLOOKUP(A24,[7]TONTFEV25!$A$6:$R$41,12,0),0) -> 0 | Q24: =IFERROR(VLOOKUP(A24,[8]TONTFEV25!$A$6:$R$38,10,0),0) -> 0 | R24: =IFERROR(VLOOKUP(A24,[9]TONTFEV25!$A$6:$R$42,10,0),0) -> 0 | U24: =G24+H24+S24+R24+P24+O24+M24+K24+Q24+V24+W24 -> 1017500 | Y24: =K24+M24+O24 -> 125000 | AQ24: =IF(I24="ECHEC",((K24+M24+O24)*20/100),0) -> 0 | AR24: =IF(I24="ECHEC",((K24+M24+O24)*20/100),0) -> 0 | AS24: =IF(I24="ECHEC",0,(K24+G24-25000)) -> 917500 | AV24: 600000 | AW24: =IF(AC24=0,AI24,(1*25000*12)+AI24-AC24) -> 0 | AX24: =IF(AD24=0,AJ24,(1*75000*12)+(AJ24)-AD24) -> 0 | AY24: =IF(AE24=0,AK24,(1*100000*12)+(AK24)-AE24) -> 0 | AZ24: =SUM(AV24:AY24)-BF24+Z24+BH24+BI24+BJ24+BK24+BL24+BM24+BN24 -> 600000 | BC24: =F24 -> 892500 | BD24: =IF(AZ24=0,(AZ24-BA24-BC24),(AZ24-BA24-BB24-BC24))+892500 -> 600000 | BE24: OK | BF24: =Z24*1/100*BG24 -> 0 | BG24: 10 | BO24: S/TOTAL | BQ24: =SUM(BQ19:BQ23) -> 0
A25: AS201622 | B25: =VLOOKUP(A25,[5]LISTADHERENT!A$5:H$50,3,0) -> NDJOMO ETIENNE | C25: =IF(I25<>"ECHEC",D25+E25+F25-U25,0) -> 0 | D25: =VLOOKUP(A25,[6]HISTOBQUEFEV25!$A$6:$H$48,5,0) -> 260000 | E25: =VLOOKUP(A25,[6]HISTOBQUEFEV25!$A$6:$H$43,4,0) -> 0 | F25: =VLOOKUP(A25,[6]HISTOBQUEFEV25!$A$6:$H$43,6,0) -> 0 | G25: 10000 | H25: =IF(I25="ESPECES",3000,0) -> 0 | I25: =IF($D25<>0,"BANQUE",IF($E25<>0,"ESPECES","ECHEC")) -> BANQUE | J25: 1 | K25: =IF($D25<>0,J25*50000,IF($E25<>0,J25*50000,0)) -> 50000 | M25: =IF($D25<>0,L25*75000,IF($E25<>0,L25*75000,0)) -> 0 | N25: 2 | O25: =IF($D25<>0,N25*100000,IF($E25<>0,N25*100000,0)) -> 200000 | P25: =IFERROR(VLOOKUP(A25,[7]TONTFEV25!$A$6:$R$41,12,0),0) -> 0 | Q25: =IFERROR(VLOOKUP(A25,[8]TONTFEV25!$A$6:$R$38,10,0),0) -> 0 | R25: =IFERROR(VLOOKUP(A25,[9]TONTFEV25!$A$6:$R$42,10,0),0) -> 0 | U25: =G25+H25+S25+R25+P25+O25+M25+K25+Q25+V25+W25 -> 260000 | Y25: =K25+M25+O25 -> 250000 | AK25: 100000 | AN25: 1000 | AP25: BANQUE | AQ25: =IF(I25="ECHEC",((K25+M25+O25)*20/100),0) -> 0 | AR25: =IF(I25="ECHEC",((K25+M25+O25)*20/100),0) -> 0 | AS25: =IF(I25="ECHEC",0,(K25+G25-25000)) -> 35000 | AW25: =IF(AC25=0,AI25,(1*25000*12)+AI25-AC25) -> 0 | AX25: =IF(AD25=0,AJ25,(1*75000*12)+(AJ25)-AD25) -> 0 | AY25: =IF(AE25=0,AK25,(1*100000*12)+(AK25)-AE25) -> 100000 | AZ25: =SUM(AV25:AY25)-BF25+Z25+BH25+BI25+BJ25+BK25+BL25+BM25+BN25 -> 100000 | BC25: =F25 -> 0 | BD25: =IF(AZ25=0,(AZ25-BA25-BC25),(AZ25-BA25-BB25-BC25)) -> 100000 | BE25: OK | BF25: =Z25*1/100*BG25 -> 0 | BG25: 10
A26: AS201624 | B26: =VLOOKUP(A26,[5]LISTADHERENT!A$5:H$50,3,0) -> NGONDIEP CLAUDE | C26: =IF(I26<>"ECHEC",D26+E26+F26-U26,0) -> 0 | D26: =VLOOKUP(A26,[6]HISTOBQUEFEV25!$A$6:$H$48,5,0) -> 240000 | E26: =VLOOKUP(A26,[6]HISTOBQUEFEV25!$A$6:$H$43,4,0) -> 0 | F26: =VLOOKUP(A26,[6]HISTOBQUEFEV25!$A$6:$H$43,6,0) -> 0 | G26: 15000 | H26: =IF(I26="ESPECES",3000,0) -> 0 | I26: =IF($D26<>0,"BANQUE",IF($E26<>0,"ESPECES","ECHEC")) -> BANQUE | J26: 1 | K26: =IF($D26<>0,J26*50000,IF($E26<>0,J26*50000,0)) -> 50000 | L26: 1 | M26: =IF($D26<>0,L26*75000,IF($E26<>0,L26*75000,0)) -> 75000 | N26: 1 | O26: =IF($D26<>0,N26*100000,IF($E26<>0,N26*100000,0)) -> 100000 | P26: =IFERROR(VLOOKUP(A26,[7]TONTFEV25!$A$6:$R$41,12,0),0) -> 0 | Q26: =IFERROR(VLOOKUP(A26,[8]TONTFEV25!$A$6:$R$38,10,0),0) -> 0 | R26: =IFERROR(VLOOKUP(A26,[9]TONTFEV25!$A$6:$R$42,10,0),0) -> 0 | U26: =G26+H26+S26+R26+P26+O26+M26+K26+Q26+V26+W26 -> 240000 | Y26: =K26+M26+O26 -> 225000 | AQ26: =IF(I26="ECHEC",((K26+M26+O26)*20/100),0) -> 0 | AR26: =IF(I26="ECHEC",((K26+M26+O26)*20/100),0) -> 0 | AS26: =IF(I26="ECHEC",0,(K26+G26-25000)) -> 40000 | AW26: =IF(AC26=0,AI26,(1*25000*12)+AI26-AC26) -> 0 | AX26: =IF(AD26=0,AJ26,(1*75000*12)+(AJ26)-AD26) -> 0 | AY26: =IF(AE26=0,AK26,(1*100000*12)+(AK26)-AE26) -> 0 | AZ26: =SUM(AV26:AY26)-BF26+Z26+BH26+BI26+BJ26+BK26+BL26+BM26+BN26 -> 0 | BC26: =F26 -> 0 | BD26: =IF(AZ26=0,(AZ26-BA26-BC26),(AZ26-BA26-BB26-BC26)) -> 0 | BF26: =Z26*1/100*BG26 -> 0 | BG26: 10 | BO26: GRATIFICATION BUREAU 2023 | BP26: FRAIS EXEPTIONNEL
A27: AS201626 | B27: =VLOOKUP(A27,[5]LISTADHERENT!A$5:H$50,3,0) -> NGUIEMEGNI MATHIEU BLAISE | C27: =IF(I27<>"ECHEC",D27+E27+F27-U27,0) -> 0 | D27: =VLOOKUP(A27,[6]HISTOBQUEFEV25!$A$6:$H$48,5,0) -> 225000 | E27: =VLOOKUP(A27,[6]HISTOBQUEFEV25!$A$6:$H$43,4,0) -> 25000 | F27: =VLOOKUP(A27,[6]HISTOBQUEFEV25!$A$6:$H$43,6,0) -> 0 | H27: =IF(I27="ESPECES",3000,0) -> 0 | I27: =IF($D27<>0,"BANQUE",IF($E27<>0,"ESPECES","ECHEC")) -> BANQUE | J27: 1 | K27: =IF($D27<>0,J27*50000,IF($E27<>0,J27*50000,0)) -> 50000 | M27: =IF($D27<>0,L27*75000,IF($E27<>0,L27*75000,0)) -> 0 | N27: 2 | O27: =IF($D27<>0,N27*100000,IF($E27<>0,N27*100000,0)) -> 200000 | P27: =IFERROR(VLOOKUP(A27,[7]TONTFEV25!$A$6:$R$41,12,0),0) -> 0 | Q27: =IFERROR(VLOOKUP(A27,[8]TONTFEV25!$A$6:$R$38,10,0),0) -> 0 | R27: =IFERROR(VLOOKUP(A27,[9]TONTFEV25!$A$6:$R$42,10,0),0) -> 0 | U27: =G27+H27+S27+R27+P27+O27+M27+K27+Q27+V27+W27 -> 250000 | Y27: =K27+M27+O27 -> 250000 | AC27: 26000 | AF27: BANQUE | AK27: 200000 | AN27: =3000+3500 -> 6500 | AP27: BANQUE | AQ27: =IF(I27="ECHEC",((K27+M27+O27)*20/100),0) -> 0 | AR27: =IF(I27="ECHEC",((K27+M27+O27)*20/100),0) -> 0 | AS27: =IF(I27="ECHEC",0,(K27+G27-25000)) -> 25000 | AW27: =IF(AC27=0,AI27,(1*25000*12)+AI27-AC27) -> 274000 | AX27: =IF(AD27=0,AJ27,(1*75000*12)+(AJ27)-AD27) -> 0 | AY27: =IF(AE27=0,AK27,(1*100000*12)+(AK27)-AE27) -> 200000 | AZ27: =SUM(AV27:AY27)-BF27+Z27+BH27+BI27+BJ27+BK27+BL27+BM27+BN27 -> 474000 | BC27: =F27 -> 0 | BD27: =IF(AZ27=0,(AZ27-BA27-BC27),(AZ27-BA27-BB27-BC27)) -> 474000 | BE27: OK | BF27: =Z27*1/100*BG27 -> 0 | BG27: 10 | BO27: DOSSIER TECHNIQUE NGIEMENI | BP27: FRAIS EXEPTIONNEL
A28: AS201628 | B28: =VLOOKUP(A28,[5]LISTADHERENT!A$5:H$50,3,0) -> NKAMGANG JUSTIN DEJOLIE | C28: =IF(I28<>"ECHEC",D28+E28+F28-U28,0) -> 0 | D28: =VLOOKUP(A28,[6]HISTOBQUEFEV25!$A$6:$H$48,5,0) -> 100000 | E28: =VLOOKUP(A28,[6]HISTOBQUEFEV25!$A$6:$H$43,4,0) -> 0 | F28: =VLOOKUP(A28,[6]HISTOBQUEFEV25!$A$6:$H$43,6,0) -> 0 | G28: 8000 | H28: =IF(I28="ESPECES",3000,0) -> 0 | I28: =IF($D28<>0,"BANQUE",IF($E28<>0,"ESPECES","ECHEC")) -> BANQUE | J28: 1 | K28: =IF($D28<>0,J28*50000,IF($E28<>0,J28*50000,0)) -> 50000 | M28: =IF($D28<>0,L28*75000,IF($E28<>0,L28*75000,0)) -> 0 | O28: =IF($D28<>0,N28*100000,IF($E28<>0,N28*100000,0)) -> 0 | P28: =IFERROR(VLOOKUP(A28,[7]TONTFEV25!$A$6:$R$41,12,0),0) -> 42000 | Q28: =IFERROR(VLOOKUP(A28,[8]TONTFEV25!$A$6:$R$38,10,0),0) -> 0 | R28: =IFERROR(VLOOKUP(A28,[9]TONTFEV25!$A$6:$R$42,10,0),0) -> 0 | U28: =G28+H28+S28+R28+P28+O28+M28+K28+Q28+V28+W28 -> 100000 | Y28: =K28+M28+O28 -> 50000 | AC28: 27000 | AF28: BANQUE | AI28: 41000 | AL28: 1000 | AP28: BANQUE | AQ28: =IF(I28="ECHEC",((K28+M28+O28)*20/100),0) -> 0 | AR28: =IF(I28="ECHEC",((K28+M28+O28)*20/100),0) -> 0 | AS28: =IF(I28="ECHEC",0,(K28+G28-25000)) -> 33000 | AW28: =IF(AC28=0,AI28,(1*25000*12)+AI28-AC28) -> 314000 | AX28: =IF(AD28=0,AJ28,(1*75000*12)+(AJ28)-AD28) -> 0 | AY28: =IF(AE28=0,AK28,(1*100000*12)+(AK28)-AE28) -> 0 | AZ28: =SUM(AV28:AY28)-BF28+Z28+BH28+BI28+BJ28+BK28+BL28+BM28+BN28 -> 314000 | BA28: 41000 | BC28: =F28 -> 0 | BD28: =IF(AZ28=0,(AZ28-BA28-BC28),(AZ28-BA28-BB28-BC28)) -> 273000 | BE28: OK | BF28: =Z28*1/100*BG28 -> 0 | BG28: 10
A29: AS201656 | B29: =VLOOKUP(A29,[5]LISTADHERENT!A$5:H$50,3,0) -> NOUBE ETIENNE | C29: =IF(I29<>"ECHEC",D29+E29+F29-U29,0) -> 0 | D29: =VLOOKUP(A29,[6]HISTOBQUEFEV25!$A$6:$H$48,5,0) -> 50000 | E29: =VLOOKUP(A29,[6]HISTOBQUEFEV25!$A$6:$H$43,4,0) -> 0 | F29: =VLOOKUP(A29,[6]HISTOBQUEFEV25!$A$6:$H$43,6,0) -> 0 | H29: =IF(I29="ESPECES",3000,0) -> 0 | I29: =IF($D29<>0,"BANQUE",IF($E29<>0,"ESPECES","ECHEC")) -> BANQUE | J29: 1 | K29: =IF($D29<>0,J29*50000,IF($E29<>0,J29*50000,0)) -> 50000 | M29: =IF($D29<>0,L29*75000,IF($E29<>0,L29*75000,0)) -> 0 | O29: =IF($D29<>0,N29*100000,IF($E29<>0,N29*100000,0)) -> 0 | P29: =IFERROR(VLOOKUP(A29,[7]TONTFEV25!$A$6:$R$41,12,0),0) -> 0 | Q29: =IFERROR(VLOOKUP(A29,[8]TONTFEV25!$A$6:$R$38,10,0),0) -> 0 | R29: =IFERROR(VLOOKUP(A29,[9]TONTFEV25!$A$6:$R$42,10,0),0) -> 0 | U29: =G29+H29+S29+R29+P29+O29+M29+K29+Q29+V29+W29 -> 50000 | Y29: =K29+M29+O29 -> 50000 | AQ29: =IF(I29="ECHEC",((K29+M29+O29)*20/100),0) -> 0 | AR29: =IF(I29="ECHEC",((K29+M29+O29)*20/100),0) -> 0 | AS29: =IF(I29="ECHEC",0,(K29+G29-25000)) -> 25000 | AW29: =IF(AC29=0,AI29,(1*25000*12)+AI29-AC29) -> 0 | AX29: =IF(AD29=0,AJ29,(1*75000*12)+(AJ29)-AD29) -> 0 | AY29: =IF(AE29=0,AK29,(1*100000*12)+(AK29)-AE29) -> 0 | AZ29: =SUM(AV29:AY29)-BF29+Z29+BH29+BI29+BJ29+BK29+BL29+BM29+BN29 -> 0 | BC29: =F29 -> 0 | BD29: =IF(AZ29=0,(AZ29-BA29-BC29),(AZ29-BA29-BB29-BC29)) -> 0 | BF29: =Z29*1/100*BG29 -> 0 | BG29: 10
A30: AS201633 | B30: =VLOOKUP(A30,[5]LISTADHERENT!A$5:H$50,3,0) -> PATEGO NJOSSU GUSTAVE | C30: =IF(I30<>"ECHEC",D30+E30+F30-U30,0) -> 0 | D30: =VLOOKUP(A30,[6]HISTOBQUEFEV25!$A$6:$H$48,5,0) -> 125000 | E30: =VLOOKUP(A30,[6]HISTOBQUEFEV25!$A$6:$H$43,4,0) -> 0 | F30: =VLOOKUP(A30,[6]HISTOBQUEFEV25!$A$6:$H$43,6,0) -> 0 | H30: =IF(I30="ESPECES",3000,0) -> 0 | I30: =IF($D30<>0,"BANQUE",IF($E30<>0,"ESPECES","ECHEC")) -> BANQUE | J30: 1 | K30: =IF($D30<>0,J30*50000,IF($E30<>0,J30*50000,0)) -> 50000 | L30: 1 | M30: =IF($D30<>0,L30*75000,IF($E30<>0,L30*75000,0)) -> 75000 | O30: =IF($D30<>0,N30*100000,IF($E30<>0,N30*100000,0)) -> 0 | P30: =IFERROR(VLOOKUP(A30,[7]TONTFEV25!$A$6:$R$41,12,0),0) -> 0 | Q30: =IFERROR(VLOOKUP(A30,[8]TONTFEV25!$A$6:$R$38,10,0),0) -> 0 | R30: =IFERROR(VLOOKUP(A30,[9]TONTFEV25!$A$6:$R$42,10,0),0) -> 0 | U30: =G30+H30+S30+R30+P30+O30+M30+K30+Q30+V30+W30 -> 125000 | Y30: =K30+M30+O30 -> 125000 | AQ30: =IF(I30="ECHEC",((K30+M30+O30)*20/100),0) -> 0 | AR30: =IF(I30="ECHEC",((K30+M30+O30)*20/100),0) -> 0 | AS30: =IF(I30="ECHEC",0,(K30+G30-25000)) -> 25000 | AW30: =IF(AC30=0,AI30,(1*25000*12)+AI30-AC30) -> 0 | AX30: =IF(AD30=0,AJ30,(1*75000*12)+(AJ30)-AD30) -> 0 | AY30: =IF(AE30=0,AK30,(1*100000*12)+(AK30)-AE30) -> 0 | AZ30: =SUM(AV30:AY30)-BF30+Z30+BH30+BI30+BJ30+BK30+BL30+BM30+BN30 -> 0 | BC30: =F30 -> 0 | BD30: =IF(AZ30=0,(AZ30-BA30-BC30),(AZ30-BA30-BB30-BC30)) -> 0 | BF30: =Z30*1/100*BG30 -> 0 | BG30: 10 | BO30: S/TOTAL | BQ30: =SUM(BQ26:BQ28) -> 0
A31: AS201657 | B31: =VLOOKUP(A31,[5]LISTADHERENT!A$5:H$50,3,0) -> SEUMO POLYCARPE | C31: =IF(I31<>"ECHEC",D31+E31+F31-U31,0) -> 0 | D31: =VLOOKUP(A31,[6]HISTOBQUEFEV25!$A$6:$H$48,5,0) -> 50000 | E31: =VLOOKUP(A31,[6]HISTOBQUEFEV25!$A$6:$H$43,4,0) -> 0 | F31: =VLOOKUP(A31,[6]HISTOBQUEFEV25!$A$6:$H$43,6,0) -> 0 | H31: =IF(I31="ESPECES",3000,0) -> 0 | I31: =IF($D31<>0,"BANQUE",IF($E31<>0,"ESPECES","ECHEC")) -> BANQUE | J31: 1 | K31: =IF($D31<>0,J31*50000,IF($E31<>0,J31*50000,0)) -> 50000 | M31: =IF($D31<>0,L31*75000,IF($E31<>0,L31*75000,0)) -> 0 | O31: =IF($D31<>0,N31*100000,IF($E31<>0,N31*100000,0)) -> 0 | P31: =IFERROR(VLOOKUP(A31,[7]TONTFEV25!$A$6:$R$41,12,0),0) -> 0 | Q31: =IFERROR(VLOOKUP(A31,[8]TONTFEV25!$A$6:$R$38,10,0),0) -> 0 | R31: =IFERROR(VLOOKUP(A31,[9]TONTFEV25!$A$6:$R$42,10,0),0) -> 0 | U31: =G31+H31+S31+R31+P31+O31+M31+K31+Q31+V31+W31 -> 50000 | Y31: =K31+M31+O31 -> 50000 | AI31: 40000 | AL31: 1000 | AP31: BANQUE | AQ31: =IF(I31="ECHEC",((K31+M31+O31)*20/100),0) -> 0 | AR31: =IF(I31="ECHEC",((K31+M31+O31)*20/100),0) -> 0 | AS31: =IF(I31="ECHEC",0,(K31+G31-25000)) -> 25000 | AW31: =IF(AC31=0,AI31,(1*25000*12)+AI31-AC31) -> 40000 | AX31: =IF(AD31=0,AJ31,(1*75000*12)+(AJ31)-AD31) -> 0 | AY31: =IF(AE31=0,AK31,(1*100000*12)+(AK31)-AE31) -> 0 | AZ31: =SUM(AV31:AY31)-BF31+Z31+BH31+BI31+BJ31+BK31+BL31+BM31+BN31 -> 40000 | BA31: 40000 | BC31: =F31 -> 0 | BD31: =IF(AZ31=0,(AZ31-BA31-BC31),(AZ31-BA31-BB31-BC31)) -> 0 | BF31: =Z31*1/100*BG31 -> 0 | BG31: 10
A32: AS201653 | B32: =VLOOKUP(A32,[5]LISTADHERENT!A$5:H$50,3,0) -> SIME BRICE | C32: =IF(I32<>"ECHEC",D32+E32+F32-U32,0) -> 0 | D32: =VLOOKUP(A32,[6]HISTOBQUEFEV25!$A$6:$H$48,5,0) -> 250000 | E32: =VLOOKUP(A32,[6]HISTOBQUEFEV25!$A$6:$H$43,4,0) -> 0 | F32: =VLOOKUP(A32,[6]HISTOBQUEFEV25!$A$6:$H$43,6,0) -> 0 | H32: =IF(I32="ESPECES",3000,0) -> 0 | I32: =IF($D32<>0,"BANQUE",IF($E32<>0,"ESPECES","ECHEC")) -> BANQUE | J32: 1 | K32: =IF($D32<>0,J32*50000,IF($E32<>0,J32*50000,0)) -> 50000 | M32: =IF($D32<>0,L32*75000,IF($E32<>0,L32*75000,0)) -> 0 | N32: 2 | O32: =IF($D32<>0,N32*100000,IF($E32<>0,N32*100000,0)) -> 200000 | P32: =IFERROR(VLOOKUP(A32,[7]TONTFEV25!$A$6:$R$41,12,0),0) -> 0 | Q32: =IFERROR(VLOOKUP(A32,[8]TONTFEV25!$A$6:$R$38,10,0),0) -> 0 | R32: =IFERROR(VLOOKUP(A32,[9]TONTFEV25!$A$6:$R$42,10,0),0) -> 0 | U32: =G32+H32+S32+R32+P32+O32+M32+K32+Q32+V32+W32 -> 250000 | Y32: =K32+M32+O32 -> 250000 | AQ32: =IF(I32="ECHEC",((K32+M32+O32)*20/100),0) -> 0 | AR32: =IF(I32="ECHEC",((K32+M32+O32)*20/100),0) -> 0 | AS32: =IF(I32="ECHEC",0,(K32+G32-25000)) -> 25000 | AW32: =IF(AC32=0,AI32,(1*25000*12)+AI32-AC32) -> 0 | AX32: =IF(AD32=0,AJ32,(1*75000*12)+(AJ32)-AD32) -> 0 | AY32: =IF(AE32=0,AK32,(1*100000*12)+(AK32)-AE32) -> 0 | AZ32: =SUM(AV32:AY32)-BF32+Z32+BH32+BI32+BJ32+BK32+BL32+BM32+BN32 -> 0 | BC32: =F32 -> 0 | BD32: =IF(AZ32=0,(AZ32-BA32-BC32),(AZ32-BA32-BB32-BC32)) -> 0 | BF32: =Z32*1/100*BG32 -> 0 | BG32: 10 | BO32: DECES | BP32: MUTUELLE
A33: AS201629 | B33: =VLOOKUP(A33,[5]LISTADHERENT!A$5:H$50,3,0) -> SIMO FONGANG ERIC | C33: =IF(I33<>"ECHEC",D33+E33+F33-U33,0) -> 0 | D33: =VLOOKUP(A33,[6]HISTOBQUEFEV25!$A$6:$H$48,5,0) -> 50000 | E33: =VLOOKUP(A33,[6]HISTOBQUEFEV25!$A$6:$H$43,4,0) -> 0 | F33: =VLOOKUP(A33,[6]HISTOBQUEFEV25!$A$6:$H$43,6,0) -> 0 | H33: =IF(I33="ESPECES",3000,0) -> 0 | I33: =IF($D33<>0,"BANQUE",IF($E33<>0,"ESPECES","ECHEC")) -> BANQUE | J33: 1 | K33: =IF($D33<>0,J33*50000,IF($E33<>0,J33*50000,0)) -> 50000 | P33: =IFERROR(VLOOKUP(A33,[7]TONTFEV25!$A$6:$R$41,12,0),0) -> 0 | Q33: =IFERROR(VLOOKUP(A33,[8]TONTFEV25!$A$6:$R$38,10,0),0) -> 0 | R33: =IFERROR(VLOOKUP(A33,[9]TONTFEV25!$A$6:$R$42,10,0),0) -> 0 | U33: =G33+H33+S33+R33+P33+O33+M33+K33+Q33+V33+W33 -> 50000 | Y33: =K33+M33+O33 -> 50000 | AQ33: =IF(I33="ECHEC",((K33+M33+O33)*20/100),0) -> 0 | AR33: =IF(I33="ECHEC",((K33+M33+O33)*20/100),0) -> 0 | AS33: =IF(I33="ECHEC",0,(K33+G33-25000)) -> 25000 | AW33: =IF(AC33=0,AI33,(1*25000*12)+AI33-AC33) -> 0 | AX33: =IF(AD33=0,AJ33,(1*75000*12)+(AJ33)-AD33) -> 0 | AY33: =IF(AE33=0,AK33,(1*100000*12)+(AK33)-AE33) -> 0 | AZ33: =SUM(AV33:AY33)-BF33+Z33+BH33+BI33+BJ33+BK33+BL33+BM33+BN33 -> 0 | BC33: =F33 -> 0 | BD33: =IF(AZ33=0,(AZ33-BA33-BC33),(AZ33-BA33-BB33-BC33)) -> 0 | BF33: =Z33*1/100*BG33 -> 0 | BG33: 10
A34: AS201638 | B34: =VLOOKUP(A34,[5]LISTADHERENT!A$5:H$50,3,0) -> SIMO PIERRE | C34: =IF(I34<>"ECHEC",D34+E34+F34-U34,0) -> 0 | D34: =VLOOKUP(A34,[6]HISTOBQUEFEV25!$A$6:$H$48,5,0) -> 150000 | E34: =VLOOKUP(A34,[6]HISTOBQUEFEV25!$A$6:$H$43,4,0) -> 0 | F34: =VLOOKUP(A34,[6]HISTOBQUEFEV25!$A$6:$H$43,6,0) -> 0 | H34: =IF(I34="ESPECES",3000,0) -> 0 | I34: =IF($D34<>0,"BANQUE",IF($E34<>0,"ESPECES","ECHEC")) -> BANQUE | J34: 1 | K34: =IF($D34<>0,J34*50000,IF($E34<>0,J34*50000,0)) -> 50000 | M34: =IF($D34<>0,L34*75000,IF($E34<>0,L34*75000,0)) -> 0 | N34: 1 | O34: =IF($D34<>0,N34*100000,IF($E34<>0,N34*100000,0)) -> 100000 | P34: =IFERROR(VLOOKUP(A34,[7]TONTFEV25!$A$6:$R$41,12,0),0) -> 0 | Q34: =IFERROR(VLOOKUP(A34,[8]TONTFEV25!$A$6:$R$38,10,0),0) -> 0 | R34: =IFERROR(VLOOKUP(A34,[9]TONTFEV25!$A$6:$R$42,10,0),0) -> 0 | U34: =G34+H34+S34+R34+P34+O34+M34+K34+Q34+V34+W34 -> 150000 | Y34: =K34+M34+O34 -> 150000 | AE34: 70000 | AF34: BANQUE | AQ34: =IF(I34="ECHEC",((K34+M34+O34)*20/100),0) -> 0 | AR34: =IF(I34="ECHEC",((K34+M34+O34)*20/100),0) -> 0 | AS34: =IF(I34="ECHEC",0,(K34+G34-25000)) -> 25000 | AW34: =IF(AC34=0,AI34,(1*25000*12)+AI34-AC34) -> 0 | AX34: =IF(AD34=0,AJ34,(1*75000*12)+(AJ34)-AD34) -> 0 | AY34: =IF(AE34=0,AK34,(1*100000*12)+(AK34)-AE34) -> 1130000 | AZ34: =SUM(AV34:AY34)-BF34+Z34+BH34+BI34+BJ34+BK34+BL34+BM34+BN34 -> 1130000 | BC34: =F34 -> 0 | BD34: =IF(AZ34=0,(AZ34-BA34-BC34),(AZ34-BA34-BB34-BC34)) -> 1130000 | BE34: OK | BF34: =Z34*1/100*BG34 -> 0 | BG34: 10
A35: AS201641 | B35: =VLOOKUP(A35,[5]LISTADHERENT!A$5:H$50,3,0) -> TCHOUAMOU MATHIEU | C35: =IF(I35<>"ECHEC",D35+E35+F35-U35,0) -> 0 | D35: =VLOOKUP(A35,[6]HISTOBQUEFEV25!$A$6:$H$48,5,0) -> 125000 | E35: =VLOOKUP(A35,[6]HISTOBQUEFEV25!$A$6:$H$43,4,0) -> 0 | F35: =VLOOKUP(A35,[6]HISTOBQUEFEV25!$A$6:$H$43,6,0) -> 0 | H35: =IF(I35="ESPECES",3000,0) -> 0 | I35: =IF($D35<>0,"BANQUE",IF($E35<>0,"ESPECES","ECHEC")) -> BANQUE | J35: 1 | K35: =IF($D35<>0,J35*50000,IF($E35<>0,J35*50000,0)) -> 50000 | L35: 1 | M35: =IF($D35<>0,L35*75000,IF($E35<>0,L35*75000,0)) -> 75000 | O35: =IF($D35<>0,N35*100000,IF($E35<>0,N35*100000,0)) -> 0 | P35: =IFERROR(VLOOKUP(A35,[7]TONTFEV25!$A$6:$R$41,12,0),0) -> 0 | Q35: =IFERROR(VLOOKUP(A35,[8]TONTFEV25!$A$6:$R$38,10,0),0) -> 0 | R35: =IFERROR(VLOOKUP(A35,[9]TONTFEV25!$A$6:$R$42,10,0),0) -> 0 | U35: =G35+H35+S35+R35+P35+O35+M35+K35+Q35+V35+W35 -> 125000 | Y35: =K35+M35+O35 -> 125000 | AQ35: =IF(I35="ECHEC",((K35+M35+O35)*20/100),0) -> 0 | AR35: =IF(I35="ECHEC",((K35+M35+O35)*20/100),0) -> 0 | AS35: =IF(I35="ECHEC",0,(K35+G35-25000)) -> 25000 | AW35: =IF(AC35=0,AI35,(1*25000*12)+AI35-AC35) -> 0 | AX35: =IF(AD35=0,AJ35,(1*75000*12)+(AJ35)-AD35) -> 0 | AY35: =IF(AE35=0,AK35,(1*100000*12)+(AK35)-AE35) -> 0 | AZ35: =SUM(AV35:AY35)-BF35+Z35+BH35+BI35+BJ35+BK35+BL35+BM35+BN35 -> 0 | BC35: =F35 -> 0 | BD35: =IF(AZ35=0,(AZ35-BA35-BC35),(AZ35-BA35-BB35-BC35)) -> 0 | BF35: =Z35*1/100*BG35 -> 0 | BG35: 10
A36: AS201660 | B36: =VLOOKUP(A36,[5]LISTADHERENT!A$5:H$50,3,0) -> TCHOUATEU AUGUSTIN | C36: =IF(I36<>"ECHEC",D36+E36+F36-U36,0) -> 0 | D36: =VLOOKUP(A36,[6]HISTOBQUEFEV25!$A$6:$H$48,5,0) -> 150000 | E36: =VLOOKUP(A36,[6]HISTOBQUEFEV25!$A$6:$H$43,4,0) -> 0 | F36: =VLOOKUP(A36,[6]HISTOBQUEFEV25!$A$6:$H$43,6,0) -> 0 | H36: =IF(I36="ESPECES",3000,0) -> 0 | I36: =IF($D36<>0,"BANQUE",IF($E36<>0,"ESPECES","ECHEC")) -> BANQUE | J36: 1 | K36: =IF($D36<>0,J36*50000,IF($E36<>0,J36*50000,0)) -> 50000 | M36: =IF($D36<>0,L36*75000,IF($E36<>0,L36*75000,0)) -> 0 | N36: 1 | O36: =IF($D36<>0,N36*100000,IF($E36<>0,N36*100000,0)) -> 100000 | P36: =IFERROR(VLOOKUP(A36,[7]TONTFEV25!$A$6:$R$41,12,0),0) -> 0 | Q36: =IFERROR(VLOOKUP(A36,[8]TONTFEV25!$A$6:$R$38,10,0),0) -> 0 | R36: =IFERROR(VLOOKUP(A36,[9]TONTFEV25!$A$6:$R$42,10,0),0) -> 0 | U36: =G36+H36+S36+R36+P36+O36+M36+K36+Q36+V36+W36 -> 150000 | Y36: =K36+M36+O36 -> 150000 | AQ36: =IF(I36="ECHEC",((K36+M36+O36)*20/100),0) -> 0 | AR36: =IF(I36="ECHEC",((K36+M36+O36)*20/100),0) -> 0 | AS36: =IF(I36="ECHEC",0,(K36+G36-25000)) -> 25000 | AW36: =IF(AC36=0,AI36,(1*25000*12)+AI36-AC36) -> 0 | AX36: =IF(AD36=0,AJ36,(1*75000*12)+(AJ36)-AD36) -> 0 | AY36: =IF(AE36=0,AK36,(1*100000*12)+(AK36)-AE36) -> 0 | AZ36: =SUM(AV36:AY36)-BF36+Z36+BH36+BI36+BJ36+BK36+BL36+BM36+BN36 -> 0 | BC36: =F36 -> 0 | BD36: =IF(AZ36=0,(AZ36-BA36-BC36),(AZ36-BA36-BB36-BC36)) -> 0 | BF36: =Z36*1/100*BG36 -> 0 | BG36: 10 | BO36: S/TOTAL | BQ36: =SUM(BQ32:BQ35) -> 0
A37: AS201643 | B37: =VLOOKUP(A37,[5]LISTADHERENT!A$5:H$50,3,0) -> TCHOUTOU NANA CLAUDE | C37: =IF(I37<>"ECHEC",D37+E37+F37-U37,0) -> 0 | D37: =VLOOKUP(A37,[6]HISTOBQUEFEV25!$A$6:$H$48,5,0) -> 50000 | E37: =VLOOKUP(A37,[6]HISTOBQUEFEV25!$A$6:$H$43,4,0) -> 0 | F37: =VLOOKUP(A37,[6]HISTOBQUEFEV25!$A$6:$H$43,6,0) -> 0 | H37: =IF(I37="ESPECES",3000,0) -> 0 | I37: =IF($D37<>0,"BANQUE",IF($E37<>0,"ESPECES","ECHEC")) -> BANQUE | J37: 1 | K37: =IF($D37<>0,J37*50000,IF($E37<>0,J37*50000,0)) -> 50000 | M37: =IF($D37<>0,L37*75000,IF($E37<>0,L37*75000,0)) -> 0 | O37: =IF($D37<>0,N37*100000,IF($E37<>0,N37*100000,0)) -> 0 | P37: =IFERROR(VLOOKUP(A37,[7]TONTFEV25!$A$6:$R$41,12,0),0) -> 0 | Q37: =IFERROR(VLOOKUP(A37,[8]TONTFEV25!$A$6:$R$38,10,0),0) -> 0 | R37: =IFERROR(VLOOKUP(A37,[9]TONTFEV25!$A$6:$R$42,10,0),0) -> 0 | U37: =G37+H37+S37+R37+P37+O37+M37+K37+Q37+V37+W37 -> 50000 | Y37: =K37+M37+O37 -> 50000 | AQ37: =IF(I37="ECHEC",((K37+M37+O37)*20/100),0) -> 0 | AR37: =IF(I37="ECHEC",((K37+M37+O37)*20/100),0) -> 0 | AS37: =IF(I37="ECHEC",0,(K37+G37-25000)) -> 25000 | AW37: =IF(AC37=0,AI37,(1*25000*12)+AI37-AC37) -> 0 | AX37: =IF(AD37=0,AJ37,(1*75000*12)+(AJ37)-AD37) -> 0 | AY37: =IF(AE37=0,AK37,(1*100000*12)+(AK37)-AE37) -> 0 | AZ37: =SUM(AV37:AY37)-BF37+Z37+BH37+BI37+BJ37+BK37+BL37+BM37+BN37 -> 100000 | BC37: =F37 -> 0 | BD37: =IF(AZ37=0,(AZ37-BA37-BC37),(AZ37-BA37-BB37-BC37)) -> 100000 | BE37: OK | BF37: =Z37*1/100*BG37 -> 0 | BG37: 10 | BK37: 100000 | BO37: S/TOTAL | BQ37: =SUM(BQ34:BQ36) -> 0
A38: AS201662 | B38: =VLOOKUP(A38,[5]LISTADHERENT!A$5:H$50,3,0) -> TIEYAM ERNEST | C38: =IF(I38<>"ECHEC",D38+E38+F38-U38,0) -> 0 | D38: =VLOOKUP(A38,[6]HISTOBQUEFEV25!$A$6:$H$48,5,0) -> 0 | E38: =VLOOKUP(A38,[6]HISTOBQUEFEV25!$A$6:$H$43,4,0) -> 50000 | F38: =VLOOKUP(A38,[6]HISTOBQUEFEV25!$A$6:$H$43,6,0) -> 0 | H38: =IF(I38="ESPECES",3000,0)-3000 -> 0 | I38: =IF($D38<>0,"BANQUE",IF($E38<>0,"ESPECES","ECHEC")) -> ESPECES | J38: 1 | K38: =IF($D38<>0,J38*50000,IF($E38<>0,J38*50000,0)) -> 50000 | M38: =IF($D38<>0,L38*75000,IF($E38<>0,L38*75000,0)) -> 0 | O38: =IF($D38<>0,N38*100000,IF($E38<>0,N38*100000,0)) -> 0 | P38: =IFERROR(VLOOKUP(A38,[7]TONTFEV25!$A$6:$R$41,12,0),0) -> 0 | Q38: =IFERROR(VLOOKUP(A38,[8]TONTFEV25!$A$6:$R$38,10,0),0) -> 0 | R38: =IFERROR(VLOOKUP(A38,[9]TONTFEV25!$A$6:$R$42,10,0),0) -> 0 | U38: =G38+H38+S38+R38+P38+O38+M38+K38+Q38+V38+W38 -> 50000 | Y38: =K38+M38+O38 -> 50000 | AQ38: =IF(I38="ECHEC",((K38+M38+O38)*20/100),0) -> 0 | AR38: =IF(I38="ECHEC",((K38+M38+O38)*20/100),0) -> 0 | AS38: =IF(I38="ECHEC",0,(K38+G38-25000)) -> 25000 | AW38: =IF(AC38=0,AI38,(1*25000*12)+AI38-AC38) -> 0 | AX38: =IF(AD38=0,AJ38,(1*75000*12)+(AJ38)-AD38) -> 0 | AY38: =IF(AE38=0,AK38,(1*100000*12)+(AK38)-AE38) -> 0 | AZ38: =SUM(AV38:AY38)-BF38+Z38+BH38+BI38+BJ38+BK38+BL38+BM38+BN38 -> 0 | BC38: =F38 -> 0 | BD38: =IF(AZ38=0,(AZ38-BA38-BC38),(AZ38-BA38-BB38-BC38)) -> 0 | BF38: =Z38*1/100*BG38 -> 0 | BG38: 10
A39: AS201658 | B39: =VLOOKUP(A39,[5]LISTADHERENT!A$5:H$50,3,0) -> YANTCHOU GERVAIS | C39: =IF(I39<>"ECHEC",D39+E39+F39-U39,0) -> 0 | D39: =VLOOKUP(A39,[6]HISTOBQUEFEV25!$A$6:$H$48,5,0) -> 125000 | E39: =VLOOKUP(A39,[6]HISTOBQUEFEV25!$A$6:$H$43,4,0) -> 0 | F39: =VLOOKUP(A39,[6]HISTOBQUEFEV25!$A$6:$H$43,6,0) -> 0 | H39: =IF(I39="ESPECES",3000,0) -> 0 | I39: =IF($D39<>0,"BANQUE",IF($E39<>0,"ESPECES","ECHEC")) -> BANQUE | J39: 1 | K39: =IF($D39<>0,J39*50000,IF($E39<>0,J39*50000,0)) -> 50000 | L39: 1 | M39: =IF($D39<>0,L39*75000,IF($E39<>0,L39*75000,0)) -> 75000 | O39: =IF($D39<>0,N39*100000,IF($E39<>0,N39*100000,0)) -> 0 | P39: =IFERROR(VLOOKUP(A39,[7]TONTFEV25!$A$6:$R$41,12,0),0) -> 0 | Q39: =IFERROR(VLOOKUP(A39,[8]TONTFEV25!$A$6:$R$38,10,0),0) -> 0 | R39: =IFERROR(VLOOKUP(A39,[9]TONTFEV25!$A$6:$R$42,10,0),0) -> 0 | U39: =G39+H39+S39+R39+P39+O39+M39+K39+Q39+V39+W39 -> 125000 | Y39: =K39+M39+O39 -> 125000 | AQ39: =IF(I39="ECHEC",((K39+M39+O39)*20/100),0) -> 0 | AR39: =IF(I39="ECHEC",((K39+M39+O39)*20/100),0) -> 0 | AS39: =IF(I39="ECHEC",0,(K39+G39-25000)) -> 25000 | AW39: =IF(AC39=0,AI39,(1*25000*12)+AI39-AC39) -> 0 | AX39: =IF(AD39=0,AJ39,(1*75000*12)+(AJ39)-AD39) -> 0 | AY39: =IF(AE39=0,AK39,(1*100000*12)+(AK39)-AE39) -> 0 | AZ39: =SUM(AV39:AY39)-BF39+Z39+BH39+BI39+BJ39+BK39+BL39+BM39+BN39 -> 0 | BC39: =F39 -> 0 | BD39: =IF(AZ39=0,(AZ39-BA39-BC39),(AZ39-BA39-BB39-BC39)) -> 0 | BF39: =Z39*1/100*BG39 -> 0 | BG39: 10
A40: AS201646 | B40: =VLOOKUP(A40,[5]LISTADHERENT!A$5:H$50,3,0) -> YEPMOU JEAN JACQUES | C40: =IF(I40<>"ECHEC",D40+E40+F40-U40,0) -> 0 | D40: =VLOOKUP(A40,[6]HISTOBQUEFEV25!$A$6:$H$48,5,0) -> 0 | E40: =VLOOKUP(A40,[6]HISTOBQUEFEV25!$A$6:$H$43,4,0) -> 50000 | F40: =VLOOKUP(A40,[6]HISTOBQUEFEV25!$A$6:$H$43,6,0) -> 0 | G40: -3000 | H40: =IF(I40="ESPECES",3000,0) -> 3000 | I40: =IF($D40<>0,"BANQUE",IF($E40<>0,"ESPECES","ECHEC")) -> ESPECES | J40: 1 | K40: =IF($D40<>0,J40*50000,IF($E40<>0,J40*50000,0)) -> 50000 | M40: =IF($D40<>0,L40*75000,IF($E40<>0,L40*75000,0)) -> 0 | O40: =IF($D40<>0,N40*100000,IF($E40<>0,N40*100000,0)) -> 0 | P40: =IFERROR(VLOOKUP(A40,[7]TONTFEV25!$A$6:$R$41,12,0),0) -> 0 | Q40: =IFERROR(VLOOKUP(A40,[8]TONTFEV25!$A$6:$R$38,10,0),0) -> 0 | R40: =IFERROR(VLOOKUP(A40,[9]TONTFEV25!$A$6:$R$42,10,0),0) -> 0 | U40: =G40+H40+S40+R40+P40+O40+M40+K40+Q40+V40+W40 -> 50000 | Y40: =K40+M40+O40 -> 50000 | AQ40: =IF(I40="ECHEC",((K40+M40+O40)*20/100),0) -> 0 | AR40: =IF(I40="ECHEC",((K40+M40+O40)*20/100),0) -> 0 | AS40: =IF(I40="ECHEC",0,(K40+G40-25000)) -> 22000 | AW40: =IF(AC40=0,AI40,(1*25000*12)+AI40-AC40) -> 0 | AX40: =IF(AD40=0,AJ40,(1*75000*12)+(AJ40)-AD40) -> 0 | AY40: =IF(AE40=0,AK40,(1*100000*12)+(AK40)-AE40) -> 0 | AZ40: =SUM(AV40:AY40)-BF40+Z40+BH40+BI40+BJ40+BK40+BL40+BM40+BN40 -> 0 | BC40: =F40 -> 0 | BD40: =IF(AZ40=0,(AZ40-BA40-BC40),(AZ40-BA40-BB40-BC40)) -> 0 | BF40: =Z40*1/100*BG40 -> 0 | BG40: 10 | BO40: COLLATION | BP40: COLLATION
A41: AS201659 | B41: =VLOOKUP(A41,[5]LISTADHERENT!A$5:H$50,3,0) -> YIALA ALAIN OSCAR | C41: =IF(I41<>"ECHEC",D41+E41+F41-U41,0) -> 0 | D41: =VLOOKUP(A41,[6]HISTOBQUEFEV25!$A$6:$H$48,5,0) -> 250000 | E41: =VLOOKUP(A41,[6]HISTOBQUEFEV25!$A$6:$H$43,4,0) -> 0 | F41: =VLOOKUP(A41,[6]HISTOBQUEFEV25!$A$6:$H$43,6,0) -> 0 | H41: =IF(I41="ESPECES",3000,0) -> 0 | I41: =IF($D41<>0,"BANQUE",IF($E41<>0,"ESPECES","ECHEC")) -> BANQUE | J41: 1 | K41: =IF($D41<>0,J41*50000,IF($E41<>0,J41*50000,0)) -> 50000 | M41: =IF($D41<>0,L41*75000,IF($E41<>0,L41*75000,0)) -> 0 | N41: 2 | O41: =IF($D41<>0,N41*100000,IF($E41<>0,N41*100000,0)) -> 200000 | P41: =IFERROR(VLOOKUP(A41,[7]TONTFEV25!$A$6:$R$41,12,0),0) -> 0 | Q41: =IFERROR(VLOOKUP(A41,[8]TONTFEV25!$A$6:$R$38,10,0),0) -> 0 | R41: =IFERROR(VLOOKUP(A41,[9]TONTFEV25!$A$6:$R$42,10,0),0) -> 0 | U41: =G41+H41+S41+R41+P41+O41+M41+K41+Q41+V41+W41 -> 250000 | Y41: =K41+M41+O41 -> 250000 | AQ41: =IF(I41="ECHEC",((K41+M41+O41)*20/100),0) -> 0 | AR41: =IF(I41="ECHEC",((K41+M41+O41)*20/100),0) -> 0 | AS41: =IF(I41="ECHEC",0,(K41+G41-25000)) -> 25000 | AW41: =IF(AC41=0,AI41,(1*25000*12)+AI41-AC41) -> 0 | AX41: =IF(AD41=0,AJ41,(1*75000*12)+(AJ41)-AD41) -> 0 | AY41: =IF(AE41=0,AK41,(1*100000*12)+(AK41)-AE41) -> 0 | AZ41: =SUM(AV41:AY41)-BF41+Z41+BH41+BI41+BJ41+BK41+BL41+BM41+BN41 -> 0 | BC41: =F41 -> 0 | BD41: =IF(AZ41=0,(AZ41-BA41-BC41),(AZ41-BA41-BB41-BC41)) -> 0 | BF41: =Z41*1/100*BG41 -> 0 | BG41: 10 | BO41: BOISSON | BP41: COLLATION
A42: AS201647 | B42: =VLOOKUP(A42,[5]LISTADHERENT!A$5:H$50,3,0) -> YOUMBI EMMANUEL | C42: =IF(I42<>"ECHEC",D42+E42+F42-U42,0) -> 0 | D42: =VLOOKUP(A42,[6]HISTOBQUEFEV25!$A$6:$H$48,5,0) -> 225000 | E42: =VLOOKUP(A42,[6]HISTOBQUEFEV25!$A$6:$H$43,4,0) -> 0 | F42: =VLOOKUP(A42,[6]HISTOBQUEFEV25!$A$6:$H$43,6,0) -> 0 | H42: =IF(I42="ESPECES",3000,0) -> 0 | I42: =IF($D42<>0,"BANQUE",IF($E42<>0,"ESPECES","ECHEC")) -> BANQUE | J42: 1 | K42: =IF($D42<>0,J42*50000,IF($E42<>0,J42*50000,0)) -> 50000 | L42: 1 | M42: =IF($D42<>0,L42*75000,IF($E42<>0,L42*75000,0)) -> 75000 | N42: 1 | O42: =IF($D42<>0,N42*100000,IF($E42<>0,N42*100000,0)) -> 100000 | P42: =IFERROR(VLOOKUP(A42,[7]TONTFEV25!$A$6:$R$41,12,0),0) -> 0 | Q42: =IFERROR(VLOOKUP(A42,[8]TONTFEV25!$A$6:$R$38,10,0),0) -> 0 | R42: =IFERROR(VLOOKUP(A42,[9]TONTFEV25!$A$6:$R$42,10,0),0) -> 0 | U42: =G42+H42+S42+R42+P42+O42+M42+K42+Q42+V42+W42 -> 225000 | Y42: =K42+M42+O42 -> 225000 | AQ42: =IF(I42="ECHEC",((K42+M42+O42)*20/100),0) -> 0 | AR42: =IF(I42="ECHEC",((K42+M42+O42)*20/100),0) -> 0 | AS42: =IF(I42="ECHEC",0,(K42+G42-25000)) -> 25000 | AV42: 100000 | AW42: =IF(AC42=0,AI42,(1*25000*12)+AI42-AC42) -> 0 | AX42: =IF(AD42=0,AJ42,(1*75000*12)+(AJ42)-AD42) -> 0 | AY42: =IF(AE42=0,AK42,(1*100000*12)+(AK42)-AE42) -> 0 | AZ42: =SUM(AV42:AY42)-BF42+Z42+BH42+BI42+BJ42+BK42+BL42+BM42+BN42 -> 100000 | BC42: =F42 -> 0 | BD42: =IF(AZ42=0,(AZ42-BA42-BC42),(AZ42-BA42-BB42-BC42)) -> 100000 | BE42: OK | BF42: =Z42*1/100*BG42 -> 0 | BG42: 10
B44: TOTAUX | C44: =SUM(C6:C43) -> 25000 | D44: =SUM(D6:D43) -> 5655375 | E44: =SUM(E6:E43) -> 300000 | F44: =SUM(F6:F43) -> 892500 | G44: =SUM(G6:G43) -> 1627875 | H44: =SUM(H6:H43) -> 3000 | I44: =SUM(I6:I43) -> 0 | J44: =SUM(J6:J43) -> 35 | ... S44: =SUM(S6:S43) -> 0 | U44: =SUM(U6:U43) -> 6822875 | V44: =SUM(V6:V43) -> 0 | W44: =SUM(W6:W43) -> 25000 | X44: =SUM(X6:X43) -> 0 | Y44: =SUM(Y6:Y43) -> 5125000 | Z44: =SUM(Z6:Z43) -> 500000 | AA44: =SUM(AA6:AA43) -> 0 | AC44: =SUM(AC6:AC43) -> 79000 | AD44: =SUM(AD6:AD43) -> 45000 | AE44: =SUM(AE6:AE43) -> 235000 | AF44: =SUM(AF6:AF43) -> 0 | AG44: =SUM(AG6:AG43) -> 0 | AI44: =SUM(AI6:AI43) -> 121000 | AJ44: =SUM(AJ6:AJ43) -> 203000 | AK44: =SUM(AK6:AK43) -> 700000 | AL44: =SUM(AL6:AL43) -> 3000 | AM44: =SUM(AM6:AM43) -> 7500 | AN44: =SUM(AN6:AN43) -> 19500 | AO44: =SUM(AO6:AO43) -> 0 | AQ44: =SUM(AQ6:AQ43) -> 0 | AR44: =SUM(AR6:AR43) -> 0 | AS44: =SUM(AS6:AS43) -> 2527875 | AT44: =SUM(AT6:AT43) -> 0 | AU44: =SUM(AU6:AU43) -> 0 | AV44: =SUM(AV6:AV43) -> 700000 | AW44: =SUM(AW6:AW43) -> 942000 | AX44: =SUM(AX6:AX43) -> 1058000 | ... BF44: =SUM(BF6:BF43) -> 30000 | BH44: =SUM(BH6:BH43) -> 36000 | BI44: =SUM(BI6:BI43) -> 0 | BJ44: =SUM(BJ6:BJ43) -> 0 | BK44: =SUM(BK6:BK43) -> 100000 | BL44: =SUM(BL6:BL43) -> 0 | BM44: =SUM(BM6:BM43) -> 0 | BO44: S/TOTAL | BQ44: =SUM(BQ40:BQ42) -> 0
BA46: =E44 -> 300000 | BB46: ESPECES EN CAISSE | BD46: 5578500 | BE46: CHEQUE TIRE
B47: LIBELLE | C47: BANQUE | G47: ESPECES | BA47: =+BA46-BA44 -> 0 | BD47: =+BD46-BD44 -> -600000
C48: SORTIE | D48: ENTREE | E48: EN COMPTE | G48: ENTREE | H48: SORTIE | I48: SOLDE | BO48: S/TOTAL | BQ48: =SUM(BQ46:BQ47) -> 0
B49: REPORT
B50: OPERATIONS DU JOUR | C50: =BD44 -> 6178500 | D50: =+D44 -> 5655375 | E50: =+C50-D50 -> 523125 | G50: =E44 -> 300000 | H50: =+BA44 -> 300000 | I50: =+G50-H50 -> 0 | BO50: FOYER
AZ88: =SUM(AZ8:AZ87) -> 14706000

Sheet HISTOMARS25
A1: ASSOCIATION | B1: ASELBY
A2: ANNEE | B2: 2025
A3: 1 | B3: 2 | C3: 3 | D3: 4 | E3: 5 | F3: 6 | G3: 7 | H3: 8 | I3: 9 | J3: 10 | K3: 11 | L3: 12 | M3: 13 | N3: 14 | O3: 15 | P3: 16 | Q3: 17 | R3: 18 | S3: 19 | T3: 20 | U3: 21 | V3: 22 | W3: 23 | X3: 24 | Y3: 25 | Z3: 26 | AA3: 27 | AB3: 28 | AC3: 29 | AD3: 30 | AE3: 31 | AF3: 32 | AG3: 33 | AH3: 34 | AI3: 35 | AJ3: 36 | AK3: 37 | AL3: 38 | AM3: 39 | AN3: 40 | AO3: 41 | AP3: 42 | AQ3: 43 | AR3: 44 | AS3: 45 | AT3: 46 | AU3: 47 | AV3: 48 | AW3: 49 | AX3: 50 | AY3: 51 | AZ3: 52 | BA3: 53 | BB3: 54 | BC3: 55 | BD3: 56 | BE3: 57 | BF3: 58 | BG3: 59 | BH3: 60 | BI3: 61 | BJ3: 62 | BK3: 63 | BL3: 64 | BM3: 65 | BN3: 66 | BO3: 67 | BP3: 68 | BQ3: 69
B4: TABLEAU DE BORD SAISIE DES DONNEES
A5: MATRICULE | B5: NOM ET PRENOM | C5: BONUS MALUS | D5: VERSEMENT BANQUE | E5: VERSEMENT ESPECES | F5: AUTRE VERSEMENTS | G5: COMPLEMENT EPARGNE | H5: PENALITE VERSEMENT ESPECES | I5: MODE PAIEMENT TONTINE | J5: NBRE DE LOT | K5: TONTINE 25 000 | L5: NBRE DE LOT | M5: TONTINE 75 000 | N5: NBRE DE LOT | O5: TONTINE 100 000 | P5: REMBOURSEMENT PETIT LOT T25 | Q5: REMBOURSEMENT PETIT LOT T75 | R5: REMBOURSEMENT PETIT LOT T100 | S5: REMBOURSEMENT PRÊT FONDS | T5: MODE PAIEMENT REMBOURSEMENT PRÊT FONDS | U5: MONTANT ENGAGEMENT | V5: SANCTION | W5: INSCRIPTION | X5: EPARGNE ASSURANCE | Y5: TONTINE MOIS | Z5: PRÊT FONDS | AA5: MODE PAIEMENT PRÊT | AB5: NUM CHEQUE | AC5: ACHAT LOT PRINCIPAL T25 | AD5: ACHAT LOT PRINCIPAL T75 | AE5: ACHAT LOT PRINCIPAL T100 | AF5: MODE PAIEMENT LOT PRINCIPAL | AG5: NUM CHEQUE | AH5: PENALITE VERSEMENT ESPECES | AI5: VENTE PETIT LOT T25 | AJ5: VENTE PETIT LOT T75 | AK5: VENTE PETIT LOT T100 | AL5: INTERET PETIT LOT T25 | AM5: INTERET PETIT LOT T75 | AN5: INTERET PETIT LOT T100 | AO5: NUM CHEQUE | AP5: MODE REMBOURSEMENT PAIEMENT PETIT LOT | AQ5: PENELAITE RETARD TONTINE | AR5: PENELAITE ECHEC TONTINE | AS5: RESTE | AT5: MUTUELLE | AU5: REMBOURSEMENT TRANSPORT | AV5: RETRAIT PARTIEL FONDS | AW5: MONTANT T25 | AX5: MONTANT T75 | AY5: MONTANT T100 | AZ5: MONTANT CHEQUE | BA5: MONTANT ESPECES | BB5: CONTRIBUTION FOYER | BC5: AUTRES MODE DE VERST | BD5: MONTANT CHEQUE EFFECTIF | BE5: NUMERO CHEQUE | BF5: INTERET PRÊT | BG5: NBRE MOIS | BH5: DEPENSE FONDS DE ROULEMENT | BI5: DEPENSE FRAIS EXCEPTIONNEL | BJ5: DEPENSE FONDS MUTUEL | BK5: DEPENSE COLLATION RECEPTION | BL5: PENALITE PRET FONDS | BM5: DEPENSE PENALITE VERSEMENT BANQUE | BN5: AUTRES DEPENSES | BO5: LIBELLE | BP5: COMPTE | BQ5: MONTANT
A6: AS201648 | B6: =VLOOKUP(A6,[5]LISTADHERENT!A$5:H$50,3,0) -> ASELBY | C6: =IF(I6<>"ECHEC",D6+E6+F6-U6,0) -> 0 | D6: =VLOOKUP(A6,[6]HISTOBQUEMARS25!$A$6:$H$48,5,0) -> 250000 | E6: =VLOOKUP(A6,[6]HISTOBQUEMARS25!$A$6:$H$43,4,0) -> 0 | F6: =VLOOKUP(A6,[6]HISTOBQUEMARS25!$A$6:$H$43,6,0) -> 0 | H6: =IF(I6="ESPECES",3000,0) -> 0 | I6: =IF($D6<>0,"BANQUE",IF($E6<>0,"ESPECES","ECHEC")) -> BANQUE | K6: =IF($D6<>0,J6*50000,IF($E6<>0,J6*50000,0)) -> 0 | L6: 2 | M6: =IF($D6<>0,L6*75000,IF($E6<>0,L6*75000,0)) -> 150000 | N6: 1 | O6: =IF($D6<>0,N6*100000,IF($E6<>0,N6*100000,0)) -> 100000 | P6: =IFERROR(VLOOKUP(A6,[7]TONTMARS25!$A$6:$R$41,12,0),0) -> 0 | Q6: =IFERROR(VLOOKUP(A6,[8]TONTMARS25!$A$6:$R$41,10,0),0) -> 0 | R6: =IFERROR(VLOOKUP(A6,[9]TONTMARS25!$A$6:$R$42,10,0),0) -> 0 | U6: =G6+H6+S6+R6+P6+O6+M6+K6+Q6+V6+W6 -> 250000 | Y6: =K6+M6+O6 -> 250000 | AQ6: =IF(I6="ECHEC",((K6+M6+O6)*20/100),0) -> 0 | AR6: =IF(I6="ECHEC",((K6+M6+O6)*20/100),0) -> 0 | AW6: =IF(AC6=0,AI6,(1*25000*12)+AI6-AC6) -> 0 | AX6: =IF(AD6=0,AJ6,(1*75000*12)+(AJ6)-AD6) -> 0 | AY6: =IF(AE6=0,AK6,(1*100000*12)+(AK6)-AE6) -> 0 | AZ6: =SUM(AV6:AY6)-BF6+Z6+BH6+BI6+BJ6+BK6+BL6+BM6+BN6 -> 352000 | BC6: =F6 -> 0 | BD6: =IF(AZ6=0,(AZ6-BA6-BC6),(AZ6-BA6-BB6-BC6)) -> 352000 | BF6: =Z6*1/100*BG6 -> 0 | BG6: 9 | BH6: =BQ17 -> 52000 | BI6: =BQ30 -> 0 | BJ6: =BQ36 -> 300000 | BN6: =+BQ24 -> 0 | BO6: ACHAT FOURNITURE | BP6: FONDS DE ROULEMENT
A7: AS201601 | B7: =VLOOKUP(A7,[5]LISTADHERENT!A$5:H$50,3,0) -> BAKOP ACHILLE | C7: =IF(I7<>"ECHEC",D7+E7+F7-U7,0) -> 0 | D7: =VLOOKUP(A7,[6]HISTOBQUEMARS25!$A$6:$H$48,5,0) -> 0 | E7: =VLOOKUP(A7,[6]HISTOBQUEMARS25!$A$6:$H$43,4,0) -> 50000 | F7: =VLOOKUP(A7,[6]HISTOBQUEMARS25!$A$6:$H$43,6,0) -> 0 | H7: =IF(I7="ESPECES",3000,0)-3000 -> 0 | I7: =IF($D7<>0,"BANQUE",IF($E7<>0,"ESPECES","ECHEC")) -> ESPECES | J7: 1 | K7: =IF($D7<>0,J7*50000,IF($E7<>0,J7*50000,0)) -> 50000 | M7: =IF($D7<>0,L7*75000,IF($E7<>0,L7*75000,0)) -> 0 | O7: =IF($D7<>0,N7*100000,IF($E7<>0,N7*100000,0)) -> 0 | P7: =IFERROR(VLOOKUP(A7,[7]TONTMARS25!$A$6:$R$41,12,0),0) -> 0 | Q7: =IFERROR(VLOOKUP(A7,[8]TONTMARS25!$A$6:$R$41,10,0),0) -> 0 | R7: =IFERROR(VLOOKUP(A7,[9]TONTMARS25!$A$6:$R$42,10,0),0) -> 0 | U7: =G7+H7+S7+R7+P7+O7+M7+K7+Q7+V7+W7 -> 50000 | Y7: =K7+M7+O7 -> 50000 | AQ7: =IF(I7="ECHEC",((K7+M7+O7)*20/100),0) -> 0 | AR7: =IF(I7="ECHEC",((K7+M7+O7)*20/100),0) -> 0 | AS7: =IF(I7="ECHEC",0,(K7+G7-25000)) -> 25000 | AW7: =IF(AC7=0,AI7,(1*25000*12)+AI7-AC7) -> 0 | AX7: =IF(AD7=0,AJ7,(1*75000*12)+(AJ7)-AD7) -> 0 | AY7: =IF(AE7=0,AK7,(1*100000*12)+(AK7)-AE7) -> 0 | AZ7: =SUM(AV7:AY7)-BF7+Z7+BH7+BI7+BJ7+BK7+BL7+BM7+BN7 -> 0 | BC7: =F7 -> 0 | BD7: =IF(AZ7=0,(AZ7-BA7-BC7),(AZ7-BA7-BB7-BC7)) -> 0 | BF7: =Z7*1/100*BG7 -> 0 | BG7: 9 | BO7: COMMUNICATION | BP7: FONDS DE ROULEMENT
A8: AS201602 | B8: =VLOOKUP(A8,[5]LISTADHERENT!A$5:H$50,3,0) -> BOUTCHOUANG WILLIAM | C8: =IF(I8<>"ECHEC",D8+E8+F8-U8,0) -> -500000 | D8: =VLOOKUP(A8,[6]HISTOBQUEMARS25!$A$6:$H$48,5,0) -> 228000 | E8: =VLOOKUP(A8,[6]HISTOBQUEMARS25!$A$6:$H$43,4,0) -> 0 | F8: =VLOOKUP(A8,[6]HISTOBQUEMARS25!$A$6:$H$43,6,0) -> 0 | H8: =IF(I8="ESPECES",3000,0) -> 0 | I8: =IF($D8<>0,"BANQUE",IF($E8<>0,"ESPECES","ECHEC")) -> BANQUE | J8: 1 | K8: =IF($D8<>0,J8*50000,IF($E8<>0,J8*50000,0)) -> 50000 | L8: 1 | M8: =IF($D8<>0,L8*75000,IF($E8<>0,L8*75000,0)) -> 75000 | O8: =IF($D8<>0,N8*100000,IF($E8<>0,N8*100000,0)) -> 0 | P8: =IFERROR(VLOOKUP(A8,[7]TONTMARS25!$A$6:$R$41,12,0),0) -> 0 | Q8: =IFERROR(VLOOKUP(A8,[8]TONTMARS25!$A$6:$R$41,10,0),0) -> 103000 | R8: =IFERROR(VLOOKUP(A8,[9]TONTMARS25!$A$6:$R$42,10,0),0) -> 0 | S8: 500000 | T8: AUTRES | U8: =G8+H8+S8+R8+P8+O8+M8+K8+Q8+V8+W8 -> 728000 | Y8: =K8+M8+O8 -> 125000 | Z8: 500000 | AP8: BANQUE | AQ8: =IF(I8="ECHEC",((K8+M8+O8)*20/100),0) -> 0 | AR8: =IF(I8="ECHEC",((K8+M8+O8)*20/100),0) -> 0 | AS8: =IF(I8="ECHEC",0,(K8+G8-25000)) -> 25000 | AW8: =IF(AC8=0,AI8,(1*25000*12)+AI8-AC8) -> 0 | AX8: =IF(AD8=0,AJ8,(1*75000*12)+(AJ8)-AD8) -> 0 | AY8: =IF(AE8=0,AK8,(1*100000*12)+(AK8)-AE8) -> 0 | AZ8: =SUM(AV8:AY8)-BF8+Z8+BH8+BI8+BJ8+BK8+BL8+BM8+BN8 -> 485000 | BC8: =F8 -> 0 | BD8: =IF(AZ8=0,(AZ8-BA8-BC8),(AZ8-BA8-BB8-BC8))-485000 -> 0 | BF8: =Z8*1/100*BG8 -> 15000 | BG8: 3 | BO8: COMMISSION | BP8: FONDS DE ROULEMENT
A9: AS201604 | B9: =VLOOKUP(A9,[5]LISTADHERENT!A$5:H$50,3,0) -> DJOMO JEAN PAUL | C9: =IF(I9<>"ECHEC",D9+E9+F9-U9,0) -> 0 | D9: =VLOOKUP(A9,[6]HISTOBQUEMARS25!$A$6:$H$48,5,0) -> 457500 | E9: =VLOOKUP(A9,[6]HISTOBQUEMARS25!$A$6:$H$43,4,0) -> 0 | F9: =VLOOKUP(A9,[6]HISTOBQUEMARS25!$A$6:$H$43,6,0) -> 0 | H9: =IF(I9="ESPECES",3000,0) -> 0 | I9: =IF($D9<>0,"BANQUE",IF($E9<>0,"ESPECES","ECHEC")) -> BANQUE | J9: 1 | K9: =IF($D9<>0,J9*50000,IF($E9<>0,J9*50000,0)) -> 50000 | M9: =IF($D9<>0,L9*75000,IF($E9<>0,L9*75000,0)) -> 0 | N9: 2 | O9: =IF($D9<>0,N9*100000,IF($E9<>0,N9*100000,0)) -> 200000 | P9: =IFERROR(VLOOKUP(A9,[7]TONTMARS25!$A$6:$R$41,12,0),0) -> 0 | Q9: =IFERROR(VLOOKUP(A9,[8]TONTMARS25!$A$6:$R$41,10,0),0) -> 0 | R9: =IFERROR(VLOOKUP(A9,[9]TONTMARS25!$A$6:$R$42,10,0),0) -> 207500 | U9: =G9+H9+S9+R9+P9+O9+M9+K9+Q9+V9+W9 -> 457500 | Y9: =K9+M9+O9 -> 250000 | AK9: 200000 | AN9: =2000+1500 -> 3500 | AP9: BANQUE | AQ9: =IF(I9="ECHEC",((K9+M9+O9)*20/100),0) -> 0 | AR9: =IF(I9="ECHEC",((K9+M9+O9)*20/100),0) -> 0 | AS9: =IF(I9="ECHEC",0,(K9+G9-25000)) -> 25000 | AW9: =IF(AC9=0,AI9,(1*25000*12)+AI9-AC9) -> 0 | AX9: =IF(AD9=0,AJ9,(1*75000*12)+(AJ9)-AD9) -> 0 | AY9: =IF(AE9=0,AK9,(1*100000*12)+(AK9)-AE9) -> 200000 | AZ9: =SUM(AV9:AY9)-BF9+Z9+BH9+BI9+BJ9+BK9+BL9+BM9+BN9 -> 200000 | BA9: 200000 | BC9: =F9 -> 0 | BD9: =IF(AZ9=0,(AZ9-BA9-BC9),(AZ9-BA9-BB9-BC9)) -> 0 | BF9: =Z9*1/100*BG9 -> 0 | BG9: 9 | BO9: OUVERTURE COMPTE | BP9: FONDS DE ROULEMENT
