Workbook
Name BANQUE: #REF!
Name BANQUE: #REF!
Name BANQUE: #REF!
Name BANQUE: #REF!
Name BANQUE: #REF!
Name MODEET30000: [1]MODEVERSEMENT!$A$1:$A$3
Name MODEET30000: [2]MODEVERSEMENT!$A$1:$A$3
Name MODEPAID: [3]Feuil2!$A$1:$A$3
Name MODEPAID: [3]Feuil2!$A$1:$A$3
Name MODEPAID: [3]Feuil2!$A$1:$A$3
Name MODEPAID30000: MVTRESUME24AUTREMVT!#REF!
Name MODEPAIDOK: [4]MODEVERSEMENT!$A$1:$A$4
Name MODEPAIDS: [1]MODEVERSEMENT!$A$1:$A$3
Name MODEPAIDS: [2]MODEVERSEMENT!$A$1:$A$3
Name MODET25000: [5]MODEVERSEMENT!$A$1:$A$3
Name MODET25000: [5]MODEVERSEMENT!$A$1:$A$3
Name MODET25000: [5]MODEVERSEMENT!$A$1:$A$3
Name MODET25000: [6]MODEVERSEMENT!$A$1:$A$3
Name MODET3000: [1]MODEVERSEMENT!$A$1:$A$3
Name MODET3000: [2]MODEVERSEMENT!$A$1:$A$3
Name MODET30000: MVTRESUME24AUTREMVT!#REF!
Name MODEVERSEMENT: #REF!
Name MODEVERSEMENT: #REF!
Name MODEVERSEMENT: #REF!
Name MODEVERSEMENT: #REF!
Name MODEVERSEMENT: #REF!
Name MODEVERSEMENTS: [7]MODEVERSEMENT!$A$1:$A$3
Name MODEVERSEMENTS: [7]MODEVERSEMENT!$A$1:$A$3
Name MODEVERSEMENTS: [7]MODEVERSEMENT!$A$1:$A$3
Name MODEVERSEMENTS: [8]MODEVERSEMENT!$A$1:$A$3
Name MODPAID: MVTRESUME24AUTREMVT!#REF!
Name MODPAID: TONTRESUME24T100!#REF!
Name MODPAID: TONTRESUME24T25!#REF!
Name MODPAID: TONTRESUME24T75!#REF!
Name VALMODEPAID: [9]MODEPAID!$A$1:$A$3
Name VALMODEPAID: [10]MODEPAID!$A$1:$A$3
Name VALMODEPAID: [10]MODEPAID!$A$1:$A$3
Name VALMODEPAID: [10]MODEPAID!$A$1:$A$3
Name VALMODEPAID: [11]MODEPAID!$A$1:$A$3

Sheet MVTRESUME24AUTREMVT
A1: ASSOCIATION | B1: ASELBY
A2: ANNEE | B2: 2024
A3: BILAN MI PARCOURS AUTRES MOUVEMENTS
A5: MATRICULE | B5: NOM ET PRENOM | C5: FONDS DEFINITIF | D5: EPARGNE | E5: FONDS DE ROULEMENT | F5: FRAIS EXCEPTIONNEL | G5: COLLATION | H5: PENALITE VST ESPECES | I5: INSCRISPTION | J5: MUTUELLE | K5: DETTE DEFINITIVE | L5: INTERET PRÊT EXERCISE | M5: DATE REMBOURSEMENT | N5: FONDS DE ROULEMENT | O5: FRAIS EXCEPTIONNEL | P5: FONDS MUTUELLE | Q5: COLLATION RECEPTION | R5: AUTRES DEPENSES
A6: AS201648 | B6: =VLOOKUP(A6,[12]LISTADHERENT!A$5:H$60,3,0) -> ASELBY | C6: =[16]MVTRESUME24!C7+[16]MVTRESUME24!D7 -> 886523.26 | D6: =+[16]MVTRESUME24!L7 -> 0 | E6: =+[16]MVTRESUME24!M7 -> 0 | F6: =+[16]MVTRESUME24!N7 -> 0 | G6: =+[16]MVTRESUME24!O7 -> 0 | H6: =+[16]MVTRESUME24!P7 -> 0 | I6: =+[16]MVTRESUME24!Q7 -> 0 | J6: =+[16]MVTRESUME24!R7 -> 0 | K6: =+[16]MVTRESUME24!W7 -> 0 | L6: =+[16]MVTRESUME24!AM7 -> 0 | M6: =IF(L6=0,"",VLOOKUP(A6,[16]MVTRESUME24!A7:AQ41,38,0)) | N6: =+[16]MVTRESUME24!AF7 -> 154000 | O6: =+[16]MVTRESUME24!AG7 -> 300000 | P6: =+[16]MVTRESUME24!AH7 -> 100000 | Q6: =+[16]MVTRESUME24!AI7 -> 200000 | R6: =[16]MVTRESUME24!AN7 -> 0
A7: AS201601 | B7: =VLOOKUP(A7,[12]LISTADHERENT!A$5:H$60,3,0) -> BAKOP ACHILLE | C7: =[16]MVTRESUME24!C8+[16]MVTRESUME24!D8 -> 678482.5 | D7: =+[16]MVTRESUME24!L8 -> 129000 | E7: =+[16]MVTRESUME24!M8 -> 6000 | F7: =+[16]MVTRESUME24!N8 -> 6000 | G7: =+[16]MVTRESUME24!O8 -> 24000 | H7: =+[16]MVTRESUME24!P8 -> 3000 | I7: =+[16]MVTRESUME24!Q8 -> 0 | J7: =+[16]MVTRESUME24!R8 -> 0 | K7: =+[16]MVTRESUME24!W8 -> 600000 | L7: =+[16]MVTRESUME24!AM8 -> 24000 | M7: =IF(L7=0,"",VLOOKUP(A7,[16]MVTRESUME24!A8:AQ42,38,0)) -> 45474 | N7: 0 | O7: 0 | P7: 0 | Q7: 0
A8: AS201602 | B8: =VLOOKUP(A8,[12]LISTADHERENT!A$5:H$60,3,0) -> BOUTCHOUANG WILLIAM | C8: =[16]MVTRESUME24!C9+[16]MVTRESUME24!D9 -> 700033.13 | D8: =+[16]MVTRESUME24!L9 -> 111000 | E8: =+[16]MVTRESUME24!M9 -> 6000 | F8: =+[16]MVTRESUME24!N9 -> 6000 | G8: =+[16]MVTRESUME24!O9 -> 24000 | H8: =+[16]MVTRESUME24!P9 -> 3000 | I8: =+[16]MVTRESUME24!Q9 -> 0 | J8: =+[16]MVTRESUME24!R9 -> 0 | K8: =+[16]MVTRESUME24!W9 -> 500000 | L8: =+[16]MVTRESUME24!AM9 -> 40000 | M8: =IF(L8=0,"",VLOOKUP(A8,[16]MVTRESUME24!A9:AQ43,38,0)) -> 45352 | N8: 0 | O8: 0 | P8: 0 | Q8: 0
A9: AS201604 | B9: =VLOOKUP(A9,[12]LISTADHERENT!A$5:H$60,3,0) -> DJOMO JEAN PAUL | C9: =[16]MVTRESUME24!C10+[16]MVTRESUME24!D10 -> 753357.83 | D9: =+[16]MVTRESUME24!L10 -> 111500 | E9: =+[16]MVTRESUME24!M10 -> 6000 | F9: =+[16]MVTRESUME24!N10 -> 6000 | G9: =+[16]MVTRESUME24!O10 -> 24000 | H9: =+[16]MVTRESUME24!P10 -> 0 | I9: =+[16]MVTRESUME24!Q10 -> 0 | J9: =+[16]MVTRESUME24!R10 -> 0 | K9: =+[16]MVTRESUME24!W10 -> 1000000 | L9: =+[16]MVTRESUME24!AM10 -> 120000 | M9: =IF(L9=0,"",VLOOKUP(A9,[16]MVTRESUME24!A10:AQ44,38,0)) -> 45627 | N9: 0 | O9: 0 | P9: 0 | Q9: 0
A10: AS201654 | B10: =VLOOKUP(A10,[12]LISTADHERENT!A$5:H$60,3,0) -> DJOMOU TCHAPDA | C10: =[16]MVTRESUME24!C11+[16]MVTRESUME24!D11 -> 700294.68 | D10: =+[16]MVTRESUME24!L11 -> 106000 | E10: =+[16]MVTRESUME24!M11 -> 6000 | F10: =+[16]MVTRESUME24!N11 -> 6000 | G10: =+[16]MVTRESUME24!O11 -> 24000 | H10: =+[16]MVTRESUME24!P11 -> 6000 | I10: =+[16]MVTRESUME24!Q11 -> 0 | J10: =+[16]MVTRESUME24!R11 -> 0 | K10: =+[16]MVTRESUME24!W11 -> 1000000 | L10: =+[16]MVTRESUME24!AM11 -> 120000 | M10: =IF(L10=0,"",VLOOKUP(A10,[16]MVTRESUME24!A11:AQ45,38,0)) -> 45627 | N10: 0 | O10: 0 | P10: 0 | Q10: 0
A11: AS201605 | B11: =VLOOKUP(A11,[12]LISTADHERENT!A$5:H$60,3,0) -> DJOUKWE NANGUEN GUY BLAISE | C11: =[16]MVTRESUME24!C12+[16]MVTRESUME24!D12 -> 702196.77 | D11: =+[16]MVTRESUME24!L12 -> 134000 | E11: =+[16]MVTRESUME24!M12 -> 6000 | F11: =+[16]MVTRESUME24!N12 -> 6000 | G11: =+[16]MVTRESUME24!O12 -> 24000 | H11: =+[16]MVTRESUME24!P12 -> 0 | I11: =+[16]MVTRESUME24!Q12 -> 0 | J11: =+[16]MVTRESUME24!R12 -> 0 | K11: =+[16]MVTRESUME24!W12 -> 1000000 | L11: =+[16]MVTRESUME24!AM12 -> 60000 | M11: =IF(L11=0,"",VLOOKUP(A11,[16]MVTRESUME24!A12:AQ46,38,0)) -> 45352 | N11: 0 | O11: 0 | P11: 0 | Q11: 0
A12: AS201608 | B12: =VLOOKUP(A12,[12]LISTADHERENT!A$5:H$60,3,0) -> DJUOMBESSY ANTOINE | C12: =[16]MVTRESUME24!C13+[16]MVTRESUME24!D13 -> 714513.28 | D12: =+[16]MVTRESUME24!L13 -> 148000 | E12: =+[16]MVTRESUME24!M13 -> 6000 | F12: =+[16]MVTRESUME24!N13 -> 6000 | G12: =+[16]MVTRESUME24!O13 -> 24000 | H12: =+[16]MVTRESUME24!P13 -> 0 | I12: =+[16]MVTRESUME24!Q13 -> 0 | J12: =+[16]MVTRESUME24!R13 -> 0 | K12: =+[16]MVTRESUME24!W13 -> 140000 | L12: =+[16]MVTRESUME24!AM13 -> 60000 | M12: =IF(L12=0,"",VLOOKUP(A12,[16]MVTRESUME24!A13:AQ47,38,0)) -> 45474 | N12: 0 | O12: 0 | P12: 0 | Q12: 0
A13: AS201651 | B13: =VLOOKUP(A13,[12]LISTADHERENT!A$5:H$60,3,0) -> DOMOU FABIEN | C13: =[16]MVTRESUME24!C14+[16]MVTRESUME24!D14 -> 700041.24 | D13: =+[16]MVTRESUME24!L14 -> 114000 | E13: =+[16]MVTRESUME24!M14 -> 6000 | F13: =+[16]MVTRESUME24!N14 -> 6000 | G13: =+[16]MVTRESUME24!O14 -> 24000 | H13: =+[16]MVTRESUME24!P14 -> 0 | I13: =+[16]MVTRESUME24!Q14 -> 0 | J13: =+[16]MVTRESUME24!R14 -> 0 | K13: =+[16]MVTRESUME24!W14 -> 1000000 | L13: =+[16]MVTRESUME24!AM14 -> 120000 | M13: =IF(L13=0,"",VLOOKUP(A13,[16]MVTRESUME24!A14:AQ48,38,0)) -> 45627 | N13: 0 | O13: 0 | P13: 0 | Q13: 0
A14: AS201609 | B14: =VLOOKUP(A14,[12]LISTADHERENT!A$5:H$60,3,0) -> DONHOU DAVID | C14: =[16]MVTRESUME24!C15+[16]MVTRESUME24!D15 -> 1218031.3 | D14: =+[16]MVTRESUME24!L15 -> 114000 | E14: =+[16]MVTRESUME24!M15 -> 6000 | F14: =+[16]MVTRESUME24!N15 -> 6000 | G14: =+[16]MVTRESUME24!O15 -> 24000 | H14: =+[16]MVTRESUME24!P15 -> 0 | I14: =+[16]MVTRESUME24!Q15 -> 0 | J14: =+[16]MVTRESUME24!R15 -> 0 | K14: =+[16]MVTRESUME24!W15 -> 0 | L14: =+[16]MVTRESUME24!AM15 -> 0 | M14: =IF(L14=0,"",VLOOKUP(A14,[16]MVTRESUME24!A15:AQ49,38,0)) | N14: 0 | O14: 0 | P14: 0 | Q14: 0
A15: AS201611 | B15: =VLOOKUP(A15,[12]LISTADHERENT!A$5:H$60,3,0) -> HENGUE PAUL OMER | C15: =[16]MVTRESUME24!C16+[16]MVTRESUME24!D16 -> 757899.6 | D15: =+[16]MVTRESUME24!L16 -> 114000 | E15: =+[16]MVTRESUME24!M16 -> 6000 | F15: =+[16]MVTRESUME24!N16 -> 6000 | G15: =+[16]MVTRESUME24!O16 -> 24000 | H15: =+[16]MVTRESUME24!P16 -> 0 | I15: =+[16]MVTRESUME24!Q16 -> 0 | J15: =+[16]MVTRESUME24!R16 -> 0 | K15: =+[16]MVTRESUME24!W16 -> 1000000 | L15: =+[16]MVTRESUME24!AM16 -> 70000 | M15: =IF(L15=0,"",VLOOKUP(A15,[16]MVTRESUME24!A16:AQ50,38,0)) -> 45627 | N15: 0 | O15: 0 | P15: 0 | Q15: 0
A16: AS201613 | B16: =VLOOKUP(A16,[12]LISTADHERENT!A$5:H$60,3,0) -> HOTCHO BENJAMIN | C16: =[16]MVTRESUME24!C17+[16]MVTRESUME24!D17 -> 729661.21 | D16: =+[16]MVTRESUME24!L17 -> 324000 | E16: =+[16]MVTRESUME24!M17 -> 6000 | F16: =+[16]MVTRESUME24!N17 -> 6000 | G16: =+[16]MVTRESUME24!O17 -> 24000 | H16: =+[16]MVTRESUME24!P17 -> 0 | I16: =+[16]MVTRESUME24!Q17 -> 0 | J16: =+[16]MVTRESUME24!R17 -> 0 | K16: =+[16]MVTRESUME24!W17 -> 238500 | L16: =+[16]MVTRESUME24!AM17 -> 0 | M16: =IF(L16=0,"",VLOOKUP(A16,[16]MVTRESUME24!A17:AQ51,38,0)) | N16: 0 | O16: 0 | P16: 0 | Q16: 0
A17: AS201617 | B17: =VLOOKUP(A17,[12]LISTADHERENT!A$5:H$60,3,0) -> KOUAMOU MOISE | C17: =[16]MVTRESUME24!C18+[16]MVTRESUME24!D18 -> 709267.51 | D17: =+[16]MVTRESUME24!L18 -> 114500 | E17: =+[16]MVTRESUME24!M18 -> 6000 | F17: =+[16]MVTRESUME24!N18 -> 6000 | G17: =+[16]MVTRESUME24!O18 -> 24000 | H17: =+[16]MVTRESUME24!P18 -> 0 | I17: =+[16]MVTRESUME24!Q18 -> 0 | J17: =+[16]MVTRESUME24!R18 -> 0 | K17: =+[16]MVTRESUME24!W18 -> 500000 | L17: =+[16]MVTRESUME24!AM18 -> 110000 | M17: =IF(L17=0,"",VLOOKUP(A17,[16]MVTRESUME24!A18:AQ52,38,0)) -> 45627 | N17: 0 | O17: 0 | P17: 0 | Q17: 100000
A18: AS201619 | B18: =VLOOKUP(A18,[12]LISTADHERENT!A$5:H$60,3,0) -> KOUATCHO MESSACK | C18: =[16]MVTRESUME24!C19+[16]MVTRESUME24!D19 -> 724428.63 | D18: =+[16]MVTRESUME24!L19 -> 164000 | E18: =+[16]MVTRESUME24!M19 -> 6000 | F18: =+[16]MVTRESUME24!N19 -> 6000 | G18: =+[16]MVTRESUME24!O19 -> 24000 | H18: =+[16]MVTRESUME24!P19 -> 3000 | I18: =+[16]MVTRESUME24!Q19 -> 0 | J18: =+[16]MVTRESUME24!R19 -> 0 | K18: =+[16]MVTRESUME24!W19 -> 350000 | L18: =+[16]MVTRESUME24!AM19 -> 64000 | M18: =IF(L18=0,"",VLOOKUP(A18,[16]MVTRESUME24!A19:AQ53,38,0)) -> 45474 | N18: 0 | O18: 0 | P18: 0 | Q18: 0
... A39: AS201647 | B39: =VLOOKUP(A39,[12]LISTADHERENT!A$5:H$60,3,0) -> YOUMBI EMMANUEL | C39: =[16]MVTRESUME24!C40+[16]MVTRESUME24!D40 -> 1857835 | D39: =+[16]MVTRESUME24!L40 -> 114000 | E39: =+[16]MVTRESUME24!M40 -> 6000 | F39: =+[16]MVTRESUME24!N40 -> 6000 | G39: =+[16]MVTRESUME24!O40 -> 24000 | H39: =+[16]MVTRESUME24!P40 -> 0 | I39: =+[16]MVTRESUME24!Q40 -> 0 | J39: =+[16]MVTRESUME24!R40 -> 0 | K39: =+[16]MVTRESUME24!W40 -> 0 | L39: =+[16]MVTRESUME24!AM40 -> 0 | M39: =IF(L39=0,"",VLOOKUP(A39,[16]MVTRESUME24!A40:AQ74,38,0)) | N39: 0 | O39: 0 | P39: 0 | Q39: 100000
A41: TOTAL | C41: =SUM(C6:C40) -> 24229657 | D41: =SUM(D6:D40) -> 5070000 | E41: =SUM(E6:E40) -> 192000 | F41: =SUM(F6:F40) -> 192000 | G41: =SUM(G6:G40) -> 768000 | H41: =SUM(H6:H40) -> 42000 | I41: =SUM(I6:I40) -> 75000 | J41: =SUM(J6:J40) -> 120000 | ... L41: =SUM(L6:L40) -> 1656500 | N41: =SUM(N6:N40) -> 154000 | O41: =SUM(O6:O40) -> 300000 | P41: =SUM(P6:P40) -> 100000 | Q41: =SUM(Q6:Q40) -> 600000 | R41: =SUM(R6:R40) -> 0

Sheet TONTRESUME24T25
A1: ASSOCIATION | B1: ASELBY
A2: ANNEE | B2: 2024
A3: BILAN MI PARCOURS TONTINE 25 000
A4: MATRICULE | B4: NOM ET PRENOM | C4: MONTANT TONTINE | D4: PENALITE VERSEMENT ESPECES | E4: INTERET PETIT LOT | F4: MONTANT LOT PRINCIPAL PERCU | G4: INTERET LOT PRINCIPAL | H4: MOIS OBTENTION | I4: REPARTITION INTERET | J4: INTERET PERCU PAR ADHERENT
A5: AS201601 | B5: =VLOOKUP(A5,[12]LISTADHERENT!A$5:H$60,3,0) -> BAKOP ACHILLE | C5: =[13]TONTRESUME24!D6 -> 150000 | D5: =[13]TONTRESUME24!F6 -> 3000 | E5: =[13]TONTRESUME24!I6 -> 1000 | F5: =[13]TONTRESUME24!Q6 -> 290000 | G5: =[13]TONTRESUME24!R6 -> 10000 | H5: =IF(G5=0,"",VLOOKUP(A5,[13]TONTRESUME24!A6:U37,19,0)) -> 45352 | I5: =[13]TONTRESUME24!T6 -> 5515.625 | J5: =[13]TONTRESUME24!U6 -> 0
A6: AS201602 | B6: =VLOOKUP(A6,[12]LISTADHERENT!A$5:H$60,3,0) -> BOUTCHOUANG WILLIAM | C6: =[13]TONTRESUME24!D7 -> 150000 | D6: =[13]TONTRESUME24!F7 -> 3000 | E6: =[13]TONTRESUME24!I7 -> 0 | F6: =[13]TONTRESUME24!Q7 -> 0 | G6: =[13]TONTRESUME24!R7 -> 0 | H6: =IF(G6=0,"",VLOOKUP(A6,[13]TONTRESUME24!A7:U38,19,0)) | I6: =[13]TONTRESUME24!T7 -> 5515.625 | J6: =[13]TONTRESUME24!U7 -> 0
A7: AS201604 | B7: =VLOOKUP(A7,[12]LISTADHERENT!A$5:H$60,3,0) -> DJOMO JEAN PAUL | C7: =[13]TONTRESUME24!D8 -> 150000 | D7: =[13]TONTRESUME24!F8 -> 0 | E7: =[13]TONTRESUME24!I8 -> 0 | F7: =[13]TONTRESUME24!Q8 -> 282000 | G7: =[13]TONTRESUME24!R8 -> 18000 | H7: =IF(G7=0,"",VLOOKUP(A7,[13]TONTRESUME24!A8:U39,19,0)) -> 45352 | I7: =[13]TONTRESUME24!T8 -> 5515.625 | J7: =[13]TONTRESUME24!U8 -> 0
A8: AS201654 | B8: =VLOOKUP(A8,[12]LISTADHERENT!A$5:H$60,3,0) -> DJOMOU TCHAPDA | C8: =[13]TONTRESUME24!D9 -> 150000 | D8: =[13]TONTRESUME24!F9 -> 6000 | E8: =[13]TONTRESUME24!I9 -> 2500 | F8: =[13]TONTRESUME24!Q9 -> 0 | G8: =[13]TONTRESUME24!R9 -> 0 | H8: =IF(G8=0,"",VLOOKUP(A8,[13]TONTRESUME24!A9:U40,19,0)) | I8: =[13]TONTRESUME24!T9 -> 5515.625 | J8: =[13]TONTRESUME24!U9 -> 0
A9: AS201605 | B9: =VLOOKUP(A9,[12]LISTADHERENT!A$5:H$60,3,0) -> DJOUKWE NANGUEN GUY BLAISE | C9: =[13]TONTRESUME24!D10 -> 150000 | D9: =[13]TONTRESUME24!F10 -> 0 | E9: =[13]TONTRESUME24!I10 -> 3500 | F9: =[13]TONTRESUME24!Q10 -> 284000 | G9: =[13]TONTRESUME24!R10 -> 16000 | H9: =IF(G9=0,"",VLOOKUP(A9,[13]TONTRESUME24!A10:U41,19,0)) -> 45323 | I9: =[13]TONTRESUME24!T10 -> 5515.625 | J9: =[13]TONTRESUME24!U10 -> 0
A10: AS201608 | B10: =VLOOKUP(A10,[12]LISTADHERENT!A$5:H$60,3,0) -> DJUOMBESSY ANTOINE | C10: =[13]TONTRESUME24!D11 -> 150000 | D10: =[13]TONTRESUME24!F11 -> 0 | E10: =[13]TONTRESUME24!I11 -> 0 | F10: =[13]TONTRESUME24!Q11 -> 0 | G10: =[13]TONTRESUME24!R11 -> 0 | H10: =IF(G10=0,"",VLOOKUP(A10,[13]TONTRESUME24!A11:U42,19,0)) | I10: =[13]TONTRESUME24!T11 -> 5515.625 | J10: =[13]TONTRESUME24!U11 -> 0
A11: AS201651 | B11: =VLOOKUP(A11,[12]LISTADHERENT!A$5:H$60,3,0) -> DOMOU FABIEN | C11: =[13]TONTRESUME24!D12 -> 150000 | D11: =[13]TONTRESUME24!F12 -> 0 | E11: =[13]TONTRESUME24!I12 -> 0 | F11: =[13]TONTRESUME24!Q12 -> 0 | G11: =[13]TONTRESUME24!R12 -> 0 | H11: =IF(G11=0,"",VLOOKUP(A11,[13]TONTRESUME24!A12:U43,19,0)) | I11: =[13]TONTRESUME24!T12 -> 5515.625 | J11: =[13]TONTRESUME24!U12 -> 0
A12: AS201609 | B12: =VLOOKUP(A12,[12]LISTADHERENT!A$5:H$60,3,0) -> DONHOU DAVID | C12: =[13]TONTRESUME24!D13 -> 150000 | D12: =[13]TONTRESUME24!F13 -> 0 | E12: =[13]TONTRESUME24!I13 -> 0 | F12: =[13]TONTRESUME24!Q13 -> 0 | G12: =[13]TONTRESUME24!R13 -> 0 | H12: =IF(G12=0,"",VLOOKUP(A12,[13]TONTRESUME24!A13:U44,19,0)) | I12: =[13]TONTRESUME24!T13 -> 5515.625 | J12: =[13]TONTRESUME24!U13 -> 0
A13: AS201611 | B13: =VLOOKUP(A13,[12]LISTADHERENT!A$5:H$60,3,0) -> HENGUE PAUL OMER | C13: =[13]TONTRESUME24!D14 -> 150000 | D13: =[13]TONTRESUME24!F14 -> 0 | E13: =[13]TONTRESUME24!I14 -> 0 | F13: =[13]TONTRESUME24!Q14 -> 290000 | G13: =[13]TONTRESUME24!R14 -> 10000 | H13: =IF(G13=0,"",VLOOKUP(A13,[13]TONTRESUME24!A14:U45,19,0)) -> 45383 | I13: =[13]TONTRESUME24!T14 -> 5515.625 | J13: =[13]TONTRESUME24!U14 -> 0
A14: AS201613 | B14: =VLOOKUP(A14,[12]LISTADHERENT!A$5:H$60,3,0) -> HOTCHO BENJAMIN | C14: =[13]TONTRESUME24!D15 -> 150000 | D14: =[13]TONTRESUME24!F15 -> 0 | E14: =[13]TONTRESUME24!I15 -> 0 | F14: =[13]TONTRESUME24!Q15 -> 288000 | G14: =[13]TONTRESUME24!R15 -> 12000 | H14: =IF(G14=0,"",VLOOKUP(A14,[13]TONTRESUME24!A15:U46,19,0)) -> 45292 | I14: =[13]TONTRESUME24!T15 -> 5515.625 | J14: =[13]TONTRESUME24!U15 -> 0
A15: AS201617 | B15: =VLOOKUP(A15,[12]LISTADHERENT!A$5:H$60,3,0) -> KOUAMOU MOISE | C15: =[13]TONTRESUME24!D16 -> 150000 | D15: =[13]TONTRESUME24!F16 -> 0 | E15: =[13]TONTRESUME24!I16 -> 500 | F15: =[13]TONTRESUME24!Q16 -> 283000 | G15: =[13]TONTRESUME24!R16 -> 17000 | H15: =IF(G15=0,"",VLOOKUP(A15,[13]TONTRESUME24!A16:U47,19,0)) -> 45323 | I15: =[13]TONTRESUME24!T16 -> 5515.625 | J15: =[13]TONTRESUME24!U16 -> 0
A16: AS201619 | B16: =VLOOKUP(A16,[12]LISTADHERENT!A$5:H$60,3,0) -> KOUATCHO MESSACK | C16: =[13]TONTRESUME24!D17 -> 150000 | D16: =[13]TONTRESUME24!F17 -> 3000 | E16: =[13]TONTRESUME24!I17 -> 0 | F16: =[13]TONTRESUME24!Q17 -> 287000 | G16: =[13]TONTRESUME24!R17 -> 13000 | H16: =IF(G16=0,"",VLOOKUP(A16,[13]TONTRESUME24!A17:U48,19,0)) -> 45292 | I16: =[13]TONTRESUME24!T17 -> 5515.625 | J16: =[13]TONTRESUME24!U17 -> 0
... A36: AS201647 | B36: =VLOOKUP(A36,[12]LISTADHERENT!A$5:H$60,3,0) -> YOUMBI EMMANUEL | C36: =[13]TONTRESUME24!D37 -> 150000 | D36: =[13]TONTRESUME24!F37 -> 0 | E36: =[13]TONTRESUME24!I37 -> 0 | F36: =[13]TONTRESUME24!Q37 -> 0 | G36: =[13]TONTRESUME24!R37 -> 0 | H36: =IF(G36=0,"",VLOOKUP(A36,[13]TONTRESUME24!A37:U68,19,0)) | I36: =[13]TONTRESUME24!T37 -> 5515.625 | J36: =[13]TONTRESUME24!U37 -> 0
A38: TOTAL | C38: =SUM(C5:C38) -> 4800000 | D38: =SUM(D5:D38) -> 42000 | E38: =SUM(E5:E38) -> 13500 | F38: =SUM(F5:F38) -> 4637000 | G38: =SUM(G5:G38) -> 163000 | I38: =SUM(I6:I37) -> 170984.38 | J38: =SUM(J6:J37) -> 0

Sheet TONTRESUME24T75
A1: ASSOCIATION | B1: ASELBY
A2: ANNEE | B2: 2024
A3: BILAN MI PARCOURS TONTINE 75 000
A4: MATRICULE | B4: NOM ET PRENOM | C4: MONTANT TONTINE | D4: INTERET PETIT LOT | E4: MONTANT LOT PRINCIPAL PERCU | F4: INTERET LOT PRINCIPAL | G4: MOIS OBTENTION | H4: MOIS OBTENTION 2 | I4: REPARTITION INTERET | J4: INTERET PERCU PAR ADHERENT
A5: AS201648 | B5: =VLOOKUP(A5,[12]LISTADHERENT!A$5:H$60,3,0) -> ASELBY | C5: =+[14]TONTRESUME24!D6 -> 450000 | D5: =+[14]TONTRESUME24!G6 -> 0 | E5: =+[14]TONTRESUME24!O6 -> 0 | F5: =+[14]TONTRESUME24!P6 -> 0 | G5: =IF(F5=0,"",VLOOKUP(TONTRESUME24T75!A5,[14]TONTRESUME24!A6:T19,17,0)) | H5: =IF(C5=450000,"",VLOOKUP(TONTRESUME24T75!A5,[14]TONTRESUME24!A6:U19,18,0)) | I5: =+[14]TONTRESUME24!S6 -> 14555.556 | J5: =+[14]TONTRESUME24!T6 -> 0
A6: AS201602 | B6: =VLOOKUP(A6,[12]LISTADHERENT!A$5:H$60,3,0) -> BOUTCHOUANG WILLIAM | C6: =+[14]TONTRESUME24!D7 -> 450000 | D6: =+[14]TONTRESUME24!G7 -> 0 | E6: =+[14]TONTRESUME24!O7 -> 0 | F6: =+[14]TONTRESUME24!P7 -> 0 | G6: =IF(F6=0,"",VLOOKUP(TONTRESUME24T75!A6,[14]TONTRESUME24!A7:T20,17,0)) | H6: =IF(C6=450000,"",VLOOKUP(TONTRESUME24T75!A6,[14]TONTRESUME24!A7:U20,18,0)) | I6: =+[14]TONTRESUME24!S7 -> 14555.556 | J6: =+[14]TONTRESUME24!T7 -> 0
A7: AS201654 | B7: =VLOOKUP(A7,[12]LISTADHERENT!A$5:H$60,3,0) -> DJOMOU TCHAPDA | C7: =+[14]TONTRESUME24!D8 -> 450000 | D7: =+[14]TONTRESUME24!G8 -> 4500 | E7: =+[14]TONTRESUME24!O8 -> 872000 | F7: =+[14]TONTRESUME24!P8 -> 28000 | G7: =IF(F7=0,"",VLOOKUP(TONTRESUME24T75!A7,[14]TONTRESUME24!A8:T21,17,0)) -> 45352 | H7: =IF(C7=450000,"",VLOOKUP(TONTRESUME24T75!A7,[14]TONTRESUME24!A8:U21,18,0)) | I7: =+[14]TONTRESUME24!S8 -> 14555.556 | J7: =+[14]TONTRESUME24!T8 -> 0
A8: AS201605 | B8: =VLOOKUP(A8,[12]LISTADHERENT!A$5:H$60,3,0) -> DJOUKWE NANGUEN GUY BLAISE | C8: =+[14]TONTRESUME24!D9 -> 450000 | D8: =+[14]TONTRESUME24!G9 -> 11000 | E8: =+[14]TONTRESUME24!O9 -> 884000 | F8: =+[14]TONTRESUME24!P9 -> 16000 | G8: =IF(F8=0,"",VLOOKUP(TONTRESUME24T75!A8,[14]TONTRESUME24!A9:T22,17,0)) -> 45323 | H8: =IF(C8=450000,"",VLOOKUP(TONTRESUME24T75!A8,[14]TONTRESUME24!A9:U22,18,0)) | I8: =+[14]TONTRESUME24!S9 -> 14555.556 | J8: =+[14]TONTRESUME24!T9 -> 0
A9: AS201608 | B9: =VLOOKUP(A9,[12]LISTADHERENT!A$5:H$60,3,0) -> DJUOMBESSY ANTOINE | C9: =+[14]TONTRESUME24!D10 -> 450000 | D9: =+[14]TONTRESUME24!G10 -> 1000 | E9: =+[14]TONTRESUME24!O10 -> 840000 | F9: =+[14]TONTRESUME24!P10 -> 60000 | G9: =IF(F9=0,"",VLOOKUP(TONTRESUME24T75!A9,[14]TONTRESUME24!A10:T23,17,0)) -> 45292 | H9: =IF(C9=450000,"",VLOOKUP(TONTRESUME24T75!A9,[14]TONTRESUME24!A10:U23,18,0)) | I9: =+[14]TONTRESUME24!S10 -> 14555.556 | J9: =+[14]TONTRESUME24!T10 -> 0
A10: AS201613 | B10: =VLOOKUP(A10,[12]LISTADHERENT!A$5:H$60,3,0) -> HOTCHO BENJAMIN | C10: =+[14]TONTRESUME24!D11 -> 450000 | D10: =+[14]TONTRESUME24!G11 -> 0 | E10: =+[14]TONTRESUME24!O11 -> 892500 | F10: =+[14]TONTRESUME24!P11 -> 7500 | G10: =IF(F10=0,"",VLOOKUP(TONTRESUME24T75!A10,[14]TONTRESUME24!A11:T24,17,0)) -> 45444 | H10: =IF(C10=450000,"",VLOOKUP(TONTRESUME24T75!A10,[14]TONTRESUME24!A11:U24,18,0)) | I10: =+[14]TONTRESUME24!S11 -> 14555.556 | J10: =+[14]TONTRESUME24!T11 -> 0
A11: AS201611 | B11: =VLOOKUP(A11,[12]LISTADHERENT!A$5:H$60,3,0) -> HENGUE PAUL OMER | C11: =+[14]TONTRESUME24!D12 -> 450000 | D11: =+[14]TONTRESUME24!G12 -> 0 | E11: =+[14]TONTRESUME24!O12 -> 892500 | F11: =+[14]TONTRESUME24!P12 -> 7500 | G11: =IF(F11=0,"",VLOOKUP(TONTRESUME24T75!A11,[14]TONTRESUME24!A12:T25,17,0)) -> 45444 | H11: =IF(C11=450000,"",VLOOKUP(TONTRESUME24T75!A11,[14]TONTRESUME24!A12:U25,18,0)) | I11: =+[14]TONTRESUME24!S12 -> 14555.556 | J11: =+[14]TONTRESUME24!T12 -> 0
A12: AS201649 | B12: =VLOOKUP(A12,[12]LISTADHERENT!A$5:H$60,3,0) -> MBOGNING TUGMA GUY | C12: =+[14]TONTRESUME24!D13 -> 450000 | D12: =+[14]TONTRESUME24!G13 -> 7500 | E12: =+[14]TONTRESUME24!O13 -> 884000 | F12: =+[14]TONTRESUME24!P13 -> 16000 | G12: =IF(F12=0,"",VLOOKUP(TONTRESUME24T75!A12,[14]TONTRESUME24!A13:T26,17,0)) -> 45323 | H12: =IF(C12=450000,"",VLOOKUP(TONTRESUME24T75!A12,[14]TONTRESUME24!A13:U26,18,0)) | I12: =+[14]TONTRESUME24!S13 -> 29111.111 | J12: =+[14]TONTRESUME24!T13 -> 0
A13: AS201621 | B13: =VLOOKUP(A13,[12]LISTADHERENT!A$5:H$60,3,0) -> NANKAM APPOLINAIRE | C13: =+[14]TONTRESUME24!D14 -> 450000 | D13: =+[14]TONTRESUME24!G14 -> 0 | E13: =+[14]TONTRESUME24!O14 -> 0 | F13: =+[14]TONTRESUME24!P14 -> 0 | G13: =IF(F13=0,"",VLOOKUP(TONTRESUME24T75!A13,[14]TONTRESUME24!A14:T27,17,0)) | H13: =IF(C13=450000,"",VLOOKUP(TONTRESUME24T75!A13,[14]TONTRESUME24!A14:U27,18,0)) | I13: =+[14]TONTRESUME24!S14 -> 14555.556 | J13: =+[14]TONTRESUME24!T14 -> 0
A14: AS201624 | B14: =VLOOKUP(A14,[12]LISTADHERENT!A$5:H$60,3,0) -> NGONDIEP CLAUDE | C14: =+[14]TONTRESUME24!D15 -> 450000 | D14: =+[14]TONTRESUME24!G15 -> 0 | E14: =+[14]TONTRESUME24!O15 -> 0 | F14: =+[14]TONTRESUME24!P15 -> 0 | G14: =IF(F14=0,"",VLOOKUP(TONTRESUME24T75!A14,[14]TONTRESUME24!A15:T28,17,0)) | H14: =IF(C14=450000,"",VLOOKUP(TONTRESUME24T75!A14,[14]TONTRESUME24!A15:U28,18,0)) | I14: =+[14]TONTRESUME24!S15 -> 14555.556 | J14: =+[14]TONTRESUME24!T15 -> 0
A15: AS201626 | B15: =VLOOKUP(A15,[12]LISTADHERENT!A$5:H$60,3,0) -> NGUIEMEGNI MATHIEU BLAISE | C15: =+[14]TONTRESUME24!D16 -> 1350000 | D15: =+[14]TONTRESUME24!G16 -> 500 | E15: =+[14]TONTRESUME24!O16 -> 1710000 | F15: =+[14]TONTRESUME24!P16 -> 90000 | G15: =IF(F15=0,"",VLOOKUP(TONTRESUME24T75!A15,[14]TONTRESUME24!A16:T29,17,0)) -> 45292 | H15: =IF(C15=450000,"",VLOOKUP(TONTRESUME24T75!A15,[14]TONTRESUME24!A16:U29,18,0)) -> 45413 | I15: =+[14]TONTRESUME24!S16 -> 43666.667 | J15: =+[14]TONTRESUME24!T16 -> 0
A16: AS201633 | B16: =VLOOKUP(A16,[12]LISTADHERENT!A$5:H$60,3,0) -> PATEGO NJOSSU GUSTAVE | C16: =+[14]TONTRESUME24!D17 -> 450000 | D16: =+[14]TONTRESUME24!G17 -> 0 | E16: =+[14]TONTRESUME24!O17 -> 0 | F16: =+[14]TONTRESUME24!P17 -> 0 | G16: =IF(F16=0,"",VLOOKUP(TONTRESUME24T75!A16,[14]TONTRESUME24!A17:T30,17,0)) | H16: =IF(C16=450000,"",VLOOKUP(TONTRESUME24T75!A16,[14]TONTRESUME24!A17:U30,18,0)) | I16: =+[14]TONTRESUME24!S17 -> 14555.556 | J16: =+[14]TONTRESUME24!T17 -> 0
... A18: AS201647 | B18: =VLOOKUP(A18,[12]LISTADHERENT!A$5:H$60,3,0) -> YOUMBI EMMANUEL | C18: =+[14]TONTRESUME24!D19 -> 450000 | D18: =+[14]TONTRESUME24!G19 -> 0 | E18: =+[14]TONTRESUME24!O19 -> 0 | F18: =+[14]TONTRESUME24!P19 -> 0 | G18: =IF(F18=0,"",VLOOKUP(TONTRESUME24T75!A18,[14]TONTRESUME24!A19:T32,17,0)) | H18: =IF(C18=450000,"",VLOOKUP(TONTRESUME24T75!A18,[14]TONTRESUME24!A19:U32,18,0)) | I18: =+[14]TONTRESUME24!S19 -> 14555.556 | J18: =+[14]TONTRESUME24!T19 -> 0
A20: TOTAL PART | C20: =SUM(C5:C19) -> 7200000 | D20: =SUM(D5:D19) -> 29500 | E20: =SUM(E5:E19) -> 7867500 | F20: =SUM(F5:F19) -> 232500 | I20: =SUM(I7:I19) -> 218333.33 | J20: =SUM(J7:J19) -> 0

Sheet TONTRESUME24T100
A1: ASSOCIATION | B1: ASELBY
A2: ANNEE | B2: 2024
A3: BILAN MI PARCOURS TONTINE 100 000
A4: MATRICULE | B4: NOM ET PRENOM | C4: MONTANT TONTINE | D4: INTERET PETIT LOT | E4: MONTANT LOT PRINCIPAL PERCU | F4: INTERET LOT PRINCIPAL | G4: MOIS OBTENTION | H4: MOIS OBTENTION 2 | I4: REPARTITION INTERET | J4: INTERET PERCU PAR ADHERENT
A5: AS201648 | B5: =VLOOKUP(A5,[12]LISTADHERENT!A$5:H$60,3,0) -> ASELBY | C5: =+[15]TONTRESUME24!D6 -> 600000 | D5: =+[15]TONTRESUME24!G6 -> 0 | E5: =+[15]TONTRESUME24!O6 -> 0 | F5: =+[15]TONTRESUME24!P6 -> 0 | G5: =IF(F5=0,"",VLOOKUP(TONTRESUME24T100!A5,[15]TONTRESUME24!A6:T19,17,0)) | H5: =IF(C5=600000,"",VLOOKUP(TONTRESUME24T100!A5,[15]TONTRESUME24!A6:U19,18,0)) | J5: =[15]TONTRESUME24!T6 -> 0
A6: AS201604 | B6: =VLOOKUP(A6,[12]LISTADHERENT!A$5:H$60,3,0) -> DJOMO JEAN PAUL | C6: =+[15]TONTRESUME24!D7 -> 1200000 | D6: =+[15]TONTRESUME24!G7 -> 2000 | E6: =+[15]TONTRESUME24!O7 -> 1085000 | F6: =+[15]TONTRESUME24!P7 -> 115000 | G6: =IF(F6=0,"",VLOOKUP(TONTRESUME24T100!A6,[15]TONTRESUME24!A7:T20,17,0)) -> 45292 | I6: =[15]TONTRESUME24!S7 -> 70222.222 | J6: =[15]TONTRESUME24!T7 -> 0
A7: AS201608 | B7: =VLOOKUP(A7,[12]LISTADHERENT!A$5:H$60,3,0) -> DJUOMBESSY ANTOINE | C7: =+[15]TONTRESUME24!D8 -> 1200000 | D7: =+[15]TONTRESUME24!G8 -> 1000 | E7: =+[15]TONTRESUME24!O8 -> 1190000 | F7: =+[15]TONTRESUME24!P8 -> 10000 | G7: =IF(F7=0,"",VLOOKUP(TONTRESUME24T100!A7,[15]TONTRESUME24!A8:T21,17,0)) -> 45413 | I7: =[15]TONTRESUME24!S8 -> 70222.222 | J7: =[15]TONTRESUME24!T8 -> 0
A8: AS201613 | B8: =VLOOKUP(A8,[12]LISTADHERENT!A$5:H$60,3,0) -> HOTCHO BENJAMIN | C8: =+[15]TONTRESUME24!D9 -> 600000 | D8: =+[15]TONTRESUME24!G9 -> 0 | E8: =+[15]TONTRESUME24!O9 -> 1185000 | F8: =+[15]TONTRESUME24!P9 -> 15000 | G8: =IF(F8=0,"",VLOOKUP(TONTRESUME24T100!A8,[15]TONTRESUME24!A9:T22,17,0)) -> 45383 | H8: =IF(C8=600000,"",VLOOKUP(TONTRESUME24T100!A8,[15]TONTRESUME24!A9:U22,18,0)) | I8: =[15]TONTRESUME24!S9 -> 35111.111 | J8: =[15]TONTRESUME24!T9 -> 0
A9: AS201617 | B9: =VLOOKUP(A9,[12]LISTADHERENT!A$5:H$60,3,0) -> KOUAMOU MOISE | C9: =+[15]TONTRESUME24!D10 -> 600000 | D9: =+[15]TONTRESUME24!G10 -> 2000 | E9: =+[15]TONTRESUME24!O10 -> 1130000 | F9: =+[15]TONTRESUME24!P10 -> 70000 | G9: =IF(F9=0,"",VLOOKUP(TONTRESUME24T100!A9,[15]TONTRESUME24!A10:T23,17,0)) -> 45352 | H9: =IF(C9=600000,"",VLOOKUP(TONTRESUME24T100!A9,[15]TONTRESUME24!A10:U23,18,0)) | I9: =[15]TONTRESUME24!S10 -> 35111.111 | J9: =[15]TONTRESUME24!T10 -> 0
A10: AS201619 | B10: =VLOOKUP(A10,[12]LISTADHERENT!A$5:H$60,3,0) -> KOUATCHO MESSACK | C10: =+[15]TONTRESUME24!D11 -> 600000 | D10: =+[15]TONTRESUME24!G11 -> 7000 | E10: =+[15]TONTRESUME24!O11 -> 1160000 | F10: =+[15]TONTRESUME24!P11 -> 40000 | G10: =IF(F10=0,"",VLOOKUP(TONTRESUME24T100!A10,[15]TONTRESUME24!A11:T24,17,0)) -> 45323 | H10: =IF(C10=600000,"",VLOOKUP(TONTRESUME24T100!A10,[15]TONTRESUME24!A11:U24,18,0)) | I10: =[15]TONTRESUME24!S11 -> 35111.111 | J10: =[15]TONTRESUME24!T11 -> 0
A11: AS201649 | B11: =VLOOKUP(A11,[12]LISTADHERENT!A$5:H$60,3,0) -> MBOGNING TUGMA GUY | C11: =+[15]TONTRESUME24!D12 -> 600000 | D11: =+[15]TONTRESUME24!G12 -> 6000 | E11: =+[15]TONTRESUME24!O12 -> 1085000 | F11: =+[15]TONTRESUME24!P12 -> 115000 | G11: =IF(F11=0,"",VLOOKUP(TONTRESUME24T100!A11,[15]TONTRESUME24!A12:T25,17,0)) -> 45292 | H11: =IF(C11=600000,"",VLOOKUP(TONTRESUME24T100!A11,[15]TONTRESUME24!A12:U25,18,0)) | I11: =[15]TONTRESUME24!S12 -> 35111.111 | J11: =[15]TONTRESUME24!T12 -> 0
A12: AS201622 | B12: =VLOOKUP(A12,[12]LISTADHERENT!A$5:H$60,3,0) -> NDJOMO ETIENNE | C12: =+[15]TONTRESUME24!D13 -> 1200000 | D12: =+[15]TONTRESUME24!G13 -> 4000 | E12: =+[15]TONTRESUME24!O13 -> 0 | F12: =+[15]TONTRESUME24!P13 -> 0 | G12: =IF(F12=0,"",VLOOKUP(TONTRESUME24T100!A12,[15]TONTRESUME24!A13:T26,17,0)) | I12: =[15]TONTRESUME24!S13 -> 70222.222 | J12: =[15]TONTRESUME24!T13 -> 0
A13: AS201624 | B13: =VLOOKUP(A13,[12]LISTADHERENT!A$5:H$60,3,0) -> NGONDIEP CLAUDE | C13: =+[15]TONTRESUME24!D14 -> 600000 | D13: =+[15]TONTRESUME24!G14 -> 5000 | E13: =+[15]TONTRESUME24!O14 -> 1185000 | F13: =+[15]TONTRESUME24!P14 -> 15000 | G13: =IF(F13=0,"",VLOOKUP(TONTRESUME24T100!A13,[15]TONTRESUME24!A14:T27,17,0)) -> 45444 | H13: =IF(C13=600000,"",VLOOKUP(TONTRESUME24T100!A13,[15]TONTRESUME24!A14:U27,18,0)) | I13: =[15]TONTRESUME24!S14 -> 35111.111 | J13: =[15]TONTRESUME24!T14 -> 0
A14: AS201626 | B14: =VLOOKUP(A14,[12]LISTADHERENT!A$5:H$60,3,0) -> NGUIEMEGNI MATHIEU BLAISE | C14: =+[15]TONTRESUME24!D15 -> 600000 | D14: =+[15]TONTRESUME24!G15 -> 9000 | E14: =+[15]TONTRESUME24!O15 -> 1075000 | F14: =+[15]TONTRESUME24!P15 -> 125000 | G14: =IF(F14=0,"",VLOOKUP(TONTRESUME24T100!A14,[15]TONTRESUME24!A15:T28,17,0)) -> 45292 | H14: =IF(C14=600000,"",VLOOKUP(TONTRESUME24T100!A14,[15]TONTRESUME24!A15:U28,18,0)) | I14: =[15]TONTRESUME24!S15 -> 35111.111 | J14: =[15]TONTRESUME24!T15 -> 0
A15: AS201653 | B15: =VLOOKUP(A15,[12]LISTADHERENT!A$5:H$60,3,0) -> SIME BRICE | C15: =+[15]TONTRESUME24!D16 -> 1200000 | D15: =+[15]TONTRESUME24!G16 -> 1000 | E15: =+[15]TONTRESUME24!O16 -> 2350000 | F15: =+[15]TONTRESUME24!P16 -> 50000 | G15: =IF(F15=0,"",VLOOKUP(TONTRESUME24T100!A15,[15]TONTRESUME24!A16:T29,17,0)) -> 45323 | H15: =IF(C15=600000,"",VLOOKUP(TONTRESUME24T100!A15,[15]TONTRESUME24!A16:U29,18,0)) -> 45444 | I15: =[15]TONTRESUME24!S16 -> 70222.222 | J15: =[15]TONTRESUME24!T16 -> 0
A16: AS201660 | B16: =VLOOKUP(A16,[12]LISTADHERENT!A$5:H$60,3,0) -> TCHOUATEU AUGUSTIN | C16: =+[15]TONTRESUME24!D17 -> 600000 | D16: =+[15]TONTRESUME24!G17 -> 0 | E16: =+[15]TONTRESUME24!O17 -> 0 | F16: =+[15]TONTRESUME24!P17 -> 0 | G16: =IF(F16=0,"",VLOOKUP(TONTRESUME24T100!A16,[15]TONTRESUME24!A17:T30,17,0)) | H16: =IF(C16=600000,"",VLOOKUP(TONTRESUME24T100!A16,[15]TONTRESUME24!A17:U30,18,0)) | I16: =[15]TONTRESUME24!S17 -> 35111.111 | J16: =[15]TONTRESUME24!T17 -> 0
A17: AS201638 | B17: =VLOOKUP(A17,[12]LISTADHERENT!A$5:H$60,3,0) -> SIMO PIERRE | C17: =+[15]TONTRESUME24!D18 -> 600000 | D17: =+[15]TONTRESUME24!G18 -> 0 | E17: =+[15]TONTRESUME24!O18 -> 1160000 | F17: =+[15]TONTRESUME24!P18 -> 40000 | G17: =IF(F17=0,"",VLOOKUP(TONTRESUME24T100!A17,[15]TONTRESUME24!A18:T31,17,0)) -> 45383 | H17: =IF(C17=600000,"",VLOOKUP(TONTRESUME24T100!A17,[15]TONTRESUME24!A18:U31,18,0)) | I17: =[15]TONTRESUME24!S18 -> 35111.111
A18: AS201659 | B18: =VLOOKUP(A18,[12]LISTADHERENT!A$5:H$60,3,0) -> YIALA ALAIN OSCAR | C18: =+[15]TONTRESUME24!D19 -> 600000 | D18: =+[15]TONTRESUME24!G19 -> 0 | E18: =+[15]TONTRESUME24!O19 -> 0 | F18: =+[15]TONTRESUME24!P19 -> 0 | G18: =IF(F18=0,"",VLOOKUP(TONTRESUME24T100!A18,[15]TONTRESUME24!A19:T32,17,0)) | H18: =IF(C18=600000,"",VLOOKUP(TONTRESUME24T100!A18,[15]TONTRESUME24!A19:U32,18,0)) | I18: =[15]TONTRESUME24!S19 -> 35111.111
A20: TOTAL PART | C20: =SUM(C5:C19) -> 10800000 | D20: =SUM(D5:D19) -> 37000 | E20: =SUM(E5:E19) -> 12605000 | F20: =SUM(F5:F19) -> 595000 | I20: =SUM(I5:I17) -> 561777.78 | J20: =SUM(J5:J17) -> 0
