Workbook
Name MODEPAID: MODEPAID!$A$1:$A$3
Name MODEPAID: #REF!
Name MODEPAID: #REF!
Name MODEPAID: #REF!
Name MODEPAID: #REF!
Name MODEPAID: #REF!
Name MODEPAID: #REF!
Name MODEPAID: #REF!
Name MODEPAID: #REF!
Name MODEPAID: #REF!
Name MODEPAID: #REF!
Name MODEPAID: #REF!
Name MODEPAID: #REF!
Name MODEPAID: #REF!
Name MODEPAID: #REF!
Name MODEPAID: #REF!
Name MODEPAID: #REF!
Name VALMODEPAID: MODEPAID!$A$1:$A$3

Sheet Feuil1
B1: INTERET VENTE | C1: MISE A PRIX | D1: INTERET MISE EN VENTE | E1: INTERET PETIT LOT | F1: INT CUMUL MISE EN VENTE | G1: INTERET NON REMB | H1: PETIT LOT + INTERET
A2: 42979 | B2: =#REF! -> #REF! | C2: 200000 | D2: =B2-C2 -> #REF! | E2: =#REF! -> #REF! | H2: =#REF! -> #REF! | I2: OK
A3: 43009 | B3: =+#REF! -> #REF! | C3: 200000 | D3: =B3-C3 -> #REF! | E3: =+#REF! -> #REF! | F3: =D2+E2+D3 -> #REF! | H3: =#REF! -> #REF! | I3: OK
A4: 43040 | B4: =+#REF! -> #REF! | C4: 200000 | D4: =B4-C4 -> #REF! | E4: =+#REF! -> #REF! | F4: =F3+D4+E3 -> #REF! | H4: =#REF! -> #REF! | I4: OK
A5: 43070 | B5: =#REF! -> #REF! | C5: 200000 | D5: =B5-C5 -> #REF! | E5: =+#REF! -> #REF! | F5: =F4+D5+E4 -> #REF! | G5: 200000 | H5: =#REF! -> #REF! | I5: NOK
A6: 43101 | B6: =+#REF! -> #REF! | C6: 200000 | D6: =B6-C6 -> #REF! | E6: =+#REF! -> #REF! | F6: =F5+D6+E5 -> #REF! | H6: =#REF! -> #REF!
A7: 43132 | B7: =+#REF! -> #REF! | C7: 200000 | D7: =B7-C7 -> #REF! | E7: =+#REF! -> #REF! | F7: =F6+D7+E6 -> #REF! | G7: 200000 | H7: =#REF! -> #REF!
A8: 43160 | B8: =+#REF! -> #REF! | C8: 200000 | D8: =B8-C8 -> #REF! | E8: =+#REF! -> #REF! | F8: =F7+D8+E7 -> #REF! | H8: =#REF! -> #REF!
A9: 43191 | B9: =+#REF! -> #REF! | C9: 200000 | D9: =B9-C9 -> #REF! | E9: =+#REF! -> #REF! | F9: =F8+D9+E8 -> #REF! | H9: =#REF! -> #REF!
A10: 43221 | B10: =+#REF! -> #REF! | C10: 200000 | D10: =B10-C10 -> #REF! | E10: =+#REF! -> #REF! | F10: =F9+D10+E9 -> #REF! | H10: =#REF! -> #REF!
A11: 43252 | B11: =+#REF! -> #REF! | C11: 200000 | D11: =B11-C11 -> #REF! | E11: =+#REF! -> #REF! | F11: =F10+D11+E10 -> #REF! | H11: =#REF! -> #REF!
A12: 43282 | B12: =+#REF! -> #REF! | C12: 100000 | D12: =B12-C12 -> #REF! | E12: =+#REF! -> #REF! | F12: =F11+D12+E11 -> #REF! | H12: =#REF! -> #REF!
A13: 43313 | B13: 200000 | C13: 200000 | D13: 0 | E13: 0 | F13: =F12+D13+E12 -> #REF! | H13: =#REF! -> #REF!
B14: =SUM(B2:B13) -> #REF! | C14: =SUM(C2:C13) -> 2300000
C15: =+B14-C14 -> #REF! | D15: =SUM(D2:D14) -> #REF! | E15: =SUM(E2:E14) -> #REF! | H15: 1145500 | I15: 2300000
H16: 12000
B17: NGONDIEP | D17: 101000 | H17: =+H15+H16 -> 1157500
B18: NANGUEN | D18: 96000 | H18: 200000
B19: FOTSO THOMAS | D19: 206000 | H19: 269000
H20: =+H17+H18+H19 -> 1626500
H21: =D15+E15-H20 -> #REF!
D22: =SUM(D17:D21) -> 403000

Sheet MODEPAID
A1: BANQUE
A2: ESPECES
A3: ECHEC

Sheet TONTNOV
A1: ASSOCIATION | B1: ASELBY
A2: ANNEE | B2: 2019/2020
A3: TONTINE | B3: 100000
C4: 43793
A5: MATRICULE | B5: NOM ET PRENOM | C5: MONTANT TONTINE | D5: PENALITE | E5: MODE VERSEMENT TONTINE | F5: REPORT ECHEC PETIT LOT | G5: MODE VERSEMENT VENTE PETIT LOT | H5: VENTE PETIT LOT | I5: INTERET PETIT LOT | J5: MODE VERSEMENT VENTE PETIT LOT | K5: NUMERO CHEQUE | L5: REMBOURSEMENT | M5: MODE VERSEMENT REMBOURSEMENT | N5: MODE VERSEMENT TONTINE PRINCIPAL | O5: NUMERO CHEQUE | P5: MONTANT TONTINE LOT PRINCIPAL | Q5: INTERET LOT PRINCIPAL | R5: DATE VENTE
A6: AS201608 | B6: =VLOOKUP(A6,[1]LISTADHERENT!A$5:H$60,3,0) -> DJUOMBESSY ANTOINE | C6: =IF(E6="ECHEC",0,IF(E6="",0,100000)) -> 100000 | D6: =IF(E6="ESPECES",0,0) -> 0 | E6: BANQUE | P6: =IF(Q6=0,0,($C$38-Q6)) -> 0
A7: AS201613 | B7: =VLOOKUP(A7,[1]LISTADHERENT!A$5:H$60,3,0) -> HOTCHO BENJAMIN | C7: =IF(E7="ECHEC",0,IF(E7="",0,100000)) -> 100000 | D7: =IF(E7="ESPECES",0,0) -> 0 | E7: BANQUE | P7: =IF(Q7=0,0,($C$38-Q7)) -> 0
A8: AS201619 | B8: =VLOOKUP(A8,[1]LISTADHERENT!A$5:H$60,3,0) -> KOUATCHO MESSACK | C8: =IF(E8="ECHEC",0,IF(E8="",0,100000)) -> 100000 | D8: =IF(E8="ESPECES",0,0) -> 0 | E8: BANQUE | H8: =100000+50000 -> 150000 | I8: =2500+1000 -> 3500 | J8: ESPECES | P8: =IF(Q8=0,0,($C$38-Q8)) -> 0
A9: AS201617 | B9: =VLOOKUP(A9,[1]LISTADHERENT!A$5:H$60,3,0) -> KOUAMOU MOISE | C9: =IF(E9="ECHEC",0,IF(E9="",0,100000)) -> 100000 | D9: =IF(E9="ESPECES",0,0) -> 0 | E9: BANQUE | P9: =IF(Q9=0,0,($C$38-Q9)) -> 0
A10: AS201649 | B10: =VLOOKUP(A10,[1]LISTADHERENT!A$5:H$60,3,0) -> MBOGNING TUGMA GUY | C10: =IF(E10="ECHEC",0,IF(E10="",0,100000)) -> 100000 | D10: =IF(E10="ESPECES",0,0) -> 0 | E10: BANQUE | H10: =100000+100000 -> 200000 | I10: =2500+5500 -> 8000 | J10: BANQUE | P10: =IF(Q10=0,0,($C$38-Q10)) -> 0
A11: AS201649 | B11: =VLOOKUP(A11,[1]LISTADHERENT!A$5:H$60,3,0) -> MBOGNING TUGMA GUY | C11: =IF(E11="ECHEC",0,IF(E11="",0,100000)) -> 100000 | D11: =IF(E11="ESPECES",0,0) -> 0 | E11: BANQUE | P11: =IF(Q11=0,0,($C$38-Q11)) -> 0
A12: AS201639 | B12: =VLOOKUP(A12,[1]LISTADHERENT!A$5:H$60,3,0) -> NANGUEN MARTIN | C12: =IF(E12="ECHEC",0,IF(E12="",0,100000)) -> 100000 | D12: =IF(E12="ESPECES",0,0) -> 0 | E12: BANQUE | P12: =IF(Q12=0,0,($C$38-Q12)) -> 0
A13: AS201622 | B13: =VLOOKUP(A13,[1]LISTADHERENT!A$5:H$60,3,0) -> NDJOMO ETIENNE | C13: =IF(E13="ECHEC",0,IF(E13="",0,100000)) -> 100000 | D13: =IF(E13="ESPECES",0,0) -> 0 | E13: BANQUE | P13: =IF(Q13=0,0,($C$38-Q13)) -> 0
A14: AS201624 | B14: =VLOOKUP(A14,[1]LISTADHERENT!A$5:H$60,3,0) -> NGONDIEP CLAUDE | C14: =IF(E14="ECHEC",0,IF(E14="",0,100000)) -> 100000 | D14: =IF(E14="ESPECES",0,0) -> 0 | E14: BANQUE | P14: =IF(Q14=0,0,($C$38-Q14)) -> 0
A15: AS201614 | B15: =VLOOKUP(A15,[1]LISTADHERENT!A$5:H$60,3,0) -> NKEHE DAVID | C15: =IF(E15="ECHEC",0,IF(E15="",0,100000)) -> 100000 | D15: =IF(E15="ESPECES",0,0) -> 0 | E15: ESPECES | N15: BANQUE | P15: =IF(Q15=0,0,($C$38-Q15)) -> 1350000 | Q15: 150000 | R15: 43793
A16: AS201629 | B16: =VLOOKUP(A16,[1]LISTADHERENT!A$5:H$60,3,0) -> NKEPSEU DIEUDONNE | C16: =IF(E16="ECHEC",0,IF(E16="",0,100000)) -> 100000 | D16: =IF(E16="ESPECES",0,0) -> 0 | E16: BANQUE | P16: =IF(Q16=0,0,($C$38-Q16)) -> 0
A17: AS201636 | B17: =VLOOKUP(A17,[1]LISTADHERENT!A$5:H$60,3,0) -> SIMO FONGANG ERIC | C17: =IF(E17="ECHEC",0,IF(E17="",0,100000)) -> 100000 | D17: =IF(E17="ESPECES",0,0) -> 0 | E17: BANQUE | P17: =IF(Q17=0,0,($C$38-Q17)) -> 0
A18: AS201636 | B18: =VLOOKUP(A18,[1]LISTADHERENT!A$5:H$60,3,0) -> SIMO FONGANG ERIC | C18: =IF(E18="ECHEC",0,IF(E18="",0,100000)) -> 100000 | D18: =IF(E18="ESPECES",0,0) -> 0 | E18: BANQUE | P18: =IF(Q18=0,0,($C$38-Q18)) -> 0
A19: AS201637 | B19: =VLOOKUP(A19,[1]LISTADHERENT!A$5:H$60,3,0) -> SIME MATHIEU | C19: =IF(E19="ECHEC",0,IF(E19="",0,100000)) -> 100000 | D19: =IF(E19="ESPECES",0,0) -> 0 | E19: BANQUE | P19: =IF(Q19=0,0,($C$38-Q19)) -> 0
A20: AS201637 | B20: =VLOOKUP(A20,[1]LISTADHERENT!A$5:H$60,3,0) -> SIME MATHIEU | C20: =IF(E20="ECHEC",0,IF(E20="",0,100000)) -> 100000 | D20: =IF(E20="ESPECES",0,0) -> 0 | E20: BANQUE | P20: =IF(Q20=0,0,($C$38-Q20)) -> 0
A21: AS201641 | B21: =VLOOKUP(A21,[1]LISTADHERENT!A$5:H$60,3,0) -> TCHOUAMOU MATHIEU | C21: =IF(E21="ECHEC",0,IF(E21="",0,100000)) -> 100000 | D21: =IF(E21="ESPECES",0,0) -> 0 | E21: BANQUE | P21: =IF(Q21=0,0,($C$38-Q21)) -> 0
A22: AS201644 | B22: =VLOOKUP(A22,[1]LISTADHERENT!A$5:H$60,3,0) -> TIEYAM ERNEST | C22: =IF(E22="ECHEC",0,IF(E22="",0,100000)) -> 100000 | D22: =IF(E22="ESPECES",0,0) -> 0 | E22: BANQUE | H22: =100000+100000 -> 200000 | I22: =4000+9000 -> 13000 | J22: BANQUE | P22: =IF(Q22=0,0,($C$38-Q22)) -> 0
A23: AS201647 | B23: =VLOOKUP(A23,[1]LISTADHERENT!A$5:H$60,3,0) -> YOUMBI EMMANUEL | C23: =IF(E23="ECHEC",0,IF(E23="",0,100000)) -> 100000 | D23: =IF(E23="ESPECES",0,0) -> 0 | E23: BANQUE | P23: =IF(Q23=0,0,($C$38-Q23)) -> 0
A25: TOTAL | C25: =SUM(C6:C24) -> 1800000 | D25: =SUM(D6:D24) -> 0 | F25: =SUM(F6:F24) -> 0 | H25: =SUM(H6:H24) -> 550000 | I25: =SUM(I6:I24) -> 24500 | L25: =SUM(L6:L24) -> 0 | P25: =SUM(P6:P24) -> 1350000 | Q25: =SUM(Q6:Q24) -> 150000
C27: TONTINE | D27: REMBOURSEMENT PETIT LOT | E27: VENTE PETIT LOT | F27: VENTE LOT PRINCIPAL | G27: SOLDE EN CAISSE | M27: TONTINE + REMB + INTERET VENTE | N27: =C32+D32+Q25 -> 1950000
M28: VENDUE | N28: =IF(N27>=2800000,1500000*2,1500000) -> 1500000
B29: ESPECES | C29: =SUMIFS(C6:C24,E6:E24,"ESPECES") -> 100000 | D29: =SUMIFS(L6:L24,M6:M24,"ESPECES")+SUMIFS(F6:F24,G6:G24,"ESPECES") -> 0 | E29: =SUMIFS(H6:H24,J6:J24,"ESPECES") -> 150000 | F29: =SUMIFS(P6:P24,N6:N24,"ESPECES") -> 0 | G29: =C29+D29-E29-F29 -> -50000
B30: BANQUE | C30: =SUMIFS(C6:C24,E6:E24,"BANQUE") -> 1700000 | D30: =SUMIFS(L6:L24,M6:M24,"BANQUE")+SUMIFS(F6:F24,G6:G24,"BANQUE") -> 0 | E30: =SUMIFS(H6:H24,J6:J24,"BANQUE") -> 400000 | F30: =SUMIFS(P6:P24,N6:N24,"BANQUE") -> 1350000 | G30: =C30+D30-E30-F30 -> -50000 | M30: PETIT LOT | N30: =N27-N28 -> 450000
B32: TOTAL | C32: =C29+C30 -> 1800000 | D32: =D29+D30 -> 0 | E32: =E29+E30 -> 550000 | F32: =F29+F30 -> 1350000 | G32: =G29+G30 -> -100000 | M32: RELIQUAT | N32: =N30-H25 -> -100000 | O32: =N32 -> -100000 | P32: CUMUL
M34: ECHEC TONTINE | N34: =COUNTIFS(E6:E24,"ECHEC")*100000 -> 0 | O34: =N34 -> 0 | P34: CUMUL
B35: INTERET LOT PRINCIPAL | C35: =Q25 -> 150000 | M35: ECHEC REMBOURSEMENT | N35: =SUMIFS(F6:F24,G6:G24,"ECHEC") -> 0 | P35: CUMUL
B36: INTERET PETIT LOT | C36: =+I25 -> 24500
B38: MONTANT TONTINE | C38: 1500000
B39: MONTANT PETIT LOT A VENDRE | C39: =H25 -> 550000

Sheet TONTDEC
A1: ASSOCIATION | B1: ASELBY
A2: ANNEE | B2: 2019/2020
A3: TONTINE | B3: 100000
C4: 43814
A5: MATRICULE | B5: NOM ET PRENOM | C5: MONTANT TONTINE | D5: PENALITE | E5: MODE VERSEMENT TONTINE | F5: REPORT ECHEC PETIT LOT | G5: MODE VERSEMENT VENTE PETIT LOT | H5: VENTE PETIT LOT | I5: INTERET PETIT LOT | J5: MODE VERSEMENT VENTE PETIT LOT | K5: NUMERO CHEQUE | L5: REMBOURSEMENT | M5: MODE VERSEMENT REMBOURSEMENT | N5: MODE VERSEMENT TONTINE PRINCIPAL | O5: NUMERO CHEQUE | P5: MONTANT TONTINE LOT PRINCIPAL | Q5: INTERET LOT PRINCIPAL | R5: DATE VENTE
A6: AS201608 | B6: =VLOOKUP(A6,[1]LISTADHERENT!A$5:H$60,3,0) -> DJUOMBESSY ANTOINE | C6: =IF(E6="ECHEC",0,IF(E6="",0,100000)) -> 100000 | D6: =IF(E6="ESPECES",0,0) -> 0 | E6: BANQUE | F6: =TONTNOV!F6 -> 0 | L6: =TONTNOV!H6+TONTNOV!I6 -> 0 | P6: =IF(Q6=0,0,($C$38-Q6)) -> 0
A7: AS201613 | B7: =VLOOKUP(A7,[1]LISTADHERENT!A$5:H$60,3,0) -> HOTCHO BENJAMIN | C7: =IF(E7="ECHEC",0,IF(E7="",0,100000)) -> 100000 | D7: =IF(E7="ESPECES",0,0) -> 0 | E7: BANQUE | F7: =TONTNOV!F7 -> 0 | L7: =TONTNOV!H7+TONTNOV!I7 -> 0 | P7: =IF(Q7=0,0,($C$38-Q7)) -> 0
A8: AS201619 | B8: =VLOOKUP(A8,[1]LISTADHERENT!A$5:H$60,3,0) -> KOUATCHO MESSACK | C8: =IF(E8="ECHEC",0,IF(E8="",0,100000)) -> 100000 | D8: =IF(E8="ESPECES",0,0) -> 0 | E8: BANQUE | F8: =TONTNOV!F8 -> 0 | L8: =TONTNOV!H8+TONTNOV!I8 -> 153500 | M8: BANQUE | P8: =IF(Q8=0,0,($C$38-Q8)) -> 1250000 | Q8: 250000 | R8: 43814
A9: AS201617 | B9: =VLOOKUP(A9,[1]LISTADHERENT!A$5:H$60,3,0) -> KOUAMOU MOISE | C9: =IF(E9="ECHEC",0,IF(E9="",0,100000)) -> 100000 | D9: =IF(E9="ESPECES",0,0) -> 0 | E9: BANQUE | F9: =TONTNOV!F9 -> 0 | L9: =TONTNOV!H9+TONTNOV!I9 -> 0 | P9: =IF(Q9=0,0,($C$38-Q9)) -> 0
A10: AS201649 | B10: =VLOOKUP(A10,[1]LISTADHERENT!A$5:H$60,3,0) -> MBOGNING TUGMA GUY | C10: =IF(E10="ECHEC",0,IF(E10="",0,100000)) -> 100000 | D10: =IF(E10="ESPECES",0,0) -> 0 | E10: BANQUE | F10: =TONTNOV!F10 -> 0 | L10: =TONTNOV!H10+TONTNOV!I10 -> 208000 | M10: BANQUE | P10: =IF(Q10=0,0,($C$38-Q10)) -> 0
A11: AS201649 | B11: =VLOOKUP(A11,[1]LISTADHERENT!A$5:H$60,3,0) -> MBOGNING TUGMA GUY | C11: =IF(E11="ECHEC",0,IF(E11="",0,100000)) -> 100000 | D11: =IF(E11="ESPECES",0,0) -> 0 | E11: BANQUE | F11: =TONTNOV!F11 -> 0 | L11: =TONTNOV!H11+TONTNOV!I11 -> 0 | P11: =IF(Q11=0,0,($C$38-Q11)) -> 0
A12: AS201639 | B12: =VLOOKUP(A12,[1]LISTADHERENT!A$5:H$60,3,0) -> NANGUEN MARTIN | C12: =IF(E12="ECHEC",0,IF(E12="",0,100000)) -> 100000 | D12: =IF(E12="ESPECES",0,0) -> 0 | E12: BANQUE | F12: =TONTNOV!F12 -> 0 | L12: =TONTNOV!H12+TONTNOV!I12 -> 0 | P12: =IF(Q12=0,0,($C$38-Q12)) -> 0
A13: AS201622 | B13: =VLOOKUP(A13,[1]LISTADHERENT!A$5:H$60,3,0) -> NDJOMO ETIENNE | C13: =IF(E13="ECHEC",0,IF(E13="",0,100000)) -> 100000 | D13: =IF(E13="ESPECES",0,0) -> 0 | E13: BANQUE | F13: =TONTNOV!F13 -> 0 | L13: =TONTNOV!H13+TONTNOV!I13 -> 0 | P13: =IF(Q13=0,0,($C$38-Q13)) -> 0
A14: AS201624 | B14: =VLOOKUP(A14,[1]LISTADHERENT!A$5:H$60,3,0) -> NGONDIEP CLAUDE | C14: =IF(E14="ECHEC",0,IF(E14="",0,100000)) -> 100000 | D14: =IF(E14="ESPECES",0,0) -> 0 | E14: BANQUE | F14: =TONTNOV!F14 -> 0 | L14: =TONTNOV!H14+TONTNOV!I14 -> 0 | P14: =IF(Q14=0,0,($C$38-Q14)) -> 0
A15: AS201614 | B15: =VLOOKUP(A15,[1]LISTADHERENT!A$5:H$60,3,0) -> NKEHE DAVID | C15: =IF(E15="ECHEC",0,IF(E15="",0,100000)) -> 100000 | D15: =IF(E15="ESPECES",0,0) -> 0 | E15: BANQUE | F15: =TONTNOV!F15 -> 0 | L15: =TONTNOV!H15+TONTNOV!I15 -> 0 | P15: =IF(Q15=0,0,($C$38-Q15)) -> 0
A16: AS201629 | B16: =VLOOKUP(A16,[1]LISTADHERENT!A$5:H$60,3,0) -> NKEPSEU DIEUDONNE | C16: =IF(E16="ECHEC",0,IF(E16="",0,100000)) -> 100000 | D16: =IF(E16="ESPECES",0,0) -> 0 | E16: ESPECES | F16: =TONTNOV!F16 -> 0 | L16: =TONTNOV!H16+TONTNOV!I16 -> 0 | P16: =IF(Q16=0,0,($C$38-Q16)) -> 0
A17: AS201636 | B17: =VLOOKUP(A17,[1]LISTADHERENT!A$5:H$60,3,0) -> SIMO FONGANG ERIC | C17: =IF(E17="ECHEC",0,IF(E17="",0,100000)) -> 100000 | D17: =IF(E17="ESPECES",0,0) -> 0 | E17: ESPECES | F17: =TONTNOV!F17 -> 0 | L17: =TONTNOV!H17+TONTNOV!I17 -> 0 | P17: =IF(Q17=0,0,($C$38-Q17)) -> 1255000 | Q17: 245000 | R17: 43814
A18: AS201636 | B18: =VLOOKUP(A18,[1]LISTADHERENT!A$5:H$60,3,0) -> SIMO FONGANG ERIC | C18: =IF(E18="ECHEC",0,IF(E18="",0,100000)) -> 100000 | D18: =IF(E18="ESPECES",0,0) -> 0 | E18: ESPECES | F18: =TONTNOV!F18 -> 0 | L18: =TONTNOV!H18+TONTNOV!I18 -> 0 | N18: BANQUE | P18: =IF(Q18=0,0,($C$38-Q18)) -> 0
A19: AS201637 | B19: =VLOOKUP(A19,[1]LISTADHERENT!A$5:H$60,3,0) -> SIME MATHIEU | C19: =IF(E19="ECHEC",0,IF(E19="",0,100000)) -> 100000 | D19: =IF(E19="ESPECES",0,0) -> 0 | E19: BANQUE | F19: =TONTNOV!F19 -> 0 | L19: =TONTNOV!H19+TONTNOV!I19 -> 0 | P19: =IF(Q19=0,0,($C$38-Q19)) -> 0
A20: AS201637 | B20: =VLOOKUP(A20,[1]LISTADHERENT!A$5:H$60,3,0) -> SIME MATHIEU | C20: =IF(E20="ECHEC",0,IF(E20="",0,100000)) -> 100000 | D20: =IF(E20="ESPECES",0,0) -> 0 | E20: BANQUE | F20: =TONTNOV!F20 -> 0 | L20: =TONTNOV!H20+TONTNOV!I20 -> 0 | P20: =IF(Q20=0,0,($C$38-Q20)) -> 0
A21: AS201641 | B21: =VLOOKUP(A21,[1]LISTADHERENT!A$5:H$60,3,0) -> TCHOUAMOU MATHIEU | C21: =IF(E21="ECHEC",0,IF(E21="",0,100000)) -> 100000 | D21: =IF(E21="ESPECES",0,0) -> 0 | E21: BANQUE | F21: =TONTNOV!F21 -> 0 | L21: =TONTNOV!H21+TONTNOV!I21 -> 0 | P21: =IF(Q21=0,0,($C$38-Q21)) -> 0
A22: AS201644 | B22: =VLOOKUP(A22,[1]LISTADHERENT!A$5:H$60,3,0) -> TIEYAM ERNEST | C22: =IF(E22="ECHEC",0,IF(E22="",0,100000)) -> 100000 | D22: =IF(E22="ESPECES",0,0) -> 0 | E22: BANQUE | F22: =TONTNOV!F22 -> 0 | L22: =TONTNOV!H22+TONTNOV!I22 -> 213000 | M22: ESPECES | P22: =IF(Q22=0,0,($C$38-Q22)) -> 0
A23: AS201647 | B23: =VLOOKUP(A23,[1]LISTADHERENT!A$5:H$60,3,0) -> YOUMBI EMMANUEL | C23: =IF(E23="ECHEC",0,IF(E23="",0,100000)) -> 100000 | D23: =IF(E23="ESPECES",0,0) -> 0 | E23: BANQUE | F23: =TONTNOV!F23 -> 0 | L23: =TONTNOV!H23+TONTNOV!I23 -> 0 | P23: =IF(Q23=0,0,($C$38-Q23)) -> 0
A25: TOTAL | C25: =SUM(C6:C24) -> 1800000 | D25: =SUM(D6:D24) -> 0 | F25: =SUM(F6:F24) -> 0 | H25: =SUM(H6:H24) -> 0 | I25: =SUM(I6:I24) -> 0 | L25: =SUM(L6:L24) -> 574500 | P25: =SUM(P6:P24) -> 2505000 | Q25: =SUM(Q6:Q24) -> 495000
C27: TONTINE | D27: REMBOURSEMENT PETIT LOT | E27: VENTE PETIT LOT | F27: VENTE LOT PRINCIPAL | G27: SOLDE EN CAISSE | M27: TONTINE + REMB + INTERET VENTE | N27: =C32+D32+Q25 -> 2869500
M28: VENDUE | N28: =IF(N27>=2800000,1500000*2,1500000) -> 3000000
B29: ESPECES | C29: =SUMIFS(C6:C24,E6:E24,"ESPECES") -> 300000 | D29: =SUMIFS(L6:L24,M6:M24,"ESPECES")+SUMIFS(F6:F24,G6:G24,"ESPECES") -> 213000 | E29: =SUMIFS(H6:H24,J6:J24,"ESPECES") -> 0 | F29: =SUMIFS(P6:P24,N6:N24,"ESPECES") -> 0 | G29: =C29+D29-E29-F29 -> 513000
B30: BANQUE | C30: =SUMIFS(C6:C24,E6:E24,"BANQUE") -> 1500000 | D30: =SUMIFS(L6:L24,M6:M24,"BANQUE")+SUMIFS(F6:F24,G6:G24,"BANQUE") -> 361500 | E30: =SUMIFS(H6:H24,J6:J24,"BANQUE") -> 0 | F30: =SUMIFS(P6:P24,N6:N24,"BANQUE") -> 0 | G30: =C30+D30-E30-F30 -> 1861500 | M30: PETIT LOT | N30: =N27-N28 -> -130500
B32: TOTAL | C32: =C29+C30 -> 1800000 | D32: =D29+D30 -> 574500 | E32: =E29+E30 -> 0 | F32: =F29+F30 -> 0 | G32: =G29+G30 -> 2374500 | M32: RELIQUAT | N32: =N30-H25 -> -130500 | O32: =N32+TONTNOV!O32 -> -230500 | P32: CUMUL
M34: ECHEC TONTINE | N34: =COUNTIFS(E6:E24,"ECHEC")*100000 -> 0 | O34: =N34+TONTNOV!O34 -> 0 | P34: CUMUL
B35: INTERET LOT PRINCIPAL | C35: =Q25 -> 495000 | M35: ECHEC REMBOURSEMENT | N35: =SUMIFS(F6:F24,G6:G24,"ECHEC") -> 0 | P35: CUMUL
B36: INTERET PETIT LOT | C36: =+I25 -> 0
B38: MONTANT TONTINE | C38: 1500000
B39: MONTANT PETIT LOT A VENDRE | C39: =H25 -> 0

Sheet TONTJANV
A1: ASSOCIATION | B1: ASELBY
A2: ANNEE | B2: 2019/2020
A3: TONTINE | B3: 100000
C4: 43848
A5: MATRICULE | B5: NOM ET PRENOM | C5: MONTANT TONTINE | D5: PENALITE | E5: MODE VERSEMENT TONTINE | F5: REPORT ECHEC PETIT LOT | G5: MODE VERSEMENT VENTE PETIT LOT | H5: VENTE PETIT LOT | I5: INTERET PETIT LOT | J5: MODE VERSEMENT VENTE PETIT LOT | K5: NUMERO CHEQUE | L5: REMBOURSEMENT | M5: MODE VERSEMENT REMBOURSEMENT | N5: MODE VERSEMENT TONTINE PRINCIPAL | O5: NUMERO CHEQUE | P5: MONTANT TONTINE LOT PRINCIPAL | Q5: INTERET LOT PRINCIPAL | R5: DATE VENTE
A6: AS201608 | B6: =VLOOKUP(A6,[1]LISTADHERENT!A$5:H$60,3,0) -> DJUOMBESSY ANTOINE | C6: =IF(E6="ECHEC",0,IF(E6="",0,100000)) -> 100000 | D6: =IF(E6="ESPECES",0,0) -> 0 | E6: BANQUE | F6: =TONTDEC!F6 -> 0 | L6: =TONTDEC!H6+TONTDEC!I6 -> 0 | P6: =IF(Q6=0,0,($C$38-Q6)) -> 0
A7: AS201613 | B7: =VLOOKUP(A7,[1]LISTADHERENT!A$5:H$60,3,0) -> HOTCHO BENJAMIN | C7: =IF(E7="ECHEC",0,IF(E7="",0,100000)) -> 100000 | D7: =IF(E7="ESPECES",0,0) -> 0 | E7: BANQUE | F7: =TONTDEC!F7 -> 0 | L7: =TONTDEC!H7+TONTDEC!I7 -> 0 | P7: =IF(Q7=0,0,($C$38-Q7)) -> 0
A8: AS201619 | B8: =VLOOKUP(A8,[1]LISTADHERENT!A$5:H$60,3,0) -> KOUATCHO MESSACK | C8: =IF(E8="ECHEC",0,IF(E8="",0,100000)) -> 100000 | D8: =IF(E8="ESPECES",0,0) -> 0 | E8: BANQUE | F8: =TONTDEC!F8 -> 0 | H8: 100000 | I8: 4000 | J8: ESPECES | L8: =TONTDEC!H8+TONTDEC!I8 -> 0 | P8: =IF(Q8=0,0,($C$38-Q8)) -> 0
A9: AS201617 | B9: =VLOOKUP(A9,[1]LISTADHERENT!A$5:H$60,3,0) -> KOUAMOU MOISE | C9: =IF(E9="ECHEC",0,IF(E9="",0,100000)) -> 100000 | D9: =IF(E9="ESPECES",0,0) -> 0 | E9: BANQUE | F9: =TONTDEC!F9 -> 0 | L9: =TONTDEC!H9+TONTDEC!I9 -> 0 | P9: =IF(Q9=0,0,($C$38-Q9)) -> 0
A10: AS201649 | B10: =VLOOKUP(A10,[1]LISTADHERENT!A$5:H$60,3,0) -> MBOGNING TUGMA GUY | C10: =IF(E10="ECHEC",0,IF(E10="",0,100000)) -> 100000 | D10: =IF(E10="ESPECES",0,0) -> 0 | E10: BANQUE | F10: =TONTDEC!F10 -> 0 | L10: =TONTDEC!H10+TONTDEC!I10 -> 0 | P10: =IF(Q10=0,0,($C$38-Q10)) -> 1270000 | Q10: 230000
A11: AS201649 | B11: =VLOOKUP(A11,[1]LISTADHERENT!A$5:H$60,3,0) -> MBOGNING TUGMA GUY | C11: =IF(E11="ECHEC",0,IF(E11="",0,100000)) -> 100000 | D11: =IF(E11="ESPECES",0,0) -> 0 | E11: BANQUE | F11: =TONTDEC!F11 -> 0 | L11: =TONTDEC!H11+TONTDEC!I11 -> 0 | P11: =IF(Q11=0,0,($C$38-Q11)) -> 0
A12: AS201639 | B12: =VLOOKUP(A12,[1]LISTADHERENT!A$5:H$60,3,0) -> NANGUEN MARTIN | C12: =IF(E12="ECHEC",0,IF(E12="",0,100000)) -> 100000 | D12: =IF(E12="ESPECES",0,0) -> 0 | E12: BANQUE | F12: =TONTDEC!F12 -> 0 | L12: =TONTDEC!H12+TONTDEC!I12 -> 0 | P12: =IF(Q12=0,0,($C$38-Q12)) -> 0
A13: AS201622 | B13: =VLOOKUP(A13,[1]LISTADHERENT!A$5:H$60,3,0) -> NDJOMO ETIENNE | C13: =IF(E13="ECHEC",0,IF(E13="",0,100000)) -> 100000 | D13: =IF(E13="ESPECES",0,0) -> 0 | E13: BANQUE | F13: =TONTDEC!F13 -> 0 | L13: =TONTDEC!H13+TONTDEC!I13 -> 0 | P13: =IF(Q13=0,0,($C$38-Q13)) -> 0
A14: AS201624 | B14: =VLOOKUP(A14,[1]LISTADHERENT!A$5:H$60,3,0) -> NGONDIEP CLAUDE | C14: =IF(E14="ECHEC",0,IF(E14="",0,100000)) -> 100000 | D14: =IF(E14="ESPECES",0,0) -> 0 | E14: BANQUE | F14: =TONTDEC!F14 -> 0 | H14: 99500 | I14: 4000 | J14: ESPECES | L14: =TONTDEC!H14+TONTDEC!I14 -> 0 | P14: =IF(Q14=0,0,($C$38-Q14)) -> 0
A15: AS201614 | B15: =VLOOKUP(A15,[1]LISTADHERENT!A$5:H$60,3,0) -> NKEHE DAVID | C15: =IF(E15="ECHEC",0,IF(E15="",0,100000)) -> 100000 | D15: =IF(E15="ESPECES",0,0) -> 0 | E15: BANQUE | F15: =TONTDEC!F15 -> 0 | H15: 100000 | I15: 6000 | J15: ESPECES | L15: =TONTDEC!H15+TONTDEC!I15 -> 0 | P15: =IF(Q15=0,0,($C$38-Q15)) -> 0
A16: AS201629 | B16: =VLOOKUP(A16,[1]LISTADHERENT!A$5:H$60,3,0) -> NKEPSEU DIEUDONNE | C16: =IF(E16="ECHEC",0,IF(E16="",0,100000)) -> 100000 | D16: =IF(E16="ESPECES",0,0) -> 0 | E16: BANQUE | F16: =TONTDEC!F16 -> 0 | L16: =TONTDEC!H16+TONTDEC!I16 -> 0 | P16: =IF(Q16=0,0,($C$38-Q16)) -> 0
A17: AS201636 | B17: =VLOOKUP(A17,[1]LISTADHERENT!A$5:H$60,3,0) -> SIMO FONGANG ERIC | C17: =IF(E17="ECHEC",0,IF(E17="",0,100000)) -> 100000 | D17: =IF(E17="ESPECES",0,0) -> 0 | E17: BANQUE | F17: =TONTDEC!F17 -> 0 | L17: =TONTDEC!H17+TONTDEC!I17 -> 0 | P17: =IF(Q17=0,0,($C$38-Q17)) -> 0
A18: AS201636 | B18: =VLOOKUP(A18,[1]LISTADHERENT!A$5:H$60,3,0) -> SIMO FONGANG ERIC | C18: =IF(E18="ECHEC",0,IF(E18="",0,100000)) -> 100000 | D18: =IF(E18="ESPECES",0,0) -> 0 | E18: BANQUE | F18: =TONTDEC!F18 -> 0 | L18: =TONTDEC!H18+TONTDEC!I18 -> 0 | P18: =IF(Q18=0,0,($C$38-Q18)) -> 0
A19: AS201637 | B19: =VLOOKUP(A19,[1]LISTADHERENT!A$5:H$60,3,0) -> SIME MATHIEU | C19: =IF(E19="ECHEC",0,IF(E19="",0,100000)) -> 100000 | D19: =IF(E19="ESPECES",0,0) -> 0 | E19: BANQUE | F19: =TONTDEC!F19 -> 0 | L19: =TONTDEC!H19+TONTDEC!I19 -> 0 | P19: =IF(Q19=0,0,($C$38-Q19)) -> 0
A20: AS201637 | B20: =VLOOKUP(A20,[1]LISTADHERENT!A$5:H$60,3,0) -> SIME MATHIEU | C20: =IF(E20="ECHEC",0,IF(E20="",0,100000)) -> 100000 | D20: =IF(E20="ESPECES",0,0) -> 0 | E20: BANQUE | F20: =TONTDEC!F20 -> 0 | L20: =TONTDEC!H20+TONTDEC!I20 -> 0 | P20: =IF(Q20=0,0,($C$38-Q20)) -> 0
A21: AS201641 | B21: =VLOOKUP(A21,[1]LISTADHERENT!A$5:H$60,3,0) -> TCHOUAMOU MATHIEU | C21: =IF(E21="ECHEC",0,IF(E21="",0,100000)) -> 100000 | D21: =IF(E21="ESPECES",0,0) -> 0 | E21: BANQUE | F21: =TONTDEC!F21 -> 0 | L21: =TONTDEC!H21+TONTDEC!I21 -> 0 | P21: =IF(Q21=0,0,($C$38-Q21)) -> 0
A22: AS201644 | B22: =VLOOKUP(A22,[1]LISTADHERENT!A$5:H$60,3,0) -> TIEYAM ERNEST | C22: =IF(E22="ECHEC",0,IF(E22="",0,100000)) -> 100000 | D22: =IF(E22="ESPECES",0,0) -> 0 | E22: BANQUE | F22: =TONTDEC!F22 -> 0 | H22: 200000 | I22: 10000 | J22: ESPECES | L22: =TONTDEC!H22+TONTDEC!I22 -> 0 | P22: =IF(Q22=0,0,($C$38-Q22)) -> 0
A23: AS201647 | B23: =VLOOKUP(A23,[1]LISTADHERENT!A$5:H$60,3,0) -> YOUMBI EMMANUEL | C23: =IF(E23="ECHEC",0,IF(E23="",0,100000)) -> 100000 | D23: =IF(E23="ESPECES",0,0) -> 0 | E23: BANQUE | F23: =TONTDEC!F23 -> 0 | L23: =TONTDEC!H23+TONTDEC!I23 -> 0 | P23: =IF(Q23=0,0,($C$38-Q23)) -> 0
A25: TOTAL | C25: =SUM(C6:C24) -> 1800000 | D25: =SUM(D6:D24) -> 0 | F25: =SUM(F6:F24) -> 0 | H25: =SUM(H6:H24) -> 499500 | I25: =SUM(I6:I24) -> 24000 | L25: =SUM(L6:L24) -> 0 | P25: =SUM(P6:P24) -> 1270000 | Q25: =SUM(Q6:Q24) -> 230000
C27: TONTINE | D27: REMBOURSEMENT PETIT LOT | E27: VENTE PETIT LOT | F27: VENTE LOT PRINCIPAL | G27: SOLDE EN CAISSE | M27: TONTINE + REMB + INTERET VENTE | N27: =C32+D32+Q25 -> 2030000
M28: VENDUE | N28: =IF(N27>=2800000,1500000*2,1500000) -> 1500000
B29: ESPECES | C29: =SUMIFS(C6:C24,E6:E24,"ESPECES") -> 0 | D29: =SUMIFS(L6:L24,M6:M24,"ESPECES")+SUMIFS(F6:F24,G6:G24,"ESPECES") -> 0 | E29: =SUMIFS(H6:H24,J6:J24,"ESPECES") -> 499500 | F29: =SUMIFS(P6:P24,N6:N24,"ESPECES") -> 0 | G29: =C29+D29-E29-F29 -> -499500
B30: BANQUE | C30: =SUMIFS(C6:C24,E6:E24,"BANQUE") -> 1800000 | D30: =SUMIFS(L6:L24,M6:M24,"BANQUE")+SUMIFS(F6:F24,G6:G24,"BANQUE") -> 0 | E30: =SUMIFS(H6:H24,J6:J24,"BANQUE") -> 0 | F30: =SUMIFS(P6:P24,N6:N24,"BANQUE") -> 0 | G30: =C30+D30-E30-F30 -> 1800000 | M30: PETIT LOT | N30: =N27-N28 -> 530000
B32: TOTAL | C32: =C29+C30 -> 1800000 | D32: =D29+D30 -> 0 | E32: =E29+E30 -> 499500 | F32: =F29+F30 -> 0 | G32: =G29+G30 -> 1300500 | M32: RELIQUAT | N32: =N30-H25 -> 30500 | O32: =N32+TONTDEC!O32 -> -200000 | P32: CUMUL
M34: ECHEC TONTINE | N34: =COUNTIFS(E6:E24,"ECHEC")*100000 -> 0 | O34: =N34+TONTDEC!O34 -> 0 | P34: CUMUL
B35: INTERET LOT PRINCIPAL | C35: =Q25 -> 230000 | M35: ECHEC REMBOURSEMENT | N35: =SUMIFS(F6:F24,G6:G24,"ECHEC") -> 0 | P35: CUMUL
B36: INTERET PETIT LOT | C36: =+I25 -> 24000
B38: MONTANT TONTINE | C38: 1500000
B39: MONTANT PETIT LOT A VENDRE | C39: =H25 -> 499500

Sheet TONTFEV
A1: ASSOCIATION | B1: ASELBY
A2: ANNEE | B2: 2019/2020
A3: TONTINE | B3: 100000
C4: 43877
A5: MATRICULE | B5: NOM ET PRENOM | C5: MONTANT TONTINE | D5: PENALITE | E5: MODE VERSEMENT TONTINE | F5: REPORT ECHEC PETIT LOT | G5: MODE VERSEMENT VENTE PETIT LOT | H5: VENTE PETIT LOT | I5: INTERET PETIT LOT | J5: MODE VERSEMENT VENTE PETIT LOT | K5: NUMERO CHEQUE | L5: REMBOURSEMENT | M5: MODE VERSEMENT REMBOURSEMENT | N5: MODE VERSEMENT TONTINE PRINCIPAL | O5: NUMERO CHEQUE | P5: MONTANT TONTINE LOT PRINCIPAL | Q5: INTERET LOT PRINCIPAL | R5: DATE VENTE
A6: AS201608 | B6: =VLOOKUP(A6,[1]LISTADHERENT!A$5:H$60,3,0) -> DJUOMBESSY ANTOINE | C6: =IF(E6="ECHEC",0,IF(E6="",0,100000)) -> 100000 | D6: =IF(E6="ESPECES",0,0) -> 0 | E6: BANQUE | F6: =TONTJANV!F6 -> 0 | L6: =TONTJANV!H6+TONTJANV!I6 -> 0 | P6: =IF(Q6=0,0,($C$38-Q6)) -> 0
A7: AS201613 | B7: =VLOOKUP(A7,[1]LISTADHERENT!A$5:H$60,3,0) -> HOTCHO BENJAMIN | C7: =IF(E7="ECHEC",0,IF(E7="",0,100000)) -> 100000 | D7: =IF(E7="ESPECES",0,0) -> 0 | E7: BANQUE | F7: =TONTJANV!F7 -> 0 | L7: =TONTJANV!H7+TONTJANV!I7 -> 0 | P7: =IF(Q7=0,0,($C$38-Q7)) -> 0
A8: AS201619 | B8: =VLOOKUP(A8,[1]LISTADHERENT!A$5:H$60,3,0) -> KOUATCHO MESSACK | C8: =IF(E8="ECHEC",0,IF(E8="",0,100000)) -> 100000 | D8: =IF(E8="ESPECES",0,0) -> 0 | E8: BANQUE | F8: =TONTJANV!F8 -> 0 | H8: 100000 | I8: 3000 | J8: BANQUE | L8: =TONTJANV!H8+TONTJANV!I8 -> 104000 | M8: ESPECES | P8: =IF(Q8=0,0,($C$38-Q8)) -> 0
A9: AS201617 | B9: =VLOOKUP(A9,[1]LISTADHERENT!A$5:H$60,3,0) -> KOUAMOU MOISE | C9: =IF(E9="ECHEC",0,IF(E9="",0,100000)) -> 100000 | D9: =IF(E9="ESPECES",0,0) -> 0 | E9: BANQUE | F9: =TONTJANV!F9 -> 0 | L9: =TONTJANV!H9+TONTJANV!I9 -> 0 | P9: =IF(Q9=0,0,($C$38-Q9)) -> 0
A10: AS201649 | B10: =VLOOKUP(A10,[1]LISTADHERENT!A$5:H$60,3,0) -> MBOGNING TUGMA GUY | C10: =IF(E10="ECHEC",0,IF(E10="",0,100000)) -> 100000 | D10: =IF(E10="ESPECES",0,0) -> 0 | E10: BANQUE | F10: =TONTJANV!F10 -> 0 | H10: 200000 | I10: 5000 | J10: ESPECES | L10: =TONTJANV!H10+TONTJANV!I10 -> 0 | P10: =IF(Q10=0,0,($C$38-Q10)) -> 0
A11: AS201649 | B11: =VLOOKUP(A11,[1]LISTADHERENT!A$5:H$60,3,0) -> MBOGNING TUGMA GUY | C11: =IF(E11="ECHEC",0,IF(E11="",0,100000)) -> 100000 | D11: =IF(E11="ESPECES",0,0) -> 0 | E11: BANQUE | F11: =TONTJANV!F11 -> 0 | L11: =TONTJANV!H11+TONTJANV!I11 -> 0 | P11: =IF(Q11=0,0,($C$38-Q11)) -> 0
A12: AS201639 | B12: =VLOOKUP(A12,[1]LISTADHERENT!A$5:H$60,3,0) -> NANGUEN MARTIN | C12: =IF(E12="ECHEC",0,IF(E12="",0,100000)) -> 100000 | D12: =IF(E12="ESPECES",0,0) -> 0 | E12: BANQUE | F12: =TONTJANV!F12 -> 0 | L12: =TONTJANV!H12+TONTJANV!I12 -> 0 | P12: =IF(Q12=0,0,($C$38-Q12)) -> 0
A13: AS201622 | B13: =VLOOKUP(A13,[1]LISTADHERENT!A$5:H$60,3,0) -> NDJOMO ETIENNE | C13: =IF(E13="ECHEC",0,IF(E13="",0,100000)) -> 100000 | D13: =IF(E13="ESPECES",0,0) -> 0 | E13: BANQUE | F13: =TONTJANV!F13 -> 0 | H13: 100000 | I13: 3000 | J13: BANQUE | L13: =TONTJANV!H13+TONTJANV!I13 -> 0 | P13: =IF(Q13=0,0,($C$38-Q13)) -> 0
A14: AS201624 | B14: =VLOOKUP(A14,[1]LISTADHERENT!A$5:H$60,3,0) -> NGONDIEP CLAUDE | C14: =IF(E14="ECHEC",0,IF(E14="",0,100000)) -> 100000 | D14: =IF(E14="ESPECES",0,0) -> 0 | E14: BANQUE | F14: =TONTJANV!F14 -> 0 | L14: =TONTJANV!H14+TONTJANV!I14 -> 103500 | M14: ESPECES | P14: =IF(Q14=0,0,($C$38-Q14)) -> 0
A15: AS201614 | B15: =VLOOKUP(A15,[1]LISTADHERENT!A$5:H$60,3,0) -> NKEHE DAVID | C15: =IF(E15="ECHEC",0,IF(E15="",0,100000)) -> 100000 | D15: =IF(E15="ESPECES",0,0) -> 0 | E15: ESPECES | F15: =TONTJANV!F15 -> 0 | H15: 213500 | I15: 4000 | J15: ESPECES | L15: =TONTJANV!H15+TONTJANV!I15 -> 106000 | M15: ESPECES | P15: =IF(Q15=0,0,($C$38-Q15)) -> 0
A16: AS201629 | B16: =VLOOKUP(A16,[1]LISTADHERENT!A$5:H$60,3,0) -> NKEPSEU DIEUDONNE | C16: =IF(E16="ECHEC",0,IF(E16="",0,100000)) -> 100000 | D16: =IF(E16="ESPECES",0,0) -> 0 | E16: BANQUE | F16: =TONTJANV!F16 -> 0 | H16: 100000 | I16: 2000 | J16: BANQUE | L16: =TONTJANV!H16+TONTJANV!I16 -> 0 | N16: BANQUE | P16: =IF(Q16=0,0,($C$38-Q16)) -> 1400000 | Q16: 100000
A17: AS201636 | B17: =VLOOKUP(A17,[1]LISTADHERENT!A$5:H$60,3,0) -> SIMO FONGANG ERIC | C17: =IF(E17="ECHEC",0,IF(E17="",0,100000)) -> 100000 | D17: =IF(E17="ESPECES",0,0) -> 0 | E17: BANQUE | F17: =TONTJANV!F17 -> 0 | L17: =TONTJANV!H17+TONTJANV!I17 -> 0 | P17: =IF(Q17=0,0,($C$38-Q17)) -> 0
A18: AS201636 | B18: =VLOOKUP(A18,[1]LISTADHERENT!A$5:H$60,3,0) -> SIMO FONGANG ERIC | C18: =IF(E18="ECHEC",0,IF(E18="",0,100000)) -> 100000 | D18: =IF(E18="ESPECES",0,0) -> 0 | E18: BANQUE | F18: =TONTJANV!F18 -> 0 | L18: =TONTJANV!H18+TONTJANV!I18 -> 0 | P18: =IF(Q18=0,0,($C$38-Q18)) -> 0
A19: AS201637 | B19: =VLOOKUP(A19,[1]LISTADHERENT!A$5:H$60,3,0) -> SIME MATHIEU | C19: =IF(E19="ECHEC",0,IF(E19="",0,100000)) -> 100000 | D19: =IF(E19="ESPECES",0,0) -> 0 | E19: BANQUE | F19: =TONTJANV!F19 -> 0 | L19: =TONTJANV!H19+TONTJANV!I19 -> 0 | P19: =IF(Q19=0,0,($C$38-Q19)) -> 0
A20: AS201637 | B20: =VLOOKUP(A20,[1]LISTADHERENT!A$5:H$60,3,0) -> SIME MATHIEU | C20: =IF(E20="ECHEC",0,IF(E20="",0,100000)) -> 100000 | D20: =IF(E20="ESPECES",0,0) -> 0 | E20: BANQUE | F20: =TONTJANV!F20 -> 0 | L20: =TONTJANV!H20+TONTJANV!I20 -> 0 | P20: =IF(Q20=0,0,($C$38-Q20)) -> 0
A21: AS201641 | B21: =VLOOKUP(A21,[1]LISTADHERENT!A$5:H$60,3,0) -> TCHOUAMOU MATHIEU | C21: =IF(E21="ECHEC",0,IF(E21="",0,100000)) -> 100000 | D21: =IF(E21="ESPECES",0,0) -> 0 | E21: BANQUE | F21: =TONTJANV!F21 -> 0 | L21: =TONTJANV!H21+TONTJANV!I21 -> 0 | P21: =IF(Q21=0,0,($C$38-Q21)) -> 0
A22: AS201644 | B22: =VLOOKUP(A22,[1]LISTADHERENT!A$5:H$60,3,0) -> TIEYAM ERNEST | C22: =IF(E22="ECHEC",0,IF(E22="",0,100000)) -> 100000 | D22: =IF(E22="ESPECES",0,0) -> 0 | E22: BANQUE | F22: 230000 | G22: ECHEC | L22: =TONTJANV!H22+TONTJANV!I22 -> 210000 | M22: ECHEC | P22: =IF(Q22=0,0,($C$38-Q22)) -> 0
A23: AS201647 | B23: =VLOOKUP(A23,[1]LISTADHERENT!A$5:H$60,3,0) -> YOUMBI EMMANUEL | C23: =IF(E23="ECHEC",0,IF(E23="",0,100000)) -> 100000 | D23: =IF(E23="ESPECES",0,0) -> 0 | E23: BANQUE | L23: =TONTJANV!H23+TONTJANV!I23 -> 0 | P23: =IF(Q23=0,0,($C$38-Q23)) -> 0
A25: TOTAL | C25: =SUM(C6:C24) -> 1800000 | D25: =SUM(D6:D24) -> 0 | F25: =SUM(F6:F24) -> 230000 | H25: =SUM(H6:H24) -> 713500 | I25: =SUM(I6:I24) -> 17000 | L25: =SUM(L6:L24) -> 523500 | P25: =SUM(P6:P24) -> 1400000 | Q25: =SUM(Q6:Q24) -> 100000
C27: TONTINE | D27: REMBOURSEMENT PETIT LOT | E27: VENTE PETIT LOT | F27: VENTE LOT PRINCIPAL | G27: SOLDE EN CAISSE | M27: TONTINE + REMB + INTERET VENTE | N27: =C32+D32+Q25 -> 2213500
M28: VENDUE | N28: =IF(N27>=2800000,1500000*2,1500000) -> 1500000
B29: ESPECES | C29: =SUMIFS(C6:C24,E6:E24,"ESPECES") -> 100000 | D29: =SUMIFS(L6:L24,M6:M24,"ESPECES")+SUMIFS(F6:F24,G6:G24,"ESPECES") -> 313500 | E29: =SUMIFS(H6:H24,J6:J24,"ESPECES") -> 413500 | F29: =SUMIFS(P6:P24,N6:N24,"ESPECES") -> 0 | G29: =C29+D29-E29-F29 -> 0
B30: BANQUE | C30: =SUMIFS(C6:C24,E6:E24,"BANQUE") -> 1700000 | D30: =SUMIFS(L6:L24,M6:M24,"BANQUE")+SUMIFS(F6:F24,G6:G24,"BANQUE") -> 0 | E30: =SUMIFS(H6:H24,J6:J24,"BANQUE") -> 300000 | F30: =SUMIFS(P6:P24,N6:N24,"BANQUE") -> 1400000 | G30: =C30+D30-E30-F30 -> 0 | M30: PETIT LOT | N30: =N27-N28 -> 713500
B32: TOTAL | C32: =C29+C30 -> 1800000 | D32: =D29+D30 -> 313500 | E32: =E29+E30 -> 713500 | F32: =F29+F30 -> 1400000 | G32: =G29+G30 -> 0 | M32: RELIQUAT | N32: =N30-H25 -> 0 | O32: =N32+TONTJANV!O32 -> -200000 | P32: CUMUL
M34: ECHEC TONTINE | N34: =COUNTIFS(E6:E24,"ECHEC")*100000 -> 0 | O34: =N34+TONTJANV!O34 -> 0 | P34: CUMUL
B35: INTERET LOT PRINCIPAL | C35: =Q25 -> 100000 | M35: ECHEC REMBOURSEMENT | N35: =SUMIFS(F6:F24,G6:G24,"ECHEC") -> 230000 | P35: CUMUL
B36: INTERET PETIT LOT | C36: =+I25 -> 17000
B38: MONTANT TONTINE | C38: 1500000
B39: MONTANT PETIT LOT A VENDRE | C39: =H25 -> 713500

Sheet TONTMARS
A1: ASSOCIATION | B1: ASELBY
A2: ANNEE | B2: 2019/2020
A3: TONTINE | B3: 100000
C4: 43905
A5: MATRICULE | B5: NOM ET PRENOM | C5: MONTANT TONTINE | D5: PENALITE | E5: MODE VERSEMENT TONTINE | F5: REPORT ECHEC PETIT LOT | G5: MODE VERSEMENT VENTE PETIT LOT | H5: VENTE PETIT LOT | I5: INTERET PETIT LOT | J5: MODE VERSEMENT VENTE PETIT LOT | K5: NUMERO CHEQUE | L5: REMBOURSEMENT | M5: MODE VERSEMENT REMBOURSEMENT | N5: MODE VERSEMENT TONTINE PRINCIPAL | O5: NUMERO CHEQUE | P5: MONTANT TONTINE LOT PRINCIPAL | Q5: INTERET LOT PRINCIPAL | R5: DATE VENTE
A6: AS201608 | B6: =VLOOKUP(A6,[1]LISTADHERENT!A$5:H$60,3,0) -> DJUOMBESSY ANTOINE | C6: =IF(E6="ECHEC",0,IF(E6="",0,100000)) -> 100000 | D6: =IF(E6="ESPECES",0,0) -> 0 | E6: BANQUE | F6: =TONTFEV!F6 -> 0 | L6: =TONTFEV!H6+TONTFEV!I6 -> 0 | P6: =IF(Q6=0,0,($C$38-Q6)) -> 0
A7: AS201613 | B7: =VLOOKUP(A7,[1]LISTADHERENT!A$5:H$60,3,0) -> HOTCHO BENJAMIN | C7: =IF(E7="ECHEC",0,IF(E7="",0,100000)) -> 100000 | D7: =IF(E7="ESPECES",0,0) -> 0 | E7: BANQUE | F7: =TONTFEV!F7 -> 0 | L7: =TONTFEV!H7+TONTFEV!I7 -> 0 | P7: =IF(Q7=0,0,($C$38-Q7)) -> 0
A8: AS201619 | B8: =VLOOKUP(A8,[1]LISTADHERENT!A$5:H$60,3,0) -> KOUATCHO MESSACK | C8: =IF(E8="ECHEC",0,IF(E8="",0,100000)) -> 100000 | D8: =IF(E8="ESPECES",0,0) -> 0 | E8: BANQUE | F8: =TONTFEV!F8 -> 0 | H8: 200000 | I8: 2500 | J8: BANQUE | L8: =TONTFEV!H8+TONTFEV!I8 -> 103000 | M8: BANQUE | P8: =IF(Q8=0,0,($C$38-Q8)) -> 0
A9: AS201617 | B9: =VLOOKUP(A9,[1]LISTADHERENT!A$5:H$60,3,0) -> KOUAMOU MOISE | C9: =IF(E9="ECHEC",0,IF(E9="",0,100000)) -> 100000 | D9: =IF(E9="ESPECES",0,0) -> 0 | E9: BANQUE | F9: =TONTFEV!F9 -> 0 | L9: =TONTFEV!H9+TONTFEV!I9 -> 0 | P9: =IF(Q9=0,0,($C$38-Q9)) -> 1365000 | Q9: 135000
A10: AS201649 | B10: =VLOOKUP(A10,[1]LISTADHERENT!A$5:H$60,3,0) -> MBOGNING TUGMA GUY | C10: =IF(E10="ECHEC",0,IF(E10="",0,100000)) -> 100000 | D10: =IF(E10="ESPECES",0,0) -> 0 | E10: BANQUE | F10: =TONTFEV!F10 -> 0 | H10: 100000 | I10: 1000 | J10: BANQUE | L10: =TONTFEV!H10+TONTFEV!I10 -> 205000 | M10: BANQUE | P10: =IF(Q10=0,0,($C$38-Q10)) -> 0
A11: AS201649 | B11: =VLOOKUP(A11,[1]LISTADHERENT!A$5:H$60,3,0) -> MBOGNING TUGMA GUY | C11: =IF(E11="ECHEC",0,IF(E11="",0,100000)) -> 100000 | D11: =IF(E11="ESPECES",0,0) -> 0 | E11: BANQUE | F11: =TONTFEV!F11 -> 0 | L11: =TONTFEV!H11+TONTFEV!I11 -> 0 | P11: =IF(Q11=0,0,($C$38-Q11)) -> 0
A12: AS201639 | B12: =VLOOKUP(A12,[1]LISTADHERENT!A$5:H$60,3,0) -> NANGUEN MARTIN | C12: =IF(E12="ECHEC",0,IF(E12="",0,100000)) -> 100000 | D12: =IF(E12="ESPECES",0,0) -> 0 | E12: BANQUE | F12: =TONTFEV!F12 -> 0 | L12: =TONTFEV!H12+TONTFEV!I12 -> 0 | P12: =IF(Q12=0,0,($C$38-Q12)) -> 0
A13: AS201622 | B13: =VLOOKUP(A13,[1]LISTADHERENT!A$5:H$60,3,0) -> NDJOMO ETIENNE | C13: =IF(E13="ECHEC",0,IF(E13="",0,100000)) -> 100000 | D13: =IF(E13="ESPECES",0,0) -> 0 | E13: BANQUE | F13: =TONTFEV!F13 -> 0 | H13: 100000 | I13: 1500 | J13: BANQUE | L13: =TONTFEV!H13+TONTFEV!I13 -> 103000 | M13: BANQUE | P13: =IF(Q13=0,0,($C$38-Q13)) -> 0
A14: AS201624 | B14: =VLOOKUP(A14,[1]LISTADHERENT!A$5:H$60,3,0) -> NGONDIEP CLAUDE | C14: =IF(E14="ECHEC",0,IF(E14="",0,100000)) -> 100000 | D14: =IF(E14="ESPECES",0,0) -> 0 | E14: BANQUE | F14: =TONTFEV!F14 -> 0 | L14: =TONTFEV!H14+TONTFEV!I14 -> 0 | P14: =IF(Q14=0,0,($C$38-Q14)) -> 0
A15: AS201614 | B15: =VLOOKUP(A15,[1]LISTADHERENT!A$5:H$60,3,0) -> NKEHE DAVID | C15: =IF(E15="ECHEC",0,IF(E15="",0,100000)) -> 100000 | D15: =IF(E15="ESPECES",0,0) -> 0 | E15: BANQUE | F15: 225500 | G15: ECHEC | H15: 217500 | I15: 8000 | J15: ECHEC | L15: =TONTFEV!H15+TONTFEV!I15 -> 217500 | M15: ECHEC | P15: =IF(Q15=0,0,($C$38-Q15)) -> 0
A16: AS201629 | B16: =VLOOKUP(A16,[1]LISTADHERENT!A$5:H$60,3,0) -> NKEPSEU DIEUDONNE | C16: =IF(E16="ECHEC",0,IF(E16="",0,100000)) -> 100000 | D16: =IF(E16="ESPECES",0,0) -> 0 | E16: BANQUE | F16: =TONTFEV!F16 -> 0 | H16: 200000 | I16: 3000 | J16: BANQUE | L16: =TONTFEV!H16+TONTFEV!I16 -> 102000 | M16: BANQUE | P16: =IF(Q16=0,0,($C$38-Q16)) -> 0
A17: AS201636 | B17: =VLOOKUP(A17,[1]LISTADHERENT!A$5:H$60,3,0) -> SIMO FONGANG ERIC | C17: =IF(E17="ECHEC",0,IF(E17="",0,100000)) -> 100000 | D17: =IF(E17="ESPECES",0,0) -> 0 | E17: ESPECES | F17: =TONTFEV!F17 -> 0 | H17: 200000 | I17: 2500 | J17: BANQUE | L17: =TONTFEV!H17+TONTFEV!I17 -> 0 | P17: =IF(Q17=0,0,($C$38-Q17)) -> 0
A18: AS201636 | B18: =VLOOKUP(A18,[1]LISTADHERENT!A$5:H$60,3,0) -> SIMO FONGANG ERIC | C18: =IF(E18="ECHEC",0,IF(E18="",0,100000)) -> 100000 | D18: =IF(E18="ESPECES",0,0) -> 0 | E18: ESPECES | F18: =TONTFEV!F18 -> 0 | L18: =TONTFEV!H18+TONTFEV!I18 -> 0 | P18: =IF(Q18=0,0,($C$38-Q18)) -> 0
A19: AS201637 | B19: =VLOOKUP(A19,[1]LISTADHERENT!A$5:H$60,3,0) -> SIME MATHIEU | C19: =IF(E19="ECHEC",0,IF(E19="",0,100000)) -> 100000 | D19: =IF(E19="ESPECES",0,0) -> 0 | E19: BANQUE | F19: =TONTFEV!F19 -> 0 | L19: =TONTFEV!H19+TONTFEV!I19 -> 0 | P19: =IF(Q19=0,0,($C$38-Q19)) -> 0
A20: AS201637 | B20: =VLOOKUP(A20,[1]LISTADHERENT!A$5:H$60,3,0) -> SIME MATHIEU | C20: =IF(E20="ECHEC",0,IF(E20="",0,100000)) -> 100000 | D20: =IF(E20="ESPECES",0,0) -> 0 | E20: BANQUE | F20: =TONTFEV!F20 -> 0 | L20: =TONTFEV!H20+TONTFEV!I20 -> 0 | P20: =IF(Q20=0,0,($C$38-Q20)) -> 0
A21: AS201641 | B21: =VLOOKUP(A21,[1]LISTADHERENT!A$5:H$60,3,0) -> TCHOUAMOU MATHIEU | C21: =IF(E21="ECHEC",0,IF(E21="",0,100000)) -> 100000 | D21: =IF(E21="ESPECES",0,0) -> 0 | E21: BANQUE | F21: =TONTFEV!F21 -> 0 | H21: 200000 | I21: 2000 | J21: BANQUE | L21: =TONTFEV!H21+TONTFEV!I21 -> 0 | P21: =IF(Q21=0,0,($C$38-Q21)) -> 0
A22: AS201644 | B22: =VLOOKUP(A22,[1]LISTADHERENT!A$5:H$60,3,0) -> TIEYAM ERNEST | C22: =IF(E22="ECHEC",0,IF(E22="",0,100000)) -> 100000 | D22: =IF(E22="ESPECES",0,0) -> 0 | E22: BANQUE | F22: =TONTFEV!F22 -> 230000 | G22: ESPECES | H22: 200000 | I22: 2000 | J22: BANQUE | L22: =TONTFEV!H22+TONTFEV!I22 -> 0 | M22: BANQUE | P22: =IF(Q22=0,0,($C$38-Q22)) -> 0
A23: AS201647 | B23: =VLOOKUP(A23,[1]LISTADHERENT!A$5:H$60,3,0) -> YOUMBI EMMANUEL | C23: =IF(E23="ECHEC",0,IF(E23="",0,100000)) -> 100000 | D23: =IF(E23="ESPECES",0,0) -> 0 | E23: BANQUE | F23: =TONTFEV!F23 -> 0 | L23: =TONTFEV!H23+TONTFEV!I23 -> 0 | P23: =IF(Q23=0,0,($C$38-Q23)) -> 0
A25: TOTAL | C25: =SUM(C6:C24) -> 1800000 | D25: =SUM(D6:D24) -> 0 | F25: =SUM(F6:F24) -> 455500 | H25: =SUM(H6:H24) -> 1417500 | I25: =SUM(I6:I24) -> 22500 | L25: =SUM(L6:L24) -> 730500 | P25: =SUM(P6:P24) -> 1365000 | Q25: =SUM(Q6:Q24) -> 135000
C27: TONTINE | D27: REMBOURSEMENT PETIT LOT | E27: VENTE PETIT LOT | F27: VENTE LOT PRINCIPAL | G27: SOLDE EN CAISSE | M27: TONTINE + REMB + INTERET VENTE | N27: =C32+D32+Q25 -> 2678000
M28: VENDUE | N28: =IF(N27>=2800000,1500000*2,1500000) -> 1500000
B29: ESPECES | C29: =SUMIFS(C6:C24,E6:E24,"ESPECES") -> 200000 | D29: =SUMIFS(L6:L24,M6:M24,"ESPECES")+SUMIFS(F6:F24,G6:G24,"ESPECES") -> 230000 | E29: =SUMIFS(H6:H24,J6:J24,"ESPECES") -> 0 | F29: =SUMIFS(P6:P24,N6:N24,"ESPECES") -> 0 | G29: =C29+D29-E29-F29 -> 430000
B30: BANQUE | C30: =SUMIFS(C6:C24,E6:E24,"BANQUE") -> 1600000 | D30: =SUMIFS(L6:L24,M6:M24,"BANQUE")+SUMIFS(F6:F24,G6:G24,"BANQUE") -> 513000 | E30: =SUMIFS(H6:H24,J6:J24,"BANQUE") -> 1200000 | F30: =SUMIFS(P6:P24,N6:N24,"BANQUE") -> 0 | G30: =C30+D30-E30-F30 -> 913000 | M30: PETIT LOT | N30: =N27-N28 -> 1178000
B32: TOTAL | C32: =C29+C30 -> 1800000 | D32: =D29+D30 -> 743000 | E32: =E29+E30 -> 1200000 | F32: =F29+F30 -> 0 | G32: =G29+G30 -> 1343000 | M32: RELIQUAT | N32: =N30-H25 -> -239500 | O32: =N32+TONTFEV!O32 -> -439500 | P32: CUMUL
M34: ECHEC TONTINE | N34: =COUNTIFS(E6:E24,"ECHEC")*100000 -> 0 | O34: =N34+TONTFEV!O34 -> 0 | P34: CUMUL
B35: INTERET LOT PRINCIPAL | C35: =Q25 -> 135000 | M35: ECHEC REMBOURSEMENT | N35: =SUMIFS(F6:F24,G6:G24,"ECHEC") -> 225500 | P35: CUMUL
B36: INTERET PETIT LOT | C36: =+I25 -> 22500
B38: MONTANT TONTINE | C38: 1500000
B39: MONTANT PETIT LOT A VENDRE | C39: =H25 -> 1417500

Sheet TONTAVRIL
A1: ASSOCIATION | B1: ASELBY
A2: ANNEE | B2: 2019/2020
A3: TONTINE | B3: 100000
C4: 43940
A5: MATRICULE | B5: NOM ET PRENOM | C5: MONTANT TONTINE | D5: PENALITE | E5: MODE VERSEMENT TONTINE | F5: REPORT ECHEC PETIT LOT | G5: MODE VERSEMENT VENTE PETIT LOT | H5: VENTE PETIT LOT | I5: INTERET PETIT LOT | J5: MODE VERSEMENT VENTE PETIT LOT | K5: NUMERO CHEQUE | L5: REMBOURSEMENT | M5: MODE VERSEMENT REMBOURSEMENT | N5: MODE VERSEMENT TONTINE PRINCIPAL | O5: NUMERO CHEQUE | P5: MONTANT TONTINE LOT PRINCIPAL | Q5: INTERET LOT PRINCIPAL | R5: DATE VENTE
A6: AS201608 | B6: =VLOOKUP(A6,[1]LISTADHERENT!A$5:H$60,3,0) -> DJUOMBESSY ANTOINE | C6: =IF(E6="ECHEC",0,IF(E6="",0,100000)) -> 100000 | D6: =IF(E6="ESPECES",0,0) -> 0 | E6: BANQUE | F6: =TONTMARS!F6 -> 0 | L6: =TONTMARS!H6+TONTMARS!I6 -> 0 | P6: =IF(Q6=0,0,($C$38-Q6)) -> 0
A7: AS201613 | B7: =VLOOKUP(A7,[1]LISTADHERENT!A$5:H$60,3,0) -> HOTCHO BENJAMIN | C7: =IF(E7="ECHEC",0,IF(E7="",0,100000)) -> 100000 | D7: =IF(E7="ESPECES",0,0) -> 0 | E7: BANQUE | F7: =TONTMARS!F7 -> 0 | L7: =TONTMARS!H7+TONTMARS!I7 -> 0 | N7: BANQUE | P7: =IF(Q7=0,0,($C$38-Q7)) -> 1400000 | Q7: 100000
A8: AS201619 | B8: =VLOOKUP(A8,[1]LISTADHERENT!A$5:H$60,3,0) -> KOUATCHO MESSACK | C8: =IF(E8="ECHEC",0,IF(E8="",0,100000)) -> 100000 | D8: =IF(E8="ESPECES",0,0) -> 0 | E8: BANQUE | F8: =TONTMARS!F8 -> 0 | L8: =TONTMARS!H8+TONTMARS!I8 -> 202500 | M8: BANQUE | P8: =IF(Q8=0,0,($C$38-Q8)) -> 0
A9: AS201617 | B9: =VLOOKUP(A9,[1]LISTADHERENT!A$5:H$60,3,0) -> KOUAMOU MOISE | C9: =IF(E9="ECHEC",0,IF(E9="",0,100000)) -> 100000 | D9: =IF(E9="ESPECES",0,0) -> 0 | E9: BANQUE | F9: =TONTMARS!F9 -> 0 | L9: =TONTMARS!H9+TONTMARS!I9 -> 0 | P9: =IF(Q9=0,0,($C$38-Q9)) -> 0
A10: AS201649 | B10: =VLOOKUP(A10,[1]LISTADHERENT!A$5:H$60,3,0) -> MBOGNING TUGMA GUY | C10: =IF(E10="ECHEC",0,IF(E10="",0,100000)) -> 100000 | D10: =IF(E10="ESPECES",0,0) -> 0 | E10: BANQUE | F10: =TONTMARS!F10 -> 0 | L10: =TONTMARS!H10+TONTMARS!I10 -> 101000 | M10: BANQUE | P10: =IF(Q10=0,0,($C$38-Q10)) -> 0
A11: AS201649 | B11: =VLOOKUP(A11,[1]LISTADHERENT!A$5:H$60,3,0) -> MBOGNING TUGMA GUY | C11: =IF(E11="ECHEC",0,IF(E11="",0,100000)) -> 100000 | D11: =IF(E11="ESPECES",0,0) -> 0 | E11: BANQUE | F11: =TONTMARS!F11 -> 0 | L11: =TONTMARS!H11+TONTMARS!I11 -> 0 | P11: =IF(Q11=0,0,($C$38-Q11)) -> 0
A12: AS201639 | B12: =VLOOKUP(A12,[1]LISTADHERENT!A$5:H$60,3,0) -> NANGUEN MARTIN | C12: =IF(E12="ECHEC",0,IF(E12="",0,100000)) -> 100000 | D12: =IF(E12="ESPECES",0,0) -> 0 | E12: BANQUE | F12: =TONTMARS!F12 -> 0 | L12: =TONTMARS!H12+TONTMARS!I12 -> 0 | P12: =IF(Q12=0,0,($C$38-Q12)) -> 0
A13: AS201622 | B13: =VLOOKUP(A13,[1]LISTADHERENT!A$5:H$60,3,0) -> NDJOMO ETIENNE | C13: =IF(E13="ECHEC",0,IF(E13="",0,100000)) -> 100000 | D13: =IF(E13="ESPECES",0,0) -> 0 | E13: BANQUE | F13: =TONTMARS!F13 -> 0 | L13: =TONTMARS!H13+TONTMARS!I13 -> 101500 | M13: BANQUE | N13: BANQUE | P13: =IF(Q13=0,0,($C$38-Q13)) -> 1400000 | Q13: 100000
A14: AS201624 | B14: =VLOOKUP(A14,[1]LISTADHERENT!A$5:H$60,3,0) -> NGONDIEP CLAUDE | C14: =IF(E14="ECHEC",0,IF(E14="",0,100000)) -> 100000 | D14: =IF(E14="ESPECES",0,0) -> 0 | E14: BANQUE | F14: =TONTMARS!F14 -> 0 | L14: =TONTMARS!H14+TONTMARS!I14 -> 0 | P14: =IF(Q14=0,0,($C$38-Q14)) -> 0
A15: AS201614 | B15: =VLOOKUP(A15,[1]LISTADHERENT!A$5:H$60,3,0) -> NKEHE DAVID | C15: =IF(E15="ECHEC",0,IF(E15="",0,100000)) -> 100000 | D15: =IF(E15="ESPECES",0,0) -> 0 | E15: BANQUE | F15: =TONTMARS!F15 -> 225500 | G15: ECHEC | L15: =TONTMARS!H15+TONTMARS!I15 -> 225500 | P15: =IF(Q15=0,0,($C$38-Q15)) -> 0
A16: AS201629 | B16: =VLOOKUP(A16,[1]LISTADHERENT!A$5:H$60,3,0) -> NKEPSEU DIEUDONNE | C16: =IF(E16="ECHEC",0,IF(E16="",0,100000)) -> 100000 | D16: =IF(E16="ESPECES",0,0) -> 0 | E16: BANQUE | F16: =TONTMARS!F16 -> 0 | L16: =TONTMARS!H16+TONTMARS!I16 -> 203000 | M16: BANQUE | P16: =IF(Q16=0,0,($C$38-Q16)) -> 0
A17: AS201636 | B17: =VLOOKUP(A17,[1]LISTADHERENT!A$5:H$60,3,0) -> SIMO FONGANG ERIC | C17: =IF(E17="ECHEC",0,IF(E17="",0,100000)) -> 100000 | D17: =IF(E17="ESPECES",0,0) -> 0 | E17: ESPECES | F17: =TONTMARS!F17 -> 0 | L17: =TONTMARS!H17+TONTMARS!I17-22000 -> 180500 | M17: ESPECES | P17: =IF(Q17=0,0,($C$38-Q17)) -> 0
A18: AS201636 | B18: =VLOOKUP(A18,[1]LISTADHERENT!A$5:H$60,3,0) -> SIMO FONGANG ERIC | C18: =IF(E18="ECHEC",0,IF(E18="",0,100000)) -> 100000 | D18: =IF(E18="ESPECES",0,0) -> 0 | E18: ESPECES | F18: =TONTMARS!F18 -> 0 | L18: =TONTMARS!H18+TONTMARS!I18 -> 0 | P18: =IF(Q18=0,0,($C$38-Q18)) -> 0
A19: AS201637 | B19: =VLOOKUP(A19,[1]LISTADHERENT!A$5:H$60,3,0) -> SIME MATHIEU | C19: =IF(E19="ECHEC",0,IF(E19="",0,100000)) -> 100000 | D19: =IF(E19="ESPECES",0,0) -> 0 | E19: BANQUE | F19: =TONTMARS!F19 -> 0 | L19: =TONTMARS!H19+TONTMARS!I19 -> 0 | P19: =IF(Q19=0,0,($C$38-Q19)) -> 0
A20: AS201637 | B20: =VLOOKUP(A20,[1]LISTADHERENT!A$5:H$60,3,0) -> SIME MATHIEU | C20: =IF(E20="ECHEC",0,IF(E20="",0,100000)) -> 100000 | D20: =IF(E20="ESPECES",0,0) -> 0 | E20: BANQUE | F20: =TONTMARS!F20 -> 0 | L20: =TONTMARS!H20+TONTMARS!I20 -> 0 | P20: =IF(Q20=0,0,($C$38-Q20)) -> 0
A21: AS201641 | B21: =VLOOKUP(A21,[1]LISTADHERENT!A$5:H$60,3,0) -> TCHOUAMOU MATHIEU | C21: =IF(E21="ECHEC",0,IF(E21="",0,100000)) -> 100000 | D21: =IF(E21="ESPECES",0,0) -> 0 | E21: BANQUE | F21: =TONTMARS!F21 -> 0 | L21: =TONTMARS!H21+TONTMARS!I21 -> 202000 | M21: BANQUE | P21: =IF(Q21=0,0,($C$38-Q21)) -> 0
A22: AS201644 | B22: =VLOOKUP(A22,[1]LISTADHERENT!A$5:H$60,3,0) -> TIEYAM ERNEST | C22: =IF(E22="ECHEC",0,IF(E22="",0,100000)) -> 100000 | D22: =IF(E22="ESPECES",0,0) -> 0 | E22: BANQUE | F22: 210000 | G22: ECHEC | L22: =TONTMARS!H22+TONTMARS!I22 -> 202000 | P22: =IF(Q22=0,0,($C$38-Q22)) -> 0
A23: AS201647 | B23: =VLOOKUP(A23,[1]LISTADHERENT!A$5:H$60,3,0) -> YOUMBI EMMANUEL | C23: =IF(E23="ECHEC",0,IF(E23="",0,100000)) -> 100000 | D23: =IF(E23="ESPECES",0,0) -> 0 | E23: BANQUE | F23: 0 | L23: =TONTFEV!H23+TONTFEV!I23 -> 0 | P23: =IF(Q23=0,0,($C$38-Q23)) -> 0
A25: TOTAL | C25: =SUM(C6:C24) -> 1800000 | D25: =SUM(D6:D24) -> 0 | F25: =SUM(F6:F24) -> 435500 | H25: =SUM(H6:H24) -> 0 | I25: =SUM(I6:I24) -> 0 | L25: =SUM(L6:L24) -> 1418000 | P25: =SUM(P6:P24) -> 2800000 | Q25: =SUM(Q6:Q24) -> 200000
C27: TONTINE | D27: REMBOURSEMENT PETIT LOT | E27: VENTE PETIT LOT | F27: VENTE LOT PRINCIPAL | G27: SOLDE EN CAISSE | M27: TONTINE + REMB + INTERET VENTE | N27: =C32+D32+Q25 -> 2990500
M28: VENDUE | N28: =IF(N27>=2800000,1500000*2,1500000) -> 3000000
B29: ESPECES | C29: =SUMIFS(C6:C24,E6:E24,"ESPECES") -> 200000 | D29: =SUMIFS(L6:L24,M6:M24,"ESPECES")+SUMIFS(F6:F24,G6:G24,"ESPECES") -> 180500 | E29: =SUMIFS(H6:H24,J6:J24,"ESPECES") -> 0 | F29: =SUMIFS(P6:P24,N6:N24,"ESPECES") -> 0 | G29: =C29+D29-E29-F29 -> 380500
B30: BANQUE | C30: =SUMIFS(C6:C24,E6:E24,"BANQUE") -> 1600000 | D30: =SUMIFS(L6:L24,M6:M24,"BANQUE")+SUMIFS(F6:F24,G6:G24,"BANQUE") -> 810000 | E30: =SUMIFS(H6:H24,J6:J24,"BANQUE") -> 0 | F30: =SUMIFS(P6:P24,N6:N24,"BANQUE") -> 2800000 | G30: =C30+D30-E30-F30 -> -390000 | M30: PETIT LOT | N30: =N27-N28 -> -9500
B32: TOTAL | C32: =C29+C30 -> 1800000 | D32: =D29+D30 -> 990500 | E32: =E29+E30 -> 0 | F32: =F29+F30 -> 2800000 | G32: =G29+G30 -> -9500 | M32: RELIQUAT | N32: =N30-H25 -> -9500 | O32: =N32+TONTMARS!O32 -> -449000 | P32: CUMUL
M34: ECHEC TONTINE | N34: =COUNTIFS(E6:E24,"ECHEC")*100000 -> 0 | O34: =N34+TONTMARS!O34 -> 0 | P34: CUMUL
B35: INTERET LOT PRINCIPAL | C35: =Q25 -> 200000 | M35: ECHEC REMBOURSEMENT | N35: =SUMIFS(F6:F24,G6:G24,"ECHEC") -> 435500 | P35: CUMUL
B36: INTERET PETIT LOT | C36: =+I25 -> 0
B38: MONTANT TONTINE | C38: 1500000
B39: MONTANT PETIT LOT A VENDRE | C39: =H25 -> 0

Sheet TONTMAI
A1: ASSOCIATION | B1: ASELBY
A2: ANNEE | B2: 2019/2020
A3: TONTINE | B3: 100000
C4: 43968
A5: MATRICULE | B5: NOM ET PRENOM | C5: MONTANT TONTINE | D5: PENALITE | E5: MODE VERSEMENT TONTINE | F5: REPORT ECHEC PETIT LOT | G5: MODE VERSEMENT VENTE PETIT LOT | H5: VENTE PETIT LOT | I5: INTERET PETIT LOT | J5: MODE VERSEMENT VENTE PETIT LOT | K5: NUMERO CHEQUE | L5: REMBOURSEMENT | M5: MODE VERSEMENT REMBOURSEMENT | N5: MODE VERSEMENT TONTINE PRINCIPAL | O5: NUMERO CHEQUE | P5: MONTANT TONTINE LOT PRINCIPAL | Q5: INTERET LOT PRINCIPAL | R5: DATE VENTE
A6: AS201608 | B6: =VLOOKUP(A6,[1]LISTADHERENT!A$5:H$60,3,0) -> DJUOMBESSY ANTOINE | C6: =IF(E6="ECHEC",0,IF(E6="",0,100000)) -> 100000 | D6: =IF(E6="ESPECES",0,0) -> 0 | E6: BANQUE | F6: =TONTAVRIL!F6 -> 0 | L6: =TONTAVRIL!H6+TONTAVRIL!I6 -> 0 | P6: =IF(Q6=0,0,($C$38-Q6)) -> 0
A7: AS201613 | B7: =VLOOKUP(A7,[1]LISTADHERENT!A$5:H$60,3,0) -> HOTCHO BENJAMIN | C7: =IF(E7="ECHEC",0,IF(E7="",0,100000)) -> 100000 | D7: =IF(E7="ESPECES",0,0) -> 0 | E7: BANQUE | F7: =TONTAVRIL!F7 -> 0 | L7: =TONTAVRIL!H7+TONTAVRIL!I7 -> 0 | P7: =IF(Q7=0,0,($C$38-Q7)) -> 0
A8: AS201619 | B8: =VLOOKUP(A8,[1]LISTADHERENT!A$5:H$60,3,0) -> KOUATCHO MESSACK | C8: =IF(E8="ECHEC",0,IF(E8="",0,100000)) -> 100000 | D8: =IF(E8="ESPECES",0,0) -> 0 | E8: BANQUE | F8: =TONTAVRIL!F8 -> 0 | H8: 200000 | I8: 10000 | L8: =TONTAVRIL!H8+TONTAVRIL!I8 -> 0 | P8: =IF(Q8=0,0,($C$38-Q8)) -> 0
A9: AS201617 | B9: =VLOOKUP(A9,[1]LISTADHERENT!A$5:H$60,3,0) -> KOUAMOU MOISE | C9: =IF(E9="ECHEC",0,IF(E9="",0,100000)) -> 100000 | D9: =IF(E9="ESPECES",0,0) -> 0 | E9: BANQUE | F9: =TONTAVRIL!F9 -> 0 | L9: =TONTAVRIL!H9+TONTAVRIL!I9 -> 0 | P9: =IF(Q9=0,0,($C$38-Q9)) -> 0
A10: AS201649 | B10: =VLOOKUP(A10,[1]LISTADHERENT!A$5:H$60,3,0) -> MBOGNING TUGMA GUY | C10: =IF(E10="ECHEC",0,IF(E10="",0,100000)) -> 100000 | D10: =IF(E10="ESPECES",0,0) -> 0 | E10: BANQUE | F10: =TONTAVRIL!F10 -> 0 | L10: =TONTAVRIL!H10+TONTAVRIL!I10 -> 0 | P10: =IF(Q10=0,0,($C$38-Q10)) -> 0
A11: AS201649 | B11: =VLOOKUP(A11,[1]LISTADHERENT!A$5:H$60,3,0) -> MBOGNING TUGMA GUY | C11: =IF(E11="ECHEC",0,IF(E11="",0,100000)) -> 100000 | D11: =IF(E11="ESPECES",0,0) -> 0 | E11: BANQUE | F11: =TONTAVRIL!F11 -> 0 | L11: =TONTAVRIL!H11+TONTAVRIL!I11 -> 0 | P11: =IF(Q11=0,0,($C$38-Q11)) -> 0
A12: AS201639 | B12: =VLOOKUP(A12,[1]LISTADHERENT!A$5:H$60,3,0) -> NANGUEN MARTIN | C12: =IF(E12="ECHEC",0,IF(E12="",0,100000)) -> 100000 | D12: =IF(E12="ESPECES",0,0) -> 0 | E12: BANQUE | F12: =TONTAVRIL!F12 -> 0 | L12: =TONTAVRIL!H12+TONTAVRIL!I12 -> 0 | P12: =IF(Q12=0,0,($C$38-Q12)) -> 0
A13: AS201622 | B13: =VLOOKUP(A13,[1]LISTADHERENT!A$5:H$60,3,0) -> NDJOMO ETIENNE | C13: =IF(E13="ECHEC",0,IF(E13="",0,100000)) -> 100000 | D13: =IF(E13="ESPECES",0,0) -> 0 | E13: BANQUE | F13: =TONTAVRIL!F13 -> 0 | H13: 126000 | I13: 1000 | L13: =TONTAVRIL!H13+TONTAVRIL!I13 -> 0 | P13: =IF(Q13=0,0,($C$38-Q13)) -> 0
A14: AS201624 | B14: =VLOOKUP(A14,[1]LISTADHERENT!A$5:H$60,3,0) -> NGONDIEP CLAUDE | C14: =IF(E14="ECHEC",0,IF(E14="",0,100000)) -> 100000 | D14: =IF(E14="ESPECES",0,0) -> 0 | E14: BANQUE | F14: =TONTAVRIL!F14 -> 0 | L14: =TONTAVRIL!H14+TONTAVRIL!I14 -> 0 | P14: =IF(Q14=0,0,($C$38-Q14)) -> 1370000 | Q14: 130000
A15: AS201614 | B15: =VLOOKUP(A15,[1]LISTADHERENT!A$5:H$60,3,0) -> NKEHE DAVID | C15: =IF(E15="ECHEC",0,IF(E15="",0,100000)) -> 100000 | D15: =IF(E15="ESPECES",0,0) -> 0 | E15: ESPECES | F15: =TONTAVRIL!F15 -> 225500 | G15: ECHEC | L15: =TONTAVRIL!H15+TONTAVRIL!I15 -> 0 | M15: ECHEC | P15: =IF(Q15=0,0,($C$38-Q15)) -> 0
A16: AS201629 | B16: =VLOOKUP(A16,[1]LISTADHERENT!A$5:H$60,3,0) -> NKEPSEU DIEUDONNE | C16: =IF(E16="ECHEC",0,IF(E16="",0,100000)) -> 100000 | D16: =IF(E16="ESPECES",0,0) -> 0 | E16: BANQUE | F16: =TONTAVRIL!F16 -> 0 | L16: =TONTAVRIL!H16+TONTAVRIL!I16 -> 0 | P16: =IF(Q16=0,0,($C$38-Q16)) -> 0
A17: AS201636 | B17: =VLOOKUP(A17,[1]LISTADHERENT!A$5:H$60,3,0) -> SIMO FONGANG ERIC | C17: =IF(E17="ECHEC",0,IF(E17="",0,100000)) -> 100000 | D17: =IF(E17="ESPECES",0,0) -> 0 | E17: ESPECES | F17: =TONTAVRIL!F17 -> 0 | H17: 200000 | I17: 11000 | L17: =TONTAVRIL!H17+TONTAVRIL!I17 -> 0 | P17: =IF(Q17=0,0,($C$38-Q17)) -> 0
A18: AS201636 | B18: =VLOOKUP(A18,[1]LISTADHERENT!A$5:H$60,3,0) -> SIMO FONGANG ERIC | C18: =IF(E18="ECHEC",0,IF(E18="",0,100000)) -> 100000 | D18: =IF(E18="ESPECES",0,0) -> 0 | E18: ESPECES | F18: =TONTAVRIL!F18 -> 0 | L18: =TONTAVRIL!H18+TONTAVRIL!I18 -> 0 | P18: =IF(Q18=0,0,($C$38-Q18)) -> 0
A19: AS201637 | B19: =VLOOKUP(A19,[1]LISTADHERENT!A$5:H$60,3,0) -> SIME MATHIEU | C19: =IF(E19="ECHEC",0,IF(E19="",0,100000)) -> 100000 | D19: =IF(E19="ESPECES",0,0) -> 0 | E19: BANQUE | F19: =TONTAVRIL!F19 -> 0 | L19: =TONTAVRIL!H19+TONTAVRIL!I19 -> 0 | P19: =IF(Q19=0,0,($C$38-Q19)) -> 0
A20: AS201637 | B20: =VLOOKUP(A20,[1]LISTADHERENT!A$5:H$60,3,0) -> SIME MATHIEU | C20: =IF(E20="ECHEC",0,IF(E20="",0,100000)) -> 100000 | D20: =IF(E20="ESPECES",0,0) -> 0 | E20: BANQUE | F20: =TONTAVRIL!F20 -> 0 | L20: =TONTAVRIL!H20+TONTAVRIL!I20 -> 0 | P20: =IF(Q20=0,0,($C$38-Q20)) -> 0
A21: AS201641 | B21: =VLOOKUP(A21,[1]LISTADHERENT!A$5:H$60,3,0) -> TCHOUAMOU MATHIEU | C21: =IF(E21="ECHEC",0,IF(E21="",0,100000)) -> 100000 | D21: =IF(E21="ESPECES",0,0) -> 0 | E21: BANQUE | F21: =TONTAVRIL!F21 -> 0 | L21: =TONTAVRIL!H21+TONTAVRIL!I21 -> 0 | P21: =IF(Q21=0,0,($C$38-Q21)) -> 0
A22: AS201644 | B22: =VLOOKUP(A22,[1]LISTADHERENT!A$5:H$60,3,0) -> TIEYAM ERNEST | C22: =IF(E22="ECHEC",0,IF(E22="",0,100000)) -> 100000 | D22: =IF(E22="ESPECES",0,0) -> 0 | E22: BANQUE | F22: =TONTAVRIL!F22 -> 210000 | G22: ESPECES | H22: 100000 | I22: 6000 | L22: =TONTAVRIL!H22+TONTAVRIL!I22 -> 0 | M22: ESPECES | P22: =IF(Q22=0,0,($C$38-Q22)) -> 0
A23: AS201647 | B23: =VLOOKUP(A23,[1]LISTADHERENT!A$5:H$60,3,0) -> YOUMBI EMMANUEL | C23: =IF(E23="ECHEC",0,IF(E23="",0,100000)) -> 100000 | D23: =IF(E23="ESPECES",0,0) -> 0 | E23: BANQUE | F23: =TONTAVRIL!F23 -> 0 | L23: =TONTAVRIL!H23+TONTAVRIL!I23 -> 0 | P23: =IF(Q23=0,0,($C$38-Q23)) -> 0
A25: TOTAL | C25: =SUM(C6:C24) -> 1800000 | D25: =SUM(D6:D24) -> 0 | F25: =SUM(F6:F24) -> 435500 | H25: =SUM(H6:H24) -> 626000 | I25: =SUM(I6:I24) -> 28000 | L25: =SUM(L6:L24) -> 0 | P25: =SUM(P6:P24) -> 1370000 | Q25: =SUM(Q6:Q24) -> 130000
C27: TONTINE | D27: REMBOURSEMENT PETIT LOT | E27: VENTE PETIT LOT | F27: VENTE LOT PRINCIPAL | G27: SOLDE EN CAISSE | M27: TONTINE + REMB + INTERET VENTE | N27: =C32+D32+Q25 -> 2140000
M28: VENDUE | N28: =IF(N27>=2800000,1500000*2,1500000) -> 1500000
B29: ESPECES | C29: =SUMIFS(C6:C24,E6:E24,"ESPECES") -> 300000 | D29: =SUMIFS(L6:L24,M6:M24,"ESPECES")+SUMIFS(F6:F24,G6:G24,"ESPECES") -> 210000 | E29: =SUMIFS(H6:H24,J6:J24,"ESPECES") -> 0 | F29: =SUMIFS(P6:P24,N6:N24,"ESPECES") -> 0 | G29: =C29+D29-E29-F29 -> 510000
B30: BANQUE | C30: =SUMIFS(C6:C24,E6:E24,"BANQUE") -> 1500000 | D30: =SUMIFS(L6:L24,M6:M24,"BANQUE")+SUMIFS(F6:F24,G6:G24,"BANQUE") -> 0 | E30: =SUMIFS(H6:H24,J6:J24,"BANQUE") -> 0 | F30: =SUMIFS(P6:P24,N6:N24,"BANQUE") -> 0 | G30: =C30+D30-E30-F30 -> 1500000 | M30: PETIT LOT | N30: =N27-N28 -> 640000
B32: TOTAL | C32: =C29+C30 -> 1800000 | D32: =D29+D30 -> 210000 | E32: =E29+E30 -> 0 | F32: =F29+F30 -> 0 | G32: =G29+G30 -> 2010000 | M32: RELIQUAT | N32: =N30-H25 -> 14000 | O32: =N32+TONTAVRIL!O32 -> -435000 | P32: CUMUL
M34: ECHEC TONTINE | N34: =COUNTIFS(E6:E24,"ECHEC")*100000 -> 0 | O34: =N34+TONTAVRIL!O34 -> 0 | P34: CUMUL
B35: INTERET LOT PRINCIPAL | C35: =Q25 -> 130000 | M35: ECHEC REMBOURSEMENT | N35: =SUMIFS(F6:F24,G6:G24,"ECHEC") -> 225500 | P35: CUMUL
B36: INTERET PETIT LOT | C36: =+I25 -> 28000
B38: MONTANT TONTINE | C38: 1500000
B39: MONTANT PETIT LOT A VENDRE | C39: =H25 -> 626000

Sheet TONTJUIN
A1: ASSOCIATION | B1: ASELBY
A2: ANNEE | B2: 2019/2020
A3: TONTINE | B3: 100000
C4: 44003
A5: MATRICULE | B5: NOM ET PRENOM | C5: MONTANT TONTINE | D5: PENALITE | E5: MODE VERSEMENT TONTINE | F5: REPORT ECHEC PETIT LOT | G5: MODE VERSEMENT VENTE PETIT LOT | H5: VENTE PETIT LOT | I5: INTERET PETIT LOT | J5: MODE VERSEMENT VENTE PETIT LOT | K5: NUMERO CHEQUE | L5: REMBOURSEMENT | M5: MODE VERSEMENT REMBOURSEMENT | N5: MODE VERSEMENT TONTINE PRINCIPAL | O5: NUMERO CHEQUE | P5: MONTANT TONTINE LOT PRINCIPAL | Q5: INTERET LOT PRINCIPAL | R5: DATE VENTE
A6: AS201608 | B6: =VLOOKUP(A6,[1]LISTADHERENT!A$5:H$60,3,0) -> DJUOMBESSY ANTOINE | C6: =IF(E6="ECHEC",0,IF(E6="",0,100000)) -> 100000 | D6: =IF(E6="ESPECES",0,0) -> 0 | E6: BANQUE | F6: =TONTMAI!F6 -> 0 | L6: =TONTMAI!H6+TONTMAI!I6 -> 0 | P6: =IF(Q6=0,0,($C$38-Q6)) -> 0
A7: AS201613 | B7: =VLOOKUP(A7,[1]LISTADHERENT!A$5:H$60,3,0) -> HOTCHO BENJAMIN | C7: =IF(E7="ECHEC",0,IF(E7="",0,100000)) -> 100000 | D7: =IF(E7="ESPECES",0,0) -> 0 | E7: BANQUE | F7: =TONTMAI!F7 -> 0 | L7: =TONTMAI!H7+TONTMAI!I7 -> 0 | P7: =IF(Q7=0,0,($C$38-Q7)) -> 0
A8: AS201619 | B8: =VLOOKUP(A8,[1]LISTADHERENT!A$5:H$60,3,0) -> KOUATCHO MESSACK | C8: =IF(E8="ECHEC",0,IF(E8="",0,100000)) -> 100000 | D8: =IF(E8="ESPECES",0,0) -> 0 | E8: BANQUE | F8: =TONTMAI!F8 -> 0 | H8: 200000 | I8: 2000 | J8: BANQUE | L8: =TONTMAI!H8+TONTMAI!I8 -> 210000 | M8: BANQUE | P8: =IF(Q8=0,0,($C$38-Q8)) -> 0
A9: AS201617 | B9: =VLOOKUP(A9,[1]LISTADHERENT!A$5:H$60,3,0) -> KOUAMOU MOISE | C9: =IF(E9="ECHEC",0,IF(E9="",0,100000)) -> 100000 | D9: =IF(E9="ESPECES",0,0) -> 0 | E9: BANQUE | F9: =TONTMAI!F9 -> 0 | L9: =TONTMAI!H9+TONTMAI!I9 -> 0 | P9: =IF(Q9=0,0,($C$38-Q9)) -> 0
A10: AS201649 | B10: =VLOOKUP(A10,[1]LISTADHERENT!A$5:H$60,3,0) -> MBOGNING TUGMA GUY | C10: =IF(E10="ECHEC",0,IF(E10="",0,100000)) -> 100000 | D10: =IF(E10="ESPECES",0,0) -> 0 | E10: BANQUE | F10: =TONTMAI!F10 -> 0 | H10: 100000 | I10: 1000 | J10: ESPECES | L10: =TONTMAI!H10+TONTMAI!I10 -> 0 | P10: =IF(Q10=0,0,($C$38-Q10)) -> 0
A11: AS201649 | B11: =VLOOKUP(A11,[1]LISTADHERENT!A$5:H$60,3,0) -> MBOGNING TUGMA GUY | C11: =IF(E11="ECHEC",0,IF(E11="",0,100000)) -> 100000 | D11: =IF(E11="ESPECES",0,0) -> 0 | E11: BANQUE | F11: =TONTMAI!F11 -> 0 | L11: =TONTMAI!H11+TONTMAI!I11 -> 0 | P11: =IF(Q11=0,0,($C$38-Q11)) -> 0
A12: AS201639 | B12: =VLOOKUP(A12,[1]LISTADHERENT!A$5:H$60,3,0) -> NANGUEN MARTIN | C12: =IF(E12="ECHEC",0,IF(E12="",0,100000)) -> 100000 | D12: =IF(E12="ESPECES",0,0) -> 0 | E12: BANQUE | F12: =TONTMAI!F12 -> 0 | L12: =TONTMAI!H12+TONTMAI!I12 -> 0 | P12: =IF(Q12=0,0,($C$38-Q12)) -> 0
A13: AS201622 | B13: =VLOOKUP(A13,[1]LISTADHERENT!A$5:H$60,3,0) -> NDJOMO ETIENNE | C13: =IF(E13="ECHEC",0,IF(E13="",0,100000)) -> 100000 | D13: =IF(E13="ESPECES",0,0) -> 0 | E13: BANQUE | F13: =TONTMAI!F13 -> 0 | H13: 200000 | I13: 2000 | J13: BANQUE | L13: =TONTMAI!H13+TONTMAI!I13 -> 127000 | M13: ESPECES | P13: =IF(Q13=0,0,($C$38-Q13)) -> 0
A14: AS201624 | B14: =VLOOKUP(A14,[1]LISTADHERENT!A$5:H$60,3,0) -> NGONDIEP CLAUDE | C14: =IF(E14="ECHEC",0,IF(E14="",0,100000)) -> 100000 | D14: =IF(E14="ESPECES",0,0) -> 0 | E14: BANQUE | F14: =TONTMAI!F14 -> 0 | L14: =TONTMAI!H14+TONTMAI!I14 -> 0 | P14: =IF(Q14=0,0,($C$38-Q14)) -> 0
A15: AS201614 | B15: =VLOOKUP(A15,[1]LISTADHERENT!A$5:H$60,3,0) -> NKEHE DAVID | C15: =IF(E15="ECHEC",0,IF(E15="",0,100000)) -> 0 | D15: =IF(E15="ESPECES",0,0) -> 0 | E15: ECHEC | F15: =TONTMAI!F15 -> 225500 | G15: ECHEC | L15: =TONTMAI!H15+TONTMAI!I15 -> 0 | M15: ECHEC | P15: =IF(Q15=0,0,($C$38-Q15)) -> 0
A16: AS201629 | B16: =VLOOKUP(A16,[1]LISTADHERENT!A$5:H$60,3,0) -> NKEPSEU DIEUDONNE | C16: =IF(E16="ECHEC",0,IF(E16="",0,100000)) -> 100000 | D16: =IF(E16="ESPECES",0,0) -> 0 | E16: BANQUE | F16: =TONTMAI!F16 -> 0 | L16: =TONTMAI!H16+TONTMAI!I16 -> 0 | P16: =IF(Q16=0,0,($C$38-Q16)) -> 0
A17: AS201636 | B17: =VLOOKUP(A17,[1]LISTADHERENT!A$5:H$60,3,0) -> SIMO FONGANG ERIC | C17: =IF(E17="ECHEC",0,IF(E17="",0,100000)) -> 100000 | D17: =IF(E17="ESPECES",0,0) -> 0 | E17: ESPECES | F17: 233000 | G17: ECHEC | L17: =TONTMAI!H17+TONTMAI!I17+22000 -> 233000 | M17: ECHEC | P17: =IF(Q17=0,0,($C$38-Q17)) -> 0
A18: AS201636 | B18: =VLOOKUP(A18,[1]LISTADHERENT!A$5:H$60,3,0) -> SIMO FONGANG ERIC | C18: =IF(E18="ECHEC",0,IF(E18="",0,100000)) -> 100000 | D18: =IF(E18="ESPECES",0,0) -> 0 | E18: ESPECES | F18: =TONTMAI!F18 -> 0 | L18: =TONTMAI!H18+TONTMAI!I18 -> 0 | P18: =IF(Q18=0,0,($C$38-Q18)) -> 0
A19: AS201637 | B19: =VLOOKUP(A19,[1]LISTADHERENT!A$5:H$60,3,0) -> SIME MATHIEU | C19: =IF(E19="ECHEC",0,IF(E19="",0,100000)) -> 100000 | D19: =IF(E19="ESPECES",0,0) -> 0 | E19: BANQUE | F19: =TONTMAI!F19 -> 0 | L19: =TONTMAI!H19+TONTMAI!I19 -> 0 | P19: =IF(Q19=0,0,($C$38-Q19)) -> 0
A20: AS201637 | B20: =VLOOKUP(A20,[1]LISTADHERENT!A$5:H$60,3,0) -> SIME MATHIEU | C20: =IF(E20="ECHEC",0,IF(E20="",0,100000)) -> 100000 | D20: =IF(E20="ESPECES",0,0) -> 0 | E20: BANQUE | F20: =TONTMAI!F20 -> 0 | L20: =TONTMAI!H20+TONTMAI!I20 -> 0 | P20: =IF(Q20=0,0,($C$38-Q20)) -> 0
A21: AS201641 | B21: =VLOOKUP(A21,[1]LISTADHERENT!A$5:H$60,3,0) -> TCHOUAMOU MATHIEU | C21: =IF(E21="ECHEC",0,IF(E21="",0,100000)) -> 100000 | D21: =IF(E21="ESPECES",0,0) -> 0 | E21: BANQUE | F21: =TONTMAI!F21 -> 0 | H21: 238000 | I21: 2000 | J21: BANQUE | L21: =TONTMAI!H21+TONTMAI!I21 -> 0 | P21: =IF(Q21=0,0,($C$38-Q21)) -> 0
A22: AS201644 | B22: =VLOOKUP(A22,[1]LISTADHERENT!A$5:H$60,3,0) -> TIEYAM ERNEST | C22: =IF(E22="ECHEC",0,IF(E22="",0,100000)) -> 100000 | D22: =IF(E22="ESPECES",0,0) -> 0 | E22: ESPECES | H22: 100000 | I22: 1000 | J22: BANQUE | L22: =TONTMAI!H22+TONTMAI!I22 -> 106000 | M22: BANQUE | N22: BANQUE | P22: =IF(Q22=0,0,($C$38-Q22)) -> 1305000 | Q22: 195000
A23: AS201647 | B23: =VLOOKUP(A23,[1]LISTADHERENT!A$5:H$60,3,0) -> YOUMBI EMMANUEL | C23: =IF(E23="ECHEC",0,IF(E23="",0,100000)) -> 100000 | D23: =IF(E23="ESPECES",0,0) -> 0 | E23: BANQUE | F23: =TONTMAI!F23 -> 0 | L23: =TONTMAI!H23+TONTMAI!I23 -> 0 | P23: =IF(Q23=0,0,($C$38-Q23)) -> 0
A25: TOTAL | C25: =SUM(C6:C24) -> 1700000 | D25: =SUM(D6:D24) -> 0 | F25: =SUM(F6:F24) -> 458500 | H25: =SUM(H6:H24) -> 838000 | I25: =SUM(I6:I24) -> 8000 | L25: =SUM(L6:L24) -> 676000 | P25: =SUM(P6:P24) -> 1305000 | Q25: =SUM(Q6:Q24) -> 195000
C27: TONTINE | D27: REMBOURSEMENT PETIT LOT | E27: VENTE PETIT LOT | F27: VENTE LOT PRINCIPAL | G27: SOLDE EN CAISSE | M27: TONTINE + REMB + INTERET VENTE | N27: =C32+D32+Q25 -> 2338000
M28: VENDUE | N28: =IF(N27>=2800000,1500000*2,1500000) -> 1500000
B29: ESPECES | C29: =SUMIFS(C6:C24,E6:E24,"ESPECES") -> 300000 | D29: =SUMIFS(L6:L24,M6:M24,"ESPECES")+SUMIFS(F6:F24,G6:G24,"ESPECES") -> 127000 | E29: =SUMIFS(H6:H24,J6:J24,"ESPECES") -> 100000 | F29: =SUMIFS(P6:P24,N6:N24,"ESPECES") -> 0 | G29: =C29+D29-E29-F29 -> 327000
B30: BANQUE | C30: =SUMIFS(C6:C24,E6:E24,"BANQUE") -> 1400000 | D30: =SUMIFS(L6:L24,M6:M24,"BANQUE")+SUMIFS(F6:F24,G6:G24,"BANQUE") -> 316000 | E30: =SUMIFS(H6:H24,J6:J24,"BANQUE") -> 738000 | F30: =SUMIFS(P6:P24,N6:N24,"BANQUE") -> 1305000 | G30: =C30+D30-E30-F30 -> -327000 | M30: PETIT LOT | N30: =N27-N28 -> 838000
B32: TOTAL | C32: =C29+C30 -> 1700000 | D32: =D29+D30 -> 443000 | E32: =E29+E30 -> 838000 | F32: =F29+F30 -> 1305000 | G32: =G29+G30 -> 0 | M32: RELIQUAT | N32: =N30-H25 -> 0 | O32: =N32+TONTMAI!O32 -> -435000 | P32: CUMUL
M34: ECHEC TONTINE | N34: =COUNTIFS(E6:E24,"ECHEC")*100000 -> 100000 | O34: =N34+TONTMAI!O34 -> 100000 | P34: CUMUL
B35: INTERET LOT PRINCIPAL | C35: =Q25 -> 195000 | M35: ECHEC REMBOURSEMENT | N35: =SUMIFS(F6:F24,G6:G24,"ECHEC") -> 458500 | P35: CUMUL
B36: INTERET PETIT LOT | C36: =+I25 -> 8000
B38: MONTANT TONTINE | C38: 1500000
B39: MONTANT PETIT LOT A VENDRE | C39: =H25 -> 838000

Sheet TONTJUIL
A1: ASSOCIATION | B1: ASELBY
A2: ANNEE | B2: 2019/2020
A3: TONTINE | B3: 100000
C4: 44031
A5: MATRICULE | B5: NOM ET PRENOM | C5: MONTANT TONTINE | D5: PENALITE | E5: MODE VERSEMENT TONTINE | F5: REPORT ECHEC PETIT LOT | G5: MODE VERSEMENT VENTE PETIT LOT | H5: VENTE PETIT LOT | I5: INTERET PETIT LOT | J5: MODE VERSEMENT VENTE PETIT LOT | K5: NUMERO CHEQUE | L5: REMBOURSEMENT | M5: MODE VERSEMENT REMBOURSEMENT | N5: MODE VERSEMENT TONTINE PRINCIPAL | O5: NUMERO CHEQUE | P5: MONTANT TONTINE LOT PRINCIPAL | Q5: INTERET LOT PRINCIPAL | R5: DATE VENTE
A6: AS201608 | B6: =VLOOKUP(A6,[1]LISTADHERENT!A$5:H$60,3,0) -> DJUOMBESSY ANTOINE | C6: =IF(E6="ECHEC",0,IF(E6="",0,100000)) -> 100000 | D6: =IF(E6="ESPECES",0,0) -> 0 | E6: BANQUE | F6: =TONTJUIN!F6 -> 0 | L6: =TONTJUIN!H6+TONTJUIN!I6 -> 0 | P6: =IF(Q6=0,0,($C$38-Q6)) -> 0
A7: AS201613 | B7: =VLOOKUP(A7,[1]LISTADHERENT!A$5:H$60,3,0) -> HOTCHO BENJAMIN | C7: =IF(E7="ECHEC",0,IF(E7="",0,100000)) -> 100000 | D7: =IF(E7="ESPECES",0,0) -> 0 | E7: BANQUE | F7: =TONTJUIN!F7 -> 0 | L7: =TONTJUIN!H7+TONTJUIN!I7 -> 0 | P7: =IF(Q7=0,0,($C$38-Q7)) -> 0
A8: AS201619 | B8: =VLOOKUP(A8,[1]LISTADHERENT!A$5:H$60,3,0) -> KOUATCHO MESSACK | C8: =IF(E8="ECHEC",0,IF(E8="",0,100000)) -> 100000 | D8: =IF(E8="ESPECES",0,0) -> 0 | E8: BANQUE | F8: =TONTJUIN!F8 -> 0 | H8: 69000 | I8: 1500 | J8: ESPECES | L8: =TONTJUIN!H8+TONTJUIN!I8 -> 202000 | M8: BANQUE | P8: =IF(Q8=0,0,($C$38-Q8)) -> 0
A9: AS201617 | B9: =VLOOKUP(A9,[1]LISTADHERENT!A$5:H$60,3,0) -> KOUAMOU MOISE | C9: =IF(E9="ECHEC",0,IF(E9="",0,100000)) -> 100000 | D9: =IF(E9="ESPECES",0,0) -> 0 | E9: BANQUE | F9: =TONTJUIN!F9 -> 0 | L9: =TONTJUIN!H9+TONTJUIN!I9 -> 0 | P9: =IF(Q9=0,0,($C$38-Q9)) -> 0
A10: AS201649 | B10: =VLOOKUP(A10,[1]LISTADHERENT!A$5:H$60,3,0) -> MBOGNING TUGMA GUY | C10: =IF(E10="ECHEC",0,IF(E10="",0,100000)) -> 100000 | D10: =IF(E10="ESPECES",0,0) -> 0 | E10: BANQUE | F10: =TONTJUIN!F10 -> 0 | L10: =TONTJUIN!H10+TONTJUIN!I10 -> 101000 | M10: ESPECES | P10: =IF(Q10=0,0,($C$38-Q10)) -> 0
A11: AS201649 | B11: =VLOOKUP(A11,[1]LISTADHERENT!A$5:H$60,3,0) -> MBOGNING TUGMA GUY | C11: =IF(E11="ECHEC",0,IF(E11="",0,100000)) -> 100000 | D11: =IF(E11="ESPECES",0,0) -> 0 | E11: BANQUE | F11: =TONTJUIN!F11 -> 0 | L11: =TONTJUIN!H11+TONTJUIN!I11 -> 0 | N11: BANQUE | P11: =IF(Q11=0,0,($C$38-Q11)) -> 1255000 | Q11: 245000
A12: AS201639 | B12: =VLOOKUP(A12,[1]LISTADHERENT!A$5:H$60,3,0) -> NANGUEN MARTIN | C12: =IF(E12="ECHEC",0,IF(E12="",0,100000)) -> 100000 | D12: =IF(E12="ESPECES",0,0) -> 0 | E12: BANQUE | F12: =TONTJUIN!F12 -> 0 | L12: =TONTJUIN!H12+TONTJUIN!I12 -> 0 | P12: =IF(Q12=0,0,($C$38-Q12)) -> 0
A13: AS201622 | B13: =VLOOKUP(A13,[1]LISTADHERENT!A$5:H$60,3,0) -> NDJOMO ETIENNE | C13: =IF(E13="ECHEC",0,IF(E13="",0,100000)) -> 100000 | D13: =IF(E13="ESPECES",0,0) -> 0 | E13: BANQUE | F13: =TONTJUIN!F13 -> 0 | L13: =TONTJUIN!H13+TONTJUIN!I13 -> 202000 | M13: BANQUE | P13: =IF(Q13=0,0,($C$38-Q13)) -> 0
A14: AS201624 | B14: =VLOOKUP(A14,[1]LISTADHERENT!A$5:H$60,3,0) -> NGONDIEP CLAUDE | C14: =IF(E14="ECHEC",0,IF(E14="",0,100000)) -> 100000 | D14: =IF(E14="ESPECES",0,0) -> 0 | E14: BANQUE | F14: =TONTJUIN!F14 -> 0 | L14: =TONTJUIN!H14+TONTJUIN!I14 -> 0 | P14: =IF(Q14=0,0,($C$38-Q14)) -> 0
A15: AS201614 | B15: =VLOOKUP(A15,[1]LISTADHERENT!A$5:H$60,3,0) -> NKEHE DAVID | C15: =IF(E15="ECHEC",0,IF(E15="",0,100000)) -> 0 | D15: =IF(E15="ESPECES",0,0) -> 0 | E15: ECHEC | F15: =TONTJUIN!F15 -> 225500 | G15: ECHEC | L15: =TONTJUIN!H15+TONTJUIN!I15 -> 0 | M15: ECHEC | P15: =IF(Q15=0,0,($C$38-Q15)) -> 0
A16: AS201629 | B16: =VLOOKUP(A16,[1]LISTADHERENT!A$5:H$60,3,0) -> NKEPSEU DIEUDONNE | C16: =IF(E16="ECHEC",0,IF(E16="",0,100000)) -> 100000 | D16: =IF(E16="ESPECES",0,0) -> 0 | E16: BANQUE | F16: =TONTJUIN!F16 -> 0 | L16: =TONTJUIN!H16+TONTJUIN!I16 -> 0 | P16: =IF(Q16=0,0,($C$38-Q16)) -> 0
A17: AS201636 | B17: =VLOOKUP(A17,[1]LISTADHERENT!A$5:H$60,3,0) -> SIMO FONGANG ERIC | C17: =IF(E17="ECHEC",0,IF(E17="",0,100000)) -> 100000 | D17: =IF(E17="ESPECES",0,0) -> 0 | E17: ESPECES | F17: =TONTJUIN!F17 -> 233000 | G17: ECHEC | L17: =TONTJUIN!H17+TONTJUIN!I17 -> 0 | M17: ESPECES | P17: =IF(Q17=0,0,($C$38-Q17)) -> 0
A18: AS201636 | B18: =VLOOKUP(A18,[1]LISTADHERENT!A$5:H$60,3,0) -> SIMO FONGANG ERIC | C18: =IF(E18="ECHEC",0,IF(E18="",0,100000)) -> 100000 | D18: =IF(E18="ESPECES",0,0) -> 0 | E18: ESPECES | F18: =TONTJUIN!F18 -> 0 | L18: =TONTJUIN!H18+TONTJUIN!I18 -> 0 | N18: BANQUE | P18: =IF(Q18=0,0,($C$38-Q18)) -> 1254000 | Q18: 246000
A19: AS201637 | B19: =VLOOKUP(A19,[1]LISTADHERENT!A$5:H$60,3,0) -> SIME MATHIEU | C19: =IF(E19="ECHEC",0,IF(E19="",0,100000)) -> 100000 | D19: =IF(E19="ESPECES",0,0) -> 0 | E19: BANQUE | F19: =TONTJUIN!F19 -> 0 | L19: =TONTJUIN!H19+TONTJUIN!I19 -> 0 | P19: =IF(Q19=0,0,($C$38-Q19)) -> 0
A20: AS201637 | B20: =VLOOKUP(A20,[1]LISTADHERENT!A$5:H$60,3,0) -> SIME MATHIEU | C20: =IF(E20="ECHEC",0,IF(E20="",0,100000)) -> 100000 | D20: =IF(E20="ESPECES",0,0) -> 0 | E20: BANQUE | F20: =TONTJUIN!F20 -> 0 | L20: =TONTJUIN!H20+TONTJUIN!I20 -> 0 | P20: =IF(Q20=0,0,($C$38-Q20)) -> 0
A21: AS201641 | B21: =VLOOKUP(A21,[1]LISTADHERENT!A$5:H$60,3,0) -> TCHOUAMOU MATHIEU | C21: =IF(E21="ECHEC",0,IF(E21="",0,100000)) -> 100000 | D21: =IF(E21="ESPECES",0,0) -> 0 | E21: BANQUE | F21: =TONTJUIN!F21 -> 0 | L21: =TONTJUIN!H21+TONTJUIN!I21 -> 240000 | M21: BANQUE | P21: =IF(Q21=0,0,($C$38-Q21)) -> 0
A22: AS201644 | B22: =VLOOKUP(A22,[1]LISTADHERENT!A$5:H$60,3,0) -> TIEYAM ERNEST | C22: =IF(E22="ECHEC",0,IF(E22="",0,100000)) -> 0 | D22: =IF(E22="ESPECES",0,0) -> 0 | E22: ECHEC | F22: 103000 | G22: ECHEC | L22: =TONTJUIN!H22+TONTJUIN!I22 -> 101000 | M22: ECHEC | P22: =IF(Q22=0,0,($C$38-Q22)) -> 0
A23: AS201647 | B23: =VLOOKUP(A23,[1]LISTADHERENT!A$5:H$60,3,0) -> YOUMBI EMMANUEL | C23: =IF(E23="ECHEC",0,IF(E23="",0,100000)) -> 100000 | D23: =IF(E23="ESPECES",0,0) -> 0 | E23: BANQUE | F23: =TONTJUIN!F23 -> 0 | L23: =TONTJUIN!H23+TONTJUIN!I23 -> 0 | P23: =IF(Q23=0,0,($C$38-Q23)) -> 0
A25: TOTAL | C25: =SUM(C6:C24) -> 1600000 | D25: =SUM(D6:D24) -> 0 | F25: =SUM(F6:F24) -> 561500 | H25: =SUM(H6:H24) -> 69000 | I25: =SUM(I6:I24) -> 1500 | L25: =SUM(L6:L24) -> 846000 | P25: =SUM(P6:P24) -> 2509000 | Q25: =SUM(Q6:Q24) -> 491000
C27: TONTINE | D27: REMBOURSEMENT PETIT LOT | E27: VENTE PETIT LOT | F27: VENTE LOT PRINCIPAL | G27: SOLDE EN CAISSE | M27: TONTINE + REMB + INTERET VENTE | N27: =C32+D32+Q25 -> 2836000
M28: VENDUE | N28: =IF(N27>=2800000,1500000*2,1500000) -> 3000000
B29: ESPECES | C29: =SUMIFS(C6:C24,E6:E24,"ESPECES") -> 200000 | D29: =SUMIFS(L6:L24,M6:M24,"ESPECES")+SUMIFS(F6:F24,G6:G24,"ESPECES") -> 101000 | E29: =SUMIFS(H6:H24,J6:J24,"ESPECES") -> 69000 | F29: =SUMIFS(P6:P24,N6:N24,"ESPECES") -> 0 | G29: =C29+D29-E29-F29 -> 232000
B30: BANQUE | C30: =SUMIFS(C6:C24,E6:E24,"BANQUE") -> 1400000 | D30: =SUMIFS(L6:L24,M6:M24,"BANQUE")+SUMIFS(F6:F24,G6:G24,"BANQUE") -> 644000 | E30: =SUMIFS(H6:H24,J6:J24,"BANQUE") -> 0 | F30: =SUMIFS(P6:P24,N6:N24,"BANQUE") -> 2509000 | G30: =C30+D30-E30-F30 -> -465000 | M30: PETIT LOT | N30: =N27-N28 -> -164000
B32: TOTAL | C32: =C29+C30 -> 1600000 | D32: =D29+D30 -> 745000 | E32: =E29+E30 -> 69000 | F32: =F29+F30 -> 2509000 | G32: =G29+G30 -> -233000 | M32: RELIQUAT | N32: =N30-H25 -> -233000 | O32: =N32+TONTJUIN!O32 -> -668000 | P32: CUMUL
M34: ECHEC TONTINE | N34: =COUNTIFS(E6:E24,"ECHEC")*100000 -> 200000 | O34: =N34+TONTJUIN!O34 -> 300000 | P34: CUMUL
B35: INTERET LOT PRINCIPAL | C35: =Q25 -> 491000 | M35: ECHEC REMBOURSEMENT | N35: =SUMIFS(F6:F24,G6:G24,"ECHEC") -> 561500 | P35: CUMUL
B36: INTERET PETIT LOT | C36: =+I25 -> 1500
B38: MONTANT TONTINE | C38: 1500000
B39: MONTANT PETIT LOT A VENDRE | C39: =H25 -> 69000

Sheet TONTAOUT
A1: ASSOCIATION | B1: ASELBY
A2: ANNEE | B2: 2019/2020
A3: TONTINE | B3: 100000
C4: 16/O8/2020
A5: MATRICULE | B5: NOM ET PRENOM | C5: MONTANT TONTINE | D5: PENALITE | E5: MODE VERSEMENT TONTINE | F5: REPORT ECHEC PETIT LOT | G5: MODE VERSEMENT VENTE PETIT LOT | H5: VENTE PETIT LOT | I5: INTERET PETIT LOT | J5: MODE VERSEMENT VENTE PETIT LOT | K5: NUMERO CHEQUE | L5: REMBOURSEMENT | M5: MODE VERSEMENT REMBOURSEMENT | N5: MODE VERSEMENT TONTINE PRINCIPAL | O5: NUMERO CHEQUE | P5: MONTANT TONTINE LOT PRINCIPAL | Q5: INTERET LOT PRINCIPAL | R5: DATE VENTE
A6: AS201608 | B6: =VLOOKUP(A6,[1]LISTADHERENT!A$5:H$60,3,0) -> DJUOMBESSY ANTOINE | C6: =IF(E6="ECHEC",0,IF(E6="",0,100000)) -> 100000 | D6: =IF(E6="ESPECES",0,0) -> 0 | E6: BANQUE | F6: =TONTJUIL!F6 -> 0 | L6: =TONTJUIL!H6+TONTJUIL!I6 -> 0 | P6: =IF(Q6=0,0,($C$38-Q6)) -> 0
A7: AS201613 | B7: =VLOOKUP(A7,[1]LISTADHERENT!A$5:H$60,3,0) -> HOTCHO BENJAMIN | C7: =IF(E7="ECHEC",0,IF(E7="",0,100000)) -> 100000 | D7: =IF(E7="ESPECES",0,0) -> 0 | E7: BANQUE | F7: =TONTJUIL!F7 -> 0 | L7: =TONTJUIL!H7+TONTJUIL!I7 -> 0 | P7: =IF(Q7=0,0,($C$38-Q7)) -> 0
A8: AS201619 | B8: =VLOOKUP(A8,[1]LISTADHERENT!A$5:H$60,3,0) -> KOUATCHO MESSACK | C8: =IF(E8="ECHEC",0,IF(E8="",0,100000)) -> 100000 | D8: =IF(E8="ESPECES",0,0) -> 0 | E8: BANQUE | F8: =TONTJUIL!F8 -> 0 | H8: 229000 | I8: 7000 | L8: =TONTJUIL!H8+TONTJUIL!I8 -> 70500 | M8: BANQUE | P8: =IF(Q8=0,0,($C$38-Q8)) -> 0
A9: AS201617 | B9: =VLOOKUP(A9,[1]LISTADHERENT!A$5:H$60,3,0) -> KOUAMOU MOISE | C9: =IF(E9="ECHEC",0,IF(E9="",0,100000)) -> 100000 | D9: =IF(E9="ESPECES",0,0) -> 0 | E9: ESPECES | F9: =TONTJUIL!F9 -> 0 | L9: =TONTJUIL!H9+TONTJUIL!I9 -> 0 | P9: =IF(Q9=0,0,($C$38-Q9)) -> 0
A10: AS201649 | B10: =VLOOKUP(A10,[1]LISTADHERENT!A$5:H$60,3,0) -> MBOGNING TUGMA GUY | C10: =IF(E10="ECHEC",0,IF(E10="",0,100000)) -> 100000 | D10: =IF(E10="ESPECES",0,0) -> 0 | E10: BANQUE | F10: =TONTJUIL!F10 -> 0 | L10: =TONTJUIL!H10+TONTJUIL!I10 -> 0 | P10: =IF(Q10=0,0,($C$38-Q10)) -> 0
A11: AS201649 | B11: =VLOOKUP(A11,[1]LISTADHERENT!A$5:H$60,3,0) -> MBOGNING TUGMA GUY | C11: =IF(E11="ECHEC",0,IF(E11="",0,100000)) -> 100000 | D11: =IF(E11="ESPECES",0,0) -> 0 | E11: BANQUE | F11: =TONTJUIL!F11 -> 0 | L11: =TONTJUIL!H11+TONTJUIL!I11 -> 0 | P11: =IF(Q11=0,0,($C$38-Q11)) -> 0
A12: AS201639 | B12: =VLOOKUP(A12,[1]LISTADHERENT!A$5:H$60,3,0) -> NANGUEN MARTIN | C12: =IF(E12="ECHEC",0,IF(E12="",0,100000)) -> 100000 | D12: =IF(E12="ESPECES",0,0) -> 0 | E12: BANQUE | F12: =TONTJUIL!F12 -> 0 | L12: =TONTJUIL!H12+TONTJUIL!I12 -> 0 | P12: =IF(Q12=0,0,($C$38-Q12)) -> 0
A13: AS201622 | B13: =VLOOKUP(A13,[1]LISTADHERENT!A$5:H$60,3,0) -> NDJOMO ETIENNE | C13: =IF(E13="ECHEC",0,IF(E13="",0,100000)) -> 100000 | D13: =IF(E13="ESPECES",0,0) -> 0 | E13: BANQUE | F13: =TONTJUIL!F13 -> 0 | L13: =TONTJUIL!H13+TONTJUIL!I13 -> 0 | P13: =IF(Q13=0,0,($C$38-Q13)) -> 0
A14: AS201624 | B14: =VLOOKUP(A14,[1]LISTADHERENT!A$5:H$60,3,0) -> NGONDIEP CLAUDE | C14: =IF(E14="ECHEC",0,IF(E14="",0,100000)) -> 100000 | D14: =IF(E14="ESPECES",0,0) -> 0 | E14: ESPECES | F14: =TONTJUIL!F14 -> 0 | L14: =TONTJUIL!H14+TONTJUIL!I14 -> 0 | P14: =IF(Q14=0,0,($C$38-Q14)) -> 0
A15: AS201614 | B15: =VLOOKUP(A15,[1]LISTADHERENT!A$5:H$60,3,0) -> NKEHE DAVID | C15: =IF(E15="ECHEC",0,IF(E15="",0,100000)) -> 0 | D15: =IF(E15="ESPECES",0,0) -> 0 | E15: ECHEC | F15: =TONTJUIL!F15 -> 225500 | G15: ECHEC | L15: =TONTJUIL!H15+TONTJUIL!I15 -> 0 | P15: =IF(Q15=0,0,($C$38-Q15)) -> 0
A16: AS201629 | B16: =VLOOKUP(A16,[1]LISTADHERENT!A$5:H$60,3,0) -> NKEPSEU DIEUDONNE | C16: =IF(E16="ECHEC",0,IF(E16="",0,100000)) -> 100000 | D16: =IF(E16="ESPECES",0,0) -> 0 | E16: BANQUE | F16: =TONTJUIL!F16 -> 0 | L16: =TONTJUIL!H16+TONTJUIL!I16 -> 0 | P16: =IF(Q16=0,0,($C$38-Q16)) -> 0
A17: AS201636 | B17: =VLOOKUP(A17,[1]LISTADHERENT!A$5:H$60,3,0) -> SIMO FONGANG ERIC | C17: =IF(E17="ECHEC",0,IF(E17="",0,100000)) -> 100000 | D17: =IF(E17="ESPECES",0,0) -> 0 | E17: ESPECES | F17: =TONTJUIL!F17 -> 233000 | G17: ECHEC | L17: =TONTJUIL!H17+TONTJUIL!I17 -> 0 | P17: =IF(Q17=0,0,($C$38-Q17)) -> 0
A18: AS201636 | B18: =VLOOKUP(A18,[1]LISTADHERENT!A$5:H$60,3,0) -> SIMO FONGANG ERIC | C18: =IF(E18="ECHEC",0,IF(E18="",0,100000)) -> 100000 | D18: =IF(E18="ESPECES",0,0) -> 0 | E18: ESPECES | F18: =TONTJUIL!F18 -> 0 | L18: =TONTJUIL!H18+TONTJUIL!I18 -> 0 | P18: =IF(Q18=0,0,($C$38-Q18)) -> 0
A19: AS201637 | B19: =VLOOKUP(A19,[1]LISTADHERENT!A$5:H$60,3,0) -> SIME MATHIEU | C19: =IF(E19="ECHEC",0,IF(E19="",0,100000)) -> 100000 | D19: =IF(E19="ESPECES",0,0) -> 0 | E19: ESPECES | F19: =TONTJUIL!F19 -> 0 | L19: =TONTJUIL!H19+TONTJUIL!I19 -> 0 | N19: BANQUE | P19: =IF(Q19=0,0,($C$38-Q19)) -> 1340000 | Q19: 160000
A20: AS201637 | B20: =VLOOKUP(A20,[1]LISTADHERENT!A$5:H$60,3,0) -> SIME MATHIEU | C20: =IF(E20="ECHEC",0,IF(E20="",0,100000)) -> 100000 | D20: =IF(E20="ESPECES",0,0) -> 0 | E20: ESPECES | F20: =TONTJUIL!F20 -> 0 | L20: =TONTJUIL!H20+TONTJUIL!I20 -> 0 | P20: =IF(Q20=0,0,($C$38-Q20)) -> 0
A21: AS201641 | B21: =VLOOKUP(A21,[1]LISTADHERENT!A$5:H$60,3,0) -> TCHOUAMOU MATHIEU | C21: =IF(E21="ECHEC",0,IF(E21="",0,100000)) -> 100000 | D21: =IF(E21="ESPECES",0,0) -> 0 | E21: BANQUE | F21: =TONTJUIL!F21 -> 0 | L21: =TONTJUIL!H21+TONTJUIL!I21 -> 0 | P21: =IF(Q21=0,0,($C$38-Q21)) -> 0
A22: AS201644 | B22: =VLOOKUP(A22,[1]LISTADHERENT!A$5:H$60,3,0) -> TIEYAM ERNEST | C22: =IF(E22="ECHEC",0,IF(E22="",0,100000)) -> 100000 | D22: =IF(E22="ESPECES",0,0) -> 0 | E22: ESPECES | F22: =TONTJUIL!F22 -> 103000 | G22: ECHEC | L22: =TONTJUIL!H22+TONTJUIL!I22 -> 0 | P22: =IF(Q22=0,0,($C$38-Q22)) -> 0
A23: AS201647 | B23: =VLOOKUP(A23,[1]LISTADHERENT!A$5:H$60,3,0) -> YOUMBI EMMANUEL | C23: =IF(E23="ECHEC",0,IF(E23="",0,100000)) -> 100000 | D23: =IF(E23="ESPECES",0,0) -> 0 | E23: BANQUE | F23: =TONTJUIL!F23 -> 0 | L23: =TONTJUIL!H23+TONTJUIL!I23 -> 0 | P23: =IF(Q23=0,0,($C$38-Q23)) -> 0
A25: TOTAL | C25: =SUM(C6:C24) -> 1700000 | D25: =SUM(D6:D24) -> 0 | F25: =SUM(F6:F24) -> 561500 | H25: =SUM(H6:H24) -> 229000 | I25: =SUM(I6:I24) -> 7000 | L25: =SUM(L6:L24) -> 70500 | P25: =SUM(P6:P24) -> 1340000 | Q25: =SUM(Q6:Q24) -> 160000
C27: TONTINE | D27: REMBOURSEMENT PETIT LOT | E27: VENTE PETIT LOT | F27: VENTE LOT PRINCIPAL | G27: SOLDE EN CAISSE | M27: TONTINE + REMB + INTERET VENTE | N27: =C32+D32+Q25 -> 1930500
M28: VENDUE | N28: =IF(N27>=2800000,1500000*2,1500000) -> 1500000
B29: ESPECES | C29: =SUMIFS(C6:C24,E6:E24,"ESPECES") -> 700000 | D29: =SUMIFS(L6:L24,M6:M24,"ESPECES")+SUMIFS(F6:F24,G6:G24,"ESPECES") -> 0 | E29: =SUMIFS(H6:H24,J6:J24,"ESPECES") -> 0 | F29: =SUMIFS(P6:P24,N6:N24,"ESPECES") -> 0 | G29: =C29+D29-E29-F29 -> 700000
B30: BANQUE | C30: =SUMIFS(C6:C24,E6:E24,"BANQUE") -> 1000000 | D30: =SUMIFS(L6:L24,M6:M24,"BANQUE")+SUMIFS(F6:F24,G6:G24,"BANQUE") -> 70500 | E30: =SUMIFS(H6:H24,J6:J24,"BANQUE") -> 0 | F30: =SUMIFS(P6:P24,N6:N24,"BANQUE") -> 1340000 | G30: =C30+D30-E30-F30 -> -269500 | M30: PETIT LOT | N30: =N27-N28 -> 430500
B32: TOTAL | C32: =C29+C30 -> 1700000 | D32: =D29+D30 -> 70500 | E32: =E29+E30 -> 0 | F32: =F29+F30 -> 1340000 | G32: =G29+G30 -> 430500 | M32: RELIQUAT | N32: =N30-H25 -> 201500 | O32: =N32+TONTJUIL!O32 -> -466500 | P32: CUMUL
M34: ECHEC TONTINE | N34: =COUNTIFS(E6:E24,"ECHEC")*100000 -> 100000 | O34: =N34+TONTJUIL!O34 -> 400000 | P34: CUMUL
B35: INTERET LOT PRINCIPAL | C35: =Q25 -> 160000 | M35: ECHEC REMBOURSEMENT | N35: =SUMIFS(F6:F24,G6:G24,"ECHEC") -> 561500 | P35: CUMUL
B36: INTERET PETIT LOT | C36: =+I25 -> 7000
B38: MONTANT TONTINE | C38: 1500000
B39: MONTANT PETIT LOT A VENDRE | C39: =H25 -> 229000

Sheet TONTSEPT
A1: ASSOCIATION | B1: ASELBY
A2: ANNEE | B2: 2019/2020
A3: TONTINE | B3: 100000
C4: 44094
A5: MATRICULE | B5: NOM ET PRENOM | C5: MONTANT TONTINE | D5: PENALITE | E5: MODE VERSEMENT TONTINE | F5: REPORT ECHEC PETIT LOT | G5: MODE VERSEMENT VENTE PETIT LOT | H5: VENTE PETIT LOT | I5: INTERET PETIT LOT | J5: MODE VERSEMENT VENTE PETIT LOT | K5: NUMERO CHEQUE | L5: REMBOURSEMENT | M5: MODE VERSEMENT REMBOURSEMENT | N5: MODE VERSEMENT TONTINE PRINCIPAL | O5: NUMERO CHEQUE | P5: MONTANT TONTINE LOT PRINCIPAL | Q5: INTERET LOT PRINCIPAL | R5: DATE VENTE
A6: AS201608 | B6: =VLOOKUP(A6,[1]LISTADHERENT!A$5:H$60,3,0) -> DJUOMBESSY ANTOINE | C6: =IF(E6="ECHEC",0,IF(E6="",0,100000)) -> 100000 | D6: =IF(E6="ESPECES",0,0) -> 0 | E6: BANQUE | F6: =TONTAOUT!F6 -> 0 | L6: =TONTAOUT!H6+TONTAOUT!I6 -> 0 | P6: =IF(Q6=0,0,($C$38-Q6)) -> 0
A7: AS201613 | B7: =VLOOKUP(A7,[1]LISTADHERENT!A$5:H$60,3,0) -> HOTCHO BENJAMIN | C7: =IF(E7="ECHEC",0,IF(E7="",0,100000)) -> 100000 | D7: =IF(E7="ESPECES",0,0) -> 0 | E7: BANQUE | F7: =TONTAOUT!F7 -> 0 | L7: =TONTAOUT!H7+TONTAOUT!I7 -> 0 | P7: =IF(Q7=0,0,($C$38-Q7)) -> 0
A8: AS201619 | B8: =VLOOKUP(A8,[1]LISTADHERENT!A$5:H$60,3,0) -> KOUATCHO MESSACK | C8: =IF(E8="ECHEC",0,IF(E8="",0,100000)) -> 100000 | D8: =IF(E8="ESPECES",0,0) -> 0 | E8: ESPECES | F8: =TONTAOUT!F8 -> 0 | H8: 136000 | I8: 5000 | J8: BANQUE | L8: =TONTAOUT!H8+TONTAOUT!I8 -> 236000 | M8: ESPECES | P8: =IF(Q8=0,0,($C$38-Q8)) -> 0
A9: AS201617 | B9: =VLOOKUP(A9,[1]LISTADHERENT!A$5:H$60,3,0) -> KOUAMOU MOISE | C9: =IF(E9="ECHEC",0,IF(E9="",0,100000)) -> 100000 | D9: =IF(E9="ESPECES",0,0) -> 0 | E9: BANQUE | F9: =TONTAOUT!F9 -> 0 | L9: =TONTAOUT!H9+TONTAOUT!I9 -> 0 | P9: =IF(Q9=0,0,($C$38-Q9)) -> 0
A10: AS201649 | B10: =VLOOKUP(A10,[1]LISTADHERENT!A$5:H$60,3,0) -> MBOGNING TUGMA GUY | C10: =IF(E10="ECHEC",0,IF(E10="",0,100000)) -> 100000 | D10: =IF(E10="ESPECES",0,0) -> 0 | E10: BANQUE | F10: =TONTAOUT!F10 -> 0 | L10: =TONTAOUT!H10+TONTAOUT!I10 -> 0 | P10: =IF(Q10=0,0,($C$38-Q10)) -> 0
A11: AS201649 | B11: =VLOOKUP(A11,[1]LISTADHERENT!A$5:H$60,3,0) -> MBOGNING TUGMA GUY | C11: =IF(E11="ECHEC",0,IF(E11="",0,100000)) -> 100000 | D11: =IF(E11="ESPECES",0,0) -> 0 | E11: BANQUE | F11: =TONTAOUT!F11 -> 0 | L11: =TONTAOUT!H11+TONTAOUT!I11 -> 0 | P11: =IF(Q11=0,0,($C$38-Q11)) -> 0
A12: AS201639 | B12: =VLOOKUP(A12,[1]LISTADHERENT!A$5:H$60,3,0) -> NANGUEN MARTIN | C12: =IF(E12="ECHEC",0,IF(E12="",0,100000)) -> 0 | D12: =IF(E12="ESPECES",0,0) -> 0 | E12: ECHEC | F12: =TONTAOUT!F12 -> 0 | L12: =TONTAOUT!H12+TONTAOUT!I12 -> 0 | P12: =IF(Q12=0,0,($C$38-Q12)) -> 0
A13: AS201622 | B13: =VLOOKUP(A13,[1]LISTADHERENT!A$5:H$60,3,0) -> NDJOMO ETIENNE | C13: =IF(E13="ECHEC",0,IF(E13="",0,100000)) -> 100000 | D13: =IF(E13="ESPECES",0,0) -> 0 | E13: BANQUE | F13: =TONTAOUT!F13 -> 0 | L13: =TONTAOUT!H13+TONTAOUT!I13 -> 0 | P13: =IF(Q13=0,0,($C$38-Q13)) -> 0
A14: AS201624 | B14: =VLOOKUP(A14,[1]LISTADHERENT!A$5:H$60,3,0) -> NGONDIEP CLAUDE | C14: =IF(E14="ECHEC",0,IF(E14="",0,100000)) -> 0 | D14: =IF(E14="ESPECES",0,0) -> 0 | E14: ECHEC | F14: =TONTAOUT!F14 -> 0 | L14: =TONTAOUT!H14+TONTAOUT!I14 -> 0 | P14: =IF(Q14=0,0,($C$38-Q14)) -> 0
A15: AS201614 | B15: =VLOOKUP(A15,[1]LISTADHERENT!A$5:H$60,3,0) -> NKEHE DAVID | C15: =IF(E15="ECHEC",0,IF(E15="",0,100000)) -> 0 | D15: =IF(E15="ESPECES",0,0) -> 0 | E15: ECHEC | F15: =TONTAOUT!F15 -> 225500 | G15: ECHEC | L15: =TONTAOUT!H15+TONTAOUT!I15 -> 0 | P15: =IF(Q15=0,0,($C$38-Q15)) -> 0
A16: AS201629 | B16: =VLOOKUP(A16,[1]LISTADHERENT!A$5:H$60,3,0) -> NKEPSEU DIEUDONNE | C16: =IF(E16="ECHEC",0,IF(E16="",0,100000)) -> 100000 | D16: =IF(E16="ESPECES",0,0) -> 0 | E16: BANQUE | F16: =TONTAOUT!F16 -> 0 | L16: =TONTAOUT!H16+TONTAOUT!I16 -> 0 | P16: =IF(Q16=0,0,($C$38-Q16)) -> 0
A17: AS201636 | B17: =VLOOKUP(A17,[1]LISTADHERENT!A$5:H$60,3,0) -> SIMO FONGANG ERIC | C17: =IF(E17="ECHEC",0,IF(E17="",0,100000)) -> 100000 | D17: =IF(E17="ESPECES",0,0) -> 0 | E17: BANQUE | F17: =TONTAOUT!F17 -> 233000 | G17: ECHEC | L17: =TONTAOUT!H17+TONTAOUT!I17 -> 0 | P17: =IF(Q17=0,0,($C$38-Q17)) -> 0
A18: AS201636 | B18: =VLOOKUP(A18,[1]LISTADHERENT!A$5:H$60,3,0) -> SIMO FONGANG ERIC | C18: =IF(E18="ECHEC",0,IF(E18="",0,100000)) -> 100000 | D18: =IF(E18="ESPECES",0,0) -> 0 | E18: BANQUE | F18: =TONTAOUT!F18 -> 0 | L18: =TONTAOUT!H18+TONTAOUT!I18 -> 0 | P18: =IF(Q18=0,0,($C$38-Q18)) -> 0
A19: AS201637 | B19: =VLOOKUP(A19,[1]LISTADHERENT!A$5:H$60,3,0) -> SIME MATHIEU | C19: =IF(E19="ECHEC",0,IF(E19="",0,100000)) -> 100000 | D19: =IF(E19="ESPECES",0,0) -> 0 | E19: BANQUE | F19: =TONTAOUT!F19 -> 0 | H19: 200000 | I19: 8000 | J19: ESPECES | L19: =TONTAOUT!H19+TONTAOUT!I19 -> 0 | P19: =IF(Q19=0,0,($C$38-Q19)) -> 0
A20: AS201637 | B20: =VLOOKUP(A20,[1]LISTADHERENT!A$5:H$60,3,0) -> SIME MATHIEU | C20: =IF(E20="ECHEC",0,IF(E20="",0,100000)) -> 100000 | D20: =IF(E20="ESPECES",0,0) -> 0 | E20: BANQUE | F20: =TONTAOUT!F20 -> 0 | L20: =TONTAOUT!H20+TONTAOUT!I20 -> 0 | P20: =IF(Q20=0,0,($C$38-Q20)) -> 0
A21: AS201641 | B21: =VLOOKUP(A21,[1]LISTADHERENT!A$5:H$60,3,0) -> TCHOUAMOU MATHIEU | C21: =IF(E21="ECHEC",0,IF(E21="",0,100000)) -> 100000 | D21: =IF(E21="ESPECES",0,0) -> 0 | E21: BANQUE | F21: =TONTAOUT!F21 -> 0 | L21: =TONTAOUT!H21+TONTAOUT!I21 -> 0 | N21: BANQUE | P21: =IF(Q21=0,0,($C$38-Q21)) -> 1400000 | Q21: 100000
A22: AS201644 | B22: =VLOOKUP(A22,[1]LISTADHERENT!A$5:H$60,3,0) -> TIEYAM ERNEST | C22: =IF(E22="ECHEC",0,IF(E22="",0,100000)) -> 100000 | D22: =IF(E22="ESPECES",0,0) -> 0 | E22: BANQUE | F22: =TONTAOUT!F22 -> 103000 | G22: ECHEC | L22: =TONTAOUT!H22+TONTAOUT!I22 -> 0 | P22: =IF(Q22=0,0,($C$38-Q22)) -> 0
A23: AS201647 | B23: =VLOOKUP(A23,[1]LISTADHERENT!A$5:H$60,3,0) -> YOUMBI EMMANUEL | C23: =IF(E23="ECHEC",0,IF(E23="",0,100000)) -> 100000 | D23: =IF(E23="ESPECES",0,0) -> 0 | E23: BANQUE | F23: =TONTAOUT!F23 -> 0 | L23: =TONTAOUT!H23+TONTAOUT!I23 -> 0 | P23: =IF(Q23=0,0,($C$38-Q23)) -> 0
A25: TOTAL | C25: =SUM(C6:C24) -> 1500000 | D25: =SUM(D6:D24) -> 0 | F25: =SUM(F6:F24) -> 561500 | H25: =SUM(H6:H24) -> 336000 | I25: =SUM(I6:I24) -> 13000 | L25: =SUM(L6:L24) -> 236000 | P25: =SUM(P6:P24) -> 1400000 | Q25: =SUM(Q6:Q24) -> 100000
C27: TONTINE | D27: REMBOURSEMENT PETIT LOT | E27: VENTE PETIT LOT | F27: VENTE LOT PRINCIPAL | G27: SOLDE EN CAISSE | M27: TONTINE + REMB + INTERET VENTE | N27: =C32+D32+Q25 -> 1836000
M28: VENDUE | N28: =IF(N27>=2800000,1500000*2,1500000) -> 1500000
B29: ESPECES | C29: =SUMIFS(C6:C24,E6:E24,"ESPECES") -> 100000 | D29: =SUMIFS(L6:L24,M6:M24,"ESPECES")+SUMIFS(F6:F24,G6:G24,"ESPECES") -> 236000 | E29: =SUMIFS(H6:H24,J6:J24,"ESPECES") -> 200000 | F29: =SUMIFS(P6:P24,N6:N24,"ESPECES") -> 0 | G29: =C29+D29-E29-F29 -> 136000
B30: BANQUE | C30: =SUMIFS(C6:C24,E6:E24,"BANQUE") -> 1400000 | D30: =SUMIFS(L6:L24,M6:M24,"BANQUE")+SUMIFS(F6:F24,G6:G24,"BANQUE") -> 0 | E30: =SUMIFS(H6:H24,J6:J24,"BANQUE") -> 136000 | F30: =SUMIFS(P6:P24,N6:N24,"BANQUE") -> 1400000 | G30: =C30+D30-E30-F30 -> -136000 | M30: PETIT LOT | N30: =N27-N28 -> 336000
B32: TOTAL | C32: =C29+C30 -> 1500000 | D32: =D29+D30 -> 236000 | E32: =E29+E30 -> 336000 | F32: =F29+F30 -> 1400000 | G32: =G29+G30 -> 0 | M32: RELIQUAT | N32: =N30-H25 -> 0 | O32: =N32+TONTAOUT!O32 -> -466500 | P32: CUMUL
M34: ECHEC TONTINE | N34: =COUNTIFS(E6:E24,"ECHEC")*100000 -> 300000 | O34: =N34+TONTAOUT!O34 -> 700000 | P34: CUMUL
B35: INTERET LOT PRINCIPAL | C35: =Q25 -> 100000 | M35: ECHEC REMBOURSEMENT | N35: =SUMIFS(F6:F24,G6:G24,"ECHEC") -> 561500 | P35: CUMUL
B36: INTERET PETIT LOT | C36: =+I25 -> 13000
B38: MONTANT TONTINE | C38: 1500000
B39: MONTANT PETIT LOT A VENDRE | C39: =H25 -> 336000

Sheet TONTOCT
A1: ASSOCIATION | B1: ASELBY
A2: ANNEE | B2: 2019/2020
A3: TONTINE | B3: 100000
C4: 44122
A5: MATRICULE | B5: NOM ET PRENOM | C5: MONTANT TONTINE | D5: PENALITE | E5: MODE VERSEMENT TONTINE | F5: REPORT ECHEC PETIT LOT | G5: MODE VERSEMENT VENTE PETIT LOT | H5: VENTE PETIT LOT | I5: INTERET PETIT LOT | J5: MODE VERSEMENT VENTE PETIT LOT | K5: NUMERO CHEQUE | L5: REMBOURSEMENT | M5: MODE VERSEMENT REMBOURSEMENT | N5: MODE VERSEMENT TONTINE PRINCIPAL | O5: NUMERO CHEQUE | P5: MONTANT TONTINE LOT PRINCIPAL | Q5: INTERET LOT PRINCIPAL | R5: DATE VENTE
A6: AS201608 | B6: =VLOOKUP(A6,[1]LISTADHERENT!A$5:H$60,3,0) -> DJUOMBESSY ANTOINE | C6: =IF(E6="ECHEC",0,IF(E6="",0,100000)) -> 100000 | D6: =IF(E6="ESPECES",0,0) -> 0 | E6: BANQUE | F6: =TONTSEPT!F6 -> 0 | L6: =TONTSEPT!H6+TONTSEPT!I6 -> 0 | P6: =IF(Q6=0,0,($C$38-Q6)) -> 0
A7: AS201613 | B7: =VLOOKUP(A7,[1]LISTADHERENT!A$5:H$60,3,0) -> HOTCHO BENJAMIN | C7: =IF(E7="ECHEC",0,IF(E7="",0,100000)) -> 100000 | D7: =IF(E7="ESPECES",0,0) -> 0 | E7: BANQUE | F7: =TONTSEPT!F7 -> 0 | L7: =TONTSEPT!H7+TONTSEPT!I7 -> 0 | P7: =IF(Q7=0,0,($C$38-Q7)) -> 0
A8: AS201619 | B8: =VLOOKUP(A8,[1]LISTADHERENT!A$5:H$60,3,0) -> KOUATCHO MESSACK | C8: =IF(E8="ECHEC",0,IF(E8="",0,100000)) -> 100000 | D8: =IF(E8="ESPECES",0,0) -> 0 | E8: BANQUE | F8: =TONTSEPT!F8 -> 0 | H8: 200000 | I8: 6000 | L8: =TONTSEPT!H8+TONTSEPT!I8 -> 141000 | M8: ESPECES | P8: =IF(Q8=0,0,($C$38-Q8)) -> 0
A9: AS201617 | B9: =VLOOKUP(A9,[1]LISTADHERENT!A$5:H$60,3,0) -> KOUAMOU MOISE | C9: =IF(E9="ECHEC",0,IF(E9="",0,100000)) -> 100000 | D9: =IF(E9="ESPECES",0,0) -> 0 | E9: BANQUE | F9: =TONTSEPT!F9 -> 0 | L9: =TONTSEPT!H9+TONTSEPT!I9 -> 0 | P9: =IF(Q9=0,0,($C$38-Q9)) -> 0
A10: AS201649 | B10: =VLOOKUP(A10,[1]LISTADHERENT!A$5:H$60,3,0) -> MBOGNING TUGMA GUY | C10: =IF(E10="ECHEC",0,IF(E10="",0,100000)) -> 100000 | D10: =IF(E10="ESPECES",0,0) -> 0 | E10: BANQUE | F10: =TONTSEPT!F10 -> 0 | H10: 159000 | I10: 2500 | L10: =TONTSEPT!H10+TONTSEPT!I10 -> 0 | P10: =IF(Q10=0,0,($C$38-Q10)) -> 0
A11: AS201649 | B11: =VLOOKUP(A11,[1]LISTADHERENT!A$5:H$60,3,0) -> MBOGNING TUGMA GUY | C11: =IF(E11="ECHEC",0,IF(E11="",0,100000)) -> 100000 | D11: =IF(E11="ESPECES",0,0) -> 0 | E11: BANQUE | F11: =TONTSEPT!F11 -> 0 | L11: =TONTSEPT!H11+TONTSEPT!I11 -> 0 | P11: =IF(Q11=0,0,($C$38-Q11)) -> 0
A12: AS201639 | B12: =VLOOKUP(A12,[1]LISTADHERENT!A$5:H$60,3,0) -> NANGUEN MARTIN | C12: =IF(E12="ECHEC",0,IF(E12="",0,100000))+100000 -> 200000 | D12: =IF(E12="ESPECES",0,0) -> 0 | E12: BANQUE | F12: =TONTSEPT!F12 -> 0 | L12: =TONTSEPT!H12+TONTSEPT!I12 -> 0 | P12: =IF(Q12=0,0,($C$38-Q12)) -> 1390000 | Q12: 110000
A13: AS201622 | B13: =VLOOKUP(A13,[1]LISTADHERENT!A$5:H$60,3,0) -> NDJOMO ETIENNE | C13: =IF(E13="ECHEC",0,IF(E13="",0,100000)) -> 100000 | D13: =IF(E13="ESPECES",0,0) -> 0 | E13: BANQUE | F13: =TONTSEPT!F13 -> 0 | L13: =TONTSEPT!H13+TONTSEPT!I13 -> 0 | P13: =IF(Q13=0,0,($C$38-Q13)) -> 0
A14: AS201624 | B14: =VLOOKUP(A14,[1]LISTADHERENT!A$5:H$60,3,0) -> NGONDIEP CLAUDE | C14: =IF(E14="ECHEC",0,IF(E14="",0,100000))+100000 -> 200000 | D14: =IF(E14="ESPECES",0,0) -> 0 | E14: BANQUE | F14: =TONTSEPT!F14 -> 0 | L14: =TONTSEPT!H14+TONTSEPT!I14 -> 0 | P14: =IF(Q14=0,0,($C$38-Q14)) -> 0
A15: AS201614 | B15: =VLOOKUP(A15,[1]LISTADHERENT!A$5:H$60,3,0) -> NKEHE DAVID | C15: =IF(E15="ECHEC",0,IF(E15="",0,100000)) -> 0 | D15: =IF(E15="ESPECES",0,0) -> 0 | E15: ECHEC | F15: =TONTSEPT!F15 -> 225500 | G15: ECHEC | L15: =TONTSEPT!H15+TONTSEPT!I15 -> 0 | P15: =IF(Q15=0,0,($C$38-Q15)) -> 0
A16: AS201629 | B16: =VLOOKUP(A16,[1]LISTADHERENT!A$5:H$60,3,0) -> NKEPSEU DIEUDONNE | C16: =IF(E16="ECHEC",0,IF(E16="",0,100000)) -> 100000 | D16: =IF(E16="ESPECES",0,0) -> 0 | E16: BANQUE | F16: =TONTSEPT!F16 -> 0 | H16: 100000 | I16: 1000 | L16: =TONTSEPT!H16+TONTSEPT!I16 -> 0 | P16: =IF(Q16=0,0,($C$38-Q16)) -> 0
A17: AS201636 | B17: =VLOOKUP(A17,[1]LISTADHERENT!A$5:H$60,3,0) -> SIMO FONGANG ERIC | C17: =IF(E17="ECHEC",0,IF(E17="",0,100000)) -> 100000 | D17: =IF(E17="ESPECES",0,0) -> 0 | E17: ESPECES | F17: =TONTSEPT!F17 -> 233000 | G17: ECHEC | L17: =TONTSEPT!H17+TONTSEPT!I17 -> 0 | P17: =IF(Q17=0,0,($C$38-Q17)) -> 0
A18: AS201636 | B18: =VLOOKUP(A18,[1]LISTADHERENT!A$5:H$60,3,0) -> SIMO FONGANG ERIC | C18: =IF(E18="ECHEC",0,IF(E18="",0,100000)) -> 100000 | D18: =IF(E18="ESPECES",0,0) -> 0 | E18: ESPECES | F18: =TONTSEPT!F18 -> 0 | L18: =TONTSEPT!H18+TONTSEPT!I18 -> 0 | P18: =IF(Q18=0,0,($C$38-Q18)) -> 0
A19: AS201637 | B19: =VLOOKUP(A19,[1]LISTADHERENT!A$5:H$60,3,0) -> SIME MATHIEU | C19: =IF(E19="ECHEC",0,IF(E19="",0,100000)) -> 100000 | D19: =IF(E19="ESPECES",0,0) -> 0 | E19: BANQUE | F19: 224000 | G19: ECHEC | L19: =TONTSEPT!H19+TONTSEPT!I19 -> 208000 | M19: ECHEC | P19: =IF(Q19=0,0,($C$38-Q19)) -> 0
A20: AS201637 | B20: =VLOOKUP(A20,[1]LISTADHERENT!A$5:H$60,3,0) -> SIME MATHIEU | C20: =IF(E20="ECHEC",0,IF(E20="",0,100000)) -> 100000 | D20: =IF(E20="ESPECES",0,0) -> 0 | E20: BANQUE | F20: =TONTSEPT!F20 -> 0 | L20: =TONTSEPT!H20+TONTSEPT!I20 -> 0 | P20: =IF(Q20=0,0,($C$38-Q20)) -> 0
A21: AS201641 | B21: =VLOOKUP(A21,[1]LISTADHERENT!A$5:H$60,3,0) -> TCHOUAMOU MATHIEU | C21: =IF(E21="ECHEC",0,IF(E21="",0,100000)) -> 100000 | D21: =IF(E21="ESPECES",0,0) -> 0 | E21: BANQUE | F21: =TONTSEPT!F21 -> 0 | H21: 200000 | I21: 4500 | L21: =TONTSEPT!H21+TONTSEPT!I21 -> 0 | P21: =IF(Q21=0,0,($C$38-Q21)) -> 0
A22: AS201644 | B22: =VLOOKUP(A22,[1]LISTADHERENT!A$5:H$60,3,0) -> TIEYAM ERNEST | C22: =IF(E22="ECHEC",0,IF(E22="",0,100000)) -> 100000 | D22: =IF(E22="ESPECES",0,0) -> 0 | E22: ESPECES | F22: =TONTSEPT!F22 -> 103000 | G22: ECHEC | L22: =TONTSEPT!H22+TONTSEPT!I22 -> 0 | P22: =IF(Q22=0,0,($C$38-Q22)) -> 0
A23: AS201647 | B23: =VLOOKUP(A23,[1]LISTADHERENT!A$5:H$60,3,0) -> YOUMBI EMMANUEL | C23: =IF(E23="ECHEC",0,IF(E23="",0,100000)) -> 100000 | D23: =IF(E23="ESPECES",0,0) -> 0 | E23: BANQUE | F23: =TONTSEPT!F23 -> 0 | L23: =TONTSEPT!H23+TONTSEPT!I23 -> 0 | P23: =IF(Q23=0,0,($C$38-Q23)) -> 0
A25: TOTAL | C25: =SUM(C6:C24) -> 1900000 | D25: =SUM(D6:D24) -> 0 | F25: =SUM(F6:F24) -> 785500 | H25: =SUM(H6:H24) -> 659000 | I25: =SUM(I6:I24) -> 14000 | L25: =SUM(L6:L24) -> 349000 | P25: =SUM(P6:P24) -> 1390000 | Q25: =SUM(Q6:Q24) -> 110000
C27: TONTINE | D27: REMBOURSEMENT PETIT LOT | E27: VENTE PETIT LOT | F27: VENTE LOT PRINCIPAL | G27: SOLDE EN CAISSE | M27: TONTINE + REMB + INTERET VENTE | N27: =C32+D32+Q25 -> 2151000
M28: VENDUE | N28: =IF(N27>=2800000,1500000*2,1500000) -> 1500000
B29: ESPECES | C29: =SUMIFS(C6:C24,E6:E24,"ESPECES") -> 300000 | D29: =SUMIFS(L6:L24,M6:M24,"ESPECES")+SUMIFS(F6:F24,G6:G24,"ESPECES") -> 141000 | E29: =SUMIFS(H6:H24,J6:J24,"ESPECES") -> 0 | F29: =SUMIFS(P6:P24,N6:N24,"ESPECES") -> 0 | G29: =C29+D29-E29-F29 -> 441000
B30: BANQUE | C30: =SUMIFS(C6:C24,E6:E24,"BANQUE") -> 1600000 | D30: =SUMIFS(L6:L24,M6:M24,"BANQUE")+SUMIFS(F6:F24,G6:G24,"BANQUE") -> 0 | E30: =SUMIFS(H6:H24,J6:J24,"BANQUE") -> 0 | F30: =SUMIFS(P6:P24,N6:N24,"BANQUE") -> 0 | G30: =C30+D30-E30-F30 -> 1600000 | M30: PETIT LOT | N30: =N27-N28 -> 651000
B32: TOTAL | C32: =C29+C30 -> 1900000 | D32: =D29+D30 -> 141000 | E32: =E29+E30 -> 0 | F32: =F29+F30 -> 0 | G32: =G29+G30 -> 2041000 | M32: RELIQUAT | N32: =N30-H25 -> -8000 | O32: =N32+TONTSEPT!O32 -> -474500 | P32: CUMUL
M34: ECHEC TONTINE | N34: =COUNTIFS(E6:E24,"ECHEC")*100000 -> 100000 | O34: =N34+TONTSEPT!O34-200000 -> 600000 | P34: CUMUL
B35: INTERET LOT PRINCIPAL | C35: =Q25 -> 110000 | M35: ECHEC REMBOURSEMENT | N35: =SUMIFS(F6:F24,G6:G24,"ECHEC") -> 785500 | P35: CUMUL
B36: INTERET PETIT LOT | C36: =+I25 -> 14000
B38: MONTANT TONTINE | C38: 1500000
B39: MONTANT PETIT LOT A VENDRE | C39: =H25 -> 659000

Sheet TONTNOV20
A1: ASSOCIATION | B1: ASELBY
A2: ANNEE | B2: 2019/2020
A3: TONTINE | B3: 100000
C4: 44150
A5: MATRICULE | B5: NOM ET PRENOM | C5: MONTANT TONTINE | D5: PENALITE | E5: MODE VERSEMENT TONTINE | F5: REPORT ECHEC PETIT LOT | G5: MODE VERSEMENT VENTE PETIT LOT | H5: VENTE PETIT LOT | I5: INTERET PETIT LOT | J5: MODE VERSEMENT VENTE PETIT LOT | K5: NUMERO CHEQUE | L5: REMBOURSEMENT | M5: MODE VERSEMENT REMBOURSEMENT | N5: MODE VERSEMENT TONTINE PRINCIPAL | O5: NUMERO CHEQUE | P5: MONTANT TONTINE LOT PRINCIPAL | Q5: INTERET LOT PRINCIPAL | R5: DATE VENTE
A6: AS201608 | B6: =VLOOKUP(A6,[1]LISTADHERENT!A$5:H$60,3,0) -> DJUOMBESSY ANTOINE | C6: =IF(E6="ECHEC",0,IF(E6="",0,100000)) -> 0 | D6: =IF(E6="ESPECES",0,0) -> 0 | E6: ECHEC | F6: =TONTOCT!F6 -> 0 | L6: =TONTOCT!H6+TONTOCT!I6 -> 0 | P6: =IF(Q6=0,0,($C$38-Q6)) -> 0
A7: AS201613 | B7: =VLOOKUP(A7,[1]LISTADHERENT!A$5:H$60,3,0) -> HOTCHO BENJAMIN | C7: =IF(E7="ECHEC",0,IF(E7="",0,100000)) -> 0 | D7: =IF(E7="ESPECES",0,0) -> 0 | E7: ECHEC | F7: =TONTOCT!F7 -> 0 | L7: =TONTOCT!H7+TONTOCT!I7 -> 0 | P7: =IF(Q7=0,0,($C$38-Q7)) -> 0
A8: AS201619 | B8: =VLOOKUP(A8,[1]LISTADHERENT!A$5:H$60,3,0) -> KOUATCHO MESSACK | C8: =IF(E8="ECHEC",0,IF(E8="",0,100000)) -> 0 | D8: =IF(E8="ESPECES",0,0) -> 0 | E8: ECHEC | F8: =TONTOCT!F8 -> 0 | L8: =TONTOCT!H8+TONTOCT!I8 -> 206000 | P8: =IF(Q8=0,0,($C$38-Q8)) -> 0
A9: AS201617 | B9: =VLOOKUP(A9,[1]LISTADHERENT!A$5:H$60,3,0) -> KOUAMOU MOISE | C9: =IF(E9="ECHEC",0,IF(E9="",0,100000)) -> 0 | D9: =IF(E9="ESPECES",0,0) -> 0 | E9: ECHEC | F9: =TONTOCT!F9 -> 0 | L9: =TONTOCT!H9+TONTOCT!I9 -> 0 | P9: =IF(Q9=0,0,($C$38-Q9)) -> 0
A10: AS201649 | B10: =VLOOKUP(A10,[1]LISTADHERENT!A$5:H$60,3,0) -> MBOGNING TUGMA GUY | C10: =IF(E10="ECHEC",0,IF(E10="",0,100000)) -> 0 | D10: =IF(E10="ESPECES",0,0) -> 0 | E10: ECHEC | F10: =TONTOCT!F10 -> 0 | L10: =TONTOCT!H10+TONTOCT!I10 -> 161500 | P10: =IF(Q10=0,0,($C$38-Q10)) -> 0
A11: AS201649 | B11: =VLOOKUP(A11,[1]LISTADHERENT!A$5:H$60,3,0) -> MBOGNING TUGMA GUY | C11: =IF(E11="ECHEC",0,IF(E11="",0,100000)) -> 0 | D11: =IF(E11="ESPECES",0,0) -> 0 | E11: ECHEC | F11: =TONTOCT!F11 -> 0 | L11: =TONTOCT!H11+TONTOCT!I11 -> 0 | P11: =IF(Q11=0,0,($C$38-Q11)) -> 0
A12: AS201639 | B12: =VLOOKUP(A12,[1]LISTADHERENT!A$5:H$60,3,0) -> NANGUEN MARTIN | C12: =IF(E12="ECHEC",0,IF(E12="",0,100000)) -> 0 | D12: =IF(E12="ESPECES",0,0) -> 0 | E12: ECHEC | F12: =TONTOCT!F12 -> 0 | L12: =TONTOCT!H12+TONTOCT!I12 -> 0 | P12: =IF(Q12=0,0,($C$38-Q12)) -> 0
A13: AS201622 | B13: =VLOOKUP(A13,[1]LISTADHERENT!A$5:H$60,3,0) -> NDJOMO ETIENNE | C13: =IF(E13="ECHEC",0,IF(E13="",0,100000)) -> 0 | D13: =IF(E13="ESPECES",0,0) -> 0 | E13: ECHEC | F13: =TONTOCT!F13 -> 0 | L13: =TONTOCT!H13+TONTOCT!I13 -> 0 | P13: =IF(Q13=0,0,($C$38-Q13)) -> 0
A14: AS201624 | B14: =VLOOKUP(A14,[1]LISTADHERENT!A$5:H$60,3,0) -> NGONDIEP CLAUDE | C14: =IF(E14="ECHEC",0,IF(E14="",0,100000)) -> 0 | D14: =IF(E14="ESPECES",0,0) -> 0 | E14: ECHEC | F14: =TONTOCT!F14 -> 0 | L14: =TONTOCT!H14+TONTOCT!I14 -> 0 | P14: =IF(Q14=0,0,($C$38-Q14)) -> 0
A15: AS201614 | B15: =VLOOKUP(A15,[1]LISTADHERENT!A$5:H$60,3,0) -> NKEHE DAVID | C15: =IF(E15="ECHEC",0,IF(E15="",0,100000)) -> 0 | D15: =IF(E15="ESPECES",0,0) -> 0 | E15: ECHEC | F15: =TONTOCT!F15 -> 225500 | L15: =TONTOCT!H15+TONTOCT!I15 -> 0 | P15: =IF(Q15=0,0,($C$38-Q15)) -> 0
A16: AS201629 | B16: =VLOOKUP(A16,[1]LISTADHERENT!A$5:H$60,3,0) -> NKEPSEU DIEUDONNE | C16: =IF(E16="ECHEC",0,IF(E16="",0,100000)) -> 0 | D16: =IF(E16="ESPECES",0,0) -> 0 | E16: ECHEC | F16: =TONTOCT!F16 -> 0 | L16: =TONTOCT!H16+TONTOCT!I16 -> 101000 | P16: =IF(Q16=0,0,($C$38-Q16)) -> 0
A17: AS201636 | B17: =VLOOKUP(A17,[1]LISTADHERENT!A$5:H$60,3,0) -> SIMO FONGANG ERIC | C17: =IF(E17="ECHEC",0,IF(E17="",0,100000)) -> 0 | D17: =IF(E17="ESPECES",0,0) -> 0 | E17: ECHEC | F17: =TONTOCT!F17 -> 233000 | L17: =TONTOCT!H17+TONTOCT!I17 -> 0 | P17: =IF(Q17=0,0,($C$38-Q17)) -> 0
... A23: AS201647 | B23: =VLOOKUP(A23,[1]LISTADHERENT!A$5:H$60,3,0) -> YOUMBI EMMANUEL | C23: =IF(E23="ECHEC",0,IF(E23="",0,100000)) -> 0 | D23: =IF(E23="ESPECES",0,0) -> 0 | E23: ECHEC | F23: =TONTOCT!F23 -> 0 | L23: =TONTOCT!H23+TONTOCT!I23 -> 0 | P23: =IF(Q23=0,0,($C$38-Q23)) -> 0
A25: TOTAL | C25: =SUM(C6:C24) -> 0 | D25: =SUM(D6:D24) -> 0 | F25: =SUM(F6:F24) -> 785500 | H25: =SUM(H6:H24) -> 0 | I25: =SUM(I6:I24) -> 0 | L25: =SUM(L6:L24) -> 673000 | P25: =SUM(P6:P24) -> 0 | Q25: =SUM(Q6:Q24) -> 0
C27: TONTINE | D27: REMBOURSEMENT PETIT LOT | E27: VENTE PETIT LOT | F27: VENTE LOT PRINCIPAL | G27: SOLDE EN CAISSE | M27: TONTINE + REMB + INTERET VENTE | N27: =C32+D32+Q25 -> 0
M28: VENDUE | N28: =IF(N27>=2800000,1500000*2,1500000) -> 1500000
B29: ESPECES | C29: =SUMIFS(C6:C24,E6:E24,"ESPECES") -> 0 | D29: =SUMIFS(L6:L24,M6:M24,"ESPECES")+SUMIFS(F6:F24,G6:G24,"ESPECES") -> 0 | E29: =SUMIFS(H6:H24,J6:J24,"ESPECES") -> 0 | F29: =SUMIFS(P6:P24,N6:N24,"ESPECES") -> 0 | G29: =C29+D29-E29-F29 -> 0
B30: BANQUE | C30: =SUMIFS(C6:C24,E6:E24,"BANQUE") -> 0 | D30: =SUMIFS(L6:L24,M6:M24,"BANQUE")+SUMIFS(F6:F24,G6:G24,"BANQUE") -> 0 | E30: =SUMIFS(H6:H24,J6:J24,"BANQUE") -> 0 | F30: =SUMIFS(P6:P24,N6:N24,"BANQUE") -> 0 | G30: =C30+D30-E30-F30 -> 0 | M30: PETIT LOT | N30: =N27-N28 -> -1500000
B32: TOTAL | C32: =C29+C30 -> 0 | D32: =D29+D30 -> 0 | E32: =E29+E30 -> 0 | F32: =F29+F30 -> 0 | G32: =G29+G30 -> 0 | M32: RELIQUAT | N32: =N30-H25 -> -1500000 | O32: =N32+TONTOCT!O32 -> -1974500 | P32: CUMUL
M34: ECHEC TONTINE | N34: =COUNTIFS(E6:E24,"ECHEC")*100000 -> 1800000 | O34: =N34+TONTOCT!O34 -> 2400000 | P34: CUMUL
B35: INTERET LOT PRINCIPAL | C35: =Q25 -> 0 | M35: ECHEC REMBOURSEMENT | N35: =SUMIFS(F6:F24,G6:G24,"ECHEC") -> 0 | P35: CUMUL
B36: INTERET PETIT LOT | C36: =+I25 -> 0
B38: MONTANT TONTINE | C38: 1500000
B39: MONTANT PETIT LOT A VENDRE | C39: =H25 -> 0

Sheet TONTDEC20
A1: ASSOCIATION | B1: ASELBY
A2: ANNEE | B2: 2019/2020
A3: TONTINE | B3: 100000
C4: 44185
A5: MATRICULE | B5: NOM ET PRENOM | C5: MONTANT TONTINE | D5: PENALITE | E5: MODE VERSEMENT TONTINE | F5: REPORT ECHEC PETIT LOT | G5: MODE VERSEMENT VENTE PETIT LOT | H5: VENTE PETIT LOT | I5: INTERET PETIT LOT | J5: MODE VERSEMENT VENTE PETIT LOT | K5: NUMERO CHEQUE | L5: REMBOURSEMENT | M5: MODE VERSEMENT REMBOURSEMENT | N5: MODE VERSEMENT TONTINE PRINCIPAL | O5: NUMERO CHEQUE | P5: MONTANT TONTINE LOT PRINCIPAL | Q5: INTERET LOT PRINCIPAL | R5: DATE VENTE
A6: AS201608 | B6: =VLOOKUP(A6,[1]LISTADHERENT!A$5:H$60,3,0) -> DJUOMBESSY ANTOINE | C6: =IF(E6="ECHEC",0,IF(E6="",0,100000)) -> 0 | D6: =IF(E6="ESPECES",0,0) -> 0 | E6: ECHEC | F6: =TONTNOV20!F6 -> 0 | L6: =TONTNOV20!H6+TONTNOV20!I6 -> 0 | P6: =IF(Q6=0,0,($C$38-Q6)) -> 0
A7: AS201613 | B7: =VLOOKUP(A7,[1]LISTADHERENT!A$5:H$60,3,0) -> HOTCHO BENJAMIN | C7: =IF(E7="ECHEC",0,IF(E7="",0,100000)) -> 0 | D7: =IF(E7="ESPECES",0,0) -> 0 | E7: ECHEC | F7: =TONTNOV20!F7 -> 0 | L7: =TONTNOV20!H7+TONTNOV20!I7 -> 0 | P7: =IF(Q7=0,0,($C$38-Q7)) -> 0
A8: AS201619 | B8: =VLOOKUP(A8,[1]LISTADHERENT!A$5:H$60,3,0) -> KOUATCHO MESSACK | C8: =IF(E8="ECHEC",0,IF(E8="",0,100000)) -> 0 | D8: =IF(E8="ESPECES",0,0) -> 0 | E8: ECHEC | F8: =TONTNOV20!F8 -> 0 | L8: =TONTNOV20!H8+TONTNOV20!I8 -> 0 | P8: =IF(Q8=0,0,($C$38-Q8)) -> 0
A9: AS201617 | B9: =VLOOKUP(A9,[1]LISTADHERENT!A$5:H$60,3,0) -> KOUAMOU MOISE | C9: =IF(E9="ECHEC",0,IF(E9="",0,100000)) -> 0 | D9: =IF(E9="ESPECES",0,0) -> 0 | E9: ECHEC | F9: =TONTNOV20!F9 -> 0 | L9: =TONTNOV20!H9+TONTNOV20!I9 -> 0 | P9: =IF(Q9=0,0,($C$38-Q9)) -> 0
A10: AS201649 | B10: =VLOOKUP(A10,[1]LISTADHERENT!A$5:H$60,3,0) -> MBOGNING TUGMA GUY | C10: =IF(E10="ECHEC",0,IF(E10="",0,100000)) -> 0 | D10: =IF(E10="ESPECES",0,0) -> 0 | E10: ECHEC | F10: =TONTNOV20!F10 -> 0 | L10: =TONTNOV20!H10+TONTNOV20!I10 -> 0 | P10: =IF(Q10=0,0,($C$38-Q10)) -> 0
A11: AS201649 | B11: =VLOOKUP(A11,[1]LISTADHERENT!A$5:H$60,3,0) -> MBOGNING TUGMA GUY | C11: =IF(E11="ECHEC",0,IF(E11="",0,100000)) -> 0 | D11: =IF(E11="ESPECES",0,0) -> 0 | E11: ECHEC | F11: =TONTNOV20!F11 -> 0 | L11: =TONTNOV20!H11+TONTNOV20!I11 -> 0 | P11: =IF(Q11=0,0,($C$38-Q11)) -> 0
A12: AS201639 | B12: =VLOOKUP(A12,[1]LISTADHERENT!A$5:H$60,3,0) -> NANGUEN MARTIN | C12: =IF(E12="ECHEC",0,IF(E12="",0,100000)) -> 0 | D12: =IF(E12="ESPECES",0,0) -> 0 | E12: ECHEC | F12: =TONTNOV20!F12 -> 0 | L12: =TONTNOV20!H12+TONTNOV20!I12 -> 0 | P12: =IF(Q12=0,0,($C$38-Q12)) -> 0
A13: AS201622 | B13: =VLOOKUP(A13,[1]LISTADHERENT!A$5:H$60,3,0) -> NDJOMO ETIENNE | C13: =IF(E13="ECHEC",0,IF(E13="",0,100000)) -> 0 | D13: =IF(E13="ESPECES",0,0) -> 0 | E13: ECHEC | F13: =TONTNOV20!F13 -> 0 | L13: =TONTNOV20!H13+TONTNOV20!I13 -> 0 | P13: =IF(Q13=0,0,($C$38-Q13)) -> 0
A14: AS201624 | B14: =VLOOKUP(A14,[1]LISTADHERENT!A$5:H$60,3,0) -> NGONDIEP CLAUDE | C14: =IF(E14="ECHEC",0,IF(E14="",0,100000)) -> 0 | D14: =IF(E14="ESPECES",0,0) -> 0 | E14: ECHEC | F14: =TONTNOV20!F14 -> 0 | L14: =TONTNOV20!H14+TONTNOV20!I14 -> 0 | P14: =IF(Q14=0,0,($C$38-Q14)) -> 0
A15: AS201614 | B15: =VLOOKUP(A15,[1]LISTADHERENT!A$5:H$60,3,0) -> NKEHE DAVID | C15: =IF(E15="ECHEC",0,IF(E15="",0,100000)) -> 0 | D15: =IF(E15="ESPECES",0,0) -> 0 | E15: ECHEC | F15: =TONTNOV20!F15 -> 225500 | L15: =TONTNOV20!H15+TONTNOV20!I15 -> 0 | P15: =IF(Q15=0,0,($C$38-Q15)) -> 0
A16: AS201629 | B16: =VLOOKUP(A16,[1]LISTADHERENT!A$5:H$60,3,0) -> NKEPSEU DIEUDONNE | C16: =IF(E16="ECHEC",0,IF(E16="",0,100000)) -> 0 | D16: =IF(E16="ESPECES",0,0) -> 0 | E16: ECHEC | F16: =TONTNOV20!F16 -> 0 | L16: =TONTNOV20!H16+TONTNOV20!I16 -> 0 | P16: =IF(Q16=0,0,($C$38-Q16)) -> 0
A17: AS201636 | B17: =VLOOKUP(A17,[1]LISTADHERENT!A$5:H$60,3,0) -> SIMO FONGANG ERIC | C17: =IF(E17="ECHEC",0,IF(E17="",0,100000)) -> 0 | D17: =IF(E17="ESPECES",0,0) -> 0 | E17: ECHEC | F17: =TONTNOV20!F17 -> 233000 | L17: =TONTNOV20!H17+TONTNOV20!I17 -> 0 | P17: =IF(Q17=0,0,($C$38-Q17)) -> 0
... A23: AS201647 | B23: =VLOOKUP(A23,[1]LISTADHERENT!A$5:H$60,3,0) -> YOUMBI EMMANUEL | C23: =IF(E23="ECHEC",0,IF(E23="",0,100000)) -> 0 | D23: =IF(E23="ESPECES",0,0) -> 0 | E23: ECHEC | F23: =TONTNOV20!F23 -> 0 | L23: =TONTNOV20!H23+TONTNOV20!I23 -> 0 | P23: =IF(Q23=0,0,($C$38-Q23)) -> 0
A25: TOTAL | C25: =SUM(C6:C24) -> 0 | D25: =SUM(D6:D24) -> 0 | F25: =SUM(F6:F24) -> 785500 | H25: =SUM(H6:H24) -> 0 | I25: =SUM(I6:I24) -> 0 | L25: =SUM(L6:L24) -> 0 | P25: =SUM(P6:P24) -> 0 | Q25: =SUM(Q6:Q24) -> 0
C27: TONTINE | D27: REMBOURSEMENT PETIT LOT | E27: VENTE PETIT LOT | F27: VENTE LOT PRINCIPAL | G27: SOLDE EN CAISSE | M27: TONTINE + REMB + INTERET VENTE | N27: =C32+D32+Q25 -> 0
M28: VENDUE | N28: =IF(N27>=2800000,1500000*2,1500000) -> 1500000
B29: ESPECES | C29: =SUMIFS(C6:C24,E6:E24,"ESPECES") -> 0 | D29: =SUMIFS(L6:L24,M6:M24,"ESPECES")+SUMIFS(F6:F24,G6:G24,"ESPECES") -> 0 | E29: =SUMIFS(H6:H24,J6:J24,"ESPECES") -> 0 | F29: =SUMIFS(P6:P24,N6:N24,"ESPECES") -> 0 | G29: =C29+D29-E29-F29 -> 0
B30: BANQUE | C30: =SUMIFS(C6:C24,E6:E24,"BANQUE") -> 0 | D30: =SUMIFS(L6:L24,M6:M24,"BANQUE")+SUMIFS(F6:F24,G6:G24,"BANQUE") -> 0 | E30: =SUMIFS(H6:H24,J6:J24,"BANQUE") -> 0 | F30: =SUMIFS(P6:P24,N6:N24,"BANQUE") -> 0 | G30: =C30+D30-E30-F30 -> 0 | M30: PETIT LOT | N30: =N27-N28 -> -1500000
B32: TOTAL | C32: =C29+C30 -> 0 | D32: =D29+D30 -> 0 | E32: =E29+E30 -> 0 | F32: =F29+F30 -> 0 | G32: =G29+G30 -> 0 | M32: RELIQUAT | N32: =N30-H25 -> -1500000 | O32: =N32+TONTNOV20!O32 -> -3474500 | P32: CUMUL
M34: ECHEC TONTINE | N34: =COUNTIFS(E6:E24,"ECHEC")*100000 -> 1800000 | O34: =N34+TONTNOV20!O34 -> 4200000 | P34: CUMUL
B35: INTERET LOT PRINCIPAL | C35: =Q25 -> 0 | M35: ECHEC REMBOURSEMENT | N35: =SUMIFS(F6:F24,G6:G24,"ECHEC") -> 0 | P35: CUMUL
B36: INTERET PETIT LOT | C36: =+I25 -> 0
B38: MONTANT TONTINE | C38: 1500000
B39: MONTANT PETIT LOT A VENDRE | C39: =H25 -> 0

Sheet TONTRESUME
A1: ASSOCIATION | B1: ASELBY | D1: RECAPITULATIF
A2: ANNEE | B2: 2019/2020
A3: TONTINE | B3: 100000
C4: 44185
A5: MATRICULE | B5: NOM ET PRENOM | C5: MONTANT TONTINE | D5: VENTE PETIT LOT | E5: INTERET PETIT LOT | F5: REMBOURSEMENT | G5: MONTANT TONTINE LOT PRINCIPAL | H5: INTERET LOT PRINCIPAL | I5: DATE VENTE | J5: BONUS
A6: AS201608 | B6: =VLOOKUP(A6,[1]LISTADHERENT!A$5:H$60,3,0) -> DJUOMBESSY ANTOINE | C6: =TONTNOV!C6+TONTDEC!C6+TONTJANV!C6+TONTFEV!C6+TONTMARS!C6+TONTAVRIL!C6+TONTMAI!C6+TONTJUIN!C6+TONTJUIL!C6+TONTAOUT!C6+TONTSEPT!C6+TONTOCT!C6+TONTNOV20!C6+TONTDEC20!C6 -> 1200000 | D6: =TONTNOV!H6+TONTDEC!H6+TONTJANV!H6+TONTFEV!H6+TONTMARS!H6+TONTAVRIL!H6+TONTMAI!H6+TONTJUIN!H6+TONTJUIL!H6+TONTAOUT!H6+TONTSEPT!H6+TONTOCT!H6+TONTNOV20!H6+TONTDEC20!H6 -> 0 | E6: =TONTNOV!I6+TONTDEC!I6+TONTJANV!I6+TONTFEV!I6+TONTMARS!I6+TONTAVRIL!I6+TONTMAI!I6+TONTJUIN!I6+TONTJUIL!I6+TONTAOUT!I6+TONTSEPT!I6+TONTOCT!I6+TONTNOV20!I6+TONTDEC20!I6 -> 0 | F6: =TONTNOV!L6+TONTDEC!L6+TONTJANV!L6+TONTFEV!L6+TONTMARS!L6+TONTAVRIL!L6+TONTMAI!L6+TONTJUIN!L6+TONTJUIL!L6+TONTAOUT!L6+TONTSEPT!L6+TONTOCT!L6+TONTNOV20!L6+TONTDEC20!L6 -> 0 | G6: =TONTNOV!P6+TONTDEC!P6+TONTJANV!P6+TONTFEV!P6+TONTMARS!P6+TONTAVRIL!P6+TONTMAI!P6+TONTJUIN!P6+TONTJUIL!P6+TONTAOUT!P6+TONTSEPT!P6+TONTOCT!P6+TONTNOV20!P6+TONTDEC20!P6 -> 0 | H6: =TONTNOV!Q6+TONTDEC!Q6+TONTJANV!Q6+TONTFEV!Q6+TONTMARS!Q6+TONTAVRIL!Q6+TONTMAI!Q6+TONTJUIN!Q6+TONTJUIL!Q6+TONTAOUT!Q6+TONTSEPT!Q6+TONTOCT!Q6+TONTNOV20!Q6+TONTDEC20!Q6 -> 0 | J6: =IF(G6=0,0,(H6-100000)) -> 0
A7: AS201613 | B7: =VLOOKUP(A7,[1]LISTADHERENT!A$5:H$60,3,0) -> HOTCHO BENJAMIN | C7: =TONTNOV!C7+TONTDEC!C7+TONTJANV!C7+TONTFEV!C7+TONTMARS!C7+TONTAVRIL!C7+TONTMAI!C7+TONTJUIN!C7+TONTJUIL!C7+TONTAOUT!C7+TONTSEPT!C7+TONTOCT!C7+TONTNOV20!C7+TONTDEC20!C7 -> 1200000 | D7: =TONTNOV!H7+TONTDEC!H7+TONTJANV!H7+TONTFEV!H7+TONTMARS!H7+TONTAVRIL!H7+TONTMAI!H7+TONTJUIN!H7+TONTJUIL!H7+TONTAOUT!H7+TONTSEPT!H7+TONTOCT!H7+TONTNOV20!H7+TONTDEC20!H7 -> 0 | E7: =TONTNOV!I7+TONTDEC!I7+TONTJANV!I7+TONTFEV!I7+TONTMARS!I7+TONTAVRIL!I7+TONTMAI!I7+TONTJUIN!I7+TONTJUIL!I7+TONTAOUT!I7+TONTSEPT!I7+TONTOCT!I7+TONTNOV20!I7+TONTDEC20!I7 -> 0 | F7: =TONTNOV!L7+TONTDEC!L7+TONTJANV!L7+TONTFEV!L7+TONTMARS!L7+TONTAVRIL!L7+TONTMAI!L7+TONTJUIN!L7+TONTJUIL!L7+TONTAOUT!L7+TONTSEPT!L7+TONTOCT!L7+TONTNOV20!L7+TONTDEC20!L7 -> 0 | G7: =TONTNOV!P7+TONTDEC!P7+TONTJANV!P7+TONTFEV!P7+TONTMARS!P7+TONTAVRIL!P7+TONTMAI!P7+TONTJUIN!P7+TONTJUIL!P7+TONTAOUT!P7+TONTSEPT!P7+TONTOCT!P7+TONTNOV20!P7+TONTDEC20!P7 -> 1400000 | H7: =TONTNOV!Q7+TONTDEC!Q7+TONTJANV!Q7+TONTFEV!Q7+TONTMARS!Q7+TONTAVRIL!Q7+TONTMAI!Q7+TONTJUIN!Q7+TONTJUIL!Q7+TONTAOUT!Q7+TONTSEPT!Q7+TONTOCT!Q7+TONTNOV20!Q7+TONTDEC20!Q7 -> 100000 | I7: 43940 | J7: =IF(G7=0,0,(H7-100000)) -> 0
A8: AS201619 | B8: =VLOOKUP(A8,[1]LISTADHERENT!A$5:H$60,3,0) -> KOUATCHO MESSACK | C8: =TONTNOV!C8+TONTDEC!C8+TONTJANV!C8+TONTFEV!C8+TONTMARS!C8+TONTAVRIL!C8+TONTMAI!C8+TONTJUIN!C8+TONTJUIL!C8+TONTAOUT!C8+TONTSEPT!C8+TONTOCT!C8+TONTNOV20!C8+TONTDEC20!C8 -> 1200000 | D8: =TONTNOV!H8+TONTDEC!H8+TONTJANV!H8+TONTFEV!H8+TONTMARS!H8+TONTAVRIL!H8+TONTMAI!H8+TONTJUIN!H8+TONTJUIL!H8+TONTAOUT!H8+TONTSEPT!H8+TONTOCT!H8+TONTNOV20!H8+TONTDEC20!H8 -> 1584000 | E8: =TONTNOV!I8+TONTDEC!I8+TONTJANV!I8+TONTFEV!I8+TONTMARS!I8+TONTAVRIL!I8+TONTMAI!I8+TONTJUIN!I8+TONTJUIL!I8+TONTAOUT!I8+TONTSEPT!I8+TONTOCT!I8+TONTNOV20!I8+TONTDEC20!I8 -> 44500 | F8: =TONTNOV!L8+TONTDEC!L8+TONTJANV!L8+TONTFEV!L8+TONTMARS!L8+TONTAVRIL!L8+TONTMAI!L8+TONTJUIN!L8+TONTJUIL!L8+TONTAOUT!L8+TONTSEPT!L8+TONTOCT!L8+TONTNOV20!L8+TONTDEC20!L8 -> 1628500 | G8: =TONTNOV!P8+TONTDEC!P8+TONTJANV!P8+TONTFEV!P8+TONTMARS!P8+TONTAVRIL!P8+TONTMAI!P8+TONTJUIN!P8+TONTJUIL!P8+TONTAOUT!P8+TONTSEPT!P8+TONTOCT!P8+TONTNOV20!P8+TONTDEC20!P8 -> 1250000 | H8: =TONTNOV!Q8+TONTDEC!Q8+TONTJANV!Q8+TONTFEV!Q8+TONTMARS!Q8+TONTAVRIL!Q8+TONTMAI!Q8+TONTJUIN!Q8+TONTJUIL!Q8+TONTAOUT!Q8+TONTSEPT!Q8+TONTOCT!Q8+TONTNOV20!Q8+TONTDEC20!Q8 -> 250000 | I8: 43819 | J8: =IF(G8=0,0,(H8-100000)) -> 150000
A9: AS201617 | B9: =VLOOKUP(A9,[1]LISTADHERENT!A$5:H$60,3,0) -> KOUAMOU MOISE | C9: =TONTNOV!C9+TONTDEC!C9+TONTJANV!C9+TONTFEV!C9+TONTMARS!C9+TONTAVRIL!C9+TONTMAI!C9+TONTJUIN!C9+TONTJUIL!C9+TONTAOUT!C9+TONTSEPT!C9+TONTOCT!C9+TONTNOV20!C9+TONTDEC20!C9 -> 1200000 | D9: =TONTNOV!H9+TONTDEC!H9+TONTJANV!H9+TONTFEV!H9+TONTMARS!H9+TONTAVRIL!H9+TONTMAI!H9+TONTJUIN!H9+TONTJUIL!H9+TONTAOUT!H9+TONTSEPT!H9+TONTOCT!H9+TONTNOV20!H9+TONTDEC20!H9 -> 0 | E9: =TONTNOV!I9+TONTDEC!I9+TONTJANV!I9+TONTFEV!I9+TONTMARS!I9+TONTAVRIL!I9+TONTMAI!I9+TONTJUIN!I9+TONTJUIL!I9+TONTAOUT!I9+TONTSEPT!I9+TONTOCT!I9+TONTNOV20!I9+TONTDEC20!I9 -> 0 | F9: =TONTNOV!L9+TONTDEC!L9+TONTJANV!L9+TONTFEV!L9+TONTMARS!L9+TONTAVRIL!L9+TONTMAI!L9+TONTJUIN!L9+TONTJUIL!L9+TONTAOUT!L9+TONTSEPT!L9+TONTOCT!L9+TONTNOV20!L9+TONTDEC20!L9 -> 0 | G9: =TONTNOV!P9+TONTDEC!P9+TONTJANV!P9+TONTFEV!P9+TONTMARS!P9+TONTAVRIL!P9+TONTMAI!P9+TONTJUIN!P9+TONTJUIL!P9+TONTAOUT!P9+TONTSEPT!P9+TONTOCT!P9+TONTNOV20!P9+TONTDEC20!P9 -> 1365000 | H9: =TONTNOV!Q9+TONTDEC!Q9+TONTJANV!Q9+TONTFEV!Q9+TONTMARS!Q9+TONTAVRIL!Q9+TONTMAI!Q9+TONTJUIN!Q9+TONTJUIL!Q9+TONTAOUT!Q9+TONTSEPT!Q9+TONTOCT!Q9+TONTNOV20!Q9+TONTDEC20!Q9 -> 135000 | I9: 43912 | J9: =IF(G9=0,0,(H9-100000)) -> 35000
A10: AS201649 | B10: =VLOOKUP(A10,[1]LISTADHERENT!A$5:H$60,3,0) -> MBOGNING TUGMA GUY | C10: =TONTNOV!C10+TONTDEC!C10+TONTJANV!C10+TONTFEV!C10+TONTMARS!C10+TONTAVRIL!C10+TONTMAI!C10+TONTJUIN!C10+TONTJUIL!C10+TONTAOUT!C10+TONTSEPT!C10+TONTOCT!C10+TONTNOV20!C10+TONTDEC20!C10 -> 1200000 | D10: =TONTNOV!H10+TONTDEC!H10+TONTJANV!H10+TONTFEV!H10+TONTMARS!H10+TONTAVRIL!H10+TONTMAI!H10+TONTJUIN!H10+TONTJUIL!H10+TONTAOUT!H10+TONTSEPT!H10+TONTOCT!H10+TONTNOV20!H10+TONTDEC20!H10 -> 759000 | E10: =TONTNOV!I10+TONTDEC!I10+TONTJANV!I10+TONTFEV!I10+TONTMARS!I10+TONTAVRIL!I10+TONTMAI!I10+TONTJUIN!I10+TONTJUIL!I10+TONTAOUT!I10+TONTSEPT!I10+TONTOCT!I10+TONTNOV20!I10+TONTDEC20!I10 -> 17500 | F10: =TONTNOV!L10+TONTDEC!L10+TONTJANV!L10+TONTFEV!L10+TONTMARS!L10+TONTAVRIL!L10+TONTMAI!L10+TONTJUIN!L10+TONTJUIL!L10+TONTAOUT!L10+TONTSEPT!L10+TONTOCT!L10+TONTNOV20!L10+TONTDEC20!L10 -> 776500 | G10: =TONTNOV!P10+TONTDEC!P10+TONTJANV!P10+TONTFEV!P10+TONTMARS!P10+TONTAVRIL!P10+TONTMAI!P10+TONTJUIN!P10+TONTJUIL!P10+TONTAOUT!P10+TONTSEPT!P10+TONTOCT!P10+TONTNOV20!P10+TONTDEC20!P10 -> 1270000 | H10: =TONTNOV!Q10+TONTDEC!Q10+TONTJANV!Q10+TONTFEV!Q10+TONTMARS!Q10+TONTAVRIL!Q10+TONTMAI!Q10+TONTJUIN!Q10+TONTJUIL!Q10+TONTAOUT!Q10+TONTSEPT!Q10+TONTOCT!Q10+TONTNOV20!Q10+TONTDEC20!Q10 -> 230000 | I10: 43849 | J10: =IF(G10=0,0,(H10-100000)) -> 130000
A11: AS201649 | B11: =VLOOKUP(A11,[1]LISTADHERENT!A$5:H$60,3,0) -> MBOGNING TUGMA GUY | C11: =TONTNOV!C11+TONTDEC!C11+TONTJANV!C11+TONTFEV!C11+TONTMARS!C11+TONTAVRIL!C11+TONTMAI!C11+TONTJUIN!C11+TONTJUIL!C11+TONTAOUT!C11+TONTSEPT!C11+TONTOCT!C11+TONTNOV20!C11+TONTDEC20!C11 -> 1200000 | D11: =TONTNOV!H11+TONTDEC!H11+TONTJANV!H11+TONTFEV!H11+TONTMARS!H11+TONTAVRIL!H11+TONTMAI!H11+TONTJUIN!H11+TONTJUIL!H11+TONTAOUT!H11+TONTSEPT!H11+TONTOCT!H11+TONTNOV20!H11+TONTDEC20!H11 -> 0 | E11: =TONTNOV!I11+TONTDEC!I11+TONTJANV!I11+TONTFEV!I11+TONTMARS!I11+TONTAVRIL!I11+TONTMAI!I11+TONTJUIN!I11+TONTJUIL!I11+TONTAOUT!I11+TONTSEPT!I11+TONTOCT!I11+TONTNOV20!I11+TONTDEC20!I11 -> 0 | F11: =TONTNOV!L11+TONTDEC!L11+TONTJANV!L11+TONTFEV!L11+TONTMARS!L11+TONTAVRIL!L11+TONTMAI!L11+TONTJUIN!L11+TONTJUIL!L11+TONTAOUT!L11+TONTSEPT!L11+TONTOCT!L11+TONTNOV20!L11+TONTDEC20!L11 -> 0 | G11: =TONTNOV!P11+TONTDEC!P11+TONTJANV!P11+TONTFEV!P11+TONTMARS!P11+TONTAVRIL!P11+TONTMAI!P11+TONTJUIN!P11+TONTJUIL!P11+TONTAOUT!P11+TONTSEPT!P11+TONTOCT!P11+TONTNOV20!P11+TONTDEC20!P11 -> 1255000 | H11: =TONTNOV!Q11+TONTDEC!Q11+TONTJANV!Q11+TONTFEV!Q11+TONTMARS!Q11+TONTAVRIL!Q11+TONTMAI!Q11+TONTJUIN!Q11+TONTJUIL!Q11+TONTAOUT!Q11+TONTSEPT!Q11+TONTOCT!Q11+TONTNOV20!Q11+TONTDEC20!Q11 -> 245000 | I11: 44031 | J11: =IF(G11=0,0,(H11-100000)) -> 145000
A12: AS201639 | B12: =VLOOKUP(A12,[1]LISTADHERENT!A$5:H$60,3,0) -> NANGUEN MARTIN | C12: =TONTNOV!C12+TONTDEC!C12+TONTJANV!C12+TONTFEV!C12+TONTMARS!C12+TONTAVRIL!C12+TONTMAI!C12+TONTJUIN!C12+TONTJUIL!C12+TONTAOUT!C12+TONTSEPT!C12+TONTOCT!C12+TONTNOV20!C12+TONTDEC20!C12 -> 1200000 | D12: =TONTNOV!H12+TONTDEC!H12+TONTJANV!H12+TONTFEV!H12+TONTMARS!H12+TONTAVRIL!H12+TONTMAI!H12+TONTJUIN!H12+TONTJUIL!H12+TONTAOUT!H12+TONTSEPT!H12+TONTOCT!H12+TONTNOV20!H12+TONTDEC20!H12 -> 0 | E12: =TONTNOV!I12+TONTDEC!I12+TONTJANV!I12+TONTFEV!I12+TONTMARS!I12+TONTAVRIL!I12+TONTMAI!I12+TONTJUIN!I12+TONTJUIL!I12+TONTAOUT!I12+TONTSEPT!I12+TONTOCT!I12+TONTNOV20!I12+TONTDEC20!I12 -> 0 | F12: =TONTNOV!L12+TONTDEC!L12+TONTJANV!L12+TONTFEV!L12+TONTMARS!L12+TONTAVRIL!L12+TONTMAI!L12+TONTJUIN!L12+TONTJUIL!L12+TONTAOUT!L12+TONTSEPT!L12+TONTOCT!L12+TONTNOV20!L12+TONTDEC20!L12 -> 0 | G12: =TONTNOV!P12+TONTDEC!P12+TONTJANV!P12+TONTFEV!P12+TONTMARS!P12+TONTAVRIL!P12+TONTMAI!P12+TONTJUIN!P12+TONTJUIL!P12+TONTAOUT!P12+TONTSEPT!P12+TONTOCT!P12+TONTNOV20!P12+TONTDEC20!P12 -> 1390000 | H12: =TONTNOV!Q12+TONTDEC!Q12+TONTJANV!Q12+TONTFEV!Q12+TONTMARS!Q12+TONTAVRIL!Q12+TONTMAI!Q12+TONTJUIN!Q12+TONTJUIL!Q12+TONTAOUT!Q12+TONTSEPT!Q12+TONTOCT!Q12+TONTNOV20!Q12+TONTDEC20!Q12 -> 110000 | I12: 44122 | J12: =IF(G12=0,0,(H12-100000)) -> 10000
A13: AS201622 | B13: =VLOOKUP(A13,[1]LISTADHERENT!A$5:H$60,3,0) -> NDJOMO ETIENNE | C13: =TONTNOV!C13+TONTDEC!C13+TONTJANV!C13+TONTFEV!C13+TONTMARS!C13+TONTAVRIL!C13+TONTMAI!C13+TONTJUIN!C13+TONTJUIL!C13+TONTAOUT!C13+TONTSEPT!C13+TONTOCT!C13+TONTNOV20!C13+TONTDEC20!C13 -> 1200000 | D13: =TONTNOV!H13+TONTDEC!H13+TONTJANV!H13+TONTFEV!H13+TONTMARS!H13+TONTAVRIL!H13+TONTMAI!H13+TONTJUIN!H13+TONTJUIL!H13+TONTAOUT!H13+TONTSEPT!H13+TONTOCT!H13+TONTNOV20!H13+TONTDEC20!H13 -> 526000 | E13: =TONTNOV!I13+TONTDEC!I13+TONTJANV!I13+TONTFEV!I13+TONTMARS!I13+TONTAVRIL!I13+TONTMAI!I13+TONTJUIN!I13+TONTJUIL!I13+TONTAOUT!I13+TONTSEPT!I13+TONTOCT!I13+TONTNOV20!I13+TONTDEC20!I13 -> 7500 | F13: =TONTNOV!L13+TONTDEC!L13+TONTJANV!L13+TONTFEV!L13+TONTMARS!L13+TONTAVRIL!L13+TONTMAI!L13+TONTJUIN!L13+TONTJUIL!L13+TONTAOUT!L13+TONTSEPT!L13+TONTOCT!L13+TONTNOV20!L13+TONTDEC20!L13 -> 533500 | G13: =TONTNOV!P13+TONTDEC!P13+TONTJANV!P13+TONTFEV!P13+TONTMARS!P13+TONTAVRIL!P13+TONTMAI!P13+TONTJUIN!P13+TONTJUIL!P13+TONTAOUT!P13+TONTSEPT!P13+TONTOCT!P13+TONTNOV20!P13+TONTDEC20!P13 -> 1400000 | H13: =TONTNOV!Q13+TONTDEC!Q13+TONTJANV!Q13+TONTFEV!Q13+TONTMARS!Q13+TONTAVRIL!Q13+TONTMAI!Q13+TONTJUIN!Q13+TONTJUIL!Q13+TONTAOUT!Q13+TONTSEPT!Q13+TONTOCT!Q13+TONTNOV20!Q13+TONTDEC20!Q13 -> 100000 | I13: 43940 | J13: =IF(G13=0,0,(H13-100000)) -> 0
A14: AS201624 | B14: =VLOOKUP(A14,[1]LISTADHERENT!A$5:H$60,3,0) -> NGONDIEP CLAUDE | C14: =TONTNOV!C14+TONTDEC!C14+TONTJANV!C14+TONTFEV!C14+TONTMARS!C14+TONTAVRIL!C14+TONTMAI!C14+TONTJUIN!C14+TONTJUIL!C14+TONTAOUT!C14+TONTSEPT!C14+TONTOCT!C14+TONTNOV20!C14+TONTDEC20!C14 -> 1200000 | D14: =TONTNOV!H14+TONTDEC!H14+TONTJANV!H14+TONTFEV!H14+TONTMARS!H14+TONTAVRIL!H14+TONTMAI!H14+TONTJUIN!H14+TONTJUIL!H14+TONTAOUT!H14+TONTSEPT!H14+TONTOCT!H14+TONTNOV20!H14+TONTDEC20!H14 -> 99500 | E14: =TONTNOV!I14+TONTDEC!I14+TONTJANV!I14+TONTFEV!I14+TONTMARS!I14+TONTAVRIL!I14+TONTMAI!I14+TONTJUIN!I14+TONTJUIL!I14+TONTAOUT!I14+TONTSEPT!I14+TONTOCT!I14+TONTNOV20!I14+TONTDEC20!I14 -> 4000 | F14: =TONTNOV!L14+TONTDEC!L14+TONTJANV!L14+TONTFEV!L14+TONTMARS!L14+TONTAVRIL!L14+TONTMAI!L14+TONTJUIN!L14+TONTJUIL!L14+TONTAOUT!L14+TONTSEPT!L14+TONTOCT!L14+TONTNOV20!L14+TONTDEC20!L14 -> 103500 | G14: =TONTNOV!P14+TONTDEC!P14+TONTJANV!P14+TONTFEV!P14+TONTMARS!P14+TONTAVRIL!P14+TONTMAI!P14+TONTJUIN!P14+TONTJUIL!P14+TONTAOUT!P14+TONTSEPT!P14+TONTOCT!P14+TONTNOV20!P14+TONTDEC20!P14 -> 1370000 | H14: =TONTNOV!Q14+TONTDEC!Q14+TONTJANV!Q14+TONTFEV!Q14+TONTMARS!Q14+TONTAVRIL!Q14+TONTMAI!Q14+TONTJUIN!Q14+TONTJUIL!Q14+TONTAOUT!Q14+TONTSEPT!Q14+TONTOCT!Q14+TONTNOV20!Q14+TONTDEC20!Q14 -> 130000 | I14: 43968 | J14: =IF(G14=0,0,(H14-100000)) -> 30000
A15: AS201614 | B15: =VLOOKUP(A15,[1]LISTADHERENT!A$5:H$60,3,0) -> NKEHE DAVID | C15: =TONTNOV!C15+TONTDEC!C15+TONTJANV!C15+TONTFEV!C15+TONTMARS!C15+TONTAVRIL!C15+TONTMAI!C15+TONTJUIN!C15+TONTJUIL!C15+TONTAOUT!C15+TONTSEPT!C15+TONTOCT!C15+TONTNOV20!C15+TONTDEC20!C15 -> 700000 | D15: =TONTNOV!H15+TONTDEC!H15+TONTJANV!H15+TONTFEV!H15+TONTMARS!H15+TONTAVRIL!H15+TONTMAI!H15+TONTJUIN!H15+TONTJUIL!H15+TONTAOUT!H15+TONTSEPT!H15+TONTOCT!H15+TONTNOV20!H15+TONTDEC20!H15 -> 531000 | E15: =TONTNOV!I15+TONTDEC!I15+TONTJANV!I15+TONTFEV!I15+TONTMARS!I15+TONTAVRIL!I15+TONTMAI!I15+TONTJUIN!I15+TONTJUIL!I15+TONTAOUT!I15+TONTSEPT!I15+TONTOCT!I15+TONTNOV20!I15+TONTDEC20!I15 -> 18000 | F15: =TONTNOV!L15+TONTDEC!L15+TONTJANV!L15+TONTFEV!L15+TONTMARS!L15+TONTAVRIL!L15+TONTMAI!L15+TONTJUIN!L15+TONTJUIL!L15+TONTAOUT!L15+TONTSEPT!L15+TONTOCT!L15+TONTNOV20!L15+TONTDEC20!L15 -> 549000 | G15: =TONTNOV!P15+TONTDEC!P15+TONTJANV!P15+TONTFEV!P15+TONTMARS!P15+TONTAVRIL!P15+TONTMAI!P15+TONTJUIN!P15+TONTJUIL!P15+TONTAOUT!P15+TONTSEPT!P15+TONTOCT!P15+TONTNOV20!P15+TONTDEC20!P15 -> 1350000 | H15: =TONTNOV!Q15+TONTDEC!Q15+TONTJANV!Q15+TONTFEV!Q15+TONTMARS!Q15+TONTAVRIL!Q15+TONTMAI!Q15+TONTJUIN!Q15+TONTJUIL!Q15+TONTAOUT!Q15+TONTSEPT!Q15+TONTOCT!Q15+TONTNOV20!Q15+TONTDEC20!Q15 -> 150000 | I15: 43793 | J15: =IF(G15=0,0,(H15-100000)) -> 50000
A16: AS201629 | B16: =VLOOKUP(A16,[1]LISTADHERENT!A$5:H$60,3,0) -> NKEPSEU DIEUDONNE | C16: =TONTNOV!C16+TONTDEC!C16+TONTJANV!C16+TONTFEV!C16+TONTMARS!C16+TONTAVRIL!C16+TONTMAI!C16+TONTJUIN!C16+TONTJUIL!C16+TONTAOUT!C16+TONTSEPT!C16+TONTOCT!C16+TONTNOV20!C16+TONTDEC20!C16 -> 1200000 | D16: =TONTNOV!H16+TONTDEC!H16+TONTJANV!H16+TONTFEV!H16+TONTMARS!H16+TONTAVRIL!H16+TONTMAI!H16+TONTJUIN!H16+TONTJUIL!H16+TONTAOUT!H16+TONTSEPT!H16+TONTOCT!H16+TONTNOV20!H16+TONTDEC20!H16 -> 400000 | E16: =TONTNOV!I16+TONTDEC!I16+TONTJANV!I16+TONTFEV!I16+TONTMARS!I16+TONTAVRIL!I16+TONTMAI!I16+TONTJUIN!I16+TONTJUIL!I16+TONTAOUT!I16+TONTSEPT!I16+TONTOCT!I16+TONTNOV20!I16+TONTDEC20!I16 -> 6000 | F16: =TONTNOV!L16+TONTDEC!L16+TONTJANV!L16+TONTFEV!L16+TONTMARS!L16+TONTAVRIL!L16+TONTMAI!L16+TONTJUIN!L16+TONTJUIL!L16+TONTAOUT!L16+TONTSEPT!L16+TONTOCT!L16+TONTNOV20!L16+TONTDEC20!L16 -> 406000 | G16: =TONTNOV!P16+TONTDEC!P16+TONTJANV!P16+TONTFEV!P16+TONTMARS!P16+TONTAVRIL!P16+TONTMAI!P16+TONTJUIN!P16+TONTJUIL!P16+TONTAOUT!P16+TONTSEPT!P16+TONTOCT!P16+TONTNOV20!P16+TONTDEC20!P16 -> 1400000 | H16: =TONTNOV!Q16+TONTDEC!Q16+TONTJANV!Q16+TONTFEV!Q16+TONTMARS!Q16+TONTAVRIL!Q16+TONTMAI!Q16+TONTJUIN!Q16+TONTJUIL!Q16+TONTAOUT!Q16+TONTSEPT!Q16+TONTOCT!Q16+TONTNOV20!Q16+TONTDEC20!Q16 -> 100000 | I16: 43877 | J16: =IF(G16=0,0,(H16-100000)) -> 0
A17: AS201636 | B17: =VLOOKUP(A17,[1]LISTADHERENT!A$5:H$60,3,0) -> SIMO FONGANG ERIC | C17: =TONTNOV!C17+TONTDEC!C17+TONTJANV!C17+TONTFEV!C17+TONTMARS!C17+TONTAVRIL!C17+TONTMAI!C17+TONTJUIN!C17+TONTJUIL!C17+TONTAOUT!C17+TONTSEPT!C17+TONTOCT!C17+TONTNOV20!C17+TONTDEC20!C17 -> 1200000 | D17: =TONTNOV!H17+TONTDEC!H17+TONTJANV!H17+TONTFEV!H17+TONTMARS!H17+TONTAVRIL!H17+TONTMAI!H17+TONTJUIN!H17+TONTJUIL!H17+TONTAOUT!H17+TONTSEPT!H17+TONTOCT!H17+TONTNOV20!H17+TONTDEC20!H17 -> 400000 | E17: =TONTNOV!I17+TONTDEC!I17+TONTJANV!I17+TONTFEV!I17+TONTMARS!I17+TONTAVRIL!I17+TONTMAI!I17+TONTJUIN!I17+TONTJUIL!I17+TONTAOUT!I17+TONTSEPT!I17+TONTOCT!I17+TONTNOV20!I17+TONTDEC20!I17 -> 13500 | F17: =TONTNOV!L17+TONTDEC!L17+TONTJANV!L17+TONTFEV!L17+TONTMARS!L17+TONTAVRIL!L17+TONTMAI!L17+TONTJUIN!L17+TONTJUIL!L17+TONTAOUT!L17+TONTSEPT!L17+TONTOCT!L17+TONTNOV20!L17+TONTDEC20!L17 -> 413500 | G17: =TONTNOV!P17+TONTDEC!P17+TONTJANV!P17+TONTFEV!P17+TONTMARS!P17+TONTAVRIL!P17+TONTMAI!P17+TONTJUIN!P17+TONTJUIL!P17+TONTAOUT!P17+TONTSEPT!P17+TONTOCT!P17+TONTNOV20!P17+TONTDEC20!P17 -> 1255000 | H17: =TONTNOV!Q17+TONTDEC!Q17+TONTJANV!Q17+TONTFEV!Q17+TONTMARS!Q17+TONTAVRIL!Q17+TONTMAI!Q17+TONTJUIN!Q17+TONTJUIL!Q17+TONTAOUT!Q17+TONTSEPT!Q17+TONTOCT!Q17+TONTNOV20!Q17+TONTDEC20!Q17 -> 245000 | I17: 43819 | J17: =IF(G17=0,0,(H17-100000)) -> 145000
A18: AS201636 | B18: =VLOOKUP(A18,[1]LISTADHERENT!A$5:H$60,3,0) -> SIMO FONGANG ERIC | C18: =TONTNOV!C18+TONTDEC!C18+TONTJANV!C18+TONTFEV!C18+TONTMARS!C18+TONTAVRIL!C18+TONTMAI!C18+TONTJUIN!C18+TONTJUIL!C18+TONTAOUT!C18+TONTSEPT!C18+TONTOCT!C18+TONTNOV20!C18+TONTDEC20!C18 -> 1200000 | D18: =TONTNOV!H18+TONTDEC!H18+TONTJANV!H18+TONTFEV!H18+TONTMARS!H18+TONTAVRIL!H18+TONTMAI!H18+TONTJUIN!H18+TONTJUIL!H18+TONTAOUT!H18+TONTSEPT!H18+TONTOCT!H18+TONTNOV20!H18+TONTDEC20!H18 -> 0 | E18: =TONTNOV!I18+TONTDEC!I18+TONTJANV!I18+TONTFEV!I18+TONTMARS!I18+TONTAVRIL!I18+TONTMAI!I18+TONTJUIN!I18+TONTJUIL!I18+TONTAOUT!I18+TONTSEPT!I18+TONTOCT!I18+TONTNOV20!I18+TONTDEC20!I18 -> 0 | F18: =TONTNOV!L18+TONTDEC!L18+TONTJANV!L18+TONTFEV!L18+TONTMARS!L18+TONTAVRIL!L18+TONTMAI!L18+TONTJUIN!L18+TONTJUIL!L18+TONTAOUT!L18+TONTSEPT!L18+TONTOCT!L18+TONTNOV20!L18+TONTDEC20!L18 -> 0 | G18: =TONTNOV!P18+TONTDEC!P18+TONTJANV!P18+TONTFEV!P18+TONTMARS!P18+TONTAVRIL!P18+TONTMAI!P18+TONTJUIN!P18+TONTJUIL!P18+TONTAOUT!P18+TONTSEPT!P18+TONTOCT!P18+TONTNOV20!P18+TONTDEC20!P18 -> 1254000 | H18: =TONTNOV!Q18+TONTDEC!Q18+TONTJANV!Q18+TONTFEV!Q18+TONTMARS!Q18+TONTAVRIL!Q18+TONTMAI!Q18+TONTJUIN!Q18+TONTJUIL!Q18+TONTAOUT!Q18+TONTSEPT!Q18+TONTOCT!Q18+TONTNOV20!Q18+TONTDEC20!Q18 -> 246000 | I18: 44031 | J18: =IF(G18=0,0,(H18-100000)) -> 146000
A19: AS201637 | B19: =VLOOKUP(A19,[1]LISTADHERENT!A$5:H$60,3,0) -> SIME MATHIEU | C19: =TONTNOV!C19+TONTDEC!C19+TONTJANV!C19+TONTFEV!C19+TONTMARS!C19+TONTAVRIL!C19+TONTMAI!C19+TONTJUIN!C19+TONTJUIL!C19+TONTAOUT!C19+TONTSEPT!C19+TONTOCT!C19+TONTNOV20!C19+TONTDEC20!C19 -> 1200000 | D19: =TONTNOV!H19+TONTDEC!H19+TONTJANV!H19+TONTFEV!H19+TONTMARS!H19+TONTAVRIL!H19+TONTMAI!H19+TONTJUIN!H19+TONTJUIL!H19+TONTAOUT!H19+TONTSEPT!H19+TONTOCT!H19+TONTNOV20!H19+TONTDEC20!H19 -> 200000 | E19: =TONTNOV!I19+TONTDEC!I19+TONTJANV!I19+TONTFEV!I19+TONTMARS!I19+TONTAVRIL!I19+TONTMAI!I19+TONTJUIN!I19+TONTJUIL!I19+TONTAOUT!I19+TONTSEPT!I19+TONTOCT!I19+TONTNOV20!I19+TONTDEC20!I19 -> 8000 | F19: =TONTNOV!L19+TONTDEC!L19+TONTJANV!L19+TONTFEV!L19+TONTMARS!L19+TONTAVRIL!L19+TONTMAI!L19+TONTJUIN!L19+TONTJUIL!L19+TONTAOUT!L19+TONTSEPT!L19+TONTOCT!L19+TONTNOV20!L19+TONTDEC20!L19 -> 208000 | G19: =TONTNOV!P19+TONTDEC!P19+TONTJANV!P19+TONTFEV!P19+TONTMARS!P19+TONTAVRIL!P19+TONTMAI!P19+TONTJUIN!P19+TONTJUIL!P19+TONTAOUT!P19+TONTSEPT!P19+TONTOCT!P19+TONTNOV20!P19+TONTDEC20!P19 -> 1340000 | H19: =TONTNOV!Q19+TONTDEC!Q19+TONTJANV!Q19+TONTFEV!Q19+TONTMARS!Q19+TONTAVRIL!Q19+TONTMAI!Q19+TONTJUIN!Q19+TONTJUIL!Q19+TONTAOUT!Q19+TONTSEPT!Q19+TONTOCT!Q19+TONTNOV20!Q19+TONTDEC20!Q19 -> 160000 | I19: 44059 | J19: =IF(G19=0,0,(H19-100000)) -> 60000
A20: AS201637 | B20: =VLOOKUP(A20,[1]LISTADHERENT!A$5:H$60,3,0) -> SIME MATHIEU | C20: =TONTNOV!C20+TONTDEC!C20+TONTJANV!C20+TONTFEV!C20+TONTMARS!C20+TONTAVRIL!C20+TONTMAI!C20+TONTJUIN!C20+TONTJUIL!C20+TONTAOUT!C20+TONTSEPT!C20+TONTOCT!C20+TONTNOV20!C20+TONTDEC20!C20 -> 1200000 | D20: =TONTNOV!H20+TONTDEC!H20+TONTJANV!H20+TONTFEV!H20+TONTMARS!H20+TONTAVRIL!H20+TONTMAI!H20+TONTJUIN!H20+TONTJUIL!H20+TONTAOUT!H20+TONTSEPT!H20+TONTOCT!H20+TONTNOV20!H20+TONTDEC20!H20 -> 0 | E20: =TONTNOV!I20+TONTDEC!I20+TONTJANV!I20+TONTFEV!I20+TONTMARS!I20+TONTAVRIL!I20+TONTMAI!I20+TONTJUIN!I20+TONTJUIL!I20+TONTAOUT!I20+TONTSEPT!I20+TONTOCT!I20+TONTNOV20!I20+TONTDEC20!I20 -> 0 | F20: =TONTNOV!L20+TONTDEC!L20+TONTJANV!L20+TONTFEV!L20+TONTMARS!L20+TONTAVRIL!L20+TONTMAI!L20+TONTJUIN!L20+TONTJUIL!L20+TONTAOUT!L20+TONTSEPT!L20+TONTOCT!L20+TONTNOV20!L20+TONTDEC20!L20 -> 0 | G20: =TONTNOV!P20+TONTDEC!P20+TONTJANV!P20+TONTFEV!P20+TONTMARS!P20+TONTAVRIL!P20+TONTMAI!P20+TONTJUIN!P20+TONTJUIL!P20+TONTAOUT!P20+TONTSEPT!P20+TONTOCT!P20+TONTNOV20!P20+TONTDEC20!P20 -> 0 | H20: =TONTNOV!Q20+TONTDEC!Q20+TONTJANV!Q20+TONTFEV!Q20+TONTMARS!Q20+TONTAVRIL!Q20+TONTMAI!Q20+TONTJUIN!Q20+TONTJUIL!Q20+TONTAOUT!Q20+TONTSEPT!Q20+TONTOCT!Q20+TONTNOV20!Q20+TONTDEC20!Q20 -> 0 | J20: =IF(G20=0,0,(H20-100000)) -> 0
A21: AS201641 | B21: =VLOOKUP(A21,[1]LISTADHERENT!A$5:H$60,3,0) -> TCHOUAMOU MATHIEU | C21: =TONTNOV!C21+TONTDEC!C21+TONTJANV!C21+TONTFEV!C21+TONTMARS!C21+TONTAVRIL!C21+TONTMAI!C21+TONTJUIN!C21+TONTJUIL!C21+TONTAOUT!C21+TONTSEPT!C21+TONTOCT!C21+TONTNOV20!C21+TONTDEC20!C21 -> 1200000 | D21: =TONTNOV!H21+TONTDEC!H21+TONTJANV!H21+TONTFEV!H21+TONTMARS!H21+TONTAVRIL!H21+TONTMAI!H21+TONTJUIN!H21+TONTJUIL!H21+TONTAOUT!H21+TONTSEPT!H21+TONTOCT!H21+TONTNOV20!H21+TONTDEC20!H21 -> 638000 | E21: =TONTNOV!I21+TONTDEC!I21+TONTJANV!I21+TONTFEV!I21+TONTMARS!I21+TONTAVRIL!I21+TONTMAI!I21+TONTJUIN!I21+TONTJUIL!I21+TONTAOUT!I21+TONTSEPT!I21+TONTOCT!I21+TONTNOV20!I21+TONTDEC20!I21 -> 8500 | F21: =TONTNOV!L21+TONTDEC!L21+TONTJANV!L21+TONTFEV!L21+TONTMARS!L21+TONTAVRIL!L21+TONTMAI!L21+TONTJUIN!L21+TONTJUIL!L21+TONTAOUT!L21+TONTSEPT!L21+TONTOCT!L21+TONTNOV20!L21+TONTDEC20!L21 -> 646500 | G21: =TONTNOV!P21+TONTDEC!P21+TONTJANV!P21+TONTFEV!P21+TONTMARS!P21+TONTAVRIL!P21+TONTMAI!P21+TONTJUIN!P21+TONTJUIL!P21+TONTAOUT!P21+TONTSEPT!P21+TONTOCT!P21+TONTNOV20!P21+TONTDEC20!P21 -> 1400000 | H21: =TONTNOV!Q21+TONTDEC!Q21+TONTJANV!Q21+TONTFEV!Q21+TONTMARS!Q21+TONTAVRIL!Q21+TONTMAI!Q21+TONTJUIN!Q21+TONTJUIL!Q21+TONTAOUT!Q21+TONTSEPT!Q21+TONTOCT!Q21+TONTNOV20!Q21+TONTDEC20!Q21 -> 100000 | I21: 44094 | J21: =IF(G21=0,0,(H21-100000)) -> 0
A22: AS201644 | B22: =VLOOKUP(A22,[1]LISTADHERENT!A$5:H$60,3,0) -> TIEYAM ERNEST | C22: =TONTNOV!C22+TONTDEC!C22+TONTJANV!C22+TONTFEV!C22+TONTMARS!C22+TONTAVRIL!C22+TONTMAI!C22+TONTJUIN!C22+TONTJUIL!C22+TONTAOUT!C22+TONTSEPT!C22+TONTOCT!C22+TONTNOV20!C22+TONTDEC20!C22 -> 1100000 | D22: =TONTNOV!H22+TONTDEC!H22+TONTJANV!H22+TONTFEV!H22+TONTMARS!H22+TONTAVRIL!H22+TONTMAI!H22+TONTJUIN!H22+TONTJUIL!H22+TONTAOUT!H22+TONTSEPT!H22+TONTOCT!H22+TONTNOV20!H22+TONTDEC20!H22 -> 800000 | E22: =TONTNOV!I22+TONTDEC!I22+TONTJANV!I22+TONTFEV!I22+TONTMARS!I22+TONTAVRIL!I22+TONTMAI!I22+TONTJUIN!I22+TONTJUIL!I22+TONTAOUT!I22+TONTSEPT!I22+TONTOCT!I22+TONTNOV20!I22+TONTDEC20!I22 -> 32000 | F22: =TONTNOV!L22+TONTDEC!L22+TONTJANV!L22+TONTFEV!L22+TONTMARS!L22+TONTAVRIL!L22+TONTMAI!L22+TONTJUIN!L22+TONTJUIL!L22+TONTAOUT!L22+TONTSEPT!L22+TONTOCT!L22+TONTNOV20!L22+TONTDEC20!L22 -> 832000 | G22: =TONTNOV!P22+TONTDEC!P22+TONTJANV!P22+TONTFEV!P22+TONTMARS!P22+TONTAVRIL!P22+TONTMAI!P22+TONTJUIN!P22+TONTJUIL!P22+TONTAOUT!P22+TONTSEPT!P22+TONTOCT!P22+TONTNOV20!P22+TONTDEC20!P22 -> 1305000 | H22: =TONTNOV!Q22+TONTDEC!Q22+TONTJANV!Q22+TONTFEV!Q22+TONTMARS!Q22+TONTAVRIL!Q22+TONTMAI!Q22+TONTJUIN!Q22+TONTJUIL!Q22+TONTAOUT!Q22+TONTSEPT!Q22+TONTOCT!Q22+TONTNOV20!Q22+TONTDEC20!Q22 -> 195000 | I22: 44003 | J22: =IF(G22=0,0,(H22-100000)) -> 95000
A23: AS201647 | B23: =VLOOKUP(A23,[1]LISTADHERENT!A$5:H$60,3,0) -> YOUMBI EMMANUEL | C23: =TONTNOV!C23+TONTDEC!C23+TONTJANV!C23+TONTFEV!C23+TONTMARS!C23+TONTAVRIL!C23+TONTMAI!C23+TONTJUIN!C23+TONTJUIL!C23+TONTAOUT!C23+TONTSEPT!C23+TONTOCT!C23+TONTNOV20!C23+TONTDEC20!C23 -> 1200000 | D23: =TONTNOV!H23+TONTDEC!H23+TONTJANV!H23+TONTFEV!H23+TONTMARS!H23+TONTAVRIL!H23+TONTMAI!H23+TONTJUIN!H23+TONTJUIL!H23+TONTAOUT!H23+TONTSEPT!H23+TONTOCT!H23+TONTNOV20!H23+TONTDEC20!H23 -> 0 | E23: =TONTNOV!I23+TONTDEC!I23+TONTJANV!I23+TONTFEV!I23+TONTMARS!I23+TONTAVRIL!I23+TONTMAI!I23+TONTJUIN!I23+TONTJUIL!I23+TONTAOUT!I23+TONTSEPT!I23+TONTOCT!I23+TONTNOV20!I23+TONTDEC20!I23 -> 0 | F23: =TONTNOV!L23+TONTDEC!L23+TONTJANV!L23+TONTFEV!L23+TONTMARS!L23+TONTAVRIL!L23+TONTMAI!L23+TONTJUIN!L23+TONTJUIL!L23+TONTAOUT!L23+TONTSEPT!L23+TONTOCT!L23+TONTNOV20!L23+TONTDEC20!L23 -> 0 | G23: =TONTNOV!P23+TONTDEC!P23+TONTJANV!P23+TONTFEV!P23+TONTMARS!P23+TONTAVRIL!P23+TONTMAI!P23+TONTJUIN!P23+TONTJUIL!P23+TONTAOUT!P23+TONTSEPT!P23+TONTOCT!P23+TONTNOV20!P23+TONTDEC20!P23 -> 0 | H23: =TONTNOV!Q23+TONTDEC!Q23+TONTJANV!Q23+TONTFEV!Q23+TONTMARS!Q23+TONTAVRIL!Q23+TONTMAI!Q23+TONTJUIN!Q23+TONTJUIL!Q23+TONTAOUT!Q23+TONTSEPT!Q23+TONTOCT!Q23+TONTNOV20!Q23+TONTDEC20!Q23 -> 0 | J23: =IF(G23=0,0,(H23-100000)) -> 0
A25: TOTAL | C25: =SUM(C6:C24) -> 21000000 | D25: =SUM(D6:D24) -> 5937500 | E25: =SUM(E6:E24) -> 159500 | F25: =SUM(F6:F24) -> 6097000 | G25: =SUM(G6:G24) -> 20004000 | H25: =SUM(H6:H24) -> 2496000 | J25: =SUM(J6:J24) -> 996000
F28: EN COMPTE | G28: =(G25+H25)-C25 -> 1500000
F30: RESTE | G30: =TONTNOV!N30+TONTDEC!N30+TONTJANV!N30+TONTFEV!N30+TONTMARS!N30+TONTAVRIL!N30+TONTMAI!N30+TONTJUIN!N30+TONTJUIL!N30 -> 4045500
F32: ECHEC TONTINE | G32: =TONTJUIN!N32+TONTJUIL!N32 -> -233000 | H32: NKEHEP 200000/TYAM 100000
F33: ECHEC REMB | G33: =+TONTMARS!P32+TONTJUIL!N33 -> #VALUE! | H33: NKEHEP 217000/TYAM 101500

Sheet HISTORIQUE OCT
D1: 44096 | F1: REMB | G1: T30 | H1: T75 | I1: T100 | J1: TOTAL
B2: HENGUE PAUL | C2: 105000 | G2: 30000 | H2: 75000 | J2: =SUM(G2:I2) -> 105000
B3: MBOGNING | C3: 608000 | G3: 30000 | J3: =SUM(G3:I3) -> 30000
B4: SIME BRICE | C4: 40000 | J4: =SUM(G4:I4) -> 0
B5: SIME MATHIEU | C5: 230000 | J5: =SUM(G5:I5) -> 0
B6: NGONDIEP | C6: 140000 | D6: 140000 | J6: =SUM(G6:I6) -> 0
B7: NANGUEN | C7: 100000 | D7: 100000 | E7: 30000 | G7: 30000 | I7: 200000 | J7: =SUM(G7:I7) -> 230000
B8: DOHOU | C8: 30000 | J8: =SUM(G8:I8) -> 0
B9: KOUATCHO | C9: 332000 | J9: =SUM(G9:I9) -> 0
B10: NGUIEMENI | C10: 280000 | D10: 180000 | J10: =SUM(G10:I10) -> 0
B11: SIMO PIERRE | D11: 110000 | J11: =SUM(G11:I11) -> 0
B12: NKEPSEU DIEUDONNE | C12: 161000 | J12: =SUM(G12:I12) -> 0
B13: HOTCHO BENJAMIN | C13: 240000 | J13: =SUM(G13:I13) -> 0
B14: BOUTCHOUANG | C14: 105000 | J14: =SUM(G14:I14) -> 0
B15: DJOUKWE | C15: 85000 | J15: =SUM(G15:I15) -> 0
B16: KOUAMO MOISE | C16: 130000 | J16: =SUM(G16:I16) -> 0
B17: YOUMBI EMMANUEL | C17: 280000 | J17: =SUM(G17:I17) -> 0
B18: DJOMO JEAN PAUL | C18: 55000 | D18: 100000 | J18: =SUM(G18:I18) -> 0
B19: NDJOMO ETIENNE | C19: 158000 | J19: =SUM(G19:I19) -> 0
B20: PATEGO | C20: 105000 | J20: =SUM(G20:I20) -> 0
B21: DJUOMBESSY | C21: 190000 | J21: =SUM(G21:I21) -> 0
B22: TCHIEMHOU EMMANUEL | C22: 75000 | J22: =SUM(G22:I22) -> 0
B23: DOMOU | C23: 30000 | J23: =SUM(G23:I23) -> 0
B24: TCHOUAMO | C24: 205000 | J24: =SUM(G24:I24) -> 0
B25: NANKAM | C25: 105000 | J25: =SUM(G25:I25) -> 0
B26: DJOMO TCHANDA | C26: 30000 | J26: =SUM(G26:I26) -> 0
C30: 5984000
